Workbook
Name APN: [1]Sheet1!#REF!
Name FY: [1]Sheet1!#REF!
Name NvsASD: "V2009-06-30"
Name NvsAutoDrillOk: "VY"
Name NvsElapsedTime: 0.000879629631526768
Name NvsEndTime: 40002.1158796296
Name NvsInstLang: "VENG"
Name NvsInstSpec: "%"
Name NvsInstSpec1: ","
Name NvsInstSpec2: ","
Name NvsInstSpec3: ","
Name NvsInstSpec4: ","
Name NvsInstSpec5: ","
Name NvsInstSpec6: ","
Name NvsInstSpec7: ","
Name NvsInstSpec8: ","
Name NvsInstSpec9: ","
Name NvsLayoutType: "M3"
Name NvsNplSpec: "%,X,RZF.ACCOUNT.nPlosion,CZF.."
Name NvsPanelBusUnit: "V"
Name NvsPanelEffdt: "V2009-12-31"
Name NvsPanelSetid: "VSHARE"
Name NvsReqBU: "VX0300"
Name NvsReqBUOnly: "VN"
Name NvsTransLed: "VN"
Name NvsTreeASD: "V2009-06-30"
Name NvsValTbl.ACCOUNT: "GL_ACCOUNT_TBL"
Name NvsValTbl.BUSINESS_UNIT: "BUS_UNIT_TBL_FS"
Name NvsValTbl.CURRENCY_CD: "CURRENCY_CD_VW"
Name NvsValTbl.PF_SCENARIO_ID: "PF_SCENARIO_VW"
Name PED: [1]Sheet1!#REF!

Sheet Schedule A
A1: ONCOR ELECTRIC DELIVERY COMPANY LLC
A2: Baseline of Wholesale Transmission Cost of Service
A3: As of December 31, 2024
A4: Sponsors: W. Alan Ledbetter and Matthew A. Troxle
A6: Line No. | B6: Description | C6: Test Year Ending 12/31/2024
A9: 1 | B9: Operation & Maintenance | C9: ='[2]III-A'!$G$16 -> 2.9060063e+08
A10: 2 | B10: Depreciation and Amortization | C10: ='Schedule E-1'!E39 -> 4.8034473e+08
A11: 3 | B11: Taxes Other Than Income Taxes | C11: ='Schedule E-2'!E22 -> 1.4708187e+08
A12: 4 | B12: Federal Income Taxes | C12: ='Schedule E-3'!E39-1 -> 1.2867713e+08
A13: 5 | B13: Return on Rate Base | C13: ='Schedule B'!C26 -> 910883578
A15: 6 | B15: Total Revenue Requirement | C15: =SUM(C9:C13)+C14 -> 1.9575879e+09
A17: 7 | B17: Other Revenues | C17: =-'[2]III-A'!$G$29 -> -46131717
A19: 8 | B19: Total | C19: =(C15+C17) -> 1.9114562e+09
A21: 9 | B21: ERCOT Average 4 CP (MW) | C21: 81042.657
A23: 10 | B23: Wholesale Rate $/MW | C23: =C19/C21 -> 23585.804

Sheet Schedule B
A1: ='Schedule A'!$A$1 -> ONCOR ELECTRIC DELIVERY COMPANY LLC
A2: ='Schedule A'!$A$2 -> Baseline of Wholesale Transmission Cost of Service
A3: Rate Base
A4: ='Schedule A'!A3 -> As of December 31, 2024
A5: ='Schedule A'!A4 -> Sponsors: W. Alan Ledbetter and Matthew A. Troxle
A7: Line No. | B7: Description | C7: ='Schedule A'!C6 -> Test Year Ending 12/31/2024
B9: Direct Assigned:
B10: FERC Accounts (350 - 362)
A11: 1 | B11: Original Plant In Service | C11: ='Schedule B-1'!E34 -> 1.7347867e+10
A12: 2 | B12: (Accumulated Depreciation) | C12: =-'Schedule B-5'!E35 -> -4.0931457e+09
A13: 3 | B13: Net Plant In Service | C13: =SUM(C11:C12) -> 1.3254722e+10
A15: 4 | B15: Allocated Plant Accounts - Net | C15: 3.6928541e+08
A16: 5 | B16: Working Capital | C16: -56089574
A17: 6 | B17: Plant Held for Future Use | C17: 61450358
A18: 7 | B18: Regulatory Assets | C18: 50224688
A19: 8 | B19: Other | C19: -1.4857027e+09
A20: 9 | B20: Subtotal | C20: =SUM(C15:C19) -> -1.0608318e+09
A22: 10 | B22: Total Rate Base | C22: =C13+C20 -> 1.219389e+10
A24: 11 | B24: Rate of Return | C24: 0.0747
A26: 12 | B26: Return On Rate Base | C26: =ROUND(C22*C24,0) -> 910883578
A31: Notes: Line 8, "Other" includes Inventory, Prepayments, Electric Plant
B32: Acquisition Adjustment, ADFIT and Excess Deferred Tax
B33: Regulatory Liabilities Related to the Tax Cuts and Jobs Act.

Sheet Schedule B-1
A1: ='Schedule A'!$A$1 -> ONCOR ELECTRIC DELIVERY COMPANY LLC
A2: ='Schedule A'!$A$2 -> Baseline of Wholesale Transmission Cost of Service
A3: Transmission Plant
A4: ='Schedule A'!A3 -> As of December 31, 2024
A5: ='Schedule A'!A4 -> Sponsors: W. Alan Ledbetter and Matthew A. Troxle
A7: Line No. | B7: Acct. No. | C7: Account Description | D7: Schedule / Workpaper Reference | E7: ='Schedule A'!C6 -> Test Year Ending 12/31/2024
B9: Transmission Plant
A10: 1 | B10: A350 | C10: Land and Land Rights | E10: ='[3]II-B-1'!$Q$23+'[3]II-B-1'!$Q$24 -> 8.3557233e+08
A11: 2a | B11: A351.1 | C11: Computer Hardware | E11: 0
A12: 2b | B12: A351.2 | C12: Computer Software | E12: 1.5082575e+08
A13: 2c | B13: A351.3 | C13: Communication Equipment | E13: 3528604.2
A14: 3a | B14: A352 | C14: Structures and Improvements - Base | E14: =[4]Sheet1!$C$27+[4]Sheet1!$D$27 -> 6.3266702e+08
A15: 3b | B15: A352 | C15: Structures and Improvements - DC Tie | E15: =[4]Sheet1!$E$34 -> 1693652.8
A16: 3c | B16: A352 | C16: Structures and Improvements - SVC | E16: =[4]Sheet1!$C$36+[4]Sheet1!$D$36 -> 20424706
A17: 4a | B17: A353 | C17: Station Equipment - Base | E17: =[4]Sheet1!$C$28+[4]Sheet1!$D$28 -> 4.1882953e+09
A18: 4b | B18: A353 | C18: Station Equipment - DC Tie | E18: =[4]Sheet1!$E$35 -> 19314257
A19: 4c | B19: A353 | C19: Station Equipment - SVC | E19: =[4]Sheet1!$C$37+[4]Sheet1!$D$37 -> 2.9216549e+08
A20: 5 | B20: A354 | C20: Towers and Fixtures | E20: =[4]Sheet1!$C$29+[4]Sheet1!$D$29 -> 2.1534233e+09
A21: 6 | B21: A355 | C21: Poles and Fixtures | E21: =[4]Sheet1!$C$30+[4]Sheet1!$D$30 -> 4.0735736e+09
A22: 7 | B22: A356 | C22: O. H. Conductors & Devices | E22: =[4]Sheet1!$C$31+[4]Sheet1!$D$31 -> 3.7347934e+09
A23: 8 | B23: A357 | C23: Underground Conduit | E23: =[4]Sheet1!$C$32 -> 61796401
A24: 9 | B24: A358 | C24: Underground Conductors | E24: =[4]Sheet1!$C$33 -> 96633109
A25: 10 | B25: A359 | C25: Roads and Trails | E25: 0
A26: 11 | C26: Total Transmission Plant | E26: =SUM(E10:E25) -> 1.6264707e+10
B28: Distribution Plant
A29: 12 | B29: A360 | C29: Land and Land Rights (above 60 kV) | E29: =[4]Sheet1!$C$52+'[3]II-B-1'!$Q$56 -> 38441603
A30: 13 | B30: A361 | C30: Structures and Improvements (above 60 kV) | E30: =[4]Sheet1!$C$54+[4]Sheet1!$D$54 -> 1.3509365e+08
A31: 14 | B31: A362 | C31: Station Equipment (above 60 kV) | E31: =[4]Sheet1!$C$55+[4]Sheet1!$D$55 -> 9.0962532e+08
A32: 15 | C32: Total Distribution Plant | E32: =SUM(E29:E31) -> 1.0831606e+09
A34: 16 | B34: Total Transmission Plant in Service - Gross | D34: Schedule B | E34: =E26+E32 -> 1.7347867e+10

Sheet Schedule B-5
A1: ='Schedule A'!$A$1 -> ONCOR ELECTRIC DELIVERY COMPANY LLC
A2: ='Schedule A'!$A$2 -> Baseline of Wholesale Transmission Cost of Service
A3: Accumulated Depreciation
A4: ='Schedule A'!A3 -> As of December 31, 2024
A5: ='Schedule B-1'!A5 -> Sponsors: W. Alan Ledbetter and Matthew A. Troxle
A7: Line No. | B7: Acct. No. | C7: Account Description | D7: Schedule / Workpaper Reference | E7: ='Schedule A'!C6 -> Test Year Ending 12/31/2024
B9: Accumulated Depreciation
B10: Transmission Plant
A11: 1 | B11: A350 | C11: Land and Land Rights | E11: ='[3]II-B-5'!$Q$26 -> 1.4077873e+08
A12: 2a | B12: A351.1 | C12: Computer Hardware | E12: 0
A13: 2b | B13: A351.2 | C13: Computer Software | E13: 56291413
A14: 2c | B14: A351.3 | C14: Communication Equipment | E14: 1213664.3
A15: 3a | B15: A352 | C15: Structures and Improvements - Base | E15: =133197748.04967+24796762.5938403 -> 1.5799451e+08
A16: 3b | B16: A352 | C16: Structures and Improvements - DC Tie | E16: 1013443.8
A17: 3c | B17: A352 | C17: Structures and Improvements - SVC | E17: =4115588.80353817+1315449.34295129 -> 5431038.1
A18: 4a | B18: A353 | C18: Station Equipment - Base | E18: 8.5120701e+08
A19: 4b | B19: A353 | C19: Station Equipment - DC Tie | E19: 9424771
A20: 4c | B20: A353 | C20: Station Equipment - SVC | E20: =85762185.2957596+16571115.2570487 -> 1.023333e+08
A21: 5 | B21: A354 | C21: Towers and Fixtures | E21: ='[3]II-B-5'!$Q$32 -> 6.4803222e+08
A22: 6 | B22: A355 | C22: Poles and Fixtures | E22: ='[3]II-B-5'!$Q$33 -> 1.0244216e+09
A23: 7 | B23: A356 | C23: O. H. conductors & Devices | E23: ='[3]II-B-5'!$Q$34 -> 8.6967001e+08
A24: 8 | B24: A357 | C24: Underground Conduit | E24: ='[3]II-B-5'!$Q$35 -> 24828551
A25: 9 | B25: A358 | C25: Underground Conductors | E25: ='[3]II-B-5'!$Q$36 -> 35777645
A26: 10 | B26: A359 | C26: Roads and Trails | E26: 0
A27: 11 | C27: Total Transmission Plant | E27: =SUM(E11:E26) -> 3.9284179e+09
B29: Distribution Plant
A30: 12 | B30: A360 | C30: Land and Land Rights (above 60 kV) | E30: ='[3]II-B-5'!$Q$43 -> 339719.3
A31: 13 | B31: A361 | C31: Structures and Improvements (above 60 kV) | E31: ='[3]II-B-5'!$Q$44 -> 22759235
A32: 14 | B32: A362 | C32: Station Equipment (above 60 kV) | E32: ='[3]II-B-5'!$Q$45 -> 1.4162885e+08
A33: 15 | C33: Total Distribution Plant | E33: =SUM(E30:E32) -> 1.6472781e+08
A35: 16 | B35: Total Transmission Accumulated Depreciation | D35: Schedule B | E35: =E27+E33 -> 4.0931457e+09

Sheet Schedule E-1
A1: ='Schedule A'!$A$1 -> ONCOR ELECTRIC DELIVERY COMPANY LLC
A2: ='Schedule A'!$A$2 -> Baseline of Wholesale Transmission Cost of Service
A3: Depreciation Expense
A4: ='Schedule A'!A3 -> As of December 31, 2024
A5: ='Schedule A'!A4 -> Sponsors: W. Alan Ledbetter and Matthew A. Troxle
A7: Line No. | B7: Acct. No. | C7: Account Description | D7: Schedule / Workpaper Reference | E7: ='Schedule A'!C6 -> Test Year Ending 12/31/2024 | F7: Depreciation % requested
A8: Direct Assigned:
A9: FERC Accounts (350 - 362)
B10: Transmission Plant
A11: 1 | B11: A350 | C11: Land and Land Rights | E11: =[4]Sheet1!$Z$26 -> 6441296.1 | F11: =[4]Sheet1!$M$26 -> 0.0095324396
A12: 2a | B12: A351.1 | C12: Computer Hardware | E12: 0
A13: 2b | B13: A351.2 | C13: Computer Software | E13: 12662465 | F13: =AVERAGE(F43:F46) -> 0.17286103 | G13: *
A14: 2c | B14: A351.3 | C14: Communication Equipment | E14: 122277.99 | F14: 0.0347
A15: 3a | B15: A352 | C15: Structures and Improvements - Base | E15: =[4]Sheet1!$Z$27 -> 14450715 | F15: =[4]Sheet1!$M$27 -> 0.022840949
A16: 3b | B16: A352 | C16: Structures and Improvements - DC Tie | E16: =[4]Sheet1!$Z$34 -> 37240.805 | F16: =[4]Sheet1!$M$34 -> 0.021988454
A17: 3c | B17: A352 | C17: Structures and Improvements - SVC | E17: =[4]Sheet1!$Z$36 -> 1099391.2 | F17: =[4]Sheet1!$M$36 -> 0.053826537
A18: 4a | B18: A353 | C18: Station Equipment - Base | E18: =[4]Sheet1!$S$28+[4]Sheet1!$T$28+[4]Sheet1!$U$28 -> 93020172 | F18: =[4]Sheet1!$M$28 -> 0.022209554
A19: 4b | B19: A353 | C19: Station Equipment - DC Tie | E19: =[4]Sheet1!$U$35 -> 687106.39 | F19: =[4]Sheet1!$M$35 -> 0.035575088
A20: 4c | B20: A353 | C20: Station Equipment - SVC | E20: =[4]Sheet1!$T$37+[4]Sheet1!$S$37 -> 11145366 | F20: =[4]Sheet1!$M$37 -> 0.038147441
A21: 5 | B21: A354 | C21: Towers and Fixtures | E21: =[4]Sheet1!$Z$29 -> 41336657 | F21: =[4]Sheet1!$M$29 -> 0.019195788
A22: 6 | B22: A355 | C22: Poles and Fixtures | E22: =[4]Sheet1!$Z$30 -> 1.256598e+08 | F22: =[4]Sheet1!$M$30 -> 0.030847559
A23: 7 | B23: A356 | C23: O. H. conductors & Devices | E23: =[4]Sheet1!$Z$31 -> 87131859 | F23: =[4]Sheet1!$M$31 -> 0.023329767
A24: 8 | B24: A357 | C24: Underground Conduit | E24: =[4]Sheet1!$Z$32 -> 1022587.8 | F24: =[4]Sheet1!$M$32 -> 0.016547693
A25: 9 | B25: A358 | C25: Underground Conductors | E25: =[4]Sheet1!$Z$33 -> 1783420.5 | F25: =[4]Sheet1!$M$33 -> 0.018455584
A26: 10 | B26: A359 | C26: Roads and Trails | E26: 0
A27: 11 | C27: Total Transmission Plant | E27: =SUM(E11:E26) -> 3.9660036e+08
B29: Distribution Plant
A30: 12 | B30: A360 | C30: Land and Land Rights (above 60 kV) | E30: =[4]Sheet1!$S$52 -> 36178.582 | F30: 0.01418098
A31: 13 | B31: A361 | C31: Structures and Improvements (above 60 kV) | E31: ='[5]II-E-1'!$Q$43 -> 2888075.9 | F31: 0.021378325
A32: 14 | B32: A362 | C32: Station Equipment (above 60 kV) | E32: ='[5]II-E-1'!$Q$44 -> 21322027 | F32: 0.02344045
A33: 15 | C33: Total Distribution Plant | E33: =SUM(E30:E32) -> 24246282
A35: 16 | B35: Total Direct Assigned | E35: =E27+E33 -> 4.2084664e+08
A37: 17 | B37: Allocated Expense Accounts - Net | E37: ='[5]II-E-1'!$Q$78+'[5]II-E-1'!$Q$20+'[5]II-E-1'!$N$82+'[5]II-E-1'!$N$83 -> 59498088 | F37: Various
A39: 18 | B39: Total Transmission Depreciation Expense | D39: Schedule A | E39: =E35+E37 -> 4.8034473e+08
A42: * | B42: Note that Account A351.2 Computer Software reflects a composite rate based on the following breakdown:
D43: 3 year | E43: 97373.958 | F43: 0.33945796
D44: 5 year | E44: 676915.25 | F44: 0.19044704
D45: 8 year | E45: 7233296.9 | F45: 0.097785263
D46: 15 year | E46: 4654878.5 | F46: 0.063753835
E47: =SUM(E43:E46) -> 12662465

Sheet Schedule E-2
A1: ='Schedule A'!$A$1 -> ONCOR ELECTRIC DELIVERY COMPANY LLC
A2: ='Schedule A'!$A$2 -> Baseline of Wholesale Transmission Cost of Service
A3: Taxes Other Than Federal Income Tax
A4: ='Schedule A'!A3 -> As of December 31, 2024
A5: ='Schedule A'!A4 -> Sponsors: W. Alan Ledbetter and Matthew A. Troxle
A7: Line No. | B7: FERC Account | C7: Account Description | D7: Schedule / Workpaper Reference | E7: ='Schedule A'!C6 -> Test Year Ending 12/31/2024
B10: Taxes Other Than Income Taxes:
B11: Non-Revenue Related
A12: 1 | C12: Ad Valorem Taxes | E12: ='[5]II-E-2'!$Q$27 -> 1.3564713e+08
A13: 2 | C13: Payroll Taxes | E13: ='[5]II-E-2'!$Q$22 -> 4772872.6
A14: 3 | C14: Other Franchise Taxes | E14: ='[5]II-E-2'!$Q$32 -> 1336.49
B17: Revenue Related Taxes
A19: 4 | C19: Texas Margin Tax | E19: ='[5]II-E-2'!$Q$30 -> 6660528
A22: 5 | B22: Total Taxes Other Than FIT Taxes | D22: Schedule A | E22: =SUM(E12:E19) -> 1.4708187e+08

Sheet Schedule E-3
A1: ='Schedule A'!$A$1 -> ONCOR ELECTRIC DELIVERY COMPANY LLC
A2: ='Schedule A'!$A$2 -> Baseline of Wholesale Transmission Cost of Service
A3: Federal Income Tax
A4: ='Schedule A'!A3 -> As of December 31, 2024
A5: ='Schedule A'!A4 -> Sponsors: W. Alan Ledbetter and Matthew A. Troxle
A7: Line No. | C7: Account Description | D7: Schedule Reference | E7: ='Schedule A'!C6 -> Test Year Ending 12/31/2024
B9: Federal Income Tax:
A11: 1 | C11: Return on Rate Base | D11: Schedule B | E11: ='Schedule B'!C26 -> 910883578
C13: Deduct:
A14: 2 | C14: Synchronized Interest Included In Return | E14: ='[5]II-E-3'!$Q$20 -> 3.3167381e+08
A15: 3 | C15: ITC Amortization | E15: ='[5]II-E-3'!$Q$21 -> 485229.49
A16: 4a | C16: Amort of Protected Excess DFIT | E16: ='[5]II-E-3'!$Q$22 -> 8793525.3
A17: 4b | C17: Amort of Unprotected Excess DFIT | E17: ='[5]II-E-3'!$Q$23 -> 11501584
A18: 4c | C18: Amort of Excess ADFIT Reserve | E18: ='[5]II-E-3'!$Q$24 -> -782812.41
A19: 5 | C19: Other | E19: ='[5]II-E-3'!$Q$25 -> 36110.08
C21: Add:
A22: 6 | C22: Depreciation Addback | E22: ='[5]II-E-3'!$Q$30 -> 402497.99
A23: 7 | C23: Meals, Commuter Expense, Empl Comp Plans | E23: ='[5]II-E-3'!$Q$31+'[5]II-E-3'!$Q$33+'[5]II-E-3'!$Q$34 -> -1657056.4
A25: 8 | C25: Taxable Component of Return | E25: =E11-E14-E15-E16-E17-E18-E19+E22+E23 -> 5.5792158e+08
C26: Tax Factor (1/1 - .35)(.35)
A27: 9 | C27: Tax Factor (1/1 - .21)(.21) | E27: =(1/(1-0.21))*0.21 -> 0.26582278
A29: 10 | C29: Federal Income Taxes Before Adjustments | E29: =ROUND(E25*E27,0) -> 148308267
C31: Deduct:
A32: 11 | C32: ITC Amortization | E32: ='[5]II-E-3'!$Q$44 -> 485229.49
A33: 11a | C33: Amort of Protected Excess DFIT | E33: ='[5]II-E-3'!$Q$45 -> 8793525.3
A34: 12 | C34: Amort of Unprotected Excess DFIT | E34: ='[5]II-E-3'!$Q$46 -> 11501584
A35: 13 | C35: Amort of Excess ADFIT Reserve | E35: ='[5]II-E-3'!$Q$47 -> -782812.41
A36: 14 | C36: R&D Tax Credit | E36: ='[5]II-E-3'!$Q$48 -> 36110.08
C37: Add:
A38: 15 | C38: Depreciation Differences | E38: ='[5]II-E-3'!$Q$51 -> 402497.99
A39: 16 | B39: Total Federal Income Tax | D39: Schedule A | E39: =E29-E32-E33-E34-E35-E36+E38+1 -> 1.2867713e+08
C42: Recap of Amortization of Excess DFIT
C43: Amort of Protected Excess DFIT | E43: =E33 -> 8793525.3
C44: Amort of Unprotected Excess DFIT | E44: =E34 -> 11501584
C45: Amort of Excess ADFIT Reserve | E45: =E35 -> -782812.41
C46: Total Amortization of Excess DFIT | E46: =E43+E44+E45 -> 19512297
