Workbook
Name Account: #REF!
Name Account2: #REF!
Name AccountDescr: #REF!
Name AccountDescr2: #REF!
Name Activity: #REF!
Name Activity2: #REF!
Name ActivityDescr: #REF!
Name ActivityDescr2: #REF!
Name Affiliate: #REF!
Name Affiliate2: #REF!
Name AffiliateDescr: #REF!
Name ASD: #REF!
Name CURRENTMONTH: [11]Month!$H$5
Name DeptDescr: #REF!
Name DeptDescr2: #REF!
Name DeptID: #REF!
Name DeptID2: #REF!
Name EC: #REF!
Name ECDescr: #REF!
Name ECDescr2: #REF!
Name ECID: #REF!
Name Location: #REF!
Name Location2: #REF!
Name LocationDescr: #REF!
Name LocationDescr2: #REF!
Name NvsASD: "V2019-12-31"
Name NvsAutoDrillOk: "VN"
Name NvsElapsedTime: 0.000312499993015081
Name NvsEndTime: 43852.4466666667
Name NvsInstLang: "VENG"
Name NvsInstSpec: "%,LTU_SUM01,SBAL,FACCOUNT,V1070000"
Name NvsInstSpec1: ","
Name NvsInstSpec2: ","
Name NvsInstSpec3: ","
Name NvsInstSpec4: ","
Name NvsInstSpec5: ","
Name NvsInstSpec6: ","
Name NvsInstSpec7: ","
Name NvsInstSpec8: ","
Name NvsInstSpec9: ","
Name NvsLayoutType: "M3"
Name NvsNplSpec: "%,X,RZF..,CZF.."
Name NvsPanelBusUnit: "V"
Name NvsPanelEffdt: "V1997-01-01"
Name NvsPanelSetid: "VSHARE"
Name NvsParentRef: "'[NTUSU Trial Balance Dec 2019.xls]Sheet1'!$O$19"
Name NvsReqBU: "VNTUSU"
Name NvsReqBUOnly: "VY"
Name NvsTransLed: "VY"
Name NvsTreeASD: "V2019-12-31"
Name NvsValTbl.ACCOUNT: "GL_ACCOUNT_TBL"
Name NvsValTbl.AFFILIATE: "BUS_UNIT_TBL_FS"
Name NvsValTbl.CURRENCY_CD: "CURRENCY_CD_TBL"
Name NvsValTbl.DEPTID: "DEPARTMENT_TBL"
Name NvsValTbl.PROJECT_ID: "PROJECT"
Name NvsValTbl.TU_EC: "TU_EC_TBL"
Name Task: #REF!
Name Task2: #REF!
Name TaskDescr: #REF!

Sheet WP II-B-15A_02 AFUDC NTUSU Rate
A1: From Sharyland Utilities LLC Docket No. 51611
A3: Unit | B3: Year | C3: AFUDC Rate
A4: NTUSU | B4: 2014 | C4: ='WP II-B-15A_02-5'!C17 -> 0.070357021
A5: NTUSU | B5: 2015 | C5: ='WP II-B-15A_02-4'!C17 -> 0.06790032
A6: NTUSU | B6: 2016 | C6: ='WP II-B-15A_02-3'!C17 -> 0.044797864
A7: NTUSU | B7: 2017 | C7: ='WP II-B-15A_02-2'!C17 -> 0.056277672
A8: NTUSU | B8: 2019 | C8: ='WP II-B-15A_02-1'!C16 -> 0.061799874

Sheet WP II-B-15A_02-1
A1: From Sharyland Utilities LLC Docket No. 51611
A3: WP/II-B-15a/1
A4: Assumptions used in determining AFUDC rates
A5: Sponsor: Bell
A7: 1) Debt rate is based on all outstanding debt for the utility
A8: 3) Average short-term debt balance is based on each month's actual balance for prior months and the most recent forecast numbers for remaining months
A9: 4) Short-term debt interest rates is equal to weighted average revolver borrowing rate at 06/30/2019
A10: 5) Long-term debt balance is equal to outstanding debt at 06/30/2019
A11: 6) Common equity balance is based on 06/30/2019
A12: 7) Common equity cost rate is based on approved ROE in latest rate case
A13: 8) Average CWIP balance is an average based on each month's actual balance for prior months and the most recent forecast numbers for remaining months
A16: AFUDC Formula | C16: =SUM(C17:C18) -> 0.061799874 | D16: Blended rate
A17: Ai | B17: s(S/W)+d(D/D+P+C)(1-S/W) | C17: =C23*(C22/C30)+C25*(C24/(C24+C26+C28))*(1-C22/C30) -> 0.02870603
A18: Ae | B18: [1-S/W][p(P/D+P+C)+c(C/D+P+C)] | C18: =(1-C22/C30)*(C27*(C26/(C24+C26+C28))+(C29*(C28/(C24+C26+C28)))) -> 0.033093844
A20: Ai | B20: Allowance for Borrowed Funds | C20: =C17 -> 0.02870603 | D20: (As Calculated Above)
A21: Ae | B21: Allowance for other funds (equity) | C21: =C18 -> 0.033093844 | D21: (As Calculated Above)
A22: S | B22: Average short-term debt | C22: 4000000 | D22: (See Assumptions)
A23: s | B23: short-term debt interest rate | C23: 0.06275
A24: D | B24: Long-term debt | C24: 141500000 | D24: (See Assumptions)
A25: d | B25: Long-term debt interest rate | C25: 0.03381
A26: P | B26: Preferred Stock | C26: 0
A27: p | B27: Preferred Stock cost rate | C27: 0
A28: C | B28: Common equity | C28: 110571724 | D28: (See Assumptions)
A29: c | B29: common equity cost rate | C29: 0.097 | D29: (See Assumptions)
A30: W | B30: Average balance in CWIP | C30: 18000000 | D30: (See Assumptions)
A33: Monthly Rates
A34: Ai | B34: Allowance for Borrowed Funds | C34: =C17/12 -> 0.0023921692
A35: Ae | B35: Allowance for other funds (equity) | C35: =C18/12 -> 0.0027578203

Sheet WP II-B-15A_02-2
A1: From Sharyland Utilities LLC Docket No. 51611
A3: WP/II-B-15a/2
A4: Assumptions used in determining AFUDC rates - 12/31/17
A5: Sponsor: Bell
A7: 1) Debt rate is based on all outstanding debt for the utility, including CV and GS Project Entities. TDC and InfraREIT, LP debt is not included in the calculation.
A8: 2) Will have a single rate for debt component and a single rate for other funds component for all CWIP (Permian, McAllen, CREZ, etc)
A9: 3) Average short-term debt balance is based on each month's actual balance for prior months and the most recent forecast numbers for remaining months
A10: 4) Short-term debt interest rates is equal to weighted average revolver borrowing rate at 12/31/17.
A11: 5) Long-term debt balance is equal to outstanding debt at 12/31/17
A12: 6) Common equity balance is based on 12/31/17 SDTS consolidated balance plus CV and GS Project Entities
A13: 7) Common equity cost rate is based on approved ROE in latest rate case
A14: 8) Average CWIP balance is an average based on each month's actual balance for prior months and the most recent forecast numbers for remaining months
A17: AFUDC Formula | C17: =C18+C19 -> 0.056277672
A18: Ai | B18: s(S/W)+d(D/D+P+C)(1-S/W) | C18: =C24*(C23/C31)+C26*(C25/(C25+C27+C29))*(1-C23/C31) -> 0.07459452
A19: Ae | B19: [1-S/W][p(P/D+P+C)+c(C/D+P+C)] | C19: =(1-C23/C31)*(C28*(C27/(C25+C27+C29))+(C30*(C29/(C25+C27+C29)))) -> -0.018316848
A21: Ai | B21: Allowance for Borrowed Funds | C21: =C18 -> 0.07459452 | D21: (As Calculated Above)
A22: Ae | B22: Allowance for other funds (equity) | C22: =C19 -> -0.018316848 | D22: (As Calculated Above)
A23: S | B23: Average short-term debt | C23: 76500000 | D23: (See Assumptions)
A24: s | B24: short-term debt interest rate | C24: 0.0601023
A25: D | B25: Long-term debt | C25: 1.0522012e+09 | D25: (See Assumptions)
A26: d | B26: Long-term debt interest rate | C26: 0.044579384
A27: P | B27: Preferred Stock | C27: 0
A28: p | B28: Preferred Stock cost rate | C28: 0
A29: C | B29: Common equity | C29: 9.8134435e+08 | D29: (See Assumptions)
A30: c | B30: common equity cost rate | C30: 0.097 | D30: (See Assumptions)
A31: W | B31: Average balance in CWIP | C31: 54984489 | D31: (See Assumptions)
A34: Monthly Rates
A35: Ai | B35: Allowance for Borrowed Funds | C35: =C18/12 -> 0.00621621
A36: Ae | B36: Allowance for other funds (equity) | C36: =C19/12 -> -0.001526404

Sheet WP II-B-15A_02-3
A1: From Sharyland Utilities LLC Docket No. 51611
A3: WP/II-B-15a/3
A4: Assumptions used in determining AFUDC rates - 12/31/16
A5: Sponsor: Bell
A7: 1) Debt rate is based on all outstanding debt for the utility, including CV and GS Project Entities. TDC and InfraREIT, LP debt is not included in the calculation.
A8: 2) Will have a single rate for debt component and a single rate for other funds component for all CWIP (Midland, McAllen, CREZ, etc)
A9: 3) Average short-term debt balance is based on each month's actual balance for prior months and the most recent forecast numbers for remaining months
A10: 4) Short-term debt interest rates is equal to weighted average revolver borrowing rate at 12/31/16.
A11: 5) Long-term debt balance is equal to outstanding debt at 12/31/16
A12: 6) Common equity balance is based on 12/31/16 SDTS consolidated balance plus CV and GS Project Entities
A13: 7) Common equity cost rate is based on approved ROE in latest rate case
A14: 8) Average CWIP balance is an average based on each month's actual balance for prior months and the most recent forecast numbers for remaining months
A17: AFUDC Formula | C17: =C18+C19 -> 0.044797864
A18: Ai | B18: s(S/W)+d(D/D+P+C)(1-S/W) | C18: =C24*(C23/C31)+C26*(C25/(C25+C27+C29))*(1-C23/C31) -> 0.030839716
A19: Ae | B19: [1-S/W][p(P/D+P+C)+c(C/D+P+C)] | C19: =(1-C23/C31)*(C28*(C27/(C25+C27+C29))+(C30*(C29/(C25+C27+C29)))) -> 0.013958148
A21: Ai | B21: Allowance for Borrowed Funds | C21: =C18 -> 0.030839716 | D21: (As Calculated Above)
A22: Ae | B22: Allowance for other funds (equity) | C22: =C19 -> 0.013958148 | D22: (As Calculated Above)
A23: S | B23: Average short-term debt | C23: 84271000 | D23: (See Assumptions)
A24: s | B24: short-term debt interest rate | C24: 0.034969697
A25: D | B25: Long-term debt | C25: 862292941 | D25: (See Assumptions)
A26: d | B26: Long-term debt interest rate | C26: 0.042472693
A27: P | B27: Preferred Stock | C27: 0
A28: p | B28: Preferred Stock cost rate | C28: 0
A29: C | B29: Common equity | C29: =918204000+74521000+39298000 -> 1032023000 | D29: (See Assumptions)
A30: c | B30: common equity cost rate | C30: 0.097 | D30: (See Assumptions)
A31: W | B31: Average balance in CWIP | C31: 114519000 | D31: (See Assumptions)
A34: Monthly Rates
A35: Ai | B35: Allowance for Borrowed Funds | C35: =C18/12 -> 0.0025699763
A36: Ae | B36: Allowance for other funds (equity) | C36: =C19/12 -> 0.001163179

Sheet WP II-B-15A_02-4
A1: From Sharyland Utilities LLC Docket No. 51611
A3: WP/II-B-15a/4
A4: Assumptions used in determining AFUDC rates - 12/31/15
A5: Sponsor: Bell
A7: 1) Debt rate is based on all outstanding debt for the utility, excluding parent debt at TDC and InfraREIT LP.
A8: 2) Will have a single rate for debt component and a single rate for other funds component for all CWIP (Midland, McAllen, CREZ, etc)
A9: 3) Average short-term debt balance is based on each month's actual balance for prior months and the most recent forecast numbers for remaining months
A10: 4) Short-term debt interest rates is equal to weighted average revolver borrowing rate at 12/31/15.
A11: 5) Long-term debt balance is equal to outstanding debt at 12/31/15
A12: 6) Common equity balance is based on 12/31/15 SDTS consolidated balance
A13: 7) Common equity cost rate is based on approved ROE in latest rate case
A14: 8) Average CWIP balance is an average based on each month's actual balance for prior months and the most recent forecast numbers for remaining months
A17: AFUDC Formula | C17: =C18+C19 -> 0.06790032
A18: Ai | B18: s(S/W)+d(D/D+P+C)(1-S/W) | C18: =C24*(C23/C31)+C26*(C25/(C25+C27+C29))*(1-C23/C31) -> 0.029256947
A19: Ae | B19: [1-S/W][p(P/D+P+C)+c(C/D+P+C)] | C19: =(1-C23/C31)*(C28*(C27/(C25+C27+C29))+(C30*(C29/(C25+C27+C29)))) -> 0.038643374
A21: Ai | B21: Allowance for Borrowed Funds | C21: =C18 -> 0.029256947 | D21: (As Calculated Above)
A22: Ae | B22: Allowance for other funds (equity) | C22: =C19 -> 0.038643374 | D22: (As Calculated Above)
A23: S | B23: Average short-term debt | C23: 57952000 | D23: (See Assumptions)
A24: s | B24: short-term debt interest rate | C24: 0.050056278
A25: D | B25: Long-term debt | C25: 7.7283912e+08 | D25: (See Assumptions)
A26: d | B26: Long-term debt interest rate | C26: 0.047319462
A27: P | B27: Preferred Stock | C27: 0
A28: p | B28: Preferred Stock cost rate | C28: 0
A29: C | B29: Common equity | C29: 982493768 | D29: (See Assumptions)
A30: c | B30: common equity cost rate | C30: 0.097 | D30: (See Assumptions)
A31: W | B31: Average balance in CWIP | C31: 201054000 | D31: (See Assumptions)
A34: Monthly Rates
A35: Ai | B35: Allowance for Borrowed Funds | C35: =C18/12 -> 0.0024380789
A36: Ae | B36: Allowance for other funds (equity) | C36: =C19/12 -> 0.0032202811

Sheet WP II-B-15A_02-5
A1: From Sharyland Utilities LLC Docket No. 51611
A3: WP/II-B-15a/5
A4: Assumptions used in determining AFUDC rates - 12/31/14
A5: Sponsor: Bell
A7: 1) Debt rate is based on all outstanding debt for the utility, excluding parent debt at TDC and InfraREIT LP.
A8: 2) Will have a single rate for debt component and a single rate for other funds component for all CWIP (Midland, McAllen, CREZ, etc)
A9: 3) Average short-term debt balance is assumed to be $0 because SDTS revolver balance will be repaid on Feb 6, 2014 with IPO proceeds
A10: 4) Short-term debt interest rates is equal to revolver borrowing rate at 12/31/14; however, no impact to calculation since short term borrowings are assumed to be $0. See Note 3 above
A11: 5) Long-term debt balance is equal to outstanding debt at 12/31/14
A12: 6) Common equity balance is based on 12/31/14 SDTS consolidated balance
A13: 7) Common equity cost rate is based on approved ROE in latest rate case
A14: 8) Average CWIP balance is an estimate based on the 12/31/14 WIP balance; however because short-term borrowings are assumed to be $0 (see note 3 above), this assumption does not impact our AFUDC rates
A17: AFUDC Formula | C17: =C18+C19 -> 0.070357021
A18: Ai | B18: s(S/W)+d(D/D+P+C)(1-S/W) | C18: =C25*(C24/C32)+C27*(C26/(C26+C28+C30))*(1-C24/C32) -> 0.020598201 | E18: =D18/365 -> 0
A19: Ae | B19: [1-S/W][p(P/D+P+C)+c(C/D+P+C) | C19: =(1-C24/C32)*(C29*(C28/(C26+C28+C30))+(C31*(C30/(C26+C28+C30)))) -> 0.049758821 | E19: =D19/365 -> 0
E20: =SUM(E18:E19) -> 0
A22: Ai | B22: Allowance for Borrowed Funds | C22: =C18 -> 0.020598201 | D22: (As Calculated Above)
A23: Ae | B23: Allowance for other funds (equity) | C23: =C19 -> 0.049758821 | D23: (As Calculated Above)
A24: S | B24: Average short-term debt | C24: 0 | D24: (See Assumptions)
A25: s | B25: short-term debt interest rate | C25: 0.040178683
A26: D | B26: Long-term debt | C26: 6.0975605e+08 | D26: (See Assumptions)
A27: d | B27: Long-term debt interest rate | C27: 0.042294149
A28: P | B28: Preferred Stock | C28: 0
A29: p | B29: Preferred Stock cost rate | C29: 0
A30: C | B30: Common equity | C30: 642252000 | D30: (See Assumptions)
A31: c | B31: common equity cost rate | C31: 0.097 | D31: (See Assumptions)
A32: W | B32: Average balance in CWIP | C32: 82880000 | D32: (See Assumptions)
A35: Monthly Rates
A36: Ai | B36: Allowance for Borrowed Funds | C36: =C18/12 -> 0.0017165167
A37: Ae | B37: Allowance for other funds (equity) | C37: =C19/12 -> 0.0041465684
