Workbook
Name \M: #REF!
Name _asd2: '[1]O & M'!$T$5
Name _M: #REF!
Name Account: [2]Source!#REF!
Name Account2: [2]Source!#REF!
Name AccountDescr: [2]Source!#REF!
Name AccountDescr2: [2]Source!#REF!
Name Activity: [2]Source!#REF!
Name Activity2: [2]Source!#REF!
Name ActivityDescr: [2]Source!#REF!
Name ActivityDescr2: [2]Source!#REF!
Name Affiliate: [2]Source!#REF!
Name Affiliate2: [2]Source!#REF!
Name AffiliateDescr: [2]Source!#REF!
Name ASD: '[3]O & M'!$T$5
Name Completed: '[4]FIT Paid - Combined'!$AO$5
Name completed2: '[5]FIT Paid - Combined'!$AO$5
Name Credit: [6]JOURNAL!#REF!
Name Debit: [6]JOURNAL!#REF!
Name DeptDescr: [2]Source!#REF!
Name DeptDescr2: [2]Source!#REF!
Name DeptID: [2]Source!#REF!
Name DeptID2: [2]Source!#REF!
Name EC: [2]Source!#REF!
Name ECDescr: [2]Source!#REF!
Name ECDescr2: [2]Source!#REF!
Name ECID: [2]Source!#REF!
Name Elapsed: '[4]FIT Paid - Combined'!$AO$4
Name entry: [6]JOURNAL!$B$9:$R$353,[6]JOURNAL!$I$3,[6]JOURNAL!$G$3,[6]JOURNAL!$E$3,[6]JOURNAL!$B$7,[6]JOURNAL!$B$3
Name EntryFields: [6]JOURNAL!$B$9:$R$353,[6]JOURNAL!$I$3,[6]JOURNAL!$G$3,[6]JOURNAL!$E$3,[6]JOURNAL!$B$7,[6]JOURNAL!$B$3
Name FFT: #REF!
Name KeyControlFigure: '[4]FIT Paid - Combined'!$T$399
Name Lines: [6]JOURNAL!#REF!
Name Location: [2]Source!#REF!
Name Location2: [2]Source!#REF!
Name LocationDescr: [2]Source!#REF!
Name LocationDescr2: [2]Source!#REF!
Name MENU: #REF!
Name NvsASD: "V2000-12-31"
Name NvsAutoDrillOk: "VN"
Name NvsElapsedTime: 0.000582986111112405
Name NvsElapsedTime: 0.000689467597112525
Name NvsEndTime: 36257.3051395833
Name NvsEndTime: 36923.3059673611
Name NvsInstSpec: "%"
Name NvsLayoutType: "M3"
Name NvsNplSpec: "%,X,RZF..nPlosion,CZF.."
Name NvsPanelEffdt: "V1998-01-01"
Name NvsPanelSetid: "VSHARE"
Name NvsParentRef: [7]Sheet1!$T$303
Name NvsReqBU: "VGEN"
Name NvsReqBU: "VLSGD"
Name NvsReqBUOnly: "VY"
Name NvsTransLed: "VN"
Name NvsTreeASD: "V2000-12-31"
Name NvsValTbl.ACCOUNT: "GL_ACCOUNT_TBL"
Name NvsValTbl.AFFILIATE: "BUS_UNIT_TBL_FS"
Name NvsValTbl.CURRENCY_CD: "CURRENCY_CD_TBL"
Name NvsValTbl.DEPTID: "DEPARTMENT_TBL"
Name NvsValTbl.TU_LOCATION: "TU_LOC_TBL"

Sheet  
A1: 2022 RATE CASE
A2: ONCOR ELECTRIC DELIVERY COMPANY LLC
A3: LEAD-LAG STUDY RESULTS
A4: FOR THE TEST-YEAR ENDING DECEMBER 31, 2021
A5: SPONSOR: A. THENMADATHIL
A7: Line | C7: Revenue | D7: Expense
A8: No. | B8: Description | C8: Lag Days* | D8: Lead Days | E8: Reference
B9: (a) | C9: (b) | D9: (c) | E9: (d)
A11: 1 | B11: Operation & Maintenance Expenses
A12: =A11+1 -> 2 | B12: Labor
A13: =A12+1 -> 3 | B13: Payroll | C13: =+'1'!H14 -> 52.9 | D13: =+'2'!J35 -> -12.11 | E13: WP/II-B-9/2
A14: =A13+1 -> 4 | B14: Incentive Pay | C14: =+$C$13 -> 52.9 | D14: ='3'!J17 -> -249.34672 | E14: WP/II-B-9/3
A15: =A14+1 -> 5
A16: =A15+1 -> 6 | B16: Non-Labor
A17: =A16+1 -> 7 | B17: Affiliate Charges - Sempra | C17: =+$C$13 -> 52.9 | D17: =+'4'!K24 -> -44.96 | E17: WP/II-B-9/4
A18: =A17+1 -> 8 | B18: Affiliate Charges - Other | C18: =+$C$13 -> 52.9 | D18: =+'6'!D17 -> -46.93 | E18: WP/II-B-9/6
A19: =A18+1 -> 9 | B19: TCOS
A20: =A19+1 -> 10 | B20: Oncor | C20: 0 | D20: 0 | E20: N/A
A21: =A20+1 -> 11 | B21: Non-Oncor | C21: =+$C$13 -> 52.9 | D21: ='5'!E16 -> -50.22 | E21: WP/II-B-9/5
A22: =A21+1 -> 12 | B22: Amortized O&M Expenses | C22: 0 | D22: 0 | E22: N/A
A23: =A22+1 -> 13 | B23: Other O&M | C23: =+$C$13 -> 52.9 | D23: ='6'!D17 -> -46.93 | E23: WP/II-B-9/6
A24: =A23+1 -> 14 | B24: Pension & Supplemental Retirement Benefits | C24: =+$C$13 -> 52.9 | D24: =+'6-4'!I36 -> -53.506661 | E24: WP/II-B-9/6-4
A25: =A24+1 -> 15 | B25: Other Post-Employment Benefits | C25: =+$C$13 -> 52.9 | D25: ='6-5'!I23 -> 10.708699 | E25: WP/II-B-9/6-5
A26: =A25+1 -> 16
A27: =A26+1 -> 17 | B27: Federal Income Taxes
A28: =A27+1 -> 18 | B28: Current | C28: =+$C$13 -> 52.9 | D28: =+'7'!F20 -> -36.25 | E28: WP/II-B-9/7
A29: =A28+1 -> 19 | B29: Deferred | C29: 0 | D29: 0 | E29: N/A
A30: =A29+1 -> 20
A31: =A30+1 -> 21 | B31: Taxes Other Than Income Taxes
A32: =A31+1 -> 22 | B32: Payroll Taxes | C32: =+$C$13 -> 52.9 | D32: =+'8'!D16 -> -11.66 | E32: WP/II-B-9/8
A33: =A32+1 -> 23 | B33: State Gross Margin Taxes | C33: =+$C$13 -> 52.9 | D33: =+'9'!F23 -> 47.17 | E33: WP/II-B-9/9
A34: =A33+1 -> 24 | B34: Local Franchise Taxes | C34: =+$C$13 -> 52.9 | D34: ='10'!F37 -> -54.99 | E34: WP/II-B-9/10
A35: =A34+1 -> 25 | B35: Ad Valorem Taxes | C35: =+$C$13 -> 52.9 | D35: =+'11'!G37 -> -209.9 | E35: WP/II-B-9/11
A36: =A35+1 -> 26
A37: =A36+1 -> 27 | B37: Depreciation Expense | C37: 0 | D37: 0 | E37: N/A
A38: =A37+1 -> 28
A39: =A38+1 -> 29 | B39: Return | C39: 0 | D39: 0 | E39: N/A
A40: =A39+1 -> 30
A41: =A40+1 -> 31 | B41: Average Daily Bank Balances | D41: =+'12'!H26 -> 8420858 | E41: WP/II-B-9/12
A42: =A41+1 -> 32 | B42: Working Funds and Other | D42: ='13'!C16 -> -8308312 | E42: WP/II-B-9/13
A43: =A42+1 -> 33
A44: =A43+1 -> 34 | B44: Prepaid Affiliate Charges - Other | D44: =+'14'!F29 -> 1108749 | E44: WP/II-B-9/14
A45: =A44+1 -> 35 | B45: Prepaid Non-labor (Third Party) O&M | D45: =+'14'!F30 -> 45890378 | E45: WP/II-B-9/14
A46: =A45+1 -> 36 | B46: Prepaid Local Franchise Tax | D46: =+'15'!E14 -> 204512084 | E46: WP/II-B-9/15
A47: =A46+1 -> 37
A48: =A47+1 -> 38 | B48: * WP/II-B-9/1

Sheet 1
A1: 2022 RATE CASE
A2: =' '!A2 -> ONCOR ELECTRIC DELIVERY COMPANY LLC
A3: OVERALL REVENUE LAG
A4: FOR THE LEAD-LAG STUDY-PERIOD ENDING SEPTEMBER 30, 2021
A5: SPONSOR: A. THENMADATHIL
A7: Line No. | C7: Revenue Type | E7: Revenues | F7: Ref | H7: Revenue Lag Days | I7: Ref | J7: Wtd Dollar Days
C8: (a) | E8: (b) | F8: (c) | H8: (d) | I8: (e) | J8: (f)
A10: 1 | C10: CC&B | E10: 3.7554495e+09 | F10: (1) | H10: =+'1-1'!E20 -> 52.738161 | I10: WP/II-B-9/1-1 | J10: =H10*E10 -> 1.980555e+11
A11: 2
A12: 3 | C12: FIM | E12: 5.5022935e+08 | F12: (2) | H12: =+'1-1'!H20 -> 54.040667 | I12: WP/II-B-9/1-1 | J12: =+H12*E12 -> 2.9734761e+10
A13: 4
A14: 5 | C14: Total | E14: =SUM(E10:E12) -> 4.3056788e+09 | H14: =ROUND(J14/E14,2) -> 52.9 | J14: =SUM(J10:J12) -> 2.2779026e+11
A15: 6
A16: 7 | C16: Sources: | D16: (1) | E16: CC&B Revenue.xlsx
A17: 8 | D17: (2) | E17: FIM Revenue.xlsx

Sheet 1-1
A1: 2022 RATE CASE
A2: =' '!A2 -> ONCOR ELECTRIC DELIVERY COMPANY LLC
A3: REVENUE LAG BY REVENUE TYPE
A4: FOR THE LEAD-LAG STUDY-PERIOD ENDING SEPTEMBER 30, 2021
A5: SPONSOR: A. THENMADATHIL
A7: Line No. | C7: Description | E7: CC&B | F7: Reference | H7: FIM | I7: Reference
C8: (a) | E8: (b) | F8: (c) | H8: (d) | I8: (e)
A10: 1 | C10: Average service period
A11: =A10+1 -> 2 | C11: (365.25 days/12 months)/2 | E11: =ROUND(365.25/12/2,3) -> 15.219 | H11: =ROUND(365.25/12/2,3) -> 15.219
A12: =A11+1 -> 3
A13: =A12+1 -> 4 | C13: Billing Process Lag | E13: =+'1-1-2'!D20 -> 2.8031609 | F13: WP/II-B-9/1-1-2 | H13: =+'1-1-2'!D20 -> 2.8031609 | I13: WP/II-B-9/1-1-2
A14: =A13+1 -> 5
A15: =A14+1 -> 6 | C15: Collection Lag | E15: =+'1-1-3'!E14 -> 34.716 | F15: WP/II-B-9/1-1-3 | H15: 36.018506 | I15: (1)
A16: =A15+1 -> 7
A17: =A16+1 -> 8 | C17: Receipt of funds lag | E17: 0 | H17: 0
A18: =A17+1 -> 9
A19: =A18+1 -> 10
A20: =A19+1 -> 11 | C20: Operating Revenues Lag Days | E20: =SUM(E11:E18) -> 52.738161 | H20: =SUM(H11:H18) -> 54.040667
A21: =A20+1 -> 12
A22: =A21+1 -> 13 | C22: Source: | D22: (1) | E22: FIM Revenue.xlsx

Sheet 1-1-2
A1: 2022 RATE CASE
A2: =' '!A2 -> ONCOR ELECTRIC DELIVERY COMPANY LLC
A3: BILLING LAG
A4: FOR THE LEAD-LAG STUDY-PERIOD ENDING SEPTEMBER 30, 2021
A5: SPONSOR: A. THENMADATHIL
A7: Line No. | B7: Description | C7: Hours | D7: Days | E7: Reference
B8: (a) | C8: (b) | D8: (c) | E8: (d)
A10: 1 | B10: Period from Meter Reading Date to Invoice Date:
A11: =+A10+1 -> 2
A12: =+A11+1 -> 3 | B12: Calculated from invoice sample | D12: =+'1-1-2-1'!I128 -> 2.0948276 | E12: WP/II-B-9/1-1-2-1
A13: =+A12+1 -> 4
A14: =+A13+1 -> 5
A15: =+A14+1 -> 6 | B15: Invoicing Period
A16: =+A15+1 -> 7
A17: =+A16+1 -> 8 | B17: Start at midnight and end at 5 p.m. | C17: 17 | D17: =+C17/24 -> 0.70833333
A18: =+A17+1 -> 9
A19: =+A18+1 -> 10
A20: =+A19+1 -> 11 | B20: Total Billing Lag Days | D20: =SUM(D10:D17) -> 2.8031609

Sheet 1-1-2-1
A1: 2022 RATE CASE
A2: =' '!A2 -> ONCOR ELECTRIC DELIVERY COMPANY LLC
A3: REVENUE LAG - CALCULATION OF LAG DAYS FROM METER READ TO INVOICE (INVOICE SAMPLE RESULTS)
A4: FOR THE LEAD-LAG STUDY-PERIOD ENDING SEPTEMBER 30, 2021
A5: SPONSOR: A. THENMADATHIL
A7: Line No. | C7: Invoice Number | E7: Meter Read Date | F7: Meter Read Day of Week | G7: Invoice Date | I7: Lag Days from Meter Read to Invoice
C8: (a) | E8: (b) | F8: (c) | G8: (d) | I8: (e)
A10: 1 | C10: 8100077074126595973Z11 | E10: 44107 | F10: SATURDAY | G10: 44109 | I10: =+G10-E10 -> 2
A11: =A10+1 -> 2 | C11: 8100049185045251330Z10 | E11: 44243 | F11: TUESDAY | G11: 44244 | I11: =+G11-E11 -> 1
A12: =A11+1 -> 3 | C12: 8100024388456009046Z12 | E12: 44185 | F12: SUNDAY | G12: 44186 | I12: =+G12-E12 -> 1
A13: =A12+1 -> 4 | C13: 8100085552562066843Z11 | E13: 44422 | F13: SATURDAY | G13: 44424 | I13: =+G13-E13 -> 2
A14: =A13+1 -> 5 | C14: 8100067654692395487Z05 | E14: 44244 | F14: WEDNESDAY | G14: 44245 | I14: =+G14-E14 -> 1
A15: =A14+1 -> 6 | C15: 8100071883947499761Z10 | E15: 44431 | F15: MONDAY | G15: 44432 | I15: =+G15-E15 -> 1
A16: =A15+1 -> 7 | C16: 8100011182484050189Z11 | E16: 44195 | F16: WEDNESDAY | G16: 44196 | I16: =+G16-E16 -> 1
A17: =A16+1 -> 8 | C17: 8100071193269760821Z10 | E17: 44396 | F17: MONDAY | G17: 44411 | I17: =+G17-E17 -> 15
A18: =A17+1 -> 9 | C18: 8100099838838429441Z05 | E18: 44421 | F18: FRIDAY | G18: 44424 | I18: =+G18-E18 -> 3
A19: =A18+1 -> 10 | C19: 8100042975703997060Z11 | E19: 44362 | F19: TUESDAY | G19: 44363 | I19: =+G19-E19 -> 1
A20: =A19+1 -> 11 | C20: 8100521646481945548Z11 | E20: 44243 | F20: TUESDAY | G20: 44252 | I20: =+G20-E20 -> 9
A21: =A20+1 -> 12 | C21: 8100078797199145876Z11 | E21: 44216 | F21: WEDNESDAY | G21: 44217 | I21: =+G21-E21 -> 1
A22: =A21+1 -> 13 | C22: 8100094467212000969Z11 | E22: 44443 | F22: SATURDAY | G22: 44446 | I22: =+G22-E22 -> 3
... A62: =A61+1 -> 53 | C62: 8100071719156021454Z10 | E62: 44426 | F62: WEDNESDAY | G62: 44427 | I62: =+G62-E62 -> 1
A63: 54 | C63: 8100010879393209558Z07 | E63: 44134 | F63: FRIDAY | G63: 44137 | I63: =+G63-E63 -> 3
A64: =A63+1 -> 55 | C64: 8100079087361026687Z11 | E64: 44405 | F64: WEDNESDAY | G64: 44407 | I64: =+G64-E64 -> 2
A65: =A64+1 -> 56 | C65: 8100077663497250430Z10 | E65: 44285 | F65: TUESDAY | G65: 44286 | I65: =+G65-E65 -> 1
A66: =A65+1 -> 57 | C66: 8100080521212495869Z05 | E66: 44250 | F66: TUESDAY | G66: 44251 | I66: =+G66-E66 -> 1
A67: =A66+1 -> 58 | C67: 8100039073011168055Z11 | E67: 44191 | F67: SATURDAY | G67: 44193 | I67: =+G67-E67 -> 2
A68: =A67+1 -> 59 | C68: 8100069329120748832Z10 | E68: 44420 | F68: THURSDAY | G68: 44421 | I68: =+G68-E68 -> 1
A69: =A68+1 -> 60 | C69: 8100048926514972078Z10 | E69: 44242 | F69: MONDAY | G69: 44243 | I69: =+G69-E69 -> 1
A70: =A69+1 -> 61 | C70: 8100037853653739443Z10 | E70: 44293 | F70: WEDNESDAY | G70: 44294 | I70: =+G70-E70 -> 1
A71: =A70+1 -> 62 | C71: 8100080456219611987Z10 | E71: 44242 | F71: MONDAY | G71: 44243 | I71: =+G71-E71 -> 1
A72: =A71+1 -> 63 | C72: 8100022594781329054Z10 | E72: 44317 | F72: SATURDAY | G72: 44319 | I72: =+G72-E72 -> 2
A73: =A72+1 -> 64 | C73: 8100049508108927390Z11 | E73: 44124 | F73: TUESDAY | G73: 44125 | I73: =+G73-E73 -> 1
A74: =A73+1 -> 65 | C74: 8100088592851062141Z11 | E74: 44226 | F74: SATURDAY | G74: 44228 | I74: =+G74-E74 -> 2
A75: =A74+1 -> 66 | C75: 8100055474539217486Z12 | E75: 44185 | F75: SUNDAY | G75: 44186 | I75: =+G75-E75 -> 1
... A90: =A89+1 -> 81 | C90: 8100081338536924045Z10 | E90: 44242 | F90: MONDAY | G90: 44243 | I90: =+G90-E90 -> 1
A91: 82 | C91: 8100079304813040531Z12 | E91: 44172 | F91: MONDAY | G91: 44173 | I91: =+G91-E91 -> 1
A92: =A91+1 -> 83 | C92: 8100011314505525524Z13 | E92: 44214 | F92: MONDAY | G92: 44215 | I92: =+G92-E92 -> 1
A93: =A92+1 -> 84 | C93: 8100085602856111852Z13 | E93: 44163 | F93: SATURDAY | G93: 44165 | I93: =+G93-E93 -> 2
A94: =A93+1 -> 85 | C94: 8100059242118099064Z12 | E94: 44355 | F94: TUESDAY | G94: 44356 | I94: =+G94-E94 -> 1
A95: =A94+1 -> 86 | C95: 8100083710538997582Z11 | E95: 44114 | F95: SATURDAY | G95: 44116 | I95: =+G95-E95 -> 2
A96: =A95+1 -> 87 | C96: 8100016721250593117Z10 | E96: 44379 | F96: FRIDAY | G96: 44383 | I96: =+G96-E96 -> 4
A97: =A96+1 -> 88 | C97: 8100088629683762687Z10 | E97: 44440 | F97: WEDNESDAY | G97: 44441 | I97: =+G97-E97 -> 1
A98: =A97+1 -> 89 | C98: 8100097257732128462Z10 | E98: 44415 | F98: SATURDAY | G98: 44417 | I98: =+G98-E98 -> 2
A99: =A98+1 -> 90 | C99: 8100043720164249773Z05 | E99: 44134 | F99: FRIDAY | G99: 44137 | I99: =+G99-E99 -> 3
A100: =A99+1 -> 91 | C100: 8100075059099191647Z09 | E100: 44316 | F100: FRIDAY | G100: 44319 | I100: =+G100-E100 -> 3
A101: =A100+1 -> 92 | C101: 8100082361928190354Z10 | E101: 44271 | F101: TUESDAY | G101: 44272 | I101: =+G101-E101 -> 1
A102: =A101+1 -> 93 | C102: 8100073068115991593Z10 | E102: 44242 | F102: MONDAY | G102: 44243 | I102: =+G102-E102 -> 1
A103: =A102+1 -> 94 | C103: 8100058202246720741Z10 | E103: 44240 | F103: SATURDAY | G103: 44243 | I103: =+G103-E103 -> 3
... A125: =A124+1 -> 116 | C125: 8100022522127137542Z10 | E125: 44453 | F125: TUESDAY | G125: 44454 | I125: =+G125-E125 -> 1
A126: 117 | C126: Total | I126: =SUM(I10:I125) -> 243
A127: =A126+1 -> 118
A128: 119 | C128: Average | I128: =+I126/A125 -> 2.0948276
A129: 120
A130: 121
A131: 122 | C131: Source: | E131: Revenue billing sample.xlsx

Sheet 1-1-3
A1: 2022 RATE CASE
A2: =' '!A2 -> ONCOR ELECTRIC DELIVERY COMPANY LLC
A3: CALCULATION OF COLLECTION LAG
A4: FOR THE LEAD-LAG STUDY-PERIOD ENDING SEPTEMBER 30, 2021
A5: SPONSOR: A. THENMADATHIL
A7: Line
A8: No. | B8: Description | C8: Reference | D8: Amount | E8: Collection Lag Days
B9: (a) | C9: (b) | D9: (c) | E9: (d)
A11: 1 | B11: Total Accounts Receivable | C11: WP/II-B-9/1-1-3-1 | D11: =+'1-1-3-1'!D25 -> 1.3037315e+11
A12: 2 | B12: Revenues | C12: CC&B Revenue.xlsx | D12: 3.7554495e+09
A13: 3
A14: 4 | B14: Collection Lag (Line 1/Line 2) | E14: =ROUND(D11/D12,3) -> 34.716

Sheet 1-1-3-1
A1: 2022 RATE CASE
A2: =' '!A2 -> ONCOR ELECTRIC DELIVERY COMPANY LLC
A3: COLLECTION LAG
A4: FOR THE LEAD-LAG STUDY-PERIOD ENDING SEPTEMBER 30, 2021
A5: SPONSOR: A. THENMADATHIL
A7: Line
A8: No. | B8: Description | D8: Monthly Total
B9: (a) | D9: (b)
A11: 1 | B11: Sum of CC&B Daily A/R Balances
A12: 2 | B12: 44105 | D12: =+'1-1-3-1-1'!C41 -> 1.1762378e+10
A13: 3 | B13: 44136 | D13: =+'1-1-3-1-1'!E41 -> 9.8038933e+09
A14: 4 | B14: 44166 | D14: =+'1-1-3-1-1'!G41 -> 1.010434e+10
A15: 5 | B15: 44197 | D15: =+'1-1-3-1-1'!C76 -> 1.0516028e+10
A16: 6 | B16: 44228 | D16: =+'1-1-3-1-1'!E76 -> 1.0707084e+10
A17: 7 | B17: 44256 | D17: =+'1-1-3-1-1'!G76 -> 1.1923043e+10
A18: 8 | B18: 44287 | D18: =+'1-1-3-1-1'!C111 -> 9.9091148e+09
A19: 9 | B19: 44317 | D19: =+'1-1-3-1-1'!E111 -> 9.1357107e+09
A20: 10 | B20: 44348 | D20: =+'1-1-3-1-1'!G111 -> 9.5189259e+09
A21: 11 | B21: 44378 | D21: =+'1-1-3-1-1'!C146 -> 1.1350904e+10
A22: 12 | B22: 44409 | D22: =+'1-1-3-1-1'!E146 -> 1.3010918e+10
A23: 13 | B23: 44440 | D23: =+'1-1-3-1-1'!G146 -> 1.2630809e+10
A24: 14
A25: 15 | B25: Total Accounts Receivable | D25: =SUM(D12:D24) -> 1.3037315e+11
A26: 16
A27: 17 | B27: Source: WP/II-B-9/1-1-3-1-1

Sheet 1-1-3-1-1
A1: 2022 RATE CASE
A2: ='1'!A2 -> ONCOR ELECTRIC DELIVERY COMPANY LLC
A3: CUSTOMER INFORMATION SYSTEM DAILY ACCOUNTS RECEIVABLE
A4: FOR THE LEAD-LAG STUDY-PERIOD ENDING SEPTEMBER 30, 2021
A5: SPONSOR: A. THENMADATHIL
A7: Line No. | B7: Date | C7: A/R Balance | D7: Date | E7: A/R Balance | F7: Date | G7: A/R Balance
B8: (a) | C8: (b) | D8: (c) | E8: (d) | F8: (e) | G8: (f)
A10: 1 | B10: 44105 | C10: 4.1649087e+08 | D10: =+B40+1 -> 44136 | E10: 3.4840699e+08 | F10: =+D39+1 -> 44166 | G10: 3.1293526e+08
A11: =A10+1 -> 2 | B11: =+B10+1 -> 44106 | C11: 4.1246377e+08 | D11: =+D10+1 -> 44137 | E11: 3.2906713e+08 | F11: =+F10+1 -> 44167 | G11: 3.1699304e+08
A12: =A11+1 -> 3 | B12: =+B11+1 -> 44107 | C12: 4.1246377e+08 | D12: =+D11+1 -> 44138 | E12: 3.3200559e+08 | F12: =+F11+1 -> 44168 | G12: 3.2113828e+08
A13: =A12+1 -> 4 | B13: =+B12+1 -> 44108 | C13: 4.1246377e+08 | D13: =+D12+1 -> 44139 | E13: 3.3284994e+08 | F13: =+F12+1 -> 44169 | G13: 3.1177795e+08
A14: =A13+1 -> 5 | B14: =+B13+1 -> 44109 | C14: 4.0147216e+08 | D14: =+D13+1 -> 44140 | E14: 3.3480366e+08 | F14: =+F13+1 -> 44170 | G14: 3.2506549e+08
A15: =A14+1 -> 6 | B15: =+B14+1 -> 44110 | C15: 4.0108729e+08 | D15: =+D14+1 -> 44141 | E15: 3.2862643e+08 | F15: =+F14+1 -> 44171 | G15: 3.2506549e+08
A16: =A15+1 -> 7 | B16: =+B15+1 -> 44111 | C16: 3.9959011e+08 | D16: =+D15+1 -> 44142 | E16: 3.2862643e+08 | F16: =+F15+1 -> 44172 | G16: 3.2865297e+08
A17: =A16+1 -> 8 | B17: =+B16+1 -> 44112 | C17: 3.9862667e+08 | D17: =+D16+1 -> 44143 | E17: 3.2862643e+08 | F17: =+F16+1 -> 44173 | G17: 3.2771174e+08
A18: =A17+1 -> 9 | B18: =+B17+1 -> 44113 | C18: 3.9106316e+08 | D18: =+D17+1 -> 44144 | E18: 3.2385078e+08 | F18: =+F17+1 -> 44174 | G18: 3.2842422e+08
A19: =A18+1 -> 10 | B19: =+B18+1 -> 44114 | C19: 3.9106316e+08 | D19: =+D18+1 -> 44145 | E19: 3.2380616e+08 | F19: =+F18+1 -> 44175 | G19: 3.2896895e+08
A20: =A19+1 -> 11 | B20: =+B19+1 -> 44115 | C20: 3.9106316e+08 | D20: =+D19+1 -> 44146 | E20: 3.3498921e+08 | F20: =+F19+1 -> 44176 | G20: 3.2503676e+08
A21: =A20+1 -> 12 | B21: =+B20+1 -> 44116 | C21: 4.0165998e+08 | D21: =+D20+1 -> 44147 | E21: 3.2235445e+08 | F21: =+F20+1 -> 44177 | G21: 3.2503676e+08
A22: =A21+1 -> 13 | B22: =+B21+1 -> 44117 | C22: 3.9088685e+08 | D22: =+D21+1 -> 44148 | E22: 3.209638e+08 | F22: =+F21+1 -> 44178 | G22: 3.2503676e+08
... A39: =A38+1 -> 30 | B39: =+B38+1 -> 44134 | C39: 3.4840699e+08 | D39: =+D38+1 -> 44165 | E39: 3.0534855e+08 | F39: =+F38+1 -> 44195 | G39: 3.1617165e+08
A40: =A39+1 -> 31 | B40: =+B39+1 -> 44135 | C40: 3.4840699e+08 | F40: =+F39+1 -> 44196 | G40: 3.2004974e+08
A41: =A40+1 -> 32 | C41: =SUM(C10:C40) -> 1.1762378e+10 | E41: =SUM(E10:E40) -> 9.8038933e+09 | G41: =SUM(G10:G40) -> 1.010434e+10
A42: Line No. | B42: Date | C42: A/R Balance | D42: Date | E42: A/R Balance | F42: Date | G42: A/R Balance
B43: (a) | C43: (b) | D43: (c) | E43: (d) | F43: (e) | G43: (f)
A45: =A41+1 -> 33 | B45: =+F40+1 -> 44197 | C45: 320049742 | D45: =+B75+1 -> 44228 | E45: 3.7003812e+08 | F45: =+D73+1 -> 44257 | G45: 3.731075e+08
A46: =A45+1 -> 34 | B46: =+B45+1 -> 44198 | C46: 320049742 | D46: =+D45+1 -> 44229 | E46: 3.7396466e+08 | F46: =+F45+1 -> 44258 | G46: 3.7696053e+08
A47: =A46+1 -> 35 | B47: =+B46+1 -> 44199 | C47: 320049742 | D47: =+D46+1 -> 44230 | E47: 3.7595983e+08 | F47: =+F46+1 -> 44259 | G47: 3.799082e+08
A48: =A47+1 -> 36 | B48: =+B47+1 -> 44200 | C48: 3.2569394e+08 | D48: =+D47+1 -> 44231 | E48: 3.8082559e+08 | F48: =+F47+1 -> 44260 | G48: 3.8075685e+08
A49: =A48+1 -> 37 | B49: =+B48+1 -> 44201 | C49: 3.2660685e+08 | D49: =+D48+1 -> 44232 | E49: 3.7990342e+08 | F49: =+F48+1 -> 44261 | G49: 3.8075685e+08
A50: =A49+1 -> 38 | B50: =+B49+1 -> 44202 | C50: 3.2700189e+08 | D50: =+D49+1 -> 44233 | E50: 3.7990342e+08 | F50: =+F49+1 -> 44262 | G50: 3.8075685e+08
A51: =A50+1 -> 39 | B51: =+B50+1 -> 44203 | C51: 3.3193079e+08 | D51: =+D50+1 -> 44234 | E51: 3.7990342e+08 | F51: =+F50+1 -> 44263 | G51: 3.7944955e+08
A52: =A51+1 -> 40 | B52: =+B51+1 -> 44204 | C52: 3.3111653e+08 | D52: =+D51+1 -> 44235 | E52: 3.818177e+08 | F52: =+F51+1 -> 44264 | G52: 3.8132351e+08
A53: =A52+1 -> 41 | B53: =+B52+1 -> 44205 | C53: 3.4582489e+08 | D53: =+D52+1 -> 44236 | E53: 3.7755817e+08 | F53: =+F52+1 -> 44265 | G53: 3.8269876e+08
A54: =A53+1 -> 42 | B54: =+B53+1 -> 44206 | C54: 3.4582489e+08 | D54: =+D53+1 -> 44237 | E54: 3.7212725e+08 | F54: =+F53+1 -> 44266 | G54: 3.8527124e+08
A55: =A54+1 -> 43 | B55: =+B54+1 -> 44207 | C55: 3.3279804e+08 | D55: =+D54+1 -> 44238 | E55: 3.7272351e+08 | F55: =+F54+1 -> 44267 | G55: 3.8340464e+08
A56: =A55+1 -> 44 | B56: =+B55+1 -> 44208 | C56: 3.3530803e+08 | D56: =+D55+1 -> 44239 | E56: 3.6696474e+08 | F56: =+F55+1 -> 44268 | G56: 3.8340464e+08
A57: =A56+1 -> 45 | B57: =+B56+1 -> 44209 | C57: 3.3976575e+08 | D57: =+D56+1 -> 44240 | E57: 3.6696474e+08 | F57: =+F56+1 -> 44269 | G57: 3.8340464e+08
... A73: =A72+1 -> 61 | B73: =+B72+1 -> 44225 | C73: 3.6272682e+08 | D73: =+D72+1 -> 44256 | E73: 3.7163397e+08 | F73: =+F72+1 -> 44285 | G73: 3.8563942e+08
A74: =A73+1 -> 62 | B74: =+B73+1 -> 44226 | C74: 3.6272682e+08 | E74: 0 | F74: =+F73+1 -> 44286 | G74: 3.8193918e+08
A75: =A74+1 -> 63 | B75: =+B74+1 -> 44227 | C75: 362726825 | E75: 0 | F75: =+F74+1 -> 44287 | G75: 3.8988866e+08
A76: =A75+1 -> 64 | C76: =SUM(C45:C75) -> 1.0516028e+10 | E76: =SUM(E45:E75) -> 1.0707084e+10 | G76: =SUM(G45:G75) -> 1.1923043e+10
A77: Line No. | B77: Date | C77: A/R Balance | D77: Date | E77: A/R Balance | F77: Date | G77: A/R Balance
B78: (a) | C78: (b) | D78: (c) | E78: (d) | F78: (e) | G78: (f)
A80: =A76+1 -> 65 | B80: =+F75+1 -> 44288 | C80: 389888660 | D80: =+B109+1 -> 44318 | E80: 291329465 | F80: =+D110+1 -> 44349 | G80: 2.9984269e+08
A81: =A80+1 -> 66 | B81: =+B80+1 -> 44289 | C81: 389888660 | D81: =+D80+1 -> 44319 | E81: 2.8157122e+08 | F81: =+F80+1 -> 44350 | G81: 3.0502811e+08
A82: =A81+1 -> 67 | B82: =+B81+1 -> 44290 | C82: 389888660 | D82: =+D81+1 -> 44320 | E82: 2.8767294e+08 | F82: =+F81+1 -> 44351 | G82: 3.029371e+08
A83: =A82+1 -> 68 | B83: =+B82+1 -> 44291 | C83: 3.6205611e+08 | D83: =+D82+1 -> 44321 | E83: 2.8499733e+08 | F83: =+F82+1 -> 44352 | G83: 3.029371e+08
A84: =A83+1 -> 69 | B84: =+B83+1 -> 44292 | C84: 3.591578e+08 | D84: =+D83+1 -> 44322 | E84: 2.9006655e+08 | F84: =+F83+1 -> 44353 | G84: 3.029371e+08
A85: =A84+1 -> 70 | B85: =+B84+1 -> 44293 | C85: 3.5413254e+08 | D85: =+D84+1 -> 44323 | E85: 2.9109535e+08 | F85: =+F84+1 -> 44354 | G85: 3.0502418e+08
A86: =A85+1 -> 71 | B86: =+B85+1 -> 44294 | C86: 3.5243947e+08 | D86: =+D85+1 -> 44324 | E86: 2.9109535e+08 | F86: =+F85+1 -> 44355 | G86: 3.0842964e+08
A87: =A86+1 -> 72 | B87: =+B86+1 -> 44295 | C87: 3.5151069e+08 | D87: =+D86+1 -> 44325 | E87: 2.9109535e+08 | F87: =+F86+1 -> 44356 | G87: 3.0691318e+08
A88: =A87+1 -> 73 | B88: =+B87+1 -> 44296 | C88: 3.5151069e+08 | D88: =+D87+1 -> 44326 | E88: 2.9355021e+08 | F88: =+F87+1 -> 44357 | G88: 3.1035391e+08
A89: =A88+1 -> 74 | B89: =+B88+1 -> 44297 | C89: 3.5151069e+08 | D89: =+D88+1 -> 44327 | E89: 2.9717117e+08 | F89: =+F88+1 -> 44358 | G89: 3.108776e+08
A90: =A89+1 -> 75 | B90: =+B89+1 -> 44298 | C90: 337920684 | D90: =+D89+1 -> 44328 | E90: 2.9614585e+08 | F90: =+F89+1 -> 44359 | G90: 3.108776e+08
A91: =A90+1 -> 76 | B91: =+B90+1 -> 44299 | C91: 3.3437647e+08 | D91: =+D90+1 -> 44329 | E91: 2.9289723e+08 | F91: =+F90+1 -> 44360 | G91: 3.108776e+08
A92: =A91+1 -> 77 | B92: =+B91+1 -> 44300 | C92: 3.2927704e+08 | D92: =+D91+1 -> 44330 | E92: 2.9289211e+08 | F92: =+F91+1 -> 44361 | G92: 3.0293207e+08
... A109: =A108+1 -> 94 | B109: =+B108+1 -> 44317 | C109: 291329465 | D109: =+D108+1 -> 44347 | E109: 2.9852863e+08 | F109: =+F108+1 -> 44378 | G109: 3.5296144e+08
A110: =A109+1 -> 95 | C110: 0 | D110: =+D109+1 -> 44348 | E110: 2.9785479e+08 | G110: 0
A111: =A110+1 -> 96 | C111: =SUM(C80:C110) -> 9.9091148e+09 | E111: =SUM(E80:E110) -> 9.1357107e+09 | G111: =SUM(G80:G110) -> 9.5189259e+09
A112: Line No. | B112: Date | C112: A/R Balance | D112: Date | E112: A/R Balance | F112: Date | G112: A/R Balance
B113: (a) | C113: (b) | D113: (c) | E113: (d) | F113: (e) | G113: (f)
A115: =A111+1 -> 97 | B115: =+F109+1 -> 44379 | C115: 352961442 | D115: =+B145+1 -> 44410 | E115: 3.9165614e+08 | F115: =+D145+1 -> 44441 | G115: 4.3280041e+08
A116: =A115+1 -> 98 | B116: =+B115+1 -> 44380 | C116: 352961442 | D116: =+D115+1 -> 44411 | E116: 3.9956192e+08 | F116: =+F115+1 -> 44442 | G116: 4.3436206e+08
A117: =A116+1 -> 99 | B117: =+B116+1 -> 44381 | C117: 352961442 | D117: =+D116+1 -> 44412 | E117: 4.0177418e+08 | F117: =+F116+1 -> 44443 | G117: 4.3436206e+08
A118: =A117+1 -> 100 | B118: =+B117+1 -> 44382 | C118: 352961442 | D118: =+D117+1 -> 44413 | E118: 4.0747227e+08 | F118: =+F117+1 -> 44444 | G118: 4.3436206e+08
A119: =A118+1 -> 101 | B119: =+B118+1 -> 44383 | C119: 3.392041e+08 | D119: =+D118+1 -> 44414 | E119: 4.0999493e+08 | F119: =+F118+1 -> 44445 | G119: 4.3436206e+08
A120: =A119+1 -> 102 | B120: =+B119+1 -> 44384 | C120: 3.4122625e+08 | D120: =+D119+1 -> 44415 | E120: 4.0999493e+08 | F120: =+F119+1 -> 44446 | G120: 4.309405e+08
A121: =A120+1 -> 103 | B121: =+B120+1 -> 44385 | C121: 3.4584821e+08 | D121: =+D120+1 -> 44416 | E121: 4.0999493e+08 | F121: =+F120+1 -> 44447 | G121: 4.2737909e+08
A122: =A121+1 -> 104 | B122: =+B121+1 -> 44386 | C122: 3.5368471e+08 | D122: =+D121+1 -> 44417 | E122: 4.1538589e+08 | F122: =+F121+1 -> 44448 | G122: 4.2718814e+08
A123: =A122+1 -> 105 | B123: =+B122+1 -> 44387 | C123: 3.5368471e+08 | D123: =+D122+1 -> 44418 | E123: 4.3004302e+08 | F123: =+F122+1 -> 44449 | G123: 4.333442e+08
A124: =A123+1 -> 106 | B124: =+B123+1 -> 44388 | C124: 3.5368471e+08 | D124: =+D123+1 -> 44419 | E124: 4.2895345e+08 | F124: =+F123+1 -> 44450 | G124: 4.333442e+08
A125: =A124+1 -> 107 | B125: =+B124+1 -> 44389 | C125: 3.5658885e+08 | D125: =+D124+1 -> 44420 | E125: 4.2600273e+08 | F125: =+F124+1 -> 44451 | G125: 4.333442e+08
A126: =A125+1 -> 108 | B126: =+B125+1 -> 44390 | C126: 3.6440201e+08 | D126: =+D125+1 -> 44421 | E126: 4.2710121e+08 | F126: =+F125+1 -> 44452 | G126: 4.2638611e+08
A127: =A126+1 -> 109 | B127: =+B126+1 -> 44391 | C127: 3.6495966e+08 | D127: =+D126+1 -> 44422 | E127: 4.2710121e+08 | F127: =+F126+1 -> 44453 | G127: 4.3091021e+08
... A143: =A142+1 -> 125 | B143: =+B142+1 -> 44407 | C143: 3.796992e+08 | D143: =+D142+1 -> 44438 | E143: 4.1632564e+08 | F143: =+F142+1 -> 44469 | G143: 4.4263773e+08
A144: =A143+1 -> 126 | B144: =+B143+1 -> 44408 | C144: 379699198 | D144: =+D143+1 -> 44439 | E144: 4.2748027e+08 | G144: 0
A145: =A144+1 -> 127 | B145: =+B144+1 -> 44409 | C145: 379699198 | D145: =+D144+1 -> 44440 | E145: 4.3070713e+08 | G145: 0
A146: =A145+1 -> 128 | C146: =SUM(C115:C145) -> 1.1350904e+10 | E146: =SUM(E115:E145) -> 1.3010918e+10 | G146: =SUM(G115:G145) -> 1.2630809e+10
A147: 129
A148: 130 | B148: Source: | C148: Daily Receivable Backup.xlsx | G148: =SUM(C146:G146,C111:G111,C76:G76,C41:G41) -> 1.3037315e+11

Sheet 2
A1: 2022 RATE CASE
A2: =' '!A2 -> ONCOR ELECTRIC DELIVERY COMPANY LLC
A3: LABOR - PAYROLL LEAD DAYS
A4: FOR THE LEAD-LAG STUDY-PERIOD ENDING SEPTEMBER 30, 2021
A5: SPONSOR: A. THENMADATHIL
A7: Line No. | B7: Payroll Type | C7: Payroll Expense | D7: Percent | E7: Reference | F7: (Lead)/Lag | G7: Reference | H7: Check Float | I7: Reference | J7: Total (Lead)/Lag | K7: Weighted Dollar Days
B8: (a) | C8: (b) | D8: (c) | E8: (d) | F8: (e) | G8: (f) | H8: (g) | I8: (h) | J8: (i) | K8: (j)
A10: 1 | B10: Bi-Weekly
A11: 2
A12: 3 | B12: Direct Deposit | C12: =+C15*D12 -> 46520803 | D12: =D21 -> 0.9977 | E12: WP/II-B-9/2-1 | F12: =-'2-2'!C25 -> -11.96 | G12: WP/II-B-9/2-2 | H12: =H21 -> 0 | J12: =F12+H12 -> -11.96 | K12: =C12*J12 -> -5.563888e+08
A13: 4 | B13: Manual | C13: =C15-C12 -> 107244.51 | D13: =D22 -> 0.0023 | E13: WP/II-B-9/2-1 | F13: =F12 -> -11.96 | G13: WP/II-B-9/2-2 | H13: =H22 -> -7.27 | I13: WP/II-B-9/2-4 | J13: =F13+H13 -> -19.23 | K13: =C13*J13 -> -2062311.9
A14: 5
A15: 6 | B15: Total Bi-Weekly Pay | C15: =+D15*C35 -> 46628048 | D15: =+'2-6'!E11 -> 0.1713 | E15: WP/II-B-9/2-6 | J15: =K15/C15 -> -11.976721 | K15: =SUM(K12:K13) -> -5.5845112e+08
A16: 7
A17: 8 | B17: Semi-Monthly
A18: 9
A19: 10 | B19: 1st Pay Period:
A20: 11
A21: 12 | B21: Direct Deposit | C21: =+C24*D21 -> 1.1176193e+08 | D21: =+'2-1'!F18 -> 0.9977 | E21: WP/II-B-9/2-1 | F21: =+'2-3'!C57 -> -12.08 | G21: WP/II-B-9/2-3 | H21: 0 | J21: =F21+H21 -> -12.08 | K21: =C21*J21 -> -1.3500841e+09
A22: 13 | B22: Manual | C22: =C24-C21 -> 257645.02 | D22: =+'2-1'!G18 -> 0.0023 | E22: WP/II-B-9/2-1 | F22: =+'2-3'!C57 -> -12.08 | G22: WP/II-B-9/2-3 | H22: ='2-4'!D14 -> -7.27 | I22: WP/II-B-9/2-4 | J22: =F22+H22 -> -19.35 | K22: =C22*J22 -> -4985431.2
A23: 14
A24: 15 | B24: Total 1st Pay Period | C24: =+C33*D24 -> 1.1201958e+08 | D24: ='2-5'!C31 -> 0.4966 | E24: WP/II-B-9/2-5 | J24: =K24/C24 -> -12.096721 | K24: =SUM(K21:K22) -> -1.3550695e+09
A25: 16
A26: 17 | B26: 2nd Pay Period:
A27: 18
A28: 19 | B28: Direct Deposit | C28: =+C31*D28 -> 1.132923e+08 | D28: =+'2-1'!F18 -> 0.9977 | E28: WP/II-B-9/2-1 | F28: =+'2-3'!C58 -> -12.17 | G28: WP/II-B-9/2-3 | H28: 0 | J28: =F28+H28 -> -12.17 | K28: =C28*J28 -> -1.3787673e+09
A29: 20 | B29: Manual | C29: =C31-C28 -> 261172.99 | D29: =+'2-1'!G18 -> 0.0023 | E29: WP/II-B-9/2-1 | F29: =+'2-3'!C58 -> -12.17 | G29: WP/II-B-9/2-3 | H29: =+H22 -> -7.27 | I29: WP/II-B-9/2-4 | J29: =F29+H29 -> -19.44 | K29: =C29*J29 -> -5077202.8
A30: 21
A31: 22 | B31: Total 2nd Pay Period | C31: =+D31*C33 -> 1.1355347e+08 | D31: ='2-5'!D31 -> 0.5034 | E31: WP/II-B-9/2-5 | J31: =K31/C31 -> -12.186721 | K31: =SUM(K28:K29)-1 -> -1.3838445e+09
A32: 23
A33: 24 | B33: Total Semi-Monthly | C33: =+C35*D33 -> 2.2557305e+08 | D33: =+'2-6'!F11 -> 0.8287 | E33: WP/II-B-9/2-6 | J33: =K33/C33 -> -12.142027 | K33: =K31+K24+1 -> -2.738914e+09
A34: 25
A35: 26 | B35: Total | C35: 2.7220109e+08 | D35: =+D33+D15 -> 1 | E35: Schedule II-D-3 * | F35: =ROUND(((C15*F12)+(C24*F21)+(C31*F28))/C35,2) -> -12.1 | J35: =ROUND(K35/C35,2) -> -12.11 | K35: =K33+K15 -> -3.2973651e+09
A36: 27 | E36: *Net of Incentive Pay

Sheet 2-1
A1: 2022 RATE CASE
A2: =' '!A2 -> ONCOR ELECTRIC DELIVERY COMPANY LLC
A3: PAYROLL LEAD - DIRECT DEPOSIT CALCULATION
A4: FOR THE LEAD-LAG STUDY-PERIOD ENDING SEPTEMBER 30, 2021
A5: SPONSOR: A. THENMADATHIL
A7: Line No. | B7: Period/Business Unit | C7: Direct Deposit | D7: Manual Checks | E7: Total - Direct Deposit and Manual Checks | F7: Percent Paid via Direct Deposit | G7: Percent Paid via Manual Check
B8: (a) | C8: (b) | D8: (c) | E8: (d) | F8: (e) | G8: (f)
A10: 1 | B10: 44105
A11: =A10+1 -> 2 | B11: Transmission | C11: 7333759.5 | D11: 13002.55 | E11: =+C11+D11 -> 7346762.1
A12: =A11+1 -> 3 | B12: Distribution | C12: 19176623 | D12: 58444.75 | E12: =+C12+D12 -> 19235068
A13: =A12+1 -> 4
A14: =A13+1 -> 5 | B14: 44440
A15: =A14+1 -> 6 | B15: Transmission | C15: 6931833 | D15: 0 | E15: =+C15+D15 -> 6931833
A16: =A15+1 -> 7 | B16: Distribution | C16: 20093523 | D16: 52184.22 | E16: =+C16+D16 -> 20145707
A17: =A16+1 -> 8
A18: =A17+1 -> 9 | B18: Total Payments | C18: =SUM(C10:C16) -> 53535739 | D18: =SUM(D10:D16) -> 123631.52 | E18: =SUM(E10:E16) -> 53659370 | F18: =+ROUND(C18/$E$18,4) -> 0.9977 | G18: =+ROUND(D18/$E$18,4) -> 0.0023
A19: =A18+1 -> 10
A20: =A19+1 -> 11 | F20: (1) | G20: (2)
A21: =A20+1 -> 12 | B21: Note:
A22: =A21+1 -> 13 | B22: (1) The calculation is Col (b) Ln 9 divided by Col (d) Ln 9.
A23: =A22+1 -> 14 | B23: (2) The calculation is Col (c) Ln 9 divided by Col (d) Ln 9.
A24: =A23+1 -> 15
A25: =A24+1 -> 16 | B25: Source: | C25: Payroll direct deposit.xlsx

Sheet 2-2
A1: 2022 RATE CASE
A2: =' '!A2 -> ONCOR ELECTRIC DELIVERY COMPANY LLC
A3: PAYROLL LEAD - BI-WEEKLY PAYROLL CALCULATION
A4: FOR THE LEAD-LAG STUDY-PERIOD ENDING SEPTEMBER 30, 2021
A5: SPONSOR: A. THENMADATHIL
A7: Line No. | B7: Bi-Weekly | C7: Days
B8: (a) | C8: (b)
A10: 1 | B10: Conditions:
A11: 2
A12: 3 | B12: Pay Periods cover 14 days.
A13: 4 | B13: Start on Monday and end on the second following Sunday.
A14: 5 | B14: Payment Checks or Direct Deposits typically are made on Friday, five days after end of pay period.
A15: 6 | B15: (If the scheduled pay date is a holiday, payment is made on the preceding work day. During
A16: 7 | B16: the test period, with the exception of one instance, all paydays fell on the regularly scheduled Friday.)
A17: 8
A18: 9
A19: 10 | B19: Days in Period:
A20: 11
A21: 12 | B21: 14 days. Midpoint = 7
A22: 13
A23: 14 | B23: Payroll Lead Formula:
A24: 15
A25: 16 | B25: (7 days) + (4.96 days) = | C25: =7+4.96 -> 11.96
A27: Sources: | B27: Holidays.xlsx
B28: Bi-Weekly Payroll Calendar 2021.xlsx
B29: Bi-Weekly Payroll Calendar 2020.xlsx

Sheet 2-2-1
A1: 2022 RATE CASE
A2: =' '!A2 -> ONCOR ELECTRIC DELIVERY COMPANY LLC
A3: PAYROLL LEAD - HOLIDAY/WEEKEND FACTOR CALCULATION - BI-WEEKLY
A4: FOR THE LEAD-LAG STUDY-PERIOD ENDING SEPTEMBER 30, 2021
A5: SPONSOR: A. THENMADATHIL
A8: Line No. | B8: Scheduled Payday | C8: Normal Payment Lead Days | E8: Lead Days Reflecting Holiday Adjustments | G8: Total
B9: (a) | C9: (b) | E9: (c) | G9: (d)
A11: 1 | B11: 44113 | C11: 5 | G11: =C11+E11 -> 5
A12: 2 | B12: 44127 | C12: 5 | G12: =C12+E12 -> 5
A13: 3 | B13: 44141 | C13: 5 | G13: =C13+E13 -> 5
A14: 4 | B14: 44155 | C14: 5 | G14: =C14+E14 -> 5
A15: 5 | B15: 44169 | C15: 5 | G15: =C15+E15 -> 5
A16: 6 | B16: 44183 | C16: 5 | E16: 0 | G16: =C16+E16 -> 5
A17: 7 | B17: 44196 | C17: 0 | E17: 4 | G17: =C17+E17 -> 4
A18: 8 | B18: 44211 | C18: 5 | G18: =C18+E18 -> 5
A19: 9 | B19: 44225 | C19: 5 | G19: =C19+E19 -> 5
A20: 10 | B20: 44239 | C20: 5 | G20: =C20+E20 -> 5
A21: 11 | B21: 44253 | C21: 5 | G21: =C21+E21 -> 5
A22: 12 | B22: 44267 | C22: 5 | G22: =C22+E22 -> 5
A23: 13 | B23: 44281 | C23: 5 | G23: =C23+E23 -> 5
A24: 14 | B24: 44295 | C24: 5 | G24: =C24+E24 -> 5
A25: 15 | B25: 44309 | C25: 5 | G25: =C25+E25 -> 5
A26: =+A25+1 -> 16 | B26: 44323 | C26: 5 | G26: =C26+E26 -> 5
A27: =+A26+1 -> 17 | B27: 44337 | C27: 5 | G27: =C27+E27 -> 5
A28: =+A27+1 -> 18 | B28: 44351 | C28: 5 | G28: =C28+E28 -> 5
A29: =+A28+1 -> 19 | B29: 44365 | C29: 5 | G29: =C29+E29 -> 5
A30: =+A29+1 -> 20 | B30: 44379 | C30: 5 | E30: 0 | G30: =C30+E30 -> 5
A31: =+A30+1 -> 21 | B31: 44393 | C31: 5 | G31: =C31+E31 -> 5
A32: =+A31+1 -> 22 | B32: 44407 | C32: 5 | G32: =C32+E32 -> 5
A33: =+A32+1 -> 23 | B33: 44421 | C33: 5 | G33: =C33+E33 -> 5
A34: =+A33+1 -> 24 | B34: 44435 | C34: 5 | G34: =C34+E34 -> 5
A35: =+A34+1 -> 25 | B35: 44449 | C35: 5 | E35: 0 | G35: =C35+E35 -> 5
A36: =+A35+1 -> 26 | B36: 44463 | C36: 5 | G36: =C36+E36 -> 5
A37: =+A36+1 -> 27 | B37: Total Days | C37: =SUM(C11:C36) -> 125 | E37: =SUM(E11:E36) -> 4 | G37: =SUM(G11:G36) -> 129
A38: =+A37+1 -> 28
A39: =+A38+1 -> 29
A40: =+A39+1 -> 30 | B40: Number of Annual Payroll Cycles | G40: =SUM(A36) -> 26
A41: =+A40+1 -> 31 | B41: Average of Lead Days Before Payment | G41: =ROUND(G37/G40,2) -> 4.96
A42: =+A41+1 -> 32
A43: =+A42+1 -> 33
A44: =+A43+1 -> 34 | B44: Sources: | C44: Holidays.xlsx
A45: =+A44+1 -> 35 | C45: Bi-Weekly Payroll Calendar 2021.xlsx
A46: =+A45+1 -> 36 | C46: Bi-Weekly Payroll Calendar 2020.xlsx

Sheet 2-3
A1: 2022 RATE CASE
A2: =' '!A2 -> ONCOR ELECTRIC DELIVERY COMPANY LLC
A3: PAYROLL LEAD - SEMI-MONTHLY PAYROLL CALCULATION
A4: FOR THE LEAD-LAG STUDY-PERIOD ENDING SEPTEMBER 30, 2021
A5: SPONSOR: A. THENMADATHIL
A7: Line No. | B7: Semi-Monthly
B8: (a) | C8: (b) | D8: (c) | E8: (d)
A10: 1 | B10: Assumptions:
A11: 2
A12: 3 | B12: First Pay Period | C12: 26th - 10th
A13: 4 | B13: Second Pay Period | C13: 11th - 25th
A14: 5
A15: 6
A16: 7 | B16: Days in Period:
A17: 8
A18: 9 | B18: Average Days in Month | C18: =ROUND(366/12,3) -> 30.5 | D18: Days of Year divided by 12 months
A19: 10
A20: 11 | B20: First Pay Period | C20: =C18-C21 -> 15.5 | D20: Col (b) Ln 9 minus Col (b) Ln 12
A21: 12 | B21: Second Pay Period | C21: 15
A22: 13 | B22: Average First Pay Period | C22: =ROUND(+C20/2,3) -> 7.75 | D22: Col (b) Ln 11 divided by 2
A23: 14 | B23: Average Second Pay Period | C23: =ROUND(+C21/2,3) -> 7.5 | D23: Col (b) Ln 12 divided by 2
A24: 15
A25: 16
A26: 17 | B26: Days Until Payment:
A27: 18
A28: 19 | B28: First Pay Period | C28: 5 | D28: End on 10th, Paid on 15th
A29: 20 | B29: Second Pay Period | C29: =E47 -> 5.42 | D29: Col (d) Ln 38
A30: 21 | C30: Days of Month | E30: Difference
A31: 22 | B31: 44105 | C31: 31 | D31: 25 | E31: =C31-D31 -> 6
A32: 23 | B32: 44136 | C32: 30 | D32: 25 | E32: =C32-D32 -> 5
A33: 24 | B33: 44166 | C33: 31 | D33: 25 | E33: =C33-D33 -> 6
A34: =A33+1 -> 25 | B34: 44197 | C34: 31 | D34: 25 | E34: =C34-D34 -> 6
A35: =A34+1 -> 26 | B35: 44228 | C35: 28 | D35: 25 | E35: =C35-D35 -> 3
A36: =A35+1 -> 27 | B36: 44256 | C36: 31 | D36: 25 | E36: =C36-D36 -> 6
A37: =A36+1 -> 28 | B37: 44287 | C37: 30 | D37: 25 | E37: =C37-D37 -> 5
A38: =A37+1 -> 29 | B38: 44317 | C38: 31 | D38: 25 | E38: =C38-D38 -> 6
A39: =A38+1 -> 30 | B39: 44348 | C39: 30 | D39: 25 | E39: =C39-D39 -> 5
A40: =A39+1 -> 31 | B40: 44378 | C40: 31 | D40: 25 | E40: =C40-D40 -> 6
A41: =A40+1 -> 32 | B41: 44409 | C41: 31 | D41: 25 | E41: =C41-D41 -> 6
A42: =A41+1 -> 33 | B42: 44440 | C42: 30 | D42: 25 | E42: =C42-D42 -> 5
A43: =A42+1 -> 34 | C43: =SUM(C31:C42) -> 365 | E43: =SUM(E31:E42) -> 65
A44: =A43+1 -> 35
A45: =A44+1 -> 36 | D45: Divided by Number of Months | E45: =COUNT(E31:E42) -> 12
A46: =A45+1 -> 37 | D46: Second Pay Period
A47: =A46+1 -> 38 | D47: Days Until Payment: | E47: =ROUND(E43/E45,2) -> 5.42
A48: =A47+1 -> 39
A49: =A48+1 -> 40 | B49: Weekend/Holiday Factor:
A50: =A49+1 -> 41
A51: =A50+1 -> 42 | B51: First Pay Period | C51: =+'2-3-1'!C38*-1 -> -0.67 | E51: WP/II-B-9/2-3-1
A52: =A51+1 -> 43 | B52: Second Pay Period | C52: =+'2-3-1'!D38*-1 -> -0.75 | E52: WP/II-B-9/2-3-1
A53: =A52+1 -> 44
A54: =A53+1 -> 45
A55: =A54+1 -> 46 | B55: Payroll Lead Formula:
A56: =A55+1 -> 47
A57: =A56+1 -> 48 | B57: First Pay Period | C57: =-(+C22+C28+C51) -> -12.08 | D57: Col (b) Ln 13 plus Col (b) Ln 19 plus Col (b) Ln 42
A58: =A57+1 -> 49 | B58: Second Pay Period | C58: =-(+C23+C29+C52) -> -12.17 | D58: Col (b) Ln 14 plus Col (b) Ln 20 plus Col (b) Ln 43
A59: =A58+1 -> 50 | B59: Average First and Second Pay Period | C59: =ROUND((+C57+C58)/2,3) -> -12.125 | D59: Col (b) Ln 48 plus Col (b) Ln 49 divided by 2

Sheet 2-3-1
A1: 2022 RATE CASE
A2: =' '!A2 -> ONCOR ELECTRIC DELIVERY COMPANY LLC
A3: PAYROLL LEAD - HOLIDAY/WEEKEND FACTOR CALCULATION - SEMI MONTHLY
A4: FOR THE LEAD-LAG STUDY-PERIOD ENDING SEPTEMBER 30, 2021
A5: SPONSOR: A. THENMADATHIL
C7: Days Payday Moved Up
A8: Line No. | B8: Scheduled Payday | C8: 1st Pay Period | D8: 2nd Pay Period | F8: Actual Payday | H8: Difference
B9: (a) | C9: (b) | D9: (c) | F9: (d) | H9: (e)
A11: 1 | B11: 44119 | C11: 0 | D11: 0 | F11: =+B11-C11-D11 -> 44119 | H11: =+B11-F11 -> 0
A12: 2 | B12: =+B11+16 -> 44135 | C12: 0 | D12: 1 | F12: =+B12-C12-D12 -> 44134 | H12: =+B12-F12 -> 1
A13: 3 | B13: =+B12+15 -> 44150 | C13: 2 | D13: 0 | F13: =+B13-C13-D13 -> 44148 | H13: =+B13-F13 -> 2
A14: 4 | B14: =+B13+15 -> 44165 | C14: 0 | D14: 0 | F14: =+B14-C14-D14 -> 44165 | H14: =+B14-F14 -> 0
A15: 5 | B15: =+B14+15 -> 44180 | C15: 0 | D15: 0 | F15: =+B15-C15-D15 -> 44180 | H15: =+B15-F15 -> 0
A16: 6 | B16: =+B15+16 -> 44196 | C16: 0 | D16: 0 | F16: =+B16-C16-D16 -> 44196 | H16: =+B16-F16 -> 0
A17: 7 | B17: =+B16+15 -> 44211 | C17: 0 | D17: 0 | F17: =+B17-C17-D17 -> 44211 | H17: =+B17-F17 -> 0
A18: 8 | B18: =+B17+16 -> 44227 | C18: 0 | D18: 2 | F18: =+B18-C18-D18 -> 44225 | H18: =+B18-F18 -> 2
A19: 9 | B19: =+B18+15 -> 44242 | C19: 3 | D19: 0 | F19: =+B19-C19-D19 -> 44239 | H19: =+B19-F19 -> 3
A20: 10 | B20: =+B19+13 -> 44255 | C20: 0 | D20: 2 | F20: =+B20-C20-D20 -> 44253 | H20: =+B20-F20 -> 2
A21: 11 | B21: =+B20+15 -> 44270 | C21: 0 | D21: 0 | F21: =+B21-C21-D21 -> 44270 | H21: =+B21-F21 -> 0
A22: 12 | B22: =+B21+16 -> 44286 | C22: 0 | D22: 0 | F22: =+B22-C22-D22 -> 44286 | H22: =+B22-F22 -> 0
A23: 13 | B23: =+B22+15 -> 44301 | C23: 0 | D23: 0 | F23: =+B23-C23-D23 -> 44301 | H23: =+B23-F23 -> 0
A24: 14 | B24: =+B23+15 -> 44316 | C24: 0 | D24: 0 | F24: =+B24-C24-D24 -> 44316 | H24: =+B24-F24 -> 0
A25: 15 | B25: =+B24+15 -> 44331 | C25: 1 | D25: 0 | F25: =+B25-C25-D25 -> 44330 | H25: =+B25-F25 -> 1
A26: =+A25+1 -> 16 | B26: =+B25+16 -> 44347 | C26: 0 | D26: 3 | F26: =+B26-C26-D26 -> 44344 | H26: =+B26-F26 -> 3
A27: =+A26+1 -> 17 | B27: =+B26+15 -> 44362 | C27: 0 | D27: 0 | F27: =+B27-C27-D27 -> 44362 | H27: =+B27-F27 -> 0
A28: =+A27+1 -> 18 | B28: =+B27+15 -> 44377 | C28: 0 | D28: 0 | F28: =+B28-C28-D28 -> 44377 | H28: =+B28-F28 -> 0
A29: =+A28+1 -> 19 | B29: =+B28+15 -> 44392 | C29: 0 | D29: 0 | F29: =+B29-C29-D29 -> 44392 | H29: =+B29-F29 -> 0
A30: =+A29+1 -> 20 | B30: =+B29+16 -> 44408 | C30: 0 | D30: 1 | F30: =+B30-C30-D30 -> 44407 | H30: =+B30-F30 -> 1
A31: =+A30+1 -> 21 | B31: =+B30+15 -> 44423 | C31: 2 | D31: 0 | F31: =+B31-C31-D31 -> 44421 | H31: =+B31-F31 -> 2
A32: =+A31+1 -> 22 | B32: =+B31+16 -> 44439 | C32: 0 | D32: 0 | F32: =+B32-C32-D32 -> 44439 | H32: =+B32-F32 -> 0
A33: =+A32+1 -> 23 | B33: =+B32+15 -> 44454 | C33: 0 | D33: 0 | F33: =+B33-C33-D33 -> 44454 | H33: =+B33-F33 -> 0
A34: =+A33+1 -> 24 | B34: =+B33+15 -> 44469 | C34: 0 | D34: 0 | F34: =+B34-C34-D34 -> 44469 | H34: =+B34-F34 -> 0
A35: =+A34+1 -> 25
A36: =+A35+1 -> 26 | B36: Total | C36: =SUM(C11:C35) -> 8 | D36: =SUM(D11:D35) -> 9 | H36: =SUM(H11:H35) -> 17
A37: =+A36+1 -> 27
A38: =+A37+1 -> 28 | B38: Average | C38: =ROUND(C36/12,2) -> 0.67 | D38: =ROUND(D36/12,2) -> 0.75
A39: =+A38+1 -> 29
A40: =+A39+1 -> 30 | B40: Sources: | C40: Holidays.xlsx
A41: =+A40+1 -> 31 | C41: Payroll Calendar Semi-Monthly

Sheet 2-4
A1: 2022 RATE CASE
A2: =' '!A2 -> ONCOR ELECTRIC DELIVERY COMPANY LLC
A3: PAYROLL LEAD - CHECK FLOAT CALCULATION
A4: FOR THE LEAD-LAG STUDY-PERIOD ENDING SEPTEMBER 30, 2021
A5: SPONSOR: A. THENMADATHIL
E7: Weighted
A8: Line No. | B8: Business Unit | C8: Net Amount | D8: (Lead)/Lag Days | E8: Dollar Days | F8: Total
B9: (a) | C9: (b) | D9: (c) | E9: (d)
A11: 1 | B11: Transmission | C11: 50746.94 | D11: -8.4547616 | E11: =+D11*C11 -> -429053.28
A12: 2 | B12: Distribution | C12: 196900.21 | D12: -6.9640342 | E12: =+D12*C12 -> -1371219.8
A13: 3
A14: 4 | B14: Total | C14: =SUM(C11:C12) -> 247647.15 | D14: =ROUND(E14/C14,2) -> -7.27 | E14: =SUM(E11:E12) -> -1800273.1
A15: 5
A16: 6 | B16: Source: | C16: Payroll manual check sample.xlsx

Sheet 2-5
A1: 2022 RATE CASE
A2: =' '!A2 -> ONCOR ELECTRIC DELIVERY COMPANY LLC
A3: PAYROLL LEAD - PAY CYCLE CALCULATION
A4: FOR THE LEAD-LAG STUDY-PERIOD ENDING SEPTEMBER 30, 2021
A5: SPONSOR: A. THENMADATHIL
A7: Line No. | B7: Description | C7: First Cycle | D7: Second Cycle | E7: Third Cycle | F7: Total
B8: (a) | C8: (b) | D8: (c) | E8: (c) | F8: (d)
B9: Biweekly
A10: 1 | B10: Distribution
A11: 2 | B11: October 2020 | C11: 3227958.8 | D11: 3209451.1 | E11: 0 | F11: =SUM(C11:E11) -> 6437409.9
A12: 3 | B12: September 2021 | C12: 3577242.9 | D12: 3603265.5 | E12: 0 | F12: =SUM(C12:E12) -> 7180508.4
A13: 4 | B13: Total | C13: =SUM(C11+C12) -> 6805201.7 | D13: =SUM(D11+D12) -> 6812716.6 | E13: =SUM(E11+E12) -> 0 | F13: =SUM(F11+F12) -> 13617918
A14: 5 | B14: Percent | C14: =ROUND(SUM(C13/$F$13),4) -> 0.4997 | D14: =ROUND(SUM(D13/$F$13),4) -> 0.5003 | E14: =ROUND(SUM(E13/$F$13),4) -> 0 | F14: =SUM(C13+D13+E13)/F13 -> 1
A15: 6
B16: Semimonthly
A17: 1 | B17: Distribution
A18: 2 | B18: October 2020 | C18: 11931676 | D18: 11638891 | F18: =SUM(C18:E18) -> 23570566
A19: 3 | B19: September 2021 | C19: 12194054 | D19: 12233896 | F19: =SUM(C19:E19) -> 24427950
A20: 4 | B20: Total | C20: =SUM(C18+C19) -> 24125730 | D20: =SUM(D18+D19) -> 23872786 | F20: =SUM(F18+F19) -> 47998516
A21: 5 | B21: Percent | C21: =ROUND(SUM(C20/$F$20),4) -> 0.5026 | D21: =ROUND(SUM(D20/$F$20),4) -> 0.4974 | F21: =SUM(C20+D20+E20)/F20 -> 1
A24: 7 | B24: Transmission
A25: 8 | B25: October 2020 | C25: 5401716.1 | D25: 5859475 | F25: =SUM(C25:E25) -> 11261191
A26: 9 | B26: September 2021 | C26: 5220787.5 | D26: 5497216.9 | F26: =SUM(C26:E26) -> 10718004
A27: 10 | B27: Total | C27: =SUM(C25+C26) -> 10622504 | D27: =SUM(D25+D26) -> 11356692 | F27: =SUM(F25+F26) -> 21979196
A28: 11 | B28: Percent | C28: =ROUND(SUM(C27/$F$27),4) -> 0.4833 | D28: =ROUND(SUM(D27/$F$27),4) -> 0.5167 | F28: =SUM(C27+D27+E27)/F27 -> 1
A29: 12
A30: 13 | B30: Total T&D | C30: =C27+C20 -> 34748233 | D30: =D27+D20 -> 35229478 | F30: =SUM(C30:E30) -> 69977712
A31: 14 | B31: Percent | C31: =ROUND(C30/F30,4) -> 0.4966 | D31: =ROUND(D30/F30,4) -> 0.5034 | F31: =SUM(C30+D30+E30)/F30 -> 1
A32: 15
A33: 16 | B33: Source: | C33: Payroll pay cycles.xlsx

Sheet 2-6
A1: 2022 RATE CASE
A2: =' '!A2 -> ONCOR ELECTRIC DELIVERY COMPANY LLC
A3: PAYROLL LEAD - BI-WEEKLY/SEMI-MONTHLY PAY CALCULATION
A4: FOR THE LEAD-LAG STUDY-PERIOD ENDING SEPTEMBER 30, 2021
A5: SPONSOR: A. THENMADATHIL
A7: Line | E7: Bi-Weekly | F7: Semi-Monthly
A8: No. | B8: Description | C8: Total Payroll | D8: Bi-Weekly | E8: Percent | F8: Percent
B9: (a) | C9: (b) | D9: (c) | E9: (d) | F9: (e)
A11: 1 | B11: Payroll | C11: 6.017112e+08 | D11: 1.0308301e+08 | E11: =ROUND(D11/C11,4) -> 0.1713 | F11: =1-E11 -> 0.8287
A12: 2
A13: 3 | B13: Source: | C13: Payroll semi-monthly & bi-weekly.xlsx

Sheet 3
A1: 2022 RATE CASE
A2: =' '!A2 -> ONCOR ELECTRIC DELIVERY COMPANY LLC
A3: LABOR - INCENTIVE PAY LEAD DAYS
A4: FOR THE LEAD-LAG STUDY-PERIOD ENDING SEPTEMBER 30, 2021
A5: SPONSOR: A. THENMADATHIL
A7: Line No. | B7: Description | C7: Payroll Expense | D7: Percent | E7: Reference | F7: (Lead)/Lag | G7: Reference | H7: Check Float | I7: Reference | J7: Total (Lead)/Lag | K7: Weighted Dollar Days
B8: (a) | C8: (b) | D8: (c) | E8: (d) | F8: (e) | G8: (f) | H8: (g) | I8: (h) | J8: (i) | K8: (j)
A10: 1 | B10: Test Year Incentive | C10: =+C12-C11 -> 24995198
A11: =A10+1 -> 2 | B11: Adjustment Needed | C11: 2583392.3
A12: =A11+1 -> 3 | B12: Adjusted Incentive | C12: 27578590 | E12: Source 1
A14: =A12+1 -> 4
A15: =A14+1 -> 5 | B15: Direct Deposit | C15: =+C17*D15 -> 27515160 | D15: =+'2-1'!F18 -> 0.9977 | E15: WP/II-B-9/2-1 | F15: ='3-1'!F34 -> -249.33 | G15: WP/II-B-9/3-1 | H15: 0 | J15: =+H15+F15 -> -249.33 | K15: =+J15*C15 -> -6.8603547e+09
A16: =A15+1 -> 6 | B16: Manual | C16: =+C17*D16 -> 63430.758 | D16: =+'2-1'!G18 -> 0.0023 | E16: WP/II-B-9/2-1 | F16: =F15 -> -249.33 | G16: WP/II-B-9/3-1 | H16: ='2-4'!D14 -> -7.27 | I16: WP/II-B-9/2-4 | J16: =+H16+F16 -> -256.6 | K16: =+J16*C16 -> -16276332
A17: =A16+1 -> 7 | B17: Total Adjusted Incentive | C17: =+C12 -> 27578590 | J17: =K17/C17 -> -249.34672 | K17: =+K16+K15 -> -6.8766311e+09
A18: =A17+1 -> 8
A19: =A18+1 -> 9
A20: =A19+1 -> 10 | B20: Source 1: | C20: Iteration "Adjusted Test Year Amount"

Sheet 3-1
A1: 2022 RATE CASE
A2: =' '!A2 -> ONCOR ELECTRIC DELIVERY COMPANY LLC
A3: PEP AWARD LEAD PAYMENT CALCULATION
A4: FOR THE LEAD-LAG STUDY-PERIOD ENDING SEPTEMBER 30, 2021
A5: SPONSOR: A. THENMADATHIL
A7: Line No. | B7: Month | C7: Accrual Date | D7: Mid Month | E7: Payout Date | F7: (Lead)/Lag Days
B8: (a) | C8: (b) | D8: (c) | E8: (d) | F8: (e)
A10: 1 | B10: 44105 | C10: 44135 | D10: =IF(C10=0,"",DATE(YEAR(C10),MONTH(C10),1)+INT(DAY(DATE(YEAR(C10),MONTH(C10)+1,1)-1)/2)-0.5) -> 44119.5 | E10: 44263 | F10: =D10-E10 -> -143.5
A11: 2
A12: 3 | B12: =B10+31 -> 44136 | C12: =C10+30 -> 44165 | D12: =IF(C12=0,"",DATE(YEAR(C12),MONTH(C12),1)+INT(DAY(DATE(YEAR(C12),MONTH(C12)+1,1)-1)/2)-0.5) -> 44150.5 | E12: =$E$10 -> 44263 | F12: =D12-E12 -> -112.5
A13: 4
A14: 5 | B14: =B12+30 -> 44166 | C14: =C12+31 -> 44196 | D14: =IF(C14=0,"",DATE(YEAR(C14),MONTH(C14),1)+INT(DAY(DATE(YEAR(C14),MONTH(C14)+1,1)-1)/2)-0.5) -> 44180.5 | E14: =$E$10 -> 44263 | F14: =D14-E14 -> -82.5
A15: 6
A16: 7 | B16: =B14+31 -> 44197 | C16: =C14+31 -> 44227 | D16: =IF(C16=0,"",DATE(YEAR(C16),MONTH(C16),1)+INT(DAY(DATE(YEAR(C16),MONTH(C16)+1,1)-1)/2)-0.5) -> 44211.5 | E16: 44627 | F16: =D16-E16 -> -415.5
A17: 8
A18: 9 | B18: =B16+31 -> 44228 | C18: 44255 | D18: =IF(C18=0,"",DATE(YEAR(C18),MONTH(C18),1)+INT(DAY(DATE(YEAR(C18),MONTH(C18)+1,1)-1)/2)-0.5) -> 44241.5 | E18: =+E16 -> 44627 | F18: =D18-E18 -> -385.5
A19: 10
A20: 11 | B20: =B18+29 -> 44257 | C20: 44286 | D20: =IF(C20=0,"",DATE(YEAR(C20),MONTH(C20),1)+INT(DAY(DATE(YEAR(C20),MONTH(C20)+1,1)-1)/2)-0.5) -> 44270.5 | E20: =+E18 -> 44627 | F20: =D20-E20 -> -356.5
A21: 12
A22: 13 | B22: =B20+31 -> 44288 | C22: =C20+30 -> 44316 | D22: =IF(C22=0,"",DATE(YEAR(C22),MONTH(C22),1)+INT(DAY(DATE(YEAR(C22),MONTH(C22)+1,1)-1)/2)-0.5) -> 44301.5 | E22: =+E20 -> 44627 | F22: =D22-E22 -> -325.5
A23: 14
A24: 15 | B24: =B22+30 -> 44318 | C24: =C22+31 -> 44347 | D24: =IF(C24=0,"",DATE(YEAR(C24),MONTH(C24),1)+INT(DAY(DATE(YEAR(C24),MONTH(C24)+1,1)-1)/2)-0.5) -> 44331.5 | E24: =E22 -> 44627 | F24: =D24-E24 -> -295.5
A25: 16
A26: 17 | B26: =B24+31 -> 44349 | C26: =C24+30 -> 44377 | D26: =IF(C26=0,"",DATE(YEAR(C26),MONTH(C26),1)+INT(DAY(DATE(YEAR(C26),MONTH(C26)+1,1)-1)/2)-0.5) -> 44362.5 | E26: =E24 -> 44627 | F26: =D26-E26 -> -264.5
A27: 18
A28: 19 | B28: =B26+30 -> 44379 | C28: =C26+31 -> 44408 | D28: =IF(C28=0,"",DATE(YEAR(C28),MONTH(C28),1)+INT(DAY(DATE(YEAR(C28),MONTH(C28)+1,1)-1)/2)-0.5) -> 44392.5 | E28: =E26 -> 44627 | F28: =D28-E28 -> -234.5
A29: 20
A30: 21 | B30: =B28+31 -> 44410 | C30: =C28+31 -> 44439 | D30: =IF(C30=0,"",DATE(YEAR(C30),MONTH(C30),1)+INT(DAY(DATE(YEAR(C30),MONTH(C30)+1,1)-1)/2)-0.5) -> 44423.5 | E30: =E28 -> 44627 | F30: =D30-E30 -> -203.5
A31: 22
A32: 23 | B32: =B30+31 -> 44441 | C32: =C30+30 -> 44469 | D32: =IF(C32=0,"",DATE(YEAR(C32),MONTH(C32),1)+INT(DAY(DATE(YEAR(C32),MONTH(C32)+1,1)-1)/2)-0.5) -> 44454.5 | E32: =E30 -> 44627 | F32: =D32-E32 -> -172.5
A33: 24
A34: 25 | B34: Average | F34: =ROUND(AVERAGE(F10:F32),2) -> -249.33

Sheet 3-2
A1: 2022 RATE CASE
A2: =' '!A2 -> ONCOR ELECTRIC DELIVERY COMPANY LLC
A3: METER READER INCENTIVE LEAD DAYS - PAYMENT CALCULATION
A4: FOR THE LEAD-LAG STUDY-PERIOD ENDING SEPTEMBER 30, 2021
A5: SPONSOR: A. THENMADATHIL
A7: Line No. | B7: Month | C7: Accrual Date | D7: Mid Month | E7: Payout Date | F7: (Lead)/Lag Days
B8: (a) | C8: (b) | D8: (c) | E8: (d) | F8: (e)
A10: 1 | B10: No Longer have Meter Readers thus no incentive effective 1/13.
A11: 2
A12: 3
A13: 4
A14: 5
A15: 6
A16: 7
A17: 8
A18: 9
A19: 10
A20: 11
A21: 12
A22: 13
... A34: 25

Sheet 4
A1: 2022 RATE CASE
A2: =' '!A2 -> ONCOR ELECTRIC DELIVERY COMPANY LLC
A3: NON-LABOR O&M - ONCOR ELECTRIC DELIVERY COMPANY LLC AND OTHER AFFILIATES
A4: FOR THE LEAD-LAG STUDY-PERIOD ENDING SEPTEMBER 30, 2021
A5: SPONSOR: A. THENMADATHIL
A7: Line | G7: Date | H7: Date | I7: Later of Paid | J7: Days Paid | K7: (Lead)/Lag
A8: No. | B8: Month | C8: From | D8: To | E8: Total Days | F8: Mid-Point | G8: Paid | H8: Due | I8: or Due Date | J8: After EOM | K8: Days
B9: (a) | C9: (b) | D9: (c) | E9: (d) | F9: (e) | G9: (f) | H9: (g) | I9: (h) | J9: (i) | K9: (j)
A11: 1 | B11: 44105 | C11: 44105 | D11: 44135 | E11: =D11-C11+1 -> 31 | F11: =E11/2 -> 15.5 | G11: 44165 | H11: 44165 | I11: =MAX(G11:H11) -> 44165 | J11: =+I11-D11 -> 30 | K11: =-J11-F11 -> -45.5 | N11: =H11 -> 44165
A12: =A11+1 -> 2 | B12: 44136 | C12: 44136 | D12: 44165 | E12: =D12-C12+1 -> 30 | F12: =E12/2 -> 15 | G12: 44196 | H12: 44196 | I12: =MAX(G12:H12) -> 44196 | J12: =+I12-D12 -> 31 | K12: =-J12-F12 -> -46 | N12: =H12 -> 44196
A13: =A12+1 -> 3 | B13: 44166 | C13: 44166 | D13: 44196 | E13: =D13-C13+1 -> 31 | F13: =E13/2 -> 15.5 | G13: 44227 | H13: 44227 | I13: =MAX(G13:H13) -> 44227 | J13: =+I13-D13 -> 31 | K13: =-J13-F13 -> -46.5 | N13: =H13 -> 44227
A14: =A13+1 -> 4 | B14: 44197 | C14: 44197 | D14: 44227 | E14: =D14-C14+1 -> 31 | F14: =E14/2 -> 15.5 | G14: 44253 | H14: 44253 | I14: =MAX(G14:H14) -> 44253 | J14: =+I14-D14 -> 26 | K14: =-J14-F14 -> -41.5 | N14: =H14 -> 44253
A15: =A14+1 -> 5 | B15: 44228 | C15: 44228 | D15: 44255 | E15: =D15-C15+1 -> 28 | F15: =E15/2 -> 14 | G15: 44286 | H15: 44286 | I15: =MAX(G15:H15) -> 44286 | J15: =+I15-D15 -> 31 | K15: =-J15-F15 -> -45 | N15: =H15 -> 44286
A16: =A15+1 -> 6 | B16: 44256 | C16: 44256 | D16: 44286 | E16: =D16-C16+1 -> 31 | F16: =E16/2 -> 15.5 | G16: 44316 | H16: 44316 | I16: =MAX(G16:H16) -> 44316 | J16: =+I16-D16 -> 30 | K16: =-J16-F16 -> -45.5 | N16: =H16 -> 44316
A17: =A16+1 -> 7 | B17: 44287 | C17: 44287 | D17: 44316 | E17: =D17-C17+1 -> 30 | F17: =E17/2 -> 15 | G17: 44344 | H17: 44344 | I17: =MAX(G17:H17) -> 44344 | J17: =+I17-D17 -> 28 | K17: =-J17-F17 -> -43 | N17: =H17 -> 44344
A18: =A17+1 -> 8 | B18: 44317 | C18: 44317 | D18: 44347 | E18: =D18-C18+1 -> 31 | F18: =E18/2 -> 15.5 | G18: 44377 | H18: 44377 | I18: =MAX(G18:H18) -> 44377 | J18: =+I18-D18 -> 30 | K18: =-J18-F18 -> -45.5 | N18: =H18 -> 44377
A19: =A18+1 -> 9 | B19: 44348 | C19: 44348 | D19: 44377 | E19: =D19-C19+1 -> 30 | F19: =E19/2 -> 15 | G19: 44407 | H19: 44407 | I19: =MAX(G19:H19) -> 44407 | J19: =+I19-D19 -> 30 | K19: =-J19-F19 -> -45 | N19: =H19 -> 44407
A20: =A19+1 -> 10 | B20: 44378 | C20: 44378 | D20: 44408 | E20: =D20-C20+1 -> 31 | F20: =E20/2 -> 15.5 | G20: 44439 | H20: 44439 | I20: =MAX(G20:H20) -> 44439 | J20: =+I20-D20 -> 31 | K20: =-J20-F20 -> -46.5 | N20: =H20 -> 44439
A21: =A20+1 -> 11 | B21: 44409 | C21: 44409 | D21: 44439 | E21: =D21-C21+1 -> 31 | F21: =E21/2 -> 15.5 | G21: 44469 | H21: 44469 | I21: =MAX(G21:H21) -> 44469 | J21: =+I21-D21 -> 30 | K21: =-J21-F21 -> -45.5 | N21: =H21 -> 44469
A22: =A21+1 -> 12 | B22: 44440 | C22: 44440 | D22: 44469 | E22: =D22-C22+1 -> 30 | F22: =E22/2 -> 15 | G22: 44498 | H22: 44498 | I22: =MAX(G22:H22) -> 44498 | J22: =+I22-D22 -> 29 | K22: =-J22-F22 -> -44 | N22: =H22 -> 44498
A23: =A22+1 -> 13
A24: =A23+1 -> 14 | G24: Average | K24: =ROUND(AVERAGE(K11:K22),2) -> -44.96
A25: =A24+1 -> 15
A26: =A25+1 -> 16
A27: =A26+1 -> 17 | B27: Source: | C27: Affiliate Payment Dates 12ME 9.30.21.pdf

Sheet 5
A1: 2022 RATE CASE
A2: =' '!A2 -> ONCOR ELECTRIC DELIVERY COMPANY LLC
A3: TCOS - NON-ONCOR
A4: FOR THE LEAD-LAG STUDY-PERIOD ENDING SEPTEMBER 30, 2021
A5: SPONSOR: A. THENMADATHIL
A7: Line No. | C7: Description | E7: (Lead)/Lag Days
C8: (a) | E8: (b)
A10: 1 | C10: Average service period
A11: =A10+1 -> 2 | C11: (365.25 days/12 months)/2 | E11: =ROUND(365.25/12/2,3)*-1 -> -15.219
A12: =A11+1 -> 3
A13: =A12+1 -> 4 | C13: Days from end of Service Period to Payment | E13: -35
A14: =A13+1 -> 5
A15: =A14+1 -> 6
A16: =A15+1 -> 7 | C16: Total Lead Days | E16: =ROUND(SUM(E11:E14),2) -> -50.22

Sheet 6
A1: 2022 RATE CASE
A2: =' '!A2 -> ONCOR ELECTRIC DELIVERY COMPANY LLC
A3: NON-LABOR O&M - OTHER THIRD PARTY O&M
A4: FOR THE LEAD-LAG STUDY-PERIOD ENDING SEPTEMBER 30, 2021
A5: SPONSOR: A. THENMADATHIL
A9: Line | D9: Total (Lead)/Lag | F9: Weighted
A10: No. | B10: Business Unit | C10: Amount | D10: Days | E10: Reference | F10: Dollar Days
B11: (a) | C11: (b) | D11: (c) | E11: (d) | F11: (e)
A13: 1 | B13: Transmission | C13: =+'6-1'!C17 -> 86691097 | D13: =+'6-1'!D17 -> -29.73029 | E13: WP/II-B-9/6-1 | F13: =+D13*C13 -> -2.5773515e+09
A14: =A13+1 -> 2 | B14: Distribution | C14: ='6-2'!C17 -> 4.7040816e+08 | D14: =+'6-2'!D17 -> -50.540894 | E14: WP/II-B-9/6-2 | F14: =C14*D14 -> -2.3774849e+10
A15: =A14+1 -> 3 | B15: Corporate * | C15: 1423446.1 | D15: ='6-3'!G23 -> 97.77 | E15: WP/II-B-9/6-3 | F15: =C15*D15 -> 1.3917032e+08
A16: =A15+1 -> 4
A17: =A16+1 -> 5 | B17: Total | C17: =SUM(C13:C15) -> 5.585227e+08 | D17: =ROUND(F17/C17,2) -> -46.93 | F17: =SUM(F13:F15) -> -2.621303e+10
A18: =A17+1 -> 6
A19: =A18+1 -> 7
A20: =A19+1 -> 8 | B20: * Source: | C20: Lead Lag Samples

Sheet 6-1
A1: 2022 RATE CASE
A2: =' '!A2 -> ONCOR ELECTRIC DELIVERY COMPANY LLC
A3: NON-LABOR O&M - THIRD PARTY O&M - TRANSMISSION
A4: FOR THE LEAD-LAG STUDY-PERIOD ENDING SEPTEMBER 30, 2021
A5: SPONSOR: A. THENMADATHIL
A9: Line | C9: Population | D9: (Lead)/Lag | F9: Weighted
A10: No. | B10: Strata | C10: Dollars | D10: Days | E10: Reference | F10: Dollar Days
B11: (a) | C11: (b) | D11: (c) | E11: (d) | F11: (e)
A13: 1 | B13: Item Amount < $10,000 | C13: 22309902 | D13: ='6-1-1'!G43 -> -29.36 | E13: WP/II-B-9/6-1-1 | F13: =C13*D13 -> -6.5501874e+08
A14: =A13+1 -> 2 | B14: Item Amount_>= $10,000 and <= $25,000 | C14: 14751915 | D14: ='6-1-2'!G33 -> -28.34 | E14: WP/II-B-9/6-1-2 | F14: =C14*D14 -> -4.1806928e+08
A15: =A14+1 -> 3 | B15: Item Amount > $25,000 | C15: 49629279 | D15: ='6-1-3'!G79 -> -30.31 | E15: WP/II-B-9/6-1-3 | F15: =C15*D15 -> -1.5042634e+09
A16: =A15+1 -> 4
A17: =A16+1 -> 5 | B17: Total | C17: =SUM(C13:C15) -> 86691097 | D17: =+F17/C17 -> -29.73029 | F17: =SUM(F13:F15) -> -2.5773515e+09
A18: =A17+1 -> 6
A19: =A18+1 -> 7
A20: =A19+1 -> 8
A21: =A20+1 -> 9 | B21: Source: | C21: Lead Lag Samples.xlsx

Sheet 6-1-1
A1: 2022 RATE CASE
A2: ='1-1-3-1-1'!A2 -> ONCOR ELECTRIC DELIVERY COMPANY LLC
A3: NON-LABOR O&M - THIRD PARTY O&M SAMPLE - TRANSMISSION (STRATA 1: <$10,000)
A4: FOR THE LEAD-LAG STUDY-PERIOD ENDING SEPTEMBER 30, 2021
A5: SPONSOR: A. THENMADATHIL
F7: Later of Due Date
A8: Line | D8: Begin | E8: Type of | F8: or Check Clear | G8: (Lead)/Lag | H8: Weighted Dollar
A9: No. | B9: Voucher | C9: Amount | D9: Date | E9: Begin Date | F9: Date | G9: Days | H9: Days
B10: (a) | C10: (b) | D10: (c) | E10: (d) | F10: (e) | G10: (f) | H10: (g)
A12: 1 | B12: 00457936 | C12: 96.77 | D12: 44113.5 | E12: Midpoint of Benefit Period | F12: 44121 | G12: =D12-F12 -> -7.5 | H12: =IF(ISERR(G12*C12),"",G12*C12) -> -725.775
A13: =A12+1 -> 2 | B13: 00501568 | C13: 818.05 | D13: 44264 | E13: Invoice Date | F13: 44345 | G13: =D13-F13 -> -81 | H13: =IF(ISERR(G13*C13),"",G13*C13) -> -66262.05
A14: =A13+1 -> 3 | B14: M925724 | C14: 3181 | D14: 44308.5 | E14: Midpoint of Benefit Period | F14: 44355 | G14: =D14-F14 -> -46.5 | H14: =IF(ISERR(G14*C14),"",G14*C14) -> -147916.5
A15: =A14+1 -> 4 | B15: 00483673 | C15: 637.77 | D15: 44246 | E15: Invoice Date | F15: 44279 | G15: =D15-F15 -> -33 | H15: =IF(ISERR(G15*C15),"",G15*C15) -> -21046.41
A16: =A15+1 -> 5 | B16: M913793 | C16: 594.5 | D16: 44278 | E16: Midpoint of Benefit Period | F16: 44312 | G16: =D16-F16 -> -34 | H16: =IF(ISERR(G16*C16),"",G16*C16) -> -20213
A17: =A16+1 -> 6 | B17: 00508717 | C17: 295.41 | D17: 44346.5 | E17: Midpoint of Benefit Period | F17: 44384 | G17: =D17-F17 -> -37.5 | H17: =IF(ISERR(G17*C17),"",G17*C17) -> -11077.875
A18: =A17+1 -> 7 | B18: M929919 | C18: 37.45 | D18: 44317 | E18: Midpoint of Benefit Period | F18: 44357 | G18: =D18-F18 -> -40 | H18: =IF(ISERR(G18*C18),"",G18*C18) -> -1498
A19: =A18+1 -> 8 | B19: 00498823 | C19: 220.47 | D19: 44332 | E19: Midpoint of Benefit Period | F19: 44337 | G19: =D19-F19 -> -5 | H19: =IF(ISERR(G19*C19),"",G19*C19) -> -1102.35
A20: =A19+1 -> 9 | B20: M889957 | C20: 10.28 | D20: 44262 | E20: Invoice Date | F20: 44291 | G20: =D20-F20 -> -29 | H20: =IF(ISERR(G20*C20),"",G20*C20) -> -298.12
A21: =A20+1 -> 10 | B21: 00470283 | C21: 3950 | D21: 44120 | E21: Midpoint of Benefit Period | F21: 44186 | G21: =D21-F21 -> -66 | H21: =IF(ISERR(G21*C21),"",G21*C21) -> -260700
A22: =A21+1 -> 11 | B22: 00518590 | C22: 1170.18 | D22: 44433 | E22: Invoice Date | F22: 44468 | G22: =D22-F22 -> -35 | H22: =IF(ISERR(G22*C22),"",G22*C22) -> -40956.3
A23: =A22+1 -> 12 | B23: 00465104 | C23: 65.18 | D23: 44114.5 | E23: Midpoint of Benefit Period | F23: 44153 | G23: =D23-F23 -> -38.5 | H23: =IF(ISERR(G23*C23),"",G23*C23) -> -2509.43
A24: =A23+1 -> 13 | B24: 00518893 | C24: 5458.29 | D24: 44448 | E24: Midpoint of Benefit Period | F24: 44463 | G24: =D24-F24 -> -15 | H24: =IF(ISERR(G24*C24),"",G24*C24) -> -81874.35
... A41: =A40+1 -> 30 | B41: M981952 | C41: 9.75 | D41: 44417 | E41: Midpoint of Benefit Period | F41: 44454 | G41: =D41-F41 -> -37 | H41: =IF(ISERR(G41*C41),"",G41*C41) -> -360.75
A42: =A41+1 -> 31
A43: =A42+1 -> 32 | B43: Subtotal | C43: =SUM(C12:C42) -> 35433.64 | G43: =+ROUND(H43/C43,2) -> -29.36 | H43: =SUM(H12:H42) -> -1040329.8
A44: =A43+1 -> 33
A45: =A44+1 -> 34 | B45: Source: | C45: 3rd party O&M - TRN sample 2021.xlsx

Sheet 6-1-2
A1: 2022 RATE CASE
A2: ='1-1-3-1-1'!A2 -> ONCOR ELECTRIC DELIVERY COMPANY LLC
A3: NON-LABOR O&M - THIRD PARTY O&M SAMPLE - TRANSMISSION (STRATA 2: >=$10,000 AND <=$25,000)
A4: FOR THE LEAD-LAG STUDY-PERIOD ENDING SEPTEMBER 30, 2021
A5: SPONSOR: A. THENMADATHIL
F7: Later of Due Date
A8: Line | D8: Begin | E8: Type of | F8: or Check Clear | G8: (Lead)/Lag | H8: Weighted Dollar
A9: No. | B9: Voucher | C9: Amount | D9: Date | E9: Begin Date | F9: Date | G9: Days | H9: Days
B10: (a) | C10: (b) | D10: (c) | E10: (d) | F10: (e) | G10: (f) | H10: (g)
A12: 1 | B12: 00463570 | C12: 19797.09 | D12: 44120 | E12: Midpoint of Benefit Period | F12: 44149 | G12: =D12-F12 -> -29 | H12: =IF(ISERR(G12*C12),"",G12*C12) -> -574115.61
A13: =A12+1 -> 2 | B13: M972114 | C13: 24566.04 | D13: 44362.5 | E13: Midpoint of Benefit Period | F13: 44422 | G13: =D13-F13 -> -59.5 | H13: =IF(ISERR(G13*C13),"",G13*C13) -> -1461679.4
A14: =A13+1 -> 3 | B14: 00498936 | C14: 17310.08 | D14: 44332 | E14: Midpoint of Benefit Period | F14: 44347 | G14: =D14-F14 -> -15 | H14: =IF(ISERR(G14*C14),"",G14*C14) -> -259651.2
A15: =A14+1 -> 4 | B15: M981252 | C15: 20209.4 | D15: 44379 | E15: Midpoint of Benefit Period | F15: 44440 | G15: =D15-F15 -> -61 | H15: =IF(ISERR(G15*C15),"",G15*C15) -> -1232773.4
A16: =A15+1 -> 5 | B16: 00510690 | C16: 19006.84 | D16: 44386.5 | E16: Midpoint of Benefit Period | F16: 44419 | G16: =D16-F16 -> -32.5 | H16: =IF(ISERR(G16*C16),"",G16*C16) -> -617722.3
A17: =A16+1 -> 6 | B17: M996349 | C17: 10326.55 | D17: 44425.5 | E17: Midpoint of Benefit Period | F17: 44466 | G17: =D17-F17 -> -40.5 | H17: =IF(ISERR(G17*C17),"",G17*C17) -> -418225.27
A18: =A17+1 -> 7 | B18: M827175 | C18: 23479.42 | D18: 44110.5 | E18: Midpoint of Benefit Period | F18: 44150 | G18: =D18-F18 -> -39.5 | H18: =IF(ISERR(G18*C18),"",G18*C18) -> -927437.09
A19: =A18+1 -> 8 | B19: 00517268 | C19: 23610.8 | D19: 44420.5 | E19: Midpoint of Benefit Period | F19: 44463 | G19: =D19-F19 -> -42.5 | H19: =IF(ISERR(G19*C19),"",G19*C19) -> -1003459
A20: =A19+1 -> 9 | B20: M914531 | C20: 16691.2 | D20: 44273 | E20: Midpoint of Benefit Period | F20: 44309 | G20: =D20-F20 -> -36 | H20: =IF(ISERR(G20*C20),"",G20*C20) -> -600883.2
A21: =A20+1 -> 10 | B21: M930386 | C21: 18524.15 | D21: 44306.5 | E21: Midpoint of Benefit Period | F21: 44346 | G21: =D21-F21 -> -39.5 | H21: =IF(ISERR(G21*C21),"",G21*C21) -> -731703.93
A22: =A21+1 -> 11 | B22: M917146 | C22: 23127.61 | D22: 44300.5 | E22: Midpoint of Benefit Period | F22: 44337 | G22: =D22-F22 -> -36.5 | H22: =IF(ISERR(G22*C22),"",G22*C22) -> -844157.77
A23: =A22+1 -> 12 | B23: M827174 | C23: 23050.1 | D23: 44103.5 | E23: Midpoint of Benefit Period | F23: 44143 | G23: =D23-F23 -> -39.5 | H23: =IF(ISERR(G23*C23),"",G23*C23) -> -910478.95
A24: =A23+1 -> 13 | B24: M957862 | C24: 10800 | D24: 44362.5 | E24: Midpoint of Benefit Period | F24: 44407 | G24: =D24-F24 -> -44.5 | H24: =IF(ISERR(G24*C24),"",G24*C24) -> -480600
... A31: =A30+1 -> 20 | B31: M857640 | C31: 14563.41 | D31: 44182 | E31: Midpoint of Benefit Period | F31: 44216 | G31: =D31-F31 -> -34 | H31: =IF(ISERR(G31*C31),"",G31*C31) -> -495155.94
A32: =A31+1 -> 21
A33: =A32+1 -> 22 | B33: Total | C33: =SUM(C12:C32) -> 359661.5 | G33: =+ROUND(H33/C33,2) -> -28.34 | H33: =SUM(H12:H32) -> -10193949
A34: =A33+1 -> 23
A35: =A34+1 -> 24 | B35: Source: | C35: 3rd party O&M - TRN sample 2021.xlsx

Sheet 6-1-3
A1: 2022 RATE CASE
A2: ='1-1-3-1-1'!A2 -> ONCOR ELECTRIC DELIVERY COMPANY LLC
A3: NON-LABOR O&M - THIRD PARTY O&M SAMPLE - TRANSMISSION (STRATA 3: >$25,000)
A4: FOR THE LEAD-LAG STUDY-PERIOD ENDING SEPTEMBER 30, 2021
A5: SPONSOR: A. THENMADATHIL
F7: Later of Due Date
A8: Line | D8: Begin | E8: Type of | F8: or Check Clear | G8: (Lead)/Lag | H8: Weighted Dollar
A9: No. | B9: Voucher | C9: Amount | D9: Date | E9: Begin Date | F9: Date | G9: Days | H9: Days
B10: (a) | C10: (b) | D10: (c) | E10: (d) | F10: (e) | G10: (f) | H10: (g)
A12: 1 | B12: M834028 | C12: 32538.22 | D12: 44089.5 | E12: Midpoint of Benefit Period | F12: 44155 | G12: =D12-F12 -> -65.5 | H12: =IF(ISERR(G12*C12),"",G12*C12) -> -2131253.4
A13: =+A12+1 -> 2 | B13: M809469 | C13: 77700 | D13: 44096 | E13: Invoice Date | F13: 44126 | G13: =D13-F13 -> -30 | H13: =IF(ISERR(G13*C13),"",G13*C13) -> -2331000
A14: =+A13+1 -> 3 | B14: M823693 | C14: 270108 | D14: 44103.5 | E14: Midpoint of Benefit Period | F14: 44142 | G14: =D14-F14 -> -38.5 | H14: =IF(ISERR(G14*C14),"",G14*C14) -> -10399158
A15: =+A14+1 -> 4 | B15: M838482 | C15: 70000 | D15: 44143.5 | E15: Midpoint of Benefit Period | F15: 44177 | G15: =D15-F15 -> -33.5 | H15: =IF(ISERR(G15*C15),"",G15*C15) -> -2345000
A16: =+A15+1 -> 5 | B16: 00466883 | C16: 80504.06 | D16: 44089.5 | E16: Midpoint of Benefit Period | F16: 44157 | G16: =D16-F16 -> -67.5 | H16: =IF(ISERR(G16*C16),"",G16*C16) -> -5434024
A17: =+A16+1 -> 6 | B17: M932779 | C17: 29600 | D17: 44334 | E17: Invoice Date | F17: 44364 | G17: =D17-F17 -> -30 | H17: =IF(ISERR(G17*C17),"",G17*C17) -> -888000
A18: =+A17+1 -> 7 | B18: 00508071 | C18: 95242.6 | D18: 44362.5 | E18: removed from sample | F18: 44392 | G18: =D18-F18 -> -29.5 | H18: =IF(ISERR(G18*C18),"",G18*C18) -> -2809656.7
A19: =+A18+1 -> 8 | B19: 00487902 | C19: 276269.12 | D19: 44258 | E19: Midpoint of Benefit Period | F19: 44264 | G19: =D19-F19 -> -6 | H19: =IF(ISERR(G19*C19),"",G19*C19) -> -1657614.7
A20: =+A19+1 -> 9 | B20: 00521915 | C20: 27318.45 | D20: 44485 | E20: Midpoint of Benefit Period | F20: 44484 | G20: =D20-F20 -> 1 | H20: =IF(ISERR(G20*C20),"",G20*C20) -> 27318.45
A21: =+A20+1 -> 10 | B21: 00512835 | C21: 31638.97 | D21: 44393 | E21: Midpoint of Benefit Period | F21: 44422 | G21: =D21-F21 -> -29 | H21: =IF(ISERR(G21*C21),"",G21*C21) -> -917530.13
A22: =+A21+1 -> 11 | B22: 00523186 | C22: 246280.95 | D22: 44416 | E22: Midpoint of Benefit Period | F22: 44473 | G22: =D22-F22 -> -57 | H22: =IF(ISERR(G22*C22),"",G22*C22) -> -14038014
A23: =+A22+1 -> 12 | B23: 00472865 | C23: 33871.43 | D23: 44176 | E23: Invoice Date | F23: 44206 | G23: =D23-F23 -> -30 | H23: =IF(ISERR(G23*C23),"",G23*C23) -> -1016142.9
A24: =+A23+1 -> 13 | B24: M884832 | C24: 28807.9 | D24: 44229 | E24: Midpoint of Benefit Period | F24: 44279 | G24: =D24-F24 -> -50 | H24: =IF(ISERR(G24*C24),"",G24*C24) -> -1440395
... A77: =+A76+1 -> 66 | B77: 00462030 | C77: 213494.06 | D77: 44117 | E77: Midpoint of Benefit Period | F77: 44124 | G77: =D77-F77 -> -7 | H77: =IF(ISERR(G77*C77),"",G77*C77) -> -1494458.4
A78: =+A77+1 -> 67
A79: =+A78+1 -> 68 | B79: Subtotal | C79: =SUM(C12:C78) -> 4232643 | G79: =+ROUND(H79/C79,2) -> -30.31 | H79: =SUM(H12:H78) -> -1.2828116e+08
A80: =+A79+1 -> 69
A81: =+A80+1 -> 70 | B81: Source: | C81: 3rd party O&M - TRN sample 2021.xlsx

Sheet 6-2
A1: 2022 RATE CASE
A2: =' '!A2 -> ONCOR ELECTRIC DELIVERY COMPANY LLC
A3: NON-LABOR O&M - THIRD PARTY O&M - DISTRIBUTION
A4: FOR THE LEAD-LAG STUDY-PERIOD ENDING SEPTEMBER 30, 2021
A5: SPONSOR: A. THENMADATHIL
A9: Line | C9: Population | D9: (Lead)/Lag | F9: Weighted
A10: No. | B10: Strata | C10: Dollars | D10: Days | E10: Reference | F10: Dollar Days
B11: (a) | C11: (b) | D11: (c) | E11: (d) | F11: (e)
A13: 1 | B13: Item Amount < $10,000 | C13: 1.0091309e+08 | D13: =+'6-2-1'!G38 -> -92.57 | E13: WP/II-B-9/6-2-1 | F13: =C13*D13 -> -9.3415243e+09
A14: =A13+1 -> 2 | B14: Item Amount_>= $10,000 and <= $25,000 | C14: 56499540 | D14: ='6-2-2'!G27 -> -59.96 | E14: WP/II-B-9/6-2-2 | F14: =C14*D14 -> -3.3877124e+09
A15: =A14+1 -> 3 | B15: Item Amount > $25,000 | C15: 3.1299553e+08 | D15: ='6-2-3'!G90 -> -35.29 | E15: WP/II-B-9/6-2-3 | F15: =C15*D15 -> -1.1045612e+10
A16: =A15+1 -> 4
A17: =A16+1 -> 5 | B17: Total | C17: =SUM(C13:C15) -> 4.7040816e+08 | D17: =+F17/C17 -> -50.540894 | F17: =SUM(F13:F15) -> -2.3774849e+10
A18: =A17+1 -> 6
A19: =A18+1 -> 7
A20: =A19+1 -> 8
A21: =A20+1 -> 9 | B21: Source: | C21: Lead Lag Sample.xlsx

Sheet 6-2-1
A1: 2022 RATE CASE
A2: ='1-1-3-1-1'!A2 -> ONCOR ELECTRIC DELIVERY COMPANY LLC
A3: NON-LABOR O&M - THIRD PARTY O&M SAMPLE - DISTRIBUTION (STRATA 1: <$10,000)
A4: FOR THE LEAD-LAG STUDY-PERIOD ENDING SEPTEMBER 30, 2021
A5: SPONSOR: A. THENMADATHIL
F7: Later of Due Date
A8: Line | D8: Begin | E8: Type of | F8: or Check Clear | G8: (Lead)/Lag | H8: Weighted Dollar
A9: No. | B9: Voucher | C9: Amount | D9: Date | E9: Begin Date | F9: Date | G9: Days | H9: Days
B10: (a) | C10: (b) | D10: (c) | E10: (d) | F10: (e) | G10: (f) | H10: (g)
A12: 1 | B12: 00458139 | C12: 352.32 | D12: 44061 | E12: Midpoint of Benefit Period | F12: 44114 | G12: =D12-F12 -> -53 | H12: =IF(ISERR(G12*C12),"",G12*C12) -> -18672.96
A13: 2 | B13: M906156 | C13: 1522.85 | D13: 44270 | E13: Midpoint of Benefit Period | F13: 44300 | G13: =D13-F13 -> -30 | H13: =IF(ISERR(G13*C13),"",G13*C13) -> -45685.5
A14: 3 | B14: M817440 | C14: 1062.5 | D14: 44060 | E14: Midpoint of Benefit Period | F14: 44118 | G14: =D14-F14 -> -58 | H14: =IF(ISERR(G14*C14),"",G14*C14) -> -61625
A15: 4 | B15: M996548 | C15: 256.35 | D15: 44462 | E15: Midpoint of Benefit Period | F15: 44492 | G15: =D15-F15 -> -30 | H15: =IF(ISERR(G15*C15),"",G15*C15) -> -7690.5
A16: 5 | B16: M912978 | C16: 43.4 | D16: 44305 | E16: Midpoint of Benefit Period | F16: 44333 | G16: =D16-F16 -> -28 | H16: =IF(ISERR(G16*C16),"",G16*C16) -> -1215.2
A17: 6 | B17: M814000 | C17: 114.8 | D17: 44049 | E17: Midpoint of Benefit Period | F17: 44122 | G17: =D17-F17 -> -73 | H17: =IF(ISERR(G17*C17),"",G17*C17) -> -8380.4
A18: 7 | B18: M984492 | C18: 14.32 | D18: 44439 | E18: Midpoint of Benefit Period | F18: 44466 | G18: =D18-F18 -> -27 | H18: =IF(ISERR(G18*C18),"",G18*C18) -> -386.64
A19: 8 | B19: M908893 | C19: 72.35 | D19: 44259 | E19: Midpoint of Benefit Period | F19: 44321 | G19: =D19-F19 -> -62 | H19: =IF(ISERR(G19*C19),"",G19*C19) -> -4485.7
A20: 9 | B20: M826880 | C20: 1373.7 | D20: 44094 | E20: Midpoint of Benefit Period | F20: 44139 | G20: =D20-F20 -> -45 | H20: =IF(ISERR(G20*C20),"",G20*C20) -> -61816.5
A21: 10 | B21: 00463169 | C21: 259.8 | D21: 44126 | E21: Midpoint of Benefit Period | F21: 44138 | G21: =D21-F21 -> -12 | H21: =IF(ISERR(G21*C21),"",G21*C21) -> -3117.6
A22: 11 | B22: M904500 | C22: 1151.58 | D22: 44262.5 | E22: Midpoint of Benefit Period | F22: 44303 | G22: =D22-F22 -> -40.5 | H22: =IF(ISERR(G22*C22),"",G22*C22) -> -46638.99
A23: 12 | B23: M833731 | C23: 5748.57 | D23: 43844.5 | E23: Midpoint of Benefit Period | F23: 44161 | G23: =D23-F23 -> -316.5 | H23: =IF(ISERR(G23*C23),"",G23*C23) -> -1819422.4
... A36: 25 | B36: M998580 | C36: 5345.08 | D36: 44429.5 | E36: Midpoint of Benefit Period | F36: 44469 | G36: =D36-F36 -> -39.5 | H36: =IF(ISERR(G36*C36),"",G36*C36) -> -211130.66
A37: 26
A38: 27 | B38: Total | C38: =SUM(C12:C37) -> 32932.83 | G38: =+ROUND(H38/C38,2) -> -92.57 | H38: =SUM(H12:H37) -> -3048751.1
A39: 28
A40: 29
A41: 30
A42: 31
A43: 32 | B43: Source: | C43: 3rd party O&M - ESD sample.xlsx

Sheet 6-2-2
A1: 2022 RATE CASE
A2: ='1-1-3-1-1'!A2 -> ONCOR ELECTRIC DELIVERY COMPANY LLC
A3: NON-LABOR O&M - THIRD PARTY O&M SAMPLE - DISTRIBUTION (STRATA 2: >=$10,000 AND <=$25,000)
A4: FOR THE LEAD-LAG STUDY-PERIOD ENDING SEPTEMBER 30, 2021
A5: SPONSOR: A. THENMADATHIL
F7: Later of Due Date
A8: Line | D8: Begin | E8: Type of | F8: or Check Clear | G8: (Lead)/Lag | H8: Weighted Dollar
A9: No. | B9: Voucher | C9: Amount | D9: Date | E9: Begin Date | F9: Date | G9: Days | H9: Days
B10: (a) | C10: (b) | D10: (c) | E10: (d) | F10: (e) | G10: (f) | H10: (g)
A12: 1 | B12: 00458735 | C12: 11903.87 | D12: 44150.5 | E12: Midpoint of Benefit Period | F12: 44118 | G12: =D12-F12 -> 32.5 | H12: =IF(ISERR(G12*C12),"",G12*C12) -> 386875.78
A13: =+A12+1 -> 2 | B13: M950613 | C13: 11325.66 | D13: 44365 | E13: Invoice Date | F13: 44414 | G13: =D13-F13 -> -49 | H13: =IF(ISERR(G13*C13),"",G13*C13) -> -554957.34
A14: =+A13+1 -> 3 | B14: M868864 | C14: 15375 | D14: 44060 | E14: Invoice Date | F14: 44238 | G14: =D14-F14 -> -178 | H14: =IF(ISERR(G14*C14),"",G14*C14) -> -2736750
A15: =+A14+1 -> 4 | B15: M938741 | C15: 16228.97 | D15: 44315 | E15: Midpoint of Benefit Period | F15: 44359 | G15: =D15-F15 -> -44 | H15: =IF(ISERR(G15*C15),"",G15*C15) -> -714074.68
A16: =+A15+1 -> 5 | B16: M962378 | C16: 15609.94 | D16: 44362.5 | E16: Midpoint of Benefit Period | F16: 44412 | G16: =D16-F16 -> -49.5 | H16: =IF(ISERR(G16*C16),"",G16*C16) -> -772692.03
A17: =+A16+1 -> 6 | B17: M994205 | C17: 17477.85 | D17: 44389 | E17: Midpoint of Benefit Period | F17: 44461 | G17: =D17-F17 -> -72 | H17: =IF(ISERR(G17*C17),"",G17*C17) -> -1258405.2
A18: =+A17+1 -> 7 | B18: M992166 | C18: 16325.46 | D18: 44424 | E18: Midpoint of Benefit Period | F18: 44476 | G18: =D18-F18 -> -52 | H18: =IF(ISERR(G18*C18),"",G18*C18) -> -848923.92
A19: =+A18+1 -> 8 | B19: M916587 | C19: 13544.5 | D19: 44242 | E19: Midpoint of Benefit Period | F19: 44323 | G19: =D19-F19 -> -81 | H19: =IF(ISERR(G19*C19),"",G19*C19) -> -1097104.5
A20: =+A19+1 -> 9 | B20: M864446 | C20: 18119.68 | D20: 44180.5 | E20: Midpoint of Benefit Period | F20: 44223 | G20: =D20-F20 -> -42.5 | H20: =IF(ISERR(G20*C20),"",G20*C20) -> -770086.4
A21: =+A20+1 -> 10 | B21: M856684 | C21: 18778.76 | D21: 44145.5 | E21: Midpoint of Benefit Period | F21: 44207 | G21: =D21-F21 -> -61.5 | H21: =IF(ISERR(G21*C21),"",G21*C21) -> -1154893.7
A22: =+A21+1 -> 11 | B22: 00511749 | C22: 20000 | D22: 44393 | E22: Midpoint of Benefit Period | F22: 44412 | G22: =D22-F22 -> -19 | H22: =IF(ISERR(G22*C22),"",G22*C22) -> -380000
A23: =+A22+1 -> 12 | B23: 00507553 | C23: 17600 | D23: 44332.5 | E23: Midpoint of Benefit Period | F23: 44377 | G23: =D23-F23 -> -44.5 | H23: =IF(ISERR(G23*C23),"",G23*C23) -> -783200
A24: =+A23+1 -> 13 | B24: M846369 | C24: 22946.7 | D24: 44145.5 | E24: Midpoint of Benefit Period | F24: 44183 | G24: =D24-F24 -> -37.5 | H24: =IF(ISERR(G24*C24),"",G24*C24) -> -860501.25
A25: =+A24+1 -> 14 | B25: M980020 | C25: 18000 | D25: 44320.5 | E25: Midpoint of Benefit Period | F25: 44456 | G25: =D25-F25 -> -135.5 | H25: =IF(ISERR(G25*C25),"",G25*C25) -> -2439000
A26: =+A25+1 -> 15
A27: =+A26+1 -> 16 | B27: Total | C27: =SUM(C12:C26) -> 233236.39 | G27: =+ROUND(H27/C27,2) -> -59.96 | H27: =SUM(H12:H25) -> -13983713
A28: =+A27+1 -> 17
A29: =+A28+1 -> 18
A30: =+A29+1 -> 19
A31: =+A30+1 -> 20
A32: =+A31+1 -> 21 | B32: Source: | C32: 3rd party O&M - ESD sample.XLSX

Sheet 6-2-3
A1: 2022 RATE CASE
A2: ='1-1-3-1-1'!A2 -> ONCOR ELECTRIC DELIVERY COMPANY LLC
A3: NON-LABOR O&M - THIRD PARTY O&M SAMPLE - DISTRIBUTION (STRATA 3: >$25,000)
A4: FOR THE LEAD-LAG STUDY-PERIOD ENDING SEPTEMBER 30, 2021
A5: SPONSOR: A. THENMADATHIL
F7: Later of Due Date
A8: Line | D8: Begin | E8: Type of | F8: or Check Clear | G8: (Lead)/Lag | H8: Weighted Dollar
A9: No. | B9: Voucher | C9: Amount | D9: Date | E9: Begin Date | F9: Date | G9: Days | H9: Days
B10: (a) | C10: (b) | D10: (c) | E10: (d) | F10: (e) | G10: (f) | H10: (g)
A12: 1 | B12: 00463731 | C12: 237843.55 | D12: 44123.5 | E12: Midpoint of Benefit Period | F12: 44158 | G12: =D12-F12 -> -34.5 | H12: =IF(ISERR(G12*C12),"",G12*C12) -> -8205602.5
A13: 2 | B13: M965394 | C13: 27048 | D13: 44244.5 | E13: Midpoint of Benefit Period | F13: 44429 | G13: =D13-F13 -> -184.5 | H13: =IF(ISERR(G13*C13),"",G13*C13) -> -4990356
A14: 3 | B14: M919451 | C14: 73200 | D14: 44299.5 | E14: Midpoint of Benefit Period | F14: 44339 | G14: -8 | H14: =IF(ISERR(G14*C14),"",G14*C14) -> -585600
A15: 4 | B15: M891200 | C15: 26446.84 | D15: 44245.5 | E15: Midpoint of Benefit Period | F15: 44286 | G15: =D15-F15 -> -40.5 | H15: =IF(ISERR(G15*C15),"",G15*C15) -> -1071097
A16: 5 | B16: M841062 | C16: 31848.72 | D16: 44131.5 | E16: Midpoint of Benefit Period | F16: 44171 | G16: =D16-F16 -> -39.5 | H16: =IF(ISERR(G16*C16),"",G16*C16) -> -1258024.4
A17: 6 | B17: 00490184 | C17: 26583.68 | D17: 44276 | E17: Midpoint of Benefit Period | F17: 44287 | G17: =D17-F17 -> -11 | H17: =IF(ISERR(G17*C17),"",G17*C17) -> -292420.48
A18: 7 | B18: M958442 | C18: 62315.35 | D18: 44560 | E18: Midpoint of Benefit Period | F18: 44396 | G18: =D18-F18 -> 164 | H18: =IF(ISERR(G18*C18),"",G18*C18) -> 10219717
A19: 8 | B19: M902499 | C19: 620216.53 | D19: 44246 | E19: Midpoint of Benefit Period | F19: 44301 | G19: =D19-F19 -> -55 | H19: =IF(ISERR(G19*C19),"",G19*C19) -> -34111909
A20: 9 | B20: M861986 | C20: 197582 | D20: 44180.5 | E20: Midpoint of Benefit Period | F20: 44218 | G20: =D20-F20 -> -37.5 | H20: =IF(ISERR(G20*C20),"",G20*C20) -> -7409325
A21: 10 | B21: 00476428 | C21: 260841.5 | D21: 44192.5 | E21: Midpoint of Benefit Period | F21: 44230 | G21: =D21-F21 -> -37.5 | H21: =IF(ISERR(G21*C21),"",G21*C21) -> -9781556.2
A22: 11 | B22: M987694 | C22: 82440.65 | D22: 44418.5 | E22: Midpoint of Benefit Period | F22: 44458 | G22: =D22-F22 -> -39.5 | H22: =IF(ISERR(G22*C22),"",G22*C22) -> -3256405.7
A23: 12 | B23: M962908 | C23: 35100 | D23: 44369.5 | E23: Midpoint of Benefit Period | F23: 44421 | G23: =D23-F23 -> -51.5 | H23: =IF(ISERR(G23*C23),"",G23*C23) -> -1807650
A24: 13 | B24: M932263 | C24: 66550 | D24: 44320.5 | E24: Midpoint of Benefit Period | F24: 44357 | G24: =D24-F24 -> -36.5 | H24: =IF(ISERR(G24*C24),"",G24*C24) -> -2429075
A25: 14 | B25: M876680 | C25: 320361.34 | D25: 44207 | E25: Midpoint of Benefit Period | F25: 44246 | G25: =D25-F25 -> -39 | H25: =IF(ISERR(G25*C25),"",G25*C25) -> -12494092
A26: 15 | B26: M823669 | C26: 31575.36 | D26: 44110.5 | E26: Midpoint of Benefit Period | F26: 44150 | G26: =D26-F26 -> -39.5 | H26: =IF(ISERR(G26*C26),"",G26*C26) -> -1247226.7
... A43: 32 | B43: M933625 | C43: 42082.45 | D43: 44322.5 | E43: Midpoint of Benefit Period | F43: 44357 | G43: =D43-F43 -> -34.5 | H43: =IF(ISERR(G43*C43),"",G43*C43) -> -1451844.5
A44: =A43+1 -> 33 | B44: M866807 | C44: 26623.47 | D44: 44202 | E44: Midpoint of Benefit Period | F44: 44235 | G44: =D44-F44 -> -33 | H44: =IF(ISERR(G44*C44),"",G44*C44) -> -878574.51
A45: =A44+1 -> 34 | B45: M822971 | C45: 34409.4 | D45: 44096.5 | E45: Midpoint of Benefit Period | F45: 44139 | G45: =D45-F45 -> -42.5 | H45: =IF(ISERR(G45*C45),"",G45*C45) -> -1462399.5
A46: =A45+1 -> 35 | B46: 00505094 | C46: 35485 | D46: 44340 | E46: Invoice Date | F46: 44370 | G46: =D46-F46 -> -30 | H46: =IF(ISERR(G46*C46),"",G46*C46) -> -1064550
A47: =A46+1 -> 36 | B47: 00479510 | C47: 29130.5 | D47: 44150.5 | E47: Midpoint of Benefit Period | F47: 44225 | G47: =D47-F47 -> -74.5 | H47: =IF(ISERR(G47*C47),"",G47*C47) -> -2170222.2
A48: =A47+1 -> 37 | B48: M919206 | C48: 43244.24 | D48: 44245 | E48: Midpoint of Benefit Period | F48: 44336 | G48: =D48-F48 -> -91 | H48: =IF(ISERR(G48*C48),"",G48*C48) -> -3935225.8
A49: =A48+1 -> 38 | B49: M893492 | C49: 27871.2 | D49: 44257.5 | E49: Midpoint of Benefit Period | F49: 44291 | G49: =D49-F49 -> -33.5 | H49: =IF(ISERR(G49*C49),"",G49*C49) -> -933685.2
A50: =A49+1 -> 39 | B50: M876677 | C50: 137324.94 | D50: 44209 | E50: Invoice Date | F50: 44253 | G50: =D50-F50 -> -44 | H50: =IF(ISERR(G50*C50),"",G50*C50) -> -6042297.4
A51: =A50+1 -> 40 | B51: M850919 | C51: 32306.64 | D51: 44143.5 | E51: Midpoint of Benefit Period | F51: 44189 | G51: =D51-F51 -> -45.5 | H51: =IF(ISERR(G51*C51),"",G51*C51) -> -1469952.1
A52: =A51+1 -> 41 | B52: M880068 | C52: 130011.17 | D52: 44210 | E52: Midpoint of Benefit Period | F52: 44252 | G52: =D52-F52 -> -42 | H52: =IF(ISERR(G52*C52),"",G52*C52) -> -5460469.1
A53: =A52+1 -> 42 | B53: M823227 | C53: 42240 | D53: 44071 | E53: Invoice Date | F53: 44155 | G53: =D53-F53 -> -84 | H53: =IF(ISERR(G53*C53),"",G53*C53) -> -3548160
A54: =A53+1 -> 43 | B54: 00507694 | C54: 699166.06 | D54: 44355 | E54: Midpoint of Benefit Period | F54: 44362 | G54: =D54-F54 -> -7 | H54: =IF(ISERR(G54*C54),"",G54*C54) -> -4894162.4
A55: =A54+1 -> 44 | B55: 00473785 | C55: 90904.87 | D55: 44181 | E55: Midpoint of Benefit Period | F55: 44180 | G55: =D55-F55 -> 1 | H55: =IF(ISERR(G55*C55),"",G55*C55) -> 90904.87
... A88: =A87+1 -> 77 | B88: M900687 | C88: 167873.75 | D88: 44264 | E88: Invoice Date | F88: 44302 | G88: =D88-F88 -> -38 | H88: =IF(ISERR(G88*C88),"",G88*C88) -> -6379202.5
A89: =A88+1 -> 78
A90: =A89+1 -> 79 | B90: Total | C90: =SUM(C12:C89) -> 9730341.9 | G90: =+ROUND(H90/C90,2) -> -35.29 | H90: =SUM(H12:H89) -> -3.4341538e+08
A91: =A90+1 -> 80
A92: =A91+1 -> 81
A93: =A92+1 -> 82
A94: =A93+1 -> 83
A95: =A94+1 -> 84 | B95: Source: | C95: 3rd party O&M - ESD sample.XLSX

Sheet 6-3
A1: 2022 RATE CASE
A2: ='1-1-3-1-1'!A2 -> ONCOR ELECTRIC DELIVERY COMPANY LLC
A3: NON-LABOR O&M - THIRD PARTY O&M SAMPLE - CORPORATE (DETAIL)
A4: FOR THE LEAD-LAG STUDY-PERIOD ENDING SEPTEMBER 30, 2021
A5: SPONSOR: A. THENMADATHIL
F7: Later of Due Date
A8: Line | D8: Begin | E8: Type of | F8: or Check Clear | G8: (Lead)/Lag | H8: Weighted Dollar | J8: BU
A9: No. | B9: Voucher | C9: Amount | D9: Date | E9: Begin Date | F9: Date | G9: Days | H9: Days
B10: (a) | C10: (b) | D10: (c) | E10: (d) | F10: (e) | G10: (f) | H10: (g)
A12: 1 | B12: 00480188 | C12: 206500 | D12: 44379 | E12: Midpoint of Service Period | F12: 44248 | G12: =D12-F12 -> 131 | H12: =IF(ISERR(G12*C12),"",G12*C12) -> 27051500 | J12: TRNDS
A13: =A12+1 -> 2 | B13: 00492304 | C13: 6500 | D13: 44461 | E13: Midpoint of Service Period | F13: 44309 | G13: =D13-F13 -> 152 | H13: =IF(ISERR(G13*C13),"",G13*C13) -> 988000 | J13: TRNDS
A14: =A13+1 -> 3 | B14: 00506451 | C14: 200 | D14: 44335 | E14: Invoice Date | F14: 44368 | G14: =D14-F14 -> -33 | H14: =IF(ISERR(G14*C14),"",G14*C14) -> -6600 | J14: TRNDS
A15: =A14+1 -> 4 | B15: 00457901 | C15: 6500 | D15: 44268 | E15: Midpoint of Service Period | F15: 44118 | G15: =D15-F15 -> 150 | H15: =IF(ISERR(G15*C15),"",G15*C15) -> 975000 | J15: TRNDS
A16: =A15+1 -> 5 | B16: 00469853 | C16: 4308.25 | D16: 44059 | E16: Midpoint of Service Period | F16: 44174 | G16: =D16-F16 -> -115 | H16: =IF(ISERR(G16*C16),"",G16*C16) -> -495448.75 | J16: TRNDS
A17: =A16+1 -> 6 | B17: 00508209 | C17: 14000 | D17: 44150.5 | E17: Midpoint of Service Period | F17: 44393 | G17: =D17-F17 -> -242.5 | H17: =IF(ISERR(G17*C17),"",G17*C17) -> -3395000 | J17: TRNDS
A18: =A17+1 -> 7 | B18: 00462114 | C18: 0 | E18: Midpoint of Service Period | F18: 44093 | G18: 0 | H18: =IF(ISERR(G18*C18),"",G18*C18) -> 0 | J18: TRNDS | K18: *
A19: =A18+1 -> 8 | B19: 00509932 | C19: 8027.55 | D19: 44332 | E19: Midpoint of Service Period | F19: 44389 | G19: =D19-F19 -> -57 | H19: =IF(ISERR(G19*C19),"",G19*C19) -> -457570.35 | J19: TRNDS
A20: =A19+1 -> 9 | B20: 00457903 | C20: 6700 | D20: 44269 | E20: Midpoint of Service Period | F20: 44118 | G20: =D20-F20 -> 151 | H20: =IF(ISERR(G20*C20),"",G20*C20) -> 1011700 | J20: TRNDS
A21: =A20+1 -> 10 | B21: 00461902 | C21: 7104.45 | D21: 44089.5 | E21: Midpoint of Service Period | F21: 44127 | G21: =D21-F21 -> -37.5 | H21: =IF(ISERR(G21*C21),"",G21*C21) -> -266416.88 | J21: TRNDS
A22: =A21+1 -> 11
A23: =A22+1 -> 12 | C23: =SUM(C12:C21) -> 259840.25 | G23: =+ROUND(H23/C23,2) -> 97.77 | H23: =SUM(H12:H21) -> 25405164
A24: =A23+1 -> 13
A25: =A24+1 -> 14 | B25: Source: | C25: 3rd party O&M - TRNDS sample
B27: *not included in study due to voucher being cancelled and no payment needed

Sheet 6-4
A1: 2022 RATE CASE
A2: ONCOR ELECTRIC DELIVERY COMPANY LLC
A3: O&M EXPENDITURES - PENSION BENEFITS
A4: FOR THE LEAD-LAG STUDY-PERIOD ENDING SEPTEMBER 30, 2021
A5: SPONSOR: A. THENMADATHIL
F6: Benefit Period Dates
A7: Line No. | B7: Payment Date | C7: Payment Type | D7: Payment Amount | E7: % of Total | F7: Beginning | G7: Ending | H7: Benefit Period Mid-Point | I7: Payment (Lead)/Lag | J7: Weighted Dollar Days
B8: (a) | C8: (b) | D8: (c) | E8: (d) | F8: (e) | G8: (f) | H8: (g) | I8: (h) = (g) - (a) | J8: (i) = (c) * (h)
A9: 1 | B9: 44135 | C9: Supplemental Retirement Plan | D9: 370124.61 | E9: =+D9/$D$22 -> 0.082410912 | F9: 43831 | G9: 44196 | H9: =AVERAGE(F9:G9) -> 44013.5 | I9: =+H9-B9 -> -121.5 | J9: =+D9*I9 -> -44970140
A10: 2 | B10: 44165 | C10: Supplemental Retirement Plan | D10: 372578.39 | E10: =+D10/$D$22 -> 0.082957264 | F10: 43831 | G10: 44196 | H10: =AVERAGE(F10:G10) -> 44013.5 | I10: =+H10-B10 -> -151.5 | J10: =+D10*I10 -> -56445626
A11: 3 | B11: 44196 | C11: Supplemental Retirement Plan | D11: 413825.13 | E11: =+D11/$D$22 -> 0.092141148 | F11: 43831 | G11: 44196 | H11: =AVERAGE(F11:G11) -> 44013.5 | I11: =+H11-B11 -> -182.5 | J11: =+D11*I11 -> -75523086
A12: 4 | B12: 44227 | C12: Supplemental Retirement Plan | D12: 373043.73 | E12: =+D12/$D$22 -> 0.083060876 | F12: 44197 | G12: 44561 | H12: =AVERAGE(F12:G12) -> 44379 | I12: =+H12-B12 -> 152 | J12: =+D12*I12 -> 56702647
A13: 5 | B13: 44255 | C13: Supplemental Retirement Plan | D13: 372252.15 | E13: =+D13/$D$22 -> 0.082884625 | F13: 44197 | G13: 44561 | H13: =AVERAGE(F13:G13) -> 44379 | I13: =+H13-B13 -> 124 | J13: =+D13*I13 -> 46159267
A14: 6 | B14: 44286 | C14: Supplemental Retirement Plan | D14: 370321.51 | E14: =+D14/$D$22 -> 0.082454754 | F14: 44197 | G14: 44561 | H14: =AVERAGE(F14:G14) -> 44379 | I14: =+H14-B14 -> 93 | J14: =+D14*I14 -> 34439900
A15: 7 | B15: 44316 | C15: Supplemental Retirement Plan | D15: 367750.15 | E15: =+D15/$D$22 -> 0.081882222 | F15: 44197 | G15: 44561 | H15: =AVERAGE(F15:G15) -> 44379 | I15: =+H15-B15 -> 63 | J15: =+D15*I15 -> 23168259
A16: 8 | B16: 44347 | C16: Supplemental Retirement Plan | D16: 367750.15 | E16: =+D16/$D$22 -> 0.081882222 | F16: 44197 | G16: 44561 | H16: =AVERAGE(F16:G16) -> 44379 | I16: =+H16-B16 -> 32 | J16: =+D16*I16 -> 11768005
A17: 9 | B17: 44377 | C17: Supplemental Retirement Plan | D17: 368582.42 | E17: =+D17/$D$22 -> 0.082067533 | F17: 44197 | G17: 44561 | H17: =AVERAGE(F17:G17) -> 44379 | I17: =+H17-B17 -> 2 | J17: =+D17*I17 -> 737164.84
A18: 10 | B18: 44408 | C18: Supplemental Retirement Plan | D18: 375660.68 | E18: =+D18/$D$22 -> 0.083643558 | F18: 44197 | G18: 44561 | H18: =AVERAGE(F18:G18) -> 44379 | I18: =+H18-B18 -> -29 | J18: =+D18*I18 -> -10894160
A19: 11 | B19: 44439 | C19: Supplemental Retirement Plan | D19: 369659.91 | E19: =+D19/$D$22 -> 0.082307444 | F19: 44197 | G19: 44561 | H19: =AVERAGE(F19:G19) -> 44379 | I19: =+H19-B19 -> -60 | J19: =+D19*I19 -> -22179595
A20: 12 | B20: 44469 | C20: Supplemental Retirement Plan | D20: 369659.91 | E20: =+D20/$D$22 -> 0.082307444 | F20: 44197 | G20: 44561 | H20: =AVERAGE(F20:G20) -> 44379 | I20: =+H20-B20 -> -90 | J20: =+D20*I20 -> -33269392
A21: 17
A22: 18 | B22: Suppl. Payments and Weighted Dollar Days | D22: =SUM(D9:D21) -> 4491208.7 | E22: =SUM(E9:E21) -> 1 | J22: =SUM(J9:J21) -> -70306756
A23: 19 | B23: Weighted Average Payment Lead = Column (i), Line 18 divided by Column (c), Line 18 | I23: =+J22/D22 -> -15.654306
A24: 20
A25: 21 | B25: Retirement Plan (Pro Forma 2021)
A26: 22 | B26: 44301 | C26: Retirement Plan | D26: 7400000 | E26: =+D26/$D$31 -> 0.25 | F26: 44197 | G26: 44561 | H26: =AVERAGE(F26:G26) -> 44379 | I26: =+H26-B26 -> 78 | J26: =+D26*I26 -> 577200000
A27: 23 | B27: 44392 | C27: Retirement Plan | D27: 7400000 | E27: =+D27/$D$31 -> 0.25 | F27: 44197 | G27: 44561 | H27: =AVERAGE(F27:G27) -> 44379 | I27: =+H27-B27 -> -13 | J27: =+D27*I27 -> -96200000
A28: 24 | B28: 44484 | C28: Retirement Plan | D28: 7400000 | E28: =+D28/$D$31 -> 0.25 | F28: 44197 | G28: 44561 | H28: =AVERAGE(F28:G28) -> 44379 | I28: =+H28-B28 -> -105 | J28: =+D28*I28 -> -777000000
A29: 25 | B29: 44576 | C29: Retirement Plan | D29: 7400000 | E29: =+D29/$D$31 -> 0.25 | F29: 44197 | G29: 44561 | H29: =AVERAGE(F29:G29) -> 44379 | I29: =+H29-B29 -> -197 | J29: =+D29*I29 -> -1457800000
A30: 26
A31: 27 | B31: Retirement Payments and Weighted Dollar Days | D31: =SUM(D26:D30) -> 29600000 | E31: =SUM(E26:E29) -> 1 | J31: =SUM(J26:J30) -> -1753800000
A32: 28 | B32: Weighted Average Payment Lead = Column (i), Line 27 divided by Column (c), Line 27 | I32: =+J31/D31 -> -59.25
A33: 29
A34: 30
A35: 31 | B35: Total Payments and Weighted Dollar Days | D35: =+D31+D22 -> 34091209 | J35: =+J31+J22 -> -1.8241068e+09
A36: 32 | B36: Weighted Average Payment Lead = Column (i), Line 31 divided by Column (c), Line 31 | I36: =+J35/D35 -> -53.506661
A37: 33
A38: 34 | B38: Source: | C38: Pension and OPEB Funding.xlsx

Sheet 6-5
A1: 2022 RATE CASE
A2: ONCOR ELECTRIC DELIVERY COMPANY LLC
A3: O&M EXPENDITURES - OTHER POST-EMPLOYMENT BENEFITS
A4: FOR THE LEAD-LAG STUDY-PERIOD ENDING SEPTEMBER 30, 2021
A5: SPONSOR: A. THENMADATHIL
F6: Benefit Period Dates
A7: Line No. | B7: Payment Date | C7: Payment Type | D7: Payment Amount | E7: % of Total | F7: Beginning | G7: Ending | H7: Benefit Period Mid-Point | I7: Payment (Lead)/Lag | J7: Weighted Dollar Days
B8: (a) | C8: (b) | D8: (c) | E8: (d) | F8: (e) | G8: (f) | H8: (g) | I8: (h) = (g) - (a) | J8: (i) = (c) * (h)
A10: 1 | B10: 44106 | C10: OPEB-FAS 106 | D10: 2847053 | E10: =+D10/$D$22 -> 0.08343768 | F10: 44105 | G10: 44135 | H10: =AVERAGE(F10:G10) -> 44120 | I10: =+H10-B10 -> 14 | J10: =+D10*I10 -> 39858742
A11: =A10+1 -> 2 | B11: 44141 | C11: OPEB-FAS 106 | D11: 2847053 | E11: =+D11/$D$22 -> 0.08343768 | F11: 44136 | G11: 44165 | H11: =AVERAGE(F11:G11) -> 44150.5 | I11: =+H11-B11 -> 9.5 | J11: =+D11*I11 -> 27047004
A12: =A11+1 -> 3 | B12: 44169 | C12: OPEB-FAS 106 | D12: 2847053 | E12: =+D12/$D$22 -> 0.08343768 | F12: 44166 | G12: 44196 | H12: =AVERAGE(F12:G12) -> 44181 | I12: =+H12-B12 -> 12 | J12: =+D12*I12 -> 34164636
A13: =A12+1 -> 4 | B13: 44203 | C13: OPEB-FAS 106 | D13: 2847053 | E13: =+D13/$D$22 -> 0.08343768 | F13: 44197 | G13: 44227 | H13: =AVERAGE(F13:G13) -> 44212 | I13: =+H13-B13 -> 9 | J13: =+D13*I13 -> 25623477
A14: =A13+1 -> 5 | B14: 44231 | C14: OPEB-FAS 106 | D14: 2847053 | E14: =+D14/$D$22 -> 0.08343768 | F14: 44228 | G14: 44255 | H14: =AVERAGE(F14:G14) -> 44241.5 | I14: =+H14-B14 -> 10.5 | J14: =+D14*I14 -> 29894056
A15: =A14+1 -> 6 | B15: 44260 | C15: OPEB-FAS 106 | D15: 2847053 | E15: =+D15/$D$22 -> 0.08343768 | F15: 44256 | G15: 44286 | H15: =AVERAGE(F15:G15) -> 44271 | I15: =+H15-B15 -> 11 | J15: =+D15*I15 -> 31317583
A16: =A15+1 -> 7 | B16: 44293 | C16: OPEB-FAS 106 | D16: 2839932 | E16: =+D16/$D$22 -> 0.083228987 | F16: 44287 | G16: 44316 | H16: =AVERAGE(F16:G16) -> 44301.5 | I16: =+H16-B16 -> 8.5 | J16: =+D16*I16 -> 24139422
A17: =A16+1 -> 8 | B17: 44322 | C17: OPEB-FAS 106 | D17: 2839932 | E17: =+D17/$D$22 -> 0.083228987 | F17: 44317 | G17: 44347 | H17: =AVERAGE(F17:G17) -> 44332 | I17: =+H17-B17 -> 10 | J17: =+D17*I17 -> 28399320
A18: =A17+1 -> 9 | B18: 44351 | C18: OPEB-FAS 106 | D18: 2839932 | E18: =+D18/$D$22 -> 0.083228987 | F18: 44348 | G18: 44377 | H18: =AVERAGE(F18:G18) -> 44362.5 | I18: =+H18-B18 -> 11.5 | J18: =+D18*I18 -> 32659218
A19: =A18+1 -> 10 | B19: 44383 | C19: OPEB-FAS 106 | D19: 2839932 | E19: =+D19/$D$22 -> 0.083228987 | F19: 44378 | G19: 44408 | H19: =AVERAGE(F19:G19) -> 44393 | I19: =+H19-B19 -> 10 | J19: =+D19*I19 -> 28399320
A20: =A19+1 -> 11 | B20: 44414 | C20: OPEB-FAS 106 | D20: 2839932 | E20: =+D20/$D$22 -> 0.083228987 | F20: 44409 | G20: 44439 | H20: =AVERAGE(F20:G20) -> 44424 | I20: =+H20-B20 -> 10 | J20: =+D20*I20 -> 28399320
A21: =A20+1 -> 12 | B21: 44442 | C21: OPEB-FAS 106 | D21: 2839932 | E21: =+D21/$D$22 -> 0.083228987 | F21: 44440 | G21: 44469 | H21: =AVERAGE(F21:G21) -> 44454.5 | I21: =+H21-B21 -> 12.5 | J21: =+D21*I21 -> 35499150
A22: =A21+1 -> 13 | B22: Total Payments and Weighted Dollar Days | D22: =SUM(D10:D21) -> 34121910 | E22: =SUM(E10:E21) -> 1 | J22: =SUM(J10:J21) -> 365401248
A23: =A22+1 -> 14 | B23: Weighted Average Payment Lead = Column (i), Line 13 divided by Column (c), Line 13 | I23: =+J22/D22 -> 10.708699
A24: =A23+1 -> 15
A25: =A24+1 -> 16 | B25: Source: | C25: Pension and OPEB Funding.xlsx

Sheet 7
A1: 2022 RATE CASE
A2: =' '!A2 -> ONCOR ELECTRIC DELIVERY COMPANY LLC
A3: FEDERAL INCOME TAX LEAD DAYS
A4: FOR THE LEAD-LAG STUDY-PERIOD ENDING SEPTEMBER 30, 2021
A5: SPONSOR: A. THENMADATHIL
E7: Statutory %
A8: Line | B8: Statutory Payment | D8: (Lead)/Lag | E8: of Total | F8: Weighted
A9: No. | B9: Due Date | C9: Mid-Year | D9: Days | E9: Taxes for Year | F9: Days
B10: (a) | C10: (b) | D10: (c) | E10: (d) | F10: (e)
A12: 1 | B12: 44180 | C12: =DATE(2020,1,1)+(Year/2) -> 44013.5 | D12: =C12-B12 -> -166.5 | E12: 0.25 | F12: =D12*E12 -> -41.625
A13: =A12+1 -> 2
A14: =A13+1 -> 3 | B14: 44301 | C14: =DATE(2021,1,1)+(Year/2) -> 44379.5 | D14: =C14-B14 -> 78.5 | E14: 0.25 | F14: =D14*E14 -> 19.625
A15: =A14+1 -> 4
A16: =A15+1 -> 5 | B16: 44362 | C16: =+C14 -> 44379.5 | D16: =C16-B16 -> 17.5 | E16: 0.25 | F16: =D16*E16 -> 4.375
A17: =A16+1 -> 6
A18: =A17+1 -> 7 | B18: 44454 | C18: =C16 -> 44379.5 | D18: =C18-B18 -> -74.5 | E18: 0.25 | F18: =D18*E18 -> -18.625
A19: =A18+1 -> 8
A20: =A19+1 -> 9 | B20: Total | F20: =ROUND(SUM(F12:F18),2) -> -36.25
A21: =A20+1 -> 10
A22: =A21+1 -> 11
A23: =A22+1 -> 12
A24: =A23+1 -> 13 | B24: Source: | C24: FIT Payment Dates.pdf

Sheet 8
A1: 2022 RATE CASE
A2: =' '!A2 -> ONCOR ELECTRIC DELIVERY COMPANY LLC
A3: PAYROLL TAX LEAD DAY CALCULATION
A4: FOR THE LEAD-LAG STUDY-PERIOD ENDING SEPTEMBER 30, 2021
A5: SPONSOR: A. THENMADATHIL
E7: Weighted
A8: Line | D8: (Lead)/Lag | E8: Dollar
A9: No. | B9: Description | C9: Amount | D9: Days | E9: Days | F9: Reference
B10: (a) | C10: (b) | D10: (c) | E10: (d) | F10: (e)
A12: 1 | B12: FICA | C12: ='8-1'!C104 -> 34752384 | D12: ='8-1'!E104 -> -12.1 | E12: ='8-1'!F104 -> -4.2050385e+08 | F12: WP/II-B-9/8-1
A13: =A12+1 -> 2
A14: =A13+1 -> 3 | B14: Federal & State Unemployment | C14: ='8-2'!E96 -> 646617.87 | D14: =+'8-2'!K96 -> 12.26 | E14: =+'8-2'!L96 -> 7926162.6 | F14: WP/II-B-9/8-2
A15: =A14+1 -> 4
A16: =A15+1 -> 5 | B16: Total Payroll Related Taxes | C16: =SUM(C12:C14) -> 35399002 | D16: =ROUND(E16/C16,2) -> -11.66 | E16: =SUM(E12:E14) -> -4.1257768e+08

Sheet 8-1
A1: 2022 RATE CASE
A2: =' '!A2 -> ONCOR ELECTRIC DELIVERY COMPANY LLC
A3: PAYROLL TAXES - FICA TAX LEAD DAY CALCULATION - DISTRIBUTION
A4: FOR THE LEAD-LAG STUDY-PERIOD ENDING SEPTEMBER 30, 2021
A5: SPONSOR: A. THENMADATHIL
A7: Line | B7: Payroll | C7: FICA | D7: Deposit | F7: Weighted
A8: No. | B8: Check Date | C8: Amount | D8: Date | E8: (Lead)/Lag | F8: Dollar Days
B9: (a) | C9: (b) | D9: (c) | E9: (d) | F9: (e)
A11: 1 | B11: 44112 | C11: 44810.41 | D11: 44112 | E11: =IF(C11=0,0,-(D11-B11)) -> 0 | F11: =C11*E11 -> 0
A12: =A11+1 -> 2 | B12: 44117 | C12: -5.01 | D12: 44117 | E12: =IF(C12=0,0,-(D12-B12)) -> 0 | F12: =C12*E12 -> 0
A13: =A12+1 -> 3 | B13: 44126 | C13: 44575.84 | D13: 44126 | E13: =IF(C13=0,0,-(D13-B13)) -> 0 | F13: =C13*E13 -> 0
A14: =A13+1 -> 4 | B14: 44118 | C14: 166224.02 | D14: 44118 | E14: =IF(C14=0,0,-(D14-B14)) -> 0 | F14: =C14*E14 -> 0
A15: =A14+1 -> 5 | B15: 44125 | C15: 172.37 | D15: 44125 | E15: =IF(C15=0,0,-(D15-B15)) -> 0 | F15: =C15*E15 -> 0
A16: =A15+1 -> 6 | B16: 44132 | C16: 6479.55 | D16: 44132 | E16: =IF(C16=0,0,-(D16-B16)) -> 0 | F16: =C16*E16 -> 0
A17: =A16+1 -> 7 | B17: 44133 | C17: 162027.34 | D17: 44133 | E17: =IF(C17=0,0,-(D17-B17)) -> 0 | F17: =C17*E17 -> 0
A18: =A17+1 -> 8 | B18: 44140 | C18: 50040.03 | D18: 44140 | E18: =IF(C18=0,0,-(D18-B18)) -> 0 | F18: =C18*E18 -> 0
A19: =A18+1 -> 9 | B19: 44147 | C19: 168585.55 | D19: 44147 | E19: =IF(C19=0,0,-(D19-B19)) -> 0 | F19: =C19*E19 -> 0
A20: =A19+1 -> 10 | B20: 44153 | C20: 699.47 | D20: 44153 | E20: =IF(C20=0,0,-(D20-B20)) -> 0 | F20: =C20*E20 -> 0
A21: =A20+1 -> 11 | B21: 44154 | C21: 44737.36 | D21: 44154 | E21: =IF(C21=0,0,-(D21-B21)) -> 0 | F21: =C21*E21 -> 0
A22: =A21+1 -> 12 | B22: 44160 | C22: 159413.51 | D22: 44160 | E22: =IF(C22=0,0,-(D22-B22)) -> 0 | F22: =C22*E22 -> 0
A23: =A22+1 -> 13 | B23: 44168 | C23: 47510.53 | D23: 44168 | E23: =IF(C23=0,0,-(D23-B23)) -> 0 | F23: =C23*E23 -> 0
... A94: =A93+1 -> 84 | B94: 44468 | C94: 750744.06 | D94: 44468 | E94: =IF(C94=0,0,-(D94-B94)) -> 0 | F94: =C94*E94 -> 0
A95: =A94+1 -> 85
A96: =A95+1 -> 86 | B96: Total Distribution | C96: =SUM(C11:C95) -> 26139152 | E96: =ROUND(F96/C96,2) -> 0 | F96: =SUM(F11:F95) -> 0
A97: =A96+1 -> 87
A98: =A97+1 -> 88 | B98: Transmission (WP/II-B-9/8-1-2) | C98: ='8-1-2'!C51 -> 8613231.7 | E98: =ROUND(F98/C98,2) -> 0 | F98: ='8-1-2'!F51 -> 0
A99: =A98+1 -> 89
A100: =A99+1 -> 90 | B100: Total Transmission & Distribution | C100: =C96+C98 -> 34752384 | E100: =ROUND(F100/C100,2) -> 0 | F100: =F96+F98 -> 0
A101: =A100+1 -> 91
A102: =A101+1 -> 92 | B102: Lead Days from Midpoint to Payroll Payment Date | E102: =ROUND(+'2'!F35,2) -> -12.1 | F102: WP/II-B-9/2
A103: =A102+1 -> 93
A104: =A103+1 -> 94 | B104: Total Lead Days | C104: =C100 -> 34752384 | E104: =E100+E102 -> -12.1 | F104: =C104*E104 -> -4.2050385e+08
A105: =A104+1 -> 95
A106: =A105+1 -> 96 | B106: Source: | C106: Tax Other Than Income - Payroll Taxes.xlsx

Sheet 8-1-2
A1: 2022 RATE CASE
A2: =' '!A2 -> ONCOR ELECTRIC DELIVERY COMPANY LLC
A3: PAYROLL TAXES - FICA TAX LEAD DAY CALCULATION - TRANSMISSION
A4: FOR THE LEAD-LAG STUDY-PERIOD ENDING SEPTEMBER 30, 2021
A5: SPONSOR: A. THENMADATHIL
A7: Line | B7: Payroll | C7: FICA | D7: Deposit | F7: Weighted
A8: No. | B8: Check Date | C8: Amount | D8: Date | E8: (Lead)/Lag | F8: Dollar Days
B9: (a) | C9: (b) | D9: (c) | E9: (d) | F9: (e)
A11: 1 | B11: 44118 | C11: 75621.65 | D11: 44118 | E11: =IF(C11=0,0,-(D11-B11)) -> 0 | F11: =C11*E11 -> 0
A12: =A11+1 -> 2 | B12: 44133 | C12: 82258.68 | D12: 44133 | E12: =IF(C12=0,0,-(D12-B12)) -> 0 | F12: =C12*E12 -> 0
A13: =A12+1 -> 3 | B13: 44147 | C13: 76920.32 | D13: 44147 | E13: =IF(C13=0,0,-(D13-B13)) -> 0 | F13: =C13*E13 -> 0
A14: =A13+1 -> 4 | B14: 44160 | C14: 71148.25 | D14: 44160 | E14: =IF(C14=0,0,-(D14-B14)) -> 0 | F14: =C14*E14 -> 0
A15: =A14+1 -> 5 | B15: 44179 | C15: 84028.91 | D15: 44179 | E15: =IF(C15=0,0,-(D15-B15)) -> 0 | F15: =C15*E15 -> 0
A16: =A15+1 -> 6 | B16: 44189 | C16: 288.49 | D16: 44189 | E16: =IF(C16=0,0,-(D16-B16)) -> 0 | F16: =C16*E16 -> 0
A17: =A16+1 -> 7 | B17: 44195 | C17: 79980.8 | D17: 44195 | E17: =IF(C17=0,0,-(D17-B17)) -> 0 | F17: =C17*E17 -> 0
A18: =A17+1 -> 8 | B18: 44210 | C18: 360210.61 | D18: 44210 | E18: =IF(C18=0,0,-(D18-B18)) -> 0 | F18: =C18*E18 -> 0
A19: =A18+1 -> 9 | B19: 44223 | C19: 1266.04 | D19: 44223 | E19: =IF(C19=0,0,-(D19-B19)) -> 0 | F19: =C19*E19 -> 0
A20: =A19+1 -> 10 | B20: 44224 | C20: 358754.24 | D20: 44224 | E20: =IF(C20=0,0,-(D20-B20)) -> 0 | F20: =C20*E20 -> 0
A21: =A20+1 -> 11 | B21: 44238 | C21: 355074.32 | D21: 44238 | E21: =IF(C21=0,0,-(D21-B21)) -> 0 | F21: =C21*E21 -> 0
A22: =A21+1 -> 12 | B22: 44243 | C22: 37302.42 | D22: 44243 | E22: =IF(C22=0,0,-(D22-B22)) -> 0 | F22: =C22*E22 -> 0
A23: =A22+1 -> 13 | B23: 44244 | C23: 174.69 | D23: 44244 | E23: =IF(C23=0,0,-(D23-B23)) -> 0 | F23: =C23*E23 -> 0
... A49: =A48+1 -> 39 | B49: 44468 | C49: 366240.35 | D49: 44468 | E49: =IF(C49=0,0,-(D49-B49)) -> 0 | F49: =C49*E49 -> 0
A50: =A49+1 -> 40
A51: =A50+1 -> 41 | B51: Total | C51: =SUM(C11:C50) -> 8613231.7 | E51: =ROUND(F51/C51,2) -> 0 | F51: =SUM(F11:F50) -> 0
A52: =A51+1 -> 42
A53: =A52+1 -> 43 | B53: Source: | C53: Taxes Other Than Income - Payroll Taxes.xlsx

Sheet 8-2
A1: 2022 RATE CASE
A2: =' '!A2 -> ONCOR ELECTRIC DELIVERY COMPANY LLC
A3: PAYROLL TAXES - FEDERAL AND STATE UNEMPLOYMENT TAX LEAD DAY CALCULATION - DISTRIBUTION
A4: FOR THE LEAD-LAG STUDY-PERIOD ENDING SEPTEMBER 30, 2021
A5: SPONSOR: A. THENMADATHIL
A7: Line | B7: Payroll | C7: FUTA | D7: SUTA | E7: Total | F7: Deposit | G7: Service Period | L7: Weighted
A8: No. | B8: Check Date | C8: Amount | D8: Amount | E8: Amount | F8: Date | G8: Beginning | H8: Ending | I8: Mid-Point | J8: Due Date | K8: (Lead)/Lag | L8: Dollar Days
B9: (a) | C9: (b) | D9: (c) | E9: (d) | F9: (e) | G9: (f) | H9: (g) | I9: (h) | J9: (i) | K9: (j) = (h) - (i) | L9: (k) = (d) * (j)
A11: 1 | B11: 44112 | C11: 69.47 | D11: 85.49 | E11: =D11+C11 -> 154.96 | F11: 44112 | G11: 43831 | H11: 44196 | I11: =+(G11+H11)/2 -> 44013.5 | J11: 44227 | K11: =I11-J11 -> -213.5 | L11: =E11*K11 -> -33083.96
A12: =A11+1 -> 2 | B12: 44117 | C12: -0.02 | D12: -0.11 | E12: =D12+C12 -> -0.13 | F12: 44117 | G12: 43831 | H12: 44196 | I12: =+(G12+H12)/2 -> 44013.5 | J12: 44227 | K12: =I12-J12 -> -213.5 | L12: =E12*K12 -> 27.755
A13: =A12+1 -> 3 | B13: 44126 | C13: 64.94 | D13: 79.21 | E13: =D13+C13 -> 144.15 | F13: 44126 | G13: 43831 | H13: 44196 | I13: =+(G13+H13)/2 -> 44013.5 | J13: 44227 | K13: =I13-J13 -> -213.5 | L13: =E13*K13 -> -30776.025
A14: =A13+1 -> 4 | B14: 44118 | C14: 0 | D14: 1195.55 | E14: =D14+C14 -> 1195.55 | F14: 44118 | G14: 43831 | H14: 44196 | I14: =+(G14+H14)/2 -> 44013.5 | J14: 44227 | K14: =I14-J14 -> -213.5 | L14: =E14*K14 -> -255249.92
A15: =A14+1 -> 5 | B15: 44125 | C15: 20.28 | D15: 27.53 | E15: =D15+C15 -> 47.81 | F15: 44125 | G15: 43831 | H15: 44196 | I15: =+(G15+H15)/2 -> 44013.5 | J15: 44227 | K15: =I15-J15 -> -213.5 | L15: =E15*K15 -> -10207.435
A16: =A15+1 -> 6 | B16: 44133 | C16: 630.11 | D16: 829.29 | E16: =D16+C16 -> 1459.4 | F16: 44133 | G16: 43831 | H16: 44196 | I16: =+(G16+H16)/2 -> 44013.5 | J16: 44227 | K16: =I16-J16 -> -213.5 | L16: =E16*K16 -> -311581.9
A17: =A16+1 -> 7 | B17: 44140 | C17: 21.71 | D17: 47.84 | E17: =D17+C17 -> 69.55 | F17: 44140 | G17: 43831 | H17: 44196 | I17: =+(G17+H17)/2 -> 44013.5 | J17: 44227 | K17: =I17-J17 -> -213.5 | L17: =E17*K17 -> -14848.925
A18: =A17+1 -> 8 | B18: 44147 | C18: 570.69 | D18: 826.93 | E18: =D18+C18 -> 1397.62 | F18: 44147 | G18: 43831 | H18: 44196 | I18: =+(G18+H18)/2 -> 44013.5 | J18: 44227 | K18: =I18-J18 -> -213.5 | L18: =E18*K18 -> -298391.87
A19: =A18+1 -> 9 | B19: 44153 | C19: 22.06 | D19: 29.51 | E19: =D19+C19 -> 51.57 | F19: 44153 | G19: 43831 | H19: 44196 | I19: =+(G19+H19)/2 -> 44013.5 | J19: 44227 | K19: =I19-J19 -> -213.5 | L19: =E19*K19 -> -11010.195
A20: =A19+1 -> 10 | B20: 44154 | C20: 16.53 | D20: 30.75 | E20: =D20+C20 -> 47.28 | F20: 44154 | G20: 43831 | H20: 44196 | I20: =+(G20+H20)/2 -> 44013.5 | J20: 44227 | K20: =I20-J20 -> -213.5 | L20: =E20*K20 -> -10094.28
A21: =A20+1 -> 11 | B21: 44118 | C21: 488.72 | D21: -488.72 | E21: =D21+C21 -> 0 | F21: 44118 | G21: 43831 | H21: 44196 | I21: =+(G21+H21)/2 -> 44013.5 | J21: 44227 | K21: =I21-J21 -> -213.5 | L21: =E21*K21 -> 0
A22: =A21+1 -> 12 | B22: 44160 | C22: 654.37 | D22: 841.95 | E22: =D22+C22 -> 1496.32 | F22: 44160 | G22: 43831 | H22: 44196 | I22: =+(G22+H22)/2 -> 44013.5 | J22: 44227 | K22: =I22-J22 -> -213.5 | L22: =E22*K22 -> -319464.32
A23: =A22+1 -> 13 | B23: 44168 | C23: 34.33 | D23: 39.05 | E23: =D23+C23 -> 73.38 | F23: 44168 | G23: 43831 | H23: 44196 | I23: =+(G23+H23)/2 -> 44013.5 | J23: 44227 | K23: =I23-J23 -> -213.5 | L23: =E23*K23 -> -15666.63
... A88: =A87+1 -> 78 | B88: 44468 | C88: 494.04 | D88: 652.05 | E88: =D88+C88 -> 1146.09 | F88: 44468 | G88: 44197 | H88: 44561 | I88: =+(G88+H88)/2 -> 44379 | J88: 44500 | K88: =I88-J88 -> -121 | L88: =E88*K88 -> -138676.89
A89: =A88+1 -> 79
A90: =A89+1 -> 80 | B90: Total Distrib. | C90: =SUM(C11:C89) -> 225600.75 | D90: =SUM(D11:D89) -> 259882.56 | E90: =SUM(E11:E89) -> 485483.31 | K90: =ROUND(L90/E90,2) -> 12.17 | L90: =SUM(L11:L89) -> 5906006.5
A91: =A90+1 -> 81
A92: =A91+1 -> 82
A93: =A92+1 -> 83 | B93: Transmission (WP/II-B-9/8-1-2) | E93: =+'8-2-1'!E46 -> 161134.56 | K93: =ROUND(L93/E93,2) -> 12.54 | L93: =+'8-2-1'!L46 -> 2020156
A94: =A93+1 -> 84
A95: =A94+1 -> 85
A96: =A95+1 -> 86 | B96: Total Transmission & Distribution | E96: =+E93+E90 -> 646617.87 | K96: =ROUND(L96/E96,2) -> 12.26 | L96: =+L93+L90 -> 7926162.6
A97: =A96+1 -> 87
A98: =A97+1 -> 88
A99: =A98+1 -> 89 | B99: Source: | C99: Tax Other Than Income - Payroll Taxes.xlsx

Sheet 8-2-1
A1: 2022 RATE CASE
A2: =' '!A2 -> ONCOR ELECTRIC DELIVERY COMPANY LLC
A3: PAYROLL TAXES - FEDERAL AND STATE UNEMPLOYMENT TAX LEAD DAY CALCULATION - TRANSMISSION
A4: FOR THE LEAD-LAG STUDY-PERIOD ENDING SEPTEMBER 30, 2021
A5: SPONSOR: A. THENMADATHIL
A7: Line | B7: Payroll | C7: FUTA | D7: SUTA | E7: Total | F7: Deposit | G7: Service Period | L7: Weighted
A8: No. | B8: Check Date | C8: Amount | D8: Amount | E8: Amount | F8: Date | G8: Beginning | H8: Ending | I8: Mid-Point | J8: Due Date | K8: (Lead)/Lag | L8: Dollar Days
B9: (a) | C9: (b) | D9: (c) | E9: (d) | F9: (e) | G9: (f) | H9: (g) | I9: (h) | J9: (i) | K9: (j) = (h) - (i) | L9: (k) = (d) * (j)
A11: 1 | B11: 44118 | C11: 0 | D11: 268.79 | E11: =D11+C11 -> 268.79 | F11: 44118 | G11: 43831 | H11: 44196 | I11: =+(G11+H11)/2 -> 44013.5 | J11: 44227 | K11: =+I11-J11 -> -213.5 | L11: =E11*K11 -> -57386.665
A12: =A11+1 -> 2 | B12: 44133 | C12: 123.84 | D12: 155.76 | E12: =D12+C12 -> 279.6 | F12: 44133 | G12: 43831 | H12: 44196 | I12: =+(G12+H12)/2 -> 44013.5 | J12: 44227 | K12: =+I12-J12 -> -213.5 | L12: =E12*K12 -> -59694.6
A13: =A12+1 -> 3 | B13: 44147 | C13: 124.12 | D13: 180.31 | E13: =D13+C13 -> 304.43 | F13: 44147 | G13: 43831 | H13: 44196 | I13: =+(G13+H13)/2 -> 44013.5 | J13: 44227 | K13: =+I13-J13 -> -213.5 | L13: =E13*K13 -> -64995.805
A14: =A13+1 -> 4 | B14: 44118 | C14: 83.91 | D14: -83.91 | E14: =D14+C14 -> 0 | F14: 44118 | G14: 43831 | H14: 44196 | I14: =+(G14+H14)/2 -> 44013.5 | J14: 44227 | K14: =+I14-J14 -> -213.5 | L14: =E14*K14 -> 0
A15: =A14+1 -> 5 | B15: 44160 | C15: 118.52 | D15: 164.07 | E15: =D15+C15 -> 282.59 | F15: 44160 | G15: 43831 | H15: 44196 | I15: =+(G15+H15)/2 -> 44013.5 | J15: 44227 | K15: =+I15-J15 -> -213.5 | L15: =E15*K15 -> -60332.965
A16: =A15+1 -> 6 | B16: 44179 | C16: 114.2 | D16: 162.38 | E16: =D16+C16 -> 276.58 | F16: 44179 | G16: 43831 | H16: 44196 | I16: =+(G16+H16)/2 -> 44013.5 | J16: 44227 | K16: =+I16-J16 -> -213.5 | L16: =E16*K16 -> -59049.83
A17: =A16+1 -> 7 | B17: 44189 | C17: 0.41 | D17: 0.45 | E17: =D17+C17 -> 0.86 | F17: 44189 | G17: 43831 | H17: 44196 | I17: =+(G17+H17)/2 -> 44013.5 | J17: 44227 | K17: =+I17-J17 -> -213.5 | L17: =E17*K17 -> -183.61
A18: =A17+1 -> 8 | B18: 44195 | C18: 353.62 | D18: 429.9 | E18: =D18+C18 -> 783.52 | F18: 44195 | G18: 43831 | H18: 44196 | I18: =+(G18+H18)/2 -> 44013.5 | J18: 44227 | K18: =+I18-J18 -> -213.5 | L18: =E18*K18 -> -167281.52
A19: =A18+1 -> 9 | B19: 44210 | C19: 27298.15 | D19: 31734.97 | E19: =D19+C19 -> 59033.12 | F19: 44210 | G19: 44197 | H19: 44561 | I19: =+(G19+H19)/2 -> 44379 | J19: 44316 | K19: =+I19-J19 -> 63 | L19: =E19*K19 -> 3719086.6
A20: =A19+1 -> 10 | B20: 44223 | C20: 99.3 | D20: 109.23 | E20: =D20+C20 -> 208.53 | F20: 44223 | G20: 44197 | H20: 44561 | I20: =+(G20+H20)/2 -> 44379 | J20: 44316 | K20: =+I20-J20 -> 63 | L20: =E20*K20 -> 13137.39
A21: =A20+1 -> 11 | B21: 44224 | C21: 16533.44 | D21: 25897.7 | E21: =D21+C21 -> 42431.14 | F21: 44224 | G21: 44197 | H21: 44561 | I21: =+(G21+H21)/2 -> 44379 | J21: 44316 | K21: =+I21-J21 -> 63 | L21: =E21*K21 -> 2673161.8
A22: =A21+1 -> 12 | B22: 44238 | C22: 2081.36 | D22: 6228.89 | E22: =D22+C22 -> 8310.25 | F22: 44238 | G22: 44197 | H22: 44561 | I22: =+(G22+H22)/2 -> 44379 | J22: 44316 | K22: =+I22-J22 -> 63 | L22: =E22*K22 -> 523545.75
A23: =A22+1 -> 13 | B23: 44243 | C23: 36.93 | D23: 220.32 | E23: =D23+C23 -> 257.25 | F23: 44243 | G23: 44197 | H23: 44561 | I23: =+(G23+H23)/2 -> 44379 | J23: 44316 | K23: =+I23-J23 -> 63 | L23: =E23*K23 -> 16206.75
... A45: =A44+1 -> 35 | B45: 44468 | C45: 31.42 | D45: 42.65 | E45: =D45+C45 -> 74.07 | F45: 44468 | G45: 44197 | H45: 44561 | I45: =+(G45+H45)/2 -> 44379 | J45: 44500 | K45: =+I45-J45 -> -121 | L45: =E45*K45 -> -8962.47
A46: =A45+1 -> 36 | B46: Total | C46: =SUM(C11:C45) -> 81633.36 | D46: =SUM(D11:D45) -> 79501.2 | E46: =SUM(E11:E45) -> 161134.56 | K46: =ROUND(L46/E46,2) -> 12.54 | L46: =SUM(L11:L43) -> 2020156
A47: =A46+1 -> 37
A48: =A47+1 -> 38
A49: =A48+1 -> 39 | B49: Source: | C49: Tax Other Than Income - Payroll Taxes.xlsx

Sheet 9
A1: 2022 RATE CASE
A2: =' '!A2 -> ONCOR ELECTRIC DELIVERY COMPANY LLC
A3: STATE GROSS MARGIN TAX
A4: FOR THE LEAD-LAG STUDY-PERIOD ENDING SEPTEMBER 30, 2021
A5: SPONSOR: A. THENMADATHIL
A7: Line No. | B7: Month/ Year | C7: Accrual Date | D7: Mid Month | E7: Due Date | F7: (Lead)/Lag Days
B8: (a) | C8: (b) | D8: (c) | E8: (d) | F8: (e)
A10: 1 | B10: 44105 | C10: 44135 | D10: =IF(C10=0,"",DATE(YEAR(C10),MONTH(C10),1)+INT(DAY(DATE(YEAR(C10),MONTH(C10)+1,1)-1)/2))-1 -> 44119 | E10: 43966 | F10: =D10-E10 -> 153
A11: 2 | B11: =B10+31 -> 44136 | C11: 44165 | D11: =IF(C11=0,"",DATE(YEAR(C11),MONTH(C11),1)+INT(DAY(DATE(YEAR(C11),MONTH(C11)+1,1)-1)/2))-1 -> 44150 | E11: 43966 | F11: =D11-E11 -> 184
A12: 3 | B12: =B11+30 -> 44166 | C12: 44196 | D12: =IF(C12=0,"",DATE(YEAR(C12),MONTH(C12),1)+INT(DAY(DATE(YEAR(C12),MONTH(C12)+1,1)-1)/2))-1 -> 44180 | E12: 43966 | F12: =D12-E12 -> 214
A13: 4 | B13: =B12+31 -> 44197 | C13: 44227 | D13: =IF(C13=0,"",DATE(YEAR(C13),MONTH(C13),1)+INT(DAY(DATE(YEAR(C13),MONTH(C13)+1,1)-1)/2))-1 -> 44211 | E13: 44330 | F13: =D13-E13 -> -119
A14: 5 | B14: =B13+31 -> 44228 | C14: 44255 | D14: =IF(C14=0,"",DATE(YEAR(C14),MONTH(C14),1)+INT(DAY(DATE(YEAR(C14),MONTH(C14)+1,1)-1)/2))-1 -> 44241 | E14: 44330 | F14: =D14-E14 -> -89
A15: 6 | B15: =B14+29 -> 44257 | C15: 44286 | D15: =IF(C15=0,"",DATE(YEAR(C15),MONTH(C15),1)+INT(DAY(DATE(YEAR(C15),MONTH(C15)+1,1)-1)/2))-1 -> 44270 | E15: 44330 | F15: =D15-E15 -> -60
A16: 7 | B16: =B15+31 -> 44288 | C16: 44316 | D16: =IF(C16=0,"",DATE(YEAR(C16),MONTH(C16),1)+INT(DAY(DATE(YEAR(C16),MONTH(C16)+1,1)-1)/2))-1 -> 44301 | E16: 44330 | F16: =D16-E16 -> -29
A17: 8 | B17: =B16+30 -> 44318 | C17: 44347 | D17: =IF(C17=0,"",DATE(YEAR(C17),MONTH(C17),1)+INT(DAY(DATE(YEAR(C17),MONTH(C17)+1,1)-1)/2))-1 -> 44331 | E17: 44330 | F17: =D17-E17 -> 1
A18: 9 | B18: =B17+31 -> 44349 | C18: 44377 | D18: =IF(C18=0,"",DATE(YEAR(C18),MONTH(C18),1)+INT(DAY(DATE(YEAR(C18),MONTH(C18)+1,1)-1)/2))-1 -> 44362 | E18: 44330 | F18: =D18-E18 -> 32
A19: 10 | B19: =B18+30 -> 44379 | C19: 44408 | D19: =IF(C19=0,"",DATE(YEAR(C19),MONTH(C19),1)+INT(DAY(DATE(YEAR(C19),MONTH(C19)+1,1)-1)/2))-1 -> 44392 | E19: 44330 | F19: =D19-E19 -> 62
A20: 11 | B20: =B19+31 -> 44410 | C20: 44439 | D20: =IF(C20=0,"",DATE(YEAR(C20),MONTH(C20),1)+INT(DAY(DATE(YEAR(C20),MONTH(C20)+1,1)-1)/2))-1 -> 44423 | E20: 44330 | F20: =D20-E20 -> 93
A21: 12 | B21: =B20+31 -> 44441 | C21: 44469 | D21: =IF(C21=0,"",DATE(YEAR(C21),MONTH(C21),1)+INT(DAY(DATE(YEAR(C21),MONTH(C21)+1,1)-1)/2))-1 -> 44454 | E21: 44330 | F21: =D21-E21 -> 124
A22: 13
A23: 14 | B23: Average | F23: =ROUND(AVERAGE(F10:F21),2) -> 47.17

Sheet 10
A1: 2022 RATE CASE
A2: =' '!A2 -> ONCOR ELECTRIC DELIVERY COMPANY LLC
A3: LOCAL GROSS RECEIPTS TAXES
A4: FOR THE LEAD-LAG STUDY-PERIOD ENDING SEPTEMBER 30, 2021
A5: SPONSOR: A. THENMADATHIL
A7: Line | C7: Total | D7: Amort of | E7: Accrued | G7: Weighted
A8: No. | B8: City | C8: Amount | D8: Prepaid | E8: Portion | F8: (Lead)/Lag | G8: Dollar Days
B9: (a) | C9: (b) | D9: (c) | E9: (d) | F9: (e) | G9: (f)
A11: 1 | B11: DALLAS | C11: 49842175 | D11: 33345380 | E11: =+C11-D11 -> 16496795 | F11: -16.769755 | G11: =+F11*E11 -> -2.7664721e+08
A12: =1+A11 -> 2 | B12: FORT WORTH | C12: 30496677 | D12: 20379839 | E12: =+C12-D12 -> 10116838 | F12: -17.852792 | G12: =+F12*E12 -> -1.806138e+08
A13: =1+A12 -> 3 | B13: ARLINGTON | C13: 13798194 | D13: 13778618 | E13: =+C13-D13 -> 19575.98 | F13: -299.20726 | G13: =+F13*E13 -> -5857275.4
A14: =1+A13 -> 4 | B14: PLANO | C14: 11202563 | D14: 11190843 | E14: =+C14-D14 -> 11719.35 | F14: -300.7852 | G14: =+F14*E14 -> -3525007
A15: =1+A14 -> 5 | B15: IRVING | C15: 9184992.4 | D15: 9168599.6 | E15: =+C15-D15 -> 16392.83 | F15: -302.28277 | G15: =+F15*E15 -> -4955270
A16: =1+A15 -> 6 | B16: RICHARDSON | C16: 7802378.5 | D16: 0 | E16: =+C16-D16 -> 7802378.5 | F16: -91.237222 | G16: =+F16*E16 -> -7.1186734e+08
A17: =1+A16 -> 7 | B17: GRAND PRAIRIE | C17: 6593807.9 | D17: 6583802.6 | E17: =+C17-D17 -> 10005.27 | F17: -297.58092 | G17: =+F17*E17 -> -2977377.5
A18: =1+A17 -> 8 | B18: WACO | C18: 5754791.3 | D18: 0 | E18: =+C18-D18 -> 5754791.3 | F18: -91.483143 | G18: =+F18*E18 -> -5.2646639e+08
A19: =1+A18 -> 9 | B19: CARROLLTON | C19: 5370537.1 | D19: 0 | E19: =+C19-D19 -> 5370537.1 | F19: -47.094856 | G19: =+F19*E19 -> -2.5292467e+08
A20: =1+A19 -> 10 | B20: MIDLAND | C20: 4961842.7 | D20: 4949984.3 | E20: =+C20-D20 -> 11858.42 | F20: -301.04622 | G20: =+F20*E20 -> -3569932.5
A21: =1+A20 -> 11 | B21: TYLER | C21: 4463369.3 | D21: 0 | E21: =+C21-D21 -> 4463369.3 | F21: -77.477327 | G21: =+F21*E21 -> -3.4580992e+08
A22: =1+A21 -> 12 | B22: KILLEEN | C22: 4096475.5 | D22: 0 | E22: =+C22-D22 -> 4096475.5 | F22: -46.40068 | G22: =+F22*E22 -> -1.9007925e+08
A23: =1+A22 -> 13 | B23: ODESSA | C23: 3987403.6 | D23: 3977198.4 | E23: =+C23-D23 -> 10205.21 | F23: -380.37282 | G23: =+F23*E23 -> -3881784.5
... A35: =1+A34 -> 25 | B35: FARMERS BRANCH | C35: 2125371.2 | D35: 2119370.9 | E35: =+C35-D35 -> 6000.3 | F35: -326.23444 | G35: =+F35*E35 -> -1957504.5
A36: =1+A35 -> 26
A37: =1+A36 -> 27 | C37: =SUM(C11:C36) -> 1.9202671e+08 | D37: =SUM(D11:D36) -> 1.2731609e+08 | E37: =SUM(E11:E36) -> 64710616 | F37: =ROUND(G37/E37,2) -> -54.99 | G37: =SUM(G11:G36) -> -3.5581381e+09
A38: =1+A37 -> 28
A39: =1+A38 -> 29
A40: =1+A39 -> 30
A41: =1+A40 -> 31
A42: =1+A41 -> 32 | B42: * Twenty five largest tax payments were used. Top Twenty five = 69% of payments for local gross receipts
A43: =1+A42 -> 33
A44: =1+A43 -> 34 | B44: Discretionary Charges are all paid from account 236.2415 and were paid by check.
A45: =1+A44 -> 35 | B45: Local Gross Receipt Taxes are either prepaid from account 165.9000 or in arrears from Account 236.2410
A46: =1+A45 -> 36
A47: =1+A46 -> 37 | B47: Source: | C47: Taxes other than income - Local Gross Receipts.xlsx
A48: =1+A47 -> 38
A49: =1+A48 -> 39
A50: =1+A49 -> 40
A51: =1+A50 -> 41
A52: =1+A51 -> 42
A53: =1+A52 -> 43

Sheet 11
A1: 2022 RATE CASE
A2: =' '!A2 -> ONCOR ELECTRIC DELIVERY COMPANY LLC
A3: AD VALOREM TAXES
A4: FOR THE LEAD-LAG STUDY-PERIOD ENDING SEPTEMBER 30, 2021
A5: SPONSOR: A. THENMADATHIL
A7: Line | H7: Weighted
A8: No. | B8: County | C8: Collector | D8: Payment | E8: Mid-Year | F8: Check Cleared | G8: Lag/Lead | H8: Dollar Days
B9: (a) | C9: (b) | D9: (c) | E9: (d) | F9: (e) | G9: (f) | H9: (g)
A11: 1 | B11: Dallas | C11: DALLAS COUNTY TAX OFFICE | D11: 44557245 | E11: =DATE(2020,1,1)+(Year/2) -> 44013.5 | F11: 44228 | G11: =-F11+E11 -> -214.5 | H11: =D11*G11 -> -9.557529e+09
A12: =A11+1 -> 2 | B12: Tarrant | C12: TARRANT COUNTY | D12: 34609267 | E12: =DATE(2020,1,1)+(Year/2) -> 44013.5 | F12: 44228 | G12: =-F12+E12 -> -214.5 | H12: =D12*G12 -> -7.4236877e+09
A13: =A12+1 -> 3 | B13: Collin | C13: COLLIN COUNTY | D13: 12893924 | E13: =DATE(2020,1,1)+(Year/2) -> 44013.5 | F13: 44228 | G13: =-F13+E13 -> -214.5 | H13: =D13*G13 -> -2.7657466e+09
A14: =A13+1 -> 4 | B14: Bell | C14: BELL COUNTY TAX APPRAISAL DIST | D14: 7116025 | E14: =DATE(2020,1,1)+(Year/2) -> 44013.5 | F14: 44148 | G14: =-F14+E14 -> -134.5 | H14: =D14*G14 -> -9.5710536e+08
A15: =A14+1 -> 5 | B15: Denton | C15: MICHELLE FRENCH, TAX A/C | D15: 6397614.3 | E15: =DATE(2020,1,1)+(Year/2) -> 44013.5 | F15: 44228 | G15: =-F15+E15 -> -214.5 | H15: =D15*G15 -> -1.3722883e+09
A16: =A15+1 -> 6 | B16: Midland | C16: MIDLAND CAD | D16: 5786471.9 | E16: =DATE(2020,1,1)+(Year/2) -> 44013.5 | F16: 44228 | G16: =-F16+E16 -> -214.5 | H16: =D16*G16 -> -1.2411982e+09
A17: =A16+1 -> 7 | B17: Ector | C17: ECTOR CAD | D17: 5368565.6 | E17: =DATE(2020,1,1)+(Year/2) -> 44013.5 | F17: 44228 | G17: =-F17+E17 -> -214.5 | H17: =D17*G17 -> -1.1515573e+09
A18: =A17+1 -> 8 | B18: Mclennan | C18: MCLENNAN COUNTY | D18: 4719087.2 | E18: =DATE(2020,1,1)+(Year/2) -> 44013.5 | F18: 44228 | G18: =-F18+E18 -> -214.5 | H18: =D18*G18 -> -1.0122442e+09
A19: =A18+1 -> 9 | B19: Williamson | C19: WILLIAMSON COUNTY | D19: 4649555.7 | E19: =DATE(2020,1,1)+(Year/2) -> 44013.5 | F19: 44228 | G19: =-F19+E19 -> -214.5 | H19: =D19*G19 -> -9.973297e+08
A20: =A19+1 -> 10 | B20: Smith | C20: SMITH COUNTY TAX OFFICE | D20: 4364342.5 | E20: =DATE(2020,1,1)+(Year/2) -> 44013.5 | F20: 44228 | G20: =-F20+E20 -> -214.5 | H20: =D20*G20 -> -9.3615146e+08
A21: =A20+1 -> 11 | B21: Ellis | C21: ELLIS COUNTY | D21: 3762111.4 | E21: =DATE(2020,1,1)+(Year/2) -> 44013.5 | F21: 44228 | G21: =-F21+E21 -> -214.5 | H21: =D21*G21 -> -8.069729e+08
A22: =A21+1 -> 12 | B22: Grayson | C22: GRAYSON COUNTY | D22: 3008732.4 | E22: =DATE(2020,1,1)+(Year/2) -> 44013.5 | F22: 44228 | G22: =-F22+E22 -> -214.5 | H22: =D22*G22 -> -6.4537311e+08
A23: =A22+1 -> 13 | B23: Wichita | C23: WICHITA COUNTY | D23: 2924333.7 | E23: =DATE(2020,1,1)+(Year/2) -> 44013.5 | F23: 44228 | G23: =-F23+E23 -> -214.5 | H23: =D23*G23 -> -6.2726957e+08
... A35: =A34+1 -> 25 | B35: Brown | C35: BROWN CAD | D35: 2053361 | E35: =DATE(2020,1,1)+(Year/2) -> 44013.5 | F35: 44228 | G35: =-F35+E35 -> -214.5 | H35: =D35*G35 -> -4.4044593e+08
A36: =A35+1 -> 26
A37: =A36+1 -> 27 | B37: Total | D37: =SUM(D11:D35) -> 1.6762986e+08 | G37: =ROUND(H37/D37,2) -> -209.9 | H37: =SUM(H11:H35) -> -3.5184979e+10
A38: =A37+1 -> 28
A39: =A38+1 -> 29 | B39: Note: Top 25 payments to collectors represent approximately 68% of total payments.
A40: =A39+1 -> 30
A41: =A40+1 -> 31 | B41: Source: | C41: Tax other than income - Ad Valorem.xlsx

Sheet 12
A1: 2022 RATE CASE
A2: =' '!A2 -> ONCOR ELECTRIC DELIVERY COMPANY LLC
A3: AVERAGE DAILY BANK BALANCES
A4: FOR THE TEST-YEAR ENDING DECEMBER 31, 2021
A5: SPONSOR: A. THENMADATHIL
C7: Depository Bank Accounts
C8: JPMorgan Chase Bank | D8: BNY Mellon | E8: JPMorgan Chase Bank | F8: JPMorgan Chase Bank
A9: Line No. | B9: Month/Year | C9: Miscellaneous Rcpts Acct | D9: Rep Receipt Account | E9: Cash Concentration Acct | F9: Payroll Account | H9: Total of Daily Balances
B10: (a) | C10: (b) | D10: (c) | E10: (d) | F10: ( e ) | H10: (f)
A12: 1 | B12: 44225 | C12: 33534062 | D12: 1.4715902e+08 | E12: 32548900 | F12: 1005901.6 | H12: =SUM(C12:G12) -> 2.1424788e+08
A13: =A12+1 -> 2 | B13: 44253 | C13: 15467719 | D13: 1.5931461e+08 | E13: 17540639 | F13: 1823703.8 | H13: =SUM(C13:G13) -> 1.9414667e+08
A14: =A13+1 -> 3 | B14: 44286 | C14: 15144318 | D14: 1.5042289e+08 | E14: 20304489 | F14: 20308637 | H14: =SUM(C14:G14) -> 2.0618033e+08
A15: =A14+1 -> 4 | B15: 44316 | C15: 21115024 | D15: 1.4134469e+08 | E15: 77786259 | F15: 3743430.9 | H15: =SUM(C15:G15) -> 2.4398941e+08
A16: =A15+1 -> 5 | B16: 44344 | C16: 17542557 | D16: 1.2046158e+08 | E16: 10583653 | F16: 3217413.7 | H16: =SUM(C16:G16) -> 1.518052e+08
A17: =A16+1 -> 6 | B17: 44377 | C17: 26779331 | D17: 1.1650138e+08 | E17: 10774557 | F17: 2739378.6 | H17: =SUM(C17:G17) -> 1.5679464e+08
A18: =A17+1 -> 7 | B18: 44407 | C18: 20668951 | D18: 136167655 | E18: 21079340 | F18: 3268224.9 | H18: =SUM(C18:G18) -> 1.8118417e+08
A19: =A18+1 -> 8 | B19: 44439 | C19: 36098289 | D19: 1.625558e+08 | E19: 3977594.5 | F19: 3327274.9 | H19: =SUM(C19:G19) -> 2.0595896e+08
A20: =A19+1 -> 9 | B20: 44469 | C20: 53897691 | D20: 1.8250089e+08 | E20: 17995667 | F20: 10136287 | H20: =SUM(C20:G20) -> 2.6453054e+08
A21: =A20+1 -> 10 | B21: 44498 | C21: 39201225 | D21: 1.6855496e+08 | E21: 12689525 | F21: 14456386 | H21: =SUM(C21:G21) -> 2.349021e+08
A22: =A21+1 -> 11 | B22: 44530 | C22: 14768017 | D22: 1.7826088e+08 | E22: 14077177 | F22: 12958005 | H22: =SUM(C22:G22) -> 2.2006408e+08
A23: =A22+1 -> 12 | B23: 44561 | C23: 27068781 | D23: 1.211441e+08 | E23: 6.403469e+08 | F23: 13354555 | H23: =SUM(C23:G23) -> 8.0191433e+08
A24: =A23+1 -> 13 | H24: =SUM(H12:H23) -> 3.0757183e+09
A25: =A24+1 -> 14
A26: =A25+1 -> 15 | B26: Avg Bank Bal - Col (f) Ln 13 divided by | D26: 365.25 | H26: =ROUND(H24/365.25,0) -> 8420858
A27: =A26+1 -> 16
A28: =A27+1 -> 17
A29: =A28+1 -> 18 | B29: Source: | C29: Bank balances 12.31.21.xlsx

Sheet 13
A1: 2022 RATE CASE
A2: =' '!A2 -> ONCOR ELECTRIC DELIVERY COMPANY LLC
A3: WORKING FUNDS AND OTHER
A4: FOR THE LEAD-LAG STUDY-PERIOD ENDING SEPTEMBER 30, 2021
A5: SPONSOR: A. THENMADATHIL
A7: Line No. | B7: Description | C7: Amount | D7: Reference
B8: (a) | C8: (b) | D8: (c)
A10: 1 | B10: Payroll Withholdings | C10: ='13-1'!C14 -> -895405 | D10: WP/II-B-9/13-1
A11: 2 | B11: Misc. Working Funds | C11: ='13-2'!C14 -> 0 | D11: WP/II-B-9/13-2
A12: 3 | B12: Misc. Deferred Debits & Credits | C12: ='13-3'!D14 -> -8278904 | D12: WP/II-B-9/13-3
A13: 4 | B13: Home Purchase Plan | C13: ='13-4'!J26 -> 325376 | D13: WP/II-B-9/13-4
A14: 5 | B14: Other Accounts Receivables | C14: ='13-5'!C12 -> 540621 | D14: WP/II-B-9/13-5
A15: 6
A16: 7 | B16: Misc. Funds | C16: =ROUND(SUM(C10:C15),0) -> -8308312

Sheet 13-1
A1: 2022 RATE CASE
A2: =' '!A2 -> ONCOR ELECTRIC DELIVERY COMPANY LLC
A3: PAYROLL WITHHOLDING BALANCES
A4: FOR THE LEAD-LAG STUDY-PERIOD ENDING SEPTEMBER 30, 2021
A5: SPONSOR: A. THENMADATHIL
A7: Line No. | B7: Description | C7: Total | D7: Reference
B8: (a) | C8: (b) | D8: (c)
A10: 1 | B10: FICA Taxes | C10: ='13-1-2'!E100+'13-1-1'!E56 -> 0 | D10: WP/II-B-9/13-1-1 AND WP/II-B-9/13-1-2
A11: 2 | B11: Federal Income Tax Withholding | C11: ='13-1-3'!E58+'13-1-4'!E96 -> 0 | D11: WP/II-B-9/13-1-3 AND WP/II-B-9/13-1-4
A12: 3 | B12: Thrift Plan Withholding | C12: ='13-1-5'!E44+'13-1-6'!E70 -> -895405 | D12: WP/II-B-9/13-1-5 AND WP/II-B-9/13-1-6
A13: 4
A14: 5 | B14: Total Payroll Withholding | C14: =SUM(C10:C12) -> -895405

Sheet 13-1-1
A1: 2022 RATE CASE
A2: =' '!A2 -> ONCOR ELECTRIC DELIVERY COMPANY LLC
A3: PAYROLL WITHHOLDING - TRANSMISSION
A4: FOR THE LEAD-LAG STUDY-PERIOD ENDING SEPTEMBER 30, 2021
A5: SPONSOR: A. THENMADATHIL
A7: Line No. | B7: Payroll Check Date | C7: FICA Amount | D7: Deposit Date | E7: (Lead)/Lag Days | F7: Weighted Dollar Days
B8: (a) | C8: (b) | D8: (c) | E8: (d) | F8: (e)
A10: 1 | B10: 44118 | C10: 368030.2 | D10: 44118 | E10: =IF(C10=0,0,-(D10-B10)) -> 0 | F10: =C10*E10 -> 0
A11: =A10+1 -> 2 | B11: 44133 | C11: 388440.19 | D11: 44133 | E11: =IF(C11=0,0,-(D11-B11)) -> 0 | F11: =C11*E11 -> 0
A12: =A11+1 -> 3 | B12: 44147 | C12: 351915.29 | D12: 44147 | E12: =IF(C12=0,0,-(D12-B12)) -> 0 | F12: =C12*E12 -> 0
A13: =A12+1 -> 4 | B13: 44160 | C13: 317449.57 | D13: 44160 | E13: =IF(C13=0,0,-(D13-B13)) -> 0 | F13: =C13*E13 -> 0
A14: =A13+1 -> 5 | B14: 44179 | C14: 351211.04 | D14: 44179 | E14: =IF(C14=0,0,-(D14-B14)) -> 0 | F14: =C14*E14 -> 0
A15: =A14+1 -> 6 | B15: 44189 | C15: 217.78 | D15: 44189 | E15: =IF(C15=0,0,-(D15-B15)) -> 0 | F15: =C15*E15 -> 0
A16: =A15+1 -> 7 | B16: 44195 | C16: 317531.06 | D16: 44195 | E16: =IF(C16=0,0,-(D16-B16)) -> 0 | F16: =C16*E16 -> 0
A17: =A16+1 -> 8 | B17: 44210 | C17: 360210.61 | D17: 44210 | E17: =IF(C17=0,0,-(D17-B17)) -> 0 | F17: =C17*E17 -> 0
A18: =A17+1 -> 9 | B18: 44223 | C18: 1266.04 | D18: 44223 | E18: =IF(C18=0,0,-(D18-B18)) -> 0 | F18: =C18*E18 -> 0
A19: =A18+1 -> 10 | B19: 44224 | C19: 358754.24 | D19: 44224 | E19: =IF(C19=0,0,-(D19-B19)) -> 0 | F19: =C19*E19 -> 0
A20: =A19+1 -> 11 | B20: 44238 | C20: 355074.32 | D20: 44238 | E20: =IF(C20=0,0,-(D20-B20)) -> 0 | F20: =C20*E20 -> 0
A21: =A20+1 -> 12 | B21: 44243 | C21: 37302.42 | D21: 44243 | E21: =IF(C21=0,0,-(D21-B21)) -> 0 | F21: =C21*E21 -> 0
A22: =A21+1 -> 13 | B22: 44244 | C22: 174.69 | D22: 44244 | E22: =IF(C22=0,0,-(D22-B22)) -> 0 | F22: =C22*E22 -> 0
... A48: =A47+1 -> 39 | B48: 44468 | C48: 367692.4 | D48: 44468 | E48: =IF(C48=0,0,-(D48-B48)) -> 0 | F48: =C48*E48 -> 0
A49: =A48+1 -> 40
A50: =A49+1 -> 41 | B50: Total | C50: =SUM(C10:C49) -> 10262556 | E50: =ROUND(F50/C50,2) -> 0 | F50: =SUM(F10:F49) -> 0
A51: =A50+1 -> 42
A52: =A51+1 -> 43 | B52: Average Daily Amount (Col (b) Ln 41 divided by 365.25): | E52: =+ROUND(C50/365.25,0) -> 28097
A53: =A52+1 -> 44
A54: =A53+1 -> 45 | B54: (Lead)/Lag Days Total (Col (d) Ln 41) | E54: =+E50 -> 0
A55: =A54+1 -> 46
A56: =A55+1 -> 47 | B56: Total Withholding (Col (d) Ln 43 times Ln 45) | E56: =+ROUND(E52*E54,0) -> 0
A57: =A56+1 -> 48
A58: =A57+1 -> 49 | B58: Source: | C58: Taxes Other Than Income - Payroll Taxes.xlsx

Sheet 13-1-2
A1: 2022 RATE CASE
A2: =' '!A2 -> ONCOR ELECTRIC DELIVERY COMPANY LLC
A3: PAYROLL WITHHOLDING - DISTRIBUTION
A4: FOR THE LEAD-LAG STUDY-PERIOD ENDING SEPTEMBER 30, 2021
A5: SPONSOR: A. THENMADATHIL
A7: Line No. | B7: Payroll Check Date | C7: FICA Amount | D7: Deposit Date | E7: (Lead)/Lag Days | F7: Weighted Dollar Days
B8: (a) | C8: (b) | D8: (c) | E8: (d) | F8: (e)
A10: 1 | B10: 44112 | C10: 222085.65 | D10: 44112 | E10: =IF(C10=0,0,-(D10-B10)) -> 0 | F10: =C10*E10 -> 0
A11: 2 | B11: 44117 | C11: 643.02 | D11: 44117 | E11: =IF(C11=0,0,-(D11-B11)) -> 0 | F11: =C11*E11 -> 0
A12: 3 | B12: 44126 | C12: 216102.75 | D12: 44126 | E12: =IF(C12=0,0,-(D12-B12)) -> 0 | F12: =C12*E12 -> 0
A13: 4 | B13: 44118 | C13: 756203.93 | D13: 44118 | E13: =IF(C13=0,0,-(D13-B13)) -> 0 | F13: =C13*E13 -> 0
A14: 5 | B14: 44125 | C14: 909.42 | D14: 44125 | E14: =IF(C14=0,0,-(D14-B14)) -> 0 | F14: =C14*E14 -> 0
A15: 6 | B15: 44133 | C15: 716368.46 | D15: 44133 | E15: =IF(C15=0,0,-(D15-B15)) -> 0 | F15: =C15*E15 -> 0
A16: 7 | B16: 44140 | C16: 229264.45 | D16: 44140 | E16: =IF(C16=0,0,-(D16-B16)) -> 0 | F16: =C16*E16 -> 0
A17: 8 | B17: 44147 | C17: 711168.97 | D17: 44147 | E17: =IF(C17=0,0,-(D17-B17)) -> 0 | F17: =C17*E17 -> 0
A18: 9 | B18: 44153 | C18: 1455.1 | D18: 44153 | E18: =IF(C18=0,0,-(D18-B18)) -> 0 | F18: =C18*E18 -> 0
A19: 10 | B19: 44154 | C19: 195329.35 | D19: 44154 | E19: =IF(C19=0,0,-(D19-B19)) -> 0 | F19: =C19*E19 -> 0
A20: 11 | B20: 44160 | C20: 652898.23 | D20: 44160 | E20: =IF(C20=0,0,-(D20-B20)) -> 0 | F20: =C20*E20 -> 0
A21: 12 | B21: 44168 | C21: 193569.67 | D21: 44168 | E21: =IF(C21=0,0,-(D21-B21)) -> 0 | F21: =C21*E21 -> 0
... A79: 70 | B79: 44393 | C79: 4833.82 | D79: 44393 | E79: =IF(C79=0,0,-(D79-B79)) -> 0 | F79: =C79*E79 -> 0
A80: =A79+1 -> 71 | B80: 44400 | C80: 456.99 | D80: 44400 | E80: =IF(C80=0,0,-(D80-B80)) -> 0 | F80: =C80*E80 -> 0
A81: 72 | B81: 44406 | C81: 1137824.2 | D81: 44406 | E81: =IF(C81=0,0,-(D81-B81)) -> 0 | F81: =C81*E81 -> 0
A82: =A81+1 -> 73 | B82: 44407 | C82: 345.54 | D82: 44407 | E82: =IF(C82=0,0,-(D82-B82)) -> 0 | F82: =C82*E82 -> 0
A83: =A82+1 -> 74 | B83: 44420 | C83: 1117493.8 | D83: 44420 | E83: =IF(C83=0,0,-(D83-B83)) -> 0 | F83: =C83*E83 -> 0
A84: =A83+1 -> 75 | B84: 44427 | C84: 945.95 | D84: 44427 | E84: =IF(C84=0,0,-(D84-B84)) -> 0 | F84: =C84*E84 -> 0
A85: =A84+1 -> 76 | B85: 44434 | C85: 286288.54 | D85: 44434 | E85: =IF(C85=0,0,-(D85-B85)) -> 0 | F85: =C85*E85 -> 0
A86: =A85+1 -> 77 | B86: 44438 | C86: 943373.93 | D86: 44438 | E86: =IF(C86=0,0,-(D86-B86)) -> 0 | F86: =C86*E86 -> 0
A87: =A86+1 -> 78 | B87: 44447 | C87: 900.09 | D87: 44447 | E87: =IF(C87=0,0,-(D87-B87)) -> 0 | F87: =C87*E87 -> 0
A88: =A87+1 -> 79 | B88: 44448 | C88: 252404.24 | D88: 44448 | E88: =IF(C88=0,0,-(D88-B88)) -> 0 | F88: =C88*E88 -> 0
A89: =A88+1 -> 80 | B89: 44453 | C89: 783706.33 | D89: 44453 | E89: =IF(C89=0,0,-(D89-B89)) -> 0 | F89: =C89*E89 -> 0
A90: =A89+1 -> 81 | B90: 44459 | C90: 3298.99 | D90: 44459 | E90: =IF(C90=0,0,-(D90-B90)) -> 0 | F90: =C90*E90 -> 0
A91: =A90+1 -> 82 | B91: 44462 | C91: 248244.43 | D91: 44462 | E91: =IF(C91=0,0,-(D91-B91)) -> 0 | F91: =C91*E91 -> 0
A92: =A91+1 -> 83 | B92: 44468 | C92: 755176.99 | D92: 44468 | E92: =IF(C92=0,0,-(D92-B92)) -> 0 | F92: =C92*E92 -> 0
A93: =A92+1 -> 84
A94: =A93+1 -> 85 | B94: Total | C94: =SUM(C10:C92) -> 30638560 | E94: =ROUND(F94/C94,2) -> 0 | F94: =SUM(F10:F92) -> 0
A95: =A94+1 -> 86
A96: =A95+1 -> 87 | B96: Average Daily Amount (Col (b) Ln 85 divided by 365.25): | E96: =+ROUND(C94/365.25,0) -> 83884
A97: =A96+1 -> 88
A98: =A97+1 -> 89 | B98: (Lead)/Lag Days Total (Col (d) Ln 85) | E98: =+E94 -> 0
A99: =A98+1 -> 90
A100: =A99+1 -> 91 | B100: Total Withholding (Col (d) Ln 87 times Ln 89) | E100: =+ROUND(E96*E98,0) -> 0
A101: =A100+1 -> 92
A102: =A101+1 -> 93 | B102: Source: | C102: Taxes Other Than Income - Payroll Taxes.xlsx

Sheet 13-1-3
A1: 2022 RATE CASE
A2: =' '!A2 -> ONCOR ELECTRIC DELIVERY COMPANY LLC
A3: FEDERAL INCOME TAX WITHHOLDING - TRANSMISSION
A4: FOR THE LEAD-LAG STUDY-PERIOD ENDING SEPTEMBER 30, 2021
A5: SPONSOR: A. THENMADATHIL
A7: Line No. | B7: Payroll Check Date | C7: FIT Withholding Amount | D7: Deposit Date | E7: (Lead)/Lag Days | F7: Weighted Dollar Days
B8: (a) | C8: (b) | D8: (c) | E8: (d) | F8: (e)
A10: 1 | B10: 44118 | C10: 712116.18 | D10: 44118 | E10: =IF(C10=0,0,-(D10-B10)) -> 0 | F10: =C10*E10 -> 0
A11: 2 | B11: 44125 | C11: 20620.84 | D11: 44125 | E11: =IF(C11=0,0,-(D11-B11)) -> 0 | F11: =C11*E11 -> 0
A12: 3 | B12: 44133 | C12: 823393.21 | D12: 44133 | E12: =IF(C12=0,0,-(D12-B12)) -> 0 | F12: =C12*E12 -> 0
A13: 4 | B13: 44147 | C13: 726834.55 | D13: 44147 | E13: =IF(C13=0,0,-(D13-B13)) -> 0 | F13: =C13*E13 -> 0
A14: 5 | B14: 44160 | C14: 632066.09 | D14: 44160 | E14: =IF(C14=0,0,-(D14-B14)) -> 0 | F14: =C14*E14 -> 0
A15: 6 | B15: 44179 | C15: 838098.15 | D15: 44179 | E15: =IF(C15=0,0,-(D15-B15)) -> 0 | F15: =C15*E15 -> 0
A16: 7 | B16: 44189 | C16: 626.31 | D16: 44189 | E16: =IF(C16=0,0,-(D16-B16)) -> 0 | F16: =C16*E16 -> 0
A17: 8 | B17: 44195 | C17: 763491.4 | D17: 44195 | E17: =IF(C17=0,0,-(D17-B17)) -> 0 | F17: =C17*E17 -> 0
A18: 9 | B18: 44207 | C18: 9017.21 | D18: 44207 | E18: =IF(C18=0,0,-(D18-B18)) -> 0 | F18: =C18*E18 -> 0
A19: 10 | B19: 44210 | C19: 566620.19 | D19: 44210 | E19: =IF(C19=0,0,-(D19-B19)) -> 0 | F19: =C19*E19 -> 0
A20: 11 | B20: 44223 | C20: 3641 | D20: 44223 | E20: =IF(C20=0,0,-(D20-B20)) -> 0 | F20: =C20*E20 -> 0
A21: 12 | B21: 44224 | C21: 561676.46 | D21: 44224 | E21: =IF(C21=0,0,-(D21-B21)) -> 0 | F21: =C21*E21 -> 0
... A36: 27 | B36: 44315 | C36: 683197.3 | D36: 44315 | E36: =IF(C36=0,0,-(D36-B36)) -> 0 | F36: =C36*E36 -> 0
A37: =A36+1 -> 28 | B37: 44327 | C37: 5078.53 | D37: 44327 | E37: =IF(C37=0,0,-(D37-B37)) -> 0 | F37: =C37*E37 -> 0
A38: =A37+1 -> 29 | B38: 44329 | C38: 698667.56 | D38: 44329 | E38: =IF(C38=0,0,-(D38-B38)) -> 0 | F38: =C38*E38 -> 0
A39: =A38+1 -> 30 | B39: 44336 | C39: 46853.7 | D39: 44336 | E39: =IF(C39=0,0,-(D39-B39)) -> 0 | F39: =C39*E39 -> 0
A40: =A39+1 -> 31 | B40: 44340 | C40: 1758.83 | D40: 44340 | E40: =IF(C40=0,0,-(D40-B40)) -> 0 | F40: =C40*E40 -> 0
A41: =A40+1 -> 32 | B41: 44343 | C41: 728229.92 | D41: 44343 | E41: =IF(C41=0,0,-(D41-B41)) -> 0 | F41: =C41*E41 -> 0
A42: =A41+1 -> 33 | B42: 44361 | C42: 723291.17 | D42: 44361 | E42: =IF(C42=0,0,-(D42-B42)) -> 0 | F42: =C42*E42 -> 0
A43: =A42+1 -> 34 | B43: 44376 | C43: 679533.81 | D43: 44376 | E43: =IF(C43=0,0,-(D43-B43)) -> 0 | F43: =C43*E43 -> 0
A44: =A43+1 -> 35 | B44: 44384 | C44: 132 | D44: 44384 | E44: =IF(C44=0,0,-(D44-B44)) -> 0 | F44: =C44*E44 -> 0
A45: =A44+1 -> 36 | B45: 44391 | C45: 654316.39 | D45: 44391 | E45: =IF(C45=0,0,-(D45-B45)) -> 0 | F45: =C45*E45 -> 0
A46: =A45+1 -> 37 | B46: 44406 | C46: 630597.04 | D46: 44406 | E46: =IF(C46=0,0,-(D46-B46)) -> 0 | F46: =C46*E46 -> 0
A47: =A46+1 -> 38 | B47: 44420 | C47: 645881.17 | D47: 44420 | E47: =IF(C47=0,0,-(D47-B47)) -> 0 | F47: =C47*E47 -> 0
A48: =A47+1 -> 39 | B48: 44438 | C48: 680293.88 | D48: 44438 | E48: =IF(C48=0,0,-(D48-B48)) -> 0 | F48: =C48*E48 -> 0
... A50: =A49+1 -> 41 | B50: 44468 | C50: 683272.59 | D50: 44468 | E50: =IF(C50=0,0,-(D50-B50)) -> 0 | F50: =C50*E50 -> 0
A51: =A50+1 -> 42
A52: =A51+1 -> 43 | B52: Total | C52: =SUM(C10:C50) -> 20002231 | E52: =ROUND(F52/C52,2) -> 0 | F52: =SUM(F10:F50) -> 0
A53: =A52+1 -> 44
A54: =A53+1 -> 45 | B54: Average Daily Amount (Col (b) Ln 43 divided by 365.25) | E54: =+ROUND(C52/365.25,0) -> 54763
A55: =A54+1 -> 46
A56: =A55+1 -> 47 | B56: (Lead)/Lag Days Total (Col (d) Ln 43) | E56: =+E52 -> 0
A57: =A56+1 -> 48
A58: =A57+1 -> 49 | B58: Total Withholding (Col (d) Ln 45 times Ln 47) | E58: =+ROUND(E54*E56,0) -> 0
A59: =A58+1 -> 50
A60: =A59+1 -> 51 | B60: Source: | C60: Taxes Other Than Income - Payroll Taxes.xlsx

Sheet 13-1-4
A1: 2022 RATE CASE
A2: =' '!A2 -> ONCOR ELECTRIC DELIVERY COMPANY LLC
A3: FEDERAL INCOME TAX WITHHOLDING - DISTRIBUTION
A4: FOR THE LEAD-LAG STUDY-PERIOD ENDING SEPTEMBER 30, 2021
A5: SPONSOR: A. THENMADATHIL
A7: Line No. | B7: Payroll Check Date | C7: FIT Withholding Amount | D7: Deposit Date | E7: (Lead)/Lag Days | F7: Weighted Dollar Days
B8: (a) | C8: (b) | D8: (c) | E8: (d) | F8: (e)
A10: 1 | B10: 44112 | C10: 411204.95 | D10: 44112 | E10: =IF(C10=0,0,-(D10-B10)) -> 0 | F10: =C10*E10 -> 0
A11: 2 | B11: 44126 | C11: 409089.54 | D11: 44126 | E11: =IF(C11=0,0,-(D11-B11)) -> 0 | F11: =C11*E11 -> 0
A12: 3 | B12: 44118 | C12: 1455023.1 | D12: 44118 | E12: =IF(C12=0,0,-(D12-B12)) -> 0 | F12: =C12*E12 -> 0
A13: 4 | B13: 44125 | C13: 12952.07 | D13: 44125 | E13: =IF(C13=0,0,-(D13-B13)) -> 0 | F13: =C13*E13 -> 0
A14: 5 | B14: 44132 | C14: 10501.34 | D14: 44132 | E14: =IF(C14=0,0,-(D14-B14)) -> 0 | F14: =C14*E14 -> 0
A15: 6 | B15: 44133 | C15: 1390472.6 | D15: 44133 | E15: =IF(C15=0,0,-(D15-B15)) -> 0 | F15: =C15*E15 -> 0
A16: 7 | B16: 44140 | C16: 494060.35 | D16: 44140 | E16: =IF(C16=0,0,-(D16-B16)) -> 0 | F16: =C16*E16 -> 0
A17: 8 | B17: 44147 | C17: 1496991.2 | D17: 44147 | E17: =IF(C17=0,0,-(D17-B17)) -> 0 | F17: =C17*E17 -> 0
A18: 9 | B18: 44153 | C18: 66 | D18: 44153 | E18: =IF(C18=0,0,-(D18-B18)) -> 0 | F18: =C18*E18 -> 0
A19: 10 | B19: 44154 | C19: 406636.39 | D19: 44154 | E19: =IF(C19=0,0,-(D19-B19)) -> 0 | F19: =C19*E19 -> 0
A20: 11 | B20: 44160 | C20: 1352817 | D20: 44160 | E20: =IF(C20=0,0,-(D20-B20)) -> 0 | F20: =C20*E20 -> 0
A21: 12 | B21: 44168 | C21: 455611.42 | D21: 44168 | E21: =IF(C21=0,0,-(D21-B21)) -> 0 | F21: =C21*E21 -> 0
... A80: 71 | B80: 44427 | C80: 132 | D80: 44427 | E80: =IF(C80=0,0,-(D80-B80)) -> 0 | F80: =C80*E80 -> 0
A81: =A80+1 -> 72 | B81: 44434 | C81: 567363.92 | D81: 44434 | E81: =IF(C81=0,0,-(D81-B81)) -> 0 | F81: =C81*E81 -> 0
A82: =A81+1 -> 73 | B82: 44438 | C82: 1590257.6 | D82: 44438 | E82: =IF(C82=0,0,-(D82-B82)) -> 0 | F82: =C82*E82 -> 0
A83: =A82+1 -> 74 | B83: 44447 | C83: 49557.63 | D83: 44447 | E83: =IF(C83=0,0,-(D83-B83)) -> 0 | F83: =C83*E83 -> 0
A84: =A83+1 -> 75 | B84: 44448 | C84: 471186.77 | D84: 44448 | E84: =IF(C84=0,0,-(D84-B84)) -> 0 | F84: =C84*E84 -> 0
A85: =A84+1 -> 76 | B85: 44453 | C85: 1464783.4 | D85: 44453 | E85: =IF(C85=0,0,-(D85-B85)) -> 0 | F85: =C85*E85 -> 0
A86: =A85+1 -> 77 | B86: 44459 | C86: 63257.64 | D86: 44459 | E86: =IF(C86=0,0,-(D86-B86)) -> 0 | F86: =C86*E86 -> 0
A87: =A86+1 -> 78 | B87: 44462 | C87: 483419 | D87: 44462 | E87: =IF(C87=0,0,-(D87-B87)) -> 0 | F87: =C87*E87 -> 0
A88: =A87+1 -> 79 | B88: 44468 | C88: 1468787 | D88: 44468 | E88: =IF(C88=0,0,-(D88-B88)) -> 0 | F88: =C88*E88 -> 0
A89: =A88+1 -> 80
A90: =A89+1 -> 81 | B90: Total | C90: =SUM(C10:C89) -> 65139651 | E90: =ROUND(F90/C90,2) -> 0 | F90: =SUM(F10:F89) -> 0
A91: =A90+1 -> 82
A92: =A91+1 -> 83 | B92: Average Daily Amount (Col (b) Ln 81 divided by 365.25) | E92: =+ROUND(C90/365.25,0) -> 178343
A93: =A92+1 -> 84
A94: =A93+1 -> 85 | B94: (Lead)/Lag Days Total (Col (d) Ln 81) | E94: =+E90 -> 0
A95: =A94+1 -> 86
A96: =A95+1 -> 87 | B96: Total Withholding (Col (d) Ln 83 times Ln 85) | E96: =+ROUND(E92*E94,0) -> 0
A97: =A96+1 -> 88
A98: =A97+1 -> 89 | B98: Source: | C98: Taxes Other Than Income - Payroll Taxes.xlsx

Sheet 13-1-5
A1: 2022 RATE CASE
A2: =' '!A2 -> ONCOR ELECTRIC DELIVERY COMPANY LLC
A3: THRIFT PLAN WITHHOLDING - TRANSMISSION
A4: FOR THE LEAD-LAG STUDY-PERIOD ENDING SEPTEMBER 30, 2021
A5: SPONSOR: A. THENMADATHIL
A7: Line No. | B7: Payroll Period Check Date | C7: Withholding Amount | D7: Deposit Date | E7: (Lead)/Lag Days | F7: Weighted Dollar Days
B8: (a) | C8: (b) | D8: (c) | E8: (d) | F8: (e)
A10: 1 | B10: 2020-10-15 | C10: 429672.95 | D10: 44126 | E10: =-D10+B10 -> -7 | F10: =E10*C10 -> -3007710.6
A11: 2 | B11: 2020-10-30 | C11: 432010.54 | D11: 44141 | E11: =-D11+B11 -> -7 | F11: =E11*C11 -> -3024073.8
A12: 3 | B12: 2020-11-13 | C12: 442489.55 | D12: 44155 | E12: =-D12+B12 -> -7 | F12: =E12*C12 -> -3097426.9
A13: 4 | B13: 2020-11-30 | C13: 442077.15 | D13: 44172 | E13: =-D13+B13 -> -7 | F13: =E13*C13 -> -3094540.1
A14: 5 | B14: 2020-12-07 | C14: 150.4 | D14: 44187 | E14: =-D14+B14 -> -15 | F14: =E14*C14 -> -2256
A15: 6 | B15: 2020-12-15 | C15: 468750.56 | D15: 44187 | E15: =-D15+B15 -> -7 | F15: =E15*C15 -> -3281253.9
A16: 7 | B16: 2020-12-31 | C16: 442865.21 | D16: 44204 | E16: =-D16+B16 -> -8 | F16: =E16*C16 -> -3542921.7
A17: 8 | B17: 2021-01-15 | C17: 451411.91 | D17: 44218 | E17: =-D17+B17 -> -7 | F17: =E17*C17 -> -3159883.4
A18: 9 | B18: 2021-01-29 | C18: 453576.92 | D18: 44232 | E18: =-D18+B18 -> -7 | F18: =E18*C18 -> -3175038.4
A19: 10 | B19: 2021-02-12 | C19: 478134.17 | D19: 44249 | E19: =-D19+B19 -> -10 | F19: =E19*C19 -> -4781341.7
A20: 11 | B20: 2021-02-17 | C20: 0.13 | D20: 44249 | E20: =-D20+B20 -> -5 | F20: =E20*C20 -> -0.65
A21: 12 | B21: 2021-02-18 | C21: 345.61 | D21: 44249 | E21: =-D21+B21 -> -4 | F21: =E21*C21 -> -1382.44
... A37: 28 | B37: 2021-09-30 | C37: 493922.71 | D37: 44476 | E37: =-D37+B37 -> -7 | F37: =E37*C37 -> -3457459
A38: 29 | B38: Total | C38: =SUM(C10:C37) -> 11446828 | E38: =ROUND(F38/C38,2) -> -7.16 | F38: =SUM(F10:F37) -> -82007948
A39: 30
A40: 31 | B40: Average Daily Amount (Col (b) Ln 29 divided by 365.25) | E40: =+ROUND(C38/365.25,0) -> 31340
A41: 32
A42: 33 | B42: (Lead)/Lag Days Total (Col (d) Ln 29) | E42: =+E38 -> -7.16
A43: 34
A44: 35 | B44: Total Withholding (Col (d) Ln 31 times Ln 33) | E44: =+ROUND(E40*E42,0) -> -224394
A45: 36
A46: 37 | B46: Source: | C46: Thrift.xlsx

Sheet 13-1-6
A1: 2022 RATE CASE
A2: =' '!A2 -> ONCOR ELECTRIC DELIVERY COMPANY LLC
A3: THRIFT PLAN WITHHOLDING - DISTRIBUTION
A4: FOR THE LEAD-LAG STUDY-PERIOD ENDING SEPTEMBER 30, 2021
A5: SPONSOR: A. THENMADATHIL
A7: Line No. | B7: Payroll Period Check Date | C7: Withholding Amount | D7: Deposit Date | E7: (Lead)/Lag Days | F7: Weighted Dollar Days
B8: (a) | C8: (b) | D8: (c) | E8: (d) | F8: (e)
A10: 1 | B10: 2020-10-09 | C10: 237589.38 | D10: 44120 | E10: =-D10+B10 -> -7 | F10: =E10*C10 -> -1663125.7
A11: =A10+1 -> 2 | B11: 2020-10-15 | C11: 1078070.2 | D11: 44126 | E11: =-D11+B11 -> -7 | F11: =E11*C11 -> -7546491.1
A12: =A11+1 -> 3 | B12: 2020-10-23 | C12: 238870.26 | D12: 44133 | E12: =-D12+B12 -> -6 | F12: =E12*C12 -> -1433221.6
A13: =A12+1 -> 4 | B13: 2020-10-30 | C13: 1075286.4 | D13: 44141 | E13: =-D13+B13 -> -7 | F13: =E13*C13 -> -7527004.5
A14: =A13+1 -> 5 | B14: 2020-11-06 | C14: 247966.36 | D14: 44148 | E14: =-D14+B14 -> -7 | F14: =E14*C14 -> -1735764.5
A15: =A14+1 -> 6 | B15: 2020-11-11 | C15: 87.58 | D15: 44162 | E15: =-D15+B15 -> -16 | F15: =E15*C15 -> -1401.28
A16: =A15+1 -> 7 | B16: 2020-11-13 | C16: 1094738 | D16: 44155 | E16: =-D16+B16 -> -7 | F16: =E16*C16 -> -7663166.2
A17: =A16+1 -> 8 | B17: 2020-11-20 | C17: 245509.07 | D17: 44162 | E17: =-D17+B17 -> -7 | F17: =E17*C17 -> -1718563.5
A18: =A17+1 -> 9 | B18: 2020-11-30 | C18: 1080826.4 | D18: 44172 | E18: =-D18+B18 -> -7 | F18: =E18*C18 -> -7565784.9
A19: =A18+1 -> 10 | B19: 2020-12-04 | C19: 245442 | D19: 44176 | E19: =-D19+B19 -> -7 | F19: =E19*C19 -> -1718094
A20: =A19+1 -> 11 | B20: 2020-12-15 | C20: 1146052.5 | D20: 44187 | E20: =-D20+B20 -> -7 | F20: =E20*C20 -> -8022367.4
A21: =A20+1 -> 12 | B21: 2020-12-18 | C21: 252247.25 | D21: 44188 | E21: =-D21+B21 -> -5 | F21: =E21*C21 -> -1261236.2
A22: =A21+1 -> 13 | B22: 2020-12-23 | C22: 7.14 | D22: 44204 | E22: =-D22+B22 -> -16 | F22: =E22*C22 -> -114.24
... A63: =A62+1 -> 54 | B63: 2021-09-30 | C63: 1162956.5 | D63: 44476 | E63: =-D63+B63 -> -7 | F63: =E63*C63 -> -8140695.3
A64: =A63+1 -> 55 | B64: Total | C64: =SUM(C10:C63) -> 34374220 | E64: =ROUND(F64/C64,2) -> -7.13 | F64: =SUM(F10:F63) -> -2.4524264e+08
A65: =A64+1 -> 56
A66: =A65+1 -> 57 | B66: Average Daily Amount (Col (b) Ln 55 divided by 365.25) | E66: =+ROUND(C64/365.25,0) -> 94111
A67: =A66+1 -> 58
A68: =A67+1 -> 59 | B68: (Lead)/Lag Days Total (Col (d) Ln 55) | E68: =+E64 -> -7.13
A69: =A68+1 -> 60
A70: =A69+1 -> 61 | B70: Total Withholding (Col (d) Ln 57 times Ln 59) | E70: =+ROUND(E66*E68,0) -> -671011
A71: =A70+1 -> 62
A72: =A71+1 -> 63 | B72: Source: | C72: Thrift.xlsx

Sheet 13-2
A1: 2022 RATE CASE
A2: =' '!A2 -> ONCOR ELECTRIC DELIVERY COMPANY LLC
A3: MISCELLANEOUS WORKING FUNDS SUMMARY
A4: FOR THE TEST-YEAR ENDING DECEMBER 31, 2021
A5: SPONSOR: A. THENMADATHIL
A7: Line No. | B7: Description | C7: Amount | D7: Reference
B8: (a) | C8: (b) | D8: (c)
A10: 1 | B10: Transmission | C10: ='13-2-1'!J29 -> 0 | D10: WP/II-B-9/13-2-1
A11: 2 | B11: Distribution | C11: ='13-2-2'!J29 -> 0 | D11: WP/II-B-9/13-2-2
A12: 3 | B12: Corporate | C12: ='13-2-3'!J29 -> 0 | D12: WP/II-B-9/13-2-3
A13: 4
A14: 5 | C14: =ROUND(SUM(C10:C13),0) -> 0

Sheet 13-2-1
A1: 2022 RATE CASE
A2: =' '!A2 -> ONCOR ELECTRIC DELIVERY COMPANY LLC
A3: MISCELLANEOUS WORKING FUNDS - TRANSMISSION
A4: FOR THE TEST-YEAR ENDING DECEMBER 31, 2021
A5: SPONSOR: A. THENMADATHIL
A7: Line | C7: Relocation Advances | F7: Travel Advances | I7: Working Funds - Petty Cash
A8: No. | B8: Period | C8: 1350300 | F8: 1350700 | I8: 1354000
B9: (a) | C9: (b) | D9: (c) | F9: (d) | G9: (e) | I9: (f) | J9: (g)
A11: 1 | B11: Beginning Balance | D11: 0 | G11: 0 | J11: 0
A12: =A11+1 -> 2 | B12: Ending Balance at… | C12: GL Activity | F12: GL Activity | I12: GL Activity
A13: =A12+1 -> 3 | B13: 44197 | C13: 0 | D13: =D11+C13 -> 0 | F13: 0 | G13: =G11+F13 -> 0 | I13: 0 | J13: =J11+I13 -> 0
A14: =A13+1 -> 4 | B14: 44255 | C14: 0 | D14: =D13+C14 -> 0 | F14: 0 | G14: =G13+F14 -> 0 | I14: 0 | J14: =J13+I14 -> 0
A15: =A14+1 -> 5 | B15: 44286 | C15: 0 | D15: =D14+C15 -> 0 | F15: 0 | G15: =G14+F15 -> 0 | I15: 0 | J15: =J14+I15 -> 0
A16: =A15+1 -> 6 | B16: 44316 | C16: 0 | D16: =D15+C16 -> 0 | F16: 0 | G16: =G15+F16 -> 0 | I16: 0 | J16: =J15+I16 -> 0
A17: =A16+1 -> 7 | B17: 44347 | C17: 0 | D17: =D16+C17 -> 0 | F17: 0 | G17: =G16+F17 -> 0 | I17: 0 | J17: =J16+I17 -> 0
A18: =A17+1 -> 8 | B18: 44377 | C18: 0 | D18: =D17+C18 -> 0 | F18: 0 | G18: =G17+F18 -> 0 | I18: 0 | J18: =J17+I18 -> 0
A19: =A18+1 -> 9 | B19: 44408 | C19: 0 | D19: =D18+C19 -> 0 | F19: 0 | G19: =G18+F19 -> 0 | I19: 0 | J19: =J18+I19 -> 0
A20: =A19+1 -> 10 | B20: 44439 | C20: 0 | D20: =D19+C20 -> 0 | F20: 0 | G20: =G19+F20 -> 0 | I20: 0 | J20: =J19+I20 -> 0
A21: =A20+1 -> 11 | B21: 44469 | C21: 0 | D21: =D20+C21 -> 0 | F21: 0 | G21: =G20+F21 -> 0 | I21: 0 | J21: =J20+I21 -> 0
A22: =A21+1 -> 12 | B22: 44500 | C22: 0 | D22: =D21+C22 -> 0 | F22: 0 | G22: =G21+F22 -> 0 | I22: 0 | J22: =J21+I22 -> 0
A23: =A22+1 -> 13 | B23: 44530 | C23: 0 | D23: =D22+C23 -> 0 | F23: 0 | G23: =G22+F23 -> 0 | I23: 0 | J23: =J22+I23 -> 0
A24: =A23+1 -> 14 | B24: 44561 | C24: 0 | D24: =D23+C24 -> 0 | F24: 0 | G24: =G23+F24 -> 0 | I24: 0 | J24: =J23+I24 -> 0
A25: =A24+1 -> 15
A26: =A25+1 -> 16 | B26: 13 Month Total | D26: =SUM(D11:D24) -> 0 | G26: =SUM(G11:G24) -> 0 | J26: =SUM(J11:J24) -> 0
A27: =A26+1 -> 17 | B27: 13 Month Average | D27: =+D26/13 -> 0 | G27: =+G26/13 -> 0 | J27: =+J26/13 -> 0
A28: =A27+1 -> 18
A29: =A28+1 -> 19 | B29: Total | J29: =SUM(D27:J27) -> 0
A30: =A29+1 -> 20
A31: =A30+1 -> 21
A32: =A31+1 -> 22 | B32: Source - Trial Balance - TRN

Sheet 13-2-2
A1: 2022 RATE CASE
A2: =' '!A2 -> ONCOR ELECTRIC DELIVERY COMPANY LLC
A3: MISCELLANEOUS WORKING FUNDS - DISTRIBUTION
A4: FOR THE TEST-YEAR ENDING DECEMBER 31, 2021
A5: SPONSOR: A. THENMADATHIL
A7: Line | C7: Relocation Advances | F7: Travel Advances | I7: Working Funds - Petty Cash
A8: No. | B8: Period | C8: 1350300 | F8: 1350700 | I8: 1354000
B9: (a) | C9: (b) | D9: (c) | F9: (d) | G9: (e) | I9: (f) | J9: (g)
A11: 1 | B11: Beginning Balance | D11: 0 | G11: 0 | J11: 0
A12: =A11+1 -> 2 | B12: Ending Balance at… | C12: GL Activity | F12: GL Activity | I12: GL Activity
A13: =A12+1 -> 3 | B13: 44197 | C13: 0 | D13: =D11+C13 -> 0 | F13: 0 | G13: =G11+F13 -> 0 | I13: 0 | J13: =J11+I13 -> 0
A14: =A13+1 -> 4 | B14: 44255 | C14: 0 | D14: =D13+C14 -> 0 | F14: 0 | G14: =G13+F14 -> 0 | I14: 0 | J14: =J13+I14 -> 0
A15: =A14+1 -> 5 | B15: 44286 | C15: 0 | D15: =D14+C15 -> 0 | F15: 0 | G15: =G14+F15 -> 0 | I15: 0 | J15: =J14+I15 -> 0
A16: =A15+1 -> 6 | B16: 44316 | C16: 0 | D16: =D15+C16 -> 0 | F16: 0 | G16: =G15+F16 -> 0 | I16: 0 | J16: =J15+I16 -> 0
A17: =A16+1 -> 7 | B17: 44347 | C17: 0 | D17: =D16+C17 -> 0 | F17: 0 | G17: =G16+F17 -> 0 | I17: 0 | J17: =J16+I17 -> 0
A18: =A17+1 -> 8 | B18: 44377 | C18: 0 | D18: =D17+C18 -> 0 | F18: 0 | G18: =G17+F18 -> 0 | I18: 0 | J18: =J17+I18 -> 0
A19: =A18+1 -> 9 | B19: 44408 | C19: 0 | D19: =D18+C19 -> 0 | F19: 0 | G19: =G18+F19 -> 0 | I19: 0 | J19: =J18+I19 -> 0
A20: =A19+1 -> 10 | B20: 44439 | C20: 0 | D20: =D19+C20 -> 0 | F20: 0 | G20: =G19+F20 -> 0 | I20: 0 | J20: =J19+I20 -> 0
A21: =A20+1 -> 11 | B21: 44469 | C21: 0 | D21: =D20+C21 -> 0 | F21: 0 | G21: =G20+F21 -> 0 | I21: 0 | J21: =J20+I21 -> 0
A22: =A21+1 -> 12 | B22: 44500 | C22: 0 | D22: =D21+C22 -> 0 | F22: 0 | G22: =G21+F22 -> 0 | I22: 0 | J22: =J21+I22 -> 0
A23: =A22+1 -> 13 | B23: 44530 | D23: =D22+C23 -> 0 | F23: 0 | G23: =G22+F23 -> 0 | I23: 0 | J23: =J22+I23 -> 0
A24: =A23+1 -> 14 | B24: 44561 | C24: 0 | D24: =D23+C24 -> 0 | F24: 0 | G24: =G23+F24 -> 0 | I24: 0 | J24: =J23+I24 -> 0
A25: =A24+1 -> 15
A26: =A25+1 -> 16 | B26: 13 Month Total | D26: =SUM(D11:D24) -> 0 | G26: =SUM(G11:G24) -> 0 | J26: =SUM(J11:J24) -> 0
A27: =A26+1 -> 17 | B27: 13 Month Average | D27: =+D26/13 -> 0 | G27: =+G26/13 -> 0 | J27: =+J26/13 -> 0
A28: =A27+1 -> 18
A29: =A28+1 -> 19 | J29: =SUM(D27:J27) -> 0
A30: =A29+1 -> 20 | B30: Source - Trial Balance - ESD

Sheet 13-2-3
A1: 2022 RATE CASE
A2: =' '!A2 -> ONCOR ELECTRIC DELIVERY COMPANY LLC
A3: MISCELLANEOUS WORKING FUNDS - CORPORATE
A4: FOR THE TEST-YEAR ENDING DECEMBER 31, 2021
A5: SPONSOR: A. THENMADATHIL
A7: Line | C7: Relocation Advances | F7: Travel Advances | I7: Working Funds - Petty Cash
A8: No. | B8: Period | C8: 1350300 | F8: 1350700 | I8: 1354000
B9: (a) | C9: (b) | D9: (c) | F9: (d) | G9: (e) | I9: (f) | J9: (g)
A11: 1 | B11: Beginning Balance | D11: 0 | G11: 0 | J11: 0
A12: =A11+1 -> 2 | B12: Ending Balance at… | C12: GL Activity | F12: GL Activity | I12: GL Activity
A13: =A12+1 -> 3 | B13: 44197 | C13: 0 | D13: =D11+C13 -> 0 | F13: 0 | G13: =G11+F13 -> 0 | I13: 0 | J13: 0
A14: =A13+1 -> 4 | B14: 44255 | C14: 0 | D14: =D13+C14 -> 0 | F14: 0 | G14: =G13+F14 -> 0 | I14: 0 | J14: =J13+I14 -> 0
A15: =A14+1 -> 5 | B15: 44286 | C15: 0 | D15: =D14+C15 -> 0 | F15: 0 | G15: =G14+F15 -> 0 | I15: 0 | J15: =J14+I15 -> 0
A16: =A15+1 -> 6 | B16: 44316 | C16: 0 | D16: =D15+C16 -> 0 | F16: 0 | G16: =G15+F16 -> 0 | I16: 0 | J16: =J15+I16 -> 0
A17: =A16+1 -> 7 | B17: 44347 | C17: 0 | D17: =D16+C17 -> 0 | F17: 0 | G17: =G16+F17 -> 0 | I17: 0 | J17: =J16+I17 -> 0
A18: =A17+1 -> 8 | B18: 44377 | C18: 0 | D18: =D17+C18 -> 0 | F18: 0 | G18: =G17+F18 -> 0 | I18: 0 | J18: =J17+I18 -> 0
A19: =A18+1 -> 9 | B19: 44408 | C19: 0 | D19: =D18+C19 -> 0 | F19: 0 | G19: =G18+F19 -> 0 | I19: 0 | J19: =J18+I19 -> 0
A20: =A19+1 -> 10 | B20: 44439 | C20: 0 | D20: =D19+C20 -> 0 | F20: 0 | G20: =G19+F20 -> 0 | I20: 0 | J20: =J19+I20 -> 0
A21: =A20+1 -> 11 | B21: 44469 | C21: 0 | D21: =D20+C21 -> 0 | F21: 0 | G21: =G20+F21 -> 0 | I21: 0 | J21: =J20+I21 -> 0
A22: =A21+1 -> 12 | B22: 44500 | C22: 0 | D22: =D21+C22 -> 0 | F22: 0 | G22: =G21+F22 -> 0 | I22: 0 | J22: =J21+I22 -> 0
A23: =A22+1 -> 13 | B23: 44530 | C23: 0 | D23: =D22+C23 -> 0 | F23: 0 | G23: =G22+F23 -> 0 | I23: 0 | J23: =J22+I23 -> 0
A24: =A23+1 -> 14 | B24: 44561 | C24: 0 | D24: =D23+C24 -> 0 | F24: 0 | G24: =G23+F24 -> 0 | I24: 0 | J24: =J23+I24 -> 0
A25: =A24+1 -> 15
A26: =A25+1 -> 16 | B26: 13 Month Total | D26: =SUM(D11:D24) -> 0 | G26: =SUM(G11:G24) -> 0 | J26: =SUM(J11:J24) -> 0
A27: =A26+1 -> 17 | B27: 13 Month Average | D27: =+D26/13 -> 0 | G27: =+G26/13 -> 0 | J27: =+J26/13 -> 0
A28: =A27+1 -> 18
A29: =A28+1 -> 19 | J29: =SUM(D27:J27) -> 0
A30: =A29+1 -> 20 | B30: Source - Trial Balance - TRNDS

Sheet 13-3
A1: 2022 RATE CASE
A2: =' '!A2 -> ONCOR ELECTRIC DELIVERY COMPANY LLC
A3: DEFERRED DEBITS/CREDITS SUMMARY
A4: FOR THE TEST-YEAR ENDING DECEMBER 31, 2021
A5: SPONSOR: A. THENMADATHIL
A7: Line
A8: No. | B8: Period | D8: Total | F8: Ref
B9: (a) | D9: (b) | F9: (c)
A11: 1 | B11: Transmission | D11: ='13-3-1'!J26 -> -781921.09 | F11: WP/II-B-9/13-3-1
A12: 2 | B12: Distribution | D12: ='13-3-2'!J27 -> -7496982.6 | F12: WP/II-B-9/13-3-2
A13: =A12+1 -> 3
A14: =A13+1 -> 4 | B14: 13 Month Average | D14: =ROUND(SUM(D11:D12),0) -> -8278904

Sheet 13-3-1
A1: 2022 RATE CASE
A2: =' '!A2 -> ONCOR ELECTRIC DELIVERY COMPANY LLC
A3: DEFERRED DEBITS/CREDITS - TRANSMISSION
A4: FOR THE TEST-YEAR ENDING DECEMBER 31, 2021
A5: SPONSOR: A. THENMADATHIL
A7: Line | D7: Deferred | G7: Deferred
A8: No. | B8: Period | D8: Debits | F8: Ref | G8: Credits | I8: Ref | J8: Total
B9: (a) | D9: (b) | F9: (c) | G9: (d) | I9: (e) | J9: (f)
A10: 1 | B10: Beginning Balance | D10: ='13-3-1-1'!D11 -> 1166285.9 | F10: WP/II-B-9/13-3-1-1 | G10: ='13-3-1-2'!K11 -> -1340292.7 | I10: WP/II-B-9/13-3-1-2 | J10: =SUM(D10:G10) -> -174006.72
A11: =A10+1 -> 2 | B11: Ending Balance at…
A12: =A11+1 -> 3 | B12: 44197 | D12: ='13-3-1-1'!D12 -> 0 | F12: WP/II-B-9/13-3-1-1 | G12: ='13-3-1-2'!K13 -> -1340292.7 | I12: WP/II-B-9/13-3-1-2 | J12: =SUM(D12:G12) -> -1340292.7
A13: =A12+1 -> 4 | B13: 44255 | D13: ='13-3-1-1'!D13 -> 0 | F13: WP/II-B-9/13-3-1-1 | G13: ='13-3-1-2'!K14 -> -1340292.7 | I13: WP/II-B-9/13-3-1-2 | J13: =SUM(D13:G13) -> -1340292.7
A14: =A13+1 -> 5 | B14: 44286 | D14: ='13-3-1-1'!D14 -> 1057451.4 | F14: WP/II-B-9/13-3-1-1 | G14: ='13-3-1-2'!K15 -> -1067956.9 | I14: WP/II-B-9/13-3-1-2 | J14: =SUM(D14:G14) -> -10505.5
A15: =A14+1 -> 6 | B15: 44316 | D15: ='13-3-1-1'!D15 -> 0 | F15: WP/II-B-9/13-3-1-1 | G15: ='13-3-1-2'!K16 -> -1067956.9 | I15: WP/II-B-9/13-3-1-2 | J15: =SUM(D15:G15) -> -1067956.9
A16: =A15+1 -> 7 | B16: 44347 | D16: ='13-3-1-1'!D16 -> 0 | F16: WP/II-B-9/13-3-1-1 | G16: ='13-3-1-2'!K17 -> -1067956.9 | I16: WP/II-B-9/13-3-1-2 | J16: =SUM(D16:G16) -> -1067956.9
A17: =A16+1 -> 8 | B17: 44377 | D17: ='13-3-1-1'!D17 -> 203454.6 | F17: WP/II-B-9/13-3-1-1 | G17: ='13-3-1-2'!K18 -> -1269344.9 | I17: WP/II-B-9/13-3-1-2 | J17: =SUM(D17:G17) -> -1065890.3
A18: =A17+1 -> 9 | B18: 44408 | D18: ='13-3-1-1'!D18 -> 0 | F18: WP/II-B-9/13-3-1-1 | G18: ='13-3-1-2'!K19 -> -1269344.9 | I18: WP/II-B-9/13-3-1-2 | J18: =SUM(D18:G18) -> -1269344.9
A19: =A18+1 -> 10 | B19: 44439 | D19: ='13-3-1-1'!D19 -> 0 | F19: WP/II-B-9/13-3-1-1 | G19: ='13-3-1-2'!K20 -> -1269344.9 | I19: WP/II-B-9/13-3-1-2 | J19: =SUM(D19:G19) -> -1269344.9
A20: =A19+1 -> 11 | B20: 44469 | D20: ='13-3-1-1'!D20 -> 152733.64 | F20: WP/II-B-9/13-3-1-1 | G20: ='13-3-1-2'!K21 -> -1388751.4 | I20: WP/II-B-9/13-3-1-2 | J20: =SUM(D20:G20) -> -1236017.8
A21: =A20+1 -> 12 | B21: 44500 | D21: ='13-3-1-1'!D21 -> 0 | F21: WP/II-B-9/13-3-1-1 | G21: ='13-3-1-2'!K22 -> -1388751.4 | I21: WP/II-B-9/13-3-1-2 | J21: =SUM(D21:G21) -> -1388751.4
A22: =A21+1 -> 13 | B22: 44530 | D22: ='13-3-1-1'!D22 -> 0 | F22: WP/II-B-9/13-3-1-1 | G22: ='13-3-1-2'!K23 -> -1388751.4 | I22: WP/II-B-9/13-3-1-2 | J22: =SUM(D22:G22) -> -1388751.4
A23: =A22+1 -> 14 | B23: 44561 | D23: ='13-3-1-1'!D23 -> 121297.46 | F23: WP/II-B-9/13-3-1-1 | G23: ='13-3-1-2'!K24 -> -1989116.4 | I23: WP/II-B-9/13-3-1-2 | J23: =SUM(D23:G23) -> -1867818.9
A24: =A23+1 -> 15
A25: =A24+1 -> 16 | B25: Adjusted Total | D25: =SUM(D10:D23) -> 2701223 | G25: =SUM(G10:G23) -> -17188154 | J25: =SUM(J10:J23) -> -14486931
A26: =A25+1 -> 17 | B26: Adjusted Average | D26: =D25/5 -> 540244.61 | G26: =G25/13 -> -1322165.7 | J26: =+G26+D26 -> -781921.09
A27: =A26+1 -> 18
A28: =A27+1 -> 19
A29: =A28+1 -> 20 | B29: Source - Tabs 13-3-1-1 & 13-3-1-2-TRN

Sheet 13-3-1-1
A1: 2022 RATE CASE
A2: =' '!A2 -> ONCOR ELECTRIC DELIVERY COMPANY LLC
A3: DEFERRED DEBITS - TRANSMISSION
A4: FOR THE TEST-YEAR ENDING DECEMBER 31, 2021
A5: SPONSOR: A. THENMADATHIL
A7: Line | C7: Job Orders | D7: Adjusted
A8: No. | B8: Period | C8: 1862700 | D8: Job Orders
B9: (a) | C9: (b) | D9: (c)
A11: 1 | B11: Beg Bal | C11: 1166285.9 | D11: 1166285.9
A12: =A11+1 -> 2 | B12: 44197 | C12: 20599762 | D12: 0
A13: =A12+1 -> 3 | B13: 44255 | C13: 2677534.5 | D13: 0
A14: =A13+1 -> 4 | B14: 44286 | C14: 1057451.4 | D14: 1057451.4
A15: =A14+1 -> 5 | B15: 44316 | C15: 3820540.4 | D15: 0
A16: =A15+1 -> 6 | B16: 44347 | C16: 2970948.4 | D16: 0
A17: =A16+1 -> 7 | B17: 44377 | C17: 203454.6 | D17: 203454.6
A18: =A17+1 -> 8 | B18: 44408 | C18: 3275642.7 | D18: 0
A19: =A18+1 -> 9 | B19: 44439 | C19: 3057666.1 | D19: 0
A20: =A19+1 -> 10 | B20: 44469 | C20: 152733.64 | D20: 152733.64
A21: =A20+1 -> 11 | B21: 44500 | C21: 272453.3 | D21: 0
A22: =A21+1 -> 12 | B22: 44530 | C22: -98793.94 | D22: 0
A23: =A22+1 -> 13 | B23: 44561 | C23: 121297.46 | D23: 121297.46
A24: =A23+1 -> 14 | D24: 0
A25: =A24+1 -> 15 | B25: Monthly/Quarter Total | C25: =SUM(C11:C23) -> 39276976 | D25: =SUM(D11:D23) -> 2701223
A26: =A25+1 -> 16 | B26: 13 Month Average | C26: =+C25/13 -> 3021305.9
A27: =A26+1 -> 17 | B27: Qtr-Ending Average | D27: =+D25/5 -> 540244.61
A28: =A27+1 -> 18 | B28: 1862700 – Job Orders are set up to accumulate job costs and are subsequently cleared to O&M, Capital,
A29: =A28+1 -> 19 | B29: or Regulatory Assets upon completion
A30: =A29+1 -> 20 | B30: Source: | C30: Misc items - TRN.xlsx

Sheet 13-3-1-2
A1: 2022 RATE CASE
A2: =' '!A2 -> ONCOR ELECTRIC DELIVERY COMPANY LLC
A3: DEFERRED CREDITS - TRANSMISSION
A4: FOR THE TEST-YEAR ENDING DECEMBER 31, 2021
A5: SPONSOR: A. THENMADATHIL
A7: Line | D7: IBNR Medical and Dental | G7: IBNR Per Injury Prop Damage
A8: No. | B8: Period | D8: 253.1000 | G8: 253.1010 | K8: Total
B9: (a) | D9: (b) | E9: (c) | G9: (d) | H9: (e) | K9: (f)
A11: 1 | B11: Beginning Balance | E11: -1340292.7 | H11: 0 | K11: =SUM(E11:I11) -> -1340292.7
A12: =A11+1 -> 2 | B12: Ending Balance at… | D12: GL Activity | G12: GL Activity
A13: =A12+1 -> 3 | B13: 44197 | D13: 0 | E13: =E11+D13 -> -1340292.7 | G13: 0 | H13: =G13+H11 -> 0 | K13: =E13+H13 -> -1340292.7
A14: =A13+1 -> 4 | B14: 44255 | D14: 0 | E14: =E13+D14 -> -1340292.7 | G14: 0 | H14: =H13+G14 -> 0 | K14: =E14+H14 -> -1340292.7
A15: =A14+1 -> 5 | B15: 44286 | D15: 272335.79 | E15: =E14+D15 -> -1067956.9 | G15: 0 | H15: =H14+G15 -> 0 | K15: =E15+H15 -> -1067956.9
A16: =A15+1 -> 6 | B16: 44316 | D16: 0 | E16: =E15+D16 -> -1067956.9 | G16: 0 | H16: =H15+G16 -> 0 | K16: =E16+H16 -> -1067956.9
A17: =A16+1 -> 7 | B17: 44347 | D17: 0 | E17: =E16+D17 -> -1067956.9 | G17: 0 | H17: =H16+G17 -> 0 | K17: =E17+H17 -> -1067956.9
A18: =A17+1 -> 8 | B18: 44377 | D18: -201388.06 | E18: =E17+D18 -> -1269344.9 | G18: 0 | H18: =H17+G18 -> 0 | K18: =E18+H18 -> -1269344.9
A19: =A18+1 -> 9 | B19: 44408 | D19: 0 | E19: =E18+D19 -> -1269344.9 | G19: 0 | H19: =H18+G19 -> 0 | K19: =E19+H19 -> -1269344.9
A20: =A19+1 -> 10 | B20: 44439 | D20: 0 | E20: =E19+D20 -> -1269344.9 | G20: 0 | H20: =H19+G20 -> 0 | K20: =E20+H20 -> -1269344.9
A21: =A20+1 -> 11 | B21: 44469 | D21: -119406.47 | E21: =E20+D21 -> -1388751.4 | G21: 0 | H21: =H20+G21 -> 0 | K21: =E21+H21 -> -1388751.4
A22: =A21+1 -> 12 | B22: 44500 | D22: 0 | E22: =E21+D22 -> -1388751.4 | G22: 0 | H22: =H21+G22 -> 0 | K22: =E22+H22 -> -1388751.4
A23: =A22+1 -> 13 | B23: 44530 | D23: 0 | E23: =E22+D23 -> -1388751.4 | G23: 0 | H23: =H22+G23 -> 0 | K23: =E23+H23 -> -1388751.4
A24: =A23+1 -> 14 | B24: 44561 | D24: -600364.95 | E24: =E23+D24 -> -1989116.4 | G24: 0 | H24: =H23+G24 -> 0 | K24: =E24+H24 -> -1989116.4
A25: =A24+1 -> 15 | B25: G/L Balance @ 12/31/21 | D25: =SUM(D13:D24)+E11 -> -1989116.4 | G25: 0
A26: =A25+1 -> 16 | B26: 13 Month Total | E26: =SUM(E11:E24) -> -17188154 | H26: =SUM(H11:H24) -> 0 | K26: =SUM(K11:K24) -> -17188154
A27: =A26+1 -> 17 | B27: 13 Month Average | E27: =E26/13 -> -1322165.7 | H27: =H26/13 -> 0 | K27: =K26/13 -> -1322165.7
A28: =A27+1 -> 18
A29: =A28+1 -> 19 | B29: 2531000 - This is an estimated liability (IBNR) for medical and dental claims incurred by employees but not submitted for processing.
A30: =A29+1 -> 20 | B30: 2531010 – This is an estimated liability (IBNR) for personal injury and property damage claims outstanding.
A31: =A30+1 -> 21
A32: =A31+1 -> 22 | B32: Source: | D32: Misc items - TRN.xlsx

Sheet 13-3-2
A1: 2022 RATE CASE
A2: =' '!A2 -> ONCOR ELECTRIC DELIVERY COMPANY LLC
A3: DEFERRED DEBITS/CREDITS - DISTRIBUTION
A4: FOR THE TEST-YEAR ENDING DECEMBER 31, 2021
A5: SPONSOR: A. THENMADATHIL
A7: Line | D7: Deferred | G7: Deferred
A8: No. | B8: Period | D8: Debits | F8: Ref | G8: Credits | I8: Ref | J8: Total
B9: (a) | D9: (b) | F9: (c) | G9: (d) | I9: (e) | J9: (f)
A11: 1 | B11: Beginning Balance | D11: =+'13-3-2-1'!D11 -> 3902241.4 | F11: WP/II-B-9/13-3-2-1 | G11: ='13-3-2-2'!J11 -> -11142647 | I11: WP/II-B-9/13-3-2-2 | J11: =SUM(D11:I11) -> -7240406
A12: =A11+1 -> 2 | B12: Ending Balance at…
A13: =A12+1 -> 3 | B13: 44197 | D13: =+'13-3-2-1'!D12 -> 0 | F13: WP/II-B-9/13-3-2-1 | G13: ='13-3-2-2'!J13 -> -11142647 | I13: WP/II-B-9/13-3-2-2 | J13: =SUM(D13:G13) -> -11142647
A14: =A13+1 -> 4 | B14: 44255 | D14: =+'13-3-2-1'!D13 -> 0 | F14: WP/II-B-9/13-3-2-1 | G14: ='13-3-2-2'!J14 -> -11142647 | I14: WP/II-B-9/13-3-2-2 | J14: =SUM(D14:G14) -> -11142647
A15: =A14+1 -> 5 | B15: 44286 | D15: =+'13-3-2-1'!D14 -> 3865088.7 | F15: WP/II-B-9/13-3-2-1 | G15: ='13-3-2-2'!J15 -> -9721883.1 | I15: WP/II-B-9/13-3-2-2 | J15: =SUM(D15:G15) -> -5856794.4
A16: =A15+1 -> 6 | B16: 44316 | D16: =+'13-3-2-1'!D15 -> 0 | F16: WP/II-B-9/13-3-2-1 | G16: ='13-3-2-2'!J16 -> -9721883.1 | I16: WP/II-B-9/13-3-2-2 | J16: =SUM(D16:G16) -> -9721883.1
A17: =A16+1 -> 7 | B17: 44347 | D17: =+'13-3-2-1'!D16 -> 0 | F17: WP/II-B-9/13-3-2-1 | G17: ='13-3-2-2'!J17 -> -9721883.1 | I17: WP/II-B-9/13-3-2-2 | J17: =SUM(D17:G17) -> -9721883.1
A18: =A17+1 -> 8 | B18: 44377 | D18: =+'13-3-2-1'!D17 -> 5816330.8 | F18: WP/II-B-9/13-3-2-1 | G18: ='13-3-2-2'!J18 -> -13234595 | I18: WP/II-B-9/13-3-2-2 | J18: =SUM(D18:G18) -> -7418264.2
A19: =A18+1 -> 9 | B19: 44408 | D19: =+'13-3-2-1'!D18 -> 0 | F19: WP/II-B-9/13-3-2-1 | G19: ='13-3-2-2'!J19 -> -13234595 | I19: WP/II-B-9/13-3-2-2 | J19: =SUM(D19:G19) -> -13234595
A20: =A19+1 -> 10 | B20: 44439 | D20: =+'13-3-2-1'!D19 -> 0 | F20: WP/II-B-9/13-3-2-1 | G20: ='13-3-2-2'!J20 -> -13234595 | I20: WP/II-B-9/13-3-2-2 | J20: =SUM(D20:G20) -> -13234595
A21: =A20+1 -> 11 | B21: 44469 | D21: =+'13-3-2-1'!D20 -> 6010722.7 | F21: WP/II-B-9/13-3-2-1 | G21: ='13-3-2-2'!J21 -> -13650789 | I21: WP/II-B-9/13-3-2-2 | J21: =SUM(D21:G21) -> -7640065.9
A22: =A21+1 -> 12 | B22: 44500 | D22: =+'13-3-2-1'!D21 -> 0 | F22: WP/II-B-9/13-3-2-1 | G22: ='13-3-2-2'!J22 -> -13650789 | I22: WP/II-B-9/13-3-2-2 | J22: =SUM(D22:G22) -> -13650789
A23: =A22+1 -> 13 | B23: 44530 | D23: =+'13-3-2-1'!D22 -> 0 | F23: WP/II-B-9/13-3-2-1 | G23: ='13-3-2-2'!J23 -> -13650789 | I23: WP/II-B-9/13-3-2-2 | J23: =SUM(D23:G23) -> -13650789
A24: =A23+1 -> 14 | B24: 44561 | D24: =+'13-3-2-1'!D23 -> 2843497.8 | F24: WP/II-B-9/13-3-2-1 | G24: ='13-3-2-2'!J24 -> -12549524 | I24: WP/II-B-9/13-3-2-2 | J24: =SUM(D24:G24) -> -9706025.8
A25: =A24+1 -> 15
A26: =A25+1 -> 16 | B26: Adjusted Total | D26: =SUM(D11:D24) -> 22437881 | G26: =SUM(G11:G24) -> -1.5579927e+08 | J26: =SUM(J11:J24) -> -1.3336138e+08
A27: =A26+1 -> 17 | B27: Adjusted Average | D27: =D26/5 -> 4487576.3 | G27: =G26/13 -> -11984559 | J27: =+D27+G27 -> -7496982.6
A28: =A27+1 -> 18
A29: =A28+1 -> 19
A30: =A29+1 -> 20 | B30: Source - Tabs 13-3-2-1 & 13-3-2-2-ESD

Sheet 13-3-2-1
A1: 2022 RATE CASE
A2: =' '!A2 -> ONCOR ELECTRIC DELIVERY COMPANY LLC
A3: DEFERRED DEBITS - DISTRIBUTION
A4: FOR THE TEST-YEAR ENDING DECEMBER 31, 2021
A5: SPONSOR: A. THENMADATHIL
A7: Line | C7: Job Orders | D7: Adjusted
A8: No. | B8: Period | C8: 1862700 | D8: Job Orders
B9: (a) | C9: (b) | D9: (c)
A11: 1 | B11: Beg Bal | C11: 3902241.4 | D11: 3902241.4
A12: =A11+1 -> 2 | B12: 44197 | C12: 27320329 | D12: 0
A13: =A12+1 -> 3 | B13: 44255 | C13: 53074757 | D13: 0
A14: =A13+1 -> 4 | B14: 44286 | C14: -80432239 | D14: 3865088.7
A15: =A14+1 -> 5 | B15: 44316 | C15: 1.1921858e+08 | D15: 0
A16: =A15+1 -> 6 | B16: 44347 | C16: -3447407.2 | D16: 0
A17: =A16+1 -> 7 | B17: 44377 | C17: -1.1381994e+08 | D17: 5816330.8
A18: =A17+1 -> 8 | B18: 44408 | C18: 1.3591815e+08 | D18: 0
A19: =A18+1 -> 9 | B19: 44439 | C19: 2264407.3 | D19: 0
A20: =A19+1 -> 10 | B20: 44469 | C20: -1.3798816e+08 | D20: 6010722.7
A21: =A20+1 -> 11 | B21: 44500 | C21: 30390857 | D21: 0
A22: =A21+1 -> 12 | B22: 44530 | C22: 3697121.9 | D22: 0
A23: =A22+1 -> 13 | B23: 44561 | C23: -37255204 | D23: 2843497.8
A24: =A23+1 -> 14
A25: =A24+1 -> 15 | B25: Monthly/Quarter Total | C25: =SUM(C11:C23) -> 2843497.8 | D25: =SUM(D11:D23) -> 22437881
A26: =A25+1 -> 16 | B26: 13 Month Average | C26: =+C25/13 -> 218730.6
A27: =A26+1 -> 17 | B27: Qtr-Ending Average | D27: =+D25/5 -> 4487576.3
A28: =A27+1 -> 18 | B28: 1862700 – Job Orders are set up to accumulate job costs and are subsequently cleared to O&M, Capital,
A29: =+A28+1 -> 19 | B29: or Regulatory Assets upon completion
A30: =+A29+1 -> 20 | B30: Source: | C30: Misc items - ESD.xlsx

Sheet 13-3-2-2
A1: 2022 RATE CASE
A2: =' '!A2 -> ONCOR ELECTRIC DELIVERY COMPANY LLC
A3: DEFERRED CREDITS - DISTRIBUTION
A4: FOR THE TEST-YEAR ENDING DECEMBER 31, 2021
A5: SPONSOR: A. THENMADATHIL
A7: Line | D7: IBNR Medical and Dental | G7: IBNR Per Injury Prop Damage
A8: No. | B8: Period | D8: 253.1000 | G8: 253.1010 | J8: Total
B9: (a) | D9: (b) | E9: (c) | G9: (d) | H9: (e) | J9: (f)
A11: 1 | B11: Beginning Balance | E11: -4559407.3 | H11: -6583240 | J11: =E11+H11 -> -11142647
A12: =A11+1 -> 2 | D12: GL Activity | G12: GL Activity
A13: =A12+1 -> 3 | B13: 44197 | D13: 0 | E13: =E11+D13 -> -4559407.3 | G13: 0 | H13: =H11+G13 -> -6583240 | J13: =E13+H13 -> -11142647
A14: =A13+1 -> 4 | B14: 44255 | D14: 0 | E14: =E13+D14 -> -4559407.3 | G14: 0 | H14: =H13+G14 -> -6583240 | J14: =E14+H14 -> -11142647
A15: =A14+1 -> 5 | B15: 44286 | D15: 1020764.2 | E15: =E14+D15 -> -3538643.1 | G15: 400000 | H15: =H14+G15 -> -6183240 | J15: =E15+H15 -> -9721883.1
A16: =A15+1 -> 6 | B16: 44316 | D16: 0 | E16: =E15+D16 -> -3538643.1 | G16: 0 | H16: =H15+G16 -> -6183240 | J16: =E16+H16 -> -9721883.1
A17: =A16+1 -> 7 | B17: 44347 | D17: 0 | E17: =E16+D17 -> -3538643.1 | G17: 0 | H17: =H16+G17 -> -6183240 | J17: =E17+H17 -> -9721883.1
A18: =A17+1 -> 8 | B18: 44377 | D18: -512711.94 | E18: =E17+D18 -> -4051355.1 | G18: -3000000 | H18: =H17+G18 -> -9183240 | J18: =E18+H18 -> -13234595
A19: =A18+1 -> 9 | B19: 44408 | D19: 0 | E19: =E18+D19 -> -4051355.1 | G19: 0 | H19: =H18+G19 -> -9183240 | J19: =E19+H19 -> -13234595
A20: =A19+1 -> 10 | B20: 44439 | D20: 0 | E20: =E19+D20 -> -4051355.1 | G20: 0 | H20: =H19+G20 -> -9183240 | J20: =E20+H20 -> -13234595
A21: =A20+1 -> 11 | B21: 44469 | D21: -416193.53 | E21: =E20+D21 -> -4467548.6 | G21: 0 | H21: =H20+G21 -> -9183240 | J21: =E21+H21 -> -13650789
A22: =A21+1 -> 12 | B22: 44500 | D22: 0 | E22: =E21+D22 -> -4467548.6 | G22: 0 | H22: =H21+G22 -> -9183240 | J22: =E22+H22 -> -13650789
A23: =A22+1 -> 13 | B23: 44530 | D23: 0 | E23: =E22+D23 -> -4467548.6 | G23: 0 | H23: =H22+G23 -> -9183240 | J23: =E23+H23 -> -13650789
A24: =A23+1 -> 14 | B24: 44561 | D24: -1868735.1 | E24: =E23+D24 -> -6336283.6 | G24: 2970000 | H24: =H23+G24 -> -6213240 | J24: =E24+H24 -> -12549524
A25: =A24+1 -> 15 | B25: G/L Balance @ 12/31/21 | D25: =E11+D15+D18+D21+D24 -> -6336283.6 | G25: =+H11+G13+G14+G15+G16+G17+G18+G19+G20+G21+G22+G23+G24 -> -6213240
A26: =A25+1 -> 16 | B26: 13 Month Total | E26: =SUM(E11:E24) -> -56187146 | H26: =SUM(H11:H24) -> -99612120 | J26: =SUM(J11:J24) -> -1.5579927e+08
A27: =A26+1 -> 17 | B27: 13 Month Average | E27: =E26/13 -> -4322088.1 | H27: =H26/13 -> -7662470.8 | J27: =J26/13 -> -11984559
A28: =A27+1 -> 18
A29: =A28+1 -> 19 | B29: 2531000 - This is an estimated liability (IBNR) for medical and dental claims incurred by employees but not submitted for processing.
A30: =A29+1 -> 20 | B30: 2531010 – This is an estimated liability (IBNR) for personal injury and property damage claims outstanding.
A31: =A30+1 -> 21
A32: =A31+1 -> 22 | B32: Source: | D32: Misc items - ESD.xlsx

Sheet 13-4
A1: 2022 RATE CASE
A2: =' '!A2 -> ONCOR ELECTRIC DELIVERY COMPANY LLC
A3: HOME PURCHASE PLAN
A4: FOR THE TEST-YEAR ENDING DECEMBER 31, 2021
A5: SPONSOR: A. THENMADATHIL
A7: Line No. | B7: Period | D7: Transmission Activity | E7: Transmission | G7: Distribution Activity | H7: Distribution | J7: Total
E8: 174.6000 | H8: 174.6000
B9: (a) | E9: (b) | H9: (c) | J9: (d)
A11: 1 | B11: Beg Bal. | D11: 121192.41 | E11: =+D11 -> 121192.41 | G11: 525239.98 | H11: =+G11 -> 525239.98 | J11: =+H11+E11 -> 646432.39
A12: =A11+1 -> 2 | B12: 44197 | D12: -101435.24 | E12: =E11+D12 -> 19757.17 | G12: 0 | H12: =H11+G12 -> 525239.98 | J12: =+H12+E12 -> 544997.15
A13: =A12+1 -> 3 | B13: 44255 | D13: 0 | E13: =E12+D13 -> 19757.17 | G13: 0 | H13: =H12+G13 -> 525239.98 | J13: =+H13+E13 -> 544997.15
A14: =A13+1 -> 4 | B14: 44286 | D14: 0 | E14: =E13+D14 -> 19757.17 | G14: 128949.58 | H14: =H13+G14 -> 654189.56 | J14: =+H14+E14 -> 673946.73
A15: =A14+1 -> 5 | B15: 44316 | D15: 0 | E15: =E14+D15 -> 19757.17 | G15: -470973.89 | H15: =H14+G15 -> 183215.67 | J15: =+H15+E15 -> 202972.84
A16: =A15+1 -> 6 | B16: 44347 | D16: 268696.48 | E16: =E15+D16 -> 288453.65 | G16: -162328.04 | H16: =H15+G16 -> 20887.63 | J16: =+H16+E16 -> 309341.28
A17: =A16+1 -> 7 | B17: 44377 | D17: -268696.48 | E17: =E16+D17 -> 19757.17 | G17: 0 | H17: =H16+G17 -> 20887.63 | J17: =+H17+E17 -> 40644.8
A18: =A17+1 -> 8 | B18: 44408 | D18: 0 | E18: =E17+D18 -> 19757.17 | G18: 0 | H18: =H17+G18 -> 20887.63 | J18: =+H18+E18 -> 40644.8
A19: =A18+1 -> 9 | B19: 44439 | D19: 0 | E19: =E18+D19 -> 19757.17 | G19: 0 | H19: =H18+G19 -> 20887.63 | J19: =+H19+E19 -> 40644.8
A20: =A19+1 -> 10 | B20: 44469 | D20: 180672.31 | E20: =E19+D20 -> 200429.48 | G20: 0 | H20: =H19+G20 -> 20887.63 | J20: =+H20+E20 -> 221317.11
A21: =A20+1 -> 11 | B21: 44500 | D21: 32418.46 | E21: =E20+D21 -> 232847.94 | G21: 27717.52 | H21: =H20+G21 -> 48605.15 | J21: =+H21+E21 -> 281453.09
A22: =A21+1 -> 12 | B22: 44530 | D22: 57811.25 | E22: =E21+D22 -> 290659.19 | G22: 31685.43 | H22: =H21+G22 -> 80290.58 | J22: =+H22+E22 -> 370949.77
A23: =A22+1 -> 13 | B23: 44561 | D23: 0 | E23: =E22+D23 -> 290659.19 | G23: -59402.95 | H23: =H22+G23 -> 20887.63 | J23: =+H23+E23 -> 311546.82
A24: =A23+1 -> 14 | B24: G/L Balance @ 12/31/21 | D24: =SUM(D11:D23) -> 290659.19 | G24: =SUM(G11:G23) -> 20887.63
A25: =A24+1 -> 15 | B25: 13 Month Total | E25: =SUM(E11:E23) -> 1562542 | H25: =SUM(H11:H23) -> 2667346.7 | J25: =SUM(J11:J23) -> 4229888.7
A26: =A25+1 -> 16 | B26: 13 Month Avg. | E26: =E25/13 -> 120195.54 | H26: =H25/13 -> 205180.51 | J26: =ROUND(J25/13,0) -> 325376
A27: =A26+1 -> 17
A28: =A27+1 -> 18
A29: =A28+1 -> 19 | B29: Source: | D29: Misc items - TRN.xlsx
A30: =A29+1 -> 20 | D30: Misc items - ESD.xlsx

Sheet 13-5
A1: 2022 RATE CASE
A2: =' '!A2 -> ONCOR ELECTRIC DELIVERY COMPANY LLC
A3: SUMMARY OF EMPLOYEE ACCOUNT RECEIVABLE
A4: FOR THE TEST-YEAR ENDING DECEMBER 31, 2021
A5: SPONSOR: A. THENMADATHIL
A7: Line No. | B7: Description | C7: Amount | D7: Reference
B8: (a) | C8: (b) | D8: (c)
A10: 1 | B10: Transmission Division | C10: ='13-5-1'!K26 -> 120608.23 | D10: WP/II-B-9/13-5-1
A11: 2 | B11: Distribution Division | C11: ='13-5-2'!K26 -> 420012.84 | D11: WP/II-B-9/13-5-2
A12: =A11+1 -> 3 | B12: 13 Month Average | C12: =ROUND(SUM(C10:C11),0) -> 540621

Sheet 13-5-1
A1: 2022 RATE CASE
A2: =' '!A2 -> ONCOR ELECTRIC DELIVERY COMPANY LLC
A3: EMPLOYEE ACCOUNT RECEIVABLE - TRANSMISSION
A4: FOR THE TEST-YEAR ENDING DECEMBER 31, 2021
A5: SPONSOR: A. THENMADATHIL
A7: Line | C7: Energy Cons. Activity | D7: Energy Cons. | E7: Payroll Deduction - Other Activity | F7: Payroll Deduction - Other | G7: Appliances Activity | H7: Appliances | I7: Payroll Adv. Activity | J7: Payroll Adv.
A8: No. | B8: Period | C8: 1431060 | D8: 1431060 | E8: 1431000 | F8: 1431000 | G8: 1431110 | H8: 1431110 | I8: 1431600 | J8: 1431600 | K8: Total
B9: (a) | D9: (b) | F9: (c) | H9: (d) | J9: (e) | K9: (f)
A11: 1 | B11: Beg Bal. | C11: 57081.37 | D11: =C11 -> 57081.37 | E11: 0 | F11: =+E11 -> 0 | G11: 70559.19 | H11: =G11 -> 70559.19 | J11: 0 | K11: =D11+F11+H11+J11 -> 127640.56
A12: =A11+1 -> 2 | B12: 44227 | C12: 4663.72 | D12: =D11+C12 -> 61745.09 | E12: 0 | F12: =F11+E12 -> 0 | G12: -1405.28 | H12: =H11+G12 -> 69153.91 | J12: 0 | K12: =D12+F12+H12+J12 -> 130899
A13: =A12+1 -> 3 | B13: 44255 | C13: -2160.92 | D13: =D12+C13 -> 59584.17 | E13: 1656.37 | F13: =F12+E13 -> 1656.37 | G13: 1175.79 | H13: =H12+G13 -> 70329.7 | J13: 0 | K13: =D13+F13+H13+J13 -> 131570.24
A14: =A13+1 -> 4 | B14: 44286 | C14: 1251.58 | D14: =D13+C14 -> 60835.75 | E14: -2000 | F14: =F13+E14 -> -343.63 | G14: -3976.82 | H14: =H13+G14 -> 66352.88 | J14: 0 | K14: =D14+F14+H14+J14 -> 126845
A15: =A14+1 -> 5 | B15: 44316 | C15: 2127.16 | D15: =D14+C15 -> 62962.91 | E15: 343.63 | F15: =F14+E15 -> 0 | G15: -5171.05 | H15: =H14+G15 -> 61181.83 | J15: 0 | K15: =D15+F15+H15+J15 -> 124144.74
A16: =A15+1 -> 6 | B16: 44347 | C16: -2335.92 | D16: =D15+C16 -> 60626.99 | E16: -5541 | F16: =F15+E16 -> -5541 | G16: -3903.81 | H16: =H15+G16 -> 57278.02 | J16: 0 | K16: =D16+F16+H16+J16 -> 112364.01
A17: =A16+1 -> 7 | B17: 44377 | C17: 617.36 | D17: =D16+C17 -> 61244.35 | E17: 0 | F17: =F16+E17 -> -5541 | G17: -4506.82 | H17: =H16+G17 -> 52771.2 | J17: 0 | K17: =D17+F17+H17+J17 -> 108474.55
A18: =A17+1 -> 8 | B18: 44408 | C18: 168.28 | D18: =D17+C18 -> 61412.63 | E18: 0 | F18: =F17+E18 -> -5541 | G18: 2162.11 | H18: =H17+G18 -> 54933.31 | J18: 0 | K18: =D18+F18+H18+J18 -> 110804.94
A19: =A18+1 -> 9 | B19: 44439 | C19: -2110.5 | D19: =D18+C19 -> 59302.13 | E19: 5541 | F19: =F18+E19 -> 0 | G19: 3926.51 | H19: =H18+G19 -> 58859.82 | J19: 0 | K19: =D19+F19+H19+J19 -> 118161.95
A20: =A19+1 -> 10 | B20: 44469 | C20: -4094.98 | D20: =D19+C20 -> 55207.15 | E20: 1836.02 | F20: =F19+E20 -> 1836.02 | G20: 4557.34 | H20: =H19+G20 -> 63417.16 | J20: 0 | K20: =D20+F20+H20+J20 -> 120460.33
A21: =A20+1 -> 11 | B21: 44500 | C21: 1517.82 | D21: =D20+C21 -> 56724.97 | E21: -389.24 | F21: =F20+E21 -> 1446.78 | G21: -3663.04 | H21: =H20+G21 -> 59754.12 | J21: 0 | K21: =D21+F21+H21+J21 -> 117925.87
A22: =A21+1 -> 12 | B22: 44530 | C22: 1459.48 | D22: =D21+C22 -> 58184.45 | E22: 0 | F22: =F21+E22 -> 1446.78 | G22: -334.45 | H22: =H21+G22 -> 59419.67 | J22: 0 | K22: =D22+F22+H22+J22 -> 119050.9
A23: =A22+1 -> 13 | B23: 44561 | C23: 1429.49 | D23: =D22+C23 -> 59613.94 | E23: 0 | F23: =F22+E23 -> 1446.78 | G23: -915.44 | H23: =H22+G23 -> 58504.23 | J23: 0 | K23: =D23+F23+H23+J23 -> 119564.95
A24: =A23+1 -> 14 | B24: G/L Balance @ 12/31/21 | C24: =SUM(C11:C23) -> 59613.94 | G24: =SUM(G11:G23) -> 58504.23
A25: =A24+1 -> 15 | B25: 13 Month Total | D25: =SUM(D11:D23) -> 774525.9 | F25: =SUM(F11:F23) -> -9133.9 | H25: =SUM(H11:H23) -> 802515.04 | J25: =SUM(J11:J23) -> 0 | K25: =SUM(D25:J25) -> 1567907
A26: =A25+1 -> 16 | B26: 13 Month Avg. | D26: =D25/13 -> 59578.915 | F26: =F25/13 -> -702.60769 | H26: =H25/13 -> 61731.926 | J26: =J25/13 -> 0 | K26: =K25/13 -> 120608.23
A27: =A26+1 -> 17
A28: =A27+1 -> 18 | B28: 1431060 | C28: Loans to employees to purchase qualifying "energy efficient" items. The Company pays 90% of the total cost and an amount
A29: =A28+1 -> 19 | C29: is deducted from the employee's check.
A30: =A29+1 -> 20 | B30: 1431000 | C30: Outstanding balances of employee miscellaneous receivables.
A31: =A30+1 -> 21 | B31: 1431110 | C31: Employee loan used for the purchase of appliances.
A32: =A31+1 -> 22 | B32: 1431600 | C32: Includes temporary advances to employees for emergency purposes, EXPAT, overtime not paid correctly, etc.
A33: =A32+1 -> 23
A34: =A33+1 -> 24
A35: =A34+1 -> 25 | B35: Source: | C35: Misc. items - TRN.xlsx

Sheet 13-5-2
A1: 2022 RATE CASE
A2: =' '!A2 -> ONCOR ELECTRIC DELIVERY COMPANY LLC
A3: EMPLOYEE ACCOUNT RECEIVABLE - DISTRIBUTION
A4: FOR THE TEST-YEAR ENDING DECEMBER 31, 2021
A5: SPONSOR: A. THENMADATHIL
A7: Line | C7: Energy Cons. Activity | D7: Energy Cons. | E7: Payroll Deduction - Other Activity | F7: Payroll Deduction - Other | G7: Appliances Activity | H7: Appliances | I7: Payroll Adv. Activity | J7: Payroll Adv.
A8: No. | B8: Period | C8: 1431060 | D8: 1431060 | E8: 1431000 | F8: 1431000 | G8: 1431110 | H8: 1431110 | I8: 1431600 | J8: 1431600 | K8: Total
B9: (a) | D9: (b) | F9: (c) | H9: (d) | J9: (e) | K9: (f)
A11: 1 | B11: Beg Bal. | C11: 198853.78 | D11: =C11 -> 198853.78 | E11: 0 | F11: =E11 -> 0 | G11: 248996.93 | H11: =G11 -> 248996.93 | J11: 0 | K11: =D11+F11+H11+J11 -> 447850.71
A12: =A11+1 -> 2 | B12: 44227 | C12: -8956.26 | D12: =D11+C12 -> 189897.52 | E12: 329.02 | F12: =F11+E12 -> 329.02 | G12: 3936.31 | H12: =H11+G12 -> 252933.24 | J12: 0 | K12: =D12+F12+H12+J12 -> 443159.78
A13: =A12+1 -> 3 | B13: 44255 | C13: -5719.85 | D13: =D12+C13 -> 184177.67 | E13: 4807.21 | F13: =F12+E13 -> 5136.23 | G13: -13334.09 | H13: =H12+G13 -> 239599.15 | J13: 0 | K13: =D13+F13+H13+J13 -> 428913.05
A14: =A13+1 -> 4 | B14: 44282 | C14: 2069.75 | D14: =D13+C14 -> 186247.42 | E14: -329.02 | F14: =F13+E14 -> 4807.21 | G14: 664.73 | H14: =H13+G14 -> 240263.88 | J14: 0 | K14: =D14+F14+H14+J14 -> 431318.51
A15: =A14+1 -> 5 | B15: 44310 | C15: 5288.83 | D15: =D14+C15 -> 191536.25 | E15: -4807.21 | F15: =F14+E15 -> 0 | G15: -6484.85 | H15: =H14+G15 -> 233779.03 | J15: 0 | K15: =D15+F15+H15+J15 -> 425315.28
A16: =A15+1 -> 6 | B16: 44338 | C16: -4112.42 | D16: =D15+C16 -> 187423.83 | E16: -2849.08 | F16: =F15+E16 -> -2849.08 | G16: -6150.39 | H16: =H15+G16 -> 227628.64 | J16: 0 | K16: =D16+F16+H16+J16 -> 412203.39
A17: =A16+1 -> 7 | B17: 44366 | C17: 2133.15 | D17: =D16+C17 -> 189556.98 | E17: -3275.03 | F17: =F16+E17 -> -6124.11 | G17: -4241.75 | H17: =H16+G17 -> 223386.89 | J17: 0 | K17: =D17+F17+H17+J17 -> 406819.76
A18: =A17+1 -> 8 | B18: 44394 | C18: -3564.87 | D18: =D17+C18 -> 185992.11 | E18: -5858.34 | F18: =F17+E18 -> -11982.45 | G18: 2610.86 | H18: =H17+G18 -> 225997.75 | J18: 0 | K18: =D18+F18+H18+J18 -> 400007.41
A19: =A18+1 -> 9 | B19: 44422 | C19: -3434.18 | D19: =D18+C19 -> 182557.93 | E19: 0 | F19: =F18+E19 -> -11982.45 | G19: -9078.7 | H19: =H18+G19 -> 216919.05 | J19: 0 | K19: =D19+F19+H19+J19 -> 387494.53
A20: =A19+1 -> 10 | B20: 44450 | C20: -7389.58 | D20: =D19+C20 -> 175168.35 | E20: 37592.41 | F20: =F19+E20 -> 25609.96 | G20: 1516.93 | H20: =H19+G20 -> 218435.98 | J20: 0 | K20: =D20+F20+H20+J20 -> 419214.29
A21: =A20+1 -> 11 | B21: 44478 | C21: -3861.75 | D21: =D20+C21 -> 171306.6 | E21: -1127.82 | F21: =F20+E21 -> 24482.14 | G21: 6524.69 | H21: =H20+G21 -> 224960.67 | J21: 0 | K21: =D21+F21+H21+J21 -> 420749.41
A22: =A21+1 -> 12 | B22: 44506 | C22: -3917.72 | D22: =D21+C22 -> 167388.88 | E22: -14676.85 | F22: =F21+E22 -> 9805.29 | G22: 8512.95 | H22: =H21+G22 -> 233473.62 | J22: 0 | K22: =D22+F22+H22+J22 -> 410667.79
A23: =A22+1 -> 13 | B23: 44534 | C23: -2731.66 | D23: =D22+C23 -> 164657.22 | E23: 22436.25 | F23: =F22+E23 -> 32241.54 | G23: -3919.42 | H23: =H22+G23 -> 229554.2 | J23: 0 | K23: =D23+F23+H23+J23 -> 426452.96
A24: =A23+1 -> 14 | B24: G/L Balance @ 12/31/21 | C24: =SUM(C11:C23) -> 164657.22 | E24: =SUM(E11:E23) -> 32241.54 | G24: =SUM(G11:G23) -> 229554.2
A25: =A24+1 -> 15 | B25: 13 Month Total | D25: =SUM(D11:D23) -> 2374764.5 | F25: =SUM(F11:F23) -> 69473.3 | H25: =SUM(H11:H23) -> 3015929 | J25: =SUM(J11:J23) -> 0 | K25: =SUM(D25:J25) -> 5460166.9
A26: =A25+1 -> 16 | B26: 13 Month Avg. | D26: =D25/13 -> 182674.2 | F26: =F25/13 -> 5344.1 | H26: =H25/13 -> 231994.54 | J26: =J25/13 -> 0 | K26: =K25/13 -> 420012.84
A27: =A26+1 -> 17
A28: =A27+1 -> 18 | B28: 1431060 | D28: Loans to employees to purchase qualifying "energy efficient" items. The Company pays 90% of the total cost and
A29: =A28+1 -> 19 | D29: an amount is deducted from the employee's check.
A30: =A29+1 -> 20 | B30: 1431000 | D30: Outstanding balances of employee miscellaneous receivables.
A31: =A30+1 -> 21 | B31: 1431110 | D31: Employee loan used for the purchase of appliances.
A32: =A31+1 -> 22 | B32: 1431600 | D32: Includes temporary advances to employees for emergency purposes, EXPAT, overtime not paid correctly, etc.
A33: =A32+1 -> 23
A34: =A33+1 -> 24
A35: =A34+1 -> 25 | B35: Source: | C35: Misc items - ESD.xlsx

Sheet 14
A1: 2022 RATE CASE
A2: =' '!A2 -> ONCOR ELECTRIC DELIVERY COMPANY LLC
A3: PREPAID O&M AMORTIZATION
A4: FOR THE TEST-YEAR ENDING DECEMBER 31, 2021
A5: SPONSOR: A. THENMADATHIL
A7: Line No. | B7: Description | D7: FERC Account No. | F7: Twelve-Month Amortization
B8: (a) | D8: (b) | F8: (c)
A10: 1 | B10: Insurance
A11: =A10+1 -> 2 | B11: Transmission | D11: 9240000 | F11: 2139391.2
A12: =A11+1 -> 3 | D12: 9250000 | F12: 5135246.5
A13: =A12+1 -> 4 | B13: Distribution | D13: 9240000 | F13: 1981529.9
A14: =A13+1 -> 5 | D14: 9250000 | F14: 7360668.6
A15: =A14+1 -> 6 | B15: Total | F15: =SUM(F11:F14) -> 16616836
A16: =A15+1 -> 7
A17: =A16+1 -> 8 | B17: Membership Dues
A18: =A17+1 -> 9 | B18: Transmission | D18: 9302000 | F18: 0
A19: =A18+1 -> 10 | B19: Distribution | D19: 9302000 | F19: 1341023.7
A20: =A19+1 -> 11 | B20: Total | F20: =SUM(F18:F19) -> 1341023.7
A21: =A20+1 -> 12
A22: =A21+1 -> 13 | B22: Current Software Services & Maintenance
A23: =A22+1 -> 14 | B23: Transmission | D23: 9230000 | F23: 2924394.6
A24: =A23+1 -> 15 | B24: Distribution | D24: 9230000 | F24: 26116872
A25: =A24+1 -> 16 | B25: Total | F25: =SUM(F23:F24) -> 29041267
A26: =A25+1 -> 17
A27: =A26+1 -> 18 | B27: Total | F27: =+F15+F20+F25 -> 46999127
A28: =A27+1 -> 19
A29: =A28+1 -> 20 | B29: Prepaid Affiliate Charges - Other | F29: 1108749
A30: =A29+1 -> 21 | B30: Prepaid Non-labor (Third Party) O&M | F30: 45890378
A31: =A30+1 -> 22
A32: =A31+1 -> 23
A33: =A32+1 -> 24 | B33: Source: | D33: Amortization of Prepaids.xlsx

Sheet 15
A1: 2022 RATE CASE
A2: =' '!A2 -> ONCOR ELECTRIC DELIVERY COMPANY LLC
A3: PREPAID TAX AMORTIZATION
A4: FOR THE TEST-YEAR ENDING DECEMBER 31, 2021
A5: SPONSOR: A. THENMADATHIL
A7: Line No. | B7: Description | C7: FERC Account No. | E7: Twelve-Month Amortization
B8: (a) | C8: (b) | E8: (c)
A10: 1 | B10: Local Gross Receipt Tax Amortization
A11: =A10+1 -> 2 | B11: Distribution | C11: 4082410 | E11: 2.0451208e+08
A12: =A11+1 -> 3 | B12: Transmission | C12: 4082410 | E12: 0
A13: =A12+1 -> 4 | B13: Corporate | C13: 4082500 | E13: 0
A14: =A13+1 -> 5 | B14: Total | E14: =ROUND(SUM(E11:E12),0) -> 204512084
A15: =A14+1 -> 6
A16: =A15+1 -> 7 | B16: Source:
A17: =A16+1 -> 8 | B17: Amortization of prepaids - Local Gross Receipts tax.xlsx

Sheet Sheet1
