Workbook
Name \p: #REF!
Name \p: #REF!
Name \p: #REF!
Name \p: #REF!
Name \p: #REF!
Name \p: #REF!
Name \p: #REF!
Name \p: #REF!
Name \p: #REF!
Name \p: #REF!
Name \p: #REF!
Name \p: #REF!
Name \p: #REF!
Name \p: #REF!
Name _2006_Summary_Combined: #REF!
Name _2006_Summary_Combined: #REF!
Name _2006_Summary_Combined: #REF!
Name _2006_Summary_Combined: #REF!
Name _2006_Summary_Combined: #REF!
Name _2006_Summary_Combined: #REF!
Name _2006_Summary_Combined: #REF!
Name _2006_Summary_Combined: #REF!
Name _2006_Summary_Combined: #REF!
Name _2006_Summary_Combined: #REF!
Name _2006_Summary_Combined: #REF!
Name _2006_Summary_Combined: #REF!
Name _2006_Summary_Combined: #REF!
Name _2006_Summary_Combined: #REF!
Name _2006_Summary_Combined: #REF!
Name _963: #REF!
Name _963: #REF!
Name _963: #REF!
Name _963: #REF!
Name _963: #REF!
Name _963: #REF!
Name _963: #REF!
Name _963: #REF!
Name _963: #REF!
Name _963: #REF!
Name _963: #REF!
Name _963: #REF!
Name _963: #REF!
Name _963: #REF!
Name _985: #REF!
Name _985: #REF!
Name _985: #REF!
Name _985: #REF!
Name _985: #REF!
Name _985: #REF!
Name _985: #REF!
Name _985: #REF!
Name _985: #REF!
Name _985: #REF!
Name _985: #REF!
Name _985: #REF!
Name _985: #REF!
Name _985: #REF!
Name _991: #REF!
Name _991: #REF!
Name _991: #REF!

Sheet WP II-B.1 Prepayments
A1: PUBLIC UTILITY COMMISSION OF TEXAS | F1: WP/ II-B.1
A2: AEP TEXAS INC - CENTRAL DIVISION
A3: PREPAYMENTS
A4: TEST YEAR ENDING 12/31/2018
A8: Line No. | B8: Account Number | C8: Description | D8: Transmission | E8: Distribution | F8: Total T&D
A9: 1 | B9: Per Book Balances at Test Year End
A10: =A9+1 -> 2 | B10: 1650001 | C10: Prepaid Insurance | D10: 227989 | E10: 658074 | F10: =SUM(D10:E10) -> 886063
A11: =A10+1 -> 3 | B11: 1650005 | C11: Prepaid Employee Benefits | D11: 0 | E11: 0 | F11: =SUM(D11:E11) -> 0
A12: =A11+1 -> 4 | B12: 1650006 | C12: Other Prepayments | D12: 405000 | E12: -175667 | F12: =SUM(D12:E12) -> 229333
A13: =A12+1 -> 5 | B13: 1650010 | C13: Prepaid Pension Benefits | D13: 14547992 | E13: 120007525 | F13: =SUM(D13:E13) -> 134555517
A14: =A13+1 -> 6 | B14: 1650014 | C14: FAS 158 Qual Contra Asset | D14: -14547992 | E14: -120007525 | F14: =SUM(D14:E14) -> -134555517
A15: =A14+1 -> 7 | B15: 1650021 | C15: Prepaid Insurance - EIS | D15: 145586 | E15: 1043255 | F15: =SUM(D15:E15) -> 1188841
A16: =A15+1 -> 8 | B16: 1650023 | C16: Prepaid Lease | D16: 148117 | E16: 87643 | F16: =SUM(D16:E16) -> 235760
A17: =A16+1 -> 9 | B17: 1650035 | C17: PRW Without MED-D Benefits | D17: 2683304 | E17: 28153030 | F17: =SUM(D17:E17) -> 30836334
A18: =A17+1 -> 10 | B18: 1650037 | C18: FAS158 Contra-PRW Exclud Med-D | D18: -2683304 | E18: -28153030 | F18: =SUM(D18:E18) -> -30836334
A19: =A18+1 -> 11 | D19: =SUM(D10:D18) -> 926692 | E19: =SUM(E10:E18) -> 1613305 | F19: =SUM(F10:F18) -> 2539997
A20: =A19+1 -> 12
A21: =A20+1 -> 13 | B21: 13-Month Average
A22: =A21+1 -> 14 | B22: 1650001 | C22: Prepaid Insurance | D22: 192093.46 | E22: 618851.77 | F22: =SUM(D22:E22) -> 810945.23
A23: =A22+1 -> 15 | B23: 1650005 | C23: Prepaid Employee Benefits | D23: 302.30769 | E23: 2839.2308 | F23: =SUM(D23:E23) -> 3141.5385
A24: =A23+1 -> 16 | B24: 1650006 | C24: Other Prepayments | D24: 342692.31 | E24: -204378.23 | F24: =SUM(D24:E24) -> 138314.08
A25: =A24+1 -> 17 | B25: 1650010 | C25: Prepaid Pension Benefits | D25: 14993341 | E25: 122032194 | F25: =SUM(D25:E25) -> 1.3702553e+08
A26: =A25+1 -> 18 | B26: 1650014 | C26: FAS 158 Qual Contra Asset | D26: -14993341 | E26: -122032194 | F26: =SUM(D26:E26) -> -1.3702553e+08
A27: =A26+1 -> 19 | B27: 1650021 | C27: Prepaid Insurance - EIS | D27: 146820.69 | E27: 1302565.8 | F27: =SUM(D27:E27) -> 1449386.5
A28: =A27+1 -> 20 | B28: 1650023 | C28: Prepaid Lease | D28: 90198.692 | E28: 76326.385 | F28: =SUM(D28:E28) -> 166525.08
A29: =A28+1 -> 21 | B29: 1650035 | C29: PRW Without MED-D Benefits | D29: 2171299.4 | E29: 22810126 | F29: =SUM(D29:E29) -> 24981426
A30: =A29+1 -> 22 | B30: 1650037 | C30: FAS158 Contra-PRW Exclud Med-D | D30: -2171299.4 | E30: -22810126 | F30: =SUM(D30:E30) -> -24981426
A31: =A30+1 -> 23 | D31: =SUM(D22:D30) -> 772107.46 | E31: =SUM(E22:E30) -> 1796204.9 | F31: =SUM(F22:F30) -> 2568312.4
A32: =A31+1 -> 24
A33: =A32+1 -> 25 | C33: Adjustment | D33: =D31-D19 -> -154584.54 | E33: =E31-E19 -> 182899.92 | F33: =F31-F19 -> 28315.385
B39: Purpose: To adjust prepayments to reflect 13 month average balance

Sheet WP II-B.2 Material and Supplies
A1: PUBLIC UTILITY COMMISSION OF TEXAS | F1: WP/ II-B.2
A2: AEP TEXAS INC - CENTRAL DIVISION
A3: MATERIALS AND SUPPLIES
A4: TEST YEAR ENDING 12/31/2018
A8: Line No. | B8: Account Number | C8: Description | D8: Transmission | E8: Distribution | F8: Total T&D
A9: 1 | B9: Per Book Balances at Test Year End
A10: 2 | B10: 154 | C10: Material and Supplies | D10: ='[10]II-B-8-1 M&S MONTHLY'!$P$13 -> 11764735 | E10: ='[10]II-B-8-1 M&S MONTHLY'!$P$17 -> 29731671 | F10: =SUM(D10:E10) -> 41496406
A11: =A10+1 -> 3 | B11: 163 | C11: Undistributed M&S Expenses | D11: 0 | E11: 0 | F11: =SUM(D11:E11) -> 0
A12: =A11+1 -> 4
A13: =A12+1 -> 5 | B13: 13 Month Average
A14: =A13+1 -> 6 | B14: 154 | C14: Material and Supplies | D14: ='[10]II-B-8-1 M&S MONTHLY'!$Q$13 -> 12187416 | E14: ='[10]II-B-8-1 M&S MONTHLY'!$Q$17 -> 27143745 | F14: =SUM(D14:E14) -> 39331160
A15: =A14+1 -> 7 | B15: 163 | C15: Undistributed M&S Expenses | D15: 0 | E15: 0 | F15: =SUM(D15:E15) -> 0
A16: =A15+1 -> 8
A17: =A16+1 -> 9 | C17: Adjustment | D17: =D14-D10 -> 422680.12 | E17: =E14-E10 -> -2587926.1 | F17: =F14-F10 -> -2165246
B23: Purpose: To adjust materials and supplies to reflect 13 month average balance

Sheet WP II-B.3 Catastrophe
A1: PUBLIC UTILITY COMMISSION OF TEXAS | F1: WP/ II-B.3
A2: AEP TEXAS INC - CENTRAL DIVISION
A3: CATASTROPHE RESERVE ADJUSTMENT
A4: TEST YEAR ENDING 12/31/2018
A8: Line No. | B8: Account Number | C8: Description | D8: Transmission | E8: Distribution | F8: Total T&D
A9: 1 | B9: 1823 | C9: Per Book Catastrophe Reserve | D9: 1540600.1 | E9: 1.5090899e+08 | F9: =SUM(D9:E9) -> 1.5244959e+08
A10: =A9+1 -> 2 | B10: =B9 -> 1823 | C10: Transmission Carrying Costs | D10: 2995779 | E10: 0 | F10: =SUM(D10:E10) -> 2995779
A11: =A10+1 -> 3 | B11: =B10 -> 1823 | C11: Distribution Principal Securitized | D11: 0 | E11: -1.6462889e+08 | F11: =SUM(D11:E11) -> -1.6462889e+08
A12: 4 | B12: =B11 -> 1823 | C12: Adjusted Amount | D12: =SUM(D9:D11) -> 4536379 | E12: =SUM(E9:E11) -> -13719898 | F12: =SUM(F9:F11) -> -9183518.5
A14: =A12+1 -> 5 | B14: =B12 -> 1823 | C14: Adjustment | D14: =SUM(D10:D11) -> 2995779 | E14: =SUM(E10:E11) -> -1.6462889e+08 | F14: =SUM(F10:F11) -> -1.6163311e+08
B17: Purpose: To Adjust Catastrophe Reserve to be in Synch with PUCT Docket Nos. 48577 & 49308

Sheet WP II-B.4 Prepaid Pension
B1: PUBLIC UTILITY COMMISSION OF TEXAS | G1: WP II-B.4
B2: AEP TEXAS INC - CENTRAL DIVISION
B3: WP/ II-B.4 PREPAID PENSION AND FAS 158
B4: TEST YEAR ENDING 12/31/2018
A8: Line No. | B8: Account Number | C8: Description | D8: Reference | E8: Adjusted '13 Month AVG | F8: Rate Base Adjustment | G8: Total Company Electric
A11: 1 | C11: Transmission
A12: 2 | B12: 1650010 | C12: Prepaid Pension Benefits | D12: II-B-10 | E12: ='[10]II-B-10-1 Prepayments (MONTHLY)'!$Q$16 -> 14993341 | F12: =-G26*E12 -> -10484707 | G12: =+E12+F12 -> 4508633.8
A13: 3 | B13: 1650014 | C13: FAS 158 Qual Contra Asset | D13: II-B-10 | E13: ='[10]II-B-10-1 Prepayments (MONTHLY)'!$Q$17 -> -14993341 | F13: =-E13 -> 14993341 | G13: =+E13+F13 -> 0
A14: 4 | B14: 1650037 | C14: FAS158 Contra-PRW Exclud Med-D | D14: II-B-10 | E14: ='[10]II-B-10-1 Prepayments (MONTHLY)'!$Q$21 -> -2171299.4 | F14: =-E14 -> 2171299.4 | G14: =+E14+F14 -> 0
A16: 5 | E16: =+SUM(E12:E15) -> -2171299.4 | F16: =+SUM(F12:F15) -> 6679933.2 | G16: =+SUM(G12:G15) -> 4508633.8
A18: 6 | C18: Distribution
A19: 7 | B19: 1650010 | C19: Prepaid Pension Benefits | D19: II-B-10 | E19: ='[10]II-B-10-1 Prepayments (MONTHLY)'!$Q$30 -> 122032194 | F19: =-G27*E19 -> -67512724 | G19: =+E19+F19 -> 54519470
A20: 8 | B20: 1650014 | C20: FAS 158 Qual Contra Asset | D20: II-B-10 | E20: ='[10]II-B-10-1 Prepayments (MONTHLY)'!$Q$31 -> -122032194 | F20: =-E20 -> 122032194 | G20: =+E20+F20 -> 0
A21: 9 | B21: 1650037 | C21: FAS158 Contra-PRW Exclud Med-D | D21: II-B-10 | E21: ='[10]II-B-10-1 Prepayments (MONTHLY)'!$Q$35 -> -22810126 | F21: =-E21 -> 22810126 | G21: =+E21+F21 -> 0
A23: 10 | E23: =+SUM(E19:E22) -> -22810126 | F23: =+SUM(F19:F22) -> 77329596 | G23: =+SUM(G19:G22) -> 54519470
A25: 11 | F25: O&M | G25: Capital
A26: 12 | C26: Payroll Expense Ratio | D26: WP/II-D-2-3 | E26: Transmission | F26: =+'WP II-D-2-4 ASC 715 OPEB'!$E$10 -> 0.30070909 | G26: =-F26+1 -> 0.69929091
A27: 13 | D27: WP/II-D-2-3 | E27: Distribution | F27: =+'WP II-D-2-5 SFAS 112'!$F$10 -> 0.446763 | G27: =-F27+1 -> 0.553237
A30: 14 | C30: Purpose:
A31: 15 | C31: To remove FAS 158 balances from rate base and adjust prepaid pension benefits in rate
A32: 16 | C32: base per PUCT ruling in Docket 33309

Sheet WP II-B.5 Plant held for Future
B1: PUBLIC UTILITY COMMISSION OF TEXAS
B2: AEP TEXAS INC - CENTRAL DIVISION
B3: ANALYSIS OF PLANT HELD FOR FUTURE USE
B4: TEST YEAR ENDED 12/31/18
A6: Line No. | B6: Business Unit | C6: Account | D6: Plant Account | E6: description | F6: long_description | G6: Estimated In Service Date | H6: Amount | I6: Adjustment | J6: Total
A7: 1 | B7: 211 | C7: 1050001 | D7: 36000 | E7: Land Parcel | F7: James Rowe Substation : AEPTC : 5132 | G7: 2021 | H7: 186208.56 | I7: =-H7 -> -186208.56 | J7: =SUM(H7:I7) -> 0
A8: 2 | B8: 211 | C8: 1050001 | D8: 36000 | E8: Land Parcel | F8: Pantera 138kV Station : AEPTC : 5213 | G8: 2021 | H8: 287810.24 | I8: =-H8 -> -287810.24 | J8: =SUM(H8:I8) -> 0
A9: 3 | B9: 211 | C9: 1050001 | D9: 36000 | E9: Land Parcel | F9: Valadez 138kV Substation : AEPTC : 5187 | G9: 2019 | H9: 3023997.3 | J9: =SUM(H9:I9) -> 3023997.3
A10: 4 | B10: 211 | C10: 1050001 | D10: 36000 | E10: Land Parcel | F10: James Rowe Substation : AEPTC : 5132 | G10: 2021 | H10: 8712.75 | I10: =-H10 -> -8712.75 | J10: =SUM(H10:I10) -> 0
A11: 5 | B11: 211 | C11: 1050001 | D11: 36000 | E11: Land Parcel | F11: Marina 138/12kV Substation : AEPTC : 5195 | G11: TBD | H11: 272882.64 | I11: =-H11 -> -272882.64 | J11: =SUM(H11:I11) -> 0
A12: 6 | B12: 211 | C12: 1050001 | D12: 36000 | E12: Land Parcel | F12: James Rowe Substation : AEPTC : 5132 | G12: 2021 | H12: 591060.99 | I12: =-H12 -> -591060.99 | J12: =SUM(H12:I12) -> 0
A13: 7 | B13: 211 | C13: 1050001 | D13: 36000 | E13: Land Parcel | F13: Resaca 69kV Substation : AEPTC : 1204 | G13: 2020 | H13: 87385.24 | J13: =SUM(H13:I13) -> 87385.24
A14: 8 | B14: 211 | C14: 1050001 | D14: 36000 | E14: Land Parcel | F14: Resaca 69kV Substation : AEPTC : 1204 | G14: 2020 | H14: 20633.42 | J14: =SUM(H14:I14) -> 20633.42
A15: 9 | B15: 211 | C15: 1050001 | D15: 36000 | E15: Land Parcel | F15: Iowa 138/12.47KV Substation : AEPTC : 5152 | G15: 2023 | H15: 244307.96 | I15: =-H15 -> -244307.96 | J15: =SUM(H15:I15) -> 0
A16: 10 | B16: 211 | C16: 1050001 | D16: 36000 | E16: Land Parcel | F16: James Rowe Substation : AEPTC : 5132 | G16: 2021 | H16: 218592.58 | I16: =-H16 -> -218592.58 | J16: =SUM(H16:I16) -> 0
A17: 11 | B17: Total Account 1050001 | H17: =SUM(H7:H16) -> 4941591.7 | I17: =SUM(I7:I16) -> -1809575.7 | J17: =SUM(J7:J16) -> 3132016
B20: Purpose: To adjust plant held for future use to remove assets not scheduled to be in service by 12/31/2020

Sheet WP II-B.6 PRW MED-D
B1: PUBLIC UTILITY COMMISSION OF TEXAS | H1: WP II-B.6
B2: AEP TEXAS INC - CENTRAL DIVISION
B3: WP/ II-B.5 PRW WITHOUT MED-D
B4: TEST YEAR ENDING 12/31/2018
A8: Line No. | B8: Account Number | C8: Description | D8: Reference | E8: Adjusted '13 Month AVG | F8: Adjustment for capitalization | G8: Rate Base Adjustment | H8: Total Company
A11: 1 | C11: Transmission
A12: 2 | B12: 1650035 | C12: PRW Without MED-D Benefits | D12: II-B-10 | E12: ='[10]II-B-10-1 Prepayments (MONTHLY)'!$Q$20 -> 2171299.4 | F12: =G20 -> 0.69929091 | G12: =-E12*F12 -> -1518369.9 | H12: =+E12+G12 -> 652929.46
A15: 3 | C15: Distribution
A16: 4 | B16: 1650035 | C16: PRW Without MED-D Benefits | D16: II-B-10 | E16: ='[10]II-B-10-1 Prepayments (MONTHLY)'!$Q$34 -> 22810126 | F16: =G21 -> 0.553237 | G16: =-E16*F16 -> -12619406 | H16: =+E16+G16 -> 10190721
A19: 5 | F19: O&M | G19: Capital
A20: 6 | C20: Payroll Expense Ratio | D20: WP/II-D-2-3 | E20: Transmission | F20: =+'WP II-D-2-4 ASC 715 OPEB'!$E$10 -> 0.30070909 | G20: =-F20+1 -> 0.69929091
A21: 7 | D21: WP/II-D-2-3 | E21: Distribution | F21: =+'WP II-D-2-5 SFAS 112'!$F$10 -> 0.446763 | G21: =-F21+1 -> 0.553237
B24: Purpose: To adjust PWR without Med D prepayment to reflect capitalization

Sheet WP II-B-1-1 TCOS 
A1: PUBLIC UTILITY COMMISSION OF TEXAS | F1: WP II-B-1-1
A2: AEP TEXAS INC - CENTRAL DIVISION
A3: WP/ II-B ADJUSTMENTS FROM TCOS FILINGS
A4: TEST YEAR ENDING 12/31/2018
A8: Line No. | B8: Account | C8: Description | D8: Plant | E8: Provision | F8: Net
A10: 2 | B10: 356 | C10: Sonora-Hamilton Line (TCC) - Raise structures | D10: 305362.57 | E10: 34811 | F10: =+SUM(D10:E10) -> 340173.57
A11: =+A10+1 -> 3 | B11: 353 | C11: Valero East: New Line Terminal | D11: -111356.82 | E11: -9200 | F11: =+SUM(D11:E11) -> -120556.82
A12: =+A11+1 -> 4 | B12: 353 | C12: STEC Rangerville Through Path Purchase | D12: -1399739.1 | E12: -33774 | F12: =+SUM(D12:E12) -> -1433513.1
A13: =+A12+1 -> 5 | B13: 353 | C13: Lorentz 138kV Substation | D13: -141047 | E13: -11881 | F13: =+SUM(D13:E13) -> -152928
A14: =+A13+1 -> 6 | B14: 353 | C14: LON HILL - AHC | D14: -705.74 | E14: -11 | F14: =+SUM(D14:E14) -> -716.74
A15: =+A14+1 -> 7 | B15: 353 | C15: LAPALMA: ADD 345/138 KV AUTO | D15: -165268.94 | E15: -1707 | F15: =+SUM(D15:E15) -> -166975.94
A16: =+A15+1 -> 8 | B16: 350.1 | C16: Victoria - Edna 138 kV, ROW | D16: -702.22 | E16: -6 | F16: =+SUM(D16:E16) -> -708.22
A17: =+A16+1 -> 9 | B17: 355 | C17: Victoria - Edna 138 kV, Relocate | D17: -22614.9 | E17: -10666 | F17: =+SUM(D17:E17) -> -33280.9
A18: =+A17+1 -> 10 | B18: 356 | C18: Victoria - Edna 138 kV, Relocate | D18: -11725.46 | E18: -3856 | F18: =+SUM(D18:E18) -> -15581.46
A19: =+A18+1 -> 11 | B19: 355 | C19: Victoria - Lolita 138 kV, Relocate | D19: -22753.94 | E19: -9581 | F19: =+SUM(D19:E19) -> -32334.94
A20: =+A19+1 -> 12 | B20: 356 | C20: Victoria - Lolita 138 kV, Relocate | D20: -13486.82 | E20: -3959 | F20: =+SUM(D20:E20) -> -17445.82
A21: =+A20+1 -> 13 | B21: 350.1 | C21: Victoria - Lolita 138 kV, ROW | D21: -2306.57 | E21: -22 | F21: =+SUM(D21:E21) -> -2328.57
A22: =+A21+1 -> 14 | B22: 355 | C22: Gregory - Rincon 69 kV, Relocate 3.3 mile section | D22: -273093.07 | E22: -5395 | F22: =+SUM(D22:E22) -> -278488.07
... A26: =+A25+1 -> 18 | B26: 355 | C26: Brook Hollow - Point Comfort | D26: -1331.54 | E26: -2 | F26: =+SUM(D26:E26) -> -1333.54
A27: =+A26+1 -> 19 | B27: 350 | C27: Land Purchase for Bonilla Substatio | D27: -792320.94 | F27: =+SUM(D27:E27) -> -792320.94
A28: =+A27+1 -> 20 | B28: 350 | C28: Property:New Borglum 138kV | D28: -464239.99 | F28: =+SUM(D28:E28) -> -464239.99
A29: =+A28+1 -> 21
A30: =+A29+1 -> 22 | B30: Total | D30: =SUM(D10:D29) -> -3164358.8 | E30: =SUM(E10:E29) -> -55702 | F30: =SUM(F10:F29) -> -3220060.8
B34: Purpose: adjust plant in service to reflect outstanding proforma adjustments from Interim TCOS filings

Sheet WP II-B-1-2
B1: PUBLIC UTILITY COMMISSION OF TEXAS | G1: WP II-B-1-2
B2: AEP TEXAS INC - CENTRAL DIVISION
B3: WP/ II-B-1-1 HURRICANE HARVEY PLANT ADJUSTMENT
B4: TEST YEAR ENDING 12/31/2018
A8: Line No. | B8: Account Number | C8: Description | D8: Reference | E8: PLANT 101 | F8: Removal Costs | G8: Accum Depr Removal Amount
A11: 1 | B11: 36100 - Structures and Improvements Total | D11: WP II-B-1-2.1 | E11: -2308533.6 | F11: -2149571.1 | G11: -214280.32
A12: 2 | B12: 36200 - Station Equipment | D12: WP II-B-1-2.1 | E12: -5436148.3 | F12: -5061822.7 | G12: -504588.54
A13: 3 | B13: 36216 - Station Equipment-SmartGrid | D13: WP II-B-1-2.1 | E13: -122143.1 | F13: -113732.5 | G13: -11337.441
A14: =A13+1 -> 4 | B14: 36400 - Poles, Towers and Fixtures | D14: WP II-B-1-2.1 | E14: -43972452 | F14: -40944570 | G14: -4081565.5
A15: =A14+1 -> 5 | B15: 36500 - Overhead Conductors, Device | D15: WP II-B-1-2.1 | E15: -31231740 | F15: -29081166 | G15: -2898960.3
A16: =A15+1 -> 6 | B16: 36600 - Underground Conduit | D16: WP II-B-1-2.1 | E16: -253933.16 | F16: -236447.67 | G16: -23570.321
A17: =A16+1 -> 7 | B17: 36700 - Undergrnd Conductors,Device | D17: WP II-B-1-2.1 | E17: -2242889.9 | F17: -2088447.6 | G17: -208187.2
A18: =A17+1 -> 8 | B18: 36800 - Line Transformers | D18: WP II-B-1-2.1 | E18: -2085493.2 | F18: -1941889 | G18: -193577.49
A19: =A18+1 -> 9 | B19: 36900 - Services | D19: WP II-B-1-2.1 | E19: -45746.4 | F19: -42596.366 | G19: -4246.2251
A20: =A19+1 -> 10 | B20: 37100 - Installs Customer Premises | D20: WP II-B-1-2.1 | E20: -26308.78 | F20: -24497.194 | G20: -2442.0064
A21: =A20+1 -> 11 | B21: 37300 - Street Lghtng & Signal Sys | D21: WP II-B-1-2.1 | E21: -4844607.8 | F21: -4511014.8 | G21: -449681.18
A22: =A21+1 -> 12 | B22: 39700 - Communication Equipment | D22: WP II-B-1-2.1 | E22: -701948.77 | F22: -653613.55 | G22: -65155.563
A23: =A22+1 -> 13 | B23: 39716 - GridSmart Communic Equip | D23: WP II-B-1-2.1 | E23: -1365972.5 | F23: -1271913.5 | G23: -126790.89
A24: =A23+1 -> 14
A25: =A24+1 -> 15 | E25: =SUM(E11:E24) -> -94637918 | F25: =SUM(F11:F24) -> -88121282 | G25: =SUM(G11:G24) -> -8784383
B28: Purpose: To adjust plant-in-service to be in synch with PUCT Docket No 49308

Sheet WP II-B-5-1
B1: PUBLIC UTILITY COMMISSION OF TEXAS | I1: WP II-B-1-3
B2: AEP TEXAS INC - CENTRAL DIVISION
B3: WP/ II-B-1-5 ALLOCATION OF RWIP
B4: TEST YEAR ENDING 12/31/2018
D9: Transmission | E9: Distribution | H9: Transmission | I9: Distribution
A10: Line | D10: Balance Provision | E10: Balance Provision | H10: Allocate RWIP | I10: Allocate RWIP
A11: No. | D11: for Depreciation | E11: for Depreciation | F11: Total | H11: Balance | I11: Balance
A12: 1 | B12: Transmission Plant
A13: =A12+1 -> 2 | B13: Accumulated Depreciation
A14: =A13+1 -> 3 | B14: A352 | C14: Structures and Improvements | D14: 4522075.2 | F14: =SUM(D14:E14) -> 4522075.2 | H14: =$D$57*(D14/$D$54) -> -77446.356 | I14: =$E$57*(E14/$E$54) -> 0
A15: =A14+1 -> 4 | B15: A353 | C15: Station Equipment | D15: 1.4871021e+08 | F15: =SUM(D15:E15) -> 1.4871021e+08 | H15: =$D$57*(D15/$D$54) -> -2546853.6 | I15: =$E$57*(E15/$E$54) -> 0
A16: =A15+1 -> 5 | B16: A354 | C16: Towers and Fixtures | D16: 15571694 | F16: =SUM(D16:E16) -> 15571694 | H16: =$D$57*(D16/$D$54) -> -266685.3 | I16: =$E$57*(E16/$E$54) -> 0
A17: =A16+1 -> 6 | B17: A355 | C17: Poles and Fixtures | D17: 94346974 | F17: =SUM(D17:E17) -> 94346974 | H17: =$D$57*(D17/$D$54) -> -1615813.3 | I17: =$E$57*(E17/$E$54) -> 0
A18: =A17+1 -> 7 | B18: A356 | C18: O.H. Conductors & Devices | D18: 44255148 | F18: =SUM(D18:E18) -> 44255148 | H18: =$D$57*(D18/$D$54) -> -757926.36 | I18: =$E$57*(E18/$E$54) -> 0
A19: =A18+1 -> 8 | B19: A357 | C19: Undergound Conduit | D19: 6150.54 | F19: =SUM(D19:E19) -> 6150.54 | H19: =$D$57*(D19/$D$54) -> -105.33591 | I19: =$E$57*(E19/$E$54) -> 0
A20: =A19+1 -> 9 | B20: A358 | C20: Underground Conductors | D20: 2964620.9 | F20: =SUM(D20:E20) -> 2964620.9 | H20: =$D$57*(D20/$D$54) -> -50772.947 | I20: =$E$57*(E20/$E$54) -> 0
A21: =A20+1 -> 10 | B21: A359 | C21: Roads and Trails | D21: 48847.58 | F21: =SUM(D21:E21) -> 48847.58 | H21: =$D$57*(D21/$D$54) -> -836.57766 | I21: =$E$57*(E21/$E$54) -> 0
A22: =A21+1 -> 11 | C22: Subtotal | D22: =SUM(D14:D21) -> 3.1042572e+08 | E22: =SUM(E14:E21) -> 0 | F22: =SUM(F14:F21) -> 3.1042572e+08 | H22: =SUM(H14:H21) -> -5316439.8 | I22: =SUM(I14:I21) -> 0
A23: =A22+1 -> 12
A24: =A23+1 -> 13 | B24: Distribution Plant
A25: =A24+1 -> 14 | B25: Accumulated Depreciation
A26: =A25+1 -> 15 | B26: A361 | C26: Structures and Improvements | E26: 2554890.7 | F26: =SUM(D26:E26) -> 2554890.7 | H26: =$D$57*(D26/$D$54) -> 0 | I26: =$E$57*(E26/$E$54) -> -19586.675
A27: =A26+1 -> 16 | B27: A362 | C27: Station Equipment | E27: 23754966 | F27: =SUM(D27:E27) -> 23754966 | H27: =$D$57*(D27/$D$54) -> 0 | I27: =$E$57*(E27/$E$54) -> -182113.78
A28: =A27+1 -> 17 | B28: A364P | C28: Poles,Towers & Fixtures-Primary | E28: 2.5423935e+08 | F28: =SUM(D28:E28) -> 2.5423935e+08 | H28: =$D$57*(D28/$D$54) -> 0 | I28: =$E$57*(E28/$E$54) -> -1949086.7
A29: =A28+1 -> 18 | B29: A365P | C29: O.H. Conductors & Devices-Primary | E29: 2.0828835e+08 | F29: =SUM(D29:E29) -> 2.0828835e+08 | H29: =$D$57*(D29/$D$54) -> 0 | I29: =$E$57*(E29/$E$54) -> -1596810.5
A30: =A29+1 -> 19 | B30: A366P | C30: Underground Conduits-Primary | E30: 19362583 | F30: =SUM(D30:E30) -> 19362583 | H30: =$D$57*(D30/$D$54) -> 0 | I30: =$E$57*(E30/$E$54) -> -148440.25
A31: =A30+1 -> 20 | B31: A367P | C31: U.G. Conductors & Devices-Primary | E31: 69074564 | F31: =SUM(D31:E31) -> 69074564 | H31: =$D$57*(D31/$D$54) -> 0 | I31: =$E$57*(E31/$E$54) -> -529549.48
A32: =A31+1 -> 21 | B32: A368P | C32: Line Transformers-Primary | E32: 84244879 | F32: =SUM(D32:E32) -> 84244879 | H32: =$D$57*(D32/$D$54) -> 0 | I32: =$E$57*(E32/$E$54) -> -645850.36
A33: =A32+1 -> 22 | B33: A369 | C33: Services | E33: 1.0815265e+08 | F33: =SUM(D33:E33) -> 1.0815265e+08 | H33: =$D$57*(D33/$D$54) -> 0 | I33: =$E$57*(E33/$E$54) -> -829135.61
A34: =A33+1 -> 23 | B34: A370 | C34: Meters | E34: 1.1953072e+08 | F34: =SUM(D34:E34) -> 1.1953072e+08 | H34: =$D$57*(D34/$D$54) -> 0 | I34: =$E$57*(E34/$E$54) -> -916363.78
A35: =A34+1 -> 24 | B35: A371 | C35: Install. on Customer Prem. | E35: 28587588 | F35: =SUM(D35:E35) -> 28587588 | H35: =$D$57*(D35/$D$54) -> 0 | I35: =$E$57*(E35/$E$54) -> -219162.33
A36: =A35+1 -> 25 | B36: A373 | C36: Street Lights | E36: 20468539 | F36: =SUM(D36:E36) -> 20468539 | H36: =$D$57*(D36/$D$54) -> 0 | I36: =$E$57*(E36/$E$54) -> -156918.9
A37: =A36+1 -> 26 | C37: Subtotal | D37: =SUM(D26:D36) -> 0 | E37: =SUM(E26:E36) -> 9.3825908e+08 | F37: =SUM(F26:F36) -> 9.3825908e+08 | H37: =SUM(H26:H36) -> 0 | I37: =SUM(I26:I36) -> -7193018.4
A38: =A37+1 -> 27
A39: =A38+1 -> 28 | B39: General Plant
A40: =A39+1 -> 29 | B40: Accumulated Depreciation
A41: =A40+1 -> 30 | B41: A390 | C41: Structures and Improvements | D41: 445787.05 | E41: =SUM('[10]II-B-5 Depreciation'!N65:P65) -> 30479347 | F41: =SUM(D41:E41) -> 30925134 | H41: =$D$57*(D41/$D$54) -> -7634.6769 | I41: =$E$57*(E41/$E$54) -> -233665.21
A42: =A41+1 -> 31 | B42: A391 | C42: Office Furniture & Equip. | D42: 2004.85 | E42: =SUM('[10]II-B-5 Depreciation'!N66:P66) -> 419953.3 | F42: =SUM(D42:E42) -> 421958.15 | H42: =$D$57*(D42/$D$54) -> -34.335636 | I42: =$E$57*(E42/$E$54) -> -3219.5072
A43: =A42+1 -> 32 | B43: A392 | C43: Transportation Equipment | D43: 0 | E43: =SUM('[10]II-B-5 Depreciation'!N67:P67) -> 105419.09 | F43: =SUM(D43:E43) -> 105419.09 | H43: =$D$57*(D43/$D$54) -> 0 | I43: =$E$57*(E43/$E$54) -> -808.17918
A44: =A43+1 -> 33 | B44: A393 | C44: Store Equipment | D44: 437.52 | E44: =SUM('[10]II-B-5 Depreciation'!N68:P68) -> 473216.24 | F44: =SUM(D44:E44) -> 473653.76 | H44: =$D$57*(D44/$D$54) -> -7.493093 | I44: =$E$57*(E44/$E$54) -> -3627.8392
A45: =A44+1 -> 34 | B45: A394 | C45: Tools, Shop & Garage Equip. | D45: 3198759.9 | E45: =SUM('[10]II-B-5 Depreciation'!N69:P69) -> 5791609.5 | F45: =SUM(D45:E45) -> 8990369.4 | H45: =$D$57*(D45/$D$54) -> -54782.879 | I45: =$E$57*(E45/$E$54) -> -44400.48
A46: =A45+1 -> 35 | B46: A395 | C46: Laboratory Equipment | D46: 1465.2 | E46: =SUM('[10]II-B-5 Depreciation'!N70:P70) -> 13453.838 | F46: =SUM(D46:E46) -> 14919.038 | H46: =$D$57*(D46/$D$54) -> -25.093435 | I46: =$E$57*(E46/$E$54) -> -103.14177
A47: =A46+1 -> 36 | B47: A396 | C47: Power Operated Equipment | D47: 0 | E47: =SUM('[10]II-B-5 Depreciation'!N71:P71) -> -123.45356 | F47: =SUM(D47:E47) -> -123.45356 | H47: =$D$57*(D47/$D$54) -> 0 | I47: =$E$57*(E47/$E$54) -> 0.94643768
A48: =A47+1 -> 37 | C48: Subtotal | D48: =SUM(D41:D47) -> 3648454.5 | E48: =SUM(E41:E47) -> 37282876 | F48: =SUM(F41:F47) -> 40931330 | H48: =SUM(H41:H47) -> -62484.478 | I48: =SUM(I41:I47) -> -285823.41
A49: =A48+1 -> 38
A50: =A49+1 -> 39 | B50: A397 | C50: Communication Equipment | D50: 7557170.3 | E50: =SUM('[10]II-B-5 Depreciation'!N74:P74) -> 35206738 | F50: =SUM(D50:E50) -> 42763908 | H50: =$D$57*(D50/$D$54) -> -129426.27 | I50: =$E$57*(E50/$E$54) -> -269907.02
A51: =A50+1 -> 40 | B51: A398 | C51: Misc. Equipment | D51: 300648.63 | E51: =SUM('[10]II-B-5 Depreciation'!N75:P75) -> 1796231.2 | F51: =SUM(D51:E51) -> 2096879.8 | H51: =$D$57*(D51/$D$54) -> -5148.9947 | I51: =$E$57*(E51/$E$54) -> -13770.529
A52: =A51+1 -> 41 | C52: Subtotal | D52: =SUM(D50:D51) -> 7857818.9 | E52: =SUM(E50:E51) -> 37002969 | F52: =SUM(F50:F51) -> 44860788 | H52: =SUM(H50:H51) -> -134575.26 | I52: =SUM(I50:I51) -> -283677.55
A53: =A52+1 -> 42
A54: =A53+1 -> 43 | B54: Total | D54: =D52+D48+D37+D22 -> 3.2193199e+08 | E54: =E52+E48+E37+E22 -> 1.0125449e+09 | F54: =F52+F48+F37+F22 -> 1.3344769e+09 | H54: =H52+H48+H37+H22 -> -5513499.6 | I54: =I52+I48+I37+I22 -> -7762519.3
A55: =A54+1 -> 44
A56: =A55+1 -> 45
A57: =A56+1 -> 46 | B57: RWIP Balance as of 12/31/2018 | D57: -5513499.6 | E57: -7762519.3

Sheet WP II-B-9.1 D Lead Lag
I1: WP II-B-9.1
A2: PUBLIC UTILITY COMMISSION OF TEXAS
A3: AEP TEXAS INC - CENTRAL DIVISION
A4: LEAD/LAG STUDY RESULTS
A5: FOR THE TEST YEAR ENDED December 31, 2018
A8: Line | C8: Adjusted Test | E8: Avg. Daily | F8: Revenue | G8: Expense | H8: Net | I8: Working Capital
A9: No. | B9: Description | C9: Year Amount | D9: Prepayments | E9: Expense | F9: Lag Days | G9: Lead Days | H9: (Lead)/Lag | I9: Requirement
B10: (a) | C10: (b) | E10: (c) | F10: (d) | G10: (e) | H10: (f) | I10: (g)
A11: 1
A12: =+A11+1 -> 2 | B12: Operation & Maintenance Expense | C12: =+'[10]II-D-2 A&G'!N29+'[10]II-D-2 A&G'!O29+'[10]II-D-2 A&G'!P29-C14-C13 -> 1.3176422e+08 | D12: ='[11]TCC - DIST'!$D$29 -> 3454946.1 | E12: =(C12-D12)/365 -> 351532.25 | F12: ='[11]TCC - DIST'!$C$12 -> 59.16 | G12: ='[11]TCC - DIST'!$D$14 -> -30 | H12: =F12+G12 -> 29.16 | I12: =E12*H12 -> 10250681
A13: =+A12+1 -> 3 | B13: Transmission Expense | C13: ='[10]II-D-1 O&M'!N22 -> 202266.41 | E13: =(C13-D13)/365 -> 554.15455 | F13: =F12 -> 59.16 | G13: ='[11]TCC - DIST'!$D$12 -> -50.21 | H13: =F13+G13 -> 8.95 | I13: =E13*H13 -> 4959.6832
A14: =+A13+1 -> 4 | B14: Incentive Compensation | C14: 4990169.5 | E14: =(C14-D14)/365 -> 13671.697 | F14: =F12 -> 59.16 | G14: ='[11]TCC - DIST'!$D$13 -> -247.74 | H14: =F14+G14 -> -188.58 | I14: =E14*H14 -> -2578208.7
A15: =+A14+1 -> 5 | C15: =SUM(C12:C14) -> 1.3695665e+08 | I15: =SUM(I12:I14) -> 7677431.5
A16: =+A15+1 -> 6 | B16: Federal Income Taxes
A17: =+A16+1 -> 7 | B17: Current | C17: ='[10]II-E-3.15'!$J$127 -> 12572668 | E17: =C17/365 -> 34445.666 | F17: =F12 -> 59.16 | G17: ='[11]TCC - DIST'!$D$17 -> -37 | H17: =F17+G17 -> 22.16 | I17: =E17*H17 -> 763315.96
A18: =+A17+1 -> 8 | B18: Deferred | C18: =+'[10]II-E-3.15'!J129+'[10]II-E-3.15'!J136 -> 4023787.4 | E18: =C18/365 -> 11024.075 | F18: 0 | G18: ='[12]DIST - Results'!D15 -> 0 | H18: =F18+G18 -> 0 | I18: =E18*H18 -> 0
A19: =+A18+1 -> 9 | B19: Total FIT | C19: =SUM(C17:C18) -> 16596455 | D19: =SUM(D17:D18) -> 0 | I19: =SUM(I17:I18) -> 763315.96
A20: =+A19+1 -> 10
A21: =+A20+1 -> 11 | B21: Taxes Other Than Income Taxes | C21: =+'[10]II-E-2 Taxes Other'!O41+'[10]II-E-2 Taxes Other'!P41+'[10]II-E-2 Taxes Other'!Q41 -> 88812349 | D21: 0 | E21: =(C21-D21)/365 -> 243321.51 | F21: =F12 -> 59.16 | G21: ='[11]TCC - DIST'!$D$21 -> -106 | H21: =F21+G21 -> -46.84 | I21: =E21*H21 -> -11397179
A22: =+A21+1 -> 12
A23: =+A22+1 -> 13 | B23: Depreciation Expense | C23: =+'[10]II-E-1 Dep. Exp.'!N68+'[10]II-E-1 Dep. Exp.'!O68+'[10]II-E-1 Dep. Exp.'!P68 -> 1.3349303e+08 | E23: =C23/365 -> 365734.32 | F23: 0 | G23: ='[12]DIST - Results'!D20 -> 0 | H23: =F23+G23 -> 0 | I23: =E23*H23 -> 0
A24: =+A23+1 -> 14
A25: =+A24+1 -> 15 | B25: ERCOT Matrix Expense-Rider | C25: 0 | E25: =(C25-D25)/365 -> 0 | F25: 58.51 | G25: -53.92 | H25: =F25+G25 -> 4.59 | I25: =E25*H25 -> 0
A26: =+A25+1 -> 16 | B26: Current FIT - ERCOT Matrix Expense-Rider | C26: 0 | E26: =C26/365 -> 0 | F26: 58.51 | G26: =+G17 -> -37 | H26: =F26+G26 -> 21.51 | I26: =E26*H26 -> 0
A27: =+A26+1 -> 17
A28: =+A27+1 -> 18
A29: =+A28+1 -> 19 | B29: Return | C29: ='[10]I-A-1'!$K$36 -> 4.9378258e+08 | E29: =C29/365 -> 1352829 | F29: 0 | G29: ='[12]DIST - Results'!D22 -> 0 | H29: =F29+G29 -> 0 | I29: =E29*H29 -> 0
A30: =+A29+1 -> 20
A31: =+A30+1 -> 21 | C31: =SUM(C21:C29)+C15+C19 -> 8.6964107e+08 | D31: =SUM(D19:D29)+D12 -> 3454946.1 | I31: =SUM(I21:I29)+I15+I19 -> -2956431.8
A32: =+A31+1 -> 22
A33: =+A32+1 -> 23 | B33: Average Daily Bank Balances | I33: 0
A34: =+A33+1 -> 24 | B34: Working Funds and Other | I34: -176903
A35: =+A34+1 -> 25
A36: =+A35+1 -> 26 | I36: =SUM(I31:I34) -> -3133334.8
B39: Purpose: To calculate current cash working capital fot the Distribution function.

Sheet WP II-B-9.2 T Lead Lag
I1: WP II-B-9.2
A2: PUBLIC UTILITY COMMISSION OF TEXAS
A3: AEP TEXAS INC - CENTRAL DIVISION
A4: LEAD/LAG STUDY RESULTS
A5: FOR THE TEST YEAR ENDED December 31, 2018
A8: Line | C8: Adjusted Test | E8: Avg. Daily | F8: Revenue | G8: Expense | H8: Net | I8: Working Capital
A9: No. | B9: Description | C9: Year Amount | D9: Prepayments | E9: Expense | F9: Lag Days | G9: Lead Days | H9: (Lead)/Lag | I9: Requirement
B10: (a) | C10: (b) | E10: (c) | F10: (d) | G10: (e) | H10: (f) | I10: (g)
A11: 1
A12: 2 | B12: Operation & Maintenance Expense | C12: =+'[10]II-D-2 A&G'!M29-C14-C13 -> 42228509 | D12: ='[11]TCC - TRAN'!$D$28 -> 1112957.9 | E12: =(C12-D12)/365 -> 112645.35 | F12: ='[11]TCC - TRAN'!$C$13 -> 57.258333 | G12: ='[11]TCC - TRAN'!$D$14 -> -39.23 | H12: =F12+G12 -> 18.028333 | I12: =E12*H12 -> 2030807.9
A13: 2 | B13: Transmission Expense | C13: 0 | E13: =(C13-D13)/365 -> 0 | H13: =F13+G13 -> 0 | I13: =E13*H13 -> 0
A14: 2 | B14: Incentive Compensation | C14: 469830.95 | E14: =(C14-D14)/365 -> 1287.2081 | F14: =F12 -> 57.258333 | G14: ='[11]TCC - TRAN'!$D$13 -> -249.62 | H14: =F14+G14 -> -192.36167 | I14: =E14*H14 -> -247609.49
A15: 2 | C15: =SUM(C12:C14) -> 42698340 | I15: =SUM(I12:I14) -> 1783198.4
A16: 2
A17: 2 | B17: Federal Income Taxes
A18: 2 | B18: Current | C18: ='[10]II-E-3.15'!I127 -> -6149913.1 | E18: =C18/365 -> -16849.077 | F18: =F12 -> 57.258333 | G18: ='[11]TCC - TRAN'!$D$17 -> -37 | H18: =F18+G18 -> 20.258333 | I18: =E18*H18 -> -341334.22
A19: 2 | B19: Deferred | C19: ='[10]II-E-3.15'!$I$136+'[10]II-E-3.15'!I129 -> 27953770 | E19: =C19/365 -> 76585.671 | F19: 0 | G19: 0 | H19: =F19+G19 -> 0 | I19: =E19*H19 -> 0
A20: 2 | B20: Total FIT | C20: =SUM(C18:C19) -> 21803857 | D20: =SUM(D18:D19) -> 0 | I20: =I18+I19 -> -341334.22
A21: 2
A22: 2 | B22: Taxes Other Than Income Taxes | C22: =+'[10]II-E-2 Taxes Other'!N41 -> 27485447 | D22: 0 | E22: =(C22-D22)/365 -> 75302.596 | F22: =F12 -> 57.258333 | G22: ='[11]TCC - TRAN'!$D$21 -> -192.43 | H22: =F22+G22 -> -135.17167 | I22: =E22*H22 -> -10178777
A23: 2
A24: 2 | B24: Depreciation Expense | C24: =+'[10]II-E-1 Dep. Exp.'!M68 -> 58732005 | E24: =C24/365 -> 160909.6 | F24: 0 | G24: 0 | H24: =F24+G24 -> 0 | I24: =E24*H24 -> 0
A25: 2
A26: 2 | B26: Return | C26: ='[10]II-B'!G39 -> 1.2835301e+08 | E26: =C26/365 -> 351652.09 | F26: 0 | G26: 0 | H26: =F26+G26 -> 0 | I26: =E26*H26 -> 0
A27: 2
A28: 2 | C28: =SUM(C20:C26)+C15 -> 2.7907266e+08 | D28: =SUM(D20:D26)+D12 -> 1112957.9 | I28: =SUM(I20:I26)+I15 -> -8736913.2
A29: 2
A30: 2 | B30: Average Daily Bank Balances | I30: 0
A31: 2 | B31: Working Funds and Other | I31: -156593
A32: 2
A33: 2 | I33: =SUM(I28:I31) -> -8893506.2
B35: Purpose: To calculate current cash working capital fot the Distribution function.

Sheet WP II-D-1-1 Payroll
A1: PUBLIC UTILITY COMMISSION OF TEXAS | F1: WP II-D-1-1
A2: AEP TEXAS INC - CENTRAL DIVISION
A3: BASE PAYROLL EXPENSE ADJUSTMENT
A4: TEST YEAR ENDING 12/31/2018
A8: Line | B8: Description | C8: Account | D8: Test Year | E8: Projected | F8: Adjustment
A9: 1
A10: =A9+1 -> 2 | B10: Adjust Distibution Payroll Expense
A11: =A10+1 -> 3 | C11: 5800 | D11: 2338270.7 | E11: 2446265.9 | F11: =E11-D11 -> 107995.2
A12: =A11+1 -> 4 | C12: 5810 | D12: 2694435.5 | E12: 2818880.5 | F12: =E12-D12 -> 124445
A13: =A12+1 -> 5 | C13: 5820 | D13: 159806.21 | E13: 167187 | F13: =E13-D13 -> 7380.7976
A14: =A13+1 -> 6 | C14: 5830 | D14: -2555924.1 | E14: -2673971.8 | F14: =E14-D14 -> -118047.72
A15: =A14+1 -> 7 | C15: 5840 | D15: 110216.6 | E15: 115307.06 | F15: =E15-D15 -> 5090.4559
A16: =A15+1 -> 8 | C16: 5850 | D16: 24049.947 | E16: 25160.716 | F16: =E16-D16 -> 1110.7691
A17: =A16+1 -> 9 | C17: 5860 | D17: 3411971.9 | E17: 3569557 | F17: =E17-D17 -> 157585.08
A18: =A17+1 -> 10 | C18: 5870 | D18: 803431.1 | E18: 840538.3 | F18: =E18-D18 -> 37107.209
A19: =A18+1 -> 11 | C19: 5880 | D19: 7536290.6 | E19: 7884361.2 | F19: =E19-D19 -> 348070.56
A20: =A19+1 -> 12 | C20: 5900 | D20: 70346.487 | E20: 73595.505 | F20: =E20-D20 -> 3249.0177
A21: =A20+1 -> 13 | C21: 5910 | D21: 11.98458 | E21: 12.538099 | F21: =E21-D21 -> 0.55351894
A22: =A21+1 -> 14 | C22: 5920 | D22: -7268.6426 | E22: -7604.3516 | F22: =E22-D22 -> -335.70899
... A40: =A39+1 -> 32 | C40: 9350 | D40: 2292241.9 | E40: 2398111.2 | F40: =E40-D40 -> 105869.31
A41: =A40+1 -> 33 | C41: Total | D41: =SUM(D11:D40) -> 33046375 | E41: =SUM(E11:E40) -> 34572652 | F41: =SUM(F11:F40) -> 1526277.4
A42: =A41+1 -> 34
A43: =A42+1 -> 35 | B43: Adjust Transmission Payroll Expense
A44: =A43+1 -> 36 | C44: 5600 | D44: 1165459.9 | E44: 1197527.8 | F44: =E44-D44 -> 32067.93
A45: =A44+1 -> 37 | C45: 5612 | D45: 70126.638 | E45: 72056.191 | F45: =E45-D45 -> 1929.5526
A46: =A45+1 -> 38 | C46: 5620 | D46: 626029.43 | E46: 643254.79 | F46: =E46-D46 -> 17225.361
A47: =A46+1 -> 39 | C47: 5630 | D47: 23690.988 | E47: 24342.852 | F47: =E47-D47 -> 651.86366
A48: =A47+1 -> 40 | C48: 5660 | D48: 512752.5 | E48: 526861.01 | F48: =E48-D48 -> 14108.517
A49: =A48+1 -> 41 | C49: 5680 | D49: 2900.367 | E49: 2980.1713 | F49: =E49-D49 -> 79.804346
A50: =A49+1 -> 42 | C50: 5690 | D50: 785.03842 | E50: 806.63895 | F50: =E50-D50 -> 21.600535
A51: =A50+1 -> 43 | C51: 5700 | D51: 1758413.4 | E51: 1806796.6 | F51: =E51-D51 -> 48383.199
A52: =A51+1 -> 44 | C52: 5710 | D52: 447611.03 | E52: 459927.16 | F52: =E52-D52 -> 12316.133
A53: =A52+1 -> 45 | C53: 5730 | D53: 5520.8692 | E53: 5672.7774 | F53: =E53-D53 -> 151.90814
A54: =A53+1 -> 46 | C54: 9200 | D54: 1431.5424 | E54: 1470.9317 | F54: =E54-D54 -> 39.38926
A55: =A54+1 -> 47 | C55: 9302 | D55: 575.04077 | E55: 590.86316 | F55: =E55-D55 -> 15.822395
A56: =A55+1 -> 48 | C56: 9350 | D56: 33478.312 | E56: 34399.477 | F56: =E56-D56 -> 921.16441
A57: =A56+1 -> 49 | C57: Total | D57: =SUM(D44:D56) -> 4648775.1 | E57: =SUM(E44:E56) -> 4776687.3 | F57: =SUM(F44:F56) -> 127912.25
A58: =A57+1 -> 50
A59: =A58+1 -> 51 | B59: Combined Distribution and Transmission
A60: =A59+1 -> 52 | C60: 5600 | D60: 1165459.9 | E60: 1197527.8 | F60: =F44 -> 32067.93
A61: =A60+1 -> 53 | C61: 5612 | D61: 70126.638 | E61: 72056.191 | F61: =F45 -> 1929.5526
A62: =A61+1 -> 54 | C62: 5620 | D62: 626029.43 | E62: 643254.79 | F62: =F46 -> 17225.361
A63: =A62+1 -> 55 | C63: 5630 | D63: 23690.988 | E63: 24342.852 | F63: =F47 -> 651.86366
A64: =A63+1 -> 56 | C64: 5660 | D64: 512752.5 | E64: 526861.01 | F64: =F48 -> 14108.517
A65: =A64+1 -> 57 | C65: 5680 | D65: 2900.367 | E65: 2980.1713 | F65: =F49 -> 79.804346
A66: =A65+1 -> 58 | C66: 5690 | D66: 785.03842 | E66: 806.63895 | F66: =F50 -> 21.600535
A67: =A66+1 -> 59 | C67: 5700 | D67: 1758413.4 | E67: 1806796.6 | F67: =F51 -> 48383.199
A68: =A67+1 -> 60 | C68: 5710 | D68: 447611.03 | E68: 459927.16 | F68: =F52 -> 12316.133
A69: =A68+1 -> 61 | C69: 5730 | D69: 5520.8692 | E69: 5672.7774 | F69: =F53 -> 151.90814
A70: =A69+1 -> 62 | C70: 5800 | D70: 2338270.7 | E70: 2446265.9 | F70: =F11 -> 107995.2
A71: =A70+1 -> 63 | C71: 5810 | D71: 2694435.5 | E71: 2818880.5 | F71: =F12 -> 124445
A72: =A71+1 -> 64 | C72: 5820 | D72: 159806.21 | E72: 167187 | F72: =F13 -> 7380.7976
A73: =A72+1 -> 65 | C73: 5830 | D73: -2555924.1 | E73: -2673971.8 | F73: =F14 -> -118047.72
A74: =A73+1 -> 66 | C74: 5840 | D74: 110216.6 | E74: 115307.06 | F74: =F15 -> 5090.4559
A75: =A74+1 -> 67 | C75: 5850 | D75: 24049.947 | E75: 25160.716 | F75: =F16 -> 1110.7691
A76: =A75+1 -> 68 | C76: 5860 | D76: 3411971.9 | E76: 3569557 | F76: =F17 -> 157585.08
A77: =A76+1 -> 69 | C77: 5870 | D77: 803431.1 | E77: 840538.3 | F77: =F18 -> 37107.209
A78: =A77+1 -> 70 | C78: 5880 | D78: 7536290.6 | E78: 7884361.2 | F78: =F19 -> 348070.56
A79: =A78+1 -> 71 | C79: 5900 | D79: 70346.487 | E79: 73595.505 | F79: =F20 -> 3249.0177
A80: =A79+1 -> 72 | C80: 5910 | D80: 11.98458 | E80: 12.538099 | F80: =F21 -> 0.55351894
A81: =A80+1 -> 73 | C81: 5920 | D81: -7268.6426 | E81: -7604.3516 | F81: =F22 -> -335.70899
... A92: =A91+1 -> 84 | C92: 9080 | D92: 1202738.8 | E92: 1258288.4 | F92: =F33 -> 55549.603
A93: =A92+1 -> 85 | C93: 9200 | D93: 5496428.5 | E93: 5750259.4 | F93: =F34+F54 -> 253830.91
A94: =A93+1 -> 86 | C94: 9210 | D94: 9028.8979 | E94: 9445.9059 | F94: =F35 -> 417.00801
A95: =A94+1 -> 87 | C95: 9220 | D95: -4182245.8 | E95: -4375406.7 | F95: =F36 -> -193160.89
A96: =A95+1 -> 88 | C96: 9260 | D96: 5173.7936 | E96: 5412.7501 | F96: =F37 -> 238.95645
A97: =A96+1 -> 89 | C97: 9280 | D97: 115693.92 | E97: 121037.35 | F97: =F38 -> 5343.4309
A98: =A97+1 -> 90 | C98: 9302 | D98: 11340.857 | E98: 11853.908 | F98: =F39+F55 -> 513.05157
A99: =A98+1 -> 91 | C99: 9350 | D99: 2325720.2 | E99: 2432510.7 | F99: =F40+F56 -> 106790.48
A100: =A99+1 -> 92 | B100: Total | D100: =SUM(D60:D99) -> 37695150 | E100: =SUM(E60:E99) -> 39349339 | F100: =SUM(F60:F99) -> 1654189.7
B102: Purpose: To adjust payroll expense to reflect employee levels as of 12/31/2018 increased to include the 3.5%
B103: wage increase planned in 2019.

Sheet WP II-D-1-2 TCOS
B1: PUBLIC UTILITY COMMISSION OF TEXAS | E1: WP II-D-1-2
B2: AEP TEXAS INC - NORTH DIVISION
B3: REMOVE TCOS EXPENSE
B4: TEST YEAR ENDING 12/31/2018
A9: Line No. | B9: DESCRIPTION | C9: Account | D9: Transmission | E9: Distribution
A11: 1 | B11: ERCOT Matrix Expense - Affil | C11: 5650044 | E11: -25078582
A12: 2 | B12: ERCOT Matrix Expense - Non Aff | C12: 5650045 | E12: -2.416774e+08
A14: 3 | D14: =SUM(D11:D13) -> 0 | E14: =SUM(E11:E13) -> -2.6675598e+08
B16: To remove Test Year TCOS Expense recovered through Rider

Sheet WP II-D-1-3 AEPSC
B1: PUBLIC UTILITY COMMISSION OF TEXAS | F1: WP II-D-1-3
B2: AEP TEXAS INC - CENTRAL DIVISION
B3: AEPSC AND AFFILIATE ADJUSTMENT
B4: TEST YEAR ENDING 12/31/2018
A8: Line No. | B8: Description | C8: Account | D8: Transmission | E8: Distribution | F8: Total
A9: 1 | D9: `
A10: =A9+1 -> 2 | B10: Adjust AEPSC billing | C10: 5600 | D10: -103150.97 | E10: -102.11 | F10: =SUM(D10:E10) -> -103253.08
A11: =A10+1 -> 3 | C11: 5612 | D11: 31923.26 | E11: 472.93 | F11: =SUM(D11:E11) -> 32396.19
A12: =A11+1 -> 4 | C12: 5615 | D12: 5658.62 | E12: 220.47 | F12: =SUM(D12:E12) -> 5879.09
A13: =A12+1 -> 5 | C13: 5616 | D13: -2.3 | E13: -2.61 | F13: =SUM(D13:E13) -> -4.91
A14: =A13+1 -> 6 | C14: 5620 | D14: 594.94 | F14: =SUM(D14:E14) -> 594.94
A15: =A14+1 -> 7 | C15: 5630 | D15: -439.64 | E15: -1.29 | F15: =SUM(D15:E15) -> -440.93
A16: =A15+1 -> 8 | C16: 5660 | D16: -66494.35 | E16: -1276.93 | F16: =SUM(D16:E16) -> -67771.28
A17: =A16+1 -> 9 | C17: 5680 | D17: 594.42 | E17: -0.31 | F17: =SUM(D17:E17) -> 594.11
A18: =A17+1 -> 10 | C18: 5690 | D18: 99.09 | F18: =SUM(D18:E18) -> 99.09
A19: =A18+1 -> 11 | C19: 5691 | D19: 210.11 | F19: =SUM(D19:E19) -> 210.11
A20: =A19+1 -> 12 | C20: 5692 | D20: 3281.71 | E20: 13.89 | F20: =SUM(D20:E20) -> 3295.6
A21: =A20+1 -> 13 | C21: 5700 | D21: 4787.86 | E21: -0.17 | F21: =SUM(D21:E21) -> 4787.69
A22: =A21+1 -> 14 | C22: 5710 | D22: -2190.82 | E22: 61.81 | F22: =SUM(D22:E22) -> -2129.01
A23: =A22+1 -> 15 | C23: 5720 | D23: -263.75 | F23: =SUM(D23:E23) -> -263.75
A24: =A23+1 -> 16 | C24: 5730 | D24: -862.69 | E24: -7.06 | F24: =SUM(D24:E24) -> -869.75
A25: =A24+1 -> 17 | C25: 5800 | D25: 730.44 | E25: 23976.4 | F25: =SUM(D25:E25) -> 24706.84
A26: =A25+1 -> 18 | C26: 5820 | D26: 7.07 | E26: -1864.2 | F26: =SUM(D26:E26) -> -1857.13
A27: =A26+1 -> 19 | C27: 5830 | D27: -3777.19 | E27: -1751.68 | F27: =SUM(D27:E27) -> -5528.87
A28: =A27+1 -> 20 | C28: 5840 | E28: 441.44 | F28: =SUM(D28:E28) -> 441.44
A29: =A28+1 -> 21 | C29: 5860 | D29: 39.25 | E29: 31717.47 | F29: =SUM(D29:E29) -> 31756.72
A30: =A29+1 -> 22 | C30: 5880 | D30: 3619.28 | E30: 9025.91 | F30: =SUM(D30:E30) -> 12645.19
A31: =A30+1 -> 23 | C31: 5900 | E31: 417.18 | F31: =SUM(D31:E31) -> 417.18
A32: =A31+1 -> 24 | C32: 5910 | D32: 14.55 | F32: =SUM(D32:E32) -> 14.55
A33: =A32+1 -> 25 | C33: 5920 | D33: -77.84 | E33: -1650.92 | F33: =SUM(D33:E33) -> -1728.76
A34: =A33+1 -> 26 | C34: 5930 | D34: -0.63 | E34: 2210.93 | F34: =SUM(D34:E34) -> 2210.3
A35: =A34+1 -> 27 | C35: 5940 | D35: 0.51 | F35: =SUM(D35:E35) -> 0.51
A36: =A35+1 -> 28 | C36: 5970 | E36: 22.01 | F36: =SUM(D36:E36) -> 22.01
A37: =A36+1 -> 29 | C37: 5980 | D37: -0.25 | E37: -4.45 | F37: =SUM(D37:E37) -> -4.7
A38: =A37+1 -> 30 | C38: 9010 | E38: 2111.82 | F38: =SUM(D38:E38) -> 2111.82
A39: =A38+1 -> 31 | C39: 9020 | D39: 253.39 | E39: 4422.38 | F39: =SUM(D39:E39) -> 4675.77
A40: =A39+1 -> 32 | C40: 9030 | D40: 3628.75 | E40: 115166.31 | F40: =SUM(D40:E40) -> 118795.06
A41: =A40+1 -> 33 | C41: 9050 | E41: 1488.21 | F41: =SUM(D41:E41) -> 1488.21
A42: =A41+1 -> 34 | C42: 9070 | D42: -1.81 | E42: -7526.59 | F42: =SUM(D42:E42) -> -7528.4
A43: =A42+1 -> 35 | C43: 9080 | D43: -0.17 | E43: 100.12 | F43: =SUM(D43:E43) -> 99.95
A44: =A43+1 -> 36 | C44: 9100 | D44: 12.1 | E44: 90.43 | F44: =SUM(D44:E44) -> 102.53
A45: =A44+1 -> 37 | C45: 9120 | D45: -606.24 | E45: -14632.8 | F45: =SUM(D45:E45) -> -15239.04
A46: =A45+1 -> 38 | C46: 9200 | D46: -86741.97 | E46: -110324.37 | F46: =SUM(D46:E46) -> -197066.34
A47: =A46+1 -> 39 | C47: 9210 | D47: -177864.11 | E47: -291678.61 | F47: =SUM(D47:E47) -> -469542.72
A48: =A47+1 -> 40 | C48: 9220 | D48: -188.64 | E48: -188.63 | F48: =SUM(D48:E48) -> -377.27
A49: =A48+1 -> 41 | C49: 9230 | D49: -1089690.7 | E49: -1185099 | F49: =SUM(D49:E49) -> -2274789.7
A50: =A49+1 -> 42 | C50: 9240 | D50: -107.22 | E50: -126.36 | F50: =SUM(D50:E50) -> -233.58
A51: =A50+1 -> 43 | C51: 9250 | D51: -441.24 | E51: -437.28 | F51: =SUM(D51:E51) -> -878.52
A52: =A51+1 -> 44 | C52: 9260 | D52: -66.14 | E52: -220.44 | F52: =SUM(D52:E52) -> -286.58
A53: =A52+1 -> 45 | C53: 9280 | D53: -160113.79 | E53: -543449.66 | F53: =SUM(D53:E53) -> -703563.45
... A56: =A55+1 -> 48 | C56: 9350 | D56: -161.05 | E56: 2208.43 | F56: =SUM(D56:E56) -> 2047.38
A57: =A56+1 -> 49 | B57: Total | D57: =SUM(D10:D56) -> -1632788.8 | E57: =SUM(E10:E56) -> -1957910.5 | F57: =SUM(F10:F56) -> -3590699.4
A58: =A57+1 -> 50
A59: =A58+1 -> 51 | B59: Adjust Affiliate billings | C59: 5600 | D59: -127.38 | F59: =SUM(D59:E59) -> -127.38
A60: =A59+1 -> 52 | C60: 5660 | D60: =-7315.55+0.68 -> -7314.87 | F60: =SUM(D60:E60) -> -7314.87
A61: =A60+1 -> 53 | C61: 5880 | E61: -9353.74 | F61: =SUM(D61:E61) -> -9353.74
A62: =A61+1 -> 54 | C62: 9200 | D62: -5041.98 | E62: -6781.32 | F62: =SUM(D62:E62) -> -11823.3
A63: =A62+1 -> 55 | C63: 9210 | D63: -20.81 | E63: -104.94 | F63: =SUM(D63:E63) -> -125.75
A64: =A63+1 -> 56 | C64: 9230 | D64: -10826.56 | E64: -13625.45 | F64: =SUM(D64:E64) -> -24452.01
A65: =A64+1 -> 57 | C65: 9302 | D65: -880.36 | E65: -1062.03 | F65: =SUM(D65:E65) -> -1942.39
A66: =A65+1 -> 58 | D66: =SUM(D59:D65) -> -24211.96 | E66: =SUM(E59:E65) -> -30927.48 | F66: =SUM(F59:F65) -> -55139.44
A67: =A66+1 -> 59
A68: =A67+1 -> 60 | B68: Total AEPSC and affiliate adjustment | D68: =D66+D57 -> -1657000.8 | E68: =E66+E57 -> -1988838 | F68: =F66+F57 -> -3645838.8
B70: Purpose: To adjust AEPSC and other affiliate billings to AEP Texas Central Division.

Sheet WP II-D-1-4 ICP
A1: PUBLIC UTILITY COMMISSION OF TEXAS | F1: WP II-D-1-4
A2: AEP TEXAS INC - CENTRAL DIVISION
A3: ANNUAL INCENTIVE PLAN EXPENSE ADJUSTMENT
A4: TEST YEAR ENDING 12/31/2018
A8: Line | B8: Description | C8: Account | D8: Test Year | E8: Projected | F8: Adjustment
A9: 1
A10: =A9+1 -> 2 | B10: Adjust Transmission Annual Incentive Plan | C10: 5600 | D10: 135599.2 | E10: 87416.033 | F10: =E10-D10 -> -48183.168
A11: =A10+1 -> 3 | C11: 5612 | D11: 7596.7859 | E11: 4897.3805 | F11: =E11-D11 -> -2699.4054
A12: =A11+1 -> 4 | C12: 5620 | D12: 67713.764 | E12: 43652.681 | F12: =E12-D12 -> -24061.083
A13: =A12+1 -> 5 | C13: 5630 | D13: 32.248956 | E13: 20.789767 | F13: =E13-D13 -> -11.459189
A14: =A13+1 -> 6 | C14: 5660 | D14: 211203.76 | E14: 136208.37 | F14: =E14-D14 -> -74995.399
A15: =A14+1 -> 7 | C15: 5680 | D15: 533.32856 | E15: 343.81815 | F15: =E15-D15 -> -189.5104
A16: =A15+1 -> 8 | C16: 5690 | D16: 505.1387 | E16: 325.64514 | F16: =E16-D16 -> -179.49355
A17: =A16+1 -> 9 | C17: 5700 | D17: 243798.05 | E17: 157168.02 | F17: =E17-D17 -> -86630.026
A18: =A17+1 -> 10 | C18: 5710 | D18: 44247.823 | E18: 28570.322 | F18: =E18-D18 -> -15677.501
A19: =A18+1 -> 11 | C19: 5730 | D19: 187.16602 | E19: 120.65935 | F19: =E19-D19 -> -66.506675
A20: =A19+1 -> 12 | C20: 9200 | D20: 324.35125 | E20: 209.09784 | F20: =E20-D20 -> -115.25341
A21: =A20+1 -> 13 | C21: 9302 | D21: 166.545 | E21: 107.3657 | F21: =E21-D21 -> -59.1793
A22: =A21+1 -> 14 | C22: 9350 | D22: 3829.2024 | E22: 2468.552 | F22: =E22-D22 -> -1360.6504
A23: =A22+1 -> 15 | C23: Total | D23: =SUM(D10:D22) -> 715737.37 | E23: =SUM(E10:E22) -> 461508.73 | F23: =SUM(F10:F22) -> -254228.64
A24: =A23+1 -> 16
A25: =A24+1 -> 17 | B25: Adjust Distribution Annual Incentive Plan | C25: 5800 | D25: 225499.75 | E25: 174534.56 | F25: =E25-D25 -> -50965.191
A26: =A25+1 -> 18 | C26: 5810 | D26: 267328.12 | E26: 211483.04 | F26: =E26-D26 -> -55845.074
A27: =A26+1 -> 19 | C27: 5820 | D27: 24853.986 | E27: 19661.967 | F27: =E27-D27 -> -5192.019
A28: =A27+1 -> 20 | C28: 5830 | D28: 242820.8 | E28: 192094.16 | F28: =E28-D28 -> -50726.639
A29: =A28+1 -> 21 | C29: 5840 | D29: 5440.214 | E29: 4303.7486 | F29: =E29-D29 -> -1136.4654
A30: =A29+1 -> 22 | C30: 5850 | D30: 3325.1971 | E30: 2630.5606 | F30: =E30-D30 -> -694.63655
A31: =A30+1 -> 23 | C31: 5860 | D31: 609934.91 | E31: 486922.96 | F31: =E31-D31 -> -123011.95
A32: =A31+1 -> 24 | C32: 5870 | D32: 67085.457 | E32: 53071.247 | F32: =E32-D32 -> -14014.21
A33: =A32+1 -> 25 | C33: 5880 | D33: 1373030.5 | E33: 1098482.7 | F33: =E33-D33 -> -274547.79
A34: =A33+1 -> 26 | C34: 5900 | D34: 6122.5968 | E34: 6092.7854 | F34: =E34-D34 -> -29.811454
A35: =A34+1 -> 27 | C35: 5920 | D35: -4630.6975 | E35: -2751.4564 | F35: =E35-D35 -> 1879.2411
A36: =A35+1 -> 28 | C36: 5930 | D36: 1360739.2 | E36: 1078872.3 | F36: =E36-D36 -> -281866.87
A37: =A36+1 -> 29 | C37: 5940 | D37: 16316.063 | E37: 12907.623 | F37: =E37-D37 -> -3408.4396
... A52: =A51+1 -> 44 | C52: 9350 | D52: 324729.57 | E52: 215643.73 | F52: =E52-D52 -> -109085.84
A53: =A52+1 -> 45 | C53: Total | D53: =SUM(D25:D52) -> 5699203 | E53: =SUM(E25:E52) -> 4469837.5 | F53: =SUM(F25:F52) -> -1229365.5
A54: =A53+1 -> 46
A55: =A54+1 -> 47 | B55: Total Company Annual Incentive Plan Adj | C55: 5600 | D55: =D10 -> 135599.2 | E55: =E10 -> 87416.033 | F55: =E55-D55 -> -48183.168
A56: =A55+1 -> 48 | C56: 5612 | D56: =D11 -> 7596.7859 | E56: =E11 -> 4897.3805 | F56: =E56-D56 -> -2699.4054
A57: =A56+1 -> 49 | C57: 5620 | D57: =D12 -> 67713.764 | E57: =E12 -> 43652.681 | F57: =E57-D57 -> -24061.083
A58: =A57+1 -> 50 | C58: 5630 | D58: =D13 -> 32.248956 | E58: =E13 -> 20.789767 | F58: =E58-D58 -> -11.459189
A59: =A58+1 -> 51 | C59: 5660 | D59: =D14 -> 211203.76 | E59: =E14 -> 136208.37 | F59: =E59-D59 -> -74995.399
A60: =A59+1 -> 52 | C60: 5680 | D60: =D15 -> 533.32856 | E60: =E15 -> 343.81815 | F60: =E60-D60 -> -189.5104
A61: =A60+1 -> 53 | C61: 5690 | D61: =D16 -> 505.1387 | E61: =E16 -> 325.64514 | F61: =E61-D61 -> -179.49355
A62: =A61+1 -> 54 | C62: 5700 | D62: =D17 -> 243798.05 | E62: =E17 -> 157168.02 | F62: =E62-D62 -> -86630.026
A63: =A62+1 -> 55 | C63: 5710 | D63: =D18 -> 44247.823 | E63: =E18 -> 28570.322 | F63: =E63-D63 -> -15677.501
A64: =A63+1 -> 56 | C64: 5730 | D64: =D19 -> 187.16602 | E64: =E19 -> 120.65935 | F64: =E64-D64 -> -66.506675
A65: =A64+1 -> 57 | C65: 5800 | D65: =D25 -> 225499.75 | E65: =E25 -> 174534.56 | F65: =E65-D65 -> -50965.191
A66: =A65+1 -> 58 | C66: 5810 | D66: =D26 -> 267328.12 | E66: =E26 -> 211483.04 | F66: =E66-D66 -> -55845.074
A67: =A66+1 -> 59 | C67: 5820 | D67: =D27 -> 24853.986 | E67: =E27 -> 19661.967 | F67: =E67-D67 -> -5192.019
A68: =A67+1 -> 60 | C68: 5830 | D68: =D28 -> 242820.8 | E68: =E28 -> 192094.16 | F68: =E68-D68 -> -50726.639
A69: =A68+1 -> 61 | C69: 5840 | D69: =D29 -> 5440.214 | E69: =E29 -> 4303.7486 | F69: =E69-D69 -> -1136.4654
A70: =A69+1 -> 62 | C70: 5850 | D70: =D30 -> 3325.1971 | E70: =E30 -> 2630.5606 | F70: =E70-D70 -> -694.63655
A71: =A70+1 -> 63 | C71: 5860 | D71: =D31 -> 609934.91 | E71: =E31 -> 486922.96 | F71: =E71-D71 -> -123011.95
A72: =A71+1 -> 64 | C72: 5870 | D72: =D32 -> 67085.457 | E72: =E32 -> 53071.247 | F72: =E72-D72 -> -14014.21
A73: =A72+1 -> 65 | C73: 5880 | D73: =D33 -> 1373030.5 | E73: =E33 -> 1098482.7 | F73: =E73-D73 -> -274547.79
A74: =A73+1 -> 66 | C74: 5900 | D74: =D34 -> 6122.5968 | E74: =E34 -> 6092.7854 | F74: =E74-D74 -> -29.811454
A75: =A74+1 -> 67 | C75: 5920 | D75: =D35 -> -4630.6975 | E75: =E35 -> -2751.4564 | F75: =E75-D75 -> 1879.2411
A76: =A75+1 -> 68 | C76: 5930 | D76: =D36 -> 1360739.2 | E76: =E36 -> 1078872.3 | F76: =E76-D76 -> -281866.87
... A86: =A85+1 -> 78 | C86: 9080 | D86: =D46 -> 101229.92 | E86: =E46 -> 80082.903 | F86: =E86-D86 -> -21147.018
A87: =A86+1 -> 79 | C87: 9200 | D87: =D20+D47 -> 526594.95 | E87: =E20+E47 -> 398244.81 | F87: =E87-D87 -> -128350.14
A88: =A87+1 -> 80 | C88: 9210 | D88: =D48 -> 2373.168 | E88: =E48 -> 1566.8144 | F88: =E88-D88 -> -806.35358
A89: =A88+1 -> 81 | C89: 9260 | D89: =D49 -> 460.12574 | E89: =E49 -> 364.00508 | F89: =E89-D89 -> -96.120663
A90: =A89+1 -> 82 | C90: 9280 | D90: =D50 -> 9354.7329 | E90: =E50 -> 7400.5212 | F90: =E90-D90 -> -1954.2118
A91: =A90+1 -> 83 | C91: 9302 | D91: =D51+D21 -> 2927.1893 | E91: =E51+E21 -> 1929.4771 | F91: =E91-D91 -> -997.71216
A92: =A91+1 -> 84 | C92: 9350 | D92: =D52+D22 -> 328558.78 | E92: =E52+E22 -> 218112.29 | F92: =E92-D92 -> -110446.49
A93: =A92+1 -> 85 | C93: Total | D93: =SUM(D55:D92) -> 6414940.3 | E93: =SUM(E55:E92) -> 4931346.2 | F93: =SUM(F55:F92) -> -1483594.1
B95: Adjust annual incentive expense to reflect a payment at a 1.0 target amount

Sheet WP II-D-1-5 LTIP
A1: PUBLIC UTILITY COMMISSION OF TEXAS | F1: WP II-D-1-5
A2: AEP TEXAS INC - CENTRAL DIVISION
A3: LONG TERM INCENTIVE PLAN EXPENSE ADJUSTMENT
A4: TEST YEAR ENDING 12/31/2018
A8: Line | B8: Description | C8: Account | D8: Test Year | E8: Projected | F8: Adjustment
A9: 1
A10: =A9+1 -> 2 | B10: Adjust Transmission Long Term Incentive Plan | C10: 5600 | D10: 1875.7172 | E10: 1540.1889 | F10: =E10-D10 -> -335.52835
A11: =A10+1 -> 3 | C11: 5612 | D11: 93.844799 | E11: 78.309652 | F11: =E11-D11 -> -15.535147
A12: =A11+1 -> 4 | C12: 5620 | D12: 980.48555 | E12: 803.12487 | F12: =E12-D12 -> -177.36068
A13: =A12+1 -> 5 | C13: 5630 | D13: 0.56880646 | E13: 0.44937147 | F13: =E13-D13 -> -0.11943499
A14: =A13+1 -> 6 | C14: 5660 | D14: 1541.8864 | E14: 1131.1264 | F14: =E14-D14 -> -410.76005
A15: =A14+1 -> 7 | C15: 5680 | D15: 8.4760924 | E15: 6.3318971 | F15: =E15-D15 -> -2.1441954
A16: =A15+1 -> 8 | C16: 5690 | D16: 2.3156087 | E16: 1.8538759 | F16: =E16-D16 -> -0.46173275
A17: =A16+1 -> 9 | C17: 5700 | D17: 2759.2045 | E17: 2331.6476 | F17: =E17-D17 -> -427.5569
A18: =A17+1 -> 10 | C18: 5710 | D18: 644.3043 | E18: 522.00107 | F18: =E18-D18 -> -122.30324
A19: =A18+1 -> 11 | C19: 5730 | D19: 5.12832 | E19: 3.7842503 | F19: =E19-D19 -> -1.3440698
A20: =A19+1 -> 12 | C20: 9200 | D20: 2.404584 | E20: 2.213346 | F20: =E20-D20 -> -0.19123799
A21: =A20+1 -> 13 | C21: 9302 | D21: 1.3143944 | E21: 1.0821015 | F21: =E21-D21 -> -0.23229285
A22: =A21+1 -> 14 | C22: 9350 | D22: 45.706615 | E22: 38.309997 | F22: =E22-D22 -> -7.3966184
A23: =A22+1 -> 15 | C23: Total | D23: =SUM(D10:D22) -> 7961.3573 | E23: =SUM(E10:E22) -> 6460.4233 | F23: =SUM(F10:F22) -> -1500.934
A24: =A23+1 -> 16
A25: =A24+1 -> 17 | B25: Adjust Distribution Long Term Incentive Plan | C25: 5800 | D25: 17216.89 | E25: 14311.182 | F25: =E25-D25 -> -2905.7077
A26: =A25+1 -> 18 | C26: 5810 | D26: 25824.593 | E26: 21497.51 | F26: =E26-D26 -> -4327.083
A27: =A26+1 -> 19 | C27: 5820 | D27: 2852.8441 | E27: 2315.15 | F27: =E27-D27 -> -537.69411
A28: =A27+1 -> 20 | C28: 5830 | D28: 27470.216 | E28: 22783.814 | F28: =E28-D28 -> -4686.4025
A29: =A28+1 -> 21 | C29: 5840 | D29: 1092.4206 | E29: 888.99513 | F29: =E29-D29 -> -203.42546
A30: =A29+1 -> 22 | C30: 5850 | D30: 279.4773 | E30: 244.83821 | F30: =E30-D30 -> -34.63909
A31: =A30+1 -> 23 | C31: 5860 | D31: 60523.924 | E31: 50241.095 | F31: =E31-D31 -> -10282.829
A32: =A31+1 -> 24 | C32: 5870 | D32: 7140.9756 | E32: 5926.8449 | F32: =E32-D32 -> -1214.1308
A33: =A32+1 -> 25 | C33: 5880 | D33: 83922.243 | E33: 63549.225 | F33: =E33-D33 -> -20373.018
A34: =A33+1 -> 26 | C34: 5900 | D34: 76.051596 | E34: 61.443911 | F34: =E34-D34 -> -14.607685
A35: =A34+1 -> 27 | C35: 5920 | D35: 98.332019 | E35: 76.228296 | F35: =E35-D35 -> -22.103723
A36: =A35+1 -> 28 | C36: 5930 | D36: 125398.69 | E36: 103099.3 | F36: =E36-D36 -> -22299.39
A37: =A36+1 -> 29 | C37: 5940 | D37: 1254.5125 | E37: 1041.0392 | F37: =E37-D37 -> -213.47327
... A52: =A51+1 -> 44 | C52: 9350 | D52: 19429.324 | E52: 16090.214 | F52: =E52-D52 -> -3339.1107
A53: =A52+1 -> 45 | C53: Total | D53: =SUM(D25:D52) -> 483824.19 | E53: =SUM(E25:E52) -> 393963.07 | F53: =SUM(F25:F52) -> -89861.117
A54: =A53+1 -> 46
A55: =A54+1 -> 47 | B55: Total Company Long Term Incentive Plan Adj | C55: 5600 | D55: =D10 -> 1875.7172 | E55: =E10 -> 1540.1889 | F55: =E55-D55 -> -335.52835
A56: =A55+1 -> 48 | C56: 5612 | D56: =D11 -> 93.844799 | E56: =E11 -> 78.309652 | F56: =E56-D56 -> -15.535147
A57: =A56+1 -> 49 | C57: 5620 | D57: =D12 -> 980.48555 | E57: =E12 -> 803.12487 | F57: =E57-D57 -> -177.36068
A58: =A57+1 -> 50 | C58: 5630 | D58: =D13 -> 0.56880646 | E58: =E13 -> 0.44937147 | F58: =E58-D58 -> -0.11943499
A59: =A58+1 -> 51 | C59: 5660 | D59: =D14 -> 1541.8864 | E59: =E14 -> 1131.1264 | F59: =E59-D59 -> -410.76005
A60: =A59+1 -> 52 | C60: 5680 | D60: =D15 -> 8.4760924 | E60: =E15 -> 6.3318971 | F60: =E60-D60 -> -2.1441954
A61: =A60+1 -> 53 | C61: 5690 | D61: =D16 -> 2.3156087 | E61: =E16 -> 1.8538759 | F61: =E61-D61 -> -0.46173275
A62: =A61+1 -> 54 | C62: 5700 | D62: =D17 -> 2759.2045 | E62: =E17 -> 2331.6476 | F62: =E62-D62 -> -427.5569
A63: =A62+1 -> 55 | C63: 5710 | D63: =D18 -> 644.3043 | E63: =E18 -> 522.00107 | F63: =E63-D63 -> -122.30324
A64: =A63+1 -> 56 | C64: 5730 | D64: =D19 -> 5.12832 | E64: =E19 -> 3.7842503 | F64: =E64-D64 -> -1.3440698
A65: =A64+1 -> 57 | C65: 5800 | D65: =D25 -> 17216.89 | E65: =E25 -> 14311.182 | F65: =E65-D65 -> -2905.7077
A66: =A65+1 -> 58 | C66: 5810 | D66: =D26 -> 25824.593 | E66: =E26 -> 21497.51 | F66: =E66-D66 -> -4327.083
A67: =A66+1 -> 59 | C67: 5820 | D67: =D27 -> 2852.8441 | E67: =E27 -> 2315.15 | F67: =E67-D67 -> -537.69411
A68: =A67+1 -> 60 | C68: 5830 | D68: =D28 -> 27470.216 | E68: =E28 -> 22783.814 | F68: =E68-D68 -> -4686.4025
A69: =A68+1 -> 61 | C69: 5840 | D69: =D29 -> 1092.4206 | E69: =E29 -> 888.99513 | F69: =E69-D69 -> -203.42546
A70: =A69+1 -> 62 | C70: 5850 | D70: =D30 -> 279.4773 | E70: =E30 -> 244.83821 | F70: =E70-D70 -> -34.63909
A71: =A70+1 -> 63 | C71: 5860 | D71: =D31 -> 60523.924 | E71: =E31 -> 50241.095 | F71: =E71-D71 -> -10282.829
A72: =A71+1 -> 64 | C72: 5870 | D72: =D32 -> 7140.9756 | E72: =E32 -> 5926.8449 | F72: =E72-D72 -> -1214.1308
A73: =A72+1 -> 65 | C73: 5880 | D73: =D33 -> 83922.243 | E73: =E33 -> 63549.225 | F73: =E73-D73 -> -20373.018
A74: =A73+1 -> 66 | C74: 5900 | D74: =D34 -> 76.051596 | E74: =E34 -> 61.443911 | F74: =E74-D74 -> -14.607685
A75: =A74+1 -> 67 | C75: 5920 | D75: =D35 -> 98.332019 | E75: =E35 -> 76.228296 | F75: =E75-D75 -> -22.103723
A76: =A75+1 -> 68 | C76: 5930 | D76: =D36 -> 125398.69 | E76: =E36 -> 103099.3 | F76: =E76-D76 -> -22299.39
... A86: =A85+1 -> 78 | C86: 9080 | D86: =D46 -> 10763.097 | E86: =E46 -> 8907.1675 | F86: =E86-D86 -> -1855.9296
A87: =A86+1 -> 79 | C87: 9200 | D87: =D47+D20 -> 44964.546 | E87: =E47+E20 -> 37106.582 | F87: =E87-D87 -> -7857.964
A88: =A87+1 -> 80 | C88: 9210 | D88: =D48 -> 32.83226 | E88: =E48 -> 33.070168 | F88: =E88-D88 -> 0.23790804
A89: =A88+1 -> 81 | C89: 9260 | D89: =D49 -> 14.36457 | E89: =E49 -> 21.819114 | F89: =E89-D89 -> 7.4545441
A90: =A89+1 -> 82 | C90: 9280 | D90: =D50 -> 1265.2094 | E90: =E50 -> 1017.6018 | F90: =E90-D90 -> -247.60758
A91: =A90+1 -> 83 | C91: 9302 | D91: =D51+D21 -> 122.51341 | E91: =E51+E21 -> 103.12561 | F91: =E91-D91 -> -19.3878
A92: =A91+1 -> 84 | C92: 9350 | D92: =D52+D22 -> 19475.031 | E92: =E52+E22 -> 16128.524 | F92: =E92-D92 -> -3346.5073
A93: =A92+1 -> 85 | C93: Total | D93: =SUM(D55:D92) -> 491785.55 | E93: =SUM(E55:E92) -> 400423.5 | F93: =SUM(F55:F92) -> -91362.051
B95: Adjust long term incentive expense to reflect a payment at a 1.0 target amount

Sheet WP II-D-1-6 DSM
A1: PUBLIC UTILITY COMMISSION OF TEXAS | D1: WP II-D-1-6
A2: AEP TEXAS INC - CENTRAL DIVISION
A3: DSM EXPENSE ADJUSTMENT
A4: TEST YEAR ENDING 12/31/2018
A9: DESCRIPTION | B9: Account | C9: Transmission | D9: Distribution
A11: Test Year DSM Expense | B11: 9070001 | D11: =-SUM('[13]TCC 2018'!$E$25,'[13]TCC 2018'!$F$25) -> -13833608
B12: 9070014 | D12: 72975.18
C14: =SUM(C11:C13) -> 0 | D14: =SUM(D11:D13) -> -13760633
A16: To remove Test Year DSM costs recovered through Rider

Sheet WP II-D-1-7 NONRECURRING
A1: PUBLIC UTILITY COMMISSION OF TEXAS | G1: WP/ II-D-1-7
A2: AEP TEXAS INC - CENTRAL DIVISION
A3: WP/ II-D-1-7 RECLASS NONRECURRING ACTIVITY
A4: TEST YEAR ENDING 12/31/2018
A8: Line No. | B8: Account Number | C8: Description | E8: Transmission | F8: Distribution | G8: Total T&D
A10: 1 | B10: 5860 | C10: Meter Expenses | E10: 405000 | F10: -405000 | G10: =+SUM(E10:F10) -> 0
A11: 2 | C11: Correct 2/18 journal id RECLPREPAY, s/b Distribution
A13: 3 | C13: Total | E13: =+SUM(E10:E11) -> 405000 | F13: =+SUM(F10:F11) -> -405000 | G13: =+SUM(G10:G11) -> 0

Sheet WP II-D-1-8 Functionalization
A1: PUBLIC UTILITY COMMISSION OF TEXAS | G1: WP II-D-1-8
A2: AEP TEXAS INC - CENTRAL DIVISION
A3: FUNCTIONALIZE O&M ACTIVITY
A4: TEST YEAR ENDING 12/31/2018
A8: Line | B8: Description | D8: Account | E8: Transmission | F8: Distribution | G8: Total
A9: 1
A10: =A9+1 -> 2 | B10: Adjust Transmission activity recorded in distribution accounts
A11: =A10+1 -> 3 | C11: 580 | D11: Oper Supervision & Engineering | E11: -41186.71 | G11: =SUM(E11:F11) -> -41186.71
A12: =A11+1 -> 4 | C12: 582 | D12: Station Expenses | E12: -11400.12 | G12: =SUM(E12:F12) -> -11400.12
A13: =A12+1 -> 5 | C13: 583 | D13: Overhead Line Expenses | E13: -6830.28 | G13: =SUM(E13:F13) -> -6830.28
A14: =A13+1 -> 6 | C14: 586 | D14: Meter Expenses | E14: -4467.06 | G14: =SUM(E14:F14) -> -4467.06
A15: =A14+1 -> 7 | C15: 588 | D15: Miscellaneous Distribution Exp | E15: -84001.87 | G15: =SUM(E15:F15) -> -84001.87
A16: =A15+1 -> 8 | C16: 590 | D16: Maint Supv & Engineering | E16: 59.59 | G16: =SUM(E16:F16) -> 59.59
A17: =A16+1 -> 9 | C17: 591 | D17: Maintenance of Structures | E17: -10376.63 | G17: =SUM(E17:F17) -> -10376.63
A18: =A17+1 -> 10 | C18: 592 | D18: Maint of Station Equipment | E18: -46287.54 | G18: =SUM(E18:F18) -> -46287.54
A19: =A18+1 -> 11 | C19: 593 | D19: Maintenance of Overhead Lines | E19: -2050.56 | G19: =SUM(E19:F19) -> -2050.56
A20: =A19+1 -> 12 | C20: 598 | D20: Maint of Misc Distribution Plt | E20: -4527.28 | G20: =SUM(E20:F20) -> -4527.28
A21: =A20+1 -> 13 | C21: 560 | D21: Oper Supervision & Engineering | E21: 41186.71 | G21: =SUM(E21:F21) -> 41186.71
A22: =A21+1 -> 14 | C22: 562 | D22: Station Expenses | E22: 11400.12 | G22: =SUM(E22:F22) -> 11400.12
A23: =A22+1 -> 15 | C23: 563 | D23: Overhead Line Expenses | E23: 6830.28 | G23: =SUM(E23:F23) -> 6830.28
A24: =A23+1 -> 16 | C24: 566 | D24: Misc Transmission Expenses | E24: 4467.06 | G24: =SUM(E24:F24) -> 4467.06
A25: =A24+1 -> 17 | C25: 566 | D25: Misc Transmission Expenses | E25: 84001.87 | G25: =SUM(E25:F25) -> 84001.87
A26: =A25+1 -> 18 | C26: 568 | D26: Maint Supv & Engineering | E26: -59.59 | G26: =SUM(E26:F26) -> -59.59
A27: =A26+1 -> 19 | C27: 569 | D27: Maintenance of Structures | E27: 10376.63 | G27: =SUM(E27:F27) -> 10376.63
A28: =A27+1 -> 20 | C28: 570 | D28: Maint of Station Equipment | E28: 46287.54 | G28: =SUM(E28:F28) -> 46287.54
A29: =A28+1 -> 21 | C29: 571 | D29: Maintenance of Overhead Lines | E29: 2050.56 | G29: =SUM(E29:F29) -> 2050.56
A30: =A29+1 -> 22 | C30: 573 | D30: Maint of Misc Trnsmssion Plt | E30: 4527.28 | G30: =SUM(E30:F30) -> 4527.28
A31: =A30+1 -> 23 | C31: Total | E31: =SUM(E11:E30) -> 0 | F31: =SUM(F11:F30) -> 0 | G31: =SUM(G11:G30) -> 0
A32: =A31+1 -> 24
A33: =A32+1 -> 25 | B33: Adjust Distribution activity recorded in transmission accounts
A34: =A33+1 -> 26 | C34: 560 | D34: Oper Supervision & Engineering | F34: -24959.27 | G34: =SUM(E34:F34) -> -24959.27
A35: =A34+1 -> 27 | C35: 561 | D35: Load Dispatching | F35: -32711.23 | G35: =SUM(E35:F35) -> -32711.23
A36: =A35+1 -> 28 | C36: 562 | D36: Station Expenses - Nonassoc | F36: -7751.46 | G36: =SUM(E36:F36) -> -7751.46
A37: =A36+1 -> 29 | C37: 563 | D37: Overhead Line Expenses | F37: -17464.76 | G37: =SUM(E37:F37) -> -17464.76
A38: =A37+1 -> 30 | C38: 566 | D38: Misc Transmission Expenses | F38: -56404.89 | G38: =SUM(E38:F38) -> -56404.89
A39: =A38+1 -> 31 | C39: 568 | D39: Maint Supv & Engineering | F39: -26.67 | G39: =SUM(E39:F39) -> -26.67
A40: =A39+1 -> 32 | C40: 569 | D40: Maintenance of Structures | F40: -5137.54 | G40: =SUM(E40:F40) -> -5137.54
A41: =A40+1 -> 33 | C41: 570 | D41: Maint of Station Equipment | F41: -16019.71 | G41: =SUM(E41:F41) -> -16019.71
A42: =A41+1 -> 34 | C42: 571 | D42: Maintenance of Overhead Lines | F42: 521.55 | G42: =SUM(E42:F42) -> 521.55
A43: =A42+1 -> 35 | C43: 573 | D43: Maint of Misc Trnsmssion Plt | F43: -77.2 | G43: =SUM(E43:F43) -> -77.2
A44: =A43+1 -> 36 | C44: 580 | D44: Oper Supervision & Engineering | F44: 24959.27 | G44: =SUM(E44:F44) -> 24959.27
A45: =A44+1 -> 37 | C45: 581 | D45: Load Dispatching | F45: 32711.23 | G45: =SUM(E45:F45) -> 32711.23
A46: =A45+1 -> 38 | C46: 582 | D46: Station Expenses | F46: 7751.46 | G46: =SUM(E46:F46) -> 7751.46
A47: =A46+1 -> 39 | C47: 583 | D47: Overhead Line Expenses | F47: 17464.76 | G47: =SUM(E47:F47) -> 17464.76
A48: =A47+1 -> 40 | C48: 588 | D48: Miscellaneous Distribution Exp | F48: 56404.89 | G48: =SUM(E48:F48) -> 56404.89
A49: =A48+1 -> 41 | C49: 590 | D49: Maint Supv & Engineering | F49: 26.67 | G49: =SUM(E49:F49) -> 26.67
A50: =A49+1 -> 42 | C50: 591 | D50: Maintenance of Structures | F50: 5137.54 | G50: =SUM(E50:F50) -> 5137.54
A51: =A50+1 -> 43 | C51: 592 | D51: Maint of Station Equipment | F51: 16019.71 | G51: =SUM(E51:F51) -> 16019.71
A52: =A51+1 -> 44 | C52: 593 | D52: Maintenance of Overhead Lines | F52: -521.55 | G52: =SUM(E52:F52) -> -521.55
A53: =A52+1 -> 45 | C53: 598 | D53: Maint of Misc Distribution Plt | F53: 77.2 | G53: =SUM(E53:F53) -> 77.2
A54: =A53+1 -> 46 | E54: =SUM(E34:E53) -> 0 | F54: =SUM(F34:F53) -> 1.4551915e-11 | G54: =SUM(G34:G53) -> 1.4551915e-11
B57: Purpose: To correct coding of O&M expense to appropriate functional accounts

Sheet WP II-D-1-9 Bad Debt
A1: PUBLIC UTILITY COMMISSION OF TEXAS | D1: WP II-D-1-9
A2: AEP TEXAS INC - CENTRAL DIVISION
A3: BAD DEBT EXPENSE ADJUSTMENT
A4: TEST YEAR ENDING 12/31/2018
A7: DESCRIPTION | B7: FERC | C7: Transmission | D7: Distribution
A9: Bad Debt Expense For Test Year | B9: 904 | C9: 2509.02 | D9: 816088.35
A11: Adjustments:
A12: Pro forma Bad Debt Expense Adjustment | C12: ='[14]TCC Test Yr'!$E$17 -> -2500 | D12: ='[14]TCC Test Yr'!$E$99 -> -789340.03
A14: Total Adjustments | C14: =C12 -> -2500 | D14: =D12 -> -789340.03
A16: Pro forma Bad Debt Expense | C16: =SUM(C9:C12) -> 9.02 | D16: =SUM(D9:D12) -> 26748.32
A18: Total Proforma T & D | C18: =SUM(C16:D16) -> 26757.34
A21: Purpose: To adjust bad debt expense to represent actual test year bad debt cost

Sheet WP II-D-1-10 Sales Expenses
A1: PUBLIC UTILITY COMMISSION OF TEXAS | G1: WP/ II-D-1-10
A2: AEP TEXAS INC - CENTRAL DIVISION
A3: WP/ II-D-1-10 ELIMINATION OF SALES EXPENSES
A4: TEST YEAR ENDING 12/31/2018
A8: Line No. | B8: Account Number | C8: Description | E8: Transmission | F8: Distribution | G8: Total T&D
A9: 1 | B9: 9110 | C9: Supervision | E9: 0 | F9: =-13.02+2.26 -> -10.76 | G9: =+SUM(E9:F9) -> -10.76
A10: 2 | B10: 9120 | C10: Demonstrating & Selling Exp | E10: =-10191.47-'[10]Attachment II-D-1 O&M'!$I$146 -> -9585.23 | F10: =-246971.4-'[10]Attachment II-D-1 O&M'!$I$199 -> -232338.6 | G10: =+SUM(E10:F10) -> -241923.83
A12: 3 | C12: Total | E12: =+SUM(E9:E10) -> -9585.23 | F12: =+SUM(F9:F10) -> -232349.36 | G12: =+SUM(G9:G10) -> -241934.59
B22: Purpose: To eliminate Demonstrating & Selling Expenses from Operating Income in accordance with PUC SUBST. R. 25.231(b)(2)(F).

Sheet WP II-D-1-11 EMP EXP
A1: PUBLIC UTILITY COMMISSION OF TEXAS | E1: WP II-D-1-11
A2: AEP TEXAS INC - CENTRAL DIVISION
A3: WP/ II-D-1-11 EMPLOYEE EXPENSE ADJUSTMENT
A4: TEST YEAR ENDING 12/31/2018
A8: Line No. | B8: Account Number | C8: Transmission | D8: Distribution | E8: Total T&D
A9: 1 | B9: 5600 | C9: -647.64 | D9: 0 | E9: =+SUM(C9:D9) -> -647.64
A10: =+A9+1 -> 2 | B10: 5660 | C10: -41.13 | D10: 0 | E10: =+SUM(C10:D10) -> -41.13
A11: =+A10+1 -> 3 | B11: 5800 | C11: 0 | D11: -895.08 | E11: =+SUM(C11:D11) -> -895.08
A12: =+A11+1 -> 4 | B12: 5810 | C12: 0 | D12: -290.14 | E12: =+SUM(C12:D12) -> -290.14
A13: =+A12+1 -> 5 | B13: 5830 | C13: 0 | D13: -52.33 | E13: =+SUM(C13:D13) -> -52.33
A14: =+A13+1 -> 6 | B14: 5840 | C14: 0 | D14: -198.55 | E14: =+SUM(C14:D14) -> -198.55
A15: =+A14+1 -> 7 | B15: 5860 | C15: 0 | D15: -2605.82 | E15: =+SUM(C15:D15) -> -2605.82
A16: =+A15+1 -> 8 | B16: 5880 | C16: 0 | D16: -7906.67 | E16: =+SUM(C16:D16) -> -7906.67
A17: =+A16+1 -> 9 | B17: 5920 | C17: -127.56 | D17: 0 | E17: =+SUM(C17:D17) -> -127.56
A18: =+A17+1 -> 10 | B18: 5930 | C18: 0 | D18: -29.54 | E18: =+SUM(C18:D18) -> -29.54
A19: =+A18+1 -> 11 | B19: 5950 | C19: 0 | D19: -81.46 | E19: =+SUM(C19:D19) -> -81.46
A20: =+A19+1 -> 12 | B20: 9010 | C20: 0 | D20: -173.17 | E20: =+SUM(C20:D20) -> -173.17
A21: =+A20+1 -> 13 | B21: 9030 | C21: 0 | D21: -2142.69 | E21: =+SUM(C21:D21) -> -2142.69
... A26: =+A25+1 -> 18 | B26: 9350 | C26: 0 | D26: -1141.97 | E26: =+SUM(C26:D26) -> -1141.97
A27: Total | C27: =+SUM(C9:C26) -> -816.33 | D27: =+SUM(D9:D26) -> -53613.27 | E27: =+SUM(E9:E26) -> -54429.6
B31: Purpose: To remove employee expenses the Company is not seeking to recover.

Sheet WP II-D-1-12 Distibution OM
A1: PUBLIC UTILITY COMMISSION OF TEXAS | G1: WP/ II-D-1-12
A2: AEP TEXAS INC - CENTRAL DIVISION
A3: WP/ II-D-1-12 DISTRIBUTION O&M EXPENSE
A4: TEST YEAR ENDING 12/31/2018
A8: Line No. | B8: Account Number | C8: Description | E8: Transmission | F8: Distribution | G8: Total T&D
A10: 1 | B10: 5930 | C10: Vegetation Management | F10: 4000000 | G10: =+SUM(E10:F10) -> 4000000
A12: 3 | C12: Total | E12: =+SUM(E10:E10) -> 0 | F12: =+SUM(F10:F10) -> 4000000 | G12: =+SUM(G10:G10) -> 4000000
B22: Purpose: To increase Distribution O&M expense for Vegetation Management expenses as discussed in the Direct testimony of Thomas M. Coad.

Sheet WP II-D-1-13 Tree Trimming
A1: PUBLIC UTILITY COMMISSION OF TEXAS | G1: WP/ II-D-1-13
A2: AEP TEXAS INC - CENTRAL DIVISION
A3: WP/ II-D-1-13 TREE TRIMMING
A4: TEST YEAR ENDING 12/31/2018
A8: Line No. | B8: Account Number | C8: Description | E8: Transmission | F8: Distribution | G8: Total T&D
A10: 1 | B10: 5630 | C10: Tree trimming | E10: 255107 | G10: =+SUM(E10:F10) -> 255107
A11: 2 | B11: 5930 | C11: Tree trimming | F11: 2726923 | G11: =+SUM(E11:F11) -> 2726923
A13: 3 | C13: Total | E13: =+SUM(E10:E11) -> 255107 | F13: =+SUM(F10:F11) -> 2726923 | G13: =+SUM(G10:G11) -> 2982030
B23: Purpose: To increase O&M expense for non-capitalized tree trimming expense as discussed in the Direct testimony of Thomas M. Coad and Daniel R. Boezio.

Sheet WP II-D-2-1 Cr Line Fees
A1: PUBLIC UTILITY COMMISSION OF TEXAS | G1: WP/ II-D-2-1
A2: AEP TEXAS INC - CENTRAL DIVISION
A3: WP/ II-D-2-1 RECLASSIFICATION OF BANK CREDIT FEES
A4: TEST YEAR ENDING 12/31/2018
A8: Line No. | B8: Account Number | C8: Description | E8: Transmission | F8: Distribution | G8: Total T&D
A9: 1 | B9: 9302 | C9: Misc General Expenses | E9: 98080.62 | F9: 121265.57 | G9: =SUM(E9:F9) -> 219346.19
B21: Purpose: To reclassify bank lines of credit expense from interest expense (A/C 4310007) to A&G
B22: Expense (A/C 9302)

Sheet WP II-D-2-2 Catastrophe reserve
B1: PUBLIC UTILITY COMMISSION OF TEXAS | F1: WP/ II-D-2-x
B2: AEP TEXAS INC - CENTRAL DIVISION
B3: WP/ II-D-2-2 Catastrophe Rreserve Expense
B4: TEST YEAR ENDING 12/31/2018
A8: Line No. | B8: Account Number | C8: Description | D8: Transmission | E8: Distribution | F8: Total T&D
A9: 1 | B9: 1823 | C9: Filed Reserve Amount | D9: -4536379 | E9: 13719898 | F9: =SUM(D9:E9) -> 9183518.5
A10: 2 | B10: 1823 | C10: Target Reserve | D10: ='[15]Pro-Forma Adjustment'!$D$10 -> 160445.36 | E10: ='[15]Pro-Forma Adjustment'!$E$10 -> 10439555 | F10: =SUM(D10:E10) -> 10600000
A11: 3 | B11: 1823 | C11: Adjustment | D11: =D10-D9 -> 4696824.4 | E11: =E10-E9 -> -3280342.9 | F11: =SUM(D11:E11) -> 1416481.5
A12: 4 | B12: N/A | C12: Amortization Period | D12: 3 | E12: 3 | F12: 3
A13: 5 | B13: 924 | C13: Pro-Forma Adjustment To Build Storm Reserve | D13: =D11/D12 -> 1565608.1 | E13: =E11/E12 -> -1093447.6 | F13: =SUM(D13:E13) -> 472160.5
A15: 6 | B15: 924 | C15: Adjustment Annual Storm | D15: ='[15]Pro-Forma Adjustment'!$D$15 -> 35570.435 | E15: ='[15]Pro-Forma Adjustment'!$E$15 -> 2314429.6 | F15: =D15+E15 -> 2350000
A16: 7 | B16: 924 | C16: Total Reserve Amount | D16: =D13+D15 -> 1601178.6 | E16: =E13+E15 -> 1220981.9 | F16: =F13+F15 -> 2822160.5
A17: 8 | B17: 924 | C17: Amount in Test Year | D17: -126918 | E17: -1173082 | F17: =SUM(D17:E17) -> -1300000
A18: 9 | B18: 924 | C18: Pro-Forma Adjustment | D18: =D16+D17 -> 1474260.6 | E18: =E16+E17 -> 47899.972 | F18: =F16+F17 -> 1522160.5
B21: Purpose: To increase catastrophe reserve expense as discussed in the direct testimony of Randall W. Hamlett.

Sheet WP II-D-2-3 ASC 715-30 Pension
A1: PUBLIC UTILITY COMMISSION OF TEXAS | G1: WP/ II-D-2-3
A2: AEP TEXAS INC - CENTRAL DIVISION
A3: WP/ II-D-2-3 ASC 715-30 (SFAS 87) PENSION EXPENSE
A4: TEST YEAR ENDING 12/31/2018
A8: Line No. | B8: Account Number | C8: Description | D8: Reference | E8: Transmission | F8: Distribution | G8: Total T&D
A9: 1 | B9: Pension Expense Per Books For TY Ending 12/31/18
A10: =A9+1 -> 2 | B10: 9260003 | C10: Pension Plan | E10: 998625 | F10: 5942629 | G10: =+SUM(E10:F10) -> 6941254
A11: =A10+1 -> 3 | B11: 9260037 | C11: Supplemental Pension | F11: 21570 | G11: =+SUM(F11:F11) -> 21570
A12: =A11+1 -> 4 | B12: 9260042 | C12: SERP Pension - Non-Service | F12: 184591 | G12: =+SUM(F12:F12) -> 184591
A13: =A12+1 -> 5 | B13: 9260050 | C13: Frg Ben Loading - Pension | E13: -682770.93 | F13: -2546376.6 | G13: =+SUM(E13:F13) -> -3229147.5
A14: =A13+1 -> 6 | B14: 9260062 | C14: Pension Plan - Non-Service | E14: -110011.06 | F14: -1886067 | G14: =+SUM(E14:F14) -> -1996078.1
A15: =A14+1 -> 7 | C15: Test Year SFAS 87 Pension Expense | E15: =SUM(E10:E14) -> 205843.01 | F15: =SUM(F10:F14) -> 1716346.4 | G15: =SUM(G10:G14) -> 1922189.4
A16: =A15+1 -> 8
A17: =A16+1 -> 9 | B17: Gross Pension Expense | G17: =+SUM(G10:G12)+SUM(G14) -> 5151336.9
A18: =A17+1 -> 10
A19: =A18+1 -> 11 | B19: 2019 Actuarial Estimate
A20: =A19+1 -> 12 | C20: 2019 ASC 715-30 (SFAS 87) Pension Cost | D20: Qualfd Rpt | E20: 831000 | F20: 3354000 | G20: =+SUM(E20:F20) -> 4185000
A21: =A20+1 -> 13 | C21: 2019 ASC 715-30 (SFAS 87) SERP Cost | D21: SERP Rpt | E21: 0 | F21: 179000 | G21: =+SUM(E21:F21) -> 179000
A22: =A21+1 -> 14 | E22: =SUM(E20:E21) -> 831000 | F22: =SUM(F20:F21) -> 3533000 | G22: =SUM(G20:G21) -> 4364000
A23: =A22+1 -> 15
A24: =A23+1 -> 16 | B24: 2018 Payroll Expense Ratio | E24: ='[10]II-D-3.4 Exp vs Capital'!$C$24/'[10]II-D-3.4 Exp vs Capital'!$F$24 -> 0.30070909 | F24: ='[10]II-D-3.4 Exp vs Capital'!$AD$24/'[10]II-D-3.4 Exp vs Capital'!$AG$24 -> 0.446763
A25: =A24+1 -> 17 | B25: 2018 Pension Cost Expense | E25: =+E22*E24 -> 249889.25 | F25: =+F22*F24 -> 1578413.7 | G25: =SUM(E25:F25) -> 1828302.9
A26: =A25+1 -> 18
A27: =A26+1 -> 19
A28: =A27+1 -> 20 | B28: Increase (Decrease) to TY Expense | D28: 926 | E28: =+E25-E15 -> 44046.243 | F28: =+F25-F15 -> -137932.71 | G28: =+G25-G15 -> -93886.471
B31: Purpose: To adjust pension expense to reflect current actuarial reports

Sheet WP II-D-2-4 ASC 715 OPEB
A1: PUBLIC UTILITY COMMISSION OF TEXAS | G1: WP/ II-D-2-4
A2: AEP TEXAS INC - CENTRAL DIVISION
A3: WP/ II-D-2-4 ASC 715 (SFAS 106) ADUSTMENT
A4: TEST YEAR ENDING 12/31/2018
A8: Line No. | B8: Account Number | C8: Description | D8: Reference | E8: Transmission | F8: Distribution | G8: Total T&D
A9: 1 | C9: 2019 ASC 715 (SFAS 106) Net Periodic Cost-Net of Medicare Subsidy | D9: Non-UMWA | E9: -455000 | F9: -4733000 | G9: =SUM(E9:F9) -> -5188000
A10: =A9+1 -> 2 | C10: Payroll Expense Ratio | D10: II-D-3-4 | E10: ='[10]II-D-3.4 Exp vs Capital'!$C$24/'[10]II-D-3.4 Exp vs Capital'!$F$24 -> 0.30070909 | F10: ='[10]II-D-3.4 Exp vs Capital'!$AD$24/'[10]II-D-3.4 Exp vs Capital'!$AG$24 -> 0.446763
A11: =A10+1 -> 3 | C11: 2019 ASC 715 (SFAS 106) Expense | D11: (a) | E11: =+E9*E10 -> -136822.64 | F11: =+F9*F10 -> -2114529.3 | G11: =SUM(E11:F11) -> -2251351.9
A12: =A11+1 -> 4
A13: =A12+1 -> 5 | B13: 9260021 | C13: ASC 715 (SFAS 106) OPEB | E13: 86465.03 | F13: 588695.03 | G13: =SUM(E13:F13) -> 675160.06
A14: =A13+1 -> 6 | B14: 9260043 | C14: OPEB Non-Service | E14: -663769.07 | F14: -6548251 | G14: =SUM(E14:F14) -> -7212020
A15: =A14+1 -> 7 | B15: 9260053 | C15: Capitalized ASC 715 (SFAS 106) OPEB | D15: WP II-D-2-4-1 | E15: ='WP II-D-2-4-1 OPEB_FAS 112'!F20 -> -34771.539 | F15: ='WP II-D-2-4-1 OPEB_FAS 112'!F12 -> -12698.184 | G15: =SUM(E15:F15) -> -47469.722
A16: =A15+1 -> 8 | B16: 9260060 | C16: Amort-Post Retirement Benefit | E16: 52826.52 | F16: 478915.8 | G16: =SUM(E16:F16) -> 531742.32
A17: =A16+1 -> 9 | C17: Test Year OPEB expense | D17: (b) | E17: =SUM(E13:E16) -> -559249.06 | F17: =SUM(F13:F16) -> -5493338.3 | G17: =SUM(G13:G16) -> -6052587.4
A18: =A17+1 -> 10
A19: =A18+1 -> 11 | C19: Increase / (Decrease) in OPEB Expense | D19: (a) - (b) | E19: =E11-E17 -> 422426.42 | F19: =F11-F17 -> 3378809 | G19: =G11-G17 -> 3801235.4
B26: Purpose: Adjust ASC 715 (SFAS 106) Cost to 2019 Willis Towers Watson Actuarial Estimate

Sheet WP II-D-2-4-1 OPEB_FAS 112
A1: PUBLIC UTILITY COMMISSION OF TEXAS | G1: WP/ II-D-2-4-1
A2: AEP TEXAS INC - CENTRAL DIVISION
A3: WP/ II-D-2-4-1 SEPARATION OF ACCOUNT 9260053
A4: TEST YEAR ENDING 12/31/2018
A8: Line | D8: Test Year | E8: % | F8: Allocation of
A9: No | D9: Expense | F9: Capitalized Amt
A10: 1 | B10: DISTRIBUTION
A11: =A10+1 -> 2 | B11: Test year expense
A12: =A11+1 -> 3 | C12: 9260021 OPEB- Service Cost | D12: 86465.03 | E12: =D12/D14 -> -0.037500328 | F12: =E12*F16 -> -12698.184
A13: =A12+1 -> 4 | C13: 9260040 SFAS 112 Post Employment | D13: -2392179 | E13: =D13/D14 -> 1.0375003 | F13: =E13*F16 -> 351313.45
A14: =A13+1 -> 5 | D14: =SUM(D12:D13) -> -2305714 | F14: =SUM(F12:F13) -> 338615.27
A15: =A14+1 -> 6
A16: =A15+1 -> 7 | C16: 9260053 Frg Ben Loading - OPEB | F16: 338615.27
A17: =A16+1 -> 8
A18: =A17+1 -> 9 | B18: TRANSMISSION
A19: =A18+1 -> 10 | B19: Test year expense
A20: =A19+1 -> 11 | C20: 9260021 OPEB- Service Cost | D20: 86465.03 | E20: =D20/D22 -> -0.17533568 | F20: =E20*F24 -> -34771.539
A21: =A20+1 -> 12 | C21: 9260040 SFAS 112 Post Employment | D21: -579605 | E21: =D21/D22 -> 1.1753357 | F21: =E21*F24 -> 233085.65
A22: =A21+1 -> 13 | D22: =+D20+D21 -> -493139.97 | F22: =SUM(F20:F21) -> 198314.11
A23: =A22+1 -> 14
A24: =A23+1 -> 15 | C24: 9260053 Frg Ben Loading - OPEB | F24: 198314.11

Sheet WP II-D-2-5 SFAS 112
A1: PUBLIC UTILITY COMMISSION OF TEXAS | G1: WP/ II-D-2-5
A2: AEP TEXAS INC - CENTRAL DIVISION
A3: WP/ II-D-2-5 ASC 712 (SFAS 112) ADUSTMENT
A4: TEST YEAR ENDING 12/31/2018
A8: Line No. | B8: Account Number | C8: Description | D8: Reference | E8: Transmission | F8: Distribution | G8: Total T&D
C9: 2019 ASC 712 (SFAS 112)Net Periodic Cost | D9: Towers Watson | E9: =E25 -> -30205 | F9: =F25 -> 2225978 | G9: =SUM(E9:F9) -> 2195773
C10: Payroll Expense Ratio | D10: II-D-3-4 | E10: ='WP II-D-2-4 ASC 715 OPEB'!E10 -> 0.30070909 | F10: ='WP II-D-2-4 ASC 715 OPEB'!F10 -> 0.446763
C11: 2018 SFAS 112 Benefit Payments Expensed | E11: =+E9*E10 -> -9082.918 | F11: =+F9*F10 -> 994484.62 | G11: =SUM(E11:F11) -> 985401.7
B13: 9260040 | C13: ASC 712 (SFAS 112) Cost in Test Year | E13: -579605 | F13: -2392179 | G13: =SUM(E13:F13) -> -2971784
B14: 9260053 | C14: ASC 712 (SFAS 112) Costs Capitalized | D14: WP II-D-2-4-1 | E14: =+'WP II-D-2-4-1 OPEB_FAS 112'!$F$21 -> 233085.65 | F14: =+'WP II-D-2-4-1 OPEB_FAS 112'!$F$13 -> 351313.45 | G14: =SUM(E14:F14) -> 584399.1
C15: ASC 712 (SFAS 112) Expense In Test Year | E15: =+E13+E14 -> -346519.35 | F15: =+F13+F14 -> -2040865.5 | G15: =+G13+G14 -> -2387384.9
B17: 926 | C17: Increase / (Decrease) in ASC 712 (SFAS 112) Cost | E17: =+E11-E15 -> 337436.43 | F17: =+F11-F15 -> 3035350.2 | G17: =+G11-G15 -> 3372786.6
B21: memo:
E22: Transmission | F22: Distribution | G22: Total
B23: ASC 712 (SFAS 112) Liability at 12-31-2019 (2019 actuarial estimate) | D23: Post Emp Rpt - 12312018 | E23: 0 | F23: 4611939 | G23: =SUM(E23:F23) -> 4611939
B24: ASC 712 (SFAS 112) Liability at 12-31-2018 (2018 actuarial Rpt) | D24: FAS 112 Apr 2018 | E24: 30205 | F24: 2385961 | G24: =SUM(E24:F24) -> 2416166
B25: Change In ASC 712 (SFAS 112) Liability | E25: =+E23-E24 -> -30205 | F25: =+F23-F24 -> 2225978 | G25: =+G23-G24 -> 2195773
B29: Purpose: To adjust SFAS 112 expense to reflect current actuarial reports

Sheet WP II-D-2-6 GRP INS
A1: PUBLIC UTILITY COMMISSION OF TEXAS | I1: WP II-D-2-6
A2: AEP TEXAS INC - CENTRALDIVISION
A3: WP II-D-6 GROUP INSURANCE ADJUSTMENT
A4: TEST YEAR ENDING 12/31/2018
A7: Line No. | B7: Account Number | C7: Description | E7: Ref | F7: Transmission | G7: Distribution | H7: Total T&D
B8: Test Year Group Insurance Expense
A9: 1
A10: =A9+1 -> 2 | B10: 9260004 | C10: Group Life Insurance Premiums | F10: 57850.14 | G10: 336701.66 | H10: =SUM(F10:G10) -> 394551.8
A11: =A10+1 -> 3 | B11: 9260005 | C11: Group Medical Insurance Premiums | F11: 1880283 | G11: 10793215 | H11: =SUM(F11:G11) -> 12673498
A12: =A11+1 -> 4 | B12: 9260007 | C12: Group LTD Insurance Premiums | F12: 20090.69 | G12: 455600.55 | H12: =SUM(F12:G12) -> 475691.24
A13: =A12+1 -> 5 | B13: 9260009 | C13: Group Dental Insurance Premiums | F13: 83610.06 | G13: 513121.86 | H13: =SUM(F13:G13) -> 596731.92
A14: =A13+1 -> 6 | B14: 9260051 | C14: Fringe Benefit Loading-Group Insurance | F14: -1392580.1 | G14: -5534860.2 | H14: =SUM(F14:G14) -> -6927440.3
A15: =A14+1 -> 7 | B15: Net Test Year Expense | E15: (a) | F15: =SUM(F10:F14) -> 649253.87 | G15: =SUM(G10:G14) -> 6563779.3 | H15: =SUM(H10:H14) -> 7213033.2
A16: =A15+1 -> 8
A17: =A16+1 -> 9 | B17: Group Insurance Cost for 2019 | F17: =+H27 -> 2053104 | G17: =+H28 -> 12647928 | H17: =F17+G17 -> 14701032
A18: =A17+1 -> 10 | B18: 2018 Payroll Expense Ratio | E18: II D-3.4 | F18: ='WP II-D-2-5 SFAS 112'!E10 -> 0.30070909 | G18: ='WP II-D-2-5 SFAS 112'!F10 -> 0.446763
A19: =A18+1 -> 11 | B19: Projected Test Year Group Insurance Costs | E19: (b) | F19: =+F17*F18 -> 617387.03 | G19: =+G17*G18 -> 5650626.3 | H19: =SUM(F19:G19) -> 6268013.4
A20: =A19+1 -> 12
A21: =A20+1 -> 13
A22: =A21+1 -> 14 | B22: Net Group Insurance Expense Adjustment | E22: (b) - (a) | F22: =+F19-F15 -> -31866.837 | G22: =+G19-G15 -> -913152.98 | H22: =+H19-H15 -> -945019.82
A23: =A22+1 -> 15
A24: =A23+1 -> 16
A25: =A24+1 -> 17 | B25: YTD Feb 2019 Annualized | G25: Total | H25: Annualized
A26: =A25+1 -> 18 | B26: FERC A/C | G26: YTD Feb 2019 | H26: Cost
A27: =A26+1 -> 19 | B27: Transmission | G27: 171092 | H27: =G27*12 -> 2053104
A28: =A27+1 -> 20 | B28: Distribution | G28: 1053994 | H28: =G28*12 -> 12647928
A29: =A28+1 -> 21
A30: =A29+1 -> 22
A31: =A30+1 -> 23 | B31: Purpose:
A32: =A31+1 -> 24 | B32: To adjust test year group insurance costs to projected costs by annualizing February 2019 costs.
A33: =A32+1 -> 25 | B33: The discussion of this adjustment can be found in the testimony of Randall W. Hamlett

Sheet WP II-D-2-7 Dues and Contr Exp
A1: PUBLIC UTILITY COMMISSION OF TEXAS | I1: WP/ II-D-2-7
A2: AEP TEXAS INC - CENTRAL DIVISION
A3: WP/ II-D-2-7 RECLASSIFY DUES AND DONATIONS ABOVE THE LINE
A4: TEST YEAR ENDING 12/31/2018
A8: Line No. | B8: Account Number | C8: Description | E8: Transmission | F8: Distribution | G8: Total T&D
A9: 1 | B9: 5930 | C9: Maintenance of Overhead Lines | E9: 0 | F9: -0.99 | G9: =+SUM(E9:F9) -> -0.99
A10: 2 | B10: 9302 | C10: Misc General Expenses | E10: 303741.97 | F10: 381086.73 | G10: =+SUM(E10:F10) -> 684828.7
A11: 3 | C11: Total | E11: =+SUM(E9:E10) -> 303741.97 | F11: =+SUM(F9:F10) -> 381085.74 | G11: =+SUM(G9:G10) -> 684827.71
B21: To reclassify applicable dues and contributions above the line.

Sheet WP II-D-2-8 Reg Comm Exp
A1: PUBLIC UTILITY COMMISSION OF TEXAS | I1: WP II-D-2-8
A2: AEP TEXAS INC - CENTRAL DIVISION
A3: WP II-D-2-8 REGULATORY COMMISSION EXPENSES
A4: TEST YEAR ENDING 12/31/2018
A8: Line No. | B8: Account Number | C8: Description | E8: Transmission | F8: Distribution | G8: Total T&D
A9: 1 | B9: 928 | C9: Regulatory Commission Exp | E9: -191990.69 | F9: -1101088.2 | G9: =+SUM(E9:F9) -> -1293078.9
A10: 2 | D10: Total | E10: =+E9 -> -191990.69 | F10: =+F9 -> -1101088.2 | G10: =+G9 -> -1293078.9
B14: Purpose: To remove current rate case expenses and other regulatory expenses excluded from cost of service.

Sheet WP II-D-2.5-1 Educational 
B1: PUBLIC UTILITY COMMISSION OF TEXAS
B2: AEP TEXAS INC. (CENTRAL DIVISION)
B3: WP/ II-D-2.5-1 SUMMARY OF EDUCATIONAL
B4: TEST YEAR ENDING 12/31/2018
B5: DOCKET XXXXX
E6: 1 | F6: 2 | G6: 3 | H6: 4 | I6: 5 | J6: 6 | K6: 7 | L6: 8 | M6: 9 | N6: 10 | O6: 11 | P6: 12 | Q6: 13
H7: Company | I7: Texas
B8: Account | C8: Organization | D8: Reference | E8: Total | F8: Non-Regulated | G8: Known | H8: Total | I8: Retail | J8: Allocation to | K8: FF | L8: Funct | M8: TRAN | N8: DIST | O8: MET | P8: TDCS | Q8: Total
A9: Line | B9: Number | D9: Schedule | E9: Company | F9: or Non-Electric | G9: Change | H9: Electric | I9: Allocation | J9: Texas | K9: # | L9: Factor | R9: CHECK
A10: No. | I10: Factor | L10: Name
A11: 1 | B11: 4261 | C11: ARANSAS COUNTY ISD | D11: II-D-2.5 | E11: 0 | F11: 0 | G11: 1000 | H11: =SUM(F11:G11) -> 1000 | I11: ='[16]Juris Alloc Split'!$M$351 -> 1 | J11: =+H11*I11 -> 1000 | K11: * | L11: * | M11: 459.07165 | N11: 540.92835 | O11: 0 | P11: 0 | Q11: =SUM(M11:P11) -> 1000 | R11: =+Q11-J11 -> 0
A12: =+A11+1 -> 2 | B12: 4261 | C12: AREA X FFA ASSOCIATION | D12: II-D-2.5 | E12: 0 | F12: 0 | G12: 10000 | H12: =SUM(F12:G12) -> 10000 | I12: ='[16]Juris Alloc Split'!$M$351 -> 1 | J12: =+H12*I12 -> 10000 | K12: * | L12: * | M12: 4590.7165 | N12: 5409.2835 | O12: 0 | P12: 0 | Q12: =SUM(M12:P12) -> 10000 | R12: =+Q12-J12 -> 0
A13: =+A12+1 -> 3 | B13: 4261 | C13: ASSOCIATION OF FORMER STUDENTS OF TEXAS A&M UNIVERSITY | D13: II-D-2.5 | E13: 0 | F13: 0 | G13: 3655 | H13: =SUM(F13:G13) -> 3655 | I13: ='[16]Juris Alloc Split'!$M$351 -> 1 | J13: =+H13*I13 -> 3655 | K13: * | L13: * | M13: 1677.9069 | N13: 1977.0931 | O13: 0 | P13: 0 | Q13: =SUM(M13:P13) -> 3655 | R13: =+Q13-J13 -> 0
A14: =+A13+1 -> 4 | B14: 4261 | C14: BAKER MIDDLE SCHOOL | D14: II-D-2.5 | E14: 0 | F14: 0 | G14: 500 | H14: =SUM(F14:G14) -> 500 | I14: ='[16]Juris Alloc Split'!$M$351 -> 1 | J14: =+H14*I14 -> 500 | K14: * | L14: * | M14: 229.53583 | N14: 270.46417 | O14: 0 | P14: 0 | Q14: =SUM(M14:P14) -> 500 | R14: =+Q14-J14 -> 0
A15: =+A14+1 -> 5 | B15: 4261 | C15: BERNARDA JAIME JUNIOR HIGH SCHOOL | D15: II-D-2.5 | E15: 0 | F15: 0 | G15: 500 | H15: =SUM(F15:G15) -> 500 | I15: ='[16]Juris Alloc Split'!$M$351 -> 1 | J15: =+H15*I15 -> 500 | K15: * | L15: * | M15: 229.53583 | N15: 270.46417 | O15: 0 | P15: 0 | Q15: =SUM(M15:P15) -> 500 | R15: =+Q15-J15 -> 0
A16: =+A15+1 -> 6 | B16: 4261 | C16: CALALLEN EDUCATION FOUNDATION | D16: II-D-2.5 | E16: 0 | F16: 0 | G16: 1500 | H16: =SUM(F16:G16) -> 1500 | I16: ='[16]Juris Alloc Split'!$M$351 -> 1 | J16: =+H16*I16 -> 1500 | K16: * | L16: * | M16: 688.60748 | N16: 811.39252 | O16: 0 | P16: 0 | Q16: =SUM(M16:P16) -> 1500 | R16: =+Q16-J16 -> 0
A17: =+A16+1 -> 7 | B17: 4261 | C17: CAMP WOOD PUBLIC LIBRARY | D17: II-D-2.5 | E17: 0 | F17: 0 | G17: 500 | H17: =SUM(F17:G17) -> 500 | I17: ='[16]Juris Alloc Split'!$M$351 -> 1 | J17: =+H17*I17 -> 500 | K17: * | L17: * | M17: 229.53583 | N17: 270.46417 | O17: 0 | P17: 0 | Q17: =SUM(M17:P17) -> 500 | R17: =+Q17-J17 -> 0
A18: =+A17+1 -> 8 | B18: 4261 | C18: CITIZENS FOR EDUCATIONAL EXCELLENCE | D18: II-D-2.5 | E18: 0 | F18: 0 | G18: 8000 | H18: =SUM(F18:G18) -> 8000 | I18: ='[16]Juris Alloc Split'!$M$351 -> 1 | J18: =+H18*I18 -> 8000 | K18: * | L18: * | M18: 3672.5732 | N18: 4327.4268 | O18: 0 | P18: 0 | Q18: =SUM(M18:P18) -> 8000 | R18: =+Q18-J18 -> 0
A19: =+A18+1 -> 9 | B19: 4261 | C19: CLARK ELEMENTARY | D19: II-D-2.5 | E19: 0 | F19: 0 | G19: 500 | H19: =SUM(F19:G19) -> 500 | I19: ='[16]Juris Alloc Split'!$M$351 -> 1 | J19: =+H19*I19 -> 500 | K19: * | L19: * | M19: 229.53583 | N19: 270.46417 | O19: 0 | P19: 0 | Q19: =SUM(M19:P19) -> 500 | R19: =+Q19-J19 -> 0
A20: =+A19+1 -> 10 | B20: 4261 | C20: COLES HIGH SCHOOL | D20: II-D-2.5 | E20: 0 | F20: 0 | G20: 2000 | H20: =SUM(F20:G20) -> 2000 | I20: ='[16]Juris Alloc Split'!$M$351 -> 1 | J20: =+H20*I20 -> 2000 | K20: * | L20: * | M20: 918.1433 | N20: 1081.8567 | O20: 0 | P20: 0 | Q20: =SUM(M20:P20) -> 2000 | R20: =+Q20-J20 -> 0
A21: =+A20+1 -> 11 | B21: 4261 | C21: COLLEGIATE HIGH SCHOOL | D21: II-D-2.5 | E21: 0 | F21: 0 | G21: 11000 | H21: =SUM(F21:G21) -> 11000 | I21: ='[16]Juris Alloc Split'!$M$351 -> 1 | J21: =+H21*I21 -> 11000 | K21: * | L21: * | M21: 5049.7882 | N21: 5950.2118 | O21: 0 | P21: 0 | Q21: =SUM(M21:P21) -> 11000 | R21: =+Q21-J21 -> 0
A22: =+A21+1 -> 12 | B22: 4261 | C22: COLLINS PARR ELEMENTARY | D22: II-D-2.5 | E22: 0 | F22: 0 | G22: 500 | H22: =SUM(F22:G22) -> 500 | I22: ='[16]Juris Alloc Split'!$M$351 -> 1 | J22: =+H22*I22 -> 500 | K22: * | L22: * | M22: 229.53583 | N22: 270.46417 | O22: 0 | P22: 0 | Q22: =SUM(M22:P22) -> 500 | R22: =+Q22-J22 -> 0
A23: =+A22+1 -> 13 | B23: 4261 | C23: COMMUNITIES IN SCHOOLS | D23: II-D-2.5 | E23: 0 | F23: 0 | G23: 400 | H23: =SUM(F23:G23) -> 400 | I23: ='[16]Juris Alloc Split'!$M$351 -> 1 | J23: =+H23*I23 -> 400 | K23: * | L23: * | M23: 183.62866 | N23: 216.37134 | O23: 0 | P23: 0 | Q23: =SUM(M23:P23) -> 400 | R23: =+Q23-J23 -> 0
... A88: =+A87+1 -> 78 | B88: 4265 | C88: TAPIA, AMY (STEM DONATION) | D88: II-D-2.5 | E88: 0 | F88: 0 | G88: 500 | H88: =SUM(F88:G88) -> 500 | I88: ='[16]Juris Alloc Split'!$M$351 -> 1 | J88: =+H88*I88 -> 500 | K88: * | L88: * | M88: 97.503539 | N88: 402.49646 | O88: 0 | P88: 0 | Q88: =SUM(M88:P88) -> 500 | R88: =+Q88-J88 -> 0
A90: =+A88+1 -> 79 | C90: TOTAL EDUCATIONAL | D90: II-D-2.5 | E90: =SUM(E11:E88) -> 0 | F90: =SUM(F11:F88) -> 0 | G90: =SUM(G11:G88) -> 192605 | H90: =SUM(H11:H88) -> 192605 | J90: =SUM(J11:J88) -> 192605 | M90: =SUM(M11:M88) -> 87759.334 | N90: =SUM(N11:N88) -> 104845.67 | O90: =SUM(O11:O89) -> 0 | P90: =SUM(P11:P88) -> 0 | Q90: =SUM(Q11:Q88) -> 192605 | R90: =SUM(R11:R88) -> 0
A92: =+A90+1 -> 80 | F92: *AEP Texas (Central Division) maintains functional ledgers for transmission and distribution. Please see the testimony of Randall W. Hamlett for Meter and TDCS functionalization.

Sheet WP II-D-2.5-1 Educationl AEPSC 
B1: PUBLIC UTILITY COMMISSION OF TEXAS
B2: AEPSC BILLINGS TO AEP TEXAS INC. (CENTRAL DIVISION)
B3: WP/ II-D-2.5-1 SUMMARY OF EDUCATIONAL
B4: TEST YEAR ENDING 12/31/2018
B5: DOCKET XXXXX
E6: 1 | F6: 2 | G6: 3 | H6: 4 | I6: 5 | J6: 6 | K6: 7 | L6: 8 | M6: 9 | N6: 10 | O6: 11 | P6: 12 | Q6: 13
H7: Company | I7: Texas
B8: Account | C8: Organization | D8: Reference | E8: Total | F8: Non-Regulated | G8: Known | H8: Total | I8: Retail | J8: Allocation to | K8: FF | L8: Funct | M8: TRAN | N8: DIST | O8: MET | P8: TDCS | Q8: Total
A9: Line | B9: Number | D9: Schedule | E9: Company | F9: or Non-Electric | G9: Change | H9: Electric | I9: Allocation | J9: Texas | K9: # | L9: Factor | R9: CHECK
A10: No. | I10: Factor | L10: Name
A11: 1 | B11: 4261 | C11: ALLEGHENY COLLEGE | D11: II-D-2.5 | E11: 0 | F11: 0 | G11: =+M11+N11 -> 19.45 | H11: =SUM(F11:G11) -> 19.45 | I11: 1 | J11: =+H11*I11 -> 19.45 | K11: * | L11: * | M11: 10.21 | N11: 9.24 | O11: 0 | P11: 0 | Q11: =SUM(M11:P11) -> 19.45 | R11: =+Q11-J11 -> 0
A12: =+A11+1 -> 2 | B12: 4261 | C12: BETHANY LUTHERAN COLLEGE | D12: II-D-2.5 | E12: 0 | F12: 0 | G12: =+M12+N12 -> 19.45 | H12: =SUM(F12:G12) -> 19.45 | I12: 1 | J12: =+H12*I12 -> 19.45 | K12: * | L12: * | M12: 10.21 | N12: 9.24 | O12: 0 | P12: 0 | Q12: =SUM(M12:P12) -> 19.45 | R12: =+Q12-J12 -> 0
A13: =+A12+1 -> 3 | B13: 4261 | C13: BINGHAMTON UNIVERSITY FOUNDATION | D13: II-D-2.5 | E13: 0 | F13: 0 | G13: =+M13+N13 -> 19.47 | H13: =SUM(F13:G13) -> 19.47 | I13: 1 | J13: =+H13*I13 -> 19.47 | K13: * | L13: * | M13: 10.22 | N13: 9.25 | O13: 0 | P13: 0 | Q13: =SUM(M13:P13) -> 19.47 | R13: =+Q13-J13 -> 0
A14: =+A13+1 -> 4 | B14: 4261 | C14: BUFFALO HIGH SCHOOL | D14: II-D-2.5 | E14: 0 | F14: 0 | G14: =+M14+N14 -> 7.7 | H14: =SUM(F14:G14) -> 7.7 | I14: 1 | J14: =+H14*I14 -> 7.7 | K14: * | L14: * | M14: 4.04 | N14: 3.66 | O14: 0 | P14: 0 | Q14: =SUM(M14:P14) -> 7.7 | R14: =+Q14-J14 -> 0
A15: =+A14+1 -> 5 | B15: 4261 | C15: COLUMBIA UNIVERSITY | D15: II-D-2.5 | E15: 0 | F15: 0 | G15: =+M15+N15 -> 46.44 | H15: =SUM(F15:G15) -> 46.44 | I15: 1 | J15: =+H15*I15 -> 46.44 | K15: * | L15: * | M15: 24.37 | N15: 22.07 | O15: 0 | P15: 0 | Q15: =SUM(M15:P15) -> 46.44 | R15: =+Q15-J15 -> 0
A16: =+A15+1 -> 6 | B16: 4261 | C16: COOPER UNION | D16: II-D-2.5 | E16: 0 | F16: 0 | G16: =+M16+N16 -> 43.81 | H16: =SUM(F16:G16) -> 43.81 | I16: 1 | J16: =+H16*I16 -> 43.81 | K16: * | L16: * | M16: 22.99 | N16: 20.82 | O16: 0 | P16: 0 | Q16: =SUM(M16:P16) -> 43.81 | R16: =+Q16-J16 -> 0
A17: =+A16+1 -> 7 | B17: 4261 | C17: CORNELL UNIVERSITY | D17: II-D-2.5 | E17: 0 | F17: 0 | G17: =+M17+N17 -> 19.46 | H17: =SUM(F17:G17) -> 19.46 | I17: 1 | J17: =+H17*I17 -> 19.46 | K17: * | L17: * | M17: 10.21 | N17: 9.25 | O17: 0 | P17: 0 | Q17: =SUM(M17:P17) -> 19.46 | R17: =+Q17-J17 -> 0
A18: =+A17+1 -> 8 | B18: 4261 | C18: CROWDER COLLEGE FOUNDATION INC | D18: II-D-2.5 | E18: 0 | F18: 0 | G18: =+M18+N18 -> 76.94 | H18: =SUM(F18:G18) -> 76.94 | I18: 1 | J18: =+H18*I18 -> 76.94 | K18: * | L18: * | M18: 40.38 | N18: 36.56 | O18: 0 | P18: 0 | Q18: =SUM(M18:P18) -> 76.94 | R18: =+Q18-J18 -> 0
A19: =+A18+1 -> 9 | B19: 4261 | C19: DARTMOUTH COLLEGE | D19: II-D-2.5 | E19: 0 | F19: 0 | G19: =+M19+N19 -> 38.92 | H19: =SUM(F19:G19) -> 38.92 | I19: 1 | J19: =+H19*I19 -> 38.92 | K19: * | L19: * | M19: 20.43 | N19: 18.49 | O19: 0 | P19: 0 | Q19: =SUM(M19:P19) -> 38.92 | R19: =+Q19-J19 -> 0
A20: =+A19+1 -> 10 | B20: 4261 | C20: ELIZABETHTOWN COLLEGE | D20: II-D-2.5 | E20: 0 | F20: 0 | G20: =+M20+N20 -> 77.88 | H20: =SUM(F20:G20) -> 77.88 | I20: 1 | J20: =+H20*I20 -> 77.88 | K20: * | L20: * | M20: 40.87 | N20: 37.01 | O20: 0 | P20: 0 | Q20: =SUM(M20:P20) -> 77.88 | R20: =+Q20-J20 -> 0
A21: =+A20+1 -> 11 | B21: 4261 | C21: GANNON UNIVERSITY | D21: II-D-2.5 | E21: 0 | F21: 0 | G21: =+M21+N21 -> 38.71 | H21: =SUM(F21:G21) -> 38.71 | I21: 1 | J21: =+H21*I21 -> 38.71 | K21: * | L21: * | M21: 20.32 | N21: 18.39 | O21: 0 | P21: 0 | Q21: =SUM(M21:P21) -> 38.71 | R21: =+Q21-J21 -> 0
A22: =+A21+1 -> 12 | B22: 4261 | C22: HARVARD UNIVERSITY | D22: II-D-2.5 | E22: 0 | F22: 0 | G22: =+M22+N22 -> 3893.67 | H22: =SUM(F22:G22) -> 3893.67 | I22: 1 | J22: =+H22*I22 -> 3893.67 | K22: * | L22: * | M22: 2043.43 | N22: 1850.24 | O22: 0 | P22: 0 | Q22: =SUM(M22:P22) -> 3893.67 | R22: =+Q22-J22 -> 0
A23: =+A22+1 -> 13 | B23: 4261 | C23: HOFSTRA UNIVERSITY | D23: II-D-2.5 | E23: 0 | F23: 0 | G23: =+M23+N23 -> 23.08 | H23: =SUM(F23:G23) -> 23.08 | I23: 1 | J23: =+H23*I23 -> 23.08 | K23: * | L23: * | M23: 12.11 | N23: 10.97 | O23: 0 | P23: 0 | Q23: =SUM(M23:P23) -> 23.08 | R23: =+Q23-J23 -> 0
... A48: =+A47+1 -> 38 | B48: 4261 | C48: WILLIAM PATERSON | D48: II-D-2.5 | E48: 0 | F48: 0 | G48: =+M48+N48 -> 38.89 | H48: =SUM(F48:G48) -> 38.89 | I48: 1 | J48: =+H48*I48 -> 38.89 | K48: * | L48: * | M48: 20.41 | N48: 18.48 | O48: 0 | P48: 0 | Q48: =SUM(M48:P48) -> 38.89 | R48: =+Q48-J48 -> 0
A50: 39 | C50: TOTAL EDUCATIONAL | D50: II-D-2.5 | E50: =SUM(E11:E48) -> 0 | F50: =SUM(F11:F48) -> 0 | G50: =SUM(G11:G48) -> 12027.72 | H50: =SUM(H11:H48) -> 12027.72 | J50: =SUM(J11:J48) -> 12027.72 | M50: =SUM(M11:M48) -> 6312.26 | N50: =SUM(N11:N48) -> 5715.46 | O50: =SUM(O11:O49) -> 0 | P50: =SUM(P11:P48) -> 0 | Q50: =SUM(Q11:Q48) -> 12027.72 | R50: =SUM(R11:R48) -> 0
A52: 40 | F52: *AEP Texas (Central Division) maintains functional ledgers for transmission and distribution. Please see the testimony of Randall W. Hamlett for Meter and TDCS functionalization.

Sheet WP II-D-2.5-2 Com Service
B1: PUBLIC UTILITY COMMISSION OF TEXAS
B2: AEP TEXAS INC. (CENTRAL DIVISION)
B3: WP/ II-D-2.5-2 SUMMARY OF COMMUNITY SERVICE
B4: TEST YEAR ENDING 12/31/2018
B5: DOCKET XXXXX
E6: 1 | F6: 2 | G6: 3 | H6: 4 | I6: 5 | J6: 6 | K6: 7 | L6: 8 | M6: 9 | N6: 10 | O6: 11 | P6: 12 | Q6: 13
H7: Company | I7: Texas
B8: Account | C8: Organization | D8: Reference | E8: Total | F8: Non-Regulated | G8: Known | H8: Total | I8: Retail | J8: Allocation to | K8: FF | L8: Funct | M8: TRAN | N8: DIST | O8: MET | P8: TDCS | Q8: Total
A9: Line | B9: Number | D9: Schedule | E9: Company | F9: or Non-Electric | G9: Change | H9: Electric | I9: Allocation | J9: Texas | K9: # | L9: Factor | R9: CHECK
A10: No. | I10: Factor | L10: Name
A12: 1 | B12: 4261 | C12: AMERICAN CANCER SOCIETY | D12: II-D-2.5 | E12: 0 | F12: 0 | G12: 5000 | H12: =SUM(F12:G12) -> 5000 | I12: ='[16]Juris Alloc Split'!$M$351 -> 1 | J12: =+H12*I12 -> 5000 | K12: * | L12: * | M12: 2295.3583 | N12: 2704.6417 | O12: 0 | P12: 0 | Q12: =SUM(M12:P12) -> 5000 | R12: =+Q12-J12 -> 0
A13: =+A12+1 -> 2 | B13: 4261 | C13: AMERICAN HEART ASSOCIATION | D13: II-D-2.5 | E13: 0 | F13: 0 | G13: 49500 | H13: =SUM(F13:G13) -> 49500 | I13: ='[16]Juris Alloc Split'!$M$351 -> 1 | J13: =+H13*I13 -> 49500 | K13: * | L13: * | M13: 22724.047 | N13: 26775.953 | O13: 0 | P13: 0 | Q13: =SUM(M13:P13) -> 49500 | R13: =+Q13-J13 -> 0
A14: =+A13+1 -> 3 | B14: 4261 | C14: AMERICAN LEGION | D14: II-D-2.5 | E14: 0 | F14: 0 | G14: 1000 | H14: =SUM(F14:G14) -> 1000 | I14: ='[16]Juris Alloc Split'!$M$351 -> 1 | J14: =+H14*I14 -> 1000 | K14: * | L14: * | M14: 459.07165 | N14: 540.92835 | O14: 0 | P14: 0 | Q14: =SUM(M14:P14) -> 1000 | R14: =+Q14-J14 -> 0
A15: =+A14+1 -> 4 | B15: 4261 | C15: ARCE, ANTONIO (UNITED WAY CAMPAIGN) | D15: II-D-2.5 | E15: 0 | F15: 0 | G15: 1000 | H15: =SUM(F15:G15) -> 1000 | I15: ='[16]Juris Alloc Split'!$M$351 -> 1 | J15: =+H15*I15 -> 1000 | K15: * | L15: * | M15: 459.07165 | N15: 540.92835 | O15: 0 | P15: 0 | Q15: =SUM(M15:P15) -> 1000 | R15: =+Q15-J15 -> 0
A16: =+A15+1 -> 5 | B16: 4261 | C16: ART MUSEUM OF SOUTH TEXAS | D16: II-D-2.5 | E16: 0 | F16: 0 | G16: 15000 | H16: =SUM(F16:G16) -> 15000 | I16: ='[16]Juris Alloc Split'!$M$351 -> 1 | J16: =+H16*I16 -> 15000 | K16: * | L16: * | M16: 6886.0748 | N16: 8113.9252 | O16: 0 | P16: 0 | Q16: =SUM(M16:P16) -> 15000 | R16: =+Q16-J16 -> 0
A17: =+A16+1 -> 6 | B17: 4261 | C17: AUTISM AWARENESS & EDUCATION FOUNDATION | D17: II-D-2.5 | E17: 0 | F17: 0 | G17: 1000 | H17: =SUM(F17:G17) -> 1000 | I17: ='[16]Juris Alloc Split'!$M$351 -> 1 | J17: =+H17*I17 -> 1000 | K17: * | L17: * | M17: 459.07165 | N17: 540.92835 | O17: 0 | P17: 0 | Q17: =SUM(M17:P17) -> 1000 | R17: =+Q17-J17 -> 0
A18: =+A17+1 -> 7 | B18: 4261 | C18: BIG BROTHERS/BIG SISTERS | D18: II-D-2.5 | E18: 0 | F18: 0 | G18: 2500 | H18: =SUM(F18:G18) -> 2500 | I18: ='[16]Juris Alloc Split'!$M$351 -> 1 | J18: =+H18*I18 -> 2500 | K18: * | L18: * | M18: 1147.6791 | N18: 1352.3209 | O18: 0 | P18: 0 | Q18: =SUM(M18:P18) -> 2500 | R18: =+Q18-J18 -> 0
A19: =+A18+1 -> 8 | B19: 4261 | C19: BORDER TEXAN OF THE YEAR COMMITTEE | D19: II-D-2.5 | E19: 0 | F19: 0 | G19: 1250 | H19: =SUM(F19:G19) -> 1250 | I19: ='[16]Juris Alloc Split'!$M$351 -> 1 | J19: =+H19*I19 -> 1250 | K19: * | L19: * | M19: 573.83956 | N19: 676.16044 | O19: 0 | P19: 0 | Q19: =SUM(M19:P19) -> 1250 | R19: =+Q19-J19 -> 0
A20: =+A19+1 -> 9 | B20: 4261 | C20: BOY SCOUTS OF AMERICA | D20: II-D-2.5 | E20: 0 | F20: 0 | G20: 12400 | H20: =SUM(F20:G20) -> 12400 | I20: ='[16]Juris Alloc Split'!$M$351 -> 1 | J20: =+H20*I20 -> 12400 | K20: * | L20: * | M20: 5692.4885 | N20: 6707.5115 | O20: 0 | P20: 0 | Q20: =SUM(M20:P20) -> 12400 | R20: =+Q20-J20 -> 0
A21: =+A20+1 -> 10 | B21: 4261 | C21: BOYS & GIRLS CLUBS | D21: II-D-2.5 | E21: 0 | F21: 0 | G21: 4350 | H21: =SUM(F21:G21) -> 4350 | I21: ='[16]Juris Alloc Split'!$M$351 -> 1 | J21: =+H21*I21 -> 4350 | K21: * | L21: * | M21: 1996.9617 | N21: 2353.0383 | O21: 0 | P21: 0 | Q21: =SUM(M21:P21) -> 4350 | R21: =+Q21-J21 -> 0
A22: =+A21+1 -> 11 | B22: 4261 | C22: BUCCANEER COMMISSION | D22: II-D-2.5 | E22: 0 | F22: 0 | G22: 6000 | H22: =SUM(F22:G22) -> 6000 | I22: ='[16]Juris Alloc Split'!$M$351 -> 1 | J22: =+H22*I22 -> 6000 | K22: * | L22: * | M22: 2754.4299 | N22: 3245.5701 | O22: 0 | P22: 0 | Q22: =SUM(M22:P22) -> 6000 | R22: =+Q22-J22 -> 0
A23: =+A22+1 -> 12 | B23: 4261 | C23: CACTUS JACK FOUNDATION | D23: II-D-2.5 | E23: 0 | F23: 0 | G23: 1500 | H23: =SUM(F23:G23) -> 1500 | I23: ='[16]Juris Alloc Split'!$M$351 -> 1 | J23: =+H23*I23 -> 1500 | K23: * | L23: * | M23: 688.60748 | N23: 811.39252 | O23: 0 | P23: 0 | Q23: =SUM(M23:P23) -> 1500 | R23: =+Q23-J23 -> 0
A24: =+A23+1 -> 13 | B24: 4261 | C24: CASA OF CAMERON & WILLACY COUNTIES INC | D24: II-D-2.5 | E24: 0 | F24: 0 | G24: 600 | H24: =SUM(F24:G24) -> 600 | I24: ='[16]Juris Alloc Split'!$M$351 -> 1 | J24: =+H24*I24 -> 600 | K24: * | L24: * | M24: 275.44299 | N24: 324.55701 | O24: 0 | P24: 0 | Q24: =SUM(M24:P24) -> 600 | R24: =+Q24-J24 -> 0
... A150: =+A149+1 -> 139 | B150: 4265 | C150: SALAZAR, CHRISTINA M (UNITED WAY CAMPAIGN) | D150: II-D-2.5 | E150: 0 | F150: 0 | G150: 2000 | H150: =SUM(F150:G150) -> 2000 | I150: ='[16]Juris Alloc Split'!$M$351 -> 1 | J150: =+H150*I150 -> 2000 | K150: * | L150: * | M150: 390.01416 | N150: 1609.9858 | O150: 0 | P150: 0 | Q150: =SUM(M150:P150) -> 2000 | R150: =+Q150-J150 -> 0
A152: =+A150+1 -> 140 | C152: TOTAL COMMUNITY SERVICE | D152: II-D-2.5 | E152: =SUM(E11:E150) -> 0 | F152: =SUM(F11:F150) -> 0 | G152: =SUM(G11:G150) -> 415850 | H152: =SUM(H11:H150) -> 415850 | J152: =SUM(J11:J150) -> 415850 | M152: =SUM(M11:M150) -> 190469.24 | N152: =SUM(N11:N150) -> 225380.76 | O152: =SUM(O11:O150) -> 0 | P152: =SUM(P11:P150) -> 0 | Q152: =SUM(Q11:Q150) -> 415850 | R152: =SUM(R11:R150) -> 0
A154: =+A152+1 -> 141 | F154: *AEP Texas (Central Division) maintains functional ledgers for transmission and distribution. Please see the testimony of Peter K. Kimani for Meter and TDCS functionalization.

Sheet WP II-D-2.5-2 Com Service AEPSC
B1: PUBLIC UTILITY COMMISSION OF TEXAS
B2: AEPSC BILLINGS TO AEP TEXAS INC. (CENTRAL DIVISION)
B3: WP/ II-D-2.5-2 SUMMARY OF COMMUNITY SERVICE
B4: TEST YEAR ENDING 12/31/2018
B5: DOCKET XXXXX
E6: 1 | F6: 2 | G6: 3 | H6: 4 | I6: 5 | J6: 6 | K6: 7 | L6: 8 | M6: 9 | N6: 10 | O6: 11 | P6: 12 | Q6: 13
H7: Company | I7: Texas
B8: Account | C8: Organization | D8: Reference | E8: Total | F8: Non-Regulated | G8: Known | H8: Total | I8: Retail | J8: Allocation to | K8: FF | L8: Funct | M8: TRAN | N8: DIST | O8: MET | P8: TDCS | Q8: Total
A9: Line | B9: Number | D9: Schedule | E9: Company | F9: or Non-Electric | G9: Change | H9: Electric | I9: Allocation | J9: Texas | K9: # | L9: Factor | R9: CHECK
A10: No. | I10: Factor | L10: Name
A12: 1 | B12: 4261 | C12: 95TH DIVISION FOUNDATION | D12: II-D-2.5 | E12: 0 | F12: 0 | G12: =+M12+N12 -> 38.93 | H12: =SUM(F12:G12) -> 38.93 | I12: 1 | J12: =+H12*I12 -> 38.93 | K12: * | L12: * | M12: 20.43 | N12: 18.5 | O12: 0 | P12: 0 | Q12: =SUM(M12:P12) -> 38.93 | R12: =+Q12-J12 -> 0
A13: =+A12+1 -> 2 | B13: 4261 | C13: AMERICAN KIDNEY FOUNDATION | D13: II-D-2.5 | E13: 0 | F13: 0 | G13: =+M13+N13 -> 7.78 | H13: =SUM(F13:G13) -> 7.78 | I13: 1 | J13: =+H13*I13 -> 7.78 | K13: * | L13: * | M13: 4.08 | N13: 3.7 | O13: 0 | P13: 0 | Q13: =SUM(M13:P13) -> 7.78 | R13: =+Q13-J13 -> 0
A14: =+A13+1 -> 3 | B14: 4261 | C14: AMERICANS FOR A CLEAN ENERGY GRID | D14: II-D-2.5 | E14: 0 | F14: 0 | G14: =+M14+N14 -> 4327.99 | H14: =SUM(F14:G14) -> 4327.99 | I14: 1 | J14: =+H14*I14 -> 4327.99 | K14: * | L14: * | M14: 2271.36 | N14: 2056.63 | O14: 0 | P14: 0 | Q14: =SUM(M14:P14) -> 4327.99 | R14: =+Q14-J14 -> 0
A15: =+A14+1 -> 4 | B15: 4261 | C15: BANK OF AMERICA | D15: II-D-2.5 | E15: 0 | F15: 0 | G15: =+M15+N15 -> 245.6 | H15: =SUM(F15:G15) -> 245.6 | I15: 1 | J15: =+H15*I15 -> 245.6 | K15: * | L15: * | M15: 128.89 | N15: 116.71 | O15: 0 | P15: 0 | Q15: =SUM(M15:P15) -> 245.6 | R15: =+Q15-J15 -> 0
A16: =+A15+1 -> 5 | B16: 4261 | C16: CITADEL FOUNDATION | D16: II-D-2.5 | E16: 0 | F16: 0 | G16: =+M16+N16 -> 23.36 | H16: =SUM(F16:G16) -> 23.36 | I16: 1 | J16: =+H16*I16 -> 23.36 | K16: * | L16: * | M16: 12.26 | N16: 11.1 | O16: 0 | P16: 0 | Q16: =SUM(M16:P16) -> 23.36 | R16: =+Q16-J16 -> 0
A17: =+A16+1 -> 6 | B17: 4261 | C17: HORTONS KIDS INC | D17: II-D-2.5 | E17: 0 | F17: 0 | G17: =+M17+N17 -> 389.17 | H17: =SUM(F17:G17) -> 389.17 | I17: 1 | J17: =+H17*I17 -> 389.17 | K17: * | L17: * | M17: 204.24 | N17: 184.93 | O17: 0 | P17: 0 | Q17: =SUM(M17:P17) -> 389.17 | R17: =+Q17-J17 -> 0
A18: =+A17+1 -> 7 | B18: 4261 | C18: IN THE GARDEN MISSIONS | D18: II-D-2.5 | E18: 0 | F18: 0 | G18: =+M18+N18 -> 38.89 | H18: =SUM(F18:G18) -> 38.89 | I18: 1 | J18: =+H18*I18 -> 38.89 | K18: * | L18: * | M18: 20.41 | N18: 18.48 | O18: 0 | P18: 0 | Q18: =SUM(M18:P18) -> 38.89 | R18: =+Q18-J18 -> 0
A19: =+A18+1 -> 8 | B19: 4261 | C19: NATIONAL PRESS FOUNDATION | D19: II-D-2.5 | E19: 0 | F19: 0 | G19: =+M19+N19 -> 272.56 | H19: =SUM(F19:G19) -> 272.56 | I19: 1 | J19: =+H19*I19 -> 272.56 | K19: * | L19: * | M19: 143.04 | N19: 129.52 | O19: 0 | P19: 0 | Q19: =SUM(M19:P19) -> 272.56 | R19: =+Q19-J19 -> 0
A20: =+A19+1 -> 9 | B20: 4261 | C20: SALVATION ARMY | D20: II-D-2.5 | E20: 0 | F20: 0 | G20: =+M20+N20 -> 2336.21 | H20: =SUM(F20:G20) -> 2336.21 | I20: 1 | J20: =+H20*I20 -> 2336.21 | K20: * | L20: * | M20: 1226.06 | N20: 1110.15 | O20: 0 | P20: 0 | Q20: =SUM(M20:P20) -> 2336.21 | R20: =+Q20-J20 -> 0
A21: =+A20+1 -> 10 | B21: 4261 | C21: VALLEY HOSPICE | D21: II-D-2.5 | E21: 0 | F21: 0 | G21: =+M21+N21 -> 11.54 | H21: =SUM(F21:G21) -> 11.54 | I21: 1 | J21: =+H21*I21 -> 11.54 | K21: * | L21: * | M21: 6.06 | N21: 5.48 | O21: 0 | P21: 0 | Q21: =SUM(M21:P21) -> 11.54 | R21: =+Q21-J21 -> 0
A22: =+A21+1 -> 11 | B22: 4261 | C22: FIRST TEE | D22: II-D-2.5 | E22: 0 | F22: 0 | G22: =+M22+N22 -> 467.24 | H22: =SUM(F22:G22) -> 467.24 | I22: 1 | J22: =+H22*I22 -> 467.24 | K22: * | L22: * | M22: 245.21 | N22: 222.03 | O22: 0 | P22: 0 | Q22: =SUM(M22:P22) -> 467.24 | R22: =+Q22-J22 -> 0
A24: 12 | C24: TOTAL COMMUNITY SERVICE | D24: II-D-2.5 | E24: =SUM(E11:E22) -> 0 | F24: =SUM(F11:F22) -> 0 | G24: =SUM(G11:G22) -> 8159.27 | H24: =SUM(H11:H22) -> 8159.27 | J24: =SUM(J11:J22) -> 8159.27 | M24: =SUM(M11:M22) -> 4282.04 | N24: =SUM(N11:N22) -> 3877.23 | O24: =SUM(O11:O22) -> 0 | P24: =SUM(P11:P22) -> 0 | Q24: =SUM(Q11:Q22) -> 8159.27 | R24: =SUM(R11:R22) -> 0
A26: 13 | F26: *AEP Texas (Central Division) maintains functional ledgers for transmission and distribution. Please see the testimony of Randall W. Hamlett for Meter and TDCS functionalization.

Sheet WP II-D-2.5-3 Bus-Econ
B2: PUBLIC UTILITY COMMISSION OF TEXAS
B3: AEP TEXAS INC. (CENTRAL DIVISION)
B4: WP/ II-D-2.5-3 SUMMARY OF BUSINESS / ECONOMIC DEVELOPMENT
B5: TEST YEAR ENDING 12/31/2018
B6: ='WP II-D-2.5-2 Com Service'!B5 -> DOCKET XXXXX
E9: 1 | F9: 2 | G9: 3 | H9: 4 | I9: 5 | J9: 6 | K9: 7 | L9: 8 | M9: 9 | N9: 10 | O9: 11 | P9: 12 | Q9: 13
H10: Company | I10: Texas
B11: Account | C11: Organization | D11: Reference | E11: Total | F11: Non-Regulated | G11: Known | H11: Total | I11: Retail | J11: Allocation to | K11: FF | L11: Funct | M11: TRAN | N11: DIST | O11: MET | P11: TDCS | Q11: Total
A12: Line | B12: Number | D12: Schedule | E12: Company | F12: or Non-Electric | G12: Change | H12: Electric | I12: Allocation | J12: Texas | K12: # | L12: Factor | R12: CHECK
A13: No. | I13: Factor | L13: Name
A14: 1 | B14: 4261 | C14: ASSOCIATION OF FUNDRAISING PROFESSIONALS | D14: II-D-2.5 | E14: 0 | F14: 0 | G14: 2500 | H14: =SUM(F14:G14) -> 2500 | I14: ='[16]Juris Alloc Split'!$M$351 -> 1 | J14: =+H14*I14 -> 2500 | K14: * | L14: * | M14: 1147.6791 | N14: 1352.3209 | O14: 0 | P14: 0 | Q14: =SUM(M14:P14) -> 2500 | R14: =+Q14-J14 -> 0
A15: =+A14+1 -> 2 | B15: 4261 | C15: BAY AREA CITIZENS AGAINST LAWSUIT ABUSE | D15: II-D-2.5 | E15: 0 | F15: 0 | G15: 2000 | H15: =SUM(F15:G15) -> 2000 | I15: ='[16]Juris Alloc Split'!$M$351 -> 1 | J15: =+H15*I15 -> 2000 | K15: * | L15: * | M15: 918.1433 | N15: 1081.8567 | O15: 0 | P15: 0 | Q15: =SUM(M15:P15) -> 2000 | R15: =+Q15-J15 -> 0
A16: =+A15+1 -> 3 | B16: 4261 | C16: CHAMBER OF COMMERCE OF ZAPATA | D16: II-D-2.5 | E16: 0 | F16: 0 | G16: 500 | H16: =SUM(F16:G16) -> 500 | I16: ='[16]Juris Alloc Split'!$M$351 -> 1 | J16: =+H16*I16 -> 500 | K16: * | L16: * | M16: 229.53583 | N16: 270.46417 | O16: 0 | P16: 0 | Q16: =SUM(M16:P16) -> 500 | R16: =+Q16-J16 -> 0
A17: =+A16+1 -> 4 | B17: 4261 | C17: COASTAL BEND COUNCIL OF GOVERNMENTS (HURRICANE CONFERENCE) | D17: II-D-2.5 | E17: 0 | F17: 0 | G17: 1500 | H17: =SUM(F17:G17) -> 1500 | I17: ='[16]Juris Alloc Split'!$M$351 -> 1 | J17: =+H17*I17 -> 1500 | K17: * | L17: * | M17: 688.60748 | N17: 811.39252 | O17: 0 | P17: 0 | Q17: =SUM(M17:P17) -> 1500 | R17: =+Q17-J17 -> 0
A18: =+A17+1 -> 5 | B18: 4261 | C18: CORPUS CHRISTI CONVENTION & VISITORS BUREAU | D18: II-D-2.5 | E18: 0 | F18: 0 | G18: 1000 | H18: =SUM(F18:G18) -> 1000 | I18: ='[16]Juris Alloc Split'!$M$351 -> 1 | J18: =+H18*I18 -> 1000 | K18: * | L18: * | M18: 459.07165 | N18: 540.92835 | O18: 0 | P18: 0 | Q18: =SUM(M18:P18) -> 1000 | R18: =+Q18-J18 -> 0
A19: =+A18+1 -> 6 | B19: 4261 | C19: GREATER LAREDO DEVELOPMENT FOUNDATION | D19: II-D-2.5 | E19: 0 | F19: 0 | G19: 1500 | H19: =SUM(F19:G19) -> 1500 | I19: ='[16]Juris Alloc Split'!$M$351 -> 1 | J19: =+H19*I19 -> 1500 | K19: * | L19: * | M19: 688.60748 | N19: 811.39252 | O19: 0 | P19: 0 | Q19: =SUM(M19:P19) -> 1500 | R19: =+Q19-J19 -> 0
A20: =+A19+1 -> 7 | B20: 4261 | C20: HARLINGEN AREA CHAMBER OF COMMERCE | D20: II-D-2.5 | E20: 0 | F20: 0 | G20: 1510 | H20: =SUM(F20:G20) -> 1510 | I20: ='[16]Juris Alloc Split'!$M$351 -> 1 | J20: =+H20*I20 -> 1510 | K20: * | L20: * | M20: 693.19819 | N20: 816.80181 | O20: 0 | P20: 0 | Q20: =SUM(M20:P20) -> 1510 | R20: =+Q20-J20 -> 0
A21: =+A20+1 -> 8 | B21: 4261 | C21: LAREDO BUILDERS ASSOCIATION | D21: II-D-2.5 | E21: 0 | F21: 0 | G21: 2250 | H21: =SUM(F21:G21) -> 2250 | I21: ='[16]Juris Alloc Split'!$M$351 -> 1 | J21: =+H21*I21 -> 2250 | K21: * | L21: * | M21: 1032.9112 | N21: 1217.0888 | O21: 0 | P21: 0 | Q21: =SUM(M21:P21) -> 2250 | R21: =+Q21-J21 -> 0
A22: =+A21+1 -> 9 | B22: 4261 | C22: LAREDO CHAMBER OF COMMERCE | D22: II-D-2.5 | E22: 0 | F22: 0 | G22: 3137.5 | H22: =SUM(F22:G22) -> 3137.5 | I22: ='[16]Juris Alloc Split'!$M$351 -> 1 | J22: =+H22*I22 -> 3137.5 | K22: * | L22: * | M22: 1440.3373 | N22: 1697.1627 | O22: 0 | P22: 0 | Q22: =SUM(M22:P22) -> 3137.5 | R22: =+Q22-J22 -> 0
A23: =+A22+1 -> 10 | B23: 4261 | C23: LAREDO MANUFACTURERS ASSOCIATION | D23: II-D-2.5 | E23: 0 | F23: 0 | G23: 500 | H23: =SUM(F23:G23) -> 500 | I23: ='[16]Juris Alloc Split'!$M$351 -> 1 | J23: =+H23*I23 -> 500 | K23: * | L23: * | M23: 229.53583 | N23: 270.46417 | O23: 0 | P23: 0 | Q23: =SUM(M23:P23) -> 500 | R23: =+Q23-J23 -> 0
A24: =+A23+1 -> 11 | B24: 4261 | C24: LDF NONPROFIT FOUNDATION | D24: II-D-2.5 | E24: 0 | F24: 0 | G24: 6500 | H24: =SUM(F24:G24) -> 6500 | I24: ='[16]Juris Alloc Split'!$M$351 -> 1 | J24: =+H24*I24 -> 6500 | K24: * | L24: * | M24: 2983.9657 | N24: 3516.0343 | O24: 0 | P24: 0 | Q24: =SUM(M24:P24) -> 6500 | R24: =+Q24-J24 -> 0
A25: =+A24+1 -> 12 | B25: 4261 | C25: MCALLEN CHAMBER OF COMMERCE | D25: II-D-2.5 | E25: 0 | F25: 0 | G25: 2000 | H25: =SUM(F25:G25) -> 2000 | I25: ='[16]Juris Alloc Split'!$M$351 -> 1 | J25: =+H25*I25 -> 2000 | K25: * | L25: * | M25: 918.1433 | N25: 1081.8567 | O25: 0 | P25: 0 | Q25: =SUM(M25:P25) -> 2000 | R25: =+Q25-J25 -> 0
A26: =+A25+1 -> 13 | B26: 4261 | C26: MID-COAST HURRICANE CONFERENCE | D26: II-D-2.5 | E26: 0 | F26: 0 | G26: 1500 | H26: =SUM(F26:G26) -> 1500 | I26: ='[16]Juris Alloc Split'!$M$351 -> 1 | J26: =+H26*I26 -> 1500 | K26: * | L26: * | M26: 688.60748 | N26: 811.39252 | O26: 0 | P26: 0 | Q26: =SUM(M26:P26) -> 1500 | R26: =+Q26-J26 -> 0
... A48: =+A47+1 -> 35 | B48: 4265 | C48: VICTORIA CHAMBER OF COMMERCE | D48: II-D-2.5 | E48: 0 | F48: 0 | G48: 250 | H48: =SUM(F48:G48) -> 250 | I48: ='[16]Juris Alloc Split'!$M$351 -> 1 | J48: =+H48*I48 -> 250 | K48: * | L48: * | M48: 48.75177 | N48: 201.24823 | O48: 0 | P48: 0 | Q48: =SUM(M48:P48) -> 250 | R48: =+Q48-J48 -> 0
A50: 37 | C50: TOTAL BUSINESS / ECONOMIC DEVELOPMENT | D50: II-D-2.5 | E50: =+SUM(E14:E48) -> 0 | F50: =+SUM(F14:F48) -> 0 | G50: =+SUM(G14:G48) -> 68497.5 | H50: =+SUM(H14:H48) -> 68497.5 | J50: =+SUM(J14:J48) -> 68497.5 | K50: =+SUM(K14:K48) -> 0 | L50: =+SUM(L14:L48) -> 0 | M50: =+SUM(M14:M48) -> 22962.362 | N50: =+SUM(N14:N48) -> 45535.138 | O50: =+SUM(O14:O48) -> 0 | P50: =+SUM(P14:P48) -> 0 | Q50: =+SUM(Q14:Q48) -> 68497.5 | R50: =+SUM(R14:R48) -> 0
A52: 38 | F52: *AEP Texas (Central Division) maintains functional ledgers for transmission and distribution. Please see the testimony of Randall W. Hamlett for Meter and TDCS functionalization.

Sheet WP II-D-2.5-3 Bus-Econ AEPSC
B2: PUBLIC UTILITY COMMISSION OF TEXAS
B3: AEPSC BILLINGS TO AEP TEXAS INC. (CENTRAL DIVISION)
B4: WP/ II-D-2.5-3 SUMMARY OF BUSINESS / ECONOMIC DEVELOPMENT
B5: TEST YEAR ENDING 12/31/2018
B6: ='WP II-D-2.5-2 Com Service AEPSC'!B5 -> DOCKET XXXXX
E9: 1 | F9: 2 | G9: 3 | H9: 4 | I9: 5 | J9: 6 | K9: 7 | L9: 8 | M9: 9 | N9: 10 | O9: 11 | P9: 12 | Q9: 13
H10: Company | I10: Texas
B11: Account | C11: Organization | D11: Reference | E11: Total | F11: Non-Regulated | G11: Known | H11: Total | I11: Retail | J11: Allocation to | K11: FF | L11: Funct | M11: TRAN | N11: DIST | O11: MET | P11: TDCS | Q11: Total
A12: Line | B12: Number | D12: Schedule | E12: Company | F12: or Non-Electric | G12: Change | H12: Electric | I12: Allocation | J12: Texas | K12: # | L12: Factor | R12: CHECK
A13: No. | I13: Factor | L13: Name
A14: 1 | B14: 4261 | C14: ASSOCIATION OF GRADUATES | D14: II-D-2.5 | E14: 0 | F14: 0 | G14: =+M14+N14 -> 19.46 | H14: =SUM(F14:G14) -> 19.46 | I14: 1 | J14: =+H14*I14 -> 19.46 | K14: * | L14: * | M14: 10.21 | N14: 9.25 | O14: 0 | P14: 0 | Q14: =SUM(M14:P14) -> 19.46 | R14: =+Q14-J14 -> 0
A15: =+A14+1 -> 2 | B15: 4261 | C15: COUNCIL OF STATE GOVERNMENTS | D15: II-D-2.5 | E15: 0 | F15: 0 | G15: =+M15+N15 -> 1168.1 | H15: =SUM(F15:G15) -> 1168.1 | I15: 1 | J15: =+H15*I15 -> 1168.1 | K15: * | L15: * | M15: 613.03 | N15: 555.07 | O15: 0 | P15: 0 | Q15: =SUM(M15:P15) -> 1168.1 | R15: =+Q15-J15 -> 0
A16: =+A15+1 -> 3 | B16: 4261 | C16: EDISON ELECTRIC INSTITUTE | D16: II-D-2.5 | E16: 0 | F16: 0 | G16: =+M16+N16 -> 4427.05 | H16: =SUM(F16:G16) -> 4427.05 | I16: 1 | J16: =+H16*I16 -> 4427.05 | K16: * | L16: * | M16: 2323.35 | N16: 2103.7 | O16: 0 | P16: 0 | Q16: =SUM(M16:P16) -> 4427.05 | R16: =+Q16-J16 -> 0
A17: =+A16+1 -> 4 | B17: 4261 | C17: MIDWESTERN GOVERNORS ASSOCIATION | D17: II-D-2.5 | E17: 0 | F17: 0 | G17: =+M17+N17 -> 584.05 | H17: =SUM(F17:G17) -> 584.05 | I17: 1 | J17: =+H17*I17 -> 584.05 | K17: * | L17: * | M17: 306.51 | N17: 277.54 | O17: 0 | P17: 0 | Q17: =SUM(M17:P17) -> 584.05 | R17: =+Q17-J17 -> 0
A18: =+A17+1 -> 5 | B18: 4261 | C18: NATIONAL GOVERNORS ASSOCIATION | D18: II-D-2.5 | E18: 0 | F18: 0 | G18: =+M18+N18 -> 5817.22 | H18: =SUM(F18:G18) -> 5817.22 | I18: 1 | J18: =+H18*I18 -> 5817.22 | K18: * | L18: * | M18: 3052.92 | N18: 2764.3 | O18: 0 | P18: 0 | Q18: =SUM(M18:P18) -> 5817.22 | R18: =+Q18-J18 -> 0
A19: =+A18+1 -> 6 | B19: 4261 | C19: UNMANNED SYSTEMS ASSOCIATION OF VIRGINIA | D19: II-D-2.5 | E19: 0 | F19: 0 | G19: =+M19+N19 -> 388.95 | H19: =SUM(F19:G19) -> 388.95 | I19: 1 | J19: =+H19*I19 -> 388.95 | K19: * | L19: * | M19: 204.12 | N19: 184.83 | O19: 0 | P19: 0 | Q19: =SUM(M19:P19) -> 388.95 | R19: =+Q19-J19 -> 0
A20: =+A19+1 -> 7 | B20: 4264 | C20: NATIONAL PETROLEUM COUNCIL | D20: II-D-2.5 | E20: 0 | F20: 0 | G20: =+M20+N20 -> 86.19 | H20: =SUM(F20:G20) -> 86.19 | I20: 1 | J20: =+H20*I20 -> 86.19 | K20: * | L20: * | M20: 48.48 | N20: 37.71 | O20: 0 | P20: 0 | Q20: =SUM(M20:P20) -> 86.19 | R20: =+Q20-J20 -> 0
A21: =+A20+1 -> 8 | B21: 4264 | C21: UNITED STATES CHAMBER OF COMMERCE | D21: II-D-2.5 | E21: 0 | F21: 0 | G21: =+M21+N21 -> 44615.11 | H21: =SUM(F21:G21) -> 44615.11 | I21: 1 | J21: =+H21*I21 -> 44615.11 | K21: * | L21: * | M21: 24635.4 | N21: 19979.71 | O21: 0 | P21: 0 | Q21: =SUM(M21:P21) -> 44615.11 | R21: =+Q21-J21 -> 0
A22: =+A21+1 -> 9 | B22: 4265 | C22: BLACKBAUD INC | D22: II-D-2.5 | E22: 0 | F22: 0 | G22: =+M22+N22 -> -1816.18 | H22: =SUM(F22:G22) -> -1816.18 | I22: 1 | J22: =+H22*I22 -> -1816.18 | K22: * | L22: * | M22: -989.95 | N22: -826.23 | O22: 0 | P22: 0 | Q22: =SUM(M22:P22) -> -1816.18 | R22: =+Q22-J22 -> 0
A23: =+A22+1 -> 10 | B23: 4265 | C23: NATIONAL PETROLEUM COUNCIL | D23: II-D-2.5 | E23: 0 | F23: 0 | G23: =+M23+N23 -> 2786.77 | H23: =SUM(F23:G23) -> 2786.77 | I23: 1 | J23: =+H23*I23 -> 2786.77 | K23: * | L23: * | M23: 1567.59 | N23: 1219.18 | O23: 0 | P23: 0 | Q23: =SUM(M23:P23) -> 2786.77 | R23: =+Q23-J23 -> 0
A24: =+A23+1 -> 11 | B24: 4265 | C24: NEW YORK FINANCIAL WRITERS ASSOCIATION | D24: II-D-2.5 | E24: 0 | F24: 0 | G24: =+M24+N24 -> 370.24 | H24: =SUM(F24:G24) -> 370.24 | I24: 1 | J24: =+H24*I24 -> 370.24 | K24: * | L24: * | M24: 205.04 | N24: 165.2 | O24: 0 | P24: 0 | Q24: =SUM(M24:P24) -> 370.24 | R24: =+Q24-J24 -> 0
A26: 12 | C26: TOTAL BUSINESS / ECONOMIC DEVELOPMENT | D26: II-D-2.5 | E26: =+SUM(E14:E24) -> 0 | F26: =+SUM(F14:F24) -> 0 | G26: =+SUM(G14:G24) -> 58446.96 | H26: =+SUM(H14:H24) -> 58446.96 | J26: =+SUM(J14:J24) -> 58446.96 | K26: =+SUM(K14:K24) -> 0 | L26: =+SUM(L14:L24) -> 0 | M26: =+SUM(M14:M24) -> 31976.7 | N26: =+SUM(N14:N24) -> 26470.26 | O26: =+SUM(O14:O24) -> 0 | P26: =+SUM(P14:P24) -> 0 | Q26: =+SUM(Q14:Q24) -> 58446.96 | R26: =+SUM(R14:R24) -> 0
A28: 13 | F28: *AEP Texas (Central Division) maintains functional ledgers for transmission and distribution. Please see the testimony of Randall W. Hamlett for Meter and TDCS functionalization.

Sheet WP II-D-2.5-4 Industry
B2: PUBLIC UTILITY COMMISSION OF TEXAS
B3: AEP TEXAS INC. (CENTRAL DIVISION)
B4: WP/ II-D-2.5-5 SUMMARY OF INDUSTRY
B5: TEST YEAR ENDING 12/31/2018
B6: ='WP II-D-2.5-2 Com Service'!B5 -> DOCKET XXXXX
E9: 1 | F9: 2 | G9: 3 | H9: 4 | I9: 5 | J9: 6 | K9: 7 | L9: 8 | M9: 9 | N9: 10 | O9: 11 | P9: 12 | Q9: 13
H10: Company | I10: Texas
B11: Account | C11: Organization | D11: Reference | E11: Total | F11: Non-Regulated | G11: Known | H11: Total | I11: Retail | J11: Allocation to | K11: FF | L11: Funct | M11: TRAN | N11: DIST | O11: MET | P11: TDCS | Q11: Total
A12: Line | B12: Number | D12: Schedule | E12: Company | F12: or Non-Electric | G12: Change | H12: Electric | I12: Allocation | J12: Texas | K12: # | L12: Factor | R12: CHECK
A13: No. | I13: Factor | L13: Name
A14: 1 | B14: 4261 | C14: EDISON ELECTRIC INSTITUTE | D14: II-D-2.5 | E14: 0 | F14: 0 | G14: 3844.2 | H14: =SUM(F14:G14) -> 3844.2 | I14: ='[16]Juris Alloc Split'!$M$351 -> 1 | J14: =((H14-M14)*I14)+M14 -> 3844.2 | K14: * | L14: * | M14: 1764.7632 | N14: 2079.4368 | O14: 0 | P14: 0 | Q14: =SUM(M14:P14) -> 3844.2 | R14: =+Q14-J14 -> 0
A16: 2 | C16: TOTAL ECONOMIC DEVELOPMENT | D16: II-D-2.5 | E16: =+SUM(E14:E15) -> 0 | F16: =+SUM(F14:F15) -> 0 | G16: =+SUM(G14:G15) -> 3844.2 | H16: =+SUM(H14:H15) -> 3844.2 | J16: =+SUM(J14:J15) -> 3844.2 | M16: =+SUM(M14:M15) -> 1764.7632 | N16: =+SUM(N14:N15) -> 2079.4368 | O16: =+SUM(O14:O15) -> 0 | P16: =+SUM(P14:P15) -> 0 | Q16: =+SUM(Q14:Q15) -> 3844.2 | R16: =+SUM(R14:R15) -> 0
F18: *AEP Texas (Central Division) maintains functional ledgers for transmission and distribution. Please see the testimony of Randall W. Hamlett for Meter and TDCS functionalization.

Sheet WP II-D-2.5-4 Industry AEPSC
B2: PUBLIC UTILITY COMMISSION OF TEXAS
B3: AEPSC BILLINGS TO AEP TEXAS INC. (CENTRAL DIVISION)
B4: WP/ II-D-2.5-5 SUMMARY OF INDUSTRY
B5: TEST YEAR ENDING 12/31/2018
B6: ='WP II-D-2.5-2 Com Service AEPSC'!B5 -> DOCKET XXXXX
E9: 1 | F9: 2 | G9: 3 | H9: 4 | I9: 5 | J9: 6 | K9: 7 | L9: 8 | M9: 9 | N9: 10 | O9: 11 | P9: 12 | Q9: 13
H10: Company | I10: Texas
B11: Account | C11: Organization | D11: Reference | E11: Total | F11: Non-Regulated | G11: Known | H11: Total | I11: Retail | J11: Allocation to | K11: FF | L11: Funct | M11: TRAN | N11: DIST | O11: MET | P11: TDCS | Q11: Total
A12: Line | B12: Number | D12: Schedule | E12: Company | F12: or Non-Electric | G12: Change | H12: Electric | I12: Allocation | J12: Texas | K12: # | L12: Factor | R12: CHECK
A13: No. | I13: Factor | L13: Name
A14: 1 | B14: 4261 | C14: EDISON ELECTRIC INSTITUTE | D14: II-D-2.5 | E14: 0 | F14: 0 | H14: =SUM(F14:G14) -> 0 | I14: 1 | J14: =((H14-M14)*I14)+M14 -> 0 | K14: * | L14: * | O14: 0 | P14: 0 | Q14: =SUM(M14:P14) -> 0 | R14: =+Q14-J14 -> 0
A16: 2 | C16: TOTAL ECONOMIC DEVELOPMENT | D16: II-D-2.5 | E16: =+SUM(E14:E15) -> 0 | F16: =+SUM(F14:F15) -> 0 | G16: =+SUM(G14:G15) -> 0 | H16: =+SUM(H14:H15) -> 0 | J16: =+SUM(J14:J15) -> 0 | M16: =+SUM(M14:M15) -> 0 | N16: =+SUM(N14:N15) -> 0 | O16: =+SUM(O14:O15) -> 0 | P16: =+SUM(P14:P15) -> 0 | Q16: =+SUM(Q14:Q15) -> 0 | R16: =+SUM(R14:R15) -> 0
A18: 3 | F18: *AEP Texas (Central Division) maintains functional ledgers for transmission and distribution. Please see the testimony of Randall W. Hamlett for Meter and TDCS functionalization.

Sheet WP II-E-2-1 FICA
A1: PUBLIC UTILITY COMMISSION OF TEXAS
A2: AEP TEXAS INC - CENTRAL DIVISION
A3: WP/ II-B ADJUSTMENTS FROM TCOS FILINGS
A4: TEST YEAR ENDING 12/31/2018
A8: Line No. | B8: Account | C8: Description | D8: Ref | E8: Total | F8: Transmission | G8: Distribution
B11: 408.1 | C11: FICA Adjustment for Base Payroll
A12: 1 | C12: Total FICA Costs | D12: II-E-2 | E12: ='[10]II-E-2 Taxes Other'!$F$18+'[10]II-E-2 Taxes Other'!$E$18 -> 8526240.7
A14: 2 | C14: Central Division Test Year Base Payroll | D14: II-D-3.2 | E14: ='[10]II-D-3.2 Reg and Overtime'!$AC$24 -> 91591287
A15: 3 | C15: Central Division Test Year Overtime Payroll | D15: II-D-3.2 | E15: ='[10]II-D-3.2 Reg and Overtime'!$AD$24 -> 14737965
A16: 4 | C16: Central Division Test Year Special Pay | D16: II-D-3.2 | E16: ='[10]II-D-3.2 Reg and Overtime'!$AF$24 -> 8979886
A17: 5 | C17: Total Central Division Test Year Compensation | E17: =SUM(E14:E16) -> 1.1530914e+08
A19: 6 | C19: Effective FICA rate | E19: =E12/E17 -> 0.073942454
A21: 7 | C21: Payroll related proforma adjustments
A22: 8 | C22: Base Payroll | D22: WP II-D-1.1 | E22: ='WP II-D-1-1 Payroll'!F100 -> 1654189.7 | F22: ='WP II-D-1-1 Payroll'!F57 -> 127912.25 | G22: ='WP II-D-1-1 Payroll'!F41 -> 1526277.4 | W22: 0
A23: 9 | C23: Annual Incentive | D23: WP II-D-1.4 | E23: ='WP II-D-1-4 ICP'!F93 -> -1483594.1 | F23: ='WP II-D-1-4 ICP'!F23 -> -254228.64 | G23: ='WP II-D-1-4 ICP'!F53 -> -1229365.5
A24: 10 | C24: Long Term Incentive | D24: WP II-D-1.5 | E24: ='WP II-D-1-5 LTIP'!F93 -> -91362.051 | F24: ='WP II-D-1-5 LTIP'!F23 -> -1500.934 | G24: ='WP II-D-1-5 LTIP'!F53 -> -89861.117
A25: 11 | C25: Total payroll related adjustments | E25: =SUM(E22:E24) -> 79233.493 | F25: =SUM(F22:F24) -> -127817.32 | G25: =SUM(G22:G24) -> 207050.82
A27: 12 | C27: Total FICA expense adjustment | E27: =E25*E19 -> 5858.719 | F27: =F25*E19 -> -9451.1265 | G27: =G25*E19 -> 15309.845
C31: PURPOSE
C32: To adjust FICA expense consistent with base payroll and incentive payroll adjustments. The discussion of this adjustment can be found in the testimony of Mr. Randall Hamlett.

Sheet WP II-E-2-2 Ad Valorem
A1: PUBLIC UTILITY COMMISSION OF TEXAS | D1: WP II-E-2-2
A2: AEP TEXAS INC - CENTRAL DIVISION
A3: AD VALOREM EXPENSE ADJUSTMENT
A4: TEST YEAR ENDING 12/31/2018
A7: DESCRIPTION | B7: FERC | C7: Transmission | D7: Distribution
A9: Ad Valorem Expense For Test Year | B9: 4081005 | C9: 17702781 | D9: 32572266
B10: 4081029 | C10: 313347.7 | D10: 1056008.4
A11: Adjustments:
A12: Pro forma Ad Valorem Expense Adjustment | C12: =+'[10]II-E-2.1 Ad valorem'!$E$33 -> 8452126.3 | D12: =+'[10]II-E-2.1 Ad valorem'!$F$33 -> 1811782.4
A14: Total Adjustments | C14: =C12 -> 8452126.3 | D14: =D12 -> 1811782.4
A16: Pro forma Ad Valorem Expense | C16: =SUM(C9:C12) -> 26468255 | D16: =SUM(D9:D12) -> 35440057
A18: Total Proforma T & D | D18: =SUM(C16:D16) -> 61908311
A24: Month | B24: FERC Account | C24: Transmission | D24: Distribution | E24: Grand Total
A26: Jan | B26: 408100518 | C26: 1747078 | D26: 2493778 | E26: =+D26+C26 -> 4240856
B27: 408102917 | C27: -4.67 | D27: 10658 | E27: =+D27+C27 -> 10653.33
B28: 408102918 | C28: 10625 | D28: 31875 | E28: =+D28+C28 -> 42500
A29: Jan Total | C29: =SUM(C26:C28) -> 1757698.3 | D29: =SUM(D26:D28) -> 2536311 | E29: =SUM(E26:E28) -> 4294009.3
A30: Feb | B30: 408100516 | C30: 0 | D30: 1884.59 | E30: =+D30+C30 -> 1884.59
B31: 408100517 | C31: -3036156.6 | D31: 2968131.8 | E31: =+D31+C31 -> -68024.82
B32: 408100518 | C32: 1747078 | D32: 2493778 | E32: =+D32+C32 -> 4240856
B33: 408102917 | C33: 56185.37 | D33: 168556.13 | E33: =+D33+C33 -> 224741.5
B34: 408102918 | C34: 10625 | D34: 31875 | E34: =+D34+C34 -> 42500
A35: Feb Total | C35: =SUM(C30:C34) -> -1222268.2 | D35: =SUM(D30:D34) -> 5664225.5 | E35: =SUM(E30:E34) -> 4441957.3
A36: Mar | B36: 408100516 | C36: 0 | D36: 273.96 | E36: =+D36+C36 -> 273.96
B37: 408100517 | C37: 0 | D37: 4569.84 | E37: =+D37+C37 -> 4569.84
B38: 408100518 | C38: 1747078 | D38: 2493778 | E38: =+D38+C38 -> 4240856
B39: 408102918 | C39: 10625 | D39: 31875 | E39: =+D39+C39 -> 42500
A40: Mar Total | C40: =SUM(C36:C39) -> 1757703 | D40: =SUM(D36:D39) -> 2530496.8 | E40: =SUM(E36:E39) -> 4288199.8
A41: Apr | B41: 408100518 | C41: 1747078 | D41: 2493778 | E41: =+D41+C41 -> 4240856
B42: 408102918 | C42: 10625 | D42: 31875 | E42: =+D42+C42 -> 42500
A43: Apr Total | C43: =SUM(C41:C42) -> 1757703 | D43: =SUM(D41:D42) -> 2525653 | E43: =SUM(E41:E42) -> 4283356
A44: May | B44: 408100517 | C44: 0 | D44: 161.37 | E44: =+D44+C44 -> 161.37
B45: 408100518 | C45: 1900948 | D45: 2707581 | E45: =+D45+C45 -> 4608529
B46: 408102918 | C46: 64653.33 | D46: 193959.67 | E46: =+D46+C46 -> 258613
A47: May Total | C47: =SUM(C44:C46) -> 1965601.3 | D47: =SUM(D44:D46) -> 2901702 | E47: =SUM(E44:E46) -> 4867303.4
A48: Jun | B48: 408100518 | C48: 1777852 | D48: 2536539 | E48: =+D48+C48 -> 4314391
B49: 408102918 | C49: 21431 | D49: 64292 | E49: =+D49+C49 -> 85723
A50: Jun Total | C50: =SUM(C48:C49) -> 1799283 | D50: =SUM(D48:D49) -> 2600831 | E50: =SUM(E48:E49) -> 4400114
A51: Jul | B51: 408100518 | C51: 1777852 | D51: 2536539 | E51: =+D51+C51 -> 4314391
B52: 408102918 | C52: 21431 | D52: 64292 | E52: =+D52+C52 -> 85723
A53: Jul Total | C53: =SUM(C51:C52) -> 1799283 | D53: =SUM(D51:D52) -> 2600831 | E53: =SUM(E51:E52) -> 4400114
A54: Aug | B54: 408100514 | C54: 0 | D54: -523.07 | E54: =+D54+C54 -> -523.07
B55: 408100517 | C55: 1135.39 | D55: -3777 | E55: =+D55+C55 -> -2641.61
B56: 408100518 | C56: 1777852 | D56: 2536539 | E56: =+D56+C56 -> 4314391
B57: 408102918 | C57: 21431 | D57: 64292 | E57: =+D57+C57 -> 85723
A58: Aug Total | C58: =SUM(C54:C57) -> 1800418.4 | D58: =SUM(D54:D57) -> 2596530.9 | E58: =SUM(E54:E57) -> 4396949.3
A59: Sep | B59: 408100517 | C59: 0 | D59: -8873.93 | E59: =+D59+C59 -> -8873.93
B60: 408100518 | C60: 1777852 | D60: 2536539 | E60: =+D60+C60 -> 4314391
B61: 408102917 | C61: 0 | D61: 103273.2 | E61: =+D61+C61 -> 103273.2
B62: 408102918 | C62: 21431 | D62: 64292 | E62: =+D62+C62 -> 85723
A63: Sep Total | C63: =SUM(C59:C62) -> 1799283 | D63: =SUM(D59:D62) -> 2695230.3 | E63: =SUM(E59:E62) -> 4494513.3
A64: Oct | B64: 408100518 | C64: 1777852 | D64: 2536539 | E64: =+D64+C64 -> 4314391
B65: 408102917 | C65: 0 | D65: 2018.05 | E65: =+D65+C65 -> 2018.05
B66: 408102918 | C66: 21431 | D66: 64292 | E66: =+D66+C66 -> 85723
A67: Oct Total | C67: =SUM(C64:C66) -> 1799283 | D67: =SUM(D64:D66) -> 2602849 | E67: =SUM(E64:E66) -> 4402132
A68: Nov | B68: 408100518 | C68: 1777852 | D68: 2536539 | E68: =+D68+C68 -> 4314391
B69: 408102918 | C69: 21431 | D69: 64292 | E69: =+D69+C69 -> 85723
A70: Nov Total | C70: =SUM(C68:C69) -> 1799283 | D70: =SUM(D68:D69) -> 2600831 | E70: =SUM(E68:E69) -> 4400114
A71: Dec | B71: 408100513 | C71: 0 | D71: 136.45 | E71: =+D71+C71 -> 136.45
B72: 408100514 | C72: 0 | D72: 137.23 | E72: =+D72+C72 -> 137.23
B73: 408100515 | C73: 0 | D73: 137.23 | E73: =+D73+C73 -> 137.23
B74: 408100516 | C74: 0 | D74: 137.68 | E74: =+D74+C74 -> 137.68
B75: 408100517 | C75: 0 | D75: 137.84 | E75: =+D75+C75 -> 137.84
B76: 408100518 | C76: 1181429.9 | D76: 1707804.9 | E76: =+D76+C76 -> 2889234.8
B77: 408102918 | C77: 21427.67 | D77: 64291.33 | E77: =+D77+C77 -> 85719
A78: Dec Total | C78: =SUM(C71:C77) -> 1202857.6 | D78: =SUM(D71:D77) -> 1772782.7 | E78: =SUM(E71:E77) -> 2975640.3
A79: Grand Total | C79: =+C78+C70+C67+C63+C58+C53+C50+C47+C43+C40+C35+C29 -> 18016128 | D79: =+D78+D70+D67+D63+D58+D53+D50+D47+D43+D40+D35+D29 -> 33628274 | E79: =+E78+E70+E67+E63+E58+E53+E50+E47+E43+E40+E35+E29 -> 51644403

Sheet WP II-E-2-3 Municipal Fees
A1: AEP TEXAS INC - CENTRAL DIVISION | H1: WP II-E-2-3
A2: Municipal Franchise Fees
A3: For Test Period Ending December 31, 2018
A6: Line No. | B6: Revenue Month | F6: Monthly kWh Billed | H6: Franchise Fees Paid
A8: 1 | B8: 43101 | F8: 2329499793 | H8: 4795388.5
A9: 2 | B9: =+B8+31 -> 43132 | F9: 1799407606 | H9: 3262205.4
A10: 3 | B10: =+B9+31 -> 43163 | F10: 1899200561 | H10: 3028081.9
A11: 4 | B11: =+B10+31 -> 43194 | F11: 1967257311 | H11: 3241580.7
A12: 5 | B12: =+B11+31 -> 43225 | F12: 2037678717 | H12: 3494631.2
A13: 6 | B13: =+B12+31 -> 43256 | F13: 2550380777 | H13: 4596577.3
A14: 7 | B14: =+B13+31 -> 43287 | F14: 2444177907 | H14: 4663798.8
A15: 8 | B15: =+B14+31 -> 43318 | F15: 2541619220 | H15: 4801245.7
A16: 9 | B16: =+B15+31 -> 43349 | F16: 2607846278 | H16: 4747793.9
A17: 10 | B17: =+B16+31 -> 43380 | F17: 2024169841 | H17: 3981422.8
A18: 11 | B18: =+B17+31 -> 43411 | F18: 2039304532 | H18: 3370548.6
A19: 12 | B19: =+B18+31 -> 43442 | F19: 1821258685 | H19: 3211105.8
A21: 13 | B21: TOTAL | F21: =SUM(F8:F20) -> 26061801228 | H21: =SUM(H8:H20) -> 47194381
A23: 14 | B23: Total municipal franchise fees for the 12-mtd ended December 31, 2018 | H23: =H21 -> 47194381
A26: 15 | B26: Per Test Year Books | H26: =+H23 -> 47194381
A28: 16 | B28: Local Muncipal Franchise Fee Rate per KWH | H28: =+H23/F21 -> 0.0018108641
A30: 17 | B30: KWH per Test Year Requested PER Schedule II-H-1.1 | F30: ='[17]II-H-1.1'!$J$30 -> 2.6313304e+10 | H30: =+F30*H28 -> 47649817
A32: 18 | B32: Pro Forma Adjustment Amount | H32: =+H30-H26 -> 455436.55

Sheet WP II-E-1 Amort. Exp
A1: PUBLIC UTILITY COMMISSION OF TEXAS | I1: WP/ II-E-1
A2: AEP TEXAS INC - CENTRAL DIVISION
A3: WP/ II-E-4-1 ELIMINATION OF AMORT. EXP
A4: TEST YEAR ENDING 12/31/2018
A8: Line No. | B8: Account Number | C8: Description | E8: Transmission | F8: Distribution | G8: Total T&D
A9: 1 | B9: 4073 | C9: Regulatory Debits | F9: -9441782.5 | G9: =+SUM(E9:F9) -> -9441782.5
A10: 2 | B10: 4074 | C10: Regulatory Credits | E10: 0 | F10: 3030075.8 | G10: =+SUM(E10:F10) -> 3030075.8
A11: 3 | C11: Total | E11: =+SUM(E9:E10) -> 0 | F11: =+SUM(F9:F10) -> -6411706.7 | G11: =+SUM(G9:G10) -> -6411706.7
A21: 4 | B21: To remove amortization expense recovered through riders and to remove amortization expense for items fully amortized at the effective rate date.

Sheet WP II-E-2-4 Gross Margin tax
B1: PUBLIC UTILITY COMMISSION OF TEXAS
B2: AEP TEXAS INC - CENTRAL DIVISION
B3: TEXAS MARGIN TAX
B4: TEST YEAR ENDING 12/31/2018
B7: 1 | C7: 2 | D7: 3 | E7: 4 | F7: 5
A8: Line
A9: No. | B9: Description | C9: Reference | D9: Transmission | E9: Distribution | F9: Total Company
A12: 1 | B12: Test Year Revenues | C12: I-A-1 | D12: 2.3490696e+08 | E12: 7.1187659e+08 | F12: =+D12+E12 -> 9.4678355e+08 | G12: =+[18]FERC_IS1!$K$44 -> 9.4678355e+08
A13: =A12+1 -> 2
A14: =A13+1 -> 3 | B14: Requested Revenue Requirement | C14: I-A-1 | D14: ='[10]I-A-1'!$G$36 -> 2.7428239e+08 | E14: ='[10]I-A'!$F$30 -> 7.6158129e+08 | F14: =+D14+E14 -> 1.0358637e+09
A15: =A14+1 -> 4
A16: =A15+1 -> 5 | B16: Increase/(Decrease) in Gross Operating Revenues | C16: line 1 divided line 2 minus 1 | D16: =(+D14/D12)-1 -> 0.1676214 | E16: =(+E14/E12)-1 -> 0.069822079
A17: =A16+1 -> 6
A18: =A17+1 -> 7 | B18: Gross Margin Tax Expense in Test Year | C18: II-E-2 Taxes Other | D18: 281208 | E18: 971618 | F18: =+D18+E18 -> 1252826
A19: =A18+1 -> 8 | B19: Less Prior Year Tax Adjustments | D19: -238278 | E19: -621184 | F19: =+D19+E19 -> -859462
A20: =A19+1 -> 9 | B20: Adjusted Gross Margin Tax Expense in Test Year | C20: plus line 7 minus line 8 | D20: =+D18-D19 -> 519486 | E20: =+E18-E19 -> 1592802 | F20: =+D20+E20 -> 2112288
A21: =A20+1 -> 10
A22: =A21+1 -> 11 | B22: Requested Texas Gross Margin Tax | C22: line 5 times line 9 | D22: =+D20*(1+D16) -> 606562.97 | E22: =+E20*(1+E16) -> 1704014.7 | F22: =SUM(D22:E22) -> 2310577.7
A23: =A22+1 -> 12
A24: =A23+1 -> 13 | B24: Pro Froma Adjustment | C24: plus line 11 minus line 7 | D24: =+D22-D18 -> 325354.97 | E24: =+E22-E18 -> 732396.75 | F24: =+F22-F18 -> 1057751.7
A25: =A24+1 -> 14
D31: x969
C32: 4540001 | D32: 1901031.6 | E32: D
C33: 4561001 | D33: 17774679 | E33: D
D34: =SUM(D32:D33) -> 19675711
B36: =CELL("filename",B1) -> https://sharenow.sp.aepsc.com/shsvcs/regsvcs/aeptexas/2018 Base Rate Case/Schedules/Randy Schedules/[AEPTexas Central Div WorkPaper Schedules TYE 12-31-18.xlsx]WP II-E-2-4 Gross Margin tax

Sheet WP II-E-2-5 Sales and Use
A1: AEP TEXAS INC - CENTRAL DIVISION | H1: WP II-E-2-5
A2: Sales and Use Tax
A3: For Test Period Ending December 31, 2018
F6: Test Year Ending 12/31/2018
F7: Transmission | G7: Distribution | H7: Total T&D
A8: Line No. | B8: Account | C8: Description | H8: Monthly kWh Billed
A10: 1 | B10: =+[19]PIVOT!$A5 -> 408101900 | C10: State Sales and Use Taxes | F10: -26100 | G10: -111400 | H10: =+F10+G10 -> -137500
A11: 2 | B11: =+[19]PIVOT!$A6 -> 408101916 | C11: State Sales and Use Taxes | F11: 40896.94 | G11: 153850.41 | H11: =+F11+G11 -> 194747.35
A12: 3 | B12: =+[19]PIVOT!$A7 -> 408101917 | C12: State Sales and Use Taxes | F12: 0 | G12: 0.31 | H12: =+F12+G12 -> 0.31
A13: 4 | B13: =+[19]PIVOT!$A8 -> 408101918 | C13: State Sales and Use Taxes | F13: 2103.39 | G13: 0.63 | H13: =+F13+G13 -> 2104.02
A14: 5 | F14: =SUM(F10:F13) -> 16900.33 | G14: =SUM(G10:G13) -> 42451.35 | H14: =SUM(H10:H13) -> 59351.68
A15: 6
A16: 7 | B16: Adjustment for Prior year Audits | F16: =+F10+F11+F12 -> 14796.94 | G16: =+G10+G11+G12 -> 42450.72 | H16: =+F16+G16 -> 57247.66
A17: 8 | B17: Adjusted Test Year Amount | F17: =+F14-F16 -> 2103.39 | G17: =+G14-G16 -> 0.63 | H17: =+H14-H16 -> 2104.02
A18: 9 | B18: Estimated % Related to construction | F18: =+F31 -> 0.92788939 | G18: =+F18 -> 0.92788939
A19: =+A18+1 -> 10 | B19: Adjustment for Construction Portion of Adjusted
A20: =+A19+1 -> 11 | B20: Test Year Amount | F20: =+F17*F18 -> 1951.7133 | G20: =+G17*G18 -> 0.58457032 | H20: =+F20+G20 -> 1952.2978
A21: =+A20+1 -> 12
A22: =+A21+1 -> 13 | B22: Total Adjustment to State Sales and Use Tax | F22: =-F20-F16 -> -16748.653 | G22: =-G20-G16 -> -42451.305 | H22: =-H20-H16 -> -59199.958
A23: =+A22+1 -> 14
A24: =+A23+1 -> 15 | B24: Pro Froma Expense Amount | F24: =F14+F22 -> 151.67673 | G24: =G14+G22 -> 0.045429682 | H24: =H14+H22 -> 151.72216
A25: =+A24+1 -> 16
A26: =+A25+1 -> 17 | B26: Expense/Capital Allocation
A27: =+A26+1 -> 18 | B27: Per 12/31/2018 Form 1, Pg 227
A28: =+A27+1 -> 19
A29: =+A28+1 -> 20 | B29: A/C 154 Materials assigned to Construction | F29: 38504075
A30: =+A29+1 -> 21 | B30: Total M&S in A/C 154 | F30: 41496406
A31: =+A30+1 -> 22 | B31: Estimated Amount Related to Construction | F31: =+F29/F30 -> 0.92788939
A32: =+A31+1 -> 23
A33: =+A32+1 -> 24
A34: =+A33+1 -> 25

Sheet WP II-E-4.5 Rate Case Exp Est
F1: Central | G1: North
A2: AEP Texas Inc. Estimated Rate Case Expenses | F2: Divisional Allocation (1)
A3: For the Test Year Ended December 31, 2018 | F3: 3.6708695e+09 | G3: 1.286704e+09 | H3: =+SUM(F3:G3) -> 4.9575735e+09
F4: =+F3/H3 -> 0.74045689 | G4: =+G3/H3 -> 0.25954311
A5: Company Expenses | F5: Central | G5: North
A6: Employee Travel (includes meals and hotels) | D6: 300000 | F6: =+D6*$F$4 -> 222137.07 | G6: =+D6*G4 -> 77862.932
A8: Other Expenses
A9: Printing and Delivery | B9: 150000 | F9: =+B9*$F$4 -> 111068.53 | G9: =+B9*$G$4 -> 38931.466
A10: Temporary Employees | B10: 100000 | F10: =+B10*$F$4 -> 74045.689 | G10: =+B10*$G$4 -> 25954.311
A11: Newspaper Notice | B11: 300000 | F11: =+B11*$F$4 -> 222137.07 | G11: =+B11*$G$4 -> 77862.932
A12: Miscellaneous | B12: 50000 | F12: =+B12*$F$4 -> 37022.845 | G12: =+B12*$G$4 -> 12977.155
A13: Total Other Expenses | D13: =SUM(B9:B12) -> 600000 | F13: =+SUM(F9:F12) -> 444274.14 | G13: =+SUM(G9:G12) -> 155725.86
A15: Outside Legal | D15: 3000000 | F15: =+D15*$F$4 -> 2221370.7 | G15: =+D15*G4 -> 778629.32
A17: Consulting
A18: Hevert - Scottmadden, LLC ROE | B18: 100000 | F18: =+B18*$F$4 -> 74045.689 | G18: =+B18*$G$4 -> 25954.311
A19: Patrick Baryenbruch Affiliate | B19: 100000 | F19: =+B19*$F$4 -> 74045.689 | G19: =+B19*$G$4 -> 25954.311
A20: Joyce - Expergy Lead Lag | B20: 125000 | F20: =+B20*$F$4 -> 92557.112 | G20: =+B20*$G$4 -> 32442.888
A21: Wilson - Lewis & Ellis Catastrophe Reserve | B21: 10000 | F21: =+B21*$F$4 -> 7404.5689 | G21: =+B21*$G$4 -> 2595.4311
A22: Fetter - Regulation UnFettered Cap Structure | B22: 100000 | F22: =+B22*$F$4 -> 74045.689 | G22: =+B22*$G$4 -> 25954.311
A23: Total Other Consulting | D23: =SUM(B18:B22) -> 435000 | F23: =+D23*$F$4 -> 322098.75 | G23: =+SUM(G18:G22) -> 112901.25
A25: Cities Expenses | D25: 2000000 | F25: =+D25*$F$4 -> 1480913.8 | G25: =+D25*G4 -> 519086.21
A26: Total Estimated Rate Case Expenses | D26: =SUM(D6:D25) -> 6335000 | F26: =+F25+F23+F15+F13+F6 -> 4690794.4 | G26: =+G25+G23+G15+G13+G6 -> 1644205.6
A28: (1) Allocation based on requested rate base

Sheet WP II-E-5
A1: AEP TCC - T&D Revenues TY Ending December 2018 | F1: WP-II-E-5
D5: Unadjusted Revenue* | J5: Adjustments | O5: Adjusted Revenue
A6: FERC A/C | B6: Description | D6: Transmission | F6: Distribution | H6: Total T&D | J6: Transmission | K6: Distribution | L6: Metering | M6: Total T&D | O6: Transmission | P6: Distribution | Q6: Metering | R6: Total T&D
A7: 4500000 | B7: Forfeited Discounts | D7: 0 | F7: 170638.71 | H7: 170638.71 | M7: 0 | O7: 0 | P7: 170638.71 | Q7: 0 | R7: 170638.71
B8: Total A/C 450 | D8: 0 | F8: 170638.71 | H8: 170638.71 | J8: 0 | K8: 0 | L8: 0 | M8: 0 | O8: 0 | P8: 170638.71 | Q8: 0 | R8: 170638.71
A10: 4510001 | B10: Misc Service Rev - Nonaffil | D10: 0 | F10: 1491341.1 | H10: 1491341.1 | K10: 151133 | L10: 60270 | M10: 211403 | O10: 0 | P10: 1642474.1 | Q10: 60270 | R10: 1702744.1
B11: Total A/C 451 | D11: 0 | F11: 1491341.1 | H11: 1491341.1 | J11: 0 | K11: 151133 | L11: 60270 | M11: 211403 | O11: 0 | P11: 1642474.1 | Q11: 60270 | R11: 1702744.1
A13: 4540001 | B13: Rent From Elect Property - Af | D13: 118183.68 | F13: 3121857 | H13: 3240040.7 | M13: 0 | O13: 118183.68 | P13: 3121857 | Q13: 0 | R13: 3240040.7
A14: 4540002 | B14: Rent From Elect Property-NAC | D14: 203810.12 | F14: 9232962.3 | H14: 9436772.4 | J14: 3212532.5 | K14: -3590402.5 | M14: -377870 | O14: 3416342.6 | P14: 5642559.8 | Q14: 0 | R14: 9058902.4
A15: 4540004 | B15: Rent From Elect Prop-ABD-Nonaf | D15: 9188.93 | F15: 32158.97 | H15: 41347.9 | M15: 0 | R15: 0
A16: 4540005 | B16: Rent from Elec Prop-Pole Attch | D16: 0 | F16: 6709833.9 | H16: 6709833.9 | J16: 0 | K16: -28151.77 | L16: 0 | M16: -28151.77 | O16: 0 | P16: 6681682.1 | Q16: 0 | R16: 6681682.1
B17: Total A/C 454 | D17: 331182.73 | F17: 19096812 | H17: 19427995 | J17: 3212532.5 | K17: -3618554.3 | L17: 0 | M17: -406021.77 | O17: 3543715.2 | P17: 15478258 | Q17: 0 | R17: 19021973
A20: 4560001 | B20: Oth Elect Rev - Affiliated | D20: 0 | F20: 1469849.9 | H20: 1469849.9 | K20: 0 | M20: 0 | O20: 0 | P20: 1469849.9 | Q20: 0 | R20: 1469849.9
A21: 4560007 | B21: Oth Elect Rev - DSM Program | D21: 0 | F21: -1377936.2 | H21: -1377936.2 | K21: 1377936.2 | M21: 1377936.2 | O21: 0 | P21: 0 | Q21: 0 | R21: 0
A22: 4560012 | B22: Oth Elect Rev - Nonaffiliated | D22: 0 | F22: 57975.73 | H22: 57975.73 | K22: 0 | M22: 0 | O22: 0 | P22: 57975.73 | Q22: 0 | R22: 57975.73
A23: 4560015 | B23: Other Electric Revenues - ABD | D23: 0 | F23: 907515.13 | H23: 907515.13 | J23: 0 | K23: 0 | L23: 0 | M23: 0 | O23: 0 | P23: 907515.13 | Q23: 0 | R23: 907515.13
A24: 4560016 | B24: Financial Trading Rev-Unreal | M24: 0 | O24: 0 | P24: 0 | Q24: 0 | R24: 0
A25: 4560041 | B25: Miscellaneous Revenue-NonAffil | M25: 0 | O25: 0 | P25: 0 | Q25: 0 | R25: 0
A26: 4560088 | B26: LCRA Unbilled Revenue | M26: 0 | O26: 0 | P26: 0 | Q26: 0 | R26: 0
A27: 4560118 | B27: MTM Fleet Fuel Hedging | M27: 0 | O27: 0 | P27: 0 | Q27: 0 | R27: 0
A28: 4560180 | B28: Amort of Defer Equity Inc | D28: 0 | F28: 7258952 | H28: 7258952 | K28: -7258952 | M28: -7258952 | O28: 0 | P28: 0 | Q28: 0 | R28: 0
A29: 4561018 | B29: Oth Elect Rev - Trans - Affil | M29: 0 | O29: 0 | P29: 0 | Q29: 0 | R29: 0
A30: 4561019 | B30: Oth Elec Rev Trans Non Affil | D30: 1246552.4 | F30: 0 | H30: 1246552.4 | M30: 0 | O30: 1246552.4 | P30: 0 | Q30: 0 | R30: 1246552.4
A31: Other Elec. Revenues | D31: 1246552.4 | F31: 8316356.5 | H31: 9562909 | J31: 0 | K31: -5881015.8 | L31: 0 | M31: -5881015.8 | O31: 1246552.4 | P31: 2435340.7 | Q31: 0 | R31: 3681893.2
A33: Other Electric Revenues | D33: 1577735.1 | F33: 29075148 | H33: 30652884 | J33: 3212532.5 | K33: -9348437.1 | L33: 60270 | M33: -6075634.6 | O33: 4790267.7 | P33: 19726711 | Q33: 60270 | R33: 24577249
B36: Trans Matrix Revenue/Distr Wires Revenue
A37: 4560073 | B37: Residential Wires Revenues | D37: 0 | F37: 3.8488742e+08 | H37: 3.8488742e+08 | J37: 0 | K37: -3.8488742e+08 | L37: 0 | M37: -3.8488742e+08 | O37: 0 | P37: 0 | Q37: 0 | R37: 0
A38: 4560074 | B38: Commercial Wires Revenues | D38: 0 | F38: 2.6349965e+08 | H38: 2.6349965e+08 | J38: 0 | K38: -2.6349965e+08 | L38: 0 | M38: -2.6349965e+08 | O38: 0 | P38: 0 | Q38: 0 | R38: 0
A39: 4560075 | B39: Industrial Wires Revenues | D39: 0 | F39: 58981386 | H39: 58981386 | J39: 0 | K39: -58981386 | L39: 0 | M39: -58981386 | O39: 0 | P39: 0 | Q39: 0 | R39: 0
A40: 4560076 | B40: Other Wires Revenues | D40: 0 | F40: 10196394 | H40: 10196394 | J40: 0 | K40: -10196394 | L40: 0 | M40: -10196394 | O40: 0 | P40: 0 | Q40: 0 | R40: 0
A41: 4561000 | B41: ERCOT Matrix Revenue - Non Aff | D41: 2.2090827e+08 | F41: 0 | H41: 2.2090827e+08 | J41: -2.2090827e+08 | M41: -2.2090827e+08 | O41: 0 | P41: 0 | Q41: 0 | R41: 0
A42: 4561001 | B42: ERCOT Matrix Revenue - Affilia | D42: 21770470 | F42: 0 | H42: 21770470 | J42: -21770470 | M42: -21770470 | O42: 0 | P42: 0 | Q42: 0 | R42: 0
D43: 2.4267874e+08 | F43: 7.1756485e+08 | H43: 9.6024359e+08 | J43: -2.4267874e+08 | K43: -7.1756485e+08 | L43: 0 | M43: -9.6024359e+08 | O43: 0 | P43: 0 | Q43: 0 | R43: 0
B45: Total A/C 456 | D45: 2.4392529e+08 | F45: 7.258812e+08 | H45: 9.6980649e+08 | J45: -2.4267874e+08 | K45: -7.2344586e+08 | L45: 0 | M45: -9.661246e+08 | O45: 1246552.4 | P45: 2435340.7 | Q45: 0 | R45: 3681893.2
B49: Total Revenues A/C 450-456 | D49: 2.4425647e+08 | F49: 7.4664e+08 | G49: 0 | H49: 9.9089647e+08 | I49: 0 | J49: -2.3946621e+08 | K49: -7.2691328e+08 | L49: 60270 | M49: -9.6631922e+08 | N49: 0 | O49: 4790267.7 | P49: 19726711 | Q49: 60270 | R49: 24577249
A51: *Revenue does not include consolidations
