Workbook
Name \p: #REF!
Name \p: #REF!
Name \p: #REF!
Name \p: #REF!
Name _1961COPY: #REF!
Name _1961COPY: #REF!
Name _1961COPY: #REF!
Name _1961COPY: #REF!
Name _1961COPY: #REF!
Name _1961COPY: #REF!
Name _1961COPY: #REF!
Name _1961COPY: 'II-E-3.12 ITC Utilized'!$A$1185:$B$1186
Name _1962: #REF!
Name _1962: #REF!
Name _1962: #REF!
Name _1962: #REF!
Name _1962: #REF!
Name _1962: #REF!
Name _1962: #REF!
Name _1962: 'II-E-3.10'!$B$61:$G$111
Name _1962: 'II-E-3.12 ITC Utilized'!$A$1:$E$37
Name _1963: #REF!
Name _1963: #REF!
Name _1963: #REF!
Name _1963: #REF!
Name _1963: #REF!
Name _1963: #REF!
Name _1963: #REF!
Name _1963: 'II-E-3.10'!$B$115:$G$163
Name _1963: 'II-E-3.12 ITC Utilized'!#REF!
Name _1964: #REF!
Name _1964: #REF!
Name _1964: #REF!
Name _1964: #REF!
Name _1964: #REF!
Name _1964: #REF!
Name _1964: #REF!
Name _1964: 'II-E-3.10'!$B$167:$G$215
Name _1964: 'II-E-3.12 ITC Utilized'!#REF!
Name _1965: #REF!
Name _1965: #REF!
Name _1965: #REF!
Name _1965: #REF!
Name _1965: #REF!
Name _1965: #REF!
Name _1965: #REF!
Name _1965: 'II-E-3.10'!$B$219:$G$267
Name _1965: 'II-E-3.12 ITC Utilized'!#REF!
Name _1966: #REF!
Name _1966: #REF!
Name _1966: #REF!
Name _1966: #REF!
Name _1966: #REF!
Name _1966: #REF!
Name _1966: #REF!
Name _1966: 'II-E-3.10'!$B$271:$G$319
Name _1966: 'II-E-3.12 ITC Utilized'!#REF!
Name _1967: #REF!
Name _1967: #REF!
Name _1967: #REF!

Sheet Macros

Sheet I-A
F1: Schedule I-A
B2: PUBLIC UTILITY COMMISSION OF TEXAS
B3: AEP TEXAS INC
B4: I-A COST OF SERVICE SUMMARY
B5: TEST YEAR ENDING 12/31/2018
C8: 1 | D8: 2 | E8: 3 | F8: 4
C10: Reference | D10: Amount at | E10: Adjustment | F10: Amount
A11: Line | B11: Description | C11: Schedule | D11: at | E11: to | F11: at
A12: No. | D12: Existing Rates | E12: Existing Rates | F12: Proposed Rates
A14: 1 | B14: Transmission and Distribution Cost of Service | C14: 1-A-1 | D14: =D16+D17+D18 -> 5.9140261e+08 | E14: =E16+E17+E18 -> 27752838 | F14: =F16+F17+F18 -> 6.1915544e+08
A15: =A14+1 -> 2
A16: =A15+1 -> 3 | B16: Distribution Customer Meter | D16: ='[9]I-A'!$D$16+'[10]I-A'!$D$16 -> 4.5079701e+08 | E16: =F16-D16 -> 1.6835844e+08 | F16: ='I-A-1'!K36 -> 6.1915544e+08
A17: =A16+1 -> 4 | B17: Transition System Base Rate Charge Adjustment | D17: ='[10]I-A'!$D$17+'[9]I-A'!$D$17 -> 1.317052e+08 | E17: =-D17 -> -1.317052e+08 | F17: =SUM(D17:E17) -> 0
A18: =A17+1 -> 5 | B18: Energy Efficiency Base Rate | D18: ='[10]I-A'!$D$18+'[9]I-A'!$D$18 -> 8900402 | E18: =-D18 -> -8900402 | F18: =SUM(D18:E18) -> 0
A19: =A18+1 -> 6 | B19: Transmission and Distribution Cost of Service | D19: =SUM(D16:D18) -> 5.9140261e+08 | E19: =SUM(E16:E18) -> 27752838 | F19: =SUM(F16:F18) -> 6.1915544e+08
A20: =A19+1 -> 7
A21: =A20+1 -> 8 | B21: DCRF | D21: ='[10]I-A'!$D$21+'[9]I-A'!$D$21 -> 73810076 | E21: =-D21 -> -73810076 | F21: =SUM(D21:E21) -> 0
A22: =A21+1 -> 9 | B22: TCRF | D22: ='[10]I-A'!$D$22+'[9]I-A'!$D$22 -> 2.0226217e+08 | E22: =F22-D22 -> 1.2512656e+08 | F22: ='[10]I-A'!$F$22+'[9]I-A'!$F$22 -> 3.2738873e+08
A23: =A22+1 -> 10 | B23: Rider - Advanced Metering Recovery | D23: ='[10]I-A'!$D$23+'[9]I-A'!$D$23 -> 29883535 | E23: =-D23 -> -29883535 | F23: =SUM(D23:E23) -> 0
A24: =A23+1 -> 11 | B24: Rider - Energy Efficiency | D24: ='[10]I-A'!$D$24+'[9]I-A'!$D$24 -> 11349957 | E24: ='[10]I-A'!$E$24+'[9]I-A'!$E$24 -> 8900401.8 | F24: =SUM(D24:E24) -> 20250359
A25: =A24+1 -> 12 | B25: Rider - Merger Savings | D25: ='[10]I-A'!$D$25+'[9]I-A'!$D$25 -> -989896.26 | E25: =-D25 -> 989896.26 | F25: =SUM(D25:E25) -> 0
A26: =A25+1 -> 13 | B26: Rider - Tax Refund | E26: ='[10]I-A'!$E$26+'[9]I-A'!$E$26 -> -20741598 | F26: =SUM(D26:E26) -> -20741598
A27: =A26+1 -> 14 | F27: =SUM(D27:E27) -> 0
A28: =A27+1 -> 15 | F28: =SUM(D28:E28) -> 0
A29: =A28+1 -> 16
A30: =A29+1 -> 17 | B30: TOTAL NON-BYPASSABLE DELIVERY CHARGE | D30: =SUM(D19:D29) -> 9.0771845e+08 | E30: =SUM(E19:E29) -> 38334482 | F30: =SUM(F19:F29) -> 9.4605293e+08
A31: =A30+1 -> 18
A32: =A31+1 -> 19 | B32: Transition Charge Allowance | D32: -3169202.7 | F32: =D32 -> -3169202.7
A33: =A32+1 -> 20 | B33: Transition Charge 2 | D33: 2.0167863e+08 | F33: =D33 -> 2.0167863e+08
A34: =A33+1 -> 21 | B34: Transition Charge 3 | D34: 75526075 | F34: =D34 -> 75526075
A35: =A34+1 -> 22
A36: =A35+1 -> 23 | B36: Nuclear Decommissioning | D36: -387868.4 | F36: =D36 -> -387868.4
A37: =A36+1 -> 24 | B37: Rider - Competitive Metering | D37: ='[9]I-A'!$D$37+'[10]I-A'!$D$33 -> 2774.48 | F37: =D37 -> 2774.48
A38: =A37+1 -> 25 | B38: Rider - State Colleges and Universities Discount Rider | D38: ='[9]I-A'!$D$38+'[10]I-A'!$D$34 -> -564139.09 | E38: =-D38 -> 564139.09 | F38: =SUM(D38:E38) -> 0
A39: =A38+1 -> 26
A40: =A39+1 -> 27 | B40: TOTAL | D40: =SUM(D30:D38) -> 1.1808047e+09 | E40: =SUM(E30:E38) -> 38898621 | F40: =SUM(F30:F38) -> 1.2197033e+09
B43: TRANSMISSION
B44: TCOS revenues per Docket 49192 | D44: =280015560.83116+143357310 -> 4.2337287e+08
B45: Transmission revenue requirement | D45: ='I-A-1'!G36 -> 4.2021337e+08
B47: Net change | D47: =D45-D44+D46 -> -3159501.9

Sheet I-A-1
K1: Schedule I-A-1
B2: PUBLIC UTILITY COMMISSION OF TEXAS
B3: AEP TEXAS INC
B4: I-A-1 TOTAL COST OF SERVICE BY FUNCTION
B5: TEST YEAR ENDING 12/31/2018
B6: ='I-A'!B6
D8: 1 | E8: 2 | F8: 3 | G8: 4 | H8: 5 | I8: 6 | J8: 7 | K8: 8
D9: Test Year | F9: Company | G9: Transmission | H9: Distribution | I9: Metering | J9: T&D Customer | L9: Check
C10: Reference | D10: Total | E10: Company | F10: Total | G10: Function | H10: Function | I10: Function | J10: Service | K10: Total
A11: Line | B11: Description | C11: Schedule | D11: Electric | E11: Adjustments | F11: Request | G11: (TRAN) | H11: (DIST) | I11: (MET) | J11: (TDCS) | K11: TX-Retail
A12: No.
A14: 1 | B14: Operating and Maintenance, and A&G Expenses | C14: II-D-2 | D14: ='II-D-2 A&G'!E29-'II-D-2 A&G'!F31 -> 5.7351097e+08 | E14: =+F14-D14 -> -3.3130573e+08 | F14: ='II-D-2 A&G'!J29 -> 2.4220524e+08 | G14: ='II-D-2 A&G'!M29 -> 67024337 | H14: ='II-D-2 A&G'!N29 -> 1.31959e+08 | I14: ='II-D-2 A&G'!O29 -> 25903002 | J14: ='II-D-2 A&G'!P29 -> 17318896 | K14: =+SUM(H14:J14) -> 1.751809e+08 | L14: =K14+G14-F14 -> -0.020000041
A15: =+A14+1 -> 2 | B15: Depreciation & Amortization Expenses | C15: II-E-1 | D15: ='II-E-1 Dep. Exp.'!E68-'II-E-1 Dep. Exp.'!F68 -> 2.4188912e+08 | E15: =+F15-D15 -> 23130483 | F15: ='II-E-1 Dep. Exp.'!J68 -> 2.650196e+08 | G15: ='II-E-1 Dep. Exp.'!M68 -> 93376396 | H15: ='II-E-1 Dep. Exp.'!N68 -> 1.4027223e+08 | I15: ='II-E-1 Dep. Exp.'!O68 -> 31187220 | J15: ='II-E-1 Dep. Exp.'!P68 -> 183756.44 | K15: =+SUM(H15:J15) -> 1.7164321e+08 | L15: =K15+G15-F15 -> 0
A16: =+A15+1 -> 3 | B16: Taxes Other Than Federal Income Tax | C16: II-E-2 | D16: ='II-E-2 Taxes Other'!E41+'II-E-2 Taxes Other'!F41 -> 1.3034397e+08 | E16: =+F16-D16 -> 22441203 | F16: ='II-E-2 Taxes Other'!K41 -> 1.5278517e+08 | G16: ='II-E-2 Taxes Other'!N41 -> 47195345 | H16: ='II-E-2 Taxes Other'!O41 -> 1.0184134e+08 | I16: ='II-E-2 Taxes Other'!P41 -> 2894842 | J16: ='II-E-2 Taxes Other'!Q41 -> 853638.85 | K16: =+SUM(H16:J16) -> 1.0558982e+08 | L16: =K16+G16-F16 -> 0
A17: =+A16+1 -> 4 | B17: Federal Income Tax | C17: II-E-3 | D17: ='II-E-3 FIT'!E51 -> 56176858 | E17: =+F17-D17 -> -4681468 | F17: ='II-E-3 FIT'!J51 -> 51495390 | G17: ='II-E-3 FIT'!M51 -> 31504840 | H17: ='II-E-3 FIT'!N51 -> 18624105 | I17: ='II-E-3 FIT'!O51 -> 1211467 | J17: ='II-E-3 FIT'!P51 -> 154978 | K17: =+SUM(H17:J17) -> 19990550 | L17: =K17+G17-F17 -> 0
A18: =+A17+1 -> 5 | L18: =K18+G18-F18 -> 0
A19: =+A18+1 -> 6 | B19: Return on Rate Base | C19: II-B | D19: ='II-B'!D39 -> 4.2011268e+08 | E19: =+F19-D19 -> -61389678 | F19: ='II-B'!F39 -> 3.58723e+08 | G19: ='II-B'!G39 -> 1.8647719e+08 | H19: ='II-B'!H39 -> 1.6264276e+08 | I19: ='II-B'!I39 -> 8832868 | J19: ='II-B'!J39 -> 770176.56 | K19: =+SUM(H19:J19) -> 1.722458e+08 | L19: =K19+G19-F19 -> 0
A20: =+A19+1 -> 7 | L20: =K20+G20-F20 -> 0
A21: =+A20+1 -> 8 | B21: TOTAL COST OF SERVICE | D21: =SUM(D14:D20) -> 1.4220336e+09 | E21: =SUM(E14:E20) -> -3.5180519e+08 | F21: =SUM(F14:F20) -> 1.0702284e+09 | G21: =SUM(G14:G20) -> 4.2557811e+08 | H21: =SUM(H14:H20) -> 5.5533944e+08 | I21: =SUM(I14:I20) -> 70029399 | J21: =SUM(J14:J20) -> 19281446 | K21: =+SUM(H21:J21) -> 6.4465029e+08 | L21: =K21+G21-F21 -> -0.0200001
A22: =+A21+1 -> 9
A23: =+A22+1 -> 10 | B23: Decommissioning Expense | C23: II-E-4 | D23: 0 | E23: 0 | F23: 0 | G23: 0 | H23: 0 | K23: =+SUM(H23:J23) -> 0
A24: =+A23+1 -> 11 | K24: =+SUM(H24:J24) -> 0
A25: =+A24+1 -> 12 | K25: =+SUM(H25:J25) -> 0
A26: =+A25+1 -> 13 | K26: =+SUM(H26:J26) -> 0
A27: =+A26+1 -> 14 | B27: Minus: Other Revenues | C27: II-E-5 | D27: ='[10]I-A-1'!D27+'[9]I-A-1'!D27 -> -1.2831254e+09 | E27: ='[10]I-A-1'!E27+'[9]I-A-1'!E27 -> 1.2522659e+09 | F27: ='[10]I-A-1'!F27+'[9]I-A-1'!F27 -> -30859584 | G27: ='[10]I-A-1'!G27+'[9]I-A-1'!G27 -> -5364743.9 | H27: ='[10]I-A-1'!H27+'[9]I-A-1'!H27 -> -25302644 | I27: ='[10]I-A-1'!I27+'[9]I-A-1'!I27 -> -192196.48 | J27: ='[10]I-A-1'!J27+'[9]I-A-1'!J27 -> 0 | K27: =+SUM(H27:J27) -> -25494840 | L27: =K27+G27-F27 -> 0
A28: =+A27+1 -> 15
A29: =+A28+1 -> 16 | B29: TOTAL ADJUSTED REVENUE REQUIREMENT | D29: =SUM(D21:D27) -> 1.3890815e+08 | E29: =SUM(E21:E27) -> 9.0046067e+08 | F29: =SUM(F21:F27) -> 1.0393688e+09 | G29: =SUM(G21:G27) -> 4.2021337e+08 | H29: =SUM(H21:H27) -> 5.300368e+08 | I29: =SUM(I21:I27) -> 69837202 | J29: =SUM(J21:J27) -> 19281446 | K29: =SUM(K21:K27) -> 6.1915544e+08
A30: =+A29+1 -> 17
A31: =+A30+1 -> 18
A32: =+A31+1 -> 19
A33: =+A32+1 -> 20 | B33: TOTAL REVENUE REQUIREMENT FOR DISTRIBUTION ASSETS ONLY | H33: =SUM(H29:H32) -> 5.300368e+08 | I33: =SUM(I29:I32) -> 69837202 | J33: =SUM(J29:J32) -> 19281446 | K33: =+SUM(H33:J33) -> 6.1915544e+08
A34: =+A33+1 -> 21
A35: =+A34+1 -> 22 | K35: =+H35 -> 0
A36: =+A35+1 -> 23 | B36: TOTAL ADJUSTED REVENUE REQUIREMENT | D36: =SUM(D29:D35) -> 1.3890815e+08 | E36: =SUM(E29:E35) -> 9.0046067e+08 | F36: =SUM(F29:F35) -> 1.0393688e+09 | G36: =SUM(G29:G35) -> 4.2021337e+08 | H36: =SUM(H33:H35) -> 5.300368e+08 | I36: =SUM(I33:I35) -> 69837202 | J36: =SUM(J33:J35) -> 19281446 | K36: =SUM(H36:J36) -> 6.1915544e+08
F37: ='[10]I-A-1'!F37+'[9]I-A-1'!F36 -> 1.0393688e+09 | G37: ='[10]I-A-1'!G37+'[9]I-A-1'!G36 -> 4.2021337e+08 | H37: ='[10]I-A-1'!H37+'[9]I-A-1'!H36 -> 5.300368e+08 | I37: ='[10]I-A-1'!I37+'[9]I-A-1'!I36 -> 69837203 | J37: ='[10]I-A-1'!J37+'[9]I-A-1'!J36 -> 19281446 | K37: ='[10]I-A-1'!K37+'[9]I-A-1'!K36 -> 6.1915545e+08

Sheet I-A-2
B2: PUBLIC UTILITY COMMISSION OF TEXAS
B3: AEP TEXAS INC
B4: I-A-2 ADJUSTMENTS TO TEST YEAR
B5: TEST YEAR ENDING 12/31/2018
B10: Description | C10: Sched | D10: Workpaper
A11: Line | C11: I-A-1 | D11: Schedule | E11: Amount | F11: Witness
A12: No. | C12: Ref
A14: 1 | B14: O&M Expense
A15: =A14+1 -> 2
A16: =A15+1 -> 3 | B16: Expense amount, as adjusted by FERC Account:
A17: =A16+1 -> 4 | B17: 556 | C17: Line 1 | D17: WP II-D-1 | E17: -1.47 | F17: Please See Exhibit RWH-2 for the list of sponsoring witnesses
A18: =A17+1 -> 5 | B18: 560 | C18: Line 1 | D18: WP II-D-1 | E18: 16405039 | F18: Please See Exhibit RWH-2 for the list of sponsoring witnesses
A19: =A18+1 -> 6 | B19: 561 | C19: Line 1 | D19: WP II-D-1 | E19: 2855275.5 | F19: Please See Exhibit RWH-2 for the list of sponsoring witnesses
A20: =A19+1 -> 7 | B20: 562 | C20: Line 1 | D20: WP II-D-1 | E20: 838863.31 | F20: Please See Exhibit RWH-2 for the list of sponsoring witnesses
A21: =A20+1 -> 8 | B21: 563 | C21: Line 1 | D21: WP II-D-1 | E21: 607135.54 | F21: Please See Exhibit RWH-2 for the list of sponsoring witnesses
A22: =A21+1 -> 9 | B22: 565 | C22: Line 1 | D22: WP II-D-1 | E22: 0 | F22: Please See Exhibit RWH-2 for the list of sponsoring witnesses
A23: =A22+1 -> 10 | B23: 565 | C23: Line 1 | D23: WP II-D-1 | E23: 560180.51 | F23: Please See Exhibit RWH-2 for the list of sponsoring witnesses
A24: =A23+1 -> 11 | B24: 566 | C24: Line 1 | D24: WP II-D-1 | E24: 6405455.1 | F24: Please See Exhibit RWH-2 for the list of sponsoring witnesses
A25: =A24+1 -> 12 | B25: 567 | C25: Line 1 | D25: WP II-D-1 | E25: 2260064.6 | F25: Please See Exhibit RWH-2 for the list of sponsoring witnesses
A26: =A25+1 -> 13 | B26: 557 | C26: Line 1 | D26: WP II-D-1 | E26: -7191.61 | F26: Please See Exhibit RWH-2 for the list of sponsoring witnesses
A27: =A26+1 -> 14 | B27: 568 | C27: Line 1 | D27: WP II-D-1 | E27: 85370.202 | F27: Please See Exhibit RWH-2 for the list of sponsoring witnesses
A28: =A27+1 -> 15 | B28: 569 | C28: Line 1 | D28: WP II-D-1 | E28: 1518853 | F28: Please See Exhibit RWH-2 for the list of sponsoring witnesses
A29: =A28+1 -> 16 | B29: 570 | C29: Line 1 | D29: WP II-D-1 | E29: 6632854.4 | F29: Please See Exhibit RWH-2 for the list of sponsoring witnesses
A30: =A29+1 -> 17 | B30: 571 | C30: Line 1 | D30: WP II-D-1 | E30: 11547130 | F30: Please See Exhibit RWH-2 for the list of sponsoring witnesses
A31: =A30+1 -> 18 | B31: 572 | C31: Line 1 | D31: WP II-D-1 | E31: 1584.63 | F31: Please See Exhibit RWH-2 for the list of sponsoring witnesses
A32: =A31+1 -> 19 | B32: 573 | C32: Line 1 | D32: WP II-D-1 | E32: -19558.549 | F32: Please See Exhibit RWH-2 for the list of sponsoring witnesses
A33: =A32+1 -> 20 | B33: 580 | C33: Line 1 | D33: WP II-D-1 | E33: 7795705.8 | F33: Please See Exhibit RWH-2 for the list of sponsoring witnesses
A34: =A33+1 -> 21 | B34: 581 | C34: Line 1 | D34: WP II-D-1 | E34: 3556648.7 | F34: Please See Exhibit RWH-2 for the list of sponsoring witnesses
A35: =A34+1 -> 22 | B35: 582 | C35: Line 1 | D35: WP II-D-1 | E35: 1548391.2 | F35: Please See Exhibit RWH-2 for the list of sponsoring witnesses
A36: =A35+1 -> 23 | B36: 583 | C36: Line 1 | D36: WP II-D-1 | E36: 5876627.4 | F36: Please See Exhibit RWH-2 for the list of sponsoring witnesses
A37: =A36+1 -> 24 | B37: 584 | C37: Line 1 | D37: WP II-D-1 | E37: 1268562.8 | F37: Please See Exhibit RWH-2 for the list of sponsoring witnesses
A38: =A37+1 -> 25 | B38: 585 | C38: Line 1 | D38: WP II-D-1 | E38: 103205.15 | F38: Please See Exhibit RWH-2 for the list of sponsoring witnesses
A39: =A38+1 -> 26 | B39: 586 | C39: Line 1 | D39: WP II-D-1 | E39: 7427114.4 | F39: Please See Exhibit RWH-2 for the list of sponsoring witnesses
A40: =A39+1 -> 27 | B40: 587 | C40: Line 1 | D40: WP II-D-1 | E40: 1240621.7 | F40: Please See Exhibit RWH-2 for the list of sponsoring witnesses
A41: =A40+1 -> 28 | B41: 588 | C41: Line 1 | D41: WP II-D-1 | E41: 27904703 | F41: Please See Exhibit RWH-2 for the list of sponsoring witnesses
A42: =A41+1 -> 29 | B42: 589 | C42: Line 1 | D42: WP II-D-1 | E42: 2009215.5 | F42: Please See Exhibit RWH-2 for the list of sponsoring witnesses
A43: =A42+1 -> 30 | B43: 590 | C43: Line 1 | D43: WP II-D-1 | E43: 153114.44 | F43: Please See Exhibit RWH-2 for the list of sponsoring witnesses
A44: =A43+1 -> 31 | B44: 591 | C44: Line 1 | D44: WP II-D-1 | E44: 18936.124 | F44: Please See Exhibit RWH-2 for the list of sponsoring witnesses
A45: =A44+1 -> 32 | B45: 592 | C45: Line 1 | D45: WP II-D-1 | E45: 2625066.2 | F45: Please See Exhibit RWH-2 for the list of sponsoring witnesses
A46: =A45+1 -> 33 | B46: 593 | C46: Line 1 | D46: WP II-D-1 | E46: 46799475 | F46: Please See Exhibit RWH-2 for the list of sponsoring witnesses
A47: =A46+1 -> 34 | B47: 594 | C47: Line 1 | D47: WP II-D-1 | E47: 1989939.1 | F47: Please See Exhibit RWH-2 for the list of sponsoring witnesses
A48: =A47+1 -> 35 | B48: 595 | C48: Line 1 | D48: WP II-D-1 | E48: 1162583.1 | F48: Please See Exhibit RWH-2 for the list of sponsoring witnesses
... A56: =A55+1 -> 43 | B56: 905 | C56: Line 1 | D56: WP II-D-1 | E56: 121942.5 | F56: Please See Exhibit RWH-2 for the list of sponsoring witnesses
A57: =A56+1 -> 44 | B57: 907 | C57: Line 1 | D57: WP II-D-1 | E57: 0 | F57: Please See Exhibit RWH-2 for the list of sponsoring witnesses
A58: =A57+1 -> 45 | B58: 907 | C58: Line 1 | D58: WP II-D-1 | E58: 611082.71 | F58: Please See Exhibit RWH-2 for the list of sponsoring witnesses
A59: =A58+1 -> 46 | B59: 908 | C59: Line 1 | D59: WP II-D-1 | E59: 1591051 | F59: Please See Exhibit RWH-2 for the list of sponsoring witnesses
A60: =A59+1 -> 47 | B60: 909 | C60: Line 1 | D60: WP II-D-1 | E60: 286.31 | F60: Please See Exhibit RWH-2 for the list of sponsoring witnesses
A61: =A60+1 -> 48 | B61: 910 | C61: Line 1 | D61: WP II-D-1 | E61: 9803.25 | F61: Please See Exhibit RWH-2 for the list of sponsoring witnesses
A62: =A61+1 -> 49 | B62: 911 | C62: Line 1 | D62: WP II-D-1 | E62: 1.2789769e-13 | F62: Please See Exhibit RWH-2 for the list of sponsoring witnesses
A63: =A62+1 -> 50 | B63: 912 | C63: Line 1 | D63: WP II-D-1 | E63: 0 | F63: Please See Exhibit RWH-2 for the list of sponsoring witnesses
A64: =A63+1 -> 51 | B64: 920 | C64: Line 1 | D64: WP II-D-2 | E64: 30692127 | F64: Please See Exhibit RWH-2 for the list of sponsoring witnesses
A65: =A64+1 -> 52 | B65: 921 | C65: Line 1 | D65: WP II-D-2 | E65: 2193265.5 | F65: Please See Exhibit RWH-2 for the list of sponsoring witnesses
A66: =A65+1 -> 53 | B66: 922 | C66: Line 1 | D66: WP II-D-2 | E66: -9735616.1 | F66: Please See Exhibit RWH-2 for the list of sponsoring witnesses
A67: =A66+1 -> 54 | B67: 923 | C67: Line 1 | D67: WP II-D-2 | E67: 4900305.4 | F67: Please See Exhibit RWH-2 for the list of sponsoring witnesses
A68: =A67+1 -> 55 | B68: 924 | C68: Line 1 | D68: WP II-D-2 | E68: 5490052.1 | F68: Please See Exhibit RWH-2 for the list of sponsoring witnesses
A69: =A68+1 -> 56 | B69: 925 | C69: Line 1 | D69: WP II-D-2 | E69: 4593337.5 | F69: Please See Exhibit RWH-2 for the list of sponsoring witnesses
... A73: =A72+1 -> 60 | B73: 931 | C73: Line 1 | D73: WP II-D-2 | E73: 925662.61 | F73: Please See Exhibit RWH-2 for the list of sponsoring witnesses
A74: =A73+1 -> 61 | B74: 935 | C74: Line 1 | D74: WP II-D-2 | E74: 17538318 | F74: Please See Exhibit RWH-2 for the list of sponsoring witnesses
A75: =A74+1 -> 62
A76: =A75+1 -> 63 | B76: Less: Amount per books (test year) by FERC Account:
A77: =A76+1 -> 64
A78: =A77+1 -> 65 | B78: 556 | C78: Line 1 | D78: WP II-D-1 | E78: 0.02 | F78: Please See Exhibit RWH-2 for the list of sponsoring witnesses
A79: =A78+1 -> 66 | B79: 560 | C79: Line 1 | D79: WP II-D-1 | E79: 16503788 | F79: Please See Exhibit RWH-2 for the list of sponsoring witnesses
A80: =A79+1 -> 67 | B80: 561 | C80: Line 1 | D80: WP II-D-1 | E80: 2827017.9 | F80: Please See Exhibit RWH-2 for the list of sponsoring witnesses
A81: =A80+1 -> 68 | B81: 562 | C81: Line 1 | D81: WP II-D-1 | E81: 818963.38 | F81: Please See Exhibit RWH-2 for the list of sponsoring witnesses
A82: =A81+1 -> 69 | B82: 563 | C82: Line 1 | D82: WP II-D-1 | E82: 339704.88 | F82: Please See Exhibit RWH-2 for the list of sponsoring witnesses
A83: =A82+1 -> 70 | B83: 565 | C83: Line 1 | D83: WP II-D-1 | E83: 3.2739421e+08 | F83: Please See Exhibit RWH-2 for the list of sponsoring witnesses
A84: =A83+1 -> 71 | B84: 565 | C84: Line 1 | D84: WP II-D-1 | E84: 560180.51 | F84: Please See Exhibit RWH-2 for the list of sponsoring witnesses
A85: =A84+1 -> 72 | B85: 566 | C85: Line 1 | D85: WP II-D-1 | E85: 6618645.2 | F85: Please See Exhibit RWH-2 for the list of sponsoring witnesses
A86: =A85+1 -> 73 | B86: 567 | C86: Line 1 | D86: WP II-D-1 | E86: 2260064.6 | F86: Please See Exhibit RWH-2 for the list of sponsoring witnesses
A87: =A86+1 -> 74 | B87: 557 | C87: Line 1 | D87: WP II-D-1 | E87: 0 | F87: Please See Exhibit RWH-2 for the list of sponsoring witnesses
A88: =A87+1 -> 75 | B88: 568 | C88: Line 1 | D88: WP II-D-1 | E88: 77816.38 | F88: Please See Exhibit RWH-2 for the list of sponsoring witnesses
A89: =A88+1 -> 76 | B89: 569 | C89: Line 1 | D89: WP II-D-1 | E89: 1507894.4 | F89: Please See Exhibit RWH-2 for the list of sponsoring witnesses
A90: =A89+1 -> 77 | B90: 570 | C90: Line 1 | D90: WP II-D-1 | E90: 6596559.4 | F90: Please See Exhibit RWH-2 for the list of sponsoring witnesses
A91: =A90+1 -> 78 | B91: 571 | C91: Line 1 | D91: WP II-D-1 | E91: 11547919 | F91: Please See Exhibit RWH-2 for the list of sponsoring witnesses
A92: =A91+1 -> 79 | B92: 572 | C92: Line 1 | D92: WP II-D-1 | E92: 2101.8 | F92: Please See Exhibit RWH-2 for the list of sponsoring witnesses
A93: =A92+1 -> 80 | B93: 573 | C93: Line 1 | D93: WP II-D-1 | E93: -24487.91 | F93: Please See Exhibit RWH-2 for the list of sponsoring witnesses
A94: =A93+1 -> 81 | B94: 580 | C94: Line 1 | D94: WP II-D-1 | E94: 7732451.9 | F94: Please See Exhibit RWH-2 for the list of sponsoring witnesses
A95: =A94+1 -> 82 | B95: 581 | C95: Line 1 | D95: WP II-D-1 | E95: 3452162.8 | F95: Please See Exhibit RWH-2 for the list of sponsoring witnesses
A96: =A95+1 -> 83 | B96: 582 | C96: Line 1 | D96: WP II-D-1 | E96: 1572942.1 | F96: Please See Exhibit RWH-2 for the list of sponsoring witnesses
A97: =A96+1 -> 84 | B97: 583 | C97: Line 1 | D97: WP II-D-1 | E97: 6065648.3 | F97: Please See Exhibit RWH-2 for the list of sponsoring witnesses
A98: =A97+1 -> 85 | B98: 584 | C98: Line 1 | D98: WP II-D-1 | E98: 1264210.9 | F98: Please See Exhibit RWH-2 for the list of sponsoring witnesses
A99: =A98+1 -> 86 | B99: 585 | C99: Line 1 | D99: WP II-D-1 | E99: 102722.04 | F99: Please See Exhibit RWH-2 for the list of sponsoring witnesses
A100: =A99+1 -> 87 | B100: 586 | C100: Line 1 | D100: WP II-D-1 | E100: 7384635.6 | F100: Please See Exhibit RWH-2 for the list of sponsoring witnesses
A101: =A100+1 -> 88 | B101: 587 | C101: Line 1 | D101: WP II-D-1 | E101: 1216737 | F101: Please See Exhibit RWH-2 for the list of sponsoring witnesses
A102: =A101+1 -> 89 | B102: 588 | C102: Line 1 | D102: WP II-D-1 | E102: 27940375 | F102: Please See Exhibit RWH-2 for the list of sponsoring witnesses
A103: =A102+1 -> 90 | B103: 589 | C103: Line 1 | D103: WP II-D-1 | E103: 2009215.5 | F103: Please See Exhibit RWH-2 for the list of sponsoring witnesses
A104: =A103+1 -> 91 | B104: 590 | C104: Line 1 | D104: WP II-D-1 | E104: 155019.66 | F104: Please See Exhibit RWH-2 for the list of sponsoring witnesses
A105: =A104+1 -> 92 | B105: 591 | C105: Line 1 | D105: WP II-D-1 | E105: 23146.9 | F105: Please See Exhibit RWH-2 for the list of sponsoring witnesses
A106: =A105+1 -> 93 | B106: 592 | C106: Line 1 | D106: WP II-D-1 | E106: 2665397.5 | F106: Please See Exhibit RWH-2 for the list of sponsoring witnesses
A107: =A106+1 -> 94 | B107: 593 | C107: Line 1 | D107: WP II-D-1 | E107: 37955120 | F107: Please See Exhibit RWH-2 for the list of sponsoring witnesses
A108: =A107+1 -> 95 | B108: 594 | C108: Line 1 | D108: WP II-D-1 | E108: 1987925.4 | F108: Please See Exhibit RWH-2 for the list of sponsoring witnesses
A109: =A108+1 -> 96 | B109: 595 | C109: Line 1 | D109: WP II-D-1 | E109: 1152139.8 | F109: Please See Exhibit RWH-2 for the list of sponsoring witnesses
... A117: =A116+1 -> 104 | B117: 905 | C117: Line 1 | D117: WP II-D-1 | E117: 120030.72 | F117: Please See Exhibit RWH-2 for the list of sponsoring witnesses
A118: =A117+1 -> 105 | B118: 907 | C118: Line 1 | D118: WP II-D-1 | E118: 16882931 | F118: Please See Exhibit RWH-2 for the list of sponsoring witnesses
A119: =A118+1 -> 106 | B119: 907 | C119: Line 1 | D119: WP II-D-1 | E119: 590633.72 | F119: Please See Exhibit RWH-2 for the list of sponsoring witnesses
A120: =A119+1 -> 107 | B120: 908 | C120: Line 1 | D120: WP II-D-1 | E120: 1559076.5 | F120: Please See Exhibit RWH-2 for the list of sponsoring witnesses
A121: =A120+1 -> 108 | B121: 909 | C121: Line 1 | D121: WP II-D-1 | E121: 286.31 | F121: Please See Exhibit RWH-2 for the list of sponsoring witnesses
A122: =A121+1 -> 109 | B122: 910 | C122: Line 1 | D122: WP II-D-1 | E122: 9638.29 | F122: Please See Exhibit RWH-2 for the list of sponsoring witnesses
A123: =A122+1 -> 110 | B123: 911 | C123: Line 1 | D123: WP II-D-1 | E123: 13.47 | F123: Please See Exhibit RWH-2 for the list of sponsoring witnesses
...

Sheet II-B
K1: Schedule II-B
B2: PUBLIC UTILITY COMMISSION OF TEXAS
B3: AEP TEXAS INC
B4: II-B RATE BASE BY FUNCTION
B5: TEST YEAR ENDING 12/31/2018
B6: ='I-A'!B6
D8: 1 | E8: 2 | F8: 3 | G8: 4 | H8: 5 | I8: 6 | J8: 7 | K8: 8
D9: Test Year | F9: Company
C10: Reference | D10: Total | E10: Company | F10: Total | G10: TRAN | H10: DIST | I10: MET | J10: TDCS | K10: Total | L10: Check
A11: Line | B11: Description | C11: Schedule | D11: Electric | E11: Adjustments | F11: Request | K11: TX-Retail
A12: No.
A14: 1 | B14: Original Cost of Plant | C14: II-B-1 | D14: ='II-B-1 Plant'!E51-'II-B-1 Plant'!F51 -> 7.8651045e+09 | E14: =+F14-D14 -> -91588360 | F14: ='II-B-1 Plant'!J51 -> 7.7735162e+09 | G14: ='II-B-1 Plant'!M51 -> 3.7156586e+09 | H14: =+F14-G14-I14-J14 -> 3.8243995e+09 | I14: ='II-B-1 Plant'!O51 -> 2.3345323e+08 | J14: ='II-B-1 Plant'!P51 -> 4800.4855 | K14: =+SUM(H14:J14) -> 4.0578575e+09
A15: =+A14+1 -> 2 | B15: General Plant | C15: II-B-2 | D15: ='II-B-2 General Plant'!E31-'II-B-2 General Plant'!F31 -> 4.1291424e+08 | E15: =+F15-D15 -> 1258230.7 | F15: ='II-B-2 General Plant'!J31 -> 4.1417247e+08 | G15: ='II-B-2 General Plant'!M31 -> 1.4358583e+08 | H15: =+F15-G15-I15-J15 -> 2.5813457e+08 | I15: ='II-B-2 General Plant'!O31 -> 9638071.8 | J15: ='II-B-2 General Plant'!P31 -> 2813996.7 | K15: =+SUM(H15:J15) -> 2.7058664e+08
A16: =+A15+1 -> 3 | B16: Comm. Equipment | C16: II-B-3 | D16: ='II-B-3 Comm. Equip.'!E17-'II-B-3 Comm. Equip.'!F17 -> 1.2471037e+08 | E16: =+F16-D16 -> -1925527.1 | F16: ='II-B-3 Comm. Equip.'!J17 -> 1.2278485e+08 | G16: ='II-B-3 Comm. Equip.'!M17 -> 11247748 | H16: =+F16-G16-I16-J16 -> 95208035 | I16: ='II-B-3 Comm. Equip.'!O17 -> 16328967 | J16: ='II-B-3 Comm. Equip.'!P17 -> 97.082531 | K16: =+SUM(H16:J16) -> 1.115371e+08
A17: =+A16+1 -> 4 | B17: Total Plant | D17: =SUM(D14:D16) -> 8.4027291e+09 | E17: =SUM(E14:E16) -> -92255657 | F17: =SUM(F14:F16) -> 8.3104735e+09 | G17: =SUM(G14:G16) -> 3.8704922e+09 | H17: =SUM(H14:H16) -> 4.1777421e+09 | I17: =SUM(I14:I16) -> 2.5942027e+08 | J17: =SUM(J14:J16) -> 2818894.3 | K17: =SUM(K14:K16) -> 4.4399813e+09
A18: =+A17+1 -> 5
A19: =+A18+1 -> 6 | B19: Minus: Accumulated Depreciation | C19: II-B-5 | D19: =-'II-B-5 Depreciation'!E53-'II-B-5 Depreciation'!E80+'II-B-5 Depreciation'!F53+'II-B-5 Depreciation'!F80 -> -2.0915659e+09 | E19: =+F19-D19 -> 21158740 | F19: =-'II-B-5 Depreciation'!J53-'II-B-5 Depreciation'!J80 -> -2.0704071e+09 | G19: =-'II-B-5 Depreciation'!M53-'II-B-5 Depreciation'!M80 -> -5.9276057e+08 | H19: =+F19-G19-I19-J19 -> -1.3212813e+09 | I19: =-'II-B-5 Depreciation'!O53-'II-B-5 Depreciation'!O80 -> -1.557741e+08 | J19: =-'II-B-5 Depreciation'!P53-'II-B-5 Depreciation'!P80 -> -591110.36 | K19: =+SUM(H19:J19) -> -1.4776466e+09
A20: =+A19+1 -> 7 | B20: Net Plant In Service | D20: =SUM(D17:D19) -> 6.3111633e+09 | E20: =SUM(E17:E19) -> -71096917 | F20: =SUM(F17:F19) -> 6.2400664e+09 | G20: =SUM(G17:G19) -> 3.2777317e+09 | H20: =SUM(H17:H19) -> 2.8564608e+09 | I20: =SUM(I17:I19) -> 1.0364617e+08 | J20: =SUM(J17:J19) -> 2227784 | K20: =SUM(K17:K19) -> 2.9623347e+09
A21: =+A20+1 -> 8
A22: =+A21+1 -> 9 | B22: Other Rate Base Items:
A23: =+A22+1 -> 10 | B23: CWIP | C23: II-B-4 | D23: =+'II-B-4 CWIP'!E15-'II-B-4 CWIP'!F18 -> 8.3600397e+08 | E23: =+F23-D23 -> -8.3600397e+08 | F23: =+'II-B-4 CWIP'!H15 -> 0 | K23: =+SUM(H23:J23) -> 0
A24: =+A23+1 -> 11 | B24: Cash Working Capital | C24: II-B-9 | D24: ='II-B-9 CWCapital'!E21 -> 0 | E24: =+F24-D24 -> -22940282 | F24: =+'II-B-9 CWCapital'!J27 -> -22940282 | G24: =+'II-B-9 CWCapital'!M27 -> -16030645 | H24: =+'II-B-9 CWCapital'!N27 -> -5222388.9 | I24: =+'II-B-9 CWCapital'!O27 -> -1687248.9 | J24: =+'II-B-9 CWCapital'!P27 -> 0 | K24: =+SUM(H24:J24) -> -6909637.8
A25: =+A24+1 -> 12 | B25: Prepayments | C25: II-B-10 | D25: ='II-B-10 Prepayments'!E32-'II-B-10 Prepayments'!F32 -> 3321592.2 | E25: =+F25-D25 -> 83596897 | F25: ='II-B-10 Prepayments'!J34 -> 86918490 | G25: ='II-B-10 Prepayments'!M34 -> 7413933.4 | H25: =+F25-G25-I25-J25 -> 51592864 | I25: ='II-B-10 Prepayments'!O34 -> 15909433 | J25: ='II-B-10 Prepayments'!P34 -> 12002259 | K25: =+SUM(H25:J25) -> 79504556
A26: =+A25+1 -> 13 | B26: Materials & Supplies | C26: II-B-8 | D26: ='II-B-8 M&S'!E19-'II-B-8 M&S'!F19 -> 48920552 | E26: =+F26-D26 -> -1642649.5 | F26: ='II-B-8 M&S'!J21 -> 47277903 | G26: ='II-B-8 M&S'!M21 -> 15176994 | H26: =+F26-G26-I26-J26 -> 31038229 | I26: ='II-B-8 M&S'!O21 -> 1061695 | J26: ='II-B-8 M&S'!P21 -> 984.63864 | K26: =+SUM(H26:J26) -> 32100909
A27: =+A26+1 -> 14 | B27: Plant Held for Future Use | C27: II-B-6 | D27: ='II-B-6 Plant Future'!E19 -> 4941591.7 | E27: =+F27-D27 -> -1809575.7 | F27: ='II-B-6 Plant Future'!K16 -> 3132016 | H27: ='II-B-6 Plant Future'!M19 -> 3132016 | J27: 0 | K27: =+SUM(H27:J27) -> 3132016
A28: =+A27+1 -> 15 | B28: Accumulated Provisions and ADIT | C28: II-B-7 | D28: ='II-B-7 Accum. Provisions'!E21-'II-B-7 Accum. Provisions'!F21 -> -7.8247377e+08 | E28: =+F28-D28 -> 2718715.6 | F28: ='II-B-7 Accum. Provisions'!J23 -> -7.7975505e+08 | G28: ='II-B-7 Accum. Provisions'!M23 -> -3.5551501e+08 | H28: =+'II-B-7 Accum. Provisions'!N23 -> -3.9372002e+08 | I28: =+'II-B-7 Accum. Provisions'!O23 -> -26771625 | J28: =+'II-B-7 Accum. Provisions'!P23 -> -3748404.2 | K28: =+SUM(H28:J28) -> -4.2424004e+08
A29: =+A28+1 -> 16 | B29: Rate Base - Other | C29: II-B-11 | D29: ='II-B-11 Rate Base Other'!E26-'II-B-11 Rate Base Other'!F26 -> -7.2787606e+08 | E29: =+F29-D29 -> 1.413207e+08 | F29: ='II-B-11 Rate Base Other'!J26 -> -5.8655535e+08 | G29: ='II-B-11 Rate Base Other'!M26 -> -3.21874e+08 | H29: ='II-B-11 Rate Base Other'!N26 -> -2.5542378e+08 | I29: ='II-B-11 Rate Base Other'!O26 -> -9062766.8 | J29: ='II-B-11 Rate Base Other'!P26 -> -194805.38 | K29: =+SUM(H29:J29) -> -2.6468135e+08
A30: =+A29+1 -> 17 | B30: Regulatory Assets | C30: II-B-12 | D30: ='II-B-12 Reg. Assets'!E27 -> 2.4256073e+08 | E30: =+F30-D30 -> -1.6163311e+08 | F30: ='II-B-12 Reg. Assets'!J27 -> 80927618 | G30: ='II-B-12 Reg. Assets'!M27 -> 28183978 | H30: =+F30-G30-I30-J30 -> 10427639 | I30: ='II-B-12 Reg. Assets'!O27 -> 41720546 | J30: ='II-B-12 Reg. Assets'!P27 -> 595454.45 | K30: =+SUM(H30:J30) -> 52743639
A31: =+A30+1 -> 18
A32: =+A31+1 -> 19
A33: =+A32+1 -> 20 | B33: Subtotal | D33: =SUM(D23:D32) -> -3.7460139e+08 | E33: =SUM(E23:E32) -> -7.9639327e+08 | F33: =SUM(F23:F32) -> -1.1709947e+09 | G33: =SUM(G23:G32) -> -6.4264475e+08 | H33: =SUM(H23:H32) -> -5.5817543e+08 | I33: =SUM(I23:I32) -> 21170033 | J33: =SUM(J23:J32) -> 8655488.8 | K33: =SUM(K23:K32) -> -5.2834991e+08
A34: =+A33+1 -> 21
A35: =+A34+1 -> 22 | B35: TOTAL RATE BASE | D35: =D33+D20 -> 5.9365619e+09 | E35: =E33+E20 -> -8.6749019e+08 | F35: =F33+F20 -> 5.0690717e+09 | G35: =G33+G20 -> 2.6350869e+09 | H35: =H33+H20 -> 2.2982853e+09 | I35: =I33+I20 -> 1.248162e+08 | J35: =J33+J20 -> 10883273 | K35: =K33+K20 -> 2.4339848e+09
A36: =+A35+1 -> 23
A37: =+A36+1 -> 24 | B37: Rate of Return | D37: ='II-C-2.1'!$G$25 -> 0.070767 | F37: ='II-C-2.1'!$G$25 -> 0.070767 | G37: ='II-C-2.1'!$G$25 -> 0.070767 | H37: ='II-C-2.1'!$G$25 -> 0.070767 | I37: ='II-C-2.1'!$G$25 -> 0.070767 | J37: ='II-C-2.1'!$G$25 -> 0.070767
A38: =+A37+1 -> 25
A39: =+A38+1 -> 26 | B39: RETURN ON RATE BASE | D39: =+D35*D37 -> 4.2011268e+08 | F39: =+F35*F37 -> 3.58723e+08 | G39: =+G35*G37 -> 1.8647719e+08 | H39: =+H35*H37 -> 1.6264276e+08 | I39: =+I35*I37 -> 8832868 | J39: =+J35*J37 -> 770176.56 | K39: =+SUM(H39:J39) -> 1.722458e+08

Sheet II-B-1 Plant
B2: PUBLIC UTILITY COMMISSION OF TEXAS
B3: AEP TEXAS INC
B4: II-B-1 ORIGINAL COST OF UTILITY PLANT
B5: TEST YEAR ENDING 12/31/2018
B6: ='I-A'!B6
E8: 1 | F8: 2 | G8: 3 | H8: 4 | I8: 5 | J8: 6 | K8: 7 | L8: 8 | M8: 9 | N8: 10 | O8: 11 | P8: 12 | Q8: 13
H9: Company | I9: Texas
B10: Account | C10: Description | D10: Reference | E10: Total | F10: Non-Regulated | G10: Known | H10: Total | I10: Retail | J10: Allocation to | K10: FF | L10: Functionalization | M10: TRAN | N10: DIST | O10: MET | P10: TDCS | Q10: Total
A11: Line | B11: Number | D11: Schedule | E11: Company | F11: or | G11: Change | H11: Electric | I11: Allocation | J11: Texas | K11: # | L11: Factor | R11: CHECK
A12: No. | F12: Non-Electric | I12: Factor | L12: Name
A14: 1 | B14: Intangible Plant-Gross | D14: II-B-1
A15: =+A14+1 -> 2 | B15: A301 | C15: Organization | E15: ='[10]II-B-1 Plant'!E15+'[9]II-B-1 Plant'!E15 -> 21967.68 | F15: ='[10]II-B-1 Plant'!F15+'[9]II-B-1 Plant'!F15 -> 1731.05 | G15: ='[10]II-B-1 Plant'!G15+'[9]II-B-1 Plant'!G15 -> 0 | H15: =+E15-F15+G15 -> 20236.63 | I15: 1 | J15: =+I15*H15 -> 20236.63 | K15: 25 | L15: TOTREV | M15: ='[10]II-B-1 Plant'!M15+'[9]II-B-1 Plant'!M15 -> 2113.29 | N15: ='[10]II-B-1 Plant'!N15+'[9]II-B-1 Plant'!N15 -> 15244.304 | O15: ='[10]II-B-1 Plant'!O15+'[9]II-B-1 Plant'!O15 -> 2457.0266 | P15: ='[10]II-B-1 Plant'!P15+'[9]II-B-1 Plant'!P15 -> 422.00911 | Q15: =+SUM(M15:P15) -> 20236.63
A16: =+A15+1 -> 3 | B16: A302 | C16: Franchise & Consents | E16: ='[10]II-B-1 Plant'!E16+'[9]II-B-1 Plant'!E16 -> 0 | F16: ='[10]II-B-1 Plant'!F16+'[9]II-B-1 Plant'!F16 -> 0 | G16: ='[10]II-B-1 Plant'!G16+'[9]II-B-1 Plant'!G16 -> 0 | H16: =+E16-F16+G16 -> 0 | I16: 1 | J16: =+I16*H16 -> 0 | K16: 25 | L16: TOTREV | M16: ='[10]II-B-1 Plant'!M16+'[9]II-B-1 Plant'!M16 -> 0 | N16: ='[10]II-B-1 Plant'!N16+'[9]II-B-1 Plant'!N16 -> 0 | O16: ='[10]II-B-1 Plant'!O16+'[9]II-B-1 Plant'!O16 -> 0 | P16: ='[10]II-B-1 Plant'!P16+'[9]II-B-1 Plant'!P16 -> 0 | Q16: =+SUM(M16:P16) -> 0
A17: =+A16+1 -> 4 | B17: A303 | C17: Miscellaneous Intangible Plant | E17: ='[10]II-B-1 Plant'!E17+'[9]II-B-1 Plant'!E17 -> 1.4393051e+08 | F17: ='[10]II-B-1 Plant'!F17+'[9]II-B-1 Plant'!F17 -> 545799.06 | G17: ='[10]II-B-1 Plant'!G17+'[9]II-B-1 Plant'!G17 -> 0 | H17: =+E17-F17+G17 -> 1.4338471e+08 | I17: 1 | J17: =SUM((H17-M17)*I17)+M17 -> 1.4338471e+08 | K17: 29/20 | L17: DIRECT/DPLTSVC-NX | M17: ='[10]II-B-1 Plant'!M17+'[9]II-B-1 Plant'!M17 -> 37599009 | N17: ='[10]II-B-1 Plant'!N17+'[9]II-B-1 Plant'!N17 -> 1.0213767e+08 | O17: ='[10]II-B-1 Plant'!O17+'[9]II-B-1 Plant'!O17 -> 3643656.7 | P17: ='[10]II-B-1 Plant'!P17+'[9]II-B-1 Plant'!P17 -> 4378.4764 | Q17: =+SUM(M17:P17) -> 1.4338471e+08
A18: =+A17+1 -> 5 | C18: Subtotal | E18: =+SUM(E15:E17) -> 1.4395248e+08 | F18: =+SUM(F15:F17) -> 547530.11 | G18: =+SUM(G15:G17) -> 0 | H18: =+SUM(H15:H17) -> 1.4340495e+08 | J18: =SUM(J15:J17) -> 1.4340495e+08 | M18: =+SUM(M15:M17) -> 37601122 | N18: =+SUM(N15:N17) -> 1.0215291e+08 | O18: =+SUM(O15:O17) -> 3646113.7 | P18: =+SUM(P15:P17) -> 4800.4855 | Q18: =+SUM(Q15:Q17) -> 1.4340495e+08
A19: =+A18+1 -> 6
A20: =+A19+1 -> 7 | B20: Transmission Plant-Gross | D20: II-B-1
A21: =+A20+1 -> 8 | B21: A349 | C21: Land Owned in Fee | E21: ='[9]II-B-1 Plant'!E21 -> 0 | F21: ='[9]II-B-1 Plant'!F21 -> 0 | G21: ='[9]II-B-1 Plant'!G21 -> 0 | H21: =+E21-F21+G21 -> 0 | J21: =+I21*H21 -> 0 | K21: 29 | L21: DIRECT | M21: ='[9]II-B-1 Plant'!M21 -> 0 | N21: ='[9]II-B-1 Plant'!N21 -> 0 | O21: ='[9]II-B-1 Plant'!O21 -> 0 | P21: ='[9]II-B-1 Plant'!P21 -> 0 | Q21: =+SUM(M21:P21) -> 0
A22: =+A21+1 -> 9 | B22: A350 | C22: Land and Land Rights | E22: ='[10]II-B-1 Plant'!E21+'[10]II-B-1 Plant'!E22+'[9]II-B-1 Plant'!E22 -> 1.0721588e+08 | F22: ='[10]II-B-1 Plant'!F21+'[10]II-B-1 Plant'!F22+'[9]II-B-1 Plant'!F22 -> 0 | G22: ='[10]II-B-1 Plant'!G21+'[10]II-B-1 Plant'!G22+'[9]II-B-1 Plant'!G22 -> -2865367.4 | H22: =+E22-F22+G22 -> 1.0435051e+08 | I22: 1 | J22: =SUM((H22-M22)*I22)+M22 -> 1.0435051e+08 | K22: 29 | L22: DIRECT | M22: ='[10]II-B-1 Plant'!M21+'[10]II-B-1 Plant'!M22+'[9]II-B-1 Plant'!M22 -> 1.0435051e+08 | N22: ='[10]II-B-1 Plant'!N21+'[10]II-B-1 Plant'!N22+'[9]II-B-1 Plant'!N22 -> -1.3969839e-09 | O22: ='[10]II-B-1 Plant'!O21+'[10]II-B-1 Plant'!O22+'[9]II-B-1 Plant'!O22 -> 0 | P22: ='[10]II-B-1 Plant'!P21+'[10]II-B-1 Plant'!P22+'[9]II-B-1 Plant'!P22 -> 0 | Q22: =+SUM(M22:P22) -> 1.0435051e+08
A23: =+A22+1 -> 10 | B23: A352 | C23: Structures and Improvements | E23: ='[10]II-B-1 Plant'!E23+'[9]II-B-1 Plant'!E23 -> 57812679 | F23: ='[10]II-B-1 Plant'!F23+'[9]II-B-1 Plant'!F23 -> 0 | G23: ='[10]II-B-1 Plant'!G23+'[9]II-B-1 Plant'!G23 -> -57283.7 | H23: =+E23-F23+G23 -> 57755396 | I23: 1 | J23: =SUM((H23-M23)*I23)+M23 -> 57755396 | K23: 29 | L23: DIRECT | M23: ='[10]II-B-1 Plant'!M23+'[9]II-B-1 Plant'!M23 -> 57755396 | N23: ='[10]II-B-1 Plant'!N23+'[9]II-B-1 Plant'!N23 -> 0 | O23: ='[10]II-B-1 Plant'!O23+'[9]II-B-1 Plant'!O23 -> 0 | P23: ='[10]II-B-1 Plant'!P23+'[9]II-B-1 Plant'!P23 -> 0 | Q23: =+SUM(M23:P23) -> 57755396
A24: =+A23+1 -> 11 | B24: A353 | C24: Station Equipment | E24: ='[10]II-B-1 Plant'!E24+'[9]II-B-1 Plant'!E24 -> 1.8046015e+09 | F24: ='[10]II-B-1 Plant'!F24+'[9]II-B-1 Plant'!F24 -> 238419.99 | G24: ='[10]II-B-1 Plant'!G24+'[9]II-B-1 Plant'!G24 -> -2088112.7 | H24: =+E24-F24+G24 -> 1.802275e+09 | I24: 1 | J24: =SUM((H24-M24)*I24)+M24 -> 1.802275e+09 | K24: 29 | L24: DIRECT | M24: ='[10]II-B-1 Plant'!M24+'[9]II-B-1 Plant'!M24 -> 1.802275e+09 | N24: ='[10]II-B-1 Plant'!N24+'[9]II-B-1 Plant'!N24 -> -2.3841858e-07 | O24: ='[10]II-B-1 Plant'!O24+'[9]II-B-1 Plant'!O24 -> 0 | P24: ='[10]II-B-1 Plant'!P24+'[9]II-B-1 Plant'!P24 -> 0 | Q24: =+SUM(M24:P24) -> 1.802275e+09
A25: =+A24+1 -> 12 | B25: A354 | C25: Towers and Fixtures | E25: ='[10]II-B-1 Plant'!E25+'[9]II-B-1 Plant'!E25 -> 49999122 | F25: ='[10]II-B-1 Plant'!F25+'[9]II-B-1 Plant'!F25 -> 0 | G25: ='[10]II-B-1 Plant'!G25+'[9]II-B-1 Plant'!G25 -> 5744.77 | H25: =+E25-F25+G25 -> 50004867 | I25: 1 | J25: =SUM((H25-M25)*I25)+M25 -> 50004867 | K25: 29 | L25: DIRECT | M25: ='[10]II-B-1 Plant'!M25+'[9]II-B-1 Plant'!M25 -> 50004867 | N25: ='[10]II-B-1 Plant'!N25+'[9]II-B-1 Plant'!N25 -> 0 | O25: ='[10]II-B-1 Plant'!O25+'[9]II-B-1 Plant'!O25 -> 0 | P25: ='[10]II-B-1 Plant'!P25+'[9]II-B-1 Plant'!P25 -> 0 | Q25: =+SUM(M25:P25) -> 50004867
A26: =+A25+1 -> 13 | B26: A355 | C26: Poles and Fixtures | E26: ='[10]II-B-1 Plant'!E26+'[9]II-B-1 Plant'!E26 -> 9.370228e+08 | F26: ='[10]II-B-1 Plant'!F26+'[9]II-B-1 Plant'!F26 -> 0 | G26: ='[10]II-B-1 Plant'!G26+'[9]II-B-1 Plant'!G26 -> -333289.99 | H26: =+E26-F26+G26 -> 9.3668951e+08 | I26: 1 | J26: =SUM((H26-M26)*I26)+M26 -> 9.3668951e+08 | K26: 29 | L26: DIRECT | M26: ='[10]II-B-1 Plant'!M26+'[9]II-B-1 Plant'!M26 -> 9.3668951e+08 | N26: ='[10]II-B-1 Plant'!N26+'[9]II-B-1 Plant'!N26 -> 0 | O26: ='[10]II-B-1 Plant'!O26+'[9]II-B-1 Plant'!O26 -> 0 | P26: ='[10]II-B-1 Plant'!P26+'[9]II-B-1 Plant'!P26 -> 0 | Q26: =+SUM(M26:P26) -> 9.3668951e+08
A27: =+A26+1 -> 14 | B27: A356 | C27: O.H. Conductors & Devices | E27: ='[10]II-B-1 Plant'!E27+'[9]II-B-1 Plant'!E27 -> 6.9705641e+08 | F27: ='[10]II-B-1 Plant'!F27+'[9]II-B-1 Plant'!F27 -> 0 | G27: ='[10]II-B-1 Plant'!G27+'[9]II-B-1 Plant'!G27 -> -54296.42 | H27: =+E27-F27+G27 -> 6.9700211e+08 | I27: 1 | J27: =SUM((H27-M27)*I27)+M27 -> 6.9700211e+08 | K27: 29 | L27: DIRECT | M27: ='[10]II-B-1 Plant'!M27+'[9]II-B-1 Plant'!M27 -> 6.9700211e+08 | N27: ='[10]II-B-1 Plant'!N27+'[9]II-B-1 Plant'!N27 -> 0 | O27: ='[10]II-B-1 Plant'!O27+'[9]II-B-1 Plant'!O27 -> 0 | P27: ='[10]II-B-1 Plant'!P27+'[9]II-B-1 Plant'!P27 -> 0 | Q27: =+SUM(M27:P27) -> 6.9700211e+08
A28: =+A27+1 -> 15 | B28: A357 | C28: Undergound Conduit | E28: ='[10]II-B-1 Plant'!E28+'[9]II-B-1 Plant'!E28 -> 4836777 | F28: ='[10]II-B-1 Plant'!F28+'[9]II-B-1 Plant'!F28 -> 0 | G28: ='[10]II-B-1 Plant'!G28+'[9]II-B-1 Plant'!G28 -> 0 | H28: =+E28-F28+G28 -> 4836777 | I28: 1 | J28: =SUM((H28-M28)*I28)+M28 -> 4836777 | K28: 29 | L28: DIRECT | M28: ='[10]II-B-1 Plant'!M28+'[9]II-B-1 Plant'!M28 -> 4836777 | N28: ='[10]II-B-1 Plant'!N28+'[9]II-B-1 Plant'!N28 -> 0 | O28: ='[10]II-B-1 Plant'!O28+'[9]II-B-1 Plant'!O28 -> 0 | P28: ='[10]II-B-1 Plant'!P28+'[9]II-B-1 Plant'!P28 -> 0 | Q28: =+SUM(M28:P28) -> 4836777
A29: =+A28+1 -> 16 | B29: A358 | C29: Underground Conductors | E29: ='[10]II-B-1 Plant'!E29+'[9]II-B-1 Plant'!E29 -> 25088976 | F29: ='[10]II-B-1 Plant'!F29+'[9]II-B-1 Plant'!F29 -> 0 | G29: ='[10]II-B-1 Plant'!G29+'[9]II-B-1 Plant'!G29 -> 0 | H29: =+E29-F29+G29 -> 25088976 | I29: 1 | J29: =SUM((H29-M29)*I29)+M29 -> 25088976 | K29: 29 | L29: DIRECT | M29: ='[10]II-B-1 Plant'!M29+'[9]II-B-1 Plant'!M29 -> 25088976 | N29: ='[10]II-B-1 Plant'!N29+'[9]II-B-1 Plant'!N29 -> 0 | O29: ='[10]II-B-1 Plant'!O29+'[9]II-B-1 Plant'!O29 -> 0 | P29: ='[10]II-B-1 Plant'!P29+'[9]II-B-1 Plant'!P29 -> 0 | Q29: =+SUM(M29:P29) -> 25088976
A30: =+A29+1 -> 17 | B30: A359 | C30: Roads and Trails | E30: ='[10]II-B-1 Plant'!E30+'[9]II-B-1 Plant'!E30 -> 54376.24 | F30: ='[10]II-B-1 Plant'!F30+'[9]II-B-1 Plant'!F30 -> 0 | G30: ='[10]II-B-1 Plant'!G30+'[9]II-B-1 Plant'!G30 -> 0 | H30: =+E30-F30+G30 -> 54376.24 | I30: 1 | J30: =SUM((H30-M30)*I30)+M30 -> 54376.24 | K30: 29 | L30: DIRECT | M30: ='[10]II-B-1 Plant'!M30+'[9]II-B-1 Plant'!M30 -> 54376.24 | N30: ='[10]II-B-1 Plant'!N30+'[9]II-B-1 Plant'!N30 -> 0 | O30: ='[10]II-B-1 Plant'!O30+'[9]II-B-1 Plant'!O30 -> 0 | P30: ='[10]II-B-1 Plant'!P30+'[9]II-B-1 Plant'!P30 -> 0 | Q30: =+SUM(M30:P30) -> 54376.24
A31: =+A30+1 -> 18 | C31: Subtotal | E31: =SUM(E21:E30) -> 3.6836885e+09 | F31: =SUM(F21:F30) -> 238419.99 | G31: =SUM(G21:G30) -> -5392605.5 | H31: =SUM(H21:H30) -> 3.6780575e+09 | J31: =SUM(J21:J30) -> 3.6780575e+09 | M31: =SUM(M21:M30) -> 3.6780575e+09 | N31: =SUM(N21:N30) -> -2.3981556e-07 | O31: =SUM(O21:O30) -> 0 | P31: =SUM(P21:P30) -> 0 | Q31: =SUM(Q21:Q30) -> 3.6780575e+09
A32: =+A31+1 -> 19
A33: =+A32+1 -> 20 | B33: Distribution Plant-Gross | D33: II-B-1
A34: =+A33+1 -> 21 | B34: A360 | C34: Land and Land Rights | E34: ='[10]II-B-1 Plant'!E34+'[9]II-B-1 Plant'!E34 -> 23099513 | F34: ='[10]II-B-1 Plant'!F34+'[9]II-B-1 Plant'!F34 -> 0 | G34: ='[10]II-B-1 Plant'!G34+'[9]II-B-1 Plant'!G34 -> 0 | H34: =+E34-F34+G34 -> 23099513 | I34: 1 | J34: =SUM((H34-M34)*I34)+M34 -> 23099513 | K34: 29 | L34: DIRECT | M34: ='[10]II-B-1 Plant'!M34+'[9]II-B-1 Plant'!M34 -> 0 | N34: ='[10]II-B-1 Plant'!N34+'[9]II-B-1 Plant'!N34 -> 23099513 | O34: ='[10]II-B-1 Plant'!O34+'[9]II-B-1 Plant'!O34 -> 0 | P34: ='[10]II-B-1 Plant'!P34+'[9]II-B-1 Plant'!P34 -> 0 | Q34: =+SUM(M34:P34) -> 23099513
A35: =+A34+1 -> 22 | B35: A361 | C35: Structures and Improvements | E35: ='[10]II-B-1 Plant'!E35+'[9]II-B-1 Plant'!E35 -> 19700103 | F35: ='[10]II-B-1 Plant'!F35+'[9]II-B-1 Plant'!F35 -> 0 | G35: ='[10]II-B-1 Plant'!G35+'[9]II-B-1 Plant'!G35 -> -2149571.1 | H35: =+E35-F35+G35 -> 17550532 | I35: 1 | J35: =SUM((H35-M35)*I35)+M35 -> 17550532 | K35: 29 | L35: DIRECT | M35: ='[10]II-B-1 Plant'!M35+'[9]II-B-1 Plant'!M35 -> 0 | N35: ='[10]II-B-1 Plant'!N35+'[9]II-B-1 Plant'!N35 -> 17550532 | O35: ='[10]II-B-1 Plant'!O35+'[9]II-B-1 Plant'!O35 -> 0 | P35: ='[10]II-B-1 Plant'!P35+'[9]II-B-1 Plant'!P35 -> 0 | Q35: =+SUM(M35:P35) -> 17550532
A36: =+A35+1 -> 23 | B36: A362 | C36: Station Equipment | E36: ='[10]II-B-1 Plant'!E36+'[9]II-B-1 Plant'!E36 -> 5.5331907e+08 | F36: ='[10]II-B-1 Plant'!F36+'[9]II-B-1 Plant'!F36 -> 0 | G36: ='[10]II-B-1 Plant'!G36+'[9]II-B-1 Plant'!G36 -> -5175555.2 | H36: =+E36-F36+G36 -> 5.4814351e+08 | I36: 1 | J36: =SUM((H36-M36)*I36)+M36 -> 5.4814351e+08 | K36: 29 | L36: DIRECT | M36: ='[10]II-B-1 Plant'!M36+'[9]II-B-1 Plant'!M36 -> 0 | N36: ='[10]II-B-1 Plant'!N36+'[9]II-B-1 Plant'!N36 -> 5.4814351e+08 | O36: ='[10]II-B-1 Plant'!O36+'[9]II-B-1 Plant'!O36 -> 0 | P36: ='[10]II-B-1 Plant'!P36+'[9]II-B-1 Plant'!P36 -> 0 | Q36: =+SUM(M36:P36) -> 5.4814351e+08
A37: =+A36+1 -> 24 | B37: A363 | C37: Storage Battery Equipment | E37: ='[10]II-B-1 Plant'!E37+'[9]II-B-1 Plant'!E37 -> 0 | F37: ='[10]II-B-1 Plant'!F37+'[9]II-B-1 Plant'!F37 -> 0 | G37: ='[10]II-B-1 Plant'!G37+'[9]II-B-1 Plant'!G37 -> 0 | H37: =+E37-F37+G37 -> 0 | J37: =SUM((H37-M37)*I37)+M37 -> 0 | K37: 29 | L37: DIRECT | M37: ='[10]II-B-1 Plant'!M37+'[9]II-B-1 Plant'!M37 -> 0 | N37: ='[10]II-B-1 Plant'!N37+'[9]II-B-1 Plant'!N37 -> 0 | O37: ='[10]II-B-1 Plant'!O37+'[9]II-B-1 Plant'!O37 -> 0 | P37: ='[10]II-B-1 Plant'!P37+'[9]II-B-1 Plant'!P37 -> 0 | Q37: =+SUM(M37:P37) -> 0
A38: =+A37+1 -> 25 | B38: A364 | C38: Poles,Towers & Fixtures-Primary | E38: ='[10]II-B-1 Plant'!E38+'[9]II-B-1 Plant'!E38 -> 8.5231111e+08 | F38: ='[10]II-B-1 Plant'!F38+'[9]II-B-1 Plant'!F38 -> 0 | G38: ='[10]II-B-1 Plant'!G38+'[9]II-B-1 Plant'!G38 -> -40944570 | H38: =+E38-F38+G38 -> 8.1136654e+08 | I38: 1 | J38: =SUM((H38-M38)*I38)+M38 -> 8.1136654e+08 | K38: 29 | L38: DIRECT | M38: ='[10]II-B-1 Plant'!M38+'[9]II-B-1 Plant'!M38 -> 0 | N38: ='[10]II-B-1 Plant'!N38+'[9]II-B-1 Plant'!N38 -> 8.1136654e+08 | O38: ='[10]II-B-1 Plant'!O38+'[9]II-B-1 Plant'!O38 -> 0 | P38: ='[10]II-B-1 Plant'!P38+'[9]II-B-1 Plant'!P38 -> 0 | Q38: =+SUM(M38:P38) -> 8.1136654e+08
A39: =+A38+1 -> 26 | B39: A365 | C39: O.H. Conductors & Devices-Primary | E39: ='[10]II-B-1 Plant'!E39+'[9]II-B-1 Plant'!E39 -> 7.4906994e+08 | F39: ='[10]II-B-1 Plant'!F39+'[9]II-B-1 Plant'!F39 -> 0 | G39: ='[10]II-B-1 Plant'!G39+'[9]II-B-1 Plant'!G39 -> -29081166 | H39: =+E39-F39+G39 -> 7.1998877e+08 | I39: 1 | J39: =SUM((H39-M39)*I39)+M39 -> 7.1998877e+08 | K39: 29 | L39: DIRECT | M39: ='[10]II-B-1 Plant'!M39+'[9]II-B-1 Plant'!M39 -> 0 | N39: ='[10]II-B-1 Plant'!N39+'[9]II-B-1 Plant'!N39 -> 7.1998877e+08 | O39: ='[10]II-B-1 Plant'!O39+'[9]II-B-1 Plant'!O39 -> 0 | P39: ='[10]II-B-1 Plant'!P39+'[9]II-B-1 Plant'!P39 -> 0 | Q39: =+SUM(M39:P39) -> 7.1998877e+08
A40: =+A39+1 -> 27 | B40: A366 | C40: Underground Conduits-Primary | E40: ='[10]II-B-1 Plant'!E40+'[9]II-B-1 Plant'!E40 -> 81076082 | F40: ='[10]II-B-1 Plant'!F40+'[9]II-B-1 Plant'!F40 -> 0 | G40: ='[10]II-B-1 Plant'!G40+'[9]II-B-1 Plant'!G40 -> -236447.67 | H40: =+E40-F40+G40 -> 80839635 | I40: 1 | J40: =SUM((H40-M40)*I40)+M40 -> 80839635 | K40: 29 | L40: DIRECT | M40: ='[10]II-B-1 Plant'!M40+'[9]II-B-1 Plant'!M40 -> 0 | N40: ='[10]II-B-1 Plant'!N40+'[9]II-B-1 Plant'!N40 -> 80839635 | O40: ='[10]II-B-1 Plant'!O40+'[9]II-B-1 Plant'!O40 -> 0 | P40: ='[10]II-B-1 Plant'!P40+'[9]II-B-1 Plant'!P40 -> 0 | Q40: =+SUM(M40:P40) -> 80839635
A41: =+A40+1 -> 28 | B41: A367 | C41: U.G. Conductors & Devices-Primary | E41: ='[10]II-B-1 Plant'!E41+'[9]II-B-1 Plant'!E41 -> 3.4829801e+08 | F41: ='[10]II-B-1 Plant'!F41+'[9]II-B-1 Plant'!F41 -> 0 | G41: ='[10]II-B-1 Plant'!G41+'[9]II-B-1 Plant'!G41 -> -2088447.6 | H41: =+E41-F41+G41 -> 3.4620957e+08 | I41: 1 | J41: =SUM((H41-M41)*I41)+M41 -> 3.4620957e+08 | K41: 29 | L41: DIRECT | M41: ='[10]II-B-1 Plant'!M41+'[9]II-B-1 Plant'!M41 -> 0 | N41: ='[10]II-B-1 Plant'!N41+'[9]II-B-1 Plant'!N41 -> 3.4620957e+08 | O41: ='[10]II-B-1 Plant'!O41+'[9]II-B-1 Plant'!O41 -> 0 | P41: ='[10]II-B-1 Plant'!P41+'[9]II-B-1 Plant'!P41 -> 0 | Q41: =+SUM(M41:P41) -> 3.4620957e+08
A42: =+A41+1 -> 29 | B42: A368 | C42: Line Transformers-Primary | E42: ='[10]II-B-1 Plant'!E42+'[9]II-B-1 Plant'!E42 -> 6.9968632e+08 | F42: ='[10]II-B-1 Plant'!F42+'[9]II-B-1 Plant'!F42 -> 0 | G42: ='[10]II-B-1 Plant'!G42+'[9]II-B-1 Plant'!G42 -> -1941889 | H42: =+E42-F42+G42 -> 6.9774443e+08 | I42: 1 | J42: =SUM((H42-M42)*I42)+M42 -> 6.9774443e+08 | K42: 29 | L42: DIRECT | M42: ='[10]II-B-1 Plant'!M42+'[9]II-B-1 Plant'!M42 -> 0 | N42: ='[10]II-B-1 Plant'!N42+'[9]II-B-1 Plant'!N42 -> 6.9774443e+08 | O42: ='[10]II-B-1 Plant'!O42+'[9]II-B-1 Plant'!O42 -> 0 | P42: ='[10]II-B-1 Plant'!P42+'[9]II-B-1 Plant'!P42 -> 0 | Q42: =+SUM(M42:P42) -> 6.9774443e+08
A43: =+A42+1 -> 30 | B43: A369 | C43: Services | E43: ='[10]II-B-1 Plant'!E43+'[9]II-B-1 Plant'!E43 -> 3.0381696e+08 | F43: ='[10]II-B-1 Plant'!F43+'[9]II-B-1 Plant'!F43 -> 0 | G43: ='[10]II-B-1 Plant'!G43+'[9]II-B-1 Plant'!G43 -> -42596.366 | H43: =+E43-F43+G43 -> 3.0377436e+08 | I43: 1 | J43: =SUM((H43-M43)*I43)+M43 -> 3.0377436e+08 | K43: 29 | L43: DIRECT | M43: ='[10]II-B-1 Plant'!M43+'[9]II-B-1 Plant'!M43 -> 0 | N43: ='[10]II-B-1 Plant'!N43+'[9]II-B-1 Plant'!N43 -> 3.0377436e+08 | O43: ='[10]II-B-1 Plant'!O43+'[9]II-B-1 Plant'!O43 -> 0 | P43: ='[10]II-B-1 Plant'!P43+'[9]II-B-1 Plant'!P43 -> 0 | Q43: =+SUM(M43:P43) -> 3.0377436e+08
A44: =+A43+1 -> 31 | B44: A370 | C44: Meters | E44: ='[10]II-B-1 Plant'!E44+'[9]II-B-1 Plant'!E44+'[10]II-B-1 Plant'!E45 -> 2.2980712e+08 | F44: ='[10]II-B-1 Plant'!F44+'[9]II-B-1 Plant'!F44+'[10]II-B-1 Plant'!F45 -> 0 | G44: ='[10]II-B-1 Plant'!G44+'[9]II-B-1 Plant'!G44+'[10]II-B-1 Plant'!G45 -> 0 | H44: =+E44-F44+G44 -> 2.2980712e+08 | I44: 1 | J44: =SUM((H44-M44)*I44)+M44 -> 2.2980712e+08 | K44: 29 | L44: DIRECT | M44: ='[10]II-B-1 Plant'!M44+'[9]II-B-1 Plant'!M44+'[10]II-B-1 Plant'!M45 -> 0 | N44: ='[10]II-B-1 Plant'!N44+'[9]II-B-1 Plant'!N44+'[10]II-B-1 Plant'!N45 -> 0 | O44: ='[10]II-B-1 Plant'!O44+'[9]II-B-1 Plant'!O44+'[10]II-B-1 Plant'!O45 -> 2.2980712e+08 | P44: ='[10]II-B-1 Plant'!P44+'[9]II-B-1 Plant'!P44+'[10]II-B-1 Plant'!P45 -> 0 | Q44: =+SUM(M44:P44) -> 2.2980712e+08
A45: =+A44+1 -> 32 | B45: A371 | C45: Install. on Customer Prem. | E45: ='[10]II-B-1 Plant'!E46+'[9]II-B-1 Plant'!E45 -> 70383156 | F45: ='[10]II-B-1 Plant'!F46+'[9]II-B-1 Plant'!F45 -> 0 | G45: ='[10]II-B-1 Plant'!G46+'[9]II-B-1 Plant'!G45 -> -24497.194 | H45: =+E45-F45+G45 -> 70358659 | I45: 1 | J45: =SUM((H45-M45)*I45)+M45 -> 70358659 | K45: 29 | L45: DIRECT | M45: ='[10]II-B-1 Plant'!M46+'[9]II-B-1 Plant'!M45 -> 0 | N45: ='[10]II-B-1 Plant'!N46+'[9]II-B-1 Plant'!N45 -> 70358659 | O45: ='[10]II-B-1 Plant'!O46+'[9]II-B-1 Plant'!O45 -> 0 | P45: ='[10]II-B-1 Plant'!P46+'[9]II-B-1 Plant'!P45 -> 0 | Q45: =+SUM(M45:P45) -> 70358659
A46: =+A45+1 -> 33 | B46: A372 | C46: Leased Prop. on Cust. Premises | E46: ='[10]II-B-1 Plant'!E47+'[9]II-B-1 Plant'!E46 -> 86895.92 | F46: ='[10]II-B-1 Plant'!F47+'[9]II-B-1 Plant'!F46 -> 0 | G46: ='[10]II-B-1 Plant'!G47+'[9]II-B-1 Plant'!G46 -> 0 | H46: =+E46-F46+G46 -> 86895.92 | I46: 1 | J46: =SUM((H46-M46)*I46)+M46 -> 86895.92 | K46: 29 | L46: DIRECT | M46: ='[10]II-B-1 Plant'!M47+'[9]II-B-1 Plant'!M46 -> 0 | N46: ='[10]II-B-1 Plant'!N47+'[9]II-B-1 Plant'!N46 -> 86895.92 | O46: ='[10]II-B-1 Plant'!O47+'[9]II-B-1 Plant'!O46 -> 0 | P46: ='[10]II-B-1 Plant'!P47+'[9]II-B-1 Plant'!P46 -> 0 | Q46: =+SUM(M46:P46) -> 86895.92
A47: =+A46+1 -> 34 | B47: A373 | C47: Street Lights | E47: ='[10]II-B-1 Plant'!E48+'[9]II-B-1 Plant'!E47 -> 1.0759518e+08 | F47: ='[10]II-B-1 Plant'!F48+'[9]II-B-1 Plant'!F47 -> 0 | G47: ='[10]II-B-1 Plant'!G48+'[9]II-B-1 Plant'!G47 -> -4511014.8 | H47: =+E47-F47+G47 -> 1.0308417e+08 | I47: 1 | J47: =SUM((H47-M47)*I47)+M47 -> 1.0308417e+08 | K47: 29 | L47: DIRECT | M47: ='[10]II-B-1 Plant'!M48+'[9]II-B-1 Plant'!M47 -> 0 | N47: ='[10]II-B-1 Plant'!N48+'[9]II-B-1 Plant'!N47 -> 1.0308417e+08 | O47: ='[10]II-B-1 Plant'!O48+'[9]II-B-1 Plant'!O47 -> 0 | P47: ='[10]II-B-1 Plant'!P48+'[9]II-B-1 Plant'!P47 -> 0 | Q47: =+SUM(M47:P47) -> 1.0308417e+08
A48: =+A47+1 -> 35 | B48: A374 | C48: Land Owned in Fee | E48: ='[10]II-B-1 Plant'!E49+'[9]II-B-1 Plant'!E48 -> 0 | F48: ='[10]II-B-1 Plant'!F49+'[9]II-B-1 Plant'!F48 -> 0 | G48: ='[10]II-B-1 Plant'!G49+'[9]II-B-1 Plant'!G48 -> 0 | K48: 29 | L48: DIRECT | M48: ='[10]II-B-1 Plant'!M49+'[9]II-B-1 Plant'!M48 -> 0 | N48: ='[10]II-B-1 Plant'!N49+'[9]II-B-1 Plant'!N48 -> 0 | O48: ='[10]II-B-1 Plant'!O49+'[9]II-B-1 Plant'!O48 -> 0 | P48: ='[10]II-B-1 Plant'!P49+'[9]II-B-1 Plant'!P48 -> 0 | Q48: =+SUM(M48:P48) -> 0
A49: =+A48+1 -> 36 | C49: Subtotal | E49: =SUM(E34:E48) -> 4.0382495e+09 | F49: =SUM(F34:F48) -> 0 | G49: =SUM(G34:G48) -> -86195755 | H49: =SUM(H34:H48) -> 3.9520537e+09 | J49: =SUM(J34:J48) -> 3.9520537e+09 | M49: =SUM(M34:M48) -> 0 | N49: =SUM(N34:N48) -> 3.7222466e+09 | O49: =SUM(O34:O48) -> 2.2980712e+08 | P49: =SUM(P34:P48) -> 0 | Q49: =SUM(Q34:Q48) -> 3.9520537e+09
A50: =+A49+1 -> 37
A51: =+A50+1 -> 38 | B51: TOTAL INT, TRAN, DIST PLANT-GROSS | D51: II-B-1 | E51: =E18+E31+E49 -> 7.8658905e+09 | F51: =F18+F31+F49 -> 785950.1 | G51: =G18+G31+G49 -> -91588360 | H51: =H18+H31+H49 -> 7.7735162e+09 | J51: =J18+J31+J49 -> 7.7735162e+09 | M51: =M18+M31+M49 -> 3.7156586e+09 | N51: =N18+N31+N49 -> 3.8243995e+09 | O51: =O18+O31+O49 -> 2.3345323e+08 | P51: =P18+P31+P49 -> 4800.4855 | Q51: =+Q49+Q31+Q18 -> 7.7735162e+09
A52: =+A51+1 -> 39 | B52: TOTAL TRAN, DIST PLANT-GROSS | D52: II-B-1 | E52: =E31+E49 -> 7.721938e+09 | F52: =F31+F49 -> 238419.99 | G52: =G31+G49 -> -91588360 | H52: =H31+H49 -> 7.6301112e+09 | J52: =J31+J49 -> 7.6301112e+09 | M52: =M31+M49 -> 3.6780575e+09 | N52: =N31+N49 -> 3.7222466e+09 | O52: =O31+O49 -> 2.2980712e+08 | P52: =P31+P49 -> 0 | Q52: =Q31+Q49 -> 7.6301112e+09
E54: =E51-F51 -> 7.8651045e+09

Sheet II-B-2 General Plant
B2: PUBLIC UTILITY COMMISSION OF TEXAS
B3: AEP TEXAS INC
B4: II-B-2 GENERAL PLANT FUNCTIONALIZATION
B5: TEST YEAR ENDING 12/31/2018
B6: ='I-A'!B6
E8: 1 | F8: 2 | G8: 3 | H8: 4 | I8: 5 | J8: 6 | K8: 7 | L8: 8 | M8: 9 | N8: 10 | O8: 11 | P8: 12 | Q8: 13
H9: Company | I9: Texas
B10: Account | C10: Description | D10: Reference | E10: Total | F10: Non-Regulated | G10: Known | H10: Total | I10: Retail | J10: Allocation to | K10: FF | L10: Funct | M10: TRAN | N10: DIST | O10: MET | P10: TDCS | Q10: Total
A11: Line | B11: Number | D11: Schedule | E11: Company | F11: or | G11: Change | H11: Electric | I11: Allocation | J11: Texas | K11: # | L11: Factor | R11: CHECK
A12: No. | F12: Non-Electric | I12: Factor | L12: Name
A14: 1 | B14: General Plant-Gross | D14: II-B-2
A15: =+A14+1 -> 2 | B15: A388 | C15: Land Owned in Fee | E15: ='[10]II-B-2 General Plant'!E15+'[9]II-B-2 General Plant'!E15 -> 0 | F15: ='[10]II-B-2 General Plant'!F15+'[9]II-B-2 General Plant'!F15 -> 0 | G15: ='[10]II-B-2 General Plant'!G15+'[9]II-B-2 General Plant'!G15 -> 0 | H15: =+E15-F15+G15 -> 0 | I15: 0 | J15: =+I15*H15 -> 0 | M15: ='[10]II-B-2 General Plant'!M15+'[9]II-B-2 General Plant'!M15 -> 0 | N15: ='[10]II-B-2 General Plant'!N15+'[9]II-B-2 General Plant'!N15 -> 0 | O15: ='[10]II-B-2 General Plant'!O15+'[9]II-B-2 General Plant'!O15 -> 0 | P15: ='[10]II-B-2 General Plant'!P15+'[9]II-B-2 General Plant'!P15 -> 0 | Q15: =+SUM(M15:P15) -> 0
A16: =+A15+1 -> 3 | B16: A389 | C16: Land and Land Rights | E16: ='[10]II-B-2 General Plant'!E16+'[10]II-B-2 General Plant'!E17+'[9]II-B-2 General Plant'!E16 -> 14943659 | F16: ='[10]II-B-2 General Plant'!F16+'[10]II-B-2 General Plant'!F17+'[9]II-B-2 General Plant'!F16 -> 0 | G16: ='[10]II-B-2 General Plant'!G16+'[10]II-B-2 General Plant'!G17+'[9]II-B-2 General Plant'!G16 -> 1258230.7 | H16: =+E16-F16+G16 -> 16201890 | I16: 1 | J16: =SUM((H16-M16)*I16)+M16 -> 16201890 | K16: 29/22 | L16: DIRECT/DSQFT | M16: ='[10]II-B-2 General Plant'!M16+'[10]II-B-2 General Plant'!M17+'[9]II-B-2 General Plant'!M16 -> 1258230.7 | N16: ='[10]II-B-2 General Plant'!N16+'[10]II-B-2 General Plant'!N17+'[9]II-B-2 General Plant'!N16 -> 14205666 | O16: ='[10]II-B-2 General Plant'!O16+'[10]II-B-2 General Plant'!O17+'[9]II-B-2 General Plant'!O16 -> 558461.94 | P16: ='[10]II-B-2 General Plant'!P16+'[10]II-B-2 General Plant'!P17+'[9]II-B-2 General Plant'!P16 -> 179531.54 | Q16: =+SUM(M16:P16) -> 16201890
A17: =+A16+1 -> 4 | B17: A390 | C17: Structures and Improvements | E17: ='[10]II-B-2 General Plant'!E18+'[9]II-B-2 General Plant'!E17 -> 3.3352769e+08 | F17: ='[10]II-B-2 General Plant'!F18+'[9]II-B-2 General Plant'!F17 -> 2661.7 | G17: ='[10]II-B-2 General Plant'!G18+'[9]II-B-2 General Plant'!G17 -> 0 | H17: =+E17-F17+G17 -> 3.3352503e+08 | I17: 1 | J17: =SUM((H17-M17)*I17)+M17 -> 3.3352503e+08 | K17: 29/22 | L17: DIRECT/DSQFT | M17: ='[10]II-B-2 General Plant'!M18+'[9]II-B-2 General Plant'!M17 -> 1.1665066e+08 | N17: ='[10]II-B-2 General Plant'!N18+'[9]II-B-2 General Plant'!N17 -> 2.0638456e+08 | O17: ='[10]II-B-2 General Plant'!O18+'[9]II-B-2 General Plant'!O17 -> 7908998.8 | P17: ='[10]II-B-2 General Plant'!P18+'[9]II-B-2 General Plant'!P17 -> 2580810.9 | Q17: =+SUM(M17:P17) -> 3.3352503e+08
A18: =+A17+1 -> 5 | B18: A391 | C18: Office Furniture & Equip. | E18: ='[10]II-B-2 General Plant'!E19+'[9]II-B-2 General Plant'!E18+'[10]II-B-2 General Plant'!E20 -> 7161931 | F18: ='[10]II-B-2 General Plant'!F19+'[9]II-B-2 General Plant'!F18+'[10]II-B-2 General Plant'!F20 -> 184508.68 | G18: ='[10]II-B-2 General Plant'!G19+'[9]II-B-2 General Plant'!G18+'[10]II-B-2 General Plant'!G20 -> 0 | H18: =+E18-F18+G18 -> 6977422.3 | I18: 1 | J18: =SUM((H18-M18)*I18)+M18 -> 6977422.3 | K18: 29/22 | L18: DIRECT/DSQFT | M18: ='[10]II-B-2 General Plant'!M19+'[9]II-B-2 General Plant'!M18+'[10]II-B-2 General Plant'!M20 -> 2035756.6 | N18: ='[10]II-B-2 General Plant'!N19+'[9]II-B-2 General Plant'!N18+'[10]II-B-2 General Plant'!N20 -> 4749326.6 | O18: ='[10]II-B-2 General Plant'!O19+'[9]II-B-2 General Plant'!O18+'[10]II-B-2 General Plant'!O20 -> 138760.08 | P18: ='[10]II-B-2 General Plant'!P19+'[9]II-B-2 General Plant'!P18+'[10]II-B-2 General Plant'!P20 -> 53579.066 | Q18: =+SUM(M18:P18) -> 6977422.3
A19: =+A18+1 -> 6 | B19: A392 | C19: Transportation Equipment | E19: ='[10]II-B-2 General Plant'!E21+'[10]II-B-2 General Plant'!E22+'[9]II-B-2 General Plant'!E19 -> 283185.64 | F19: ='[10]II-B-2 General Plant'!F21+'[10]II-B-2 General Plant'!F22+'[9]II-B-2 General Plant'!F19 -> 19016.03 | G19: ='[10]II-B-2 General Plant'!G21+'[10]II-B-2 General Plant'!G22+'[9]II-B-2 General Plant'!G19 -> 0 | H19: =+E19-F19+G19 -> 264169.61 | I19: 1 | J19: =SUM((H19-M19)*I19)+M19 -> 264169.61 | K19: 29/16 | L19: DIRECT/DPLTXGNL-N | M19: ='[10]II-B-2 General Plant'!M21+'[10]II-B-2 General Plant'!M22+'[9]II-B-2 General Plant'!M19 -> 1993.09 | N19: ='[10]II-B-2 General Plant'!N21+'[10]II-B-2 General Plant'!N22+'[9]II-B-2 General Plant'!N19 -> 254202.08 | O19: ='[10]II-B-2 General Plant'!O21+'[10]II-B-2 General Plant'!O22+'[9]II-B-2 General Plant'!O19 -> 7974.0804 | P19: ='[10]II-B-2 General Plant'!P21+'[10]II-B-2 General Plant'!P22+'[9]II-B-2 General Plant'!P19 -> 0.36431269 | Q19: =+SUM(M19:P19) -> 264169.61
A20: =+A19+1 -> 7 | B20: A393 | C20: Store Equipment | E20: ='[10]II-B-2 General Plant'!E23+'[9]II-B-2 General Plant'!E20 -> 1316420.4 | F20: ='[10]II-B-2 General Plant'!F23+'[9]II-B-2 General Plant'!F20 -> 29447.92 | G20: ='[10]II-B-2 General Plant'!G23+'[9]II-B-2 General Plant'!G20 -> 0 | H20: =+E20-F20+G20 -> 1286972.5 | I20: 1 | J20: =SUM((H20-M20)*I20)+M20 -> 1286972.5 | K20: 29/28 | L20: DIRECT/DMANDS | M20: ='[10]II-B-2 General Plant'!M23+'[9]II-B-2 General Plant'!M20 -> 3676.24 | N20: ='[10]II-B-2 General Plant'!N23+'[9]II-B-2 General Plant'!N20 -> 1242141.7 | O20: ='[10]II-B-2 General Plant'!O23+'[9]II-B-2 General Plant'!O20 -> 41125.522 | P20: ='[10]II-B-2 General Plant'!P23+'[9]II-B-2 General Plant'!P20 -> 29.054975 | Q20: =+SUM(M20:P20) -> 1286972.5
A21: =+A20+1 -> 8 | B21: A394 | C21: Tools, Shop & Garage Equip. | E21: ='[10]II-B-2 General Plant'!E24+'[9]II-B-2 General Plant'!E21 -> 48850563 | F21: ='[10]II-B-2 General Plant'!F24+'[9]II-B-2 General Plant'!F21 -> 51269.93 | G21: ='[10]II-B-2 General Plant'!G24+'[9]II-B-2 General Plant'!G21 -> 0 | H21: =+E21-F21+G21 -> 48799293 | I21: 1 | J21: =SUM((H21-M21)*I21)+M21 -> 48799293 | K21: 29/16 | L21: DIRECT/DPLTXGNL-N | M21: ='[10]II-B-2 General Plant'!M24+'[9]II-B-2 General Plant'!M21 -> 23106515 | N21: ='[10]II-B-2 General Plant'!N24+'[9]II-B-2 General Plant'!N21 -> 24912214 | O21: ='[10]II-B-2 General Plant'!O24+'[9]II-B-2 General Plant'!O21 -> 780530.33 | P21: ='[10]II-B-2 General Plant'!P24+'[9]II-B-2 General Plant'!P21 -> 34.696336 | Q21: =+SUM(M21:P21) -> 48799293
A22: =+A21+1 -> 9 | B22: A395 | C22: Laboratory Equipment | E22: ='[10]II-B-2 General Plant'!E25+'[9]II-B-2 General Plant'!E22 -> 2366780.8 | F22: ='[10]II-B-2 General Plant'!F25+'[9]II-B-2 General Plant'!F22 -> 1925886.6 | G22: ='[10]II-B-2 General Plant'!G25+'[9]II-B-2 General Plant'!G22 -> 0 | H22: =+E22-F22+G22 -> 440894.21 | I22: 1 | J22: =SUM((H22-M22)*I22)+M22 -> 440894.21 | K22: 29/16 | L22: DIRECT/DPLTXGNL-N | M22: ='[10]II-B-2 General Plant'!M25+'[9]II-B-2 General Plant'!M22 -> 75794.62 | N22: ='[10]II-B-2 General Plant'!N25+'[9]II-B-2 General Plant'!N22 -> 354456.1 | O22: ='[10]II-B-2 General Plant'!O25+'[9]II-B-2 General Plant'!O22 -> 10643.488 | P22: ='[10]II-B-2 General Plant'!P25+'[9]II-B-2 General Plant'!P22 -> 0 | Q22: =+SUM(M22:P22) -> 440894.21
A23: =+A22+1 -> 10 | B23: A396 | C23: Power Operated Equipment | E23: ='[10]II-B-2 General Plant'!E26+'[9]II-B-2 General Plant'!E23 -> 225096.38 | F23: ='[10]II-B-2 General Plant'!F26+'[9]II-B-2 General Plant'!F23 -> 32898.03 | G23: ='[10]II-B-2 General Plant'!G26+'[9]II-B-2 General Plant'!G23 -> 0 | H23: =+E23-F23+G23 -> 192198.35 | I23: 1 | J23: =SUM((H23-M23)*I23)+M23 -> 192198.35 | K23: 29/16 | L23: DIRECT/DPLTXGNL-N | M23: ='[10]II-B-2 General Plant'!M26+'[9]II-B-2 General Plant'!M23 -> 0 | N23: ='[10]II-B-2 General Plant'!N26+'[9]II-B-2 General Plant'!N23 -> 186595.33 | O23: ='[10]II-B-2 General Plant'!O26+'[9]II-B-2 General Plant'!O23 -> 5603.0213 | P23: ='[10]II-B-2 General Plant'!P26+'[9]II-B-2 General Plant'!P23 -> 0 | Q23: =+SUM(M23:P23) -> 192198.35
A24: =+A23+1 -> 11 | C24: Subtotal | E24: =SUM(E15:E23) -> 4.0867533e+08 | F24: =SUM(F15:F23) -> 2245688.9 | G24: =SUM(G15:G23) -> 1258230.7 | H24: =SUM(H15:H23) -> 4.0768787e+08 | J24: =SUM(J15:J23) -> 4.0768787e+08 | M24: =SUM(M15:M23) -> 1.4313262e+08 | N24: =SUM(N15:N23) -> 2.5228917e+08 | O24: =SUM(O15:O23) -> 9452097.3 | P24: =SUM(P15:P23) -> 2813985.6 | Q24: =SUM(Q15:Q23) -> 4.0768787e+08
A25: =+A24+1 -> 12
A26: =+A25+1 -> 13 | B26: A398 | C26: Misc. Equipment | E26: ='[10]II-B-2 General Plant'!E29+'[9]II-B-2 General Plant'!E26 -> 5163815.6 | F26: ='[10]II-B-2 General Plant'!F29+'[9]II-B-2 General Plant'!F26 -> 51787.88 | G26: ='[10]II-B-2 General Plant'!G29+'[9]II-B-2 General Plant'!G26 -> 0 | H26: =+E26-F26+G26 -> 5112027.8 | I26: 1 | J26: =SUM((H26-M26)*I26)+M26 -> 5112027.8 | K26: 29/16 | L26: DIRECT/DPLTXGNL-N | M26: ='[10]II-B-2 General Plant'!M29+'[9]II-B-2 General Plant'!M26 -> 453209.64 | N26: ='[10]II-B-2 General Plant'!N29+'[9]II-B-2 General Plant'!N26 -> 4514924.7 | O26: ='[10]II-B-2 General Plant'!O29+'[9]II-B-2 General Plant'!O26 -> 143884.57 | P26: ='[10]II-B-2 General Plant'!P29+'[9]II-B-2 General Plant'!P26 -> 8.8805376 | Q26: =+SUM(M26:P26) -> 5112027.8
A27: =+A26+1 -> 14 | B27: A399 | C27: Other Tangible | E27: ='[10]II-B-2 General Plant'!E30+'[9]II-B-2 General Plant'!E27 -> 1372572.4 | F27: ='[10]II-B-2 General Plant'!F30+'[9]II-B-2 General Plant'!F27 -> 0 | G27: ='[10]II-B-2 General Plant'!G30+'[9]II-B-2 General Plant'!G27 -> 0 | H27: =+E27-F27+G27 -> 1372572.4 | I27: 1 | J27: =SUM((H27-M27)*I27)+M27 -> 1372572.4 | K27: 29/16 | L27: DIRECT/DPLTXGNL-N | M27: ='[10]II-B-2 General Plant'!M30+'[9]II-B-2 General Plant'!M27 -> 0 | N27: ='[10]II-B-2 General Plant'!N30+'[9]II-B-2 General Plant'!N27 -> 1330480.2 | O27: ='[10]II-B-2 General Plant'!O30+'[9]II-B-2 General Plant'!O27 -> 42089.951 | P27: ='[10]II-B-2 General Plant'!P30+'[9]II-B-2 General Plant'!P27 -> 2.2850494 | Q27: =+SUM(M27:P27) -> 1372572.4
A28: =+A27+1 -> 15
A29: =+A28+1 -> 16 | C29: Subtotal | E29: =SUM(E26:E28) -> 6536388 | F29: =SUM(F26:F28) -> 51787.88 | G29: =SUM(G26:G28) -> 0 | H29: =SUM(H26:H28) -> 6484600.2 | J29: =SUM(J26:J28) -> 6484600.2 | M29: =SUM(M26:M28) -> 453209.64 | N29: =SUM(N26:N28) -> 5845404.8 | O29: =SUM(O26:O28) -> 185974.52 | P29: =SUM(P26:P28) -> 11.165587 | Q29: =SUM(Q26:Q28) -> 6484600.2
A30: =+A29+1 -> 17
A31: =+A30+1 -> 18 | B31: TOTAL GENERAL PLANT GROSS | D31: II-B-2 | E31: =E24+E29 -> 4.1521172e+08 | F31: =F24+F29 -> 2297476.8 | G31: =G24+G29 -> 1258230.7 | H31: =H24+H29 -> 4.1417247e+08 | J31: =+J29+J24 -> 4.1417247e+08 | M31: =M24+M29 -> 1.4358583e+08 | N31: =N24+N29 -> 2.5813457e+08 | O31: =O24+O29 -> 9638071.8 | P31: =P24+P29 -> 2813996.7 | Q31: =Q24+Q29 -> 4.1417247e+08
E34: =E31-F31 -> 4.1291424e+08

Sheet II-B-3 Comm. Equip.
B2: PUBLIC UTILITY COMMISSION OF TEXAS
B3: AEP TEXAS INC
B4: II-B-3 COMMUNICATION EQUIPMENT
B5: TEST YEAR ENDING 12/31/2018
B6: ='I-A'!B6
E8: 1 | F8: 2 | G8: 3 | H8: 4 | I8: 5 | J8: 6 | K8: 7 | L8: 8 | M8: 9 | N8: 10 | O8: 11 | P8: 12 | Q8: 13
H9: Company | I9: Texas
B10: Account | C10: Description | D10: Reference | E10: Total | F10: Non-Regulated | G10: Known | H10: Total | I10: Retail | J10: Allocation to | K10: FF | L10: Funct | M10: TRAN | N10: DIST | O10: MET | P10: TDCS | Q10: Total
A11: Line | B11: Number | D11: Schedule | E11: Company | F11: or | G11: Change | H11: Electric | I11: Allocation | J11: Texas | K11: # | L11: Factor | R11: CHECK
A12: No. | F12: Non-Electric | I12: Factor | L12: Name
A14: 1 | B14: A397 | C14: Total Communication Equipment | E14: ='[10]II-B-3 Comm. Equip.'!E19+'[9]II-B-3 Comm. Equip.'!E14 -> 1.2494796e+08 | F14: ='[10]II-B-3 Comm. Equip.'!F19+'[9]II-B-3 Comm. Equip.'!F14 -> 237590.12 | G14: ='[10]II-B-3 Comm. Equip.'!G19+'[9]II-B-3 Comm. Equip.'!G14 -> -1925527.1 | H14: =+E14-F14+G14 -> 1.2278485e+08 | I14: 1 | J14: =SUM((H14-M14)*I14)+M14 -> 1.2278485e+08 | K14: 29/16 | L14: DIRECT/DPLTXGNL-N | M14: ='[10]II-B-3 Comm. Equip.'!M19+'[9]II-B-3 Comm. Equip.'!M14 -> 11247748 | N14: ='[10]II-B-3 Comm. Equip.'!N19+'[9]II-B-3 Comm. Equip.'!N14 -> 95208035 | O14: ='[10]II-B-3 Comm. Equip.'!O19+'[9]II-B-3 Comm. Equip.'!O14 -> 16328967 | P14: ='[10]II-B-3 Comm. Equip.'!P19+'[9]II-B-3 Comm. Equip.'!P14 -> 97.082531 | Q14: =+SUM(M14:P14) -> 1.2278485e+08
A15: =+A14+1 -> 2 | C15: Subtotal | E15: =SUM(E14) -> 1.2494796e+08 | F15: =SUM(F14) -> 237590.12 | G15: =SUM(G14) -> -1925527.1 | H15: =SUM(H14) -> 1.2278485e+08 | J15: =SUM(J14) -> 1.2278485e+08 | M15: =SUM(M14) -> 11247748 | N15: =SUM(N14) -> 95208035 | O15: =SUM(O14) -> 16328967 | P15: =SUM(P14) -> 97.082531 | Q15: =SUM(Q14) -> 1.2278485e+08
A16: =+A15+1 -> 3
A17: =+A16+1 -> 4 | B17: TOTAL COMMUNICATION EQUIPMENT | E17: =+E15 -> 1.2494796e+08 | F17: =+F15 -> 237590.12 | G17: =+G15 -> -1925527.1 | H17: =+H15 -> 1.2278485e+08 | J17: =+J15 -> 1.2278485e+08 | M17: =+M15 -> 11247748 | N17: =+N15 -> 95208035 | O17: =+O15 -> 16328967 | P17: =+P15 -> 97.082531 | Q17: =+Q15 -> 1.2278485e+08
A18: =+A17+1 -> 5
A19: =+A18+1 -> 6 | B19: TOTAL GENERAL PLANT GROSS INCLUDE. COMM. EQUIP. | D19: II-B-2-3 | E19: =+'II-B-2 General Plant'!E31+'II-B-3 Comm. Equip.'!E17 -> 5.4015968e+08 | F19: =+'II-B-2 General Plant'!F31+'II-B-3 Comm. Equip.'!F17 -> 2535066.9 | G19: =+'II-B-2 General Plant'!G31+'II-B-3 Comm. Equip.'!G17 -> -667296.38 | H19: =+'II-B-2 General Plant'!H31+'II-B-3 Comm. Equip.'!H17 -> 5.3695732e+08 | J19: =+'II-B-2 General Plant'!J31+'II-B-3 Comm. Equip.'!J17 -> 5.3695732e+08 | M19: =+'II-B-2 General Plant'!M31+'II-B-3 Comm. Equip.'!M17 -> 1.5483358e+08 | N19: =+'II-B-2 General Plant'!N31+'II-B-3 Comm. Equip.'!N17 -> 3.5334261e+08 | O19: =+'II-B-2 General Plant'!O31+'II-B-3 Comm. Equip.'!O17 -> 25967039 | P19: =+'II-B-2 General Plant'!P31+'II-B-3 Comm. Equip.'!P17 -> 2814093.8 | Q19: =+'II-B-2 General Plant'!Q31+'II-B-3 Comm. Equip.'!Q17 -> 5.3695732e+08
A20: =+A19+1 -> 7
A21: =+A20+1 -> 8 | B21: TOTAL PLANT IN SERVICE-GROSS (INCL. INTANGIBLES) | D21: II-B-1-3 | E21: =+'II-B-1 Plant'!E51+'II-B-2 General Plant'!E31+'II-B-3 Comm. Equip.'!E17 -> 8.4060502e+09 | F21: =+'II-B-1 Plant'!F51+'II-B-2 General Plant'!F31+'II-B-3 Comm. Equip.'!F17 -> 3321017 | G21: =+'II-B-1 Plant'!G51+'II-B-2 General Plant'!G31+'II-B-3 Comm. Equip.'!G17 -> -92255657 | H21: =+'II-B-1 Plant'!H51+'II-B-2 General Plant'!H31+'II-B-3 Comm. Equip.'!H17 -> 8.3104735e+09 | J21: =+'II-B-1 Plant'!J51+'II-B-2 General Plant'!J31+'II-B-3 Comm. Equip.'!J17 -> 8.3104735e+09 | M21: =+'II-B-1 Plant'!M51+'II-B-2 General Plant'!M31+'II-B-3 Comm. Equip.'!M17 -> 3.8704922e+09 | N21: =+'II-B-1 Plant'!N51+'II-B-2 General Plant'!N31+'II-B-3 Comm. Equip.'!N17 -> 4.1777421e+09 | O21: =+'II-B-1 Plant'!O51+'II-B-2 General Plant'!O31+'II-B-3 Comm. Equip.'!O17 -> 2.5942027e+08 | P21: =+'II-B-1 Plant'!P51+'II-B-2 General Plant'!P31+'II-B-3 Comm. Equip.'!P17 -> 2818894.3 | Q21: =+'II-B-1 Plant'!Q51+'II-B-2 General Plant'!Q31+'II-B-3 Comm. Equip.'!Q17 -> 8.3104735e+09
A22: =+A21+1 -> 9
A23: =+A22+1 -> 10 | B23: TOTAL PLANT IN SERVICE-GROSS (EXCL. INTANGIBLES) | D23: II-B-1-3 | E23: =+'II-B-1 Plant'!E52+'II-B-2 General Plant'!E31+'II-B-3 Comm. Equip.'!E17 -> 8.2620977e+09 | F23: =+'II-B-1 Plant'!F52+'II-B-2 General Plant'!F31+'II-B-3 Comm. Equip.'!F17 -> 2773486.9 | G23: =+'II-B-1 Plant'!G52+'II-B-2 General Plant'!G31+'II-B-3 Comm. Equip.'!G17 -> -92255657 | H23: =+'II-B-1 Plant'!H52+'II-B-2 General Plant'!H31+'II-B-3 Comm. Equip.'!H17 -> 8.1670685e+09 | J23: =+'II-B-1 Plant'!J52+'II-B-2 General Plant'!J31+'II-B-3 Comm. Equip.'!J17 -> 8.1670685e+09 | M23: =+'II-B-1 Plant'!M52+'II-B-2 General Plant'!M31+'II-B-3 Comm. Equip.'!M17 -> 3.8328911e+09 | N23: =+'II-B-1 Plant'!N52+'II-B-2 General Plant'!N31+'II-B-3 Comm. Equip.'!N17 -> 4.0755892e+09 | O23: =+'II-B-1 Plant'!O52+'II-B-2 General Plant'!O31+'II-B-3 Comm. Equip.'!O17 -> 2.5577415e+08 | P23: =+'II-B-1 Plant'!P52+'II-B-2 General Plant'!P31+'II-B-3 Comm. Equip.'!P17 -> 2814093.8 | Q23: =+'II-B-1 Plant'!Q52+'II-B-2 General Plant'!Q31+'II-B-3 Comm. Equip.'!Q17 -> 8.1670685e+09
E26: =E17-F17 -> 1.2471037e+08

Sheet II-B-4 CWIP
Q1: SCHEDULE II-B-4
B2: PUBLIC UTILITY COMMISSION OF TEXAS
B3: AEP TEXAS INC
B4: II-B-4 CONSTRUCTION WORK IN PROGRESS
B5: TEST YEAR ENDING 12/31/2018
B6: ='I-A'!B6
E8: 1 | F8: 2 | G8: 3 | H8: 4 | I8: 5 | J8: 6 | K8: 7 | L8: 8 | M8: 9 | N8: 10 | O8: 11 | P8: 12 | Q8: 13
H9: Company | I9: Texas
B10: Account | C10: Description | D10: Reference | E10: Total | F10: Non-Regulated or | G10: Known | H10: Total | I10: Retail | J10: Allocation to | K10: FF | L10: Funct | M10: TRAN | N10: DIST | O10: MET | P10: TDCS | Q10: Total
A11: Line | B11: Number | D11: Schedule | E11: Company | F11: Non-Electric | G11: Change | H11: Electric | I11: Allocation | J11: Texas | K11: # | L11: Factor | R11: CHECK
A12: No. | I12: Factor | L12: Name
A14: 1 | C14: Construction Work in Progress
A15: =+A14+1 -> 2 | B15: A107 | C15: CWIP | E15: ='[10]II-B-4 CWIP'!E15+'[9]II-B-4 CWIP'!E15 -> 8.3618645e+08 | F15: ='[10]II-B-4 CWIP'!F15+'[9]II-B-4 CWIP'!F15 -> 182478.16 | G15: ='[10]II-B-4 CWIP'!G15+'[9]II-B-4 CWIP'!G15 -> -8.3600397e+08 | H15: =+E15-F15+G15 -> 0 | J15: =+H15*I15 -> 0 | K15: * | L15: * | N15: =+J15-M15 -> 0 | Q15: =+SUM(M15:P15) -> 0
A16: =+A15+1 -> 3 | C16: Subtotal | E16: =SUM(E15) -> 8.3618645e+08 | F16: =SUM(F15) -> 182478.16 | G16: =SUM(G15) -> -8.3600397e+08 | H16: =SUM(H15) -> 0 | N16: =+N15 -> 0 | Q16: =+Q15 -> 0
A17: =+A16+1 -> 4
A18: =+A17+1 -> 5 | B18: TOTAL CWIP | D18: II-B-4 | E18: =E16 -> 8.3618645e+08 | F18: =F16 -> 182478.16 | G18: =G16 -> -8.3600397e+08 | H18: =H16 -> 0 | N18: =+N16 -> 0 | Q18: =+Q16 -> 0

Sheet II-B-5 Depreciation
B2: PUBLIC UTILITY COMMISSION OF TEXAS
B3: AEP TEXAS INC
B4: II-B-5 ACCUMULATED DEPRECIATION
B5: TEST YEAR ENDING 12/31/2018
B6: ='I-A'!B6
E8: 1 | F8: 2 | G8: 3 | H8: 4 | I8: 5 | J8: 6 | K8: 7 | L8: 8 | M8: 9 | N8: 10 | O8: 11 | P8: 12 | Q8: 13
H9: Company | I9: Texas
B10: Account | C10: Description | D10: Reference | E10: Total | F10: Non-Regulated or | G10: Known | H10: Total | I10: Retail | J10: Allocation to | K10: FF | L10: Funct | M10: TRAN | N10: DIST | O10: MET | P10: TDCS | Q10: Total
A11: Line | B11: Number | D11: Schedule | E11: Company | F11: Non-Electric | G11: Change | H11: Electric | I11: Allocation | J11: Texas | K11: # | L11: Factor | R11: CHECK
A12: No. | I12: Factor | L12: Name
A14: 1 | B14: Intangible Plant
A15: =+A14+1 -> 2 | B15: Accumulated Depreciation | D15: II-B-5
A16: =+A15+1 -> 3 | B16: A301 | C16: Organization | E16: ='[10]II-B-5 Depreciation'!E16+'[9]II-B-5 Depreciation'!E16 -> 1731.05 | F16: ='[10]II-B-5 Depreciation'!F16+'[9]II-B-5 Depreciation'!F16 -> 1731.05 | G16: ='[10]II-B-5 Depreciation'!G16+'[9]II-B-5 Depreciation'!G16 -> 0 | H16: ='[10]II-B-5 Depreciation'!H16+'[9]II-B-5 Depreciation'!H16 -> 0 | I16: 0 | J16: =+I16*H16 -> 0 | K16: 25 | L16: TOTREV | M16: ='[10]II-B-5 Depreciation'!M16+'[9]II-B-5 Depreciation'!M16 -> 0 | N16: ='[10]II-B-5 Depreciation'!N16+'[9]II-B-5 Depreciation'!N16 -> 0 | O16: ='[10]II-B-5 Depreciation'!O16+'[9]II-B-5 Depreciation'!O16 -> 0 | P16: ='[10]II-B-5 Depreciation'!P16+'[9]II-B-5 Depreciation'!P16 -> 0 | Q16: =+SUM(M16:P16) -> 0
A17: =+A16+1 -> 4 | B17: A302 | C17: Franchise & Consents-Merger assets-Other | E17: ='[10]II-B-5 Depreciation'!E17+'[9]II-B-5 Depreciation'!E17 -> 0 | F17: ='[10]II-B-5 Depreciation'!F17+'[9]II-B-5 Depreciation'!F17 -> 0 | G17: ='[10]II-B-5 Depreciation'!G17+'[9]II-B-5 Depreciation'!G17 -> 0 | H17: ='[10]II-B-5 Depreciation'!H17+'[9]II-B-5 Depreciation'!H17 -> 0 | I17: 0 | J17: =+I17*H17 -> 0 | K17: 25 | L17: TOTREV | M17: ='[10]II-B-5 Depreciation'!M17+'[9]II-B-5 Depreciation'!M17 -> 0 | N17: ='[10]II-B-5 Depreciation'!N17+'[9]II-B-5 Depreciation'!N17 -> 0 | O17: ='[10]II-B-5 Depreciation'!O17+'[9]II-B-5 Depreciation'!O17 -> 0 | P17: ='[10]II-B-5 Depreciation'!P17+'[9]II-B-5 Depreciation'!P17 -> 0 | Q17: =+SUM(M17:P17) -> 0
A18: =+A17+1 -> 5 | B18: A303 | C18: Miscellaneous Intangible Plant | E18: ='[10]II-B-5 Depreciation'!E18+'[9]II-B-5 Depreciation'!E18 -> 65741349 | F18: ='[10]II-B-5 Depreciation'!F18+'[9]II-B-5 Depreciation'!F18 -> 542502.38 | G18: ='[10]II-B-5 Depreciation'!G18+'[9]II-B-5 Depreciation'!G18 -> 0 | H18: ='[10]II-B-5 Depreciation'!H18+'[9]II-B-5 Depreciation'!H18 -> 65198847 | I18: 1 | J18: =SUM((H18-M18)*I18)+M18 -> 65198847 | K18: 29/20 | L18: DIRECT/DPLTSVC-NX | M18: ='[10]II-B-5 Depreciation'!M18+'[9]II-B-5 Depreciation'!M18 -> 14369345 | N18: ='[10]II-B-5 Depreciation'!N18+'[9]II-B-5 Depreciation'!N18 -> 49074516 | O18: ='[10]II-B-5 Depreciation'!O18+'[9]II-B-5 Depreciation'!O18 -> 1752865.8 | P18: ='[10]II-B-5 Depreciation'!P18+'[9]II-B-5 Depreciation'!P18 -> 2120.3165 | Q18: =+SUM(M18:P18) -> 65198847
A19: =+A18+1 -> 6 | C19: Subtotal | E19: =+SUM(E16:E18) -> 65743080 | F19: =+SUM(F16:F18) -> 544233.43 | G19: =+SUM(G16:G18) -> 0 | H19: =+SUM(H16:H18) -> 65198847 | J19: =+SUM(J16:J18) -> 65198847 | M19: =+SUM(M16:M18) -> 14369345 | N19: =+SUM(N16:N18) -> 49074516 | O19: =+SUM(O16:O18) -> 1752865.8 | P19: =+SUM(P16:P18) -> 2120.3165 | Q19: =SUM(Q18) -> 65198847
A20: =+A19+1 -> 7
A21: =+A20+1 -> 8 | B21: Transmission Plant
A22: =+A21+1 -> 9 | B22: Accumulated Depreciation | D22: II-B-5
A23: =+A22+1 -> 10 | B23: A349 | C23: Land Owned in Fee | E23: ='[9]II-B-5 Depreciation'!E23 -> 0 | F23: ='[9]II-B-5 Depreciation'!F23 -> 0 | G23: ='[9]II-B-5 Depreciation'!G23 -> 0 | H23: =+E23-F23 -> 0 | J23: =+H23*I23 -> 0 | K23: 29 | L23: DIRECT | M23: ='[9]II-B-5 Depreciation'!M23 -> 0 | N23: ='[9]II-B-5 Depreciation'!N23 -> 0 | O23: ='[9]II-B-5 Depreciation'!O23 -> 0 | P23: ='[9]II-B-5 Depreciation'!P23 -> 0 | Q23: =+SUM(M23:P23) -> 0
A24: =+A23+1 -> 11 | B24: A350 | C24: Land and Land Rights | E24: ='[10]II-B-5 Depreciation'!E23+'[10]II-B-5 Depreciation'!E24+'[9]II-B-5 Depreciation'!E24 -> 27621788 | F24: ='[10]II-B-5 Depreciation'!F23+'[10]II-B-5 Depreciation'!F24+'[9]II-B-5 Depreciation'!F24 -> 0 | G24: ='[10]II-B-5 Depreciation'!G23+'[10]II-B-5 Depreciation'!G24+'[9]II-B-5 Depreciation'!G24 -> 347539 | H24: =+E24-F24+G24 -> 27969327 | I24: 1 | J24: =SUM((H24-M24)*I24)+M24 -> 27969327 | K24: 29 | L24: DIRECT | M24: ='[10]II-B-5 Depreciation'!M23+'[10]II-B-5 Depreciation'!M24+'[9]II-B-5 Depreciation'!M24 -> 27969327 | N24: ='[10]II-B-5 Depreciation'!N23+'[10]II-B-5 Depreciation'!N24+'[9]II-B-5 Depreciation'!N24 -> -0.010000002 | O24: ='[10]II-B-5 Depreciation'!O23+'[10]II-B-5 Depreciation'!O24+'[9]II-B-5 Depreciation'!O24 -> 0 | P24: ='[10]II-B-5 Depreciation'!P23+'[10]II-B-5 Depreciation'!P24+'[9]II-B-5 Depreciation'!P24 -> 0 | Q24: =+SUM(M24:P24) -> 27969327
A25: =+A24+1 -> 12 | B25: A352 | C25: Structures and Improvements | E25: ='[10]II-B-5 Depreciation'!E25+'[9]II-B-5 Depreciation'!E25 -> 4866051.5 | F25: ='[10]II-B-5 Depreciation'!F25+'[9]II-B-5 Depreciation'!F25 -> 0 | G25: ='[10]II-B-5 Depreciation'!G25+'[9]II-B-5 Depreciation'!G25 -> -98315.944 | H25: =+E25-F25+G25 -> 4767735.5 | I25: 1 | J25: =SUM((H25-M25)*I25)+M25 -> 4767735.5 | K25: 29 | L25: DIRECT | M25: ='[10]II-B-5 Depreciation'!M25+'[9]II-B-5 Depreciation'!M25 -> 4767735.5 | N25: ='[10]II-B-5 Depreciation'!N25+'[9]II-B-5 Depreciation'!N25 -> 0 | O25: ='[10]II-B-5 Depreciation'!O25+'[9]II-B-5 Depreciation'!O25 -> 0 | P25: ='[10]II-B-5 Depreciation'!P25+'[9]II-B-5 Depreciation'!P25 -> 0 | Q25: =+SUM(M25:P25) -> 4767735.5
A26: =+A25+1 -> 13 | B26: A353 | C26: Station Equipment | E26: ='[10]II-B-5 Depreciation'!E26+'[9]II-B-5 Depreciation'!E26 -> 2.3459164e+08 | F26: ='[10]II-B-5 Depreciation'!F26+'[9]II-B-5 Depreciation'!F26 -> 168161.62 | G26: ='[10]II-B-5 Depreciation'!G26+'[9]II-B-5 Depreciation'!G26 -> -7799154.9 | H26: =+E26-F26+G26 -> 2.2662432e+08 | I26: 1 | J26: =SUM((H26-M26)*I26)+M26 -> 2.2662432e+08 | K26: 29 | L26: DIRECT | M26: ='[10]II-B-5 Depreciation'!M26+'[9]II-B-5 Depreciation'!M26 -> 2.2662432e+08 | N26: ='[10]II-B-5 Depreciation'!N26+'[9]II-B-5 Depreciation'!N26 -> 0 | O26: ='[10]II-B-5 Depreciation'!O26+'[9]II-B-5 Depreciation'!O26 -> 0 | P26: ='[10]II-B-5 Depreciation'!P26+'[9]II-B-5 Depreciation'!P26 -> 0 | Q26: =+SUM(M26:P26) -> 2.2662432e+08
A27: =+A26+1 -> 14 | B27: A354 | C27: Towers and Fixtures | E27: ='[10]II-B-5 Depreciation'!E27+'[9]II-B-5 Depreciation'!E27 -> 17306994 | F27: ='[10]II-B-5 Depreciation'!F27+'[9]II-B-5 Depreciation'!F27 -> 0 | G27: ='[10]II-B-5 Depreciation'!G27+'[9]II-B-5 Depreciation'!G27 -> -372018.55 | H27: =+E27-F27+G27 -> 16934976 | I27: 1 | J27: =SUM((H27-M27)*I27)+M27 -> 16934976 | K27: 29 | L27: DIRECT | M27: ='[10]II-B-5 Depreciation'!M27+'[9]II-B-5 Depreciation'!M27 -> 16934976 | N27: ='[10]II-B-5 Depreciation'!N27+'[9]II-B-5 Depreciation'!N27 -> 0 | O27: ='[10]II-B-5 Depreciation'!O27+'[9]II-B-5 Depreciation'!O27 -> 0 | P27: ='[10]II-B-5 Depreciation'!P27+'[9]II-B-5 Depreciation'!P27 -> 0 | Q27: =+SUM(M27:P27) -> 16934976
A28: =+A27+1 -> 15 | B28: A355 | C28: Poles and Fixtures | E28: ='[10]II-B-5 Depreciation'!E28+'[9]II-B-5 Depreciation'!E28 -> 1.9316713e+08 | F28: ='[10]II-B-5 Depreciation'!F28+'[9]II-B-5 Depreciation'!F28 -> 0 | G28: ='[10]II-B-5 Depreciation'!G28+'[9]II-B-5 Depreciation'!G28 -> -7635548.1 | H28: =+E28-F28+G28 -> 1.8553158e+08 | I28: 1 | J28: =SUM((H28-M28)*I28)+M28 -> 1.8553158e+08 | K28: 29 | L28: DIRECT | M28: ='[10]II-B-5 Depreciation'!M28+'[9]II-B-5 Depreciation'!M28 -> 1.8553158e+08 | N28: ='[10]II-B-5 Depreciation'!N28+'[9]II-B-5 Depreciation'!N28 -> 0 | O28: ='[10]II-B-5 Depreciation'!O28+'[9]II-B-5 Depreciation'!O28 -> 0 | P28: ='[10]II-B-5 Depreciation'!P28+'[9]II-B-5 Depreciation'!P28 -> 0 | Q28: =+SUM(M28:P28) -> 1.8553158e+08
A29: =+A28+1 -> 16 | B29: A356 | C29: O.H. Conductors & Devices | E29: ='[10]II-B-5 Depreciation'!E29+'[9]II-B-5 Depreciation'!E29 -> 1.0301999e+08 | F29: ='[10]II-B-5 Depreciation'!F29+'[9]II-B-5 Depreciation'!F29 -> 0 | G29: ='[10]II-B-5 Depreciation'!G29+'[9]II-B-5 Depreciation'!G29 -> -4226091.7 | H29: =+E29-F29+G29 -> 98793898 | I29: 1 | J29: =SUM((H29-M29)*I29)+M29 -> 98793898 | K29: 29 | L29: DIRECT | M29: ='[10]II-B-5 Depreciation'!M29+'[9]II-B-5 Depreciation'!M29 -> 98793898 | N29: ='[10]II-B-5 Depreciation'!N29+'[9]II-B-5 Depreciation'!N29 -> 0 | O29: ='[10]II-B-5 Depreciation'!O29+'[9]II-B-5 Depreciation'!O29 -> 0 | P29: ='[10]II-B-5 Depreciation'!P29+'[9]II-B-5 Depreciation'!P29 -> 0 | Q29: =+SUM(M29:P29) -> 98793898
A30: =+A29+1 -> 17 | B30: A357 | C30: Undergound Conduit | E30: ='[10]II-B-5 Depreciation'!E30+'[9]II-B-5 Depreciation'!E30 -> 18800.1 | F30: ='[10]II-B-5 Depreciation'!F30+'[9]II-B-5 Depreciation'!F30 -> 0 | G30: ='[10]II-B-5 Depreciation'!G30+'[9]II-B-5 Depreciation'!G30 -> -872.80473 | H30: =+E30-F30+G30 -> 17927.295 | I30: 1 | J30: =SUM((H30-M30)*I30)+M30 -> 17927.295 | K30: 29 | L30: DIRECT | M30: ='[10]II-B-5 Depreciation'!M30+'[9]II-B-5 Depreciation'!M30 -> 17927.295 | N30: ='[10]II-B-5 Depreciation'!N30+'[9]II-B-5 Depreciation'!N30 -> 0 | O30: ='[10]II-B-5 Depreciation'!O30+'[9]II-B-5 Depreciation'!O30 -> 0 | P30: ='[10]II-B-5 Depreciation'!P30+'[9]II-B-5 Depreciation'!P30 -> 0 | Q30: =+SUM(M30:P30) -> 17927.295
A31: =+A30+1 -> 18 | B31: A358 | C31: Underground Conductors | E31: ='[10]II-B-5 Depreciation'!E31+'[9]II-B-5 Depreciation'!E31 -> 2965428 | F31: ='[10]II-B-5 Depreciation'!F31+'[9]II-B-5 Depreciation'!F31 -> 0 | G31: ='[10]II-B-5 Depreciation'!G31+'[9]II-B-5 Depreciation'!G31 -> -50821.92 | H31: =+E31-F31+G31 -> 2914606.1 | I31: 1 | J31: =SUM((H31-M31)*I31)+M31 -> 2914606.1 | K31: 29 | L31: DIRECT | M31: ='[10]II-B-5 Depreciation'!M31+'[9]II-B-5 Depreciation'!M31 -> 2914606.1 | N31: ='[10]II-B-5 Depreciation'!N31+'[9]II-B-5 Depreciation'!N31 -> 0 | O31: ='[10]II-B-5 Depreciation'!O31+'[9]II-B-5 Depreciation'!O31 -> 0 | P31: ='[10]II-B-5 Depreciation'!P31+'[9]II-B-5 Depreciation'!P31 -> 0 | Q31: =+SUM(M31:P31) -> 2914606.1
A32: =+A31+1 -> 19 | B32: A359 | C32: Roads and Trails | E32: ='[10]II-B-5 Depreciation'!E32+'[9]II-B-5 Depreciation'!E32 -> 48847.58 | F32: ='[10]II-B-5 Depreciation'!F32+'[9]II-B-5 Depreciation'!F32 -> 0 | G32: ='[10]II-B-5 Depreciation'!G32+'[9]II-B-5 Depreciation'!G32 -> -836.57766 | H32: =+E32-F32+G32 -> 48011.002 | I32: 1 | J32: =SUM((H32-M32)*I32)+M32 -> 48011.002 | K32: 29 | L32: DIRECT | M32: ='[10]II-B-5 Depreciation'!M32+'[9]II-B-5 Depreciation'!M32 -> 48011.002 | N32: ='[10]II-B-5 Depreciation'!N32+'[9]II-B-5 Depreciation'!N32 -> 0 | O32: ='[10]II-B-5 Depreciation'!O32+'[9]II-B-5 Depreciation'!O32 -> 0 | P32: ='[10]II-B-5 Depreciation'!P32+'[9]II-B-5 Depreciation'!P32 -> 0 | Q32: =+SUM(M32:P32) -> 48011.002
A33: =+A32+1 -> 20 | C33: Subtotal | E33: =SUM(E23:E32) -> 5.8360666e+08 | F33: =SUM(F23:F32) -> 168161.62 | G33: =SUM(G23:G32) -> -19836122 | H33: =SUM(H23:H32) -> 5.6360238e+08 | J33: =SUM(J23:J32) -> 5.6360238e+08 | M33: =SUM(M23:M32) -> 5.6360238e+08 | N33: =SUM(N23:N32) -> -0.010000002 | O33: =SUM(O23:O32) -> 0 | P33: =SUM(P23:P32) -> 0 | Q33: =SUM(Q24:Q32) -> 5.6360238e+08
A34: =+A33+1 -> 21
A35: =+A34+1 -> 22 | B35: Distribution Plant
A36: =+A35+1 -> 23 | B36: Accumulated Depreciation | D36: II-B-5
A37: =+A36+1 -> 24 | B37: A360 | C37: Land and Land Rights | E37: ='[10]II-B-5 Depreciation'!E37+'[9]II-B-5 Depreciation'!E37 -> 837604 | F37: ='[10]II-B-5 Depreciation'!F37+'[9]II-B-5 Depreciation'!F37 -> 0 | G37: ='[10]II-B-5 Depreciation'!G37+'[9]II-B-5 Depreciation'!G37 -> 0 | H37: =+E37-F37+G37 -> 837604 | I37: 1 | J37: =SUM((H37-M37)*I37)+M37 -> 837604 | K37: 29 | L37: DIRECT | M37: 0 | N37: =+J37-M37 -> 837604 | Q37: =+SUM(M37:P37) -> 837604
A38: =+A37+1 -> 25 | B38: A361 | C38: Structures and Improvements | E38: ='[10]II-B-5 Depreciation'!E38+'[9]II-B-5 Depreciation'!E38 -> 2636877.3 | F38: ='[10]II-B-5 Depreciation'!F38+'[9]II-B-5 Depreciation'!F38 -> 0 | G38: ='[10]II-B-5 Depreciation'!G38+'[9]II-B-5 Depreciation'!G38 -> 193333.38 | H38: =+E38-F38+G38 -> 2830210.7 | I38: 1 | J38: =SUM((H38-M38)*I38)+M38 -> 2830210.7 | K38: 29 | L38: DIRECT | M38: 0 | N38: =+J38-M38 -> 2830210.7 | Q38: =+SUM(M38:P38) -> 2830210.7
A39: =+A38+1 -> 26 | B39: A362 | C39: Station Equipment | E39: ='[10]II-B-5 Depreciation'!E39+'[9]II-B-5 Depreciation'!E39 -> 73803878 | F39: ='[10]II-B-5 Depreciation'!F39+'[9]II-B-5 Depreciation'!F39 -> 0 | G39: ='[10]II-B-5 Depreciation'!G39+'[9]II-B-5 Depreciation'!G39 -> 101652.22 | H39: =+E39-F39+G39 -> 73905530 | I39: 1 | J39: =SUM((H39-M39)*I39)+M39 -> 73905530 | K39: 29 | L39: DIRECT | M39: 0 | N39: =+J39-M39 -> 73905530 | Q39: =+SUM(M39:P39) -> 73905530
A40: =+A39+1 -> 27 | B40: A363 | C40: Storage Battery Equipment | E40: ='[10]II-B-5 Depreciation'!E40+'[9]II-B-5 Depreciation'!E40 -> 0 | F40: ='[10]II-B-5 Depreciation'!F40+'[9]II-B-5 Depreciation'!F40 -> 0 | G40: ='[10]II-B-5 Depreciation'!G40+'[9]II-B-5 Depreciation'!G40 -> 0 | H40: =+E40-F40+G40 -> 0 | I40: 1 | J40: =SUM((H40-M40)*I40)+M40 -> 0 | K40: 29 | L40: DIRECT | M40: 0 | N40: =+J40-M40-O40-P40 -> 0 | Q40: =+SUM(M40:P40) -> 0
A41: =+A40+1 -> 28 | B41: A364P | C41: Poles,Towers & Fixtures-Primary | E41: ='[10]II-B-5 Depreciation'!E41+'[9]II-B-5 Depreciation'!E41 -> 3.4508229e+08 | F41: ='[10]II-B-5 Depreciation'!F41+'[9]II-B-5 Depreciation'!F41 -> 0 | G41: ='[10]II-B-5 Depreciation'!G41+'[9]II-B-5 Depreciation'!G41 -> 1696648.8 | H41: =+E41-F41+G41 -> 3.4677894e+08 | I41: 1 | J41: =SUM((H41-M41)*I41)+M41 -> 3.4677894e+08 | K41: 29 | L41: DIRECT | M41: 0 | N41: =+J41-M41 -> 3.4677894e+08 | Q41: =+SUM(M41:P41) -> 3.4677894e+08
A42: =+A41+1 -> 29 | B42: A365P | C42: O.H. Conductors & Devices-Primary | E42: ='[10]II-B-5 Depreciation'!E42+'[9]II-B-5 Depreciation'!E42 -> 2.3966574e+08 | F42: ='[10]II-B-5 Depreciation'!F42+'[9]II-B-5 Depreciation'!F42 -> 0 | G42: ='[10]II-B-5 Depreciation'!G42+'[9]II-B-5 Depreciation'!G42 -> 1144775.7 | H42: =+E42-F42+G42 -> 2.4081051e+08 | I42: 1 | J42: =SUM((H42-M42)*I42)+M42 -> 2.4081051e+08 | K42: 29 | L42: DIRECT | M42: 0 | N42: =+J42-M42 -> 2.4081051e+08 | Q42: =+SUM(M42:P42) -> 2.4081051e+08
A43: =+A42+1 -> 30 | B43: A366P | C43: Underground Conduits-Primary | E43: ='[10]II-B-5 Depreciation'!E43+'[9]II-B-5 Depreciation'!E43 -> 25671626 | F43: ='[10]II-B-5 Depreciation'!F43+'[9]II-B-5 Depreciation'!F43 -> 0 | G43: ='[10]II-B-5 Depreciation'!G43+'[9]II-B-5 Depreciation'!G43 -> -153945.06 | H43: =+E43-F43+G43 -> 25517681 | I43: 1 | J43: =SUM((H43-M43)*I43)+M43 -> 25517681 | K43: 29 | L43: DIRECT | M43: 0 | N43: =+J43-M43 -> 25517681 | Q43: =+SUM(M43:P43) -> 25517681
A44: =+A43+1 -> 31 | B44: A367P | C44: U.G. Conductors & Devices-Primary | E44: ='[10]II-B-5 Depreciation'!E44+'[9]II-B-5 Depreciation'!E44 -> 90087579 | F44: ='[10]II-B-5 Depreciation'!F44+'[9]II-B-5 Depreciation'!F44 -> 0 | G44: ='[10]II-B-5 Depreciation'!G44+'[9]II-B-5 Depreciation'!G44 -> -418795.87 | H44: =+E44-F44+G44 -> 89668783 | I44: 1 | J44: =SUM((H44-M44)*I44)+M44 -> 89668783 | K44: 29 | L44: DIRECT | M44: 0 | N44: =+J44-M44 -> 89668783 | Q44: =+SUM(M44:P44) -> 89668783
A45: =+A44+1 -> 32 | B45: A368P | C45: Line Transformers-Primary | E45: ='[10]II-B-5 Depreciation'!E45+'[9]II-B-5 Depreciation'!E45 -> 1.2617857e+08 | F45: ='[10]II-B-5 Depreciation'!F45+'[9]II-B-5 Depreciation'!F45 -> 0 | G45: ='[10]II-B-5 Depreciation'!G45+'[9]II-B-5 Depreciation'!G45 -> -645693.18 | H45: =+E45-F45+G45 -> 1.2553288e+08 | I45: 1 | J45: =SUM((H45-M45)*I45)+M45 -> 1.2553288e+08 | K45: 29 | L45: DIRECT | M45: 0 | N45: =+J45-M45 -> 1.2553288e+08 | Q45: =+SUM(M45:P45) -> 1.2553288e+08
A46: =+A45+1 -> 33 | B46: A369 | C46: Services | E46: ='[10]II-B-5 Depreciation'!E46+'[9]II-B-5 Depreciation'!E46 -> 1.7075874e+08 | F46: ='[10]II-B-5 Depreciation'!F46+'[9]II-B-5 Depreciation'!F46 -> 0 | G46: ='[10]II-B-5 Depreciation'!G46+'[9]II-B-5 Depreciation'!G46 -> -1112354.2 | H46: =+E46-F46+G46 -> 1.6964638e+08 | I46: 1 | J46: =SUM((H46-M46)*I46)+M46 -> 1.6964638e+08 | K46: 29 | L46: DIRECT | M46: 0 | N46: =+J46-M46 -> 1.6964638e+08 | Q46: =+SUM(M46:P46) -> 1.6964638e+08
A47: =+A46+1 -> 34 | B47: A370 | C47: Meters | E47: ='[10]II-B-5 Depreciation'!E47+'[9]II-B-5 Depreciation'!E47 -> 1.5149251e+08 | F47: ='[10]II-B-5 Depreciation'!F47+'[9]II-B-5 Depreciation'!F47 -> 0 | G47: ='[10]II-B-5 Depreciation'!G47+'[9]II-B-5 Depreciation'!G47 -> -1063111 | H47: =+E47-F47+G47 -> 1.504294e+08 | I47: 1 | J47: =SUM((H47-M47)*I47)+M47 -> 1.504294e+08 | K47: 29 | L47: DIRECT | M47: 0 | N47: 0 | O47: =J47 -> 1.504294e+08 | Q47: =+SUM(M47:P47) -> 1.504294e+08
A48: =+A47+1 -> 35 | B48: A371 | C48: Install. on Customer Prem. | E48: ='[10]II-B-5 Depreciation'!E48+'[9]II-B-5 Depreciation'!E48 -> 43840024 | F48: ='[10]II-B-5 Depreciation'!F48+'[9]II-B-5 Depreciation'!F48 -> 0 | G48: ='[10]II-B-5 Depreciation'!G48+'[9]II-B-5 Depreciation'!G48 -> -286760.54 | H48: =+E48-F48+G48 -> 43553264 | I48: 1 | J48: =SUM((H48-M48)*I48)+M48 -> 43553264 | K48: 29 | L48: DIRECT | M48: 0 | N48: =+J48-M48 -> 43553264 | Q48: =+SUM(M48:P48) -> 43553264
A49: =+A48+1 -> 36 | B49: A372 | C49: Leased Prop. on Cust. Premises | E49: ='[10]II-B-5 Depreciation'!E49+'[9]II-B-5 Depreciation'!E49 -> 71534.01 | F49: ='[10]II-B-5 Depreciation'!F49+'[9]II-B-5 Depreciation'!F49 -> 0 | G49: ='[10]II-B-5 Depreciation'!G49+'[9]II-B-5 Depreciation'!G49 -> -328.43643 | H49: =+E49-F49+G49 -> 71205.574 | I49: 1 | J49: =SUM((H49-M49)*I49)+M49 -> 71205.574 | K49: 29 | L49: DIRECT | M49: 0 | N49: =+J49-M49 -> 71205.574 | Q49: =+SUM(M49:P49) -> 71205.574
A50: =+A49+1 -> 37 | B50: A373 | C50: Street Lights | E50: ='[10]II-B-5 Depreciation'!E50+'[9]II-B-5 Depreciation'!E50 -> 32943721 | F50: ='[10]II-B-5 Depreciation'!F50+'[9]II-B-5 Depreciation'!F50 -> 0 | G50: ='[10]II-B-5 Depreciation'!G50+'[9]II-B-5 Depreciation'!G50 -> 233419.94 | H50: =+E50-F50+G50 -> 33177141 | I50: 1 | J50: =SUM((H50-M50)*I50)+M50 -> 33177141 | K50: 29 | L50: DIRECT | M50: 0 | N50: =+J50-M50 -> 33177141 | Q50: =+SUM(M50:P50) -> 33177141
A51: =+A50+1 -> 38 | C51: Subtotal | E51: =SUM(E37:E50) -> 1.3030707e+09 | F51: =SUM(F37:F50) -> 0 | G51: =SUM(G37:G50) -> -311158.24 | H51: =SUM(H37:H50) -> 1.3027595e+09 | J51: =SUM(J37:J50) -> 1.3027595e+09 | M51: =SUM(M37:M50) -> 0 | N51: =SUM(N37:N50) -> 1.1523301e+09 | O51: =SUM(O47:O50) -> 1.504294e+08 | P51: =SUM(P47:P50) -> 0 | Q51: =SUM(Q37:Q50) -> 1.3027595e+09
A52: =+A51+1 -> 39
A53: =+A52+1 -> 40 | B53: TOTAL INT, TRAN, DIST PLANT-ACCUM DEP. | D53: II-B-5 | E53: =E19+E33+E51 -> 1.9524204e+09 | F53: =F19+F33+F51 -> 712395.05 | G53: =G19+G33+G51 -> -20147280 | H53: =H19+H33+H51 -> 1.9315608e+09 | J53: =J19+J33+J51 -> 1.9315608e+09 | M53: =M19+M33+M51 -> 5.7797173e+08 | N53: =N19+N33+N51 -> 1.2014046e+09 | O53: =O19+O33+O51 -> 1.5218226e+08 | P53: =P19+P33+P51 -> 2120.3165 | Q53: =Q19+Q33+Q51 -> 1.9315608e+09
A54: =+A53+1 -> 41 | B54: TOTAL TRAN, DIST PLANT-ACCUM DEP. | D54: II-B-5 | E54: =E33+E51 -> 1.8866773e+09 | F54: =F33+F51 -> 168161.62 | G54: =G33+G51 -> -20147280 | H54: =H33+H51 -> 1.8663619e+09 | J54: =J33+J51 -> 1.8663619e+09 | M54: =M33+M51 -> 5.6360238e+08 | N54: =N33+N51 -> 1.1523301e+09 | O54: =O33+O51 -> 1.504294e+08 | P54: =P33+P51 -> 0 | Q54: =Q33+Q51 -> 1.8663619e+09
A55: =+A54+1 -> 42
A56: =+A55+1 -> 43 | B56: TOTAL INT, TRAN, DIST PLANT-NET | D56: II-B-1 - II-B-5 | E56: =+'II-B-1 Plant'!E51-'II-B-5 Depreciation'!E53 -> 5.91347e+09 | F56: =+'II-B-1 Plant'!F51-'II-B-5 Depreciation'!F53 -> 73555.05 | G56: =+'II-B-1 Plant'!G51-'II-B-5 Depreciation'!G53 -> -71441081 | H56: =+'II-B-1 Plant'!H51-'II-B-5 Depreciation'!H53 -> 5.8419554e+09 | J56: =+'II-B-1 Plant'!J51-'II-B-5 Depreciation'!J53 -> 5.8419554e+09 | M56: =+'II-B-1 Plant'!M51-'II-B-5 Depreciation'!M53 -> 3.1376869e+09 | N56: =+'II-B-1 Plant'!N51-'II-B-5 Depreciation'!N53 -> 2.6229949e+09 | O56: =+'II-B-1 Plant'!O51-'II-B-5 Depreciation'!O53 -> 81270965 | P56: =+'II-B-1 Plant'!P51-'II-B-5 Depreciation'!P53 -> 2680.169 | Q56: =+'II-B-1 Plant'!Q51-'II-B-5 Depreciation'!Q53 -> 5.8419554e+09
A57: =+A56+1 -> 44 | B57: TOTAL TRAN, DIST PLANT-NET | D57: II-B-1 - II-B-5 | E57: =+'II-B-1 Plant'!E52-'II-B-5 Depreciation'!E54 -> 5.8352607e+09 | F57: =+'II-B-1 Plant'!F52-'II-B-5 Depreciation'!F54 -> 70258.37 | G57: =+'II-B-1 Plant'!G52-'II-B-5 Depreciation'!G54 -> -71441081 | H57: =+'II-B-1 Plant'!H52-'II-B-5 Depreciation'!H54 -> 5.7637493e+09 | J57: =+'II-B-1 Plant'!J52-'II-B-5 Depreciation'!J54 -> 5.7637493e+09 | M57: =+'II-B-1 Plant'!M52-'II-B-5 Depreciation'!M54 -> 3.1144551e+09 | N57: =+'II-B-1 Plant'!N52-'II-B-5 Depreciation'!N54 -> 2.5699165e+09 | O57: =+'II-B-1 Plant'!O52-'II-B-5 Depreciation'!O54 -> 79377717 | P57: =+'II-B-1 Plant'!P52-'II-B-5 Depreciation'!P54 -> 0 | Q57: =+'II-B-1 Plant'!Q52-'II-B-5 Depreciation'!Q54 -> 5.7637493e+09
A61: 45 | B61: General Plant | D61: II-B-5
A62: =+A61+1 -> 46 | B62: Accumulated Depreciation
A63: =+A62+1 -> 47 | B63: A388 | C63: Land Owned in Fee | E63: ='[10]II-B-5 Depreciation'!E61+'[9]II-B-5 Depreciation'!E63 -> 0 | F63: ='[10]II-B-5 Depreciation'!F61+'[9]II-B-5 Depreciation'!F63 -> 0 | G63: ='[10]II-B-5 Depreciation'!G61+'[9]II-B-5 Depreciation'!G63 -> 0 | H63: =+E63-F63+G63 -> 0 | J63: =SUM((H63-M63)*I63)+M63 -> 0 | M63: ='[10]II-B-5 Depreciation'!M61+'[9]II-B-5 Depreciation'!M63 -> 0 | N63: ='[10]II-B-5 Depreciation'!N61+'[9]II-B-5 Depreciation'!N63 -> 0 | O63: ='[10]II-B-5 Depreciation'!O61+'[9]II-B-5 Depreciation'!O63 -> 0 | P63: ='[10]II-B-5 Depreciation'!P61+'[9]II-B-5 Depreciation'!P63 -> 0 | Q63: =+SUM(M63:P63) -> 0
A64: =+A63+1 -> 48 | B64: A389 | C64: Land and Land Rights | E64: ='[10]II-B-5 Depreciation'!E62+'[9]II-B-5 Depreciation'!E64 -> 17632.61 | F64: ='[10]II-B-5 Depreciation'!F62+'[9]II-B-5 Depreciation'!F64 -> 0 | G64: ='[10]II-B-5 Depreciation'!G62+'[9]II-B-5 Depreciation'!G64 -> 0 | H64: =+E64-F64+G64 -> 17632.61 | I64: 1 | J64: =SUM((H64-M64)*I64)+M64 -> 17632.61 | K64: 29/22 | L64: DIRECT/DSQFT | M64: ='[10]II-B-5 Depreciation'!M62+'[9]II-B-5 Depreciation'!M64 -> 0 | N64: ='[10]II-B-5 Depreciation'!N62+'[9]II-B-5 Depreciation'!N64 -> 17357.991 | O64: ='[10]II-B-5 Depreciation'!O62+'[9]II-B-5 Depreciation'!O64 -> 129.53725 | P64: ='[10]II-B-5 Depreciation'!P62+'[9]II-B-5 Depreciation'!P64 -> 145.08172 | Q64: =+SUM(M64:P64) -> 17632.61
A65: =+A64+1 -> 49 | B65: A390 | C65: Structures and Improvements | E65: ='[10]II-B-5 Depreciation'!E63+'[9]II-B-5 Depreciation'!E65 -> 54291041 | F65: ='[10]II-B-5 Depreciation'!F63+'[9]II-B-5 Depreciation'!F65 -> 860.22 | G65: ='[10]II-B-5 Depreciation'!G63+'[9]II-B-5 Depreciation'!G65 -> -360690.68 | H65: =+E65-F65+G65 -> 53929490 | I65: 1 | J65: =SUM((H65-M65)*I65)+M65 -> 53929490 | K65: 29/22 | L65: DIRECT/DSQFT | M65: ='[10]II-B-5 Depreciation'!M63+'[9]II-B-5 Depreciation'!M65 -> 673296.33 | N65: ='[10]II-B-5 Depreciation'!N63+'[9]II-B-5 Depreciation'!N65 -> 51238628 | O65: ='[10]II-B-5 Depreciation'!O63+'[9]II-B-5 Depreciation'!O65 -> 1446334.1 | P65: ='[10]II-B-5 Depreciation'!P63+'[9]II-B-5 Depreciation'!P65 -> 571231.61 | Q65: =+SUM(M65:P65) -> 53929490
A66: =+A65+1 -> 50 | B66: A391 | C66: Office Furniture & Equip. | E66: ='[10]II-B-5 Depreciation'!E64+'[9]II-B-5 Depreciation'!E66 -> 2196605.2 | F66: ='[10]II-B-5 Depreciation'!F64+'[9]II-B-5 Depreciation'!F66 -> 182508.66 | G66: ='[10]II-B-5 Depreciation'!G64+'[9]II-B-5 Depreciation'!G66 -> -15839.889 | H66: =+E66-F66+G66 -> 1998256.6 | I66: 1 | J66: =SUM((H66-M66)*I66)+M66 -> 1998256.6 | K66: 29/22 | L66: DIRECT/DSQFT | M66: ='[10]II-B-5 Depreciation'!M64+'[9]II-B-5 Depreciation'!M66 -> 96313.724 | N66: ='[10]II-B-5 Depreciation'!N64+'[9]II-B-5 Depreciation'!N66 -> 1855950.8 | O66: ='[10]II-B-5 Depreciation'!O64+'[9]II-B-5 Depreciation'!O66 -> 28509.877 | P66: ='[10]II-B-5 Depreciation'!P64+'[9]II-B-5 Depreciation'!P66 -> 17482.285 | Q66: =+SUM(M66:P66) -> 1998256.6
A67: =+A66+1 -> 51 | B67: A392 | C67: Transportation Equipment | E67: ='[10]II-B-5 Depreciation'!E65+'[9]II-B-5 Depreciation'!E67 -> 134398.99 | F67: ='[10]II-B-5 Depreciation'!F65+'[9]II-B-5 Depreciation'!F67 -> 5519.59 | G67: ='[10]II-B-5 Depreciation'!G65+'[9]II-B-5 Depreciation'!G67 -> -980.35884 | H67: =+E67-F67+G67 -> 127899.04 | I67: 1 | J67: =SUM((H67-M67)*I67)+M67 -> 127899.04 | K67: 29/16 | L67: DIRECT/DPLTXGNL-N | M67: ='[10]II-B-5 Depreciation'!M65+'[9]II-B-5 Depreciation'!M67 -> 1215.69 | N67: ='[10]II-B-5 Depreciation'!N65+'[9]II-B-5 Depreciation'!N67 -> 122898.21 | O67: ='[10]II-B-5 Depreciation'!O65+'[9]II-B-5 Depreciation'!O67 -> 3785.04 | P67: ='[10]II-B-5 Depreciation'!P65+'[9]II-B-5 Depreciation'!P67 -> 0.10117202 | Q67: =+SUM(M67:P67) -> 127899.04
A68: =+A67+1 -> 52 | B68: A393 | C68: Store Equipment | E68: ='[10]II-B-5 Depreciation'!E66+'[9]II-B-5 Depreciation'!E68 -> 549801.3 | F68: ='[10]II-B-5 Depreciation'!F66+'[9]II-B-5 Depreciation'!F68 -> 5834.12 | G68: ='[10]II-B-5 Depreciation'!G66+'[9]II-B-5 Depreciation'!G68 -> -3941.508 | H68: =+E68-F68+G68 -> 540025.67 | I68: 1 | J68: =SUM((H68-M68)*I68)+M68 -> 540025.67 | K68: 29/28 | L68: DIRECT/DMANDS | M68: ='[10]II-B-5 Depreciation'!M66+'[9]II-B-5 Depreciation'!M68 -> 430.02691 | N68: ='[10]II-B-5 Depreciation'!N66+'[9]II-B-5 Depreciation'!N68 -> 522166.4 | O68: ='[10]II-B-5 Depreciation'!O66+'[9]II-B-5 Depreciation'!O68 -> 17416.057 | P68: ='[10]II-B-5 Depreciation'!P66+'[9]II-B-5 Depreciation'!P68 -> 13.184903 | Q68: =+SUM(M68:P68) -> 540025.67
A69: =+A68+1 -> 53 | B69: A394 | C69: Tools, Shop & Garage Equip. | E69: ='[10]II-B-5 Depreciation'!E67+'[9]II-B-5 Depreciation'!E69 -> 12772512 | F69: ='[10]II-B-5 Depreciation'!F67+'[9]II-B-5 Depreciation'!F69 -> 45542.07 | G69: ='[10]II-B-5 Depreciation'!G67+'[9]II-B-5 Depreciation'!G69 -> -208348.53 | H69: =+E69-F69+G69 -> 12518621 | I69: 1 | J69: =SUM((H69-M69)*I69)+M69 -> 12518621 | K69: 29/16 | L69: DIRECT/DPLTXGNL-N | M69: ='[10]II-B-5 Depreciation'!M67+'[9]II-B-5 Depreciation'!M69 -> 4788282.4 | N69: ='[10]II-B-5 Depreciation'!N67+'[9]II-B-5 Depreciation'!N69 -> 7496590.9 | O69: ='[10]II-B-5 Depreciation'!O67+'[9]II-B-5 Depreciation'!O69 -> 233738.66 | P69: ='[10]II-B-5 Depreciation'!P67+'[9]II-B-5 Depreciation'!P69 -> 9.2241705 | Q69: =+SUM(M69:P69) -> 12518621
A70: =+A69+1 -> 54 | B70: A395 | C70: Laboratory Equipment | E70: ='[10]II-B-5 Depreciation'!E68+'[9]II-B-5 Depreciation'!E70 -> 1931462 | F70: ='[10]II-B-5 Depreciation'!F68+'[9]II-B-5 Depreciation'!F70 -> 1916439.8 | G70: ='[10]II-B-5 Depreciation'!G68+'[9]II-B-5 Depreciation'!G70 -> -128.23521 | H70: =+E70-F70+G70 -> 14893.945 | I70: 1 | J70: =SUM((H70-M70)*I70)+M70 -> 14893.945 | K70: 29/16 | L70: DIRECT/DPLTXGNL-N | M70: ='[10]II-B-5 Depreciation'!M68+'[9]II-B-5 Depreciation'!M70 -> 1440.1066 | N70: ='[10]II-B-5 Depreciation'!N68+'[9]II-B-5 Depreciation'!N70 -> 13061.628 | O70: ='[10]II-B-5 Depreciation'!O68+'[9]II-B-5 Depreciation'!O70 -> 392.21014 | P70: ='[10]II-B-5 Depreciation'!P68+'[9]II-B-5 Depreciation'!P70 -> 0 | Q70: =+SUM(M70:P70) -> 14893.945
A71: =+A70+1 -> 55 | B71: A396 | C71: Power Operated Equipment | E71: ='[10]II-B-5 Depreciation'!E69+'[9]II-B-5 Depreciation'!E71 -> 17310.25 | F71: ='[10]II-B-5 Depreciation'!F69+'[9]II-B-5 Depreciation'!F71 -> 17434.65 | G71: ='[10]II-B-5 Depreciation'!G69+'[9]II-B-5 Depreciation'!G71 -> 0.94643768 | H71: =+E71-F71+G71 -> -123.45356 | I71: 1 | J71: =SUM((H71-M71)*I71)+M71 -> -123.45356 | K71: 29/16 | L71: DIRECT/DPLTXGNL-N | M71: ='[10]II-B-5 Depreciation'!M69+'[9]II-B-5 Depreciation'!M71 -> 0 | N71: ='[10]II-B-5 Depreciation'!N69+'[9]II-B-5 Depreciation'!N71 -> -119.85461 | O71: ='[10]II-B-5 Depreciation'!O69+'[9]II-B-5 Depreciation'!O71 -> -3.5989536 | P71: ='[10]II-B-5 Depreciation'!P69+'[9]II-B-5 Depreciation'!P71 -> 0 | Q71: =+SUM(M71:P71) -> -123.45356
A72: =+A71+1 -> 56 | C72: Subtotal | E72: =SUM(E63:E71) -> 71910763 | F72: =SUM(F63:F71) -> 2174139.1 | G72: =SUM(G63:G71) -> -589928.26 | H72: =SUM(H63:H71) -> 69146695 | J72: =SUM(J63:J71) -> 69146695 | M72: =SUM(M63:M71) -> 5560978.2 | N72: =SUM(N63:N71) -> 61266534 | O72: =SUM(O63:O71) -> 1730301.9 | P72: =SUM(P63:P71) -> 588881.49 | Q72: =SUM(Q63:Q71) -> 69146695
A73: =+A72+1 -> 57
A74: =+A73+1 -> 58 | B74: A397 | C74: Communication Equipment | E74: ='[10]II-B-5 Depreciation'!E72+'[9]II-B-5 Depreciation'!E74 -> 66079661 | F74: ='[10]II-B-5 Depreciation'!F72+'[9]II-B-5 Depreciation'!F74 -> 204596.86 | G74: ='[10]II-B-5 Depreciation'!G72+'[9]II-B-5 Depreciation'!G74 -> -394776.32 | H74: =+E74-F74+G74 -> 65480288 | I74: 1 | J74: =SUM((H74-M74)*I74)+M74 -> 65480288 | K74: 29/16 | L74: DIRECT/DPLTXGNL-N | M74: ='[10]II-B-5 Depreciation'!M72+'[9]II-B-5 Depreciation'!M74 -> 8883451.2 | N74: ='[10]II-B-5 Depreciation'!N72+'[9]II-B-5 Depreciation'!N74 -> 54854333 | O74: ='[10]II-B-5 Depreciation'!O72+'[9]II-B-5 Depreciation'!O74 -> 1742401.9 | P74: ='[10]II-B-5 Depreciation'!P72+'[9]II-B-5 Depreciation'!P74 -> 101.77074 | Q74: =+SUM(M74:P74) -> 65480288
A75: =+A74+1 -> 59 | B75: A398 | C75: Misc. Equipment | E75: ='[10]II-B-5 Depreciation'!E73+'[9]II-B-5 Depreciation'!E75 -> 3271773.7 | F75: ='[10]II-B-5 Depreciation'!F73+'[9]II-B-5 Depreciation'!F75 -> 51787.88 | G75: ='[10]II-B-5 Depreciation'!G73+'[9]II-B-5 Depreciation'!G75 -> -26755.826 | H75: =+E75-F75+G75 -> 3193230 | I75: 1 | J75: =SUM((H75-M75)*I75)+M75 -> 3193230 | K75: 29/16 | L75: DIRECT/DPLTXGNL-N | M75: ='[10]II-B-5 Depreciation'!M73+'[9]II-B-5 Depreciation'!M75 -> 344411.23 | N75: ='[10]II-B-5 Depreciation'!N73+'[9]II-B-5 Depreciation'!N75 -> 2761213.6 | O75: ='[10]II-B-5 Depreciation'!O73+'[9]II-B-5 Depreciation'!O75 -> 87600.18 | P75: ='[10]II-B-5 Depreciation'!P73+'[9]II-B-5 Depreciation'!P75 -> 5.0080469 | Q75: =+SUM(M75:P75) -> 3193230
A76: =+A75+1 -> 60 | B76: A399 | C76: Other Tangible-Deprc. | H76: =+E76-F76+G76 -> 0 | J76: =SUM((H76-M76)*I76)+M76 -> 0 | Q76: =+SUM(M76:P76) -> 0
A77: =+A76+1 -> 61 | B77: A399 | C77: Other Tangible-Deprc. Asset Retirement Obligation | E77: ='[10]II-B-5 Depreciation'!E74+'[9]II-B-5 Depreciation'!E77 -> 1026156.2 | F77: ='[10]II-B-5 Depreciation'!F74+'[9]II-B-5 Depreciation'!F77 -> 0 | G77: ='[10]II-B-5 Depreciation'!G74+'[9]II-B-5 Depreciation'!G77 -> 0 | H77: =+E77-F77+G77 -> 1026156.2 | I77: 1 | J77: =SUM((H77-M77)*I77)+M77 -> 1026156.2 | K77: 29/16 | L77: DIRECT/DPLTXGNL-N | M77: ='[10]II-B-5 Depreciation'!M74+'[9]II-B-5 Depreciation'!M77 -> 0 | N77: ='[10]II-B-5 Depreciation'!N74+'[9]II-B-5 Depreciation'!N77 -> 994620.14 | O77: ='[10]II-B-5 Depreciation'!O74+'[9]II-B-5 Depreciation'!O77 -> 31534.227 | P77: ='[10]II-B-5 Depreciation'!P74+'[9]II-B-5 Depreciation'!P77 -> 1.7822211 | Q77: =+SUM(M77:P77) -> 1026156.2
A78: =+A77+1 -> 62 | C78: Subtotal | E78: =SUM(E74:E77) -> 70377591 | F78: =SUM(F74:F77) -> 256384.74 | G78: =SUM(G74:G77) -> -421532.15 | H78: =SUM(H74:H77) -> 69699674 | J78: =SUM(J74:J77) -> 69699674 | M78: =SUM(M74:M77) -> 9227862.4 | N78: =SUM(N74:N77) -> 58610167 | O78: =SUM(O74:O77) -> 1861536.3 | P78: =SUM(P74:P77) -> 108.56101 | Q78: =SUM(Q74:Q77) -> 69699674
A79: =+A78+1 -> 63
A80: =+A79+1 -> 64 | B80: TOTAL ACCUM. DEP. FOR GENERAL PLANT | D80: II-B-5 | E80: =E72+E78 -> 1.4228835e+08 | F80: =F72+F78 -> 2430523.8 | G80: =G72+G78 -> -1011460.4 | H80: =H72+H78 -> 1.3884637e+08 | J80: =J72+J78 -> 1.3884637e+08 | M80: =M72+M78 -> 14788841 | N80: =N72+N78 -> 1.198767e+08 | O80: =O72+O78 -> 3591838.2 | P80: =P72+P78 -> 588990.05 | Q80: =Q72+Q78 -> 1.3884637e+08
A81: =+A80+1 -> 65 | B81: TOTAL GENERAL PLANT-NET | D81: II-B-2-3 - II-B-5 | E81: =+'II-B-2 General Plant'!E31+'II-B-3 Comm. Equip.'!E17-'II-B-5 Depreciation'!E80 -> 3.9787133e+08 | F81: =+'II-B-2 General Plant'!F31+'II-B-3 Comm. Equip.'!F17-'II-B-5 Depreciation'!F80 -> 104543.05 | G81: =+'II-B-2 General Plant'!G31+'II-B-3 Comm. Equip.'!G17-'II-B-5 Depreciation'!G80 -> 344164.02 | H81: =+'II-B-2 General Plant'!H31+'II-B-3 Comm. Equip.'!H17-'II-B-5 Depreciation'!H80 -> 3.9811095e+08 | J81: =+'II-B-2 General Plant'!J31+'II-B-3 Comm. Equip.'!J17-'II-B-5 Depreciation'!J80 -> 3.9811095e+08 | M81: =+'II-B-2 General Plant'!M31+'II-B-3 Comm. Equip.'!M17-'II-B-5 Depreciation'!M80 -> 1.4004474e+08 | N81: =+'II-B-2 General Plant'!N31+'II-B-3 Comm. Equip.'!N17-'II-B-5 Depreciation'!N80 -> 2.3346591e+08 | O81: =+'II-B-2 General Plant'!O31+'II-B-3 Comm. Equip.'!O17-'II-B-5 Depreciation'!O80 -> 22375201 | P81: =+'II-B-2 General Plant'!P31+'II-B-3 Comm. Equip.'!P17-'II-B-5 Depreciation'!P80 -> 2225103.8 | Q81: =+'II-B-2 General Plant'!Q31+'II-B-3 Comm. Equip.'!Q17-'II-B-5 Depreciation'!Q80 -> 3.9811095e+08
A82: =+A81+1 -> 66
A83: =+A82+1 -> 67 | B83: TOTAL PLANT IN SERVICE NET (INCL. INTANGIBLES) | D83: II-B-1-3 - II-B-5 | E83: =+'II-B-1 Plant'!E51+'II-B-2 General Plant'!E31+'II-B-3 Comm. Equip.'!E17-'II-B-5 Depreciation'!E53-'II-B-5 Depreciation'!E80 -> 6.3113414e+09 | F83: =+'II-B-1 Plant'!F51+'II-B-2 General Plant'!F31+'II-B-3 Comm. Equip.'!F17-'II-B-5 Depreciation'!F53-'II-B-5 Depreciation'!F80 -> 178098.1 | G83: =+'II-B-1 Plant'!G51+'II-B-2 General Plant'!G31+'II-B-3 Comm. Equip.'!G17-'II-B-5 Depreciation'!G53-'II-B-5 Depreciation'!G80 -> -71096917 | H83: =+'II-B-1 Plant'!H51+'II-B-2 General Plant'!H31+'II-B-3 Comm. Equip.'!H17-'II-B-5 Depreciation'!H53-'II-B-5 Depreciation'!H80 -> 6.2400664e+09 | J83: =+'II-B-1 Plant'!J51+'II-B-2 General Plant'!J31+'II-B-3 Comm. Equip.'!J17-'II-B-5 Depreciation'!J53-'II-B-5 Depreciation'!J80 -> 6.2400664e+09 | M83: =+'II-B-1 Plant'!M51+'II-B-2 General Plant'!M31+'II-B-3 Comm. Equip.'!M17-'II-B-5 Depreciation'!M53-'II-B-5 Depreciation'!M80 -> 3.2777317e+09 | N83: =+'II-B-1 Plant'!N51+'II-B-2 General Plant'!N31+'II-B-3 Comm. Equip.'!N17-'II-B-5 Depreciation'!N53-'II-B-5 Depreciation'!N80 -> 2.8564608e+09 | O83: =+'II-B-1 Plant'!O51+'II-B-2 General Plant'!O31+'II-B-3 Comm. Equip.'!O17-'II-B-5 Depreciation'!O53-'II-B-5 Depreciation'!O80 -> 1.0364617e+08 | P83: =+'II-B-1 Plant'!P51+'II-B-2 General Plant'!P31+'II-B-3 Comm. Equip.'!P17-'II-B-5 Depreciation'!P53-'II-B-5 Depreciation'!P80 -> 2227784 | Q83: =+'II-B-1 Plant'!Q51+'II-B-2 General Plant'!Q31+'II-B-3 Comm. Equip.'!Q17-'II-B-5 Depreciation'!Q53-'II-B-5 Depreciation'!Q80 -> 6.2400664e+09
A84: =+A83+1 -> 68
A85: =+A84+1 -> 69 | B85: TOTAL PLANT IN SERVICE NET (EXCL. INTANGIBLES) | D85: II-B-1-3 - II-B-5 | E85: =+'II-B-1 Plant'!E52+'II-B-2 General Plant'!E31+'II-B-3 Comm. Equip.'!E17-'II-B-5 Depreciation'!E54-'II-B-5 Depreciation'!E80 -> 6.233132e+09 | F85: =+'II-B-1 Plant'!F52+'II-B-2 General Plant'!F31+'II-B-3 Comm. Equip.'!F17-'II-B-5 Depreciation'!F54-'II-B-5 Depreciation'!F80 -> 174801.42 | G85: =+'II-B-1 Plant'!G52+'II-B-2 General Plant'!G31+'II-B-3 Comm. Equip.'!G17-'II-B-5 Depreciation'!G54-'II-B-5 Depreciation'!G80 -> -71096917 | H85: =+'II-B-1 Plant'!H52+'II-B-2 General Plant'!H31+'II-B-3 Comm. Equip.'!H17-'II-B-5 Depreciation'!H54-'II-B-5 Depreciation'!H80 -> 6.1618603e+09 | J85: =+'II-B-1 Plant'!J52+'II-B-2 General Plant'!J31+'II-B-3 Comm. Equip.'!J17-'II-B-5 Depreciation'!J54-'II-B-5 Depreciation'!J80 -> 6.1618603e+09 | M85: =+'II-B-1 Plant'!M52+'II-B-2 General Plant'!M31+'II-B-3 Comm. Equip.'!M17-'II-B-5 Depreciation'!M54-'II-B-5 Depreciation'!M80 -> 3.2544999e+09 | N85: =+'II-B-1 Plant'!N52+'II-B-2 General Plant'!N31+'II-B-3 Comm. Equip.'!N17-'II-B-5 Depreciation'!N54-'II-B-5 Depreciation'!N80 -> 2.8033824e+09 | O85: =+'II-B-1 Plant'!O52+'II-B-2 General Plant'!O31+'II-B-3 Comm. Equip.'!O17-'II-B-5 Depreciation'!O54-'II-B-5 Depreciation'!O80 -> 1.0175292e+08 | P85: =+'II-B-1 Plant'!P52+'II-B-2 General Plant'!P31+'II-B-3 Comm. Equip.'!P17-'II-B-5 Depreciation'!P54-'II-B-5 Depreciation'!P80 -> 2225103.8 | Q85: =+'II-B-1 Plant'!Q52+'II-B-2 General Plant'!Q31+'II-B-3 Comm. Equip.'!Q17-'II-B-5 Depreciation'!Q54-'II-B-5 Depreciation'!Q80 -> 6.1618603e+09
E88: =E53+E80-F53-F80 -> 2.0915659e+09
E90: =E83-F83 -> 6.3111633e+09

Sheet II-B-6 Plant Future
P1: Schedule II-B-6
B2: PUBLIC UTILITY COMMISSION OF TEXAS
B3: AEP TEXAS INC
B4: II-B-6 PLANT HELD FOR FUTURE USE
B5: ='I-A'!B5 -> TEST YEAR ENDING 12/31/2018
B6: ='I-A'!B6
E8: 1 | F8: 2 | G8: 3 | H8: 4 | I8: 5 | J8: 6 | K8: 7 | L8: 8 | M8: 9 | N8: 10 | O8: 11 | P8: 12
H9: Company
B10: Account | C10: Description | D10: Reference | E10: Total | F10: Non-Regulated or | G10: Known | H10: Total | I10: FF | J10: Functionalization | K10: Allocation to | L10: TRAN | M10: DIST | N10: MET | O10: TDCS | P10: Total
A11: Line | B11: Number | D11: Schedule | E11: Company | F11: Non-Electric | G11: Change | H11: Electric | I11: # | J11: Factor | K11: Texas | Q11: CHECK
A12: No. | J12: Name
A14: 1 | B14: Other Rate Base Items
A15: =+A14+1 -> 2
A16: =+A15+1 -> 3 | B16: A105 | C16: Plant Held for Future Use | D16: II-B-6 | E16: ='[9]II-B-6 Plant Future'!E16+'[10]II-B-6 Plant Held For Future'!E16 -> 4941591.7 | F16: ='[9]II-B-6 Plant Future'!F16+'[10]II-B-6 Plant Held For Future'!F16 -> 0 | G16: ='[9]II-B-6 Plant Future'!G16+'[10]II-B-6 Plant Held For Future'!G16 -> -1809575.7 | H16: =SUM(E16:G16) -> 3132016 | I16: 29 | J16: DIRECT | K16: =H16 -> 3132016 | L16: ='[9]II-B-6 Plant Future'!L16+'[10]II-B-6 Plant Held For Future'!L16 -> 0 | M16: ='[9]II-B-6 Plant Future'!M16+'[10]II-B-6 Plant Held For Future'!M16 -> 3132016 | N16: ='[9]II-B-6 Plant Future'!N16+'[10]II-B-6 Plant Held For Future'!N16 -> 0 | O16: ='[9]II-B-6 Plant Future'!O16+'[10]II-B-6 Plant Held For Future'!O16 -> 0 | P16: =SUM(L16:O16) -> 3132016
A17: =+A16+1 -> 4 | C17: Subtotal | E17: =SUM(E16) -> 4941591.7 | G17: =+G16 -> -1809575.7 | H17: =+H16 -> 3132016 | K17: =+K16 -> 3132016 | M17: =+M16 -> 3132016 | P17: =+P16 -> 3132016
A18: =+A17+1 -> 5
A19: =+A18+1 -> 6 | B19: TOTAL PLANT HELD FOR FUTURE USE | D19: II-B-6 | E19: =+E17 -> 4941591.7 | G19: =+G17 -> -1809575.7 | H19: =+H17 -> 3132016 | K19: =+K17 -> 3132016 | M19: =+M17 -> 3132016 | P19: =+P17 -> 3132016
A20: =+A19+1 -> 7
A21: =+A20+1 -> 8 | C21: *AEP Texas maintains functional ledgers for transmission and distribution. Please see the testimony of Randall W. Hamlett for Meter and TDCS functionalization.

Sheet II-B-7 Accum. Provisions
B2: PUBLIC UTILITY COMMISSION OF TEXAS
B3: AEP TEXAS INC
B4: II-B-7 ACCUMULATED PROVISION BALANCES
B5: ='I-A'!B5 -> TEST YEAR ENDING 12/31/2018
B6: ='I-A'!B6
E8: 1 | F8: 2 | G8: 3 | H8: 4 | I8: 5 | J8: 6 | K8: 7 | L8: 8 | M8: 9 | N8: 10 | O8: 11 | P8: 12 | Q8: 13
H9: Company | I9: Texas
B10: Account | C10: Description | D10: Reference | E10: Total | F10: Non-Regulated or | G10: Known | H10: Total | I10: Retail | J10: Allocation to | K10: FF | L10: Funct | M10: TRAN | N10: DIST | O10: MET | P10: TDCS | Q10: Total
A11: Line | B11: Number | D11: Schedule | E11: Company | F11: Non-Electric | G11: Change | H11: Electric | I11: Allocation | J11: Texas | K11: # | L11: Factor | R11: CHECK
A12: No. | I12: Factor | L12: Name
A14: 1 | B14: Other Rate Base Items
A15: =+A14+1 -> 2 | B15: 2300001 | C15: Asset Retirement Obligations | E15: ='[10]II-B-7 Accum. Provisions'!E17+'[9]II-B-7 Accum. Provisions'!E15 -> -27348667 | F15: ='[10]II-B-7 Accum. Provisions'!F17+'[9]II-B-7 Accum. Provisions'!F15 -> -23706536 | G15: ='[10]II-B-7 Accum. Provisions'!G17+'[9]II-B-7 Accum. Provisions'!G15 -> 0 | H15: =+E15-F15+G15 -> -3642131.3 | I15: 1 | J15: =+H15*I15 -> -3642131.3 | K15: 29 | L15: DIRECT | M15: ='[10]II-B-7 Accum. Provisions'!M17+'[9]II-B-7 Accum. Provisions'!M15 -> 0 | N15: ='[10]II-B-7 Accum. Provisions'!N17+'[9]II-B-7 Accum. Provisions'!N15 -> -3642131.3 | O15: ='[10]II-B-7 Accum. Provisions'!O17+'[9]II-B-7 Accum. Provisions'!O15 -> 0 | P15: ='[10]II-B-7 Accum. Provisions'!P17+'[9]II-B-7 Accum. Provisions'!P15 -> 0 | Q15: =SUM(M15:P15) -> -3642131.3
A16: =+A15+1 -> 3 | B16: 2350001 | C16: Customer Deposits | E16: ='[10]II-B-7 Accum. Provisions'!E16+'[9]II-B-7 Accum. Provisions'!E16 -> -20000 | F16: ='[10]II-B-7 Accum. Provisions'!F16+'[9]II-B-7 Accum. Provisions'!F16 -> 0 | G16: ='[10]II-B-7 Accum. Provisions'!G16+'[9]II-B-7 Accum. Provisions'!G16 -> 0 | H16: =+E16-F16+G16 -> -20000 | I16: 1 | J16: =+H16*I16 -> -20000 | K16: 29 | L16: DIRECT | M16: ='[10]II-B-7 Accum. Provisions'!M16+'[9]II-B-7 Accum. Provisions'!M16 -> 0 | N16: ='[10]II-B-7 Accum. Provisions'!N16+'[9]II-B-7 Accum. Provisions'!N16 -> -20000 | O16: ='[10]II-B-7 Accum. Provisions'!O16+'[9]II-B-7 Accum. Provisions'!O16 -> 0 | P16: ='[10]II-B-7 Accum. Provisions'!P16+'[9]II-B-7 Accum. Provisions'!P16 -> 0 | Q16: =SUM(M16:P16) -> -20000
A17: =+A16+1 -> 4 | B17: 2281001 | C17: Reserve for Catastrophe | E17: ='[9]II-B-7 Accum. Provisions'!E17 -> 0 | F17: ='[9]II-B-7 Accum. Provisions'!F17 -> 0 | G17: ='[9]II-B-7 Accum. Provisions'!G17 -> 0 | H17: =+E17-F17+G17 -> 0 | I17: 1 | J17: =SUM((H17-M17)*I17)+M17 -> 0 | K17: * | L17: * | M17: ='[9]II-B-7 Accum. Provisions'!M17 -> 0 | N17: ='[9]II-B-7 Accum. Provisions'!N17 -> 0 | O17: ='[9]II-B-7 Accum. Provisions'!O17 -> 0 | P17: ='[9]II-B-7 Accum. Provisions'!P17 -> 0 | Q17: =SUM(M17:P17) -> 0
A18: =+A17+1 -> 5 | B18: 2520000 | C18: Customers Advances for Construction | E18: ='[10]II-B-7 Accum. Provisions'!E18+'[9]II-B-7 Accum. Provisions'!E18 -> 0 | F18: ='[10]II-B-7 Accum. Provisions'!F18+'[9]II-B-7 Accum. Provisions'!F18 -> 0 | G18: ='[10]II-B-7 Accum. Provisions'!G18+'[9]II-B-7 Accum. Provisions'!G18 -> 0 | H18: =+E18-F18+G18 -> 0 | I18: 1 | J18: =SUM((H18-M18)*I18)+M18 -> 0 | K18: * | L18: * | M18: ='[10]II-B-7 Accum. Provisions'!M18+'[9]II-B-7 Accum. Provisions'!M18 -> 0 | N18: ='[10]II-B-7 Accum. Provisions'!N18+'[9]II-B-7 Accum. Provisions'!N18 -> 0 | O18: ='[10]II-B-7 Accum. Provisions'!O18+'[9]II-B-7 Accum. Provisions'!O18 -> 0 | P18: ='[10]II-B-7 Accum. Provisions'!P18+'[9]II-B-7 Accum. Provisions'!P18 -> 0 | Q18: =SUM(M18:P18) -> 0
A19: =+A18+1 -> 6 | C19: Subtotal | E19: =SUM(E15:E18) -> -27368667 | F19: =SUM(F15:F18) -> -23706536 | G19: =SUM(G15:G18) -> 0 | H19: =SUM(H15:H18) -> -3662131.3 | J19: =SUM(J15:J18) -> -3662131.3 | M19: =SUM(M15:M18) -> 0 | N19: =SUM(N15:N18) -> -3662131.3 | O19: =SUM(O15:O18) -> 0 | P19: =SUM(P15:P18) -> 0 | Q19: =SUM(Q15:Q18) -> -3662131.3
A20: =+A19+1 -> 7
A21: =+A20+1 -> 8 | B21: Accumulated Deferred Income Taxes | D21: II-E-3.5 | E21: =+'II-E-3.5 ADFIT'!F126 -> -9.1695015e+08 | F21: =+'II-E-3.5 ADFIT'!G126 -> -1.3447638e+08 | G21: =+'II-E-3.5 ADFIT'!H126 -> 6380846.9 | H21: =+E21-F21+G21 -> -7.7609292e+08 | I21: 1 | J21: =SUM((H21-M21)*I21)+M21 -> -7.7609292e+08 | K21: * | L21: * | M21: =+'II-E-3.5 ADFIT'!N126 -> -3.5551501e+08 | N21: =+'II-E-3.5 ADFIT'!O126 -> -3.9005788e+08 | O21: =+'II-E-3.5 ADFIT'!P126 -> -26771625 | P21: =+'II-E-3.5 ADFIT'!Q126 -> -3748404.2 | Q21: =SUM(M21:P21) -> -7.7609292e+08
A22: =+A21+1 -> 9
A23: =+A22+1 -> 10 | B23: TOTAL ACCUMULATED PROVISIONS | D23: II-B-7 | E23: =+E21+E19 -> -9.4431881e+08 | F23: =+F21+F19 -> -1.5818291e+08 | G23: =+G21+G19 -> 6380846.9 | H23: =+H21+H19 -> -7.7975505e+08 | J23: =+J21+J19 -> -7.7975505e+08 | M23: =+M21+M19 -> -3.5551501e+08 | N23: =+N21+N19 -> -3.9372002e+08 | O23: =+O21+O19 -> -26771625 | P23: =+P21+P19 -> -3748404.2 | Q23: =+Q21+Q19 -> -7.7975505e+08
E26: =E21-F21 -> -7.8247377e+08

Sheet II-B-8 M&S
B2: PUBLIC UTILITY COMMISSION OF TEXAS
B3: AEP TEXAS INC
B4: II-B-8 MATERIALS AND SUPPLIES
B5: TEST YEAR ENDING 12/31/2018
B6: ='I-A'!B6
E8: 1 | F8: 2 | G8: 3 | H8: 4 | I8: 5 | J8: 6 | K8: 7 | L8: 8 | M8: 9 | N8: 10 | O8: 11 | P8: 12 | Q8: 13
H9: Company | I9: Texas
B10: Account | C10: Description | D10: Reference | E10: Total | F10: Non-Regulated or | G10: Known | H10: Total | I10: Retail | J10: Allocation to | K10: FF | L10: Funct | M10: TRAN | N10: DIST | O10: MET | P10: TDCS | Q10: Total
A11: Line | B11: Number | D11: Schedule | E11: Company | F11: Non-Electric | G11: Change | H11: Electric | I11: Allocation | J11: Texas | K11: # | L11: Factor | R11: CHECK
A12: No. | I12: Factor | L12: Name
A14: 1 | B14: Other Rate Base Items
A15: =+A14+1 -> 2 | B15: Working Capital
A16: =+A15+1 -> 3 | C16: Materials and Supplies
A17: =+A16+1 -> 4 | B17: 154 | C17: Material and Supplies | E17: ='[10]II-B-8 M&S'!E17+'[9]II-B-8 M&S'!E17 -> 52796335 | F17: ='[10]II-B-8 M&S'!F17+'[9]II-B-8 M&S'!F17 -> 3875783.2 | G17: ='[10]II-B-8 M&S'!G17+'[9]II-B-8 M&S'!G17 -> -1642649.5 | H17: =+E17-F17+G17 -> 47277903 | I17: 1 | J17: =SUM((H17-M17)*I17)+M17 -> 47277903 | K17: 29/20 | L17: DIRECT/DPLTSVC-NX | M17: ='[10]II-B-8 M&S'!M17+'[9]II-B-8 M&S'!M17 -> 15176994 | N17: ='[10]II-B-8 M&S'!N17+'[9]II-B-8 M&S'!N17 -> 31038229 | O17: ='[10]II-B-8 M&S'!O17+'[9]II-B-8 M&S'!O17 -> 1061695 | P17: ='[10]II-B-8 M&S'!P17+'[9]II-B-8 M&S'!P17 -> 984.63864 | Q17: =SUM(M17:P17) -> 47277903
A18: =+A17+1 -> 5 | B18: 163 | C18: Undistributed M&S Expenses | H18: =+E18-F18+G18 -> 0 | I18: 0 | J18: =SUM((H18-M18)*I18)+M18 -> 0 | K18: 29/20 | L18: DIRECT/DPLTSVC-NX | Q18: =SUM(M18:P18) -> 0
A19: =+A18+1 -> 6 | C19: Subtotal | E19: =SUM(E17:E18) -> 52796335 | F19: =SUM(F17:F18) -> 3875783.2 | G19: =SUM(G17:G18) -> -1642649.5 | H19: =SUM(H17:H18) -> 47277903 | J19: =SUM(J17:J18) -> 47277903 | M19: =SUM(M17:M18) -> 15176994 | N19: =SUM(N17:N18) -> 31038229 | O19: =SUM(O17:O18) -> 1061695 | P19: =SUM(P17:P18) -> 984.63864 | Q19: =SUM(Q17:Q18) -> 47277903
A20: =+A19+1 -> 7
A21: =+A20+1 -> 8 | B21: TOTAL MATERIALS & SUPPLIES | D21: II-B-8 | E21: =SUM(E19) -> 52796335 | F21: =SUM(F19) -> 3875783.2 | G21: =SUM(G19) -> -1642649.5 | H21: =SUM(H19) -> 47277903 | J21: =SUM(J19) -> 47277903 | M21: =SUM(M19) -> 15176994 | N21: =SUM(N19) -> 31038229 | O21: =SUM(O19) -> 1061695 | P21: =SUM(P19) -> 984.63864 | Q21: =SUM(Q19) -> 47277903
E24: =E21-F21 -> 48920552

Sheet II-B-8 MONTHLY
Q1: SCHEDULE II-B-8
B2: PUBLIC UTILITY COMMISSION OF TEXAS | Q2: MONTHLY
B3: AEP TEXAS INC
B4: II-B-8 RATE BASE ACC. - MATERIALS & SUPPLIES
B5: TEST YEAR ENDING 12/31/2018
E8: 1 | F8: 2 | G8: 3 | H8: 4 | I8: 5 | J8: 6 | K8: 7 | L8: 8 | M8: 9 | N8: 10 | O8: 11 | P8: 12 | Q8: 13
H9: Company | I9: Texas
B10: Account | C10: Description | D10: Reference | E10: Total | F10: Non-Regulated or | G10: Known | H10: Total | I10: Retail | J10: Allocation to | K10: FF | L10: Funct | M10: TRAN | N10: DIST | O10: MET | P10: TDCS | Q10: Total
A11: Line | B11: Number | D11: Schedule | E11: Company | F11: Non-Electric | G11: Change | H11: Electric | I11: Allocation | J11: Texas | K11: # | L11: Factor
A12: No. | I12: Factor | L12: Name
A14: 1
A15: =+A14+1 -> 2
A16: =+A15+1 -> 3 | C16: This Schedule of monthly information is not provided on a combined basis. Please see the Central Division Schedules and North Divisions Schedules.
A17: =+A16+1 -> 4
A18: =+A17+1 -> 5
A19: =+A18+1 -> 6
A20: =+A19+1 -> 7
A21: =+A20+1 -> 8 | B21: TOTAL MATERIALS & SUPPLIES | D21: II-B-8

Sheet II-B-9 CWCapital
B2: PUBLIC UTILITY COMMISSION OF TEXAS
B3: AEP TEXAS INC
B4: II-B-9 CASH WORKING CAPITAL
B5: TEST YEAR ENDING 12/31/2018
B6: ='I-A'!B6
E8: 1 | F8: 2 | G8: 3 | H8: 4 | I8: 5 | J8: 6 | K8: 7 | L8: 8 | M8: 9 | N8: 10 | O8: 11 | P8: 12 | Q8: 13
H9: Company | I9: Texas
B10: Account | C10: Description | D10: Reference | E10: Total | F10: Non-Regulated or | G10: Known | H10: Total | I10: Retail | J10: Allocation to | K10: FF | L10: Funct | M10: TRAN | N10: DIST | O10: MET | P10: TDCS | Q10: Total
A11: Line | B11: Number | D11: Schedule | E11: Company | F11: Non-Electric | G11: Change | H11: Electric | I11: Allocation | J11: Texas | K11: # | L11: Factor | R11: CHECK
A12: No. | I12: Factor | L12: Name
A14: 1
A15: =+A14+1 -> 2
A16: =+A15+1 -> 3
A17: =+A16+1 -> 4
A18: =+A17+1 -> 5
A19: =+A18+1 -> 6 | C19: Other Rate Base Items
A20: =+A19+1 -> 7 | C20: Working Capital
A21: =+A20+1 -> 8 | C21: Cash Working Capital | D21: II-B-9 | E21: ='[10]II-B-9 CWCapital'!E16+'[9]II-B-9 CWCapital'!E21 -> 0 | F21: ='[10]II-B-9 CWCapital'!F16+'[9]II-B-9 CWCapital'!F21 -> 0 | G21: ='[10]II-B-9 CWCapital'!G16+'[9]II-B-9 CWCapital'!G21 -> -22940282 | H21: ='[10]II-B-9 CWCapital'!H16+'[9]II-B-9 CWCapital'!H21 -> -22940282 | J21: =H21 -> -22940282 | K21: 29/8 | L21: DIRECT/DISTOPX | M21: ='[10]II-B-9 CWCapital'!M16+'[9]II-B-9 CWCapital'!M21 -> -16030645 | N21: ='[10]II-B-9 CWCapital'!N16+'[9]II-B-9 CWCapital'!N21 -> -5222388.9 | O21: ='[10]II-B-9 CWCapital'!O16+'[9]II-B-9 CWCapital'!O21 -> -1687248.9 | P21: ='[10]II-B-9 CWCapital'!P16+'[9]II-B-9 CWCapital'!P21 -> 0 | Q21: =SUM(M21:P21) -> -22940282
A22: =+A21+1 -> 9
A23: =+A22+1 -> 10 | C23: Subtotal
A24: =+A23+1 -> 11
A25: =+A24+1 -> 12 | B25: TOTAL CASH WORKING CAPITAL | D25: II-B-9 | E25: =SUM(E21:E24) -> 0 | F25: =SUM(F21:F24) -> 0 | G25: =SUM(G21:G24) -> -22940282 | H25: =SUM(H21:H24) -> -22940282 | J25: =SUM(J21:J24) -> -22940282 | M25: =SUM(M21:M24) -> -16030645 | N25: =SUM(N21:N24) -> -5222388.9 | O25: =SUM(O21:O24) -> -1687248.9 | P25: =SUM(P21:P24) -> 0 | Q25: =SUM(Q21:Q24) -> -22940282
A26: =+A25+1 -> 13
A27: =+A26+1 -> 14 | B27: TOTAL WORKING CAPITAL | D27: II-B-8-9 | E27: =E25 -> 0 | F27: =F25 -> 0 | G27: =G25 -> -22940282 | H27: =H25 -> -22940282 | J27: =J25 -> -22940282 | M27: =M25 -> -16030645 | N27: =N25 -> -5222388.9 | O27: =O25 -> -1687248.9 | P27: =P25 -> 0 | Q27: =Q25 -> -22940282

Sheet II-B-10 Prepayments
B2: PUBLIC UTILITY COMMISSION OF TEXAS
B3: AEP TEXAS INC
B4: II-B-10 PREPAYMENTS
B5: ='II-B'!B5 -> TEST YEAR ENDING 12/31/2018
B6: ='I-A'!B6
E8: 1 | F8: 2 | G8: 3 | H8: 4 | I8: 5 | J8: 6 | K8: 7 | L8: 8 | M8: 9 | N8: 10 | O8: 11 | P8: 12 | Q8: 13
H9: Company | I9: Texas
B10: Account | C10: Description | D10: Reference | E10: Total | F10: Non-Regulated or | G10: Known | H10: Total | I10: Retail | J10: Allocation to | K10: FF | L10: Funct | M10: TRAN | N10: DIST | O10: MET | P10: TDCS | Q10: Total
A11: Line | B11: Number | D11: Schedule | E11: Company | F11: Non-Electric | G11: Change | H11: Electric | I11: Allocation | J11: Texas | K11: # | L11: Factor | R11: CHECK
A12: No. | I12: Factor | L12: Name
A14: 1 | B14: Other Rate Base Items
A15: =+A14+1 -> 2 | B15: Working Capital
A16: =+A15+1 -> 3 | C16: Prepayments | D16: II-B-10
A17: =+A16+1 -> 4 | B17: 1650001 Prepaid Insurance | E17: ='[10]II-B-10 Prepayments'!E17+'[9]II-B-10 Prepayments'!E17 -> 1175550.3 | F17: ='[10]II-B-10 Prepayments'!F17+'[9]II-B-10 Prepayments'!F17 -> 28569.023 | G17: ='[10]II-B-10 Prepayments'!G17+'[9]II-B-10 Prepayments'!G17 -> -98324.949 | H17: ='[10]II-B-10 Prepayments'!H17+'[9]II-B-10 Prepayments'!H17 -> 1048656.3 | I17: 1 | J17: =SUM((H17-M17)*I17)+M17 -> 1048656.3 | K17: 29/18 | L17: DIRECT/DPLTSVC-N | M17: ='[10]II-B-10 Prepayments'!M17+'[9]II-B-10 Prepayments'!M17 -> 272565.31 | N17: ='[10]II-B-10 Prepayments'!N17+'[9]II-B-10 Prepayments'!N17 -> 748328.87 | O17: ='[10]II-B-10 Prepayments'!O17+'[9]II-B-10 Prepayments'!O17 -> 27179.212 | P17: ='[10]II-B-10 Prepayments'!P17+'[9]II-B-10 Prepayments'!P17 -> 582.93281 | Q17: =SUM(M17:P17) -> 1048656.3
A18: =+A17+1 -> 5 | B18: 1650005 | C18: Prepaid Employee Benefits | E18: ='[10]II-B-10 Prepayments'!E18+'[9]II-B-10 Prepayments'!E18 -> 0 | F18: ='[10]II-B-10 Prepayments'!F18+'[9]II-B-10 Prepayments'!F18 -> 0 | G18: ='[10]II-B-10 Prepayments'!G18+'[9]II-B-10 Prepayments'!G18 -> 4735.3138 | H18: ='[10]II-B-10 Prepayments'!H18+'[9]II-B-10 Prepayments'!H18 -> 4735.3138 | I18: 1 | J18: =SUM((H18-M18)*I18)+M18 -> 4735.3138 | K18: 29/12 | L18: DIRECT/DPAYXAG | M18: ='[10]II-B-10 Prepayments'!M18+'[9]II-B-10 Prepayments'!M18 -> 892.68615 | N18: ='[10]II-B-10 Prepayments'!N18+'[9]II-B-10 Prepayments'!N18 -> 2505.0746 | O18: ='[10]II-B-10 Prepayments'!O18+'[9]II-B-10 Prepayments'!O18 -> 769.7985 | P18: ='[10]II-B-10 Prepayments'!P18+'[9]II-B-10 Prepayments'!P18 -> 567.75454 | Q18: =SUM(M18:P18) -> 4735.3138
A19: =+A18+1 -> 6 | B19: 1650006 | C19: Other Prepayments | E19: ='[10]II-B-10 Prepayments'!E19+'[9]II-B-10 Prepayments'!E19 -> 320427.67 | F19: ='[10]II-B-10 Prepayments'!F19+'[9]II-B-10 Prepayments'!F19 -> 0 | G19: ='[10]II-B-10 Prepayments'!G19+'[9]II-B-10 Prepayments'!G19 -> -123186.34 | H19: ='[10]II-B-10 Prepayments'!H19+'[9]II-B-10 Prepayments'!H19 -> 197241.33 | I19: 1 | J19: =SUM((H19-M19)*I19)+M19 -> 197241.33 | K19: 29/10 | L19: DIRECT/DGNLPLT-N | M19: ='[10]II-B-10 Prepayments'!M19+'[9]II-B-10 Prepayments'!M19 -> 342692.31 | N19: ='[10]II-B-10 Prepayments'!N19+'[9]II-B-10 Prepayments'!N19 -> -163799.02 | O19: ='[10]II-B-10 Prepayments'!O19+'[9]II-B-10 Prepayments'!O19 -> 18322.243 | P19: ='[10]II-B-10 Prepayments'!P19+'[9]II-B-10 Prepayments'!P19 -> 25.802628 | Q19: =SUM(M19:P19) -> 197241.33
A20: =+A19+1 -> 7 | B20: 1650010 Prepaid Pension Benefits | E20: ='[10]II-B-10 Prepayments'!E20+'[9]II-B-10 Prepayments'!E20 -> 1.8579197e+08 | F20: ='[10]II-B-10 Prepayments'!F20+'[9]II-B-10 Prepayments'!F20 -> 21449829 | G20: ='[10]II-B-10 Prepayments'!G20+'[9]II-B-10 Prepayments'!G20 -> -94634305 | H20: ='[10]II-B-10 Prepayments'!H20+'[9]II-B-10 Prepayments'!H20 -> 69707832 | I20: 1 | J20: =SUM((H20-M20)*I20)+M20 -> 69707832 | K20: 29/12 | L20: DIRECT/DPAYXAG | M20: ='[10]II-B-10 Prepayments'!M20+'[9]II-B-10 Prepayments'!M20 -> 23488263 | N20: ='[10]II-B-10 Prepayments'!N20+'[9]II-B-10 Prepayments'!N20 -> 29557363 | O20: ='[10]II-B-10 Prepayments'!O20+'[9]II-B-10 Prepayments'!O20 -> 9414362 | P20: ='[10]II-B-10 Prepayments'!P20+'[9]II-B-10 Prepayments'!P20 -> 7247844.3 | Q20: =SUM(M20:P20) -> 69707832
A21: =+A20+1 -> 8 | B21: 1650014 FAS 158 Qual Contra Asset | E21: ='[10]II-B-10 Prepayments'!E21+'[9]II-B-10 Prepayments'!E21 -> -1.8579197e+08 | F21: ='[10]II-B-10 Prepayments'!F21+'[9]II-B-10 Prepayments'!F21 -> -21449829 | G21: ='[10]II-B-10 Prepayments'!G21+'[9]II-B-10 Prepayments'!G21 -> 1.6434214e+08 | H21: ='[10]II-B-10 Prepayments'!H21+'[9]II-B-10 Prepayments'!H21 -> 0 | I21: 1 | J21: =SUM((H21-M21)*I21)+M21 -> 0 | K21: 29/12 | L21: DIRECT/DPAYXAG | M21: ='[10]II-B-10 Prepayments'!M21+'[9]II-B-10 Prepayments'!M21 -> -18140991 | N21: ='[10]II-B-10 Prepayments'!N21+'[9]II-B-10 Prepayments'!N21 -> 11656719 | O21: ='[10]II-B-10 Prepayments'!O21+'[9]II-B-10 Prepayments'!O21 -> 3680076.8 | P21: ='[10]II-B-10 Prepayments'!P21+'[9]II-B-10 Prepayments'!P21 -> 2804194.9 | Q21: =SUM(M21:P21) -> 0
A22: =+A21+1 -> 9 | B22: 1650021 Prepaid Insurance - EIS | E22: ='[10]II-B-10 Prepayments'!E22+'[9]II-B-10 Prepayments'!E22 -> 1562597.6 | F22: ='[10]II-B-10 Prepayments'!F22+'[9]II-B-10 Prepayments'!F22 -> 28799.03 | G22: ='[10]II-B-10 Prepayments'!G22+'[9]II-B-10 Prepayments'!G22 -> 338069.11 | H22: ='[10]II-B-10 Prepayments'!H22+'[9]II-B-10 Prepayments'!H22 -> 1871867.7 | I22: 1 | J22: =SUM((H22-M22)*I22)+M22 -> 1871867.7 | K22: 29/10 | L22: DIRECT/DGNLPLT-N | M22: ='[10]II-B-10 Prepayments'!M22+'[9]II-B-10 Prepayments'!M22 -> 220355 | N22: ='[10]II-B-10 Prepayments'!N22+'[9]II-B-10 Prepayments'!N22 -> 1465089.2 | O22: ='[10]II-B-10 Prepayments'!O22+'[9]II-B-10 Prepayments'!O22 -> 184031.01 | P22: ='[10]II-B-10 Prepayments'!P22+'[9]II-B-10 Prepayments'!P22 -> 2392.5043 | Q22: =SUM(M22:P22) -> 1871867.7
A23: =+A22+1 -> 10 | B23: 1650023 Prepaid Lease | E23: ='[10]II-B-10 Prepayments'!E23+'[9]II-B-10 Prepayments'!E23 -> 320384.73 | F23: ='[10]II-B-10 Prepayments'!F23+'[9]II-B-10 Prepayments'!F23 -> 0 | G23: ='[10]II-B-10 Prepayments'!G23+'[9]II-B-10 Prepayments'!G23 -> 7014.8277 | H23: ='[10]II-B-10 Prepayments'!H23+'[9]II-B-10 Prepayments'!H23 -> 327399.56 | I23: 1 | J23: =SUM((H23-M23)*I23)+M23 -> 327399.56 | K23: 29/10 | L23: DIRECT/DGNLPLT-N | M23: ='[10]II-B-10 Prepayments'!M23+'[9]II-B-10 Prepayments'!M23 -> 249884.54 | N23: ='[10]II-B-10 Prepayments'!N23+'[9]II-B-10 Prepayments'!N23 -> 74654.996 | O23: ='[10]II-B-10 Prepayments'!O23+'[9]II-B-10 Prepayments'!O23 -> 2787.7981 | P23: ='[10]II-B-10 Prepayments'!P23+'[9]II-B-10 Prepayments'!P23 -> 72.225593 | Q23: =SUM(M23:P23) -> 327399.56
A24: =+A23+1 -> 11 | B24: 1650035 PRW Without MED-D Benefits | E24: ='[10]II-B-10 Prepayments'!E24+'[9]II-B-10 Prepayments'!E24 -> 42440417 | F24: ='[10]II-B-10 Prepayments'!F24+'[9]II-B-10 Prepayments'!F24 -> 1266552 | G24: ='[10]II-B-10 Prepayments'!G24+'[9]II-B-10 Prepayments'!G24 -> -27413107 | H24: ='[10]II-B-10 Prepayments'!H24+'[9]II-B-10 Prepayments'!H24 -> 13760758 | I24: 1 | J24: =SUM((H24-M24)*I24)+M24 -> 13760758 | K24: 29/12 | L24: DIRECT/DPAYXAG | M24: ='[10]II-B-10 Prepayments'!M24+'[9]II-B-10 Prepayments'!M24 -> 4380179.2 | N24: ='[10]II-B-10 Prepayments'!N24+'[9]II-B-10 Prepayments'!N24 -> 5999155.3 | O24: ='[10]II-B-10 Prepayments'!O24+'[9]II-B-10 Prepayments'!O24 -> 1910632 | P24: ='[10]II-B-10 Prepayments'!P24+'[9]II-B-10 Prepayments'!P24 -> 1470791.1 | Q24: =SUM(M24:P24) -> 13760758
A25: =+A24+1 -> 12 | B25: 1650037 FAS158 Contra-PRW Exclud Med-D | E25: ='[10]II-B-10 Prepayments'!E25+'[9]II-B-10 Prepayments'!E25 -> -42440417 | F25: ='[10]II-B-10 Prepayments'!F25+'[9]II-B-10 Prepayments'!F25 -> -1266552 | G25: ='[10]II-B-10 Prepayments'!G25+'[9]II-B-10 Prepayments'!G25 -> 41173865 | H25: ='[10]II-B-10 Prepayments'!H25+'[9]II-B-10 Prepayments'!H25 -> 0 | I25: 1 | J25: =SUM((H25-M25)*I25)+M25 -> 0 | K25: 29/12 | L25: DIRECT/DPAYXAG | M25: ='[10]II-B-10 Prepayments'!M25+'[9]II-B-10 Prepayments'!M25 -> -3399907.7 | N25: ='[10]II-B-10 Prepayments'!N25+'[9]II-B-10 Prepayments'!N25 -> 2252848 | O25: ='[10]II-B-10 Prepayments'!O25+'[9]II-B-10 Prepayments'!O25 -> 671271.98 | P25: ='[10]II-B-10 Prepayments'!P25+'[9]II-B-10 Prepayments'!P25 -> 475787.77 | Q25: =SUM(M25:P25) -> 0
A26: =+A25+1 -> 13
A27: =+A26+1 -> 14
A28: =+A27+1 -> 15
A29: =+A28+1 -> 16
A30: =+A29+1 -> 17
A31: =+A30+1 -> 18 | E31: 0
A32: =+A31+1 -> 19 | C32: Subtotal | E32: =SUM(E17:E25) -> 3378960.3 | F32: =SUM(F17:F25) -> 57368.053 | G32: =SUM(G17:G25) -> 83596897 | H32: =SUM(H17:H25) -> 86918490 | J32: =SUM(J17:J25) -> 86918490 | M32: =SUM(M17:M25) -> 7413933.4 | N32: =SUM(N17:N25) -> 51592864 | O32: =SUM(O17:O25) -> 15909433 | P32: =SUM(P17:P25) -> 12002259 | Q32: =SUM(Q17:Q25) -> 86918490
A33: =+A32+1 -> 20
A34: =+A33+1 -> 21 | B34: TOTAL PREPAYMENTS | D34: II-B-10 | E34: =SUM(E32) -> 3378960.3 | F34: =SUM(F32) -> 57368.053 | G34: =SUM(G32) -> 83596897 | H34: =SUM(H32) -> 86918490 | J34: =SUM(J32) -> 86918490 | M34: =SUM(M32) -> 7413933.4 | N34: =SUM(N32) -> 51592864 | O34: =SUM(O32) -> 15909433 | P34: =SUM(P32) -> 12002259 | Q34: =SUM(Q32) -> 86918490
A35: =+A34+1 -> 22
A36: =+A35+1 -> 23 | B36: WORKING CAPITAL TOTAL | D36: II-B-8-10 | E36: =+'II-B-8 M&S'!E21+'II-B-9 CWCapital'!E27+'II-B-10 Prepayments'!E34 -> 56175296 | F36: =+'II-B-8 M&S'!F21+'II-B-9 CWCapital'!F27+'II-B-10 Prepayments'!F34 -> 3933151.2 | G36: =+'II-B-8 M&S'!G21+'II-B-9 CWCapital'!G27+'II-B-10 Prepayments'!G34 -> 59013966 | H36: =+'II-B-8 M&S'!H21+'II-B-9 CWCapital'!H27+'II-B-10 Prepayments'!H34 -> 1.1125611e+08 | J36: =+'II-B-8 M&S'!J21+'II-B-9 CWCapital'!J27+'II-B-10 Prepayments'!J34 -> 1.1125611e+08 | M36: =+'II-B-8 M&S'!M21+'II-B-9 CWCapital'!O27+'II-B-10 Prepayments'!M34 -> 20903678 | N36: =+'II-B-8 M&S'!N21+'II-B-9 CWCapital'!P27+'II-B-10 Prepayments'!N34 -> 82631094 | O36: =+'II-B-8 M&S'!O21+'II-B-9 CWCapital'!Q27+'II-B-10 Prepayments'!O34 -> -5969154.6 | P36: =+'II-B-8 M&S'!P21+'II-B-9 CWCapital'!R27+'II-B-10 Prepayments'!P34 -> 12003244 | Q36: =+'II-B-8 M&S'!Q21+'II-B-9 CWCapital'!Q27+'II-B-10 Prepayments'!Q34 -> 1.1125611e+08
E39: =E34-F34 -> 3321592.2

Sheet II-B-10 MONTHLY
Q1: SCHEDULE II-B-10
B2: PUBLIC UTILITY COMMISSION OF TEXAS | Q2: MONTHLY
B3: AEP TEXAS INC
B4: II-B-10 RATE BASE ACCOUNTS - PREPAYMENTS
B5: ='II-B'!B5 -> TEST YEAR ENDING 12/31/2018
E8: 1 | F8: 2 | G8: 3 | H8: 4 | I8: 5 | J8: 6 | K8: 7 | L8: 8 | M8: 9 | N8: 10 | O8: 11 | P8: 12 | Q8: 13
H9: Company | I9: Texas
B10: Account | C10: Description | D10: Reference | E10: Total | F10: Non-Regulated or | G10: Known | H10: Total | I10: Retail | J10: Allocation to | K10: FF | L10: Funct | M10: TRAN | N10: DIST | O10: MET | P10: TDCS | Q10: Total
A11: Line | B11: Number | D11: Schedule | E11: Company | F11: Non-Electric | G11: Change | H11: Electric | I11: Allocation | J11: Texas | K11: # | L11: Factor
A12: No. | I12: Factor | L12: Name
A14: 1
A15: =+A14+1 -> 2 | C15: This Schedule of monthly information is not provided on a combined basis. Please see the Central Division Schedules and North Divisions Schedules.
A16: =+A15+1 -> 3
A17: =+A16+1 -> 4
A18: =+A17+1 -> 5 | B18: TOTAL PREPAYMENTS | D18: II-B-10

Sheet II-B-11 Rate Base Other
B2: PUBLIC UTILITY COMMISSION OF TEXAS
B3: AEP TEXAS INC
B4: II-B-11 OTHER RATE BASE ITEMS
B5: TEST YEAR ENDING 12/31/2018
B6: ='I-A'!B6
E8: 1 | F8: 2 | G8: 3 | H8: 4 | I8: 5 | J8: 6 | K8: 7 | L8: 8 | M8: 9 | N8: 10 | O8: 11 | P8: 12 | Q8: 13
H9: Company | I9: Texas
B10: Account | C10: Description | D10: Reference | E10: Total | F10: Non-Regulated or | G10: Known | H10: Total | I10: Retail | J10: Allocation to | K10: FF | L10: Funct | M10: TRAN | N10: DIST | O10: MET | P10: TDCS | Q10: Total
A11: Line | B11: Number | D11: Schedule | E11: Company | F11: Non-Electric | G11: Change | H11: Electric | I11: Allocation | J11: Texas | K11: # | L11: Factor | R11: CHECK
A12: No. | I12: Factor | L12: Name
A14: 1 | B14: Other Rate Base Items
A15: =+A14+1 -> 2 | B15: 2540052 | C15: Excess Earnings | E15: ='[10]II-B-11 Rate Base Other'!E15 -> -6325667.4 | F15: ='[10]II-B-11 Rate Base Other'!F15 -> 0 | G15: ='[10]II-B-11 Rate Base Other'!G15 -> 0 | H15: =+E15-F15+G15 -> -6325667.4 | I15: 1 | J15: =SUM((H15-M15)*I15)+M15 -> -6325667.4 | K15: 29/18 | L15: DIRECT/DPLTSVC-N | M15: ='[10]II-B-11 Rate Base Other'!M15 -> 0 | N15: ='[10]II-B-11 Rate Base Other'!N15 -> -5979351.9 | O15: ='[10]II-B-11 Rate Base Other'!O15 -> -345054.5 | P15: ='[10]II-B-11 Rate Base Other'!P15 -> -1260.9027 | Q15: =SUM(M15:P15) -> -6325667.4
A16: =+A15+1 -> 3 | B16: 2543001 | C16: SFAS 109 Reg. Liability- ITC Grossup | E16: ='[10]II-B-11 Rate Base Other'!E16+'[9]II-B-11 Rate Base Other'!E15 -> -2834862.3 | F16: ='[10]II-B-11 Rate Base Other'!F16+'[9]II-B-11 Rate Base Other'!F15 -> 0 | G16: ='[10]II-B-11 Rate Base Other'!G16+'[9]II-B-11 Rate Base Other'!G15 -> 0 | H16: =+E16-F16+G16 -> -2834862.3 | I16: 1 | J16: =SUM((H16-M16)*I16)+M16 -> -2834862.3 | K16: 29/18 | L16: DIRECT/DPLTSVC-N | M16: ='[10]II-B-11 Rate Base Other'!M16+'[9]II-B-11 Rate Base Other'!M15 -> -1963478.7 | N16: ='[10]II-B-11 Rate Base Other'!N16+'[9]II-B-11 Rate Base Other'!N15 -> -837990.25 | O16: ='[10]II-B-11 Rate Base Other'!O16+'[9]II-B-11 Rate Base Other'!O15 -> -32803.528 | P16: ='[10]II-B-11 Rate Base Other'!P16+'[9]II-B-11 Rate Base Other'!P15 -> -589.8829 | Q16: =SUM(M16:P16) -> -2834862.3
A17: =+A16+1 -> 4 | B17: 2544001 | C17: SFAS 109 Reg. Liability-Excess ADIT & Grossup | E17: ='[10]II-B-11 Rate Base Other'!E17+'[9]II-B-11 Rate Base Other'!E16 -> -6.704527e+08 | F17: ='[10]II-B-11 Rate Base Other'!F17+'[9]II-B-11 Rate Base Other'!F16 -> 0 | G17: ='[10]II-B-11 Rate Base Other'!G17+'[9]II-B-11 Rate Base Other'!G16 -> 1.413207e+08 | H17: =+E17-F17+G17 -> -5.29132e+08 | I17: 1 | J17: =SUM((H17-M17)*I17)+M17 -> -5.29132e+08 | K17: 29/18 | L17: DIRECT/DPLTSVC-N | M17: ='[10]II-B-11 Rate Base Other'!M17+'[9]II-B-11 Rate Base Other'!M16 -> -276966784 | N17: ='[10]II-B-11 Rate Base Other'!N17+'[9]II-B-11 Rate Base Other'!N16 -> -2.4327728e+08 | O17: ='[10]II-B-11 Rate Base Other'!O17+'[9]II-B-11 Rate Base Other'!O16 -> -8694684.1 | P17: ='[10]II-B-11 Rate Base Other'!P17+'[9]II-B-11 Rate Base Other'!P16 -> -193256.33 | Q17: =SUM(M17:P17) -> -5.29132e+08
A18: =+A17+1 -> 5 | B18: 2550001 | C18: Pre 1971 Unamortized ITC | E18: ='[9]II-B-11 Rate Base Other'!E17 -> -31693 | F18: ='[9]II-B-11 Rate Base Other'!F17 -> 0 | G18: ='[9]II-B-11 Rate Base Other'!G17 -> 0 | H18: =+E18-F18+G18 -> -31693 | I18: 1 | J18: =SUM((H18-M18)*I18)+M18 -> -31693 | K18: 29/18 | L18: DIRECT/DPLTSVC-N | M18: ='[9]II-B-11 Rate Base Other'!M17 -> -31693 | N18: ='[9]II-B-11 Rate Base Other'!N17 -> 0 | O18: ='[9]II-B-11 Rate Base Other'!O17 -> 0 | P18: ='[9]II-B-11 Rate Base Other'!P17 -> 0 | Q18: =SUM(M18:P18) -> -31693
A19: =+A18+1 -> 6
A20: =+A19+1 -> 7 | B20: 2530000 | C20: Other Deferred Credits | E20: ='[10]II-B-11 Rate Base Other'!E19+'[9]II-B-11 Rate Base Other'!E19 -> -11704114 | F20: ='[10]II-B-11 Rate Base Other'!F19+'[9]II-B-11 Rate Base Other'!F19 -> 0 | G20: ='[10]II-B-11 Rate Base Other'!G19+'[9]II-B-11 Rate Base Other'!G19 -> 0 | H20: =+E20-F20+G20 -> -11704114 | I20: 1 | J20: =SUM((H20-M20)*I20)+M20 -> -11704114 | K20: 29/18 | L20: DIRECT/DPLTSVC-N | M20: ='[10]II-B-11 Rate Base Other'!M19+'[9]II-B-11 Rate Base Other'!M19 -> -12204166 | N20: ='[10]II-B-11 Rate Base Other'!N19+'[9]II-B-11 Rate Base Other'!N19 -> 484575.07 | O20: ='[10]II-B-11 Rate Base Other'!O19+'[9]II-B-11 Rate Base Other'!O19 -> 15031.066 | P20: ='[10]II-B-11 Rate Base Other'!P19+'[9]II-B-11 Rate Base Other'!P19 -> 445.70229 | Q20: =SUM(M20:P20) -> -11704114
A21: =+A20+1 -> 8 | B21: 2530050 | C21: Deferred Rev -Pole Attachments | E21: ='[10]II-B-11 Rate Base Other'!E20+'[9]II-B-11 Rate Base Other'!E20 -> -1341462.6 | F21: ='[10]II-B-11 Rate Base Other'!F20+'[9]II-B-11 Rate Base Other'!F20 -> 0 | G21: ='[10]II-B-11 Rate Base Other'!G20+'[9]II-B-11 Rate Base Other'!G20 -> 0 | H21: =+E21-F21+G21 -> -1341462.6 | I21: 1 | J21: =SUM((H21-M21)*I21)+M21 -> -1341462.6 | K21: 29 | L21: DIRECT | M21: ='[10]II-B-11 Rate Base Other'!M20+'[9]II-B-11 Rate Base Other'!M20 -> 0 | N21: ='[10]II-B-11 Rate Base Other'!N20+'[9]II-B-11 Rate Base Other'!N20 -> -1341462.6 | O21: ='[10]II-B-11 Rate Base Other'!O20+'[9]II-B-11 Rate Base Other'!O20 -> 0 | P21: ='[10]II-B-11 Rate Base Other'!P20+'[9]II-B-11 Rate Base Other'!P20 -> 0 | Q21: =SUM(M21:P21) -> -1341462.6
A22: =+A21+1 -> 9 | B22: 2530112 | C22: Other Deferred Credits-Curr | E22: ='[10]II-B-11 Rate Base Other'!E21+'[9]II-B-11 Rate Base Other'!E21 -> -10950657 | F22: ='[10]II-B-11 Rate Base Other'!F21+'[9]II-B-11 Rate Base Other'!F21 -> 0 | G22: ='[10]II-B-11 Rate Base Other'!G21+'[9]II-B-11 Rate Base Other'!G21 -> 0 | H22: =+E22-F22+G22 -> -10950657 | I22: 1 | J22: =SUM((H22-M22)*I22)+M22 -> -10950657 | K22: 29/18 | L22: DIRECT/DPLTSVC-N | M22: ='[10]II-B-11 Rate Base Other'!M21+'[9]II-B-11 Rate Base Other'!M21 -> -10782632 | N22: ='[10]II-B-11 Rate Base Other'!N21+'[9]II-B-11 Rate Base Other'!N21 -> -162625.49 | O22: ='[10]II-B-11 Rate Base Other'!O21+'[9]II-B-11 Rate Base Other'!O21 -> -5255.7974 | P22: ='[10]II-B-11 Rate Base Other'!P21+'[9]II-B-11 Rate Base Other'!P21 -> -143.96689 | Q22: =SUM(M22:P22) -> -10950657
A23: =+A22+1 -> 10 | B23: 2530120 | C23: Environ Remediation LT | E23: ='[10]II-B-11 Rate Base Other'!E22 -> -195067.55 | F23: ='[10]II-B-11 Rate Base Other'!F22 -> -169280.67 | G23: ='[10]II-B-11 Rate Base Other'!G22 -> 0 | H23: =+E23-F23+G23 -> -25786.885 | I23: 1 | J23: =SUM((H23-M23)*I23)+M23 -> -25786.885 | K23: 29 | L23: DIRECT | M23: ='[10]II-B-11 Rate Base Other'!M22 -> 0 | N23: ='[10]II-B-11 Rate Base Other'!N22 -> -25786.885 | O23: ='[10]II-B-11 Rate Base Other'!O22 -> 0 | P23: ='[10]II-B-11 Rate Base Other'!P22 -> 0 | Q23: =SUM(M23:P23) -> -25786.885
A24: =+A23+1 -> 11 | B24: 2530124 | C24: Contr In Aid of Constr Advance | E24: ='[10]II-B-11 Rate Base Other'!E23+'[9]II-B-11 Rate Base Other'!E22 -> -24209109 | F24: ='[10]II-B-11 Rate Base Other'!F23+'[9]II-B-11 Rate Base Other'!F22 -> 0 | G24: ='[10]II-B-11 Rate Base Other'!G23+'[9]II-B-11 Rate Base Other'!G22 -> 0 | H24: =+E24-F24+G24 -> -24209109 | I24: 1 | J24: =SUM((H24-M24)*I24)+M24 -> -24209109 | K24: 29 | L24: DIRECT | M24: ='[10]II-B-11 Rate Base Other'!M23+'[9]II-B-11 Rate Base Other'!M22 -> -19925248 | N24: ='[10]II-B-11 Rate Base Other'!N23+'[9]II-B-11 Rate Base Other'!N22 -> -4283861.2 | O24: ='[10]II-B-11 Rate Base Other'!O23+'[9]II-B-11 Rate Base Other'!O22 -> 0 | P24: ='[10]II-B-11 Rate Base Other'!P23+'[9]II-B-11 Rate Base Other'!P22 -> 0 | Q24: =SUM(M24:P24) -> -24209109
A25: =+A24+1 -> 12
A26: =+A25+1 -> 13 | B26: TOTAL OTHER RATE BASE ITEMS | D26: II-B-11 | E26: =SUM(E15:E25) -> -7.2804534e+08 | F26: =SUM(F15:F25) -> -169280.67 | G26: =SUM(G15:G25) -> 1.413207e+08 | H26: =SUM(H15:H25) -> -5.8655535e+08 | J26: =SUM(J15:J25) -> -5.8655535e+08 | M26: =SUM(M15:M25) -> -3.21874e+08 | N26: =SUM(N15:N25) -> -2.5542378e+08 | O26: =SUM(O15:O25) -> -9062766.8 | P26: =SUM(P15:P25) -> -194805.38 | Q26: =SUM(Q15:Q25) -> -5.8655535e+08
E29: =E26-F26 -> -7.2787606e+08

Sheet II-B-12 Reg. Assets
B2: PUBLIC UTILITY COMMISSION OF TEXAS
B3: AEP TEXAS INC
B4: II-B-12 RATE BASE ACCOUNTS - REGULATORY ASSETS
B5: TEST YEAR ENDING 12/31/2018
B6: ='I-A'!B6
E8: 1 | F8: 2 | G8: 3 | H8: 4 | I8: 5 | J8: 6 | K8: 7 | L8: 8 | M8: 9 | N8: 10 | O8: 11 | P8: 12 | Q8: 13
H9: Company | I9: Texas
B10: Account | C10: Description | D10: Reference | E10: Total | F10: Non-Regulated or | G10: Known | H10: Total | I10: Retail | J10: Allocation to | K10: FF | L10: Funct | M10: TRAN | N10: DIST | O10: MET | P10: TDCS | Q10: Total
A11: Line | B11: Number | D11: Schedule | E11: Company | F11: Non-Electric | G11: Change | H11: Electric | I11: Allocation | J11: Texas | K11: # | L11: Factor | R11: CHECK
A12: No. | I12: Factor | L12: Name
A14: 1 | B14: Other Rate Base Items
A15: =+A14+1 -> 2 | B15: Regulatory Assets/(Liabilities) in Rate Base | D15: II-B-12
A16: =+A15+1 -> 3
A17: =+A16+1 -> 4 | B17: 1823098 | C17: Debt Refinancing - Restructuring Costs | E17: ='[9]II-B-12 Reg. Assets'!E17 -> 18238.02 | F17: ='[9]II-B-12 Reg. Assets'!F17 -> 0 | G17: ='[9]II-B-12 Reg. Assets'!G17 -> 0 | H17: =+E17-F17+G17 -> 18238.02 | I17: 1 | J17: =H17 -> 18238.02 | K17: 17 | L17: PLTSVC-N | M17: ='[9]II-B-12 Reg. Assets'!M17 -> 8977.31 | N17: ='[9]II-B-12 Reg. Assets'!N17 -> 8974.088 | O17: ='[9]II-B-12 Reg. Assets'!O17 -> 278.36783 | P17: ='[9]II-B-12 Reg. Assets'!P17 -> 8.2541836 | Q17: =SUM(M17:P17) -> 18238.02
A18: =+A17+1 -> 5 | B18: 1823185 | C18: Reg Asset-Catastrophe Reserve | E18: ='[9]II-B-12 Reg. Assets'!E18 -> 1.5244959e+08 | F18: ='[9]II-B-12 Reg. Assets'!F18 -> 0 | G18: ='[9]II-B-12 Reg. Assets'!G18 -> -1.6163311e+08 | H18: =+E18-F18+G18 -> -9183518.5 | I18: 1 | J18: =H18 -> -9183518.5 | K18: 29/16 | L18: DIRECT/DPLTXGNL-N | M18: ='[9]II-B-12 Reg. Assets'!M18 -> 4536379 | N18: ='[9]II-B-12 Reg. Assets'!N18 -> -13319931 | O18: ='[9]II-B-12 Reg. Assets'!O18 -> -399966.38 | P18: ='[9]II-B-12 Reg. Assets'!P18 -> 0 | Q18: =SUM(M18:P18) -> -9183518.5
A19: =+A18+1 -> 6 | B19: 1823223 | C19: Non-AMI Meters | E19: ='[10]II-B-12 Reg. Assets'!E17+'[9]II-B-12 Reg. Assets'!E19 -> 97413925 | F19: ='[10]II-B-12 Reg. Assets'!F17+'[9]II-B-12 Reg. Assets'!F19 -> 0 | G19: ='[10]II-B-12 Reg. Assets'!G17+'[9]II-B-12 Reg. Assets'!G19 -> 0 | H19: =+E19-F19+G19 -> 97413925 | I19: 1 | J19: =H19 -> 97413925 | K19: 29 | L19: DIRECT | M19: ='[10]II-B-12 Reg. Assets'!M17+'[9]II-B-12 Reg. Assets'!M19 -> 0 | N19: ='[10]II-B-12 Reg. Assets'!N17+'[9]II-B-12 Reg. Assets'!N19 -> 0 | O19: ='[10]II-B-12 Reg. Assets'!O17+'[9]II-B-12 Reg. Assets'!O19 -> 97413925 | P19: ='[10]II-B-12 Reg. Assets'!P17+'[9]II-B-12 Reg. Assets'!P19 -> 0 | Q19: =SUM(M19:P19) -> 97413925
A20: =+A19+1 -> 7 | B20: 1823224 | C20: Non-AMI Meter Amortization | E20: ='[10]II-B-12 Reg. Assets'!E18+'[9]II-B-12 Reg. Assets'!E20 -> -57335346 | F20: ='[10]II-B-12 Reg. Assets'!F18+'[9]II-B-12 Reg. Assets'!F20 -> 0 | G20: ='[10]II-B-12 Reg. Assets'!G18+'[9]II-B-12 Reg. Assets'!G20 -> 0 | H20: =+E20-F20+G20 -> -57335346 | I20: 1 | J20: =SUM((H20-M20)*I20)+M20 -> -57335346 | K20: 29 | L20: DIRECT | M20: ='[10]II-B-12 Reg. Assets'!M18+'[9]II-B-12 Reg. Assets'!M20 -> 0 | N20: ='[10]II-B-12 Reg. Assets'!N18+'[9]II-B-12 Reg. Assets'!N20 -> 0 | O20: ='[10]II-B-12 Reg. Assets'!O18+'[9]II-B-12 Reg. Assets'!O20 -> -57335346 | P20: ='[10]II-B-12 Reg. Assets'!P18+'[9]II-B-12 Reg. Assets'!P20 -> 0 | Q20: =SUM(M20:P20) -> -57335346
A21: =+A20+1 -> 8 | B21: 1823299 | C21: SFAS 106 Medicare Subsidy | E21: ='[10]II-B-12 Reg. Assets'!E19+'[9]II-B-12 Reg. Assets'!E21 -> 4177567.3 | F21: ='[10]II-B-12 Reg. Assets'!F19+'[9]II-B-12 Reg. Assets'!F21 -> 0 | G21: ='[10]II-B-12 Reg. Assets'!G19+'[9]II-B-12 Reg. Assets'!G21 -> 0 | H21: =+E21-F21+G21 -> 4177567.3 | I21: 1 | J21: =SUM((H21-M21)*I21)+M21 -> 4177567.3 | K21: 29/12 | L21: DIRECT/DPAYXAG | M21: ='[10]II-B-12 Reg. Assets'!M19+'[9]II-B-12 Reg. Assets'!M21 -> 441737.29 | N21: ='[10]II-B-12 Reg. Assets'!N19+'[9]II-B-12 Reg. Assets'!N21 -> 2423367.5 | O21: ='[10]II-B-12 Reg. Assets'!O19+'[9]II-B-12 Reg. Assets'!O21 -> 751669.77 | P21: ='[10]II-B-12 Reg. Assets'!P19+'[9]II-B-12 Reg. Assets'!P21 -> 560792.8 | Q21: =SUM(M21:P21) -> 4177567.3
A22: =+A21+1 -> 9 | B22: 1823301 | C22: SFAS 109 Flow Thru Defd FIT | E22: ='[10]II-B-12 Reg. Assets'!E20+'[9]II-B-12 Reg. Assets'!E22 -> 18607693 | F22: ='[10]II-B-12 Reg. Assets'!F20+'[9]II-B-12 Reg. Assets'!F22 -> -0.04 | G22: ='[10]II-B-12 Reg. Assets'!G20+'[9]II-B-12 Reg. Assets'!G22 -> 0 | H22: =+E22-F22+G22 -> 18607693 | I22: 1 | J22: =SUM((H22-M22)*I22)+M22 -> 18607693 | K22: 29/18 | L22: DIRECT/DPLTSVC-N | M22: ='[10]II-B-12 Reg. Assets'!M20+'[9]II-B-12 Reg. Assets'!M22 -> 13929515 | N22: ='[10]II-B-12 Reg. Assets'!N20+'[9]II-B-12 Reg. Assets'!N22 -> 4185002.8 | O22: ='[10]II-B-12 Reg. Assets'!O20+'[9]II-B-12 Reg. Assets'!O22 -> 479435.21 | P22: ='[10]II-B-12 Reg. Assets'!P20+'[9]II-B-12 Reg. Assets'!P22 -> 13740.538 | Q22: =SUM(M22:P22) -> 18607693
A23: =+A22+1 -> 10 | B23: 1823302 | C23: SFAS 109 Flow Thru Defd SIT | E23: ='[10]II-B-12 Reg. Assets'!E21+'[9]II-B-12 Reg. Assets'!E23 -> 27229059 | F23: ='[10]II-B-12 Reg. Assets'!F21+'[9]II-B-12 Reg. Assets'!F23 -> 0 | G23: ='[10]II-B-12 Reg. Assets'!G21+'[9]II-B-12 Reg. Assets'!G23 -> 0 | H23: =+E23-F23+G23 -> 27229059 | I23: 1 | J23: =SUM((H23-M23)*I23)+M23 -> 27229059 | K23: 29/18 | L23: DIRECT/DPLTSVC-N | M23: ='[10]II-B-12 Reg. Assets'!M21+'[9]II-B-12 Reg. Assets'!M23 -> 9267370 | N23: ='[10]II-B-12 Reg. Assets'!N21+'[9]II-B-12 Reg. Assets'!N23 -> 17130226 | O23: ='[10]II-B-12 Reg. Assets'!O21+'[9]II-B-12 Reg. Assets'!O23 -> 810550.28 | P23: ='[10]II-B-12 Reg. Assets'!P21+'[9]II-B-12 Reg. Assets'!P23 -> 20912.854 | Q23: =SUM(M23:P23) -> 27229059
A24: =+A23+1 -> 11
A25: =+A24+1 -> 12 | C25: Subtotal | E25: =SUM(E16:E24) -> 2.4256073e+08 | F25: =SUM(F16:F24) -> -0.04 | G25: =SUM(G16:G24) -> -1.6163311e+08 | H25: =SUM(H16:H24) -> 80927618 | J25: =SUM(J16:J24) -> 80927618 | M25: =SUM(M16:M24) -> 28183978 | N25: =SUM(N16:N24) -> 10427639 | O25: =SUM(O16:O24) -> 41720546 | P25: =SUM(P16:P24) -> 595454.45 | Q25: =SUM(Q16:Q24) -> 80927618
A26: =+A25+1 -> 13
A27: =+A26+1 -> 14 | B27: TOTAL REGULATORY ASSETS | D27: II-B-12 | E27: =E25 -> 2.4256073e+08 | F27: =F25 -> -0.04 | G27: =G25 -> -1.6163311e+08 | H27: =H25 -> 80927618 | J27: =J25 -> 80927618 | K27: =K25 -> 0 | L27: =L25 -> 0 | M27: =M25 -> 28183978 | N27: =N25 -> 10427639 | O27: =O25 -> 41720546 | P27: =P25 -> 595454.45 | Q27: =Q25 -> 80927618
A28: =+A27+1 -> 15
A29: =+A28+1 -> 16 | B29: TOTAL OTHER RATE BASE ITEMS | D29: II-B-6-12 | E29: =+'II-B-7 Accum. Provisions'!E23+'II-B-8 M&S'!E21+'II-B-9 CWCapital'!E27+'II-B-10 Prepayments'!E34+'II-B-11 Rate Base Other'!E26+'II-B-12 Reg. Assets'!E27+'II-B-6 Plant Future'!E19 -> -1.3686865e+09 | F29: =+'II-B-7 Accum. Provisions'!F23+'II-B-8 M&S'!F21+'II-B-9 CWCapital'!F27+'II-B-10 Prepayments'!F34+'II-B-11 Rate Base Other'!F26+'II-B-12 Reg. Assets'!F27+'II-B-6 Plant Future'!F19 -> -1.5441904e+08 | G29: =+'II-B-7 Accum. Provisions'!G23+'II-B-8 M&S'!G21+'II-B-9 CWCapital'!G27+'II-B-10 Prepayments'!G34+'II-B-11 Rate Base Other'!G26+'II-B-12 Reg. Assets'!G27+'II-B-6 Plant Future'!G19 -> 43272831 | H29: =+'II-B-7 Accum. Provisions'!H23+'II-B-8 M&S'!H21+'II-B-9 CWCapital'!H27+'II-B-10 Prepayments'!H34+'II-B-11 Rate Base Other'!H26+'II-B-12 Reg. Assets'!H27+'II-B-6 Plant Future'!H19 -> -1.1709947e+09 | J29: =+'II-B-7 Accum. Provisions'!J23+'II-B-8 M&S'!J21+'II-B-9 CWCapital'!J27+'II-B-10 Prepayments'!J34+'II-B-11 Rate Base Other'!J26+'II-B-12 Reg. Assets'!J27+'II-B-6 Plant Future'!K19 -> -1.1709947e+09 | M29: =+'II-B-7 Accum. Provisions'!M23+'II-B-8 M&S'!M21+'II-B-9 CWCapital'!M27+'II-B-10 Prepayments'!M34+'II-B-11 Rate Base Other'!M26+'II-B-12 Reg. Assets'!M27+'II-B-6 Plant Future'!L19 -> -6.4264475e+08 | N29: =+'II-B-7 Accum. Provisions'!N23+'II-B-8 M&S'!N21+'II-B-9 CWCapital'!N27+'II-B-10 Prepayments'!N34+'II-B-11 Rate Base Other'!N26+'II-B-12 Reg. Assets'!N27+'II-B-6 Plant Future'!M19 -> -5.5817543e+08 | O29: =+'II-B-7 Accum. Provisions'!O23+'II-B-8 M&S'!O21+'II-B-9 CWCapital'!O27+'II-B-10 Prepayments'!O34+'II-B-11 Rate Base Other'!O26+'II-B-12 Reg. Assets'!O27+'II-B-6 Plant Future'!N19 -> 21170033 | P29: =+'II-B-7 Accum. Provisions'!P23+'II-B-8 M&S'!P21+'II-B-9 CWCapital'!P27+'II-B-10 Prepayments'!P34+'II-B-11 Rate Base Other'!P26+'II-B-12 Reg. Assets'!P27+'II-B-6 Plant Future'!O19 -> 8655488.8 | Q29: =SUM(M29:P29) -> -1.1709947e+09
A30: =+A29+1 -> 17
A31: =+A30+1 -> 18 | B31: TOTAL RATE BASE | D31: II-B-1-12 | E31: =+'II-B-1 Plant'!E51+'II-B-2 General Plant'!E31+'II-B-3 Comm. Equip.'!E17+'II-B-4 CWIP'!E18+'II-B-6 Plant Future'!E19+'II-B-7 Accum. Provisions'!E23+'II-B-8 M&S'!E21+'II-B-9 CWCapital'!E25+'II-B-10 Prepayments'!E34+'II-B-11 Rate Base Other'!E26+'II-B-12 Reg. Assets'!E27-'II-B-5 Depreciation'!E53-'II-B-5 Depreciation'!E80 -> 5.7788413e+09 | F31: =+'II-B-1 Plant'!F51+'II-B-2 General Plant'!F31+'II-B-3 Comm. Equip.'!F17+'II-B-4 CWIP'!F18+'II-B-6 Plant Future'!F19+'II-B-7 Accum. Provisions'!F23+'II-B-8 M&S'!F21+'II-B-9 CWCapital'!F25+'II-B-10 Prepayments'!F34+'II-B-11 Rate Base Other'!F26+'II-B-12 Reg. Assets'!F27-'II-B-5 Depreciation'!F53-'II-B-5 Depreciation'!F80 -> -1.5405847e+08 | G31: =+'II-B-1 Plant'!G51+'II-B-2 General Plant'!G31+'II-B-3 Comm. Equip.'!G17+'II-B-4 CWIP'!G18+'II-B-6 Plant Future'!G19+'II-B-7 Accum. Provisions'!G23+'II-B-8 M&S'!G21+'II-B-9 CWCapital'!G25+'II-B-10 Prepayments'!G34+'II-B-11 Rate Base Other'!G26+'II-B-12 Reg. Assets'!G27-'II-B-5 Depreciation'!G53-'II-B-5 Depreciation'!G80 -> -8.6382806e+08 | H31: =+'II-B-1 Plant'!H51+'II-B-2 General Plant'!H31+'II-B-3 Comm. Equip.'!H17+'II-B-4 CWIP'!H18+'II-B-6 Plant Future'!H19+'II-B-7 Accum. Provisions'!H23+'II-B-8 M&S'!H21+'II-B-9 CWCapital'!H25+'II-B-10 Prepayments'!H34+'II-B-11 Rate Base Other'!H26+'II-B-12 Reg. Assets'!H27-'II-B-5 Depreciation'!H53-'II-B-5 Depreciation'!H80 -> 5.0690717e+09 | I31: =+'II-B-1 Plant'!I51+'II-B-2 General Plant'!I31+'II-B-3 Comm. Equip.'!I17+'II-B-4 CWIP'!I18+'II-B-5 Depreciation'!I83+'II-B-6 Plant Future'!I19+'II-B-7 Accum. Provisions'!I23+'II-B-8 M&S'!I21+'II-B-9 CWCapital'!I25+'II-B-10 Prepayments'!I34+'II-B-11 Rate Base Other'!I26+'II-B-12 Reg. Assets'!I27 -> 0 | J31: =+'II-B-1 Plant'!J51+'II-B-2 General Plant'!J31+'II-B-3 Comm. Equip.'!J17+'II-B-4 CWIP'!J18-'II-B-5 Depreciation'!J53-'II-B-5 Depreciation'!J80+'II-B-6 Plant Future'!K19+'II-B-7 Accum. Provisions'!J23+'II-B-8 M&S'!J21+'II-B-9 CWCapital'!J27+'II-B-10 Prepayments'!J34+'II-B-11 Rate Base Other'!J26+'II-B-12 Reg. Assets'!J27 -> 5.0690717e+09 | M31: =+'II-B-1 Plant'!M51+'II-B-2 General Plant'!M31+'II-B-3 Comm. Equip.'!M17+'II-B-4 CWIP'!M18-'II-B-5 Depreciation'!M53-'II-B-5 Depreciation'!M80+'II-B-6 Plant Future'!L19+'II-B-7 Accum. Provisions'!M23+'II-B-8 M&S'!M21+'II-B-9 CWCapital'!M27+'II-B-10 Prepayments'!M34+'II-B-11 Rate Base Other'!M26+'II-B-12 Reg. Assets'!M27 -> 2.6350869e+09 | N31: =+'II-B-1 Plant'!N51+'II-B-2 General Plant'!N31+'II-B-3 Comm. Equip.'!N17+'II-B-4 CWIP'!N18-'II-B-5 Depreciation'!N53-'II-B-5 Depreciation'!N80+'II-B-6 Plant Future'!M19+'II-B-7 Accum. Provisions'!N23+'II-B-8 M&S'!N21+'II-B-9 CWCapital'!N27+'II-B-10 Prepayments'!N34+'II-B-11 Rate Base Other'!N26+'II-B-12 Reg. Assets'!N27 -> 2.2982853e+09 | O31: =+'II-B-1 Plant'!O51+'II-B-2 General Plant'!O31+'II-B-3 Comm. Equip.'!O17+'II-B-4 CWIP'!O18-'II-B-5 Depreciation'!O53-'II-B-5 Depreciation'!O80+'II-B-6 Plant Future'!N19+'II-B-7 Accum. Provisions'!O23+'II-B-8 M&S'!O21+'II-B-9 CWCapital'!O27+'II-B-10 Prepayments'!O34+'II-B-11 Rate Base Other'!O26+'II-B-12 Reg. Assets'!O27 -> 1.248162e+08 | P31: =+'II-B-1 Plant'!P51+'II-B-2 General Plant'!P31+'II-B-3 Comm. Equip.'!P17+'II-B-4 CWIP'!P18-'II-B-5 Depreciation'!P53-'II-B-5 Depreciation'!P80+'II-B-6 Plant Future'!O19+'II-B-7 Accum. Provisions'!P23+'II-B-8 M&S'!P21+'II-B-9 CWCapital'!P27+'II-B-10 Prepayments'!P34+'II-B-11 Rate Base Other'!P26+'II-B-12 Reg. Assets'!P27 -> 10883273 | Q31: =+'II-B-1 Plant'!Q51+'II-B-2 General Plant'!Q31+'II-B-3 Comm. Equip.'!Q17+'II-B-4 CWIP'!Q18-'II-B-5 Depreciation'!Q53-'II-B-5 Depreciation'!Q80+'II-B-6 Plant Future'!P19+'II-B-7 Accum. Provisions'!Q23+'II-B-8 M&S'!Q21+'II-B-9 CWCapital'!Q27+'II-B-10 Prepayments'!Q34+'II-B-11 Rate Base Other'!Q26+'II-B-12 Reg. Assets'!Q27 -> 5.0690717e+09
A32: =+A31+1 -> 19
A33: =+A32+1 -> 20 | B33: Rate of Return | D33: II-C-2.1 | H33: ='II-C-1 ROR'!D15 -> 0.070767 | J33: =H33 -> 0.070767 | M33: =$H$33 -> 0.070767 | N33: =$H$33 -> 0.070767 | O33: =$H$33 -> 0.070767 | P33: =$H$33 -> 0.070767 | Q33: =$H$33 -> 0.070767
A34: =+A33+1 -> 21
A35: =+A34+1 -> 22 | B35: RETURN ON RATE BASE | H35: =+H31*H33 -> 3.58723e+08 | J35: =+J31*J33 -> 3.58723e+08 | M35: =+M31*M33 -> 1.8647719e+08 | N35: =+N31*N33 -> 1.6264276e+08 | O35: =+O31*O33 -> 8832868 | P35: =+P31*P33 -> 770176.56 | Q35: =+Q31*Q33 -> 3.58723e+08

Sheet II-B-13 Gain on Disposition
B2: PUBLIC UTILITY COMMISSION OF TEXAS
B3: AEP TEXAS INC
B4: II-B-13 Gain or Loss on Sale of Utility Assets
B5: =+'[11]II-D-2.4 Advertising'!C5 -> TEST YEAR ENDING 12/31/2018
B6: ='I-A'!B6
E8: 1 | F8: 2 | G8: 3 | H8: 4 | I8: 5 | J8: 6 | K8: 7 | L8: 8 | M8: 9 | N8: =+M8+1 -> 10 | O8: =+N8+1 -> 11 | P8: =+O8+1 -> 12 | Q8: =+P8+1 -> 13
H9: Company | I9: Texas
A10: Line | B10: Account | C10: Description | D10: Reference | E10: Total | F10: Non-Regulated or | G10: Known | H10: Total | I10: Retail | J10: Allocation to | K10: FF | L10: Funct | M10: TRAN | N10: DIST | O10: MET | P10: TDCS | Q10: Total
A11: No. | B11: Number | D11: Schedule | E11: Company | F11: Non-Electric | G11: Change | H11: Electric | I11: Allocation | J11: Texas | K11: # | L11: Factor | R11: CHECK
I12: Factor | L12: Name
A13: 1 | R13: =Q13-H13 -> 0
A14: =A13+1 -> 2 | B14: 4116000 | C14: Gain on dispostion of Plant | E14: ='[10]II-B-13 Gain or Loss'!$E$14+'[9]II-B-13 Gain on Disposition'!$E$14 -> 186359.76 | H14: =SUM(E14:G14) -> 186359.76 | I14: 1 | J14: =H14 -> 186359.76 | K14: 29 | L14: DIRECT | N14: =E14 -> 186359.76 | Q14: =SUM(M14:P14) -> 186359.76 | R14: =Q14-H14 -> 0
A15: =A14+1 -> 3 | C15: 4,649.84 acres of Walker County Site, Texas to
A16: =A15+1 -> 4 | C16: Nestle Waters North America, Inc
A17: =A16+1 -> 5
A18: =A17+1 -> 6 | B18: Total | E18: =SUM(E13:E17) -> 186359.76 | F18: =SUM(F13:F17) -> 0 | G18: =SUM(G13:G17) -> 0 | H18: =SUM(H13:H17) -> 186359.76 | J18: =SUM(J13:J17) -> 186359.76 | M18: =SUM(M13:M17) -> 0 | N18: =SUM(N13:N17) -> 186359.76 | O18: =SUM(O13:O17) -> 0 | P18: =SUM(P13:P17) -> 0 | Q18: =SUM(Q13:Q17) -> 186359.76

Sheet II-C-1 ROR
I1: Scheduled II-C-1
B2: PUBLIC UTILITY COMMISSION OF TEXAS
B3: AEP TEXAS INC
B4: II-C-1 RATE OF RETURN CALCULATION
B5: TEST YEAR ENDING 12/31/2018
B6: ='I-A'!B6
D8: 1 | E8: 2 | F8: 3 | G8: 4 | H8: 5 | I8: 6
D9: Company | E9: Transmission | F9: Distribution | G9: Metering | H9: T&D Customer
C10: Reference | D10: Total | E10: Function | F10: Function | G10: Function | H10: Service | I10: Total
A11: Line | B11: Description | C11: Schedule | D11: Request | E11: (TRAN) | F11: (DIST) | G11: (MET) | H11: (TDCS) | I11: TX-Retail
A12: No.
A14: 1 | B14: Requested Rate Base | C14: II-B | D14: ='II-B'!F35 -> 5.0690717e+09 | E14: ='II-B'!G35 -> 2.6350869e+09 | F14: ='II-B'!H35 -> 2.2982853e+09 | G14: =+'II-B'!I35 -> 1.248162e+08 | H14: =+'II-B'!J35 -> 10883273 | I14: =SUM(F14:H14) -> 2.4339848e+09
A15: =+A14+1 -> 2 | B15: Weighted Cost of Capital | C15: II-C-2.1 | D15: ='II-C-2.1'!$G$25 -> 0.070767 | E15: ='II-C-2.1'!$G$25 -> 0.070767 | F15: ='II-C-2.1'!$G$25 -> 0.070767 | G15: ='II-C-2.1'!$G$25 -> 0.070767 | H15: ='II-C-2.1'!$G$25 -> 0.070767 | I15: ='II-C-2.1'!$G$25 -> 0.070767
A16: =+A15+1 -> 3 | B16: Return on Rate Base In Revenue Requirement | D16: =+D14*D15 -> 3.58723e+08 | E16: =+E14*E15 -> 1.8647719e+08 | F16: =+F14*F15 -> 1.6264276e+08 | G16: =+G14*G15 -> 8832868 | H16: =+H14*H15 -> 770176.56 | I16: =+I14*I15 -> 1.722458e+08
A17: =+A16+1 -> 4
A18: =+A17+1 -> 5
A19: =+A18+1 -> 6
A20: =+A19+1 -> 7 | B20: The final revenue requirement is based on the rate of return method. Schedule II-B reflects the components of the total requested rate base for determining the allowed return on rate base. Schedule II-C-2.1 calculates the Weighted Cost of Capital used in determining the requested return on rate base.
A21: =+A20+1 -> 8

Sheet II-C-1.1 ROR Method
K1: Schedule II-C-1.1
B2: PUBLIC UTILITY COMMISSION OF TEXAS
B3: AEP TEXAS INC
B4: II-C-1.1 RATE OF RETURN METHOD
B5: TEST YEAR ENDING 12/31/2018
B6: ='I-A'!B6
D8: 1 | E8: 2 | F8: 3 | G8: 4 | H8: 5 | I8: 6 | J8: 7 | K8: 8
D9: Test Year | F9: Company | G9: Transmission | H9: Distribution | I9: Metering | J9: T&D Customer
C10: Reference | D10: Total | E10: Company | F10: Total | G10: Function | H10: Function | I10: Function | J10: Service | K10: Total
A11: Line | B11: Description | C11: Schedule | D11: Electric | E11: Adjustments | F11: Request | G11: (TRAN) | H11: (DIST) | I11: (MET) | J11: (TDCS) | K11: TX-Retail
A12: No.
A14: 1 | B14: Weighted Cost of Capital
A15: =+A14+1 -> 2 | B15: Common Equity | F15: ='II-C-2.1'!G22 -> 0.04725
A16: =+A15+1 -> 3 | B16: Preferred Stock | F16: 0
A17: =+A16+1 -> 4 | B17: Long Term Debt | F17: ='II-C-2.1'!G23 -> 0.023517
A18: =+A17+1 -> 5 | F18: =SUM(F15:F17) -> 0.070767
A19: =+A18+1 -> 6
A20: =+A19+1 -> 7
A21: =+A20+1 -> 8
A22: =+A21+1 -> 9
A23: =+A22+1 -> 10
A24: =+A23+1 -> 11 | B24: AEP Texas has used a 55% debt and 45% common equity ratio in quantifying its WCOC. See Schedule II-C-2.1
A25: =+A24+1 -> 12

Sheet II-C-2.1
I1: Schedule II-C-2.1
B2: PUBLIC UTILITY COMMISSION OF TEXAS
B3: AEP TEXAS INC
B4: II-C-2.1 WEIGHTED AVERAGE COST OF CAPITAL
B5: TEST YEAR ENDING 12/31/2018
B6: ='I-A'!B6
A9: Line | E9: Percent of | G9: Weighted
A10: No. | D10: Balance | E10: Total | F10: Cost | G10: Cost
A12: 1 | B12: Common Equity | D12: 2566689482 | E12: =D12/D15 -> 0.45333386 | F12: 0.105 | G12: =ROUND(+E12*F12,6) -> 0.0476
A13: =A12+1 -> 2 | B13: Long-Term Debt | D13: ='II-C-2.4'!W48 -> 3095118968 | E13: =D13/D15 -> 0.54666614 | F13: =+'II-C-2.4a'!K39 -> 0.042757762 | G13: =ROUND(+E13*F13,6) -> 0.023374
A14: =A13+1 -> 3
A15: =A14+1 -> 4 | B15: Total | D15: =SUM(D12:D13) -> 5661808450 | E15: =SUM(E12:E13) -> 1 | G15: =SUM(G12:G13) -> 0.070974
A16: =A15+1 -> 5
A17: =A16+1 -> 6
A18: =A17+1 -> 7
A19: =A18+1 -> 8 | B19: Adjusted to 45/55 Capital Structure | E19: Percent of | G19: Weighted
A20: =A19+1 -> 9 | E20: Total | F20: Cost | G20: Cost
A21: =A20+1 -> 10
A22: =A21+1 -> 11 | B22: Common Equity | E22: 0.45 | F22: =F12 -> 0.105 | G22: =ROUND(+E22*F22,6) -> 0.04725
A23: =A22+1 -> 12 | B23: Long-Term Debt | E23: 0.55 | F23: =F13 -> 0.042757762 | G23: =ROUND(+E23*F23,6) -> 0.023517
A24: =A23+1 -> 13
A25: =A24+1 -> 14 | B25: Total | E25: =SUM(E22:E24) -> 1 | G25: =SUM(G22:G24) -> 0.070767

Sheet II-C-2.2
B2: PUBLIC UTILITY COMMISSION OF TEXAS
B3: AEP TEXAS INC
B4: II-C-2.2 Weighted Average Cost of Preferred Stock
B5: For Test Year Ended 12/31/18
B6: ='I-A'!B6
C7: (a) | E7: (b) | G7: (c) | I7: (d) | K7: (e) | M7: (f) | O7: (g) | Q7: (h) | S7: (i) | U7: (j) | W7: (k) | Y7: (l) | AA7: (m) | AC7: (n) | AE7: (o)
O8: Underwriting | Q8: Gain or | U8: Net | AA8: Issue
G9: Mandatory | M9: Premium | O9: Fees and | Q9: (Loss) on | S9: Original | U9: Proceeds | W9: Par Value | Y9: Current | AA9: As % of | AC9: Cost | AE9: Weighted
A10: Line | E10: Issuance | G10: Redemption | I10: Dividend | K10: Par Value | M10: or | O10: Issuance | Q10: Redeemed | S10: Net | U10: As % of | W10: Currently | Y10: Net | AA10: Total Net | AC10: of | AE10: Average
A11: No. | C11: Description | E11: Date | G11: (Y/N) | I11: Rate | K11: at Issuance | M11: (Discount) | O11: Expenses | Q11: Stock | S11: Proceeds | U11: Par | W11: Outstanding | Y11: Proceeds | AA11: Proceeds | AC11: Money | AE11: Cost
A13: 1 | C13: XX | E13: XX/XX/XX | G13: X | I13: 0 | K13: 0 | M13: 0 | O13: 0 | Q13: 0 | S13: =K13+M13-O13+Q13 -> 0 | U13: =IF(ISERR(S13/K13),0,S13/K13) -> 0 | W13: 0 | Y13: =U13*W13 -> 0 | AA13: =IF(ISERR(Y13/$Y$18),0,Y13/$Y$18) -> 0 | AC13: 0 | AE13: =AA13*AC13 -> 0
A14: 2 | C14: XX | E14: XX/XX/XX | G14: X | I14: 0 | K14: 0 | M14: 0 | O14: 0 | Q14: 0 | S14: =K14+M14-O14+Q14 -> 0 | U14: =IF(ISERR(S14/K14),0,S14/K14) -> 0 | W14: 0 | Y14: =U14*W14 -> 0 | AA14: =IF(ISERR(Y14/$Y$18),0,Y14/$Y$18) -> 0 | AC14: 0 | AE14: =AA14*AC14 -> 0
A15: 3 | C15: XX | E15: XX/XX/XX | G15: X | I15: 0 | K15: 0 | M15: 0 | O15: 0 | Q15: 0 | S15: =K15+M15-O15+Q15 -> 0 | U15: =IF(ISERR(S15/K15),0,S15/K15) -> 0 | W15: 0 | Y15: =U15*W15 -> 0 | AA15: =IF(ISERR(Y15/$Y$18),0,Y15/$Y$18) -> 0 | AC15: 0 | AE15: =AA15*AC15 -> 0
A16: 4 | C16: XX | E16: XX/XX/XX | G16: X | I16: 0 | K16: 0 | M16: 0 | O16: 0 | Q16: 0 | S16: =K16+M16-O16+Q16 -> 0 | U16: =IF(ISERR(S16/K16),0,S16/K16) -> 0 | W16: 0 | Y16: =U16*W16 -> 0 | AA16: =IF(ISERR(Y16/$Y$18),0,Y16/$Y$18) -> 0 | AC16: 0 | AE16: =AA16*AC16 -> 0
A18: 5 | Q18: Total | W18: =SUM(W13:W16) -> 0 | Y18: =SUM(Y13:Y16) -> 0 | AA18: =SUM(AA13:AA16) -> 0 | AE18: =SUM(AE13:AE16) -> 0
A20: 6 | O20: Plus: | Q20: Unamortized Premium (Discount) | W20: 0
A21: 7 | O21: Less: | Q21: Unamortized Fees and Issuance Expenses | W21: 0
A22: 8 | O22: Plus: | Q22: Unamort. Gains (Losses) on Redeemed Stock | W22: 0
A23: 9
A24: 10 | Q24: Net Balance of Preferred Stock | W24: =W18+W20-W21+W22 -> 0

Sheet II-C-2.2a
J1: Schedule II-C-2.2a
B2: PUBLIC UTILITY COMMISSION OF TEXAS
B3: AEP TEXAS INC
B4: II-C-2.2a Adjusted Cost of Preferred Stock
B5: For Test Year Ended 12/31/18
A14: Line
A15: No
A16: 1 | C16: Balance of Unamortized Gains (Losses) on | J16: ='II-C-2.2'!W22 -> 0
A17: =A16+1 -> 2 | C17: Redeemed Stock (Sched.II-C-2.2)
A18: =A17+1 -> 3 | B18: - | C18: Balance Related to Gains (Losses) Identified
A19: =A18+1 -> 4 | C19: in Col.(h) of Schedule II-C-2.2
A20: =A19+1 -> 5
A21: =A20+1 -> 6 | C21: Net Balance of Unamortized Gains (Losses) Not | J21: =+J16-J18 -> 0
A22: =A21+1 -> 7 | C22: Accounted for in Col.(h) of Schedule II-C-2.2
A23: =A22+1 -> 8
A24: =A23+1 -> 9
A25: =A24+1 -> 10 | C25: Annual Amortization of Gains (Losses) on | J25: 0
A26: =A25+1 -> 11 | C26: Redeemed Stock
A27: =A26+1 -> 12 | B27: - | C27: Annual Amortization Related to Gains (Losses) | J27: 0
A28: =A27+1 -> 13 | C28: Identified in Col.(h) of Schedule II-C-2.2
A29: =A28+1 -> 14
A30: =A29+1 -> 15 | C30: Net Annual Amortization of Gains (Losses) Not | J30: =+J25-J27 -> 0
A31: =A30+1 -> 16 | C31: Accounted for in Col.(h) of Schedule II-C-2.2
A32: =A31+1 -> 17
A33: =A32+1 -> 18
A34: =A33+1 -> 19 | C34: Net Balance of Preferred Stock (Sched.II-C-2.2) | J34: ='II-C-2.2'!W24 -> 0
A35: =A34+1 -> 20 | B35: - | C35: Net Balance of Unamortized Gains (Losses) from Line 6 | J35: =J21 -> 0
A36: =A35+1 -> 21
A37: =A36+1 -> 22 | C37: Preferred Stock Balance Excluding Net Gains (Losses) | J37: =+J34-J35 -> 0
A38: =A37+1 -> 23
A39: =A38+1 -> 24 | B39: x | C39: Weighted Average Cost of Preferred Stock (Sched.II-C-2.2) | J39: ='II-C-2.2'!AE18 -> 0
A40: =A39+1 -> 25
A41: =A40+1 -> 26 | C41: Annual Preferred Stock Requirement | J41: =+J37*J39 -> 0
A42: =A41+1 -> 27
A43: =A42+1 -> 28 | B43: - | C43: Net Amortization of Gains (Losses) from Line 15 | J43: =J30 -> 0
A44: =A43+1 -> 29
A45: =A44+1 -> 30 | C45: Adjusted Annual Preferred Stock Requirement | J45: =+J41-J43 -> 0
A46: =A45+1 -> 31
A47: =A46+1 -> 32 | C47: Adjusted Cost of Preferred Stock (Line 30/Line 19) | J47: =+J45/J34 -> #DIV/0!

Sheet II-C-2.3
AE1: Schedule II-C-2.3
B2: PUBLIC UTILITY COMMISSION OF TEXAS
B3: AEP TEXAS INC
B4: II-C-2.3 Weighted Average Cost of Preferred Trust Securities
B5: For Test Year Ended 12/31/18
C6: (a) | E6: (b) | G6: (c) | I6: (d) | K6: (e) | M6: (f) | O6: (g) | Q6: (h) | S6: (i) | U6: (j) | W6: (k) | Y6: (l) | AA6: (m) | AC6: (n) | AE6: (o)
O7: Underwriting | Q7: Gain or | U7: Net | AA7: Issue | AC7: Cost
M8: Premium | O8: Fees and | Q8: (Loss) on | S8: Original | U8: Proceeds | W8: Par Value | Y8: Current | AA8: As % of | AC8: of | AE8: Weighted
A9: Line | E9: Issuance | G9: Maturity | I9: Interest | K9: Par Value | M9: or | O9: Issuance | Q9: Redeemed | S9: Net | U9: As % of | W9: Currently | Y9: Net | AA9: Total Net | AC9: Money | AE9: Average
A10: No. | C10: Description | E10: Date | G10: Date | I10: Rate | K10: at Issuance | M10: (Discount) | O10: Expenses | Q10: Stock | S10: Proceeds | U10: Par | W10: Outstanding | Y10: Proceeds | AA10: Proceeds | AC10: (see note) | AE10: Cost
A12: 1 | C12: XX | E12: XX/XX/XX | G12: X | I12: 0 | K12: 0 | M12: 0 | O12: 0 | Q12: 0 | S12: =K12+M12-O12+Q12 -> 0 | U12: =IF(ISERR(S12/K12),0,S12/K12) -> 0 | W12: 0 | Y12: =U12*W12 -> 0 | AA12: =IF(ISERR(Y12/$Y$16),0,Y12/$Y$16) -> 0 | AC12: 0 | AE12: =AA12*AC12 -> 0
A13: =A12+1 -> 2 | C13: XX | E13: XX/XX/XX | G13: X | I13: 0 | K13: 0 | M13: 0 | O13: 0 | Q13: 0 | S13: =K13+M13-O13+Q13 -> 0 | U13: =IF(ISERR(S13/K13),0,S13/K13) -> 0 | W13: 0 | Y13: =U13*W13 -> 0 | AA13: =IF(ISERR(Y13/$Y$16),0,Y13/$Y$16) -> 0 | AC13: 0 | AE13: =AA13*AC13 -> 0
A14: =A13+1 -> 3 | C14: XX | E14: XX/XX/XX | G14: X | I14: 0 | K14: 0 | M14: 0 | O14: 0 | Q14: 0 | S14: =K14+M14-O14+Q14 -> 0 | U14: =IF(ISERR(S14/K14),0,S14/K14) -> 0 | W14: 0 | Y14: =U14*W14 -> 0 | AA14: =IF(ISERR(Y14/$Y$16),0,Y14/$Y$16) -> 0 | AC14: 0 | AE14: =AA14*AC14 -> 0
A15: =A14+1 -> 4
A16: =A15+1 -> 5 | Q16: Total | W16: =SUM(W12:W14) -> 0 | Y16: =SUM(Y12:Y14) -> 0 | AA16: =SUM(AA12:AA14) -> 0 | AE16: =SUM(AE12:AE14) -> 0
A17: =A16+1 -> 6
A18: =A17+1 -> 7 | O18: Plus: | Q18: Unamortized Premium (Discount) | W18: 0
A19: =A18+1 -> 8 | B19: Note: The cost (column n) of Preferred Trust Securities should be reported on a pre-tax basis; that is, | O19: Less: | Q19: Unamortized Fees and Issuance Expenses | W19: 0
A20: =A19+1 -> 9 | B20: do NOT multiply the cost by [1- tax rate] when completing this schedule. | O20: Plus: | Q20: Unamort. Gains (Losses) on Redeemed Securities | W20: 0
A21: =A20+1 -> 10
A22: =A21+1 -> 11 | Q22: Net Balance of Preferred Trust Securities | W22: =W16+W18-W19+W20 -> 0

Sheet II-C-2.3a
J1: Schedule II-C-2.3a
B2: PUBLIC UTILITY COMMISSION OF TEXAS
B3: AEP TEXAS INC
B4: II-C-2.3a Adjusted Cost of Preferred Trust Securities
A6: Line No.
A7: 1 | C7: Balance of Unamortized Gains (Losses) on | J7: ='II-C-2.3'!W20 -> 0
A8: =A7+1 -> 2 | C8: Redeemed Securities (Sched.II-C-2.3)
A9: =A8+1 -> 3 | B9: - | C9: Balance Related to Gains (Losses) Identified | J9: 0
A10: =A9+1 -> 4 | C10: in Col.(h) of Schedule II-C-2.3
A11: =A10+1 -> 5
A12: =A11+1 -> 6 | C12: Net Balance of Unamortized Gains (Losses) Not | J12: =+J7-J9 -> 0
A13: =A12+1 -> 7 | C13: Accounted for in Col.(h) of Schedule II-C-2.3
A14: =A13+1 -> 8
A15: =A14+1 -> 9
A16: =A15+1 -> 10 | C16: Annual Amortization of Gains (Losses) on | J16: 0
A17: =A16+1 -> 11 | C17: Redeemed Securities
A18: =A17+1 -> 12 | B18: - | C18: Annual Amortization Related to Gains (Losses) | J18: 0
A19: =A18+1 -> 13 | C19: Identified in Col.(h) of Schedule II-C-2.3
A20: =A19+1 -> 14
A21: =A20+1 -> 15 | C21: Net Annual Amortization of Gains (Losses) Not | J21: =+J16-J18 -> 0
A22: =A21+1 -> 16 | C22: Accounted for in Col.(h) of Schedule II-C-2.3
A23: =A22+1 -> 17
A24: =A23+1 -> 18
A25: =A24+1 -> 19 | C25: Net Balance of Preferred Trust Securities (Sched.II-C-2.3) | J25: ='II-C-2.3'!W22 -> 0
A26: =A25+1 -> 20 | B26: - | C26: Net Balance of Unamortized Gains (Losses) from Line 6 | J26: =J12 -> 0
A27: =A26+1 -> 21
A28: =A27+1 -> 22 | C28: Preferred Trust Securities Balance Excluding Net Gains (Losses) | J28: =+J25-J26 -> 0
A29: =A28+1 -> 23
A30: =A29+1 -> 24 | B30: x | C30: Weighted Average Cost of Preferred Trust Securities (Sched.II-C-2.3) | J30: ='II-C-2.3'!AE16 -> 0
A31: =A30+1 -> 25
A32: =A31+1 -> 26 | C32: Annual Preferred Trust Securities Requirement | J32: =+J28*J30 -> 0
A33: =A32+1 -> 27
A34: =A33+1 -> 28 | B34: - | C34: Net Amortization of Gains (Losses) from Line 15 | J34: =J21 -> 0
A35: =A34+1 -> 29
A36: =A35+1 -> 30 | C36: Adjusted Annual Preferred Trust Securities Requirement | J36: =+J32-J34 -> 0
A37: =A36+1 -> 31
A38: =A37+1 -> 32 | C38: Adjusted Cost of Preferred Trust Securities (Line 30/Line 19) | J38: 0

Sheet II-C-2.4
C1: PUBLIC UTILITY COMMISSION OF TEXAS | AE1: Schedule II-C-2.4
C2: AEP TEXAS INC
C3: II-C-2.4 Weighted Average Cost of Long-Term Debt
C4: For Test Year Ended 12/31/2018
C7: (a) | E7: (b) | G7: (c) | I7: (d) | K7: (e) | M7: (f) | O7: (g) | Q7: (h) | S7: (i) | U7: (j) | W7: (k) | Y7: (l) | AA7: (m) | AC7: (n) | AE7: (o)
K8: Principal | M8: Premium | O8: Underwriting | Q8: Gain or (Loss) | S8: Original | U8: Proceeds | W8: Principal | Y8: Current | AA8: Issue As | AE8: Weighted
E9: Issuance | G9: Maturity | I9: Interest | K9: Amount | M9: or | O9: Fees and | Q9: on Reacquired | S9: Net | U9: As % of | W9: Currently | Y9: Net | AA9: % of Total | AC9: Cost | AE9: Average
A10: Line | C10: Description | E10: Date | G10: Date | I10: Rate | K10: at Issuance | M10: (Discount) | O10: Issuance Exp | Q10: Debt | S10: Proceeds | U10: Par | W10: Outstanding | Y10: Proceeds | AA10: Net Proceeds | AC10: of Debt | AE10: Cost
C11: Senior Unsecured Notes
A12: 1 | C12: Senior Note, Series 2008B | E12: 39539 | G12: 50496 | I12: 0.0676 | K12: 70000000 | M12: 0 | O12: 457765 | Q12: 0 | S12: 69542235 | U12: =IF(ISERR(S12/K12),0,S12/K12) -> 0.9934605 | W12: 70000000 | Y12: =U12*W12 -> 69542235 | AA12: =IF(ISERR(Y12/$Y$42),0,Y12/$Y$42) -> 0.022555348 | AC12: =YIELD(E12,G12,(I12),(U12*100),100,2,2) -> 0.068114399 | AE12: =AA12*AC12 -> 0.001536344
A13: =A12+1 -> 2 | C13: Senior Note, Series A | E13: 41759 | G13: 43585 | I13: 0.0261 | K13: 50000000 | M13: 0 | O13: =106723.95+123998.6+6290.87+7309.13 -> 244322.55 | Q13: 0 | S13: 49755677 | U13: =IF(ISERR(S13/K13),0,S13/K13) -> 0.99511355 | W13: 50000000 | Y13: =U13*W13 -> 49755677 | AA13: =IF(ISERR(Y13/$Y$42),0,Y13/$Y$42) -> 0.01613777 | AC13: =YIELD(E13,G13,(I13),(U13*100),100,2,2) -> 0.027151737 | AE13: =AA13*AC13 -> 0.0004381685
A14: =A13+1 -> 3 | C14: Senior Note, Series B - 3.81% | E14: 41759 | G14: 46142 | I14: 0.0381 | K14: 50000000 | M14: 0 | O14: =106723.95+123998.6+6290.87+7309.13 -> 244322.55 | Q14: 0 | S14: 49755677 | U14: =IF(ISERR(S14/K14),0,S14/K14) -> 0.99511355 | W14: 50000000 | Y14: =U14*W14 -> 49755677 | AA14: =IF(ISERR(Y14/$Y$42),0,Y14/$Y$42) -> 0.01613777 | AC14: =YIELD(E14,G14,(I14),(U14*100),100,2,2) -> 0.038612653 | AE14: =AA14*AC14 -> 0.00062312212
A15: =A14+1 -> 4 | C15: Senior Note, Series B - 6.65% | E15: 37670 | G15: 48625 | I15: 0.0665 | K15: 275000000 | M15: -1342000 | O15: 2504241 | Q15: 0 | S15: 271153759 | U15: =IF(ISERR(S15/K15),0,S15/K15) -> 0.98601367 | W15: 275000000 | Y15: =U15*W15 -> 271153759 | AA15: =IF(ISERR(Y15/$Y$42),0,Y15/$Y$42) -> 0.087946086 | AC15: =YIELD(E15,G15,(I15),(U15*100),100,2,2) -> 0.067593728 | AE15: =AA15*AC15 -> 0.0059446039
A16: =A15+1 -> 5 | C16: Senior Note, Series C | E16: 41759 | G16: 52717 | I16: 0.0467 | K16: 100000000 | M16: 0 | O16: =207170.01+240703.17+12211.69+14188.31 -> 474273.18 | Q16: 0 | S16: 99525727 | U16: =IF(ISERR(S16/K16),0,S16/K16) -> 0.99525727 | W16: 100000000 | Y16: =U16*W16 -> 99525727 | AA16: =IF(ISERR(Y16/$Y$42),0,Y16/$Y$42) -> 0.032280202 | AC16: =YIELD(E16,G16,(I16),(U16*100),100,2,2) -> 0.046996471 | AE16: =AA16*AC16 -> 0.0015170556
A17: =A16+1 -> 6 | C17: Senior Note, Series C 2.40% | E17: 43000 | G17: 44835 | I17: 0.024 | K17: 400000000 | M17: -696000 | O17: 2400000 | Q17: 0 | S17: 396904000 | U17: =IF(ISERR(S17/K17),0,S17/K17) -> 0.99226 | W17: 400000000 | Y17: =U17*W17 -> 396904000 | AA17: =IF(ISERR(Y17/$Y$42),0,Y17/$Y$42) -> 0.12873195 | AC17: =YIELD(E17,G17,(I17),(U17*100),100,2,2) -> 0.025653598 | AE17: =AA17*AC17 -> 0.0033024378
A18: =A17+1 -> 7 | C18: Senior Note, Series D | E18: 41942 | G18: 52900 | I18: 0.0477 | K18: 100000000 | M18: 0 | O18: =207170.01+240703.17+12211.69+14188.31 -> 474273.18 | Q18: 0 | S18: 99525727 | U18: =IF(ISERR(S18/K18),0,S18/K18) -> 0.99525727 | W18: 100000000 | Y18: =U18*W18 -> 99525727 | AA18: =IF(ISERR(Y18/$Y$42),0,Y18/$Y$42) -> 0.032280202 | AC18: =YIELD(E18,G18,(I18),(U18*100),100,2,2) -> 0.047999932 | AE18: =AA18*AC18 -> 0.0015494475
A19: =A18+1 -> 8 | C19: Senior Note, Series D 3.80% | E19: 43000 | G19: 53966 | I19: 0.038 | K19: 300000000 | M19: -3450000 | O19: 2625000 | Q19: 0 | S19: 293925000 | U19: =IF(ISERR(S19/K19),0,S19/K19) -> 0.97975 | W19: 300000000 | Y19: =U19*W19 -> 293925000 | AA19: =IF(ISERR(Y19/$Y$42),0,Y19/$Y$42) -> 0.095331717 | AC19: =YIELD(E19,G19,(I19),(U19*100),100,2,2) -> 0.039152502 | AE19: =AA19*AC19 -> 0.0037324753
A20: =A19+1 -> 9 | C20: Senior Note, Series E | E20: 42277 | G20: 44834 | I20: 0.0327 | K20: 25000000 | M20: 0 | O20: 126464.11 | Q20: 0 | S20: 24873536 | U20: =IF(ISERR(S20/K20),0,S20/K20) -> 0.99494144 | W20: 25000000 | Y20: =U20*W20 -> 24873536 | AA20: =IF(ISERR(Y20/$Y$42),0,Y20/$Y$42) -> 0.0080674896 | AC20: =YIELD(E20,G20,(I20),(U20*100),100,2,2) -> 0.033516748 | AE20: =AA20*AC20 -> 0.00027039602
A21: =A20+1 -> 10 | C21: Senior Note, Series E 3.95% | E21: 43237 | G21: 46905 | I21: 0.0395 | K21: 500000000 | M21: -1650000 | O21: 3250000 | Q21: 0 | S21: 495100000 | U21: =IF(ISERR(S21/K21),0,S21/K21) -> 0.9902 | W21: 500000000 | Y21: =U21*W21 -> 495100000 | AA21: =IF(ISERR(Y21/$Y$42),0,Y21/$Y$42) -> 0.16058087 | AC21: =YIELD(E21,G21,(I21),(U21*100),100,2,2) -> 0.04069756 | AE21: =AA21*AC21 -> 0.0065352498
A22: =A21+1 -> 11 | C22: Senior Note, Series F | E22: 42277 | G22: 45930 | I22: 0.0375 | K22: 50000000 | M22: 0 | O22: 252928.21 | Q22: 0 | S22: 49747072 | U22: =IF(ISERR(S22/K22),0,S22/K22) -> 0.99494144 | W22: 50000000 | Y22: =U22*W22 -> 49747072 | AA22: =IF(ISERR(Y22/$Y$42),0,Y22/$Y$42) -> 0.016134979 | AC22: =YIELD(E22,G22,(I22),(U22*100),100,2,2) -> 0.038113111 | AE22: =AA22*AC22 -> 0.00061495426
A23: =A22+1 -> 12 | C23: Senior Note, Series G | E23: 42265 | G23: 45931 | I23: 0.0385 | K23: 250000000 | M23: -2447500 | O23: 1625000 | Q23: 0 | S23: 245927500 | U23: =IF(ISERR(S23/K23),0,S23/K23) -> 0.98371 | W23: 250000000 | Y23: =U23*W23 -> 245927500 | AA23: =IF(ISERR(Y23/$Y$42),0,Y23/$Y$42) -> 0.079764195 | AC23: =YIELD(E23,G23,(I23),(U23*100),100,2,2) -> 0.040491475 | AE23: =AA23*AC23 -> 0.0032297699
A24: =A23+1 -> 13 | C24: Senior Note, Series G | E24: 42353 | G24: 49658 | I24: 0.0471 | K24: 50000000 | M24: 0 | O24: 252928.21 | Q24: 0 | S24: 49747072 | U24: =IF(ISERR(S24/K24),0,S24/K24) -> 0.99494144 | W24: 50000000 | Y24: =U24*W24 -> 49747072 | AA24: =IF(ISERR(Y24/$Y$42),0,Y24/$Y$42) -> 0.016134979 | AC24: =YIELD(E24,G24,(I24),(U24*100),100,2,2) -> 0.047494572 | AE24: =AA24*AC24 -> 0.00076632393
A25: =A24+1 -> 14 | C25: Senior Notes, Series C | E25: 41313 | G25: 44985 | I25: 0.0309 | K25: 125000000 | M25: 0 | O25: 597740.92 | Q25: 0 | S25: 1.2440226e+08 | U25: =IF(ISERR(S25/K25),0,S25/K25) -> 0.99521807 | W25: 125000000 | Y25: =U25*W25 -> 1.2440226e+08 | AA25: =IF(ISERR(Y25/$Y$42),0,Y25/$Y$42) -> 0.040348664 | AC25: =YIELD(E25,G25,(I25),(U25*100),100,2,2) -> 0.031457221 | AE25: =AA25*AC25 -> 0.0012692568
A26: =A25+1 -> 15 | C26: Senior Notes, Series D | E26: 41313 | G26: 52289 | I26: 0.0448 | K26: 75000000 | M26: 0 | O26: 358644.55 | Q26: 0 | S26: 74641355 | U26: =IF(ISERR(S26/K26),0,S26/K26) -> 0.99521807 | W26: 75000000 | Y26: =U26*W26 -> 74641355 | AA26: =IF(ISERR(Y26/$Y$42),0,Y26/$Y$42) -> 0.024209198 | AC26: =YIELD(E26,G26,(I26),(U26*100),100,2,2) -> 0.045090986 | AE26: =AA26*AC26 -> 0.0010916166
A27: =A26+1 -> 16 | C27: Matagorda Cnty Navigation Dist. #1 PCRB, Series 2008-1 | E27: 41428 | G27: 47635 | I27: 0.04 | K27: 60265000 | M27: 0 | O27: 438769.75 | Q27: 0 | S27: =K27+M27-O27+Q27 -> 59826230 | U27: =IF(ISERR(S27/K27),0,S27/K27) -> 0.99271933 | W27: 60265000 | Y27: =U27*W27 -> 59826230 | AA27: =IF(ISERR(Y27/$Y$42),0,Y27/$Y$42) -> 0.019404056 | AC27: =YIELD(E27,G27,(I27),(U27*100),100,2,2) -> 0.040597049 | AE27: =AA27*AC27 -> 0.00078774742
A28: =A27+1 -> 17 | C28: Matagorda Cnty Navigation Dist. #1 PCRB, Series 2008-2 | E28: 41428 | G28: 47635 | I28: 0.04 | K28: 60000000 | M28: 0 | O28: 436840.37 | Q28: 0 | S28: =K28+M28-O28+Q28 -> 59563160 | U28: =IF(ISERR(S28/K28),0,S28/K28) -> 0.99271933 | W28: 60000000 | Y28: =U28*W28 -> 59563160 | AA28: =IF(ISERR(Y28/$Y$42),0,Y28/$Y$42) -> 0.019318732 | AC28: =YIELD(E28,G28,(I28),(U28*100),100,2,2) -> 0.040597049 | AE28: =AA28*AC28 -> 0.00078428351
A29: =A28+1 -> 18 | C29: Matagorda Cnty Navigation District #1, Series 1996 | E29: 42968 | G29: 47604 | I29: 0.0175 | K29: 60000000 | M29: 0 | O29: 439653.85 | Q29: 0 | S29: =K29+M29-O29+Q29 -> 59560346 | U29: =IF(ISERR(S29/K29),0,S29/K29) -> 0.99267244 | W29: 60000000 | Y29: =U29*W29 -> 59560346 | AA29: =IF(ISERR(Y29/$Y$42),0,Y29/$Y$42) -> 0.019317819 | AC29: =YIELD(E29,G29,(I29),(U29*100),100,2,2) -> 0.018148301 | AE29: =AA29*AC29 -> 0.00035058561
A30: =A29+1 -> 19 | C30: Matagorda Cnty Navigation District #1, Series 2005A | E30: 39057 | G30: 47604 | I30: 0.0456 | K30: 111700000 | M30: 0 | O30: 1277849 | Q30: 0 | S30: =K30+M30-O30+Q30 -> 110422151 | U30: =IF(ISERR(S30/K30),0,S30/K30) -> 0.98855999 | W30: 111700000 | Y30: =U30*W30 -> 110422151 | AA30: =IF(ISERR(Y30/$Y$42),0,Y30/$Y$42) -> 0.035814352 | AC30: =YIELD(E30,G30,(I30),(U30*100),100,2,2) -> 0.046403633 | AE30: =AA30*AC30 -> 0.001661916
A31: =A30+1 -> 20 | C31: Matagorda Cnty Navigation District #1, Series 2005B | E31: 39057 | G31: 47604 | I31: 0.0471 | K31: 50000000 | M31: 0 | O31: 552686 | Q31: 0 | S31: =K31+M31-O31+Q31 -> 49447314 | U31: =IF(ISERR(S31/K31),0,S31/K31) -> 0.98894628 | W31: 50000000 | Y31: =U31*W31 -> 49447314 | AA31: =IF(ISERR(Y31/$Y$42),0,Y31/$Y$42) -> 0.016037756 | AC31: =YIELD(E31,G31,(I31),(U31*100),100,2,2) -> 0.047887393 | AE31: =AA31*AC31 -> 0.00076800632
A32: =A31+1 -> 21 | C32: Matagorda PCB Series 2001A | E32: 39995 | G32: 47423 | I32: 0.063 | K32: 100635000 | M32: 0 | O32: 814384.03 | Q32: 0 | S32: =K32+M32-O32+Q32 -> 99820616 | U32: =IF(ISERR(S32/K32),0,S32/K32) -> 0.99190755 | W32: 100635000 | Y32: =U32*W32 -> 99820616 | AA32: =IF(ISERR(Y32/$Y$42),0,Y32/$Y$42) -> 0.032375847 | AC32: =YIELD(E32,G32,(I32),(U32*100),100,2,2) -> 0.063705698 | AE32: =AA32*AC32 -> 0.0020625259
A33: =A32+1 -> 22 | C33: Red River Authority of Texas PCRB (CPL, PSO, WTU) | E33: 39240 | G33: 43983 | I33: 0.0459 | K33: 6330000 | M33: 0 | O33: 95402 | Q33: 0 | S33: =K33+M33-O33+Q33 -> 6234598 | U33: =IF(ISERR(S33/K33),0,S33/K33) -> 0.98492859 | W33: 6330000 | Y33: =U33*W33 -> 6234598 | AA33: =IF(ISERR(Y33/$Y$42),0,Y33/$Y$42) -> 0.0020221313 | AC33: =YIELD(E33,G33,(I33),(U33*100),100,2,2) -> 0.047467439 | AE33: =AA33*AC33 -> 9.5985393e-05
A34: =A33+1 -> 23 | C34: Red River Authority of Texas PCRB (CPL, PSO, WTU) | E34: 39240 | G34: 43983 | I34: 0.0445 | K34: 44310000 | M34: 0 | O34: 673131 | Q34: 0 | S34: =K34+M34-O34+Q34 -> 43636869 | U34: =IF(ISERR(S34/K34),0,S34/K34) -> 0.9848086 | W34: 44310000 | Y34: =U34*W34 -> 43636869 | AA34: =IF(ISERR(Y34/$Y$42),0,Y34/$Y$42) -> 0.014153194 | AC34: =YIELD(E34,G34,(I34),(U34*100),100,2,2) -> 0.04606685 | AE34: =AA34*AC34 -> 0.00065199308
A35: =A34+1 -> 24
A36: =A35+1 -> 25 | C36: 3 yr Credit Facility - TNC | E36: 42576 | G36: 43671 | I36: 0.039375 | K36: 75000000 | M36: 0 | O36: 299082 | Q36: 0 | S36: =K36+M36-O36+Q36 -> 74700918 | U36: =IF(ISERR(S36/K36),0,S36/K36) -> 0.99601224 | W36: =+K36 -> 75000000 | Y36: =U36*W36 -> 74700918 | AA36: =IF(ISERR(Y36/$Y$42),0,Y36/$Y$42) -> 0.024228517 | AC36: =YIELD(E36,G36,(I36),(U36*100),100,2,2) -> 0.040800761 | AE36: =AA36*AC36 -> 0.00098854191
A37: =A36+1 -> 26 | C37: 3 yr Credit Facility - TCC | E37: 42576 | G37: 43671 | I37: 0.039375 | K37: 125000000 | M37: 0 | O37: 495555.99 | Q37: 0 | S37: =K37+M37-O37+Q37 -> 1.2450444e+08 | U37: =IF(ISERR(S37/K37),0,S37/K37) -> 0.99603555 | W37: =+K37 -> 125000000 | Y37: =U37*W37 -> 1.2450444e+08 | AA37: =IF(ISERR(Y37/$Y$42),0,Y37/$Y$42) -> 0.040381806 | AC37: =YIELD(E37,G37,(I37),(U37*100),100,2,2) -> 0.040792406 | AE37: =AA37*AC37 -> 0.001647271
A38: =A37+1 -> 27 | C38: Goodfellow Air Force Base | E38: 40148 | G38: 58380 | I38: 0.045 | K38: 1001186.7 | M38: 0 | O38: 0 | Q38: 0 | S38: =K38+M38-O38+Q38 -> 1001186.7 | U38: =IF(ISERR(S38/K38),0,S38/K38) -> 1 | W38: 938397.23 | Y38: =U38*W38 -> 938397.23 | AA38: =IF(ISERR(Y38/$Y$42),0,Y38/$Y$42) -> 0.00030436002 | AC38: =YIELD(E38,G38,(I38),(U38*100),100,2,2) -> 0.04499825 | AE38: =AA38*AC38 -> 1.3695668e-05
A39: =A38+1 -> 28
A40: =A39+1 -> 29
A41: =A40+1 -> 30
A42: =A41+1 -> 31 | Q42: Total | W42: =SUM(W12:W38) -> 3.1141784e+09 | Y42: =SUM(Y12:Y38) -> 3.0831816e+09 | AA42: =SUM(AA12:AA38) -> 1 | AE42: =SUM(AE12:AE38) -> 0.042233774
A43: =A42+1 -> 32
A44: =A43+1 -> 33 | O44: Plus: | Q44: Unamortized Premium (Discount) | W44: 3565682.4
A45: =A44+1 -> 34 | O45: Less: | Q45: Unamortized Fees and Issuance Expenses | W45: 9469829.9
A46: =A45+1 -> 35 | O46: Plus: | Q46: Unamortized Gains (Losses) on Reacq. Debt | W46: ='II-C-2.4a'!K27 -> -6023917
A47: =A46+1 -> 36
A48: =A47+1 -> 37 | Q48: Net Balance of Debt | W48: =W42-W44-W45+W46 -> 3095118968

Sheet II-C-2.4a
B1: PUBLIC UTILITY COMMISSION OF TEXAS | K1: Schedule II-C-2.4a
B2: AEP TEXAS INC
B3: II-C-2.4a Cost of Long-Term Debt
B4: For Test Year Ended 12/31/2018
A6: Line
A7: No.
A8: 1 | C8: Balance of Unamortized Gains (Losses) on | K8: -6023917
A9: =A8+1 -> 2 | C9: Reacquired Debt (Sched.II-C-2.4)
A10: =A9+1 -> 3 | B10: - | C10: Balance Related to Gains (Losses) Identified | K10: 0
A11: =A10+1 -> 4 | C11: in Col.(h) of Schedule II-C-2.4
A12: =A11+1 -> 5
A13: =A12+1 -> 6 | C13: Net Balance of Unamortized Gains (Losses) Not | K13: =+K8+K10 -> -6023917
A14: =A13+1 -> 7 | C14: Accounted for in Col.(h) of Schedule II-C-2.4
A15: =A14+1 -> 8
A16: =A15+1 -> 9
A17: =A16+1 -> 10 | C17: Annual Amortization of Gains (Losses) on | K17: -1367393
A18: =A17+1 -> 11 | C18: Reacquired Debt
A19: =A18+1 -> 12 | B19: - | C19: Annual Amortization Related to Gains (Losses) | K19: 0
A20: =A19+1 -> 13 | C20: Identified in Col.(h) of Schedule II-C-2.4
A21: =A20+1 -> 14
A22: =A21+1 -> 15 | C22: Net Annual Amortization of Gains (Losses) Not | K22: =+K17+K19 -> -1367393
A23: =A22+1 -> 16 | C23: Accounted for in Col.(h) of Schedule II-C-2.4
A24: =A23+1 -> 17
A25: =A24+1 -> 18
A26: =A25+1 -> 19 | C26: Net Balance of Debt (Sched.II-C-2.4) | K26: ='II-C-2.4'!W48 -> 3095118968
A27: =A26+1 -> 20 | B27: - | C27: Net Balance of Unamortized Gains (Losses) from Line 6 | K27: =K13 -> -6023917
A28: =A27+1 -> 21
A29: =A28+1 -> 22 | C29: Debt Balance Excluding Net Gains (Losses) | K29: =+K26-K27 -> 3101142885
A30: =A29+1 -> 23
A31: =A30+1 -> 24 | B31: x | C31: Weighted Average Cost of Debt (Sched.II-C-2.4) | K31: ='II-C-2.4'!AE42 -> 0.042233774
A32: =A31+1 -> 25
A33: =A32+1 -> 26 | C33: Annual Debt Requirement | K33: =+K29*K31 -> 1.3097297e+08
A34: =A33+1 -> 27
A35: =A34+1 -> 28 | B35: - | C35: Net Amortization of Gains (Losses) from Line 15 | K35: =K22 -> -1367393
A36: =A35+1 -> 29
A37: =A36+1 -> 30 | C37: Adjusted Annual Debt Requirement | K37: =+K33-K35 -> 1.3234036e+08
A38: =A37+1 -> 31
A39: =A38+1 -> 32 | C39: Adjusted Cost of Debt (Line 30/Line 19) | K39: =+K37/K26 -> 0.042757762

Sheet II-C-2.5
E1: PUBLIC UTILITY COMMISSION OF TEXAS | Q1: Schedule II-C-2.5
E2: AEP TEXAS INC - CENTRAL DIVISION
A3: Weighted Average Cost of
A4: Short-Term Debt
A5: 42185
K7: End of Monitoring Period
K8: 12 Months Ended 06/30/15
K10: (a) | M10: (b) | O10: (c) | Q10: (d)
B11: Amount ($000) | M11: Balance | Q11: Weighted
A12: Line | E12: Balance at end of | G12: Balance at end of | I12: Balance at end of | K12: Balance | M12: As a % | O12: Average | Q12: Average
A13: No. | E13: 42004 | G13: 41639 | I13: 41274 | K13: Outstanding | M13: of Total | O13: Cost | Q13: Cost
A15: 1 | B15: Commercial Paper\AEP Money Pool | E15: =72603880.8/1000 -> 72603.881 | G15: =105538468.52/1000 -> 105538.47 | I15: =103335086/1000 -> 103335.09 | K15: =79682346/1000 -> 79682.346 | M15: =IF(ISERR(+K15/$K$19),0,K15/$K$19) -> 1 | O15: 0.003835 | P15: ** | Q15: =M15*O15 -> 0.003835
A16: 2 | B16: Bank Loans | E16: 0 | G16: 0 | I16: 0 | K16: 0 | M16: =IF(ISERR(+K16/$K$19),0,K16/$K$19) -> 0 | O16: 0 | Q16: =M16*O16 -> 0
A17: 3 | B17: Other | E17: 0 | G17: 0 | I17: 0 | K17: 0 | M17: =IF(ISERR(+K17/$K$19),0,K17/$K$19) -> 0 | O17: 0 | Q17: =M17*O17 -> 0
A19: 4 | B19: Total Notes Payable | E19: =SUM(E15:E17) -> 72603.881 | G19: =SUM(G15:G17) -> 105538.47 | I19: =SUM(I15:I17) -> 103335.09 | K19: =SUM(K15:K17) -> 79682.346 | M19: =SUM(M15:M17) -> 1 | Q19: =SUM(Q15:Q17) -> 0.003835
C22: ** Average cost is the daily average cost for the test year ending June 30, 2015

Sheet II-C-2-5
I1: Schedule II-C-2.5
B2: PUBLIC UTILITY COMMISSION OF TEXAS
B3: AEP TEXAS INC
B4: II-C-2.5 Weighted Average Cost of Short Term Debt
B5: 43465
F8: End of Monitoring Period
F9: 12 Months Ended December 31, 2018
F11: (a) | G11: (b) | H11: (c) | I11: (d)
G12: Balance | I12: Weighted
C13: Balance at end of | D13: Balance at end of | E13: Balance at end of | F13: Balance | G13: As a % | H13: Average | I13: Average
C14: 42369 | D14: 42735 | E14: 43100 | F14: Outstanding | G14: of Total | H14: Cost | I14: Cost
B16: Commercial Paper | C16: 0 | D16: 0 | E16: 0 | F16: 0 | G16: =IF(ISERR(+F16/$F$20),0,F16/$F$20) -> 0 | I16: =G16*H18 -> 0
B17: Bank Loans | C17: 0 | D17: 0 | E17: 0 | F17: 0 | G17: =IF(ISERR(+F17/$F$20),0,F17/$F$20) -> 0 | I17: =G17*H17 -> 0
B18: Other (Adv to Affiliates) | C18: 95057840 | D18: -1.6950456e+08 | E18: 1.0353815e+08 | F18: -2.1604223e+08 | G18: =IF(ISERR(+F18/$F$20),0,F18/$F$20) -> 1 | H18: 0.029723355 | I18: =G18*H18 -> 0.029723355
B20: Total Notes Payable | C20: =SUM(C16:C18) -> 95057840 | D20: =SUM(D16:D18) -> -1.6950456e+08 | E20: =SUM(E16:E18) -> 1.0353815e+08 | F20: =SUM(F16:F18) -> -2.1604223e+08 | G20: =SUM(G16:G18) -> 1 | I20: =SUM(I16:I18) -> 0.029723355

Sheet II-C-2.5.1
K1: Schedule II-C-2.5.1
B2: PUBLIC UTILITY COMMISSION OF TEXAS
B3: AEP TEXAS INC
B4: II-C-5.1Average Daily Balances and Costs for Short Term Debt
B5: For the test year ended 12/31/2018
D8: Commercial Paper | G8: Bank Loans | J8: Other
A9: Line | B9: Month Ended: | D9: Average Daily Balance | E9: Average Cost | G9: Average Daily Balance | H9: Average Cost | J9: Average Daily Balance | K9: Average Cost
A10: 1 | B10: 43131 | D10: 0 | E10: 0 | G10: 0 | H10: 0 | J10: -37146147 | K10: 0.018948327
A12: 2 | B12: 43159 | D12: 0 | E12: 0 | G12: 0 | H12: 0 | J12: 2.1060026e+08 | K12: 0.018684811
A14: 3 | B14: 43190 | D14: 0 | E14: 0 | G14: 0 | H14: 0 | J14: 2.6620947e+08 | K14: 0.022272797
A16: 4 | B16: 43220 | D16: 0 | E16: 0 | G16: 0 | H16: 0 | J16: 3.0971446e+08 | K16: 0.024913173
A18: 5 | B18: 43251 | D18: 0 | E18: 0 | G18: 0 | H18: 0 | J18: 1.4414436e+08 | K18: 0.024745165
A20: 6 | B20: 43281 | D20: 0 | E20: 0 | G20: 0 | H20: 0 | J20: -49180310 | K20: 0.023916081
A22: 7 | B22: 43312 | D22: 0 | E22: 0 | G22: 0 | H22: 0 | J22: -19472155 | K22: 0.023984906
A24: 8 | B24: 43343 | D24: 0 | E24: 0 | G24: 0 | H24: 0 | J24: 33302069 | K24: 0.019961024
A26: 9 | B26: 43373 | D26: 0 | E26: 0 | G26: 0 | H26: 0 | J26: 57674752 | K26: 0.019348822
A28: 10 | B28: 43404 | D28: 0 | E28: 0 | G28: 0 | H28: 0 | J28: 1.2864001e+08 | K28: 0.020100694
A30: 11 | B30: 43434 | D30: 0 | E30: 0 | G30: 0 | H30: 0 | J30: 1.764744e+08 | K30: 0.020221176
A32: 12 | B32: 43465 | D32: 0 | E32: 0 | G32: 0 | H32: 0 | J32: 1.5359562e+08 | K32: 0.027493107

Sheet II-C-2.6
G1: Schedule II-C-2.6
B2: PUBLIC UTILITY COMMISSION OF TEXAS
B3: AEP TEXAS INC
B4: II-C-2.6 SECURITY ISSUANCE RESTRICTIONS
B5: TEST YEAR ENDED 12/31/2018
B9: Excerpt from AEP Texas Central and AEP Texas North Credit Agreements:
C10: Section 5.02 ( e )
C11: Restrictive Agreements. Enter into, or permit any Significant Subsidiary
C12: to enter into (except in connection with or pursuant to any Restructuring Law), any agreement
C13: after the date hereof, or amend, supplement or otherwise modify any agreement existing on the
C14: date hereof, that imposes any restriction on the ability of any Significant Subsidiary to make
C15: payments, directly or indirectly, to its shareholders by way of dividends, advances, repayment of
C16: loans or intercompany charges, expenses and accruals or other returns on investments that is
C17: more restrictive than any such restriction applicable to such Significant Subsidiary on the date
C18: hereof; provided, however, that any Significant Subsidiary may agree to a financial covenant
C19: limiting its ratio of Consolidated Debt to Consolidated Capital to no more than 0.675 to 1.000.
C22: Defined Terms
C23: “Significant Subsidiary” means, at any time, any Subsidiary of the Borrower that
... C50: components of accumulated other comprehensive income (loss).
B53: Additional information and calculations related to Schedule II-C-2.6 Security Issuance Restrictions is Highly Sensitive under the terms of the Protective Order. The Highly Sensitive information is available for review at the Austin offices of American Electric Power Company (AEP), 400 West 15th Street, Suite 1520, Austin, Texas, 78701, (512) 481-4562, during normal business hours.

Sheet II-C-2.6.1
J1: Schedule II-C-2.6.1
B2: PUBLIC UTILITY COMMISSION OF TEXAS
B3: AEP TEXAS INC
B4: II-C-2.6 SECURITY ISSUANCE RESTRICTIONS
B5: FOR THE TEST YEAR ENDED 12/31/2018
B9: Some of the information responsive to this request is HIGHLY SENSITIVE under the terms of the Protective Order. The Confidential information is available for review at the Austin offices of American Electric Power Company (AEP), 400 West 15th Street, Suite 1520, Austin, Texas, 78701, (512) 481-4562, during normal business hours.

Sheet II-C-2.7
J1: Schedule II-C-2.7
B2: PUBLIC UTILITY COMMISSION OF TEXAS
B3: AEP TEXAS INC
B4: II-C-2.7 CAPITAL REQUIREMENTS AND ACQUISITION PLAN
B5: FOR THE TEST YEAR ENDED 12/31/2018
B9: The information responsive to this request is HIGHLY SENSITIVE under the terms of the Protective Order. The Confidential information is available for review at the Austin offices of American Electric Power Company (AEP), 400 West 15th Street, Suite 1520, Austin, Texas, 78701, (512) 481-4562, during normal business hours.

Sheet II-C-2.8 
M1: Schedule II-C-2.8
B2: PUBLIC UTILITY COMMISSION OF TEXAS
B3: AEP TEXAS INC
B4: II-C-2.8 Financial Statistics1
B5: For the test Year ended 12/31/2018
M9: Test
A10: Line | C10: Fiscal Year: | E10: 2014 | G10: 2015 | I10: 2016 | K10: 2017 | M10: Year
A13: 1 | C13: Total Debt as a Percent | E13: 0.74136279 | G13: 0.69845747 | I13: 0.67267342 | K13: 0.62856061 | M13: 0.61521245
A14: 2 | C14: of Total Capital*
A15: 3
A16: 4 | C16: CWIP as a Percent of Net Plant | E16: 0.054369646 | G16: 0.055219831 | I16: 0.066748582 | K16: 0.12245238 | M16: 0.10463066
A17: 5
A18: 6 | C18: Construction Expenditures as a | E18: 0.12667633 | G18: 0.12480883 | I18: 0.12982447 | K18: 0.18299356 | M18: 0.23092022
A19: 7 | C19: Percent of Total Capital
A20: 8
A21: 9 | C21: Pre-Tax Interest Coverage | E21: 2.3685197 | G21: 2.135674 | I21: 4.0853509 | K21: 2.9260619 | M21: 2.3871357
A22: 10
A23: 11 | C23: Funds From Operations / Total Debt | E23: 0.15457633 | G23: 0.15805604 | I23: 0.16608111 | K23: 0.18197189 | M23: 0.15989503
A24: 12
A25: 13
A26: 14 | C26: Fixed Charge Coverage | E26: 2.3598545 | G26: 2.1282378 | I26: 4.0522197 | K26: 2.9144677 | M26: 2.3792379
A27: 15
A28: 16 | C28: Fixed Charge Coverage Ratio (Including | E28: 2.3598545 | G28: 2.1282378 | I28: 4.0522197 | K28: 2.9144677 | M28: 2.3792379
A29: 17 | C29: Distributions on Pref Trust Securities)
A30: 18
A31: 19 | C31: Funds From Operations Interest Coverage | E31: 4.5491425 | G31: 4.6524106 | I31: 7.9807852 | K31: 5.6434698 | M31: 5.4687343
A32: 20
A33: 21 | C33: Net Cash Flow / Capital Outlays | E33: 1.1505583 | G33: 1.1566356 | I33: 1.2056057 | K33: 1.4829392 | M33: 2.165833
A34: 22
A35: 23
A36: 24 | C36: Cash Coverage of Common Dividends | E36: 15.549657 | G36: 18.84969 | I36: 16.635294 | K36: 0 | M36: 0
A37: 25
A38: 26
A39: 27 | C39: Return on Average Common Equity | E39: 0.11572481 | G39: 0.086360572 | I39: 0.12370145 | K39: 0.16227659 | M39: 0.088979346
C42: *Total Company Long-term debt net of Securitization Bonds.
B43: 1 | C43: This schedule reflects total Company financial statistics due to the requirement that the schedule be based on audited financial statements.
C44: It includes data from generation, transmission and distribution functions. The testimony of TCC witness Charles Patton includes T&D only
C45: returns for the historical periods covered by this schedule.
A47: 1 | C47: Short-term Debt | E47: 27926 | G47: 82080 | I47: 207 | K47: 0 | M47: 776711
A48: =+A47+1 -> 2 | C48: Long-term Debt* | E48: 1176430 | G48: 1052804 | I48: 843781 | K48: 1307652 | M48: 412099
A49: =+A48+1 -> 3 | C49: Long-term Debt due within a year | E49: 154383.69 | G49: 152900 | I49: 365742 | K49: 237651 | M49: 229131
A50: =+A49+1 -> 4 | C50: Total Debt | E50: 1358739.7 | G50: 1287784 | I50: 1209730 | K50: 1545303 | M50: 1417941
A51: =+A50+1 -> 5 | C51: *Total Company Long-term debt net of Securitization Bonds.
A52: =+A51+1 -> 6
A53: =+A52+1 -> 7 | C53: Preferred Stock | E53: 5938.8 | G53: 5940 | I53: 5940 | K53: 5940 | M53: 5942
A54: =+A53+1 -> 8 | C54: Preferred Trust Securities | E54: 0 | G54: 0 | I54: 0 | K54: 140889 | M54: 136250
A55: =+A54+1 -> 9 | C55: Common Equity** | E55: 968481 | G55: 947630 | I55: 1268643 | K55: 1209049 | M55: 1101134
A56: =+A55+1 -> 10 | C56: Total Capital | E56: 2333159.5 | G56: 2241354 | I56: 2484313 | K56: 2901181 | M56: 2661267
A57: =+A56+1 -> 11
A58: =+A57+1 -> 12
A59: =+A58+1 -> 13 | C59: Construction Work in Progress | E59: 97407 | G59: 129800 | I59: 50612 | K59: 58953 | M59: 200947
A60: =+A59+1 -> 14 | C60: Net Electric Utility Plant | E60: 2135667 | G60: 2021117 | I60: 1769150 | K60: 1729679 | M60: 3220244
A61: =+A60+1 -> 15
A62: =+A61+1 -> 16 | C62: Construction Expenditure | E62: 254131 | G62: 178628 | I62: 106656 | K62: 141771 | M62: 151645
A63: =+A62+1 -> 17 | C63: Average Total Capital | E63: 2200510.7 | G63: 2362833.5 | I63: 2692747 | K63: 2781224 | M63: 2905802
A64: =+A63+1 -> 18
A65: =+A64+1 -> 19
A66: =+A65+1 -> 20 | C66: Income from Continuing Operations | E66: -182536 | G66: -173779 | I66: 174122 | K66: 217669 | M66: 275941
A67: =+A66+1 -> 21 | C67: +/- Nonrecurring Items (Before Tax) | E67: 0 | G67: 0 | I67: 0 | K67: 0 | M67: 0
A68: =+A67+1 -> 22 | C68: +Minority Interest | E68: 0 | G68: 0 | I68: 0 | K68: 0 | M68: 0
A69: =+A68+1 -> 23 | C69: -Equity AFUDC | E69: 1307 | G69: -1003 | I69: -1170 | K69: -507 | M69: -485
A70: =+A69+1 -> 24 | C70: +Income Taxes | E70: 14885 | G70: 12441 | I70: 135058 | K70: 105172 | M70: 139014
A71: =+A70+1 -> 25 | C71: +Interest Incurred | E71: -107043 | G71: 113514 | I71: 117958 | K71: 123098 | M71: 119282
A72: =+A71+1 -> 26 | C72: Total | E72: -273387 | G72: -48827 | I72: 425968 | K72: 445432 | M72: 533752
A73: =+A72+1 -> 27
A74: =+A73+1 -> 28
A75: =+A74+1 -> 29 | C75: Cash flow From Operations | E75: 114508 | G75: -72267 | I75: 286608 | K75: 357378 | M75: 147493
A76: =+A75+1 -> 30 | C76: Subtract: Change in Working Capital | E76: 23896 | G76: 154931 | I76: -136065 | K76: -100672 | M76: 259446
A77: =+A76+1 -> 31 | C77: Subtract: Trust Preferred Interest | E77: 0 | G77: 0 | I77: -6575 | K77: -11271 | M77: -11209
A78: =+A77+1 -> 32 | C78: Funds from Operations | E78: 138404 | G78: 82664 | I78: 143968 | K78: 245435 | M78: 395730
A79: =+A78+1 -> 33
A80: =+A79+1 -> 34 | C80: Distribution Related to Trust Preferred Securities | E80: 0 | G80: 0 | I80: -6575 | K80: -11271 | M80: -11209
A81: =+A80+1 -> 35 | C81: Interest Expense | E81: -108940 | G81: 112006 | I81: 123785 | K81: 133812 | M81: 125871
A82: =+A81+1 -> 36 | C82: AFUDC - Debt | E82: 1897 | G82: 1508 | I82: 748 | K82: 557 | M82: 4620
A83: =+A82+1 -> 37 | C83: Interest Incurred | E83: -107043 | G83: 113514 | I83: 117958 | K83: 123098 | M83: 119282
A84: =+A83+1 -> 38
A85: =+A84+1 -> 39 | C85: Funds from Operations | E85: 138404 | G85: 82664 | I85: 143968 | K85: 245435 | M85: 395730
A86: =+A85+1 -> 40 | C86: Subtract: Preferred Dividends | E86: 241 | G86: 241 | I86: 241 | K86: 241 | M86: 241
A87: =+A86+1 -> 41 | C87: Subtract: Common Dividends | E87: 0 | G87: 150000 | I87: 172000 | K87: 120801 | M87: 115505
A88: =+A87+1 -> 42 | C88: Net Cash Flow | E88: 138163 | G88: -67577 | I88: -28273 | K88: 124393 | M88: 279984
A89: =+A88+1 -> 43
A90: =+A89+1 -> 44 | C90: Net Income Applicable to Common Stock | E90: -182777 | G90: -174020 | I90: 173881 | K90: 217428 | M90: 275704

Sheet II-C-2.9 
B2: PUBLIC UTILITY COMMISSION OF TEXAS
B3: AEP TEXAS INC
B4: II-C-2.9 GROWTH IN EARNINGS, DIVIDENDS, AND BOOK VALUE1
B5: FOR THE TEST YEAR ENDED 12/31/2018
B6: $ Millions
B11: (A) | C11: (B) | E11: (C) | G11: (D) | I11: (E) | K11: (F) | L11: (G) | M11: (H) | N11: (I) | O11: (J) | P11: (K) | Q11: (L) | R11: (M) | S11: (N) | T11: (O) | U11: (P) | V11: (Q) | W11: (R) | X11: (S) | Y11: (T) | Z11: (U)
C12: BEGINNING | E12: NET INCOME | I12: ADDTL. | K12: ENDING | L12: AVERAGE | N12: PERCENT | W12: MARKET | Y12: NET INCOME
C13: COMMON | E13: FOR | G13: COMMON | I13: EQUITY | K13: COMMON | L13: COMMON | N13: EARNINGS | O13: IMPLIED | P13: WTD. AVG. | Q13: WTD. AVG. | R13: YEAR END | V13: YEAR END | W13: TO | X13: NON-RECURRING | Y13: FOR COMMON | Z13: DESCRIPTION OF
A14: Line | B14: YEAR | C14: EQUITY | D14: + | E14: COMMON | F14: - | G14: DIVIDENDS | H14: + | I14: (NET) | J14: = | K14: EQUITY | L14: EQUITY | M14: ROE | N14: RETAINED | O14: GROWTH | P14: SHARES | Q14: SHARES | R14: SHARES | S14: EPS | T14: DPS | U14: BVPS | V14: MARKET | W14: BOOK | X14: GAINS/(LOSSES) | Y14: (ADJUSTED) | Z14: NON-RECURRING
A15: No. | I15: F-(B+C-D) | L15: (B+F) / 2 | M15: C/G | N15: (C-D) / C | O15: H x I | P15: (FOR EPS) | Q15: (FOR DPS) | R15: (FOR BVPS) | S15: C/K | T15: D/L | U15: F/M | V15: PRICE | W15: Q/P | X15: (NET OF TAX) | Y15: C-S | Z15: ITEM
A17: 1 | B17: AEP
A18: =A17+1 -> 2 | B18: 2018 | C18: =K19 -> 18313600 | E18: 1931300 | G18: 1255500 | I18: =K18-(C18+E18-G18) -> 70000 | K18: 19059400 | L18: =(C18+K18)/2 -> 18686500 | M18: =E18/L18 -> 0.10335269 | N18: =(E18-G18)/E18 -> 0.34991974 | O18: =M18*N18 -> 0.036165146 | P18: 492774600 | Q18: =P18 -> 492774600 | R18: 493245876 | S18: =(E18/P18)*1000 -> 3.9192361 | T18: =(G18/Q18)*1000 -> 2.547818 | U18: =(K18/R18)*1000 -> 38.640769 | V18: 74.74 | W18: =V18/U18 -> 1.9342265 | Y18: =E18-X18 -> 1931300
A19: =A18+1 -> 3 | B19: 2017 | C19: =K20 -> 17420100 | E19: 1928900 | G19: 1191900 | I19: =K19-(C19+E19-G19) -> 156500 | K19: 18313600 | L19: =(C19+K19)/2 -> 17866850 | M19: =E19/L19 -> 0.10795971 | N19: =(E19-G19)/E19 -> 0.38208305 | O19: =M19*N19 -> 0.041249577 | P19: 491814651 | Q19: =P19 -> 491814651 | R19: 492005598 | S19: =(E19/P19)*1000 -> 3.922006 | T19: =(G19/Q19)*1000 -> 2.423474 | U19: =(K19/R19)*1000 -> 37.222341 | V19: 73.57 | W19: =V19/U19 -> 1.9765012 | Y19: =E19-X19 -> 1928900
A20: =A19+1 -> 4 | B20: 2016 | C20: 17904900 | E20: 618000 | G20: 1121000 | I20: =K20-(C20+E20-G20) -> 18200 | K20: 17420100 | L20: =(C20+K20)/2 -> 17662500 | M20: =E20/L20 -> 0.034989384 | N20: =(E20-G20)/E20 -> -0.81391586 | O20: =M20*N20 -> -0.028478415 | P20: 491495458 | Q20: =P20 -> 491495458 | R20: 491711928 | S20: =(E20/P20)*1000 -> 1.257387 | T20: =(G20/Q20)*1000 -> 2.2807942 | U20: =(K20/R20)*1000 -> 35.427451 | V20: 62.96 | W20: =V20/U20 -> 1.777153 | X20: -2500 | Y20: =E20-X20 -> 620500 | Z20: Loss from Discontinued Operations
A21: =A20+1 -> 5 | B21: AEP Texas
A22: =A21+1 -> 6 | B22: 2018 | C22: =K23 -> 2169900 | E22: 211300 | G22: 0 | I22: =K22-(C22+E22-G22) -> 199300 | K22: 2580500 | L22: =(C22+K22)/2 -> 2375200 | M22: =E22/L22 -> 0.08896093 | N22: =(E22-G22)/E22 -> 1 | O22: =M22*N22 -> 0.08896093
A23: =A22+1 -> 7 | B23: 2017 | C23: =K24 -> 1657100 | E23: 310500 | G23: 0 | I23: =K23-(C23+E23-G23) -> 202300 | K23: 2169900 | L23: =(C23+K23)/2 -> 1913500 | M23: =E23/L23 -> 0.1622681 | N23: =(E23-G23)/E23 -> 1 | O23: =M23*N23 -> 0.1622681
A24: =A23+1 -> 8 | B24: 2016 | C24: 1674700 | E24: 146600 | G24: 34000 | I24: =K24-(C24+E24-G24) -> -130200 | K24: 1657100 | L24: =(C24+K24)/2 -> 1665900 | M24: =E24/L24 -> 0.08800048 | N24: =(E24-G24)/E24 -> 0.7680764 | O24: =M24*N24 -> 0.067591092

Sheet II-C-2.10 
J1: Schedule II-C-2.10
B2: PUBLIC UTILITY COMMISSION OF TEXAS
B3: AEP TEXAS INC
B4: II-C-2.10 RATING AGENCY REPORTS
B5: FOR THE TEST YEAR ENDED 12/31/2018
B9: The information responsive to this request is HIGHLY SENSITIVE under the terms of the Protective Order. The Confidential information is available for review at the Austin offices of American Electric Power Company (AEP), 400 West 15th Street, Suite 1520, Austin, Texas, 78701, (512) 481-4562, during normal business hours.

Sheet II-C-3
D1: Schedule II-C-3
B2: PUBLIC UTILITY COMMISSION OF TEXAS
B3: AEP TEXAS INC
B4: II-C-3 INTERNAL/EXTERNAL AUDITS
B5: TEST YEAR ENDING 12/31/2018
B6: ='I-A'!B6
B10: AEP Internal Reports Completed in 2018
B12: East Texas HVDC Tie Billings Review (2014-2016), report issued February 2018.
B13: Audit of allocations and billings associated with East Texas Tie.
B15: Service Delivery, report issued March 2018. Audit of select distribution processes
B16: such as order execution and work order accounting on a company wide basis.
B18: Aransas Pass and Lon Hill Service Centers, report issued May 2018.
B19: Audit of select environmental, safety and health processes.
B21: Hurricane Harvey Cost, report issued July 2018. Audit of cost accumulation
B22: associated with Hurricane Harvey.
B24: Oklaunion Power Station, report issued October 2018. Audit of select
B25: environmental, safety and health processes.
B27: Oklaunion Co-Owner Billings Review (2016 and 2017), report issued November 2018.
... B43: FERC Docket No. FA17-1-000

Sheet II-D-1 O&M
B2: PUBLIC UTILITY COMMISSION OF TEXAS
B3: AEP TEXAS INC
B4: II-D-1 OPERATIONS AND MAINTENANCE EXPENSE
B5: TEST YEAR ENDING 12/31/2018
B6: ='I-A'!B6
E8: 1 | F8: 2 | G8: 3 | H8: 4 | I8: 5 | J8: 6 | K8: 7 | L8: 8 | M8: 9 | N8: 10 | O8: 11 | P8: 12 | Q8: 13
H9: Company | I9: Texas
B10: Account | C10: Description | D10: Reference | E10: Total | F10: Non-Regulated or | G10: Known | H10: Total | I10: Retail | J10: Allocation to | K10: FF | L10: Funct | M10: TRAN | N10: DIST | O10: MET | P10: TDCS | Q10: Total
