Workbook

Sheet Summary
A1: AEP Texas
A2: Income Tax Refund Rider
B4: Total | C4: Annual
A5: Description | B5: Amount | C5: Refund Amt
A6: TCC Distribution
A7: Income Tax Rate | B7: ='Stub Period'!F15 -> 9293055.3 | C7: =B7/4 -> 2323263.8
A8: Protected | B8: ='Stub Period'!F43 -> 4734348.4 | C8: =B8/4 -> 1183587.1
A9: Unprotected | B9: =-'Unprotected With Interest'!C57 -> 39725541 | C9: =B9/4 -> 9931385.2
A10: Total TCC Distribution | B10: =SUM(B7:B9) -> 53752945 | C10: =SUM(C7:C9) -> 13438236
A12: TNC Distribution
A13: Income Tax Rate | B13: ='Stub Period'!C15 -> 2372459.7 | C13: =B13/4 -> 593114.93
A14: Protected | B14: ='Stub Period'!C43 -> 1193273.4 | C14: =B14/4 -> 298318.34
A15: Unprotected | B15: =-'Unprotected With Interest'!C110 -> 25647715 | C15: =B15/4 -> 6411928.8
A16: Total TNC Distribution | B16: =SUM(B13:B15) -> 29213448 | C16: =SUM(C13:C15) -> 7303362.1
A18: Total Distribution
A19: Income Tax Rate | B19: =B7+B13 -> 11665515 | C19: =B19/4 -> 2916378.8
A20: Protected | B20: =B8+B14 -> 5927621.7 | C20: =B20/4 -> 1481905.4
A21: Unprotected | B21: =B9+B15 -> 65373256 | C21: =B21/4 -> 16343314
A22: Total Distribution | B22: =SUM(B19:B21) -> 82966393 | C22: =SUM(C19:C21) -> 20741598
B24: Total One-Time
A25: Description | B25: Refund Amt
A26: TCC Transmission
A27: Income Tax Rate | B27: ='Stub Period'!E15 -> 7723828.8
A28: Protected | B28: ='Stub Period'!E43 -> 1634119.1
A29: Unprotected | B29: =-'Unprotected With Interest'!F57 -> 12848996
A30: Total TCC Transmission | B30: =SUM(B27:B29) -> 22206944
A32: TNC Transmission
A33: Income Tax Rate | B33: ='Stub Period'!B15 -> 2388363.7
A34: Protected | B34: ='Stub Period'!B43 -> 739100.9
A35: Unprotected | B35: =-'Unprotected With Interest'!F110 -> 3926274.7
A36: Total TNC Transmission | B36: =SUM(B33:B35) -> 7053739.3
A38: Total Transmission
A39: Income Tax Rate | B39: =B27+B33 -> 10112192
A40: Protected | B40: =B28+B34 -> 2373220
A41: Unprotected | B41: =B29+B35 -> 16775271
A42: Total Transmission | B42: =SUM(B39:B41) -> 29260683
A44: TCC Total
A45: Income Tax Rate | B45: =B7+B27 -> 17016884
A46: Protected | B46: =B8+B28 -> 6368467.5
A47: Unprotected | B47: =B9+B29 -> 52574537
A48: Total TCC | B48: =SUM(B45:B47) -> 75959889
A50: TNC Total
A51: Income Tax Rate | B51: =B13+B33 -> 4760823.4
A52: Protected | B52: =B14+B34 -> 1932374.2
A53: Unprotected | B53: =B15+B35 -> 29573990
A54: Total TNC | B54: =SUM(B51:B53) -> 36267188
A56: Total Total
A57: Income Tax Rate | B57: =B19+B39 -> 21777708
A58: Protected | B58: =B20+B40 -> 8300841.8
A59: Unprotected | B59: =B21+B41 -> 82148527
A60: Total | B60: =SUM(B57:B59) -> 1.1222708e+08

Sheet Stub Period
A1: AEP Texas
A2: Income Tax Refund Rider
B5: North Division Income Tax Rate | E5: Central Division Income Tax Rate | H5: Total Income Tax Rate
A6: Month | B6: Transmission | C6: Distribution | D6: Total | E6: Transmission | F6: Distribution | G6: Total | H6: Transmission | I6: Distribution | J6: Total
A7: 43101 | B7: 105214.26 | C7: 80130.49 | D7: =B7+C7 -> 185344.75 | E7: 340256.78 | F7: 286906.39 | G7: =E7+F7 -> 627163.17 | H7: =B7+E7 -> 445471.04 | I7: =C7+F7 -> 367036.88 | J7: =H7+I7 -> 812507.92
A8: 43132 | B8: 465948.86 | C8: 317266.64 | D8: =B8+C8 -> 783215.5 | E8: 1506851.4 | F8: 1125900.1 | G8: =E8+F8 -> 2632751.6 | H8: =B8+E8 -> 1972800.3 | I8: =C8+F8 -> 1443166.8 | J8: =H8+I8 -> 3415967.1
A9: 43160 | B9: 465948.86 | C9: 290865.08 | D9: =B9+C9 -> 756813.94 | E9: 1506851.4 | F9: 1086943.6 | G9: =E9+F9 -> 2593795 | H9: =B9+E9 -> 1972800.3 | I9: =C9+F9 -> 1377808.7 | J9: =H9+I9 -> 3350609
A10: 43191 | B10: 465948.86 | C10: 287021.86 | D10: =B10+C10 -> 752970.72 | E10: 1506851.4 | F10: 1155670 | G10: =E10+F10 -> 2662521.4 | H10: =B10+E10 -> 1972800.3 | I10: =C10+F10 -> 1442691.8 | J10: =H10+I10 -> 3415492.1
A11: 43221 | B11: 465948.86 | C11: 295371.23 | D11: =B11+C11 -> 761320.09 | E11: 1506851.4 | F11: 1222405.8 | G11: =E11+F11 -> 2729257.2 | H11: =B11+E11 -> 1972800.3 | I11: =C11+F11 -> 1517777 | J11: =H11+I11 -> 3490577.3
A12: 43252 | B12: 419353.97 | C12: 336895.65 | D12: =B12+C12 -> 756249.62 | E12: 1356166.3 | F12: 1387521 | G12: =E12+F12 -> 2743687.3 | H12: =B12+E12 -> 1775520.3 | I12: =C12+F12 -> 1724416.6 | J12: =H12+I12 -> 3499936.9
A13: 43282 | B13: 0 | C13: 381525.22 | D13: =B13+C13 -> 381525.22 | E13: 0 | F13: 1493302 | G13: =E13+F13 -> 1493302 | H13: =B13+E13 -> 0 | I13: =C13+F13 -> 1874827.3 | J13: =H13+I13 -> 1874827.3
A14: 43313 | B14: 0 | C14: 383383.55 | D14: =B14+C14 -> 383383.55 | E14: 0 | F14: 1534406.5 | G14: =E14+F14 -> 1534406.5 | H14: =B14+E14 -> 0 | I14: =C14+F14 -> 1917790 | J14: =H14+I14 -> 1917790
A15: Total | B15: =SUM(B7:B14) -> 2388363.7 | C15: =SUM(C7:C14) -> 2372459.7 | D15: =SUM(D7:D14) -> 4760823.4 | E15: =SUM(E7:E14) -> 7723828.8 | F15: =SUM(F7:F14) -> 9293055.3 | G15: =SUM(G7:G14) -> 17016884 | H15: =SUM(H7:H14) -> 10112192 | I15: =SUM(I7:I14) -> 11665515 | J15: =SUM(J7:J14) -> 21777708
B17: North Division Protected | E17: Central Division Protected | H17: Total Protected
A18: Month | B18: Transmission | C18: Distribution | D18: Total | E18: Transmission | F18: Distribution | G18: Total | H18: Transmission | I18: Distribution | J18: Total
A19: 43101 | B19: 0 | C19: 0 | D19: =B19+C19 -> 0 | E19: 0 | F19: 0 | G19: =E19+F19 -> 0 | H19: =B19+E19 -> 0 | I19: =C19+F19 -> 0 | J19: =H19+I19 -> 0
A20: 43132 | B20: 0 | C20: 0 | D20: =B20+C20 -> 0 | E20: 0 | F20: 0 | G20: =E20+F20 -> 0 | H20: =B20+E20 -> 0 | I20: =C20+F20 -> 0 | J20: =H20+I20 -> 0
A21: 43160 | B21: 77119.97 | C21: 367570.8 | D21: =B21+C21 -> 444690.77 | E21: 185080.03 | F21: 1458348.4 | G21: =E21+F21 -> 1643428.4 | H21: =B21+E21 -> 262200 | I21: =C21+F21 -> 1825919.2 | J21: =H21+I21 -> 2088119.2
A22: 43191 | B22: 34648.1 | C22: 165140.51 | D22: =B22+C22 -> 199788.61 | E22: 83151.9 | F22: 655200 | G22: =E22+F22 -> 738351.9 | H22: =B22+E22 -> 117800 | I22: =C22+F22 -> 820340.51 | J22: =H22+I22 -> 938140.51
A23: 43221 | B23: 34648.1 | C23: 165140.51 | D23: =B23+C23 -> 199788.61 | E23: 83151.9 | F23: 655200 | G23: =E23+F23 -> 738351.9 | H23: =B23+E23 -> 117800 | I23: =C23+F23 -> 820340.51 | J23: =H23+I23 -> 938140.51
A24: 43252 | B24: 34648.1 | C24: 165140.51 | D24: =B24+C24 -> 199788.61 | E24: 83151.9 | F24: 655200 | G24: =E24+F24 -> 738351.9 | H24: =B24+E24 -> 117800 | I24: =C24+F24 -> 820340.51 | J24: =H24+I24 -> 938140.51
A25: 43282 | B25: 34648.1 | C25: 165140.51 | D25: =B25+C25 -> 199788.61 | E25: 83151.9 | F25: 655200 | G25: =E25+F25 -> 738351.9 | H25: =B25+E25 -> 117800 | I25: =C25+F25 -> 820340.51 | J25: =H25+I25 -> 938140.51
A26: 43313 | B26: 34648.1 | C26: 165140.51 | D26: =B26+C26 -> 199788.61 | E26: 83151.9 | F26: 655200 | G26: =E26+F26 -> 738351.9 | H26: =B26+E26 -> 117800 | I26: =C26+F26 -> 820340.51 | J26: =H26+I26 -> 938140.51
A27: 43344 | B27: 34648.1 | C27: 0 | D27: =B27+C27 -> 34648.1 | E27: 83151.9 | F27: 0 | G27: =E27+F27 -> 83151.9 | H27: =B27+E27 -> 117800 | I27: =C27+F27 -> 0 | J27: =H27+I27 -> 117800
A28: 43374 | B28: 34648.1 | C28: 0 | D28: =B28+C28 -> 34648.1 | E28: 83151.9 | F28: 0 | G28: =E28+F28 -> 83151.9 | H28: =B28+E28 -> 117800 | I28: =C28+F28 -> 0 | J28: =H28+I28 -> 117800
A29: 43405 | B29: 34648.1 | C29: 0 | D29: =B29+C29 -> 34648.1 | E29: 83151.9 | F29: 0 | G29: =E29+F29 -> 83151.9 | H29: =B29+E29 -> 117800 | I29: =C29+F29 -> 0 | J29: =H29+I29 -> 117800
A30: 43435 | B30: 47854.37 | C30: 0 | D30: =B30+C30 -> 47854.37 | E30: -51512.76 | F30: 0 | G30: =E30+F30 -> -51512.76 | H30: =B30+E30 -> -3658.39 | I30: =C30+F30 -> 0 | J30: =H30+I30 -> -3658.39
... A33: 43525 | B33: 28078.48 | C33: 0 | D33: =B33+C33 -> 28078.48 | E33: 69611.39 | F33: 0 | G33: =E33+F33 -> 69611.39 | H33: =B33+E33 -> 97689.87 | I33: =C33+F33 -> 0 | J33: =H33+I33 -> 97689.87
A34: 43556 | B34: =B33 -> 28078.48 | C34: =C33 -> 0 | D34: =B34+C34 -> 28078.48 | E34: =E33 -> 69611.39 | F34: =F33 -> 0 | G34: =E34+F34 -> 69611.39 | H34: =B34+E34 -> 97689.87 | I34: =C34+F34 -> 0 | J34: =H34+I34 -> 97689.87
A35: 43586 | B35: =B34 -> 28078.48 | C35: =C34 -> 0 | D35: =B35+C35 -> 28078.48 | E35: =E34 -> 69611.39 | F35: =F34 -> 0 | G35: =E35+F35 -> 69611.39 | H35: =B35+E35 -> 97689.87 | I35: =C35+F35 -> 0 | J35: =H35+I35 -> 97689.87
A36: 43617 | B36: =B35 -> 28078.48 | C36: =C35 -> 0 | D36: =B36+C36 -> 28078.48 | E36: =E35 -> 69611.39 | F36: =F35 -> 0 | G36: =E36+F36 -> 69611.39 | H36: =B36+E36 -> 97689.87 | I36: =C36+F36 -> 0 | J36: =H36+I36 -> 97689.87
A37: 43647 | B37: =B36 -> 28078.48 | C37: =C36 -> 0 | D37: =B37+C37 -> 28078.48 | E37: =E36 -> 69611.39 | F37: =F36 -> 0 | G37: =E37+F37 -> 69611.39 | H37: =B37+E37 -> 97689.87 | I37: =C37+F37 -> 0 | J37: =H37+I37 -> 97689.87
A38: 43678 | B38: =B37 -> 28078.48 | C38: =C37 -> 0 | D38: =B38+C38 -> 28078.48 | E38: =E37 -> 69611.39 | F38: =F37 -> 0 | G38: =E38+F38 -> 69611.39 | H38: =B38+E38 -> 97689.87 | I38: =C38+F38 -> 0 | J38: =H38+I38 -> 97689.87
A39: 43709 | B39: =B38 -> 28078.48 | C39: =C38 -> 0 | D39: =B39+C39 -> 28078.48 | E39: =E38 -> 69611.39 | F39: =F38 -> 0 | G39: =E39+F39 -> 69611.39 | H39: =B39+E39 -> 97689.87 | I39: =C39+F39 -> 0 | J39: =H39+I39 -> 97689.87
A40: 43739 | B40: =B39 -> 28078.48 | C40: =C39 -> 0 | D40: =B40+C40 -> 28078.48 | E40: =E39 -> 69611.39 | F40: =F39 -> 0 | G40: =E40+F40 -> 69611.39 | H40: =B40+E40 -> 97689.87 | I40: =C40+F40 -> 0 | J40: =H40+I40 -> 97689.87
A41: 43770 | B41: =B40 -> 28078.48 | C41: =C40 -> 0 | D41: =B41+C41 -> 28078.48 | E41: =E40 -> 69611.39 | F41: =F40 -> 0 | G41: =E41+F41 -> 69611.39 | H41: =B41+E41 -> 97689.87 | I41: =C41+F41 -> 0 | J41: =H41+I41 -> 97689.87
A42: 43800 | B42: =B41 -> 28078.48 | C42: =C41 -> 0 | D42: =B42+C42 -> 28078.48 | E42: =E41 -> 69611.39 | F42: =F41 -> 0 | G42: =E42+F42 -> 69611.39 | H42: =B42+E42 -> 97689.87 | I42: =C42+F42 -> 0 | J42: =H42+I42 -> 97689.87
A43: Total | B43: =SUM(B19:B42) -> 739100.9 | C43: =SUM(C19:C42) -> 1193273.4 | D43: =SUM(D19:D42) -> 1932374.3 | E43: =SUM(E19:E42) -> 1634119.1 | F43: =SUM(F19:F42) -> 4734348.4 | G43: =SUM(G19:G42) -> 6368467.5 | H43: =SUM(H19:H42) -> 2373220.1 | I43: =SUM(I19:I42) -> 5927621.7 | J43: =SUM(J19:J42) -> 8300841.8
B45: North Division Total | E45: Central Division Total | H45: Total
A46: Month | B46: Transmission | C46: Distribution | D46: Total | E46: Transmission | F46: Distribution | G46: Total | H46: Transmission | I46: Distribution | J46: Total
A47: 43101 | B47: =B7+B19 -> 105214.26 | C47: =C7+C19 -> 80130.49 | D47: =B47+C47 -> 185344.75 | E47: =E7+E19 -> 340256.78 | F47: =F7+F19 -> 286906.39 | G47: =E47+F47 -> 627163.17 | H47: =B47+E47 -> 445471.04 | I47: =C47+F47 -> 367036.88 | J47: =H47+I47 -> 812507.92
A48: 43132 | B48: =B8+B20 -> 465948.86 | C48: =C8+C20 -> 317266.64 | D48: =B48+C48 -> 783215.5 | E48: =E8+E20 -> 1506851.4 | F48: =F8+F20 -> 1125900.1 | G48: =E48+F48 -> 2632751.6 | H48: =B48+E48 -> 1972800.3 | I48: =C48+F48 -> 1443166.8 | J48: =H48+I48 -> 3415967.1
A49: 43160 | B49: =B9+B21 -> 543068.83 | C49: =C9+C21 -> 658435.88 | D49: =B49+C49 -> 1201504.7 | E49: =E9+E21 -> 1691931.5 | F49: =F9+F21 -> 2545292 | G49: =E49+F49 -> 4237223.5 | H49: =B49+E49 -> 2235000.3 | I49: =C49+F49 -> 3203727.9 | J49: =H49+I49 -> 5438728.2
A50: 43191 | B50: =B10+B22 -> 500596.96 | C50: =C10+C22 -> 452162.37 | D50: =B50+C50 -> 952759.33 | E50: =E10+E22 -> 1590003.3 | F50: =F10+F22 -> 1810870 | G50: =E50+F50 -> 3400873.3 | H50: =B50+E50 -> 2090600.3 | I50: =C50+F50 -> 2263032.3 | J50: =H50+I50 -> 4353632.6
A51: 43221 | B51: =B11+B23 -> 500596.96 | C51: =C11+C23 -> 460511.74 | D51: =B51+C51 -> 961108.7 | E51: =E11+E23 -> 1590003.3 | F51: =F11+F23 -> 1877605.8 | G51: =E51+F51 -> 3467609.1 | H51: =B51+E51 -> 2090600.3 | I51: =C51+F51 -> 2338117.5 | J51: =H51+I51 -> 4428717.8
A52: 43252 | B52: =B12+B24 -> 454002.07 | C52: =C12+C24 -> 502036.16 | D52: =B52+C52 -> 956038.23 | E52: =E12+E24 -> 1439318.2 | F52: =F12+F24 -> 2042721 | G52: =E52+F52 -> 3482039.2 | H52: =B52+E52 -> 1893320.3 | I52: =C52+F52 -> 2544757.2 | J52: =H52+I52 -> 4438077.4
A53: 43282 | B53: =B13+B25 -> 34648.1 | C53: =C13+C25 -> 546665.73 | D53: =B53+C53 -> 581313.83 | E53: =E13+E25 -> 83151.9 | F53: =F13+F25 -> 2148502 | G53: =E53+F53 -> 2231653.9 | H53: =B53+E53 -> 117800 | I53: =C53+F53 -> 2695167.8 | J53: =H53+I53 -> 2812967.8
A54: 43313 | B54: =B14+B26 -> 34648.1 | C54: =C14+C26 -> 548524.06 | D54: =B54+C54 -> 583172.16 | E54: =E14+E26 -> 83151.9 | F54: =F14+F26 -> 2189606.5 | G54: =E54+F54 -> 2272758.4 | H54: =B54+E54 -> 117800 | I54: =C54+F54 -> 2738130.5 | J54: =H54+I54 -> 2855930.5
A55: 43344 | B55: =B27 -> 34648.1 | C55: =C27 -> 0 | D55: =B55+C55 -> 34648.1 | E55: =E27 -> 83151.9 | F55: =F27 -> 0 | G55: =E55+F55 -> 83151.9 | H55: =B55+E55 -> 117800 | I55: =C55+F55 -> 0 | J55: =H55+I55 -> 117800
A56: 43374 | B56: =B28 -> 34648.1 | C56: =C28 -> 0 | D56: =B56+C56 -> 34648.1 | E56: =E28 -> 83151.9 | F56: =F28 -> 0 | G56: =E56+F56 -> 83151.9 | H56: =B56+E56 -> 117800 | I56: =C56+F56 -> 0 | J56: =H56+I56 -> 117800
A57: 43405 | B57: =B29 -> 34648.1 | C57: =C29 -> 0 | D57: =B57+C57 -> 34648.1 | E57: =E29 -> 83151.9 | F57: =F29 -> 0 | G57: =E57+F57 -> 83151.9 | H57: =B57+E57 -> 117800 | I57: =C57+F57 -> 0 | J57: =H57+I57 -> 117800
A58: 43435 | B58: =B30 -> 47854.37 | C58: =C30 -> 0 | D58: =B58+C58 -> 47854.37 | E58: =E30 -> -51512.76 | F58: =F30 -> 0 | G58: =E58+F58 -> -51512.76 | H58: =B58+E58 -> -3658.39 | I58: =C58+F58 -> 0 | J58: =H58+I58 -> -3658.39
A59: 43466 | B59: =B31 -> 34648.1 | C59: =C31 -> 0 | D59: =B59+C59 -> 34648.1 | E59: =E31 -> 83151.9 | F59: =F31 -> 0 | G59: =E59+F59 -> 83151.9 | H59: =B59+E59 -> 117800 | I59: =C59+F59 -> 0 | J59: =H59+I59 -> 117800
A60: 43497 | B60: =B32 -> 21508.86 | C60: =C32 -> 0 | D60: =B60+C60 -> 21508.86 | E60: =E32 -> 56070.88 | F60: =F32 -> 0 | G60: =E60+F60 -> 56070.88 | H60: =B60+E60 -> 77579.74 | I60: =C60+F60 -> 0 | J60: =H60+I60 -> 77579.74
A61: 43525 | B61: =B33 -> 28078.48 | C61: =C33 -> 0 | D61: =B61+C61 -> 28078.48 | E61: =E33 -> 69611.39 | F61: =F33 -> 0 | G61: =E61+F61 -> 69611.39 | H61: =B61+E61 -> 97689.87 | I61: =C61+F61 -> 0 | J61: =H61+I61 -> 97689.87
A62: 43556 | B62: =B34 -> 28078.48 | C62: =C34 -> 0 | D62: =B62+C62 -> 28078.48 | E62: =E34 -> 69611.39 | F62: =F34 -> 0 | G62: =E62+F62 -> 69611.39 | H62: =B62+E62 -> 97689.87 | I62: =C62+F62 -> 0 | J62: =H62+I62 -> 97689.87
A63: 43586 | B63: =B35 -> 28078.48 | C63: =C35 -> 0 | D63: =B63+C63 -> 28078.48 | E63: =E35 -> 69611.39 | F63: =F35 -> 0 | G63: =E63+F63 -> 69611.39 | H63: =B63+E63 -> 97689.87 | I63: =C63+F63 -> 0 | J63: =H63+I63 -> 97689.87
A64: 43617 | B64: =B36 -> 28078.48 | C64: =C36 -> 0 | D64: =B64+C64 -> 28078.48 | E64: =E36 -> 69611.39 | F64: =F36 -> 0 | G64: =E64+F64 -> 69611.39 | H64: =B64+E64 -> 97689.87 | I64: =C64+F64 -> 0 | J64: =H64+I64 -> 97689.87
A65: 43647 | B65: =B37 -> 28078.48 | C65: =C37 -> 0 | D65: =B65+C65 -> 28078.48 | E65: =E37 -> 69611.39 | F65: =F37 -> 0 | G65: =E65+F65 -> 69611.39 | H65: =B65+E65 -> 97689.87 | I65: =C65+F65 -> 0 | J65: =H65+I65 -> 97689.87
A66: 43678 | B66: =B38 -> 28078.48 | C66: =C38 -> 0 | D66: =B66+C66 -> 28078.48 | E66: =E38 -> 69611.39 | F66: =F38 -> 0 | G66: =E66+F66 -> 69611.39 | H66: =B66+E66 -> 97689.87 | I66: =C66+F66 -> 0 | J66: =H66+I66 -> 97689.87
... A70: 43800 | B70: =B42 -> 28078.48 | C70: =C42 -> 0 | D70: =B70+C70 -> 28078.48 | E70: =E42 -> 69611.39 | F70: =F42 -> 0 | G70: =E70+F70 -> 69611.39 | H70: =B70+E70 -> 97689.87 | I70: =C70+F70 -> 0 | J70: =H70+I70 -> 97689.87
A71: Total | B71: =SUM(B47:B70) -> 3127464.6 | C71: =SUM(C47:C70) -> 3565733.1 | D71: =SUM(D47:D70) -> 6693197.6 | E71: =SUM(E47:E70) -> 9357948 | F71: =SUM(F47:F70) -> 14027404 | G71: =SUM(G47:G70) -> 23385352 | H71: =SUM(H47:H70) -> 12485413 | I71: =SUM(I47:I70) -> 17593137 | J71: =SUM(J47:J70) -> 30078549

Sheet Unprotected With Interest
A1: AEP Texas
A2: Unprotected Tax Refund With Interest
A3: 4 Year Refund Period
A4: Carrying Cost Rate | C4: ='[1]II-C-1.1 ROR Method'!$F$17+('[1]II-C-1.1 ROR Method'!$F$15/0.79) -> 0.083327127
B6: TCC Distribution | E6: TCC Transmission | H6: TCC Total
A7: Month | B7: Interest | C7: Refund | D7: Balance | E7: Interest | F7: Refund | G7: Balance | H7: Interest | I7: Refund | J7: Balance
A8: Beg. Bal. | D8: =-'WP Unprotected Balances'!D24/0.79 -> 33684805 | G8: =-'WP Unprotected Balances'!D33/0.79 -> 12848996 | J8: =D8+G8 -> 46533801
A9: 43831 | B9: =$C$4/12*D8 -> 233904.83 | C9: -827615.43 | D9: =D8+B9+C9 -> 33091094 | F9: =-G8 -> -12848996 | H9: =B9 -> 233904.83 | I9: =C9+F9 -> -13676612 | J9: =J8+H9+I9 -> 33091094
A10: 43862 | B10: =$C$4/12*D9 -> 229782.15 | C10: =C9 -> -827615.43 | D10: =D9+B10+C10 -> 32493261 | H10: =B10 -> 229782.15 | I10: =C10+F10 -> -827615.43 | J10: =J9+H10+I10 -> 32493261
A11: 43891 | B11: =$C$4/12*D10 -> 225630.84 | C11: =C10 -> -827615.43 | D11: =D10+B11+C11 -> 31891277 | H11: =B11 -> 225630.84 | I11: =C11+F11 -> -827615.43 | J11: =J10+H11+I11 -> 31891277
A12: 43922 | B12: =$C$4/12*D11 -> 221450.7 | C12: =C11 -> -827615.43 | D12: =D11+B12+C12 -> 31285112 | H12: =B12 -> 221450.7 | I12: =C12+F12 -> -827615.43 | J12: =J11+H12+I12 -> 31285112
A13: 43952 | B13: =$C$4/12*D12 -> 217241.54 | C13: =C12 -> -827615.43 | D13: =D12+B13+C13 -> 30674738 | H13: =B13 -> 217241.54 | I13: =C13+F13 -> -827615.43 | J13: =J12+H13+I13 -> 30674738
A14: 43983 | B14: =$C$4/12*D13 -> 213003.15 | C14: =C13 -> -827615.43 | D14: =D13+B14+C14 -> 30060126 | H14: =B14 -> 213003.15 | I14: =C14+F14 -> -827615.43 | J14: =J13+H14+I14 -> 30060126
A15: 44013 | B15: =$C$4/12*D14 -> 208735.32 | C15: =C14 -> -827615.43 | D15: =D14+B15+C15 -> 29441246 | H15: =B15 -> 208735.32 | I15: =C15+F15 -> -827615.43 | J15: =J14+H15+I15 -> 29441246
A16: 44044 | B16: =$C$4/12*D15 -> 204437.87 | C16: =C15 -> -827615.43 | D16: =D15+B16+C16 -> 28818068 | H16: =B16 -> 204437.87 | I16: =C16+F16 -> -827615.43 | J16: =J15+H16+I16 -> 28818068
A17: 44075 | B17: =$C$4/12*D16 -> 200110.57 | C17: =C16 -> -827615.43 | D17: =D16+B17+C17 -> 28190563 | H17: =B17 -> 200110.57 | I17: =C17+F17 -> -827615.43 | J17: =J16+H17+I17 -> 28190563
A18: 44105 | B18: =$C$4/12*D17 -> 195753.22 | C18: =C17 -> -827615.43 | D18: =D17+B18+C18 -> 27558701 | H18: =B18 -> 195753.22 | I18: =C18+F18 -> -827615.43 | J18: =J17+H18+I18 -> 27558701
A19: 44136 | B19: =$C$4/12*D18 -> 191365.61 | C19: =C18 -> -827615.43 | D19: =D18+B19+C19 -> 26922451 | H19: =B19 -> 191365.61 | I19: =C19+F19 -> -827615.43 | J19: =J18+H19+I19 -> 26922451
A20: 44166 | B20: =$C$4/12*D19 -> 186947.54 | C20: =C19 -> -827615.43 | D20: =D19+B20+C20 -> 26281783 | H20: =B20 -> 186947.54 | I20: =C20+F20 -> -827615.43 | J20: =J19+H20+I20 -> 26281783
A21: 44197 | B21: =$C$4/12*D20 -> 182498.79 | C21: =C20 -> -827615.43 | D21: =D20+B21+C21 -> 25636667 | H21: =B21 -> 182498.79 | I21: =C21+F21 -> -827615.43 | J21: =J20+H21+I21 -> 25636667
... A56: 45261 | B56: =$C$4/12*D55 -> 5707.2705 | C56: =C55 -> -827615.43 | D56: =D55+B56+C56 -> -1.8288847e-07 | H56: =B56 -> 5707.2705 | I56: =C56+F56 -> -827615.43 | J56: =J55+H56+I56 -> -1.8288847e-07
A57: Total | B57: =SUM(B9:B56) -> 6040735.8 | C57: =SUM(C9:C56) -> -39725541 | E57: =SUM(E9:E56) -> 0 | F57: =SUM(F9:F56) -> -12848996 | H57: =SUM(H9:H56) -> 6040735.8 | I57: =SUM(I9:I56) -> -52574537
B59: TNC Distribution | E59: TNC Transmission | H59: TNC Total
A60: Month | B60: Interest | C60: Refund | D60: Balance | E60: Interest | F60: Refund | G60: Balance | H60: Interest | I60: Refund | J60: Balance
A61: Beg. Bal. | D61: =-'WP Unprotected Balances'!D13/0.79 -> 21747678 | G61: =-'WP Unprotected Balances'!D42/0.79 -> 3926274.7 | J61: =D61+G61 -> 25673953
A62: 43831 | B62: =$C$4/12*D61 -> 151014.3 | C62: -534327.4 | D62: =D61+B62+C62 -> 21364365 | F62: =-G61 -> -3926274.7 | G62: =G61+E62+F62 -> 0 | H62: =B62 -> 151014.3 | I62: =C62+F62 -> -4460602.1 | J62: =J61+H62+I62 -> 21364365
A63: 43862 | B63: =$C$4/12*D62 -> 148352.6 | C63: =C62 -> -534327.4 | D63: =D62+B63+C63 -> 20978391 | G63: =G62+E63+F63 -> 0 | H63: =B63 -> 148352.6 | I63: =C63+F63 -> -534327.4 | J63: =J62+H63+I63 -> 20978391
A64: 43891 | B64: =$C$4/12*D63 -> 145672.42 | C64: =C63 -> -534327.4 | D64: =D63+B64+C64 -> 20589736 | G64: =G63+E64+F64 -> 0 | H64: =B64 -> 145672.42 | I64: =C64+F64 -> -534327.4 | J64: =J63+H64+I64 -> 20589736
A65: 43922 | B65: =$C$4/12*D64 -> 142973.63 | C65: =C64 -> -534327.4 | D65: =D64+B65+C65 -> 20198382 | G65: =G64+E65+F65 -> 0 | H65: =B65 -> 142973.63 | I65: =C65+F65 -> -534327.4 | J65: =J64+H65+I65 -> 20198382
A66: 43952 | B66: =$C$4/12*D65 -> 140256.09 | C66: =C65 -> -534327.4 | D66: =D65+B66+C66 -> 19804311 | G66: =G65+E66+F66 -> 0 | H66: =B66 -> 140256.09 | I66: =C66+F66 -> -534327.4 | J66: =J65+H66+I66 -> 19804311
A67: 43983 | B67: =$C$4/12*D66 -> 137519.69 | C67: =C66 -> -534327.4 | D67: =D66+B67+C67 -> 19407503 | G67: =G66+E67+F67 -> 0 | H67: =B67 -> 137519.69 | I67: =C67+F67 -> -534327.4 | J67: =J66+H67+I67 -> 19407503
A68: 44013 | B68: =$C$4/12*D67 -> 134764.29 | C68: =C67 -> -534327.4 | D68: =D67+B68+C68 -> 19007940 | G68: =G67+E68+F68 -> 0 | H68: =B68 -> 134764.29 | I68: =C68+F68 -> -534327.4 | J68: =J67+H68+I68 -> 19007940
A69: 44044 | B69: =$C$4/12*D68 -> 131989.75 | C69: =C68 -> -534327.4 | D69: =D68+B69+C69 -> 18605602 | G69: =G68+E69+F69 -> 0 | H69: =B69 -> 131989.75 | I69: =C69+F69 -> -534327.4 | J69: =J68+H69+I69 -> 18605602
A70: 44075 | B70: =$C$4/12*D69 -> 129195.95 | C70: =C69 -> -534327.4 | D70: =D69+B70+C70 -> 18200471 | G70: =G69+E70+F70 -> 0 | H70: =B70 -> 129195.95 | I70: =C70+F70 -> -534327.4 | J70: =J69+H70+I70 -> 18200471
A71: 44105 | B71: =$C$4/12*D70 -> 126382.74 | C71: =C70 -> -534327.4 | D71: =D70+B71+C71 -> 17792526 | G71: =G70+E71+F71 -> 0 | H71: =B71 -> 126382.74 | I71: =C71+F71 -> -534327.4 | J71: =J70+H71+I71 -> 17792526
A72: 44136 | B72: =$C$4/12*D71 -> 123550 | C72: =C71 -> -534327.4 | D72: =D71+B72+C72 -> 17381749 | G72: =G71+E72+F72 -> 0 | H72: =B72 -> 123550 | I72: =C72+F72 -> -534327.4 | J72: =J71+H72+I72 -> 17381749
A73: 44166 | B73: =$C$4/12*D72 -> 120697.6 | C73: =C72 -> -534327.4 | D73: =D72+B73+C73 -> 16968119 | G73: =G72+E73+F73 -> 0 | H73: =B73 -> 120697.6 | I73: =C73+F73 -> -534327.4 | J73: =J72+H73+I73 -> 16968119
A74: 44197 | B74: =$C$4/12*D73 -> 117825.38 | C74: =C73 -> -534327.4 | D74: =D73+B74+C74 -> 16551617 | G74: =G73+E74+F74 -> 0 | H74: =B74 -> 117825.38 | I74: =C74+F74 -> -534327.4 | J74: =J73+H74+I74 -> 16551617
... A109: 45261 | B109: =$C$4/12*D108 -> 3684.744 | C109: =C108 -> -534327.4 | D109: =D108+B109+C109 -> 4.4237822e-09 | G109: =G108+E109+F109 -> 0 | H109: =B109 -> 3684.744 | I109: =C109+F109 -> -534327.4 | J109: =J108+H109+I109 -> 4.4237822e-09
B110: =SUM(B62:B109) -> 3900036.8 | C110: =SUM(C62:C109) -> -25647715 | E110: =SUM(E62:E109) -> 0 | F110: =SUM(F62:F109) -> -3926274.7 | H110: =SUM(H62:H109) -> 3900036.8 | I110: =SUM(I62:I109) -> -29573990
B112: Total Distribution | E112: Total Transmission | H112: Total Total
A113: Month | B113: Interest | C113: Refund | D113: Balance | E113: Interest | F113: Refund | G113: Balance | H113: Interest | I113: Refund | J113: Balance
A114: Beg. Bal. | D114: =D8+D61 -> 55432484 | G114: =G8+G61 -> 16775271 | J114: =D114+G114 -> 72207754
A115: 43831 | B115: =B9+B62 -> 384919.13 | C115: =C9+C62 -> -1361942.8 | D115: =D114+B115+C115 -> 54455460 | E115: =E9+E62 -> 0 | F115: =F9+F62 -> -16775271 | G115: =G114+E115+F115 -> 0 | H115: =H9+H62 -> 384919.13 | I115: =I9+I62 -> -18137214 | J115: =J114+H115+I115 -> 54455460
A116: 43862 | B116: =B10+B63 -> 378134.75 | C116: =C10+C63 -> -1361942.8 | D116: =D115+B116+C116 -> 53471652 | E116: =E10+E63 -> 0 | F116: =F10+F63 -> 0 | G116: =G115+E116+F116 -> 0 | H116: =H10+H63 -> 378134.75 | I116: =I10+I63 -> -1361942.8 | J116: =J115+H116+I116 -> 53471652
A117: 43891 | B117: =B11+B64 -> 371303.26 | C117: =C11+C64 -> -1361942.8 | D117: =D116+B117+C117 -> 52481012 | E117: =E11+E64 -> 0 | F117: =F11+F64 -> 0 | G117: =G116+E117+F117 -> 0 | H117: =H11+H64 -> 371303.26 | I117: =I11+I64 -> -1361942.8 | J117: =J116+H117+I117 -> 52481012
A118: 43922 | B118: =B12+B65 -> 364424.33 | C118: =C12+C65 -> -1361942.8 | D118: =D117+B118+C118 -> 51483494 | E118: =E12+E65 -> 0 | F118: =F12+F65 -> 0 | G118: =G117+E118+F118 -> 0 | H118: =H12+H65 -> 364424.33 | I118: =I12+I65 -> -1361942.8 | J118: =J117+H118+I118 -> 51483494
A119: 43952 | B119: =B13+B66 -> 357497.63 | C119: =C13+C66 -> -1361942.8 | D119: =D118+B119+C119 -> 50479048 | E119: =E13+E66 -> 0 | F119: =F13+F66 -> 0 | G119: =G118+E119+F119 -> 0 | H119: =H13+H66 -> 357497.63 | I119: =I13+I66 -> -1361942.8 | J119: =J118+H119+I119 -> 50479048
A120: 43983 | B120: =B14+B67 -> 350522.84 | C120: =C14+C67 -> -1361942.8 | D120: =D119+B120+C120 -> 49467628 | E120: =E14+E67 -> 0 | F120: =F14+F67 -> 0 | G120: =G119+E120+F120 -> 0 | H120: =H14+H67 -> 350522.84 | I120: =I14+I67 -> -1361942.8 | J120: =J119+H120+I120 -> 49467628
A121: 44013 | B121: =B15+B68 -> 343499.61 | C121: =C15+C68 -> -1361942.8 | D121: =D120+B121+C121 -> 48449185 | E121: =E15+E68 -> 0 | F121: =F15+F68 -> 0 | G121: =G120+E121+F121 -> 0 | H121: =H15+H68 -> 343499.61 | I121: =I15+I68 -> -1361942.8 | J121: =J120+H121+I121 -> 48449185
A122: 44044 | B122: =B16+B69 -> 336427.62 | C122: =C16+C69 -> -1361942.8 | D122: =D121+B122+C122 -> 47423670 | E122: =E16+E69 -> 0 | F122: =F16+F69 -> 0 | G122: =G121+E122+F122 -> 0 | H122: =H16+H69 -> 336427.62 | I122: =I16+I69 -> -1361942.8 | J122: =J121+H122+I122 -> 47423670
A123: 44075 | B123: =B17+B70 -> 329306.51 | C123: =C17+C70 -> -1361942.8 | D123: =D122+B123+C123 -> 46391034 | E123: =E17+E70 -> 0 | F123: =F17+F70 -> 0 | G123: =G122+E123+F123 -> 0 | H123: =H17+H70 -> 329306.51 | I123: =I17+I70 -> -1361942.8 | J123: =J122+H123+I123 -> 46391034
A124: 44105 | B124: =B18+B71 -> 322135.96 | C124: =C18+C71 -> -1361942.8 | D124: =D123+B124+C124 -> 45351227 | E124: =E18+E71 -> 0 | F124: =F18+F71 -> 0 | G124: =G123+E124+F124 -> 0 | H124: =H18+H71 -> 322135.96 | I124: =I18+I71 -> -1361942.8 | J124: =J123+H124+I124 -> 45351227
A125: 44136 | B125: =B19+B72 -> 314915.62 | C125: =C19+C72 -> -1361942.8 | D125: =D124+B125+C125 -> 44304200 | E125: =E19+E72 -> 0 | F125: =F19+F72 -> 0 | G125: =G124+E125+F125 -> 0 | H125: =H19+H72 -> 314915.62 | I125: =I19+I72 -> -1361942.8 | J125: =J124+H125+I125 -> 44304200
A126: 44166 | B126: =B20+B73 -> 307645.14 | C126: =C20+C73 -> -1361942.8 | D126: =D125+B126+C126 -> 43249902 | E126: =E20+E73 -> 0 | F126: =F20+F73 -> 0 | G126: =G125+E126+F126 -> 0 | H126: =H20+H73 -> 307645.14 | I126: =I20+I73 -> -1361942.8 | J126: =J125+H126+I126 -> 43249902
... A162: 45261 | B162: =B56+B109 -> 9392.0145 | C162: =C56+C109 -> -1361942.8 | D162: =D161+B162+C162 -> -2.0954758e-07 | E162: =E56+E109 -> 0 | F162: =F56+F109 -> 0 | G162: =G161+E162+F162 -> 0 | H162: =H56+H109 -> 9392.0145 | I162: =I56+I109 -> -1361942.8 | J162: =J161+H162+I162 -> -2.02097e-07
B163: =SUM(B115:B162) -> 9940772.5 | C163: =SUM(C115:C162) -> -65373256 | E163: =SUM(E115:E162) -> 0 | F163: =SUM(F115:F162) -> -16775271 | H163: =SUM(H115:H162) -> 9940772.5 | I163: =SUM(I115:I162) -> -82148527

Sheet WP Unprotected Balances
A1: AEP Texas
A2: Unprotected Texas Excess Balance
A3: As of January 1, 2020
B6: TNC Dist
B7: 282- TX unprotected | C7: 283- TX unprotected | D7: Total
A9: March 2019 Balance | B9: -10482731 | C9: -8478018 | D9: =SUM(B9:C9) -> -18960749 | E9: =D9/0.79 -> -24000948
A11: Apr - Dec 19 Amort | B11: =197787*9 -> 1780083 | D11: =SUM(B11:C11) -> 1780083
A13: Jan 1, 2020 Balance | B13: =SUM(B9:B11) -> -8702648 | C13: =SUM(C9:C12) -> -8478018 | D13: =SUM(B13:C13) -> -17180666
B15: TCC Dist
B16: 282- TX unprotected | C16: 283- TX unprotected | D16: Total
A18: March 2019 Balance | B18: -34913506 | C18: -47820231 | D18: =SUM(B18:C18) -> -82733737 | E18: =D18/0.79 -> -1.0472625e+08
A20: Apr - Dec 19 Amort | B20: =658745*9 -> 5928705 | C20: 0 | D20: =SUM(B20:C20) -> 5928705
A22: Hurricane Harvey Securitization | B22: 2373805 | C22: 47820231 | D22: =SUM(B22:C22) -> 50194036
A24: Jan 1, 2020 Balance | B24: =SUM(B18:B22) -> -26610996 | C24: =SUM(C18:C22) -> 0 | D24: =SUM(D18:D22) -> -26610996 | E24: Good (Not Grossed-Up Values)
B26: TCC Tran | D26: =(D24-D20)*1/0.79 -> -41189495
B27: 282- TX unprotected | C27: 283- TX unprotected | D27: Total
A29: March 2019 Balance | B29: -1031149 | C29: -9119558 | D29: =SUM(B29:C29) -> -10150707 | E29: =D29/0.79 -> -12848996
A31: Apr - Dec 19 Amort | B31: 0 | C31: 0 | D31: =SUM(B31:C31) -> 0
A33: Jan 1, 2020 Balance | B33: =SUM(B29:B31) -> -1031149 | C33: =SUM(C29:C32) -> -9119558 | D33: =SUM(B33:C33) -> -10150707
D34: =D33*1/0.79 -> -12848996
B35: TNC Tran
B36: 282- TX unprotected | C36: 283- TX unprotected | D36: Total
A38: March 2019 Balance | B38: -2315223 | C38: -786534 | D38: =SUM(B38:C38) -> -3101757 | E38: =D38/0.79 -> -3926274.7
A40: Apr - Dec 19 Amort | B40: 0 | C40: 0 | D40: =SUM(B40:C40) -> 0
A42: Jan 1, 2020 Balance | B42: =SUM(B38:B40) -> -2315223 | C42: =SUM(C38:C41) -> -786534 | D42: =SUM(B42:C42) -> -3101757
