Workbook

Sheet RBH-1 Constant Growth DCF
B2: Constant Growth Discounted Cash Flow Model
B3: 30 Day Average Stock Price
E5: [1] | F5: [2] | G5: [3] | H5: [4] | I5: [5] | J5: [6] | K5: [7] | L5: [8] | N5: [9] | O5: [10] | P5: [11]
B6: Company | C6: Ticker | E6: Annualized Dividend | F6: Average Stock Price | G6: Dividend Yield | H6: Expected Dividend Yield | I6: Zacks Earnings Growth | J6: First Call Earnings Growth | K6: Value Line Earnings Growth | L6: Average Earnings Growth | N6: Low ROE | O6: Mean ROE | P6: High ROE
B8: ALLETE, Inc. | C8: ALE | E8: 2.35 | F8: 80.266667 | G8: =E8/F8 -> 0.029277409 | H8: =G8*(1+0.5*L8) -> 0.030082537 | I8: NA | J8: 0.06 | K8: 0.05 | L8: =AVERAGE(I8:K8) -> 0.055 | N8: =G8*(1+0.5*MIN(I8:K8))+MIN(I8:K8) -> 0.080009344 | O8: =H8+L8 -> 0.085082537 | P8: =G8*(1+0.5*MAX(I8:K8))+MAX(I8:K8) -> 0.090155731
B9: Alliant Energy Corporation | C9: LNT | E9: 1.42 | F9: 45.564667 | G9: =E9/F9 -> 0.031164499 | H9: =G9*(1+0.5*L9) -> 0.03219033 | I9: 0.06 | J9: 0.0725 | K9: 0.065 | L9: =AVERAGE(I9:K9) -> 0.065833333 | N9: =G9*(1+0.5*MIN(I9:K9))+MIN(I9:K9) -> 0.092099434 | O9: =H9+L9 -> 0.098023664 | P9: =G9*(1+0.5*MAX(I9:K9))+MAX(I9:K9) -> 0.10479421
B10: Ameren Corporation | C10: AEE | E10: 1.9 | F10: 70.764333 | G10: =E10/F10 -> 0.026849684 | H10: =G10*(1+0.5*L10) -> 0.027789423 | I10: 0.068 | J10: 0.077 | K10: 0.065 | L10: =AVERAGE(I10:K10) -> 0.07 | N10: =G10*(1+0.5*MIN(I10:K10))+MIN(I10:K10) -> 0.092722299 | O10: =H10+L10 -> 0.097789423 | P10: =G10*(1+0.5*MAX(I10:K10))+MAX(I10:K10) -> 0.1048834
B11: Avangrid, Inc. | C11: AGR | E11: 1.76 | F11: 49.391 | G11: =E11/F11 -> 0.035634022 | H11: =G11*(1+0.5*L11) -> 0.037350394 | I11: 0.077 | J11: 0.092 | K11: 0.12 | L11: =AVERAGE(I11:K11) -> 0.096333333 | N11: =G11*(1+0.5*MIN(I11:K11))+MIN(I11:K11) -> 0.11400593 | O11: =H11+L11 -> 0.13368373 | P11: =G11*(1+0.5*MAX(I11:K11))+MAX(I11:K11) -> 0.15777206
B12: Black Hills Corporation | C12: BKH | E12: 2.02 | F12: 70.591333 | G12: =E12/F12 -> 0.028615411 | H12: =G12*(1+0.5*L12) -> 0.029322688 | I12: 0.047 | J12: 0.0363 | K12: 0.065 | L12: =AVERAGE(I12:K12) -> 0.049433333 | N12: =G12*(1+0.5*MIN(I12:K12))+MIN(I12:K12) -> 0.06543478 | O12: =H12+L12 -> 0.078756022 | P12: =G12*(1+0.5*MAX(I12:K12))+MAX(I12:K12) -> 0.094545412
B13: CMS Energy Corporation | C13: CMS | E13: 1.53 | F13: 53.586333 | G13: =E13/F13 -> 0.028552056 | H13: =G13*(1+0.5*L13) -> 0.029498557 | I13: 0.06 | J13: 0.0689 | K13: 0.07 | L13: =AVERAGE(I13:K13) -> 0.0663 | N13: =G13*(1+0.5*MIN(I13:K13))+MIN(I13:K13) -> 0.089408618 | O13: =H13+L13 -> 0.095798557 | P13: =G13*(1+0.5*MAX(I13:K13))+MAX(I13:K13) -> 0.099551378
B14: Consolidated Edison, Inc. | C14: ED | E14: 2.96 | F14: 80.953667 | G14: =E14/F14 -> 0.036564125 | H14: =G14*(1+0.5*L14) -> 0.037051037 | I14: 0.02 | J14: 0.0299 | K14: 0.03 | L14: =AVERAGE(I14:K14) -> 0.026633333 | N14: =G14*(1+0.5*MIN(I14:K14))+MIN(I14:K14) -> 0.056929766 | O14: =H14+L14 -> 0.063684371 | P14: =G14*(1+0.5*MAX(I14:K14))+MAX(I14:K14) -> 0.067112587
B15: DTE Energy Company | C15: DTE | E15: 3.78 | F15: 121.32633 | G15: =E15/F15 -> 0.031155644 | H15: =G15*(1+0.5*L15) -> 0.031942843 | I15: 0.06 | J15: 0.0416 | K15: 0.05 | L15: =AVERAGE(I15:K15) -> 0.050533333 | N15: =G15*(1+0.5*MIN(I15:K15))+MIN(I15:K15) -> 0.073403681 | O15: =H15+L15 -> 0.082476176 | P15: =G15*(1+0.5*MAX(I15:K15))+MAX(I15:K15) -> 0.092090313
B16: Duke Energy Corporation | C16: DUK | E16: 3.71 | F16: 89.399333 | G16: =E16/F16 -> 0.041499191 | H16: =G16*(1+0.5*L16) -> 0.042536671 | I16: 0.05 | J16: 0.045 | K16: 0.055 | L16: =AVERAGE(I16:K16) -> 0.05 | N16: =G16*(1+0.5*MIN(I16:K16))+MIN(I16:K16) -> 0.087432923 | O16: =H16+L16 -> 0.092536671 | P16: =G16*(1+0.5*MAX(I16:K16))+MAX(I16:K16) -> 0.097640419
B17: El Paso Electric Company | C17: EE | E17: 1.44 | F17: 55.155333 | G17: =E17/F17 -> 0.026108083 | H17: =G17*(1+0.5*L17) -> 0.026578028 | I17: 0.027 | J17: 0.051 | K17: 0.03 | L17: =AVERAGE(I17:K17) -> 0.036 | N17: =G17*(1+0.5*MIN(I17:K17))+MIN(I17:K17) -> 0.053460542 | O17: =H17+L17 -> 0.062578028 | P17: =G17*(1+0.5*MAX(I17:K17))+MAX(I17:K17) -> 0.077773839
B18: Evergy, Inc | C18: EVRG | E18: 1.9 | F18: 57.002667 | G18: =E18/F18 -> 0.033331774 | H18: =G18*(1+0.5*L18) -> 0.03441089 | I18: 0.067 | J18: 0.0625 | K18: NMF | L18: =AVERAGE(I18:K18) -> 0.06475 | N18: =G18*(1+0.5*MIN(I18:K18))+MIN(I18:K18) -> 0.096873392 | O18: =H18+L18 -> 0.09916089 | P18: =G18*(1+0.5*MAX(I18:K18))+MAX(I18:K18) -> 0.10144839
B19: Eversource Energy | C19: ES | E19: 2.14 | F19: 69.894333 | G19: =E19/F19 -> 0.030617647 | H19: =G19*(1+0.5*L19) -> 0.031489229 | I19: 0.057 | J19: 0.0588 | K19: 0.055 | L19: =AVERAGE(I19:K19) -> 0.056933333 | N19: =G19*(1+0.5*MIN(I19:K19))+MIN(I19:K19) -> 0.086459632 | O19: =H19+L19 -> 0.088422562 | P19: =G19*(1+0.5*MAX(I19:K19))+MAX(I19:K19) -> 0.090317805
B20: Hawaiian Electric Industries, Inc. | C20: HE | E20: 1.28 | F20: 38.426667 | G20: =E20/F20 -> 0.033310201 | H20: =G20*(1+0.5*L20) -> 0.034281749 | I20: 0.062 | J20: 0.078 | K20: 0.035 | L20: =AVERAGE(I20:K20) -> 0.058333333 | N20: =G20*(1+0.5*MIN(I20:K20))+MIN(I20:K20) -> 0.06889313 | O20: =H20+L20 -> 0.092615082 | P20: =G20*(1+0.5*MAX(I20:K20))+MAX(I20:K20) -> 0.1126093
B21: NextEra Energy, Inc. | C21: NEE | E21: 5 | F21: 185.68567 | G21: =E21/F21 -> 0.026927226 | H21: =G21*(1+0.5*L21) -> 0.028011496 | I21: 0.077 | J21: 0.0746 | K21: 0.09 | L21: =AVERAGE(I21:K21) -> 0.080533333 | N21: =G21*(1+0.5*MIN(I21:K21))+MIN(I21:K21) -> 0.10253161 | O21: =H21+L21 -> 0.10854483 | P21: =G21*(1+0.5*MAX(I21:K21))+MAX(I21:K21) -> 0.11813895
B22: NorthWestern Corporation | C22: NWE | E22: 2.3 | F22: 67.207333 | G22: =E22/F22 -> 0.034222456 | H22: =G22*(1+0.5*L22) -> 0.034698148 | I22: 0.031 | J22: 0.0274 | K22: 0.025 | L22: =AVERAGE(I22:K22) -> 0.0278 | N22: =G22*(1+0.5*MIN(I22:K22))+MIN(I22:K22) -> 0.059650237 | O22: =H22+L22 -> 0.062498148 | P22: =G22*(1+0.5*MAX(I22:K22))+MAX(I22:K22) -> 0.065752904
B23: OGE Energy Corp. | C23: OGE | E23: 1.46 | F23: 41.971 | G23: =E23/F23 -> 0.034785924 | H23: =G23*(1+0.5*L23) -> 0.035768626 | I23: 0.048 | J23: NA | K23: 0.065 | L23: =AVERAGE(I23:K23) -> 0.0565 | N23: =G23*(1+0.5*MIN(I23:K23))+MIN(I23:K23) -> 0.083620786 | O23: =H23+L23 -> 0.092268626 | P23: =G23*(1+0.5*MAX(I23:K23))+MAX(I23:K23) -> 0.10091647
B24: Otter Tail Corporation | C24: OTTR | E24: 1.4 | F24: 49.899 | G24: =E24/F24 -> 0.028056674 | H24: =G24*(1+0.5*L24) -> 0.029038658 | I24: NA | J24: 0.09 | K24: 0.05 | L24: =AVERAGE(I24:K24) -> 0.07 | N24: =G24*(1+0.5*MIN(I24:K24))+MIN(I24:K24) -> 0.078758091 | O24: =H24+L24 -> 0.099038658 | P24: =G24*(1+0.5*MAX(I24:K24))+MAX(I24:K24) -> 0.11931922
B25: Pinnacle West Capital Corporation | C25: PNW | E25: 2.95 | F25: 91.666333 | G25: =E25/F25 -> 0.032181935 | H25: =G25*(1+0.5*L25) -> 0.033005793 | I25: 0.048 | J25: 0.0456 | K25: 0.06 | L25: =AVERAGE(I25:K25) -> 0.0512 | N25: =G25*(1+0.5*MIN(I25:K25))+MIN(I25:K25) -> 0.078515683 | O25: =H25+L25 -> 0.084205793 | P25: =G25*(1+0.5*MAX(I25:K25))+MAX(I25:K25) -> 0.093147393
B26: PNM Resources, Inc. | C26: PNM | E26: 1.16 | F26: 44.137 | G26: =E26/F26 -> 0.026281804 | H26: =G26*(1+0.5*L26) -> 0.026991413 | I26: 0.046 | J26: 0.041 | K26: 0.075 | L26: =AVERAGE(I26:K26) -> 0.054 | N26: =G26*(1+0.5*MIN(I26:K26))+MIN(I26:K26) -> 0.067820581 | O26: =H26+L26 -> 0.080991413 | P26: =G26*(1+0.5*MAX(I26:K26))+MAX(I26:K26) -> 0.10226737
B27: Portland General Electric Company | C27: POR | E27: 1.45 | F27: 49.886667 | G27: =E27/F27 -> 0.029065883 | H27: =G27*(1+0.5*L27) -> 0.029690799 | I27: 0.04 | J27: 0.049 | K27: 0.04 | L27: =AVERAGE(I27:K27) -> 0.043 | N27: =G27*(1+0.5*MIN(I27:K27))+MIN(I27:K27) -> 0.0696472 | O27: =H27+L27 -> 0.072690799 | P27: =G27*(1+0.5*MAX(I27:K27))+MAX(I27:K27) -> 0.078777997
B28: Southern Company | C28: SO | E28: 2.4 | F28: 49.840333 | G28: =E28/F28 -> 0.048153771 | H28: =G28*(1+0.5*L28) -> 0.048969175 | I28: 0.045 | J28: 0.0216 | K28: 0.035 | L28: =AVERAGE(I28:K28) -> 0.033866667 | N28: =G28*(1+0.5*MIN(I28:K28))+MIN(I28:K28) -> 0.070273832 | O28: =H28+L28 -> 0.082835842 | P28: =G28*(1+0.5*MAX(I28:K28))+MAX(I28:K28) -> 0.094237231
B29: WEC Energy Group, Inc. | C29: WEC | E29: 2.36 | F29: 75.560333 | G29: =E29/F29 -> 0.031233319 | H29: =G29*(1+0.5*L29) -> 0.032013631 | I29: 0.044 | J29: 0.0459 | K29: 0.06 | L29: =AVERAGE(I29:K29) -> 0.049966667 | N29: =G29*(1+0.5*MIN(I29:K29))+MIN(I29:K29) -> 0.075920452 | O29: =H29+L29 -> 0.081980298 | P29: =G29*(1+0.5*MAX(I29:K29))+MAX(I29:K29) -> 0.092170319
B30: Xcel Energy Inc. | C30: XEL | E30: 1.62 | F30: 54.412667 | G30: =E30/F30 -> 0.029772479 | H30: =G30*(1+0.5*L30) -> 0.030665654 | I30: 0.059 | J30: 0.066 | K30: 0.055 | L30: =AVERAGE(I30:K30) -> 0.06 | N30: =G30*(1+0.5*MIN(I30:K30))+MIN(I30:K30) -> 0.085591223 | O30: =H30+L30 -> 0.090665654 | P30: =G30*(1+0.5*MAX(I30:K30))+MAX(I30:K30) -> 0.096754971
B32: Proxy Group Mean | G32: =AVERAGE(G8:G30) -> 0.03188527 | H32: =AVERAGE(H8:H30) -> 0.032755555 | I32: =AVERAGE(I8:I30) -> 0.052047619 | J32: =AVERAGE(J8:J30) -> 0.056118182 | K32: =AVERAGE(K8:K30) -> 0.056590909 | L32: =AVERAGE(L8:L30) -> 0.055345652 | N32: =AVERAGE(N8:N30) -> 0.079541877 | O32: =AVERAGE(O8:O30) -> 0.088101207 | P32: =AVERAGE(P8:P30) -> 0.097920768
B33: Proxy Group Median | G33: =MEDIAN(G8:G30) -> 0.031155644 | H33: =MEDIAN(H8:H30) -> 0.031942843 | I33: =MEDIAN(I8:I30) -> 0.05 | J33: =MEDIAN(J8:J30) -> 0.0549 | K33: =MEDIAN(K8:K30) -> 0.055 | L33: =MEDIAN(L8:L30) -> 0.055 | N33: =MEDIAN(N8:N30) -> 0.078758091 | O33: =MEDIAN(O8:O30) -> 0.088422562 | P33: =MEDIAN(P8:P30) -> 0.096754971
B35: Notes:
B36: [1] Source: Bloomberg Professional
B37: [2] Source: Bloomberg Professional, equals indicated number of trading day average as of March 15, 2019
B38: [3] Equals [1] / [2]
B39: [4] Equals [3] x (1 + 0.5 x [8])
B40: [5] Source: Zacks
B41: [6] Source: Yahoo! Finance
B42: [7] Source: Value Line
B43: [8] Equals Average([5], [6], [7])
B44: [9] Equals [3] x (1 + 0.5 x Minimum([5], [6], [7])) + Minimum([5], [6], [7])
B45: [10] Equals [4] + [8]
B46: [11] Equals [3] x (1 + 0.5 x Maximum([5], [6], [7])) + Maximum([5], [6], [7])
B49: =B2 -> Constant Growth Discounted Cash Flow Model
B50: 90 Day Average Stock Price
E52: [1] | F52: [2] | G52: [3] | H52: [4] | I52: [5] | J52: [6] | K52: [7] | L52: [8] | N52: [9] | O52: [10] | P52: [11]
B53: Company | C53: Ticker | E53: Annualized Dividend | F53: Average Stock Price | G53: Dividend Yield | H53: Expected Dividend Yield | I53: Zacks Earnings Growth | J53: First Call Earnings Growth | K53: Value Line Earnings Growth | L53: Average Earnings Growth | N53: Low ROE | O53: Mean ROE | P53: High ROE
B55: =B8 -> ALLETE, Inc. | C55: =C8 -> ALE | E55: =E8 -> 2.35 | F55: 78.181444 | G55: =E55/F55 -> 0.030058283 | H55: =G55*(1+0.5*L55) -> 0.030884886 | I55: =I8 -> NA | J55: =J8 -> 0.06 | K55: =K8 -> 0.05 | L55: =AVERAGE(I55:K55) -> 0.055 | N55: =G55*(1+0.5*MIN(I55:K55))+MIN(I55:K55) -> 0.08080974 | O55: =H55+L55 -> 0.085884886 | P55: =G55*(1+0.5*MAX(I55:K55))+MAX(I55:K55) -> 0.090960032
B56: =B9 -> Alliant Energy Corporation | C56: =C9 -> LNT | E56: =E9 -> 1.42 | F56: 44.331444 | G56: =E56/F56 -> 0.03203144 | H56: =G56*(1+0.5*L56) -> 0.033085808 | I56: =I9 -> 0.06 | J56: =J9 -> 0.0725 | K56: =K9 -> 0.065 | L56: =AVERAGE(I56:K56) -> 0.065833333 | N56: =G56*(1+0.5*MIN(I56:K56))+MIN(I56:K56) -> 0.092992383 | O56: =H56+L56 -> 0.098919142 | P56: =G56*(1+0.5*MAX(I56:K56))+MAX(I56:K56) -> 0.10569258
B57: =B10 -> Ameren Corporation | C57: =C10 -> AEE | E57: =E10 -> 1.9 | F57: 68.434222 | G57: =E57/F57 -> 0.027763887 | H57: =G57*(1+0.5*L57) -> 0.028735623 | I57: =I10 -> 0.068 | J57: =J10 -> 0.077 | K57: =K10 -> 0.065 | L57: =AVERAGE(I57:K57) -> 0.07 | N57: =G57*(1+0.5*MIN(I57:K57))+MIN(I57:K57) -> 0.093666213 | O57: =H57+L57 -> 0.098735623 | P57: =G57*(1+0.5*MAX(I57:K57))+MAX(I57:K57) -> 0.1058328
B58: =B11 -> Avangrid, Inc. | C58: =C11 -> AGR | E58: =E11 -> 1.76 | F58: 49.630889 | G58: =E58/F58 -> 0.035461787 | H58: =G58*(1+0.5*L58) -> 0.037169863 | I58: =I11 -> 0.077 | J58: =J11 -> 0.092 | K58: =K11 -> 0.12 | L58: =AVERAGE(I58:K58) -> 0.096333333 | N58: =G58*(1+0.5*MIN(I58:K58))+MIN(I58:K58) -> 0.11382707 | O58: =H58+L58 -> 0.1335032 | P58: =G58*(1+0.5*MAX(I58:K58))+MAX(I58:K58) -> 0.15758949
B59: =B12 -> Black Hills Corporation | C59: =C12 -> BKH | E59: =E12 -> 2.02 | F59: 66.381556 | G59: =E59/F59 -> 0.03043014 | H59: =G59*(1+0.5*L59) -> 0.031182271 | I59: =I12 -> 0.047 | J59: =J12 -> 0.0363 | K59: =K12 -> 0.065 | L59: =AVERAGE(I59:K59) -> 0.049433333 | N59: =G59*(1+0.5*MIN(I59:K59))+MIN(I59:K59) -> 0.067282447 | O59: =H59+L59 -> 0.080615605 | P59: =G59*(1+0.5*MAX(I59:K59))+MAX(I59:K59) -> 0.096419119
B60: =B13 -> CMS Energy Corporation | C60: =C13 -> CMS | E60: =E13 -> 1.53 | F60: 51.666111 | G60: =E60/F60 -> 0.029613222 | H60: =G60*(1+0.5*L60) -> 0.0305949 | I60: =I13 -> 0.06 | J60: =J13 -> 0.0689 | K60: =K13 -> 0.07 | L60: =AVERAGE(I60:K60) -> 0.0663 | N60: =G60*(1+0.5*MIN(I60:K60))+MIN(I60:K60) -> 0.090501618 | O60: =H60+L60 -> 0.0968949 | P60: =G60*(1+0.5*MAX(I60:K60))+MAX(I60:K60) -> 0.10064968
B61: =B14 -> Consolidated Edison, Inc. | C61: =C14 -> ED | E61: =E14 -> 2.96 | F61: 79.049444 | G61: =E61/F61 -> 0.037444918 | H61: =G61*(1+0.5*L61) -> 0.03794356 | I61: =I14 -> 0.02 | J61: =J14 -> 0.0299 | K61: =K14 -> 0.03 | L61: =AVERAGE(I61:K61) -> 0.026633333 | N61: =G61*(1+0.5*MIN(I61:K61))+MIN(I61:K61) -> 0.057819368 | O61: =H61+L61 -> 0.064576893 | P61: =G61*(1+0.5*MAX(I61:K61))+MAX(I61:K61) -> 0.068006592
B62: =B15 -> DTE Energy Company | C62: =C15 -> DTE | E62: =E15 -> 3.78 | F62: 117.08344 | G62: =E62/F62 -> 0.032284667 | H62: =G62*(1+0.5*L62) -> 0.033100393 | I62: =I15 -> 0.06 | J62: =J15 -> 0.0416 | K62: =K15 -> 0.05 | L62: =AVERAGE(I62:K62) -> 0.050533333 | N62: =G62*(1+0.5*MIN(I62:K62))+MIN(I62:K62) -> 0.074556188 | O62: =H62+L62 -> 0.083633726 | P62: =G62*(1+0.5*MAX(I62:K62))+MAX(I62:K62) -> 0.093253207
B63: =B16 -> Duke Energy Corporation | C63: =C16 -> DUK | E63: =E16 -> 3.71 | F63: 87.557111 | G63: =E63/F63 -> 0.042372344 | H63: =G63*(1+0.5*L63) -> 0.043431652 | I63: =I16 -> 0.05 | J63: =J16 -> 0.045 | K63: =K16 -> 0.055 | L63: =AVERAGE(I63:K63) -> 0.05 | N63: =G63*(1+0.5*MIN(I63:K63))+MIN(I63:K63) -> 0.088325721 | O63: =H63+L63 -> 0.093431652 | P63: =G63*(1+0.5*MAX(I63:K63))+MAX(I63:K63) -> 0.098537583
B64: =B17 -> El Paso Electric Company | C64: =C17 -> EE | E64: =E17 -> 1.44 | F64: 53.941333 | G64: =E64/F64 -> 0.026695669 | H64: =G64*(1+0.5*L64) -> 0.027176191 | I64: =I17 -> 0.027 | J64: =J17 -> 0.051 | K64: =K17 -> 0.03 | L64: =AVERAGE(I64:K64) -> 0.036 | N64: =G64*(1+0.5*MIN(I64:K64))+MIN(I64:K64) -> 0.054056061 | O64: =H64+L64 -> 0.063176191 | P64: =G64*(1+0.5*MAX(I64:K64))+MAX(I64:K64) -> 0.078376409
B65: =B18 -> Evergy, Inc | C65: =C18 -> EVRG | E65: =E18 -> 1.9 | F65: 57.635333 | G65: =E65/F65 -> 0.032965889 | H65: =G65*(1+0.5*L65) -> 0.03403316 | I65: =I18 -> 0.067 | J65: =J18 -> 0.0625 | K65: =K18 -> NMF | L65: =AVERAGE(I65:K65) -> 0.06475 | N65: =G65*(1+0.5*MIN(I65:K65))+MIN(I65:K65) -> 0.096496073 | O65: =H65+L65 -> 0.09878316 | P65: =G65*(1+0.5*MAX(I65:K65))+MAX(I65:K65) -> 0.10107025
B66: =B19 -> Eversource Energy | C66: =C19 -> ES | E66: =E19 -> 2.14 | F66: 67.678556 | G66: =E66/F66 -> 0.03162006 | H66: =G66*(1+0.5*L66) -> 0.032520178 | I66: =I19 -> 0.057 | J66: =J19 -> 0.0588 | K66: =K19 -> 0.055 | L66: =AVERAGE(I66:K66) -> 0.056933333 | N66: =G66*(1+0.5*MIN(I66:K66))+MIN(I66:K66) -> 0.087489612 | O66: =H66+L66 -> 0.089453511 | P66: =G66*(1+0.5*MAX(I66:K66))+MAX(I66:K66) -> 0.09134969
... B77: =B30 -> Xcel Energy Inc. | C77: =C30 -> XEL | E77: =E30 -> 1.62 | F77: 51.948444 | G77: =E77/F77 -> 0.031184764 | H77: =G77*(1+0.5*L77) -> 0.032120307 | I77: =I30 -> 0.059 | J77: =J30 -> 0.066 | K77: =K30 -> 0.055 | L77: =AVERAGE(I77:K77) -> 0.06 | N77: =G77*(1+0.5*MIN(I77:K77))+MIN(I77:K77) -> 0.087042345 | O77: =H77+L77 -> 0.092120307 | P77: =G77*(1+0.5*MAX(I77:K77))+MAX(I77:K77) -> 0.098213862
B79: Proxy Group Mean | G79: =AVERAGE(G55:G77) -> 0.032902448 | H79: =AVERAGE(H55:H77) -> 0.033798252 | I79: =AVERAGE(I55:I77) -> 0.052047619 | J79: =AVERAGE(J55:J77) -> 0.056118182 | K79: =AVERAGE(K55:K77) -> 0.056590909 | L79: =AVERAGE(L55:L77) -> 0.055345652 | N79: =AVERAGE(N55:N77) -> 0.080580515 | O79: =AVERAGE(O55:O77) -> 0.089143904 | P79: =AVERAGE(P55:P77) -> 0.098968061
B80: Proxy Group Median | G80: =MEDIAN(G55:G77) -> 0.03203144 | H80: =MEDIAN(H55:H77) -> 0.033085808 | I80: =MEDIAN(I55:I77) -> 0.05 | J80: =MEDIAN(J55:J77) -> 0.0549 | K80: =MEDIAN(K55:K77) -> 0.055 | L80: =MEDIAN(L55:L77) -> 0.055 | N80: =MEDIAN(N55:N77) -> 0.079580322 | O80: =MEDIAN(O55:O77) -> 0.089453511 | P80: =MEDIAN(P55:P77) -> 0.098213862
B82: Notes:
B83: =B36 -> [1] Source: Bloomberg Professional
B84: =B37 -> [2] Source: Bloomberg Professional, equals indicated number of trading day average as of March 15, 2019
B85: =B38 -> [3] Equals [1] / [2]
B86: =B39 -> [4] Equals [3] x (1 + 0.5 x [8])
B87: =B40 -> [5] Source: Zacks
B88: =B41 -> [6] Source: Yahoo! Finance
B89: =B42 -> [7] Source: Value Line
B90: =B43 -> [8] Equals Average([5], [6], [7])
B91: =B44 -> [9] Equals [3] x (1 + 0.5 x Minimum([5], [6], [7])) + Minimum([5], [6], [7])
B92: =B45 -> [10] Equals [4] + [8]
B93: =B46 -> [11] Equals [3] x (1 + 0.5 x Maximum([5], [6], [7])) + Maximum([5], [6], [7])
B96: =B49 -> Constant Growth Discounted Cash Flow Model
B97: 180 Day Average Stock Price
E99: [1] | F99: [2] | G99: [3] | H99: [4] | I99: [5] | J99: [6] | K99: [7] | L99: [8] | N99: [9] | O99: [10] | P99: [11]
B100: Company | C100: Ticker | E100: Annualized Dividend | F100: Average Stock Price | G100: Dividend Yield | H100: Expected Dividend Yield | I100: Zacks Earnings Growth | J100: First Call Earnings Growth | K100: Value Line Earnings Growth | L100: Average Earnings Growth | N100: Low ROE | O100: Mean ROE | P100: High ROE
B102: =B55 -> ALLETE, Inc. | C102: =C55 -> ALE | E102: =E55 -> 2.35 | F102: 77.342444 | G102: =E102/F102 -> 0.030384351 | H102: =G102*(1+0.5*L102) -> 0.031219921 | I102: =I55 -> NA | J102: =J55 -> 0.06 | K102: =K55 -> 0.05 | L102: =AVERAGE(I102:K102) -> 0.055 | N102: =G102*(1+0.5*MIN(I102:K102))+MIN(I102:K102) -> 0.08114396 | O102: =H102+L102 -> 0.086219921 | P102: =G102*(1+0.5*MAX(I102:K102))+MAX(I102:K102) -> 0.091295882
B103: =B56 -> Alliant Energy Corporation | C103: =C56 -> LNT | E103: =E56 -> 1.42 | F103: 43.677611 | G103: =E103/F103 -> 0.032510936 | H103: =G103*(1+0.5*L103) -> 0.033581087 | I103: =I56 -> 0.06 | J103: =J56 -> 0.0725 | K103: =K56 -> 0.065 | L103: =AVERAGE(I103:K103) -> 0.065833333 | N103: =G103*(1+0.5*MIN(I103:K103))+MIN(I103:K103) -> 0.093486264 | O103: =H103+L103 -> 0.099414421 | P103: =G103*(1+0.5*MAX(I103:K103))+MAX(I103:K103) -> 0.10618946
B104: =B57 -> Ameren Corporation | C104: =C57 -> AEE | E104: =E57 -> 1.9 | F104: 65.925667 | G104: =E104/F104 -> 0.028820338 | H104: =G104*(1+0.5*L104) -> 0.02982905 | I104: =I57 -> 0.068 | J104: =J57 -> 0.077 | K104: =K57 -> 0.065 | L104: =AVERAGE(I104:K104) -> 0.07 | N104: =G104*(1+0.5*MIN(I104:K104))+MIN(I104:K104) -> 0.094756999 | O104: =H104+L104 -> 0.09982905 | P104: =G104*(1+0.5*MAX(I104:K104))+MAX(I104:K104) -> 0.10692992
B105: =B58 -> Avangrid, Inc. | C105: =C58 -> AGR | E105: =E58 -> 1.76 | F105: 49.673 | G105: =E105/F105 -> 0.035431723 | H105: =G105*(1+0.5*L105) -> 0.037138351 | I105: =I58 -> 0.077 | J105: =J58 -> 0.092 | K105: =K58 -> 0.12 | L105: =AVERAGE(I105:K105) -> 0.096333333 | N105: =G105*(1+0.5*MIN(I105:K105))+MIN(I105:K105) -> 0.11379584 | O105: =H105+L105 -> 0.13347168 | P105: =G105*(1+0.5*MAX(I105:K105))+MAX(I105:K105) -> 0.15755763
B106: =B59 -> Black Hills Corporation | C106: =C59 -> BKH | E106: =E59 -> 2.02 | F106: 63.292444 | G106: =E106/F106 -> 0.031915342 | H106: =G106*(1+0.5*L106) -> 0.032704183 | I106: =I59 -> 0.047 | J106: =J59 -> 0.0363 | K106: =K59 -> 0.065 | L106: =AVERAGE(I106:K106) -> 0.049433333 | N106: =G106*(1+0.5*MIN(I106:K106))+MIN(I106:K106) -> 0.068794605 | O106: =H106+L106 -> 0.082137516 | P106: =G106*(1+0.5*MAX(I106:K106))+MAX(I106:K106) -> 0.09795259
B107: =B60 -> CMS Energy Corporation | C107: =C60 -> CMS | E107: =E60 -> 1.53 | F107: 50.313167 | G107: =E107/F107 -> 0.030409535 | H107: =G107*(1+0.5*L107) -> 0.031417611 | I107: =I60 -> 0.06 | J107: =J60 -> 0.0689 | K107: =K60 -> 0.07 | L107: =AVERAGE(I107:K107) -> 0.0663 | N107: =G107*(1+0.5*MIN(I107:K107))+MIN(I107:K107) -> 0.091321821 | O107: =H107+L107 -> 0.097717611 | P107: =G107*(1+0.5*MAX(I107:K107))+MAX(I107:K107) -> 0.10147387
B108: =B61 -> Consolidated Edison, Inc. | C108: =C61 -> ED | E108: =E61 -> 2.96 | F108: 78.629222 | G108: =E108/F108 -> 0.037645037 | H108: =G108*(1+0.5*L108) -> 0.038146344 | I108: =I61 -> 0.02 | J108: =J61 -> 0.0299 | K108: =K61 -> 0.03 | L108: =AVERAGE(I108:K108) -> 0.026633333 | N108: =G108*(1+0.5*MIN(I108:K108))+MIN(I108:K108) -> 0.058021488 | O108: =H108+L108 -> 0.064779677 | P108: =G108*(1+0.5*MAX(I108:K108))+MAX(I108:K108) -> 0.068209713
B109: =B62 -> DTE Energy Company | C109: =C62 -> DTE | E109: =E62 -> 3.78 | F109: 113.54772 | G109: =E109/F109 -> 0.033289968 | H109: =G109*(1+0.5*L109) -> 0.034131094 | I109: =I62 -> 0.06 | J109: =J62 -> 0.0416 | K109: =K62 -> 0.05 | L109: =AVERAGE(I109:K109) -> 0.050533333 | N109: =G109*(1+0.5*MIN(I109:K109))+MIN(I109:K109) -> 0.075582399 | O109: =H109+L109 -> 0.084664428 | P109: =G109*(1+0.5*MAX(I109:K109))+MAX(I109:K109) -> 0.094288667
B110: =B63 -> Duke Energy Corporation | C110: =C63 -> DUK | E110: =E63 -> 3.71 | F110: 84.288278 | G110: =E110/F110 -> 0.04401561 | H110: =G110*(1+0.5*L110) -> 0.045116001 | I110: =I63 -> 0.05 | J110: =J63 -> 0.045 | K110: =K63 -> 0.055 | L110: =AVERAGE(I110:K110) -> 0.05 | N110: =G110*(1+0.5*MIN(I110:K110))+MIN(I110:K110) -> 0.090005962 | O110: =H110+L110 -> 0.095116001 | P110: =G110*(1+0.5*MAX(I110:K110))+MAX(I110:K110) -> 0.10022604
B111: =B64 -> El Paso Electric Company | C111: =C64 -> EE | E111: =E64 -> 1.44 | F111: 57.172056 | G111: =E111/F111 -> 0.02518713 | H111: =G111*(1+0.5*L111) -> 0.025640498 | I111: =I64 -> 0.027 | J111: =J64 -> 0.051 | K111: =K64 -> 0.03 | L111: =AVERAGE(I111:K111) -> 0.036 | N111: =G111*(1+0.5*MIN(I111:K111))+MIN(I111:K111) -> 0.052527156 | O111: =H111+L111 -> 0.061640498 | P111: =G111*(1+0.5*MAX(I111:K111))+MAX(I111:K111) -> 0.076829402
B112: =B65 -> Evergy, Inc | C112: =C65 -> EVRG | E112: =E65 -> 1.9 | F112: 57.021778 | G112: =E112/F112 -> 0.033320603 | H112: =G112*(1+0.5*L112) -> 0.034399357 | I112: =I65 -> 0.067 | J112: =J65 -> 0.0625 | K112: =K65 -> NMF | L112: =AVERAGE(I112:K112) -> 0.06475 | N112: =G112*(1+0.5*MIN(I112:K112))+MIN(I112:K112) -> 0.096861871 | O112: =H112+L112 -> 0.099149357 | P112: =G112*(1+0.5*MAX(I112:K112))+MAX(I112:K112) -> 0.10143684
B113: =B66 -> Eversource Energy | C113: =C66 -> ES | E113: =E66 -> 2.14 | F113: 64.584222 | G113: =E113/F113 -> 0.033135028 | H113: =G113*(1+0.5*L113) -> 0.034078272 | I113: =I66 -> 0.057 | J113: =J66 -> 0.0588 | K113: =K66 -> 0.055 | L113: =AVERAGE(I113:K113) -> 0.056933333 | N113: =G113*(1+0.5*MIN(I113:K113))+MIN(I113:K113) -> 0.089046241 | O113: =H113+L113 -> 0.091011605 | P113: =G113*(1+0.5*MAX(I113:K113))+MAX(I113:K113) -> 0.092909198
... B124: =B77 -> Xcel Energy Inc. | C124: =C77 -> XEL | E124: =E77 -> 1.62 | F124: 49.725333 | G124: =E124/F124 -> 0.032578967 | H124: =G124*(1+0.5*L124) -> 0.033556336 | I124: =I77 -> 0.059 | J124: =J77 -> 0.066 | K124: =K77 -> 0.055 | L124: =AVERAGE(I124:K124) -> 0.06 | N124: =G124*(1+0.5*MIN(I124:K124))+MIN(I124:K124) -> 0.088474889 | O124: =H124+L124 -> 0.093556336 | P124: =G124*(1+0.5*MAX(I124:K124))+MAX(I124:K124) -> 0.099654073
B126: Proxy Group Mean | G126: =AVERAGE(G102:G124) -> 0.033750656 | H126: =AVERAGE(H102:H124) -> 0.034669672 | I126: =AVERAGE(I102:I124) -> 0.052047619 | J126: =AVERAGE(J102:J124) -> 0.056118182 | K126: =AVERAGE(K102:K124) -> 0.056590909 | L126: =AVERAGE(L102:L124) -> 0.055345652 | N126: =AVERAGE(N102:N124) -> 0.081448725 | O126: =AVERAGE(O102:O124) -> 0.090015324 | P126: =AVERAGE(P102:P124) -> 0.09984303
B127: Proxy Group Median | G127: =MEDIAN(G102:G124) -> 0.033135028 | H127: =MEDIAN(H102:H124) -> 0.034078272 | I127: =MEDIAN(I102:I124) -> 0.05 | J127: =MEDIAN(J102:J124) -> 0.0549 | K127: =MEDIAN(K102:K124) -> 0.055 | L127: =MEDIAN(L102:L124) -> 0.055 | N127: =MEDIAN(N102:N124) -> 0.08114396 | O127: =MEDIAN(O102:O124) -> 0.091011605 | P127: =MEDIAN(P102:P124) -> 0.099654073
B129: Notes:
B130: =B83 -> [1] Source: Bloomberg Professional
B131: =B84 -> [2] Source: Bloomberg Professional, equals indicated number of trading day average as of March 15, 2019
B132: =B85 -> [3] Equals [1] / [2]
B133: =B86 -> [4] Equals [3] x (1 + 0.5 x [8])
B134: =B87 -> [5] Source: Zacks
B135: =B88 -> [6] Source: Yahoo! Finance
B136: =B89 -> [7] Source: Value Line
B137: =B90 -> [8] Equals Average([5], [6], [7])
...

Sheet RBH-2 MRP Bloomberg
B2: Ex-Ante Market Risk Premium
B3: Market DCF Method Based - Bloomberg
D5: [1] | E5: [2] | F5: [3]
D6: S&P 500 Est. Required Market Return | E6: Current 30-Year Treasury (30-day average) | F6: Implied Market Risk Premium
D7: =I512 -> 0.13639002 | E7: ='RBH-4 CAPM'!C10 -> 0.030316667 | F7: =D7-E7 -> 0.10607335
D10: [4] | E10: [5] | F10: [6] | G10: [7] | H10: [8] | I10: [9]
B11: Company | C11: Ticker | D11: Market Capitalization | E11: Weight in Index | F11: Estimated Dividend Yield | G11: Long-Term Growth Est. | H11: DCF Result | I11: Weighted DCF Result
B12: Agilent Technologies Inc | C12: A | D12: 25750.537 | E12: =IF(OR(H12="N/A",D12="N/A"),"N/A",D12/$D$512) -> N/A | F12: 0.0082737361 | G12: N/A | H12: =IFERROR(F12*(1+0.5*G12)+G12,"N/A") -> N/A | I12: =IF(AND(ISNUMBER(D12),ISNUMBER(H12)),E12*H12,"N/A") -> N/A
B13: American Airlines Group Inc | C13: AAL | D13: 14113.816 | E13: =IF(OR(H13="N/A",D13="N/A"),"N/A",D13/$D$512) -> 0.00056869667 | F13: 0.012917595 | G13: 0.09535 | H13: =IFERROR(F13*(1+0.5*G13)+G13,"N/A") -> 0.10888344 | I13: =IF(AND(ISNUMBER(D13),ISNUMBER(H13)),E13*H13,"N/A") -> 6.192165e-05
B14: Advance Auto Parts Inc | C14: AAP | D14: 11097.404 | E14: =IF(OR(H14="N/A",D14="N/A"),"N/A",D14/$D$512) -> 0.00044715451 | F14: 0.0015499871 | G14: 0.15473 | H14: =IFERROR(F14*(1+0.5*G14)+G14,"N/A") -> 0.1563999 | I14: =IF(AND(ISNUMBER(D14),ISNUMBER(H14)),E14*H14,"N/A") -> 6.9934921e-05
B15: Apple Inc | C15: AAPL | D15: 877607.91 | E15: =IF(OR(H15="N/A",D15="N/A"),"N/A",D15/$D$512) -> 0.035361996 | F15: 0.015780142 | G15: 0.094 | H15: =IFERROR(F15*(1+0.5*G15)+G15,"N/A") -> 0.11052181 | I15: =IF(AND(ISNUMBER(D15),ISNUMBER(H15)),E15*H15,"N/A") -> 0.0039082717
B16: AbbVie Inc | C16: ABBV | D16: 119983.29 | E16: =IF(OR(H16="N/A",D16="N/A"),"N/A",D16/$D$512) -> 0.0048345607 | F16: 0.053122695 | G16: 0.08813 | H16: =IFERROR(F16*(1+0.5*G16)+G16,"N/A") -> 0.14359355 | I16: =IF(AND(ISNUMBER(D16),ISNUMBER(H16)),E16*H16,"N/A") -> 0.00069421171
B17: AmerisourceBergen Corp | C17: ABC | D17: 16925.188 | E17: =IF(OR(H17="N/A",D17="N/A"),"N/A",D17/$D$512) -> 0.000681977 | F17: 0.020042405 | G17: 0.08697 | H17: =IFERROR(F17*(1+0.5*G17)+G17,"N/A") -> 0.10788395 | I17: =IF(AND(ISNUMBER(D17),ISNUMBER(H17)),E17*H17,"N/A") -> 7.3574372e-05
B18: ABIOMED Inc | C18: ABMD | D18: 15023.943 | E18: =IF(OR(H18="N/A",D18="N/A"),"N/A",D18/$D$512) -> 0.00060536899 | F18: 0.00% | G18: 0.29 | H18: =IFERROR(F18*(1+0.5*G18)+G18,"N/A") -> 0.29 | I18: =IF(AND(ISNUMBER(D18),ISNUMBER(H18)),E18*H18,"N/A") -> 0.00017555701
B19: Abbott Laboratories | C19: ABT | D19: 140271.72 | E19: =IF(OR(H19="N/A",D19="N/A"),"N/A",D19/$D$512) -> 0.0056520546 | F19: 0.01525169 | G19: 0.11688 | H19: =IFERROR(F19*(1+0.5*G19)+G19,"N/A") -> 0.133023 | I19: =IF(AND(ISNUMBER(D19),ISNUMBER(H19)),E19*H19,"N/A") -> 0.00075185325
B20: Accenture PLC | C20: ACN | D20: 106224.74 | E20: =IF(OR(H20="N/A",D20="N/A"),"N/A",D20/$D$512) -> 0.0042801789 | F20: 0.017615241 | G20: 0.10267 | H20: =IFERROR(F20*(1+0.5*G20)+G20,"N/A") -> 0.12118952 | I20: =IF(AND(ISNUMBER(D20),ISNUMBER(H20)),E20*H20,"N/A") -> 0.00051871283
B21: Adobe Inc | C21: ADBE | D21: 125746.54 | E21: =IF(OR(H21="N/A",D21="N/A"),"N/A",D21/$D$512) -> 0.0050667827 | F21: 0 | G21: 0.1716 | H21: =IFERROR(F21*(1+0.5*G21)+G21,"N/A") -> 0.1716 | I21: =IF(AND(ISNUMBER(D21),ISNUMBER(H21)),E21*H21,"N/A") -> 0.00086945991
B22: Analog Devices Inc | C22: ADI | D22: 40289.903 | E22: =IF(OR(H22="N/A",D22="N/A"),"N/A",D22/$D$512) -> 0.0016234258 | F22: 0.018959686 | G22: 0.11975 | H22: =IFERROR(F22*(1+0.5*G22)+G22,"N/A") -> 0.1398449 | I22: =IF(AND(ISNUMBER(D22),ISNUMBER(H22)),E22*H22,"N/A") -> 0.00022702782
B23: Archer-Daniels-Midland Co | C23: ADM | D23: 24184.634 | E23: =IF(OR(H23="N/A",D23="N/A"),"N/A",D23/$D$512) -> 0.00097448635 | F23: 0.032862436 | G23: 0.014 | H23: =IFERROR(F23*(1+0.5*G23)+G23,"N/A") -> 0.047092473 | I23: =IF(AND(ISNUMBER(D23),ISNUMBER(H23)),E23*H23,"N/A") -> 4.5890972e-05
B24: Automatic Data Processing Inc | C24: ADP | D24: 67657.642 | E24: =IF(OR(H24="N/A",D24="N/A"),"N/A",D24/$D$512) -> 0.002726171 | F24: 0.018710965 | G24: 0.14 | H24: =IFERROR(F24*(1+0.5*G24)+G24,"N/A") -> 0.16002073 | I24: =IF(AND(ISNUMBER(D24),ISNUMBER(H24)),E24*H24,"N/A") -> 0.00043624388
B25: Alliance Data Systems Corp | C25: ADS | D25: 9137.3309 | E25: =IF(OR(H25="N/A",D25="N/A"),"N/A",D25/$D$512) -> 0.0003681761 | F25: 0.014361116 | G25: -0.01325 | H25: =IFERROR(F25*(1+0.5*G25)+G25,"N/A") -> 0.0010159736 | I25: =IF(AND(ISNUMBER(D25),ISNUMBER(H25)),E25*H25,"N/A") -> 3.7405718e-07
B26: Autodesk Inc | C26: ADSK | D26: 33569.674 | E26: =IF(OR(H26="N/A",D26="N/A"),"N/A",D26/$D$512) -> 0.0013526435 | F26: 0 | G26: 0.51812 | H26: =IFERROR(F26*(1+0.5*G26)+G26,"N/A") -> 0.51812 | I26: =IF(AND(ISNUMBER(D26),ISNUMBER(H26)),E26*H26,"N/A") -> 0.00070083167
B27: Ameren Corp | C27: AEE | D27: 17868.424 | E27: =IF(OR(H27="N/A",D27="N/A"),"N/A",D27/$D$512) -> 0.00071998339 | F27: 0.026738773 | G27: 0.06353 | H27: =IFERROR(F27*(1+0.5*G27)+G27,"N/A") -> 0.09111813 | I27: =IF(AND(ISNUMBER(D27),ISNUMBER(H27)),E27*H27,"N/A") -> 6.5603541e-05
B28: American Electric Power Co Inc | C28: AEP | D28: 41342.43 | E28: =IF(OR(H28="N/A",D28="N/A"),"N/A",D28/$D$512) -> 0.001665836 | F28: 0.032096409 | G28: 0.0612 | H28: =IFERROR(F28*(1+0.5*G28)+G28,"N/A") -> 0.094278559 | I28: =IF(AND(ISNUMBER(D28),ISNUMBER(H28)),E28*H28,"N/A") -> 0.00015705262
B29: AES Corp/VA | C29: AES | D29: 12128.619 | E29: =IF(OR(H29="N/A",D29="N/A"),"N/A",D29/$D$512) -> 0.00048870591 | F29: 0.03036592 | G29: 0.07668 | H29: =IFERROR(F29*(1+0.5*G29)+G29,"N/A") -> 0.10821015 | I29: =IF(AND(ISNUMBER(D29),ISNUMBER(H29)),E29*H29,"N/A") -> 5.288294e-05
B30: Aflac Inc | C30: AFL | D30: 37479.102 | E30: =IF(OR(H30="N/A",D30="N/A"),"N/A",D30/$D$512) -> 0.0015101685 | F30: 0.021901902 | G30: 0.0343 | H30: =IFERROR(F30*(1+0.5*G30)+G30,"N/A") -> 0.05657752 | I30: =IF(AND(ISNUMBER(D30),ISNUMBER(H30)),E30*H30,"N/A") -> 8.5441589e-05
... B33: Apartment Investment & Management Co | C33: AIV | D33: 7325.8169 | E33: =IF(OR(H33="N/A",D33="N/A"),"N/A",D33/$D$512) -> 0.00029518365 | F33: 0.040882237 | G33: 0.08767 | H33: =IFERROR(F33*(1+0.5*G33)+G33,"N/A") -> 0.13034431 | I33: =IF(AND(ISNUMBER(D33),ISNUMBER(H33)),E33*H33,"N/A") -> 3.8475509e-05
B34: Assurant Inc | C34: AIZ | D34: 6091.2515 | E34: =IF(OR(H34="N/A",D34="N/A"),"N/A",D34/$D$512) -> N/A | F34: 0.025270941 | G34: N/A | H34: =IFERROR(F34*(1+0.5*G34)+G34,"N/A") -> N/A | I34: =IF(AND(ISNUMBER(D34),ISNUMBER(H34)),E34*H34,"N/A") -> N/A
B35: Arthur J Gallagher & Co | C35: AJG | D35: 14776.337 | E35: =IF(OR(H35="N/A",D35="N/A"),"N/A",D35/$D$512) -> 0.00059539203 | F35: 0.02136273 | G35: 0.1017 | H35: =IFERROR(F35*(1+0.5*G35)+G35,"N/A") -> 0.12414903 | I35: =IF(AND(ISNUMBER(D35),ISNUMBER(H35)),E35*H35,"N/A") -> 7.391734e-05
B36: Akamai Technologies Inc | C36: AKAM | D36: 11828.01 | E36: =IF(OR(H36="N/A",D36="N/A"),"N/A",D36/$D$512) -> 0.00047659327 | F36: 0.00% | G36: 0.154 | H36: =IFERROR(F36*(1+0.5*G36)+G36,"N/A") -> 0.154 | I36: =IF(AND(ISNUMBER(D36),ISNUMBER(H36)),E36*H36,"N/A") -> 7.3395364e-05
B37: Albemarle Corp | C37: ALB | D37: 9033.4951 | E37: =IF(OR(H37="N/A",D37="N/A"),"N/A",D37/$D$512) -> 0.00036399218 | F37: 0.016050105 | G37: 0.12188 | H37: =IFERROR(F37*(1+0.5*G37)+G37,"N/A") -> 0.1389082 | I37: =IF(AND(ISNUMBER(D37),ISNUMBER(H37)),E37*H37,"N/A") -> 5.0561497e-05
B38: Align Technology Inc | C38: ALGN | D38: 20183.712 | E38: =IF(OR(H38="N/A",D38="N/A"),"N/A",D38/$D$512) -> 0.00081327472 | F38: 0.00% | G38: 0.23193 | H38: =IFERROR(F38*(1+0.5*G38)+G38,"N/A") -> 0.23193 | I38: =IF(AND(ISNUMBER(D38),ISNUMBER(H38)),E38*H38,"N/A") -> 0.00018862281
B39: Alaska Air Group Inc | C39: ALK | D39: 6889.4826 | E39: =IF(OR(H39="N/A",D39="N/A"),"N/A",D39/$D$512) -> 0.00027760216 | F39: 0.024497848 | G39: 0.2537 | H39: =IFERROR(F39*(1+0.5*G39)+G39,"N/A") -> 0.2813054 | I39: =IF(AND(ISNUMBER(D39),ISNUMBER(H39)),E39*H39,"N/A") -> 7.8090987e-05
B40: Allstate Corp/The | C40: ALL | D40: 31483.381 | E40: =IF(OR(H40="N/A",D40="N/A"),"N/A",D40/$D$512) -> 0.0012685792 | F40: 0.02039224 | G40: 0.09 | H40: =IFERROR(F40*(1+0.5*G40)+G40,"N/A") -> 0.11130989 | I40: =IF(AND(ISNUMBER(D40),ISNUMBER(H40)),E40*H40,"N/A") -> 0.00014120542
B41: Allegion PLC | C41: ALLE | D41: 8351.0614 | E41: =IF(OR(H41="N/A",D41="N/A"),"N/A",D41/$D$512) -> 0.00033649446 | F41: 0.012012216 | G41: 0.10217 | H41: =IFERROR(F41*(1+0.5*G41)+G41,"N/A") -> 0.11479586 | I41: =IF(AND(ISNUMBER(D41),ISNUMBER(H41)),E41*H41,"N/A") -> 3.862817e-05
B42: Alexion Pharmaceuticals Inc | C42: ALXN | D42: 30411.948 | E42: =IF(OR(H42="N/A",D42="N/A"),"N/A",D42/$D$512) -> 0.0012254073 | F42: 0 | G42: 0.1578 | H42: =IFERROR(F42*(1+0.5*G42)+G42,"N/A") -> 0.1578 | I42: =IF(AND(ISNUMBER(D42),ISNUMBER(H42)),E42*H42,"N/A") -> 0.00019336928
B43: Applied Materials Inc | C43: AMAT | D43: 38345.967 | E43: =IF(OR(H43="N/A",D43="N/A"),"N/A",D43/$D$512) -> 0.0015450977 | F43: 0.020970537 | G43: 0.0923 | H43: =IFERROR(F43*(1+0.5*G43)+G43,"N/A") -> 0.11423833 | I43: =IF(AND(ISNUMBER(D43),ISNUMBER(H43)),E43*H43,"N/A") -> 0.00017650937
B44: Advanced Micro Devices Inc | C44: AMD | D44: 23413.411 | E44: =IF(OR(H44="N/A",D44="N/A"),"N/A",D44/$D$512) -> 0.00094341098 | F44: 0 | G44: 0.15667 | H44: =IFERROR(F44*(1+0.5*G44)+G44,"N/A") -> 0.15667 | I44: =IF(AND(ISNUMBER(D44),ISNUMBER(H44)),E44*H44,"N/A") -> 0.0001478042
B45: AMETEK Inc | C45: AME | D45: 18385.789 | E45: =IF(OR(H45="N/A",D45="N/A"),"N/A",D45/$D$512) -> 0.00074082991 | F45: 0.0070907066 | G45: 0.08978 | H45: =IFERROR(F45*(1+0.5*G45)+G45,"N/A") -> 0.097189008 | I45: =IF(AND(ISNUMBER(D45),ISNUMBER(H45)),E45*H45,"N/A") -> 7.2000525e-05
B46: Affiliated Managers Group Inc | C46: AMG | D46: 5691.5259 | E46: =IF(OR(H46="N/A",D46="N/A"),"N/A",D46/$D$512) -> 0.00022933215 | F46: 0.012684042 | G46: 0.0498 | H46: =IFERROR(F46*(1+0.5*G46)+G46,"N/A") -> 0.062799875 | I46: =IF(AND(ISNUMBER(D46),ISNUMBER(H46)),E46*H46,"N/A") -> 1.4402031e-05
B47: Amgen Inc | C47: AMGN | D47: 119004.45 | E47: =IF(OR(H47="N/A",D47="N/A"),"N/A",D47/$D$512) -> 0.0047951196 | F47: 0.029763648 | G47: 0.0583 | H47: =IFERROR(F47*(1+0.5*G47)+G47,"N/A") -> 0.088931258 | I47: =IF(AND(ISNUMBER(D47),ISNUMBER(H47)),E47*H47,"N/A") -> 0.00042643602
B48: Ameriprise Financial Inc | C48: AMP | D48: 17473.721 | E48: =IF(OR(H48="N/A",D48="N/A"),"N/A",D48/$D$512) -> 0.0007040794 | F48: 0.029422704 | G48: 0.118 | H48: =IFERROR(F48*(1+0.5*G48)+G48,"N/A") -> 0.14915864 | I48: =IF(AND(ISNUMBER(D48),ISNUMBER(H48)),E48*H48,"N/A") -> 0.00010501953
B49: American Tower Corp | C49: AMT | D49: 83361.263 | E49: =IF(OR(H49="N/A",D49="N/A"),"N/A",D49/$D$512) -> 0.0033589267 | F49: 0.019521617 | G49: 0.18212 | H49: =IFERROR(F49*(1+0.5*G49)+G49,"N/A") -> 0.20341926 | I49: =IF(AND(ISNUMBER(D49),ISNUMBER(H49)),E49*H49,"N/A") -> 0.00068327036
B50: Amazon.com Inc | C50: AMZN | D50: 841116.18 | E50: =IF(OR(H50="N/A",D50="N/A"),"N/A",D50/$D$512) -> 0.033891612 | F50: 0 | G50: 0.37603 | H50: =IFERROR(F50*(1+0.5*G50)+G50,"N/A") -> 0.37603 | I50: =IF(AND(ISNUMBER(D50),ISNUMBER(H50)),E50*H50,"N/A") -> 0.012744263
... B78: Brown-Forman Corp | C78: BF/B | D78: 24125.498 | E78: =IF(OR(H78="N/A",D78="N/A"),"N/A",D78/$D$512) -> 0.00097210355 | F78: 0.012938856 | G78: 0.0991 | H78: =IFERROR(F78*(1+0.5*G78)+G78,"N/A") -> 0.11267998 | I78: =IF(AND(ISNUMBER(D78),ISNUMBER(H78)),E78*H78,"N/A") -> 0.00010953661
B79: Brighthouse Financial Inc | C79: BHF | D79: 4616.6505 | E79: =IF(OR(H79="N/A",D79="N/A"),"N/A",D79/$D$512) -> 0.00018602154 | F79: 0.00% | G79: 0.11135 | H79: =IFERROR(F79*(1+0.5*G79)+G79,"N/A") -> 0.11135 | I79: =IF(AND(ISNUMBER(D79),ISNUMBER(H79)),E79*H79,"N/A") -> 2.0713499e-05
B80: Baker Hughes a GE Co | C80: BHGE | D80: 28864.14 | E80: =IF(OR(H80="N/A",D80="N/A"),"N/A",D80/$D$512) -> 0.0011630406 | F80: 0.022836625 | G80: 0.40815 | H80: =IFERROR(F80*(1+0.5*G80)+G80,"N/A") -> 0.43564701 | I80: =IF(AND(ISNUMBER(D80),ISNUMBER(H80)),E80*H80,"N/A") -> 0.00050667514
B81: Biogen Inc | C81: BIIB | D81: 64888.327 | E81: =IF(OR(H81="N/A",D81="N/A"),"N/A",D81/$D$512) -> 0.0026145853 | F81: 0 | G81: 0.0508 | H81: =IFERROR(F81*(1+0.5*G81)+G81,"N/A") -> 0.0508 | I81: =IF(AND(ISNUMBER(D81),ISNUMBER(H81)),E81*H81,"N/A") -> 0.00013282093
B82: Bank of New York Mellon Corp/The | C82: BK | D82: 50721.192 | E82: =IF(OR(H82="N/A",D82="N/A"),"N/A",D82/$D$512) -> 0.0020437402 | F82: 0.022722139 | G82: 0.07333 | H82: =IFERROR(F82*(1+0.5*G82)+G82,"N/A") -> 0.096885246 | I82: =IF(AND(ISNUMBER(D82),ISNUMBER(H82)),E82*H82,"N/A") -> 0.00019800827
B83: Booking Holdings Inc | C83: BKNG | D83: 78869.946 | E83: =IF(OR(H83="N/A",D83="N/A"),"N/A",D83/$D$512) -> 0.0031779553 | F83: 0 | G83: 0.125 | H83: =IFERROR(F83*(1+0.5*G83)+G83,"N/A") -> 0.125 | I83: =IF(AND(ISNUMBER(D83),ISNUMBER(H83)),E83*H83,"N/A") -> 0.00039724441
B84: BlackRock Inc | C84: BLK | D84: 68933.834 | E84: =IF(OR(H84="N/A",D84="N/A"),"N/A",D84/$D$512) -> 0.0027775934 | F84: 0.030600853 | G84: 0.08527 | H84: =IFERROR(F84*(1+0.5*G84)+G84,"N/A") -> 0.11717552 | I84: =IF(AND(ISNUMBER(D84),ISNUMBER(H84)),E84*H84,"N/A") -> 0.00032546595
B85: Ball Corp | C85: BLL | D85: 19214.827 | E85: =IF(OR(H85="N/A",D85="N/A"),"N/A",D85/$D$512) -> 0.00077423485 | F85: 0.0069565217 | G85: 0.065 | H85: =IFERROR(F85*(1+0.5*G85)+G85,"N/A") -> 0.072182609 | I85: =IF(AND(ISNUMBER(D85),ISNUMBER(H85)),E85*H85,"N/A") -> 5.5886292e-05
B86: Bristol-Myers Squibb Co | C86: BMY | D86: 81568.487 | E86: =IF(OR(H86="N/A",D86="N/A"),"N/A",D86/$D$512) -> 0.0032866892 | F86: 0.032966373 | G86: 0.11023 | H86: =IFERROR(F86*(1+0.5*G86)+G86,"N/A") -> 0.14501331 | I86: =IF(AND(ISNUMBER(D86),ISNUMBER(H86)),E86*H86,"N/A") -> 0.0004766137
B87: Broadridge Financial Solutions Inc | C87: BR | D87: 11978.745 | E87: =IF(OR(H87="N/A",D87="N/A"),"N/A",D87/$D$512) -> 0.00048266693 | F87: 0.01839691 | G87: 0.1 | H87: =IFERROR(F87*(1+0.5*G87)+G87,"N/A") -> 0.11931676 | I87: =IF(AND(ISNUMBER(D87),ISNUMBER(H87)),E87*H87,"N/A") -> 5.7590251e-05
B88: Berkshire Hathaway Inc | C88: BRK/B | D88: 503471.13 | E88: =IF(OR(H88="N/A",D88="N/A"),"N/A",D88/$D$512) -> 0.020286672 | F88: 0.00% | G88: -0.016 | H88: =IFERROR(F88*(1+0.5*G88)+G88,"N/A") -> -0.016 | I88: =IF(AND(ISNUMBER(D88),ISNUMBER(H88)),E88*H88,"N/A") -> -0.00032458675
B89: Boston Scientific Corp | C89: BSX | D89: 55729.529 | E89: =IF(OR(H89="N/A",D89="N/A"),"N/A",D89/$D$512) -> 0.0022455442 | F89: 0 | G89: 0.3346 | H89: =IFERROR(F89*(1+0.5*G89)+G89,"N/A") -> 0.3346 | I89: =IF(AND(ISNUMBER(D89),ISNUMBER(H89)),E89*H89,"N/A") -> 0.00075135909
B90: BorgWarner Inc | C90: BWA | D90: 7849.7145 | E90: =IF(OR(H90="N/A",D90="N/A"),"N/A",D90/$D$512) -> 0.00031629338 | F90: 0.018011108 | G90: 0.05778 | H90: =IFERROR(F90*(1+0.5*G90)+G90,"N/A") -> 0.076311449 | I90: =IF(AND(ISNUMBER(D90),ISNUMBER(H90)),E90*H90,"N/A") -> 2.4136806e-05
B91: Boston Properties Inc | C91: BXP | D91: 20509.553 | E91: =IF(OR(H91="N/A",D91="N/A"),"N/A",D91/$D$512) -> 0.00082640405 | F91: 0.029312943 | G91: 0.06238 | H91: =IFERROR(F91*(1+0.5*G91)+G91,"N/A") -> 0.092607213 | I91: =IF(AND(ISNUMBER(D91),ISNUMBER(H91)),E91*H91,"N/A") -> 7.6530976e-05
B92: Citigroup Inc | C92: C | D92: 152576.63 | E92: =IF(OR(H92="N/A",D92="N/A"),"N/A",D92/$D$512) -> 0.0061478639 | F92: 0.030019942 | G92: 0.11233 | H92: =IFERROR(F92*(1+0.5*G92)+G92,"N/A") -> 0.14403601 | I92: =IF(AND(ISNUMBER(D92),ISNUMBER(H92)),E92*H92,"N/A") -> 0.0008855138
B93: Conagra Brands Inc | C93: CAG | D93: 11213.473 | E93: =IF(OR(H93="N/A",D93="N/A"),"N/A",D93/$D$512) -> 0.00045183139 | F93: 0.036422694 | G93: 0.08 | H93: =IFERROR(F93*(1+0.5*G93)+G93,"N/A") -> 0.1178796 | I93: =IF(AND(ISNUMBER(D93),ISNUMBER(H93)),E93*H93,"N/A") -> 5.3261704e-05
B94: Cardinal Health Inc | C94: CAH | D94: 14981.297 | E94: =IF(OR(H94="N/A",D94="N/A"),"N/A",D94/$D$512) -> 0.00060365062 | F94: 0.039188383 | G94: 0.04765 | H94: =IFERROR(F94*(1+0.5*G94)+G94,"N/A") -> 0.087772046 | I94: =IF(AND(ISNUMBER(D94),ISNUMBER(H94)),E94*H94,"N/A") -> 5.298365e-05
B95: Caterpillar Inc | C95: CAT | D95: 76357.255 | E95: =IF(OR(H95="N/A",D95="N/A"),"N/A",D95/$D$512) -> 0.0030767099 | F95: 0.026426472 | G95: 0.1335 | H95: =IFERROR(F95*(1+0.5*G95)+G95,"N/A") -> 0.16169044 | I95: =IF(AND(ISNUMBER(D95),ISNUMBER(H95)),E95*H95,"N/A") -> 0.00049747457
B96: Chubb Ltd | C96: CB | D96: 62500.241 | E96: =IF(OR(H96="N/A",D96="N/A"),"N/A",D96/$D$512) -> 0.0025183607 | F96: 0.022317565 | G96: 0.106 | H96: =IFERROR(F96*(1+0.5*G96)+G96,"N/A") -> 0.1295004 | I96: =IF(AND(ISNUMBER(D96),ISNUMBER(H96)),E96*H96,"N/A") -> 0.0003261287
B97: Cboe Global Markets Inc | C97: CBOE | D97: 10831.517 | E97: =IF(OR(H97="N/A",D97="N/A"),"N/A",D97/$D$512) -> 0.00043644099 | F97: 0.0134762 | G97: 0.1346 | H97: =IFERROR(F97*(1+0.5*G97)+G97,"N/A") -> 0.14898315 | I97: =IF(AND(ISNUMBER(D97),ISNUMBER(H97)),E97*H97,"N/A") -> 6.5022352e-05
B98: CBRE Group Inc | C98: CBRE | D98: 17006.671 | E98: =IF(OR(H98="N/A",D98="N/A"),"N/A",D98/$D$512) -> 0.00068526025 | F98: 0 | G98: 0.0855 | H98: =IFERROR(F98*(1+0.5*G98)+G98,"N/A") -> 0.0855 | I98: =IF(AND(ISNUMBER(D98),ISNUMBER(H98)),E98*H98,"N/A") -> 5.8589751e-05
B99: CBS Corp | C99: CBS | D99: 17796.486 | E99: =IF(OR(H99="N/A",D99="N/A"),"N/A",D99/$D$512) -> 0.00071708475 | F99: 0.016331237 | G99: 0.15053 | H99: =IFERROR(F99*(1+0.5*G99)+G99,"N/A") -> 0.16809041 | I99: =IF(AND(ISNUMBER(D99),ISNUMBER(H99)),E99*H99,"N/A") -> 0.00012053507
B100: Crown Castle International Corp | C100: CCI | D100: 51958.515 | E100: =IF(OR(H100="N/A",D100="N/A"),"N/A",D100/$D$512) -> 0.0020935964 | F100: 0.03662321 | G100: 0.162 | H100: =IFERROR(F100*(1+0.5*G100)+G100,"N/A") -> 0.20158969 | I100: =IF(AND(ISNUMBER(D100),ISNUMBER(H100)),E100*H100,"N/A") -> 0.00042204745
B101: Carnival Corp | C101: CCL | D101: 38926.681 | E101: =IF(OR(H101="N/A",D101="N/A"),"N/A",D101/$D$512) -> 0.0015684967 | F101: 0.03642466 | G101: 0.10933 | H101: =IFERROR(F101*(1+0.5*G101)+G101,"N/A") -> 0.14774581 | I101: =IF(AND(ISNUMBER(D101),ISNUMBER(H101)),E101*H101,"N/A") -> 0.00023173882
B102: Cadence Design Systems Inc | C102: CDNS | D102: 17149.547 | E102: =IF(OR(H102="N/A",D102="N/A"),"N/A",D102/$D$512) -> 0.00069101725 | F102: 0.00% | G102: 0.1035 | H102: =IFERROR(F102*(1+0.5*G102)+G102,"N/A") -> 0.1035 | I102: =IF(AND(ISNUMBER(D102),ISNUMBER(H102)),E102*H102,"N/A") -> 7.1520286e-05
B103: Celanese Corp | C103: CE | D103: 12941.57 | E103: =IF(OR(H103="N/A",D103="N/A"),"N/A",D103/$D$512) -> 0.00052146265 | F103: 0.023253976 | G103: 0.0705 | H103: =IFERROR(F103*(1+0.5*G103)+G103,"N/A") -> 0.094573679 | I103: =IF(AND(ISNUMBER(D103),ISNUMBER(H103)),E103*H103,"N/A") -> 4.9316641e-05
B104: Celgene Corp | C104: CELG | D104: 62113.458 | E104: =IF(OR(H104="N/A",D104="N/A"),"N/A",D104/$D$512) -> 0.0025027758 | F104: 0 | G104: 0.20698 | H104: =IFERROR(F104*(1+0.5*G104)+G104,"N/A") -> 0.20698 | I104: =IF(AND(ISNUMBER(D104),ISNUMBER(H104)),E104*H104,"N/A") -> 0.00051802453
B105: Cerner Corp | C105: CERN | D105: 18783.74 | E105: =IF(OR(H105="N/A",D105="N/A"),"N/A",D105/$D$512) -> 0.0007568648 | F105: 0 | G105: 0.132 | H105: =IFERROR(F105*(1+0.5*G105)+G105,"N/A") -> 0.132 | I105: =IF(AND(ISNUMBER(D105),ISNUMBER(H105)),E105*H105,"N/A") -> 9.9906154e-05
B106: CF Industries Holdings Inc | C106: CF | D106: 9595.4385 | E106: =IF(OR(H106="N/A",D106="N/A"),"N/A",D106/$D$512) -> 0.00038663491 | F106: 0.028013937 | G106: 0.1975 | H106: =IFERROR(F106*(1+0.5*G106)+G106,"N/A") -> 0.22828031 | I106: =IF(AND(ISNUMBER(D106),ISNUMBER(H106)),E106*H106,"N/A") -> 8.8261138e-05
B107: Citizens Financial Group Inc | C107: CFG | D107: 16514.19 | E107: =IF(OR(H107="N/A",D107="N/A"),"N/A",D107/$D$512) -> 0.0006654164 | F107: 0.037524394 | G107: 0.1669 | H107: =IFERROR(F107*(1+0.5*G107)+G107,"N/A") -> 0.2075558 | I107: =IF(AND(ISNUMBER(D107),ISNUMBER(H107)),E107*H107,"N/A") -> 0.00013811104
B108: Church & Dwight Co Inc | C108: CHD | D108: 16573.732 | E108: =IF(OR(H108="N/A",D108="N/A"),"N/A",D108/$D$512) -> 0.00066781558 | F108: 0.013694362 | G108: 0.07683 | H108: =IFERROR(F108*(1+0.5*G108)+G108,"N/A") -> 0.091050431 | I108: =IF(AND(ISNUMBER(D108),ISNUMBER(H108)),E108*H108,"N/A") -> 6.0804896e-05
B109: CH Robinson Worldwide Inc | C109: CHRW | D109: 12179.98 | E109: =IF(OR(H109="N/A",D109="N/A"),"N/A",D109/$D$512) -> 0.00049077544 | F109: 0.022752809 | G109: 0.09067 | H109: =IFERROR(F109*(1+0.5*G109)+G109,"N/A") -> 0.11445431 | I109: =IF(AND(ISNUMBER(D109),ISNUMBER(H109)),E109*H109,"N/A") -> 5.6171363e-05
B110: Charter Communications Inc | C110: CHTR | D110: 89394.139 | E110: =IF(OR(H110="N/A",D110="N/A"),"N/A",D110/$D$512) -> 0.0036020131 | F110: 0 | G110: 0.4116 | H110: =IFERROR(F110*(1+0.5*G110)+G110,"N/A") -> 0.4116 | I110: =IF(AND(ISNUMBER(D110),ISNUMBER(H110)),E110*H110,"N/A") -> 0.0014825886
B111: Cigna Corp | C111: CI | D111: 63260.815 | E111: =IF(OR(H111="N/A",D111="N/A"),"N/A",D111/$D$512) -> 0.0025490069 | F111: 0.0001802343 | G111: 0.11802 | H111: =IFERROR(F111*(1+0.5*G111)+G111,"N/A") -> 0.11821087 | I111: =IF(AND(ISNUMBER(D111),ISNUMBER(H111)),E111*H111,"N/A") -> 0.00030132033
B112: Cincinnati Financial Corp | C112: CINF | D112: 13967.01 | E112: =IF(OR(H112="N/A",D112="N/A"),"N/A",D112/$D$512) -> N/A | F112: 0.027189909 | G112: N/A | H112: =IFERROR(F112*(1+0.5*G112)+G112,"N/A") -> N/A | I112: =IF(AND(ISNUMBER(D112),ISNUMBER(H112)),E112*H112,"N/A") -> N/A
B113: Colgate-Palmolive Co | C113: CL | D113: 57904.66 | E113: =IF(OR(H113="N/A",D113="N/A"),"N/A",D113/$D$512) -> 0.0023331881 | F113: 0.025684524 | G113: 0.06072 | H113: =IFERROR(F113*(1+0.5*G113)+G113,"N/A") -> 0.087184306 | I113: =IF(AND(ISNUMBER(D113),ISNUMBER(H113)),E113*H113,"N/A") -> 0.00020341739
B114: Clorox Co/The | C114: CLX | D114: 20592.156 | E114: =IF(OR(H114="N/A",D114="N/A"),"N/A",D114/$D$512) -> 0.00082973243 | F114: 0.024204892 | G114: 0.04913 | H114: =IFERROR(F114*(1+0.5*G114)+G114,"N/A") -> 0.073929485 | I114: =IF(AND(ISNUMBER(D114),ISNUMBER(H114)),E114*H114,"N/A") -> 6.1341691e-05
B115: Comerica Inc | C115: CMA | D115: 12991.702 | E115: =IF(OR(H115="N/A",D115="N/A"),"N/A",D115/$D$512) -> 0.00052348266 | F115: 0.031955755 | G115: 0.132 | H115: =IFERROR(F115*(1+0.5*G115)+G115,"N/A") -> 0.16606484 | I115: =IF(AND(ISNUMBER(D115),ISNUMBER(H115)),E115*H115,"N/A") -> 8.6932061e-05
B116: Comcast Corp | C116: CMCSA | D116: 183165.7 | E116: =IF(OR(H116="N/A",D116="N/A"),"N/A",D116/$D$512) -> 0.0073804084 | F116: 0.020681987 | G116: 0.11028 | H116: =IFERROR(F116*(1+0.5*G116)+G116,"N/A") -> 0.13210239 | I116: =IF(AND(ISNUMBER(D116),ISNUMBER(H116)),E116*H116,"N/A") -> 0.0009749696
B117: CME Group Inc | C117: CME | D117: 60875.413 | E117: =IF(OR(H117="N/A",D117="N/A"),"N/A",D117/$D$512) -> 0.0024528905 | F117: 0.033061009 | G117: 0.12233 | H117: =IFERROR(F117*(1+0.5*G117)+G117,"N/A") -> 0.15741319 | I117: =IF(AND(ISNUMBER(D117),ISNUMBER(H117)),E117*H117,"N/A") -> 0.0003861173
B118: Chipotle Mexican Grill Inc | C118: CMG | D118: 17674.274 | E118: =IF(OR(H118="N/A",D118="N/A"),"N/A",D118/$D$512) -> 0.00071216038 | F118: 0 | G118: 0.20312 | H118: =IFERROR(F118*(1+0.5*G118)+G118,"N/A") -> 0.20312 | I118: =IF(AND(ISNUMBER(D118),ISNUMBER(H118)),E118*H118,"N/A") -> 0.00014465402
B119: Cummins Inc | C119: CMI | D119: 24766.712 | E119: =IF(OR(H119="N/A",D119="N/A"),"N/A",D119/$D$512) -> 0.00099794037 | F119: 0.029400928 | G119: 0.06663 | H119: =IFERROR(F119*(1+0.5*G119)+G119,"N/A") -> 0.097010419 | I119: =IF(AND(ISNUMBER(D119),ISNUMBER(H119)),E119*H119,"N/A") -> 9.6810614e-05
B120: CMS Energy Corp | C120: CMS | D120: 15737.208 | E120: =IF(OR(H120="N/A",D120="N/A"),"N/A",D120/$D$512) -> 0.000634109 | F120: 0.027552674 | G120: 0.06608 | H120: =IFERROR(F120*(1+0.5*G120)+G120,"N/A") -> 0.094543015 | I120: =IF(AND(ISNUMBER(D120),ISNUMBER(H120)),E120*H120,"N/A") -> 5.9950576e-05
B121: Centene Corp | C121: CNC | D121: 24439.372 | E121: =IF(OR(H121="N/A",D121="N/A"),"N/A",D121/$D$512) -> 0.00098475066 | F121: 0 | G121: 0.1368 | H121: =IFERROR(F121*(1+0.5*G121)+G121,"N/A") -> 0.1368 | I121: =IF(AND(ISNUMBER(D121),ISNUMBER(H121)),E121*H121,"N/A") -> 0.00013471389
B122: CenterPoint Energy Inc | C122: CNP | D122: 15449.375 | E122: =IF(OR(H122="N/A",D122="N/A"),"N/A",D122/$D$512) -> 0.00062251117 | F122: 0.038039598 | G122: 0.06438 | H122: =IFERROR(F122*(1+0.5*G122)+G122,"N/A") -> 0.10364409 | I122: =IF(AND(ISNUMBER(D122),ISNUMBER(H122)),E122*H122,"N/A") -> 6.4519605e-05
B123: Capital One Financial Corp | C123: COF | D123: 39456.377 | E123: =IF(OR(H123="N/A",D123="N/A"),"N/A",D123/$D$512) -> 0.0015898401 | F123: 0.019589707 | G123: 0.0477 | H123: =IFERROR(F123*(1+0.5*G123)+G123,"N/A") -> 0.067756922 | I123: =IF(AND(ISNUMBER(D123),ISNUMBER(H123)),E123*H123,"N/A") -> 0.00010772267
B124: Cabot Oil & Gas Corp | C124: COG | D124: 10977.913 | E124: =IF(OR(H124="N/A",D124="N/A"),"N/A",D124/$D$512) -> 0.0004423398 | F124: 0.010913999 | G124: 0.27913 | H124: =IFERROR(F124*(1+0.5*G124)+G124,"N/A") -> 0.29156721 | I124: =IF(AND(ISNUMBER(D124),ISNUMBER(H124)),E124*H124,"N/A") -> 0.00012897178
... B130: Capri Holdings Ltd | C130: CPRI | D130: 6922.042 | E130: =IF(OR(H130="N/A",D130="N/A"),"N/A",D130/$D$512) -> 0.0002789141 | F130: 0 | G130: 0.0673 | H130: =IFERROR(F130*(1+0.5*G130)+G130,"N/A") -> 0.0673 | I130: =IF(AND(ISNUMBER(D130),ISNUMBER(H130)),E130*H130,"N/A") -> 1.8770919e-05
B131: Copart Inc | C131: CPRT | D131: 13470.995 | E131: =IF(OR(H131="N/A",D131="N/A"),"N/A",D131/$D$512) -> 0.00054279508 | F131: 0.00% | G131: 0.2 | H131: =IFERROR(F131*(1+0.5*G131)+G131,"N/A") -> 0.2 | I131: =IF(AND(ISNUMBER(D131),ISNUMBER(H131)),E131*H131,"N/A") -> 0.00010855902
B132: salesforce.com Inc | C132: CRM | D132: 124524.21 | E132: =IF(OR(H132="N/A",D132="N/A"),"N/A",D132/$D$512) -> 0.0050175306 | F132: 0 | G132: 0.24129 | H132: =IFERROR(F132*(1+0.5*G132)+G132,"N/A") -> 0.24129 | I132: =IF(AND(ISNUMBER(D132),ISNUMBER(H132)),E132*H132,"N/A") -> 0.00121068
B133: Cisco Systems Inc | C133: CSCO | D133: 234187.87 | E133: =IF(OR(H133="N/A",D133="N/A"),"N/A",D133/$D$512) -> 0.0094362761 | F133: 0.025601504 | G133: 0.0684 | H133: =IFERROR(F133*(1+0.5*G133)+G133,"N/A") -> 0.094877075 | I133: =IF(AND(ISNUMBER(D133),ISNUMBER(H133)),E133*H133,"N/A") -> 0.00089528628
B134: CSX Corp | C134: CSX | D134: 59386.047 | E134: =IF(OR(H134="N/A",D134="N/A"),"N/A",D134/$D$512) -> 0.0023928785 | F134: 0.012512018 | G134: 0.1047 | H134: =IFERROR(F134*(1+0.5*G134)+G134,"N/A") -> 0.11786702 | I134: =IF(AND(ISNUMBER(D134),ISNUMBER(H134)),E134*H134,"N/A") -> 0.00028204147
B135: Cintas Corp | C135: CTAS | D135: 21488.998 | E135: =IF(OR(H135="N/A",D135="N/A"),"N/A",D135/$D$512) -> 0.0008658694 | F135: 0.0097689127 | G135: 0.12017 | H135: =IFERROR(F135*(1+0.5*G135)+G135,"N/A") -> 0.13052588 | I135: =IF(AND(ISNUMBER(D135),ISNUMBER(H135)),E135*H135,"N/A") -> 0.00011301836
B136: CenturyLink Inc | C136: CTL | D136: 13054.579 | E136: =IF(OR(H136="N/A",D136="N/A"),"N/A",D136/$D$512) -> 0.00052601619 | F136: 0.10016543 | G136: 0.02497 | H136: =IFERROR(F136*(1+0.5*G136)+G136,"N/A") -> 0.12638599 | I136: =IF(AND(ISNUMBER(D136),ISNUMBER(H136)),E136*H136,"N/A") -> 6.6481078e-05
B137: Cognizant Technology Solutions Corp | C137: CTSH | D137: 41481.911 | E137: =IF(OR(H137="N/A",D137="N/A"),"N/A",D137/$D$512) -> 0.0016714562 | F137: 0.0108554 | G137: 0.114 | H137: =IFERROR(F137*(1+0.5*G137)+G137,"N/A") -> 0.12547416 | I137: =IF(AND(ISNUMBER(D137),ISNUMBER(H137)),E137*H137,"N/A") -> 0.00020972455
B138: Citrix Systems Inc | C138: CTXS | D138: 13288.502 | E138: =IF(OR(H138="N/A",D138="N/A"),"N/A",D138/$D$512) -> 0.00053544179 | F138: 0 | G138: 0.1185 | H138: =IFERROR(F138*(1+0.5*G138)+G138,"N/A") -> 0.1185 | I138: =IF(AND(ISNUMBER(D138),ISNUMBER(H138)),E138*H138,"N/A") -> 6.3449852e-05
...

Sheet RBH-2 MRP Value Line
B2: Ex-Ante Market Risk Premium
B3: Market DCF Method Based - Value Line
D5: [1] | E5: [2] | F5: [3]
D6: S&P 500 Est. Required Market Return | E6: Current 30-Year Treasury (30-day average) | F6: Implied Market Risk Premium
D7: =I512 -> 0.16747389 | E7: ='RBH-4 CAPM'!C10 -> 0.030316667 | F7: =D7-E7 -> 0.13715722
D10: [4] | E10: [5] | F10: [6] | G10: [7] | H10: [8] | I10: [9]
B11: Company | C11: Ticker | D11: Market Capitalization | E11: Weight in Index | F11: Estimated Dividend Yield | G11: Long-Term Growth Est. | H11: DCF Result | I11: Weighted DCF Result
B12: Agilent Technologies Inc | C12: A | D12: 25036.14 | E12: =IF(OR(H12="N/A",D12="N/A"),"N/A",D12/$D$512) -> 0.0011363597 | F12: 0.0084 | G12: 0.095 | H12: =IFERROR(F12*(1+0.5*G12)+G12,"N/A") -> 0.103799 | I12: =IF(AND(ISNUMBER(D12),ISNUMBER(H12)),E12*H12,"N/A") -> 0.000117953
B13: American Airlines Group Inc | C13: AAL | D13: 14839.21 | E13: =IF(OR(H13="N/A",D13="N/A"),"N/A",D13/$D$512) -> 0.00067353354 | F13: 0.0124 | G13: 0.01 | H13: =IFERROR(F13*(1+0.5*G13)+G13,"N/A") -> 0.022462 | I13: =IF(AND(ISNUMBER(D13),ISNUMBER(H13)),E13*H13,"N/A") -> 1.512891e-05
B14: Advance Auto Parts Inc | C14: AAP | D14: 11235.15 | E14: =IF(OR(H14="N/A",D14="N/A"),"N/A",D14/$D$512) -> 0.00050994968 | F14: 0.0016 | G14: 0.13 | H14: =IFERROR(F14*(1+0.5*G14)+G14,"N/A") -> 0.131704 | I14: =IF(AND(ISNUMBER(D14),ISNUMBER(H14)),E14*H14,"N/A") -> 6.7162412e-05
B15: Apple Inc | C15: AAPL | D15: 815891 | E15: =IF(OR(H15="N/A",D15="N/A"),"N/A",D15/$D$512) -> 0.037032292 | F15: 0.0187 | G15: 0.175 | H15: =IFERROR(F15*(1+0.5*G15)+G15,"N/A") -> 0.19533625 | I15: =IF(AND(ISNUMBER(D15),ISNUMBER(H15)),E15*H15,"N/A") -> 0.007233749
B16: AbbVie Inc | C16: ABBV | D16: 117685.5 | E16: =IF(OR(H16="N/A",D16="N/A"),"N/A",D16/$D$512) -> 0.0053416005 | F16: 0.0547 | G16: 0.145 | H16: =IFERROR(F16*(1+0.5*G16)+G16,"N/A") -> 0.20366575 | I16: =IF(AND(ISNUMBER(D16),ISNUMBER(H16)),E16*H16,"N/A") -> 0.0010879011
B17: AmerisourceBergen Corp | C17: ABC | D17: 16107.54 | E17: =IF(OR(H17="N/A",D17="N/A"),"N/A",D17/$D$512) -> 0.00073110148 | F17: 0.021 | G17: 0.08 | H17: =IFERROR(F17*(1+0.5*G17)+G17,"N/A") -> 0.10184 | I17: =IF(AND(ISNUMBER(D17),ISNUMBER(H17)),E17*H17,"N/A") -> 7.4455375e-05
B18: ABIOMED Inc | C18: ABMD | D18: 14302.31 | E18: =IF(OR(H18="N/A",D18="N/A"),"N/A",D18/$D$512) -> 0.00064916431 | F18: 0 | G18: 0.245 | H18: =IFERROR(F18*(1+0.5*G18)+G18,"N/A") -> 0.245 | I18: =IF(AND(ISNUMBER(D18),ISNUMBER(H18)),E18*H18,"N/A") -> 0.00015904526
B19: Abbott Laboratories | C19: ABT | D19: 134886.4 | E19: =IF(OR(H19="N/A",D19="N/A"),"N/A",D19/$D$512) -> 0.0061223282 | F19: 0.0167 | G19: 0.1 | H19: =IFERROR(F19*(1+0.5*G19)+G19,"N/A") -> 0.117535 | I19: =IF(AND(ISNUMBER(D19),ISNUMBER(H19)),E19*H19,"N/A") -> 0.00071958785
B20: Accenture PLC | C20: ACN | D20: 103264.5 | E20: =IF(OR(H20="N/A",D20="N/A"),"N/A",D20/$D$512) -> 0.004687049 | F20: 0.0189 | G20: 0.095 | H20: =IFERROR(F20*(1+0.5*G20)+G20,"N/A") -> 0.11479775 | I20: =IF(AND(ISNUMBER(D20),ISNUMBER(H20)),E20*H20,"N/A") -> 0.00053806268
B21: Adobe Inc | C21: ADBE | D21: 124578.4 | E21: =IF(OR(H21="N/A",D21="N/A"),"N/A",D21/$D$512) -> 0.0056544608 | F21: 0 | G21: 0.22 | H21: =IFERROR(F21*(1+0.5*G21)+G21,"N/A") -> 0.22 | I21: =IF(AND(ISNUMBER(D21),ISNUMBER(H21)),E21*H21,"N/A") -> 0.0012439814
B22: Analog Devices Inc | C22: ADI | D22: 38923.42 | E22: =IF(OR(H22="N/A",D22="N/A"),"N/A",D22/$D$512) -> 0.0017666863 | F22: 0.0204 | G22: 0.105 | H22: =IFERROR(F22*(1+0.5*G22)+G22,"N/A") -> 0.126471 | I22: =IF(AND(ISNUMBER(D22),ISNUMBER(H22)),E22*H22,"N/A") -> 0.00022343458
B23: Archer-Daniels-Midland Co | C23: ADM | D23: 23615.2 | E23: =IF(OR(H23="N/A",D23="N/A"),"N/A",D23/$D$512) -> 0.001071865 | F23: 0.0332 | G23: 0.095 | H23: =IFERROR(F23*(1+0.5*G23)+G23,"N/A") -> 0.129777 | I23: =IF(AND(ISNUMBER(D23),ISNUMBER(H23)),E23*H23,"N/A") -> 0.00013910342
... B25: Alliance Data Systems Corp | C25: ADS | D25: 9043.95 | E25: =IF(OR(H25="N/A",D25="N/A"),"N/A",D25/$D$512) -> 0.0004104938 | F25: 0.0152 | G25: 0.135 | H25: =IFERROR(F25*(1+0.5*G25)+G25,"N/A") -> 0.151226 | I25: =IF(AND(ISNUMBER(D25),ISNUMBER(H25)),E25*H25,"N/A") -> 6.2077335e-05
B26: Autodesk Inc | C26: ADSK | D26: 33458 | E26: =IF(OR(H26="N/A",D26="N/A"),"N/A",D26/$D$512) -> N/A | F26: 0 | G26: N/A | H26: =IFERROR(F26*(1+0.5*G26)+G26,"N/A") -> N/A | I26: =IF(AND(ISNUMBER(D26),ISNUMBER(H26)),E26*H26,"N/A") -> N/A
B27: Ameren Corp | C27: AEE | D27: 17413.29 | E27: =IF(OR(H27="N/A",D27="N/A"),"N/A",D27/$D$512) -> 0.00079036787 | F27: 0.0275 | G27: 0.065 | H27: =IFERROR(F27*(1+0.5*G27)+G27,"N/A") -> 0.09339375 | I27: =IF(AND(ISNUMBER(D27),ISNUMBER(H27)),E27*H27,"N/A") -> 7.3815419e-05
B28: American Electric Power Co Inc | C28: AEP | D28: 40174.8 | E28: =IF(OR(H28="N/A",D28="N/A"),"N/A",D28/$D$512) -> 0.0018234849 | F28: 0.0339 | G28: 0.04 | H28: =IFERROR(F28*(1+0.5*G28)+G28,"N/A") -> 0.074578 | I28: =IF(AND(ISNUMBER(D28),ISNUMBER(H28)),E28*H28,"N/A") -> 0.00013599186
B29: AES Corp/VA | C29: AES | D29: 11702.79 | E29: =IF(OR(H29="N/A",D29="N/A"),"N/A",D29/$D$512) -> N/A | F29: 0.0311 | G29: N/A | H29: =IFERROR(F29*(1+0.5*G29)+G29,"N/A") -> N/A | I29: =IF(AND(ISNUMBER(D29),ISNUMBER(H29)),E29*H29,"N/A") -> N/A
B30: Aflac Inc | C30: AFL | D30: 36729.55 | E30: =IF(OR(H30="N/A",D30="N/A"),"N/A",D30/$D$512) -> 0.0016671092 | F30: 0.023 | G30: 0.085 | H30: =IFERROR(F30*(1+0.5*G30)+G30,"N/A") -> 0.1089775 | I30: =IF(AND(ISNUMBER(D30),ISNUMBER(H30)),E30*H30,"N/A") -> 0.00018167739
B31: Allergan PLC | C31: AGN | D31: 48219.6 | E31: =IF(OR(H31="N/A",D31="N/A"),"N/A",D31/$D$512) -> 0.0021886285 | F31: 0.0207 | G31: 0.045 | H31: =IFERROR(F31*(1+0.5*G31)+G31,"N/A") -> 0.06616575 | I31: =IF(AND(ISNUMBER(D31),ISNUMBER(H31)),E31*H31,"N/A") -> 0.00014481225
B32: American International Group Inc | C32: AIG | D32: 36987.13 | E32: =IF(OR(H32="N/A",D32="N/A"),"N/A",D32/$D$512) -> 0.0016788005 | F32: 0.0306 | G32: 0.52 | H32: =IFERROR(F32*(1+0.5*G32)+G32,"N/A") -> 0.558556 | I32: =IF(AND(ISNUMBER(D32),ISNUMBER(H32)),E32*H32,"N/A") -> 0.00093770407
B33: Apartment Investment & Management Co | C33: AIV | D33: 7526.18 | E33: =IF(OR(H33="N/A",D33="N/A"),"N/A",D33/$D$512) -> 0.00034160408 | F33: 0.0326 | G33: 0.055 | H33: =IFERROR(F33*(1+0.5*G33)+G33,"N/A") -> 0.0884965 | I33: =IF(AND(ISNUMBER(D33),ISNUMBER(H33)),E33*H33,"N/A") -> 3.0230765e-05
B34: Assurant Inc | C34: AIZ | D34: 6259.43 | E34: =IF(OR(H34="N/A",D34="N/A"),"N/A",D34/$D$512) -> 0.00028410785 | F34: 0.0239 | G34: 0.075 | H34: =IFERROR(F34*(1+0.5*G34)+G34,"N/A") -> 0.09979625 | I34: =IF(AND(ISNUMBER(D34),ISNUMBER(H34)),E34*H34,"N/A") -> 2.8352898e-05
B35: Arthur J Gallagher & Co | C35: AJG | D35: 14372.69 | E35: =IF(OR(H35="N/A",D35="N/A"),"N/A",D35/$D$512) -> 0.00065235877 | F35: 0.022 | G35: 0.17 | H35: =IFERROR(F35*(1+0.5*G35)+G35,"N/A") -> 0.19387 | I35: =IF(AND(ISNUMBER(D35),ISNUMBER(H35)),E35*H35,"N/A") -> 0.00012647279
B36: Akamai Technologies Inc | C36: AKAM | D36: 11972.36 | E36: =IF(OR(H36="N/A",D36="N/A"),"N/A",D36/$D$512) -> 0.00054341073 | F36: 0 | G36: 0.175 | H36: =IFERROR(F36*(1+0.5*G36)+G36,"N/A") -> 0.175 | I36: =IF(AND(ISNUMBER(D36),ISNUMBER(H36)),E36*H36,"N/A") -> 9.5096878e-05
B37: Albemarle Corp | C37: ALB | D37: 8983.42 | E37: =IF(OR(H37="N/A",D37="N/A"),"N/A",D37/$D$512) -> 0.00040774641 | F37: 0.0174 | G37: 0.085 | H37: =IFERROR(F37*(1+0.5*G37)+G37,"N/A") -> 0.1031395 | I37: =IF(AND(ISNUMBER(D37),ISNUMBER(H37)),E37*H37,"N/A") -> 4.2054761e-05
B38: Align Technology Inc | C38: ALGN | D38: 18773.59 | E38: =IF(OR(H38="N/A",D38="N/A"),"N/A",D38/$D$512) -> 0.00085211022 | F38: 0 | G38: 0.285 | H38: =IFERROR(F38*(1+0.5*G38)+G38,"N/A") -> 0.285 | I38: =IF(AND(ISNUMBER(D38),ISNUMBER(H38)),E38*H38,"N/A") -> 0.00024285141
B39: Alaska Air Group Inc | C39: ALK | D39: 6902.05 | E39: =IF(OR(H39="N/A",D39="N/A"),"N/A",D39/$D$512) -> 0.00031327558 | F39: 0.025 | G39: 0.035 | H39: =IFERROR(F39*(1+0.5*G39)+G39,"N/A") -> 0.0604375 | I39: =IF(AND(ISNUMBER(D39),ISNUMBER(H39)),E39*H39,"N/A") -> 1.8933593e-05
B40: Allstate Corp/The | C40: ALL | D40: 32167.8 | E40: =IF(OR(H40="N/A",D40="N/A"),"N/A",D40/$D$512) -> 0.001460057 | F40: 0.0215 | G40: 0.115 | H40: =IFERROR(F40*(1+0.5*G40)+G40,"N/A") -> 0.13773625 | I40: =IF(AND(ISNUMBER(D40),ISNUMBER(H40)),E40*H40,"N/A") -> 0.00020110277
B41: Allegion PLC | C41: ALLE | D41: 8325.22 | E41: =IF(OR(H41="N/A",D41="N/A"),"N/A",D41/$D$512) -> 0.00037787152 | F41: 0.0123 | G41: 0.105 | H41: =IFERROR(F41*(1+0.5*G41)+G41,"N/A") -> 0.11794575 | I41: =IF(AND(ISNUMBER(D41),ISNUMBER(H41)),E41*H41,"N/A") -> 4.456834e-05
... B43: Applied Materials Inc | C43: AMAT | D43: 35668.7 | E43: =IF(OR(H43="N/A",D43="N/A"),"N/A",D43/$D$512) -> 0.0016189585 | F43: 0.0213 | G43: 0.19 | H43: =IFERROR(F43*(1+0.5*G43)+G43,"N/A") -> 0.2133235 | I43: =IF(AND(ISNUMBER(D43),ISNUMBER(H43)),E43*H43,"N/A") -> 0.0003453619
B44: Advanced Micro Devices Inc | C44: AMD | D44: 22190.4 | E44: =IF(OR(H44="N/A",D44="N/A"),"N/A",D44/$D$512) -> N/A | F44: 0 | G44: N/A | H44: =IFERROR(F44*(1+0.5*G44)+G44,"N/A") -> N/A | I44: =IF(AND(ISNUMBER(D44),ISNUMBER(H44)),E44*H44,"N/A") -> N/A
B45: AMETEK Inc | C45: AME | D45: 18320.91 | E45: =IF(OR(H45="N/A",D45="N/A"),"N/A",D45/$D$512) -> 0.00083156363 | F45: 0.0071 | G45: 0.105 | H45: =IFERROR(F45*(1+0.5*G45)+G45,"N/A") -> 0.11247275 | I45: =IF(AND(ISNUMBER(D45),ISNUMBER(H45)),E45*H45,"N/A") -> 9.3528248e-05
B46: Affiliated Managers Group Inc | C46: AMG | D46: 6061.77 | E46: =IF(OR(H46="N/A",D46="N/A"),"N/A",D46/$D$512) -> 0.0002751363 | F46: 0.0154 | G46: 0.065 | H46: =IFERROR(F46*(1+0.5*G46)+G46,"N/A") -> 0.0809005 | I46: =IF(AND(ISNUMBER(D46),ISNUMBER(H46)),E46*H46,"N/A") -> 2.2258665e-05
B47: Amgen Inc | C47: AMGN | D47: 114247.2 | E47: =IF(OR(H47="N/A",D47="N/A"),"N/A",D47/$D$512) -> 0.0051855403 | F47: 0.0322 | G47: 0.07 | H47: =IFERROR(F47*(1+0.5*G47)+G47,"N/A") -> 0.103327 | I47: =IF(AND(ISNUMBER(D47),ISNUMBER(H47)),E47*H47,"N/A") -> 0.00053580632
B48: Ameriprise Financial Inc | C48: AMP | D48: 17464.92 | E48: =IF(OR(H48="N/A",D48="N/A"),"N/A",D48/$D$512) -> 0.00079271129 | F48: 0.0288 | G48: 0.16 | H48: =IFERROR(F48*(1+0.5*G48)+G48,"N/A") -> 0.191104 | I48: =IF(AND(ISNUMBER(D48),ISNUMBER(H48)),E48*H48,"N/A") -> 0.0001514903
B49: American Tower Corp | C49: AMT | D49: 80110.86 | E49: =IF(OR(H49="N/A",D49="N/A"),"N/A",D49/$D$512) -> 0.0036361337 | F49: 0.0196 | G49: 0.095 | H49: =IFERROR(F49*(1+0.5*G49)+G49,"N/A") -> 0.115531 | I49: =IF(AND(ISNUMBER(D49),ISNUMBER(H49)),E49*H49,"N/A") -> 0.00042008616
B50: Amazon.com Inc | C50: AMZN | D50: 795089.5 | E50: =IF(OR(H50="N/A",D50="N/A"),"N/A",D50/$D$512) -> 0.036088137 | F50: 0 | G50: 0.57 | H50: =IFERROR(F50*(1+0.5*G50)+G50,"N/A") -> 0.57 | I50: =IF(AND(ISNUMBER(D50),ISNUMBER(H50)),E50*H50,"N/A") -> 0.020570238
B51: Arista Networks Inc | C51: ANET | D51: 20825.81 | E51: =IF(OR(H51="N/A",D51="N/A"),"N/A",D51/$D$512) -> 0.00094525797 | F51: 0 | G51: 0.19 | H51: =IFERROR(F51*(1+0.5*G51)+G51,"N/A") -> 0.19 | I51: =IF(AND(ISNUMBER(D51),ISNUMBER(H51)),E51*H51,"N/A") -> 0.00017959901
B52: ANSYS Inc | C52: ANSS | D52: 15022.29 | E52: =IF(OR(H52="N/A",D52="N/A"),"N/A",D52/$D$512) -> 0.00068184332 | F52: 0 | G52: 0.13 | H52: =IFERROR(F52*(1+0.5*G52)+G52,"N/A") -> 0.13 | I52: =IF(AND(ISNUMBER(D52),ISNUMBER(H52)),E52*H52,"N/A") -> 8.8639631e-05
B53: Anthem Inc | C53: ANTM | D53: 75010.34 | E53: =IF(OR(H53="N/A",D53="N/A"),"N/A",D53/$D$512) -> 0.0034046273 | F53: 0.011 | G53: 0.18 | H53: =IFERROR(F53*(1+0.5*G53)+G53,"N/A") -> 0.19199 | I53: =IF(AND(ISNUMBER(D53),ISNUMBER(H53)),E53*H53,"N/A") -> 0.0006536544
B54: Aon PLC | C54: AON | D54: 39207.06 | E54: =IF(OR(H54="N/A",D54="N/A"),"N/A",D54/$D$512) -> 0.0017795604 | F54: 0.0098 | G54: 0.095 | H54: =IFERROR(F54*(1+0.5*G54)+G54,"N/A") -> 0.1052655 | I54: =IF(AND(ISNUMBER(D54),ISNUMBER(H54)),E54*H54,"N/A") -> 0.00018732631
B55: AO Smith Corp | C55: AOS | D55: 8529.03 | E55: =IF(OR(H55="N/A",D55="N/A"),"N/A",D55/$D$512) -> 0.00038712221 | F55: 0.0174 | G55: 0.125 | H55: =IFERROR(F55*(1+0.5*G55)+G55,"N/A") -> 0.1434875 | I55: =IF(AND(ISNUMBER(D55),ISNUMBER(H55)),E55*H55,"N/A") -> 5.5547198e-05
B56: Apache Corp | C56: APA | D56: 12694.77 | E56: =IF(OR(H56="N/A",D56="N/A"),"N/A",D56/$D$512) -> N/A | F56: 0.0301 | G56: N/A | H56: =IFERROR(F56*(1+0.5*G56)+G56,"N/A") -> N/A | I56: =IF(AND(ISNUMBER(D56),ISNUMBER(H56)),E56*H56,"N/A") -> N/A
B57: Anadarko Petroleum Corp | C57: APC | D57: 21356.23 | E57: =IF(OR(H57="N/A",D57="N/A"),"N/A",D57/$D$512) -> N/A | F57: 0.0278 | G57: N/A | H57: =IFERROR(F57*(1+0.5*G57)+G57,"N/A") -> N/A | I57: =IF(AND(ISNUMBER(D57),ISNUMBER(H57)),E57*H57,"N/A") -> N/A
B58: Air Products & Chemicals Inc | C58: APD | D58: 39456.71 | E58: =IF(OR(H58="N/A",D58="N/A"),"N/A",D58/$D$512) -> 0.0017908917 | F58: 0.0258 | G58: 0.095 | H58: =IFERROR(F58*(1+0.5*G58)+G58,"N/A") -> 0.1220255 | I58: =IF(AND(ISNUMBER(D58),ISNUMBER(H58)),E58*H58,"N/A") -> 0.00021853445
B59: Amphenol Corp | C59: APH | D59: 28135.39 | E59: =IF(OR(H59="N/A",D59="N/A"),"N/A",D59/$D$512) -> 0.0012770308 | F59: 0.0099 | G59: 0.1 | H59: =IFERROR(F59*(1+0.5*G59)+G59,"N/A") -> 0.110395 | I59: =IF(AND(ISNUMBER(D59),ISNUMBER(H59)),E59*H59,"N/A") -> 0.00014097782
B60: Aptiv PLC | C60: APTV | D60: 21355.66 | E60: =IF(OR(H60="N/A",D60="N/A"),"N/A",D60/$D$512) -> 0.00096930721 | F60: 0.0107 | G60: 0.11 | H60: =IFERROR(F60*(1+0.5*G60)+G60,"N/A") -> 0.1212885 | I60: =IF(AND(ISNUMBER(D60),ISNUMBER(H60)),E60*H60,"N/A") -> 0.00011756582
B61: Alexandria Real Estate Equities Inc | C61: ARE | D61: 13640.47 | E61: =IF(OR(H61="N/A",D61="N/A"),"N/A",D61/$D$512) -> N/A | F61: 0.0284 | G61: N/A | H61: =IFERROR(F61*(1+0.5*G61)+G61,"N/A") -> N/A | I61: =IF(AND(ISNUMBER(D61),ISNUMBER(H61)),E61*H61,"N/A") -> N/A
B62: Arconic Inc | C62: ARNC | D62: 8852.99 | E62: =IF(OR(H62="N/A",D62="N/A"),"N/A",D62/$D$512) -> N/A | F62: 0.0131 | G62: N/A | H62: =IFERROR(F62*(1+0.5*G62)+G62,"N/A") -> N/A | I62: =IF(AND(ISNUMBER(D62),ISNUMBER(H62)),E62*H62,"N/A") -> N/A
B63: Atmos Energy Corp | C63: ATO | D63: 11626.18 | E63: =IF(OR(H63="N/A",D63="N/A"),"N/A",D63/$D$512) -> 0.00052769805 | F63: 0.0218 | G63: 0.075 | H63: =IFERROR(F63*(1+0.5*G63)+G63,"N/A") -> 0.0976175 | I63: =IF(AND(ISNUMBER(D63),ISNUMBER(H63)),E63*H63,"N/A") -> 5.1512564e-05
B64: Activision Blizzard Inc | C64: ATVI | D64: 31603 | E64: =IF(OR(H64="N/A",D64="N/A"),"N/A",D64/$D$512) -> 0.0014344214 | F64: 0.0092 | G64: 0.145 | H64: =IFERROR(F64*(1+0.5*G64)+G64,"N/A") -> 0.154867 | I64: =IF(AND(ISNUMBER(D64),ISNUMBER(H64)),E64*H64,"N/A") -> 0.00022214454
B65: AvalonBay Communities Inc | C65: AVB | D65: 26997.38 | E65: =IF(OR(H65="N/A",D65="N/A"),"N/A",D65/$D$512) -> 0.001225378 | F65: 0.0312 | G65: 0.055 | H65: =IFERROR(F65*(1+0.5*G65)+G65,"N/A") -> 0.087058 | I65: =IF(AND(ISNUMBER(D65),ISNUMBER(H65)),E65*H65,"N/A") -> 0.00010667895
B66: Broadcom Inc | C66: AVGO | D66: 109655.6 | E66: =IF(OR(H66="N/A",D66="N/A"),"N/A",D66/$D$512) -> 0.0049771332 | F66: 0.0399 | G66: 0.475 | H66: =IFERROR(F66*(1+0.5*G66)+G66,"N/A") -> 0.52437625 | I66: =IF(AND(ISNUMBER(D66),ISNUMBER(H66)),E66*H66,"N/A") -> 0.0026098904
B67: Avery Dennison Corp | C67: AVY | D67: 9379.13 | E67: =IF(OR(H67="N/A",D67="N/A"),"N/A",D67/$D$512) -> 0.00042570721 | F67: 0.0204 | G67: 0.115 | H67: =IFERROR(F67*(1+0.5*G67)+G67,"N/A") -> 0.136573 | I67: =IF(AND(ISNUMBER(D67),ISNUMBER(H67)),E67*H67,"N/A") -> 5.814011e-05
B68: American Water Works Co Inc | C68: AWK | D68: 18357.58 | E68: =IF(OR(H68="N/A",D68="N/A"),"N/A",D68/$D$512) -> 0.00083322804 | F68: 0.0191 | G68: 0.1 | H68: =IFERROR(F68*(1+0.5*G68)+G68,"N/A") -> 0.120055 | I68: =IF(AND(ISNUMBER(D68),ISNUMBER(H68)),E68*H68,"N/A") -> 0.00010003319
B69: American Express Co | C69: AXP | D69: 92112.44 | E69: =IF(OR(H69="N/A",D69="N/A"),"N/A",D69/$D$512) -> 0.0041808707 | F69: 0.0153 | G69: 0.09 | H69: =IFERROR(F69*(1+0.5*G69)+G69,"N/A") -> 0.1059885 | I69: =IF(AND(ISNUMBER(D69),ISNUMBER(H69)),E69*H69,"N/A") -> 0.00044312421
B70: AutoZone Inc | C70: AZO | D70: 23716.91 | E70: =IF(OR(H70="N/A",D70="N/A"),"N/A",D70/$D$512) -> 0.0010764815 | F70: 0 | G70: 0.125 | H70: =IFERROR(F70*(1+0.5*G70)+G70,"N/A") -> 0.125 | I70: =IF(AND(ISNUMBER(D70),ISNUMBER(H70)),E70*H70,"N/A") -> 0.00013456018
B71: Boeing Co/The | C71: BA | D71: 239862.4 | E71: =IF(OR(H71="N/A",D71="N/A"),"N/A",D71/$D$512) -> 0.01088706 | F71: 0.0195 | G71: 0.175 | H71: =IFERROR(F71*(1+0.5*G71)+G71,"N/A") -> 0.19620625 | I71: =IF(AND(ISNUMBER(D71),ISNUMBER(H71)),E71*H71,"N/A") -> 0.0021361092
B72: Bank of America Corp | C72: BAC | D72: 281453.1 | E72: =IF(OR(H72="N/A",D72="N/A"),"N/A",D72/$D$512) -> 0.012774811 | F72: 0.021 | G72: 0.13 | H72: =IFERROR(F72*(1+0.5*G72)+G72,"N/A") -> 0.152365 | I72: =IF(AND(ISNUMBER(D72),ISNUMBER(H72)),E72*H72,"N/A") -> 0.0019464341
B73: Baxter International Inc | C73: BAX | D73: 39846.76 | E73: =IF(OR(H73="N/A",D73="N/A"),"N/A",D73/$D$512) -> 0.0018085956 | F73: 0.0102 | G73: 0.125 | H73: =IFERROR(F73*(1+0.5*G73)+G73,"N/A") -> 0.1358375 | I73: =IF(AND(ISNUMBER(D73),ISNUMBER(H73)),E73*H73,"N/A") -> 0.0002456751
B74: BB&T Corp | C74: BBT | D74: 37807.54 | E74: =IF(OR(H74="N/A",D74="N/A"),"N/A",D74/$D$512) -> 0.0017160379 | F74: 0.0327 | G74: 0.1 | H74: =IFERROR(F74*(1+0.5*G74)+G74,"N/A") -> 0.134335 | I74: =IF(AND(ISNUMBER(D74),ISNUMBER(H74)),E74*H74,"N/A") -> 0.00023052395
... B78: Brown-Forman Corp | C78: BF/B | D78: 23939.42 | E78: =IF(OR(H78="N/A",D78="N/A"),"N/A",D78/$D$512) -> 0.0010865809 | F78: 0.0133 | G78: 0.155 | H78: =IFERROR(F78*(1+0.5*G78)+G78,"N/A") -> 0.16933075 | I78: =IF(AND(ISNUMBER(D78),ISNUMBER(H78)),E78*H78,"N/A") -> 0.00018399156
B79: Brighthouse Financial Inc | C79: BHF | D79: N/A | E79: =IF(OR(H79="N/A",D79="N/A"),"N/A",D79/$D$512) -> N/A | F79: 0 | G79: N/A | H79: =IFERROR(F79*(1+0.5*G79)+G79,"N/A") -> N/A | I79: =IF(AND(ISNUMBER(D79),ISNUMBER(H79)),E79*H79,"N/A") -> N/A
B80: Baker Hughes a GE Co | C80: BHGE | D80: 10732.6 | E80: =IF(OR(H80="N/A",D80="N/A"),"N/A",D80/$D$512) -> N/A | F80: 0.0276 | G80: N/A | H80: =IFERROR(F80*(1+0.5*G80)+G80,"N/A") -> N/A | I80: =IF(AND(ISNUMBER(D80),ISNUMBER(H80)),E80*H80,"N/A") -> N/A
B81: Biogen Inc | C81: BIIB | D81: 63525.57 | E81: =IF(OR(H81="N/A",D81="N/A"),"N/A",D81/$D$512) -> 0.0028833477 | F81: 0 | G81: 0.065 | H81: =IFERROR(F81*(1+0.5*G81)+G81,"N/A") -> 0.065 | I81: =IF(AND(ISNUMBER(D81),ISNUMBER(H81)),E81*H81,"N/A") -> 0.0001874176
B82: Bank of New York Mellon Corp/The | C82: BK | D82: 50655.05 | E82: =IF(OR(H82="N/A",D82="N/A"),"N/A",D82/$D$512) -> 0.0022991706 | F82: 0.0219 | G82: 0.09 | H82: =IFERROR(F82*(1+0.5*G82)+G82,"N/A") -> 0.1128855 | I82: =IF(AND(ISNUMBER(D82),ISNUMBER(H82)),E82*H82,"N/A") -> 0.00025954302
B83: Booking Holdings Inc | C83: BKNG | D83: 80430.32 | E83: =IF(OR(H83="N/A",D83="N/A"),"N/A",D83/$D$512) -> 0.0036506336 | F83: 0 | G83: 0.14 | H83: =IFERROR(F83*(1+0.5*G83)+G83,"N/A") -> 0.14 | I83: =IF(AND(ISNUMBER(D83),ISNUMBER(H83)),E83*H83,"N/A") -> 0.0005110887
B84: BlackRock Inc | C84: BLK | D84: 67218.66 | E84: =IF(OR(H84="N/A",D84="N/A"),"N/A",D84/$D$512) -> 0.0030509725 | F84: 0.0312 | G84: 0.09 | H84: =IFERROR(F84*(1+0.5*G84)+G84,"N/A") -> 0.122604 | I84: =IF(AND(ISNUMBER(D84),ISNUMBER(H84)),E84*H84,"N/A") -> 0.00037406143
B85: Ball Corp | C85: BLL | D85: 18331.91 | E85: =IF(OR(H85="N/A",D85="N/A"),"N/A",D85/$D$512) -> 0.00083206291 | F85: 0.0073 | G85: 0.22 | H85: =IFERROR(F85*(1+0.5*G85)+G85,"N/A") -> 0.228103 | I85: =IF(AND(ISNUMBER(D85),ISNUMBER(H85)),E85*H85,"N/A") -> 0.00018979605
B86: Bristol-Myers Squibb Co | C86: BMY | D86: 84074.57 | E86: =IF(OR(H86="N/A",D86="N/A"),"N/A",D86/$D$512) -> 0.0038160416 | F86: 0.0318 | G86: 0.135 | H86: =IFERROR(F86*(1+0.5*G86)+G86,"N/A") -> 0.1689465 | I86: =IF(AND(ISNUMBER(D86),ISNUMBER(H86)),E86*H86,"N/A") -> 0.00064470687
B87: Broadridge Financial Solutions Inc | C87: BR | D87: 11410.33 | E87: =IF(OR(H87="N/A",D87="N/A"),"N/A",D87/$D$512) -> 0.00051790088 | F87: 0.0204 | G87: 0.11 | H87: =IFERROR(F87*(1+0.5*G87)+G87,"N/A") -> 0.131522 | I87: =IF(AND(ISNUMBER(D87),ISNUMBER(H87)),E87*H87,"N/A") -> 6.811536e-05
B88: Berkshire Hathaway Inc | C88: BRK/B | D88: 0 | E88: =IF(OR(H88="N/A",D88="N/A"),"N/A",D88/$D$512) -> N/A | F88: 0 | G88: N/A | H88: =IFERROR(F88*(1+0.5*G88)+G88,"N/A") -> N/A | I88: =IF(AND(ISNUMBER(D88),ISNUMBER(H88)),E88*H88,"N/A") -> N/A
B89: Boston Scientific Corp | C89: BSX | D89: 54780.88 | E89: =IF(OR(H89="N/A",D89="N/A"),"N/A",D89/$D$512) -> 0.0024864369 | F89: 0 | G89: 0.17 | H89: =IFERROR(F89*(1+0.5*G89)+G89,"N/A") -> 0.17 | I89: =IF(AND(ISNUMBER(D89),ISNUMBER(H89)),E89*H89,"N/A") -> 0.00042269428
B90: BorgWarner Inc | C90: BWA | D90: 8043.5 | E90: =IF(OR(H90="N/A",D90="N/A"),"N/A",D90/$D$512) -> 0.0003650846 | F90: 0.0176 | G90: 0.08 | H90: =IFERROR(F90*(1+0.5*G90)+G90,"N/A") -> 0.098304 | I90: =IF(AND(ISNUMBER(D90),ISNUMBER(H90)),E90*H90,"N/A") -> 3.5889276e-05
B91: Boston Properties Inc | C91: BXP | D91: 20441.89 | E91: =IF(OR(H91="N/A",D91="N/A"),"N/A",D91/$D$512) -> 0.00092783231 | F91: 0.0294 | G91: 0.035 | H91: =IFERROR(F91*(1+0.5*G91)+G91,"N/A") -> 0.0649145 | I91: =IF(AND(ISNUMBER(D91),ISNUMBER(H91)),E91*H91,"N/A") -> 6.0229771e-05
B92: Citigroup Inc | C92: C | D92: 151168.3 | E92: =IF(OR(H92="N/A",D92="N/A"),"N/A",D92/$D$512) -> 0.0068613437 | F92: 0.032 | G92: 0.085 | H92: =IFERROR(F92*(1+0.5*G92)+G92,"N/A") -> 0.11836 | I92: =IF(AND(ISNUMBER(D92),ISNUMBER(H92)),E92*H92,"N/A") -> 0.00081210864
B93: Conagra Brands Inc | C93: CAG | D93: 10863.81 | E93: =IF(OR(H93="N/A",D93="N/A"),"N/A",D93/$D$512) -> 0.00049309501 | F93: 0.038 | G93: 0.045 | H93: =IFERROR(F93*(1+0.5*G93)+G93,"N/A") -> 0.083855 | I93: =IF(AND(ISNUMBER(D93),ISNUMBER(H93)),E93*H93,"N/A") -> 4.1348482e-05
B94: Cardinal Health Inc | C94: CAH | D94: 14155 | E94: =IF(OR(H94="N/A",D94="N/A"),"N/A",D94/$D$512) -> 0.00064247809 | F94: 0.0411 | G94: 0.1 | H94: =IFERROR(F94*(1+0.5*G94)+G94,"N/A") -> 0.143155 | I94: =IF(AND(ISNUMBER(D94),ISNUMBER(H94)),E94*H94,"N/A") -> 9.197395e-05
B95: Caterpillar Inc | C95: CAT | D95: 78366.2 | E95: =IF(OR(H95="N/A",D95="N/A"),"N/A",D95/$D$512) -> 0.0035569457 | F95: 0.0259 | G95: 0.17 | H95: =IFERROR(F95*(1+0.5*G95)+G95,"N/A") -> 0.1981015 | I95: =IF(AND(ISNUMBER(D95),ISNUMBER(H95)),E95*H95,"N/A") -> 0.00070463628
B96: Chubb Ltd | C96: CB | D96: 61178.88 | E96: =IF(OR(H96="N/A",D96="N/A"),"N/A",D96/$D$512) -> 0.0027768343 | F96: 0.022 | G96: 0.085 | H96: =IFERROR(F96*(1+0.5*G96)+G96,"N/A") -> 0.107935 | I96: =IF(AND(ISNUMBER(D96),ISNUMBER(H96)),E96*H96,"N/A") -> 0.00029971761
B97: Cboe Global Markets Inc | C97: CBOE | D97: 10351.08 | E97: =IF(OR(H97="N/A",D97="N/A"),"N/A",D97/$D$512) -> 0.00046982282 | F97: 0.0134 | G97: 0.17 | H97: =IFERROR(F97*(1+0.5*G97)+G97,"N/A") -> 0.184539 | I97: =IF(AND(ISNUMBER(D97),ISNUMBER(H97)),E97*H97,"N/A") -> 8.6700634e-05
B98: CBRE Group Inc | C98: CBRE | D98: 16996.28 | E98: =IF(OR(H98="N/A",D98="N/A"),"N/A",D98/$D$512) -> 0.0007714403 | F98: 0 | G98: 0.105 | H98: =IFERROR(F98*(1+0.5*G98)+G98,"N/A") -> 0.105 | I98: =IF(AND(ISNUMBER(D98),ISNUMBER(H98)),E98*H98,"N/A") -> 8.1001231e-05
B99: CBS Corp | C99: CBS | D99: 18427.5 | E99: =IF(OR(H99="N/A",D99="N/A"),"N/A",D99/$D$512) -> 0.00083640162 | F99: 0.0147 | G99: 0.105 | H99: =IFERROR(F99*(1+0.5*G99)+G99,"N/A") -> 0.12047175 | I99: =IF(AND(ISNUMBER(D99),ISNUMBER(H99)),E99*H99,"N/A") -> 0.00010076277
B100: Crown Castle International Corp | C100: CCI | D100: 50107.1 | E100: =IF(OR(H100="N/A",D100="N/A"),"N/A",D100/$D$512) -> 0.0022742998 | F100: 0.0381 | G100: 0.105 | H100: =IFERROR(F100*(1+0.5*G100)+G100,"N/A") -> 0.14510025 | I100: =IF(AND(ISNUMBER(D100),ISNUMBER(H100)),E100*H100,"N/A") -> 0.00033000147
... B123: Capital One Financial Corp | C123: COF | D123: 38498.84 | E123: =IF(OR(H123="N/A",D123="N/A"),"N/A",D123/$D$512) -> 0.0017474151 | F123: 0.0197 | G123: 0.1 | H123: =IFERROR(F123*(1+0.5*G123)+G123,"N/A") -> 0.120685 | I123: =IF(AND(ISNUMBER(D123),ISNUMBER(H123)),E123*H123,"N/A") -> 0.00021088679
B124: Cabot Oil & Gas Corp | C124: COG | D124: 10902.31 | E124: =IF(OR(H124="N/A",D124="N/A"),"N/A",D124/$D$512) -> N/A | F124: 0.0112 | G124: N/A | H124: =IFERROR(F124*(1+0.5*G124)+G124,"N/A") -> N/A | I124: =IF(AND(ISNUMBER(D124),ISNUMBER(H124)),E124*H124,"N/A") -> N/A
B125: Cooper Cos Inc/The | C125: COO | D125: 14217.63 | E125: =IF(OR(H125="N/A",D125="N/A"),"N/A",D125/$D$512) -> 0.00064532079 | F125: 0.0002 | G125: 0.145 | H125: =IFERROR(F125*(1+0.5*G125)+G125,"N/A") -> 0.1452145 | I125: =IF(AND(ISNUMBER(D125),ISNUMBER(H125)),E125*H125,"N/A") -> 9.3709935e-05
B126: ConocoPhillips | C126: COP | D126: 78226.89 | E126: =IF(OR(H126="N/A",D126="N/A"),"N/A",D126/$D$512) -> N/A | F126: 0.018 | G126: N/A | H126: =IFERROR(F126*(1+0.5*G126)+G126,"N/A") -> N/A | I126: =IF(AND(ISNUMBER(D126),ISNUMBER(H126)),E126*H126,"N/A") -> N/A
B127: Costco Wholesale Corp | C127: COST | D127: 95505.97 | E127: =IF(OR(H127="N/A",D127="N/A"),"N/A",D127/$D$512) -> 0.0043348988 | F127: 0.0112 | G127: 0.085 | H127: =IFERROR(F127*(1+0.5*G127)+G127,"N/A") -> 0.096676 | I127: =IF(AND(ISNUMBER(D127),ISNUMBER(H127)),E127*H127,"N/A") -> 0.00041908068
B128: Coty Inc | C128: COTY | D128: 8158.03 | E128: =IF(OR(H128="N/A",D128="N/A"),"N/A",D128/$D$512) -> 0.00037028297 | F128: 0.046 | G128: 0.09 | H128: =IFERROR(F128*(1+0.5*G128)+G128,"N/A") -> 0.13807 | I128: =IF(AND(ISNUMBER(D128),ISNUMBER(H128)),E128*H128,"N/A") -> 5.112497e-05
B129: Campbell Soup Co | C129: CPB | D129: 10811.92 | E129: =IF(OR(H129="N/A",D129="N/A"),"N/A",D129/$D$512) -> N/A | F129: 0.039 | G129: N/A | H129: =IFERROR(F129*(1+0.5*G129)+G129,"N/A") -> N/A | I129: =IF(AND(ISNUMBER(D129),ISNUMBER(H129)),E129*H129,"N/A") -> N/A
B130: Capri Holdings Ltd | C130: CPRI | D130: 6629.59 | E130: =IF(OR(H130="N/A",D130="N/A"),"N/A",D130/$D$512) -> 0.00030090896 | F130: 0 | G130: 0.075 | H130: =IFERROR(F130*(1+0.5*G130)+G130,"N/A") -> 0.075 | I130: =IF(AND(ISNUMBER(D130),ISNUMBER(H130)),E130*H130,"N/A") -> 2.2568172e-05
B131: Copart Inc | C131: CPRT | D131: 13209.87 | E131: =IF(OR(H131="N/A",D131="N/A"),"N/A",D131/$D$512) -> 0.00059957979 | F131: 0 | G131: 0.13 | H131: =IFERROR(F131*(1+0.5*G131)+G131,"N/A") -> 0.13 | I131: =IF(AND(ISNUMBER(D131),ISNUMBER(H131)),E131*H131,"N/A") -> 7.7945373e-05
...

Sheet RBH-3 Beta
B2: Bloomberg and Value Line Beta Coefficients
E4: [1] | F4: [2]
B5: Company | C5: Ticker | E5: Bloomberg | F5: Value Line
B7: ='RBH-1 Constant Growth DCF'!B8 -> ALLETE, Inc. | C7: ='RBH-1 Constant Growth DCF'!C8 -> ALE | E7: 0.4482832 | F7: 0.65
B8: ='RBH-1 Constant Growth DCF'!B9 -> Alliant Energy Corporation | C8: ='RBH-1 Constant Growth DCF'!C9 -> LNT | E8: 0.52806807 | F8: 0.65
B9: ='RBH-1 Constant Growth DCF'!B10 -> Ameren Corporation | C9: ='RBH-1 Constant Growth DCF'!C10 -> AEE | E9: 0.43553996 | F9: 0.6
B10: ='RBH-1 Constant Growth DCF'!B11 -> Avangrid, Inc. | C10: ='RBH-1 Constant Growth DCF'!C11 -> AGR | E10: 0.46795049 | F10: 0.4
B11: ='RBH-1 Constant Growth DCF'!B12 -> Black Hills Corporation | C11: ='RBH-1 Constant Growth DCF'!C12 -> BKH | E11: 0.53396392 | F11: 0.75
B12: ='RBH-1 Constant Growth DCF'!B13 -> CMS Energy Corporation | C12: ='RBH-1 Constant Growth DCF'!C13 -> CMS | E12: 0.46631581 | F12: 0.55
B13: ='RBH-1 Constant Growth DCF'!B14 -> Consolidated Edison, Inc. | C13: ='RBH-1 Constant Growth DCF'!C14 -> ED | E13: 0.46974313 | F13: 0.45
B14: ='RBH-1 Constant Growth DCF'!B15 -> DTE Energy Company | C14: ='RBH-1 Constant Growth DCF'!C15 -> DTE | E14: 0.50299174 | F14: 0.55
B15: ='RBH-1 Constant Growth DCF'!B16 -> Duke Energy Corporation | C15: ='RBH-1 Constant Growth DCF'!C16 -> DUK | E15: 0.43103719 | F15: 0.5
B16: ='RBH-1 Constant Growth DCF'!B17 -> El Paso Electric Company | C16: ='RBH-1 Constant Growth DCF'!C17 -> EE | E16: 0.50251919 | F16: 0.65
B17: ='RBH-1 Constant Growth DCF'!B18 -> Evergy, Inc | C17: ='RBH-1 Constant Growth DCF'!C18 -> EVRG | E17: 0.41390449 | F17: 0.52285924
B18: ='RBH-1 Constant Growth DCF'!B19 -> Eversource Energy | C18: ='RBH-1 Constant Growth DCF'!C19 -> ES | E18: 0.56493223 | F18: 0.6
... B29: ='RBH-1 Constant Growth DCF'!B30 -> Xcel Energy Inc. | C29: ='RBH-1 Constant Growth DCF'!C30 -> XEL | E29: 0.47912061 | F29: 0.5
B31: Mean | E31: =AVERAGE(E7:E29) -> 0.48488443 | F31: =AVERAGE(F7:F29) -> 0.5879504
B33: Notes:
B34: [1] Source: Bloomberg Professional
B35: [2] Source: Value Line

Sheet RBH-4 CAPM
B2: Capital Asset Pricing Model and Empirical Capital Asset Pricing Model Results
B3: Bloomberg, and Value Line Derived Market Risk Premium
C5: 1 | D5: =C5+1 -> 2 | E5: =D5+1 -> 3 | F5: =E5+1 -> 4 | G5: =F5+1 -> 5 | H5: =G5+1 -> 6 | I5: [7] | J5: [8]
G6: CAPM | I6: ECAPM
C7: Risk-Free Rate | D7: Average Beta Coefficient | E7: Bloomberg Market DCF Derived | F7: Value Line Market DCF Derived | G7: Bloomberg MRP | H7: Value Line MRP | I7: Bloomberg MRP | J7: Value Line MRP
B9: PROXY GROUP AVERAGE BLOOMBERG BETA COEFFICIENT
B10: Current 30-Year Treasury (30-day average) [9] | C10: 0.030316667 | D10: ='RBH-3 Beta'!E31 -> 0.48488443 | E10: ='RBH-2 MRP Bloomberg'!F7 -> 0.10607335 | F10: ='RBH-2 MRP Value Line'!F7 -> 0.13715722 | G10: =$C10+$D10*E10 -> 0.081749983 | H10: =$C10+$D10*F10 -> 0.096822067 | I10: =$C10+($D10*E10*0.75)+(0.25*E10) -> 0.095409992 | J10: =$C10+($D10*F10*0.75)+(0.25*F10) -> 0.11448502
B11: Near-Term Projected 30-Year Treasury [10] | C11: =AVERAGE(3.1,3.1,3.2,3.3,3.4,3.4)/100 -> 0.0325 | D11: =D10 -> 0.48488443 | E11: =E10 -> 0.10607335 | F11: =F10 -> 0.13715722 | G11: =$C11+$D11*E11 -> 0.083933317 | H11: =$C11+$D11*F11 -> 0.0990054 | I11: =$C11+($D11*E11*0.75)+(0.25*E11) -> 0.097593325 | J11: =$C11+($D11*F11*0.75)+(0.25*F11) -> 0.11666836
B12: Mean | G12: =AVERAGE(G10:G11) -> 0.08284165 | H12: =AVERAGE(H10:H11) -> 0.097913733 | I12: =AVERAGE(I10:I11) -> 0.096501659 | J12: =AVERAGE(J10:J11) -> 0.11557669
G14: CAPM | I14: ECAPM
C15: Risk-Free Rate | D15: Average Beta Coefficient | E15: Bloomberg Market DCF Derived | F15: Value Line Market DCF Derived | G15: Bloomberg MRP | H15: Value Line MRP | I15: Bloomberg MRP | J15: Value Line MRP
B17: PROXY GROUP AVERAGE VALUE LINE AVERAGE BETA COEFFICIENT
B18: Current 30-Year Treasury (30-day average) [9] | C18: =C10 -> 0.030316667 | D18: ='RBH-3 Beta'!F31 -> 0.5879504 | E18: =E10 -> 0.10607335 | F18: =F10 -> 0.13715722 | G18: =$C18+$D18*E18 -> 0.092682537 | H18: =$C18+$D18*F18 -> 0.11095831 | I18: =$C18+($D18*E18*0.75)+(0.25*E18) -> 0.10360941 | J18: =$C18+($D18*F18*0.75)+(0.25*F18) -> 0.1250872
B19: Near-Term Projected 30-Year Treasury [10] | C19: =C11 -> 0.0325 | D19: =D18 -> 0.5879504 | E19: =E10 -> 0.10607335 | F19: =F10 -> 0.13715722 | G19: =$C19+$D19*E19 -> 0.09486587 | H19: =$C19+$D19*F19 -> 0.11314164 | I19: =$C19+($D19*E19*0.75)+(0.25*E19) -> 0.10579274 | J19: =$C19+($D19*F19*0.75)+(0.25*F19) -> 0.12727054
B20: Mean | G20: =AVERAGE(G18:G19) -> 0.093774203 | H20: =AVERAGE(H18:H19) -> 0.11204998 | I20: =AVERAGE(I18:I19) -> 0.10470107 | J20: =AVERAGE(J18:J19) -> 0.12617887
B22: Notes:
B23: [1] See Notes [9] and [10]
B24: [2] Source: Exhibit RBH-3
B25: [3] Source: Exhibit RBH-2
B26: [4] Source: Exhibit RBH-2
B27: [5] Equals Col. [1] + (Col. [2] x Col. [3])
B28: [6] Equals Col. [1] + (Col. [2] x Col. [4])
B29: [7] Equals Col. [1] + (Col. [2] x Col. [3] x 0.75) + (Col. [3] x 0.25)
B30: [8] Equals Col. [1] + (Col. [2] x Col. [4] x 0.75) + (Col. [4] x 0.25)
B31: [9] Source: Bloomberg Professional
B32: [10] Source: Blue Chip Financial Forecasts, Vol. 38, No. 3, March 1, 2019, at 2.

Sheet RBH-5 Risk Premium
C2: Bond Yield Plus Risk Premium
C4: [1] | D4: [2] | E4: [3] | F4: [4] | G4: [5]
C5: Constant | D5: Slope | E5: 30-Year Treasury Yield | F5: Risk Premium | G5: Return on Equity
C6: =INTERCEPT(G46:G1629,LN(F46:F1629)) -> -0.024847305 | D6: =SLOPE(G46:G1629,LN(F46:F1629)) -> -0.026837421
D7: Current 30-Year Treasury | E7: ='RBH-4 CAPM'!C10 -> 0.030316667 | F7: =($C$6+LN(E7)*$D$6) -> 0.068977867 | G7: =E7+F7 -> 0.099294534
D8: Near-Term Projected 30-Year Treasury | E8: ='RBH-4 CAPM'!C11 -> 0.0325 | F8: =($C$6+LN(E8)*$D$6) -> 0.067111527 | G8: =E8+F8 -> 0.099611527
D9: Long-Term Projected 30-Year Treasury | E9: =AVERAGE(3.9,4.2)/100 -> 0.0405 | F9: =($C$6+LN(E9)*$D$6) -> 0.061205633 | G9: =E9+F9 -> 0.10170563
B30: Notes:
B31: [1] Constant of regression equation
B32: [2] Slope of regression equation
B33: [3] Source: Current = Bloomberg Professional,
B34: [3] Near Term Projected = Blue Chip Financial Forecasts, Vol. 38, No. 3, March 1, 2019, at 2.
B35: [3] Long Term Projected = Blue Chip Financial Forecasts, Vol. 37, No. 12, December 1, 2018, at 14.
B36: [4] Equals [1] + ln([3]) x [2]
B37: [5] Equals [3] + [4]
B38: [6] Source: S&P Global Market Intelligence
B39: [7] Source: S&P Global Market Intelligence
B40: [8] Source: Bloomberg Professional, equals 200-trading day average (i.e. lag period)
B41: [9] Equals [7] - [8]
D43: =C2 -> Bond Yield Plus Risk Premium
D44: [6] | E44: [7] | F44: [8] | G44: [9]
D45: Date of Electric Rate Case | E45: Return on Equity | F45: 30-Year Treasury Yield | G45: Risk Premium | I45: < 9%?
D46: 29221 | E46: 0.145 | F46: 0.093579 | G46: =E46-F46 -> 0.051421 | I46: =--(Risk_Prem2[[#This Row],[Return on Equity]]<0.09) -> 0
D47: 29227 | E47: 0.1439 | F47: 0.0938335 | G47: =E47-F47 -> 0.0500665 | I47: =--(Risk_Prem2[[#This Row],[Return on Equity]]<0.09) -> 0
D48: 29229 | E48: 0.15 | F48: 0.0939585 | G48: =E48-F48 -> 0.0560415 | I48: =--(Risk_Prem2[[#This Row],[Return on Equity]]<0.09) -> 0
D49: 29234 | E49: 0.1517 | F49: 0.0941565 | G49: =E49-F49 -> 0.0575435 | I49: =--(Risk_Prem2[[#This Row],[Return on Equity]]<0.09) -> 0
D50: 29237 | E50: 0.1393 | F50: 0.094369 | G50: =E50-F50 -> 0.044931 | I50: =--(Risk_Prem2[[#This Row],[Return on Equity]]<0.09) -> 0
D51: 29243 | E51: 0.155 | F51: 0.0947045 | G51: =E51-F51 -> 0.0602955 | I51: =--(Risk_Prem2[[#This Row],[Return on Equity]]<0.09) -> 0
D52: 29250 | E52: 0.1386 | F52: 0.0952055 | G52: =E52-F52 -> 0.0433945 | I52: =--(Risk_Prem2[[#This Row],[Return on Equity]]<0.09) -> 0
D53: 29251 | E53: 0.1261 | F53: 0.095306 | G53: =E53-F53 -> 0.030794 | I53: =--(Risk_Prem2[[#This Row],[Return on Equity]]<0.09) -> 0
D54: 29257 | E54: 0.1371 | F54: 0.095789 | G54: =E54-F54 -> 0.041311 | I54: =--(Risk_Prem2[[#This Row],[Return on Equity]]<0.09) -> 0
D55: 29264 | E55: 0.128 | F55: 0.096326 | G55: =E55-F55 -> 0.031674 | I55: =--(Risk_Prem2[[#This Row],[Return on Equity]]<0.09) -> 0
D56: 29265 | E56: 0.13 | F56: 0.0964645 | G56: =E56-F56 -> 0.0335355 | I56: =--(Risk_Prem2[[#This Row],[Return on Equity]]<0.09) -> 0
D57: 29270 | E57: 0.135 | F57: 0.096782 | G57: =E57-F57 -> 0.038218 | I57: =--(Risk_Prem2[[#This Row],[Return on Equity]]<0.09) -> 0
... D1629: 43538 | E1629: 0.094 | F1629: 0.031196105 | G1629: =E1629-F1629 -> 0.062803895 | I1629: =--(Risk_Prem2[[#This Row],[Return on Equity]]<0.09) -> 0
F1632: # of Cases: | G1632: =COUNT(Risk_Prem2[Return on Equity]) -> 1584 | I1632: =SUM(I46:I1629) -> 10
F1633: Average: | G1633: =AVERAGE(Risk_Prem2[Risk Premium]) -> 0.046655706

Sheet RBH-6 Expected Earnings
A1: Expected Earnings Analysis
C3: [1] | D3: [2] | E3: [3] | F3: [4] | G3: [5] | H3: [6]
C4: Expected
C5: ROE | D5: Shares Outstanding | G5: Adjustment | H5: Adjusted
A6: Company | B6: Ticker | C6: 2021-23/ 2022-24 | D6: 2019 | E6: 2021-23/ 2022-24 | F6: % Increase | G6: Factor | H6: ROE
A8: ALLETE, Inc. | B8: ALE | C8: 0.09 | D8: 51.5 | E8: 51.5 | F8: =(E8/D8)^(1/5)-1 -> 0 | G8: =2*(1+F8)/(2+F8) -> 1 | H8: =C8*G8 -> 0.09
A9: Alliant Energy Corporation | B9: LNT | C9: 0.1 | D9: 240 | E9: 250 | F9: =(E9/D9)^(1/5)-1 -> 0.0081978185 | G9: =2*(1+F9)/(2+F9) -> 1.0040822 | H9: =C9*G9 -> 0.10040822
A10: Ameren Corporation | B10: AEE | C10: 0.105 | D10: 246.5 | E10: 253 | F10: =(E10/D10)^(1/5)-1 -> 0.0052190712 | G10: =2*(1+F10)/(2+F10) -> 1.0026027 | H10: =C10*G10 -> 0.10527329
A11: Avangrid, Inc. | B11: AGR | C11: 0.065 | D11: 309 | E11: 309 | F11: =(E11/D11)^(1/5)-1 -> 0 | G11: =2*(1+F11)/(2+F11) -> 1 | H11: =C11*G11 -> 0.065
A12: Black Hills Corporation | B12: BKH | C12: 0.1 | D12: 60.5 | E12: 61 | F12: =(E12/D12)^(1/4)-1 -> 0.0020597431 | G12: =2*(1+F12)/(2+F12) -> 1.0010288 | H12: =C12*G12 -> 0.10010288
A13: CMS Energy Corporation | B13: CMS | C13: 0.14 | D13: 285 | E13: 297 | F13: =(E13/D13)^(1/5)-1 -> 0.0082827051 | G13: =2*(1+F13)/(2+F13) -> 1.0041243 | H13: =C13*G13 -> 0.1405774
A14: Consolidated Edison, Inc. | B14: ED | C14: 0.085 | D14: 328 | E14: 332 | F14: =(E14/D14)^(1/5)-1 -> 0.002427213 | G14: =2*(1+F14)/(2+F14) -> 1.0012121 | H14: =C14*G14 -> 0.085103032
A15: DTE Energy Company | B15: DTE | C15: 0.105 | D15: 192 | E15: 200 | F15: =(E15/D15)^(1/5)-1 -> 0.0081978185 | G15: =2*(1+F15)/(2+F15) -> 1.0040822 | H15: =C15*G15 -> 0.10542863
A16: Duke Energy Corporation | B16: DUK | C16: 0.085 | D16: 731.5 | E16: 750 | F16: =(E16/D16)^(1/5)-1 -> 0.005007694 | G16: =2*(1+F16)/(2+F16) -> 1.0024976 | H16: =C16*G16 -> 0.085212295
A17: El Paso Electric Company | B17: EE | C17: 0.085 | D17: 40.7 | E17: 41 | F17: =(E17/D17)^(1/4)-1 -> 0.00183768 | G17: =2*(1+F17)/(2+F17) -> 1.000918 | H17: =C17*G17 -> 0.08507803
A18: Evergy, Inc. | B18: EVRG | C18: 0.085 | D18: 225 | E18: 212 | F18: =(E18/D18)^(1/5)-1 -> -0.011832267 | G18: =2*(1+F18)/(2+F18) -> 0.99404866 | H18: =C18*G18 -> 0.084494136
A19: Eversource Energy | B19: ES | C19: 0.095 | D19: 316.89 | E19: 316.89 | F19: =(E19/D19)^(1/5)-1 -> 0 | G19: =2*(1+F19)/(2+F19) -> 1 | H19: =C19*G19 -> 0.095
A20: Hawaiian Electric Industries, Inc. | B20: HE | C20: 0.095 | D20: 110 | E20: 113 | F20: =(E20/D20)^(1/4)-1 -> 0.0067495394 | G20: =2*(1+F20)/(2+F20) -> 1.0033634 | H20: =C20*G20 -> 0.095319525
A21: NextEra Energy, Inc. | B21: NEE | C21: 0.135 | D21: 535 | E21: 535 | F21: =(E21/D21)^(1/5)-1 -> 0 | G21: =2*(1+F21)/(2+F21) -> 1 | H21: =C21*G21 -> 0.135
A22: NorthWestern Corporation | B22: NWE | C22: 0.09 | D22: 50.5 | E22: 51 | F22: =(E22/D22)^(1/4)-1 -> 0.00246611 | G22: =2*(1+F22)/(2+F22) -> 1.0012315 | H22: =C22*G22 -> 0.090110838
A23: OGE Energy Corp. | B23: OGE | C23: 0.115 | D23: 199.7 | E23: 199.7 | F23: =(E23/D23)^(1/5)-1 -> 0 | G23: =2*(1+F23)/(2+F23) -> 1 | H23: =C23*G23 -> 0.115
A24: Otter Tail Corporation | B24: OTTR | C24: 0.105 | D24: 39.75 | E24: 41.75 | F24: =(E24/D24)^(1/5)-1 -> 0.009866276 | G24: =2*(1+F24)/(2+F24) -> 1.0049089 | H24: =C24*G24 -> 0.10551544
A25: Pinnacle West Capital Corporation | B25: PNW | C25: 0.105 | D25: 112.75 | E25: 114.25 | F25: =(E25/D25)^(1/4)-1 -> 0.0033094771 | G25: =2*(1+F25)/(2+F25) -> 1.001652 | H25: =C25*G25 -> 0.10517346
A26: PNM Resources, Inc. | B26: PNM | C26: 0.095 | D26: 79.65 | E26: 83 | F26: =(E26/D26)^(1/4)-1 -> 0.010352867 | G26: =2*(1+F26)/(2+F26) -> 1.0051498 | H26: =C26*G26 -> 0.095489229
A27: Portland General Electric Company | B27: POR | C27: 0.09 | D27: 89.4 | E27: 90 | F27: =(E27/D27)^(1/4)-1 -> 0.001673646 | G27: =2*(1+F27)/(2+F27) -> 1.0008361 | H27: =C27*G27 -> 0.090075251
A28: Southern Company | B28: SO | C28: 0.13 | D28: 1050 | E28: 1090 | F28: =(E28/D28)^(1/5)-1 -> 0.0075055328 | G28: =2*(1+F28)/(2+F28) -> 1.0037387 | H28: =C28*G28 -> 0.13048604
A29: Wisconsin Energy Corporation | B29: WEC | C29: 0.125 | D29: 315.5 | E29: 315.5 | F29: =(E29/D29)^(1/5)-1 -> 0 | G29: =2*(1+F29)/(2+F29) -> 1 | H29: =C29*G29 -> 0.125
A30: Xcel Energy Inc. | B30: XEL | C30: 0.105 | D30: 518 | E30: 533 | F30: =(E30/D30)^(1/4)-1 -> 0.0071620713 | G30: =2*(1+F30)/(2+F30) -> 1.0035683 | H30: =C30*G30 -> 0.10537467
G32: Median | H32: =MEDIAN(H8:H30) -> 0.10010288
G33: Average | H33: =AVERAGE(H8:H30) -> 0.10148793
A34: Notes:
A35: [1] Source: Value Line | B35: [3] Source: Value Line | F35: [5] Equals (2 x (1 + [4])) / (2 + [4])
A36: [2] Source: Value Line | B36: [4] Equals =([3] / [2])^(1/3)-1; ([3] / [2])^(1/4)-1 | F36: [6] Equals [1] x [5]

Sheet RBH-7 Flotation Costs
B2: Flotation Cost Adjustment
B4: Two most recent open market common stock issuances per company, if available | G4: Emera issuances are included for comparison, but are not in averages.
D5: [1] | E5: [2] | F5: [3] | G5: [4] | H5: [5] | I5: [6] | J5: [7] | K5: [8] | L5: [9]
B6: Company | C6: Date | D6: Shares Issued | E6: Offering Price | F6: Underwriting Discount | G6: Offering Expense | H6: Net Proceeds Per Share | I6: Total Flotation Costs | J6: Gross Equity Issue Before Costs | K6: Net Proceeds | L6: Flotation Cost Percentage
B8: American Electric Power Company, Inc. | C8: 39904 | D8: 69000000 | E8: 24.5 | F8: 0.735 | G8: 400000 | H8: =K8/D8 -> 23.759203 | I8: =G8+(F8*D8) -> 51115000 | J8: =D8*E8 -> 1690500000 | K8: =J8-I8 -> 1639385000 | L8: =I8/J8 -> 0.030236616
B9: American Electric Power Company, Inc. | C9: 37679 | D9: 57500000 | E9: 20.95 | F9: 0.6285 | G9: 550000 | H9: =K9/D9 -> 20.311935 | I9: =G9+(F9*D9) -> 36688750 | J9: =D9*E9 -> 1204625000 | K9: =J9-I9 -> 1167936250 | L9: =I9/J9 -> 0.030456574
K10: Average | L10: =AVERAGE(L9:L9) -> 0.030456574
B12: ALLETE, Inc. | C12: 41697 | D12: 3220000 | E12: 49.75 | F12: 1.74125 | G12: 450000 | H12: =K12/D12 -> 47.868998 | I12: =G12+(F12*D12) -> 6056825 | J12: =D12*E12 -> 160195000 | K12: =J12-I12 -> 154138175 | L12: =I12/J12 -> 0.037809076
B13: ALLETE, Inc. | C13: 37036 | D13: 7475000 | E13: 23.68 | F13: 0.9472 | G13: 350000 | H13: =K13/D13 -> 22.685977 | I13: =G13+(F13*D13) -> 7430320 | J13: =D13*E13 -> 177008000 | K13: =J13-I13 -> 169577680 | L13: =I13/J13 -> 0.041977312
B14: Alliant Energy Corporation | C14: 37803 | D14: 17250000 | E14: 19.25 | F14: 0.77 | G14: 370000 | H14: =K14/D14 -> 18.458551 | I14: =G14+(F14*D14) -> 13652500 | J14: =D14*E14 -> 332062500 | K14: =J14-I14 -> 318410000 | L14: =I14/J14 -> 0.041114248
B15: Alliant Energy Corporation | C15: 37203 | D15: 9775000 | E15: 28 | F15: 1.05 | G15: 425000 | H15: =K15/D15 -> 26.906522 | I15: =G15+(F15*D15) -> 10688750 | J15: =D15*E15 -> 273700000 | K15: =J15-I15 -> 263011250 | L15: =I15/J15 -> 0.039052795
B16: Ameren Corp. | C16: 40065 | D16: 21850000 | E16: 25.25 | F16: 0.7575 | G16: 450000 | H16: =K16/D16 -> 24.471905 | I16: =G16+(F16*D16) -> 17001375 | J16: =D16*E16 -> 551712500 | K16: =J16-I16 -> 534711125 | L16: =I16/J16 -> 0.030815642
B17: Ameren Corp. | C17: 38168 | D17: 10925000 | E17: 42 | F17: 1.26 | G17: 400000 | H17: =K17/D17 -> 40.703387 | I17: =G17+(F17*D17) -> 14165500 | J17: =D17*E17 -> 458850000 | K17: =J17-I17 -> 444684500 | L17: =I17/J17 -> 0.030871745
B18: Avangrid, Inc. | C18: 41543 | D18: 5750000 | E18: 37.25 | F18: 1.30375 | G18: 250000 | H18: =K18/D18 -> 35.902772 | I18: =G18+(F18*D18) -> 7746562.5 | J18: =D18*E18 -> 214187500 | K18: =J18-I18 -> 2.0644094e+08 | L18: =I18/J18 -> 0.036167202
B19: Avangrid, Inc. | C19: 40437 | D19: 20355000 | E19: 25.75 | F19: 1.094375 | G19: 325000 | H19: =K19/D19 -> 24.639658 | I19: =G19+(F19*D19) -> 22601003 | J19: =D19*E19 -> 524141250 | K19: =J19-I19 -> 5.0154025e+08 | L19: =I19/J19 -> 0.043120062
B20: Black Hills Corporation | C20: 42327 | D20: 5980000 | E20: 40.25 | F20: 1.40875 | G20: 1200000 | H20: =K20/D20 -> 38.640581 | I20: =G20+(F20*D20) -> 9624325 | J20: =D20*E20 -> 240695000 | K20: =J20-I20 -> 231070675 | L20: =I20/J20 -> 0.039985563
B21: Black Hills Corporation | C21: 40494 | D21: 4600000 | E21: 29.75 | F21: 1.04125 | G21: 276650 | H21: =K21/D21 -> 28.648609 | I21: =G21+(F21*D21) -> 5066400 | J21: =D21*E21 -> 136850000 | K21: =J21-I21 -> 131783600 | L21: =I21/J21 -> 0.037021556
B22: CMS Energy Corporation | C22: 38441 | D22: 23000000 | E22: 12.25 | F22: 0.4288 | G22: 325000 | H22: =K22/D22 -> 11.80707 | I22: =G22+(F22*D22) -> 10187400 | J22: =D22*E22 -> 281750000 | K22: =J22-I22 -> 271562600 | L22: =I22/J22 -> 0.036157587
B23: CMS Energy Corporation | C23: 38267 | D23: 32775000 | E23: 9.1 | F23: 0.3185 | G23: 325000 | H23: =K23/D23 -> 8.7715839 | I23: =G23+(F23*D23) -> 10763838 | J23: =D23*E23 -> 298252500 | K23: =J23-I23 -> 2.8748866e+08 | L23: =I23/J23 -> 0.036089681
B24: Consolidated Edison, Inc | C24: 42955 | D24: 4100000 | E24: 83.7701 | F24: =84.06-83.7701 -> 0.2899 | G24: 350000 | H24: =K24/D24 -> 83.394834 | I24: =G24+(F24*D24) -> 1538590 | J24: =D24*E24 -> 343457410 | K24: =J24-I24 -> 341918820 | L24: =I24/J24 -> 0.0044797112
B25: Consolidated Edison, Inc | C25: 42501 | D25: 10120000 | E25: 71.5 | F25: 2.145 | G25: 550000 | H25: =K25/D25 -> 69.300652 | I25: =G25+(F25*D25) -> 22257400 | J25: =D25*E25 -> 723580000 | K25: =J25-I25 -> 701322600 | L25: =I25/J25 -> 0.030760109
B26: DTE Energy Company | C26: 37426 | D26: 6325000 | E26: 43.25 | F26: 1.4056 | G26: 250000 | H26: =K26/D26 -> 41.804874 | I26: =G26+(F26*D26) -> 9140420 | J26: =D26*E26 -> 273556250 | K26: =J26-I26 -> 264415830 | L26: =I26/J26 -> 0.033413311
B27: Duke Energy Corporation | C27: 43165 | D27: 21275000 | E27: 74.072 | F27: 0 | G27: 450000 | H27: =K27/D27 -> 74.050848 | I27: =G27+(F27*D27) -> 450000 | J27: =D27*E27 -> 1575881800 | K27: =J27-I27 -> 1575431800 | L27: =I27/J27 -> 0.00028555441
B28: Duke Energy Corporation | C28: 42430 | D28: 10637500 | E28: 72 | F28: 2.16 | G28: 400000 | H28: =K28/D28 -> 69.802397 | I28: =G28+(F28*D28) -> 23377000 | J28: =D28*E28 -> 765900000 | K28: =J28-I28 -> 742523000 | L28: =I28/J28 -> 0.030522261
B29: Evergy, Inc. | C29: 42640 | D29: =52600000+7890000 -> 60490000 | E29: 26.45 | F29: 0.7935 | G29: 500000 | H29: =K29/D29 -> 25.648234 | I29: =G29+(F29*D29) -> 48498815 | J29: =D29*E29 -> 1599960500 | K29: =J29-I29 -> 1551461685 | L29: =I29/J29 -> 0.030312508
B30: Evergy, Inc. | C30: 41540 | D30: 8916000 | E30: 31.15 | F30: 1.09 | G30: 250000 | H30: =K30/D30 -> 30.031961 | I30: =G30+(F30*D30) -> 9968440 | J30: =D30*E30 -> 277733400 | K30: =J30-I30 -> 267764960 | L30: =I30/J30 -> 0.035892118
B31: Eversource Energy | C31: 39888 | D31: 18975000 | E31: 20.2 | F31: 0.6565 | G31: 335000 | H31: =K31/D31 -> 19.525845 | I31: =G31+(F31*D31) -> 12792088 | J31: =D31*E31 -> 383295000 | K31: =J31-I31 -> 3.7050291e+08 | L31: =I31/J31 -> 0.033374
B32: Eversource Energy | C32: 38692 | D32: 23000000 | E32: 19.09 | F32: 0.62 | G32: 340000 | H32: =K32/D32 -> 18.455217 | I32: =G32+(F32*D32) -> 14600000 | J32: =D32*E32 -> 439070000 | K32: =J32-I32 -> 424470000 | L32: =I32/J32 -> 0.033252101
B33: Hawaiian Electric Industries, Inc. | C33: 41351 | D33: 7000000 | E33: 26.75 | F33: 1.00312 | G33: 450000 | H33: =K33/D33 -> 25.682594 | I33: =G33+(F33*D33) -> 7471840 | J33: =D33*E33 -> 187250000 | K33: =J33-I33 -> 179778160 | L33: =I33/J33 -> 0.039903017
B34: Hawaiian Electric Industries, Inc. | C34: 39784 | D34: 5750000 | E34: 23 | F34: 0.8625 | G34: 300000 | H34: =K34/D34 -> 22.085326 | I34: =G34+(F34*D34) -> 5259375 | J34: =D34*E34 -> 132250000 | K34: =J34-I34 -> 126990625 | L34: =I34/J34 -> 0.039768431
B35: NextEra Energy, Inc. | C35: 42675 | D35: 13800000 | E35: 124 | F35: 0 | G35: 750000 | H35: =K35/D35 -> 123.94565 | I35: =G35+(F35*D35) -> 750000 | J35: =D35*E35 -> 1711200000 | K35: =J35-I35 -> 1710450000 | L35: =I35/J35 -> 0.00043828892
B36: NextEra Energy, Inc. | C36: 41596 | D36: 11100000 | E36: 88.03 | F36: 0 | G36: 750000 | H36: =K36/D36 -> 87.962432 | I36: =G36+(F36*D36) -> 750000 | J36: =D36*E36 -> 977133000 | K36: =J36-I36 -> 976383000 | L36: =I36/J36 -> 0.0007675516
B37: NorthWestern Corporation | C37: 42276 | D37: 1100000 | E37: 51.81 | F37: 1.33 | G37: 1000000 | H37: =K37/D37 -> 49.570909 | I37: =G37+(F37*D37) -> 2463000 | J37: =D37*E37 -> 56991000 | K37: =J37-I37 -> 54528000 | L37: =I37/J37 -> 0.04321735
B38: NorthWestern Corporation | C38: 41948 | D38: 7766990 | E38: 51.5 | F38: 1.8025 | G38: 1000000 | H38: =K38/D38 -> 49.56875 | I38: =G38+(F38*D38) -> 14999999 | J38: =D38*E38 -> 399999985 | K38: =J38-I38 -> 3.8499999e+08 | L38: =I38/J38 -> 0.0375
B39: OGE Energy Corp. | C39: 37854 | D39: 5324074 | E39: 21.6 | F39: 0.79 | G39: 325000 | H39: =K39/D39 -> 20.748957 | I39: =G39+(F39*D39) -> 4531018.5 | J39: =D39*E39 -> 1.15e+08 | K39: =J39-I39 -> 1.1046898e+08 | L39: =I39/J39 -> 0.039400161
B40: Otter Tail Corporation | C40: 39709 | D40: 5175000 | E40: 30 | F40: 1.0875 | G40: 400000 | H40: =K40/D40 -> 28.835205 | I40: =G40+(F40*D40) -> 6027812.5 | J40: =D40*E40 -> 155250000 | K40: =J40-I40 -> 1.4922219e+08 | L40: =I40/J40 -> 0.03882649
B41: Otter Tail Corporation | C41: 38328 | D41: 3335000 | E41: 25.45 | F41: 0.95 | G41: 300000 | H41: =K41/D41 -> 24.410045 | I41: =G41+(F41*D41) -> 3468250 | J41: =D41*E41 -> 84875750 | K41: =J41-I41 -> 81407500 | L41: =I41/J41 -> 0.040862673
... B53: Xcel Energy Inc. | C53: 39700 | D53: 17250000 | E53: 20.25 | F53: 0.15 | G53: 600000 | H53: =K53/D53 -> 20.065217 | I53: =G53+(F53*D53) -> 3187500 | J53: =D53*E53 -> 349312500 | K53: =J53-I53 -> 346125000 | L53: =I53/J53 -> 0.0091250671
B55: Mean | I55: =AVERAGE(I8:I53) -> 13261973 | J55: =AVERAGE(J8:J53) -> 4.9698053e+08
K56: WEIGHTED AVERAGE FLOTATION COSTS: | L56: =I55/J55 -> 0.026685096 | M56: [10]
B59: Constant Growth Discounted Cash Flow Model Adjusted for Flotation Costs - 30 Day Average Stock Price
D60: [11] | E60: [12] | F60: [13] | G60: [14] | H60: [15] | I60: [16] | J60: [17] | K60: [18] | L60: [19] | M60: [20] | N60: [21]
E61: Average | G61: Expected Dividend Yield | I61: Zacks | J61: First Call | K61: Value Line | L61: Average | N61: Flotation
D62: Annualized | E62: Stock | F62: Dividend | H62: Adjusted for | I62: Earnings | J62: Earnings | K62: Earnings | L62: Earnings | N62: Adjusted
B63: Company | C63: Ticker | D63: Dividend | E63: Price | F63: Yield | G63: Current | H63: Flot. Costs | I63: Growth | J63: Growth | K63: Growth | L63: Growth | M63: DCF k(e) | N63: DCF k(e)
B65: ='RBH-1 Constant Growth DCF'!B8 -> ALLETE, Inc. | C65: ='RBH-1 Constant Growth DCF'!C8 -> ALE | D65: ='RBH-1 Constant Growth DCF'!E8 -> 2.35 | E65: ='RBH-1 Constant Growth DCF'!F8 -> 80.266667 | F65: =D65/E65 -> 0.029277409 | G65: =F65*(1+0.5*L65) -> 0.030082537 | H65: =G65/(1-$L$56) -> 0.030907302 | I65: ='RBH-1 Constant Growth DCF'!I8 -> NA | J65: ='RBH-1 Constant Growth DCF'!J8 -> 0.06 | K65: ='RBH-1 Constant Growth DCF'!K8 -> 0.05 | L65: =AVERAGE(I65:K65) -> 0.055 | M65: =G65+L65 -> 0.085082537 | N65: =H65+L65 -> 0.085907302
B66: ='RBH-1 Constant Growth DCF'!B9 -> Alliant Energy Corporation | C66: ='RBH-1 Constant Growth DCF'!C9 -> LNT | D66: ='RBH-1 Constant Growth DCF'!E9 -> 1.42 | E66: ='RBH-1 Constant Growth DCF'!F9 -> 45.564667 | F66: =D66/E66 -> 0.031164499 | G66: =F66*(1+0.5*L66) -> 0.03219033 | H66: =G66/(1-$L$56) -> 0.033072883 | I66: ='RBH-1 Constant Growth DCF'!I9 -> 0.06 | J66: ='RBH-1 Constant Growth DCF'!J9 -> 0.0725 | K66: ='RBH-1 Constant Growth DCF'!K9 -> 0.065 | L66: =AVERAGE(I66:K66) -> 0.065833333 | M66: =G66+L66 -> 0.098023664 | N66: =H66+L66 -> 0.098906217
B67: ='RBH-1 Constant Growth DCF'!B10 -> Ameren Corporation | C67: ='RBH-1 Constant Growth DCF'!C10 -> AEE | D67: ='RBH-1 Constant Growth DCF'!E10 -> 1.9 | E67: ='RBH-1 Constant Growth DCF'!F10 -> 70.764333 | F67: =D67/E67 -> 0.026849684 | G67: =F67*(1+0.5*L67) -> 0.027789423 | H67: =G67/(1-$L$56) -> 0.028551318 | I67: ='RBH-1 Constant Growth DCF'!I10 -> 0.068 | J67: ='RBH-1 Constant Growth DCF'!J10 -> 0.077 | K67: ='RBH-1 Constant Growth DCF'!K10 -> 0.065 | L67: =AVERAGE(I67:K67) -> 0.07 | M67: =G67+L67 -> 0.097789423 | N67: =H67+L67 -> 0.098551318
B68: ='RBH-1 Constant Growth DCF'!B11 -> Avangrid, Inc. | C68: ='RBH-1 Constant Growth DCF'!C11 -> AGR | D68: ='RBH-1 Constant Growth DCF'!E11 -> 1.76 | E68: ='RBH-1 Constant Growth DCF'!F11 -> 49.391 | F68: =D68/E68 -> 0.035634022 | G68: =F68*(1+0.5*L68) -> 0.037350394 | H68: =G68/(1-$L$56) -> 0.03837442 | I68: ='RBH-1 Constant Growth DCF'!I11 -> 0.077 | J68: ='RBH-1 Constant Growth DCF'!J11 -> 0.092 | K68: ='RBH-1 Constant Growth DCF'!K11 -> 0.12 | L68: =AVERAGE(I68:K68) -> 0.096333333 | M68: =G68+L68 -> 0.13368373 | N68: =H68+L68 -> 0.13470775
B69: ='RBH-1 Constant Growth DCF'!B12 -> Black Hills Corporation | C69: ='RBH-1 Constant Growth DCF'!C12 -> BKH | D69: ='RBH-1 Constant Growth DCF'!E12 -> 2.02 | E69: ='RBH-1 Constant Growth DCF'!F12 -> 70.591333 | F69: =D69/E69 -> 0.028615411 | G69: =F69*(1+0.5*L69) -> 0.029322688 | H69: =G69/(1-$L$56) -> 0.03012662 | I69: ='RBH-1 Constant Growth DCF'!I12 -> 0.047 | J69: ='RBH-1 Constant Growth DCF'!J12 -> 0.0363 | K69: ='RBH-1 Constant Growth DCF'!K12 -> 0.065 | L69: =AVERAGE(I69:K69) -> 0.049433333 | M69: =G69+L69 -> 0.078756022 | N69: =H69+L69 -> 0.079559953
B70: ='RBH-1 Constant Growth DCF'!B13 -> CMS Energy Corporation | C70: ='RBH-1 Constant Growth DCF'!C13 -> CMS | D70: ='RBH-1 Constant Growth DCF'!E13 -> 1.53 | E70: ='RBH-1 Constant Growth DCF'!F13 -> 53.586333 | F70: =D70/E70 -> 0.028552056 | G70: =F70*(1+0.5*L70) -> 0.029498557 | H70: =G70/(1-$L$56) -> 0.03030731 | I70: ='RBH-1 Constant Growth DCF'!I13 -> 0.06 | J70: ='RBH-1 Constant Growth DCF'!J13 -> 0.0689 | K70: ='RBH-1 Constant Growth DCF'!K13 -> 0.07 | L70: =AVERAGE(I70:K70) -> 0.0663 | M70: =G70+L70 -> 0.095798557 | N70: =H70+L70 -> 0.09660731
B71: ='RBH-1 Constant Growth DCF'!B14 -> Consolidated Edison, Inc. | C71: ='RBH-1 Constant Growth DCF'!C14 -> ED | D71: ='RBH-1 Constant Growth DCF'!E14 -> 2.96 | E71: ='RBH-1 Constant Growth DCF'!F14 -> 80.953667 | F71: =D71/E71 -> 0.036564125 | G71: =F71*(1+0.5*L71) -> 0.037051037 | H71: =G71/(1-$L$56) -> 0.038066855 | I71: ='RBH-1 Constant Growth DCF'!I14 -> 0.02 | J71: ='RBH-1 Constant Growth DCF'!J14 -> 0.0299 | K71: ='RBH-1 Constant Growth DCF'!K14 -> 0.03 | L71: =AVERAGE(I71:K71) -> 0.026633333 | M71: =G71+L71 -> 0.063684371 | N71: =H71+L71 -> 0.064700188
B72: ='RBH-1 Constant Growth DCF'!B15 -> DTE Energy Company | C72: ='RBH-1 Constant Growth DCF'!C15 -> DTE | D72: ='RBH-1 Constant Growth DCF'!E15 -> 3.78 | E72: ='RBH-1 Constant Growth DCF'!F15 -> 121.32633 | F72: =D72/E72 -> 0.031155644 | G72: =F72*(1+0.5*L72) -> 0.031942843 | H72: =G72/(1-$L$56) -> 0.032818611 | I72: ='RBH-1 Constant Growth DCF'!I15 -> 0.06 | J72: ='RBH-1 Constant Growth DCF'!J15 -> 0.0416 | K72: ='RBH-1 Constant Growth DCF'!K15 -> 0.05 | L72: =AVERAGE(I72:K72) -> 0.050533333 | M72: =G72+L72 -> 0.082476176 | N72: =H72+L72 -> 0.083351944
B73: ='RBH-1 Constant Growth DCF'!B16 -> Duke Energy Corporation | C73: ='RBH-1 Constant Growth DCF'!C16 -> DUK | D73: ='RBH-1 Constant Growth DCF'!E16 -> 3.71 | E73: ='RBH-1 Constant Growth DCF'!F16 -> 89.399333 | F73: =D73/E73 -> 0.041499191 | G73: =F73*(1+0.5*L73) -> 0.042536671 | H73: =G73/(1-$L$56) -> 0.043702886 | I73: ='RBH-1 Constant Growth DCF'!I16 -> 0.05 | J73: ='RBH-1 Constant Growth DCF'!J16 -> 0.045 | K73: ='RBH-1 Constant Growth DCF'!K16 -> 0.055 | L73: =AVERAGE(I73:K73) -> 0.05 | M73: =G73+L73 -> 0.092536671 | N73: =H73+L73 -> 0.093702886
B74: ='RBH-1 Constant Growth DCF'!B17 -> El Paso Electric Company | C74: ='RBH-1 Constant Growth DCF'!C17 -> EE | D74: ='RBH-1 Constant Growth DCF'!E17 -> 1.44 | E74: ='RBH-1 Constant Growth DCF'!F17 -> 55.155333 | F74: =D74/E74 -> 0.026108083 | G74: =F74*(1+0.5*L74) -> 0.026578028 | H74: =G74/(1-$L$56) -> 0.02730671 | I74: ='RBH-1 Constant Growth DCF'!I17 -> 0.027 | J74: ='RBH-1 Constant Growth DCF'!J17 -> 0.051 | K74: ='RBH-1 Constant Growth DCF'!K17 -> 0.03 | L74: =AVERAGE(I74:K74) -> 0.036 | M74: =G74+L74 -> 0.062578028 | N74: =H74+L74 -> 0.06330671
B75: ='RBH-1 Constant Growth DCF'!B18 -> Evergy, Inc | C75: ='RBH-1 Constant Growth DCF'!C18 -> EVRG | D75: ='RBH-1 Constant Growth DCF'!E18 -> 1.9 | E75: ='RBH-1 Constant Growth DCF'!F18 -> 57.002667 | F75: =D75/E75 -> 0.033331774 | G75: =F75*(1+0.5*L75) -> 0.03441089 | H75: =G75/(1-$L$56) -> 0.035354324 | I75: ='RBH-1 Constant Growth DCF'!I18 -> 0.067 | J75: ='RBH-1 Constant Growth DCF'!J18 -> 0.0625 | K75: ='RBH-1 Constant Growth DCF'!K18 -> NMF | L75: =AVERAGE(I75:K75) -> 0.06475 | M75: =G75+L75 -> 0.09916089 | N75: =H75+L75 -> 0.10010432
B76: ='RBH-1 Constant Growth DCF'!B19 -> Eversource Energy | C76: ='RBH-1 Constant Growth DCF'!C19 -> ES | D76: ='RBH-1 Constant Growth DCF'!E19 -> 2.14 | E76: ='RBH-1 Constant Growth DCF'!F19 -> 69.894333 | F76: =D76/E76 -> 0.030617647 | G76: =F76*(1+0.5*L76) -> 0.031489229 | H76: =G76/(1-$L$56) -> 0.03235256 | I76: ='RBH-1 Constant Growth DCF'!I19 -> 0.057 | J76: ='RBH-1 Constant Growth DCF'!J19 -> 0.0588 | K76: ='RBH-1 Constant Growth DCF'!K19 -> 0.055 | L76: =AVERAGE(I76:K76) -> 0.056933333 | M76: =G76+L76 -> 0.088422562 | N76: =H76+L76 -> 0.089285893
... B87: ='RBH-1 Constant Growth DCF'!B30 -> Xcel Energy Inc. | C87: ='RBH-1 Constant Growth DCF'!C30 -> XEL | D87: ='RBH-1 Constant Growth DCF'!E30 -> 1.62 | E87: ='RBH-1 Constant Growth DCF'!F30 -> 54.412667 | F87: =D87/E87 -> 0.029772479 | G87: =F87*(1+0.5*L87) -> 0.030665654 | H87: =G87/(1-$L$56) -> 0.031506405 | I87: ='RBH-1 Constant Growth DCF'!I30 -> 0.059 | J87: ='RBH-1 Constant Growth DCF'!J30 -> 0.066 | K87: ='RBH-1 Constant Growth DCF'!K30 -> 0.055 | L87: =AVERAGE(I87:K87) -> 0.06 | M87: =G87+L87 -> 0.090665654 | N87: =H87+L87 -> 0.091506405
B88: PROXY GROUP MEAN | M88: =AVERAGE(M65:M87) -> 0.088101207 | N88: =AVERAGE(N65:N87) -> 0.088999257
M90: DCF Result Adjusted For Flotation Costs: | N90: =N88 -> 0.088999257
M91: DCF Result Unadjusted For Flotation Costs: | N91: =M88 -> 0.088101207
M92: Difference (Flotation Cost Adjustment): | N92: =N90-N91 -> 0.00089804967 | O92: [22]
B93: Notes:
B94: The proxy group DCF result is adjusted for flotation costs by dividing each company's expected dividend yield by (1 - flotation cost). The flotation cost adjustment is derived as the difference between the unadjusted DCF result and the DCF result adjusted for flotation costs.
B98: [1] Source: SEC Form 424B | E98: [12] Source: Bloomberg Professional
B99: [2] Source: SEC Form 424B | E99: [13] Equals [11] / [12]
B100: [3] Source: SEC Form 424B | E100: [14] Equals [3] x (1 + 0.5 x [19])
B101: [4] Source: SEC Form 424B | E101: ="[15] Equals [4] / (1 - "&ROUND(L56,4)&")" -> [15] Equals [4] / (1 - 0.0267)
B102: [5] Equals [8] / [1] | E102: [16] Source: Zacks
B103: [6] Equals [4] + ([1] x [3]) | E103: [17] Source: Yahoo! Finance
B104: [7] Equals [1] x [2] | E104: [18] Source: Value Line
B105: [8] Equals [7] - [6] | E105: [19] Equals Average([16], [17], [18])
B106: [9] Equals [6] / [7] | E106: [20] Equals [14] + [19]
B107: [10] Equals average [6] / average [7] | E107: [21] Equals [15] + [19]
B108: [11] Source: Bloomberg Professional | E108: [22] Equals average [21] - average [20]

Sheet RBH-8 Rate Mechanisms
A2: Summary of Adjustment Clauses & Alternative Regulation/Incentive Plans
D4: Adjustment Clauses | K4: Alternative Regulation / Incentive Plans
A5: Company | B5: Parent | C5: State | D5: Fuel/ Purchased Power | E5: Decoupling (F/P) [1] | F5: New Capital Investment [2] | G5: Energy Efficiency [3] | H5: Renewables & RPS [4] | I5: Environmental [5] | J5: Other [6] | K5: Formula-Based Rates | L5: Multiyear Rate Plans | M5: Performance Based Ratemaking | N5: CWIP Allowed in Rate Base (L/F) | O5: Forward Test Year | P5: Price Freeze/ Cap | Q5: Earnings Sharing | R5: Formula-Based ROE | S5: Service Quality/ Performance | T5: Merger Savings
A6: ALLETE (Minnesota Power) | B6: ALE | C6: Minnesota | D6: ü | G6: ü | H6: ü | I6: ü | J6: ü | N6: L | O6: ü
A7: Superior Water, Light and Power Company | B7: ALE | C7: Wisconsin | D7: ü | J7: ü | N7: L | O7: ü
A8: Interstate Power and Light Company | B8: LNT | C8: Iowa | D8: ü | G8: ü | H8: ü | I8: ü | J8: ü | L8: ü | P8: ü
A9: Wisconsin Power and Light Company | B9: LNT | C9: Wisconsin | D9: ü | J9: ü | L9: ü | N9: L | O9: ü | P9: ü | Q9: ü
A10: Ameren Illinois Company | B10: AEE | C10: Illinois | D10: ü | F10: ü | G10: ü | H10: ü | I10: ü | J10: ü | K10: ü | N10: L | Q10: ü | R10: ü | S10: ü
A11: Union Electric Company | B11: AEE | C11: Missouri | D11: ü | E11: P | G11: ü | I11: ü | J11: ü
A12: United Illuminating Company | B12: AGR | C12: Connecticut | D12: ü | E12: F | G12: ü | H12: ü | I12: ü | J12: ü | L12: ü | Q12: ü
A13: Central Maine Power Company | B13: AGR | C13: Maine | D13: ü | E13: F | J13: ü | Q13: ü
A14: New York State Electric & Gas Corporation | B14: AGR | C14: New York | D14: ü | E14: F | G14: ü | H14: ü | J14: ü | L14: ü | M14: ü | P14: ü | Q14: ü
A15: Rochester Gas and Electric Corporation | B15: AGR | C15: New York | D15: ü | E15: F | G15: ü | H15: ü | J15: ü | L15: ü | M15: ü | P15: ü | Q15: ü
A16: Black Hills Colorado Electric Utility Company, LP | B16: BKH | C16: Colorado | D16: ü | F16: ü | G16: ü | H16: ü | J16: ü | M16: ü | N16: F
A17: Black Hills Power, Inc. | B17: BKH | C17: South Dakota | D17: ü | E17: P | F17: ü | G17: ü | I17: ü | J17: ü | M17: ü
A18: Black Hills Power, Inc. | B18: BKH | C18: Wyoming | D18: ü | J18: ü | M18: ü
A19: Cheyenne Light, Fuel and Power Company | B19: BKH | C19: Wyoming | D19: ü | E19: P | G19: ü | J19: ü
A20: Consumers Energy Company | B20: CMS | C20: Michigan | D20: ü | G20: ü | H20: ü | J20: ü | N20: L | O20: ü
A21: Rockland Electric Company | B21: ED | C21: New Jersey | D21: ü | F21: ü | G21: ü | H21: ü | J21: ü
A22: Consolidated Edison Company of New York, Inc. | B22: ED | C22: New York | D22: ü | E22: F | F22: ü | G22: ü | H22: ü | I22: ü | J22: ü | L22: ü | O22: ü | P22: ü | Q22: ü
A23: Orange and Rockland Utilities, Inc. | B23: ED | C23: New York | D23: ü | E23: F | F23: ü | G23: ü | H23: ü | J23: ü | L23: ü | O23: ü | P23: ü | Q23: ü
A24: DTE Electric Company | B24: DTE | C24: Michigan | D24: ü | G24: ü | H24: ü | I24: ü | J24: ü | N24: L | O24: ü
A25: Duke Energy Florida, LLC | B25: DUK | C25: Florida | D25: ü | F25: ü | G25: ü | I25: ü | J25: ü | L25: ü | M25: ü | O25: ü | P25: ü
A26: Duke Energy Indiana, LLC | B26: DUK | C26: Indiana | D26: ü | E26: P | F26: ü | G26: ü | H26: ü | I26: ü | J26: ü | N26: F | P26: ü
A27: Duke Energy Kentucky, Inc. | B27: DUK | C27: Kentucky | D27: ü | E27: P | G27: ü | I27: ü | J27: ü | N27: F | O27: ü
A28: Duke Energy Carolinas, LLC | B28: DUK | C28: North Carolina | D28: ü | E28: P | G28: ü | H28: ü | I28: ü | J28: ü | P28: ü
A29: Duke Energy Progress, LLC | B29: DUK | C29: North Carolina | D29: ü | E29: P | F29: ü | G29: ü | H29: ü | I29: ü | J29: ü
A30: Duke Energy Ohio, Inc. | B30: DUK | C30: Ohio | D30: ü | E30: P | F30: ü | G30: ü | H30: ü | J30: ü | Q30: ü
A31: Duke Energy Carolinas, LLC | B31: DUK | C31: South Carolina | D31: ü | E31: P | G31: ü | H31: ü | I31: ü | J31: ü | L31: ü | P31: ü
A32: Duke Energy Progress, LLC | B32: DUK | C32: South Carolina | D32: ü | E32: P | G32: ü | H32: ü | I32: ü | J32: ü
A33: El Paso Electric Company | B33: EE | C33: New Mexico | D33: ü | G33: ü | J33: ü
A34: El Paso Electric Company | B34: EE | C34: Texas | D34: ü | G34: ü | J34: ü
A35: Kansas City Power & Light Company | B35: EVRG | C35: Kansas | D35: ü | G35: ü | I35: ü | J35: ü
A36: Kansas City Power & Light Company | B36: EVRG | C36: Missouri | D36: ü | E36: P | G36: ü | I36: ü | J36: ü
A37: KCP&L Greater Missouri Operations Company | B37: EVRG | C37: Missouri | D37: ü | G37: ü | H37: ü | I37: ü | J37: ü
A38: Westar Energy (KPL) | B38: EVRG | C38: Kansas | D38: ü | E38: P | G38: ü | I38: ü | J38: ü | T38: ü
A39: Connecticut Light and Power Company | B39: ES | C39: Connecticut | D39: ü | E39: F | F39: ü | G39: ü | I39: ü | J39: ü | L39: ü | O39: ü | P39: ü | Q39: ü
A40: NSTAR Electric Company | B40: ES | C40: Massachusetts | D40: ü | E40: F | F40: ü | G40: ü | H40: ü | J40: ü | L40: ü | M40: ü | Q40: ü | S40: ü
A41: Western Massachusetts Electric Company | B41: ES | C41: Massachusetts | D41: ü | E41: F | F41: ü | G41: ü | H41: ü | J41: ü | L41: ü | M41: ü | Q41: ü | S41: ü
A42: Public Service Company of New Hampshire | B42: ES | C42: New Hampshire | D42: ü | E42: P | F42: ü | G42: ü | J42: ü | L42: ü | P42: ü | Q42: ü
A43: Hawaii Electric Light Company, Inc. | B43: HE | C43: Hawaii | D43: ü | E43: F | F43: ü | G43: ü | H43: ü | J43: ü | L43: ü | O43: ü | Q43: ü
A44: Hawaiian Electric Company, Inc. | B44: HE | C44: Hawaii | D44: ü | E44: F | F44: ü | G44: ü | H44: ü | J44: ü | L44: ü | O44: ü | Q44: ü
A45: Maui Electric Company, Limited | B45: HE | C45: Hawaii | D45: ü | E45: F | F45: ü | G45: ü | H45: ü | J45: ü | L45: ü | O45: ü | Q45: ü
A46: Florida Power & Light Company | B46: NEE | C46: Florida | D46: ü | G46: ü | I46: ü | J46: ü | O46: ü | P46: ü
A47: Gulf Power Company | B47: NEE | C47: Florida | D47: ü | G47: ü | I47: ü | J47: ü | L47: ü | M47: ü | N47: F | O47: ü
A48: NorthWestern Energy | B48: NWE | C48: Montana | D48: ü | G48: ü | J48: ü | O48: ü
A49: NorthWestern Energy | B49: NWE | C49: South Dakota | D49: ü | I49: ü | J49: ü | L49: ü | M49: ü | N49: L
A50: Oklahoma Gas and Electric Company | B50: OGE | C50: Arkansas | D50: ü | E50: P | F50: ü | G50: ü | I50: ü | J50: ü | K50: ü
A51: Oklahoma Gas and Electric Company | B51: OGE | C51: Oklahoma | D51: ü | E51: P | G51: ü | J51: ü | M51: ü | N51: F
A52: Otter Tail Power Company | B52: OTTR | C52: Minnesota | D52: ü | F52: ü | G52: ü | H52: ü | I52: ü | J52: ü | N52: L
A53: Otter Tail Power Company | B53: OTTR | C53: North Dakota | D53: ü | F53: ü | H53: ü | I53: ü | J53: ü | N53: F | O53: ü
A54: Otter Tail Power Company | B54: OTTR | C54: South Dakota | D54: ü | F54: ü | G54: ü | I54: ü | J54: ü | N54: L
A55: Arizona Public Service Company | B55: PNW | C55: Arizona | D55: ü | G55: ü | H55: ü | J55: ü | L55: ü | M55: ü | P55: ü
A56: Public Service Company of New Mexico | B56: PNM | C56: New Mexico | D56: NA | F56: ü | G56: ü | J56: ü | N56: F | O56: ü | Q56: ü
A57: Texas-New Mexico Power Company | B57: PNM | C57: Texas | D57: ü | E57: P | G57: ü | H57: ü | I57: ü | J57: ü | N57: L
A58: Portland General Electric Company | B58: POR | C58: Oregon | D58: ü | E58: P | G58: ü | H58: ü | I58: ü | J58: ü | O58: ü
A59: Alabama Power Company | B59: SO | C59: Alabama | D59: ü | F59: ü | I59: ü | J59: ü | K59: ü | M59: ü
A60: Georgia Power Company | B60: SO | C60: Georgia | D60: ü | F60: ü | G60: ü | I60: ü | J60: ü | L60: ü | N60: L | O60: ü | P60: ü | Q60: ü
A61: Mississippi Power Company | B61: SO | C61: Mississippi | D61: ü | E61: P | F61: ü | G61: ü | H61: ü | I61: ü | J61: ü | K61: ü | M61: ü | N61: F | O61: ü | R61: ü | S61: ü
A62: Upper Michigan Energy Resources Corp | B62: WEC | C62: Michigan | D62: ü | G62: ü | H62: ü | J62: ü | O62: ü
A63: Wisconsin Electric Power | B63: WEC | C63: Wisconsin | D63: ü | J63: ü | N63: L | O63: ü | P63: ü | Q63: ü
A64: Wisconsin Public Service Company | B64: WEC | C64: Wisconsin | D64: ü | J64: ü | N64: L | O64: ü
A65: Public Service Company of Colorado | B65: XEL | C65: Colorado | D65: ü | F65: ü | G65: ü | H65: ü | I65: ü | J65: ü | L65: ü | M65: ü | N65: L | P65: ü | Q65: ü
A66: Northern States Power Company - WI | B66: XEL | C66: Michigan | D66: ü | G66: ü | J66: ü
A67: Northern States Power Company - MN | B67: XEL | C67: Minnesota | D67: ü | E67: F | F67: ü | G67: ü | H67: ü | I67: ü | J67: ü | L67: ü | N67: L | O67: ü
A68: Southwestern Public Service Company | B68: XEL | C68: New Mexico | D68: ü | F68: ü | H68: ü | J68: ü | N68: F | P68: ü
A69: Northern States Power Company - MN | B69: XEL | C69: North Dakota | D69: ü | G69: ü | H69: ü | J69: ü | L69: ü | N69: F | Q69: ü
A70: Northern States Power Company - MN | B70: XEL | C70: South Dakota | D70: ü | E70: P | F70: ü | G70: ü | I70: ü | J70: ü | L70: ü | N70: L | P70: ü
A71: Southwestern Public Service Company | B71: XEL | C71: Texas | D71: ü | F71: ü | G71: ü | J71: ü | N71: L | P71: ü
A72: Northern States Power Company - WI | B72: XEL | C72: Wisconsin | D72: ü | J72: ü | N72: L | O72: ü | Q72: ü
D73: =COUNTA(D6:D72)-1 -> 66 | E73: =COUNTA(E6:E72) -> 32 | F73: =COUNTA(F6:F72) -> 30 | G73: =COUNTA(G6:G72) -> 56 | H73: =COUNTA(H6:H72) -> 35 | I73: =COUNTA(I6:I72) -> 38 | J73: =COUNTA(J6:J72) -> 67 | K73: =COUNTA(K6:K72) -> 4 | L73: =COUNTA(L6:L72) -> 24 | ... T73: =COUNTA(T6:T72) -> 1
C74: Notes: | D74: =D73/66 -> 1 | E74: =E73/67 -> 0.47761194 | F74: =F73/67 -> 0.44776119 | G74: =G73/67 -> 0.8358209 | H74: =H73/67 -> 0.52238806 | I74: =I73/67 -> 0.56716418 | J74: =J73/67 -> 1 | K74: =K73/67 -> 0.059701493 | L74: =L73/67 -> 0.35820896 | ... T74: =T73/67 -> 0.014925373
A75: A mechanism may cover one or more cost categories; therefore, designations may not indicate separate mechanisms for each category. Texas T&D utilities do not have retail obligation, thus do not need a purchased power clause | F75: [4] Recovers costs associated with renewable energy projects, Distributed Energy Resources, REC purchases, net metering, RPS expense, and renewable PPAs.
A76: [1] Full or partial decoupling (such as Straight-Fixed Variable rate design, weather normalization clauses, and recovery of lost revenues as a result of Energy Efficiency programs). | F76: [5] EPA upgrade costs, emissions control & allowance purchase costs, nuclear/coal plant decommissioning, and other costs to comply with state and federal environmental mandates.
A77: [2] Includes recovery of costs related to targeted new generation projects, infrastructure replacement, system integrity/hardening, Smart Grid, AMI metering, and other capital expenditures. | F77: [6] Pension expenses, bad debt costs, storm costs, vegetation management, RTO/Transmission Expense, capacity costs, transmission costs, government & franchise fees and taxes, economic development, and low income programs.
A78: [3] Utility-sponsored conservation, energy efficiency, load control, or other demand side management programs.
A79: Sources: Alternative Regulation/Incentive Plans: A State-by-State Overview, November 19, 2013; Regulatory Research Associates, Adjustment Clauses: A State-by-State Overview, September 28, 2018; Regulatory Research Associates, Rate Freezes: Their historical context and prevalence today, October 15, 2018; ACEEE Utility Business Model Database; Regulatory Research Associates Commission Profiles; SEC Form 10-Ks; Company Tariffs.

Sheet RBH-9 Capital Expenditures
A2: Planned Capital Expenditures / 2018 Net Plant
B28: Company | C28: Ticker | D28: 3-year CAPEX / Net Plant [1]
B30: ALLETE, Inc. | C30: ALE | D30: =VLOOKUP($C30,$H$30:$I$53,2,FALSE) -> 0.30403519 | H30: POR | I30: 0.19351494
B31: Alliant Energy Corporation | C31: LNT | D31: =VLOOKUP($C31,$H$30:$I$53,2,FALSE) -> 0.37959397 | H31: EVRG | I31: 0.20246412
B32: Ameren Corporation | C32: AEE | D32: =VLOOKUP($C32,$H$30:$I$53,2,FALSE) -> 0.35036716 | H32: OGE | I32: 0.20908455
B33: Avangrid, Inc. | C33: AGR | D33: =VLOOKUP($C33,$H$30:$I$53,2,FALSE) -> 0.29717684 | H33: NWE | I33: 0.21855543
B34: Black Hills Corporation | C34: BKH | D34: =VLOOKUP($C34,$H$30:$I$53,2,FALSE) -> 0.31903209 | H34: SO | I34: 0.24893035
B35: CMS Energy Corporation | C35: CMS | D35: =VLOOKUP($C35,$H$30:$I$53,2,FALSE) -> 0.37663025 | H35: ED | I35: 0.25622754
B36: Consolidated Edison, Inc. | C36: ED | D36: =VLOOKUP($C36,$H$30:$I$53,2,FALSE) -> 0.25622754 | H36: PNW | I36: 0.26509414
B37: DTE Energy Company | C37: DTE | D37: =VLOOKUP($C37,$H$30:$I$53,2,FALSE) -> 0.40180139 | H37: PNM | I37: 0.27496935
B38: Duke Energy Corporation | C38: DUK | D38: =VLOOKUP($C38,$H$30:$I$53,2,FALSE) -> 0.3111713 | H38: EE | I38: 0.28399837
B39: El Paso Electric Company | C39: EE | D39: =VLOOKUP($C39,$H$30:$I$53,2,FALSE) -> 0.28399837 | H39: HE | I39: 0.28477207
B40: Evergy, Inc | C40: EVRG | D40: =VLOOKUP($C40,$H$30:$I$53,2,FALSE) -> 0.20246412 | H40: AGR | I40: 0.29717684
B41: Eversource Energy | C41: ES | D41: =VLOOKUP($C41,$H$30:$I$53,2,FALSE) -> 0.33350365 | H41: ALE | I41: 0.30403519
... B52: Xcel Energy Inc. | C52: XEL | D52: =VLOOKUP($C52,$H$30:$I$53,2,FALSE) -> 0.31468661 | H52: NEE | I52: 0.42710851
H53: OTTR | I53: 0.46049428
B54: Median | D54: =MEDIAN(D30:D52) -> 0.30403519
B56: AEP Texas | D56: 0.42185702
B60: Notes:
B61: [1] Sources: Value Line; American Electric Power Company, Inc. SEC Form 10-K (Dec 31, 2018).

Sheet RBH-10 Capital Structure
B1: Proxy Group Capital Structure | N1: Proxy Group Capital Structure
D3: % Common Equity | P3: % Long-Term Debt
B4: Company | C4: Ticker | D4: 2018Q3 | E4: 2018Q2 | F4: 2018Q1 | G4: 2017Q4 | H4: 2017Q3 | I4: 2017Q2 | J4: 2017Q1 | K4: 2016Q4 | L4: Average | N4: Company | O4: Ticker | P4: 2018Q3 | Q4: 2018Q2 | R4: 2018Q1 | S4: 2017Q4 | T4: 2017Q3 | U4: 2017Q2 | V4: 2017Q1 | W4: 2016Q4 | X4: Average
B5: ALLETE, Inc. | C5: ALE | D5: =AVERAGEIF($C$34:$C$87,$C5,D$34:D$87) -> 0.58501785 | E5: =AVERAGEIF($C$34:$C$87,$C5,E$34:E$87) -> 0.58836391 | F5: =AVERAGEIF($C$34:$C$87,$C5,F$34:F$87) -> 0.63086801 | G5: =AVERAGEIF($C$34:$C$87,$C5,G$34:G$87) -> 0.62513431 | H5: =AVERAGEIF($C$34:$C$87,$C5,H$34:H$87) -> 0.61029354 | I5: =AVERAGEIF($C$34:$C$87,$C5,I$34:I$87) -> 0.60621298 | J5: =AVERAGEIF($C$34:$C$87,$C5,J$34:J$87) -> 0.60280394 | K5: =AVERAGEIF($C$34:$C$87,$C5,K$34:K$87) -> 0.59022914 | L5: =AVERAGE(D5:K5) -> 0.60486546 | N5: =B5 -> ALLETE, Inc. | O5: =C5 -> ALE | P5: =AVERAGEIF($C$34:$C$87,$C5,P$34:P$87) -> 0.41498215 | Q5: =AVERAGEIF($C$34:$C$87,$C5,Q$34:Q$87) -> 0.41163609 | R5: =AVERAGEIF($C$34:$C$87,$C5,R$34:R$87) -> 0.36913199 | S5: =AVERAGEIF($C$34:$C$87,$C5,S$34:S$87) -> 0.37486569 | T5: =AVERAGEIF($C$34:$C$87,$C5,T$34:T$87) -> 0.38970646 | U5: =AVERAGEIF($C$34:$C$87,$C5,U$34:U$87) -> 0.39378702 | V5: =AVERAGEIF($C$34:$C$87,$C5,V$34:V$87) -> 0.39719606 | W5: =AVERAGEIF($C$34:$C$87,$C5,W$34:W$87) -> 0.40977086 | X5: =AVERAGE(P5:W5) -> 0.39513454
B6: Alliant Energy Corporation | C6: LNT | D6: =AVERAGEIF($C$34:$C$87,$C6,D$34:D$87) -> 0.51131001 | E6: =AVERAGEIF($C$34:$C$87,$C6,E$34:E$87) -> 0.50995695 | F6: =AVERAGEIF($C$34:$C$87,$C6,F$34:F$87) -> 0.49744906 | G6: =AVERAGEIF($C$34:$C$87,$C6,G$34:G$87) -> 0.49767507 | H6: =AVERAGEIF($C$34:$C$87,$C6,H$34:H$87) -> 0.52088947 | I6: =AVERAGEIF($C$34:$C$87,$C6,I$34:I$87) -> 0.51226961 | J6: =AVERAGEIF($C$34:$C$87,$C6,J$34:J$87) -> 0.50840922 | K6: =AVERAGEIF($C$34:$C$87,$C6,K$34:K$87) -> 0.50726225 | L6: =AVERAGE(D6:K6) -> 0.5081527 | N6: =B6 -> Alliant Energy Corporation | O6: =C6 -> LNT | P6: =AVERAGEIF($C$34:$C$87,$C6,P$34:P$87) -> 0.48868999 | Q6: =AVERAGEIF($C$34:$C$87,$C6,Q$34:Q$87) -> 0.49004305 | R6: =AVERAGEIF($C$34:$C$87,$C6,R$34:R$87) -> 0.50255094 | S6: =AVERAGEIF($C$34:$C$87,$C6,S$34:S$87) -> 0.50232493 | T6: =AVERAGEIF($C$34:$C$87,$C6,T$34:T$87) -> 0.47911053 | U6: =AVERAGEIF($C$34:$C$87,$C6,U$34:U$87) -> 0.48773039 | V6: =AVERAGEIF($C$34:$C$87,$C6,V$34:V$87) -> 0.49159078 | W6: =AVERAGEIF($C$34:$C$87,$C6,W$34:W$87) -> 0.49273775 | X6: =AVERAGE(P6:W6) -> 0.4918473
B7: Ameren Corporation | C7: AEE | D7: =AVERAGEIF($C$34:$C$87,$C7,D$34:D$87) -> 0.53222044 | E7: =AVERAGEIF($C$34:$C$87,$C7,E$34:E$87) -> 0.52005448 | F7: =AVERAGEIF($C$34:$C$87,$C7,F$34:F$87) -> 0.53041818 | G7: =AVERAGEIF($C$34:$C$87,$C7,G$34:G$87) -> 0.52647563 | H7: =AVERAGEIF($C$34:$C$87,$C7,H$34:H$87) -> 0.53562408 | I7: =AVERAGEIF($C$34:$C$87,$C7,I$34:I$87) -> 0.53114762 | J7: =AVERAGEIF($C$34:$C$87,$C7,J$34:J$87) -> 0.52771716 | K7: =AVERAGEIF($C$34:$C$87,$C7,K$34:K$87) -> 0.5261993 | L7: =AVERAGE(D7:K7) -> 0.52873211 | N7: =B7 -> Ameren Corporation | O7: =C7 -> AEE | P7: =AVERAGEIF($C$34:$C$87,$C7,P$34:P$87) -> 0.46777956 | Q7: =AVERAGEIF($C$34:$C$87,$C7,Q$34:Q$87) -> 0.47994552 | R7: =AVERAGEIF($C$34:$C$87,$C7,R$34:R$87) -> 0.46958182 | S7: =AVERAGEIF($C$34:$C$87,$C7,S$34:S$87) -> 0.47352437 | T7: =AVERAGEIF($C$34:$C$87,$C7,T$34:T$87) -> 0.46437592 | U7: =AVERAGEIF($C$34:$C$87,$C7,U$34:U$87) -> 0.46885238 | V7: =AVERAGEIF($C$34:$C$87,$C7,V$34:V$87) -> 0.47228284 | W7: =AVERAGEIF($C$34:$C$87,$C7,W$34:W$87) -> 0.4738007 | X7: =AVERAGE(P7:W7) -> 0.47126789
B8: Avangrid, Inc. | C8: AGR | D8: =AVERAGEIF($C$34:$C$87,$C8,D$34:D$87) -> 0.56128108 | E8: =AVERAGEIF($C$34:$C$87,$C8,E$34:E$87) -> 0.5493108 | F8: =AVERAGEIF($C$34:$C$87,$C8,F$34:F$87) -> 0.56547108 | G8: =AVERAGEIF($C$34:$C$87,$C8,G$34:G$87) -> 0.55686623 | H8: =AVERAGEIF($C$34:$C$87,$C8,H$34:H$87) -> 0.53882178 | I8: =AVERAGEIF($C$34:$C$87,$C8,I$34:I$87) -> 0.5353735 | J8: =AVERAGEIF($C$34:$C$87,$C8,J$34:J$87) -> 0.55663531 | K8: =AVERAGEIF($C$34:$C$87,$C8,K$34:K$87) -> 0.54946627 | L8: =AVERAGE(D8:K8) -> 0.55165326 | N8: =B8 -> Avangrid, Inc. | O8: =C8 -> AGR | P8: =AVERAGEIF($C$34:$C$87,$C8,P$34:P$87) -> 0.43871892 | Q8: =AVERAGEIF($C$34:$C$87,$C8,Q$34:Q$87) -> 0.4506892 | R8: =AVERAGEIF($C$34:$C$87,$C8,R$34:R$87) -> 0.43452892 | S8: =AVERAGEIF($C$34:$C$87,$C8,S$34:S$87) -> 0.44313377 | T8: =AVERAGEIF($C$34:$C$87,$C8,T$34:T$87) -> 0.46117822 | U8: =AVERAGEIF($C$34:$C$87,$C8,U$34:U$87) -> 0.4646265 | V8: =AVERAGEIF($C$34:$C$87,$C8,V$34:V$87) -> 0.44336469 | W8: =AVERAGEIF($C$34:$C$87,$C8,W$34:W$87) -> 0.45053373 | X8: =AVERAGE(P8:W8) -> 0.44834674
B9: Black Hills Corporation | C9: BKH | D9: =AVERAGEIF($C$34:$C$87,$C9,D$34:D$87) -> 0.53196016 | E9: =AVERAGEIF($C$34:$C$87,$C9,E$34:E$87) -> 0.53824666 | F9: =AVERAGEIF($C$34:$C$87,$C9,F$34:F$87) -> 0.53790355 | G9: =AVERAGEIF($C$34:$C$87,$C9,G$34:G$87) -> 0.54396946 | H9: =AVERAGEIF($C$34:$C$87,$C9,H$34:H$87) -> 0.54753758 | I9: =AVERAGEIF($C$34:$C$87,$C9,I$34:I$87) -> 0.53843877 | J9: =AVERAGEIF($C$34:$C$87,$C9,J$34:J$87) -> 0.53202771 | K9: =AVERAGEIF($C$34:$C$87,$C9,K$34:K$87) -> 0.52809001 | L9: =AVERAGE(D9:K9) -> 0.53727174 | N9: =B9 -> Black Hills Corporation | O9: =C9 -> BKH | P9: =AVERAGEIF($C$34:$C$87,$C9,P$34:P$87) -> 0.46803984 | Q9: =AVERAGEIF($C$34:$C$87,$C9,Q$34:Q$87) -> 0.46175334 | R9: =AVERAGEIF($C$34:$C$87,$C9,R$34:R$87) -> 0.46209645 | S9: =AVERAGEIF($C$34:$C$87,$C9,S$34:S$87) -> 0.45603054 | T9: =AVERAGEIF($C$34:$C$87,$C9,T$34:T$87) -> 0.45246242 | U9: =AVERAGEIF($C$34:$C$87,$C9,U$34:U$87) -> 0.46156123 | V9: =AVERAGEIF($C$34:$C$87,$C9,V$34:V$87) -> 0.46797229 | W9: =AVERAGEIF($C$34:$C$87,$C9,W$34:W$87) -> 0.47190999 | X9: =AVERAGE(P9:W9) -> 0.46272826
B10: CMS Energy Corporation | C10: CMS | D10: =AVERAGEIF($C$34:$C$87,$C10,D$34:D$87) -> 0.53013314 | E10: =AVERAGEIF($C$34:$C$87,$C10,E$34:E$87) -> 0.52858695 | F10: =AVERAGEIF($C$34:$C$87,$C10,F$34:F$87) -> 0.53130257 | G10: =AVERAGEIF($C$34:$C$87,$C10,G$34:G$87) -> 0.52252476 | H10: =AVERAGEIF($C$34:$C$87,$C10,H$34:H$87) -> 0.53254723 | I10: =AVERAGEIF($C$34:$C$87,$C10,I$34:I$87) -> 0.5297486 | J10: =AVERAGEIF($C$34:$C$87,$C10,J$34:J$87) -> 0.52096551 | K10: =AVERAGEIF($C$34:$C$87,$C10,K$34:K$87) -> 0.51237359 | L10: =AVERAGE(D10:K10) -> 0.52602279 | N10: =B10 -> CMS Energy Corporation | O10: =C10 -> CMS | P10: =AVERAGEIF($C$34:$C$87,$C10,P$34:P$87) -> 0.46986686 | Q10: =AVERAGEIF($C$34:$C$87,$C10,Q$34:Q$87) -> 0.47141305 | R10: =AVERAGEIF($C$34:$C$87,$C10,R$34:R$87) -> 0.46869743 | S10: =AVERAGEIF($C$34:$C$87,$C10,S$34:S$87) -> 0.47747524 | T10: =AVERAGEIF($C$34:$C$87,$C10,T$34:T$87) -> 0.46745277 | U10: =AVERAGEIF($C$34:$C$87,$C10,U$34:U$87) -> 0.4702514 | V10: =AVERAGEIF($C$34:$C$87,$C10,V$34:V$87) -> 0.47903449 | W10: =AVERAGEIF($C$34:$C$87,$C10,W$34:W$87) -> 0.48762641 | X10: =AVERAGE(P10:W10) -> 0.47397721
B11: Consolidated Edison, Inc. | C11: ED | D11: =AVERAGEIF($C$34:$C$87,$C11,D$34:D$87) -> 0.48383914 | E11: =AVERAGEIF($C$34:$C$87,$C11,E$34:E$87) -> 0.48730526 | F11: =AVERAGEIF($C$34:$C$87,$C11,F$34:F$87) -> 0.4974654 | G11: =AVERAGEIF($C$34:$C$87,$C11,G$34:G$87) -> 0.49234426 | H11: =AVERAGEIF($C$34:$C$87,$C11,H$34:H$87) -> 0.49872827 | I11: =AVERAGEIF($C$34:$C$87,$C11,I$34:I$87) -> 0.49192049 | J11: =AVERAGEIF($C$34:$C$87,$C11,J$34:J$87) -> 0.49826868 | K11: =AVERAGEIF($C$34:$C$87,$C11,K$34:K$87) -> 0.49386734 | L11: =AVERAGE(D11:K11) -> 0.49296735 | N11: =B11 -> Consolidated Edison, Inc. | O11: =C11 -> ED | P11: =AVERAGEIF($C$34:$C$87,$C11,P$34:P$87) -> 0.51616086 | Q11: =AVERAGEIF($C$34:$C$87,$C11,Q$34:Q$87) -> 0.51269474 | R11: =AVERAGEIF($C$34:$C$87,$C11,R$34:R$87) -> 0.5025346 | S11: =AVERAGEIF($C$34:$C$87,$C11,S$34:S$87) -> 0.50765574 | T11: =AVERAGEIF($C$34:$C$87,$C11,T$34:T$87) -> 0.50127173 | U11: =AVERAGEIF($C$34:$C$87,$C11,U$34:U$87) -> 0.50807951 | V11: =AVERAGEIF($C$34:$C$87,$C11,V$34:V$87) -> 0.50173132 | W11: =AVERAGEIF($C$34:$C$87,$C11,W$34:W$87) -> 0.50613266 | X11: =AVERAGE(P11:W11) -> 0.50703265
B12: DTE Energy Company | C12: DTE | D12: =AVERAGEIF($C$34:$C$87,$C12,D$34:D$87) -> 0.49965418 | E12: =AVERAGEIF($C$34:$C$87,$C12,E$34:E$87) -> 0.49227751 | F12: =AVERAGEIF($C$34:$C$87,$C12,F$34:F$87) -> 0.51117751 | G12: =AVERAGEIF($C$34:$C$87,$C12,G$34:G$87) -> 0.51021485 | H12: =AVERAGEIF($C$34:$C$87,$C12,H$34:H$87) -> 0.50496839 | I12: =AVERAGEIF($C$34:$C$87,$C12,I$34:I$87) -> 0.50625425 | J12: =AVERAGEIF($C$34:$C$87,$C12,J$34:J$87) -> 0.50498449 | K12: =AVERAGEIF($C$34:$C$87,$C12,K$34:K$87) -> 0.50502143 | L12: =AVERAGE(D12:K12) -> 0.50431908 | N12: =B12 -> DTE Energy Company | O12: =C12 -> DTE | P12: =AVERAGEIF($C$34:$C$87,$C12,P$34:P$87) -> 0.50034582 | Q12: =AVERAGEIF($C$34:$C$87,$C12,Q$34:Q$87) -> 0.50772249 | R12: =AVERAGEIF($C$34:$C$87,$C12,R$34:R$87) -> 0.48882249 | S12: =AVERAGEIF($C$34:$C$87,$C12,S$34:S$87) -> 0.48978515 | T12: =AVERAGEIF($C$34:$C$87,$C12,T$34:T$87) -> 0.49503161 | U12: =AVERAGEIF($C$34:$C$87,$C12,U$34:U$87) -> 0.49374575 | V12: =AVERAGEIF($C$34:$C$87,$C12,V$34:V$87) -> 0.49501551 | W12: =AVERAGEIF($C$34:$C$87,$C12,W$34:W$87) -> 0.49497857 | X12: =AVERAGE(P12:W12) -> 0.49568092
B13: Duke Energy Corporation | C13: DUK | D13: =AVERAGEIF($C$34:$C$87,$C13,D$34:D$87) -> 0.55025439 | E13: =AVERAGEIF($C$34:$C$87,$C13,E$34:E$87) -> 0.5494026 | F13: =AVERAGEIF($C$34:$C$87,$C13,F$34:F$87) -> 0.54461778 | G13: =AVERAGEIF($C$34:$C$87,$C13,G$34:G$87) -> 0.54299426 | H13: =AVERAGEIF($C$34:$C$87,$C13,H$34:H$87) -> 0.53779827 | I13: =AVERAGEIF($C$34:$C$87,$C13,I$34:I$87) -> 0.54624884 | J13: =AVERAGEIF($C$34:$C$87,$C13,J$34:J$87) -> 0.54367753 | K13: =AVERAGEIF($C$34:$C$87,$C13,K$34:K$87) -> 0.54656217 | L13: =AVERAGE(D13:K13) -> 0.54519448 | N13: =B13 -> Duke Energy Corporation | O13: =C13 -> DUK | P13: =AVERAGEIF($C$34:$C$87,$C13,P$34:P$87) -> 0.44974561 | Q13: =AVERAGEIF($C$34:$C$87,$C13,Q$34:Q$87) -> 0.4505974 | R13: =AVERAGEIF($C$34:$C$87,$C13,R$34:R$87) -> 0.45538222 | S13: =AVERAGEIF($C$34:$C$87,$C13,S$34:S$87) -> 0.45700574 | T13: =AVERAGEIF($C$34:$C$87,$C13,T$34:T$87) -> 0.46220173 | U13: =AVERAGEIF($C$34:$C$87,$C13,U$34:U$87) -> 0.45375116 | V13: =AVERAGEIF($C$34:$C$87,$C13,V$34:V$87) -> 0.45632247 | W13: =AVERAGEIF($C$34:$C$87,$C13,W$34:W$87) -> 0.45343783 | X13: =AVERAGE(P13:W13) -> 0.45480552
B14: El Paso Electric Company | C14: EE | D14: =AVERAGEIF($C$34:$C$87,$C14,D$34:D$87) -> 0.48570705 | E14: =AVERAGEIF($C$34:$C$87,$C14,E$34:E$87) -> 0.47323613 | F14: =AVERAGEIF($C$34:$C$87,$C14,F$34:F$87) -> 0.4946215 | G14: =AVERAGEIF($C$34:$C$87,$C14,G$34:G$87) -> 0.49947086 | H14: =AVERAGEIF($C$34:$C$87,$C14,H$34:H$87) -> 0.49806459 | I14: =AVERAGEIF($C$34:$C$87,$C14,I$34:I$87) -> 0.4800545 | J14: =AVERAGEIF($C$34:$C$87,$C14,J$34:J$87) -> 0.47479256 | K14: =AVERAGEIF($C$34:$C$87,$C14,K$34:K$87) -> 0.47728499 | L14: =AVERAGE(D14:K14) -> 0.48540402 | N14: =B14 -> El Paso Electric Company | O14: =C14 -> EE | P14: =AVERAGEIF($C$34:$C$87,$C14,P$34:P$87) -> 0.51429295 | Q14: =AVERAGEIF($C$34:$C$87,$C14,Q$34:Q$87) -> 0.52676387 | R14: =AVERAGEIF($C$34:$C$87,$C14,R$34:R$87) -> 0.5053785 | S14: =AVERAGEIF($C$34:$C$87,$C14,S$34:S$87) -> 0.50052914 | T14: =AVERAGEIF($C$34:$C$87,$C14,T$34:T$87) -> 0.50193541 | U14: =AVERAGEIF($C$34:$C$87,$C14,U$34:U$87) -> 0.5199455 | V14: =AVERAGEIF($C$34:$C$87,$C14,V$34:V$87) -> 0.52520744 | W14: =AVERAGEIF($C$34:$C$87,$C14,W$34:W$87) -> 0.52271501 | X14: =AVERAGE(P14:W14) -> 0.51459598
B15: Evergy, Inc | C15: EVRG | D15: =AVERAGEIF($C$34:$C$87,$C15,D$34:D$87) -> 0.59862423 | E15: =AVERAGEIF($C$34:$C$87,$C15,E$34:E$87) -> 0.58510261 | F15: =AVERAGEIF($C$34:$C$87,$C15,F$34:F$87) -> 0.58730507 | G15: =AVERAGEIF($C$34:$C$87,$C15,G$34:G$87) -> 0.58617099 | H15: =AVERAGEIF($C$34:$C$87,$C15,H$34:H$87) -> 0.59410256 | I15: =AVERAGEIF($C$34:$C$87,$C15,I$34:I$87) -> 0.58740904 | J15: =AVERAGEIF($C$34:$C$87,$C15,J$34:J$87) -> 0.58748121 | K15: =AVERAGEIF($C$34:$C$87,$C15,K$34:K$87) -> 0.59282157 | L15: =AVERAGE(D15:K15) -> 0.58987716 | N15: =B15 -> Evergy, Inc | O15: =C15 -> EVRG | P15: =AVERAGEIF($C$34:$C$87,$C15,P$34:P$87) -> 0.40137577 | Q15: =AVERAGEIF($C$34:$C$87,$C15,Q$34:Q$87) -> 0.41489739 | R15: =AVERAGEIF($C$34:$C$87,$C15,R$34:R$87) -> 0.41269493 | S15: =AVERAGEIF($C$34:$C$87,$C15,S$34:S$87) -> 0.41382901 | T15: =AVERAGEIF($C$34:$C$87,$C15,T$34:T$87) -> 0.40589744 | U15: =AVERAGEIF($C$34:$C$87,$C15,U$34:U$87) -> 0.41259096 | V15: =AVERAGEIF($C$34:$C$87,$C15,V$34:V$87) -> 0.41251879 | W15: =AVERAGEIF($C$34:$C$87,$C15,W$34:W$87) -> 0.40717843 | X15: =AVERAGE(P15:W15) -> 0.41012284
B16: Eversource Energy | C16: ES | D16: =AVERAGEIF($C$34:$C$87,$C16,D$34:D$87) -> 0.5103303 | E16: =AVERAGEIF($C$34:$C$87,$C16,E$34:E$87) -> 0.50139608 | F16: =AVERAGEIF($C$34:$C$87,$C16,F$34:F$87) -> 0.54053016 | G16: =AVERAGEIF($C$34:$C$87,$C16,G$34:G$87) -> 0.54598868 | H16: =AVERAGEIF($C$34:$C$87,$C16,H$34:H$87) -> 0.55160769 | I16: =AVERAGEIF($C$34:$C$87,$C16,I$34:I$87) -> 0.54822475 | J16: =AVERAGEIF($C$34:$C$87,$C16,J$34:J$87) -> 0.55444741 | K16: =AVERAGEIF($C$34:$C$87,$C16,K$34:K$87) -> 0.55508533 | L16: =AVERAGE(D16:K16) -> 0.5384513 | N16: =B16 -> Eversource Energy | O16: =C16 -> ES | P16: =AVERAGEIF($C$34:$C$87,$C16,P$34:P$87) -> 0.4896697 | Q16: =AVERAGEIF($C$34:$C$87,$C16,Q$34:Q$87) -> 0.49860392 | R16: =AVERAGEIF($C$34:$C$87,$C16,R$34:R$87) -> 0.45946984 | S16: =AVERAGEIF($C$34:$C$87,$C16,S$34:S$87) -> 0.45401132 | T16: =AVERAGEIF($C$34:$C$87,$C16,T$34:T$87) -> 0.44839231 | U16: =AVERAGEIF($C$34:$C$87,$C16,U$34:U$87) -> 0.45177525 | V16: =AVERAGEIF($C$34:$C$87,$C16,V$34:V$87) -> 0.44555259 | W16: =AVERAGEIF($C$34:$C$87,$C16,W$34:W$87) -> 0.44491467 | X16: =AVERAGE(P16:W16) -> 0.4615487
... B27: Xcel Energy Inc. | C27: XEL | D27: =AVERAGEIF($C$34:$C$87,$C27,D$34:D$87) -> 0.53365011 | E27: =AVERAGEIF($C$34:$C$87,$C27,E$34:E$87) -> 0.53628287 | F27: =AVERAGEIF($C$34:$C$87,$C27,F$34:F$87) -> 0.54148118 | G27: =AVERAGEIF($C$34:$C$87,$C27,G$34:G$87) -> 0.53947356 | H27: =AVERAGEIF($C$34:$C$87,$C27,H$34:H$87) -> 0.5392922 | I27: =AVERAGEIF($C$34:$C$87,$C27,I$34:I$87) -> 0.54370902 | J27: =AVERAGEIF($C$34:$C$87,$C27,J$34:J$87) -> 0.54940489 | K27: =AVERAGEIF($C$34:$C$87,$C27,K$34:K$87) -> 0.54370076 | L27: =AVERAGE(D27:K27) -> 0.54087432 | N27: =B27 -> Xcel Energy Inc. | O27: =C27 -> XEL | P27: =AVERAGEIF($C$34:$C$87,$C27,P$34:P$87) -> 0.46634989 | Q27: =AVERAGEIF($C$34:$C$87,$C27,Q$34:Q$87) -> 0.46371713 | R27: =AVERAGEIF($C$34:$C$87,$C27,R$34:R$87) -> 0.45851882 | S27: =AVERAGEIF($C$34:$C$87,$C27,S$34:S$87) -> 0.46052644 | T27: =AVERAGEIF($C$34:$C$87,$C27,T$34:T$87) -> 0.4607078 | U27: =AVERAGEIF($C$34:$C$87,$C27,U$34:U$87) -> 0.45629098 | V27: =AVERAGEIF($C$34:$C$87,$C27,V$34:V$87) -> 0.45059511 | W27: =AVERAGEIF($C$34:$C$87,$C27,W$34:W$87) -> 0.45629924 | X27: =AVERAGE(P27:W27) -> 0.45912568
B28: Mean | D28: =AVERAGE(D5:D27) -> 0.53442383 | E28: =AVERAGE(E5:E27) -> 0.52915008 | F28: =AVERAGE(F5:F27) -> 0.5367765 | G28: =AVERAGE(G5:G27) -> 0.5339826 | H28: =AVERAGE(H5:H27) -> 0.53828763 | I28: =AVERAGE(I5:I27) -> 0.53431016 | J28: =AVERAGE(J5:J27) -> 0.5345098 | K28: =AVERAGE(K5:K27) -> 0.53487158 | L28: =AVERAGE(L5:L27) -> 0.53453902 | N28: Mean | P28: =AVERAGE(P5:P27) -> 0.46557617 | Q28: =AVERAGE(Q5:Q27) -> 0.47084992 | R28: =AVERAGE(R5:R27) -> 0.4632235 | S28: =AVERAGE(S5:S27) -> 0.4660174 | T28: =AVERAGE(T5:T27) -> 0.46171237 | U28: =AVERAGE(U5:U27) -> 0.46568984 | V28: =AVERAGE(V5:V27) -> 0.4654902 | W28: =AVERAGE(W5:W27) -> 0.46512842 | X28: =AVERAGE(X5:X27) -> 0.46546098
B31: Operating Company Capital Structure | N31: Operating Company Capital Structure
D32: % Common Equity | P32: % Long-Term Debt
B33: Operating Company | C33: Parent | D33: =D4 -> 2018Q3 | E33: =E4 -> 2018Q2 | F33: =F4 -> 2018Q1 | G33: =G4 -> 2017Q4 | H33: =H4 -> 2017Q3 | I33: =I4 -> 2017Q2 | J33: =J4 -> 2017Q1 | K33: =K4 -> 2016Q4 | L33: Average | N33: Operating Company | O33: Parent | P33: =P4 -> 2018Q3 | Q33: =Q4 -> 2018Q2 | R33: =R4 -> 2018Q1 | S33: =S4 -> 2017Q4 | T33: =T4 -> 2017Q3 | U33: =U4 -> 2017Q2 | V33: =V4 -> 2017Q1 | W33: =W4 -> 2016Q4 | X33: Average
B34: ALLETE (Minnesota Power) | C34: ALE | D34: 0.60426865 | E34: 0.60333516 | F34: 0.60378433 | G34: 0.60037747 | H34: 0.5973149 | I34: 0.59162646 | J34: 0.58712311 | K34: 0.56921131 | L34: =AVERAGE(D34:K34) -> 0.59463017 | N34: =B34 -> ALLETE (Minnesota Power) | O34: =C34 -> ALE | P34: 0.39573135 | Q34: 0.39666484 | R34: 0.39621567 | S34: 0.39962253 | T34: 0.4026851 | U34: 0.40837354 | V34: 0.41287689 | W34: 0.43078869 | X34: =AVERAGE(P34:W34) -> 0.40536983
B35: Superior Water, Light and Power Company | C35: ALE | D35: 0.56576705 | E35: 0.57339266 | F35: 0.65795169 | G35: 0.64989115 | H35: 0.62327219 | I35: 0.62079949 | J35: 0.61848476 | K35: 0.61124698 | L35: =AVERAGE(D35:K35) -> 0.61510075 | N35: =B35 -> Superior Water, Light and Power Company | O35: =C35 -> ALE | P35: 0.43423295 | Q35: 0.42660734 | R35: 0.34204831 | S35: 0.35010885 | T35: 0.37672781 | U35: 0.37920051 | V35: 0.38151524 | W35: 0.38875302 | X35: =AVERAGE(P35:W35) -> 0.38489925
B36: Interstate Power and Light Company | C36: LNT | D36: 0.49637563 | E36: 0.50469817 | F36: 0.49918076 | G36: 0.50307669 | H36: 0.51792855 | I36: 0.50894717 | J36: 0.50227845 | K36: 0.50235903 | L36: =AVERAGE(D36:K36) -> 0.50435556 | N36: =B36 -> Interstate Power and Light Company | O36: =C36 -> LNT | P36: 0.50362437 | Q36: 0.49530183 | R36: 0.50081924 | S36: 0.49692331 | T36: 0.48207145 | U36: 0.49105283 | V36: 0.49772155 | W36: 0.49764097 | X36: =AVERAGE(P36:W36) -> 0.49564444
B37: Wisconsin Power and Light Company | C37: LNT | D37: 0.5262444 | E37: 0.51521572 | F37: 0.49571736 | G37: 0.49227344 | H37: 0.52385039 | I37: 0.51559205 | J37: 0.51453998 | K37: 0.51216547 | L37: =AVERAGE(D37:K37) -> 0.51194985 | N37: =B37 -> Wisconsin Power and Light Company | O37: =C37 -> LNT | P37: 0.4737556 | Q37: 0.48478428 | R37: 0.50428264 | S37: 0.50772656 | T37: 0.47614961 | U37: 0.48440795 | V37: 0.48546002 | W37: 0.48783453 | X37: =AVERAGE(P37:W37) -> 0.48805015
B38: Ameren Illinois Company | C38: AEE | D38: 0.53181619 | E38: 0.52735241 | F38: 0.54241064 | G38: 0.53378817 | H38: 0.5497997 | I38: 0.54546921 | J38: 0.54088943 | K38: 0.53436674 | L38: =AVERAGE(D38:K38) -> 0.53823656 | N38: =B38 -> Ameren Illinois Company | O38: =C38 -> AEE | P38: 0.46818381 | Q38: 0.47264759 | R38: 0.45758936 | S38: 0.46621183 | T38: 0.4502003 | U38: 0.45453079 | V38: 0.45911057 | W38: 0.46563326 | X38: =AVERAGE(P38:W38) -> 0.46176344
B39: Union Electric Company | C39: AEE | D39: 0.5326247 | E39: 0.51275656 | F39: 0.51842573 | G39: 0.51916309 | H39: 0.52144846 | I39: 0.51682603 | J39: 0.51454488 | K39: 0.51803185 | L39: =AVERAGE(D39:K39) -> 0.51922766 | N39: =B39 -> Union Electric Company | O39: =C39 -> AEE | P39: 0.4673753 | Q39: 0.48724344 | R39: 0.48157427 | S39: 0.48083691 | T39: 0.47855154 | U39: 0.48317397 | V39: 0.48545512 | W39: 0.48196815 | X39: =AVERAGE(P39:W39) -> 0.48077234
B40: Central Maine Power Company | C40: AGR | D40: 0.64170448 | E40: 0.63527308 | F40: 0.6417819 | G40: 0.63815062 | H40: 0.63971322 | I40: 0.6327061 | J40: 0.62835518 | K40: 0.6238816 | L40: =AVERAGE(D40:K40) -> 0.63519577 | N40: =B40 -> Central Maine Power Company | O40: =C40 -> AGR | P40: 0.35829552 | Q40: 0.36472692 | R40: 0.3582181 | S40: 0.36184938 | T40: 0.36028678 | U40: 0.3672939 | V40: 0.37164482 | W40: 0.3761184 | X40: =AVERAGE(P40:W40) -> 0.36480423
B41: New York State Electric & Gas Corporation | C41: AGR | D41: 0.53954218 | E41: 0.50990166 | F41: 0.54509563 | G41: 0.53299156 | H41: 0.48270863 | I41: 0.50243253 | J41: 0.49683286 | K41: 0.48838256 | L41: =AVERAGE(D41:K41) -> 0.51223595 | N41: =B41 -> New York State Electric & Gas Corporation | O41: =C41 -> AGR | P41: 0.46045782 | Q41: 0.49009834 | R41: 0.45490437 | S41: 0.46700844 | T41: 0.51729137 | U41: 0.49756747 | V41: 0.50316714 | W41: 0.51161744 | X41: =AVERAGE(P41:W41) -> 0.48776405
B42: Rochester Gas and Electric Corporation | C42: AGR | D42: 0.48161214 | E42: 0.47774186 | F42: 0.50801737 | G42: 0.49633924 | H42: 0.48939482 | I42: 0.48464968 | J42: 0.55252807 | K42: 0.54296685 | L42: =AVERAGE(D42:K42) -> 0.50415625 | N42: =B42 -> Rochester Gas and Electric Corporation | O42: =C42 -> AGR | P42: 0.51838786 | Q42: 0.52225814 | R42: 0.49198263 | S42: 0.50366076 | T42: 0.51060518 | U42: 0.51535032 | V42: 0.44747193 | W42: 0.45703315 | X42: =AVERAGE(P42:W42) -> 0.49584375
B43: United Illuminating Company | C43: AGR | D43: 0.5822655 | E43: 0.57432658 | F43: 0.56698942 | G43: 0.55998352 | H43: 0.54347046 | I43: 0.52170569 | J43: 0.54882515 | K43: 0.54263407 | L43: =AVERAGE(D43:K43) -> 0.55502505 | N43: =B43 -> United Illuminating Company | O43: =C43 -> AGR | P43: 0.4177345 | Q43: 0.42567342 | R43: 0.43301058 | S43: 0.44001648 | T43: 0.45652954 | U43: 0.47829431 | V43: 0.45117485 | W43: 0.45736593 | X43: =AVERAGE(P43:W43) -> 0.44497495
B44: Black Hills Colorado Electric Utility Company, LP | C44: BKH | D44: 0.5303728 | E44: 0.54854321 | F44: 0.54683112 | G44: 0.55691884 | H44: 0.54963591 | I44: 0.55005162 | J44: 0.53077826 | K44: 0.52197025 | L44: =AVERAGE(D44:K44) -> 0.54188775 | N44: =B44 -> Black Hills Colorado Electric Utility Company, LP | O44: =C44 -> BKH | P44: 0.4696272 | Q44: 0.45145679 | R44: 0.45316888 | S44: 0.44308116 | T44: 0.45036409 | U44: 0.44994838 | V44: 0.46922174 | W44: 0.47802975 | X44: =AVERAGE(P44:W44) -> 0.45811225
B45: Black Hills Power, Inc. | C45: BKH | D45: 0.53509493 | E45: 0.53297681 | F45: 0.53224334 | G45: 0.5349167 | H45: 0.56137501 | I45: 0.53259442 | J45: 0.53239684 | K45: 0.52880171 | L45: =AVERAGE(D45:K45) -> 0.53629997 | N45: =B45 -> Black Hills Power, Inc. | O45: =C45 -> BKH | P45: 0.46490507 | Q45: 0.46702319 | R45: 0.46775666 | S45: 0.4650833 | T45: 0.43862499 | U45: 0.46740558 | V45: 0.46760316 | W45: 0.47119829 | X45: =AVERAGE(P45:W45) -> 0.46370003
... B49: Orange and Rockland Utilities, Inc. | C49: ED | D49: 0.48441322 | E49: 0.50738787 | F49: 0.50831541 | G49: 0.50251023 | H49: 0.50273433 | I49: 0.49807383 | J49: 0.50003868 | K49: 0.49462981 | L49: =AVERAGE(D49:K49) -> 0.49976292 | N49: =B49 -> Orange and Rockland Utilities, Inc. | O49: =C49 -> ED | P49: 0.51558678 | Q49: 0.49261213 | R49: 0.49168459 | S49: 0.49748977 | T49: 0.49726567 | U49: 0.50192617 | V49: 0.49996132 | W49: 0.50537019 | X49: =AVERAGE(P49:W49) -> 0.50023708
B50: Rockland Electric Company | C50: ED | D50: NA | E50: NA | F50: NA | G50: NA | H50: NA | I50: NA | J50: NA | K50: NA | L50: NA | N50: =B50 -> Rockland Electric Company | O50: =C50 -> ED | P50: NA | Q50: NA | R50: NA | S50: NA | T50: NA | U50: NA | V50: NA | W50: NA | X50: NA
B51: DTE Electric Company | C51: DTE | D51: 0.49965418 | E51: 0.49227751 | F51: 0.51117751 | G51: 0.51021485 | H51: 0.50496839 | I51: 0.50625425 | J51: 0.50498449 | K51: 0.50502143 | L51: =AVERAGE(D51:K51) -> 0.50431908 | N51: =B51 -> DTE Electric Company | O51: =C51 -> DTE | P51: 0.50034582 | Q51: 0.50772249 | R51: 0.48882249 | S51: 0.48978515 | T51: 0.49503161 | U51: 0.49374575 | V51: 0.49501551 | W51: 0.49497857 | X51: =AVERAGE(P51:W51) -> 0.49568092
B52: Duke Energy Carolinas, LLC | C52: DUK | D52: 0.52641209 | E52: 0.52100792 | F52: 0.51700805 | G52: 0.52976011 | H52: 0.53978359 | I52: 0.53490176 | J52: 0.53322901 | K52: 0.52812277 | L52: =AVERAGE(D52:K52) -> 0.52877816 | N52: =B52 -> Duke Energy Carolinas, LLC | O52: =C52 -> DUK | P52: 0.47358791 | Q52: 0.47899208 | R52: 0.48299195 | S52: 0.47023989 | T52: 0.46021641 | U52: 0.46509824 | V52: 0.46677099 | W52: 0.47187723 | X52: =AVERAGE(P52:W52) -> 0.47122184
B53: Duke Energy Florida, LLC | C53: DUK | D53: 0.49652591 | E53: 0.48785824 | F53: 0.49924724 | G53: 0.49245745 | H53: 0.49455242 | I53: 0.47740664 | J53: 0.46950427 | K53: 0.50831211 | L53: =AVERAGE(D53:K53) -> 0.49073303 | N53: =B53 -> Duke Energy Florida, LLC | O53: =C53 -> DUK | P53: 0.50347409 | Q53: 0.51214176 | R53: 0.50075276 | S53: 0.50754255 | T53: 0.50544758 | U53: 0.52259336 | V53: 0.53049573 | W53: 0.49168789 | X53: =AVERAGE(P53:W53) -> 0.50926697
B54: Duke Energy Indiana, LLC | C54: DUK | D54: 0.5279347 | E54: 0.52644843 | F54: 0.525401 | G54: 0.51944374 | H54: 0.51705911 | I54: 0.51886997 | J54: 0.52153388 | K54: 0.5158711 | L54: =AVERAGE(D54:K54) -> 0.52157024 | N54: =B54 -> Duke Energy Indiana, LLC | O54: =C54 -> DUK | P54: 0.4720653 | Q54: 0.47355157 | R54: 0.474599 | S54: 0.48055626 | T54: 0.48294089 | U54: 0.48113003 | V54: 0.47846612 | W54: 0.4841289 | X54: =AVERAGE(P54:W54) -> 0.47842976
B55: Duke Energy Kentucky, Inc. | C55: DUK | D55: 0.56579708 | E55: 0.55789453 | F55: 0.5372278 | G55: 0.53114828 | H55: 0.50693204 | I55: 0.55740789 | J55: 0.55428743 | K55: 0.54736553 | L55: =AVERAGE(D55:K55) -> 0.54475757 | N55: =B55 -> Duke Energy Kentucky, Inc. | O55: =C55 -> DUK | P55: 0.43420292 | Q55: 0.44210547 | R55: 0.4627722 | S55: 0.46885172 | T55: 0.49306796 | U55: 0.44259211 | V55: 0.44571257 | W55: 0.45263447 | X55: =AVERAGE(P55:W55) -> 0.45524243
B56: Duke Energy Ohio, Inc. | C56: DUK | D56: 0.67725197 | E56: 0.67097449 | F56: 0.66059108 | G56: 0.66242246 | H56: 0.65786287 | I56: 0.65383523 | J56: 0.65356302 | K56: 0.66388695 | L56: =AVERAGE(D56:K56) -> 0.66254851 | N56: =B56 -> Duke Energy Ohio, Inc. | O56: =C56 -> DUK | P56: 0.32274803 | Q56: 0.32902551 | R56: 0.33940892 | S56: 0.33757754 | T56: 0.34213713 | U56: 0.34616477 | V56: 0.34643698 | W56: 0.33611305 | X56: =AVERAGE(P56:W56) -> 0.33745149
B57: Duke Energy Progress, LLC | C57: DUK | D57: 0.50760457 | E57: 0.53223197 | F57: 0.52823152 | G57: 0.52273351 | H57: 0.51059962 | I57: 0.53507153 | J57: 0.52994757 | K57: 0.51581454 | L57: =AVERAGE(D57:K57) -> 0.52277935 | N57: =B57 -> Duke Energy Progress, LLC | O57: =C57 -> DUK | P57: 0.49239543 | Q57: 0.46776803 | R57: 0.47176848 | S57: 0.47726649 | T57: 0.48940038 | U57: 0.46492847 | V57: 0.47005243 | W57: 0.48418546 | X57: =AVERAGE(P57:W57) -> 0.47722065
B58: El Paso Electric Company | C58: EE | D58: 0.48570705 | E58: 0.47323613 | F58: 0.4946215 | G58: 0.49947086 | H58: 0.49806459 | I58: 0.4800545 | J58: 0.47479256 | K58: 0.47728499 | L58: =AVERAGE(D58:K58) -> 0.48540402 | N58: =B58 -> El Paso Electric Company | O58: =C58 -> EE | P58: 0.51429295 | Q58: 0.52676387 | R58: 0.5053785 | S58: 0.50052914 | T58: 0.50193541 | U58: 0.5199455 | V58: 0.52520744 | W58: 0.52271501 | X58: =AVERAGE(P58:W58) -> 0.51459598
B59: Kansas City Power & Light Company | C59: EVRG | D59: 0.49504484 | E59: 0.4888467 | F59: 0.49247094 | G59: 0.49149826 | H59: 0.49421106 | I59: 0.48473918 | J59: 0.49189642 | K59: 0.49609791 | L59: =AVERAGE(D59:K59) -> 0.49185066 | N59: =B59 -> Kansas City Power & Light Company | O59: =C59 -> EVRG | P59: 0.50495516 | Q59: 0.5111533 | R59: 0.50752906 | S59: 0.50850174 | T59: 0.50578894 | U59: 0.51526082 | V59: 0.50810358 | W59: 0.50390209 | X59: =AVERAGE(P59:W59) -> 0.50814934
B60: Kansas Gas and Electric Company | C60: EVRG | D60: 0.74906084 | E60: 0.74448862 | F60: 0.74294157 | G60: 0.741795 | H60: 0.74211666 | I60: 0.7369266 | J60: 0.73488366 | K60: 0.73369025 | L60: =AVERAGE(D60:K60) -> 0.7407379 | N60: =B60 -> Kansas Gas and Electric Company | O60: =C60 -> EVRG | P60: 0.25093916 | Q60: 0.25551138 | R60: 0.25705843 | S60: 0.258205 | T60: 0.25788334 | U60: 0.2630734 | V60: 0.26511634 | W60: 0.26630975 | X60: =AVERAGE(P60:W60) -> 0.2592621
B61: KCP&L Greater Missouri Operations Company | C61: EVRG | D61: 0.55695486 | E61: 0.52029805 | F61: 0.52632836 | G61: 0.52399776 | H61: 0.55138645 | I61: 0.54573939 | J61: 0.54216025 | K61: 0.54466008 | L61: =AVERAGE(D61:K61) -> 0.53894065 | N61: =B61 -> KCP&L Greater Missouri Operations Company | O61: =C61 -> EVRG | P61: 0.44304514 | Q61: 0.47970195 | R61: 0.47367164 | S61: 0.47600224 | T61: 0.44861355 | U61: 0.45426061 | V61: 0.45783975 | W61: 0.45533992 | X61: =AVERAGE(P61:W61) -> 0.46105935
B62: Westar Energy (KPL) | C62: EVRG | D62: 0.59343637 | E62: 0.58677705 | F62: 0.58747943 | G62: 0.58739294 | H62: 0.58869606 | I62: 0.582231 | J62: 0.5809845 | K62: 0.59683803 | L62: =AVERAGE(D62:K62) -> 0.58797942 | N62: =B62 -> Westar Energy (KPL) | O62: =C62 -> EVRG | P62: 0.40656363 | Q62: 0.41322295 | R62: 0.41252057 | S62: 0.41260706 | T62: 0.41130394 | U62: 0.417769 | V62: 0.4190155 | W62: 0.40316197 | X62: =AVERAGE(P62:W62) -> 0.41202058
... B65: Public Service Company of New Hampshire | C65: ES | D65: 0.431105 | E65: 0.42058298 | F65: 0.57930399 | G65: 0.57299577 | H65: 0.5925997 | I65: 0.57054386 | J65: 0.56595223 | K65: 0.56310192 | L65: =AVERAGE(D65:K65) -> 0.53702318 | N65: =B65 -> Public Service Company of New Hampshire | O65: =C65 -> ES | P65: 0.568895 | Q65: 0.57941702 | R65: 0.42069601 | S65: 0.42700423 | T65: 0.4074003 | U65: 0.42945614 | V65: 0.43404777 | W65: 0.43689808 | X65: =AVERAGE(P65:W65) -> 0.46297682
B66: Western Massachusetts Electric Company | C66: ES | D66: NA | E66: NA | F66: NA | G66: 0.53431756 | H66: 0.55018047 | I66: 0.5471419 | J66: 0.54404957 | K66: 0.54106345 | L66: =AVERAGE(D66:K66) -> 0.54335059 | N66: =B66 -> Western Massachusetts Electric Company | O66: =C66 -> ES | P66: NA | Q66: NA | R66: NA | S66: 0.46568244 | T66: 0.44981953 | U66: 0.4528581 | V66: 0.45595043 | W66: 0.45893655 | X66: =AVERAGE(P66:W66) -> 0.45664941
B67: Hawaii Electric Light Company, Inc. | C67: HE | D67: NA | E67: NA | F67: NA | G67: NA | H67: NA | I67: NA | J67: NA | K67: NA | L67: NA | N67: =B67 -> Hawaii Electric Light Company, Inc. | O67: =C67 -> HE | P67: NA | Q67: NA | R67: NA | S67: NA | T67: NA | U67: NA | V67: NA | W67: NA | X67: NA
B68: Hawaiian Electric Company, Inc. | C68: HE | D68: 0.56093123 | E68: 0.5577977 | F68: 0.57437658 | G68: 0.5741816 | H68: 0.58108338 | I68: 0.57761155 | J68: 0.5771006 | K68: 0.57703106 | L68: =AVERAGE(D68:K68) -> 0.57251421 | N68: =B68 -> Hawaiian Electric Company, Inc. | O68: =C68 -> HE | P68: 0.43906877 | Q68: 0.4422023 | R68: 0.42562342 | S68: 0.4258184 | T68: 0.41891662 | U68: 0.42238845 | V68: 0.4228994 | W68: 0.42296894 | X68: =AVERAGE(P68:W68) -> 0.42748579
B69: Maui Electric Company, Limited | C69: HE | D69: NA | E69: NA | F69: NA | G69: NA | H69: NA | I69: NA | J69: NA | K69: NA | L69: NA | N69: =B69 -> Maui Electric Company, Limited | O69: =C69 -> HE | P69: NA | Q69: NA | R69: NA | S69: NA | T69: NA | U69: NA | V69: NA | W69: NA | X69: NA
B70: Florida Power & Light Company | C70: NEE | D70: 0.64777394 | E70: 0.60837478 | F70: 0.61225474 | G70: 0.59933548 | H70: 0.63002253 | I70: 0.6277916 | J70: 0.62050757 | K70: 0.62648763 | L70: =AVERAGE(D70:K70) -> 0.62156853 | N70: =B70 -> Florida Power & Light Company | O70: =C70 -> NEE | P70: 0.35222606 | Q70: 0.39162522 | R70: 0.38774526 | S70: 0.40066452 | T70: 0.36997747 | U70: 0.3722084 | V70: 0.37949243 | W70: 0.37351237 | X70: =AVERAGE(P70:W70) -> 0.37843147
B71: NorthWestern Corporation | C71: NWE | D71: 0.48361515 | E71: 0.48406961 | F71: 0.47476683 | G71: 0.49892915 | H71: 0.48861782 | I71: 0.48605899 | J71: 0.48614841 | K71: 0.48128344 | L71: =AVERAGE(D71:K71) -> 0.48543618 | N71: =B71 -> NorthWestern Corporation | O71: =C71 -> NWE | P71: 0.51638485 | Q71: 0.51593039 | R71: 0.52523317 | S71: 0.50107085 | T71: 0.51138218 | U71: 0.51394101 | V71: 0.51385159 | W71: 0.51871656 | X71: =AVERAGE(P71:W71) -> 0.51456382
B72: Oklahoma Gas and Electric Company | C72: OGE | D72: 0.53048488 | E72: 0.54247083 | F72: 0.53593436 | G72: 0.53362909 | H72: 0.53053474 | I72: 0.52753433 | J72: 0.53461013 | K72: 0.56089626 | L72: =AVERAGE(D72:K72) -> 0.53701183 | N72: =B72 -> Oklahoma Gas and Electric Company | O72: =C72 -> OGE | P72: 0.46951512 | Q72: 0.45752917 | R72: 0.46406564 | S72: 0.46637091 | T72: 0.46946526 | U72: 0.47246567 | V72: 0.46538987 | W72: 0.43910374 | X72: =AVERAGE(P72:W72) -> 0.46298817
B73: Otter Tail Power Company | C73: OTTR | D73: 0.5348964 | E73: 0.53106725 | F73: 0.5267213 | G73: 0.57342301 | H73: 0.57240031 | I73: 0.55309305 | J73: 0.55306477 | K73: 0.55057678 | L73: =AVERAGE(D73:K73) -> 0.54940536 | N73: =B73 -> Otter Tail Power Company | O73: =C73 -> OTTR | P73: 0.4651036 | Q73: 0.46893275 | R73: 0.4732787 | S73: 0.42657699 | T73: 0.42759969 | U73: 0.44690695 | V73: 0.44693523 | W73: 0.44942322 | X73: =AVERAGE(P73:W73) -> 0.45059464
B74: Arizona Public Service Company | C74: PNW | D74: 0.53681866 | E74: 0.53708218 | F74: 0.53180454 | G74: 0.53138444 | H74: 0.53047092 | I74: 0.53315385 | J74: 0.5320427 | K74: 0.54591378 | L74: =AVERAGE(D74:K74) -> 0.53483388 | N74: =B74 -> Arizona Public Service Company | O74: =C74 -> PNW | P74: 0.46318134 | Q74: 0.46291782 | R74: 0.46819546 | S74: 0.46861556 | T74: 0.46952908 | U74: 0.46684615 | V74: 0.4679573 | W74: 0.45408622 | X74: =AVERAGE(P74:W74) -> 0.46516612
B75: Public Service Company of New Mexico | C75: PNM | D75: 0.48006072 | E75: 0.46681548 | F75: 0.46202243 | G75: 0.46063492 | H75: 0.47584119 | I75: 0.46888844 | J75: 0.46375302 | K75: 0.46012752 | L75: =AVERAGE(D75:K75) -> 0.46726796 | N75: =B75 -> Public Service Company of New Mexico | O75: =C75 -> PNM | P75: 0.51993928 | Q75: 0.53318452 | R75: 0.53797757 | S75: 0.53936508 | T75: 0.52415881 | U75: 0.53111156 | V75: 0.53624698 | W75: 0.53987248 | X75: =AVERAGE(P75:W75) -> 0.53273204
B76: Portland General Electric Company | C76: POR | D76: 0.50510645 | E76: 0.5029346 | F76: 0.50135074 | G76: 0.49796729 | H76: 0.5017093 | I76: 0.50322726 | J76: 0.50276618 | K76: 0.49819353 | L76: =AVERAGE(D76:K76) -> 0.50165692 | N76: =B76 -> Portland General Electric Company | O76: =C76 -> POR | P76: 0.49489355 | Q76: 0.4970654 | R76: 0.49864926 | S76: 0.50203271 | T76: 0.4982907 | U76: 0.49677274 | V76: 0.49723382 | W76: 0.50180647 | X76: =AVERAGE(P76:W76) -> 0.49834308
B77: Alabama Power Company | C77: SO | D77: 0.4812837 | E77: 0.47513959 | F77: 0.48857348 | G77: 0.47071357 | H77: 0.47931615 | I77: 0.47248632 | J77: 0.47003939 | K77: 0.46972719 | L77: =AVERAGE(D77:K77) -> 0.47590992 | N77: =B77 -> Alabama Power Company | O77: =C77 -> SO | P77: 0.5187163 | Q77: 0.52486041 | R77: 0.51142652 | S77: 0.52928643 | T77: 0.52068385 | U77: 0.52751368 | V77: 0.52996061 | W77: 0.53027281 | X77: =AVERAGE(P77:W77) -> 0.52409008
B78: Georgia Power Company | C78: SO | D78: 0.57265197 | E78: 0.54969002 | F78: 0.53805263 | G78: 0.50064261 | H78: 0.5034682 | I78: 0.51547823 | J78: 0.50355587 | K78: 0.5163403 | L78: =AVERAGE(D78:K78) -> 0.52498498 | N78: =B78 -> Georgia Power Company | O78: =C78 -> SO | P78: 0.42734803 | Q78: 0.45030998 | R78: 0.46194737 | S78: 0.49935739 | T78: 0.4965318 | U78: 0.48452177 | V78: 0.49644413 | W78: 0.4836597 | X78: =AVERAGE(P78:W78) -> 0.47501502
B79: Gulf Power Company | C79: SO | D79: 0.55342935 | E79: 0.54896271 | F79: 0.54270253 | G79: 0.54188107 | H79: 0.54970191 | I79: 0.54413745 | J79: 0.58797332 | K79: 0.56163678 | L79: =AVERAGE(D79:K79) -> 0.55380314 | N79: =B79 -> Gulf Power Company | O79: =C79 -> SO | P79: 0.44657065 | Q79: 0.45103729 | R79: 0.45729747 | S79: 0.45811893 | T79: 0.45029809 | U79: 0.45586255 | V79: 0.41202668 | W79: 0.43836322 | X79: =AVERAGE(P79:W79) -> 0.44619686
B80: Mississippi Power Company | C80: SO | D80: 0.45275461 | E80: 0.43866085 | F80: 0.42995647 | G80: 0.39337696 | H80: 0.47316149 | I80: 0.46759276 | J80: 0.49497092 | K80: 0.49621822 | L80: =AVERAGE(D80:K80) -> 0.45583654 | N80: =B80 -> Mississippi Power Company | O80: =C80 -> SO | P80: 0.54724539 | Q80: 0.56133915 | R80: 0.57004353 | S80: 0.60662304 | T80: 0.52683851 | U80: 0.53240724 | V80: 0.50502908 | W80: 0.50378178 | X80: =AVERAGE(P80:W80) -> 0.54416346
B81: Upper Michigan Energy Resources Corporation | C81: WEC | D81: 0.55075159 | E81: 0.54532434 | F81: 0.70042659 | G81: 0.49849046 | H81: NA | I81: NA | J81: NA | K81: NA | L81: =AVERAGE(D81:K81) -> 0.57374825 | N81: =B81 -> Upper Michigan Energy Resources Corporation | O81: =C81 -> WEC | P81: 0.44924841 | Q81: 0.45467566 | R81: 0.29957341 | S81: 0.50150954 | T81: NA | U81: NA | V81: NA | W81: NA | X81: =AVERAGE(P81:W81) -> 0.42625175
B82: Wisconsin Electric Power Company | C82: WEC | D82: 0.592514 | E82: 0.5909489 | F82: 0.56465678 | G82: 0.55937836 | H82: 0.55967954 | I82: 0.55756028 | J82: 0.55581286 | K82: 0.56741249 | L82: =AVERAGE(D82:K82) -> 0.5684954 | N82: =B82 -> Wisconsin Electric Power Company | O82: =C82 -> WEC | P82: 0.407486 | Q82: 0.4090511 | R82: 0.43534322 | S82: 0.44062164 | T82: 0.44032046 | U82: 0.44243972 | V82: 0.44418714 | W82: 0.43258751 | X82: =AVERAGE(P82:W82) -> 0.4315046
B83: Wisconsin Public Service Corporation | C83: WEC | D83: 0.60588024 | E83: 0.59533659 | F83: 0.58350367 | G83: 0.58060593 | H83: 0.55681587 | I83: 0.55211761 | J83: 0.54015034 | K83: 0.55777067 | L83: =AVERAGE(D83:K83) -> 0.57152261 | N83: =B83 -> Wisconsin Public Service Corporation | O83: =C83 -> WEC | P83: 0.39411976 | Q83: 0.40466341 | R83: 0.41649633 | S83: 0.41939407 | T83: 0.44318413 | U83: 0.44788239 | V83: 0.45984966 | W83: 0.44222933 | X83: =AVERAGE(P83:W83) -> 0.42847739
B84: Northern States Power Company - MN | C84: XEL | D84: 0.52635107 | E84: 0.52607887 | F84: 0.52591615 | G84: 0.52378577 | H84: 0.52220594 | I84: 0.52776836 | J84: 0.52624075 | K84: 0.52307426 | L84: =AVERAGE(D84:K84) -> 0.52517765 | N84: =B84 -> Northern States Power Company - MN | O84: =C84 -> XEL | P84: 0.47364893 | Q84: 0.47392113 | R84: 0.47408385 | S84: 0.47621423 | T84: 0.47779406 | U84: 0.47223164 | V84: 0.47375925 | W84: 0.47692574 | X84: =AVERAGE(P84:W84) -> 0.47482235
B85: Northern States Power Company - WI | C85: XEL | D85: 0.48448846 | E85: 0.53854779 | F85: 0.53792259 | G85: 0.53361331 | H85: 0.55565943 | I85: 0.5521952 | J85: 0.55656049 | K85: 0.54927472 | L85: =AVERAGE(D85:K85) -> 0.53853275 | N85: =B85 -> Northern States Power Company - WI | O85: =C85 -> XEL | P85: 0.51551154 | Q85: 0.46145221 | R85: 0.46207741 | S85: 0.46638669 | T85: 0.44434057 | U85: 0.4478048 | V85: 0.44343951 | W85: 0.45072528 | X85: =AVERAGE(P85:W85) -> 0.46146725
B86: Public Service Company of Colorado | C86: XEL | D86: 0.5608163 | E86: 0.54172383 | F86: 0.56665164 | G86: 0.5650419 | H86: 0.55639235 | I86: 0.54881229 | J86: 0.5700475 | K86: 0.56318463 | L86: =AVERAGE(D86:K86) -> 0.5590838 | N86: =B86 -> Public Service Company of Colorado | O86: =C86 -> XEL | P86: 0.4391837 | Q86: 0.45827617 | R86: 0.43334836 | S86: 0.4349581 | T86: 0.44360765 | U86: 0.45118771 | V86: 0.4299525 | W86: 0.43681537 | X86: =AVERAGE(P86:W86) -> 0.4409162
B87: Southwestern Public Service Company | C87: XEL | D87: 0.5629446 | E87: 0.538781 | F87: 0.53543436 | G87: 0.53545327 | H87: 0.52291109 | I87: 0.54606022 | J87: 0.5447708 | K87: 0.53926943 | L87: =AVERAGE(D87:K87) -> 0.5407031 | N87: =B87 -> Southwestern Public Service Company | O87: =C87 -> XEL | P87: 0.4370554 | Q87: 0.461219 | R87: 0.46456564 | S87: 0.46454673 | T87: 0.47708891 | U87: 0.45393978 | V87: 0.4552292 | W87: 0.46073057 | X87: =AVERAGE(P87:W87) -> 0.4592969
B88: Mean | D88: =AVERAGE(D34:D87) -> 0.54063683 | E88: =AVERAGE(E34:E87) -> 0.53556532 | F88: =AVERAGE(F34:F87) -> 0.54393288 | G88: =AVERAGE(G34:G87) -> 0.5379199 | H88: =AVERAGE(H34:H87) -> 0.54128347 | I88: =AVERAGE(I34:I87) -> 0.5387513 | J88: =AVERAGE(J34:J87) -> 0.5409532 | K88: =AVERAGE(K34:K87) -> 0.54054701 | L88: =AVERAGE(L34:L87) -> 0.54030015 | N88: Mean | P88: =AVERAGE(P34:P87) -> 0.45936317 | Q88: =AVERAGE(Q34:Q87) -> 0.46443468 | R88: =AVERAGE(R34:R87) -> 0.45606712 | S88: =AVERAGE(S34:S87) -> 0.4620801 | T88: =AVERAGE(T34:T87) -> 0.45871653 | U88: =AVERAGE(U34:U87) -> 0.4612487 | V88: =AVERAGE(V34:V87) -> 0.4590468 | W88: =AVERAGE(W34:W87) -> 0.45945299 | X88: =AVERAGE(X34:X87) -> 0.45969985
B90: Source: S&P Global Market Intelligence
