Workbook

Sheet  Exh Rate Case Exp
A1: AEP TEXAS INC
A2: SUMMARY OF RATE CASE EXPENSES
A3: PUC DOCKET NOS. 33309, 33310, 34301, 40261, 47015, 48222 and 48577
A5: AEP Texas | B5: Total Expenses
A7: PUC Docket No. 33309/33310/34301
A8: Legal Expenses - Central | B8: ='Trailing Charges Central'!I166 -> 211749.86
A9: Legal Expenses - North | B9: ='Trailing Charges North'!I30 -> 1827.2
A10: Total Requested Company Expenses Docket No. 33309/33310/34301 | B10: =B8+B9 -> 213577.06
A13: PUC Docket No. 40261
A14: Legal Expenses | B14: =+'Docket 40261'!H23 -> 82047.58
A15: Employee Expenses | B15: =+'Docket 40261'!H27 -> 55.48
A16: Total Company Expenses Docket No. 40261 | B16: =SUM(B14:B15) -> 82103.06
A19: PUC Docket No. 47015
A20: Other Expenses | B20: ='2017 DCRF 47015'!H21 -> 4314.05
A21: Employee Expenses | B21: =+'2017 DCRF 47015'!H74 -> 4005.91
A22: Total Company Expenses Docket No. 47015 | B22: =SUM(B20:B21) -> 8319.96
A25: PUC Docket No. 48222
A26: Other Expenses | B26: =+'2018 DCRF 48222 '!H30 -> 372.25
A27: Employee Expenses | B27: =+'2018 DCRF 48222 '!H66 -> 23414.13
A28: Total Company Expenses Docket No. 48222 | B28: =+SUM(B26:B27) -> 23786.38
A30: PUC Docket No. 48577
A31: Consultant Expenses | B31: =+'Docket 48577 '!H10 -> 2400
A32: Legal Expenses | B32: =+'Docket 48577 '!H47 -> 366397.52
A33: Other Expenses | B33: =+'Docket 48577 '!H71 -> 26383.77
A34: Employee Expenses | B34: =+'Docket 48577 '!H101 -> 3994.81
A35: Total Company Expenses Docket No. 48577 | B35: =SUM(B31:B34) -> 399176.1
A38: Total Company Expenses Docket Nos. 33309, 33310, 34301, 40261, 47015, 48222 and 48577 | B38: =B10+B16+B22+B28+B35 -> 726962.56
A39: Less: Over-Recovery on 34301 Rate Case Amortization- Allocable to Cities | B39: ='Trailing Charges Central'!I170 -> -143175.95
A41: Total Company Expenses to be collected for Docket Nos. 33309, 33310, 34301, 40261, 47015, 48222 and 48577 | B41: =B38+B39 -> 583786.61
A44: Municipal Expenses Reimbursed by AEP Texas | B44: Total Expenses
A46: PUC Docket No. 33309/33310/34301
A47: City of Abilene | B47: =+'Trailing Charges North'!I17 -> 1094.64
A48: City of McAllen | B48: =+'Trailing Charges Central'!I63 -> 234968.2
A50: Total Expenses Requested for Reimbursment Associated with Docket Nos. 33309/33310/34301 | B50: =SUM(B47:B49) -> 236062.84
A53: PUC Docket No. 47015
A54: City of McAllen | B54: =+'2017 DCRF 47015'!H15 -> 12680.27
A55: Total Expenses Reimbursed Docket No. 48222 | B55: =SUM(B54:B54) -> 12680.27
A58: Financo
A59: City of McAllen | B59: =+'2018 DCRF 48222 '!H17 -> 24321.45
A60: Total Expenses Reimbursed Docket No. 48222 | B60: =SUM(B59:B59) -> 24321.45
A63: Municipal Expenses Reimbursed by AEP Texas Inc
A64: City of Abilene | B64: =+B47 -> 1094.64
A65: City of McAllen | B65: =+B59+B54+B48 -> 271969.92
A66: Total Municipal Expenses Reimbursed for Docket Nos. 33309, 33310, 34301, 40261, 48222 and 48577 | B66: =SUM(B64:B65) -> 273064.56
A68: Less: Over-Recovery on 34301 Rate Case Amortization- Allocable to Legal | B68: =+'Trailing Charges Central'!I169 -> -158875.18
A69: Total Municipal Expenses to be collected for Docket Nos. 33309, 33310, 34301, 40261, 48222 and 48577 | B69: =B66+B68 -> 114189.38
A72: Total AEP Texas Inc and Municipal Expense Docket Nos. 33309,33310,34301,40261,48222, and 48577 | B72: =+B66+B38 -> 1000027.1
A73: Total AEP Texas Expenses for Dockets Nos. 33309, 33310, 34301, 40261, 47015, 48222 and 48577 | B73: =B68+B39 -> -302051.13
A74: Total AEP Texas Inc and Municipal Expense Docket Nos. 33309,33310,34301,40261,48222, and 48577 net of Over-Recovery | B74: =B41+B69 -> 697975.99

Sheet Exh Rate Case Exp 2
A1: AEP TEXAS INC
A2: SUMMARY OF RATE CASE EXPENSES
A3: PUC DOCKET NOS. 33309, 33310, 34301, 40261, 47015, 48222 and 48577
B5: Description of Service Provided | C5: Total Expenses
A6: =' Exh Rate Case Exp'!A7 -> PUC Docket No. 33309/33310/34301
A8: Legal Expenses
A9: Bracewell & Giuliani | B9: Bracewell & Giuliani attorneys provided counsel to AEP Texas in Docket Nos. 33309 and 33310. These costs were required to carry out the activities required to prosecute this case. These activities are described in detail in the voluminous invoices provided in the work papers to this Exhibit. As shown in the invoices, the activities were not duplicative or excessive and provided substantial value to the Company. The billing rates to AEP Texas for the attorneys at Bracewell & Giuliani ranged between $120/hour to $325/hour. Paralegal services were charged to AEP Texas at a rate of $80/hour to $90/hour. Bracewell & Giuliani was also reimbursed for expenses related to copying and courier charges. The billing rates charged by Bracewell & Giuliani to AEP Texas were the firm's normal hourly billing rates, were comparable to the rates charged by other attorneys for similar services to other Texas utilities, and were the normal hourly rates or were lower than the normal hourly billing rates charged by the firm for services to non-regulated entities. | C9: ='Trailing Charges Central'!I101 -> 147341.08
A10: Clark Thomas & Winters | B10: Clark Thomas & Winters attorneys provided counsel to AEP Texas in Docket Nos. 33309, 33310 and 34301. These costs were required to carry out the activities required to prosecute this case. These activities are described in detail in the voluminous invoices provided in the work papers to this Exhibit. As shown in the invoices, the activities were not duplicative or excessive and provided substantial value to the Company. The billing rates to AEP Texas for the attorneys at Clark Thomas & Winters ranged between $125/hour to $340/hour. Paralegal services were charged to AEP Texas at a rate of $90/hour. Clark Thomas & Winters was also reimbursed for expenses related to copying and courier charges. The billing rates charged by Clark Thomas & Winters to AEP Texas were the firm's normal hourly billing rates, were comparable to the rates charged by other attorneys for similar services to other Texas utilities, and were the normal hourly rates or were lower than the normal hourly billing rates charged by the firm for services to non-regulated entities. | C10: ='Trailing Charges Central'!I165+'Trailing Charges North'!I30 -> 66235.98
B11: Total Legal | C11: =C9+C10 -> 213577.06
B13: Over-Recovery on 34301 Rate Case Amortization | C13: ='Trailing Charges Central'!I170 -> -143175.95
A15: Total Expenses Associated with Dockets 33309, 33310 and 34301 | C15: =C11+C13 -> 70401.106
A17: =+' Exh Rate Case Exp'!A13 -> PUC Docket No. 40261
A19: Legal Expenses
A20: Bracewell & Giuliani | B20: Bracewell & Giuliani attorneys provided counsel to AEP Texas in Docket No 40261. These costs were required to carry out the activites required to prosecute this case. These activities are described in detail in the voluminous invoices provided in the work papers to this Exhibit. As shown in the invoices, the activities were not duplicative or excessive and provided substantial value to the Company. The billing rates to AEP Texas for the Attorney at Bracewell & Giuliani ranged between $150/hour to $320/hour. Bracewell & Giuliani was also reimbursed for expenses related to copying and courier charges. The billing rates charged by Bracewell & Giuliani to AEP Texas were the firm's normal hourly billing rates, were comparable to the rates charged by other attorneys for similar services to other Texas utilities, and were the normal hourly rates or were lower than the normal hourly rates charged by the firm for services to non-regulated utilities. | C20: ='Docket 40261'!H23 -> 82047.58
B21: Total Legal | C21: =SUM(C20) -> 82047.58
A23: Employee Expenses
B24: Non payroll employee expenses related to Docket No. 47015 including air fare, car rentals, taxi, hotels, meals, supplies and miscellaneous expenses. | C24: ='Docket 40261'!H27 -> 55.48
A26: Total Expenses Associated with Docket 40261 | C26: =C21+C24 -> 82103.06
A27: =+' Exh Rate Case Exp'!A19 -> PUC Docket No. 47015
A30: Other Expenses
A31: FedEx | B31: These expenses cover delivery services to provide time-sensitive documents to attorneys or representatives of other parties to Docket No. 47015 located outside of Austin or to members of the AEP Texas rate case team located outside of Austin where facsimile transmission was not feasible due to the bulk of the documents, such as multi-page responses to discovery and voluminous materials requested from AEP Texas' voluminous room. | C31: ='2017 DCRF 47015'!H20 -> 4314.05
B32: Total Other | C32: =C31 -> 4314.05
A34: Employee Expenses
B35: Non payroll employee expenses related to Docket No. 47015 including air fare, car rentals, taxi, hotels, meals, supplies and miscellaneous expenses. | C35: ='2017 DCRF 47015'!H74 -> 4005.91
A37: Total Expenses Associated with Docket 47015 | C37: =C32+C35 -> 8319.96
A39: =+' Exh Rate Case Exp'!A25 -> PUC Docket No. 48222
A41: Other Expenses
A42: Robert Half | B42: Robert Half furnished temporary clerical personnel to AEP's Austin regulatory services office to assist with the preparation of the rate filing package and responding to discovery. AEP's Austin regulatory services office does not have sufficient full time clerical personnel to handle the requirements associated with preparation of a major rate case filing and the extensive discovery generated by such a case. | C42: ='2018 DCRF 48222 '!H25 -> 322.09
A43: US Postal Service | B43: Cost of postage necessary to mail documents and other materials to parties in connection with the case. | C43: ='2018 DCRF 48222 '!H29 -> 50.16
B44: Total Other | C44: =SUM(C42:C43) -> 372.25
A46: Employee Expenses
B47: Non payroll employee expenses related to Docket No. 48222 including air fare, car rentals, taxi, hotels, meals, supplies and miscellaneous expenses. | C47: ='2018 DCRF 48222 '!H66 -> 23414.13
A49: Total Expenses Associated with Docket 44701 | C49: =C44+C47 -> 23786.38
A51: =+' Exh Rate Case Exp'!A30 -> PUC Docket No. 48577
A53: Legal Expenses
A54: Duggins, Wren, Mann & Romero, LLP | B54: DWMR attorneys provided counsel to AEP Texas in Docket No. 48577. These costs were required to carry out the activities required to prosecute this case. These activities are described in detail in the voluminous invoices provided in the work papers to this Exhibit. As shown in the invoices, the activities were not duplicative or excessive and provided substantial value to the Company. The billing rates to AEP Texas for the attorneys at DWMR ranged between $335/hour to $395/hour. Paralegal services were charged to AEP Texas at a rate of $135/hour. DWMR was also reimbursed for courier expenses. The billing rates charged by DWMR to AEP Texas were the firm's normal hourly billing rates, were comparable to the rates charged by other attorneys for similar services to other Texas utilities, and were the normal hourly rates or were lower than the normal hourly billing rates charged by the firm for services to non-regulated entities. | C54: ='Docket 48577 '!H46 -> 366397.52
B55: Total Legal | C55: =SUM(C54) -> 366397.52
A57: Consultant Expenses
A58: Financo | C58: ='Docket 48577 '!H9 -> 2400
B59: Total Consultant | C59: =C58 -> 2400
A61: Other Expenses
A62: Robert Half | B62: Robert Half furnished temporary clerical personnel to AEP's Austin regulatory services office to assist with the preparation of the rate filing package and responding to discovery. AEP's Austin regulatory services office does not have sufficient full time clerical personnel to handle the requirements associated with preparation of a major rate case filing and the extensive discovery generated by such a case. | C62: ='Docket 48577 '!H59 -> 997.23
A63: Texas Press Service, Inc. | B63: Handles the newspaper notice required by PUC Procedural Rule §22.51 | C63: ='Docket 48577 '!H64 -> 24863.83
A64: US Postal Service | B64: Cost of postage necessary to mail documents and other materials to parties in connection with the case. | C64: ='Docket 48577 '!H70 -> 522.71
B65: Total Other | C65: =SUM(C62:C64) -> 26383.77
A67: Employee Expenses
B68: Non payroll employee expenses related to Docket No. 45691 including meals, supplies and miscellaneous expenses. | C68: ='Docket 48577 '!H101 -> 3994.81
A70: Total Expenses Associated with Docket 48577 | C70: =C55+C59+C65+C68 -> 399176.1
A73: Total AEP Texas Expenses for Dockets Nos. 33309, 33310, 34301, 40261, 47015, 48222 and 48577 | C73: =C70+C49+C37+C26+C15 -> 583786.61

Sheet Docket 40261
A1: AMERICAN ELECTRIC POWER TEXAS INC
A2: SUMMARY OF RATE CASE EXPENSES
A3: PUC DOCKET NO. 40261
A6: Category | B6: Descr | C6: Voucher | D6: Vendor | E6: Name | F6: Amount | G6: Adjustment | H6: Requested | I6: Employee Name | J6: Year | K6: Period | L6: Invoice | M6: Invoice Date
A7: Legal | B7: Legal | C7: 01499816 | D7: 0000199577 | E7: BRACEWELL & GIULIANI LLP | F7: 5824.8 | G7: 0 | H7: =+F7+G7 -> 5824.8 | J7: 2012 | K7: 3 | L7: 21505447 | M7: 40966
A8: Legal | B8: Legal | C8: 01500576 | D8: 0000199577 | E8: BRACEWELL & GIULIANI LLP | F8: 16914.5 | G8: 0 | H8: =+F8+G8 -> 16914.5 | J8: 2012 | K8: 3 | L8: 21506988 | M8: 40966
E9: Subtotal | F9: =+F8+F7 -> 22739.3 | G9: =+G8+G7 -> 0 | H9: =+H8+H7 -> 22739.3
A10: Legal | B10: Legal | C10: 01507417 | D10: 0000199577 | E10: BRACEWELL & GIULIANI LLP | F10: 15392 | H10: =+F10+G10 -> 15392 | J10: 2012 | K10: 4 | L10: 21509869 | M10: 3/31/2012
E11: Subtotal | F11: =+F10 -> 15392 | G11: =+G10 -> 0 | H11: =+H10 -> 15392
A12: Legal | B12: Legal | C12: 01515976 | D12: 0000199577 | E12: BRACEWELL & GIULIANI LLP | F12: 32550.12 | H12: =+F12+G12 -> 32550.12 | J12: 2012 | K12: 5 | L12: 21512285 | M12: 4/30/2012
E13: Subtotal | F13: =+F12 -> 32550.12 | G13: =+G12 -> 0 | H13: =+H12 -> 32550.12
A14: Legal | B14: Legal | C14: 01525515 | D14: 0000199577 | E14: BRACEWELL & GIULIANI LLP | F14: 3243.04 | H14: =+F14+G14 -> 3243.04 | J14: 2012 | K14: 6 | L14: 21515035 | M14: 5/31/2012
E15: Subtotal | F15: =+F14 -> 3243.04 | G15: =+G14 -> 0 | H15: =+H14 -> 3243.04
A16: Legal | B16: Legal | C16: 01533428 | D16: 0000199577 | E16: BRACEWELL & GIULIANI LLP | F16: 6580.04 | H16: =+F16+G16 -> 6580.04 | J16: 2012 | K16: 8 | L16: 21517990 | M16: 7/31/2012
E17: Subtotal | F17: =+F16 -> 6580.04 | G17: =+G16 -> 0 | H17: =+H16 -> 6580.04
A18: Legal | B18: Legal | C18: 01543356 | D18: 0000199577 | E18: BRACEWELL & GIULIANI LLP | F18: 1415.08 | H18: =+F18+G18 -> 1415.08 | J18: 2012 | K18: 9 | L18: 21521308 | M18: 8/31/2012
E19: Subtotal | F19: =+F18 -> 1415.08 | G19: =+G18 -> 0 | H19: =+H18 -> 1415.08
A20: Legal | B20: Legal | C20: 01549738 | D20: 0000199577 | E20: BRACEWELL & GIULIANI LLP | F20: 128 | H20: =+F20+G20 -> 128 | J20: 2012 | K20: 10 | L20: 21523732 | M20: 9/30/2012
E21: Subtotal | F21: =+F20 -> 128 | G21: =+G20 -> 0 | H21: =+H20 -> 128
E22: Total BRACEWELL & GIULIANI LLP | F22: =+F21+F19+F17+F15+F13+F11+F9 -> 82047.58 | G22: =+G21+G19+G17+G15+G13+G11+G9 -> 0 | H22: =+H21+H19+H17+H15+H13+H11+H9 -> 82047.58
A23: Total Legal | F23: =+F22 -> 82047.58 | G23: =+G22 -> 0 | H23: =+H22 -> 82047.58
A25: Employee Expense | B25: Meal - Business | C25: 01508982 | D25: 0000146747 | E25: JP MORGAN CHASE CORPORATE CARD ACTIVITY | F25: 55.48 | G25: 0 | H25: =+F25+G25 -> 55.48 | I25: WALKER, TERI L | J25: 2012 | K25: 4 | L25: 0000091005ER79 | M25: 4/23/2012
E26: Subtotal | F26: =+F25 -> 55.48 | G26: =+G25 -> 0 | H26: =+H25 -> 55.48
A27: Total Employee Expense | F27: =+F26 -> 55.48 | G27: =+G26 -> 0 | H27: =+H26 -> 55.48
A29: Grand Total - Docket 40261 | F29: =+F27+F22 -> 82103.06 | G29: =+G27+G22 -> 0 | H29: =+H27+H22 -> 82103.06
A33: Divisional Allocation
A34: Sum of Sum Amount | B34: Unit
B35: 119 | C35: 211 | E35: Grand Total
A36: Total | B36: 41051.53 | C36: 41051.53 | E36: =+C36+B36 -> 82103.06
A37: Rate Case Expense Divisional Split | B37: 0.5 | C37: 0.5

Sheet 2017 DCRF 47015
A1: AMERICAN ELECTRIC POWER TEXAS INC
A2: SUMMARY OF RATE CASE EXPENSES
A3: PUC DOCKET NO. 47015
A6: Category | B6: Desc | C6: Voucher | D6: Vendor | E6: Name | F6: Amount | G6: Adjustment | H6: Requested | I6: Emp. Name | J6: Year | K6: Period | L6: Invoice | M6: Invoice date
A7: Cities | B7: Intervenor | C7: 804669 | D7: 97118 | E7: MCALLEN, CITY OF | F7: 4239.96 | G7: 0 | H7: =+F7+G7 -> 4239.96 | J7: 2017 | K7: (06) Jun | L7: 4701597482378 | M7: 42873
A8: Cities | B8: Intervenor | C8: 807297 | D8: 97118 | E8: MCALLEN, CITY OF | F8: 7329.81 | G8: 0 | H8: =+F8+G8 -> 7329.81 | J8: 2017 | K8: (06) Jun | L8: 4701597483244 | M8: 42895
E9: Subtotal | F9: =+SUM(F7:F8) -> 11569.77 | G9: =+SUM(G7:G8) -> 0 | H9: =+SUM(H7:H8) -> 11569.77
A10: Cities | B10: Intervenor | C10: 812336 | D10: 97118 | E10: MCALLEN, CITY OF | F10: 814.5 | G10: 0 | H10: =+F10+G10 -> 814.5 | J10: 2017 | K10: (08) Aug | L10: 4701597484267 | M10: 42926
E11: Subtotal | F11: =+F10 -> 814.5 | G11: =+G10 -> 0 | H11: =+H10 -> 814.5
A12: Cities | B12: Intervenor | C12: 828777 | D12: 97118 | E12: MCALLEN, CITY OF | F12: 296 | G12: 0 | H12: =+F12+G12 -> 296 | J12: 2017 | K12: (10) Oct | L12: 4701597485160 | M12: 42961
E13: Subtotal | F13: =+F12 -> 296 | G13: =+G12 -> 0 | H13: =+H12 -> 296
E14: Total MCALLEN, CITY OF | F14: =+F13+F11+F9 -> 12680.27 | G14: =+G13+G11+G9 -> 0 | H14: =+H13+H11+H9 -> 12680.27
A15: Total Cities | F15: =+F14 -> 12680.27 | G15: =+G14 -> 0 | H15: =+H14 -> 12680.27
A17: Other | B17: Postage | C17: 178556 | D17: 109159 | E17: FEDEX | F17: 19.09 | G17: 0 | H17: =+F17+G17 -> 19.09 | J17: 2017 | K17: (04) Apr | L17: 576921009 | M17: 42838
A18: Other | B18: Postage | C18: 794435 | D18: 109159 | E18: FEDEX | F18: 4294.96 | G18: 0 | H18: =+F18+G18 -> 4294.96 | J18: 2017 | K18: (04) Apr | L18: 576154348 | M18: 42831
E19: Subtotal | F19: =+SUM(F17:F18) -> 4314.05 | G19: =+SUM(G17:G18) -> 0 | H19: =+SUM(H17:H18) -> 4314.05
E20: Total FEDEX | F20: =+F19 -> 4314.05 | G20: =+G19 -> 0 | H20: =+H19 -> 4314.05
A21: Total Other | F21: =+F20 -> 4314.05 | G21: =+G20 -> 0 | H21: =+H20 -> 4314.05
A23: Employee Expense | B23: Parking | C23: 2054773 | D23: 161803 | E23: BANK OF AMERICA | F23: 5 | G23: 0 | H23: =+F23+G23 -> 5 | I23: STEWIEN, CAROL J | J23: 2017 | K23: (03) Mar | L23: EX0000432404 | M23: 42817
A24: Employee Expense | B24: Personal Mileage | C24: 2062408 | D24: 93058 | E24: TOUNGATE, JAY E | F24: 251.45 | G24: 0 | H24: =+F24+G24 -> 251.45 | I24: TOUNGATE, JAY E | J24: 2017 | K24: (04) Apr | L24: EX0000438248 | M24: 42830
A25: Employee Expense | B25: Meal-Self | C25: 2062408 | D25: 93058 | E25: TOUNGATE, JAY E | F25: 24.16 | G25: 0 | H25: =+F25+G25 -> 24.16 | I25: TOUNGATE, JAY E | J25: 2017 | K25: (04) Apr | L25: EX0000438248 | M25: 42830
A26: Employee Expense | B26: Meal-Self | C26: 2062408 | D26: 93058 | E26: TOUNGATE, JAY E | F26: 12.5 | G26: 0 | H26: =+F26+G26 -> 12.5 | I26: TOUNGATE, JAY E | J26: 2017 | K26: (04) Apr | L26: EX0000438248 | M26: 42830
A27: Employee Expense | B27: Meal-Self | C27: 2062408 | D27: 93058 | E27: TOUNGATE, JAY E | F27: 10.7 | G27: 0 | H27: =+F27+G27 -> 10.7 | I27: TOUNGATE, JAY E | J27: 2017 | K27: (04) Apr | L27: EX0000438248 | M27: 42830
A28: Employee Expense | B28: Parking | C28: 2062409 | D28: 161803 | E28: BANK OF AMERICA | F28: 15 | G28: 0 | H28: =+F28+G28 -> 15 | I28: TOUNGATE, JAY E | J28: 2017 | K28: (04) Apr | L28: EX0000438248 | M28: 42830
A29: Employee Expense | B29: Parking | C29: 2062409 | D29: 161803 | E29: BANK OF AMERICA | F29: 5 | G29: 0 | H29: =+F29+G29 -> 5 | I29: TOUNGATE, JAY E | J29: 2017 | K29: (04) Apr | L29: EX0000438248 | M29: 42830
A30: Employee Expense | B30: Parking | C30: 2062409 | D30: 161803 | E30: BANK OF AMERICA | F30: 15 | G30: 0 | H30: =+F30+G30 -> 15 | I30: TOUNGATE, JAY E | J30: 2017 | K30: (04) Apr | L30: EX0000438248 | M30: 42830
A31: Employee Expense | B31: Parking | C31: 2062409 | D31: 161803 | E31: BANK OF AMERICA | F31: 5 | G31: 0 | H31: =+F31+G31 -> 5 | I31: TOUNGATE, JAY E | J31: 2017 | K31: (04) Apr | L31: EX0000438248 | M31: 42830
A32: Employee Expense | B32: Meal-Self | C32: 2062409 | D32: 161803 | E32: BANK OF AMERICA | F32: 22.35 | G32: 0 | H32: =+F32+G32 -> 22.35 | I32: TOUNGATE, JAY E | J32: 2017 | K32: (04) Apr | L32: EX0000438248 | M32: 42830
A33: Employee Expense | B33: Meal-Self | C33: 2062409 | D33: 161803 | E33: BANK OF AMERICA | F33: 6.48 | G33: 0 | H33: =+F33+G33 -> 6.48 | I33: TOUNGATE, JAY E | J33: 2017 | K33: (04) Apr | L33: EX0000438248 | M33: 42830
A34: Employee Expense | B34: Meal-Self | C34: 2062409 | D34: 161803 | E34: BANK OF AMERICA | F34: 18.64 | G34: 0 | H34: =+F34+G34 -> 18.64 | I34: TOUNGATE, JAY E | J34: 2017 | K34: (04) Apr | L34: EX0000438248 | M34: 42830
... A38: Employee Expense | B38: Meal-Self | C38: 2062409 | D38: 161803 | E38: BANK OF AMERICA | F38: 14.17 | G38: 0 | H38: =+F38+G38 -> 14.17 | I38: TOUNGATE, JAY E | J38: 2017 | K38: (04) Apr | L38: EX0000438248 | M38: 42830
E39: Subtotal | F39: =+SUM(F23:F38) -> 498.4 | G39: =+SUM(G23:G38) -> 0 | H39: =+SUM(H23:H38) -> 498.4
A41: Employee Expense | B41: Personal Mileage | C41: 2079293 | D41: 93058 | E41: TOUNGATE, JAY E | F41: 13.91 | G41: 0 | H41: =+F41+G41 -> 13.91 | I41: TOUNGATE, JAY E | J41: 2017 | K41: (05) May | L41: EX0000456925 | M41: 42873
A42: Employee Expense | B42: Personal Mileage | C42: 2079293 | D42: 93058 | E42: TOUNGATE, JAY E | F42: 13.91 | G42: 0 | H42: =+F42+G42 -> 13.91 | I42: TOUNGATE, JAY E | J42: 2017 | K42: (05) May | L42: EX0000456925 | M42: 42873
A43: Employee Expense | B43: Meal-Self | C43: 2079294 | D43: 161803 | E43: BANK OF AMERICA | F43: 13 | G43: 0 | H43: =+F43+G43 -> 13 | I43: TOUNGATE, JAY E | J43: 2017 | K43: (05) May | L43: EX0000456925 | M43: 42873
A44: Employee Expense | B44: Meal-Self | C44: 2079294 | D44: 161803 | E44: BANK OF AMERICA | F44: 20.27 | G44: 0 | H44: =+F44+G44 -> 20.27 | I44: TOUNGATE, JAY E | J44: 2017 | K44: (05) May | L44: EX0000456925 | M44: 42873
A45: Employee Expense | B45: Meal-Business | C45: 2079294 | D45: 161803 | E45: BANK OF AMERICA | F45: 55.65 | G45: 0 | H45: =+F45+G45 -> 55.65 | I45: TOUNGATE, JAY E | J45: 2017 | K45: (05) May | L45: EX0000456925 | M45: 42873
A46: Employee Expense | B46: Meal-Self | C46: 2079294 | D46: 161803 | E46: BANK OF AMERICA | F46: 26 | G46: 0 | H46: =+F46+G46 -> 26 | I46: TOUNGATE, JAY E | J46: 2017 | K46: (05) May | L46: EX0000456925 | M46: 42873
A47: Employee Expense | B47: Meal-Self | C47: 2079294 | D47: 161803 | E47: BANK OF AMERICA | F47: 9.06 | G47: 0 | H47: =+F47+G47 -> 9.06 | I47: TOUNGATE, JAY E | J47: 2017 | K47: (05) May | L47: EX0000456925 | M47: 42873
A48: Employee Expense | B48: Meal-Self | C48: 2079294 | D48: 161803 | E48: BANK OF AMERICA | F48: 16.78 | G48: 0 | H48: =+F48+G48 -> 16.78 | I48: TOUNGATE, JAY E | J48: 2017 | K48: (05) May | L48: EX0000456925 | M48: 42873
A49: Employee Expense | B49: Meal-Self | C49: 2079294 | D49: 161803 | E49: BANK OF AMERICA | F49: 23.54 | G49: 0 | H49: =+F49+G49 -> 23.54 | I49: TOUNGATE, JAY E | J49: 2017 | K49: (05) May | L49: EX0000456925 | M49: 42873
A50: Employee Expense | B50: Meal-Self | C50: 2079294 | D50: 161803 | E50: BANK OF AMERICA | F50: 16.21 | G50: 0 | H50: =+F50+G50 -> 16.21 | I50: TOUNGATE, JAY E | J50: 2017 | K50: (05) May | L50: EX0000456925 | M50: 42873
A51: Employee Expense | B51: Meal-Self | C51: 2079294 | D51: 161803 | E51: BANK OF AMERICA | F51: 7.77 | G51: 0 | H51: =+F51+G51 -> 7.77 | I51: TOUNGATE, JAY E | J51: 2017 | K51: (05) May | L51: EX0000456925 | M51: 42873
A52: Employee Expense | B52: Parking | C52: 2079294 | D52: 161803 | E52: BANK OF AMERICA | F52: 5 | G52: 0 | H52: =+F52+G52 -> 5 | I52: TOUNGATE, JAY E | J52: 2017 | K52: (05) May | L52: EX0000456925 | M52: 42873
A53: Employee Expense | B53: Hotel | C53: 2079294 | D53: 161803 | E53: BANK OF AMERICA | F53: =249+249+249+269+269 -> 1285 | G53: 0 | H53: =+F53+G53 -> 1285 | I53: TOUNGATE, JAY E | J53: 2017 | K53: (05) May | L53: EX0000456925 | M53: 42873
A54: Employee Expense | B54: Tax | C54: 2079294 | D54: 161803 | E54: BANK OF AMERICA | F54: =2.48+2.48+2.48+2.48+2.48 -> 12.4 | G54: 0 | H54: =+F54+G54 -> 12.4 | I54: TOUNGATE, JAY E | J54: 2017 | K54: (05) May | L54: EX0000456925 | M54: 42873
A55: Employee Expense | B55: Tax | C55: 2079294 | D55: 161803 | E55: BANK OF AMERICA | F55: =14.94+14.94+14.94+16.14+16.14 -> 77.1 | G55: 0 | H55: =+F55+G55 -> 77.1 | I55: TOUNGATE, JAY E | J55: 2017 | K55: (05) May | L55: EX0000456925 | M55: 42873
A56: Employee Expense | B56: Tax | C56: 2079294 | D56: 161803 | E56: BANK OF AMERICA | F56: =22.41+22.41+22.41+24.21+24.21 -> 115.65 | G56: 0 | H56: =+F56+G56 -> 115.65 | I56: TOUNGATE, JAY E | J56: 2017 | K56: (05) May | L56: EX0000456925 | M56: 42873
A57: Employee Expense | B57: Parking | C57: 2079294 | D57: 161803 | E57: BANK OF AMERICA | F57: =30+30+30+30+30 -> 150 | G57: 0 | H57: =+F57+G57 -> 150 | I57: TOUNGATE, JAY E | J57: 2017 | K57: (05) May | L57: EX0000456925 | M57: 42873
A58: Employee Expense | B58: Airfare | C58: 2079294 | D58: 161803 | E58: BANK OF AMERICA | F58: 477.96 | G58: 0 | H58: =+F58+G58 -> 477.96 | I58: TOUNGATE, JAY E | J58: 2017 | K58: (05) May | L58: EX0000456925 | M58: 42873
A59: Employee Expense | B59: Car Rental | C59: 2079294 | D59: 161803 | E59: BANK OF AMERICA | F59: 51.3 | G59: 0 | H59: =+F59+G59 -> 51.3 | I59: TOUNGATE, JAY E | J59: 2017 | K59: (05) May | L59: EX0000456925 | M59: 42873
A60: Employee Expense | B60: Parking | C60: 2079294 | D60: 161803 | E60: BANK OF AMERICA | F60: 17 | G60: 0 | H60: =+F60+G60 -> 17 | I60: TOUNGATE, JAY E | J60: 2017 | K60: (05) May | L60: EX0000456925 | M60: 42873
A61: Employee Expense | B61: Hotel | C61: 2079294 | D61: 161803 | E61: BANK OF AMERICA | F61: 194 | G61: 0 | H61: =+F61+G61 -> 194 | I61: TOUNGATE, JAY E | J61: 2017 | K61: (05) May | L61: EX0000456925 | M61: 42873
A62: Employee Expense | B62: Tax | C62: 2079294 | D62: 161803 | E62: BANK OF AMERICA | F62: 11.64 | G62: 0 | H62: =+F62+G62 -> 11.64 | I62: TOUNGATE, JAY E | J62: 2017 | K62: (05) May | L62: EX0000456925 | M62: 42873
A63: Employee Expense | B63: Tax | C63: 2079294 | D63: 161803 | E63: BANK OF AMERICA | F63: 17.46 | G63: 0 | H63: =+F63+G63 -> 17.46 | I63: TOUNGATE, JAY E | J63: 2017 | K63: (05) May | L63: EX0000456925 | M63: 42873
A64: Employee Expense | B64: Parking | C64: 2079294 | D64: 161803 | E64: BANK OF AMERICA | F64: 15 | G64: 0 | H64: =+F64+G64 -> 15 | I64: TOUNGATE, JAY E | J64: 2017 | K64: (05) May | L64: EX0000456925 | M64: 42873
A65: Employee Expense | B65: Airfare | C65: 2079294 | D65: 161803 | E65: BANK OF AMERICA | F65: 477.96 | G65: 0 | H65: =+F65+G65 -> 477.96 | I65: TOUNGATE, JAY E | J65: 2017 | K65: (05) May | L65: EX0000456925 | M65: 42873
A66: Employee Expense | B66: Car Rental | C66: 2079294 | D66: 161803 | E66: BANK OF AMERICA | F66: 102.59 | G66: 0 | H66: =+F66+G66 -> 102.59 | I66: TOUNGATE, JAY E | J66: 2017 | K66: (05) May | L66: EX0000456925 | M66: 42873
A67: Employee Expense | B67: Parking | C67: 2079294 | D67: 161803 | E67: BANK OF AMERICA | F67: 34 | G67: 0 | H67: =+F67+G67 -> 34 | I67: TOUNGATE, JAY E | J67: 2017 | K67: (05) May | L67: EX0000456925 | M67: 42873
A68: Employee Expense | B68: Hotel | C68: 2079294 | D68: 161803 | E68: BANK OF AMERICA | F68: 229 | G68: 0 | H68: =+F68+G68 -> 229 | I68: TOUNGATE, JAY E | J68: 2017 | K68: (05) May | L68: EX0000456925 | M68: 42873
A69: Employee Expense | B69: Tax | C69: 2079294 | D69: 161803 | E69: BANK OF AMERICA | F69: 13.74 | G69: 0 | H69: =+F69+G69 -> 13.74 | I69: TOUNGATE, JAY E | J69: 2017 | K69: (05) May | L69: EX0000456925 | M69: 42873
... A72: Employee Expense | B72: Airfare | C72: 2079294 | D72: 161803 | E72: BANK OF AMERICA | F72: -16 | G72: 0 | H72: =+F72+G72 -> -16 | I72: TOUNGATE, JAY E | J72: 2017 | K72: (05) May | L72: EX0000456925 | M72: 42873
E73: Subtotal | F73: =+SUM(F41:F72) -> 3537.51 | G73: =+SUM(G41:G72) -> -30 | H73: =+SUM(H41:H72) -> 3507.51
A74: Total Employee Expense | F74: =+F73+F39 -> 4035.91 | G74: =+G73+G39 -> -30 | H74: =+H73+H39 -> 4005.91
A76: Grand Total - 2017 DCRF Docket 47015 | F76: =+F74+F21+F15 -> 21030.23 | G76: =+G74+G21+G15 -> -30 | H76: =+H74+H21+H15 -> 21000.23
A80: Divisional Allocation
B81: Column Labels
B82: 103 | C82: 211 | D82: Grand Total
A83: Sum of Requested | B83: 4000.91 | C83: 16999.32 | D83: 21000.23
A85: Per GL (Account 928) | B85: Business Unit
A86: W/O | B86: 119 | C86: 211 | D86: Grand Total
A87: SPX17DCR01 | B87: 331.47 | C87: 1351.79 | D87: 1683.26
A88: SPX18DCR01 | B88: 14984.56 | C88: 61509.27 | D88: 76493.83
A89: UTX17DCR01 | B89: 5206.33 | C89: 18243.45 | D89: 23449.78
A90: UTX18DCR01 | B90: 11543.52 | C90: 46469.89 | D90: 58013.41
A91: Grand Total | B91: 32065.88 | C91: 127574.4 | D91: 159640.28
A93: 2017 DCRF | B93: 5537.8 | C93: 19595.24 | D93: 25133.04
A94: 2018 DCRF | B94: 26528.08 | C94: 107979.16 | D94: 134507.24
D95: 159640.28
B97: 119 | C97: 211
A98: 2017 DCRF | B98: =+B93/D93 -> 0.22033944 | C98: =+C93/D93 -> 0.77966056
A99: 2018 DCRF | B99: =+B94/D94 -> 0.19722418 | C99: =+C94/D94 -> 0.80277582
A101: Request | B101: =+B98*H76 -> 4627.179 | C101: =+C98*H76 -> 16373.051 | D101: =+SUM(B101:C101) -> 21000.23

Sheet 2018 DCRF 48222 
A1: AMERICAN ELECTRIC POWER TEXAS INC
A2: SUMMARY OF RATE CASE EXPENSES
A3: PUC DOCKET NO. 48222
A6: Category | B6: Desc | C6: Voucher | D6: Vendor | E6: Name | F6: Amount | G6: Adjustment | H6: Requested | I6: Emp. Name | J6: Year | K6: Period | L6: Invoice | M6: Invoice Date
A7: Cities | B7: Intervenor | C7: 00891815 | D7: 0000097118 | E7: MCALLEN, CITY OF | F7: 5660.6 | G7: 0 | H7: =+F7+G7 -> 5660.6 | J7: 2018 | K7: 9 | L7: 97491936DKT48222 | M7: 43230
A8: Cities | B8: Intervenor | C8: 00891816 | D8: 0000097118 | E8: MCALLEN, CITY OF | F8: 17041 | G8: 0 | H8: =+F8+G8 -> 17041 | J8: 2018 | K8: 9 | L8: 97492334DKT48222 | M8: 43263
A9: Cities | B9: Intervenor | C9: 00891817 | D9: 0000097118 | E9: MCALLEN, CITY OF | F9: 175 | G9: 0 | H9: =+F9+G9 -> 175 | J9: 2018 | K9: 9 | L9: 97494170DKT48222 | M9: 43320
A10: Cities | B10: Intervenor | C10: 00891818 | D10: 0000097118 | E10: MCALLEN, CITY OF | F10: 313.5 | G10: 0 | H10: =+F10+G10 -> 313.5 | J10: 2018 | K10: 9 | L10: 97494843DKT48222 | M10: 43354
A11: Cities | B11: Intervenor | C11: 00891819 | D11: 0000097118 | E11: MCALLEN, CITY OF | F11: 743 | G11: 0 | H11: =+F11+G11 -> 743 | J11: 2018 | K11: 9 | L11: 97494955DKT48222 | M11: 43344
E12: Subtotal | F12: =+SUM(F7:F11) -> 23933.1 | G12: =+SUM(G7:G11) -> 0 | H12: =+SUM(H7:H11) -> 23933.1
A13: Cities | B13: Intervenor | C13: 00895179 | D13: 0000097118 | E13: MCALLEN, CITY OF | F13: 358.75 | G13: 0 | H13: =+F13+G13 -> 358.75 | J13: 2018 | K13: 10 | L13: 0000106587EX0000683369 | M13: 43377
A14: Cities | B14: Intervenor | C14: 00895179 | D14: 0000097118 | E14: MCALLEN, CITY OF | F14: 29.6 | G14: 0 | H14: =+F14+G14 -> 29.6 | J14: 2018 | K14: 10 | L14: 0000106587EX0000683369 | M14: 43377
E15: Subtotal | F15: =+SUM(F13:F14) -> 388.35 | G15: =+SUM(G13:G14) -> 0 | H15: =+SUM(H13:H14) -> 388.35
E16: Total MCALLEN, CITY OF | F16: =+F15+F12 -> 24321.45 | G16: =+G15+G12 -> 0 | H16: =+H15+H12 -> 24321.45
A17: Total Cities | F17: =+F16 -> 24321.45 | G17: =+G16 -> 0 | H17: =+H16 -> 24321.45
A19: Other | B19: Temporary Employees | C19: 2215275 | D19: 164567 | E19: ROBERT HALF TECHNOLOGY | F19: 247.1 | G19: 0 | H19: =+F19+G19 -> 247.1 | J19: 2018 | K19: (04) Apr | L19: AEPIN00126670 | M19: 43199
E20: Subtotal | F20: =+F19 -> 247.1 | G20: =+G19 -> 0 | H20: =+H19 -> 247.1
A21: Other | B21: Temporary Employees | C21: 2230324 | D21: 164567 | E21: ROBERT HALF TECHNOLOGY | F21: 49.42 | G21: 0 | H21: =+F21+G21 -> 49.42 | J21: 2018 | K21: (05) May | L21: AEPIN00130429 | M21: 43220
E22: Subtotal | F22: =+F21 -> 49.42 | G22: =+G21 -> 0 | H22: =+H21 -> 49.42
A23: Other | B23: Temporary Employees | C23: 2278581 | D23: 164567 | E23: ROBERT HALF TECHNOLOGY | F23: 25.57 | G23: 0 | H23: =+F23+G23 -> 25.57 | J23: 2018 | K23: (08) Aug | L23: AEPIN00150177 | M23: 43336
E24: Subtotal | F24: =+F23 -> 25.57 | G24: =+G23 -> 0 | H24: =+H23 -> 25.57
E25: Total ROBERT HALF TECHNOLOGY | F25: =+F24+F22+F20 -> 322.09 | G25: =+G24+G22+G20 -> 0 | H25: =+H24+H22+H20 -> 322.09
A27: Other | B27: Postage | C27: 885914 | D27: 80046 | E27: US POSTAL SERVICE | F27: 50.16 | G27: 0 | H27: =+F27+G27 -> 50.16 | J27: 2018 | K27: (08) Aug | L27: 201802 | M27: 43329
E28: Subtotal | F28: =+F27 -> 50.16 | G28: =+G27 -> 0 | H28: =+H27 -> 50.16
E29: Total US POSTAL SERVICE | F29: =+F28 -> 50.16 | G29: =+G28 -> 0 | H29: =+H28 -> 50.16
A30: Total Other | F30: =+F29+F25 -> 372.25 | G30: =+G29+G25 -> 0 | H30: =+H29+H25 -> 372.25
A33: Employee Expense | B33: Office Supplies | C33: 854762 | D33: 161803 | E33: BANK OF AMERICA | F33: 180.79 | G33: 0 | H33: =+F33+G33 -> 180.79 | I33: GULLICKSON, GREGORY K | J33: 2018 | K33: (03) Mar | L33: EX0000590208 | M33: 43171
A34: Employee Expense | B34: Office Supplies | C34: 854857 | D34: 161803 | E34: BANK OF AMERICA | F34: 399.64 | G34: 0 | H34: =+F34+G34 -> 399.64 | I34: GULLICKSON, GREGORY K | J34: 2018 | K34: (03) Mar | L34: EX0000590211 | M34: 43171
A35: Employee Expense | B35: Office Supplies | C35: 856146 | D35: 161803 | E35: BANK OF AMERICA | F35: 342.55 | G35: 0 | H35: =+F35+G35 -> 342.55 | I35: GULLICKSON, GREGORY K | J35: 2018 | K35: (03) Mar | L35: EX0000591684 | M35: 43178
A36: Employee Expense | B36: Tax | C36: 858342 | D36: 161803 | E36: BANK OF AMERICA | F36: 204.52 | G36: 0 | H36: =+F36+G36 -> 204.52 | I36: GULLICKSON, GREGORY K | J36: 2018 | K36: (03) Mar | L36: EX0000598796 | M36: 43187
A37: Employee Expense | B37: Office Supplies | C37: 858342 | D37: 161803 | E37: BANK OF AMERICA | F37: 565 | G37: 0 | H37: =+F37+G37 -> 565 | I37: GULLICKSON, GREGORY K | J37: 2018 | K37: (03) Mar | L37: EX0000598796 | M37: 43187
A38: Employee Expense | B38: Office Supplies | C38: 858342 | D38: 161803 | E38: BANK OF AMERICA | F38: 1914 | G38: 0 | H38: =+F38+G38 -> 1914 | I38: GULLICKSON, GREGORY K | J38: 2018 | K38: (03) Mar | L38: EX0000598796 | M38: 43187
E39: Subtotal | F39: =+SUM(F33:F38) -> 3606.5 | G39: =+SUM(G33:G38) -> 0 | H39: =+SUM(H33:H38) -> 3606.5
A40: Employee Expense | B40: Meal-Business | C40: 862052 | D40: 161803 | E40: BANK OF AMERICA | F40: 57.23 | G40: 0 | H40: =+F40+G40 -> 57.23 | I40: BEATY, STEVEN J | J40: 2018 | K40: (04) Apr | L40: EX0000608540 | M40: 43209
A41: Employee Expense | B41: Postage | C41: 862960 | D41: 161803 | E41: BANK OF AMERICA | F41: 19 | G41: 0 | H41: =+F41+G41 -> 19 | I41: GULLICKSON, GREGORY K | J41: 2018 | K41: (04) Apr | L41: EX0000610656 | M41: 43215
A42: Employee Expense | B42: Postage | C42: 862960 | D42: 161803 | E42: BANK OF AMERICA | F42: 12.72 | G42: 0 | H42: =+F42+G42 -> 12.72 | I42: GULLICKSON, GREGORY K | J42: 2018 | K42: (04) Apr | L42: EX0000610656 | M42: 43215
E43: Subtotal | F43: =+SUM(F40:F42) -> 88.95 | G43: =+SUM(G40:G42) -> 0 | H43: =+SUM(H40:H42) -> 88.95
A44: Employee Expense | B44: Meal-Business | C44: 868015 | D44: 161803 | E44: BANK OF AMERICA | F44: 61.91 | G44: 0 | H44: =+F44+G44 -> 61.91 | I44: BEATY, STEVEN J | J44: 2018 | K44: (05) May | L44: EX0000623604 | M44: 43242
A45: Employee Expense | B45: Meal-Business | C45: 868015 | D45: 161803 | E45: BANK OF AMERICA | F45: 57.9 | G45: 0 | H45: =+F45+G45 -> 57.9 | I45: BEATY, STEVEN J | J45: 2018 | K45: (05) May | L45: EX0000623604 | M45: 43242
A46: Employee Expense | B46: Meal-Self | C46: 2227859 | D46: 161803 | E46: BANK OF AMERICA | F46: 19 | G46: 0 | H46: =+F46+G46 -> 19 | I46: KIMANI, PETER K | J46: 2018 | K46: (05) May | L46: EX0000620517 | M46: 43235
A47: Employee Expense | B47: Meal-Self | C47: 2227859 | D47: 161803 | E47: BANK OF AMERICA | F47: 4.61 | G47: 0 | H47: =+F47+G47 -> 4.61 | I47: KIMANI, PETER K | J47: 2018 | K47: (05) May | L47: EX0000620517 | M47: 43235
A48: Employee Expense | B48: Meal-Self | C48: 2227859 | D48: 161803 | E48: BANK OF AMERICA | F48: 12.83 | G48: 0 | H48: =+F48+G48 -> 12.83 | I48: KIMANI, PETER K | J48: 2018 | K48: (05) May | L48: EX0000620517 | M48: 43235
A49: Employee Expense | B49: Taxi | C49: 2227859 | D49: 161803 | E49: BANK OF AMERICA | F49: 37.08 | G49: 0 | H49: =+F49+G49 -> 37.08 | I49: KIMANI, PETER K | J49: 2018 | K49: (05) May | L49: EX0000620517 | M49: 43235
A50: Employee Expense | B50: Hotel | C50: 2227859 | D50: 161803 | E50: BANK OF AMERICA | F50: 229 | G50: 0 | H50: =+F50+G50 -> 229 | I50: KIMANI, PETER K | J50: 2018 | K50: (05) May | L50: EX0000620517 | M50: 43235
A51: Employee Expense | B51: Tax | C51: 2227859 | D51: 161803 | E51: BANK OF AMERICA | F51: 13.74 | G51: 0 | H51: =+F51+G51 -> 13.74 | I51: KIMANI, PETER K | J51: 2018 | K51: (05) May | L51: EX0000620517 | M51: 43235
A52: Employee Expense | B52: Tax | C52: 2227859 | D52: 161803 | E52: BANK OF AMERICA | F52: 20.61 | G52: 0 | H52: =+F52+G52 -> 20.61 | I52: KIMANI, PETER K | J52: 2018 | K52: (05) May | L52: EX0000620517 | M52: 43235
A53: Employee Expense | B53: Parking | C53: 2227859 | D53: 161803 | E53: BANK OF AMERICA | F53: 24 | G53: 0 | H53: =+F53+G53 -> 24 | I53: KIMANI, PETER K | J53: 2018 | K53: (05) May | L53: EX0000620517 | M53: 43235
A54: Employee Expense | B54: Taxi | C54: 2227860 | D54: 254271 | E54: KIMANI, PETER K | F54: 31.3 | G54: 0 | H54: =+F54+G54 -> 31.3 | I54: KIMANI, PETER K | J54: 2018 | K54: (05) May | L54: EX0000620532 | M54: 43235
A55: Employee Expense | B55: Airfare | C55: 2232793 | D55: 254271 | E55: KIMANI, PETER K | F55: 574.66 | G55: 0 | H55: =+F55+G55 -> 574.66 | I55: KIMANI, PETER K | J55: 2018 | K55: (05) May | L55: EX0000622472 | M55: 43238
E56: Subtotal | F56: =+SUM(F44:F55) -> 1086.64 | G56: =+SUM(G44:G55) -> 0 | H56: =+SUM(H44:H55) -> 1086.64
A57: Employee Expense | B57: Postage | C57: 872975 | D57: 161803 | E57: BANK OF AMERICA | F57: 9868.12 | G57: 0 | H57: =+F57+G57 -> 9868.12 | I57: GULLICKSON, GREGORY K | J57: 2018 | K57: (06) Jun | L57: EX0000631736 | M57: 43265
A58: Employee Expense | B58: Courier | C58: 873463 | D58: 161803 | E58: BANK OF AMERICA | F58: 11 | G58: 0 | H58: =+F58+G58 -> 11 | I58: GULLICKSON, GREGORY K | J58: 2018 | K58: (06) Jun | L58: EX0000634721 | M58: 43269
A59: Employee Expense | B59: Printing | C59: 875982 | D59: 161803 | E59: BANK OF AMERICA | F59: 7410.04 | G59: 0 | H59: =+F59+G59 -> 7410.04 | I59: GULLICKSON, GREGORY K | J59: 2018 | K59: (06) Jun | L59: EX0000639966 | M59: 43278
A60: Employee Expense | B60: Printing | C60: 875982 | D60: 161803 | E60: BANK OF AMERICA | F60: 923.05 | G60: 0 | H60: =+F60+G60 -> 923.05 | I60: GULLICKSON, GREGORY K | J60: 2018 | K60: (06) Jun | L60: EX0000639966 | M60: 43278
A61: Employee Expense | B61: Postage | C61: 876369 | D61: 161803 | E61: BANK OF AMERICA | F61: 31.48 | G61: 0 | H61: =+F61+G61 -> 31.48 | I61: GULLICKSON, GREGORY K | J61: 2018 | K61: (06) Jun | L61: EX0000640229 | M61: 43280
E62: Subtotal | F62: =+SUM(F57:F61) -> 18243.69 | G62: =+SUM(G57:G61) -> 0 | H62: =+SUM(H57:H61) -> 18243.69
A63: Employee Expense | B63: Tax | C63: 895179 | D63: 161803 | E63: BANK OF AMERICA | F63: 29.6 | G63: 0 | H63: =+F63+G63 -> 29.6 | I63: GULLICKSON, GREGORY K | J63: 2018 | K63: (10) Oct | L63: EX0000683369 | M63: 43377
A64: Employee Expense | B64: Printing | C64: 895179 | D64: 161803 | E64: BANK OF AMERICA | F64: 358.75 | G64: 0 | H64: =+F64+G64 -> 358.75 | I64: GULLICKSON, GREGORY K | J64: 2018 | K64: (10) Oct | L64: EX0000683369 | M64: 43377
E65: Subtotal | F65: =+SUM(F63:F64) -> 388.35 | G65: =+SUM(G63:G64) -> 0 | H65: =+SUM(H63:H64) -> 388.35
A66: Total Employee Expense | F66: =+F65+F62+F56+F43+F39 -> 23414.13 | G66: =+G65+G62+G56+G43+G39 -> 0 | H66: =+H65+H62+H56+H43+H39 -> 23414.13
A68: Grand Total - 2018 DCRF Docket 48222 | F68: =+F66+F30+F17 -> 48107.83 | G68: =+G66+G30+G17 -> 0 | H68: =+H66+H30+H17 -> 48107.83
A74: Divisional Allocation
B75: Column Labels
B76: 103 | C76: 211 | D76: 211 | E76: Grand Total
A77: Sum of Requested | B77: 966.83 | C77: 22819.55 | D77: 24321.45 | E77: 48107.83
A80: Per GL (Account 928) | B80: Business Unit
A81: W/O | B81: 119 | C81: 211 | D81: Grand Total
A82: SPX17DCR01 | B82: 331.47 | C82: 1351.79 | D82: 1683.26
A83: SPX18DCR01 | B83: 14984.56 | C83: 61509.27 | D83: 76493.83
A84: UTX17DCR01 | B84: 5206.33 | C84: 18243.45 | D84: 23449.78
A85: UTX18DCR01 | B85: 11543.52 | C85: 46469.89 | D85: 58013.41
A86: Grand Total | B86: 32065.88 | C86: 127574.4 | D86: 159640.28
A88: 2017 DCRF | B88: 5537.8 | C88: 19595.24 | D88: 25133.04
A89: 2018 DCRF | B89: 26528.08 | C89: 107979.16 | D89: 134507.24
D90: 159640.28
B92: 119 | C92: 211
A93: 2017 DCRF | B93: =+B88/D88 -> 0.22033944 | C93: =+C88/D88 -> 0.77966056
A94: 2018 DCRF | B94: =+B89/D89 -> 0.19722418 | C94: =+C89/D89 -> 0.80277582
A95: Request | B95: =+B94*H68 -> 9488.0273 | C95: =+C94*H68 -> 38619.803 | D95: =+SUM(B95:C95) -> 48107.83

Sheet Docket 48577 
A1: AMERICAN ELECTRIC POWER TEXAS INC
A2: SUMMARY OF RATE CASE EXPENSES
A3: PUC DOCKET NO. 48577
A6: Category | B6: Desc | C6: Voucher | D6: Vendor | E6: Name | F6: Amount | G6: Adjustment | H6: Requested | I6: Employee | J6: Year | K6: Period | L6: Invoice | M6: Invoice Date
A7: Consultant | B7: Prof. Services | C7: 282134 | D7: 26132 | E7: FINANCO INC | F7: 2400 | G7: 0 | H7: 2400 | J7: 2017 | K7: (11) Nov | L7: 4013 | M7: 43008
E8: Subtotal | F8: =+F7 -> 2400 | G8: =+G7 -> 0 | H8: =+H7 -> 2400
E9: Total FINANCO INC | F9: =+F8 -> 2400 | G9: =+G8 -> 0 | H9: =+H8 -> 2400
A10: Total Consultant | F10: =+F9 -> 2400 | G10: =+G9 -> 0 | H10: =+H9 -> 2400
A13: Legal | B13: Legal | C13: 844337 | D13: 256019 | E13: DUGGINS WREN MANN & ROMERO LLP | F13: 26299.81 | G13: 0 | H13: =+F13+G13 -> 26299.81 | J13: 2018 | K13: (01) Jan | L13: 27422 | M13: 43111
E14: Subtotal | F14: =+F13 -> 26299.81 | G14: =+G13 -> 0 | H14: =+H13 -> 26299.81
A15: Legal | B15: Legal | C15: 850306 | D15: 256019 | E15: DUGGINS WREN MANN & ROMERO LLP | F15: 37698.17 | G15: 0 | H15: =+F15+G15 -> 37698.17 | J15: 2018 | K15: (02) Feb | L15: 27636 | M15: 43143
E16: Subtotal | F16: =+F15 -> 37698.17 | G16: =+G15 -> 0 | H16: =+H15 -> 37698.17
A17: Legal | B17: Legal | C17: 856698 | D17: 256019 | E17: DUGGINS WREN MANN & ROMERO LLP | F17: 25392.28 | G17: 0 | H17: =+F17+G17 -> 25392.28 | J17: 2018 | K17: (03) Mar | L17: 27881 | M17: 43173
E18: Subtotal | F18: =+F17 -> 25392.28 | G18: =+G17 -> 0 | H18: =+H17 -> 25392.28
A19: Legal | B19: Legal | C19: 860826 | D19: 256019 | E19: DUGGINS WREN MANN & ROMERO LLP | F19: 3039.73 | G19: 0 | H19: =+F19+G19 -> 3039.73 | J19: 2018 | K19: (04) Apr | L19: 28025 | M19: 43196
E20: Subtotal | F20: =+F19 -> 3039.73 | G20: =+G19 -> 0 | H20: =+H19 -> 3039.73
A21: Legal | B21: Legal | C21: 866372 | D21: 256019 | E21: DUGGINS WREN MANN & ROMERO LLP | F21: 9147.55 | G21: 0 | H21: =+F21+G21 -> 9147.55 | J21: 2018 | K21: (05) May | L21: 28280 | M21: 43230
E22: Subtotal | F22: =+F21 -> 9147.55 | G22: =+G21 -> 0 | H22: =+H21 -> 9147.55
A23: Legal | B23: Legal | C23: 872909 | D23: 256019 | E23: DUGGINS WREN MANN & ROMERO LLP | F23: 2592.55 | G23: 0 | H23: =+F23+G23 -> 2592.55 | J23: 2018 | K23: (06) Jun | L23: 28516 | M23: 43263
E24: Subtotal | F24: =+F23 -> 2592.55 | G24: =+G23 -> 0 | H24: =+H23 -> 2592.55
A25: Legal | B25: Legal | C25: 878991 | D25: 256019 | E25: DUGGINS WREN MANN & ROMERO LLP | F25: 30811.33 | G25: 0 | H25: =+F25+G25 -> 30811.33 | J25: 2018 | K25: (07) Jul | L25: 28752 | M25: 43291
A26: Legal | B26: Legal | C26: 878992 | D26: 256019 | E26: DUGGINS WREN MANN & ROMERO LLP | F26: 225.15 | G26: 0 | H26: =+F26+G26 -> 225.15 | J26: 2018 | K26: (07) Jul | L26: 28753 | M26: 43291
E27: Subtotal | F27: =+F26+F25 -> 31036.48 | G27: =+G26+G25 -> 0 | H27: =+H26+H25 -> 31036.48
A28: Legal | B28: Legal | C28: 884858 | D28: 256019 | E28: DUGGINS WREN MANN & ROMERO LLP | F28: 36165.13 | G28: 0 | H28: =+F28+G28 -> 36165.13 | J28: 2018 | K28: (08) Aug | L28: 29038 | M28: 43321
E29: Subtotal | F29: =+F28 -> 36165.13 | G29: =+G28 -> 0 | H29: =+H28 -> 36165.13
A30: Legal | B30: Legal | C30: 891475 | D30: 256019 | E30: DUGGINS WREN MANN & ROMERO LLP | F30: 38537.33 | G30: 0 | H30: =+F30+G30 -> 38537.33 | J30: 2018 | K30: (09) Sep | L30: 29329 | M30: 43356
E31: Subtotal | F31: =+F30 -> 38537.33 | G31: =+G30 -> 0 | H31: =+H30 -> 38537.33
A32: Legal | B32: Legal | C32: 896878 | D32: 256019 | E32: DUGGINS WREN MANN & ROMERO LLP | F32: 3511.21 | G32: 0 | H32: =+F32+G32 -> 3511.21 | J32: 2018 | K32: (10) Oct | L32: 29525 | M32: 43384
E33: Subtotal | F33: =+F32 -> 3511.21 | G33: =+G32 -> 0 | H33: =+H32 -> 3511.21
A34: Legal | B34: Legal | C34: 907606 | D34: 256019 | E34: DUGGINS WREN MANN & ROMERO LLP | F34: 31734.05 | G34: 0 | H34: =+F34+G34 -> 31734.05 | J34: 2018 | K34: (12) Dec | L34: 29524 | M34: 43384
A35: Legal | B35: Legal | C35: 908014 | D35: 256019 | E35: DUGGINS WREN MANN & ROMERO LLP | F35: 18588.84 | G35: 0 | H35: =+F35+G35 -> 18588.84 | J35: 2018 | K35: (12) Dec | L35: 29754 | M35: 43416
A36: Legal | B36: Legal | C36: 908364 | D36: 256019 | E36: DUGGINS WREN MANN & ROMERO LLP | F36: 17068.73 | G36: 0 | H36: =+F36+G36 -> 17068.73 | J36: 2018 | K36: (12) Dec | L36: 29753 | M36: 43416
A37: Legal | B37: Legal | C37: 910274 | D37: 256019 | E37: DUGGINS WREN MANN & ROMERO LLP | F37: 16101.54 | G37: 0 | H37: =+F37+G37 -> 16101.54 | J37: 2018 | K37: (12) Dec | L37: 29978 | M37: 43440
A38: Legal | B38: Legal | C38: 911224 | D38: 256019 | E38: DUGGINS WREN MANN & ROMERO LLP | F38: 10251.91 | G38: 0 | H38: =+F38+G38 -> 10251.91 | J38: 2018 | K38: (12) Dec | L38: 29977 | M38: 43440
E39: Subtotal | F39: =+SUM(F34:F38) -> 93745.07 | G39: =+SUM(G34:G38) -> 0 | H39: =+SUM(H34:H38) -> 93745.07
A40: Legal | B40: Legal | C40: 916059 | D40: 256019 | E40: DUGGINS WREN MANN & ROMERO LLP | F40: 726.79 | G40: 0 | H40: 726.79 | J40: 2019 | K40: (01) Jan | L40: 30257 | M40: 43476
A41: Legal | B41: Legal | C41: 916060 | D41: 256019 | E41: DUGGINS WREN MANN & ROMERO LLP | F41: 28173.42 | G41: 0 | H41: 28173.42 | J41: 2019 | K41: (01) Jan | L41: 30258 | M41: 43476
E42: Subtotal | F42: =+SUM(F40:F41) -> 28900.21 | G42: =+SUM(G40:G41) -> 0 | H42: =+SUM(H40:H41) -> 28900.21
A43: Legal | B43: Legal | C43: 921399 | D43: 256019 | E43: DUGGINS WREN MANN & ROMERO LLP | F43: 30168 | G43: 0 | H43: =+F43+G43 -> 30168 | J43: 2019 | K43: (02) Feb | L43: 30507 | M43: 43508
A44: Legal | B44: Legal | C44: 921995 | D44: 256019 | E44: DUGGINS WREN MANN & ROMERO LLP | F44: 164 | G44: 0 | H44: =+F44+G44 -> 164 | J44: 2019 | K44: (02) Feb | L44: 30506 | M44: 43508
E45: Subtotal | F45: =+F44+F43 -> 30332 | G45: =+G44+G43 -> 0 | H45: =+H44+H43 -> 30332
E46: Total DUGGINS WREN MANN & ROMERO LLP | F46: =+F39+F33+F31+F29+F27+F24+F22+F20+F18+F16+F14+F42+F45 -> 366397.52 | G46: =+G39+G33+G31+G29+G27+G24+G22+G20+G18+G16+G14+G42+G45 -> 0 | H46: =+H39+H33+H31+H29+H27+H24+H22+H20+H18+H16+H14+H42+H45 -> 366397.52
A47: Total Legal | F47: =+F46 -> 366397.52 | G47: =+G46 -> 0 | H47: =+H46 -> 366397.52
A50: Other | B50: Temporary Employees | C50: 2272641 | D50: 164567 | E50: ROBERT HALF TECHNOLOGY | F50: 178.99 | G50: 0 | H50: =+F50+G50 -> 178.99 | J50: 2018 | K50: (09) Sep | L50: AEPIN00148071 | M50: 43325
A51: Other | B51: Temporary Employees | C51: 2276015 | D51: 164567 | E51: ROBERT HALF TECHNOLOGY | F51: 178.99 | G51: 0 | H51: =+F51+G51 -> 178.99 | J51: 2018 | K51: (09) Sep | L51: AEPIN00149552 | M51: 43332
A52: Other | B52: Temporary Employees | C52: 2278581 | D52: 164567 | E52: ROBERT HALF TECHNOLOGY | F52: 166.2 | G52: 0 | H52: =+F52+G52 -> 166.2 | J52: 2018 | K52: (09) Sep | L52: AEPIN00150177 | M52: 43336
A53: Other | B53: Temporary Employees | C53: 2284017 | D53: 164567 | E53: ROBERT HALF TECHNOLOGY | F53: 25.57 | G53: 0 | H53: =+F53+G53 -> 25.57 | J53: 2018 | K53: (09) Sep | L53: AEPIN00151642 | M53: 43346
A54: Other | B54: Temporary Employees | C54: 2285060 | D54: 164567 | E54: ROBERT HALF TECHNOLOGY | F54: 204.56 | G54: 0 | H54: =+F54+G54 -> 204.56 | J54: 2018 | K54: (09) Sep | L54: AEPIN00153064 | M54: 43353
A55: Other | B55: Temporary Employees | C55: 2288522 | D55: 164567 | E55: ROBERT HALF TECHNOLOGY | F55: 217.35 | G55: 0 | H55: =+F55+G55 -> 217.35 | J55: 2018 | K55: (09) Sep | L55: AEPIN00154473 | M55: 43360
E56: Subtotal | F56: =+SUM(F50:F55) -> 971.66 | G56: =+SUM(G50:G55) -> 0 | H56: =+SUM(H50:H55) -> 971.66
A57: Other | B57: Temporary Employees | C57: 2295298 | D57: 164567 | E57: ROBERT HALF TECHNOLOGY | F57: 25.57 | G57: 0 | H57: =+F57+G57 -> 25.57 | J57: 2018 | K57: (12) Dec | L57: AEPIN00156118 | M57: 43371
E58: Subtotal | F58: =+F57 -> 25.57 | G58: =+G57 -> 0 | H58: =+H57 -> 25.57
E59: Total ROBERT HALF TECHNOLOGY | F59: =+F58+F56 -> 997.23 | G59: =+G58+G56 -> 0 | H59: =+H58+H56 -> 997.23
A61: Other | B61: Notice | C61: 890441 | D61: 108885 | E61: TEXAS PRESS SERVICE INC | F61: 22968.9 | G61: 0 | H61: =+F61+G61 -> 22968.9 | J61: 2018 | K61: (09) Sep | L61: 14491 | M61: 43342
A62: Other | B62: Notice | C62: 890441 | D62: 108885 | E62: TEXAS PRESS SERVICE INC | F62: 1894.93 | G62: 0 | H62: =+F62+G62 -> 1894.93 | J62: 2018 | K62: (09) Sep | L62: 14491 | M62: 43342
E63: Subtotal | F63: =+F62+F61 -> 24863.83 | G63: =+G62+G61 -> 0 | H63: =+H62+H61 -> 24863.83
E64: Total TEXAS PRESS SERVICE INC | F64: =+F63 -> 24863.83 | G64: =+G63 -> 0 | H64: =+H63 -> 24863.83
A66: Other | B66: Postage | C66: 885914 | D66: 80046 | E66: US POSTAL SERVICE | F66: 181.37 | G66: 0 | H66: =+F66+G66 -> 181.37 | J66: 2018 | K66: (09) Sep | L66: 201802 | M66: 43329
E67: Subtotal | F67: =+F66 -> 181.37 | G67: =+G66 -> 0 | H67: =+H66 -> 181.37
A68: Other | B68: Postage | C68: 921653 | D68: 80046 | E68: US POSTAL SERVICE | F68: 341.34 | G68: 0 | H68: =+F68+G68 -> 341.34 | J68: 2019 | K68: (02) Feb | L68: 201901 | M68: 43514
E69: Subtotal | F69: =+F68 -> 341.34 | G69: =+G68 -> 0 | H69: =+H68 -> 341.34
A70: Other | B70: Postage | E70: Total US POSTAL SERVICE | F70: =+F67+F69 -> 522.71 | G70: =+G67+G69 -> 0 | H70: =+H67+H69 -> 522.71
A71: Total Other | F71: =+F70+F64+F59 -> 26383.77 | G71: =+G70+G64+G59 -> 0 | H71: =+H70+H64+H59 -> 26383.77
A75: Employee Expense | B75: Parking | C75: 2188846 | D75: 161803 | E75: BANK OF AMERICA | F75: 12 | G75: 0 | H75: =+F75+G75 -> 12 | I75: STEWIEN, CAROL J | J75: 2018 | K75: (02) Feb | L75: EX0000577234 | M75: 43144
E76: Subtotal | F76: =+F75 -> 12 | G76: =+G75 -> 0 | H76: =+H75 -> 12
A77: Employee Expense | B77: Personal Mileage | C77: 893482 | D77: 18796 | E77: COAD, THOMAS M | F77: 279.04 | G77: 0 | H77: =+F77+G77 -> 279.04 | I77: COAD, THOMAS M | J77: 2018 | K77: (09) Sep | L77: EX0000673864 | M77: 43369
A78: Employee Expense | B78: Postage | C78: 887776 | D78: 161803 | E78: BANK OF AMERICA | F78: 12.72 | G78: 0 | H78: 12.72 | I78: GULLICKSON, GREGORY K | J78: 2018 | K78: (09) Sep | L78: EX0000664427 | M78: 43340
A79: Employee Expense | B79: Printing | C79: 891270 | D79: 161803 | E79: BANK OF AMERICA | F79: 2308.97 | G79: 0 | H79: 2308.97 | I79: GULLICKSON, GREGORY K | J79: 2018 | K79: (09) Sep | L79: EX0000673255 | M79: 43356
A80: Employee Expense | B80: Postage | C80: 893807 | D80: 161803 | E80: BANK OF AMERICA | F80: 6 | G80: 0 | H80: =+F80+G80 -> 6 | I80: GULLICKSON, GREGORY K | J80: 2018 | K80: (09) Sep | L80: EX0000676777 | M80: 43370
A81: Employee Expense | B81: Printing | C81: 893807 | D81: 161803 | E81: BANK OF AMERICA | F81: 256.55 | G81: 0 | H81: =+F81+G81 -> 256.55 | I81: GULLICKSON, GREGORY K | J81: 2018 | K81: (09) Sep | L81: EX0000676777 | M81: 43370
A82: Employee Expense | B82: Postage | C82: 893808 | D82: 161803 | E82: BANK OF AMERICA | F82: 15.07 | G82: 0 | H82: =+F82+G82 -> 15.07 | I82: GULLICKSON, GREGORY K | J82: 2018 | K82: (09) Sep | L82: EX0000680831 | M82: 43370
A83: Employee Expense | B83: Meal-Self | C83: 2290189 | D83: 161803 | E83: BANK OF AMERICA | F83: 5.3 | G83: 0 | H83: =+F83+G83 -> 5.3 | I83: HAMLETT, RANDALL W | J83: 2018 | K83: (09) Sep | L83: EX0000677641 | M83: 43367
A84: Employee Expense | B84: Meal-Self | C84: 2290189 | D84: 161803 | E84: BANK OF AMERICA | F84: 3.24 | G84: 0 | H84: =+F84+G84 -> 3.24 | I84: HAMLETT, RANDALL W | J84: 2018 | K84: (09) Sep | L84: EX0000677641 | M84: 43367
A85: Employee Expense | B85: Meal-Self | C85: 2290188 | D85: 91417 | E85: HAMLETT, RANDALL W | F85: 19.31 | G85: 0 | H85: =+F85+G85 -> 19.31 | I85: HAMLETT, RANDALL W | J85: 2018 | K85: (09) Sep | L85: EX0000677641 | M85: 43367
A86: Employee Expense | B86: Personal Mileage | C86: 2290188 | D86: 91417 | E86: HAMLETT, RANDALL W | F86: 16.35 | G86: 0 | H86: =+F86+G86 -> 16.35 | I86: HAMLETT, RANDALL W | J86: 2018 | K86: (09) Sep | L86: EX0000677641 | M86: 43367
A87: Employee Expense | B87: Taxi | C87: 2290188 | D87: 91417 | E87: HAMLETT, RANDALL W | F87: 28.19 | G87: 0 | H87: =+F87+G87 -> 28.19 | I87: HAMLETT, RANDALL W | J87: 2018 | K87: (09) Sep | L87: EX0000677641 | M87: 43367
E88: Subtotal | F88: =+SUM(F77:F87) -> 2950.74 | G88: =+SUM(G77:G87) -> 0 | H88: =+SUM(H77:H87) -> 2950.74
A89: Employee Expense | B89: Transcription | C89: 898740 | D89: 161803 | E89: BANK OF AMERICA | F89: 260 | G89: 0 | H89: =+F89+G89 -> 260 | I89: GULLICKSON, GREGORY K | J89: 2018 | K89: (10) Oct | L89: EX0000691420 | M89: 43395
A90: Employee Expense | B90: Tax | C90: 898740 | D90: 161803 | E90: BANK OF AMERICA | F90: 21.45 | G90: 0 | H90: =+F90+G90 -> 21.45 | I90: GULLICKSON, GREGORY K | J90: 2018 | K90: (10) Oct | L90: EX0000691420 | M90: 43395
A91: Employee Expense | B91: Airfare | C91: 2290189 | D91: 161803 | E91: BANK OF AMERICA | F91: 536.46 | G91: 0 | H91: =+F91+G91 -> 536.46 | I91: HAMLETT, RANDALL W | J91: 2018 | K91: (10) Oct | L91: EX0000677641 | M91: 43367
A92: Employee Expense | B92: Taxi | C92: 2290189 | D92: 161803 | E92: BANK OF AMERICA | F92: 40.68 | G92: 0 | H92: =+F92+G92 -> 40.68 | I92: HAMLETT, RANDALL W | J92: 2018 | K92: (10) Oct | L92: EX0000677641 | M92: 43367
A93: Employee Expense | B93: Parking | C93: 2290189 | D93: 161803 | E93: BANK OF AMERICA | F93: 12 | G93: 0 | H93: =+F93+G93 -> 12 | I93: HAMLETT, RANDALL W | J93: 2018 | K93: (10) Oct | L93: EX0000677641 | M93: 43367
E94: Subtotal | F94: =+SUM(F89:F93) -> 870.59 | G94: =+SUM(G89:G93) -> 0 | H94: =+SUM(H89:H93) -> 870.59
A95: Employee Expense | B95: Postage | C95: 898743 | D95: 161803 | E95: BANK OF AMERICA | F95: 6.48 | G95: 0 | H95: =+F95+G95 -> 6.48 | I95: GULLICKSON, GREGORY K | J95: 2018 | K95: (12) Dec | L95: EX0000691447 | M95: 43395
A96: Employee Expense | B96: Postage | C96: 898820 | D96: 161803 | E96: BANK OF AMERICA | F96: 53 | G96: 0 | H96: =+F96+G96 -> 53 | I96: GULLICKSON, GREGORY K | J96: 2018 | K96: (12) Dec | L96: EX0000691960 | M96: 43395
A97: Employee Expense | B97: Postage | C97: 899599 | D97: 161803 | E97: BANK OF AMERICA | F97: 30 | G97: 0 | H97: =+F97+G97 -> 30 | I97: GULLICKSON, GREGORY K | J97: 2018 | K97: (12) Dec | L97: EX0000693396 | M97: 43398
A98: Employee Expense | B98: Parking | C98: 2300846 | D98: 161803 | E98: BANK OF AMERICA | F98: 60 | G98: 0 | H98: =+F98+G98 -> 60 | I98: STEWIEN, CAROL J | J98: 2018 | K98: (12) Dec | L98: EX0000688260 | M98: 43385
A99: Employee Expense | B99: Parking | C99: 2327626 | D99: 161803 | E99: BANK OF AMERICA | F99: 12 | G99: 0 | H99: =+F99+G99 -> 12 | I99: STEWIEN, CAROL J | J99: 2018 | K99: (12) Dec | L99: EX0000713888 | M99: 43439
E100: Subtotal | F100: =+SUM(F95:F99) -> 161.48 | G100: =+SUM(G95:G99) -> 0 | H100: =+SUM(H95:H99) -> 161.48
A101: Total Employee Expense | F101: =+F100+F94+F88+F76 -> 3994.81 | G101: =+G100+G94+G88+G76 -> 0 | H101: =+H100+H94+H88+H76 -> 3994.81
A103: Grand Total - Docket 48577 | F103: =+F101+F71+F47+F10 -> 399176.1 | G103: =+G101+G71+G47+G10 -> 0 | H103: =+H101+H71+H47+H10 -> 399176.1

Sheet Trailing Charges Central
A1: AMERICAN ELECTRIC POWER TEXAS INC
A2: SUMMARY OF RATE CASE EXPENSES
A3: PUC DOCKET NOS. 28840/33309 (CENTRAL)
A7: Category | B7: Descr | C7: Voucher | D7: Vendor | E7: Name | F7: Amount | G7: Adjustment | H7: Total | I7: Central Division Requested | J7: Central % | K7: Employee Name | L7: Year | M7: Period | N7: Invoice | O7: Invoice Date
A8: Cities | B8: Cities | C8: 01064000 | D8: 0000097118 | E8: MCALLEN, CITY OF | F8: 172 | G8: 0 | H8: =+F8+G8 -> 172 | I8: =+H8 -> 172 | J8: =+I8/H8 -> 1 | L8: 2008 | M8: 4 | N8: 33309FEB2008 | O8: 39545
A9: Cities | B9: Cities | C9: 01064008 | D9: 0000097118 | E9: MCALLEN, CITY OF | F9: 710.5 | G9: 0 | H9: =+F9+G9 -> 710.5 | I9: =+H9 -> 710.5 | J9: =+I9/H9 -> 1 | L9: 2008 | M9: 4 | N9: 33309 | O9: 39545
A10: Cities | B10: Cities | C10: 01066033 | D10: 0000097118 | E10: MCALLEN, CITY OF | F10: 4283.46 | G10: 0 | H10: =+F10+G10 -> 4283.46 | I10: =+H10 -> 4283.46 | J10: =+I10/H10 -> 1 | L10: 2008 | M10: 4 | N10: 33309 | O10: 39545
A11: Cities | B11: Cities | C11: 01066711 | D11: 0000097118 | E11: MCALLEN, CITY OF | F11: 203 | G11: 0 | H11: =+F11+G11 -> 203 | I11: =+H11 -> 203 | J11: =+I11/H11 -> 1 | L11: 2008 | M11: 4 | N11: 33309 | O11: 39504
A12: Cities | B12: Cities | C12: 01059153 | D12: 0000097118 | E12: MCALLEN, CITY OF | F12: 29331.96 | G12: 0 | H12: =+F12+G12 -> 29331.96 | I12: =+H12 -> 29331.96 | J12: =+I12/H12 -> 1 | L12: 2008 | M12: 4 | N12: 33309 | O12: 39521
A13: Cities | B13: Cities | C13: 01063999 | D13: 0000097118 | E13: MCALLEN, CITY OF | F13: 23391.38 | G13: 0 | H13: =+F13+G13 -> 23391.38 | I13: =+H13 -> 23391.38 | J13: =+I13/H13 -> 1 | L13: 2008 | M13: 4 | N13: 33309DEC2007 | O13: 39545
E14: Subtotal | F14: =+SUM(F8:F13) -> 58092.3 | G14: =+SUM(G8:G13) -> 0 | H14: =+SUM(H8:H13) -> 58092.3 | I14: =+SUM(I8:I13) -> 58092.3
A15: Cities | B15: Cities | C15: 01079391 | D15: 0000097118 | E15: MCALLEN, CITY OF | F15: 7111 | G15: 0 | H15: =+F15+G15 -> 7111 | I15: =+H15 -> 7111 | J15: =+I15/H15 -> 1 | L15: 2008 | M15: 5 | N15: 35915 | O15: 39580
E16: Subtotal | F16: =+F15 -> 7111 | G16: =+G15 -> 0 | H16: =+H15 -> 7111 | I16: =+I15 -> 7111
A17: Cities | B17: Cities | C17: 01091323 | D17: 0000097118 | E17: MCALLEN, CITY OF | F17: 7535.9 | G17: 0 | H17: =+F17+G17 -> 7535.9 | I17: =+H17 -> 7535.9 | J17: =+I17/H17 -> 1 | L17: 2008 | M17: 6 | N17: 36251 | O17: 39610
E18: Subtotal | F18: =+F17 -> 7535.9 | G18: =+G17 -> 0 | H18: =+H17 -> 7535.9 | I18: =+I17 -> 7535.9
A19: Cities | B19: Cities | C19: 01111817 | D19: 0000097118 | E19: MCALLEN, CITY OF | F19: 2266.6 | G19: 0 | H19: =+F19+G19 -> 2266.6 | I19: =+H19 -> 2266.6 | J19: =+I19/H19 -> 1 | L19: 2008 | M19: 8 | N19: 3330936553 | O19: 39626
A20: Cities | B20: Cities | C20: 01103762 | D20: 0000097118 | E20: MCALLEN, CITY OF | F20: 23391.38 | G20: 0 | H20: =+F20+G20 -> 23391.38 | I20: =+H20 -> 23391.38 | J20: =+I20/H20 -> 1 | L20: 2008 | M20: 8 | N20: 3330934911 | O20: 39545
E21: Subtotal | F21: =+F20+F19 -> 25657.98 | G21: =+G20+G19 -> 0 | H21: =+H20+H19 -> 25657.98 | I21: =+I20+I19 -> 25657.98
A22: Cities | B22: Cities | C22: 01119115 | D22: 0000097118 | E22: MCALLEN, CITY OF | F22: 1371.85 | G22: 0 | H22: =+F22+G22 -> 1371.85 | I22: =+H22 -> 1371.85 | J22: =+I22/H22 -> 1 | L22: 2008 | M22: 9 | N22: 3330936984 | O22: 39675
E23: Subtotal | F23: =+F22 -> 1371.85 | G23: =+G22 -> 0 | H23: =+H22 -> 1371.85 | I23: =+I22 -> 1371.85
A24: Cities | B24: Cities | C24: 01130842 | D24: 0000097118 | E24: MCALLEN, CITY OF | F24: 8434.58 | G24: 0 | H24: =+F24+G24 -> 8434.58 | I24: =+H24 -> 8434.58 | J24: =+I24/H24 -> 1 | L24: 2008 | M24: 10 | N24: 33309 | O24: 39713
E25: Subtotal | F25: =+F24 -> 8434.58 | G25: =+G24 -> 0 | H25: =+H24 -> 8434.58 | I25: =+I24 -> 8434.58
A26: Cities | B26: Cities | C26: 01151450 | D26: 0000097118 | E26: MCALLEN, CITY OF | F26: 789.79 | G26: 0 | H26: =+F26+G26 -> 789.79 | I26: =+H26 -> 789.79 | J26: =+I26/H26 -> 1 | L26: 2008 | M26: 12 | N26: 33309 | O26: 39773
E27: Subtotal | F27: =+F26 -> 789.79 | G27: =+G26 -> 0 | H27: =+H26 -> 789.79 | I27: =+I26 -> 789.79
A28: Cities | B28: Cities | C28: 01167304 | D28: 0000097118 | E28: MCALLEN, CITY OF | F28: 25394.37 | G28: 0 | H28: =+F28+G28 -> 25394.37 | I28: =+H28 -> 25394.37 | J28: =+I28/H28 -> 1 | L28: 2009 | M28: 1 | N28: 3330938672 | O28: 39822
A29: Cities | B29: Cities | C29: 01167301 | D29: 0000097118 | E29: MCALLEN, CITY OF | F29: 24209.3 | G29: 0 | H29: =+F29+G29 -> 24209.3 | I29: =+H29 -> 24209.3 | J29: =+I29/H29 -> 1 | L29: 2009 | M29: 1 | N29: 3330938484 | O29: 39794
E30: Subtotal | F30: =+F29+F28 -> 49603.67 | G30: =+G29+G28 -> 0 | H30: =+H29+H28 -> 49603.67 | I30: =+I29+I28 -> 49603.67
A31: Cities | B31: Cities | C31: 01177712 | D31: 0000097118 | E31: MCALLEN, CITY OF | F31: 16687.22 | G31: 0 | H31: =+F31+G31 -> 16687.22 | I31: =+H31 -> 16687.22 | J31: =+I31/H31 -> 1 | L31: 2009 | M31: 3 | N31: 33309 | O31: 39840
E32: Subtotal | F32: =+F31 -> 16687.22 | G32: =+G31 -> 0 | H32: =+H31 -> 16687.22 | I32: =+I31 -> 16687.22
A33: Cities | B33: Cities | C33: 01195228 | D33: 0000097118 | E33: MCALLEN, CITY OF | F33: 2127.9 | G33: 0 | H33: =+F33+G33 -> 2127.9 | I33: =+H33 -> 2127.9 | J33: =+I33/H33 -> 1 | L33: 2009 | M33: 4 | N33: 39893 | O33: 39884
A34: Cities | B34: Cities | C34: 01195227 | D34: 0000097118 | E34: MCALLEN, CITY OF | F34: 1067.25 | G34: 0 | H34: =+F34+G34 -> 1067.25 | I34: =+H34 -> 1067.25 | J34: =+I34/H34 -> 1 | L34: 2009 | M34: 4 | N34: 33309 | O34: 39869
E35: Subtotal | F35: =+F34+F33 -> 3195.15 | G35: =+G34+G33 -> 0 | H35: =+H34+H33 -> 3195.15 | I35: =+I34+I33 -> 3195.15
A36: Cities | B36: Cities | C36: 01200359 | D36: 0000097118 | E36: MCALLEN, CITY OF | F36: 703.5 | G36: 0 | H36: =+F36+G36 -> 703.5 | I36: =+H36 -> 703.5 | J36: =+I36/H36 -> 1 | L36: 2009 | M36: 5 | N36: 28840 | O36: 39798
A37: Cities | B37: Cities | C37: 01200360 | D37: 0000097118 | E37: MCALLEN, CITY OF | F37: 1962.96 | G37: 0 | H37: =+F37+G37 -> 1962.96 | I37: =+H37 -> 1962.96 | J37: =+I37/H37 -> 1 | L37: 2009 | M37: 5 | N37: 28840 | O37: 39610
A38: Cities | B38: Cities | C38: 01200361 | D38: 0000097118 | E38: MCALLEN, CITY OF | F38: 1526.81 | G38: 0 | H38: =+F38+G38 -> 1526.81 | I38: =+H38 -> 1526.81 | J38: =+I38/H38 -> 1 | L38: 2009 | M38: 5 | N38: 28840 | O38: 39580
A39: Cities | B39: Cities | C39: 01200358 | D39: 0000097118 | E39: MCALLEN, CITY OF | F39: 478.5 | G39: 0 | H39: =+F39+G39 -> 478.5 | I39: =+H39 -> 478.5 | J39: =+I39/H39 -> 1 | L39: 2009 | M39: 5 | N39: 28840 | O39: 39840
A40: Cities | B40: Cities | C40: 01200357 | D40: 0000097118 | E40: MCALLEN, CITY OF | F40: 4103.15 | G40: 0 | H40: =+F40+G40 -> 4103.15 | I40: =+H40 -> 4103.15 | J40: =+I40/H40 -> 1 | L40: 2009 | M40: 5 | N40: 33309 | O40: 39932
A41: Cities | B41: Cities | C41: 01197060 | D41: 0000097118 | E41: MCALLEN, CITY OF | F41: 9784.65 | G41: 0 | H41: =+F41+G41 -> 9784.65 | I41: =+H41 -> 9784.65 | J41: =+I41/H41 -> 1 | L41: 2009 | M41: 5 | N41: 3330937703 | O41: 39918
E42: Subtotal | F42: =+SUM(F36:F41) -> 18559.57 | G42: =+SUM(G36:G41) -> 0 | H42: =+SUM(H36:H41) -> 18559.57 | I42: =+SUM(I36:I41) -> 18559.57
A43: Cities | B43: Cities | C43: 01215483 | D43: 0000097118 | E43: MCALLEN, CITY OF | F43: 1067.97 | G43: 0 | H43: =+F43+G43 -> 1067.97 | I43: =+H43 -> 1067.97 | J43: =+I43/H43 -> 1 | L43: 2009 | M43: 7 | N43: 33309 | O43: 39988
E44: Subtotal | F44: =+F43 -> 1067.97 | G44: =+G43 -> 0 | H44: =+H43 -> 1067.97 | I44: =+I43 -> 1067.97
A45: Cities | B45: Cities | C45: 01223080 | D45: 0000097118 | E45: MCALLEN, CITY OF | F45: 12332.86 | G45: 0 | H45: =+F45+G45 -> 12332.86 | I45: =+H45 -> 12332.86 | J45: =+I45/H45 -> 1 | L45: 2009 | M45: 8 | N45: 33309 | O45: 40008
E46: Subtotal | F46: =+F45 -> 12332.86 | G46: =+G45 -> 0 | H46: =+H45 -> 12332.86 | I46: =+I45 -> 12332.86
A47: Cities | B47: Cities | C47: 00375405 | D47: 0000097118 | E47: MCALLEN, CITY OF | F47: 1281.93 | G47: 0 | H47: =+F47+G47 -> 1281.93 | I47: =+H47 -> 1281.93 | J47: =+I47/H47 -> 1 | L47: 2009 | M47: 9 | N47: 33309 | O47: 40046
A48: Cities | B48: Cities | C48: 01231135 | D48: 0000097118 | E48: MCALLEN, CITY OF | F48: 8062.22 | G48: 0 | H48: =+F48+G48 -> 8062.22 | I48: =+H48 -> 8062.22 | J48: =+I48/H48 -> 1 | L48: 2009 | M48: 9 | N48: 33309 | O48: 40035
E49: Subtotal | F49: =+F48+F47 -> 9344.15 | G49: =+G48+G47 -> 0 | H49: =+H48+H47 -> 9344.15 | I49: =+I48+I47 -> 9344.15
A50: Cities | B50: Cities | C50: 00379604 | D50: 0000097118 | E50: MCALLEN, CITY OF | F50: 507.5 | G50: 0 | H50: =+F50+G50 -> 507.5 | I50: =+H50 -> 507.5 | J50: =+I50/H50 -> 1 | L50: 2009 | M50: 10 | N50: 33309 | O50: 40099
A51: Cities | B51: Cities | C51: 00379605 | D51: 0000097118 | E51: MCALLEN, CITY OF | F51: 7568.89 | G51: 0 | H51: =+F51+G51 -> 7568.89 | I51: =+H51 -> 7568.89 | J51: =+I51/H51 -> 1 | L51: 2009 | M51: 10 | N51: 33309 | O51: 40094
E52: Subtotal | F52: =+F51+F50 -> 8076.39 | G52: =+G51+G50 -> 0 | H52: =+H51+H50 -> 8076.39 | I52: =+I51+I50 -> 8076.39
A53: Cities | B53: Cities | C53: 00382521 | D53: 0000097118 | E53: MCALLEN, CITY OF | F53: 322.29 | G53: 0 | H53: =+F53+G53 -> 322.29 | I53: =+H53 -> 322.29 | J53: =+I53/H53 -> 1 | L53: 2009 | M53: 11 | N53: 3330942903 | O53: 40120
E54: Subtotal | F54: =+F53 -> 322.29 | G54: =+G53 -> 0 | H54: =+H53 -> 322.29 | I54: =+I53 -> 322.29
A55: Cities | B55: Cities | C55: 00400328 | D55: 0000097118 | E55: MCALLEN, CITY OF | F55: 450.95 | G55: 0 | H55: =+F55+G55 -> 450.95 | I55: =+H55 -> 450.95 | J55: =+I55/H55 -> 1 | L55: 2010 | M55: 4 | N55: 3330944517 | O55: 40256
A56: Cities | B56: Cities | C56: 00402835 | D56: 0000097118 | E56: MCALLEN, CITY OF | F56: 326.5 | G56: 0 | H56: =+F56+G56 -> 326.5 | I56: =+H56 -> 326.5 | J56: =+I56/H56 -> 1 | L56: 2010 | M56: 4 | N56: 3330944896 | O56: 40274
E57: Subtotal | F57: =+F56+F55 -> 777.45 | G57: =+G56+G55 -> 0 | H57: =+H56+H55 -> 777.45 | I57: =+I56+I55 -> 777.45
A58: Cities | B58: Cities | C58: 00404438 | D58: 0000097118 | E58: MCALLEN, CITY OF | F58: 112.15 | G58: 0 | H58: =+F58+G58 -> 112.15 | I58: =+H58 -> 112.15 | J58: =+I58/H58 -> 1 | L58: 2010 | M58: 5 | N58: 45226 | O58: 40290
E59: Subtotal | F59: =+F58 -> 112.15 | G59: =+G58 -> 0 | H59: =+H58 -> 112.15 | I59: =+I58 -> 112.15
A60: Cities | B60: Cities | C60: 00410194 | D60: 0000097118 | E60: MCALLEN, CITY OF | F60: 5895.93 | G60: 0 | H60: =+F60+G60 -> 5895.93 | I60: =+H60 -> 5895.93 | J60: =+I60/H60 -> 1 | L60: 2010 | M60: 7 | N60: 45730 | O60: 40337
E61: Subtotal | F61: =+F60 -> 5895.93 | G61: =+G60 -> 0 | H61: =+H60 -> 5895.93 | I61: =+I60 -> 5895.93
E62: Total MCALLEN, CITY OF | F62: =+F61+F59+F57+F54+F52+F49+F46+F44+F42+F35+F32+F30+F27+F25+F23+F21+F18+F16+F14 -> 234968.2 | G62: =+G61+G59+G57+G54+G52+G49+G46+G44+G42+G35+G32+G30+G27+G25+G23+G21+G18+G16+G14 -> 0 | H62: =+H61+H59+H57+H54+H52+H49+H46+H44+H42+H35+H32+H30+H27+H25+H23+H21+H18+H16+H14 -> 234968.2 | I62: =+I61+I59+I57+I54+I52+I49+I46+I44+I42+I35+I32+I30+I27+I25+I23+I21+I18+I16+I14 -> 234968.2
A63: Total Cities | F63: =+F62 -> 234968.2 | G63: =+G62 -> 0 | H63: =+H62 -> 234968.2 | I63: =+I62 -> 234968.2
A66: Legal | B66: Legal | C66: 01042241 | D66: 0000199577 | E66: BRACEWELL & GIULIANI | F66: 41033.27 | G66: 0 | H66: =+F66+G66 -> 41033.27 | I66: =+H66 -> 41033.27 | J66: =+I66/H66 -> 1 | L66: 2008 | M66: 2 | N66: 21360991 | O66: 39490
E67: Subtotal | F67: =+F66 -> 41033.27 | G67: =+G66 -> 0 | H67: =+H66 -> 41033.27 | I67: =+I66 -> 41033.27
A68: Legal | B68: Legal | C68: 01049157 | D68: 0000199577 | E68: BRACEWELL & GIULIANI | F68: 1154.36 | G68: 0 | H68: =+F68+G68 -> 1154.36 | I68: =+H68 -> 1154.36 | J68: =+I68/H68 -> 1 | L68: 2008 | M68: 3 | N68: 21362731 | O68: 39511
E69: Subtotal | F69: =+F68 -> 1154.36 | G69: =+G68 -> 0 | H69: =+H68 -> 1154.36 | I69: =+I68 -> 1154.36
A70: Legal | B70: Legal | C70: 01060155 | D70: 0000199577 | E70: BRACEWELL & GIULIANI | F70: 2855.68 | G70: 0 | H70: =+F70+G70 -> 2855.68 | I70: =+H70 -> 2855.68 | J70: =+I70/H70 -> 1 | L70: 2008 | M70: 4 | N70: 21366200 | O70: 39541
E71: Subtotal | F71: =+F70 -> 2855.68 | G71: =+G70 -> 0 | H71: =+H70 -> 2855.68 | I71: =+I70 -> 2855.68
A72: Legal | B72: Legal | C72: 01085427 | D72: 0000199577 | E72: BRACEWELL & GIULIANI | F72: 3147.32 | G72: 0 | H72: =+F72+G72 -> 3147.32 | I72: =+H72 -> 3147.32 | J72: =+I72/H72 -> 1 | L72: 2008 | M72: 6 | N72: 21374055 | O72: 39611
E73: Subtotal | F73: =+F72 -> 3147.32 | G73: =+G72 -> 0 | H73: =+H72 -> 3147.32 | I73: =+I72 -> 3147.32
A74: Legal | B74: Legal | C74: 01111007 | D74: 0000199577 | E74: BRACEWELL & GIULIANI | F74: 23065.44 | G74: 0 | H74: =+F74+G74 -> 23065.44 | I74: =+H74 -> 23065.44 | J74: =+I74/H74 -> 1 | L74: 2008 | M74: 8 | N74: 21380766 | O74: 39675
E75: Subtotal | F75: =+F74 -> 23065.44 | G75: =+G74 -> 0 | H75: =+H74 -> 23065.44 | I75: =+I74 -> 23065.44
A76: Legal | B76: Legal | C76: 01120860 | D76: 0000199577 | E76: BRACEWELL & GIULIANI | F76: 5593.48 | G76: 0 | H76: =+F76+G76 -> 5593.48 | I76: =+H76 -> 5593.48 | J76: =+I76/H76 -> 1 | L76: 2008 | M76: 9 | N76: 21384375 | O76: 39709
E77: Subtotal | F77: =+F76 -> 5593.48 | G77: =+G76 -> 0 | H77: =+H76 -> 5593.48 | I77: =+I76 -> 5593.48
A78: Legal | B78: Legal | C78: 01131072 | D78: 0000199577 | E78: BRACEWELL & GIULIANI | F78: 22074.14 | G78: 0 | H78: =+F78+G78 -> 22074.14 | I78: =+H78 -> 22074.14 | J78: =+I78/H78 -> 1 | L78: 2008 | M78: 10 | N78: 21387756 | O78: 39734
E79: Subtotal | F79: =+F78 -> 22074.14 | G79: =+G78 -> 0 | H79: =+H78 -> 22074.14 | I79: =+I78 -> 22074.14
A80: Legal | B80: Legal | C80: 01139671 | D80: 0000199577 | E80: BRACEWELL & GIULIANI | F80: 13257.4 | G80: 0 | H80: =+F80+G80 -> 13257.4 | I80: =+H80 -> 13257.4 | J80: =+I80/H80 -> 1 | L80: 2008 | M80: 11 | N80: 21389410 | O80: 39757
E81: Subtotal | F81: =+F80 -> 13257.4 | G81: =+G80 -> 0 | H81: =+H80 -> 13257.4 | I81: =+I80 -> 13257.4
A82: Legal | B82: Legal | C82: 01159638 | D82: 0000199577 | E82: BRACEWELL & GIULIANI | F82: 4699.5 | G82: 0 | H82: =+F82+G82 -> 4699.5 | I82: =+H82 -> 4699.5 | J82: =+I82/H82 -> 1 | L82: 2008 | M82: 12 | N82: 21395109 | O82: 39813
A83: Legal | B83: Legal | C83: 01150213 | D83: 0000199577 | E83: BRACEWELL & GIULIANI | F83: 13031.14 | G83: 0 | H83: =+F83+G83 -> 13031.14 | I83: =+H83 -> 13031.14 | J83: =+I83/H83 -> 1 | L83: 2008 | M83: 12 | N83: 21392214 | O83: 39784
E84: Subtotal | F84: =+F83+F82 -> 17730.64 | G84: =+G83+G82 -> 0 | H84: =+H83+H82 -> 17730.64 | I84: =+I83+I82 -> 17730.64
A85: Legal | B85: Legal | C85: 01192124 | D85: 0000199577 | E85: BRACEWELL & GIULIANI | F85: 513.8 | G85: 0 | H85: =+F85+G85 -> 513.8 | I85: =+H85 -> 513.8 | J85: =+I85/H85 -> 1 | L85: 2009 | M85: 4 | N85: 21405640 | O85: 39912
E86: Subtotal | F86: =+F85 -> 513.8 | G86: =+G85 -> 0 | H86: =+H85 -> 513.8 | I86: =+I85 -> 513.8
A87: Legal | B87: Legal | C87: 00358546 | D87: 0000199577 | E87: BRACEWELL & GIULIANI | F87: 655.74 | G87: 0 | H87: =+F87+G87 -> 655.74 | I87: =+H87 -> 655.74 | J87: =+I87/H87 -> 1 | L87: 2009 | M87: 5 | N87: 21399929 | O87: 39854
E88: Subtotal | F88: =+F87 -> 655.74 | G88: =+G87 -> 0 | H88: =+H87 -> 655.74 | I88: =+I87 -> 655.74
A89: Legal | B89: Legal | C89: 00369631 | D89: 0000199577 | E89: BRACEWELL & GIULIANI | F89: 8699.75 | G89: 0 | H89: =+F89+G89 -> 8699.75 | I89: =+H89 -> 8699.75 | J89: =+I89/H89 -> 1 | L89: 2009 | M89: 8 | N89: 21416700 | O89: 40035
E90: Subtotal | F90: =+F89 -> 8699.75 | G90: =+G89 -> 0 | H90: =+H89 -> 8699.75 | I90: =+I89 -> 8699.75
A91: Legal | B91: Legal | C91: 00401472 | D91: 0000199577 | E91: BRACEWELL & GIULIANI | F91: 969 | G91: 0 | H91: =+F91+G91 -> 969 | I91: =+H91 -> 969 | J91: =+I91/H91 -> 1 | L91: 2010 | M91: 4 | N91: 21438582 | O91: 40273
E92: Subtotal | F92: =+F91 -> 969 | G92: =+G91 -> 0 | H92: =+H91 -> 969 | I92: =+I91 -> 969
A93: Legal | B93: Legal | C93: 00404322 | D93: 0000199577 | E93: BRACEWELL & GIULIANI | F93: 1938 | G93: 0 | H93: =+F93+G93 -> 1938 | I93: =+H93 -> 1938 | J93: =+I93/H93 -> 1 | L93: 2010 | M93: 5 | N93: 21442031 | O93: 40304
E94: Subtotal | F94: =+F93 -> 1938 | G94: =+G93 -> 0 | H94: =+H93 -> 1938 | I94: =+I93 -> 1938
A95: Legal | B95: Legal | C95: 00421719 | D95: 0000199577 | E95: BRACEWELL & GIULIANI | F95: 741 | G95: 0 | H95: =+F95+G95 -> 741 | I95: =+H95 -> 741 | J95: =+I95/H95 -> 1 | L95: 2010 | M95: 10 | N95: 21456067 | O95: 40457
E96: Subtotal | F96: =+F95 -> 741 | G96: =+G95 -> 0 | H96: =+H95 -> 741 | I96: =+I95 -> 741
A97: Legal | B97: Legal | C97: 00425623 | D97: 0000199577 | E97: BRACEWELL & GIULIANI | F97: 285 | G97: 0 | H97: =+F97+G97 -> 285 | I97: =+H97 -> 285 | J97: =+I97/H97 -> 1 | L97: 2010 | M97: 11 | N97: 21459912 | O97: 40490
E98: Subtotal | F98: =+F97 -> 285 | G98: =+G97 -> 0 | H98: =+H97 -> 285 | I98: =+I97 -> 285
A99: Legal | B99: Legal | C99: 00430318 | D99: 0000199577 | E99: BRACEWELL & GIULIANI | F99: 3627.06 | G99: 0 | H99: =+F99+G99 -> 3627.06 | I99: =+H99 -> 3627.06 | J99: =+I99/H99 -> 1 | L99: 2010 | M99: 12 | N99: 21463709 | O99: 40519
E100: Subtotal | F100: =+F99 -> 3627.06 | G100: =+G99 -> 0 | H100: =+H99 -> 3627.06 | I100: =+I99 -> 3627.06
E101: Total BRACEWELL & GIULIANI | F101: =+F100+F98+F96+F94+F92+F90+F88+F86+F84+F81+F79+F77+F75+F73+F71+F69+F67 -> 147341.08 | G101: =+G100+G98+G96+G94+G92+G90+G88+G86+G84+G81+G79+G77+G75+G73+G71+G69+G67 -> 0 | H101: =+H100+H98+H96+H94+H92+H90+H88+H86+H84+H81+H79+H77+H75+H73+H71+H69+H67 -> 147341.08 | I101: =+I100+I98+I96+I94+I92+I90+I88+I86+I84+I81+I79+I77+I75+I73+I71+I69+I67 -> 147341.08
A103: Legal | B103: Legal | C103: 01045578 | D103: 0000001353 | E103: CLARK THOMAS & WINTERS | F103: 9782.09 | G103: 0 | H103: =+F103+G103 -> 9782.09 | I103: =+H103 -> 9782.09 | J103: =+I103/H103 -> 1 | L103: 2008 | M103: 2 | N103: 147346 | O103: 39500
A104: Legal | B104: Legal | C104: 01045580 | D104: 0000001353 | E104: CLARK THOMAS & WINTERS | F104: 294.5 | G104: 0 | H104: =+F104+G104 -> 294.5 | I104: 228.47 | J104: =+I104/H104 -> 0.77578947 | L104: 2008 | M104: 2 | N104: 147354 | O104: 39500
E105: Subtotal | F105: =+F104+F103 -> 10076.59 | G105: =+G104+G103 -> 0 | H105: =+H104+H103 -> 10076.59 | I105: =+I104+I103 -> 10010.56
A106: legal | B106: legal | C106: 01054345 | D106: 0000001353 | E106: CLARK THOMAS & WINTERS | F106: 208.5 | G106: 0 | H106: =+F106+G106 -> 208.5 | I106: =+H106 -> 208.5 | J106: =+I106/H106 -> 1 | L106: 2008 | M106: 3 | N106: 147951 | O106: 39524
...

Sheet Trailing Charges North
A1: AMERICAN ELECTRIC POWER TEXAS INC
A2: SUMMARY OF RATE CASE EXPENSES
A3: PUC DOCKET NO. 33310 (NORTH)
A8: Category | B8: Descr | C8: Voucher | D8: Vendor | E8: Name | F8: Amount | G8: Adjustment | H8: Total | I8: North Division Requested | J8: North % | K8: Employee Name | L8: Year | M8: Period | N8: Invoice | O8: Invoice Date
A9: Cities | B9: Cities | C9: 01087298 | D9: 0000097098 | E9: ABILENE, CITY OF | F9: 273.5 | G9: 0 | H9: =+F9+G9 -> 273.5 | I9: =+H9 -> 273.5 | J9: =+I9/H9 -> 1 | L9: 2008 | M9: 6 | N9: 3331035913 | O9: 39575
A10: Cities | B10: Cities | C10: 01091322 | D10: 0000097098 | E10: ABILENE, CITY OF | F10: 633.64 | G10: 0 | H10: =+F10+G10 -> 633.64 | I10: =+H10 -> 633.64 | J10: =+I10/H10 -> 1 | L10: 2008 | M10: 6 | N10: 33310 | O10: 39617
E11: Subtotal | F11: =+F10+F9 -> 907.14 | G11: =+G10+G9 -> 0 | H11: =+H10+H9 -> 907.14 | I11: =+I10+I9 -> 907.14
A12: Cities | B12: Cities | C12: 01104330 | D12: 0000097098 | E12: ABILENE, CITY OF | F12: 29 | G12: 0 | H12: =+F12+G12 -> 29 | I12: =+G12+H12 -> 29 | J12: =+I12/H12 -> 1 | L12: 2008 | M12: 8 | N12: 3331036540 | O12: 39626
E13: Subtotal | F13: =+F12 -> 29 | G13: =+G12 -> 0 | H13: =+H12 -> 29 | I13: =+H13 -> 29
A14: Cities | B14: Cities | C14: 01151452 | D14: 0000097098 | E14: ABILENE, CITY OF | F14: 158.5 | G14: 0 | H14: =+F14+G14 -> 158.5 | I14: =+G14+H14 -> 158.5 | J14: =+I14/H14 -> 1 | L14: 2008 | M14: 12 | N14: 35913 | O14: 39778
E15: Subtotal | F15: =+F14 -> 158.5 | G15: =+G14 -> 0 | H15: =+H14 -> 158.5 | I15: =+I14 -> 158.5
E16: Total ABILENE, CITY OF | F16: =+F15+F13+F11 -> 1094.64 | G16: =+G15+G13+G11 -> 0 | H16: =+H15+H13+H11 -> 1094.64 | I16: =+I15+I13+I11 -> 1094.64
A17: Total Cities | F17: =+F16 -> 1094.64 | G17: =+G16 -> 0 | H17: =+H16 -> 1094.64 | I17: =+I16 -> 1094.64
A19: Legal | B19: Legal | C19: 01045580 | D19: 0000001353 | E19: CLARK THOMAS & WINTERS | F19: 294.5 | G19: 0 | H19: =+F19+G19 -> 294.5 | I19: 66.05 | J19: =+I19/H19 -> 0.22427844 | L19: 2008 | M19: 2 | N19: 147354 | O19: 39500
E20: Subtotal | F20: =+F19 -> 294.5 | G20: =+G19 -> 0 | H20: =+H19 -> 294.5 | I20: =+I19 -> 66.05
A21: Legal | B21: Legal | C21: 01054347 | D21: 0000001353 | E21: CLARK THOMAS & WINTERS | F21: 18 | G21: 0 | H21: =+F21+G21 -> 18 | I21: 4.04 | J21: =+I21/H21 -> 0.22444444 | L21: 2008 | M21: 3 | N21: 147958 | O21: 39524
E22: Subtotal | F22: =+F21 -> 18 | G22: =+G21 -> 0 | H22: =+H21 -> 18 | I22: =+I21 -> 4.04
A23: Legal | B23: Legal | C23: 01064198 | D23: 0000001353 | E23: CLARK THOMAS & WINTERS | F23: 4943.29 | G23: 0 | H23: =+F23+G23 -> 4943.29 | I23: 1111.37 | J23: =+I23/H23 -> 0.22482395 | L23: 2008 | M23: 4 | N23: 149417 | O23: 39552
E24: Subtotal | F24: =+F23 -> 4943.29 | G24: =+G23 -> 0 | H24: =+H23 -> 4943.29 | I24: =+I23 -> 1111.37
A25: Legal | B25: Legal | C25: 01079983 | D25: 0000001353 | E25: CLARK THOMAS & WINTERS | F25: 1991.33 | G25: 0 | H25: =+F25+G25 -> 1991.33 | I25: 447.7 | J25: =+I25/H25 -> 0.22482461 | L25: 2008 | M25: 5 | N25: 151472 | O25: 39591
E26: Subtotal | F26: =+F25 -> 1991.33 | G26: =+G25 -> 0 | H26: =+H25 -> 1991.33 | I26: =+I25 -> 447.7
A27: Legal | B27: Legal | C27: 01089740 | D27: 0000001353 | E27: CLARK THOMAS & WINTERS | F27: 873 | G27: 0 | H27: =+F27+G27 -> 873 | I27: 198.04 | J27: =+I27/H27 -> 0.22684994 | L27: 2008 | M27: 6 | N27: 152844 | O27: 39622
E28: Subtotal | F28: =+F27 -> 873 | G28: =+G27 -> 0 | H28: =+H27 -> 873 | I28: =+I27 -> 198.04
E29: Total CLARK THOMAS & WINTERS | F29: =+F28+F26+F24+F22+F20 -> 8120.12 | G29: =+G28+G26+G24+G22+G20 -> 0 | H29: =+H28+H26+H24+H22+H20 -> 8120.12 | I29: =+I28+I26+I24+I22+I20 -> 1827.2
A30: Total Legal | F30: =+F29 -> 8120.12 | G30: =+G29 -> 0 | H30: =+H29 -> 8120.12 | I30: =+I29 -> 1827.2
A32: Grand Total- North Trailing Charges Docket Nos. 31433/33310/34310 | F32: =+F30+F17 -> 9214.76 | G32: =+G30+G17 -> 0 | H32: =+H30+H17 -> 9214.76 | I32: =+I30+I17 -> 2921.84
