Workbook
Name a: #REF!
Name a: #REF!
Name page1: #REF!
Name page10: #REF!
Name page2: #REF!
Name page3: #REF!
Name page4: #REF!
Name page5: #REF!
Name page6: #REF!
Name page7: #REF!
Name page8: #REF!
Name page9: #REF!
Name q: [2]Summary!#REF!
Name q: [2]Summary!#REF!
Name ResBasic: [3]Summary!#REF!
Name ResBasic: [3]Summary!#REF!
Name ResEconomy1: [3]Summary!#REF!
Name ResEconomy1: [3]Summary!#REF!
Name ResEconomy2: [3]Summary!#REF!
Name ResEconomy2: [3]Summary!#REF!
Name ResWaterHeating: [3]Summary!#REF!
Name ResWaterHeating: [3]Summary!#REF!
Name test: [2]Summary!#REF!
Name test: [2]Summary!#REF!
Name test1: [2]Summary!#REF!
Name test1: [2]Summary!#REF!
Name total: #REF!
Name w: [2]Summary!#REF!
Name w: [2]Summary!#REF!

Sheet II-H-1
B2: PUBLIC UTILITY COMMISSION OF TEXAS
B3: AEP TEXAS INC
B4: II-H-1 SUMMARY OF TEST YEAR ADJUSTMENTS
B5: TEST YEAR ENDING 12/31/2018
B6: DOCKET NUMBER (PENDING ASSIGNMENT)
B9: Refer to Schedule II-H-1.1 for the summary of test year adjustments

Sheet II-H-1.1
B2: PUBLIC UTILITY COMMISSION OF TEXAS
B3: AEP TEXAS INC
B4: II-H-1.1 TEST YEAR SALES DATA
B5: TEST YEAR ENDING 12/31/2018
B6: DOCKET NUMBER (PENDING ASSIGNMENT)
A8: AEP TEXAS
A9: TEST YEAR DATA BY RATE CLASS
A10: FOR TEST YEAR ENDED DECEMBER 31, 2018
D12: Average | E12: Year-end | F12: Unadjusted | G12: Weather kWh | H12: Customer kWh | I12: Other kWh | J12: Adjusted
A13: LINE | B13: DESCRIPTION | C13: VOLT | D13: Customers | E13: Customers | F13: kWh at Meter | G13: Adjustment | H13: Adjustment | I13: Adjustment | J13: kWh
A15: 1 | B15: RESIDENTIAL SERVICE | C15: SEC | D15: ='II-H-3.1-3'!Q14 -> 871709.17 | E15: ='II-H-3.1-3'!O14 -> 876553 | F15: ='II-H-1.2'!P14 -> 12103111472 | G15: ='II-H-1.2'!P44 -> -169072907 | H15: ='II-H-1.2'!P74 -> 63143017 | I15: ='II-H-1.2'!P106 -> 0 | J15: ='II-H-1.2'!P136 -> 1.1997182e+10
A17: 2 | B17: SECONDARY < 10 kW | C17: SEC | D17: ='II-H-3.1-3'!Q16 -> 89262.917 | E17: ='II-H-3.1-3'!O16 -> 89158 | F17: ='II-H-1.2'!P16 -> 580596232 | G17: ='II-H-1.2'!P46 -> -345003.32 | H17: ='II-H-1.2'!P76 -> -947844.49 | I17: ='II-H-1.2'!P108 -> 0 | J17: ='II-H-1.2'!P138 -> 5.7930338e+08
A19: 3 | B19: SECONDARY > 10 kW NCP | C19: SEC | D19: ='II-H-3.1-3'!Q18 -> 71945.25 | E19: ='II-H-3.1-3'!O18 -> 72592 | F19: ='II-H-1.2'!P18 -> 8003640659 | G19: ='II-H-1.2'!P48 -> -1982220.5 | H19: ='II-H-1.2'!P78 -> 68711313 | I19: ='II-H-1.2'!P110 -> 0 | J19: ='II-H-1.2'!P140 -> 8.0703698e+09
A20: 4 | B20: SECONDARY > 10 Kw 4CP | C20: SEC | D20: ='II-H-3.1-3'!Q19 -> 493 | E20: ='II-H-3.1-3'!O19 -> 478 | F20: ='II-H-1.2'!P19 -> 1211080649 | G20: ='II-H-1.2'!P49 -> -1430125.9 | H20: ='II-H-1.2'!P79 -> -33749815 | I20: ='II-H-1.2'!P111 -> 0 | J20: ='II-H-1.2'!P141 -> 1.1759007e+09
A21: 5 | B21: TOTAL SECONDARY > 10 kW | D21: =SUM(D19:D20) -> 72438.25 | E21: =SUM(E19:E20) -> 73070 | F21: =SUM(F19:F20) -> 9214721308 | G21: =SUM(G19:G20) -> -3412346.4 | H21: =SUM(H19:H20) -> 34961497 | I21: =SUM(I19:I20) -> 0 | J21: =SUM(J19:J20) -> 9.2462705e+09
A23: 6 | B23: PRIMARY NCP | C23: PRI | D23: ='II-H-3.1-3'!Q22 -> 570.5 | E23: ='II-H-3.1-3'!O22 -> 574 | F23: ='II-H-1.2'!P22 -> 303778954 | G23: ='II-H-1.2'!P52 -> 457811.69 | H23: ='II-H-1.2'!P82 -> 1814803.6 | I23: ='II-H-1.2'!P114 -> 0 | J23: ='II-H-1.2'!P144 -> 3.0605157e+08
A24: 7 | B24: PRIMARY 4CP | C24: PRI | D24: ='II-H-3.1-3'!Q23 -> 471.75 | E24: ='II-H-3.1-3'!O23 -> 471 | F24: ='II-H-1.2'!P23 -> 4089664935 | G24: ='II-H-1.2'!P53 -> 0 | H24: ='II-H-1.2'!P83 -> -5969816.8 | I24: ='II-H-1.2'!P115 -> 0 | J24: ='II-H-1.2'!P145 -> 4.0836951e+09
A25: 8 | B25: TOTAL PRIMARY | D25: =SUM(D23:D24) -> 1042.25 | E25: =SUM(E23:E24) -> 1045 | F25: =SUM(F23:F24) -> 4393443889 | G25: =SUM(G23:G24) -> 457811.69 | H25: =SUM(H23:H24) -> -4155013.1 | I25: =SUM(I23:I24) -> 0 | J25: =SUM(J23:J24) -> 4.3897467e+09
A27: 9 | B27: TRANSMISSION | C27: TRA | D27: ='II-H-3.1-3'!Q26 -> 85 | E27: ='II-H-3.1-3'!Q26 -> 85 | F27: ='II-H-1.2'!P26 -> 5453190408 | G27: ='II-H-1.2'!P56 -> 0 | H27: ='II-H-1.2'!P86 -> 2.918065e+08 | I27: ='II-H-1.2'!P118 -> 0 | J27: ='II-H-1.2'!P148 -> 5.7449969e+09
A29: 10 | B29: LIGHTING | C29: SEC | D29: ='II-H-3.1-3'!Q28 -> 220662.25 | E29: =1873+428 -> 2301 | F29: ='II-H-1.2'!P28 -> 262407146 | G29: ='II-H-1.2'!P58 -> 0 | H29: ='II-H-1.2'!P88 -> -181100.56 | I29: ='II-H-1.2'!P120 -> 0 | J29: ='II-H-1.2'!P150 -> 2.6222605e+08
A31: 11 | B31: TOTAL RETAIL | D31: =D29+D27+D25+D21+D17+D15 -> 1255199.8 | E31: =E29+E27+E25+E21+E17+E15 -> 1042212 | F31: =F29+F27+F25+F21+F17+F15 -> 32007470455 | G31: =G29+G27+G25+G21+G17+G15 -> -172372445 | H31: =H29+H27+H25+H21+H17+H15 -> 3.8462706e+08 | I31: =I29+I27+I25+I21+I17+I15 -> 0 | J31: =J29+J27+J25+J21+J17+J15 -> 3.2219725e+10
A33: 12 | B33: WHOLESALE PRI | C33: PRI | D33: ='II-H-3.1-3'!Q32 -> 0 | E33: ='II-H-3.1-3'!O32 -> 0 | F33: ='II-H-1.2'!P32 -> 0 | G33: ='II-H-1.2'!P62 -> 0 | H33: ='II-H-1.2'!P92 -> 0 | I33: ='II-H-1.2'!P124 -> 0 | J33: ='II-H-1.2'!P154 -> 0
A34: 13 | B34: WHOLESALE TRANS | C34: TRA | D34: ='II-H-3.1-3'!Q33 -> 0 | E34: ='II-H-3.1-3'!O33 -> 0 | F34: ='II-H-1.2'!P33 -> 0 | G34: ='II-H-1.2'!P63 -> 0 | H34: ='II-H-1.2'!P93 -> 0 | I34: ='II-H-1.2'!P125 -> 0
A35: 14 | B35: TOTAL WHOLESALE | D35: ='II-H-3.1-3'!Q131 -> 0 | E35: ='II-H-3.1-3'!O131 -> 0 | F35: =SUM(F33:F34) -> 0 | G35: =SUM(G33:G34) -> 0 | H35: =SUM(H33:H34) -> 0 | I35: =SUM(I33:I34) -> 0 | J35: =SUM(J33:J34) -> 0
A37: 15 | B37: TOTAL AEP TX | D37: =+D35+D31 -> 1255199.8 | E37: =+E35+E31 -> 1042212 | F37: =+F35+F31 -> 32007470455 | G37: =+G35+G31 -> -172372445 | H37: =+H35+H31 -> 3.8462706e+08 | I37: =+I35+I31 -> 0 | J37: =+J35+J31 -> 3.2219725e+10
B39: Note: Secondary < 10 kW includes Unmetered service; Lighting customers are fixture counts.

Sheet II-H-1.2
B2: PUBLIC UTILITY COMMISSION OF TEXAS
B3: AEP TEXAS INC
B4: II-H-1.2 MONTHLY SALES DATA
B5: TEST YEAR ENDING 12/31/2018
B6: DOCKET NUMBER (PENDING ASSIGNMENT)
B7: AEP TEXAS
B8: UNADJUSTED BILLING KWH AT METER
B9: FOR TEST YEAR ENDED DECEMBER 31, 2018
A12: LINE | B12: DESCRIPTION | C12: VOLT | D12: JANUARY | E12: FEBRUARY | F12: MARCH | G12: APRIL | H12: MAY | I12: JUNE | J12: JULY | K12: AUGUST | L12: SEPTEMBER | M12: OCTOBER | N12: NOVEMBER | O12: DECEMBER | P12: TOTAL
Q13: dist rate | R13: trans rate
A14: 1 | B14: RESIDENTIAL SERVICE | C14: SEC | D14: ='[4]II-H-1.2'!$D$8+'[5]II-H-1.2'!$D$8 -> 1187765247 | E14: ='[4]II-H-1.2'!$E$8+'[5]II-H-1.2'!$E$8 -> 880784604 | F14: ='[4]II-H-1.2'!$F$8+'[5]II-H-1.2'!$F$8 -> 702884785 | G14: ='[4]II-H-1.2'!$G$8+'[5]II-H-1.2'!$G$8 -> 737229219 | H14: ='[6]Billed kWh'!J85+'[5]II-H-1.2'!$H$8 -> 818132631 | I14: ='[6]Billed kWh'!K85+'[5]II-H-1.2'!$I$8 -> 1248494359 | J14: ='[6]Billed kWh'!L85+'[5]II-H-1.2'!$J$8 -> 1307274429 | K14: ='[6]Billed kWh'!M85+'[5]II-H-1.2'!$K$8 -> 1327155842 | L14: ='[6]Billed kWh'!N85+'[5]II-H-1.2'!$L$8 -> 1281003285 | M14: ='[6]Billed kWh'!O85+'[5]II-H-1.2'!$M$8 -> 999055732 | N14: ='[6]Billed kWh'!P85+'[5]II-H-1.2'!$N$8 -> 758197962 | O14: ='[6]Billed kWh'!Q85+'[5]II-H-1.2'!$O$8 -> 855133377 | P14: =SUM(D14:O14) -> 12103111472 | Q14: ='II-H-4.1 Functions'!F15/'II-H-1.2'!P14 -> 0.014721066 | R14: ='II-H-4.1 Functions'!H15/'II-H-1.2'!P14 -> 0.0052870156
A16: 2 | B16: SECONDARY < 10 kW | C16: SEC | D16: ='[6]Billed kWh'!F12+'[5]II-H-1.2'!$D$10 -> 52387683 | E16: ='[6]Billed kWh'!G12+'[5]II-H-1.2'!$E$10 -> 44007425 | F16: ='[6]Billed kWh'!H12+'[5]II-H-1.2'!$F$10 -> 41415235 | G16: ='[6]Billed kWh'!I12+'[5]II-H-1.2'!$G$10 -> 43220513 | H16: ='[6]Billed kWh'!J12+'[5]II-H-1.2'!$H$10 -> 43994819 | I16: ='[6]Billed kWh'!K12+'[5]II-H-1.2'!$I$10 -> 53800786 | J16: ='[6]Billed kWh'!L12+'[5]II-H-1.2'!$J$10 -> 55164376 | K16: ='[6]Billed kWh'!M12+'[5]II-H-1.2'!$K$10 -> 55433077 | L16: ='[6]Billed kWh'!N12+'[5]II-H-1.2'!$L$10 -> 55189705 | M16: ='[6]Billed kWh'!O12+'[5]II-H-1.2'!$M$10 -> 48472763 | N16: ='[6]Billed kWh'!P12+'[5]II-H-1.2'!$N$10 -> 42646592 | O16: ='[6]Billed kWh'!Q12+'[5]II-H-1.2'!$O$10 -> 44863258 | P16: =SUM(D16:O16) -> 580596232 | Q16: ='II-H-4.1 Functions'!F17/'II-H-1.2'!P16 -> 0.019511289 | R16: ='II-H-4.1 Functions'!H17/'II-H-1.2'!P16 -> 0.0026675947
A18: 3 | B18: SECONDARY > 10 kW NCP | C18: SEC | D18: ='[6]Billed kWh'!F30+'[5]II-H-1.2'!$D$12 -> 617758227 | E18: ='[6]Billed kWh'!G30+'[5]II-H-1.2'!$E$12 -> 556084841 | F18: ='[6]Billed kWh'!H30+'[5]II-H-1.2'!$F$12 -> 558942613 | G18: ='[6]Billed kWh'!I30+'[5]II-H-1.2'!$G$12 -> 605162513 | H18: ='[6]Billed kWh'!J30+'[5]II-H-1.2'!$H$12 -> 628387410 | I18: ='[6]Billed kWh'!K30+'[5]II-H-1.2'!$I$12 -> 779428797 | J18: ='[6]Billed kWh'!L30+'[5]II-H-1.2'!$J$12 -> 788525135 | K18: ='[6]Billed kWh'!M30+'[5]II-H-1.2'!$K$12 -> 797101000 | L18: ='[6]Billed kWh'!N30+'[5]II-H-1.2'!$L$12 -> 806339744 | M18: ='[6]Billed kWh'!O30+'[5]II-H-1.2'!$M$12 -> 699340712 | N18: ='[6]Billed kWh'!P30+'[5]II-H-1.2'!$N$12 -> 585836747 | O18: ='[6]Billed kWh'!Q30+'[5]II-H-1.2'!$O$12 -> 580732920 | P18: =SUM(D18:O18) -> 8003640659
A19: 4 | B19: SECONDARY > 10 kW 4CP | C19: SEC | D19: ='[6]Billed kWh'!F21+'[5]II-H-1.2'!D13 -> 103285168 | E19: ='[6]Billed kWh'!G21+'[5]II-H-1.2'!E13 -> 88205306 | F19: ='[6]Billed kWh'!H21+'[5]II-H-1.2'!F13 -> 88837676 | G19: ='[6]Billed kWh'!I21+'[5]II-H-1.2'!G13 -> 92617462 | H19: ='[6]Billed kWh'!J21+'[5]II-H-1.2'!H13 -> 96277050 | I19: ='[6]Billed kWh'!K21+'[5]II-H-1.2'!I13 -> 101782093 | J19: ='[6]Billed kWh'!L21+'[5]II-H-1.2'!J13 -> 112888067 | K19: ='[6]Billed kWh'!M21+'[5]II-H-1.2'!K13 -> 107756758 | ... O19: ='[6]Billed kWh'!Q21+'[5]II-H-1.2'!O13 -> 92547279 | P19: =SUM(D19:O19) -> 1211080649
A20: 5 | B20: TOTAL SECONDARY > 10 kW | D20: =SUM(D18:D19) -> 721043395 | E20: =SUM(E18:E19) -> 644290147 | F20: =SUM(F18:F19) -> 647780289 | G20: =SUM(G18:G19) -> 697779975 | H20: =SUM(H18:H19) -> 724664460 | I20: =SUM(I18:I19) -> 881210890 | J20: =SUM(J18:J19) -> 901413202 | K20: =SUM(K18:K19) -> 904857758 | ... P20: =SUM(P18:P19) -> 9214721308
A22: 6 | B22: PRIMARY NCP | C22: PRI | D22: ='[6]Billed kWh'!F82+'[5]II-H-1.2'!D16 -> 22763927 | E22: ='[6]Billed kWh'!G82+'[5]II-H-1.2'!E16 -> 22233694 | F22: ='[6]Billed kWh'!H82+'[5]II-H-1.2'!F16 -> 21505721 | G22: ='[6]Billed kWh'!I82+'[5]II-H-1.2'!G16 -> 23581205 | H22: ='[6]Billed kWh'!J82+'[5]II-H-1.2'!H16 -> 24029745 | I22: ='[6]Billed kWh'!K82+'[5]II-H-1.2'!I16 -> 27769076 | J22: ='[6]Billed kWh'!L82+'[5]II-H-1.2'!J16 -> 25217671 | K22: ='[6]Billed kWh'!M82+'[5]II-H-1.2'!K16 -> 29729548 | ... O22: ='[6]Billed kWh'!Q82+'[5]II-H-1.2'!O16 -> 25367936 | P22: =SUM(D22:O22) -> 303778954
A23: 7 | B23: PRIMARY 4CP | C23: PRI | D23: ='[6]Billed kWh'!F77+'[5]II-H-1.2'!D17 -> 328485905 | E23: ='[6]Billed kWh'!G77+'[5]II-H-1.2'!E17 -> 292364752 | F23: ='[6]Billed kWh'!H77+'[5]II-H-1.2'!F17 -> 312199493 | G23: ='[6]Billed kWh'!I77+'[5]II-H-1.2'!G17 -> 320624447 | H23: ='[6]Billed kWh'!J77+'[5]II-H-1.2'!H17 -> 338718878 | I23: ='[6]Billed kWh'!K77+'[5]II-H-1.2'!I17 -> 370216564 | J23: ='[6]Billed kWh'!L77+'[5]II-H-1.2'!J17 -> 364949086 | K23: ='[6]Billed kWh'!M77+'[5]II-H-1.2'!K17 -> 367964122 | ... O23: ='[6]Billed kWh'!Q77+'[5]II-H-1.2'!O17 -> 328944965 | P23: =SUM(D23:O23) -> 4089664935
A24: 8 | B24: TOTAL PRIMARY | D24: =SUM(D22:D23) -> 351249832 | E24: =SUM(E22:E23) -> 314598446 | F24: =SUM(F22:F23) -> 333705214 | G24: =SUM(G22:G23) -> 344205652 | H24: =SUM(H22:H23) -> 362748623 | I24: =SUM(I22:I23) -> 397985640 | J24: =SUM(J22:J23) -> 390166757 | K24: =SUM(K22:K23) -> 397693670 | ... P24: =SUM(P22:P23) -> 4393443889
A26: 9 | B26: TRANSMISSION | C26: TRA | D26: ='[6]Billed kWh'!F97+'[5]II-H-1.2'!D20 -> 530719273 | E26: ='[6]Billed kWh'!G97+'[5]II-H-1.2'!E20 -> 349122435 | F26: ='[6]Billed kWh'!H97+'[5]II-H-1.2'!F20 -> 568341249 | G26: ='[6]Billed kWh'!I97+'[5]II-H-1.2'!G20 -> 536467367 | H26: ='[6]Billed kWh'!J97+'[5]II-H-1.2'!H20 -> 501093104 | I26: ='[6]Billed kWh'!K97+'[5]II-H-1.2'!I20 -> 504926500 | J26: ='[6]Billed kWh'!L97+'[5]II-H-1.2'!J20 -> 368328476 | K26: ='[6]Billed kWh'!M97+'[5]II-H-1.2'!K20 -> 415971240 | ... O26: ='[6]Billed kWh'!Q97+'[5]II-H-1.2'!O20 -> 364087140 | P26: =SUM(D26:O26) -> 5453190408
A28: 10 | B28: LIGHTING | C28: SEC | D28: ='[6]Billed kWh'!F71+'[5]II-H-1.2'!D22 -> 21891804 | E28: ='[6]Billed kWh'!G71+'[5]II-H-1.2'!E22 -> 21808568 | F28: ='[6]Billed kWh'!H71+'[5]II-H-1.2'!F22 -> 21865686 | G28: ='[6]Billed kWh'!I71+'[5]II-H-1.2'!G22 -> 21884664 | H28: ='[6]Billed kWh'!J71+'[5]II-H-1.2'!H22 -> 21865890 | I28: ='[6]Billed kWh'!K71+'[5]II-H-1.2'!I22 -> 21865532 | J28: ='[6]Billed kWh'!L71+'[5]II-H-1.2'!J22 -> 21871358 | K28: ='[6]Billed kWh'!M71+'[5]II-H-1.2'!K22 -> 21863875 | ... O28: ='[6]Billed kWh'!Q71+'[5]II-H-1.2'!O22 -> 21864010 | P28: =SUM(D28:O28) -> 262407146 | Q28: ='II-H-4.1 Functions'!F29/'II-H-1.2'!P28 -> 0.067212039 | R28: ='II-H-4.1 Functions'!H29/'II-H-1.2'!P28 -> 0.002609387
A30: 11 | B30: TOTAL RETAIL | D30: =D28+D26+D24+D20+D16+D14 -> 2865057234 | E30: =E28+E26+E24+E20+E16+E14 -> 2254611625 | F30: =F28+F26+F24+F20+F16+F14 -> 2315992458 | G30: =G28+G26+G24+G20+G16+G14 -> 2380787390 | H30: =H28+H26+H24+H20+H16+H14 -> 2472499527 | I30: =I28+I26+I24+I20+I16+I14 -> 3108283707 | J30: =J28+J26+J24+J20+J16+J14 -> 3044218598 | K30: =K28+K26+K24+K20+K16+K14 -> 3122975462 | ... P30: =P28+P26+P24+P20+P16+P14 -> 32007470455
A32: 12 | B32: WHOLESALE PRI | C32: PRI | D32: 0 | E32: 0 | F32: 0 | G32: 0 | H32: 0 | I32: 0 | J32: 0 | K32: 0 | L32: 0 | M32: 0 | N32: 0 | O32: 0 | P32: =SUM(D32:O32) -> 0
A33: 13 | B33: WHOLESALE TRANS | C33: TRA | P33: =SUM(D33:O33) -> 0
A34: 14 | B34: TOTAL WHOLESALE | D34: =SUM(D32:D33) -> 0 | E34: =SUM(E32:E33) -> 0 | F34: =SUM(F32:F33) -> 0 | G34: =SUM(G32:G33) -> 0 | H34: =SUM(H32:H33) -> 0 | I34: =SUM(I32:I33) -> 0 | J34: =SUM(J32:J33) -> 0 | K34: =SUM(K32:K33) -> 0 | ... P34: =SUM(P32:P33) -> 0
A36: 15 | B36: TOTAL AEP TEXAS | D36: =+D34+D30 -> 2865057234 | E36: =+E34+E30 -> 2254611625 | F36: =+F34+F30 -> 2315992458 | G36: =+G34+G30 -> 2380787390 | H36: =+H34+H30 -> 2472499527 | I36: =+I34+I30 -> 3108283707 | J36: =+J34+J30 -> 3044218598 | K36: =+K34+K30 -> 3122975462 | ... P36: =+P34+P30 -> 32007470455
B37: =+B7 -> AEP TEXAS
B38: WEATHER ADJUSTMENTS TO KWH AT METER
B39: =+B9 -> FOR TEST YEAR ENDED DECEMBER 31, 2018
A42: LINE | B42: DESCRIPTION | C42: VOLT | D42: =D12 -> JANUARY | E42: =E12 -> FEBRUARY | F42: =F12 -> MARCH | G42: =G12 -> APRIL | H42: =H12 -> MAY | I42: =I12 -> JUNE | J42: =J12 -> JULY | K42: =K12 -> AUGUST | ... O42: =O12 -> DECEMBER | P42: =+P12 -> TOTAL
A44: 1 | B44: RESIDENTIAL SERVICE | C44: SEC | D44: =-'[7]TCC by class'!C22+'[5]II-H-1.2'!D39 -> -155127058 | E44: =-'[7]TCC by class'!D22+'[5]II-H-1.2'!E39 -> -62130204 | F44: =-'[7]TCC by class'!E22+'[5]II-H-1.2'!F39 -> 7333556 | G44: =-'[7]TCC by class'!F22+'[5]II-H-1.2'!G39 -> -3961366 | H44: =-'[7]TCC by class'!G22+'[5]II-H-1.2'!H39 -> 31982624 | I44: =-'[7]TCC by class'!H22+'[5]II-H-1.2'!I39 -> -59697400 | J44: =-'[7]TCC by class'!I22+'[5]II-H-1.2'!J39 -> 4322941 | K44: =-'[7]TCC by class'!J22+'[5]II-H-1.2'!K39 -> 16737076 | ... O44: =-'[7]TCC by class'!N22+'[5]II-H-1.2'!O39 -> 33942751 | P44: =SUM(D44:O44) -> -169072907
A46: 2 | B46: SECONDARY < 10 kW | C46: SEC | D46: =-'[7]TCC by class'!C17+'[5]II-H-1.2'!D41 -> -647314.76 | E46: =-'[7]TCC by class'!D17+'[5]II-H-1.2'!E41 -> -203654.11 | F46: =-'[7]TCC by class'!E17+'[5]II-H-1.2'!F41 -> -610097.86 | G46: =-'[7]TCC by class'!F17+'[5]II-H-1.2'!G41 -> -266425.84 | H46: =-'[7]TCC by class'!G17+'[5]II-H-1.2'!H41 -> 789362.19 | I46: =-'[7]TCC by class'!H17+'[5]II-H-1.2'!I41 -> -1548911.2 | J46: =-'[7]TCC by class'!I17+'[5]II-H-1.2'!J41 -> 46199.63 | K46: =-'[7]TCC by class'!J17+'[5]II-H-1.2'!K41 -> 424092.29 | ... O46: =-'[7]TCC by class'!N17+'[5]II-H-1.2'!O41 -> 510140.7 | P46: =SUM(D46:O46) -> -345003.32
A48: 3 | B48: SECONDARY > 10 kW NCP | C48: SEC | D48: =-'[7]TCC by class'!C19+'[5]II-H-1.2'!D43 -> -7705107 | E48: =-'[7]TCC by class'!D19+'[5]II-H-1.2'!E43 -> -2506173.9 | F48: =-'[7]TCC by class'!E19+'[5]II-H-1.2'!F43 -> -9276340.2 | G48: =-'[7]TCC by class'!F19+'[5]II-H-1.2'!G43 -> -4400742.5 | H48: =-'[7]TCC by class'!G19+'[5]II-H-1.2'!H43 -> 12271334 | I48: =-'[7]TCC by class'!H19+'[5]II-H-1.2'!I43 -> -22290013 | J48: =-'[7]TCC by class'!I19+'[5]II-H-1.2'!J43 -> 2126732 | K48: =-'[7]TCC by class'!J19+'[5]II-H-1.2'!K43 -> 6402328.7 | ... O48: =-'[7]TCC by class'!N19+'[5]II-H-1.2'!O43 -> 7565286.2 | P48: =SUM(D48:O48) -> -1982220.5
A49: 4 | B49: SECONDARY > 10 kW 4CP | C49: SEC | D49: =-'[7]TCC by class'!C18+'[5]II-H-1.2'!D44 -> -1245610.1 | E49: =-'[7]TCC by class'!D18+'[5]II-H-1.2'!E44 -> -462292.73 | F49: =-'[7]TCC by class'!E18+'[5]II-H-1.2'!F44 -> -1103737.7 | G49: =-'[7]TCC by class'!F18+'[5]II-H-1.2'!G44 -> -423723.27 | H49: =-'[7]TCC by class'!G18+'[5]II-H-1.2'!H44 -> 1531043.4 | I49: =-'[7]TCC by class'!H18+'[5]II-H-1.2'!I44 -> -3302692 | J49: =-'[7]TCC by class'!I18+'[5]II-H-1.2'!J44 -> -199243.4 | K49: =-'[7]TCC by class'!J18+'[5]II-H-1.2'!K44 -> 782122.87 | ... O49: =-'[7]TCC by class'!N18+'[5]II-H-1.2'!O44 -> 772567.19 | P49: =SUM(D49:O49) -> -1430125.9
A50: 5 | B50: TOTAL SECONDARY > 10 kW | D50: =SUM(D48:D49) -> -8950717.2 | E50: =SUM(E48:E49) -> -2968466.6 | F50: =SUM(F48:F49) -> -10380078 | G50: =SUM(G48:G49) -> -4824465.8 | H50: =SUM(H48:H49) -> 13802377 | I50: =SUM(I48:I49) -> -25592705 | J50: =SUM(J48:J49) -> 1927488.6 | K50: =SUM(K48:K49) -> 7184451.6 | ... P50: =SUM(P48:P49) -> -3412346.4
A52: 6 | B52: PRIMARY NCP | C52: PRI | D52: =+-'[7]TCC by class'!C21+'[5]II-H-1.2'!D47 -> -1514158.1 | E52: =+-'[7]TCC by class'!D21+'[5]II-H-1.2'!E47 -> -456066.29 | F52: =+-'[7]TCC by class'!E21+'[5]II-H-1.2'!F47 -> -2415686.2 | G52: =+-'[7]TCC by class'!F21+'[5]II-H-1.2'!G47 -> -1151685.4 | H52: =+-'[7]TCC by class'!G21+'[5]II-H-1.2'!H47 -> 3105541.9 | I52: =+-'[7]TCC by class'!H21+'[5]II-H-1.2'!I47 -> -5087814.5 | J52: =+-'[7]TCC by class'!I21+'[5]II-H-1.2'!J47 -> 574389.74 | K52: =+-'[7]TCC by class'!J21+'[5]II-H-1.2'!K47 -> 1470588.1 | ... O52: =+-'[7]TCC by class'!N21+'[5]II-H-1.2'!O47 -> 2082473.9 | P52: =SUM(D52:O52) -> 457811.69
A53: 7 | B53: PRIMARY 4CP | C53: PRI | P53: =SUM(D53:O53) -> 0
A54: 8 | B54: TOTAL PRIMARY | D54: =SUM(D52:D53) -> -1514158.1 | E54: =SUM(E52:E53) -> -456066.29 | F54: =SUM(F52:F53) -> -2415686.2 | G54: =SUM(G52:G53) -> -1151685.4 | H54: =SUM(H52:H53) -> 3105541.9 | I54: =SUM(I52:I53) -> -5087814.5 | J54: =SUM(J52:J53) -> 574389.74 | K54: =SUM(K52:K53) -> 1470588.1 | ... P54: =SUM(P52:P53) -> 457811.69
A56: 9 | B56: TRANSMISSION | C56: TRA | D56: =-'[7]TCC by class'!C23 -> 0 | E56: =-'[7]TCC by class'!D23 -> 0 | F56: =-'[7]TCC by class'!E23 -> 0 | G56: =-'[7]TCC by class'!F23 -> 0 | H56: =-'[7]TCC by class'!G23 -> 0 | I56: =-'[7]TCC by class'!H23 -> 0 | J56: =-'[7]TCC by class'!I23 -> 0 | K56: =-'[7]TCC by class'!J23 -> 0 | ... O56: =-'[7]TCC by class'!N23 -> 0 | P56: =SUM(D56:O56) -> 0
A58: 10 | B58: LIGHTING | C58: SEC | P58: =SUM(D58:O58) -> 0
G59: 0
A60: 11 | B60: TOTAL RETAIL | D60: =D58+D56+D54+D50+D46+D44 -> -166239248 | E60: =E58+E56+E54+E50+E46+E44 -> -65758391 | F60: =F58+F56+F54+F50+F46+F44 -> -6072306 | G60: =G58+G56+G54+G50+G46+G44 -> -10203943 | H60: =H58+H56+H54+H50+H46+H44 -> 49679905 | I60: =I58+I56+I54+I50+I46+I44 -> -91926831 | J60: =J58+J56+J54+J50+J46+J44 -> 6871019 | K60: =K58+K56+K54+K50+K46+K44 -> 25816208 | ... P60: =P58+P56+P54+P50+P46+P44 -> -172372445
A62: 12 | B62: WHOLESALE PRI | C62: PRI | P62: =SUM(D62:O62) -> 0
A63: 13 | B63: WHOLESALE TRANS | C63: TRA | P63: =SUM(D63:O63) -> 0
A64: 14 | B64: TOTAL WHOLESALE | D64: =SUM(D62:D63) -> 0 | E64: =SUM(E62:E63) -> 0 | F64: =SUM(F62:F63) -> 0 | G64: =SUM(G62:G63) -> 0 | H64: =SUM(H62:H63) -> 0 | I64: =SUM(I62:I63) -> 0 | J64: =SUM(J62:J63) -> 0 | K64: =SUM(K62:K63) -> 0 | ... P64: =SUM(P62:P63) -> 0
A66: 15 | B66: =B36 -> TOTAL AEP TEXAS | D66: =+D64+D60 -> -166239248 | E66: =+E64+E60 -> -65758391 | F66: =+F64+F60 -> -6072306 | G66: =+G64+G60 -> -10203943 | H66: =+H64+H60 -> 49679905 | I66: =+I64+I60 -> -91926831 | J66: =+J64+J60 -> 6871019 | K66: =+K64+K60 -> 25816208 | ... P66: =+P64+P60 -> -172372445
B67: =B7 -> AEP TEXAS
B68: KWH CUSTOMER ADJUSTMENTS AT METER
B69: =+B39 -> FOR TEST YEAR ENDED DECEMBER 31, 2018
A72: LINE | B72: DESCRIPTION | C72: VOLT | D72: =D12 -> JANUARY | E72: =E12 -> FEBRUARY | F72: =F12 -> MARCH | G72: =G12 -> APRIL | H72: =H12 -> MAY | I72: =I12 -> JUNE | J72: =J12 -> JULY | K72: =K12 -> AUGUST | ... O72: =O12 -> DECEMBER | P72: =+P12 -> TOTAL
A74: 1 | B74: RESIDENTIAL SERVICE | C74: SEC | D74: =+'[5]II-H-1.2'!D70+'[4]II-H-1.2'!D68 -> 12503002 | E74: =+'[5]II-H-1.2'!E70+'[4]II-H-1.2'!E68 -> 9368048.5 | F74: =+'[5]II-H-1.2'!F70+'[4]II-H-1.2'!F68 -> 7041552.3 | G74: =+'[5]II-H-1.2'!G70+'[4]II-H-1.2'!G68 -> 6217210.3 | H74: =+'[5]II-H-1.2'!H70+'[4]II-H-1.2'!H68 -> 6003221.3 | I74: =+'[5]II-H-1.2'!I70+'[4]II-H-1.2'!I68 -> 8258893.8 | J74: =+'[5]II-H-1.2'!J70+'[4]II-H-1.2'!J68 -> 9280624.4 | K74: =+'[5]II-H-1.2'!K70+'[4]II-H-1.2'!K68 -> 1650067.4 | ... O74: =+'[5]II-H-1.2'!O70+'[4]II-H-1.2'!O68 -> 0 | P74: =SUM(D74:O74) -> 63143017
D75: =+'[5]II-H-1.2'!D71+'[4]II-H-1.2'!D69 -> 0 | E75: =+'[5]II-H-1.2'!E71+'[4]II-H-1.2'!E69 -> 0 | F75: =+'[5]II-H-1.2'!F71+'[4]II-H-1.2'!F69 -> 0 | G75: =+'[5]II-H-1.2'!G71+'[4]II-H-1.2'!G69 -> 0 | H75: =+'[5]II-H-1.2'!H71+'[4]II-H-1.2'!H69 -> 0 | I75: =+'[5]II-H-1.2'!I71+'[4]II-H-1.2'!I69 -> 0 | J75: =+'[5]II-H-1.2'!J71+'[4]II-H-1.2'!J69 -> 0 | K75: =+'[5]II-H-1.2'!K71+'[4]II-H-1.2'!K69 -> 0 | ... O75: =+'[5]II-H-1.2'!O71+'[4]II-H-1.2'!O69 -> 0
A76: 2 | B76: SECONDARY < 10 kW | C76: SEC | D76: =+'[5]II-H-1.2'!D72+'[4]II-H-1.2'!D70 -> -700307 | E76: =+'[5]II-H-1.2'!E72+'[4]II-H-1.2'!E70 -> 159259.05 | F76: =+'[5]II-H-1.2'!F72+'[4]II-H-1.2'!F70 -> 259624.53 | G76: =+'[5]II-H-1.2'!G72+'[4]II-H-1.2'!G70 -> 139393.97 | H76: =+'[5]II-H-1.2'!H72+'[4]II-H-1.2'!H70 -> 26978.47 | I76: =+'[5]II-H-1.2'!I72+'[4]II-H-1.2'!I70 -> -86538.954 | J76: =+'[5]II-H-1.2'!J72+'[4]II-H-1.2'!J70 -> -137188.95 | K76: =+'[5]II-H-1.2'!K72+'[4]II-H-1.2'!K70 -> -333211.51 | ... O76: =+'[5]II-H-1.2'!O72+'[4]II-H-1.2'!O70 -> 0 | P76: =SUM(D76:O76) -> -947844.49
D77: =+'[5]II-H-1.2'!D73+'[4]II-H-1.2'!D71 -> 0 | E77: =+'[5]II-H-1.2'!E73+'[4]II-H-1.2'!E71 -> 0 | F77: =+'[5]II-H-1.2'!F73+'[4]II-H-1.2'!F71 -> 0 | G77: =+'[5]II-H-1.2'!G73+'[4]II-H-1.2'!G71 -> 0 | H77: =+'[5]II-H-1.2'!H73+'[4]II-H-1.2'!H71 -> 0 | I77: =+'[5]II-H-1.2'!I73+'[4]II-H-1.2'!I71 -> 0 | J77: =+'[5]II-H-1.2'!J73+'[4]II-H-1.2'!J71 -> 0 | K77: =+'[5]II-H-1.2'!K73+'[4]II-H-1.2'!K71 -> 0 | ... O77: =+'[5]II-H-1.2'!O73+'[4]II-H-1.2'!O71 -> 0
A78: 3 | B78: SECONDARY > 10 kW NCP | C78: SEC | D78: =+'[5]II-H-1.2'!D74+'[4]II-H-1.2'!D72 -> 22895549 | E78: =+'[5]II-H-1.2'!E74+'[4]II-H-1.2'!E72 -> 10553448 | F78: =+'[5]II-H-1.2'!F74+'[4]II-H-1.2'!F72 -> 4666453.1 | G78: =+'[5]II-H-1.2'!G74+'[4]II-H-1.2'!G72 -> 4426841.6 | H78: =+'[5]II-H-1.2'!H74+'[4]II-H-1.2'!H72 -> 5570828.2 | I78: =+'[5]II-H-1.2'!I74+'[4]II-H-1.2'!I72 -> 5859441.8 | J78: =+'[5]II-H-1.2'!J74+'[4]II-H-1.2'!J72 -> 4628389 | K78: =+'[5]II-H-1.2'!K74+'[4]II-H-1.2'!K72 -> 1326701.4 | ... O78: =+'[5]II-H-1.2'!O74+'[4]II-H-1.2'!O72 -> 0 | P78: =SUM(D78:O78) -> 68711313
A79: 4 | B79: SECONDARY > 10 kW 4CP | C79: SEC | D79: =+'[5]II-H-1.2'!D75+'[4]II-H-1.2'!D73 -> -5167683.1 | E79: =+'[5]II-H-1.2'!E75+'[4]II-H-1.2'!E73 -> -4582950.2 | F79: =+'[5]II-H-1.2'!F75+'[4]II-H-1.2'!F73 -> -4540207.7 | G79: =+'[5]II-H-1.2'!G75+'[4]II-H-1.2'!G73 -> -4271688.8 | H79: =+'[5]II-H-1.2'!H75+'[4]II-H-1.2'!H73 -> -4819129.6 | I79: =+'[5]II-H-1.2'!I75+'[4]II-H-1.2'!I73 -> -3265143.5 | J79: =+'[5]II-H-1.2'!J75+'[4]II-H-1.2'!J73 -> -3785376.2 | K79: =+'[5]II-H-1.2'!K75+'[4]II-H-1.2'!K73 -> -4031956.1 | ... O79: =+'[5]II-H-1.2'!O75+'[4]II-H-1.2'!O73 -> 0 | P79: =SUM(D79:O79) -> -33749815
A80: 5 | B80: TOTAL SECONDARY > 10 kW | D80: =SUM(D78:D79) -> 17727865 | E80: =SUM(E78:E79) -> 5970498.3 | F80: =SUM(F78:F79) -> 126245.33 | G80: =SUM(G78:G79) -> 155152.85 | H80: =SUM(H78:H79) -> 751698.56 | I80: =SUM(I78:I79) -> 2594298.3 | J80: =SUM(J78:J79) -> 843012.84 | K80: =SUM(K78:K79) -> -2705254.7 | ... P80: =SUM(P78:P79) -> 34961497
A82: 6 | B82: PRIMARY NCP | C82: PRI | D82: =+'[5]II-H-1.2'!D78+'[4]II-H-1.2'!D76 -> 209850.39 | E82: =+'[5]II-H-1.2'!E78+'[4]II-H-1.2'!E76 -> 433777.94 | F82: =+'[5]II-H-1.2'!F78+'[4]II-H-1.2'!F76 -> 320784.31 | G82: =+'[5]II-H-1.2'!G78+'[4]II-H-1.2'!G76 -> 592649.44 | H82: =+'[5]II-H-1.2'!H78+'[4]II-H-1.2'!H76 -> 504307.96 | I82: =+'[5]II-H-1.2'!I78+'[4]II-H-1.2'!I76 -> 197862.46 | J82: =+'[5]II-H-1.2'!J78+'[4]II-H-1.2'!J76 -> 285981.58 | K82: =+'[5]II-H-1.2'!K78+'[4]II-H-1.2'!K76 -> -211713 | ... O82: =+'[5]II-H-1.2'!O78+'[4]II-H-1.2'!O76 -> 0 | P82: =SUM(D82:O82) -> 1814803.6
A83: 7 | B83: PRIMARY 4CP | C83: PRI | D83: =+'[5]II-H-1.2'!D79+'[4]II-H-1.2'!D77 -> 3164932.2 | E83: =+'[5]II-H-1.2'!E79+'[4]II-H-1.2'!E77 -> 1963012.5 | F83: =+'[5]II-H-1.2'!F79+'[4]II-H-1.2'!F77 -> -3532867.7 | G83: =+'[5]II-H-1.2'!G79+'[4]II-H-1.2'!G77 -> 6144855.2 | H83: =+'[5]II-H-1.2'!H79+'[4]II-H-1.2'!H77 -> -2412108.9 | I83: =+'[5]II-H-1.2'!I79+'[4]II-H-1.2'!I77 -> -7708862.3 | J83: =+'[5]II-H-1.2'!J79+'[4]II-H-1.2'!J77 -> -117472.08 | K83: =+'[5]II-H-1.2'!K79+'[4]II-H-1.2'!K77 -> 1461196.6 | ... O83: =+'[5]II-H-1.2'!O79+'[4]II-H-1.2'!O77 -> 0 | P83: =SUM(D83:O83) -> -5969816.8
A84: 8 | B84: TOTAL PRIMARY | D84: =SUM(D82:D83) -> 3374782.6 | E84: =SUM(E82:E83) -> 2396790.5 | F84: =SUM(F82:F83) -> -3212083.4 | G84: =SUM(G82:G83) -> 6737504.6 | H84: =SUM(H82:H83) -> -1907801 | I84: =SUM(I82:I83) -> -7510999.9 | J84: =SUM(J82:J83) -> 168509.5 | K84: =SUM(K82:K83) -> 1249483.6 | ... P84: =SUM(P82:P83) -> -4155013.1
A86: 9 | B86: TRANSMISSION | C86: TRA | D86: =+'[5]II-H-1.2'!D82+'[4]II-H-1.2'!D80 -> -15404659 | E86: =+'[5]II-H-1.2'!E82+'[4]II-H-1.2'!E80 -> 19485196 | F86: =+'[5]II-H-1.2'!F82+'[4]II-H-1.2'!F80 -> 51046726 | G86: =+'[5]II-H-1.2'!G82+'[4]II-H-1.2'!G80 -> 28086497 | H86: =+'[5]II-H-1.2'!H82+'[4]II-H-1.2'!H80 -> 16135194 | I86: =+'[5]II-H-1.2'!I82+'[4]II-H-1.2'!I80 -> 771941.67 | J86: =+'[5]II-H-1.2'!J82+'[4]II-H-1.2'!J80 -> 32620130 | K86: =+'[5]II-H-1.2'!K82+'[4]II-H-1.2'!K80 -> 21715583 | ... O86: =+'[5]II-H-1.2'!O82+'[4]II-H-1.2'!O80 -> 185447500 | P86: =SUM(D86:O86) -> 2.918065e+08
A88: 10 | B88: LIGHTING | C88: SEC | D88: =+'[5]II-H-1.2'!D84+'[4]II-H-1.2'!D82 -> -469391.32 | E88: =+'[5]II-H-1.2'!E84+'[4]II-H-1.2'!E82 -> 104486.5 | F88: =+'[5]II-H-1.2'!F84+'[4]II-H-1.2'!F82 -> 24170.171 | G88: =+'[5]II-H-1.2'!G84+'[4]II-H-1.2'!G82 -> 10419.224 | H88: =+'[5]II-H-1.2'!H84+'[4]II-H-1.2'!H82 -> -29278.82 | I88: =+'[5]II-H-1.2'!I84+'[4]II-H-1.2'!I82 -> 12012.603 | J88: =+'[5]II-H-1.2'!J84+'[4]II-H-1.2'!J82 -> 326579.7 | K88: =+'[5]II-H-1.2'!K84+'[4]II-H-1.2'!K82 -> -120075.73 | ... O88: =+'[5]II-H-1.2'!O84+'[4]II-H-1.2'!O82 -> 0 | P88: =SUM(D88:O88) -> -181100.56
A90: 11 | B90: TOTAL RETAIL | D90: =D88+D86+D84+D80+D76+D74 -> 17031292 | E90: =E88+E86+E84+E80+E76+E74 -> 37484278 | F90: =F88+F86+F84+F80+F76+F74 -> 55286235 | G90: =G88+G86+G84+G80+G76+G74 -> 41346178 | H90: =H88+H86+H84+H80+H76+H74 -> 20980013 | I90: =I88+I86+I84+I80+I76+I74 -> 4039607.6 | J90: =J88+J86+J84+J80+J76+J74 -> 43101667 | K90: =K88+K86+K84+K80+K76+K74 -> 21456593 | ... P90: =P88+P86+P84+P80+P76+P74 -> 3.8462706e+08
A92: 12 | B92: WHOLESALE PRI | C92: PRI | D92: =+'[5]II-H-1.2'!D88+'[4]II-H-1.2'!D86 -> 0 | E92: =+'[5]II-H-1.2'!E88+'[4]II-H-1.2'!E86 -> 0 | F92: =+'[5]II-H-1.2'!F88+'[4]II-H-1.2'!F86 -> 0 | G92: =+'[5]II-H-1.2'!G88+'[4]II-H-1.2'!G86 -> 0 | H92: =+'[5]II-H-1.2'!H88+'[4]II-H-1.2'!H86 -> 0 | I92: =+'[5]II-H-1.2'!I88+'[4]II-H-1.2'!I86 -> 0 | J92: =+'[5]II-H-1.2'!J88+'[4]II-H-1.2'!J86 -> 0 | K92: =+'[5]II-H-1.2'!K88+'[4]II-H-1.2'!K86 -> 0 | ... O92: =+'[5]II-H-1.2'!O88+'[4]II-H-1.2'!O86 -> 0 | P92: =SUM(D92:O92) -> 0
A93: 13 | B93: WHOLESALE TRANS | C93: TRA | P93: =SUM(D93:O93) -> 0
A94: 14 | B94: TOTAL WHOLESALE | D94: =SUM(D92:D93) -> 0 | E94: =SUM(E92:E93) -> 0 | F94: =SUM(F92:F93) -> 0 | G94: =SUM(G92:G93) -> 0 | H94: =SUM(H92:H93) -> 0 | I94: =SUM(I92:I93) -> 0 | J94: =SUM(J92:J93) -> 0 | K94: =SUM(K92:K93) -> 0 | ... P94: =SUM(P92:P93) -> 0
A96: 15 | B96: =B36 -> TOTAL AEP TEXAS | D96: =+D94+D90 -> 17031292 | E96: =+E94+E90 -> 37484278 | F96: =+F94+F90 -> 55286235 | G96: =+G94+G90 -> 41346178 | H96: =+H94+H90 -> 20980013 | I96: =+I94+I90 -> 4039607.6 | J96: =+J94+J90 -> 43101667 | K96: =+K94+K90 -> 21456593 | ... P96: =+P94+P90 -> 3.8462706e+08
B99: =+B7 -> AEP TEXAS
B100: OTHER KWH ADJUSTMENTS AT METER
B101: =+B39 -> FOR TEST YEAR ENDED DECEMBER 31, 2018
A104: LINE | B104: =+B42 -> DESCRIPTION | C104: =+C42 -> VOLT | D104: =+D42 -> JANUARY | E104: =+E42 -> FEBRUARY | F104: =+F42 -> MARCH | G104: =+G42 -> APRIL | H104: =+H42 -> MAY | I104: =+I42 -> JUNE | ... P104: =+P42 -> TOTAL
A106: 1 | B106: RESIDENTIAL SERVICE | C106: SEC | P106: =SUM(D106:O106) -> 0
A108: 2 | B108: SECONDARY < 10 kW | C108: SEC | P108: =SUM(D108:O108) -> 0
A110: 3 | B110: SECONDARY > 10 kW NCP | C110: SEC | P110: =SUM(D110:O110) -> 0
A111: 4 | B111: SECONDARY > 10 kW 4CP | C111: SEC | P111: =SUM(D111:O111) -> 0
A112: 5 | B112: TOTAL SECONDARY > 10 kW | P112: =SUM(P110:P111) -> 0
A114: 6 | B114: PRIMARY NCP | C114: PRI | P114: =SUM(D114:O114) -> 0
A115: 7 | B115: PRIMARY 4CP | C115: PRI | P115: =SUM(D115:O115) -> 0
A116: 8 | B116: TOTAL PRIMARY | P116: =SUM(P114:P115) -> 0
A118: 9 | B118: TRANSMISSION | C118: TRA | P118: =SUM(D118:O118) -> 0
A120: 10 | B120: LIGHTING | C120: SEC | P120: =SUM(D120:O120) -> 0
A122: 11 | B122: TOTAL RETAIL | D122: =D120+D118+D116+D112+D108+D106 -> 0 | E122: =E120+E118+E116+E112+E108+E106 -> 0 | F122: =F120+F118+F116+F112+F108+F106 -> 0 | G122: =G120+G118+G116+G112+G108+G106 -> 0 | H122: =H120+H118+H116+H112+H108+H106 -> 0 | I122: =I120+I118+I116+I112+I108+I106 -> 0 | J122: =J120+J118+J116+J112+J108+J106 -> 0 | K122: =K120+K118+K116+K112+K108+K106 -> 0 | ... P122: =P120+P118+P116+P112+P108+P106 -> 0
A124: 12 | B124: WHOLESALE PRI | C124: PRI | P124: =SUM(D124:O124) -> 0
A125: 13 | B125: WHOLESALE TRANS | C125: TRA | P125: =SUM(D125:O125) -> 0
A126: 14 | B126: TOTAL WHOLESALE | D126: =SUM(D124:D125) -> 0 | E126: =SUM(E124:E125) -> 0 | F126: =SUM(F124:F125) -> 0 | G126: =SUM(G124:G125) -> 0 | H126: =SUM(H124:H125) -> 0 | I126: =SUM(I124:I125) -> 0 | J126: =SUM(J124:J125) -> 0 | K126: =SUM(K124:K125) -> 0 | ... P126: =SUM(P124:P125) -> 0
A128: 15 | B128: =B36 -> TOTAL AEP TEXAS | D128: =+D126+D122 -> 0 | E128: =+E126+E122 -> 0 | F128: =+F126+F122 -> 0 | G128: =+G126+G122 -> 0 | H128: =+H126+H122 -> 0 | I128: =+I126+I122 -> 0 | J128: =+J126+J122 -> 0 | K128: =+K126+K122 -> 0 | ... P128: =+P126+P122 -> 0
B129: =B7 -> AEP TEXAS
B130: ADJUSTED BILLING KWH AT METER
B131: =B9 -> FOR TEST YEAR ENDED DECEMBER 31, 2018
A134: LINE | B134: DESCRIPTION | C134: VOLT | D134: =D12 -> JANUARY | E134: =E12 -> FEBRUARY | F134: =F12 -> MARCH | G134: =G12 -> APRIL | H134: =H12 -> MAY | I134: =I12 -> JUNE | J134: =J12 -> JULY | K134: =K12 -> AUGUST | ... O134: =O12 -> DECEMBER | P134: TOTAL
A136: 1 | B136: RESIDENTIAL SERVICE | C136: SEC | D136: =D106+D74+D44+D14 -> 1.0451412e+09 | E136: =E106+E74+E44+E14 -> 8.2802245e+08 | F136: =F106+F74+F44+F14 -> 7.1725989e+08 | G136: =G106+G74+G44+G14 -> 7.3948506e+08 | H136: =H106+H74+H44+H14 -> 8.5611848e+08 | I136: =I106+I74+I44+I14 -> 1.1970559e+09 | J136: =J106+J74+J44+J14 -> 1.320878e+09 | K136: =K106+K74+K44+K14 -> 1.345543e+09 | ... O136: =O106+O74+O44+O14 -> 889076128 | P136: =SUM(D136:O136) -> 1.1997182e+10
A138: 2 | B138: SECONDARY < 10 kW | C138: SEC | D138: =D108+D76+D46+D16 -> 51040061 | E138: =E108+E76+E46+E16 -> 43963030 | F138: =F108+F76+F46+F16 -> 41064762 | G138: =G108+G76+G46+G16 -> 43093481 | H138: =H108+H76+H46+H16 -> 44811160 | I138: =I108+I76+I46+I16 -> 52165336 | J138: =J108+J76+J46+J16 -> 55073387 | K138: =K108+K76+K46+K16 -> 55523958 | ... O138: =O108+O76+O46+O16 -> 45373399 | P138: =SUM(D138:O138) -> 5.7930338e+08
A140: 3 | B140: SECONDARY > 10 kW NCP | C140: SEC | D140: =D110+D78+D48+D18 -> 6.3294867e+08 | E140: =E110+E78+E48+E18 -> 5.6413212e+08 | F140: =F110+F78+F48+F18 -> 5.5433273e+08 | G140: =G110+G78+G48+G18 -> 6.0518861e+08 | H140: =H110+H78+H48+H18 -> 6.4622957e+08 | I140: =I110+I78+I48+I18 -> 7.6299823e+08 | J140: =J110+J78+J48+J18 -> 7.9528026e+08 | K140: =K110+K78+K48+K18 -> 8.0483003e+08 | ... O140: =O110+O78+O48+O18 -> 5.8829821e+08 | P140: =SUM(D140:O140) -> 8.0703698e+09
A141: 4 | B141: SECONDARY > 10 kW 4CP | C141: SEC | D141: =D111+D79+D49+D19 -> 96871875 | E141: =E111+E79+E49+E19 -> 83160063 | F141: =F111+F79+F49+F19 -> 83193731 | G141: =G111+G79+G49+G19 -> 87922050 | H141: =H111+H79+H49+H19 -> 92988964 | I141: =I111+I79+I49+I19 -> 95214257 | J141: =J111+J79+J49+J19 -> 1.0890345e+08 | K141: =K111+K79+K49+K19 -> 1.0450692e+08 | ... O141: =O111+O79+O49+O19 -> 93319846 | P141: =SUM(D141:O141) -> 1.1759007e+09
A142: 5 | B142: TOTAL SECONDARY > 10 kW | D142: =SUM(D140:D141) -> 7.2982054e+08 | E142: =SUM(E140:E141) -> 6.4729218e+08 | F142: =SUM(F140:F141) -> 6.3752646e+08 | G142: =SUM(G140:G141) -> 6.9311066e+08 | H142: =SUM(H140:H141) -> 7.3921854e+08 | I142: =SUM(I140:I141) -> 8.5821248e+08 | J142: =SUM(J140:J141) -> 9.041837e+08 | K142: =SUM(K140:K141) -> 9.0933695e+08 | ... P142: =SUM(P140:P141) -> 9.2462705e+09
A144: 6 | B144: PRIMARY NCP | C144: PRI | D144: =D114+D82+D52+D22 -> 21459619 | E144: =E114+E82+E52+E22 -> 22211406 | F144: =F114+F82+F52+F22 -> 19410819 | G144: =G114+G82+G52+G22 -> 23022169 | H144: =H114+H82+H52+H22 -> 27639595 | I144: =I114+I82+I52+I22 -> 22879124 | J144: =J114+J82+J52+J22 -> 26078042 | K144: =K114+K82+K52+K22 -> 30988423 | ... O144: =O114+O82+O52+O22 -> 27450410 | P144: =SUM(D144:O144) -> 3.0605157e+08
A145: 7 | B145: PRIMARY 4CP | C145: PRI | D145: =D115+D83+D53+D23 -> 3.3165084e+08 | E145: =E115+E83+E53+E23 -> 2.9432776e+08 | F145: =F115+F83+F53+F23 -> 3.0866663e+08 | G145: =G115+G83+G53+G23 -> 3.267693e+08 | H145: =H115+H83+H53+H23 -> 3.3630677e+08 | I145: =I115+I83+I53+I23 -> 3.625077e+08 | J145: =J115+J83+J53+J23 -> 3.6483161e+08 | K145: =K115+K83+K53+K23 -> 3.6942532e+08 | ... O145: =O115+O83+O53+O23 -> 328944965 | P145: =SUM(D145:O145) -> 4.0836951e+09
A146: 8 | B146: TOTAL PRIMARY | D146: =SUM(D144:D145) -> 3.5311046e+08 | E146: =SUM(E144:E145) -> 3.1653917e+08 | F146: =SUM(F144:F145) -> 3.2807744e+08 | G146: =SUM(G144:G145) -> 3.4979147e+08 | H146: =SUM(H144:H145) -> 3.6394636e+08 | I146: =SUM(I144:I145) -> 3.8538683e+08 | J146: =SUM(J144:J145) -> 3.9090966e+08 | K146: =SUM(K144:K145) -> 4.0041374e+08 | ... P146: =SUM(P144:P145) -> 4.3897467e+09
A148: 9 | B148: TRANSMISSION | C148: TRA | D148: =D118+D86+D56+D26 -> 5.1531461e+08 | E148: =E118+E86+E56+E26 -> 3.6860763e+08 | F148: =F118+F86+F56+F26 -> 6.1938798e+08 | G148: =G118+G86+G56+G26 -> 5.6455386e+08 | H148: =H118+H86+H56+H26 -> 5.172283e+08 | I148: =I118+I86+I56+I26 -> 5.0569844e+08 | J148: =J118+J86+J56+J26 -> 4.0094861e+08 | K148: =K118+K86+K56+K26 -> 4.3768682e+08 | ... O148: =O118+O86+O56+O26 -> 549534640 | P148: =SUM(D148:O148) -> 5.7449969e+09
A150: 10 | B150: LIGHTING | C150: SEC | D150: =D120+D88+D58+D28 -> 21422413 | E150: =E120+E88+E58+E28 -> 21913055 | F150: =F120+F88+F58+F28 -> 21889856 | G150: =G120+G88+G58+G28 -> 21895083 | H150: =H120+H88+H58+H28 -> 21836611 | I150: =I120+I88+I58+I28 -> 21877545 | J150: =J120+J88+J58+J28 -> 22197938 | K150: =K120+K88+K58+K28 -> 21743799 | ... O150: =O120+O88+O58+O28 -> 21864010 | P150: =SUM(D150:O150) -> 2.6222605e+08
A152: 11 | B152: TOTAL RETAIL | D152: =D150+D148+D146+D142+D138+D136 -> 2.7158493e+09 | E152: =E150+E148+E146+E142+E138+E136 -> 2.2263375e+09 | F152: =F150+F148+F146+F142+F138+F136 -> 2.3652064e+09 | G152: =G150+G148+G146+G142+G138+G136 -> 2.4119296e+09 | H152: =H150+H148+H146+H142+H138+H136 -> 2.5431594e+09 | I152: =I150+I148+I146+I142+I138+I136 -> 3.0203965e+09 | J152: =J150+J148+J146+J142+J138+J136 -> 3.0941913e+09 | K152: =K150+K148+K146+K142+K138+K136 -> 3.1702483e+09 | ... P152: =P150+P148+P146+P142+P138+P136 -> 3.2219725e+10
...

Sheet II-H-1.3
B2: PUBLIC UTILITY COMMISSION OF TEXAS
B3: AEP TEXAS INC
B4: II-H-1.3 UNADJUSTED TEST YEAR KWH DATA
B5: TEST YEAR ENDING 12/31/2018
B6: DOCKET NUMBER (PENDING ASSIGNMENT)
A7: AEP TEXAS
A8: UNADJUSTED BILLING KWH
A9: FOR TEST YEAR ENDED DECEMBER 31, 2018
A12: LINE | B12: DESCRIPTION | C12: VOLT | D12: KWH @ Source | E12: Percentage | F12: KWH @ Meter | G12: Percentage
A14: 1 | B14: RESIDENTIAL SERVICE | C14: SEC | D14: =+'II-H-1.2'!P167 -> 1.3073055e+10 | E14: =+D14/$D$36 -> 0.38335397 | F14: ='II-H-1.2'!P14 -> 12103111472 | G14: =F14/$F$36 -> 0.37813396
A16: 2 | B16: SECONDARY < 10 kW | C16: SEC | D16: =+'II-H-1.2'!P169 -> 6.2712521e+08 | E16: =+D16/$D$36 -> 0.018389806 | F16: ='II-H-1.2'!P16 -> 580596232 | G16: =F16/$F$36 -> 0.018139398
A18: 3 | B18: SECONDARY > 10 kW NCP | C18: SEC | D18: =+'II-H-1.2'!P171 -> 8.6450524e+09 | E18: =+D18/$D$36 -> 0.25350733 | F18: ='II-H-1.2'!P18 -> 8003640659 | G18: =F18/$F$36 -> 0.25005539
A19: 4 | B19: SECONDARY > 10 kW 4CP | C19: SEC | D19: =+'II-H-1.2'!P172 -> 1.3081367e+09 | E19: =+D19/$D$36 -> 0.038359771 | F19: ='II-H-1.2'!P19 -> 1211080649 | G19: =F19/$F$36 -> 0.037837437
A20: 5 | B20: TOTAL SECONDARY > 10 kW | D20: =SUM(D18:D19) -> 9.9531891e+09 | E20: =SUM(E18:E19) -> 0.2918671 | F20: ='II-H-1.2'!P20 -> 9214721308 | G20: =F20/$F$36 -> 0.28789283
A22: 6 | B22: PRIMARY NCP | C22: PRI | D22: =+'II-H-1.2'!P175 -> 3.1921092e+08 | E22: =+D22/$D$36 -> 0.0093605342 | F22: ='II-H-1.2'!P22 -> 303778954 | G22: =F22/$F$36 -> 0.0094908767
A23: 7 | B23: PRIMARY 4CP | C23: PRI | D23: =+'II-H-1.2'!P176 -> 4.2974199e+09 | E23: =+D23/$D$36 -> 0.12601745 | F23: ='II-H-1.2'!P23 -> 4089664935 | G23: =F23/$F$36 -> 0.1277722
A24: 8 | B24: TOTAL PRIMARY | D24: =SUM(D22:D23) -> 4.6166308e+09 | E24: =SUM(E22:E23) -> 0.13537798 | F24: ='II-H-1.2'!P24 -> 4393443889 | G24: =F24/$F$36 -> 0.13726308
A26: 9 | B26: TRANSMISSION | C26: TRA | D26: =+'II-H-1.2'!P179 -> 5.5483486e+09 | E26: =+D26/$D$36 -> 0.16269965 | F26: ='II-H-1.2'!P26 -> 5453190408 | G26: =F26/$F$36 -> 0.17037243
A28: 10 | B28: LIGHTING | C28: SEC | D28: =+'II-H-1.2'!P181 -> 2.8343645e+08 | E28: =+D28/$D$36 -> 0.0083114844 | F28: ='II-H-1.2'!P28 -> 262407146 | G28: =F28/$F$36 -> 0.0081983094
A30: 11 | B30: TOTAL RETAIL | D30: =+D14+D16+D20+D24+D26+D28 -> 3.4101785e+10 | E30: =+E14+E16+E20+E24+E26+E28 -> 1 | F30: =+F14+F16+F20+F24+F26+F28 -> 32007470455 | G30: =F30/$F$36 -> 1
A32: 12 | B32: WHOLESALE PRI | C32: PRI | D32: 0 | F32: ='II-H-1.2'!P32 -> 0 | G32: =F32/$F$36 -> 0
A33: 13 | B33: WHOLESALE TRANS | C33: TRA | D33: 0 | F33: ='II-H-1.2'!P33 -> 0 | G33: =F33/$F$36 -> 0
A34: 14 | B34: TOTAL WHOLESALE | D34: =SUM(D32:D33) -> 0 | F34: ='II-H-1.2'!P34 -> 0 | G34: =F34/$F$36 -> 0
A36: 15 | B36: TOTAL AEP TEXAS | D36: =+D30+D34 -> 3.4101785e+10 | E36: =+E30+E34 -> 1 | F36: =+F30+F34 -> 32007470455 | G36: =+G30+G34 -> 1

Sheet Sch II-H-1.5
B2: PUBLIC UTILITY COMMISSION OF TEXAS
B3: AEP TEXAS INC
B4: II-H-1.5 ADJUSTMENTS TO OPERATING STATISTICS
B5: TEST YEAR ENDING 12/31/2018
B6: DOCKET NUMBER (PENDING ASSIGNMENT)
A9: Line | B9: Description
A10: 1 | B10: This schedule provides a narrative explanation of all adjustments made to Test Year operating
B11: statistics provided in RFP Schedule II-H-1.
A13: 2 | B13: Residential Service: adjustment made for weather normalized kWh sales; annualize to
B14: year-end customer count and associated kWh sales.
A16: 3 | B16: Secondary ≤ 10 kW Service: adjustment made for weather normalized kWh sales; annualize to
B17: year-end customer count and associated kWh sales.
A19: 4 | B19: Secondary ≥10 kW Service: adjustment made for weather normalized kWh sales; annualize to
B20: year-end customer count and associated kWh sales.
A22: 5 | B22: Primary Service: adjustment made for weather normalized kWh sales; annualize to year-end
B23: customer count and associated kWh sales.
A25: 6 | B25: Transmission Service: annualize to year-end customer count and associated kWh sales.
A27: 7 | B27: Lighting Service: annualize to year-end customer count and associated kWh sales.

Sheet II-H-3.1-3
B2: PUBLIC UTILITY COMMISSION OF TEXAS
B3: AEP TEXAS INC
B4: II-H-3.1-H-3.3 CUSTOMER ADJUSTMENTS
B5: TEST YEAR ENDING 12/31/2018
B6: DOCKET NUMBER (PENDING ASSIGNMENT)
B7: ='II-H-1.2'!B7:O7 -> AEP TEXAS
B8: BOOKED CUSTOMER COUNT
B9: ='II-H-1.2'!B9:O9 -> FOR TEST YEAR ENDED DECEMBER 31, 2018
B10: II-H-3.1
D11: ='II-H-1.2'!D11 -> 0 | G11: ='II-H-1.2'!G11 -> 0
A12: LINE | B12: DESCRIPTION | C12: VOLT | D12: ='II-H-1.2'!D12 -> JANUARY | E12: ='II-H-1.2'!E12 -> FEBRUARY | F12: ='II-H-1.2'!F12 -> MARCH | G12: ='II-H-1.2'!G12 -> APRIL | H12: ='II-H-1.2'!H12 -> MAY | I12: ='II-H-1.2'!I12 -> JUNE | J12: ='II-H-1.2'!J12 -> JULY | K12: ='II-H-1.2'!K12 -> AUGUST | ... O12: ='II-H-1.2'!O12 -> DECEMBER | P12: TOTAL | Q12: AVERAGE
R13: cust | S13: meter | U13: cust | V13: meter
A14: 1 | B14: RESIDENTIAL SERVICE | C14: SEC | D14: ='[6]Incl Customers'!G85+'[5]II-H-3.1'!D8 -> 866062 | E14: ='[6]Incl Customers'!H85+'[5]II-H-3.1'!E8 -> 866633 | F14: ='[6]Incl Customers'!I85+'[5]II-H-3.1'!F8 -> 867947 | G14: ='[6]Incl Customers'!J85+'[5]II-H-3.1'!G8 -> 869158 | H14: ='[6]Incl Customers'!K85+'[5]II-H-3.1'!H8 -> 870372 | I14: ='[6]Incl Customers'!L85+'[5]II-H-3.1'!I8 -> 870490 | J14: ='[6]Incl Customers'!M85+'[5]II-H-3.1'!J8 -> 870393 | K14: ='[6]Incl Customers'!N85+'[5]II-H-3.1'!K8 -> 875458 | L14: ='[4]II-H-3.1'!$L$8+'[5]II-H-3.1'!$L$8 -> 875459 | M14: ='[4]II-H-3.1'!M8+'[5]II-H-3.1'!M8 -> 875792 | N14: ='[4]II-H-3.1'!N8+'[5]II-H-3.1'!N8 -> 876193 | O14: ='[4]II-H-3.1'!O8+'[5]II-H-3.1'!O8 -> 876553 | P14: =SUM(D14:O14) -> 10460510 | Q14: =P14/12 -> 871709.17 | R14: =+'II-H-4.1 Functions'!D15/'II-H-3.1-3'!P14 -> 3.1463551 | S14: =+'II-H-4.1 Functions'!E15/'II-H-3.1-3'!P14 -> 3.8411203 | U14: 3.19 | V14: 3.55
A16: 2 | B16: SECONDARY < 10 kW | C16: SEC | D16: ='[6]Incl Customers'!G12+'[5]II-H-3.1'!D10 -> 90324 | E16: ='[6]Incl Customers'!H12+'[5]II-H-3.1'!E10 -> 88828 | F16: ='[6]Incl Customers'!I12+'[5]II-H-3.1'!F10 -> 88597 | G16: ='[6]Incl Customers'!J12+'[5]II-H-3.1'!G10 -> 88868 | H16: ='[6]Incl Customers'!K12+'[5]II-H-3.1'!H10 -> 89101 | I16: ='[6]Incl Customers'!L12+'[5]II-H-3.1'!I10 -> 89284 | J16: ='[6]Incl Customers'!M12+'[5]II-H-3.1'!J10 -> 89364 | K16: ='[6]Incl Customers'!N12+'[5]II-H-3.1'!K10 -> 89665 | L16: ='[4]II-H-3.1'!L10+'[5]II-H-3.1'!L10 -> 89328 | M16: ='[4]II-H-3.1'!M10+'[5]II-H-3.1'!M10 -> 89393 | N16: ='[4]II-H-3.1'!N10+'[5]II-H-3.1'!N10 -> 89245 | O16: ='[4]II-H-3.1'!O10+'[5]II-H-3.1'!O10 -> 89158 | P16: =SUM(D16:O16) -> 1071155 | Q16: =P16/12 -> 89262.917 | R16: =+'II-H-4.1 Functions'!D17/'II-H-3.1-3'!P16 -> 3.4902669 | S16: =+'II-H-4.1 Functions'!E17/'II-H-3.1-3'!P16 -> 4.7033876 | U16: 3.2 | V16: 3.68
A18: 3 | B18: SECONDARY > 10 kW NCP | C18: SEC | D18: ='[6]Incl Customers'!G30+'[5]II-H-3.1'!D12 -> 69969 | E18: ='[6]Incl Customers'!H30+'[5]II-H-3.1'!E12 -> 71234 | F18: ='[6]Incl Customers'!I30+'[5]II-H-3.1'!F12 -> 71975 | G18: ='[6]Incl Customers'!J30+'[5]II-H-3.1'!G12 -> 72047 | H18: ='[6]Incl Customers'!K30+'[5]II-H-3.1'!H12 -> 71959 | I18: ='[6]Incl Customers'!L30+'[5]II-H-3.1'!I12 -> 72027 | J18: ='[6]Incl Customers'!M30+'[5]II-H-3.1'!J12 -> 72168 | K18: ='[6]Incl Customers'!N30+'[5]II-H-3.1'!K12 -> 72470 | L18: ='[4]II-H-3.1'!L12+'[5]II-H-3.1'!L12 -> 72222 | M18: ='[4]II-H-3.1'!M12+'[5]II-H-3.1'!M12 -> 72235 | N18: ='[4]II-H-3.1'!N12+'[5]II-H-3.1'!N12 -> 72445 | O18: ='[4]II-H-3.1'!O12+'[5]II-H-3.1'!O12 -> 72592 | P18: =SUM(D18:O18) -> 863343 | Q18: =P18/12 -> 71945.25 | R18: =+'II-H-4.1 Functions'!D19/'II-H-3.1-3'!P18 -> 3.4452993 | S18: =+'II-H-4.1 Functions'!E19/'II-H-3.1-3'!P18 -> 16.341177 | U18: 3.26 | V18: 15.81
A19: 4 | B19: SECONDARY > 10 kW 4CP | C19: SEC | D19: ='[6]Incl Customers'!G21+'[5]II-H-3.1'!D13 -> 505 | E19: ='[6]Incl Customers'!H21+'[5]II-H-3.1'!E13 -> 506 | F19: ='[6]Incl Customers'!I21+'[5]II-H-3.1'!F13 -> 505 | G19: ='[6]Incl Customers'!J21+'[5]II-H-3.1'!G13 -> 502 | H19: ='[6]Incl Customers'!K21+'[5]II-H-3.1'!H13 -> 503 | I19: ='[6]Incl Customers'!L21+'[5]II-H-3.1'!I13 -> 494 | J19: ='[6]Incl Customers'!M21+'[5]II-H-3.1'!J13 -> 495 | K19: ='[6]Incl Customers'!N21+'[5]II-H-3.1'!K13 -> 497 | L19: ='[4]II-H-3.1'!L13+'[5]II-H-3.1'!L13 -> 477 | M19: ='[4]II-H-3.1'!M13+'[5]II-H-3.1'!M13 -> 476 | N19: ='[4]II-H-3.1'!N13+'[5]II-H-3.1'!N13 -> 478 | O19: ='[4]II-H-3.1'!O13+'[5]II-H-3.1'!O13 -> 478 | P19: =SUM(D19:O19) -> 5916 | Q19: =P19/12 -> 493 | R19: =+'II-H-4.1 Functions'!D20/'II-H-3.1-3'!P19 -> 26.667578 | S19: =+'II-H-4.1 Functions'!E20/'II-H-3.1-3'!P19 -> 22.198059 | U19: 26.52 | V19: 15.81
A20: 5 | B20: TOTAL SECONDARY > 10 kW | D20: =SUM(D18:D19) -> 70474 | E20: =SUM(E18:E19) -> 71740 | F20: =SUM(F18:F19) -> 72480 | G20: =SUM(G18:G19) -> 72549 | H20: =SUM(H18:H19) -> 72462 | I20: =SUM(I18:I19) -> 72521 | J20: =SUM(J18:J19) -> 72663 | K20: =SUM(K18:K19) -> 72967 | ... O20: =SUM(O18:O19) -> 73070 | P20: =SUM(D20:O20) -> 869259 | Q20: =P20/12 -> 72438.25
A22: 6 | B22: PRIMARY NCP | C22: PRI | D22: ='[6]Incl Customers'!G82+'[5]II-H-3.1'!D16 -> 566 | E22: ='[6]Incl Customers'!H82+'[5]II-H-3.1'!E16 -> 565 | F22: ='[6]Incl Customers'!I82+'[5]II-H-3.1'!F16 -> 565 | G22: ='[6]Incl Customers'!J82+'[5]II-H-3.1'!G16 -> 560 | H22: ='[6]Incl Customers'!K82+'[5]II-H-3.1'!H16 -> 564 | I22: ='[6]Incl Customers'!L82+'[5]II-H-3.1'!I16 -> 572 | J22: ='[6]Incl Customers'!M82+'[5]II-H-3.1'!J16 -> 567 | K22: ='[6]Incl Customers'!N82+'[5]II-H-3.1'!K16 -> 580 | ... O22: ='[6]Incl Customers'!R82+'[5]II-H-3.1'!O16 -> 574 | P22: =SUM(D22:O22) -> 6846 | Q22: =P22/12 -> 570.5 | R22: =+'II-H-4.1 Functions'!D23/'II-H-3.1-3'!P22 -> 4.0787219 | S22: =+'II-H-4.1 Functions'!E23/'II-H-3.1-3'!P22 -> 152.38637 | U22: 3.8 | V22: 154.62
A23: 7 | B23: PRIMARY 4CP | C23: PRI | D23: ='[6]Incl Customers'!G77+'[5]II-H-3.1'!D17 -> 470 | E23: ='[6]Incl Customers'!H77+'[5]II-H-3.1'!E17 -> 470 | F23: ='[6]Incl Customers'!I77+'[5]II-H-3.1'!F17 -> 475 | G23: ='[6]Incl Customers'!J77+'[5]II-H-3.1'!G17 -> 464 | H23: ='[6]Incl Customers'!K77+'[5]II-H-3.1'!H17 -> 476 | I23: ='[6]Incl Customers'!L77+'[5]II-H-3.1'!I17 -> 480 | J23: ='[6]Incl Customers'!M77+'[5]II-H-3.1'!J17 -> 472 | K23: ='[6]Incl Customers'!N77+'[5]II-H-3.1'!K17 -> 468 | ... O23: ='[6]Incl Customers'!R77+'[5]II-H-3.1'!O17 -> 471 | P23: =SUM(D23:O23) -> 5661 | Q23: =P23/12 -> 471.75 | R23: =+'II-H-4.1 Functions'!D24/'II-H-3.1-3'!P23 -> 27.738956 | S23: =+'II-H-4.1 Functions'!E24/'II-H-3.1-3'!P23 -> 158.16809 | U23: 28.41 | V23: 154.62
A24: 8 | B24: TOTAL PRIMARY | D24: =SUM(D22:D23) -> 1036 | E24: =SUM(E22:E23) -> 1035 | F24: =SUM(F22:F23) -> 1040 | G24: =SUM(G22:G23) -> 1024 | H24: =SUM(H22:H23) -> 1040 | I24: =SUM(I22:I23) -> 1052 | J24: =SUM(J22:J23) -> 1039 | K24: =SUM(K22:K23) -> 1048 | ... O24: =SUM(O22:O23) -> 1045 | P24: =SUM(D24:O24) -> 12507 | Q24: =P24/12 -> 1042.25
A26: 9 | B26: TRANSMISSION | C26: TRA | D26: ='[6]Incl Customers'!G97+'[5]II-H-3.1'!D20 -> 85 | E26: ='[6]Incl Customers'!H97+'[5]II-H-3.1'!E20 -> 79 | F26: ='[6]Incl Customers'!I97+'[5]II-H-3.1'!F20 -> 79 | G26: ='[6]Incl Customers'!J97+'[5]II-H-3.1'!G20 -> 81 | H26: ='[6]Incl Customers'!K97+'[5]II-H-3.1'!H20 -> 84 | I26: ='[6]Incl Customers'!L97+'[5]II-H-3.1'!I20 -> 84 | J26: ='[6]Incl Customers'!M97+'[5]II-H-3.1'!J20 -> 79 | K26: ='[6]Incl Customers'!N97+'[5]II-H-3.1'!K20 -> 81 | ... O26: ='[6]Incl Customers'!R97+'[5]II-H-3.1'!O20 -> 64 | P26: =SUM(D26:O26) -> 974 | Q26: 85 | R26: =+'II-H-4.1 Functions'!D27/'II-H-3.1-3'!P26 -> 34.491335 | S26: =+'II-H-4.1 Functions'!E27/'II-H-3.1-3'!P26 -> 1534.7576 | U26: 38.84 | V26: 1869.15
A28: 10 | B28: LIGHTING | C28: SEC | D28: =+'[8]Active Units Lights'!F71+'[5]II-H-3.1'!D22 -> 228698 | E28: =+'[8]Active Units Lights'!G71+'[5]II-H-3.1'!E22 -> 219174 | F28: =+'[8]Active Units Lights'!H71+'[5]II-H-3.1'!F22 -> 219915 | G28: =+'[8]Active Units Lights'!I71+'[5]II-H-3.1'!G22 -> 220030 | H28: =+'[8]Active Units Lights'!J71+'[5]II-H-3.1'!H22 -> 220408 | I28: =+'[8]Active Units Lights'!K71+'[5]II-H-3.1'!I22 -> 220169 | J28: =+'[8]Active Units Lights'!L71+'[5]II-H-3.1'!J22 -> 217297 | K28: =+'[8]Active Units Lights'!M71+'[5]II-H-3.1'!K22 -> 221274 | ... O28: =+'[8]Active Units Lights'!Q71+'[5]II-H-3.1'!O22 -> 220232 | P28: =SUM(D28:O28) -> 2647947 | Q28: =P28/12 -> 220662.25
A30: 11 | B30: TOTAL RETAIL | D30: =D28+D26+D24+D20+D16+D14 -> 1256679 | E30: =E28+E26+E24+E20+E16+E14 -> 1247489 | F30: =F28+F26+F24+F20+F16+F14 -> 1250058 | G30: =G28+G26+G24+G20+G16+G14 -> 1251710 | H30: =H28+H26+H24+H20+H16+H14 -> 1253467 | I30: =I28+I26+I24+I20+I16+I14 -> 1253600 | J30: =J28+J26+J24+J20+J16+J14 -> 1250835 | K30: =K28+K26+K24+K20+K16+K14 -> 1260493 | ... O30: =O28+O26+O24+O20+O16+O14 -> 1260122 | P30: =SUM(D30:O30) -> 15062352 | Q30: =P30/12 -> 1255196
A32: 12 | B32: WHOLESALE PRI | C32: PRI
A33: 13 | B33: WHOLESALE TRANS | C33: TRA
A34: 14 | B34: TOTAL WHOLESALE
A36: 15 | B36: TOTAL AEP TEXAS | D36: =D34+D30 -> 1256679 | E36: =+E34+E30 -> 1247489 | F36: =+F34+F30 -> 1250058 | G36: =+G34+G30 -> 1251710 | H36: =+H34+H30 -> 1253467 | I36: =+I34+I30 -> 1253600 | J36: =+J34+J30 -> 1250835 | K36: =+K34+K30 -> 1260493 | L36: =+L34+L30 -> 1258943 | ... O36: =+O34+O30 -> 1260122 | P36: =SUM(D36:O36) -> 15062352 | Q36: =+Q34+Q30 -> 1255196
B37: Note: Secondary < 10 kW includes Unmetered service; Lighting customers are fixture counts.
B39: =+B7 -> AEP TEXAS
B40: CUSTOMER COUNT ADJUSTMENT
B41: =+B9 -> FOR TEST YEAR ENDED DECEMBER 31, 2018
D43: =D11 -> 0 | G43: =G11 -> 0
A44: LINE | B44: DESCRIPTION | C44: VOLT | D44: =+D12 -> JANUARY | E44: =+E12 -> FEBRUARY | F44: =+F12 -> MARCH | G44: =+G12 -> APRIL | H44: =+H12 -> MAY | I44: =+I12 -> JUNE | J44: =+J12 -> JULY | K44: =+K12 -> AUGUST | ... O44: =+O12 -> DECEMBER | P44: TOTAL | Q44: AVERAGE
A46: 1 | B46: RESIDENTIAL SERVICE | C46: SEC | D46: =+'[4]II-H-3.1'!D40+'[5]II-H-3.1'!D41 -> 10491 | E46: =+'[4]II-H-3.1'!E40+'[5]II-H-3.1'!E41 -> 9920 | F46: =+'[4]II-H-3.1'!F40+'[5]II-H-3.1'!F41 -> 8606 | G46: =+'[4]II-H-3.1'!G40+'[5]II-H-3.1'!G41 -> 7395 | H46: =+'[4]II-H-3.1'!H40+'[5]II-H-3.1'!H41 -> 6181 | I46: =+'[4]II-H-3.1'!I40+'[5]II-H-3.1'!I41 -> 6063 | J46: =+'[4]II-H-3.1'!J40+'[5]II-H-3.1'!J41 -> 6160 | K46: =+'[4]II-H-3.1'!K40+'[5]II-H-3.1'!K41 -> 1095 | ... O46: =+'[4]II-H-3.1'!O40+'[5]II-H-3.1'!O41 -> 0 | P46: =SUM(D46:O46) -> 58126 | Q46: =P46/12 -> 4843.8333
A48: 2 | B48: SECONDARY < 10 kW | C48: SEC | D48: =+'[4]II-H-3.1'!D42+'[5]II-H-3.1'!D43 -> -1166 | E48: =+'[4]II-H-3.1'!E42+'[5]II-H-3.1'!E43 -> 330 | F48: =+'[4]II-H-3.1'!F42+'[5]II-H-3.1'!F43 -> 561 | G48: =+'[4]II-H-3.1'!G42+'[5]II-H-3.1'!G43 -> 290 | H48: =+'[4]II-H-3.1'!H42+'[5]II-H-3.1'!H43 -> 57 | I48: =+'[4]II-H-3.1'!I42+'[5]II-H-3.1'!I43 -> -126 | J48: =+'[4]II-H-3.1'!J42+'[5]II-H-3.1'!J43 -> -206 | K48: =+'[4]II-H-3.1'!K42+'[5]II-H-3.1'!K43 -> -507 | ... O48: =+'[4]II-H-3.1'!O42+'[5]II-H-3.1'!O43 -> 0 | P48: =SUM(D48:O48) -> -1259 | Q48: =P48/12 -> -104.91667
A50: 3 | B50: SECONDARY > 10 kW NCP | C50: SEC | D50: =+'[4]II-H-3.1'!D44+'[5]II-H-3.1'!D45 -> 2623 | E50: =+'[4]II-H-3.1'!E44+'[5]II-H-3.1'!E45 -> 1358 | F50: =+'[4]II-H-3.1'!F44+'[5]II-H-3.1'!F45 -> 617 | G50: =+'[4]II-H-3.1'!G44+'[5]II-H-3.1'!G45 -> 545 | H50: =+'[4]II-H-3.1'!H44+'[5]II-H-3.1'!H45 -> 633 | I50: =+'[4]II-H-3.1'!I44+'[5]II-H-3.1'!I45 -> 565 | J50: =+'[4]II-H-3.1'!J44+'[5]II-H-3.1'!J45 -> 424 | K50: =+'[4]II-H-3.1'!K44+'[5]II-H-3.1'!K45 -> 122 | ... O50: =+'[4]II-H-3.1'!O44+'[5]II-H-3.1'!O45 -> 0 | P50: =SUM(D50:O50) -> 7761 | Q50: =P50/12 -> 646.75
A51: 4 | B51: SECONDARY > 10 kW 4CP | C51: SEC | D51: =+'[4]II-H-3.1'!D45+'[5]II-H-3.1'!D46 -> -27 | E51: =+'[4]II-H-3.1'!E45+'[5]II-H-3.1'!E46 -> -28 | F51: =+'[4]II-H-3.1'!F45+'[5]II-H-3.1'!F46 -> -27 | G51: =+'[4]II-H-3.1'!G45+'[5]II-H-3.1'!G46 -> -24 | H51: =+'[4]II-H-3.1'!H45+'[5]II-H-3.1'!H46 -> -25 | I51: =+'[4]II-H-3.1'!I45+'[5]II-H-3.1'!I46 -> -16 | J51: =+'[4]II-H-3.1'!J45+'[5]II-H-3.1'!J46 -> -17 | K51: =+'[4]II-H-3.1'!K45+'[5]II-H-3.1'!K46 -> -19 | ... O51: =+'[4]II-H-3.1'!O45+'[5]II-H-3.1'!O46 -> 0 | P51: =SUM(D51:O51) -> -180 | Q51: =P51/12 -> -15
A52: 5 | B52: TOTAL SECONDARY > 10 kW | D52: =SUM(D50:D51) -> 2596 | E52: =SUM(E50:E51) -> 1330 | F52: =SUM(F50:F51) -> 590 | G52: =SUM(G50:G51) -> 521 | H52: =SUM(H50:H51) -> 608 | I52: =SUM(I50:I51) -> 549 | J52: =SUM(J50:J51) -> 407 | K52: =SUM(K50:K51) -> 103 | ... O52: =SUM(O50:O51) -> 0 | P52: =SUM(D52:O52) -> 7581 | Q52: =SUM(Q50:Q51) -> 631.75
A54: 6 | B54: PRIMARY NCP | C54: PRI | D54: =+'[4]II-H-3.1'!D48+'[5]II-H-3.1'!D49 -> 8 | E54: =+'[4]II-H-3.1'!E48+'[5]II-H-3.1'!E49 -> 9 | F54: =+'[4]II-H-3.1'!F48+'[5]II-H-3.1'!F49 -> 9 | G54: =+'[4]II-H-3.1'!G48+'[5]II-H-3.1'!G49 -> 14 | H54: =+'[4]II-H-3.1'!H48+'[5]II-H-3.1'!H49 -> 10 | I54: =+'[4]II-H-3.1'!I48+'[5]II-H-3.1'!I49 -> 2 | J54: =+'[4]II-H-3.1'!J48+'[5]II-H-3.1'!J49 -> 7 | K54: =+'[4]II-H-3.1'!K48+'[5]II-H-3.1'!K49 -> -6 | ... O54: =+'[4]II-H-3.1'!O48+'[5]II-H-3.1'!O49 -> 0 | P54: =SUM(D54:O54) -> 42 | Q54: =P54/12 -> 3.5
A55: 7 | B55: PRIMARY 4CP | C55: PRI | D55: =+'[4]II-H-3.1'!D49+'[5]II-H-3.1'!D50 -> 1 | E55: =+'[4]II-H-3.1'!E49+'[5]II-H-3.1'!E50 -> 1 | F55: =+'[4]II-H-3.1'!F49+'[5]II-H-3.1'!F50 -> -4 | G55: =+'[4]II-H-3.1'!G49+'[5]II-H-3.1'!G50 -> 7 | H55: =+'[4]II-H-3.1'!H49+'[5]II-H-3.1'!H50 -> -5 | I55: =+'[4]II-H-3.1'!I49+'[5]II-H-3.1'!I50 -> -9 | J55: =+'[4]II-H-3.1'!J49+'[5]II-H-3.1'!J50 -> -1 | K55: =+'[4]II-H-3.1'!K49+'[5]II-H-3.1'!K50 -> 3 | ... O55: =+'[4]II-H-3.1'!O49+'[5]II-H-3.1'!O50 -> 0 | P55: =SUM(D55:O55) -> -9 | Q55: =P55/12 -> -0.75
A56: 8 | B56: TOTAL PRIMARY | D56: =SUM(D54:D55) -> 9 | E56: =SUM(E54:E55) -> 10 | F56: =SUM(F54:F55) -> 5 | G56: =SUM(G54:G55) -> 21 | H56: =SUM(H54:H55) -> 5 | I56: =SUM(I54:I55) -> -7 | J56: =SUM(J54:J55) -> 6 | K56: =SUM(K54:K55) -> -3 | ... O56: =SUM(O54:O55) -> 0 | P56: =SUM(D56:O56) -> 33 | Q56: =SUM(Q54:Q55) -> 2.75
A58: 9 | B58: TRANSMISSION | C58: TRA | D58: =+'[4]II-H-3.1'!D52+'[5]II-H-3.1'!D53 -> 0 | E58: =+'[4]II-H-3.1'!E52+'[5]II-H-3.1'!E53 -> 6 | F58: =+'[4]II-H-3.1'!F52+'[5]II-H-3.1'!F53 -> 6 | G58: =+'[4]II-H-3.1'!G52+'[5]II-H-3.1'!G53 -> 4 | H58: =+'[4]II-H-3.1'!H52+'[5]II-H-3.1'!H53 -> 1 | I58: =+'[4]II-H-3.1'!I52+'[5]II-H-3.1'!I53 -> 1 | J58: =+'[4]II-H-3.1'!J52+'[5]II-H-3.1'!J53 -> 6 | K58: =+'[4]II-H-3.1'!K52+'[5]II-H-3.1'!K53 -> 4 | ... O58: =+'[4]II-H-3.1'!O52+'[5]II-H-3.1'!O53 -> 21 | P58: =SUM(D58:O58) -> 46 | Q58: =P58/12 -> 3.8333333
A60: 10 | B60: LIGHTING | C60: SEC | D60: =+'[4]II-H-3.1'!D54+'[5]II-H-3.1'!D55 -> -8466 | E60: =+'[4]II-H-3.1'!E54+'[5]II-H-3.1'!E55 -> 1058 | F60: =+'[4]II-H-3.1'!F54+'[5]II-H-3.1'!F55 -> 317 | G60: =+'[4]II-H-3.1'!G54+'[5]II-H-3.1'!G55 -> 202 | H60: =+'[4]II-H-3.1'!H54+'[5]II-H-3.1'!H55 -> -176 | I60: =+'[4]II-H-3.1'!I54+'[5]II-H-3.1'!I55 -> 63 | J60: =+'[4]II-H-3.1'!J54+'[5]II-H-3.1'!J55 -> 2935 | K60: =+'[4]II-H-3.1'!K54+'[5]II-H-3.1'!K55 -> -1042 | ... O60: =+'[4]II-H-3.1'!O54+'[5]II-H-3.1'!O55 -> 0 | P60: =SUM(D60:O60) -> -5163 | Q60: =P60/12 -> -430.25
A62: 11 | B62: TOTAL RETAIL | D62: =D60+D58+D56+D52+D48+D46 -> 3464 | E62: =E60+E58+E56+E52+E48+E46 -> 12654 | F62: =F60+F58+F56+F52+F48+F46 -> 10085 | G62: =G60+G58+G56+G52+G48+G46 -> 8433 | H62: =H60+H58+H56+H52+H48+H46 -> 6676 | I62: =I60+I58+I56+I52+I48+I46 -> 6543 | J62: =J60+J58+J56+J52+J48+J46 -> 9308 | K62: =K60+K58+K56+K52+K48+K46 -> -350 | ... M62: =M60+M58+M56+M52+M48+M46 -> 696 | N62: =N60+N58+N56+N52+N48+N145+N46 -> 634.00041 | O62: =O60+O58+O56+O52+O48+O46 -> 21 | P62: =SUM(D62:O62) -> 59364 | Q62: =P62/12 -> 4947
A64: 12 | B64: WHOLESALE PRI | C64: PRI
A65: 13 | B65: WHOLESALE TRANS | C65: TRA
A66: 14 | B66: TOTAL WHOLESALE | D66: =SUM(D64:D65) -> 0 | E66: =SUM(E64:E65) -> 0 | F66: =SUM(F64:F65) -> 0 | G66: =SUM(G64:G65) -> 0 | H66: =SUM(H64:H65) -> 0 | I66: =SUM(I64:I65) -> 0 | J66: =SUM(J64:J65) -> 0 | K66: =SUM(K64:K65) -> 0 | ... O66: =SUM(O64:O65) -> 0 | P66: =SUM(D66:O66) -> 0 | Q66: =P66/12 -> 0
A68: 15 | B68: =B36 -> TOTAL AEP TEXAS | D68: =+D66+D62 -> 3464 | E68: =+E66+E62 -> 12654 | F68: =+F66+F62 -> 10085 | G68: =+G66+G62 -> 8433 | H68: =+H66+H62 -> 6676 | I68: =+I66+I62 -> 6543 | J68: =+J66+J62 -> 9308 | K68: =+K66+K62 -> -350 | ... O68: =+O66+O62 -> 21 | P68: =SUM(D68:O68) -> 59364 | Q68: =P68/12 -> 4947
B70: =+B37 -> Note: Secondary < 10 kW includes Unmetered service; Lighting customers are fixture counts.
B72: =+B39 -> AEP TEXAS
B73: OTHER CUSTOMER COUNT ADJUSTMENT
B74: =+B41 -> FOR TEST YEAR ENDED DECEMBER 31, 2018
D76: =D43 -> 0 | G76: =G43 -> 0
A77: LINE | B77: DESCRIPTION | C77: VOLT | D77: =+D44 -> JANUARY | E77: =+E44 -> FEBRUARY | F77: =+F44 -> MARCH | G77: =+G44 -> APRIL | H77: =+H44 -> MAY | I77: =+I44 -> JUNE | J77: =+J44 -> JULY | K77: =+K44 -> AUGUST | ... O77: =+O44 -> DECEMBER | P77: TOTAL | Q77: AVERAGE
A79: 1 | B79: RESIDENTIAL SERVICE | C79: SEC | P79: =SUM(D79:O79) -> 0 | Q79: =P79/12 -> 0
A81: 2 | B81: SECONDARY < 10 kW | C81: SEC | P81: =SUM(D81:O81) -> 0 | Q81: =P81/12 -> 0
A83: 3 | B83: SECONDARY > 10 kW NCP | C83: SEC | P83: =SUM(D83:O83) -> 0 | Q83: =P83/12 -> 0
A84: 4 | B84: SECONDARY > 10 kW 4CP | C84: SEC | P84: =SUM(D84:O84) -> 0 | Q84: =P84/12 -> 0
A85: 5 | B85: TOTAL SECONDARY > 10 kW | D85: =SUM(D83:D84) -> 0 | E85: =SUM(E83:E84) -> 0 | F85: =SUM(F83:F84) -> 0 | G85: =SUM(G83:G84) -> 0 | H85: =SUM(H83:H84) -> 0 | I85: =SUM(I83:I84) -> 0 | J85: =SUM(J83:J84) -> 0 | K85: =SUM(K83:K84) -> 0 | ... O85: =SUM(O83:O84) -> 0 | P85: =SUM(D85:O85) -> 0 | Q85: =SUM(Q83:Q84) -> 0
A87: 6 | B87: PRIMARY NCP | C87: PRI | P87: =SUM(D87:O87) -> 0 | Q87: =P87/12 -> 0
A88: 7 | B88: PRIMARY 4CP | C88: PRI | P88: =SUM(D88:O88) -> 0 | Q88: =P88/12 -> 0
A89: 8 | B89: TOTAL PRIMARY | D89: =SUM(D87:D88) -> 0 | E89: =SUM(E87:E88) -> 0 | F89: =SUM(F87:F88) -> 0 | G89: =SUM(G87:G88) -> 0 | H89: =SUM(H87:H88) -> 0 | I89: =SUM(I87:I88) -> 0 | J89: =SUM(J87:J88) -> 0 | K89: =SUM(K87:K88) -> 0 | ... N89: =SUM(N87:N88) -> 0 | P89: =SUM(D89:O89) -> 0 | Q89: =SUM(Q87:Q88) -> 0
A91: 9 | B91: TRANSMISSION | C91: TRA | P91: =SUM(D91:O91) -> 0 | Q91: =P91/12 -> 0
A93: 10 | B93: LIGHTING | C93: SEC | Q93: =P93/12 -> 0
A95: 11 | B95: TOTAL RETAIL | D95: =D93+D91+D89+D85+D81+D79 -> 0 | E95: =E93+E91+E89+E85+E81+E79 -> 0 | F95: =F93+F91+F89+F85+F81+F79 -> 0 | G95: =G93+G91+G89+G85+G81+G79 -> 0 | H95: =H93+H91+H89+H85+H81+H79 -> 0 | I95: =I93+I91+I89+I85+I81+I79 -> 0 | J95: =J93+J91+J89+J85+J81+J79 -> 0 | K95: =K93+K91+K89+K85+K81+K79 -> 0 | ... O95: =O93+O91+O89+O85+O81+O79 -> 0 | P95: =SUM(D95:O95) -> 0 | Q95: =P95/12 -> 0
A97: 12 | B97: WHOLESALE PRI | C97: PRI | P97: =SUM(D97:O97) -> 0 | Q97: =P97/12 -> 0
A98: 13 | B98: WHOLESALE TRANS | C98: TRA | P98: =SUM(D98:O98) -> 0 | Q98: =P98/12 -> 0
A99: 14 | B99: TOTAL WHOLESALE | D99: =SUM(D97:D98) -> 0 | E99: =SUM(E97:E98) -> 0 | F99: =SUM(F97:F98) -> 0 | G99: =SUM(G97:G98) -> 0 | H99: =SUM(H97:H98) -> 0 | I99: =SUM(I97:I98) -> 0 | J99: =SUM(J97:J98) -> 0 | K99: =SUM(K97:K98) -> 0 | ... O99: =SUM(O97:O98) -> 0 | P99: =SUM(D99:O99) -> 0 | Q99: =P99/12 -> 0
A101: 15 | B101: =B36 -> TOTAL AEP TEXAS | D101: =D99+D95 -> 0 | E101: =+E99+E95 -> 0 | F101: =+F99+F95 -> 0 | G101: =+G99+G95 -> 0 | H101: =+H99+H95 -> 0 | I101: =+I99+I95 -> 0 | J101: =+J99+J95 -> 0 | K101: =+K99+K95 -> 0 | L101: =+L99+L95 -> 0 | ... O101: =+O99+O95 -> 0 | P101: =SUM(D101:O101) -> 0 | Q101: =P101/12 -> 0
B103: =+B37 -> Note: Secondary < 10 kW includes Unmetered service; Lighting customers are fixture counts.
B105: =+B39 -> AEP TEXAS
B106: ADJUSTED CUSTOMER COUNT
B107: =+B9 -> FOR TEST YEAR ENDED DECEMBER 31, 2018
B108: II-H-3.2 | D108: =+D11 -> 0 | G108: =G11 -> 0
A109: Line | B109: DESCRIPTION | C109: VOLT | D109: =+D12 -> JANUARY | E109: =+E12 -> FEBRUARY | F109: =+F12 -> MARCH | G109: =+G12 -> APRIL | H109: =+H12 -> MAY | I109: =+I12 -> JUNE | J109: =+J12 -> JULY | K109: =+K12 -> AUGUST | ... P109: =+P12 -> TOTAL | Q109: AVERAGE
A111: 1 | B111: RESIDENTIAL SERVICE | C111: SEC | D111: =D46+D14+D79 -> 876553 | E111: =E46+E14+E79 -> 876553 | F111: =F46+F14+F79 -> 876553 | G111: =G46+G14+G79 -> 876553 | H111: =H46+H14+H79 -> 876553 | I111: =I46+I14+I79 -> 876553 | J111: =J46+J14+J79 -> 876553 | K111: =K46+K14+K79 -> 876553 | ... O111: =O46+O14+O79 -> 876553 | P111: =SUM(D111:O111) -> 10518636 | Q111: =P111/12 -> 876553
A113: 2 | B113: SECONDARY < 10 kW | C113: SEC | D113: =D48+D16+D81 -> 89158 | E113: =E48+E16+E81 -> 89158 | F113: =F48+F16+F81 -> 89158 | G113: =G48+G16+G81 -> 89158 | H113: =H48+H16+H81 -> 89158 | I113: =I48+I16+I81 -> 89158 | J113: =J48+J16+J81 -> 89158 | K113: =K48+K16+K81 -> 89158 | ... O113: =O48+O16+O81 -> 89158 | P113: =SUM(D113:O113) -> 1069896 | Q113: =P113/12 -> 89158
A115: 3 | B115: SECONDARY > 10 kW NCP | C115: SEC | D115: =D50+D18+D83 -> 72592 | E115: =E50+E18+E83 -> 72592 | F115: =F50+F18+F83 -> 72592 | G115: =G50+G18+G83 -> 72592 | H115: =H50+H18+H83 -> 72592 | I115: =I50+I18+I83 -> 72592 | J115: =J50+J18+J83 -> 72592 | K115: =K50+K18+K83 -> 72592 | ... O115: =O50+O18+O83 -> 72592 | P115: =SUM(D115:O115) -> 871104 | Q115: =P115/12 -> 72592
A116: 4 | B116: SECONDARY > 10 kW 4CP | C116: SEC | D116: =D51+D19+D84 -> 478 | E116: =E51+E19+E84 -> 478 | F116: =F51+F19+F84 -> 478 | G116: =G51+G19+G84 -> 478 | H116: =H51+H19+H84 -> 478 | I116: =I51+I19+I84 -> 478 | J116: =J51+J19+J84 -> 478 | K116: =K51+K19+K84 -> 478 | ... O116: =O51+O19+O84 -> 478 | P116: =SUM(D116:O116) -> 5736 | Q116: =P116/12 -> 478
A117: 5 | B117: TOTAL SECONDARY > 10 kW | D117: =SUM(D115:D116) -> 73070 | E117: =SUM(E115:E116) -> 73070 | F117: =SUM(F115:F116) -> 73070 | G117: =SUM(G115:G116) -> 73070 | H117: =SUM(H115:H116) -> 73070 | I117: =SUM(I115:I116) -> 73070 | J117: =SUM(J115:J116) -> 73070 | K117: =SUM(K115:K116) -> 73070 | ... O117: =SUM(O115:O116) -> 73070 | P117: =SUM(D117:O117) -> 876840 | Q117: =P117/12 -> 73070
A119: 6 | B119: PRIMARY NCP | C119: PRI | D119: =D54+D22+D87 -> 574 | E119: =E54+E22+E87 -> 574 | F119: =F54+F22+F87 -> 574 | G119: =G54+G22+G87 -> 574 | H119: =H54+H22+H87 -> 574 | I119: =I54+I22+I87 -> 574 | J119: =J54+J22+J87 -> 574 | K119: =K54+K22+K87 -> 574 | ... O119: =O54+O22+O87 -> 574 | P119: =SUM(D119:O119) -> 6888 | Q119: =P119/12 -> 574
A120: 7 | B120: PRIMARY 4CP | C120: PRI | D120: =D55+D23+D88 -> 471 | E120: =E55+E23+E88 -> 471 | F120: =F55+F23+F88 -> 471 | G120: =G55+G23+G88 -> 471 | H120: =H55+H23+H88 -> 471 | I120: =I55+I23+I88 -> 471 | J120: =J55+J23+J88 -> 471 | K120: =K55+K23+K88 -> 471 | ... O120: =O55+O23+O88 -> 471 | P120: =SUM(D120:O120) -> 5652 | Q120: =P120/12 -> 471
A121: 8 | B121: TOTAL PRIMARY | D121: =SUM(D119:D120) -> 1045 | E121: =SUM(E119:E120) -> 1045 | F121: =SUM(F119:F120) -> 1045 | G121: =SUM(G119:G120) -> 1045 | H121: =SUM(H119:H120) -> 1045 | I121: =SUM(I119:I120) -> 1045 | J121: =SUM(J119:J120) -> 1045 | K121: =SUM(K119:K120) -> 1045 | ... O121: =SUM(O119:O120) -> 1045 | P121: =SUM(D121:O121) -> 12540 | Q121: =P121/12 -> 1045
A123: 9 | B123: TRANSMISSION | C123: TRA | D123: =D58+D26+D91 -> 85 | E123: =E58+E26+E91 -> 85 | F123: =F58+F26+F91 -> 85 | G123: =G58+G26+G91 -> 85 | H123: =H58+H26+H91 -> 85 | I123: =I58+I26+I91 -> 85 | J123: =J58+J26+J91 -> 85 | K123: =K58+K26+K91 -> 85 | ... O123: =O58+O26+O91 -> 85 | P123: =SUM(D123:O123) -> 1020 | Q123: =P123/12 -> 85
A125: 10 | B125: LIGHTING | C125: SEC | D125: =D60+D28+D93 -> 220232 | E125: =E60+E28+E93 -> 220232 | F125: =F60+F28+F93 -> 220232 | G125: =G60+G28+G93 -> 220232 | H125: =H60+H28+H93 -> 220232 | I125: =I60+I28+I93 -> 220232 | J125: =J60+J28+J93 -> 220232 | K125: =K60+K28+K93 -> 220232 | ... O125: =O60+O28+O93 -> 220232 | P125: =SUM(D125:O125) -> 2642784 | Q125: =P125/12 -> 220232
A127: 11 | B127: TOTAL RETAIL | D127: =D125+D123+D121+D117+D113+D111 -> 1260143 | E127: =E125+E123+E121+E117+E113+E111 -> 1260143 | F127: =F125+F123+F121+F117+F113+F111 -> 1260143 | G127: =G125+G123+G121+G117+G113+G111 -> 1260143 | H127: =H125+H123+H121+H117+H113+H111 -> 1260143 | I127: =I125+I123+I121+I117+I113+I111 -> 1260143 | J127: =J125+J123+J121+J117+J113+J111 -> 1260143 | K127: =K125+K123+K121+K117+K113+K111 -> 1260143 | ... O127: =O125+O123+O121+O117+O113+O111 -> 1260143 | P127: =SUM(D127:O127) -> 15121716 | Q127: =P127/12 -> 1260143
A129: 12 | B129: WHOLESALE PRI | C129: PRI | D129: =D64+D32 -> 0 | E129: =E64+E32 -> 0 | F129: =F64+F32 -> 0 | G129: =G64+G32 -> 0 | H129: =H64+H32 -> 0 | I129: =I64+I32 -> 0 | J129: =J64+J32 -> 0 | K129: =K64+K32 -> 0 | ... O129: =O64+O32 -> 0 | P129: =SUM(D129:O129) -> 0 | Q129: =P129/12 -> 0
A130: 13 | B130: WHOLESALE TRANS | C130: TRA | P130: =SUM(D130:O130) -> 0 | Q130: =P130/12 -> 0
A131: 14 | B131: TOTAL WHOLESALE | D131: =SUM(D129:D130) -> 0 | E131: =SUM(E129:E130) -> 0 | F131: =SUM(F129:F130) -> 0 | G131: =SUM(G129:G130) -> 0 | H131: =SUM(H129:H130) -> 0 | I131: =SUM(I129:I130) -> 0 | J131: =SUM(J129:J130) -> 0 | K131: =SUM(K129:K130) -> 0 | ... O131: =SUM(O129:O130) -> 0 | P131: =SUM(D131:O131) -> 0 | Q131: =P131/12 -> 0
A133: 15 | B133: =B36 -> TOTAL AEP TEXAS | D133: =+D131+D127 -> 1260143 | E133: =+E131+E127 -> 1260143 | F133: =+F131+F127 -> 1260143 | G133: =+G131+G127 -> 1260143 | H133: =+H131+H127 -> 1260143 | I133: =+I131+I127 -> 1260143 | J133: =+J131+J127 -> 1260143 | K133: =+K131+K127 -> 1260143 | ... O133: =+O131+O127 -> 1260143 | P133: =SUM(D133:O133) -> 15121716 | Q133: =P133/12 -> 1260143
B135: =+B37 -> Note: Secondary < 10 kW includes Unmetered service; Lighting customers are fixture counts.
B138: =+B7 -> AEP TEXAS
B139: CUSTOMER COUNT ADJUSTMENT FACTOR
B140: =+B9 -> FOR TEST YEAR ENDED DECEMBER 31, 2018
B141: II-H-3.3
D142: =D11 -> 0 | G142: =G11 -> 0
A143: LINE | B143: DESCRIPTION | C143: VOLT | D143: =+D12 -> JANUARY | E143: =+E12 -> FEBRUARY | F143: =+F12 -> MARCH | G143: =+G12 -> APRIL | H143: =+H12 -> MAY | I143: =+I12 -> JUNE | J143: =+J12 -> JULY | K143: =+K12 -> AUGUST | ... O143: =+O12 -> DECEMBER
A145: 1 | B145: RESIDENTIAL SERVICE | C145: SEC | D145: =+'II-H-1.2'!D74/'II-H-1.2'!D14 -> 0.010526492 | E145: =+'II-H-1.2'!E74/'II-H-1.2'!E14 -> 0.010636027 | F145: =+'II-H-1.2'!F74/'II-H-1.2'!F14 -> 0.010018075 | G145: =+'II-H-1.2'!G74/'II-H-1.2'!G14 -> 0.008433212 | H145: =+'II-H-1.2'!H74/'II-H-1.2'!H14 -> 0.0073377116 | I145: =+'II-H-1.2'!I74/'II-H-1.2'!I14 -> 0.006615083 | J145: =+'II-H-1.2'!J74/'II-H-1.2'!J14 -> 0.0070992167 | K145: =+'II-H-1.2'!K74/'II-H-1.2'!K14 -> 0.0012433109 | ... O145: =+'II-H-1.2'!O74/'II-H-1.2'!O14 -> 0
A147: 2 | B147: SECONDARY < 10 kW | C147: SEC | D147: =+'II-H-1.2'!D76/'II-H-1.2'!D16 -> -0.01336778 | E147: =+'II-H-1.2'!E76/'II-H-1.2'!E16 -> 0.0036189131 | F147: =+'II-H-1.2'!F76/'II-H-1.2'!F16 -> 0.0062688169 | G147: =+'II-H-1.2'!G76/'II-H-1.2'!G16 -> 0.0032251808 | H147: =+'II-H-1.2'!H76/'II-H-1.2'!H16 -> 0.00061321925 | I147: =+'II-H-1.2'!I76/'II-H-1.2'!I16 -> -0.0016085072 | J147: =+'II-H-1.2'!J76/'II-H-1.2'!J16 -> -0.002486912 | K147: =+'II-H-1.2'!K76/'II-H-1.2'!K16 -> -0.0060110592 | ... O147: =+'II-H-1.2'!O76/'II-H-1.2'!O16 -> 0
A149: 3 | B149: SECONDARY > 10 kW NCP | C149: SEC | D149: =+'II-H-1.2'!D78/'II-H-1.2'!D18 -> 0.037062313 | E149: =+'II-H-1.2'!E78/'II-H-1.2'!E18 -> 0.018978126 | F149: =+'II-H-1.2'!F78/'II-H-1.2'!F18 -> 0.0083487159 | G149: =+'II-H-1.2'!G78/'II-H-1.2'!G18 -> 0.0073151286 | H149: =+'II-H-1.2'!H78/'II-H-1.2'!H18 -> 0.0088652765 | I149: =+'II-H-1.2'!I78/'II-H-1.2'!I18 -> 0.0075176102 | J149: =+'II-H-1.2'!J78/'II-H-1.2'!J18 -> 0.0058696785 | K149: =+'II-H-1.2'!K78/'II-H-1.2'!K18 -> 0.0016644082 | ... O149: =+'II-H-1.2'!O78/'II-H-1.2'!O18 -> 0
...

Sheet II-H-4.1 Monthly
B2: PUBLIC UTILITY COMMISSION OF TEXAS
B3: AEP TEXAS INC
B4: II-H-4.1 REVENUE IMPACTS MONTHLY
B5: TEST YEAR ENDING 12/31/2018
B6: DOCKET NUMBER (PENDING ASSIGNMENT)
B8: AEP TEXAS
B9: UNADJUSTED BILLED REVENUE
B10: FOR TEST YEAR ENDED DECEMBER 31, 2018
A13: LINE | B13: DESCRIPTION | C13: VOLT | D13: JANUARY | E13: FEBRUARY | F13: MARCH | G13: APRIL | H13: MAY | I13: JUNE | J13: JULY | K13: AUGUST | L13: SEPTEMBER | M13: OCTOBER | N13: NOVEMBER | O13: DECEMBER | P13: TOTAL
A15: 1 | B15: RESIDENTIAL SERVICE | C15: SEC | D15: ='[6]Sales of Elec'!F85+'[5]II-H-4.1 Monthly'!D8 -> 59562881 | E15: ='[6]Sales of Elec'!G85+'[5]II-H-4.1 Monthly'!E8 -> 46223915 | F15: ='[6]Sales of Elec'!H85+'[5]II-H-4.1 Monthly'!F8 -> 36481296 | G15: ='[6]Sales of Elec'!I85+'[5]II-H-4.1 Monthly'!G8 -> 37837457 | H15: ='[6]Sales of Elec'!J85+'[5]II-H-4.1 Monthly'!H8 -> 41112166 | I15: ='[6]Sales of Elec'!K85+'[5]II-H-4.1 Monthly'!I8 -> 58461559 | J15: ='[6]Sales of Elec'!L85+'[5]II-H-4.1 Monthly'!J8 -> 60803686 | K15: ='[6]Sales of Elec'!M85+'[5]II-H-4.1 Monthly'!K8 -> 61629222 | ... O15: ='[6]Sales of Elec'!Q85+'[5]II-H-4.1 Monthly'!O8 -> 43224125 | P15: =SUM(D15:O15) -> 5.940381e+08
A17: 2 | B17: SECONDARY < 10 kW | C17: SEC | D17: ='[6]Sales of Elec'!F12+'[5]II-H-4.1 Monthly'!D10 -> 4017775.7 | E17: ='[6]Sales of Elec'!G12+'[5]II-H-4.1 Monthly'!E10 -> 3527136.3 | F17: ='[6]Sales of Elec'!H12+'[5]II-H-4.1 Monthly'!F10 -> 3367785.1 | G17: ='[6]Sales of Elec'!I12+'[5]II-H-4.1 Monthly'!G10 -> 3473543.3 | H17: ='[6]Sales of Elec'!J12+'[5]II-H-4.1 Monthly'!H10 -> 3520682.9 | I17: ='[6]Sales of Elec'!K12+'[5]II-H-4.1 Monthly'!I10 -> 4069750.4 | J17: ='[6]Sales of Elec'!L12+'[5]II-H-4.1 Monthly'!J10 -> 4143613.9 | K17: ='[6]Sales of Elec'!M12+'[5]II-H-4.1 Monthly'!K10 -> 4161293.4 | ... O17: ='[6]Sales of Elec'!Q12+'[5]II-H-4.1 Monthly'!O10 -> 3476509.3 | P17: =SUM(D17:O17) -> 44821473
A19: 3 | B19: SECONDARY > 10 kW NCP | C19: SEC | D19: ='[6]Sales of Elec'!F30+'[5]II-H-4.1 Monthly'!D12 -> 29523362 | E19: ='[6]Sales of Elec'!G30+'[5]II-H-4.1 Monthly'!E12 -> 28956586 | F19: ='[6]Sales of Elec'!H30+'[5]II-H-4.1 Monthly'!F12 -> 27785575 | G19: ='[6]Sales of Elec'!I30+'[5]II-H-4.1 Monthly'!G12 -> 27734369 | H19: ='[6]Sales of Elec'!J30+'[5]II-H-4.1 Monthly'!H12 -> 28220722 | I19: ='[6]Sales of Elec'!K30+'[5]II-H-4.1 Monthly'!I12 -> 30198895 | J19: ='[6]Sales of Elec'!L30+'[5]II-H-4.1 Monthly'!J12 -> 30022349 | K19: ='[6]Sales of Elec'!M30+'[5]II-H-4.1 Monthly'!K12 -> 30408070 | ... O19: ='[6]Sales of Elec'!Q30+'[5]II-H-4.1 Monthly'!O12 -> 27601159 | P19: =SUM(D19:O19) -> 3.466567e+08
A20: 4 | B20: SECONDARY > 10 kW 4CP | C20: SEC | D20: ='[6]Sales of Elec'!F21+'[5]II-H-4.1 Monthly'!D13 -> 2751168.4 | E20: ='[6]Sales of Elec'!G21+'[5]II-H-4.1 Monthly'!E13 -> 2680446.6 | F20: ='[6]Sales of Elec'!H21+'[5]II-H-4.1 Monthly'!F13 -> 2602449.6 | G20: ='[6]Sales of Elec'!I21+'[5]II-H-4.1 Monthly'!G13 -> 2576572.6 | H20: ='[6]Sales of Elec'!J21+'[5]II-H-4.1 Monthly'!H13 -> 2595536.4 | I20: ='[6]Sales of Elec'!K21+'[5]II-H-4.1 Monthly'!I13 -> 2560709.3 | J20: ='[6]Sales of Elec'!L21+'[5]II-H-4.1 Monthly'!J13 -> 2650227 | K20: ='[6]Sales of Elec'!M21+'[5]II-H-4.1 Monthly'!K13 -> 2729544.8 | ... O20: ='[6]Sales of Elec'!Q21+'[5]II-H-4.1 Monthly'!O13 -> 2551472.5 | P20: =SUM(D20:O20) -> 31960019
A21: 5 | B21: TOTAL SECONDARY > 10 kW | D21: =SUM(D19:D20) -> 32274530 | E21: =SUM(E19:E20) -> 31637032 | F21: =SUM(F19:F20) -> 30388024 | G21: =SUM(G19:G20) -> 30310942 | H21: =SUM(H19:H20) -> 30816258 | I21: =SUM(I19:I20) -> 32759604 | J21: =SUM(J19:J20) -> 32672576 | K21: =SUM(K19:K20) -> 33137615 | ... P21: =SUM(P19:P20) -> 3.7861672e+08
A23: 6 | B23: PRIMARY NCP | C23: PRI | D23: ='[6]Sales of Elec'!F82+'[5]II-H-4.1 Monthly'!D16 -> 666902.32 | E23: ='[6]Sales of Elec'!G82+'[5]II-H-4.1 Monthly'!E16 -> 677520.78 | F23: ='[6]Sales of Elec'!H82+'[5]II-H-4.1 Monthly'!F16 -> 652064.27 | G23: ='[6]Sales of Elec'!I82+'[5]II-H-4.1 Monthly'!G16 -> 674447.48 | H23: ='[6]Sales of Elec'!J82+'[5]II-H-4.1 Monthly'!H16 -> 699770.27 | I23: ='[6]Sales of Elec'!K82+'[5]II-H-4.1 Monthly'!I16 -> 728477.63 | J23: ='[6]Sales of Elec'!L82+'[5]II-H-4.1 Monthly'!J16 -> 708664.35 | K23: ='[6]Sales of Elec'!M82+'[5]II-H-4.1 Monthly'!K16 -> 771698.32 | ... O23: ='[6]Sales of Elec'!Q82+'[5]II-H-4.1 Monthly'!O16 -> 732600.22 | P23: =SUM(D23:O23) -> 8725085
A24: 7 | B24: PRIMARY 4CP | C24: PRI | D24: ='[6]Sales of Elec'!F77+'[5]II-H-4.1 Monthly'!D17 -> 6997307.2 | E24: ='[6]Sales of Elec'!G77+'[5]II-H-4.1 Monthly'!E17 -> 6686883.6 | F24: ='[6]Sales of Elec'!H77+'[5]II-H-4.1 Monthly'!F17 -> 6771838.6 | G24: ='[6]Sales of Elec'!I77+'[5]II-H-4.1 Monthly'!G17 -> 6632990.7 | H24: ='[6]Sales of Elec'!J77+'[5]II-H-4.1 Monthly'!H17 -> 7112153.5 | I24: ='[6]Sales of Elec'!K77+'[5]II-H-4.1 Monthly'!I17 -> 7260254.1 | J24: ='[6]Sales of Elec'!L77+'[5]II-H-4.1 Monthly'!J17 -> 7111674.3 | K24: ='[6]Sales of Elec'!M77+'[5]II-H-4.1 Monthly'!K17 -> 7042631.6 | ... O24: ='[6]Sales of Elec'!Q77+'[5]II-H-4.1 Monthly'!O17 -> 6592901.7 | P24: =SUM(D24:O24) -> 83153991
A25: 8 | B25: TOTAL PRIMARY | D25: =SUM(D23:D24) -> 7664209.5 | E25: =SUM(E23:E24) -> 7364404.4 | F25: =SUM(F23:F24) -> 7423902.9 | G25: =SUM(G23:G24) -> 7307438.2 | H25: =SUM(H23:H24) -> 7811923.8 | I25: =SUM(I23:I24) -> 7988731.8 | J25: =SUM(J23:J24) -> 7820338.7 | K25: =SUM(K23:K24) -> 7814330 | ... P25: =SUM(P23:P24) -> 91879076
A27: 9 | B27: TRANSMISSION | C27: TRA | D27: ='[6]Sales of Elec'!F97+'[5]II-H-4.1 Monthly'!D20 -> 5167460.3 | E27: ='[6]Sales of Elec'!G97+'[5]II-H-4.1 Monthly'!E20 -> 3802453.8 | F27: ='[6]Sales of Elec'!H97+'[5]II-H-4.1 Monthly'!F20 -> 4561676.1 | G27: ='[6]Sales of Elec'!I97+'[5]II-H-4.1 Monthly'!G20 -> 4154398.8 | H27: ='[6]Sales of Elec'!J97+'[5]II-H-4.1 Monthly'!H20 -> 4347111.8 | I27: ='[6]Sales of Elec'!K97+'[5]II-H-4.1 Monthly'!I20 -> 4738061.7 | J27: ='[6]Sales of Elec'!L97+'[5]II-H-4.1 Monthly'!J20 -> 3729155.4 | K27: ='[6]Sales of Elec'!M97+'[5]II-H-4.1 Monthly'!K20 -> 3862540.2 | ... O27: ='[6]Sales of Elec'!Q97+'[5]II-H-4.1 Monthly'!O20 -> 2625361.6 | P27: =SUM(D27:O27) -> 49149052
A29: 10 | B29: LIGHTING | C29: SEC | D29: ='[6]Sales of Elec'!F71+'[5]II-H-4.1 Monthly'!D22 -> 2206674.3 | E29: ='[6]Sales of Elec'!G71+'[5]II-H-4.1 Monthly'!E22 -> 2199185 | F29: ='[6]Sales of Elec'!H71+'[5]II-H-4.1 Monthly'!F22 -> 2196843.5 | G29: ='[6]Sales of Elec'!I71+'[5]II-H-4.1 Monthly'!G22 -> 2198649.6 | H29: ='[6]Sales of Elec'!J71+'[5]II-H-4.1 Monthly'!H22 -> 2197657.9 | I29: ='[6]Sales of Elec'!K71+'[5]II-H-4.1 Monthly'!I22 -> 2198275 | J29: ='[6]Sales of Elec'!L71+'[5]II-H-4.1 Monthly'!J22 -> 2198643.7 | K29: ='[6]Sales of Elec'!M71+'[5]II-H-4.1 Monthly'!K22 -> 2197724.8 | ... O29: ='[6]Sales of Elec'!Q71+'[5]II-H-4.1 Monthly'!O22 -> 2149235.6 | P29: =SUM(D29:O29) -> 26176142
A31: 11 | B31: TOTAL RETAIL | D31: =D29+D27+D25+D21+D17+D15 -> 1.1089353e+08 | E31: =E29+E27+E25+E21+E17+E15 -> 94754126 | F31: =F29+F27+F25+F21+F17+F15 -> 84419528 | G31: =G29+G27+G25+G21+G17+G15 -> 85282429 | H31: =H29+H27+H25+H21+H17+H15 -> 89805801 | I31: =I29+I27+I25+I21+I17+I15 -> 1.1021598e+08 | J31: =J29+J27+J25+J21+J17+J15 -> 1.1136801e+08 | K31: =K29+K27+K25+K21+K17+K15 -> 1.1280272e+08 | ... P31: =P29+P27+P25+P21+P17+P15 -> 1.1846806e+09
A33: 12 | B33: WHOLESALE PRI | C33: PRI | P33: =SUM(D33:O33) -> 0
A34: 13 | B34: WHOLESALE TRANS | C34: TRA | P34: =SUM(D34:O34) -> 0
A35: 14 | B35: TOTAL WHOLESALE | D35: =SUM(D33:D34) -> 0 | E35: =SUM(E33:E34) -> 0 | F35: =SUM(F33:F34) -> 0 | G35: =SUM(G33:G34) -> 0 | H35: =SUM(H33:H34) -> 0 | I35: =SUM(I33:I34) -> 0 | J35: =SUM(J33:J34) -> 0 | K35: =SUM(K33:K34) -> 0 | ... P35: =SUM(P33:P34) -> 0
A37: 15 | B37: TOTAL AEP TEXAS | D37: =+D35+D31 -> 1.1089353e+08 | E37: =+E35+E31 -> 94754126 | F37: =+F35+F31 -> 84419528 | G37: =+G35+G31 -> 85282429 | H37: =+H35+H31 -> 89805801 | I37: =+I35+I31 -> 1.1021598e+08 | J37: =+J35+J31 -> 1.1136801e+08 | K37: =+K35+K31 -> 1.1280272e+08 | ... P37: =+P35+P31 -> 1.1846806e+09
B41: AEP TEXAS
B42: TRANSMISSION SYSTEM CHARGE ADJUSTMENT
B43: =B10 -> FOR TEST YEAR ENDED DECEMBER 31, 2018
A46: LINE | B46: DESCRIPTION | C46: VOLT | D46: =+D13 -> JANUARY | E46: =+E13 -> FEBRUARY | F46: =+F13 -> MARCH | G46: =+G13 -> APRIL | H46: =+H13 -> MAY | I46: =+I13 -> JUNE | J46: =+J13 -> JULY | K46: =+K13 -> AUGUST | ... O46: =+O13 -> DECEMBER | P46: TOTAL
A48: 1 | B48: RESIDENTIAL SERVICE | C48: SEC | D48: =-'[6]TCC Sales Elec Base Rate Dist T'!T166+'[5]II-H-4.1 Monthly'!D40 -> -6288378.5 | E48: =-'[6]TCC Sales Elec Base Rate Dist T'!U166+'[5]II-H-4.1 Monthly'!E40 -> -4665888.2 | F48: =-'[6]TCC Sales Elec Base Rate Dist T'!V166+'[5]II-H-4.1 Monthly'!F40 -> -3721823.7 | G48: =-'[6]TCC Sales Elec Base Rate Dist T'!W166+'[5]II-H-4.1 Monthly'!G40 -> -3889921.1 | H48: =-'[6]TCC Sales Elec Base Rate Dist T'!X166+'[5]II-H-4.1 Monthly'!H40 -> -4318220.9 | I48: =-'[6]TCC Sales Elec Base Rate Dist T'!Y166+'[5]II-H-4.1 Monthly'!I40 -> -6599540.8 | J48: =-'[6]TCC Sales Elec Base Rate Dist T'!Z166+'[5]II-H-4.1 Monthly'!J40 -> -6920597.2 | K48: =-'[6]TCC Sales Elec Base Rate Dist T'!AA166+'[5]II-H-4.1 Monthly'!K40 -> -7016731.2 | ... O48: =-'[6]TCC Sales Elec Base Rate Dist T'!AE166+'[5]II-H-4.1 Monthly'!O40 -> -4533211.2 | P48: =SUM(D48:O48) -> -63989339
A50: 2 | B50: SECONDARY < 10 kW | C50: SEC | D50: =-'[6]TCC Sales Elec Base Rate Dist T'!T19+'[5]II-H-4.1 Monthly'!D42 -> -140145.56 | E50: =-'[6]TCC Sales Elec Base Rate Dist T'!U19+'[5]II-H-4.1 Monthly'!E42 -> -117930.87 | F50: =-'[6]TCC Sales Elec Base Rate Dist T'!V19+'[5]II-H-4.1 Monthly'!F42 -> -110616.65 | G50: =-'[6]TCC Sales Elec Base Rate Dist T'!W19+'[5]II-H-4.1 Monthly'!G42 -> -115048.78 | H50: =-'[6]TCC Sales Elec Base Rate Dist T'!X19+'[5]II-H-4.1 Monthly'!H42 -> -117104.3 | I50: =-'[6]TCC Sales Elec Base Rate Dist T'!Y19+'[5]II-H-4.1 Monthly'!I42 -> -143402.29 | J50: =-'[6]TCC Sales Elec Base Rate Dist T'!Z19+'[5]II-H-4.1 Monthly'!J42 -> -147396.09 | K50: =-'[6]TCC Sales Elec Base Rate Dist T'!AA19+'[5]II-H-4.1 Monthly'!K42 -> -148004.46 | ... O50: =-'[6]TCC Sales Elec Base Rate Dist T'!AE19+'[5]II-H-4.1 Monthly'!O42 -> -120066.44 | P50: =SUM(D50:O50) -> -1548795.4
A52: 3 | B52: SECONDARY > 10 kW NCP | C52: SEC | D52: =-'[6]TCC Sales Elec Base Rate Dist T'!T55+'[5]II-H-4.1 Monthly'!D44 -> -3196595.3 | E52: =-'[6]TCC Sales Elec Base Rate Dist T'!U55+'[5]II-H-4.1 Monthly'!E44 -> -3141242.8 | F52: =-'[6]TCC Sales Elec Base Rate Dist T'!V55+'[5]II-H-4.1 Monthly'!F44 -> -2965288.4 | G52: =-'[6]TCC Sales Elec Base Rate Dist T'!W55+'[5]II-H-4.1 Monthly'!G44 -> -2860064.6 | H52: =-'[6]TCC Sales Elec Base Rate Dist T'!X55+'[5]II-H-4.1 Monthly'!H44 -> -2927905.4 | I52: =-'[6]TCC Sales Elec Base Rate Dist T'!Y55+'[5]II-H-4.1 Monthly'!I44 -> -3123318.5 | J52: =-'[6]TCC Sales Elec Base Rate Dist T'!Z55+'[5]II-H-4.1 Monthly'!J44 -> -3088594.9 | K52: =-'[6]TCC Sales Elec Base Rate Dist T'!AA55+'[5]II-H-4.1 Monthly'!K44 -> -3137089.5 | ... O52: =-'[6]TCC Sales Elec Base Rate Dist T'!AE55+'[5]II-H-4.1 Monthly'!O44 -> -3015447.4 | P52: =SUM(D52:O52) -> -36701168
A53: 4 | B53: SECONDARY > 10 kW 4CP | C53: SEC | D53: =-'[6]TCC Sales Elec Base Rate Dist T'!T37+'[5]II-H-4.1 Monthly'!D45 -> -351612.37 | E53: =-'[6]TCC Sales Elec Base Rate Dist T'!U37+'[5]II-H-4.1 Monthly'!E45 -> -347078.54 | F53: =-'[6]TCC Sales Elec Base Rate Dist T'!V37+'[5]II-H-4.1 Monthly'!F45 -> -349584.7 | G53: =-'[6]TCC Sales Elec Base Rate Dist T'!W37+'[5]II-H-4.1 Monthly'!G45 -> -345585.25 | H53: =-'[6]TCC Sales Elec Base Rate Dist T'!X37+'[5]II-H-4.1 Monthly'!H45 -> -349271.97 | I53: =-'[6]TCC Sales Elec Base Rate Dist T'!Y37+'[5]II-H-4.1 Monthly'!I45 -> -328297.44 | J53: =-'[6]TCC Sales Elec Base Rate Dist T'!Z37+'[5]II-H-4.1 Monthly'!J45 -> -350442.32 | K53: =-'[6]TCC Sales Elec Base Rate Dist T'!AA37+'[5]II-H-4.1 Monthly'!K45 -> -340313.07 | ... O53: =-'[6]TCC Sales Elec Base Rate Dist T'!AE37+'[5]II-H-4.1 Monthly'!O45 -> -343486.19 | P53: =SUM(D53:O53) -> -4133847.1
A54: 5 | B54: TOTAL SECONDARY > 10 kW | D54: =SUM(D52:D53) -> -3548207.7 | E54: =SUM(E52:E53) -> -3488321.4 | F54: =SUM(F52:F53) -> -3314873.1 | G54: =SUM(G52:G53) -> -3205649.8 | H54: =SUM(H52:H53) -> -3277177.3 | I54: =SUM(I52:I53) -> -3451615.9 | J54: =SUM(J52:J53) -> -3439037.2 | K54: =SUM(K52:K53) -> -3477402.6 | ... P54: =SUM(P52:P53) -> -40835015
A56: 6 | B56: PRIMARY NCP | C56: PRI | D56: =-'[6]TCC Sales Elec Base Rate Dist T'!T160+'[5]II-H-4.1 Monthly'!D48 -> -80996.35 | E56: =-'[6]TCC Sales Elec Base Rate Dist T'!U160+'[5]II-H-4.1 Monthly'!E48 -> -88502.84 | F56: =-'[6]TCC Sales Elec Base Rate Dist T'!V160+'[5]II-H-4.1 Monthly'!F48 -> -82625.69 | G56: =-'[6]TCC Sales Elec Base Rate Dist T'!W160+'[5]II-H-4.1 Monthly'!G48 -> -85888.65 | H56: =-'[6]TCC Sales Elec Base Rate Dist T'!X160+'[5]II-H-4.1 Monthly'!H48 -> -92163.95 | I56: =-'[6]TCC Sales Elec Base Rate Dist T'!Y160+'[5]II-H-4.1 Monthly'!I48 -> -97019.97 | J56: =-'[6]TCC Sales Elec Base Rate Dist T'!Z160+'[5]II-H-4.1 Monthly'!J48 -> -93002.55 | K56: =-'[6]TCC Sales Elec Base Rate Dist T'!AA160+'[5]II-H-4.1 Monthly'!K48 -> -106513.46 | ... O56: =-'[6]TCC Sales Elec Base Rate Dist T'!AE160+'[5]II-H-4.1 Monthly'!O48 -> -91481.58 | P56: =SUM(D56:O56) -> -1127710.6
A57: 7 | B57: PRIMARY 4CP | C57: PRI | D57: =-'[6]TCC Sales Elec Base Rate Dist T'!T150+'[5]II-H-4.1 Monthly'!D49 -> -1119691.8 | E57: =-'[6]TCC Sales Elec Base Rate Dist T'!U150+'[5]II-H-4.1 Monthly'!E49 -> -1085094.4 | F57: =-'[6]TCC Sales Elec Base Rate Dist T'!V150+'[5]II-H-4.1 Monthly'!F49 -> -1077634.8 | G57: =-'[6]TCC Sales Elec Base Rate Dist T'!W150+'[5]II-H-4.1 Monthly'!G49 -> -1039649.4 | H57: =-'[6]TCC Sales Elec Base Rate Dist T'!X150+'[5]II-H-4.1 Monthly'!H49 -> -1103622.5 | I57: =-'[6]TCC Sales Elec Base Rate Dist T'!Y150+'[5]II-H-4.1 Monthly'!I49 -> -1093973.3 | J57: =-'[6]TCC Sales Elec Base Rate Dist T'!Z150+'[5]II-H-4.1 Monthly'!J49 -> -1082501.7 | K57: =-'[6]TCC Sales Elec Base Rate Dist T'!AA150+'[5]II-H-4.1 Monthly'!K49 -> -1076152.8 | ... O57: =-'[6]TCC Sales Elec Base Rate Dist T'!AE150+'[5]II-H-4.1 Monthly'!O49 -> -1046925.7 | P57: =SUM(D57:O57) -> -12989907
A58: 8 | B58: TOTAL PRIMARY | D58: =SUM(D56:D57) -> -1200688.2 | E58: =SUM(E56:E57) -> -1173597.3 | F58: =SUM(F56:F57) -> -1160260.5 | G58: =SUM(G56:G57) -> -1125538 | H58: =SUM(H56:H57) -> -1195786.4 | I58: =SUM(I56:I57) -> -1190993.3 | J58: =SUM(J56:J57) -> -1175504.2 | K58: =SUM(K56:K57) -> -1182666.3 | ... P58: =SUM(P56:P57) -> -14117617
A60: 9 | B60: TRANSMISSION | C60: TRA | D60: =-'[6]TCC Sales Elec Base Rate Dist T'!T190+'[5]II-H-4.1 Monthly'!D52 -> -1139916.5 | E60: =-'[6]TCC Sales Elec Base Rate Dist T'!U190+'[5]II-H-4.1 Monthly'!E52 -> -799631.29 | F60: =-'[6]TCC Sales Elec Base Rate Dist T'!V190+'[5]II-H-4.1 Monthly'!F52 -> -960719.01 | G60: =-'[6]TCC Sales Elec Base Rate Dist T'!W190+'[5]II-H-4.1 Monthly'!G52 -> -837829.32 | H60: =-'[6]TCC Sales Elec Base Rate Dist T'!X190+'[5]II-H-4.1 Monthly'!H52 -> -893336.29 | I60: =-'[6]TCC Sales Elec Base Rate Dist T'!Y190+'[5]II-H-4.1 Monthly'!I52 -> -1008355.8 | J60: =-'[6]TCC Sales Elec Base Rate Dist T'!Z190+'[5]II-H-4.1 Monthly'!J52 -> -746546.03 | K60: =-'[6]TCC Sales Elec Base Rate Dist T'!AA190+'[5]II-H-4.1 Monthly'!K52 -> -767426.25 | ... O60: =-'[6]TCC Sales Elec Base Rate Dist T'!AE190+'[5]II-H-4.1 Monthly'!O52 -> -597428.16 | P60: =SUM(D60:O60) -> -10529707
A62: 10 | B62: LIGHTING | C62: SEC | D62: =-'[6]TCC Sales Elec Base Rate Dist T'!T138+'[5]II-H-4.1 Monthly'!D54 -> -57128.99 | E62: =-'[6]TCC Sales Elec Base Rate Dist T'!U138+'[5]II-H-4.1 Monthly'!E54 -> -56917.81 | F62: =-'[6]TCC Sales Elec Base Rate Dist T'!V138+'[5]II-H-4.1 Monthly'!F54 -> -57059.29 | G62: =-'[6]TCC Sales Elec Base Rate Dist T'!W138+'[5]II-H-4.1 Monthly'!G54 -> -57105.29 | H62: =-'[6]TCC Sales Elec Base Rate Dist T'!X138+'[5]II-H-4.1 Monthly'!H54 -> -57062.17 | I62: =-'[6]TCC Sales Elec Base Rate Dist T'!Y138+'[5]II-H-4.1 Monthly'!I54 -> -57057.64 | J62: =-'[6]TCC Sales Elec Base Rate Dist T'!Z138+'[5]II-H-4.1 Monthly'!J54 -> -57070.98 | K62: =-'[6]TCC Sales Elec Base Rate Dist T'!AA138+'[5]II-H-4.1 Monthly'!K54 -> -57050.55 | ... O62: =-'[6]TCC Sales Elec Base Rate Dist T'!AE138+'[5]II-H-4.1 Monthly'!O54 -> -57040.58 | P62: =SUM(D62:O62) -> -684721.79
A64: 11 | B64: TOTAL RETAIL | D64: =D62+D60+D58+D54+D50+D48 -> -12374465 | E64: =E62+E60+E58+E54+E50+E48 -> -10302287 | F64: =F62+F60+F58+F54+F50+F48 -> -9325352.3 | G64: =G62+G60+G58+G54+G50+G48 -> -9231092.4 | H64: =H62+H60+H58+H54+H50+H48 -> -9858687.5 | I64: =I62+I60+I58+I54+I50+I48 -> -12450966 | J64: =J62+J60+J58+J54+J50+J48 -> -12486152 | K64: =K62+K60+K58+K54+K50+K48 -> -12649281 | ... P64: =P62+P60+P58+P54+P50+P48 -> -1.317052e+08
A66: 12 | B66: WHOLESALE PRI | C66: PRI | P66: =SUM(D66:O66) -> 0
A67: 13 | B67: WHOLESALE TRANS | C67: TRA | P67: =SUM(D67:O67) -> 0
A68: 14 | B68: TOTAL WHOLESALE | D68: =SUM(D66:D67) -> 0 | E68: =SUM(E66:E67) -> 0 | F68: =SUM(F66:F67) -> 0 | G68: =SUM(G66:G67) -> 0 | H68: =SUM(H66:H67) -> 0 | I68: =SUM(I66:I67) -> 0 | J68: =SUM(J66:J67) -> 0 | K68: =SUM(K66:K67) -> 0 | ... P68: =SUM(P66:P67) -> 0
A70: 15 | B70: =B37 -> TOTAL AEP TEXAS | D70: =+D68+D64 -> -12374465 | E70: =+E68+E64 -> -10302287 | F70: =+F68+F64 -> -9325352.3 | G70: =+G68+G64 -> -9231092.4 | H70: =+H68+H64 -> -9858687.5 | I70: =+I68+I64 -> -12450966 | J70: =+J68+J64 -> -12486152 | K70: =+K68+K64 -> -12649281 | ... P70: =+P68+P64 -> -1.317052e+08
B73: AEP TEXAS
B74: BASE RATE ENERGY EFFICIENCY ADJUSTMENT
B75: =B10 -> FOR TEST YEAR ENDED DECEMBER 31, 2018
A78: LINE | B78: DESCRIPTION | C78: VOLT | D78: =+D13 -> JANUARY | E78: =+E13 -> FEBRUARY | F78: =+F13 -> MARCH | G78: =+G13 -> APRIL | H78: =+H13 -> MAY | I78: =+I13 -> JUNE | J78: =+J13 -> JULY | K78: =+K13 -> AUGUST | ... O78: =+O13 -> DECEMBER | P78: TOTAL
A80: 1 | B80: RESIDENTIAL SERVICE | C80: SEC | D80: =-'[9]2018 Monthly Revenue'!D4+'[5]II-H-4.1 Monthly'!D73 -> -427949.67 | E80: =-'[9]2018 Monthly Revenue'!E4+'[5]II-H-4.1 Monthly'!E73 -> -317299.96 | F80: =-'[9]2018 Monthly Revenue'!F4+'[5]II-H-4.1 Monthly'!F73 -> -253239.08 | G80: =-'[9]2018 Monthly Revenue'!G4+'[5]II-H-4.1 Monthly'!G73 -> -265837.26 | H80: =-'[9]2018 Monthly Revenue'!H4+'[5]II-H-4.1 Monthly'!H73 -> -294986.92 | I80: =-'[9]2018 Monthly Revenue'!I4+'[5]II-H-4.1 Monthly'!I73 -> -449999.46 | J80: =-'[9]2018 Monthly Revenue'!J4+'[5]II-H-4.1 Monthly'!J73 -> -471016.82 | K80: =-'[9]2018 Monthly Revenue'!K4+'[5]II-H-4.1 Monthly'!K73 -> -478328.62 | ... O80: =-'[9]2018 Monthly Revenue'!O4+'[5]II-H-4.1 Monthly'!O73 -> -308006.5 | P80: =SUM(D80:O80) -> -4362164.4
A82: 2 | B82: SECONDARY < 10 kW | C82: SEC | D82: =-'[9]2018 Monthly Revenue'!D5+'[5]II-H-4.1 Monthly'!D75 -> -14498.67 | E82: =-'[9]2018 Monthly Revenue'!E5+'[5]II-H-4.1 Monthly'!E75 -> -12175.43 | F82: =-'[9]2018 Monthly Revenue'!F5+'[5]II-H-4.1 Monthly'!F75 -> -11465.93 | G82: =-'[9]2018 Monthly Revenue'!G5+'[5]II-H-4.1 Monthly'!G75 -> -11985.32 | H82: =-'[9]2018 Monthly Revenue'!H5+'[5]II-H-4.1 Monthly'!H75 -> -12205.8 | I82: =-'[9]2018 Monthly Revenue'!I5+'[5]II-H-4.1 Monthly'!I75 -> -14924.24 | J82: =-'[9]2018 Monthly Revenue'!J5+'[5]II-H-4.1 Monthly'!J75 -> -15292.79 | K82: =-'[9]2018 Monthly Revenue'!K5+'[5]II-H-4.1 Monthly'!K75 -> -15208.46 | ... O82: =-'[9]2018 Monthly Revenue'!O5+'[5]II-H-4.1 Monthly'!O75 -> -12391.23 | P82: =SUM(D82:O82) -> -160723.85
A84: 3 | B84: SECONDARY > 10 kW NCP | C84: SEC | D84: =-'[9]2018 Monthly Revenue'!D7+'[5]II-H-4.1 Monthly'!D77 -> -216435.16 | E84: =-'[9]2018 Monthly Revenue'!E7+'[5]II-H-4.1 Monthly'!E77 -> -214429.79 | F84: =-'[9]2018 Monthly Revenue'!F7+'[5]II-H-4.1 Monthly'!F77 -> -207697.7 | G84: =-'[9]2018 Monthly Revenue'!G7+'[5]II-H-4.1 Monthly'!G77 -> -207235.05 | H84: =-'[9]2018 Monthly Revenue'!H7+'[5]II-H-4.1 Monthly'!H77 -> -210923.59 | I84: =-'[9]2018 Monthly Revenue'!I7+'[5]II-H-4.1 Monthly'!I77 -> -217733.38 | J84: =-'[9]2018 Monthly Revenue'!J7+'[5]II-H-4.1 Monthly'!J77 -> -217246.09 | K84: =-'[9]2018 Monthly Revenue'!K7+'[5]II-H-4.1 Monthly'!K77 -> -218447.18 | ... O84: =-'[9]2018 Monthly Revenue'!O7+'[5]II-H-4.1 Monthly'!O77 -> -210227.45 | P84: =SUM(D84:O84) -> -2559350.1
A85: 4 | B85: SECONDARY > 10 kW 4CP | C85: SEC | D85: =-'[9]2018 Monthly Revenue'!D6+'[5]II-H-4.1 Monthly'!D78 -> -22077.88 | E85: =-'[9]2018 Monthly Revenue'!E6+'[5]II-H-4.1 Monthly'!E78 -> -21228.65 | F85: =-'[9]2018 Monthly Revenue'!F6+'[5]II-H-4.1 Monthly'!F78 -> -20785.97 | G85: =-'[9]2018 Monthly Revenue'!G6+'[5]II-H-4.1 Monthly'!G78 -> -19968.94 | H85: =-'[9]2018 Monthly Revenue'!H6+'[5]II-H-4.1 Monthly'!H78 -> -20279.81 | I85: =-'[9]2018 Monthly Revenue'!I6+'[5]II-H-4.1 Monthly'!I78 -> -20561.64 | J85: =-'[9]2018 Monthly Revenue'!J6+'[5]II-H-4.1 Monthly'!J78 -> -21179.2 | K85: =-'[9]2018 Monthly Revenue'!K6+'[5]II-H-4.1 Monthly'!K78 -> -21756.01 | ... O85: =-'[9]2018 Monthly Revenue'!O6+'[5]II-H-4.1 Monthly'!O78 -> -21064.63 | P85: =SUM(D85:O85) -> -255356.6
A86: 5 | B86: TOTAL SECONDARY > 10 kW | D86: =SUM(D84:D85) -> -238513.04 | E86: =SUM(E84:E85) -> -235658.44 | F86: =SUM(F84:F85) -> -228483.67 | G86: =SUM(G84:G85) -> -227203.99 | H86: =SUM(H84:H85) -> -231203.4 | I86: =SUM(I84:I85) -> -238295.02 | J86: =SUM(J84:J85) -> -238425.29 | K86: =SUM(K84:K85) -> -240203.19 | ... P86: =SUM(P84:P85) -> -2814706.7
A88: 6 | B88: PRIMARY NCP | C88: PRI | D88: =-'[9]2018 Monthly Revenue'!D9+'[5]II-H-4.1 Monthly'!D81 -> -6516.18 | E88: =-'[9]2018 Monthly Revenue'!E9+'[5]II-H-4.1 Monthly'!E81 -> -6724.3 | F88: =-'[9]2018 Monthly Revenue'!F9+'[5]II-H-4.1 Monthly'!F81 -> -6408.69 | G88: =-'[9]2018 Monthly Revenue'!G9+'[5]II-H-4.1 Monthly'!G81 -> -6548.15 | H88: =-'[9]2018 Monthly Revenue'!H9+'[5]II-H-4.1 Monthly'!H81 -> -7003.37 | I88: =-'[9]2018 Monthly Revenue'!I9+'[5]II-H-4.1 Monthly'!I81 -> -7201.32 | J88: =-'[9]2018 Monthly Revenue'!J9+'[5]II-H-4.1 Monthly'!J81 -> -6888.64 | K88: =-'[9]2018 Monthly Revenue'!K9+'[5]II-H-4.1 Monthly'!K81 -> -7240.55 | ... O88: =-'[9]2018 Monthly Revenue'!O9+'[5]II-H-4.1 Monthly'!O81 -> -6994.56 | P88: =SUM(D88:O88) -> -84014.47
A89: 7 | B89: PRIMARY 4CP | C89: PRI | D89: =-'[9]2018 Monthly Revenue'!D8+'[5]II-H-4.1 Monthly'!D82 -> -72379.54 | E89: =-'[9]2018 Monthly Revenue'!E8+'[5]II-H-4.1 Monthly'!E82 -> -69590.2 | F89: =-'[9]2018 Monthly Revenue'!F8+'[5]II-H-4.1 Monthly'!F82 -> -69992.38 | G89: =-'[9]2018 Monthly Revenue'!G8+'[5]II-H-4.1 Monthly'!G82 -> -68974.13 | H89: =-'[9]2018 Monthly Revenue'!H8+'[5]II-H-4.1 Monthly'!H82 -> -74909.14 | I89: =-'[9]2018 Monthly Revenue'!I8+'[5]II-H-4.1 Monthly'!I82 -> -75911.55 | J89: =-'[9]2018 Monthly Revenue'!J8+'[5]II-H-4.1 Monthly'!J82 -> -74104.87 | K89: =-'[9]2018 Monthly Revenue'!K8+'[5]II-H-4.1 Monthly'!K82 -> -59673.86 | ... O89: =-'[9]2018 Monthly Revenue'!O8+'[5]II-H-4.1 Monthly'!O82 -> -67846.73 | P89: =SUM(D89:O89) -> -849038.57
A90: 8 | B90: TOTAL PRIMARY | D90: =SUM(D88:D89) -> -78895.72 | E90: =SUM(E88:E89) -> -76314.5 | F90: =SUM(F88:F89) -> -76401.07 | G90: =SUM(G88:G89) -> -75522.28 | H90: =SUM(H88:H89) -> -81912.51 | I90: =SUM(I88:I89) -> -83112.87 | J90: =SUM(J88:J89) -> -80993.51 | K90: =SUM(K88:K89) -> -66914.41 | ... P90: =SUM(P88:P89) -> -933053.04
A92: 9 | B92: TRANSMISSION | C92: TRA | D92: =-'[9]2018 Monthly Revenue'!D10+'[5]II-H-4.1 Monthly'!D85 -> -58189.46 | E92: =-'[9]2018 Monthly Revenue'!E10+'[5]II-H-4.1 Monthly'!E85 -> -47808.1 | F92: =-'[9]2018 Monthly Revenue'!F10+'[5]II-H-4.1 Monthly'!F85 -> -54845.63 | G92: =-'[9]2018 Monthly Revenue'!G10+'[5]II-H-4.1 Monthly'!G85 -> -53873.82 | H92: =-'[9]2018 Monthly Revenue'!H10+'[5]II-H-4.1 Monthly'!H85 -> -54298.38 | I92: =-'[9]2018 Monthly Revenue'!I10+'[5]II-H-4.1 Monthly'!I85 -> -57284 | J92: =-'[9]2018 Monthly Revenue'!J10+'[5]II-H-4.1 Monthly'!J85 -> -49981.48 | K92: =-'[9]2018 Monthly Revenue'!K10+'[5]II-H-4.1 Monthly'!K85 -> -50074.78 | ... O92: =-'[9]2018 Monthly Revenue'!O10+'[5]II-H-4.1 Monthly'!O85 -> -40144.85 | P92: =SUM(D92:O92) -> -629753.75
A94: 10 | B94: LIGHTING | C94: SEC | P94: =SUM(D94:O94) -> 0
A96: 11 | B96: TOTAL RETAIL | D96: =D94+D92+D90+D86+D82+D80 -> -818046.56 | E96: =E94+E92+E90+E86+E82+E80 -> -689256.43 | F96: =F94+F92+F90+F86+F82+F80 -> -624435.38 | G96: =G94+G92+G90+G86+G82+G80 -> -634422.67 | H96: =H94+H92+H90+H86+H82+H80 -> -674607.01 | I96: =I94+I92+I90+I86+I82+I80 -> -843615.59 | J96: =J94+J92+J90+J86+J82+J80 -> -855709.89 | K96: =K94+K92+K90+K86+K82+K80 -> -850729.46 | ... P96: =P94+P92+P90+P86+P82+P80 -> -8900401.8
A98: 12 | B98: WHOLESALE PRI | C98: PRI | P98: =SUM(D98:O98) -> 0
A99: 13 | B99: WHOLESALE TRANS | C99: TRA | P99: =SUM(D99:O99) -> 0
A100: 14 | B100: TOTAL WHOLESALE | D100: =SUM(D98:D99) -> 0 | E100: =SUM(E98:E99) -> 0 | F100: =SUM(F98:F99) -> 0 | G100: =SUM(G98:G99) -> 0 | H100: =SUM(H98:H99) -> 0 | I100: =SUM(I98:I99) -> 0 | J100: =SUM(J98:J99) -> 0 | K100: =SUM(K98:K99) -> 0 | ... P100: =SUM(P98:P99) -> 0
A102: 15 | B102: =B37 -> TOTAL AEP TEXAS | D102: =+D100+D96 -> -818046.56 | E102: =+E100+E96 -> -689256.43 | F102: =+F100+F96 -> -624435.38 | G102: =+G100+G96 -> -634422.67 | H102: =+H100+H96 -> -674607.01 | I102: =+I100+I96 -> -843615.59 | J102: =+J100+J96 -> -855709.89 | K102: =+K100+K96 -> -850729.46 | ... P102: =+P100+P96 -> -8900401.8
B106: AEP TEXAS
B107: ENERGY EFFICIENCY RIDER ADJUSTMENT
B108: =B10 -> FOR TEST YEAR ENDED DECEMBER 31, 2018
A111: LINE | B111: DESCRIPTION | C111: VOLT | D111: =+D13 -> JANUARY | E111: =+E13 -> FEBRUARY | F111: =+F13 -> MARCH | G111: =+G13 -> APRIL | H111: =+H13 -> MAY | I111: =+I13 -> JUNE | J111: =+J13 -> JULY | K111: =+K13 -> AUGUST | ... O111: =+O13 -> DECEMBER | P111: TOTAL
A113: 1 | B113: RESIDENTIAL SERVICE | C113: SEC | D113: =-Riders!D42 -> -615110.37 | E113: =-Riders!E42 -> -455754.72 | F113: =-Riders!F42 -> -403259.11 | G113: =-Riders!G42 -> -424731.2 | H113: =-Riders!H42 -> -471365.34 | I113: =-Riders!I42 -> -719576.43 | J113: =-Riders!J42 -> -753708.91 | K113: =-Riders!K42 -> -764935.83 | ... O113: =-Riders!O42 -> -493167.19 | P113: =SUM(D113:O113) -> -6852076.5
A115: 2 | B115: SECONDARY < 10 kW | C115: SEC | D115: =-Riders!D44 -> -10740.73 | E115: =-Riders!E44 -> -8872.92 | F115: =-Riders!F44 -> -10183.26 | G115: =-Riders!G44 -> -10631.45 | H115: =-Riders!H44 -> -10833.27 | I115: =-Riders!I44 -> -13442.36 | J115: =-Riders!J44 -> -14099.93 | K115: =-Riders!K44 -> -13643.38 | ... O115: =-Riders!O44 -> -11493.16 | P115: =SUM(D115:O115) -> -139559
A117: 3 | B117: SECONDARY > 10 kW NCP | C117: SEC | D117: =-Riders!D46 -> -269533.23 | E117: =-Riders!E46 -> -242650.5 | F117: =-Riders!F46 -> -244400.57 | G117: =-Riders!G46 -> -263495.12 | H117: =-Riders!H46 -> -274573.65 | I117: =-Riders!I46 -> -341628.61 | J117: =-Riders!J46 -> -347318.11 | K117: =-Riders!K46 -> -349497.41 | ... O117: =-Riders!O46 -> -256164.2 | P117: =SUM(D117:O117) -> -3502203.9
A118: 4 | B118: SECONDARY > 10 kW 4CP | C118: SEC | D118: =-Riders!D47 -> -45719.52 | E118: =-Riders!E47 -> -38711.65 | F118: =-Riders!F47 -> -42109.04 | G118: =-Riders!G47 -> -43243.32 | H118: =-Riders!H47 -> -44646.87 | I118: =-Riders!I47 -> -45932.36 | J118: =-Riders!J47 -> -53849.67 | K118: =-Riders!K47 -> -49578.08 | ... O118: =-Riders!O47 -> -43621.62 | P118: =SUM(D118:O118) -> -556575.63
A119: 5 | B119: TOTAL SECONDARY > 10 kW | D119: =SUM(D117:D118) -> -315252.75 | E119: =SUM(E117:E118) -> -281362.15 | F119: =SUM(F117:F118) -> -286509.61 | G119: =SUM(G117:G118) -> -306738.44 | H119: =SUM(H117:H118) -> -319220.52 | I119: =SUM(I117:I118) -> -387560.97 | J119: =SUM(J117:J118) -> -401167.78 | K119: =SUM(K117:K118) -> -399075.49 | ... P119: =SUM(P117:P118) -> -4058779.6
A121: 6 | B121: PRIMARY NCP | C121: PRI | D121: =-Riders!D50 -> -3524.47 | E121: =-Riders!E50 -> -3216.11 | F121: =-Riders!F50 -> -4258.68 | G121: =-Riders!G50 -> -5299.05 | H121: =-Riders!H50 -> -5538.64 | I121: =-Riders!I50 -> -6557.61 | J121: =-Riders!J50 -> -6730.63 | K121: =-Riders!K50 -> -6324.14 | ... O121: =-Riders!O50 -> -5450.52 | P121: =SUM(D121:O121) -> -66719.89
A122: 7 | B122: PRIMARY 4CP | C122: PRI | D122: =-Riders!D51 -> -53662.31 | E122: =-Riders!E51 -> -46294.82 | F122: =-Riders!F51 -> -70203.04 | G122: =-Riders!G51 -> -71204.56 | H122: =-Riders!H51 -> -82858.16 | I122: =-Riders!I51 -> -91683.02 | J122: =-Riders!J51 -> -89917.63 | K122: =-Riders!K51 -> -54625.11 | ... O122: =-Riders!O51 -> -65433.41 | P122: =SUM(D122:O122) -> -863766.99
A123: 8 | B123: TOTAL PRIMARY | D123: =SUM(D121:D122) -> -57186.78 | E123: =SUM(E121:E122) -> -49510.93 | F123: =SUM(F121:F122) -> -74461.72 | G123: =SUM(G121:G122) -> -76503.61 | H123: =SUM(H121:H122) -> -88396.8 | I123: =SUM(I121:I122) -> -98240.63 | J123: =SUM(J121:J122) -> -96648.26 | K123: =SUM(K121:K122) -> -60949.25 | ... P123: =SUM(P121:P122) -> -930486.88
A125: 9 | B125: TRANSMISSION | C125: TRA | D125: =-Riders!D54 -> 58976.04 | E125: =-Riders!E54 -> 48444.79 | F125: =-Riders!F54 -> 55347 | G125: =-Riders!G54 -> 54380.93 | H125: =-Riders!H54 -> 54270.61 | I125: =-Riders!I54 -> 57448.5 | J125: =-Riders!J54 -> 50213.3 | K125: =-Riders!K54 -> 50464.59 | ... O125: =-Riders!O54 -> 38548.19 | P125: =SUM(D125:O125) -> 630945.09
A127: 10 | B127: LIGHTING | C127: SEC | D127: =-'[10]TCC Riders Sales Elec'!BQ71 -> 0 | E127: =-'[10]TCC Riders Sales Elec'!BR71 -> 0 | F127: =-'[10]TCC Riders Sales Elec'!BS71 -> 0 | G127: =-'[10]TCC Riders Sales Elec'!BT71 -> 0 | H127: =-'[10]TCC Riders Sales Elec'!BU71 -> 0 | I127: =-'[10]TCC Riders Sales Elec'!BV71 -> 0 | J127: =-'[10]TCC Riders Sales Elec'!BW71 -> 0 | K127: =-'[10]TCC Riders Sales Elec'!BX71 -> 0 | ... O127: =-'[10]TCC Riders Sales Elec'!CB71 -> 0 | P127: =SUM(D127:O127) -> 0
A129: 11 | B129: TOTAL RETAIL | D129: =D127+D125+D123+D119+D115+D113 -> -939314.59 | E129: =E127+E125+E123+E119+E115+E113 -> -747055.93 | F129: =F127+F125+F123+F119+F115+F113 -> -719066.7 | G129: =G127+G125+G123+G119+G115+G113 -> -764223.77 | H129: =H127+H125+H123+H119+H115+H113 -> -835545.32 | I129: =I127+I125+I123+I119+I115+I113 -> -1161371.9 | J129: =J127+J125+J123+J119+J115+J113 -> -1215411.6 | K129: =K127+K125+K123+K119+K115+K113 -> -1188139.4 | ... P129: =P127+P125+P123+P119+P115+P113 -> -11349957
A131: 12 | B131: WHOLESALE PRI | C131: PRI | P131: =SUM(D131:O131) -> 0
A132: 13 | B132: WHOLESALE TRANS | C132: TRA | P132: =SUM(D132:O132) -> 0
A133: 14 | B133: TOTAL WHOLESALE | D133: =SUM(D131:D132) -> 0 | E133: =SUM(E131:E132) -> 0 | F133: =SUM(F131:F132) -> 0 | G133: =SUM(G131:G132) -> 0 | H133: =SUM(H131:H132) -> 0 | I133: =SUM(I131:I132) -> 0 | J133: =SUM(J131:J132) -> 0 | K133: =SUM(K131:K132) -> 0 | ... P133: =SUM(P131:P132) -> 0
A135: 15 | B135: =B37 -> TOTAL AEP TEXAS | D135: =+D133+D129 -> -939314.59 | E135: =+E133+E129 -> -747055.93 | F135: =+F133+F129 -> -719066.7 | G135: =+G133+G129 -> -764223.77 | H135: =+H133+H129 -> -835545.32 | I135: =+I133+I129 -> -1161371.9 | J135: =+J133+J129 -> -1215411.6 | K135: =+K133+K129 -> -1188139.4 | ... P135: =+P133+P129 -> -11349957
B139: AEP TEXAS
B140: TRANSITION CHARGE RIDERS ADJUSTMENT
B141: =B10 -> FOR TEST YEAR ENDED DECEMBER 31, 2018
A144: LINE | B144: DESCRIPTION | C144: VOLT | D144: =+D13 -> JANUARY | E144: =+E13 -> FEBRUARY | F144: =+F13 -> MARCH | G144: =+G13 -> APRIL | H144: =+H13 -> MAY | I144: =+I13 -> JUNE | J144: =+J13 -> JULY | K144: =+K13 -> AUGUST | ... O144: =+O13 -> DECEMBER | P144: TOTAL
A146: 1 | B146: RESIDENTIAL SERVICE | C146: SEC | D146: =-Riders!D126-Riders!D154 -> -11122866 | E146: =-Riders!E126-Riders!E154 -> -8197190.2 | F146: =-Riders!F126-Riders!F154 -> -6534694.4 | G146: =-Riders!G126-Riders!G154 -> -7105776.6 | H146: =-Riders!H126-Riders!H154 -> -7859452.3 | I146: =-Riders!I126-Riders!I154 -> -11815081 | J146: =-Riders!J126-Riders!J154 -> -12181763 | K146: =-Riders!K126-Riders!K154 -> -12533570 | ... O146: =-Riders!O126-Riders!O154 -> -7924184.4 | P146: =SUM(D146:O146) -> -1.1474721e+08
A148: 2 | B148: SECONDARY < 10 kW | C148: SEC | D148: =-Riders!D128-Riders!D156 -> -962513.88 | E148: =-Riders!E128-Riders!E156 -> -795835.85 | F148: =-Riders!F128-Riders!F156 -> -761509.34 | G148: =-Riders!G128-Riders!G156 -> -811531.06 | H148: =-Riders!H128-Riders!H156 -> -827514.94 | I148: =-Riders!I128-Riders!I156 -> -1011519.4 | J148: =-Riders!J128-Riders!J156 -> -1022074 | K148: =-Riders!K128-Riders!K156 -> -1033681.7 | ... O148: =-Riders!O128-Riders!O156 -> -828227.04 | P148: =SUM(D148:O148) -> -10869601
A150: 3 | B150: SECONDARY > 10 kW NCP | C150: SEC | D150: =-Riders!D130-Riders!D158 -> -7880552.4 | E150: =-Riders!E130-Riders!E158 -> -7545430.5 | F150: =-Riders!F130-Riders!F158 -> -7348310.5 | G150: =-Riders!G130-Riders!G158 -> -7613477.8 | H150: =-Riders!H130-Riders!H158 -> -7793236.8 | I150: =-Riders!I130-Riders!I158 -> -8822518.3 | J150: =-Riders!J130-Riders!J158 -> -8731430 | K150: =-Riders!K130-Riders!K158 -> -8896055.6 | ... O150: =-Riders!O130-Riders!O158 -> -7679673.5 | P150: =SUM(D150:O150) -> -97782094
A151: 4 | B151: SECONDARY > 10 kW 4CP | C151: SEC | D151: =-Riders!D131-Riders!D159 -> -630653.08 | E151: =-Riders!E131-Riders!E159 -> -619473.78 | F151: =-Riders!F131-Riders!F159 -> -628366.64 | G151: =-Riders!G131-Riders!G159 -> -651808.12 | H151: =-Riders!H131-Riders!H159 -> -664203 | I151: =-Riders!I131-Riders!I159 -> -701307.44 | J151: =-Riders!J131-Riders!J159 -> -653977.21 | K151: =-Riders!K131-Riders!K159 -> -732324.01 | ... O151: =-Riders!O131-Riders!O159 -> -630625.3 | P151: =SUM(D151:O151) -> -8300549.9
A152: 5 | B152: TOTAL SECONDARY > 10 kW | D152: =SUM(D150:D151) -> -8511205.4 | E152: =SUM(E150:E151) -> -8164904.3 | F152: =SUM(F150:F151) -> -7976677.1 | G152: =SUM(G150:G151) -> -8265285.9 | H152: =SUM(H150:H151) -> -8457439.8 | I152: =SUM(I150:I151) -> -9523825.8 | J152: =SUM(J150:J151) -> -9385407.2 | K152: =SUM(K150:K151) -> -9628379.6 | ... P152: =SUM(P150:P151) -> -1.0608264e+08
A154: 6 | B154: PRIMARY NCP | C154: PRI | D154: =-Riders!D134-Riders!D162 -> -134174.59 | E154: =-Riders!E134-Riders!E162 -> -133825.84 | F154: =-Riders!F134-Riders!F162 -> -130888.46 | G154: =-Riders!G134-Riders!G162 -> -138697.88 | H154: =-Riders!H134-Riders!H162 -> -141871.3 | I154: =-Riders!I134-Riders!I162 -> -147936.62 | J154: =-Riders!J134-Riders!J162 -> -142373.75 | K154: =-Riders!K134-Riders!K162 -> -149174.41 | ... O154: =-Riders!O134-Riders!O162 -> -144921.43 | P154: =SUM(D154:O154) -> -1755313.7
A155: 7 | B155: PRIMARY 4CP | C155: PRI | D155: =-Riders!D135-Riders!D163 -> -1687283.2 | E155: =-Riders!E135-Riders!E163 -> -1580834.7 | F155: =-Riders!F135-Riders!F163 -> -1594763.4 | G155: =-Riders!G135-Riders!G163 -> -1587149.5 | H155: =-Riders!H135-Riders!H163 -> -1724826.4 | I155: =-Riders!I135-Riders!I163 -> -1847021 | J155: =-Riders!J135-Riders!J163 -> -1764290.5 | K155: =-Riders!K135-Riders!K163 -> -1754728.6 | ... O155: =-Riders!O135-Riders!O163 -> -1610908.2 | P155: =SUM(D155:O155) -> -20410670
A156: 8 | B156: TOTAL PRIMARY | D156: =SUM(D154:D155) -> -1821457.8 | E156: =SUM(E154:E155) -> -1714660.5 | F156: =SUM(F154:F155) -> -1725651.8 | G156: =SUM(G154:G155) -> -1725847.4 | H156: =SUM(H154:H155) -> -1866697.7 | I156: =SUM(I154:I155) -> -1994957.6 | J156: =SUM(J154:J155) -> -1906664.2 | K156: =SUM(K154:K155) -> -1903903 | ... P156: =SUM(P154:P155) -> -22165983
A158: 9 | B158: TRANSMISSION | C158: TRA | D158: =-Riders!D138-Riders!D166 -> -1978401 | E158: =-Riders!E138-Riders!E166 -> -1512340.9 | F158: =-Riders!F138-Riders!F166 -> -1745720.7 | G158: =-Riders!G138-Riders!G166 -> -1639069.8 | H158: =-Riders!H138-Riders!H166 -> -1682111.7 | I158: =-Riders!I138-Riders!I166 -> -1756427.6 | J158: =-Riders!J138-Riders!J166 -> -1473022.4 | K158: =-Riders!K138-Riders!K166 -> -1547220.6 | ... O158: =-Riders!O138-Riders!O166 -> -1004780.1 | P158: =SUM(D158:O158) -> -18934635
A160: 10 | B160: LIGHTING | C160: SEC | D160: =-Riders!D140-Riders!D168 -> -365576.01 | E160: =-Riders!E140-Riders!E168 -> -364009.29 | F160: =-Riders!F140-Riders!F168 -> -365334.72 | G160: =-Riders!G140-Riders!G168 -> -365846.76 | H160: =-Riders!H140-Riders!H168 -> -365065.58 | I160: =-Riders!I140-Riders!I168 -> -365097.45 | J160: =-Riders!J140-Riders!J168 -> -365396.94 | K160: =-Riders!K140-Riders!K168 -> -365236.07 | ... O160: =-Riders!O140-Riders!O168 -> -370698.32 | P160: =SUM(D160:O160) -> -4404631.3
A162: 11 | B162: TOTAL RETAIL | D162: =D160+D158+D156+D152+D148+D146 -> -24762020 | E162: =E160+E158+E156+E152+E148+E146 -> -20748941 | F162: =F160+F158+F156+F152+F148+F146 -> -19109588 | G162: =G160+G158+G156+G152+G148+G146 -> -19913358 | H162: =H160+H158+H156+H152+H148+H146 -> -21058282 | I162: =I160+I158+I156+I152+I148+I146 -> -26466909 | J162: =J160+J158+J156+J152+J148+J146 -> -26334328 | K162: =K160+K158+K156+K152+K148+K146 -> -27011990 | ... P162: =P160+P158+P156+P152+P148+P146 -> -2.772047e+08
A164: 12 | B164: WHOLESALE PRI | C164: PRI | P164: =SUM(D164:O164) -> 0
A165: 13 | B165: WHOLESALE TRANS | C165: TRA | P165: =SUM(D165:O165) -> 0
A166: 14 | B166: TOTAL WHOLESALE | D166: =SUM(D164:D165) -> 0 | E166: =SUM(E164:E165) -> 0 | F166: =SUM(F164:F165) -> 0 | G166: =SUM(G164:G165) -> 0 | H166: =SUM(H164:H165) -> 0 | I166: =SUM(I164:I165) -> 0 | J166: =SUM(J164:J165) -> 0 | K166: =SUM(K164:K165) -> 0 | ... P166: =SUM(P164:P165) -> 0
A168: 15 | B168: =B37 -> TOTAL AEP TEXAS | D168: =+D166+D162 -> -24762020 | E168: =+E166+E162 -> -20748941 | F168: =+F166+F162 -> -19109588 | G168: =+G166+G162 -> -19913358 | H168: =+H166+H162 -> -21058282 | I168: =+I166+I162 -> -26466909 | J168: =+J166+J162 -> -26334328 | K168: =+K166+K162 -> -27011990 | ... P168: =+P166+P162 -> -2.772047e+08
...

Sheet II-H-4.1 Functions
B2: PUBLIC UTILITY COMMISSION OF TEXAS
B3: AEP TEXAS INC
B4: II-H-4.1 REVENUE IMPACTS FUNCTIONS
B5: TEST YEAR ENDING 12/31/2018
B6: DOCKET NUMBER (PENDING ASSIGNMENT)
A8: AEP TEXAS
A9: UNADJUSTED BILLED REVENUE
A10: FOR TEST YEAR ENDED DECEMBER 31, 2018
A13: LINE | B13: DESCRIPTION | C13: VOLT | D13: Customer Revenue - Base Tariff | E13: Meter Revenue - Base Tariff | F13: Distribution Service Revenue - Base Tariff | G13: Facilities Charge | H13: Transmission Service Revenue - Base Tariff | I13: Total Base Tariff Revenue | K13: Energy Efficiency Rider | L13: Transition Charge Riders (TC) | M13: DCRF | N13: Competitive Metering Rider | O13: Transmission Cost Recovery Rider (TCRF) | P13: State Colleges and Universities Discount Rider | Q13: Advanced Metering Recovery Rider | R13: Misc Riders | S13: Total Riders | U13: Total Revenue
W14: EECRF in base rates
A15: 1 | B15: RESIDENTIAL SERVICE | C15: SEC | D15: ='[6]TCC Sales Elec Base Rate Custom'!$T$71+'[5]II-H-4.1 Functions'!$D$8 -> 32912479 | E15: ='[6]TCC Sales Elec Base Rate Meter '!$T$40+'[5]II-H-4.1 Functions'!$E$8 -> 40180077 | F15: =SUM('[6]TCC Sales Elec Base Rate Dist T'!$H$166:$S$166)+'[5]II-H-4.1 Functions'!$F$8 -> 1.781707e+08 | H15: =SUM('[6]TCC Sales Elec Base Rate Dist T'!$T$166:$AE$166)+'[5]II-H-4.1 Functions'!$H$8 -> 63989339 | I15: =H15+F15+E15+D15+G15 -> 3.152526e+08 | K15: =-'II-H-4.1 Monthly'!P113 -> 6852076.5 | L15: =-'II-H-4.1 Monthly'!P146 -> 1.1474721e+08 | M15: =-'II-H-4.1 Monthly'!P336 -> 38120918 | N15: =-'II-H-4.1 Monthly'!P179 -> 0 | O15: =-'II-H-4.1 Monthly'!P305 -> 95799428 | P15: =-'II-H-4.1 Monthly'!P212 -> -8840.33 | Q15: =-'II-H-4.1 Monthly'!P243 -> 23799602 | R15: =-'II-H-4.1 Monthly'!P274 -> -524890.6 | S15: =SUM(K15:R15) -> 2.787855e+08 | U15: =S15+I15 -> 5.940381e+08 | W15: =-F49/F15 -> 0.024483062
A17: 2 | B17: SECONDARY < 10 kW | C17: SEC | D17: ='[6]TCC Sales Elec Base Rate Custom'!$T$11+'[5]II-H-4.1 Functions'!$D$10 -> 3738616.9 | E17: ='[6]TCC Sales Elec Base Rate Meter '!$T$8+'[5]II-H-4.1 Functions'!$E$10 -> 5038057.2 | F17: =SUM('[6]TCC Sales Elec Base Rate Dist T'!$H$19:$S$19)+'[5]II-H-4.1 Functions'!$F$10 -> 11328181 | H17: =SUM('[6]TCC Sales Elec Base Rate Dist T'!$T$19:$AE$19)+'[5]II-H-4.1 Functions'!$H$10 -> 1548795.4 | I17: =H17+F17+E17+D17+G17 -> 21653651 | K17: =-'II-H-4.1 Monthly'!P115 -> 139559 | L17: =-'II-H-4.1 Monthly'!P148 -> 10869601 | M17: =-'II-H-4.1 Monthly'!P338 -> 5077510 | N17: =-'II-H-4.1 Monthly'!P181 -> 0 | O17: =-'II-H-4.1 Monthly'!P307 -> 2695807 | P17: =-'II-H-4.1 Monthly'!P214 -> -7355.89 | Q17: =-'II-H-4.1 Monthly'!P245 -> 4429023.3 | R17: =-'II-H-4.1 Monthly'!P276 -> -36322.54 | S17: =SUM(K17:R17) -> 23167822 | U17: =S17+I17 -> 44821473 | W17: =-F51/F17 -> 0.014187966
I18: =H18+F18+E18+D18+G18 -> 0
A19: 3 | B19: SECONDARY > 10 kW NCP | C19: SEC | D19: ='[6]TCC Sales Elec Base Rate Custom'!$T$29+'[5]II-H-4.1 Functions'!$D$12 -> 2974475.1 | E19: ='[6]TCC Sales Elec Base Rate Meter '!$T$26+'[5]II-H-4.1 Functions'!$E$12 -> 14108041 | F19: =SUM('[6]TCC Sales Elec Base Rate Dist T'!$H$55:$S$55)+'[5]II-H-4.1 Functions'!$F$12 -> 1.0895568e+08 | G19: 0 | H19: =SUM('[6]TCC Sales Elec Base Rate Dist T'!$T$55:$AE$55)+'[5]II-H-4.1 Functions'!$H$12 -> 36701168 | I19: =H19+F19+E19+D19+G19 -> 1.6273936e+08 | K19: =-'II-H-4.1 Monthly'!P117 -> 3502203.9 | L19: =-'II-H-4.1 Monthly'!P150 -> 97782094 | M19: =-'II-H-4.1 Monthly'!P340 -> 21514316 | N19: =-'II-H-4.1 Monthly'!P183 -> 0 | O19: =-'II-H-4.1 Monthly'!P309 -> 59877725 | P19: =-'II-H-4.1 Monthly'!P216 -> -162767.7 | Q19: =-'II-H-4.1 Monthly'!P247 -> 1671203.2 | R19: =-'II-H-4.1 Monthly'!P278 -> -272150.19 | S19: =SUM(K19:R19) -> 1.8391262e+08 | U19: =S19+I19 -> 3.4665199e+08 | W19: =-F53/F19 -> 0.023489827
A20: 4 | B20: SECONDARY > 10 kW 4CP | C20: SEC | D20: ='[6]TCC Sales Elec Base Rate Custom'!$T$20+'[5]II-H-4.1 Functions'!$D$13 -> 157765.39 | E20: ='[6]TCC Sales Elec Base Rate Meter '!$T$17+'[5]II-H-4.1 Functions'!$E$13 -> 131323.72 | F20: =SUM('[6]TCC Sales Elec Base Rate Dist T'!$H$37:$S$37)+'[5]II-H-4.1 Functions'!$F$13 -> 11243079 | H20: =SUM('[6]TCC Sales Elec Base Rate Dist T'!$T$37:$AE$37)+'[5]II-H-4.1 Functions'!$H$13 -> 4133847.1 | I20: =H20+F20+E20+D20+G20 -> 15666015 | K20: =-'II-H-4.1 Monthly'!P118 -> 556575.63 | L20: =-'II-H-4.1 Monthly'!P151 -> 8300549.9 | M20: =-'II-H-4.1 Monthly'!P341 -> 2276327.2 | N20: =-'II-H-4.1 Monthly'!P184 -> 0 | O20: =-'II-H-4.1 Monthly'!P310 -> 5232800 | P20: =-'II-H-4.1 Monthly'!P217 -> -46593.72 | Q20: ='II-H-4.1 Monthly'!P248 -> 0 | R20: =-'II-H-4.1 Monthly'!P279 -> -25654.91 | S20: =SUM(K20:R20) -> 16294004 | U20: =S20+I20 -> 31960019 | W20: =-F54/F20 -> 0.022712337
A21: 5 | B21: TOTAL SECONDARY > 10 kW | D21: =SUM(D19:D20) -> 3132240.5 | E21: =SUM(E19:E20) -> 14239365 | F21: =SUM(F19:F20) -> 1.2019876e+08 | H21: =SUM(H19:H20) -> 40835015 | I21: =SUM(I19:I20) -> 1.7840538e+08 | K21: =SUM(K19:K20) -> 4058779.6 | L21: =SUM(L19:L20) -> 1.0608264e+08 | M21: =SUM(M19:M20) -> 23790643 | N21: =SUM(N19:N20) -> 0 | O21: =SUM(O19:O20) -> 65110525 | P21: =SUM(P19:P20) -> -209361.42 | Q21: =SUM(Q19:Q20) -> 1671203.2 | R21: =SUM(R19:R20) -> -297805.1 | S21: =SUM(S19:S20) -> 2.0020663e+08 | U21: =S21+I21 -> 3.7861201e+08
A23: 6 | B23: PRIMARY NCP | C23: PRI | D23: ='[6]TCC Sales Elec Base Rate Custom'!$T$68+'[5]II-H-4.1 Functions'!$D$16 -> 27922.93 | E23: ='[6]TCC Sales Elec Base Rate Meter '!$T$37+'[5]II-H-4.1 Functions'!$E$16 -> 1043237.1 | F23: =SUM('[6]TCC Sales Elec Base Rate Dist T'!$H$160:$S$160)+'[5]II-H-4.1 Functions'!$F$16 -> 2316816.5 | H23: =SUM('[6]TCC Sales Elec Base Rate Dist T'!$T$160:$AE$160)+'[5]II-H-4.1 Functions'!$H$16 -> 1127710.6 | I23: =H23+F23+E23+D23+G23 -> 4515687.1 | K23: =-'II-H-4.1 Monthly'!P121 -> 66719.89 | L23: =-'II-H-4.1 Monthly'!P154 -> 1755313.7 | M23: =-'II-H-4.1 Monthly'!P344 -> 385027.52 | N23: =-'II-H-4.1 Monthly'!P187 -> 0 | O23: =-'II-H-4.1 Monthly'!P313 -> 2051920.4 | P23: =-'II-H-4.1 Monthly'!P220 -> -24669.7 | Q23: =-'II-H-4.1 Monthly'!P251 -> -16292.98 | R23: =-'II-H-4.1 Monthly'!P282 -> -8620.99 | S23: =SUM(K23:R23) -> 4209397.9 | U23: =S23+I23 -> 8725085 | W23: =-F57/F23 -> 0.036262894
A24: 7 | B24: PRIMARY 4CP | C24: PRI | D24: ='[6]TCC Sales Elec Base Rate Custom'!$T$63+'[5]II-H-4.1 Functions'!$D$17 -> 157030.23 | E24: ='[6]TCC Sales Elec Base Rate Meter '!$T$32+'[5]II-H-4.1 Functions'!$E$17 -> 895389.55 | F24: =SUM('[6]TCC Sales Elec Base Rate Dist T'!$H$150:$S$150)+'[5]II-H-4.1 Functions'!$F$17 -> 24332428 | H24: =SUM('[6]TCC Sales Elec Base Rate Dist T'!$T$150:$AE$150)+'[5]II-H-4.1 Functions'!$H$17 -> 12989907 | I24: =H24+F24+E24+D24+G24 -> 38374755 | K24: =-'II-H-4.1 Monthly'!P122 -> 863766.99 | L24: =-'II-H-4.1 Monthly'!P155 -> 20410670 | M24: =-'II-H-4.1 Monthly'!P345 -> 4054830.2 | N24: =-'II-H-4.1 Monthly'!P188 -> 0 | O24: =-'II-H-4.1 Monthly'!P314 -> 19826061 | P24: =-'II-H-4.1 Monthly'!P221 -> -307466.17 | Q24: ='II-H-4.1 Monthly'!P252 -> 0 | R24: =-'II-H-4.1 Monthly'!P283 -> -68625.56 | S24: =SUM(K24:R24) -> 44779236 | U24: =S24+I24 -> 83153991 | W24: =-F58/F24 -> 0.034893294
A25: 8 | B25: TOTAL PRIMARY | D25: =SUM(D23:D24) -> 184953.16 | E25: =SUM(E23:E24) -> 1938626.7 | F25: =SUM(F23:F24) -> 26649245 | H25: =SUM(H23:H24) -> 14117617 | I25: =SUM(I23:I24) -> 42890442 | K25: =SUM(K23:K24) -> 930486.88 | L25: =SUM(L23:L24) -> 22165983 | M25: =SUM(M23:M24) -> 4439857.7 | N25: =SUM(N23:N24) -> 0 | O25: =SUM(O23:O24) -> 21877982 | P25: =SUM(P23:P24) -> -332135.87 | Q25: =SUM(Q23:Q24) -> -16292.98 | R25: =SUM(R23:R24) -> -77246.55 | S25: =SUM(S23:S24) -> 48988634 | U25: =S25+I25 -> 91879076
A27: 9 | B27: TRANSMISSION | C27: TRA | D27: ='[6]TCC Sales Elec Base Rate Custom'!$T$83+'[5]II-H-4.1 Functions'!$D$20 -> 33594.56 | E27: ='[6]TCC Sales Elec Base Rate Meter '!$T$52+'[5]II-H-4.1 Functions'!$E$20 -> 1494853.9 | F27: =SUM('[6]TCC Sales Elec Base Rate Dist T'!$H$190:$S$190)+'[5]II-H-4.1 Functions'!$F$20 -> 3044920.3 | H27: =SUM('[6]TCC Sales Elec Base Rate Dist T'!$T$190:$AE$190)+'[5]II-H-4.1 Functions'!$H$20 -> 10529707 | I27: =H27+F27+E27+D27+G27 -> 15103076 | K27: =-'II-H-4.1 Monthly'!P125 -> -630945.09 | L27: =-'II-H-4.1 Monthly'!P158 -> 18934635 | M27: =-'II-H-4.1 Monthly'!P348 -> 163233.46 | N27: =-'II-H-4.1 Monthly'!P191 -> 2774.48 | O27: =-'II-H-4.1 Monthly'!P317 -> 15604823 | P27: =-'II-H-4.1 Monthly'!P224 -> 0 | Q27: ='II-H-4.1 Monthly'!P255 -> 0 | R27: =-'II-H-4.1 Monthly'!P286 -> -22995.21 | S27: =SUM(K27:R27) -> 34051525 | U27: =S27+I27 -> 49154601 | W27: =-F61/F27 -> 0.2068211
A29: 10 | B29: LIGHTING | C29: SEC | D29: ='[6]TCC Sales Elec Base Rate Custom'!$T$57+'[5]II-H-4.1 Functions'!$D$22 -> 95482.32 | E29: 0 | F29: =SUM('[6]TCC Sales Elec Base Rate Dist T'!$H$138:$S$138)+'[5]II-H-4.1 Functions'!$F$22 -> 17636919 | G29: 0 | H29: =SUM('[6]TCC Sales Elec Base Rate Dist T'!$T$138:$AE$138)+'[5]II-H-4.1 Functions'!$H$22 -> 684721.79 | I29: =H29+F29+E29+D29+G29 -> 18417123 | K29: =-'II-H-4.1 Monthly'!P127 -> 0 | L29: =-'II-H-4.1 Monthly'!P160 -> 4404631.3 | M29: =-'II-H-4.1 Monthly'!P350 -> 2217913.2 | N29: =--'II-H-4.1 Monthly'!P193 -> 0 | O29: =-'II-H-4.1 Monthly'!P319 -> 1173609.1 | P29: =-'II-H-4.1 Monthly'!P226 -> -6445.58 | Q29: ='II-H-4.1 Monthly'!P257 -> 0 | R29: =-'II-H-4.1 Monthly'!P288 -> -30689.23 | S29: =SUM(K29:R29) -> 7759018.8 | U29: =S29+I29 -> 26176142
A31: 11 | B31: TOTAL RETAIL | D31: =D29+D27+D25+D21+D17+D15 -> 40097366 | E31: =E29+E27+E25+E21+E17+E15 -> 62890979 | F31: =F29+F27+F25+F21+F17+F15 -> 3.5702873e+08 | G31: =G29+G27+G25+G21+G17+G15 -> 0 | H31: =H29+H27+H25+H21+H17+H15 -> 1.317052e+08 | I31: =I29+I27+I25+I21+I17+I15 -> 5.9172227e+08 | K31: =K29+K27+K25+K21+K17+K15 -> 11349957 | L31: =L29+L27+L25+L21+L17+L15 -> 2.772047e+08 | M31: =M29+M27+M25+M21+M17+M15 -> 73810076 | N31: =N29+N27+N25+N21+N17+N15 -> 2774.48 | O31: =O29+O27+O25+O21+O17+O15 -> 2.0226217e+08 | P31: =P29+P27+P25+P21+P17+P15 -> -564139.09 | Q31: =Q29+Q27+Q25+Q21+Q17+Q15 -> 29883535 | R31: =R29+R27+R25+R21+R17+R15 -> -989949.23 | S31: =S29+S27+S25+S21+S17+S15 -> 5.9295913e+08 | U31: =S31+I31 -> 1.1846814e+09
A33: 12 | B33: WHOLESALE PRI | C33: PRI | I33: =SUM(D33:H33) -> 0 | S33: =SUM(K33:Q33) -> 0 | U33: =S33+I33 -> 0
A34: 13 | B34: WHOLESALE TRANS | C34: TRA | U34: =S34+I34 -> 0
A35: 14 | B35: TOTAL WHOLESALE | D35: =SUM(D33:D34) -> 0 | E35: =SUM(E33:E34) -> 0 | F35: =SUM(F33:F34) -> 0 | G35: =SUM(G33:G34) -> 0 | H35: =SUM(H33:H34) -> 0 | I35: =SUM(I33:I34) -> 0 | K35: =SUM(K33:K34) -> 0 | L35: =SUM(L33:L34) -> 0 | M35: 0 | N35: =SUM(N33:N34) -> 0 | O35: =SUM(O33:O34) -> 0 | P35: =SUM(P33:P34) -> 0 | Q35: =SUM(Q33:Q34) -> 0 | R35: =SUM(R33:R34) -> 0 | S35: =SUM(S33:S34) -> 0 | U35: =S35+I35 -> 0
A37: 15 | B37: TOTAL AEP TEXAS | D37: =+D35+D31 -> 40097366 | E37: =+E35+E31 -> 62890979 | F37: =+F35+F31 -> 3.5702873e+08 | G37: =+G35+G31 -> 0 | H37: =+H35+H31 -> 1.317052e+08 | I37: =+I35+I31 -> 5.9172227e+08 | K37: =+K35+K31 -> 11349957 | L37: =+L35+L31 -> 2.772047e+08 | M37: =+M35+M31 -> 73810076 | N37: =+N35+N31 -> 2774.48 | O37: =+O35+O31 -> 2.0226217e+08 | P37: =+P35+P31 -> -564139.09 | Q37: =+Q35+Q31 -> 29883535 | R37: =+R35+R31 -> -989949.23 | S37: =+S35+S31 -> 5.9295913e+08 | U37: =S37+I37 -> 1.1846814e+09
A42: =+A8 -> AEP TEXAS
A43: BASE TARIFF AND RIDER REVENUE ADJUSTMENTS
A44: =+A10 -> FOR TEST YEAR ENDED DECEMBER 31, 2018
A47: LINE | B47: DESCRIPTION | C47: VOLT | D47: =$D$13 -> Customer Revenue - Base Tariff | E47: =$E$13 -> Meter Revenue - Base Tariff | F47: Distribution Service Revenue - Base Tariff (Energy Efficiency) | G47: =$G$13 -> Facilities Charge | H47: =$H$13 -> Transmission Service Revenue - Base Tariff | I47: =$I$13 -> Total Base Tariff Revenue | K47: =$K$13 -> Energy Efficiency Rider | L47: =$L$13 -> Transition Charge Riders (TC) | M47: DCRF | N47: =$N$13 -> Competitive Metering Rider | O47: =$O$13 -> Transmission Cost Recovery Rider (TCRF) | P47: =$P$13 -> State Colleges and Universities Discount Rider | Q47: =$Q$13 -> Advanced Metering Recovery Rider | R47: =+R13 -> Misc Riders | S47: =$S$13 -> Total Riders | U47: =$U$13 -> Total Revenue
A49: 1 | B49: RESIDENTIAL SERVICE | C49: SEC | F49: ='II-H-4.1 Monthly'!P80 -> -4362164.4 | H49: =-H15 -> -63989339 | I49: =H49+F49+E49+D49 -> -68351503 | K49: =-K15 -> -6852076.5 | L49: =-L15 -> -1.1474721e+08 | M49: =-M15 -> -38120918 | N49: =-N15 -> 0 | O49: =-O15 -> -95799428 | P49: =-P15 -> 8840.33 | Q49: =-Q15 -> -23799602 | R49: =-R15 -> 524890.6 | S49: =SUM(K49:R49) -> -2.787855e+08 | U49: =S49+I49 -> -3.47137e+08
A51: 2 | B51: SECONDARY < 10 kW | C51: SEC | F51: ='II-H-4.1 Monthly'!P82 -> -160723.85 | H51: =-H17 -> -1548795.4 | I51: =H51+F51+E51+D51 -> -1709519.3 | K51: =-K17 -> -139559 | L51: =-L17 -> -10869601 | M51: =-M17 -> -5077510 | N51: =-N17 -> 0 | O51: =-O17 -> -2695807 | P51: =-P17 -> 7355.89 | Q51: =-Q17 -> -4429023.3 | R51: =-R17 -> 36322.54 | S51: =SUM(K51:R51) -> -23167822 | U51: =S51+I51 -> -24877341
A53: 3 | B53: SECONDARY > 10 kW NCP | C53: SEC | F53: ='II-H-4.1 Monthly'!P84 -> -2559350.1 | H53: =-H19 -> -36701168 | I53: =H53+F53+E53+D53 -> -39260518 | K53: =-K19 -> -3502203.9 | L53: =-L19 -> -97782094 | M53: =-M19 -> -21514316 | N53: =-N19 -> 0 | O53: =-O19 -> -59877725 | P53: =-P19 -> 162767.7 | Q53: =-Q19 -> -1671203.2 | R53: =-R19 -> 272150.19 | S53: =SUM(K53:R53) -> -1.8391262e+08 | U53: =S53+I53 -> -2.2317314e+08
A54: 4 | B54: SECONDARY > 10 kW 4CP | C54: SEC | F54: ='II-H-4.1 Monthly'!P85 -> -255356.6 | H54: =-H20 -> -4133847.1 | I54: =H54+F54+E54+D54 -> -4389203.7 | K54: =-K20 -> -556575.63 | L54: =-L20 -> -8300549.9 | M54: =-M20 -> -2276327.2 | N54: =-N20 -> 0 | O54: =-O20 -> -5232800 | P54: =-P20 -> 46593.72 | Q54: =-Q20 -> 0 | R54: =-R20 -> 25654.91 | S54: =SUM(K54:R54) -> -16294004 | U54: =S54+I54 -> -20683208
A55: 5 | B55: TOTAL SECONDARY > 10 kW | D55: =SUM(D53:D54) -> 0 | E55: =SUM(E53:E54) -> 0 | F55: =SUM(F53:F54) -> -2814706.7 | G55: =SUM(G53:G54) -> 0 | H55: =SUM(H53:H54) -> -40835015 | I55: =SUM(I53:I54) -> -43649722 | K55: =-K21 -> -4058779.6 | L55: =-L21 -> -1.0608264e+08 | M55: =-M21 -> -23790643 | N55: =-N21 -> 0 | O55: =SUM(O53:O54) -> -65110525 | P55: =-P21 -> 209361.42 | Q55: =-Q21 -> -1671203.2 | R55: =-R21 -> 297805.1 | S55: =SUM(K55:Q55) -> -2.0050443e+08 | U55: =S55+I55 -> -2.4415415e+08
A57: 6 | B57: PRIMARY NCP | C57: PRI | F57: ='II-H-4.1 Monthly'!P88 -> -84014.47 | H57: =-H23 -> -1127710.6 | I57: =H57+F57+E57+D57 -> -1211725.1 | K57: =-K23 -> -66719.89 | L57: =-L23 -> -1755313.7 | M57: =-M23 -> -385027.52 | N57: =-N23 -> 0 | O57: =-O23 -> -2051920.4 | P57: =-P23 -> 24669.7 | Q57: =-Q23 -> 16292.98 | R57: =-R23 -> 8620.99 | S57: =SUM(K57:R57) -> -4209397.9 | U57: =S57+I57 -> -5421122.9
A58: 7 | B58: PRIMARY 4CP | C58: PRI | F58: ='II-H-4.1 Monthly'!P89 -> -849038.57 | H58: =-H24 -> -12989907 | I58: =H58+F58+E58+D58 -> -13838945 | K58: =-K24 -> -863766.99 | L58: =-L24 -> -20410670 | M58: =-M24 -> -4054830.2 | N58: =-N24 -> 0 | O58: =-O24 -> -19826061 | P58: =-P24 -> 307466.17 | Q58: =-Q24 -> 0 | R58: =-R24 -> 68625.56 | S58: =SUM(K58:R58) -> -44779236 | U58: =S58+I58 -> -58618182
A59: 8 | B59: TOTAL PRIMARY | D59: =SUM(D57:D58) -> 0 | E59: =SUM(E57:E58) -> 0 | F59: =SUM(F57:F58) -> -933053.04 | G59: =SUM(G57:G58) -> 0 | H59: =SUM(H57:H58) -> -14117617 | I59: =SUM(I57:I58) -> -15050670 | K59: =-K25 -> -930486.88 | L59: =-L25 -> -22165983 | M59: =-M25 -> -4439857.7 | N59: =-N25 -> 0 | O59: =SUM(O57:O58) -> -21877982 | P59: =-P25 -> 332135.87 | Q59: =-Q25 -> 16292.98 | R59: =-R25 -> 77246.55 | S59: =SUM(K59:Q59) -> -49065881 | U59: =S59+I59 -> -64116551
A61: 9 | B61: TRANSMISSION | C61: TRA | F61: ='II-H-4.1 Monthly'!P92 -> -629753.75 | H61: =-H27 -> -10529707 | I61: =SUM(D61:H61) -> -11159461 | K61: =-K27 -> 630945.09 | L61: =-L27 -> -18934635 | M61: =-M27 -> -163233.46 | N61: =-N27 -> -2774.48 | O61: =-O27 -> -15604823 | P61: =-P27 -> 0 | Q61: =-Q27 -> 0 | R61: =-R27 -> 22995.21 | S61: =SUM(K61:R61) -> -34051525 | U61: =S61+I61 -> -45210986
A63: 10 | B63: LIGHTING | C63: SEC | H63: =-H29 -> -684721.79 | I63: =SUM(D63:H63) -> -684721.79 | K63: =-K29 -> 0 | L63: =-L29 -> -4404631.3 | M63: =-M29 -> -2217913.2 | N63: =-N29 -> 0 | O63: =-O29 -> -1173609.1 | P63: =-P29 -> 6445.58 | Q63: =-Q29 -> 0 | R63: =-R29 -> 30689.23 | S63: =SUM(K63:R63) -> -7759018.8 | U63: =S63+I63 -> -8443740.6
A65: 11 | B65: TOTAL RETAIL | D65: =D63+D61+D59+D55+D51+D49 -> 0 | E65: =E63+E61+E59+E55+E51+E49 -> 0 | F65: =F63+F61+F59+F55+F51+F49 -> -8900401.8 | G65: =G63+G61+G59+G55+G51+G49 -> 0 | H65: =H63+H61+H59+H55+H51+H49 -> -1.317052e+08 | I65: =I63+I61+I59+I55+I51+I49 -> -1.406056e+08 | K65: =+K49+K51+K55+K59+K61+K63 -> -11349957 | L65: =-L31 -> -2.772047e+08 | M65: =-M31 -> -73810076 | N65: =-N31 -> -2774.48 | O65: =-O31 -> -2.0226217e+08 | P65: =-P31 -> 564139.09 | Q65: =-Q31 -> -29883535 | R65: =-R31 -> 989949.23 | S65: =SUM(K65:R65) -> -5.9295913e+08 | U65: =S65+I65 -> -7.3356473e+08
A67: 12 | B67: WHOLESALE PRI | C67: PRI | H67: =-H33 -> 0 | I67: =SUM(D67:H67) -> 0 | K67: =-K33 -> 0 | L67: =-L33 -> 0 | M67: =+M33 -> 0 | N67: =-N33 -> 0 | O67: =-O33 -> 0 | P67: =-P33 -> 0 | Q67: =-Q33 -> 0 | R67: =-R33 -> 0 | S67: =SUM(K67:R67) -> 0 | U67: =S67+I67 -> 0
A68: 13 | B68: WHOLESALE TRANS | C68: TRA | K68: =-K34 -> 0 | L68: =-L34 -> 0 | N68: =-N34 -> 0 | O68: =-O34 -> 0 | P68: =-P34 -> 0 | Q68: =-Q34 -> 0 | R68: =-R34 -> 0 | U68: =S68+I68 -> 0
A69: 14 | B69: TOTAL WHOLESALE | D69: =SUM(D67:D68) -> 0 | E69: =SUM(E67:E68) -> 0 | F69: =SUM(F67:F68) -> 0 | G69: =SUM(G67:G68) -> 0 | H69: =SUM(H67:H68) -> 0 | I69: =SUM(I67:I68) -> 0 | K69: =-K35 -> 0 | L69: =-L35 -> 0 | M69: =-M35 -> 0 | N69: =-N35 -> 0 | O69: =-O35 -> 0 | P69: =-P35 -> 0 | Q69: =-Q35 -> 0 | R69: =-R35 -> 0 | S69: =SUM(K69:Q69) -> 0 | U69: =S69+I69 -> 0
A71: 15 | B71: TOTAL AEP TEXAS | D71: =+D69+D65 -> 0 | E71: =+E69+E65 -> 0 | F71: =+F69+F65 -> -8900401.8 | G71: =+G69+G65 -> 0 | H71: =+H69+H65 -> -1.317052e+08 | I71: =+I69+I65 -> -1.406056e+08 | K71: =-K37 -> -11349957 | L71: =-L37 -> -2.772047e+08 | M71: =-M37 -> -73810076 | N71: =-N37 -> -2774.48 | O71: =-O37 -> -2.0226217e+08 | P71: =-P37 -> 564139.09 | Q71: =-Q37 -> -29883535 | R71: =-R37 -> 989949.23 | S71: =SUM(K71:R71) -> -5.9295913e+08 | U71: =S71+I71 -> -7.3356473e+08
A75: =+A8 -> AEP TEXAS
A76: CUSTOMER ADJUSTMENT
A77: =A10 -> FOR TEST YEAR ENDED DECEMBER 31, 2018
A80: LINE | B80: DESCRIPTION | C80: VOLT | D80: =$D$13 -> Customer Revenue - Base Tariff | E80: =$E$13 -> Meter Revenue - Base Tariff | F80: =$F$13 -> Distribution Service Revenue - Base Tariff | G80: =$G$13 -> Facilities Charge | H80: =$H$13 -> Transmission Service Revenue - Base Tariff | I80: =$I$13 -> Total Base Tariff Revenue | K80: =$K$13 -> Energy Efficiency Rider | L80: =$L$13 -> Transition Charge Riders (TC) | M80: DCRF | N80: =$N$13 -> Competitive Metering Rider | O80: =$O$13 -> Transmission Cost Recovery Rider (TCRF) | P80: =$P$13 -> State Colleges and Universities Discount Rider | Q80: =$Q$13 -> Advanced Metering Recovery Rider | R80: =+R13 -> Misc Riders | S80: =$S$13 -> Total Riders | U80: =$U$13 -> Total Revenue
A82: 1 | B82: RESIDENTIAL SERVICE | C82: SEC | D82: ='[4]II-H-4.1 Functions'!D75+'[5]II-H-4.1 Functions'!D75 -> 182821.44 | E82: ='[4]II-H-4.1 Functions'!E75+'[5]II-H-4.1 Functions'!E75 -> 223926.68 | F82: ='[4]II-H-4.1 Functions'!F75+'[5]II-H-4.1 Functions'!F75 -> 909599.01 | I82: =SUM(D82:H82) -> 1316347.1 | S82: =SUM(K82:Q82) -> 0 | U82: =S82+I82 -> 1316347.1
A84: 2 | B84: SECONDARY < 10 kW | C84: SEC | D84: ='[4]II-H-4.1 Functions'!D77+'[5]II-H-4.1 Functions'!D77 -> -3684.4 | E84: ='[4]II-H-4.1 Functions'!E77+'[5]II-H-4.1 Functions'!E77 -> -3380.16 | F84: ='[4]II-H-4.1 Functions'!F77+'[5]II-H-4.1 Functions'!F77 -> -12224.553 | I84: =SUM(D84:H84) -> -19289.113 | S84: =SUM(K84:Q84) -> 0 | U84: =S84+I84 -> -19289.113
A86: 3 | B86: SECONDARY > 10 kW NCP | C86: SEC | D86: ='[4]II-H-4.1 Functions'!D79+'[5]II-H-4.1 Functions'!D79 -> 27148.2 | E86: ='[4]II-H-4.1 Functions'!E79+'[5]II-H-4.1 Functions'!E79 -> 128056.83 | F86: ='[4]II-H-4.1 Functions'!F79+'[5]II-H-4.1 Functions'!F79 -> 975635.05 | I86: =SUM(D86:H86) -> 1130840.1 | S86: =SUM(K86:Q86) -> 0 | U86: =S86+I86 -> 1130840.1
A87: 4 | B87: SECONDARY > 10 kW 4CP | C87: SEC | D87: ='[4]II-H-4.1 Functions'!D80+'[5]II-H-4.1 Functions'!D80 -> -4758.52 | E87: ='[4]II-H-4.1 Functions'!E80+'[5]II-H-4.1 Functions'!E80 -> -3402.31 | F87: ='[4]II-H-4.1 Functions'!F80+'[5]II-H-4.1 Functions'!F80 -> -319297.82 | I87: =SUM(D87:H87) -> -327458.65 | S87: =SUM(K87:Q87) -> 0 | U87: =S87+I87 -> -327458.65
A88: 5 | B88: TOTAL SECONDARY > 10 kW | D88: =SUM(D86:D87) -> 22389.68 | E88: =SUM(E86:E87) -> 124654.52 | F88: =SUM(F86:F87) -> 656337.23 | G88: =SUM(G86:G87) -> 0 | H88: =SUM(H86:H87) -> 0 | I88: =SUM(D88:H88) -> 803381.43 | K88: =SUM(K86:K87) -> 0 | L88: =SUM(L86:L87) -> 0 | N88: =SUM(N86:N87) -> 0 | O88: =SUM(O86:O87) -> 0 | P88: =SUM(P86:P87) -> 0 | S88: =SUM(K88:Q88) -> 0 | U88: =S88+I88 -> 803381.43
A90: 6 | B90: PRIMARY NCP | C90: PRI | D90: ='[4]II-H-4.1 Functions'!D83+'[5]II-H-4.1 Functions'!D83 -> 168.15 | E90: ='[4]II-H-4.1 Functions'!E83+'[5]II-H-4.1 Functions'!E83 -> 6439.51 | F90: ='[4]II-H-4.1 Functions'!F83+'[5]II-H-4.1 Functions'!F83 -> 15343.321 | I90: =SUM(D90:H90) -> 21950.981 | S90: =SUM(K90:Q90) -> 0 | U90: =S90+I90 -> 21950.981
A91: 7 | B91: PRIMARY 4CP | C91: PRI | D91: ='[4]II-H-4.1 Functions'!D84+'[5]II-H-4.1 Functions'!D84 -> -253.28 | E91: ='[4]II-H-4.1 Functions'!E84+'[5]II-H-4.1 Functions'!E84 -> -1405.61 | F91: ='[4]II-H-4.1 Functions'!F84+'[5]II-H-4.1 Functions'!F84 -> -37539.872 | I91: =SUM(D91:H91) -> -39198.762 | S91: =SUM(K91:Q91) -> 0 | U91: =S91+I91 -> -39198.762
A92: 8 | B92: TOTAL PRIMARY | D92: =SUM(D90:D91) -> -85.13 | E92: =SUM(E90:E91) -> 5033.9 | F92: =SUM(F90:F91) -> -22196.551 | G92: =SUM(G90:G91) -> 0 | H92: =SUM(H90:H91) -> 0 | I92: =SUM(D92:H92) -> -17247.781 | K92: =SUM(K90:K91) -> 0 | L92: =SUM(L90:L91) -> 0 | N92: =SUM(N90:N91) -> 0 | O92: =SUM(O90:O91) -> 0 | P92: =SUM(P90:P91) -> 0 | S92: =SUM(K92:Q92) -> 0 | U92: =S92+I92 -> -17247.781
A94: 9 | B94: TRANSMISSION | C94: TRA | D94: ='[4]II-H-4.1 Functions'!D87+'[5]II-H-4.1 Functions'!D87 -> 1660.28 | E94: ='[4]II-H-4.1 Functions'!E87+'[5]II-H-4.1 Functions'!E87 -> 76808.55 | F94: ='[4]II-H-4.1 Functions'!F87+'[5]II-H-4.1 Functions'!F87 -> 124634.14 | I94: =SUM(D94:H94) -> 203102.97 | S94: =SUM(K94:Q94) -> 0 | U94: =S94+I94 -> 203102.97
A96: 10 | B96: LIGHTING | C96: SEC | D96: ='[4]II-H-4.1 Functions'!D89+'[5]II-H-4.1 Functions'!D89 -> 0 | E96: ='[4]II-H-4.1 Functions'!E89+'[5]II-H-4.1 Functions'!E89 -> 0 | F96: ='[4]II-H-4.1 Functions'!F89+'[5]II-H-4.1 Functions'!F89 -> -8290.8616 | G96: =($G$29/'II-H-3.1-3'!$P$28)*'II-H-3.1-3'!P60 -> 0 | I96: =SUM(D96:H96) -> -8290.8616 | S96: =SUM(K96:Q96) -> 0 | U96: =S96+I96 -> -8290.8616
A98: 11 | B98: TOTAL RETAIL | D98: =D96+D94+D92+D88+D84+D82 -> 203101.87 | E98: =E96+E94+E92+E88+E84+E82 -> 427043.49 | F98: =F96+F94+F92+F88+F84+F82 -> 1647858.4 | G98: =G96+G94+G92+G88+G84+G82 -> 0 | H98: =H96+H94+H92+H88+H84+H82 -> 0 | I98: =SUM(D98:H98) -> 2278003.8 | K98: =K96+K94+K92+K88+K84+K82 -> 0 | L98: =L96+L94+L92+L88+L84+L82 -> 0 | N98: =N96+N94+N92+N88+N84+N82 -> 0 | O98: =O96+O94+O92+O88+O84+O82 -> 0 | P98: =P96+P94+P92+P88+P84+P82 -> 0 | S98: =SUM(K98:Q98) -> 0 | U98: =S98+I98 -> 2278003.8
A100: 12 | B100: WHOLESALE PRI | C100: PRI | I100: =SUM(D100:H100) -> 0 | S100: =SUM(K100:Q100) -> 0 | U100: =S100+I100 -> 0
A101: 13 | B101: WHOLESALE TRANS | C101: TRA | I101: =SUM(D101:H101) -> 0 | S101: =SUM(K101:Q101) -> 0 | U101: =S101+I101 -> 0
A102: 14 | B102: TOTAL WHOLESALE | D102: =SUM(D100:D101) -> 0 | E102: =SUM(E100:E101) -> 0 | F102: =SUM(F100:F101) -> 0 | G102: =SUM(G100:G101) -> 0 | H102: =SUM(H100:H101) -> 0 | I102: =SUM(D102:H102) -> 0 | K102: =SUM(K100:K101) -> 0 | L102: =SUM(L100:L101) -> 0 | N102: =SUM(N100:N101) -> 0 | O102: =SUM(O100:O101) -> 0 | P102: =SUM(P100:P101) -> 0 | S102: =SUM(K102:Q102) -> 0 | U102: =S102+I102 -> 0
A104: 15 | B104: TOTAL AEP TEXAS | D104: =+D102+D98 -> 203101.87 | E104: =+E102+E98 -> 427043.49 | F104: =+F102+F98 -> 1647858.4 | G104: =+G102+G98 -> 0 | H104: =+H102+H98 -> 0 | I104: =SUM(D104:H104) -> 2278003.8 | K104: =+K102+K98 -> 0 | L104: =+L102+L98 -> 0 | N104: =+N102+N98 -> 0 | O104: =+O102+O98 -> 0 | P104: =+P102+P98 -> 0 | Q104: =+Q102+Q98 -> 0 | S104: =SUM(K104:Q104) -> 0 | U104: =S104+I104 -> 2278003.8
A107: =+A8 -> AEP TEXAS
A108: WEATHER ADJUSTMENT
A109: =A10 -> FOR TEST YEAR ENDED DECEMBER 31, 2018
A112: LINE | B112: DESCRIPTION | C112: VOLT | D112: =$D$13 -> Customer Revenue - Base Tariff | E112: =$E$13 -> Meter Revenue - Base Tariff | F112: =$F$13 -> Distribution Service Revenue - Base Tariff | G112: =$G$13 -> Facilities Charge | H112: =$H$13 -> Transmission Service Revenue - Base Tariff | I112: =$I$13 -> Total Base Tariff Revenue | K112: =$K$13 -> Energy Efficiency Rider | L112: =$L$13 -> Transition Charge Riders (TC) | M112: DCRF | N112: =$N$13 -> Competitive Metering Rider | O112: =$O$13 -> Transmission Cost Recovery Rider (TCRF) | P112: =$P$13 -> State Colleges and Universities Discount Rider | Q112: =$Q$13 -> Advanced Metering Recovery Rider | R112: =+R13 -> Misc Riders | S112: =$S$13 -> Total Riders | U112: =$U$13 -> Total Revenue
A114: 1 | B114: RESIDENTIAL SERVICE | C114: SEC | F114: ='II-H-4.1 Monthly'!P398 -> -2564300.6 | I114: =SUM(D114:H114) -> -2564300.6 | S114: =SUM(K114:Q114) -> 0 | U114: =S114+I114 -> -2564300.6
A116: 2 | B116: SECONDARY < 10 kW | C116: SEC | F116: ='II-H-4.1 Monthly'!P400 -> -15878.932 | I116: =SUM(D116:H116) -> -15878.932 | S116: =SUM(K116:Q116) -> 0 | U116: =S116+I116 -> -15878.932
A118: 3 | B118: SECONDARY > 10 kW NCP | C118: SEC | F118: ='II-H-4.1 Monthly'!P402 -> -5939.6032 | I118: =SUM(D118:H118) -> -5939.6032 | S118: =SUM(K118:Q118) -> 0 | U118: =S118+I118 -> -5939.6032
A119: 4 | B119: SECONDARY > 10 kW 4CP | C119: SEC | F119: ='II-H-4.1 Monthly'!P403 -> -11546.866 | I119: =SUM(D119:H119) -> -11546.866 | S119: =SUM(K119:Q119) -> 0 | U119: =S119+I119 -> -11546.866
A120: 5 | B120: TOTAL SECONDARY > 10 kW | D120: =SUM(D118:D119) -> 0 | E120: =SUM(E118:E119) -> 0 | F120: =SUM(F118:F119) -> -17486.469 | G120: =SUM(G118:G119) -> 0 | H120: =SUM(H118:H119) -> 0 | I120: =SUM(I118:I119) -> -17486.469 | K120: =SUM(K118:K119) -> 0 | L120: =SUM(L118:L119) -> 0 | N120: =SUM(N118:N119) -> 0 | O120: =SUM(O118:O119) -> 0 | P120: =SUM(P118:P119) -> 0 | Q120: =SUM(Q118:Q119) -> 0 | S120: =SUM(K120:Q120) -> 0 | U120: =S120+I120 -> -17486.469
A122: 6 | B122: PRIMARY NCP | C122: PRI | I122: =SUM(D122:H122) -> 0 | S122: =SUM(K122:Q122) -> 0 | U122: =S122+I122 -> 0
A123: 7 | B123: PRIMARY 4CP | C123: PRI | I123: =SUM(D123:H123) -> 0 | S123: =SUM(K123:Q123) -> 0 | U123: =S123+I123 -> 0
A124: 8 | B124: TOTAL PRIMARY | D124: =SUM(D122:D123) -> 0 | E124: =SUM(E122:E123) -> 0 | F124: =SUM(F122:F123) -> 0 | G124: =SUM(G122:G123) -> 0 | H124: =SUM(H122:H123) -> 0 | I124: =SUM(I122:I123) -> 0 | K124: =SUM(K122:K123) -> 0 | L124: =SUM(L122:L123) -> 0 | N124: =SUM(N122:N123) -> 0 | O124: =SUM(O122:O123) -> 0 | P124: =SUM(P122:P123) -> 0 | Q124: =SUM(Q122:Q123) -> 0 | S124: =SUM(K124:Q124) -> 0 | U124: =S124+I124 -> 0
A126: 9 | B126: TRANSMISSION | C126: TRA | I126: =SUM(D126:H126) -> 0 | S126: =SUM(K126:Q126) -> 0 | U126: =S126+I126 -> 0
A128: 10 | B128: LIGHTING | C128: SEC | I128: =SUM(D128:H128) -> 0 | S128: =SUM(K128:Q128) -> 0 | U128: =S128+I128 -> 0
A130: 11 | B130: TOTAL RETAIL | D130: =D128+D126+D124+D120+D116+D114 -> 0 | E130: =E128+E126+E124+E120+E116+E114 -> 0 | F130: =F128+F126+F124+F120+F116+F114 -> -2597666 | G130: =G128+G126+G124+G120+G116+G114 -> 0 | H130: =H128+H126+H124+H120+H116+H114 -> 0 | I130: =I128+I126+I124+I120+I116+I114 -> -2597666 | K130: =K128+K126+K124+K120+K116+K114 -> 0 | L130: =L128+L126+L124+L120+L116+L114 -> 0 | N130: =N128+N126+N124+N120+N116+N114 -> 0 | O130: =O128+O126+O124+O120+O116+O114 -> 0 | P130: =P128+P126+P124+P120+P116+P114 -> 0 | Q130: =Q128+Q126+Q124+Q120+Q116+Q114 -> 0 | S130: =SUM(K130:Q130) -> 0 | U130: =S130+I130 -> -2597666
A132: 12 | B132: WHOLESALE PRI | C132: PRI | I132: =SUM(D132:H132) -> 0 | S132: =SUM(K132:Q132) -> 0 | U132: =S132+I132 -> 0
A133: 13 | B133: WHOLESALE TRANS | C133: TRA | I133: =SUM(D133:H133) -> 0 | S133: =SUM(K133:Q133) -> 0 | U133: =S133+I133 -> 0
A134: 14 | B134: TOTAL WHOLESALE | D134: =SUM(D132:D133) -> 0 | E134: =SUM(E132:E133) -> 0 | F134: =SUM(F132:F133) -> 0 | G134: =SUM(G132:G133) -> 0 | H134: =SUM(H132:H133) -> 0 | I134: =SUM(I132:I133) -> 0 | K134: =SUM(K132:K133) -> 0 | L134: =SUM(L132:L133) -> 0 | N134: =SUM(N132:N133) -> 0 | O134: =SUM(O132:O133) -> 0 | P134: =SUM(P132:P133) -> 0 | Q134: =SUM(Q132:Q133) -> 0 | S134: =SUM(K134:Q134) -> 0 | U134: =S134+I134 -> 0
A136: 15 | B136: TOTAL AEP TEXAS | D136: =+D134+D130 -> 0 | E136: =+E134+E130 -> 0 | F136: =+F134+F130 -> -2597666 | G136: =+G134+G130 -> 0 | H136: =+H134+H130 -> 0 | I136: =+I134+I130 -> -2597666 | K136: =+K134+K130 -> 0 | L136: =+L134+L130 -> 0 | N136: =+N134+N130 -> 0 | O136: =+O134+O130 -> 0 | P136: =+P134+P130 -> 0 | Q136: =+Q134+Q130 -> 0 | S136: =SUM(K136:Q136) -> 0 | U136: =S136+I136 -> -2597666
A140: =+A8 -> AEP TEXAS
A141: OTHER REVENUE ADJUSTMENTS
A142: =A10 -> FOR TEST YEAR ENDED DECEMBER 31, 2018
A145: LINE | B145: DESCRIPTION | C145: VOLT | D145: =$D$13 -> Customer Revenue - Base Tariff | E145: =$E$13 -> Meter Revenue - Base Tariff | F145: =$F$13 -> Distribution Service Revenue - Base Tariff | G145: =$G$13 -> Facilities Charge | H145: =$H$13 -> Transmission Service Revenue - Base Tariff | I145: =$I$13 -> Total Base Tariff Revenue | K145: =$K$13 -> Energy Efficiency Rider | L145: =$L$13 -> Transition Charge Riders (TC) | M145: DCRF | N145: =$N$13 -> Competitive Metering Rider | O145: =$O$13 -> Transmission Cost Recovery Rider (TCRF) | P145: =$P$13 -> State Colleges and Universities Discount Rider | Q145: =$Q$13 -> Advanced Metering Recovery Rider | R145: =+R13 -> Misc Riders | S145: =$S$13 -> Total Riders | U145: =$U$13 -> Total Revenue
A147: 1 | B147: RESIDENTIAL SERVICE | C147: SEC | I147: =SUM(D147:H147) -> 0 | S147: =SUM(K147:Q147) -> 0 | U147: =S147+I147 -> 0
A149: 2 | B149: SECONDARY < 10 kW | C149: SEC | I149: =SUM(D149:H149) -> 0 | S149: =SUM(K149:Q149) -> 0 | U149: =S149+I149 -> 0
A151: 3 | B151: SECONDARY > 10 kW NCP | C151: SEC | G151: ='II-H-4.1 Monthly'!P433 -> 0 | I151: =SUM(D151:H151) -> 0 | S151: =SUM(K151:Q151) -> 0 | U151: =S151+I151 -> 0
A152: 4 | B152: SECONDARY > 10 kW 4CP | C152: SEC | I152: =SUM(D152:H152) -> 0 | S152: =SUM(K152:Q152) -> 0 | U152: =S152+I152 -> 0
A153: 5 | B153: TOTAL SECONDARY > 10 kW | D153: =SUM(D151:D152) -> 0 | E153: =SUM(E151:E152) -> 0 | F153: =SUM(F151:F152) -> 0 | G153: =SUM(G151:G152) -> 0 | H153: =SUM(H151:H152) -> 0 | I153: =SUM(D153:H153) -> 0 | K153: =SUM(K151:K152) -> 0 | L153: =SUM(L151:L152) -> 0 | N153: =SUM(N151:N152) -> 0 | O153: =SUM(O151:O152) -> 0 | P153: =SUM(P151:P152) -> 0 | Q153: =SUM(Q151:Q152) -> 0 | S153: =SUM(K153:Q153) -> 0 | U153: =S153+I153 -> 0
A155: 6 | B155: PRIMARY NCP | C155: PRI | D155: =3.8*'II-H-3.1-3'!P87 -> 0 | E155: =154.62*'II-H-3.1-3'!P87 -> 0 | F155: ='II-H-4.1 Dist kW'!P115*2.945*(1-$W$23) -> 0 | I155: =SUM(D155:H155) -> 0 | Q155: =-7.07*'II-H-3.1-3'!P87 -> 0 | S155: =SUM(K155:Q155) -> 0 | U155: =S155+I155 -> 0
A156: 7 | B156: PRIMARY 4CP | C156: PRI | D156: =28.41*'II-H-3.1-3'!P88 -> 0 | E156: =154.62*'II-H-3.1-3'!P88 -> 0 | F156: ='II-H-4.1 Dist kW'!P116*2.945*(1-$W$24) -> 0 | I156: =SUM(D156:H156) -> 0 | S156: =SUM(K156:Q156) -> 0 | U156: =S156+I156 -> 0
A157: 8 | B157: TOTAL PRIMARY | D157: =SUM(D155:D156) -> 0 | E157: =SUM(E155:E156) -> 0 | F157: =SUM(F155:F156) -> 0 | G157: =SUM(G155:G156) -> 0 | H157: =SUM(H155:H156) -> 0 | I157: =SUM(D157:H157) -> 0 | K157: =SUM(K155:K156) -> 0 | L157: =SUM(L155:L156) -> 0 | N157: =SUM(N155:N156) -> 0 | O157: =SUM(O155:O156) -> 0 | P157: =SUM(P155:P156) -> 0 | Q157: =SUM(Q155:Q156) -> 0 | S157: =SUM(K157:Q157) -> 0 | U157: =S157+I157 -> 0
A159: 9 | B159: TRANSMISSION | C159: TRA | I159: =SUM(D159:H159) -> 0 | S159: =SUM(K159:Q159) -> 0 | U159: =S159+I159 -> 0
A161: 10 | B161: LIGHTING | C161: SEC | I161: =SUM(D161:H161) -> 0 | S161: =SUM(K161:Q161) -> 0 | U161: =S161+I161 -> 0
A163: 11 | B163: TOTAL RETAIL | D163: =D161+D159+D157+D153+D149+D147 -> 0 | E163: =E161+E159+E157+E153+E149+E147 -> 0 | F163: =F161+F159+F157+F153+F149+F147 -> 0 | G163: =G161+G159+G157+G153+G149+G147 -> 0 | H163: =H161+H159+H157+H153+H149+H147 -> 0 | I163: =SUM(D163:H163) -> 0 | K163: =K161+K159+K157+K153+K149+K147 -> 0 | L163: =L161+L159+L157+L153+L149+L147 -> 0 | N163: =N161+N159+N157+N153+N149+N147 -> 0 | O163: =O161+O159+O157+O153+O149+O147 -> 0 | P163: =P161+P159+P157+P153+P149+P147 -> 0 | Q163: =Q161+Q159+Q157+Q153+Q149+Q147 -> 0 | S163: =SUM(K163:Q163) -> 0 | U163: =S163+I163 -> 0
A165: 12 | B165: WHOLESALE PRI | C165: PRI | I165: =SUM(D165:H165) -> 0 | S165: =SUM(K165:Q165) -> 0 | U165: =S165+I165 -> 0
A166: 13 | B166: WHOLESALE TRANS | C166: TRA | I166: =SUM(D166:H166) -> 0 | S166: =SUM(K166:Q166) -> 0 | U166: =S166+I166 -> 0
...

Sheet II-H-4.1 Dist kW
B2: PUBLIC UTILITY COMMISSION OF TEXAS
B3: AEP TEXAS INC
B4: II-H-4.1 DIST KW ADJUSTMENTS
B5: TEST YEAR ENDING 12/31/2018
B6: DOCKET NUMBER (PENDING ASSIGNMENT)
B8: ='II-H-1.2'!B7:O7 -> AEP TEXAS
B9: DISTRIBUTION BILLING KW
B10: ='II-H-1.2'!B9:O9 -> FOR TEST YEAR ENDED DECEMBER 31, 2018
A13: LINE | B13: DESCRIPTION | C13: VOLT | D13: JANUARY | E13: FEBRUARY | F13: MARCH | G13: APRIL | H13: MAY | I13: JUNE | J13: JULY | K13: AUGUST | L13: SEPTEMBER | M13: OCTOBER | N13: NOVEMBER | O13: DECEMBER | P13: TOTAL
A15: 1 | B15: RESIDENTIAL SERVICE | C15: SEC | D15: ='[5]II-H-1.6 Dist'!D8 -> 0 | E15: ='[5]II-H-1.6 Dist'!E8 -> 0 | F15: ='[5]II-H-1.6 Dist'!F8 -> 0 | G15: ='[5]II-H-1.6 Dist'!G8 -> 0 | H15: ='[5]II-H-1.6 Dist'!H8 -> 0 | I15: ='[5]II-H-1.6 Dist'!I8 -> 0 | J15: ='[5]II-H-1.6 Dist'!J8 -> 0 | K15: ='[5]II-H-1.6 Dist'!K8 -> 0 | ... O15: ='[5]II-H-1.6 Dist'!O8 -> 0 | P15: =SUM(D15:O15) -> 0
A17: 2 | B17: SECONDARY < 10 kW | C17: SEC | D17: ='[5]II-H-1.6 Dist'!D10 -> 0 | E17: ='[5]II-H-1.6 Dist'!E10 -> 0 | F17: ='[5]II-H-1.6 Dist'!F10 -> 0 | G17: ='[5]II-H-1.6 Dist'!G10 -> 0 | H17: ='[5]II-H-1.6 Dist'!H10 -> 0 | I17: ='[5]II-H-1.6 Dist'!I10 -> 0 | J17: ='[5]II-H-1.6 Dist'!J10 -> 0 | K17: ='[5]II-H-1.6 Dist'!K10 -> 0 | ... O17: ='[5]II-H-1.6 Dist'!O10 -> 0 | P17: =SUM(D17:O17) -> 0
Q18: dist rate
A19: 3 | B19: SECONDARY > 10 kW NCP | C19: SEC | D19: ='[6]Billed kW-Dist'!F30+'[5]II-H-1.6 Dist'!D12 -> 2829305.9 | E19: ='[6]Billed kW-Dist'!G30+'[5]II-H-1.6 Dist'!E12 -> 2802751.5 | F19: ='[6]Billed kW-Dist'!H30+'[5]II-H-1.6 Dist'!F12 -> 2716427.8 | G19: ='[6]Billed kW-Dist'!I30+'[5]II-H-1.6 Dist'!G12 -> 2710056.6 | H19: ='[6]Billed kW-Dist'!J30+'[5]II-H-1.6 Dist'!H12 -> 2758623.2 | I19: ='[6]Billed kW-Dist'!K30+'[5]II-H-1.6 Dist'!I12 -> 2848000.2 | J19: ='[6]Billed kW-Dist'!L30+'[5]II-H-1.6 Dist'!J12 -> 2843044 | K19: ='[6]Billed kW-Dist'!M30+'[5]II-H-1.6 Dist'!K12 -> 2858847.3 | ... O19: ='[6]Billed kW-Dist'!Q30+'[5]II-H-1.6 Dist'!O12 -> 2749743.1 | P19: =SUM(D19:O19) -> 33474790 | Q19: ='II-H-4.1 Functions'!F19/'II-H-4.1 Dist kW'!P19 -> 3.2548578
A20: 4 | B20: SECONDARY > 10 kW 4CP | C20: SEC | D20: ='[6]Billed kW-Dist'!F21+'[5]II-H-1.6 Dist'!D13 -> 300319.2 | E20: ='[6]Billed kW-Dist'!G21+'[5]II-H-1.6 Dist'!E13 -> 288995.5 | F20: ='[6]Billed kW-Dist'!H21+'[5]II-H-1.6 Dist'!F13 -> 282945.6 | G20: ='[6]Billed kW-Dist'!I21+'[5]II-H-1.6 Dist'!G13 -> 271404.8 | H20: ='[6]Billed kW-Dist'!J21+'[5]II-H-1.6 Dist'!H13 -> 275660.4 | I20: ='[6]Billed kW-Dist'!K21+'[5]II-H-1.6 Dist'!I13 -> 277583.9 | J20: ='[6]Billed kW-Dist'!L21+'[5]II-H-1.6 Dist'!J13 -> 287628.9 | K20: ='[6]Billed kW-Dist'!M21+'[5]II-H-1.6 Dist'!K13 -> 293163.2 | ... O20: ='[6]Billed kW-Dist'!Q21+'[5]II-H-1.6 Dist'!O13 -> 287412 | P20: =SUM(D20:O20) -> 3461317.2 | Q20: ='II-H-4.1 Functions'!F20/'II-H-4.1 Dist kW'!P20 -> 3.2482083
A21: 5 | B21: TOTAL SECONDARY > 10 kW | D21: =SUM(D19:D20) -> 3129625.1 | E21: =SUM(E19:E20) -> 3091747 | F21: =SUM(F19:F20) -> 2999373.4 | G21: =SUM(G19:G20) -> 2981461.4 | H21: =SUM(H19:H20) -> 3034283.6 | I21: =SUM(I19:I20) -> 3125584.1 | J21: =SUM(J19:J20) -> 3130672.9 | K21: =SUM(K19:K20) -> 3152010.5 | ... P21: =SUM(P19:P20) -> 36936107
A23: 6 | B23: PRIMARY NCP | C23: PRI | D23: ='[6]Billed kW-Dist'!F82+'[5]II-H-1.6 Dist'!D16 -> 73330.5 | E23: ='[6]Billed kW-Dist'!G82+'[5]II-H-1.6 Dist'!E16 -> 76239.3 | F23: ='[6]Billed kW-Dist'!H82+'[5]II-H-1.6 Dist'!F16 -> 72461.4 | G23: ='[6]Billed kW-Dist'!I82+'[5]II-H-1.6 Dist'!G16 -> 73920.6 | H23: ='[6]Billed kW-Dist'!J82+'[5]II-H-1.6 Dist'!H16 -> 78775.7 | I23: ='[6]Billed kW-Dist'!K82+'[5]II-H-1.6 Dist'!I16 -> 81317.6 | J23: ='[6]Billed kW-Dist'!L82+'[5]II-H-1.6 Dist'!J16 -> 77028.5 | K23: ='[6]Billed kW-Dist'!M82+'[5]II-H-1.6 Dist'!K16 -> 86742.8 | ... O23: ='[6]Billed kW-Dist'!Q82+'[5]II-H-1.6 Dist'!O16 -> 78343.6 | P23: =SUM(D23:O23) -> 950830.5 | Q23: ='II-H-4.1 Functions'!F23/'II-H-4.1 Dist kW'!P23 -> 2.4366241
A24: 7 | B24: PRIMARY 4CP | C24: PRI | D24: ='[6]Billed kW-Dist'!F77+'[5]II-H-1.6 Dist'!D17 -> 788868.8 | E24: ='[6]Billed kW-Dist'!G77+'[5]II-H-1.6 Dist'!E17 -> 762911.7 | F24: ='[6]Billed kW-Dist'!H77+'[5]II-H-1.6 Dist'!F17 -> 767659 | G24: ='[6]Billed kW-Dist'!I77+'[5]II-H-1.6 Dist'!G17 -> 756983 | H24: ='[6]Billed kW-Dist'!J77+'[5]II-H-1.6 Dist'!H17 -> 813894.6 | I24: ='[6]Billed kW-Dist'!K77+'[5]II-H-1.6 Dist'!I17 -> 827804.9 | J24: ='[6]Billed kW-Dist'!L77+'[5]II-H-1.6 Dist'!J17 -> 808234.6 | K24: ='[6]Billed kW-Dist'!M77+'[5]II-H-1.6 Dist'!K17 -> 805878 | ... O24: ='[6]Billed kW-Dist'!Q77+'[5]II-H-1.6 Dist'!O17 -> 765944.5 | P24: =SUM(D24:O24) -> 9516505.9 | Q24: ='II-H-4.1 Functions'!F24/'II-H-4.1 Dist kW'!P24 -> 2.5568658
A25: 8 | B25: TOTAL PRIMARY | D25: =SUM(D23:D24) -> 862199.3 | E25: =SUM(E23:E24) -> 839151 | F25: =SUM(F23:F24) -> 840120.4 | G25: =SUM(G23:G24) -> 830903.6 | H25: =SUM(H23:H24) -> 892670.3 | I25: =SUM(I23:I24) -> 909122.5 | J25: =SUM(J23:J24) -> 885263.1 | K25: =SUM(K23:K24) -> 892620.8 | ... P25: =SUM(P23:P24) -> 10467336
A27: 9 | B27: TRANSMISSION | C27: TRA | D27: ='[6]Billed kW-Dist'!F97+'[5]II-H-1.6 Dist'!D20 -> 1475068.7 | E27: ='[6]Billed kW-Dist'!G97+'[5]II-H-1.6 Dist'!E20 -> 1215296.7 | F27: ='[6]Billed kW-Dist'!H97+'[5]II-H-1.6 Dist'!F20 -> 1391560.6 | G27: ='[6]Billed kW-Dist'!I97+'[5]II-H-1.6 Dist'!G20 -> 1366589.8 | H27: ='[6]Billed kW-Dist'!J97+'[5]II-H-1.6 Dist'!H20 -> 1380170.5 | I27: ='[6]Billed kW-Dist'!K97+'[5]II-H-1.6 Dist'!I20 -> 1456934.9 | J27: ='[6]Billed kW-Dist'!L97+'[5]II-H-1.6 Dist'!J20 -> 1276583.7 | K27: ='[6]Billed kW-Dist'!M97+'[5]II-H-1.6 Dist'!K20 -> 1275192.5 | ... O27: ='[6]Billed kW-Dist'!Q97+'[5]II-H-1.6 Dist'!O20 -> 1031409.7 | P27: =SUM(D27:O27) -> 16022010 | Q27: ='II-H-4.1 Functions'!F27/'II-H-4.1 Dist kW'!P27 -> 0.19004608
A29: 10 | B29: LIGHTING | C29: SEC | P29: =SUM(D29:O29) -> 0
A31: 11 | B31: TOTAL RETAIL | D31: =D29+D27+D25+D21+D17+D15 -> 5466893.1 | E31: =E29+E27+E25+E21+E17+E15 -> 5146194.7 | F31: =F29+F27+F25+F21+F17+F15 -> 5231054.4 | G31: =G29+G27+G25+G21+G17+G15 -> 5178954.8 | H31: =H29+H27+H25+H21+H17+H15 -> 5307124.4 | I31: =I29+I27+I25+I21+I17+I15 -> 5491641.5 | J31: =J29+J27+J25+J21+J17+J15 -> 5292519.7 | K31: =K29+K27+K25+K21+K17+K15 -> 5319823.8 | ... P31: =P29+P27+P25+P21+P17+P15 -> 63425454
A33: 12 | B33: WHOLESALE PRI | C33: PRI | P33: =SUM(D33:O33) -> 0
A34: 13 | B34: WHOLESALE TRANS | C34: TRA | P34: =SUM(D34:O34) -> 0
A35: 14 | B35: TOTAL WHOLESALE | D35: =SUM(D33:D34) -> 0 | E35: =SUM(E33:E34) -> 0 | F35: =SUM(F33:F34) -> 0 | G35: =SUM(G33:G34) -> 0 | H35: =SUM(H33:H34) -> 0 | I35: =SUM(I33:I34) -> 0 | J35: =SUM(J33:J34) -> 0 | K35: =SUM(K33:K34) -> 0 | ... P35: =SUM(P33:P34) -> 0
A37: 15 | B37: TOTAL AEP TEXAS | D37: =+D35+D31 -> 5466893.1 | E37: =+E35+E31 -> 5146194.7 | F37: =+F35+F31 -> 5231054.4 | G37: =+G35+G31 -> 5178954.8 | H37: =+H35+H31 -> 5307124.4 | I37: =+I35+I31 -> 5491641.5 | J37: =+J35+J31 -> 5292519.7 | K37: =+K35+K31 -> 5319823.8 | ... P37: =+P35+P31 -> 63425454
B39: =+B8 -> AEP TEXAS
B40: KW WEATHER ADJUSTMENT
B41: =+B10 -> FOR TEST YEAR ENDED DECEMBER 31, 2018
A44: LINE | B44: DESCRIPTION | C44: VOLT | D44: =+D13 -> JANUARY | E44: =+E13 -> FEBRUARY | F44: =+F13 -> MARCH | G44: =+G13 -> APRIL | H44: =+H13 -> MAY | I44: =+I13 -> JUNE | J44: =+J13 -> JULY | K44: =+K13 -> AUGUST | ... P44: =+P13 -> TOTAL
A46: 1 | B46: RESIDENTIAL SERVICE | C46: SEC | P46: =SUM(D46:O46) -> 0
A48: 2 | B48: SECONDARY < 10 kW | C48: SEC | P48: =SUM(D48:O48) -> 0
A50: 3 | B50: SECONDARY > 10 kW NCP | C50: SEC | D50: =+'[4]II-H-1.6 Dist'!D43+'[5]II-H-1.6 Dist'!D44 -> -35269.073 | E50: =+'[4]II-H-1.6 Dist'!E43+'[5]II-H-1.6 Dist'!E44 -> -12575.644 | F50: =+'[4]II-H-1.6 Dist'!F43+'[5]II-H-1.6 Dist'!F44 -> -44327.812 | G50: =+'[4]II-H-1.6 Dist'!G43+'[5]II-H-1.6 Dist'!G44 -> -18713.589 | H50: =+'[4]II-H-1.6 Dist'!H43+'[5]II-H-1.6 Dist'!H44 -> 53020.511 | I50: =+'[4]II-H-1.6 Dist'!I43+'[5]II-H-1.6 Dist'!I44 -> -82531.627 | J50: =+'[4]II-H-1.6 Dist'!J43+'[5]II-H-1.6 Dist'!J44 -> 6725.243 | K50: =+'[4]II-H-1.6 Dist'!K43+'[5]II-H-1.6 Dist'!K44 -> 22917.071 | ... O50: =+'[4]II-H-1.6 Dist'!O43+'[5]II-H-1.6 Dist'!O44 -> 35761.082 | P50: =SUM(D50:O50) -> -2586.6224
A51: 4 | B51: SECONDARY > 10 kW 4CP | C51: SEC | D51: =+'[4]II-H-1.6 Dist'!D44+'[5]II-H-1.6 Dist'!D45 -> -3616.1765 | E51: =+'[4]II-H-1.6 Dist'!E44+'[5]II-H-1.6 Dist'!E45 -> -1503.1346 | F51: =+'[4]II-H-1.6 Dist'!F44+'[5]II-H-1.6 Dist'!F45 -> -3467.1486 | G51: =+'[4]II-H-1.6 Dist'!G44+'[5]II-H-1.6 Dist'!G45 -> -1212.0609 | H51: =+'[4]II-H-1.6 Dist'!H44+'[5]II-H-1.6 Dist'!H45 -> 4385.1688 | I51: =+'[4]II-H-1.6 Dist'!I44+'[5]II-H-1.6 Dist'!I45 -> -9053.868 | J51: =+'[4]II-H-1.6 Dist'!J44+'[5]II-H-1.6 Dist'!J45 -> -245.53187 | K51: =+'[4]II-H-1.6 Dist'!K44+'[5]II-H-1.6 Dist'!K45 -> 2147.2832 | ... O51: =+'[4]II-H-1.6 Dist'!O44+'[5]II-H-1.6 Dist'!O45 -> 2426.6879 | P51: =SUM(D51:O51) -> -3717.9667
A52: 5 | B52: TOTAL SECONDARY > 10 kW | D52: =SUM(D50:D51) -> -38885.25 | E52: =SUM(E50:E51) -> -14078.778 | F52: =SUM(F50:F51) -> -47794.961 | G52: =SUM(G50:G51) -> -19925.65 | H52: =SUM(H50:H51) -> 57405.68 | I52: =SUM(I50:I51) -> -91585.495 | J52: =SUM(J50:J51) -> 6479.7112 | K52: =SUM(K50:K51) -> 25064.354 | ... P52: =SUM(P50:P51) -> -6304.5891
A54: 6 | B54: PRIMARY NCP | C54: PRI | D54: =+'[4]II-H-1.6 Dist'!D47+'[5]II-H-1.6 Dist'!D48 -> -4916.7955 | E54: =+'[4]II-H-1.6 Dist'!E47+'[5]II-H-1.6 Dist'!E48 -> -1568.3232 | F54: =+'[4]II-H-1.6 Dist'!F47+'[5]II-H-1.6 Dist'!F48 -> -8186.4067 | G54: =+'[4]II-H-1.6 Dist'!G47+'[5]II-H-1.6 Dist'!G48 -> -3591.9567 | H54: =+'[4]II-H-1.6 Dist'!H47+'[5]II-H-1.6 Dist'!H48 -> 10078.261 | I54: =+'[4]II-H-1.6 Dist'!I47+'[5]II-H-1.6 Dist'!I48 -> -14688.897 | J54: =+'[4]II-H-1.6 Dist'!J47+'[5]II-H-1.6 Dist'!J48 -> 1112.6183 | K54: =+'[4]II-H-1.6 Dist'!K47+'[5]II-H-1.6 Dist'!K48 -> 4108.5561 | ... O54: =+'[4]II-H-1.6 Dist'!O47+'[5]II-H-1.6 Dist'!O48 -> 6677.7505 | P54: =SUM(D54:O54) -> 2132.7748
A55: 7 | B55: PRIMARY 4CP | C55: PRI | D55: =+'[4]II-H-1.6 Dist'!D48+'[5]II-H-1.6 Dist'!D49 -> 0 | E55: =+'[4]II-H-1.6 Dist'!E48+'[5]II-H-1.6 Dist'!E49 -> 0 | F55: =+'[4]II-H-1.6 Dist'!F48+'[5]II-H-1.6 Dist'!F49 -> 0 | G55: =+'[4]II-H-1.6 Dist'!G48+'[5]II-H-1.6 Dist'!G49 -> 0 | H55: =+'[4]II-H-1.6 Dist'!H48+'[5]II-H-1.6 Dist'!H49 -> 0 | I55: =+'[4]II-H-1.6 Dist'!I48+'[5]II-H-1.6 Dist'!I49 -> 0 | J55: =+'[4]II-H-1.6 Dist'!J48+'[5]II-H-1.6 Dist'!J49 -> 0 | K55: =+'[4]II-H-1.6 Dist'!K48+'[5]II-H-1.6 Dist'!K49 -> 0 | ... O55: =+'[4]II-H-1.6 Dist'!O48+'[5]II-H-1.6 Dist'!O49 -> 0 | P55: =SUM(D55:O55) -> 0
A56: 8 | B56: TOTAL PRIMARY | D56: =SUM(D54:D55) -> -4916.7955 | E56: =SUM(E54:E55) -> -1568.3232 | F56: =SUM(F54:F55) -> -8186.4067 | G56: =SUM(G54:G55) -> -3591.9567 | H56: =SUM(H54:H55) -> 10078.261 | I56: =SUM(I54:I55) -> -14688.897 | J56: =SUM(J54:J55) -> 1112.6183 | K56: =SUM(K54:K55) -> 4108.5561 | ... P56: =SUM(P54:P55) -> 2132.7748
A58: 9 | B58: TRANSMISSION | C58: TRA | P58: =SUM(D58:O58) -> 0
A60: 10 | B60: LIGHTING | C60: SEC | P60: =SUM(D60:O60) -> 0
A62: 11 | B62: TOTAL RETAIL | D62: =D60+D58+D56+D52+D48+D46 -> -43802.045 | E62: =E60+E58+E56+E52+E48+E46 -> -15647.102 | F62: =F60+F58+F56+F52+F48+F46 -> -55981.367 | G62: =G60+G58+G56+G52+G48+G46 -> -23517.606 | H62: =H60+H58+H56+H52+H48+H46 -> 67483.941 | I62: =I60+I58+I56+I52+I48+I46 -> -106274.39 | J62: =J60+J58+J56+J52+J48+J46 -> 7592.3295 | K62: =K60+K58+K56+K52+K48+K46 -> 29172.91 | ... P62: =P60+P58+P56+P52+P48+P46 -> -4171.8142
A64: 12 | B64: WHOLESALE PRI | C64: PRI | P64: =SUM(D64:O64) -> 0
A65: 13 | B65: WHOLESALE TRANS | C65: TRA | P65: =SUM(D65:O65) -> 0
A66: 14 | B66: TOTAL WHOLESALE | D66: =SUM(D64:D65) -> 0 | E66: =SUM(E64:E65) -> 0 | F66: =SUM(F64:F65) -> 0 | G66: =SUM(G64:G65) -> 0 | H66: =SUM(H64:H65) -> 0 | I66: =SUM(I64:I65) -> 0 | J66: =SUM(J64:J65) -> 0 | K66: =SUM(K64:K65) -> 0 | ... P66: =SUM(P64:P65) -> 0
A68: 15 | B68: =B37 -> TOTAL AEP TEXAS | D68: =+D66+D62 -> -43802.045 | E68: =+E66+E62 -> -15647.102 | F68: =+F66+F62 -> -55981.367 | G68: =+G66+G62 -> -23517.606 | H68: =+H66+H62 -> 67483.941 | I68: =+I66+I62 -> -106274.39 | J68: =+J66+J62 -> 7592.3295 | K68: =+K66+K62 -> 29172.91 | ... P68: =+P66+P62 -> -4171.8142
B69: =+B8 -> AEP TEXAS
B70: KW CUSTOMER ADJUSTMENT
B71: =+B10 -> FOR TEST YEAR ENDED DECEMBER 31, 2018
A74: LINE | B74: DESCRIPTION | C74: VOLT | D74: =+D13 -> JANUARY | E74: =+E13 -> FEBRUARY | F74: =+F13 -> MARCH | G74: =+G13 -> APRIL | H74: =+H13 -> MAY | I74: =+I13 -> JUNE | J74: =+J13 -> JULY | K74: =+K13 -> AUGUST | ... O74: =+O13 -> DECEMBER | P74: TOTAL
A76: 1 | B76: RESIDENTIAL SERVICE | C76: SEC | D76: =+'[5]II-H-1.6 Dist'!D71+'[4]II-H-1.6 Dist'!D69 -> 0 | E76: =+'[5]II-H-1.6 Dist'!E71+'[4]II-H-1.6 Dist'!E69 -> 0 | F76: =+'[5]II-H-1.6 Dist'!F71+'[4]II-H-1.6 Dist'!F69 -> 0 | G76: =+'[5]II-H-1.6 Dist'!G71+'[4]II-H-1.6 Dist'!G69 -> 0 | H76: =+'[5]II-H-1.6 Dist'!H71+'[4]II-H-1.6 Dist'!H69 -> 0 | I76: =+'[5]II-H-1.6 Dist'!I71+'[4]II-H-1.6 Dist'!I69 -> 0 | J76: =+'[5]II-H-1.6 Dist'!J71+'[4]II-H-1.6 Dist'!J69 -> 0 | K76: =+'[5]II-H-1.6 Dist'!K71+'[4]II-H-1.6 Dist'!K69 -> 0 | ... O76: =+'[5]II-H-1.6 Dist'!O71+'[4]II-H-1.6 Dist'!O69 -> 0 | P76: =SUM(D76:O76) -> 0
A78: 2 | B78: SECONDARY < 10 kW | C78: SEC | D78: =+'[5]II-H-1.6 Dist'!D73+'[4]II-H-1.6 Dist'!D71 -> 0 | E78: =+'[5]II-H-1.6 Dist'!E73+'[4]II-H-1.6 Dist'!E71 -> 0 | F78: =+'[5]II-H-1.6 Dist'!F73+'[4]II-H-1.6 Dist'!F71 -> 0 | G78: =+'[5]II-H-1.6 Dist'!G73+'[4]II-H-1.6 Dist'!G71 -> 0 | H78: =+'[5]II-H-1.6 Dist'!H73+'[4]II-H-1.6 Dist'!H71 -> 0 | I78: =+'[5]II-H-1.6 Dist'!I73+'[4]II-H-1.6 Dist'!I71 -> 0 | J78: =+'[5]II-H-1.6 Dist'!J73+'[4]II-H-1.6 Dist'!J71 -> 0 | K78: =+'[5]II-H-1.6 Dist'!K73+'[4]II-H-1.6 Dist'!K71 -> 0 | ... O78: =+'[5]II-H-1.6 Dist'!O73+'[4]II-H-1.6 Dist'!O71 -> 0 | P78: =SUM(D78:O78) -> 0
A80: 3 | B80: SECONDARY > 10 kW NCP | C80: SEC | D80: =+'[5]II-H-1.6 Dist'!D75+'[4]II-H-1.6 Dist'!D73 -> 104934.88 | E80: =+'[5]II-H-1.6 Dist'!E75+'[4]II-H-1.6 Dist'!E73 -> 53165.862 | F80: =+'[5]II-H-1.6 Dist'!F75+'[4]II-H-1.6 Dist'!F73 -> 23060.093 | G80: =+'[5]II-H-1.6 Dist'!G75+'[4]II-H-1.6 Dist'!G73 -> 20468.361 | H80: =+'[5]II-H-1.6 Dist'!H75+'[4]II-H-1.6 Dist'!H73 -> 24702.73 | I80: =+'[5]II-H-1.6 Dist'!I75+'[4]II-H-1.6 Dist'!I73 -> 21647.578 | J80: =+'[5]II-H-1.6 Dist'!J75+'[4]II-H-1.6 Dist'!J73 -> 16736.61 | K80: =+'[5]II-H-1.6 Dist'!K75+'[4]II-H-1.6 Dist'!K73 -> 4880.6396 | ... O80: =+'[5]II-H-1.6 Dist'!O75+'[4]II-H-1.6 Dist'!O73 -> 0 | P80: =SUM(D80:O80) -> 303702.9
A81: 4 | B81: SECONDARY > 10 kW 4CP | C81: SEC | D81: =+'[5]II-H-1.6 Dist'!D76+'[4]II-H-1.6 Dist'!D74 -> -15258.242 | E81: =+'[5]II-H-1.6 Dist'!E76+'[4]II-H-1.6 Dist'!E74 -> -15122.516 | F81: =+'[5]II-H-1.6 Dist'!F76+'[4]II-H-1.6 Dist'!F74 -> -14391.584 | G81: =+'[5]II-H-1.6 Dist'!G76+'[4]II-H-1.6 Dist'!G74 -> -12442.336 | H81: =+'[5]II-H-1.6 Dist'!H76+'[4]II-H-1.6 Dist'!H74 -> -13799.638 | I81: =+'[5]II-H-1.6 Dist'!I76+'[4]II-H-1.6 Dist'!I74 -> -8842.2232 | J81: =+'[5]II-H-1.6 Dist'!J76+'[4]II-H-1.6 Dist'!J74 -> -9776.8934 | K81: =+'[5]II-H-1.6 Dist'!K76+'[4]II-H-1.6 Dist'!K74 -> -11509.272 | ... O81: =+'[5]II-H-1.6 Dist'!O76+'[4]II-H-1.6 Dist'!O74 -> 0 | P81: =SUM(D81:O81) -> -99239.251
A82: 5 | B82: TOTAL SECONDARY > 10 kW | D82: =SUM(D80:D81) -> 89676.638 | E82: =SUM(E80:E81) -> 38043.345 | F82: =SUM(F80:F81) -> 8668.5093 | G82: =SUM(G80:G81) -> 8026.0254 | H82: =SUM(H80:H81) -> 10903.091 | I82: =SUM(I80:I81) -> 12805.355 | J82: =SUM(J80:J81) -> 6959.7165 | K82: =SUM(K80:K81) -> -6628.6326 | ... P82: =SUM(P80:P81) -> 204463.64
A84: 6 | B84: PRIMARY NCP | C84: PRI | D84: =+'[5]II-H-1.6 Dist'!D79+'[4]II-H-1.6 Dist'!D77 -> 667.35358 | E84: =+'[5]II-H-1.6 Dist'!E79+'[4]II-H-1.6 Dist'!E77 -> 1490.5766 | F84: =+'[5]II-H-1.6 Dist'!F79+'[4]II-H-1.6 Dist'!F77 -> 1081.3027 | G84: =+'[5]II-H-1.6 Dist'!G79+'[4]II-H-1.6 Dist'!G77 -> 1857.0479 | H84: =+'[5]II-H-1.6 Dist'!H79+'[4]II-H-1.6 Dist'!H77 -> 1649.6012 | I84: =+'[5]II-H-1.6 Dist'!I79+'[4]II-H-1.6 Dist'!I77 -> 530.41225 | J84: =+'[5]II-H-1.6 Dist'!J79+'[4]II-H-1.6 Dist'!J77 -> 879.28927 | K84: =+'[5]II-H-1.6 Dist'!K79+'[4]II-H-1.6 Dist'!K77 -> -669.14764 | ... O84: =+'[5]II-H-1.6 Dist'!O79+'[4]II-H-1.6 Dist'!O77 -> 0 | P84: =SUM(D84:O84) -> 5908.0196
A85: 7 | B85: PRIMARY 4CP | C85: PRI | D85: =+'[5]II-H-1.6 Dist'!D80+'[4]II-H-1.6 Dist'!D78 -> 5317.14 | E85: =+'[5]II-H-1.6 Dist'!E80+'[4]II-H-1.6 Dist'!E78 -> 3905.9155 | F85: =+'[5]II-H-1.6 Dist'!F80+'[4]II-H-1.6 Dist'!F78 -> -7874.4422 | G85: =+'[5]II-H-1.6 Dist'!G80+'[4]II-H-1.6 Dist'!G78 -> 13211.439 | H85: =+'[5]II-H-1.6 Dist'!H80+'[4]II-H-1.6 Dist'!H78 -> -7017.0113 | I85: =+'[5]II-H-1.6 Dist'!I80+'[4]II-H-1.6 Dist'!I78 -> -16615.555 | J85: =+'[5]II-H-1.6 Dist'!J80+'[4]II-H-1.6 Dist'!J78 -> -793.89714 | K85: =+'[5]II-H-1.6 Dist'!K80+'[4]II-H-1.6 Dist'!K78 -> 3877.3475 | ... O85: =+'[5]II-H-1.6 Dist'!O80+'[4]II-H-1.6 Dist'!O78 -> 0 | P85: =SUM(D85:O85) -> -13753.862
A86: 8 | B86: TOTAL PRIMARY | D86: =SUM(D84:D85) -> 5984.4936 | E86: =SUM(E84:E85) -> 5396.4921 | F86: =SUM(F84:F85) -> -6793.1394 | G86: =SUM(G84:G85) -> 15068.487 | H86: =SUM(H84:H85) -> -5367.41 | I86: =SUM(I84:I85) -> -16085.143 | J86: =SUM(J84:J85) -> 85.392135 | K86: =SUM(K84:K85) -> 3208.1999 | ... P86: =SUM(P84:P85) -> -7845.8421
A88: 9 | B88: TRANSMISSION | C88: TRA | D88: =+'[5]II-H-1.6 Dist'!D83+'[4]II-H-1.6 Dist'!D81 -> -41291.478 | E88: =+'[5]II-H-1.6 Dist'!E83+'[4]II-H-1.6 Dist'!E81 -> 68094.835 | F88: =+'[5]II-H-1.6 Dist'!F83+'[4]II-H-1.6 Dist'!F81 -> 123946.87 | G88: =+'[5]II-H-1.6 Dist'!G83+'[4]II-H-1.6 Dist'!G81 -> 71372.213 | H88: =+'[5]II-H-1.6 Dist'!H83+'[4]II-H-1.6 Dist'!H81 -> 43518.227 | I88: =+'[5]II-H-1.6 Dist'!I83+'[4]II-H-1.6 Dist'!I81 -> 2519.4208 | J88: =+'[5]II-H-1.6 Dist'!J83+'[4]II-H-1.6 Dist'!J81 -> 112987.28 | K88: =+'[5]II-H-1.6 Dist'!K83+'[4]II-H-1.6 Dist'!K81 -> 66504.568 | ... O88: =+'[5]II-H-1.6 Dist'!O83+'[4]II-H-1.6 Dist'!O81 -> 522678.69 | P88: =SUM(D88:O88) -> 807567.44
A90: 10 | B90: LIGHTING | C90: SEC | D90: =D29*'II-H-3.1-3'!D159 -> 0 | E90: =E29*'II-H-3.1-3'!E159 -> 0 | F90: =F29*'II-H-3.1-3'!F159 -> 0 | G90: =G29*'II-H-3.1-3'!G159 -> 0 | H90: =H29*'II-H-3.1-3'!H159 -> 0 | I90: =I29*'II-H-3.1-3'!I159 -> 0 | J90: =J29*'II-H-3.1-3'!J159 -> 0 | K90: =K29*'II-H-3.1-3'!K159 -> 0 | ... O90: =O29*'II-H-3.1-3'!O159 -> 0 | P90: =SUM(D90:O90) -> 0
A92: 11 | B92: TOTAL RETAIL | D92: =D90+D88+D86+D82+D78+D76 -> 54369.653 | E92: =E90+E88+E86+E82+E78+E76 -> 111534.67 | F92: =F90+F88+F86+F82+F78+F76 -> 125822.24 | G92: =G90+G88+G86+G82+G78+G76 -> 94466.725 | H92: =H90+H88+H86+H82+H78+H76 -> 49053.909 | I92: =I90+I88+I86+I82+I78+I76 -> -760.36742 | J92: =J90+J88+J86+J82+J78+J76 -> 120032.39 | K92: =K90+K88+K86+K82+K78+K76 -> 63084.135 | ... P92: =P90+P88+P86+P82+P78+P76 -> 1004185.2
A94: 12 | B94: WHOLESALE PRI | C94: PRI | D94: =D33*'II-H-3.1-3'!D163 -> 0 | E94: =E33*'II-H-3.1-3'!E163 -> 0 | F94: =F33*'II-H-3.1-3'!F163 -> 0 | G94: =G33*'II-H-3.1-3'!G163 -> 0 | H94: =H33*'II-H-3.1-3'!H163 -> 0 | I94: =I33*'II-H-3.1-3'!I163 -> 0 | J94: =J33*'II-H-3.1-3'!J163 -> 0 | K94: =K33*'II-H-3.1-3'!K163 -> 0 | ... O94: =O33*'II-H-3.1-3'!O163 -> 0 | P94: =SUM(D94:O94) -> 0
A95: 13 | B95: WHOLESALE TRANS | C95: TRA | P95: =SUM(D95:O95) -> 0
A96: 14 | B96: TOTAL WHOLESALE | D96: =SUM(D94:D95) -> 0 | E96: =SUM(E94:E95) -> 0 | F96: =SUM(F94:F95) -> 0 | G96: =SUM(G94:G95) -> 0 | H96: =SUM(H94:H95) -> 0 | I96: =SUM(I94:I95) -> 0 | J96: =SUM(J94:J95) -> 0 | K96: =SUM(K94:K95) -> 0 | ... P96: =SUM(P94:P95) -> 0
A98: 15 | B98: =B37 -> TOTAL AEP TEXAS | D98: =+D96+D92 -> 54369.653 | E98: =+E96+E92 -> 111534.67 | F98: =+F96+F92 -> 125822.24 | G98: =+G96+G92 -> 94466.725 | H98: =+H96+H92 -> 49053.909 | I98: =+I96+I92 -> -760.36742 | J98: =+J96+J92 -> 120032.39 | K98: =+K96+K92 -> 63084.135 | ... P98: =+P96+P92 -> 1004185.2
B100: =+B69 -> AEP TEXAS
B101: OTHER KW ADJUSTMENTS
B102: =B71 -> FOR TEST YEAR ENDED DECEMBER 31, 2018
A105: LINE | B105: DESCRIPTION | C105: VOLT | D105: =D13 -> JANUARY | E105: =E13 -> FEBRUARY | F105: =F13 -> MARCH | G105: =G13 -> APRIL | H105: =H13 -> MAY | I105: =I13 -> JUNE | J105: =J13 -> JULY | K105: =K13 -> AUGUST | ... O105: =O13 -> DECEMBER | P105: TOTAL
A107: 1 | B107: RESIDENTIAL SERVICE | C107: SEC | P107: =SUM(D107:O107) -> 0
A109: 2 | B109: SECONDARY < 10 kW | C109: SEC | P109: =SUM(D109:O109) -> 0
A111: 3 | B111: SECONDARY > 10 kW NCP | C111: SEC | P111: =SUM(D111:O111) -> 0
A112: 4 | B112: SECONDARY > 10 kW 4CP | C112: SEC | P112: =SUM(D112:O112) -> 0
A113: 5 | B113: TOTAL SECONDARY > 10 kW | D113: =SUM(D111:D112) -> 0 | E113: =SUM(E111:E112) -> 0 | F113: =SUM(F111:F112) -> 0 | G113: =SUM(G111:G112) -> 0 | H113: =SUM(H111:H112) -> 0 | I113: =SUM(I111:I112) -> 0 | J113: =SUM(J111:J112) -> 0 | K113: =SUM(K111:K112) -> 0 | ... P113: =SUM(P111:P112) -> 0
A115: 6 | B115: PRIMARY NCP | C115: PRI | P115: =SUM(D115:O115) -> 0
A116: 7 | B116: PRIMARY 4CP | C116: PRI | P116: =SUM(D116:O116) -> 0
A117: 8 | B117: TOTAL PRIMARY | D117: =SUM(D115:D116) -> 0 | E117: =SUM(E115:E116) -> 0 | F117: =SUM(F115:F116) -> 0 | G117: =SUM(G115:G116) -> 0 | H117: =SUM(H115:H116) -> 0 | I117: =SUM(I115:I116) -> 0 | J117: =SUM(J115:J116) -> 0 | K117: =SUM(K115:K116) -> 0 | ... P117: =SUM(P115:P116) -> 0
A119: 9 | B119: TRANSMISSION | C119: TRA | P119: =SUM(D119:O119) -> 0
A121: 10 | B121: LIGHTING | C121: SEC | P121: =SUM(D121:O121) -> 0
A123: 11 | B123: TOTAL RETAIL | D123: =D121+D119+D117+D113+D109+D107 -> 0 | E123: =E121+E119+E117+E113+E109+E107 -> 0 | F123: =F121+F119+F117+F113+F109+F107 -> 0 | G123: =G121+G119+G117+G113+G109+G107 -> 0 | H123: =H121+H119+H117+H113+H109+H107 -> 0 | I123: =I121+I119+I117+I113+I109+I107 -> 0 | J123: =J121+J119+J117+J113+J109+J107 -> 0 | K123: =K121+K119+K117+K113+K109+K107 -> 0 | ... P123: =P121+P119+P117+P113+P109+P107 -> 0
A125: 12 | B125: WHOLESALE PRI | C125: PRI | P125: =SUM(D125:O125) -> 0
A126: 13 | B126: WHOLESALE TRANS | C126: TRA | P126: =SUM(D126:O126) -> 0
A127: 14 | B127: TOTAL WHOLESALE | D127: =SUM(D125:D126) -> 0 | E127: =SUM(E125:E126) -> 0 | F127: =SUM(F125:F126) -> 0 | G127: =SUM(G125:G126) -> 0 | H127: =SUM(H125:H126) -> 0 | I127: =SUM(I125:I126) -> 0 | J127: =SUM(J125:J126) -> 0 | K127: =SUM(K125:K126) -> 0 | ... P127: =SUM(P125:P126) -> 0
A129: 15 | B129: =B37 -> TOTAL AEP TEXAS | D129: =+D127+D123 -> 0 | E129: =+E127+E123 -> 0 | F129: =+F127+F123 -> 0 | G129: =+G127+G123 -> 0 | H129: =+H127+H123 -> 0 | I129: =+I127+I123 -> 0 | J129: =+J127+J123 -> 0 | K129: =+K127+K123 -> 0 | ... P129: =+P127+P123 -> 0
B131: =B8 -> AEP TEXAS
B132: ADJUSTED DISTRIBUTION BILLING KW
B133: =B102 -> FOR TEST YEAR ENDED DECEMBER 31, 2018
A136: LINE | B136: DESCRIPTION | C136: VOLT | D136: =D13 -> JANUARY | E136: =E13 -> FEBRUARY | F136: =F13 -> MARCH | G136: =G13 -> APRIL | H136: =H13 -> MAY | I136: =I13 -> JUNE | J136: =J13 -> JULY | K136: =K13 -> AUGUST | ... O136: =O13 -> DECEMBER | P136: TOTAL
A138: 1 | B138: RESIDENTIAL SERVICE | C138: SEC | D138: =D107+D76+D46+D15 -> 0 | E138: =E107+E76+E46+E15 -> 0 | F138: =F107+F76+F46+F15 -> 0 | G138: =G107+G76+G46+G15 -> 0 | H138: =H107+H76+H46+H15 -> 0 | I138: =I107+I76+I46+I15 -> 0 | J138: =J107+J76+J46+J15 -> 0 | K138: =K107+K76+K46+K15 -> 0 | ... O138: =O107+O76+O46+O15 -> 0 | P138: =SUM(D138:O138) -> 0
A140: 2 | B140: SECONDARY < 10 kW | C140: SEC | D140: =D109+D78+D48+D17 -> 0 | E140: =E109+E78+E48+E17 -> 0 | F140: =F109+F78+F48+F17 -> 0 | G140: =G109+G78+G48+G17 -> 0 | H140: =H109+H78+H48+H17 -> 0 | I140: =I109+I78+I48+I17 -> 0 | J140: =J109+J78+J48+J17 -> 0 | K140: =K109+K78+K48+K17 -> 0 | ... O140: =O109+O78+O48+O17 -> 0 | P140: =SUM(D140:O140) -> 0
A142: 3 | B142: SECONDARY > 10 kW NCP | C142: SEC | D142: =D111+D80+D50+D19 -> 2898971.7 | E142: =E111+E80+E50+E19 -> 2843341.7 | F142: =F111+F80+F50+F19 -> 2695160.1 | G142: =G111+G80+G50+G19 -> 2711811.4 | H142: =H111+H80+H50+H19 -> 2836346.4 | I142: =I111+I80+I50+I19 -> 2787116.2 | J142: =J111+J80+J50+J19 -> 2866505.9 | K142: =K111+K80+K50+K19 -> 2886645 | ... O142: =O111+O80+O50+O19 -> 2785504.2 | P142: =SUM(D142:O142) -> 33775906
A143: 4 | B143: SECONDARY > 10 kW 4CP | C143: SEC | D143: =D112+D81+D51+D20 -> 281444.78 | E143: =E112+E81+E51+E20 -> 272369.85 | F143: =F112+F81+F51+F20 -> 265086.87 | G143: =G112+G81+G51+G20 -> 257750.4 | H143: =H112+H81+H51+H20 -> 266245.93 | I143: =I112+I81+I51+I20 -> 259687.81 | J143: =J112+J81+J51+J20 -> 277606.47 | K143: =K112+K81+K51+K20 -> 283801.21 | ... O143: =O112+O81+O51+O20 -> 289838.69 | P143: =SUM(D143:O143) -> 3358360
A144: 5 | B144: TOTAL SECONDARY > 10 kW | D144: =SUM(D142:D143) -> 3180416.5 | E144: =SUM(E142:E143) -> 3115711.6 | F144: =SUM(F142:F143) -> 2960246.9 | G144: =SUM(G142:G143) -> 2969561.8 | H144: =SUM(H142:H143) -> 3102592.4 | I144: =SUM(I142:I143) -> 3046804 | J144: =SUM(J142:J143) -> 3144112.3 | K144: =SUM(K142:K143) -> 3170446.2 | ... P144: =SUM(P142:P143) -> 37134266
A146: 6 | B146: PRIMARY NCP | C146: PRI | D146: =D115+D84+D54+D23 -> 69081.058 | E146: =E115+E84+E54+E23 -> 76161.553 | F146: =F115+F84+F54+F23 -> 65356.296 | G146: =G115+G84+G54+G23 -> 72185.691 | H146: =H115+H84+H54+H23 -> 90503.562 | I146: =I115+I84+I54+I23 -> 67159.115 | J146: =J115+J84+J54+J23 -> 79020.408 | K146: =K115+K84+K54+K23 -> 90182.208 | ... O146: =O115+O84+O54+O23 -> 85021.351 | P146: =SUM(D146:O146) -> 958871.29
A147: 7 | B147: PRIMARY 4CP | C147: PRI | D147: =D116+D85+D55+D24 -> 794185.94 | E147: =E116+E85+E55+E24 -> 766817.62 | F147: =F116+F85+F55+F24 -> 759784.56 | G147: =G116+G85+G55+G24 -> 770194.44 | H147: =H116+H85+H55+H24 -> 806877.59 | I147: =I116+I85+I55+I24 -> 811189.34 | J147: =J116+J85+J55+J24 -> 807440.7 | K147: =K116+K85+K55+K24 -> 809755.35 | ... O147: =O116+O85+O55+O24 -> 765944.5 | P147: =SUM(D147:O147) -> 9502752
A148: 8 | B148: TOTAL PRIMARY | D148: =SUM(D146:D147) -> 863267 | E148: =SUM(E146:E147) -> 842979.17 | F148: =SUM(F146:F147) -> 825140.85 | G148: =SUM(G146:G147) -> 842380.13 | H148: =SUM(H146:H147) -> 897381.15 | I148: =SUM(I146:I147) -> 878348.46 | J148: =SUM(J146:J147) -> 886461.11 | K148: =SUM(K146:K147) -> 899937.56 | ... P148: =SUM(P146:P147) -> 10461623
A150: 9 | B150: TRANSMISSION | C150: TRA | D150: =D119+D88+D58+D27 -> 1433777.2 | E150: =E119+E88+E58+E27 -> 1283391.5 | F150: =F119+F88+F58+F27 -> 1515507.5 | G150: =G119+G88+G58+G27 -> 1437962 | H150: =H119+H88+H58+H27 -> 1423688.7 | I150: =I119+I88+I58+I27 -> 1459454.3 | J150: =J119+J88+J58+J27 -> 1389571 | K150: =K119+K88+K58+K27 -> 1341697.1 | ... O150: =O119+O88+O58+O27 -> 1554088.4 | P150: =SUM(D150:O150) -> 16829578
A152: 10 | B152: LIGHTING | C152: SEC | D152: =D121+D90+D60+D29 -> 0 | E152: =E121+E90+E60+E29 -> 0 | F152: =F121+F90+F60+F29 -> 0 | G152: =G121+G90+G60+G29 -> 0 | H152: =H121+H90+H60+H29 -> 0 | I152: =I121+I90+I60+I29 -> 0 | J152: =J121+J90+J60+J29 -> 0 | K152: =K121+K90+K60+K29 -> 0 | ... O152: =O121+O90+O60+O29 -> 0 | P152: =SUM(D152:O152) -> 0
A154: 11 | B154: TOTAL RETAIL | D154: =D152+D150+D148+D144+D140+D138 -> 5477460.7 | E154: =E152+E150+E148+E144+E140+E138 -> 5242082.3 | F154: =F152+F150+F148+F144+F140+F138 -> 5300895.3 | G154: =G152+G150+G148+G144+G140+G138 -> 5249903.9 | H154: =H152+H150+H148+H144+H140+H138 -> 5423662.2 | I154: =I152+I150+I148+I144+I140+I138 -> 5384606.7 | J154: =J152+J150+J148+J144+J140+J138 -> 5420144.4 | K154: =K152+K150+K148+K144+K140+K138 -> 5412080.8 | ... P154: =P152+P150+P148+P144+P140+P138 -> 64425467
A156: 12 | B156: WHOLESALE PRI | C156: PRI | D156: =D125+D94+D64+D33 -> 0 | E156: =E125+E94+E64+E33 -> 0 | F156: =F125+F94+F64+F33 -> 0 | G156: =G125+G94+G64+G33 -> 0 | H156: =H125+H94+H64+H33 -> 0 | I156: =I125+I94+I64+I33 -> 0 | J156: =J125+J94+J64+J33 -> 0 | K156: =K125+K94+K64+K33 -> 0 | ... O156: =O125+O94+O64+O33 -> 0 | P156: =SUM(D156:O156) -> 0
A157: 13 | B157: WHOLESALE TRANS | C157: TRA | D157: =D126+D95+D65+D34 -> 0 | E157: =E126+E95+E65+E34 -> 0 | F157: =F126+F95+F65+F34 -> 0 | G157: =G126+G95+G65+G34 -> 0 | H157: =H126+H95+H65+H34 -> 0 | I157: =I126+I95+I65+I34 -> 0 | J157: =J126+J95+J65+J34 -> 0 | K157: =K126+K95+K65+K34 -> 0 | ... O157: =O126+O95+O65+O34 -> 0 | P157: =SUM(D157:O157) -> 0
A158: 14 | B158: TOTAL WHOLESALE | D158: =SUM(D156:D157) -> 0 | E158: =SUM(E156:E157) -> 0 | F158: =SUM(F156:F157) -> 0 | G158: =SUM(G156:G157) -> 0 | H158: =SUM(H156:H157) -> 0 | I158: =SUM(I156:I157) -> 0 | J158: =SUM(J156:J157) -> 0 | K158: =SUM(K156:K157) -> 0 | ... P158: =SUM(P156:P157) -> 0
...

Sheet II-H-4.1 Tran kW
B2: PUBLIC UTILITY COMMISSION OF TEXAS
B3: AEP TEXAS INC
B4: II-H-4.1 TRAN KW ADJUSTMENTS
B5: TEST YEAR ENDING 12/31/2018
B6: DOCKET NUMBER (PENDING ASSIGNMENT)
B8: ='II-H-1.2'!B7:O7 -> AEP TEXAS
B9: TRANSMISSION KW
B10: ='II-H-1.2'!B9:O9 -> FOR TEST YEAR ENDED DECEMBER 31, 2018
A13: LINE | B13: DESCRIPTION | C13: VOLT | D13: JANUARY | E13: FEBRUARY | F13: MARCH | G13: APRIL | H13: MAY | I13: JUNE | J13: JULY | K13: AUGUST | L13: SEPTEMBER | M13: OCTOBER | N13: NOVEMBER | O13: DECEMBER | P13: TOTAL
A15: 1 | B15: RESIDENTIAL SERVICE | C15: SEC
A17: 2 | B17: SECONDARY < 10 kW | C17: SEC
Q18: tran rate
A19: 3 | B19: SECONDARY > 10 kW NCP | C19: SEC | D19: =+'[4]II-H-1.6 Tran'!D12+'[5]II-H-1.6 Tran'!D12 -> 2536920.3 | E19: =+'[4]II-H-1.6 Tran'!E12+'[5]II-H-1.6 Tran'!E12 -> 2486843.1 | F19: =+'[4]II-H-1.6 Tran'!F12+'[5]II-H-1.6 Tran'!F12 -> 2338364.3 | G19: =+'[4]II-H-1.6 Tran'!G12+'[5]II-H-1.6 Tran'!G12 -> 2260370.1 | H19: =+'[4]II-H-1.6 Tran'!H12+'[5]II-H-1.6 Tran'!H12 -> 2330821.6 | I19: =+'[4]II-H-1.6 Tran'!I12+'[5]II-H-1.6 Tran'!I12 -> 2483015.6 | J19: =+'[4]II-H-1.6 Tran'!J12+'[5]II-H-1.6 Tran'!J12 -> 2449704.7 | K19: =+'[4]II-H-1.6 Tran'!K12+'[5]II-H-1.6 Tran'!K12 -> 2484158.8 | ... O19: =+'[4]II-H-1.6 Tran'!O12+'[5]II-H-1.6 Tran'!O12 -> 2380118.4 | P19: =SUM(D19:O19) -> 29043900 | Q19: ='II-H-4.1 Functions'!H19/'II-H-4.1 Tran kW'!P19 -> 1.2636446
A20: 4 | B20: SECONDARY > 10 kW 4CP | C20: SEC | D20: =+'[4]II-H-1.6 Tran'!D13+'[5]II-H-1.6 Tran'!D13 -> 192667.2 | E20: =+'[4]II-H-1.6 Tran'!E13+'[5]II-H-1.6 Tran'!E13 -> 188386.6 | F20: =+'[4]II-H-1.6 Tran'!F13+'[5]II-H-1.6 Tran'!F13 -> 191665 | G20: =+'[4]II-H-1.6 Tran'!G13+'[5]II-H-1.6 Tran'!G13 -> 187445.8 | H20: =+'[4]II-H-1.6 Tran'!H13+'[5]II-H-1.6 Tran'!H13 -> 191674.6 | I20: =+'[4]II-H-1.6 Tran'!I13+'[5]II-H-1.6 Tran'!I13 -> 185912.6 | J20: =+'[4]II-H-1.6 Tran'!J13+'[5]II-H-1.6 Tran'!J13 -> 192497.6 | K20: =+'[4]II-H-1.6 Tran'!K13+'[5]II-H-1.6 Tran'!K13 -> 185292.6 | ... O20: =+'[4]II-H-1.6 Tran'!O13+'[5]II-H-1.6 Tran'!O13 -> 186247.9 | P20: =SUM(D20:O20) -> 2261572 | Q20: ='II-H-4.1 Functions'!H20/'II-H-4.1 Tran kW'!P20 -> 1.8278645
A21: 5 | B21: TOTAL SECONDARY > 10 kW | D21: =SUM(D19:D20) -> 2729587.5 | E21: =SUM(E19:E20) -> 2675229.7 | F21: =SUM(F19:F20) -> 2530029.3 | G21: =SUM(G19:G20) -> 2447815.9 | H21: =SUM(H19:H20) -> 2522496.2 | I21: =SUM(I19:I20) -> 2668928.2 | J21: =SUM(J19:J20) -> 2642202.3 | K21: =SUM(K19:K20) -> 2669451.4 | ... P21: =SUM(P19:P20) -> 31305472
A23: 6 | B23: PRIMARY NCP | C23: PRI | D23: =+'[4]II-H-1.6 Tran'!D16+'[5]II-H-1.6 Tran'!D16 -> 55958.7 | E23: =+'[4]II-H-1.6 Tran'!E16+'[5]II-H-1.6 Tran'!E16 -> 63885.4 | F23: =+'[4]II-H-1.6 Tran'!F16+'[5]II-H-1.6 Tran'!F16 -> 58063.1 | G23: =+'[4]II-H-1.6 Tran'!G16+'[5]II-H-1.6 Tran'!G16 -> 60147.6 | H23: =+'[4]II-H-1.6 Tran'!H16+'[5]II-H-1.6 Tran'!H16 -> 67149.9 | I23: =+'[4]II-H-1.6 Tran'!I16+'[5]II-H-1.6 Tran'!I16 -> 70338.6 | J23: =+'[4]II-H-1.6 Tran'!J16+'[5]II-H-1.6 Tran'!J16 -> 66817.3 | K23: =+'[4]II-H-1.6 Tran'!K16+'[5]II-H-1.6 Tran'!K16 -> 75430.6 | ... O23: =+'[4]II-H-1.6 Tran'!O16+'[5]II-H-1.6 Tran'!O16 -> 65045.7 | P23: =SUM(D23:O23) -> 799037.8 | Q23: ='II-H-4.1 Functions'!H23/'II-H-4.1 Tran kW'!P23 -> 1.4113357
A24: 7 | B24: PRIMARY 4CP | C24: PRI | D24: =+'[4]II-H-1.6 Tran'!D17+'[5]II-H-1.6 Tran'!D17 -> 578426.4 | E24: =+'[4]II-H-1.6 Tran'!E17+'[5]II-H-1.6 Tran'!E17 -> 561116.8 | F24: =+'[4]II-H-1.6 Tran'!F17+'[5]II-H-1.6 Tran'!F17 -> 556090.1 | G24: =+'[4]II-H-1.6 Tran'!G17+'[5]II-H-1.6 Tran'!G17 -> 536697.3 | H24: =+'[4]II-H-1.6 Tran'!H17+'[5]II-H-1.6 Tran'!H17 -> 577907.3 | I24: =+'[4]II-H-1.6 Tran'!I17+'[5]II-H-1.6 Tran'!I17 -> 571709.4 | J24: =+'[4]II-H-1.6 Tran'!J17+'[5]II-H-1.6 Tran'!J17 -> 558624.3 | K24: =+'[4]II-H-1.6 Tran'!K17+'[5]II-H-1.6 Tran'!K17 -> 556119.1 | ... O24: =+'[4]II-H-1.6 Tran'!O17+'[5]II-H-1.6 Tran'!O17 -> 546207.1 | P24: =SUM(D24:O24) -> 6734223.6 | Q24: ='II-H-4.1 Functions'!H24/'II-H-4.1 Tran kW'!P24 -> 1.928939
A25: 8 | B25: TOTAL PRIMARY | D25: =SUM(D23:D24) -> 634385.1 | E25: =SUM(E23:E24) -> 625002.2 | F25: =SUM(F23:F24) -> 614153.2 | G25: =SUM(G23:G24) -> 596844.9 | H25: =SUM(H23:H24) -> 645057.2 | I25: =SUM(I23:I24) -> 642048 | J25: =SUM(J23:J24) -> 625441.6 | K25: =SUM(K23:K24) -> 631549.7 | ... P25: =SUM(P23:P24) -> 7533261.4
A27: 9 | B27: TRANSMISSION | C27: TRA | D27: =+'[4]II-H-1.6 Tran'!D20+'[5]II-H-1.6 Tran'!D20 -> 668538.6 | E27: =+'[4]II-H-1.6 Tran'!E20+'[5]II-H-1.6 Tran'!E20 -> 469680.5 | F27: =+'[4]II-H-1.6 Tran'!F20+'[5]II-H-1.6 Tran'!F20 -> 563808.5 | G27: =+'[4]II-H-1.6 Tran'!G20+'[5]II-H-1.6 Tran'!G20 -> 492900.3 | H27: =+'[4]II-H-1.6 Tran'!H20+'[5]II-H-1.6 Tran'!H20 -> 524218.5 | I27: =+'[4]II-H-1.6 Tran'!I20+'[5]II-H-1.6 Tran'!I20 -> 591086.7 | J27: =+'[4]II-H-1.6 Tran'!J20+'[5]II-H-1.6 Tran'!J20 -> 438690.9 | K27: =+'[4]II-H-1.6 Tran'!K20+'[5]II-H-1.6 Tran'!K20 -> 450844.7 | ... O27: =+'[4]II-H-1.6 Tran'!O20+'[5]II-H-1.6 Tran'!O20 -> 357494.6 | P27: =SUM(D27:O27) -> 6224992.4 | Q27: ='II-H-4.1 Functions'!H27/'II-H-4.1 Tran kW'!P27 -> 1.6915213
A29: 10 | B29: LIGHTING | C29: SEC | P29: =SUM(D29:O29) -> 0
A31: 11 | B31: TOTAL RETAIL | D31: =D29+D27+D25+D21+D17+D15 -> 4032511.2 | E31: =E29+E27+E25+E21+E17+E15 -> 3769912.4 | F31: =F29+F27+F25+F21+F17+F15 -> 3707991 | G31: =G29+G27+G25+G21+G17+G15 -> 3537561.1 | H31: =H29+H27+H25+H21+H17+H15 -> 3691771.9 | I31: =I29+I27+I25+I21+I17+I15 -> 3902062.9 | J31: =J29+J27+J25+J21+J17+J15 -> 3706334.8 | K31: =K29+K27+K25+K21+K17+K15 -> 3751845.8 | ... P31: =P29+P27+P25+P21+P17+P15 -> 45063726
A33: 12 | B33: WHOLESALE PRI | C33: PRI | P33: =SUM(D33:O33) -> 0
A34: 13 | B34: WHOLESALE TRANS | C34: TRA | P34: =SUM(D34:O34) -> 0
A35: 14 | B35: TOTAL WHOLESALE | D35: =SUM(D33:D34) -> 0 | E35: =SUM(E33:E34) -> 0 | F35: =SUM(F33:F34) -> 0 | G35: =SUM(G33:G34) -> 0 | H35: =SUM(H33:H34) -> 0 | I35: =SUM(I33:I34) -> 0 | J35: =SUM(J33:J34) -> 0 | K35: =SUM(K33:K34) -> 0 | ... P35: =SUM(P33:P34) -> 0
A37: 15 | B37: TOTAL AEP TEXAS | D37: =+D35+D31 -> 4032511.2 | E37: =+E35+E31 -> 3769912.4 | F37: =+F35+F31 -> 3707991 | G37: =+G35+G31 -> 3537561.1 | H37: =+H35+H31 -> 3691771.9 | I37: =+I35+I31 -> 3902062.9 | J37: =+J35+J31 -> 3706334.8 | K37: =+K35+K31 -> 3751845.8 | ... P37: =+P35+P31 -> 45063726
B39: =+B8 -> AEP TEXAS
B40: KW WEATHER ADJUSTMENT
B41: =+B10 -> FOR TEST YEAR ENDED DECEMBER 31, 2018
A44: LINE | B44: DESCRIPTION | C44: VOLT | D44: =+D13 -> JANUARY | E44: =+E13 -> FEBRUARY | F44: =+F13 -> MARCH | G44: =+G13 -> APRIL | H44: =+H13 -> MAY | I44: =+I13 -> JUNE | J44: =+J13 -> JULY | K44: =+K13 -> AUGUST | ... P44: =+P13 -> TOTAL
A46: 1 | B46: RESIDENTIAL SERVICE | C46: SEC
A48: 2 | B48: SECONDARY < 10 kW | C48: SEC
A50: 3 | B50: SECONDARY > 10 kW NCP | C50: SEC | D50: =+'[4]II-H-1.6 Tran'!D43+'[5]II-H-1.6 Tran'!D44 -> -31514.853 | E50: =+'[4]II-H-1.6 Tran'!E43+'[5]II-H-1.6 Tran'!E44 -> -11048.872 | F50: =+'[4]II-H-1.6 Tran'!F43+'[5]II-H-1.6 Tran'!F44 -> -38327.117 | G50: =+'[4]II-H-1.6 Tran'!G43+'[5]II-H-1.6 Tran'!G44 -> -15656.652 | H50: =+'[4]II-H-1.6 Tran'!H43+'[5]II-H-1.6 Tran'!H44 -> 44739.678 | I50: =+'[4]II-H-1.6 Tran'!I43+'[5]II-H-1.6 Tran'!I44 -> -71933.397 | J50: =+'[4]II-H-1.6 Tran'!J43+'[5]II-H-1.6 Tran'!J44 -> 5962.341 | K50: =+'[4]II-H-1.6 Tran'!K43+'[5]II-H-1.6 Tran'!K44 -> 19916.635 | ... O50: =+'[4]II-H-1.6 Tran'!O43+'[5]II-H-1.6 Tran'!O44 -> 31437.29 | P50: =SUM(D50:O50) -> -3403.2813
A51: 4 | B51: SECONDARY > 10 kW 4CP | C51: SEC | D51: =+'[4]II-H-1.6 Tran'!D44+'[5]II-H-1.6 Tran'!D45 -> -2310.2062 | E51: =+'[4]II-H-1.6 Tran'!E44+'[5]II-H-1.6 Tran'!E45 -> -926.11569 | F51: =+'[4]II-H-1.6 Tran'!F44+'[5]II-H-1.6 Tran'!F45 -> -2586.534 | G51: =+'[4]II-H-1.6 Tran'!G44+'[5]II-H-1.6 Tran'!G45 -> -944.73036 | H51: =+'[4]II-H-1.6 Tran'!H44+'[5]II-H-1.6 Tran'!H45 -> 3117.3738 | I51: =+'[4]II-H-1.6 Tran'!I44+'[5]II-H-1.6 Tran'!I45 -> -5994.3914 | J51: =+'[4]II-H-1.6 Tran'!J44+'[5]II-H-1.6 Tran'!J45 -> -43.132452 | K51: =+'[4]II-H-1.6 Tran'!K44+'[5]II-H-1.6 Tran'!K45 -> 1354.017 | ... O51: =+'[4]II-H-1.6 Tran'!O44+'[5]II-H-1.6 Tran'!O45 -> 1789.3002 | P51: =SUM(D51:O51) -> -2337.2639
A52: 5 | B52: TOTAL SECONDARY > 10 kW | D52: =SUM(D50:D51) -> -33825.059 | E52: =SUM(E50:E51) -> -11974.988 | F52: =SUM(F50:F51) -> -40913.651 | G52: =SUM(G50:G51) -> -16601.382 | H52: =SUM(H50:H51) -> 47857.051 | I52: =SUM(I50:I51) -> -77927.788 | J52: =SUM(J50:J51) -> 5919.2085 | K52: =SUM(K50:K51) -> 21270.652 | ... P52: =SUM(P50:P51) -> -5740.5452
A54: 6 | B54: PRIMARY NCP | C54: PRI | D54: =+'[4]II-H-1.6 Tran'!D47+'[5]II-H-1.6 Tran'!D48 -> -4009.9581 | E54: =+'[4]II-H-1.6 Tran'!E47+'[5]II-H-1.6 Tran'!E48 -> -1290.7215 | F54: =+'[4]II-H-1.6 Tran'!F47+'[5]II-H-1.6 Tran'!F48 -> -6429.4269 | G54: =+'[4]II-H-1.6 Tran'!G47+'[5]II-H-1.6 Tran'!G48 -> -2931.6878 | H54: =+'[4]II-H-1.6 Tran'!H47+'[5]II-H-1.6 Tran'!H48 -> 8560.8078 | I54: =+'[4]II-H-1.6 Tran'!I47+'[5]II-H-1.6 Tran'!I48 -> -12772.613 | J54: =+'[4]II-H-1.6 Tran'!J47+'[5]II-H-1.6 Tran'!J48 -> 1073.3318 | K54: =+'[4]II-H-1.6 Tran'!K47+'[5]II-H-1.6 Tran'!K48 -> 3592.1903 | ... O54: =+'[4]II-H-1.6 Tran'!O47+'[5]II-H-1.6 Tran'!O48 -> 5541.5441 | P54: =SUM(D54:O54) -> 2662.7442
A55: 7 | B55: PRIMARY 4CP | C55: PRI | D55: =+'[4]II-H-1.6 Tran'!D48+'[5]II-H-1.6 Tran'!D49 -> 0 | E55: =+'[4]II-H-1.6 Tran'!E48+'[5]II-H-1.6 Tran'!E49 -> 0 | F55: =+'[4]II-H-1.6 Tran'!F48+'[5]II-H-1.6 Tran'!F49 -> 0 | G55: =+'[4]II-H-1.6 Tran'!G48+'[5]II-H-1.6 Tran'!G49 -> 0 | H55: =+'[4]II-H-1.6 Tran'!H48+'[5]II-H-1.6 Tran'!H49 -> 0 | I55: =+'[4]II-H-1.6 Tran'!I48+'[5]II-H-1.6 Tran'!I49 -> 0 | J55: =+'[4]II-H-1.6 Tran'!J48+'[5]II-H-1.6 Tran'!J49 -> 0 | K55: =+'[4]II-H-1.6 Tran'!K48+'[5]II-H-1.6 Tran'!K49 -> 0 | ... O55: =+'[4]II-H-1.6 Tran'!O48+'[5]II-H-1.6 Tran'!O49 -> 0 | P55: =SUM(D55:O55) -> 0
A56: 8 | B56: TOTAL PRIMARY | D56: =SUM(D54:D55) -> -4009.9581 | E56: =SUM(E54:E55) -> -1290.7215 | F56: =SUM(F54:F55) -> -6429.4269 | G56: =SUM(G54:G55) -> -2931.6878 | H56: =SUM(H54:H55) -> 8560.8078 | I56: =SUM(I54:I55) -> -12772.613 | J56: =SUM(J54:J55) -> 1073.3318 | K56: =SUM(K54:K55) -> 3592.1903 | ... P56: =SUM(P54:P55) -> 2662.7442
A58: 9 | B58: TRANSMISSION | C58: TRA | P58: =SUM(D58:O58) -> 0
A60: 10 | B60: LIGHTING | C60: SEC | P60: =SUM(D60:O60) -> 0
A62: 11 | B62: TOTAL RETAIL | D62: =D60+D58+D56+D52+D48+D46 -> -37835.018 | E62: =E60+E58+E56+E52+E48+E46 -> -13265.709 | F62: =F60+F58+F56+F52+F48+F46 -> -47343.078 | G62: =G60+G58+G56+G52+G48+G46 -> -19533.07 | H62: =H60+H58+H56+H52+H48+H46 -> 56417.859 | I62: =I60+I58+I56+I52+I48+I46 -> -90700.401 | J62: =J60+J58+J56+J52+J48+J46 -> 6992.5403 | K62: =K60+K58+K56+K52+K48+K46 -> 24862.843 | ... P62: =P60+P58+P56+P52+P48+P46 -> -3077.801
A64: 12 | B64: WHOLESALE PRI | C64: PRI | P64: =SUM(D64:O64) -> 0
A65: 13 | B65: WHOLESALE TRANS | C65: TRA | P65: =SUM(D65:O65) -> 0
A66: 14 | B66: TOTAL WHOLESALE | D66: =SUM(D64:D65) -> 0 | E66: =SUM(E64:E65) -> 0 | F66: =SUM(F64:F65) -> 0 | G66: =SUM(G64:G65) -> 0 | H66: =SUM(H64:H65) -> 0 | I66: =SUM(I64:I65) -> 0 | J66: =SUM(J64:J65) -> 0 | K66: =SUM(K64:K65) -> 0 | ... P66: =SUM(P64:P65) -> 0
A68: 15 | B68: =B37 -> TOTAL AEP TEXAS | D68: =+D66+D62 -> -37835.018 | E68: =+E66+E62 -> -13265.709 | F68: =+F66+F62 -> -47343.078 | G68: =+G66+G62 -> -19533.07 | H68: =+H66+H62 -> 56417.859 | I68: =+I66+I62 -> -90700.401 | J68: =+J66+J62 -> 6992.5403 | K68: =+K66+K62 -> 24862.843 | ... P68: =+P66+P62 -> -3077.801
B69: =+B8 -> AEP TEXAS
B70: KW CUSTOMER ADJUSTMENT
B71: =+B10 -> FOR TEST YEAR ENDED DECEMBER 31, 2018
A74: LINE | B74: DESCRIPTION | C74: VOLT | D74: =+D13 -> JANUARY | E74: =+E13 -> FEBRUARY | F74: =+F13 -> MARCH | G74: =+G13 -> APRIL | H74: =+H13 -> MAY | I74: =+I13 -> JUNE | J74: =+J13 -> JULY | K74: =+K13 -> AUGUST | ... O74: =+O13 -> DECEMBER | P74: TOTAL
A76: 1 | B76: RESIDENTIAL SERVICE | C76: SEC
A78: 2 | B78: SECONDARY < 10 kW | C78: SEC
A80: 3 | B80: SECONDARY > 10 kW NCP | C80: SEC | D80: =+'[5]II-H-1.6 Tran'!D75+'[4]II-H-1.6 Tran'!D73 -> 94497.45 | E80: =+'[5]II-H-1.6 Tran'!E75+'[4]II-H-1.6 Tran'!E73 -> 47124.189 | F80: =+'[5]II-H-1.6 Tran'!F75+'[4]II-H-1.6 Tran'!F73 -> 19765.4 | G80: =+'[5]II-H-1.6 Tran'!G75+'[4]II-H-1.6 Tran'!G73 -> 17040.731 | H80: =+'[5]II-H-1.6 Tran'!H75+'[4]II-H-1.6 Tran'!H73 -> 20888.858 | I80: =+'[5]II-H-1.6 Tran'!I75+'[4]II-H-1.6 Tran'!I73 -> 18868.653 | J80: =+'[5]II-H-1.6 Tran'!J75+'[4]II-H-1.6 Tran'!J73 -> 14412.393 | K80: =+'[5]II-H-1.6 Tran'!K75+'[4]II-H-1.6 Tran'!K73 -> 4232.478 | ... O80: =+'[5]II-H-1.6 Tran'!O75+'[4]II-H-1.6 Tran'!O73 -> 0 | P80: =SUM(D80:O80) -> 266594.38
A81: 4 | B81: SECONDARY > 10 kW 4CP | C81: SEC | D81: =+'[5]II-H-1.6 Tran'!D76+'[4]II-H-1.6 Tran'!D74 -> -10188.718 | E81: =+'[5]II-H-1.6 Tran'!E76+'[4]II-H-1.6 Tran'!E74 -> -10356.729 | F81: =+'[5]II-H-1.6 Tran'!F76+'[4]II-H-1.6 Tran'!F74 -> -10088.424 | G81: =+'[5]II-H-1.6 Tran'!G76+'[4]II-H-1.6 Tran'!G74 -> -8867.1782 | H81: =+'[5]II-H-1.6 Tran'!H76+'[4]II-H-1.6 Tran'!H74 -> -9664.5731 | I81: =+'[5]II-H-1.6 Tran'!I76+'[4]II-H-1.6 Tran'!I74 -> -6015.3243 | J81: =+'[5]II-H-1.6 Tran'!J76+'[4]II-H-1.6 Tran'!J74 -> -6604.3222 | K81: =+'[5]II-H-1.6 Tran'!K76+'[4]II-H-1.6 Tran'!K74 -> -7186.4882 | ... O81: =+'[5]II-H-1.6 Tran'!O76+'[4]II-H-1.6 Tran'!O74 -> 0 | P81: =SUM(D81:O81) -> -67800.704
A82: 5 | B82: TOTAL SECONDARY > 10 kW | D82: =SUM(D80:D81) -> 84308.732 | E82: =SUM(E80:E81) -> 36767.46 | F82: =SUM(F80:F81) -> 9676.9766 | G82: =SUM(G80:G81) -> 8173.5525 | H82: =SUM(H80:H81) -> 11224.285 | I82: =SUM(I80:I81) -> 12853.328 | J82: =SUM(J80:J81) -> 7808.0704 | K82: =SUM(K80:K81) -> -2954.0102 | ... P82: =SUM(P80:P81) -> 198793.68
A84: 6 | B84: PRIMARY NCP | C84: PRI | D84: =+'[5]II-H-1.6 Tran'!D79+'[4]II-H-1.6 Tran'!D77 -> 452.31243 | E84: =+'[5]II-H-1.6 Tran'!E79+'[4]II-H-1.6 Tran'!E77 -> 1232.499 | F84: =+'[5]II-H-1.6 Tran'!F79+'[4]II-H-1.6 Tran'!F77 -> 865.19185 | G84: =+'[5]II-H-1.6 Tran'!G79+'[4]II-H-1.6 Tran'!G77 -> 1511.4068 | H84: =+'[5]II-H-1.6 Tran'!H79+'[4]II-H-1.6 Tran'!H77 -> 1405.0797 | I84: =+'[5]II-H-1.6 Tran'!I79+'[4]II-H-1.6 Tran'!I77 -> 474.41279 | J84: =+'[5]II-H-1.6 Tran'!J79+'[4]II-H-1.6 Tran'!J77 -> 761.75863 | K84: =+'[5]II-H-1.6 Tran'!K79+'[4]II-H-1.6 Tran'!K77 -> -576.39885 | ... O84: =+'[5]II-H-1.6 Tran'!O79+'[4]II-H-1.6 Tran'!O77 -> 0 | P84: =SUM(D84:O84) -> 4778.8274
A85: 7 | B85: PRIMARY 4CP | C85: PRI | D85: =+'[5]II-H-1.6 Tran'!D80+'[4]II-H-1.6 Tran'!D78 -> 3601.4268 | E85: =+'[5]II-H-1.6 Tran'!E80+'[4]II-H-1.6 Tran'!E78 -> 2763.15 | F85: =+'[5]II-H-1.6 Tran'!F80+'[4]II-H-1.6 Tran'!F78 -> -5639.4472 | G85: =+'[5]II-H-1.6 Tran'!G80+'[4]II-H-1.6 Tran'!G78 -> 9392.1183 | H85: =+'[5]II-H-1.6 Tran'!H80+'[4]II-H-1.6 Tran'!H78 -> -4984.1618 | I85: =+'[5]II-H-1.6 Tran'!I80+'[4]II-H-1.6 Tran'!I78 -> -11532.557 | J85: =+'[5]II-H-1.6 Tran'!J80+'[4]II-H-1.6 Tran'!J78 -> -509.92578 | K85: =+'[5]II-H-1.6 Tran'!K80+'[4]II-H-1.6 Tran'!K78 -> 2672.8137 | ... O85: =+'[5]II-H-1.6 Tran'!O80+'[4]II-H-1.6 Tran'!O78 -> 0 | P85: =SUM(D85:O85) -> -9823.1633
A86: 8 | B86: TOTAL PRIMARY | D86: =SUM(D84:D85) -> 4053.7392 | E86: =SUM(E84:E85) -> 3995.649 | F86: =SUM(F84:F85) -> -4774.2553 | G86: =SUM(G84:G85) -> 10903.525 | H86: =SUM(H84:H85) -> -3579.0821 | I86: =SUM(I84:I85) -> -11058.145 | J86: =SUM(J84:J85) -> 251.83285 | K86: =SUM(K84:K85) -> 2096.4149 | ... P86: =SUM(P84:P85) -> -5044.3359
A88: 9 | B88: TRANSMISSION | C88: TRA | D88: =+'[5]II-H-1.6 Tran'!D83+'[4]II-H-1.6 Tran'!D81 -> -19126.202 | E88: =+'[5]II-H-1.6 Tran'!E83+'[4]II-H-1.6 Tran'!E81 -> 26342.159 | F88: =+'[5]II-H-1.6 Tran'!F83+'[4]II-H-1.6 Tran'!F81 -> 50301.251 | G88: =+'[5]II-H-1.6 Tran'!G83+'[4]II-H-1.6 Tran'!G81 -> 25729.677 | H88: =+'[5]II-H-1.6 Tran'!H83+'[4]II-H-1.6 Tran'!H81 -> 16622.538 | I88: =+'[5]II-H-1.6 Tran'!I83+'[4]II-H-1.6 Tran'!I81 -> 814.4625 | J88: =+'[5]II-H-1.6 Tran'!J83+'[4]II-H-1.6 Tran'!J81 -> 38919.296 | K88: =+'[5]II-H-1.6 Tran'!K83+'[4]II-H-1.6 Tran'!K81 -> 23514.526 | ... O88: =+'[5]II-H-1.6 Tran'!O83+'[4]II-H-1.6 Tran'!O81 -> 181652.69 | P88: =SUM(D88:O88) -> 346191.84
A90: 10 | B90: LIGHTING | C90: SEC | D90: =+'[5]II-H-1.6 Tran'!D85+'[4]II-H-1.6 Tran'!D83 -> 0 | E90: =+'[5]II-H-1.6 Tran'!E85+'[4]II-H-1.6 Tran'!E83 -> 0 | F90: =+'[5]II-H-1.6 Tran'!F85+'[4]II-H-1.6 Tran'!F83 -> 0 | G90: =+'[5]II-H-1.6 Tran'!G85+'[4]II-H-1.6 Tran'!G83 -> 0 | H90: =+'[5]II-H-1.6 Tran'!H85+'[4]II-H-1.6 Tran'!H83 -> 0 | I90: =+'[5]II-H-1.6 Tran'!I85+'[4]II-H-1.6 Tran'!I83 -> 0 | J90: =+'[5]II-H-1.6 Tran'!J85+'[4]II-H-1.6 Tran'!J83 -> 0 | K90: =+'[5]II-H-1.6 Tran'!K85+'[4]II-H-1.6 Tran'!K83 -> 0 | ... O90: =+'[5]II-H-1.6 Tran'!O85+'[4]II-H-1.6 Tran'!O83 -> 0 | P90: =SUM(D90:O90) -> 0
A92: 11 | B92: TOTAL RETAIL | D92: =D90+D88+D86+D82+D78+D76 -> 69236.27 | E92: =E90+E88+E86+E82+E78+E76 -> 67105.268 | F92: =F90+F88+F86+F82+F78+F76 -> 55203.972 | G92: =G90+G88+G86+G82+G78+G76 -> 44806.755 | H92: =H90+H88+H86+H82+H78+H76 -> 24267.74 | I92: =I90+I88+I86+I82+I78+I76 -> 2609.6461 | J92: =J90+J88+J86+J82+J78+J76 -> 46979.199 | K92: =K90+K88+K86+K82+K78+K76 -> 22656.931 | ... P92: =P90+P88+P86+P82+P78+P76 -> 539941.18
A94: 12 | B94: WHOLESALE PRI | C94: PRI | D94: =+'[5]II-H-1.6 Tran'!D89+'[4]II-H-1.6 Tran'!D87 -> 0 | E94: =+'[5]II-H-1.6 Tran'!E89+'[4]II-H-1.6 Tran'!E87 -> 0 | F94: =+'[5]II-H-1.6 Tran'!F89+'[4]II-H-1.6 Tran'!F87 -> 0 | G94: =+'[5]II-H-1.6 Tran'!G89+'[4]II-H-1.6 Tran'!G87 -> 0 | H94: =+'[5]II-H-1.6 Tran'!H89+'[4]II-H-1.6 Tran'!H87 -> 0 | I94: =+'[5]II-H-1.6 Tran'!I89+'[4]II-H-1.6 Tran'!I87 -> 0 | J94: =+'[5]II-H-1.6 Tran'!J89+'[4]II-H-1.6 Tran'!J87 -> 0 | K94: =+'[5]II-H-1.6 Tran'!K89+'[4]II-H-1.6 Tran'!K87 -> 0 | ... O94: =+'[5]II-H-1.6 Tran'!O89+'[4]II-H-1.6 Tran'!O87 -> 0 | P94: =SUM(D94:O94) -> 0
A95: 13 | B95: WHOLESALE TRANS | C95: TRA | P95: =SUM(D95:O95) -> 0
A96: 14 | B96: TOTAL WHOLESALE | D96: =SUM(D94:D95) -> 0 | E96: =SUM(E94:E95) -> 0 | F96: =SUM(F94:F95) -> 0 | G96: =SUM(G94:G95) -> 0 | H96: =SUM(H94:H95) -> 0 | I96: =SUM(I94:I95) -> 0 | J96: =SUM(J94:J95) -> 0 | K96: =SUM(K94:K95) -> 0 | ... P96: =SUM(P94:P95) -> 0
A98: 15 | B98: =B37 -> TOTAL AEP TEXAS | D98: =+D96+D92 -> 69236.27 | E98: =+E96+E92 -> 67105.268 | F98: =+F96+F92 -> 55203.972 | G98: =+G96+G92 -> 44806.755 | H98: =+H96+H92 -> 24267.74 | I98: =+I96+I92 -> 2609.6461 | J98: =+J96+J92 -> 46979.199 | K98: =+K96+K92 -> 22656.931 | ... P98: =+P96+P92 -> 539941.18
B99: =B69 -> AEP TEXAS
B100: OTHER KW ADJUSTMENTS
B101: =B71 -> FOR TEST YEAR ENDED DECEMBER 31, 2018
A104: LINE | B104: DESCRIPTION | C104: VOLT | D104: =D13 -> JANUARY | E104: =E13 -> FEBRUARY | F104: =F13 -> MARCH | G104: =G13 -> APRIL | H104: =H13 -> MAY | I104: =I13 -> JUNE | J104: =J13 -> JULY | K104: =K13 -> AUGUST | ... O104: =O13 -> DECEMBER | P104: TOTAL
A106: 1 | B106: RESIDENTIAL SERVICE | C106: SEC | P106: =SUM(D106:O106) -> 0
A108: 2 | B108: SECONDARY < 10 kW | C108: SEC | P108: =SUM(D108:O108) -> 0
A110: 3 | B110: SECONDARY > 10 kW NCP | C110: SEC | P110: =SUM(D110:O110) -> 0
A111: 4 | B111: SECONDARY > 10 kW 4CP | C111: SEC | P111: =SUM(D111:O111) -> 0
A112: 5 | B112: TOTAL SECONDARY > 10 kW | D112: =SUM(D110:D111) -> 0 | E112: =SUM(E110:E111) -> 0 | F112: =SUM(F110:F111) -> 0 | G112: =SUM(G110:G111) -> 0 | H112: =SUM(H110:H111) -> 0 | I112: =SUM(I110:I111) -> 0 | J112: =SUM(J110:J111) -> 0 | K112: =SUM(K110:K111) -> 0 | ... P112: =SUM(P110:P111) -> 0
A114: 6 | B114: PRIMARY NCP | C114: PRI | P114: =SUM(D114:O114) -> 0
A115: 7 | B115: PRIMARY 4CP | C115: PRI | P115: =SUM(D115:O115) -> 0
A116: 8 | B116: TOTAL PRIMARY | D116: =SUM(D114:D115) -> 0 | E116: =SUM(E114:E115) -> 0 | F116: =SUM(F114:F115) -> 0 | G116: =SUM(G114:G115) -> 0 | H116: =SUM(H114:H115) -> 0 | I116: =SUM(I114:I115) -> 0 | J116: =SUM(J114:J115) -> 0 | K116: =SUM(K114:K115) -> 0 | ... P116: =SUM(P114:P115) -> 0
A118: 9 | B118: TRANSMISSION | C118: TRA | P118: =SUM(D118:O118) -> 0
A120: 10 | B120: LIGHTING | C120: SEC | P120: =SUM(D120:O120) -> 0
A122: 11 | B122: TOTAL RETAIL | D122: =D120+D118+D116+D112+D108+D106 -> 0 | E122: =E120+E118+E116+E112+E108+E106 -> 0 | F122: =F120+F118+F116+F112+F108+F106 -> 0 | G122: =G120+G118+G116+G112+G108+G106 -> 0 | H122: =H120+H118+H116+H112+H108+H106 -> 0 | I122: =I120+I118+I116+I112+I108+I106 -> 0 | J122: =J120+J118+J116+J112+J108+J106 -> 0 | K122: =K120+K118+K116+K112+K108+K106 -> 0 | ... P122: =P120+P118+P116+P112+P108+P106 -> 0
A124: 12 | B124: WHOLESALE PRI | C124: PRI | P124: =SUM(D124:O124) -> 0
A125: 13 | B125: WHOLESALE TRANS | C125: TRA | P125: =SUM(D125:O125) -> 0
A126: 14 | B126: TOTAL WHOLESALE | D126: =SUM(D124:D125) -> 0 | E126: =SUM(E124:E125) -> 0 | F126: =SUM(F124:F125) -> 0 | G126: =SUM(G124:G125) -> 0 | H126: =SUM(H124:H125) -> 0 | I126: =SUM(I124:I125) -> 0 | J126: =SUM(J124:J125) -> 0 | K126: =SUM(K124:K125) -> 0 | ... P126: =SUM(P124:P125) -> 0
A128: 15 | B128: =B37 -> TOTAL AEP TEXAS | D128: =+D126+D122 -> 0 | E128: =+E126+E122 -> 0 | F128: =+F126+F122 -> 0 | G128: =+G126+G122 -> 0 | H128: =+H126+H122 -> 0 | I128: =+I126+I122 -> 0 | J128: =+J126+J122 -> 0 | K128: =+K126+K122 -> 0 | ... P128: =+P126+P122 -> 0
B130: =B8 -> AEP TEXAS
B131: ADJUSTED TRANSMISSION KW
B132: =B101 -> FOR TEST YEAR ENDED DECEMBER 31, 2018
A135: LINE | B135: DESCRIPTION | C135: VOLT | D135: =D13 -> JANUARY | E135: =E13 -> FEBRUARY | F135: =F13 -> MARCH | G135: =G13 -> APRIL | H135: =H13 -> MAY | I135: =I13 -> JUNE | J135: =J13 -> JULY | K135: =K13 -> AUGUST | ... O135: =O13 -> DECEMBER | P135: TOTAL
A137: 1 | B137: RESIDENTIAL SERVICE | C137: SEC
A139: 2 | B139: SECONDARY < 10 kW | C139: SEC
A141: 3 | B141: SECONDARY > 10 kW NCP | C141: SEC | D141: =D110+D80+D50+D19 -> 2599902.9 | E141: =E110+E80+E50+E19 -> 2522918.4 | F141: =F110+F80+F50+F19 -> 2319802.6 | G141: =G110+G80+G50+G19 -> 2261754.2 | H141: =H110+H80+H50+H19 -> 2396450.1 | I141: =I110+I80+I50+I19 -> 2429950.9 | J141: =J110+J80+J50+J19 -> 2470079.4 | K141: =K110+K80+K50+K19 -> 2508307.9 | ... O141: =O110+O80+O50+O19 -> 2411555.7 | P141: =SUM(D141:O141) -> 29307091
A142: 4 | B142: SECONDARY > 10 kW 4CP | C142: SEC | D142: =D111+D81+D51+D20 -> 180168.28 | E142: =E111+E81+E51+E20 -> 177103.76 | F142: =F111+F81+F51+F20 -> 178990.04 | G142: =G111+G81+G51+G20 -> 177633.89 | H142: =H111+H81+H51+H20 -> 185127.4 | I142: =I111+I81+I51+I20 -> 173902.88 | J142: =J111+J81+J51+J20 -> 185850.15 | K142: =K111+K81+K51+K20 -> 179460.13 | ... O142: =O111+O81+O51+O20 -> 188037.2 | P142: =SUM(D142:O142) -> 2191434
A143: 5 | B143: TOTAL SECONDARY > 10 kW | D143: =SUM(D141:D142) -> 2780071.2 | E143: =SUM(E141:E142) -> 2700022.2 | F143: =SUM(F141:F142) -> 2498792.6 | G143: =SUM(G141:G142) -> 2439388.1 | H143: =SUM(H141:H142) -> 2581577.5 | I143: =SUM(I141:I142) -> 2603853.7 | J143: =SUM(J141:J142) -> 2655929.6 | K143: =SUM(K141:K142) -> 2687768 | ... P143: =SUM(P141:P142) -> 31498526
A145: 6 | B145: PRIMARY NCP | C145: PRI | D145: =D114+D84+D54+D23 -> 52401.054 | E145: =E114+E84+E54+E23 -> 63827.178 | F145: =F114+F84+F54+F23 -> 52498.865 | G145: =G114+G84+G54+G23 -> 58727.319 | H145: =H114+H84+H54+H23 -> 77115.788 | I145: =I114+I84+I54+I23 -> 58040.4 | J145: =J114+J84+J54+J23 -> 68652.39 | K145: =K114+K84+K54+K23 -> 78446.391 | ... O145: =O114+O84+O54+O23 -> 70587.244 | P145: =SUM(D145:O145) -> 806479.37
A146: 7 | B146: PRIMARY 4CP | C146: PRI | D146: =D115+D85+D55+D24 -> 582027.83 | E146: =E115+E85+E55+E24 -> 563879.95 | F146: =F115+F85+F55+F24 -> 550450.65 | G146: =G115+G85+G55+G24 -> 546089.42 | H146: =H115+H85+H55+H24 -> 572923.14 | I146: =I115+I85+I55+I24 -> 560176.84 | J146: =J115+J85+J55+J24 -> 558114.37 | K146: =K115+K85+K55+K24 -> 558791.91 | ... O146: =O115+O85+O55+O24 -> 546207.1 | P146: =SUM(D146:O146) -> 6724400.4
A147: 8 | B147: TOTAL PRIMARY | D147: =SUM(D145:D146) -> 634428.88 | E147: =SUM(E145:E146) -> 627707.13 | F147: =SUM(F145:F146) -> 602949.52 | G147: =SUM(G145:G146) -> 604816.74 | H147: =SUM(H145:H146) -> 650038.93 | I147: =SUM(I145:I146) -> 618217.24 | J147: =SUM(J145:J146) -> 626766.76 | K147: =SUM(K145:K146) -> 637238.31 | ... P147: =SUM(P145:P146) -> 7530879.8
A149: 9 | B149: TRANSMISSION | C149: TRA | D149: =D118+D88+D58+D27 -> 649412.4 | E149: =E118+E88+E58+E27 -> 496022.66 | F149: =F118+F88+F58+F27 -> 614109.75 | G149: =G118+G88+G58+G27 -> 518629.98 | H149: =H118+H88+H58+H27 -> 540841.04 | I149: =I118+I88+I58+I27 -> 591901.16 | J149: =J118+J88+J58+J27 -> 477610.2 | K149: =K118+K88+K58+K27 -> 474359.23 | ... O149: =O118+O88+O58+O27 -> 539147.29 | P149: =SUM(D149:O149) -> 6571184.2
A151: 10 | B151: LIGHTING | C151: SEC | D151: =D120+D90+D60+D29 -> 0 | E151: =E120+E90+E60+E29 -> 0 | F151: =F120+F90+F60+F29 -> 0 | G151: =G120+G90+G60+G29 -> 0 | H151: =H120+H90+H60+H29 -> 0 | I151: =I120+I90+I60+I29 -> 0 | J151: =J120+J90+J60+J29 -> 0 | K151: =K120+K90+K60+K29 -> 0 | ... O151: =O120+O90+O60+O29 -> 0 | P151: =SUM(D151:O151) -> 0
A153: 11 | B153: TOTAL RETAIL | D153: =D151+D149+D147+D143+D139+D137 -> 4063912.5 | E153: =E151+E149+E147+E143+E139+E137 -> 3823752 | F153: =F151+F149+F147+F143+F139+F137 -> 3715851.9 | G153: =G151+G149+G147+G143+G139+G137 -> 3562834.8 | H153: =H151+H149+H147+H143+H139+H137 -> 3772457.5 | I153: =I151+I149+I147+I143+I139+I137 -> 3813972.1 | J153: =J151+J149+J147+J143+J139+J137 -> 3760306.5 | K153: =K151+K149+K147+K143+K139+K137 -> 3799365.6 | ... P153: =P151+P149+P147+P143+P139+P137 -> 45600590
A155: 12 | B155: WHOLESALE PRI | C155: PRI | D155: =D124+D94+D64+D33 -> 0 | E155: =E124+E94+E64+E33 -> 0 | F155: =F124+F94+F64+F33 -> 0 | G155: =G124+G94+G64+G33 -> 0 | H155: =H124+H94+H64+H33 -> 0 | I155: =I124+I94+I64+I33 -> 0 | J155: =J124+J94+J64+J33 -> 0 | K155: =K124+K94+K64+K33 -> 0 | ... O155: =O124+O94+O64+O33 -> 0 | P155: =SUM(D155:O155) -> 0
A156: 13 | B156: WHOLESALE TRANS | C156: TRA | P156: =SUM(D156:O156) -> 0
A157: 14 | B157: TOTAL WHOLESALE | D157: =SUM(D155:D156) -> 0 | E157: =SUM(E155:E156) -> 0 | F157: =SUM(F155:F156) -> 0 | G157: =SUM(G155:G156) -> 0 | H157: =SUM(H155:H156) -> 0 | I157: =SUM(I155:I156) -> 0 | J157: =SUM(J155:J156) -> 0 | K157: =SUM(K155:K156) -> 0 | ... P157: =SUM(P155:P156) -> 0
...

Sheet Sch II-H-4.2
B2: PUBLIC UTILITY COMMISSION OF TEXAS
B3: AEP TEXAS INC
B4: II-H-4.2 REVENUE CALCULATION METHODOLOGIES
B5: TEST YEAR ENDING 12/31/2018
B6: DOCKET NUMBER (PENDING ASSIGNMENT)
A9: Line | B9: Description
A10: 1 | B10: This schedule provides a narrative explanation fo the methodologies used to calculate the revenue
B11: items in RFP Schedule II-H-4.1. The following adjustments were made to the test year revenue
B12: data: (1) customer count adjustment; (2) weather adjustment; (3) removing rider revenues from
B13: electric sales revenue.
A15: 2 | B15: The customer count adjustment recognizes the changes in customer counts during the test year
B16: and adjusts the electric sales revenue and sales data as if the test-year ending customer count had
B17: been the constant value the entire twelve-month period. The adjusted customer counts and kWh
B18: associated kWh sales values are presented in RFP Schedule II-H-1.2 and RFP Schedule II-H-3.1.
B19: The resulting sales revenue adjustment provided in RFP Schedule II-H-4.1 reflects the change
B20: in customer count and kWh sales at the present tariff charge per customer or kWh.
A22: 3 | B22: The weather adjustment adjusts electric sales revenue and sales data as if the test year had
B23: experienced normal weather. AEP Texas witness Chad Burnett provided the weather adjusted kWh
B24: sales reflected in the RFP schedules. The adjustment to kWh sales are provided in RFP Schedule
B25: II-H-1.2 and the resulting sales revenue adjustment provided in RFP Schedule II-H-4.1 reflects the
B26: revenue change at the present tariff charge per kWh.
A28: 4 | B28: The adjustment that removes rider revenues from electric sales revenue exclude revnenues
B29: collected for specific purposes such as transition charges, energy efficiency cost recovery,
B30: transmission cost recovery, and nuclear decommissioning charges. The associated expenses
B31: incurred for these activities are not included in the distribution cost-of-service, thus, the revenues
B32: collected for these activities are also excluded.

Sheet Riders
B2: PUBLIC UTILITY COMMISSION OF TEXAS
B3: AEP TEXAS INC
B4: RIDERS
B5: TEST YEAR ENDING 12/31/2018
B6: DOCKET NUMBER (PENDING ASSIGNMENT)
B7: AEP TEXAS
B8: BILLED RIDER REVENUE
B9: FOR TEST YEAR ENDED DECEMBER 31, 2018
B11: AMS
A12: LINE | B12: DESCRIPTION | C12: VOLT | D12: JANUARY | E12: FEBRUARY | F12: MARCH | G12: APRIL | H12: MAY | I12: JUNE | J12: JULY | K12: AUGUST | L12: SEPTEMBER | M12: OCTOBER | N12: NOVEMBER | O12: DECEMBER | P12: TOTAL
A14: 1 | B14: RESIDENTIAL SERVICE | C14: SEC | D14: =[4]Riders!D8+[5]Riders!D8 -> 1976927.8 | E14: =[4]Riders!E8+[5]Riders!E8 -> 1973714 | F14: =[4]Riders!F8+[5]Riders!F8 -> 1976649.5 | G14: =[4]Riders!G8+[5]Riders!G8 -> 1980220.4 | H14: =[4]Riders!H8+[5]Riders!H8 -> 1983343.5 | I14: =[4]Riders!I8+[5]Riders!I8 -> 1985316.5 | J14: =[4]Riders!J8+[5]Riders!J8 -> 1987963.5 | K14: =[4]Riders!K8+[5]Riders!K8 -> 1985098.2 | ... O14: =[4]Riders!O8+[5]Riders!O8 -> 1988689.2 | P14: =SUM(D14:O14) -> 23799602
A16: 2 | B16: SECONDARY < 10 kW | C16: SEC | D16: =[4]Riders!D10+[5]Riders!D10 -> 373928.91 | E16: =[4]Riders!E10+[5]Riders!E10 -> 366619.4 | F16: =[4]Riders!F10+[5]Riders!F10 -> 365446.48 | G16: =[4]Riders!G10+[5]Riders!G10 -> 366824.55 | H16: =[4]Riders!H10+[5]Riders!H10 -> 367891.4 | I16: =[4]Riders!I10+[5]Riders!I10 -> 368761.36 | J16: =[4]Riders!J10+[5]Riders!J10 -> 369160.18 | K16: =[4]Riders!K10+[5]Riders!K10 -> 369335.63 | ... O16: =[4]Riders!O10+[5]Riders!O10 -> 370231.09 | P16: =SUM(D16:O16) -> 4429023.3
A18: 3 | B18: SECONDARY > 10 kW NCP | C18: SEC | D18: =[4]Riders!D12+[5]Riders!D12 -> 135939.76 | E18: =[4]Riders!E12+[5]Riders!E12 -> 138034.92 | F18: =[4]Riders!F12+[5]Riders!F12 -> 139488.57 | G18: =[4]Riders!G12+[5]Riders!G12 -> 139719.45 | H18: =[4]Riders!H12+[5]Riders!H12 -> 139491.53 | I18: =[4]Riders!I12+[5]Riders!I12 -> 139678.71 | J18: =[4]Riders!J12+[5]Riders!J12 -> 139767.8 | K18: =[4]Riders!K12+[5]Riders!K12 -> 139992.69 | ... O18: =[4]Riders!O12+[5]Riders!O12 -> 140133.9 | P18: =SUM(D18:O18) -> 1671203.2
A19: 4 | B19: SECONDARY > 10 kW 4CP | C19: SEC | D19: =[4]Riders!D13+[5]Riders!D13 -> 0 | E19: =[4]Riders!E13+[5]Riders!E13 -> 0 | F19: =[4]Riders!F13+[5]Riders!F13 -> 0 | G19: =[4]Riders!G13+[5]Riders!G13 -> 0 | H19: =[4]Riders!H13+[5]Riders!H13 -> 0 | I19: =[4]Riders!I13+[5]Riders!I13 -> 0 | J19: =[4]Riders!J13+[5]Riders!J13 -> 0 | K19: =[4]Riders!K13+[5]Riders!K13 -> 0 | ... O19: =[4]Riders!O13+[5]Riders!O13 -> 0 | P19: =SUM(D19:O19) -> 0
A20: 5 | B20: TOTAL SECONDARY > 10 kW | D20: =SUM(D18:D19) -> 135939.76 | E20: =SUM(E18:E19) -> 138034.92 | F20: =SUM(F18:F19) -> 139488.57 | G20: =SUM(G18:G19) -> 139719.45 | H20: =SUM(H18:H19) -> 139491.53 | I20: =SUM(I18:I19) -> 139678.71 | J20: =SUM(J18:J19) -> 139767.8 | K20: =SUM(K18:K19) -> 139992.69 | ... P20: =SUM(P18:P19) -> 1671203.2
A22: 6 | B22: PRIMARY NCP | C22: PRI | D22: =[4]Riders!D16+[5]Riders!D16 -> -1360.44 | E22: =[4]Riders!E16+[5]Riders!E16 -> -1333.7 | F22: =[4]Riders!F16+[5]Riders!F16 -> -1344.38 | G22: =[4]Riders!G16+[5]Riders!G16 -> -1340.89 | H22: =[4]Riders!H16+[5]Riders!H16 -> -1350.77 | I22: =[4]Riders!I16+[5]Riders!I16 -> -1335.72 | J22: =[4]Riders!J16+[5]Riders!J16 -> -1371.15 | K22: =[4]Riders!K16+[5]Riders!K16 -> -1367.35 | ... O22: =[4]Riders!O16+[5]Riders!O16 -> -1358.39 | P22: =SUM(D22:O22) -> -16292.98
A23: 7 | B23: PRIMARY 4CP | C23: PRI | D23: =[4]Riders!D17+[5]Riders!D17 -> 0 | E23: =[4]Riders!E17+[5]Riders!E17 -> 0 | F23: =[4]Riders!F17+[5]Riders!F17 -> 0 | G23: =[4]Riders!G17+[5]Riders!G17 -> 0 | H23: =[4]Riders!H17+[5]Riders!H17 -> 0 | I23: =[4]Riders!I17+[5]Riders!I17 -> 0 | J23: =[4]Riders!J17+[5]Riders!J17 -> 0 | K23: =[4]Riders!K17+[5]Riders!K17 -> 0 | ... O23: =[4]Riders!O17+[5]Riders!O17 -> 0 | P23: =SUM(D23:O23) -> 0
A24: 8 | B24: TOTAL PRIMARY | D24: =SUM(D22:D23) -> -1360.44 | E24: =SUM(E22:E23) -> -1333.7 | F24: =SUM(F22:F23) -> -1344.38 | G24: =SUM(G22:G23) -> -1340.89 | H24: =SUM(H22:H23) -> -1350.77 | I24: =SUM(I22:I23) -> -1335.72 | J24: =SUM(J22:J23) -> -1371.15 | K24: =SUM(K22:K23) -> -1367.35 | ... P24: =SUM(P22:P23) -> -16292.98
A26: 9 | B26: TRANSMISSION | C26: TRA | D26: 0 | E26: 0 | F26: 0 | G26: 0 | H26: 0 | I26: 0 | J26: 0 | K26: 0 | L26: 0 | M26: 0 | N26: 0 | O26: 0 | P26: =SUM(D26:O26) -> 0
A28: 10 | B28: LIGHTING | C28: SEC | D28: 0 | E28: 0 | F28: 0 | G28: 0 | H28: 0 | I28: 0 | J28: 0 | K28: 0 | L28: 0 | M28: 0 | N28: 0 | O28: 0 | P28: =SUM(D28:O28) -> 0
A30: 11 | B30: TOTAL RETAIL | D30: =D28+D26+D24+D20+D16+D14 -> 2485436 | E30: =E28+E26+E24+E20+E16+E14 -> 2477034.6 | F30: =F28+F26+F24+F20+F16+F14 -> 2480240.2 | G30: =G28+G26+G24+G20+G16+G14 -> 2485423.5 | H30: =H28+H26+H24+H20+H16+H14 -> 2489375.7 | I30: =I28+I26+I24+I20+I16+I14 -> 2492420.9 | J30: =J28+J26+J24+J20+J16+J14 -> 2495520.4 | K30: =K28+K26+K24+K20+K16+K14 -> 2493059.2 | ... P30: =P28+P26+P24+P20+P16+P14 -> 29883535
A32: 12
A33: 13
A34: 14
A36: 15 | B36: TOTAL | D36: =+D34+D30 -> 2485436 | E36: =+E34+E30 -> 2477034.6 | F36: =+F34+F30 -> 2480240.2 | G36: =+G34+G30 -> 2485423.5 | H36: =+H34+H30 -> 2489375.7 | I36: =+I34+I30 -> 2492420.9 | J36: =+J34+J30 -> 2495520.4 | K36: =+K34+K30 -> 2493059.2 | ... P36: =+P34+P30 -> 29883535
B39: EECRF
A40: LINE | B40: DESCRIPTION | C40: VOLT | D40: JANUARY | E40: FEBRUARY | F40: MARCH | G40: APRIL | H40: MAY | I40: JUNE | J40: JULY | K40: AUGUST | L40: SEPTEMBER | M40: OCTOBER | N40: NOVEMBER | O40: DECEMBER | P40: TOTAL
A42: 1 | B42: RESIDENTIAL SERVICE | C42: SEC | D42: =[4]Riders!D36+[5]Riders!D62 -> 615110.37 | E42: =[4]Riders!E36+[5]Riders!E62 -> 455754.72 | F42: =[4]Riders!F36+[5]Riders!F62 -> 403259.11 | G42: =[4]Riders!G36+[5]Riders!G62 -> 424731.2 | H42: =[4]Riders!H36+[5]Riders!H62 -> 471365.34 | I42: =[4]Riders!I36+[5]Riders!I62 -> 719576.43 | J42: =[4]Riders!J36+[5]Riders!J62 -> 753708.91 | K42: =[4]Riders!K36+[5]Riders!K62 -> 764935.83 | ... O42: =[4]Riders!O36+[5]Riders!O62 -> 493167.19 | P42: =SUM(D42:O42) -> 6852076.5
