Workbook
Name \M: #REF!
Name _asd2: '[1]O & M'!$T$5
Name _M: #REF!
Name Account: [2]Source!#REF!
Name Account2: [2]Source!#REF!
Name AccountDescr: [2]Source!#REF!
Name AccountDescr2: [2]Source!#REF!
Name Activity: [2]Source!#REF!
Name Activity2: [2]Source!#REF!
Name ActivityDescr: [2]Source!#REF!
Name ActivityDescr2: [2]Source!#REF!
Name Affiliate: [2]Source!#REF!
Name Affiliate2: [2]Source!#REF!
Name AffiliateDescr: [2]Source!#REF!
Name ASD: '[3]O & M'!$T$5
Name Completed: '[4]FIT Paid - Combined'!$AO$5
Name completed2: '[5]FIT Paid - Combined'!$AO$5
Name Credit: [6]JOURNAL!#REF!
Name Debit: [6]JOURNAL!#REF!
Name DeptDescr: [2]Source!#REF!
Name DeptDescr2: [2]Source!#REF!
Name DeptID: [2]Source!#REF!
Name DeptID2: [2]Source!#REF!
Name EC: [2]Source!#REF!
Name ECDescr: [2]Source!#REF!
Name ECDescr2: [2]Source!#REF!
Name ECID: [2]Source!#REF!
Name Elapsed: '[4]FIT Paid - Combined'!$AO$4
Name entry: [6]JOURNAL!$B$9:$R$353,[6]JOURNAL!$I$3,[6]JOURNAL!$G$3,[6]JOURNAL!$E$3,[6]JOURNAL!$B$7,[6]JOURNAL!$B$3
Name EntryFields: [6]JOURNAL!$B$9:$R$353,[6]JOURNAL!$I$3,[6]JOURNAL!$G$3,[6]JOURNAL!$E$3,[6]JOURNAL!$B$7,[6]JOURNAL!$B$3
Name FFT: #REF!
Name KeyControlFigure: '[4]FIT Paid - Combined'!$T$399
Name Lines: [6]JOURNAL!#REF!
Name Location: [2]Source!#REF!
Name Location2: [2]Source!#REF!
Name LocationDescr: [2]Source!#REF!
Name LocationDescr2: [2]Source!#REF!
Name MENU: #REF!
Name NvsASD: "V2000-12-31"
Name NvsAutoDrillOk: "VN"
Name NvsElapsedTime: 0.000582986111112405
Name NvsElapsedTime: 0.000689467597112525
Name NvsEndTime: 36257.3051395833
Name NvsEndTime: 36923.3059673611
Name NvsInstSpec: "%"
Name NvsLayoutType: "M3"
Name NvsNplSpec: "%,X,RZF..nPlosion,CZF.."
Name NvsPanelEffdt: "V1998-01-01"
Name NvsPanelSetid: "VSHARE"
Name NvsParentRef: [7]Sheet1!$T$303
Name NvsReqBU: "VGEN"
Name NvsReqBU: "VLSGD"
Name NvsReqBUOnly: "VY"
Name NvsTransLed: "VN"
Name NvsTreeASD: "V2000-12-31"
Name NvsValTbl.ACCOUNT: "GL_ACCOUNT_TBL"
Name NvsValTbl.AFFILIATE: "BUS_UNIT_TBL_FS"
Name NvsValTbl.CURRENCY_CD: "CURRENCY_CD_TBL"
Name NvsValTbl.DEPTID: "DEPARTMENT_TBL"
Name NvsValTbl.TU_LOCATION: "TU_LOC_TBL"

Sheet  
A1: 2025 RATE CASE
A2: ONCOR ELECTRIC DELIVERY COMPANY LLC
A3: LEAD-LAG STUDY RESULTS
A4: FOR THE TEST-YEAR ENDING DECEMBER 31, 2024
A5: SPONSOR: A. THENMADATHIL
A7: Line | C7: Revenue | D7: Expense
A8: No. | B8: Description | C8: Lag Days* | D8: Lead Days | E8: Reference
B9: (a) | C9: (b) | D9: (c) | E9: `
A11: 1 | B11: Operation & Maintenance Expenses
A12: =A11+1 -> 2 | B12: Labor
A13: =A12+1 -> 3 | B13: Payroll | C13: =+'1'!H14 -> 53.27 | D13: =+'2'!J18 -> -12 | E13: WP/II-B-9/2
A14: =A13+1 -> 4 | B14: Incentive Pay | C14: =+$C$13 -> 53.27 | D14: ='3'!J17 -> -255.74549 | E14: WP/II-B-9/3
A15: =A14+1 -> 5
A16: =A15+1 -> 6 | B16: Non-Labor
A17: =A16+1 -> 7 | B17: Affiliate Charges - Sempra | C17: =+$C$13 -> 53.27 | D17: =+'4'!K24 -> -45.17 | E17: WP/II-B-9/4
A18: =A17+1 -> 8 | B18: Affiliate Charges - Other | C18: =+$C$13 -> 53.27 | D18: =+'6'!D17 -> -48.81 | E18: WP/II-B-9/6
A19: =A18+1 -> 9 | B19: TCOS
A20: =A19+1 -> 10 | B20: Oncor | C20: 0 | D20: 0 | E20: N/A
A21: =A20+1 -> 11 | B21: Non-Oncor | C21: =+$C$13 -> 53.27 | D21: ='5'!E16 -> -50.22 | E21: WP/II-B-9/5
A22: =A21+1 -> 12 | B22: Amortized O&M Expenses | C22: 0 | D22: 0 | E22: N/A
A23: =A22+1 -> 13 | B23: Other O&M | C23: =+$C$13 -> 53.27 | D23: ='6'!D17 -> -48.81 | E23: WP/II-B-9/6
A24: =A23+1 -> 14 | B24: Pension & Supplemental Retirement Benefits | C24: =+$C$13 -> 53.27 | D24: =+'6-4'!I36 -> -57.434985 | E24: WP/II-B-9/6-4
A25: =A24+1 -> 15 | B25: Other Post-Employment Benefits | C25: =+$C$13 -> 53.27 | D25: ='6-5'!I23 -> 10.665188 | E25: WP/II-B-9/6-5
A26: =A25+1 -> 16
A27: =A26+1 -> 17 | B27: Federal Income Taxes
A28: =A27+1 -> 18 | B28: Current | C28: =+$C$13 -> 53.27 | D28: =+'7'!F20 -> -37.5 | E28: WP/II-B-9/7
A29: =A28+1 -> 19 | B29: Deferred | C29: 0 | D29: 0 | E29: N/A
A30: =A29+1 -> 20
A31: =A30+1 -> 21 | B31: Taxes Other Than Income Taxes
A32: =A31+1 -> 22 | B32: Payroll Taxes | C32: =+$C$13 -> 53.27 | D32: =+'8'!D16 -> -11.47 | E32: WP/II-B-9/8
A33: =A32+1 -> 23 | B33: State Gross Margin Taxes | C33: =+$C$13 -> 53.27 | D33: =+'9'!F23 -> 46.25 | E33: WP/II-B-9/9
A34: =A33+1 -> 24 | B34: Local Franchise Taxes | C34: =+$C$13 -> 53.27 | D34: ='10'!F37 -> -58.48 | E34: WP/II-B-9/10
A35: =A34+1 -> 25 | B35: Ad Valorem Taxes | C35: =+$C$13 -> 53.27 | D35: =+'11'!G37 -> -212.48 | E35: WP/II-B-9/11
A36: =A35+1 -> 26
A37: =A36+1 -> 27 | B37: Depreciation Expense | C37: 0 | D37: 0 | E37: N/A
A38: =A37+1 -> 28
A39: =A38+1 -> 29 | B39: Return | C39: 0 | D39: 0 | E39: N/A
A40: =A39+1 -> 30
A41: =A40+1 -> 31 | B41: Average Daily Bank Balances | D41: =+'12'!J26 -> 2149754 | E41: WP/II-B-9/12
A42: =A41+1 -> 32 | B42: Working Funds and Other | D42: ='13'!C16 -> -3435810 | E42: WP/II-B-9/13
A43: =A42+1 -> 33
A44: =A43+1 -> 34 | B44: Prepaid Affiliate Charges - Other | D44: =+'14'!F29 -> 117329.1 | E44: WP/II-B-9/14
A45: =A44+1 -> 35 | B45: Prepaid Non-labor (Third Party) O&M | D45: =+'14'!F30 -> 77154334 | E45: WP/II-B-9/14
A46: =A45+1 -> 36 | B46: Prepaid Local Franchise Tax | D46: =+'15'!E14 -> 217503701 | E46: WP/II-B-9/15
A47: =A46+1 -> 37
A48: =A47+1 -> 38 | B48: * WP/II-B-9/1

Sheet 1
A1: 2025 RATE CASE
A2: =' '!A2 -> ONCOR ELECTRIC DELIVERY COMPANY LLC
A3: OVERALL REVENUE LAG
A4: FOR THE LEAD-LAG STUDY-PERIOD ENDING SEPTEMBER 30, 2024
A5: SPONSOR: A. THENMADATHIL
A7: Line No. | C7: Revenue Type | E7: Revenues | F7: Ref | H7: Revenue Lag Days | I7: Ref | J7: Wtd Dollar Days
C8: (a) | E8: (b) | F8: (c) | H8: (d) | I8: (e) | J8: (f)
A10: 1 | C10: CC&B | E10: 4.9545563e+09 | F10: (1) | H10: =+'1-1'!E20 -> 53.14 | I10: WP/II-B-9/1-1 | J10: =H10*E10 -> 2.6328512e+11
A11: 2
A12: 3 | C12: FIM | E12: 4.3858816e+08 | F12: (2) | H12: =+'1-1'!H20 -> 54.782667 | I12: WP/II-B-9/1-1 | J12: =+H12*E12 -> 2.4027029e+10
A13: 4
A14: 5 | C14: Total | E14: =SUM(E10:E12) -> 5.3931445e+09 | H14: =ROUND(J14/E14,2) -> 53.27 | J14: =SUM(J10:J12) -> 2.8731215e+11
A15: 6
A16: 7 | C16: Sources: | D16: (1) | E16: CC&B Revenue.xlsx
A17: 8 | D17: (2) | E17: FIM Revenue.xlsx

Sheet 1-1
A1: 2025 RATE CASE
A2: =' '!A2 -> ONCOR ELECTRIC DELIVERY COMPANY LLC
A3: REVENUE LAG BY REVENUE TYPE
A4: FOR THE LEAD-LAG STUDY-PERIOD ENDING SEPTEMBER 30, 2024
A5: SPONSOR: A. THENMADATHIL
A7: Line No. | C7: Description | E7: CC&B | F7: Reference | H7: FIM | I7: Reference
C8: (a) | E8: (b) | F8: (c) | H8: (d) | I8: (e)
A10: 1 | C10: Average service period
A11: =A10+1 -> 2 | C11: (365.25 days/12 months)/2 | E11: =ROUND(365.25/12/2,3) -> 15.219 | H11: =ROUND(365.25/12/2,3) -> 15.219
A12: =A11+1 -> 3
A13: =A12+1 -> 4 | C13: Billing Process Lag | E13: =+'1-1-2'!D20 -> 3 | F13: WP/II-B-9/1-1-2 | H13: =+'1-1-2'!D20 -> 3 | I13: WP/II-B-9/1-1-2
A14: =A13+1 -> 5
A15: =A14+1 -> 6 | C15: Collection Lag | E15: =+'1-1-3'!E14 -> 34.921 | F15: WP/II-B-9/1-1-3 | H15: 36.563667 | I15: (1)
A16: =A15+1 -> 7
A17: =A16+1 -> 8 | C17: Receipt of funds lag | E17: 0 | H17: 0
A18: =A17+1 -> 9
A19: =A18+1 -> 10
A20: =A19+1 -> 11 | C20: Operating Revenues Lag Days | E20: =SUM(E11:E18) -> 53.14 | H20: =SUM(H11:H18) -> 54.782667
A21: =A20+1 -> 12
A22: =A21+1 -> 13 | C22: Source: | D22: (1) | E22: FIM Revenue.xlsx

Sheet 1-1-2
A1: 2025 RATE CASE
A2: =' '!A2 -> ONCOR ELECTRIC DELIVERY COMPANY LLC
A3: BILLING LAG
A4: FOR THE LEAD-LAG STUDY-PERIOD ENDING SEPTEMBER 30, 2024
A5: SPONSOR: A. THENMADATHIL
A7: Line No. | B7: Description | C7: Hours | D7: Days | E7: Reference
B8: (a) | C8: (b) | D8: (c) | E8: (d)
A10: 1 | B10: Period from Meter Reading Date to Invoice Date:
A11: =+A10+1 -> 2
A12: =+A11+1 -> 3 | B12: Calculated from invoice sample | D12: =+'1-1-2-1'!I133 -> 2.25 | E12: WP/II-B-9/1-1-2-1
A13: =+A12+1 -> 4
A14: =+A13+1 -> 5
A15: =+A14+1 -> 6 | B15: Invoicing Period
A16: =+A15+1 -> 7
A17: =+A16+1 -> 8 | B17: Start at midnight and end at 6 p.m. | C17: 18 | D17: =+C17/24 -> 0.75
A18: =+A17+1 -> 9
A19: =+A18+1 -> 10
A20: =+A19+1 -> 11 | B20: Total Billing Lag Days | D20: =SUM(D10:D17) -> 3

Sheet 1-1-2-1
A1: 2025 RATE CASE
A2: =' '!A2 -> ONCOR ELECTRIC DELIVERY COMPANY LLC
A3: REVENUE LAG - CALCULATION OF LAG DAYS FROM METER READ TO INVOICE (INVOICE SAMPLE RESULTS)
A4: FOR THE LEAD-LAG STUDY-PERIOD ENDING SEPTEMBER 30, 2024
A5: SPONSOR: A. THENMADATHIL
A7: Line No. | C7: Invoice Number | E7: Meter Read Date | F7: Meter Read Day of Week | G7: Invoice Date | I7: Lag Days from Meter Read to Invoice
C8: (a) | E8: (b) | F8: (c) | G8: (d) | I8: (e)
A10: 1 | C10: 8100043205069255144Z12 | E10: 45549 | F10: SATURDAY | G10: 45551 | I10: =+G10-E10 -> 2
A11: 2 | C11: 8100062363011579138Z11 | E11: 45440 | F11: TUESDAY | G11: 45441 | I11: =+G11-E11 -> 1
A12: 3 | C12: 8100024471742069054Z10 | E12: 45199 | F12: SATURDAY | G12: 45201 | I12: =+G12-E12 -> 2
A13: 4 | C13: 8100032714029819322Z11 | E13: 45507 | F13: SATURDAY | G13: 45509 | I13: =+G13-E13 -> 2
A14: 5 | C14: 8100074884162602514Z12 | E14: 45278 | F14: MONDAY | G14: 45279 | I14: =+G14-E14 -> 1
A15: 6 | C15: 8100057637848476372Z11 | E15: 45396 | F15: SUNDAY | G15: 45397 | I15: =+G15-E15 -> 1
A16: 7 | C16: 8100058052947228795Z11 | E16: 45445 | F16: SUNDAY | G16: 45446 | I16: =+G16-E16 -> 1
A17: 8 | C17: 8100087036466151487Z10 | E17: 45248 | F17: SATURDAY | G17: 45250 | I17: =+G17-E17 -> 2
A18: 9 | C18: 8100018086801149832Z11 | E18: 45395 | F18: SATURDAY | G18: 45397 | I18: =+G18-E18 -> 2
A19: 10 | C19: 8100089945249242888Z12 | E19: 45481 | F19: MONDAY | G19: 45482 | I19: =+G19-E19 -> 1
A20: 11 | C20: 8100002485754879007Z11 | E20: 45213 | F20: SATURDAY | G20: 45215 | I20: =+G20-E20 -> 2
A21: 12 | C21: 8100090319583189668Z12 | E21: 45409 | F21: SATURDAY | G21: 45411 | I21: =+G21-E21 -> 2
... A129: 120 | C129: 8100035760543093937Z11 | E129: 45199 | F129: SATURDAY | G129: 45201 | I129: =+G129-E129 -> 2
A130: 121
A131: 122 | C131: Total | I131: =SUM(I10:I129) -> 270
A132: 123
A133: 124 | C133: Average | I133: =+I131/A129 -> 2.25
A134: 125
A135: 126
A136: 127 | C136: Source: | E136: Revenue billing sample.xlsx

Sheet 1-1-3
A1: 2025 RATE CASE
A2: =' '!A2 -> ONCOR ELECTRIC DELIVERY COMPANY LLC
A3: CALCULATION OF COLLECTION LAG
A4: FOR THE LEAD-LAG STUDY-PERIOD ENDING SEPTEMBER 30, 2024
A5: SPONSOR: A. THENMADATHIL
A7: Line
A8: No. | B8: Description | C8: Reference | D8: Amount | E8: Collection Lag Days
B9: (a) | C9: (b) | D9: (c) | E9: (d)
A11: 1 | B11: Total Accounts Receivable | C11: WP/II-B-9/1-1-3-1 | D11: =+'1-1-3-1'!D25 -> 1.730205e+11
A12: 2 | B12: Revenues | C12: CC&B Revenue.xlsx | D12: 4.9545563e+09
A13: 3
A14: 4 | B14: Collection Lag (Line 1/Line 2) | E14: =ROUND(D11/D12,3) -> 34.921

Sheet 1-1-3-1
A1: 2025 RATE CASE
A2: =' '!A2 -> ONCOR ELECTRIC DELIVERY COMPANY LLC
A3: COLLECTION LAG
A4: FOR THE LEAD-LAG STUDY-PERIOD ENDING SEPTEMBER 30, 2024
A5: SPONSOR: A. THENMADATHIL
A7: Line
A8: No. | B8: Description | D8: Monthly Total
B9: (a) | D9: (b)
A11: 1 | B11: Sum of CC&B Daily A/R Balances
A12: 2 | B12: 45200 | D12: =+'1-1-3-1-1'!C41 -> 1.6587049e+10
A13: 3 | B13: 45231 | D13: =+'1-1-3-1-1'!E41 -> 1.3500263e+10
A14: 4 | B14: 45261 | D14: =+'1-1-3-1-1'!G41 -> 1.2938964e+10
A15: 5 | B15: 45292 | D15: =+'1-1-3-1-1'!C76 -> 1.369932e+10
A16: 6 | B16: 45323 | D16: =+'1-1-3-1-1'!E76 -> 1.5108631e+10
A17: 7 | B17: 45352 | D17: =+'1-1-3-1-1'!G76 -> 1.3348486e+10
A18: 8 | B18: 45383 | D18: =+'1-1-3-1-1'!C111 -> 1.145409e+10
A19: 9 | B19: 45413 | D19: =+'1-1-3-1-1'!E111 -> 1.2366701e+10
A20: 10 | B20: 45444 | D20: =+'1-1-3-1-1'!G111 -> 1.313313e+10
A21: 11 | B21: 45474 | D21: =+'1-1-3-1-1'!C146 -> 1.6062645e+10
A22: 12 | B22: 45505 | D22: =+'1-1-3-1-1'!E146 -> 1.7522719e+10
A23: 13 | B23: 45536 | D23: =+'1-1-3-1-1'!G146 -> 1.7298505e+10
A24: 14
A25: 15 | B25: Total Accounts Receivable | D25: =SUM(D12:D24) -> 1.730205e+11
A26: 16
A27: 17 | B27: Source: WP/II-B-9/1-1-3-1-1

Sheet 1-1-3-1-1
A1: 2025 RATE CASE
A2: ='1'!A2 -> ONCOR ELECTRIC DELIVERY COMPANY LLC
A3: CUSTOMER INFORMATION SYSTEM DAILY ACCOUNTS RECEIVABLE
A4: FOR THE LEAD-LAG STUDY-PERIOD ENDING SEPTEMBER 30, 2024
A5: SPONSOR: A. THENMADATHIL
A7: Line No. | B7: Date | C7: A/R Balance | D7: Date | E7: A/R Balance | F7: Date | G7: A/R Balance
B8: (a) | C8: (b) | D8: (c) | E8: (d) | F8: (e) | G8: (f)
A10: 1 | B10: 45200 | C10: 5.8288559e+08 | D10: =+B40+1 -> 45231 | E10: 4.991696e+08 | F10: =+D39+1 -> 45261 | G10: 3.8997668e+08
A11: =A10+1 -> 2 | B11: =+B10+1 -> 45201 | C11: 5.8288559e+08 | D11: =+D10+1 -> 45232 | E11: 4.8524353e+08 | F11: =+F10+1 -> 45262 | G11: 4.099081e+08
A12: =A11+1 -> 3 | B12: =+B11+1 -> 45202 | C12: 5.8876055e+08 | D12: =+D11+1 -> 45233 | E12: 4.8431528e+08 | F12: =+F11+1 -> 45263 | G12: 4.099081e+08
A13: =A12+1 -> 4 | B13: =+B12+1 -> 45203 | C13: 5.8770522e+08 | D13: =+D12+1 -> 45234 | E13: 4.8431528e+08 | F13: =+F12+1 -> 45264 | G13: 4.1019937e+08
A14: =A13+1 -> 5 | B14: =+B13+1 -> 45204 | C14: 5.8770522e+08 | D14: =+D13+1 -> 45235 | E14: 4.8431528e+08 | F14: =+F13+1 -> 45265 | G14: 4.1444652e+08
A15: =A14+1 -> 6 | B15: =+B14+1 -> 45205 | C15: 5.5665051e+08 | D15: =+D14+1 -> 45236 | E15: 4.7455429e+08 | F15: =+F14+1 -> 45266 | G15: 4.1209659e+08
A16: =A15+1 -> 7 | B16: =+B15+1 -> 45206 | C16: 5.5665051e+08 | D16: =+D15+1 -> 45237 | E16: 4.7595258e+08 | F16: =+F15+1 -> 45267 | G16: 4.1080649e+08
A17: =A16+1 -> 8 | B17: =+B16+1 -> 45207 | C17: 5.5665051e+08 | D17: =+D16+1 -> 45238 | E17: 4.6962688e+08 | F17: =+F16+1 -> 45268 | G17: 4.1127055e+08
A18: =A17+1 -> 9 | B18: =+B17+1 -> 45208 | C18: 5.817128e+08 | D18: =+D17+1 -> 45239 | E18: 4.6408745e+08 | F18: =+F17+1 -> 45269 | G18: 4.1127055e+08
A19: =A18+1 -> 10 | B19: =+B18+1 -> 45209 | C19: 5.7397055e+08 | D19: =+D18+1 -> 45240 | E19: 4.6703473e+08 | F19: =+F18+1 -> 45270 | G19: 4.1127055e+08
A20: =A19+1 -> 11 | B20: =+B19+1 -> 45210 | C20: 5.7062726e+08 | D20: =+D19+1 -> 45241 | E20: 4.6703473e+08 | F20: =+F19+1 -> 45271 | G20: 4.1178704e+08
A21: =A20+1 -> 12 | B21: =+B20+1 -> 45211 | C21: 5.576829e+08 | D21: =+D20+1 -> 45242 | E21: 4.6703473e+08 | F21: =+F20+1 -> 45272 | G21: 4.1268056e+08
A22: =A21+1 -> 13 | B22: =+B21+1 -> 45212 | C22: 5.394778e+08 | D22: =+D21+1 -> 45243 | E22: 4.6032428e+08 | F22: =+F21+1 -> 45273 | G22: 4.1113205e+08
... A39: =A38+1 -> 30 | B39: =+B38+1 -> 45229 | C39: 4.8181089e+08 | D39: =+D38+1 -> 45260 | E39: 3.7863746e+08 | F39: =+F38+1 -> 45290 | G39: 4.2088558e+08
A40: =A39+1 -> 31 | B40: =+B39+1 -> 45230 | C40: 4.9620935e+08 | F40: =+F39+1 -> 45291 | G40: 4.2088558e+08
A41: =A40+1 -> 32 | C41: =SUM(C10:C40) -> 1.6587049e+10 | E41: =SUM(E10:E40) -> 1.3500263e+10 | G41: =SUM(G10:G40) -> 1.2938964e+10
A42: Line No. | B42: Date | C42: A/R Balance | D42: Date | E42: A/R Balance | F42: Date | G42: A/R Balance
B43: (a) | C43: (b) | D43: (c) | E43: (d) | F43: (e) | G43: (f)
A45: =A41+1 -> 33 | B45: =+F40+1 -> 45292 | C45: 4.2088558e+08 | D45: =+B75+1 -> 45323 | E45: 4.978564e+08 | F45: =+D73+1 -> 45352 | G45: 4.8043735e+08
A46: =A45+1 -> 34 | B46: =+B45+1 -> 45293 | C46: 4.3035146e+08 | D46: =+D45+1 -> 45324 | E46: 5.1189052e+08 | F46: =+F45+1 -> 45353 | G46: 4.8043735e+08
A47: =A46+1 -> 35 | B47: =+B46+1 -> 45294 | C47: 4.3434088e+08 | D47: =+D46+1 -> 45325 | E47: 5.1189052e+08 | F47: =+F46+1 -> 45354 | G47: 4.8043735e+08
A48: =A47+1 -> 36 | B48: =+B47+1 -> 45295 | C48: 4.2675766e+08 | D48: =+D47+1 -> 45326 | E48: 5.1189052e+08 | F48: =+F47+1 -> 45355 | G48: 4.758927e+08
A49: =A48+1 -> 37 | B49: =+B48+1 -> 45296 | C49: 4.2766324e+08 | D49: =+D48+1 -> 45327 | E49: 5.1689472e+08 | F49: =+F48+1 -> 45356 | G49: 4.7589426e+08
A50: =A49+1 -> 38 | B50: =+B49+1 -> 45297 | C50: 4.4607484e+08 | D50: =+D49+1 -> 45328 | E50: 5.3747791e+08 | F50: =+F49+1 -> 45357 | G50: 4.7140242e+08
A51: =A50+1 -> 39 | B51: =+B50+1 -> 45298 | C51: 4.4607484e+08 | D51: =+D50+1 -> 45329 | E51: 5.3757316e+08 | F51: =+F50+1 -> 45358 | G51: 4.6018172e+08
A52: =A51+1 -> 40 | B52: =+B51+1 -> 45299 | C52: 4.3429311e+08 | D52: =+D51+1 -> 45330 | E52: 5.3564156e+08 | F52: =+F51+1 -> 45359 | G52: 4.5799609e+08
A53: =A52+1 -> 41 | B53: =+B52+1 -> 45300 | C53: 4.3755411e+08 | D53: =+D52+1 -> 45331 | E53: 5.3459063e+08 | F53: =+F52+1 -> 45360 | G53: 4.5799609e+08
A54: =A53+1 -> 42 | B54: =+B53+1 -> 45301 | C54: 4.3703759e+08 | D54: =+D53+1 -> 45332 | E54: 5.3459063e+08 | F54: =+F53+1 -> 45361 | G54: 4.5799609e+08
A55: =A54+1 -> 43 | B55: =+B54+1 -> 45302 | C55: 4.3746895e+08 | D55: =+D54+1 -> 45333 | E55: 5.3459063e+08 | F55: =+F54+1 -> 45362 | G55: 4.4730593e+08
A56: =A55+1 -> 44 | B56: =+B55+1 -> 45303 | C56: 4.2630195e+08 | D56: =+D55+1 -> 45334 | E56: 5.2193809e+08 | F56: =+F55+1 -> 45363 | G56: 4.4137036e+08
A57: =A56+1 -> 45 | B57: =+B56+1 -> 45304 | C57: 4.2630195e+08 | D57: =+D56+1 -> 45335 | E57: 5.2435003e+08 | F57: =+F56+1 -> 45364 | G57: 4.3342042e+08
... A73: =A72+1 -> 61 | B73: =+B72+1 -> 45320 | C73: 4.7132156e+08 | D73: =+D72+1 -> 45351 | E73: 4.7941819e+08 | F73: =+F72+1 -> 45380 | G73: 3.9366007e+08
A74: =A73+1 -> 62 | B74: =+B73+1 -> 45321 | C74: 4.8725933e+08 | E74: 0 | F74: =+F73+1 -> 45381 | G74: 3.9366007e+08
A75: =A74+1 -> 63 | B75: =+B74+1 -> 45322 | C75: 5.027735e+08 | E75: 0 | F75: =+F74+1 -> 45382 | G75: 3.9366007e+08
A76: =A75+1 -> 64 | C76: =SUM(C45:C75) -> 1.369932e+10 | E76: =SUM(E45:E75) -> 1.5108631e+10 | G76: =SUM(G45:G75) -> 1.3348486e+10
A77: Line No. | B77: Date | C77: A/R Balance | D77: Date | E77: A/R Balance | F77: Date | G77: A/R Balance
B78: (a) | C78: (b) | D78: (c) | E78: (d) | F78: (e) | G78: (f)
A80: =A76+1 -> 65 | B80: =+F75+1 -> 45383 | C80: 3.789164e+08 | D80: =+B109+1 -> 45413 | E80: 3.8189088e+08 | F80: =+D110+1 -> 45444 | G80: 4.0412472e+08
A81: =A80+1 -> 66 | B81: =+B80+1 -> 45384 | C81: 3.8779155e+08 | D81: =+D80+1 -> 45414 | E81: 3.8750796e+08 | F81: =+F80+1 -> 45445 | G81: 4.0412472e+08
A82: =A81+1 -> 67 | B82: =+B81+1 -> 45385 | C82: 3.8937989e+08 | D82: =+D81+1 -> 45415 | E82: 3.8426105e+08 | F82: =+F81+1 -> 45446 | G82: 4.1229782e+08
A83: =A82+1 -> 68 | B83: =+B82+1 -> 45386 | C83: 3.9538511e+08 | D83: =+D82+1 -> 45416 | E83: 3.8426105e+08 | F83: =+F82+1 -> 45447 | G83: 4.169031e+08
A84: =A83+1 -> 69 | B84: =+B83+1 -> 45387 | C84: 3.9183212e+08 | D84: =+D83+1 -> 45417 | E84: 3.8426105e+08 | F84: =+F83+1 -> 45448 | G84: 4.219544e+08
A85: =A84+1 -> 70 | B85: =+B84+1 -> 45388 | C85: 3.9183212e+08 | D85: =+D84+1 -> 45418 | E85: 3.956504e+08 | F85: =+F84+1 -> 45449 | G85: 4.2052464e+08
A86: =A85+1 -> 71 | B86: =+B85+1 -> 45389 | C86: 3.9183212e+08 | D86: =+D85+1 -> 45419 | E86: 3.9968861e+08 | F86: =+F85+1 -> 45450 | G86: 4.2063458e+08
A87: =A86+1 -> 72 | B87: =+B86+1 -> 45390 | C87: 3.869329e+08 | D87: =+D86+1 -> 45420 | E87: 4.0097659e+08 | F87: =+F86+1 -> 45451 | G87: 4.2063458e+08
A88: =A87+1 -> 73 | B88: =+B87+1 -> 45391 | C88: 3.8968384e+08 | D88: =+D87+1 -> 45421 | E88: 4.0073856e+08 | F88: =+F87+1 -> 45452 | G88: 4.2063458e+08
A89: =A88+1 -> 74 | B89: =+B88+1 -> 45392 | C89: 3.8772272e+08 | D89: =+D88+1 -> 45422 | E89: 3.9930552e+08 | F89: =+F88+1 -> 45453 | G89: 4.2558602e+08
A90: =A89+1 -> 75 | B90: =+B89+1 -> 45393 | C90: 3.8700876e+08 | D90: =+D89+1 -> 45423 | E90: 3.9930552e+08 | F90: =+F89+1 -> 45454 | G90: 4.2912381e+08
A91: =A90+1 -> 76 | B91: =+B90+1 -> 45394 | C91: 3.8436146e+08 | D91: =+D90+1 -> 45424 | E91: 3.9930552e+08 | F91: =+F90+1 -> 45455 | G91: 4.3181582e+08
A92: =A91+1 -> 77 | B92: =+B91+1 -> 45395 | C92: 3.8436146e+08 | D92: =+D91+1 -> 45425 | E92: 3.9701996e+08 | F92: =+F91+1 -> 45456 | G92: 4.3056973e+08
... A109: =A108+1 -> 94 | B109: =+B108+1 -> 45412 | C109: 3.7559401e+08 | D109: =+D108+1 -> 45442 | E109: 3.99215e+08 | F109: =+F108+1 -> 45473 | G109: 4.6835883e+08
A110: =A109+1 -> 95 | C110: 0 | D110: =+D109+1 -> 45443 | E110: 4.0412472e+08 | G110: 0
A111: =A110+1 -> 96 | C111: =SUM(C80:C110) -> 1.145409e+10 | E111: =SUM(E80:E110) -> 1.2366701e+10 | G111: =SUM(G80:G110) -> 1.313313e+10
A112: Line No. | B112: Date | C112: A/R Balance | D112: Date | E112: A/R Balance | F112: Date | G112: A/R Balance
B113: (a) | C113: (b) | D113: (c) | E113: (d) | F113: (e) | G113: (f)
A115: =A111+1 -> 97 | B115: =+F109+1 -> 45474 | C115: 4.8643767e+08 | D115: =+B145+1 -> 45505 | E115: 5.6192338e+08 | F115: =+D145+1 -> 45536 | G115: 5.7465218e+08
A116: =A115+1 -> 98 | B116: =+B115+1 -> 45475 | C116: 5.0590512e+08 | D116: =+D115+1 -> 45506 | E116: 5.5617358e+08 | F116: =+F115+1 -> 45537 | G116: 5.7465218e+08
A117: =A116+1 -> 99 | B117: =+B116+1 -> 45476 | C117: 5.0754484e+08 | D117: =+D116+1 -> 45507 | E117: 5.5617358e+08 | F117: =+F116+1 -> 45538 | G117: 5.5964506e+08
A118: =A117+1 -> 100 | B118: =+B117+1 -> 45477 | C118: 5.0754484e+08 | D118: =+D117+1 -> 45508 | E118: 5.5617358e+08 | F118: =+F117+1 -> 45539 | G118: 5.7099716e+08
A119: =A118+1 -> 101 | B119: =+B118+1 -> 45478 | C119: 4.9734997e+08 | D119: =+D118+1 -> 45509 | E119: 5.6067692e+08 | F119: =+F118+1 -> 45540 | G119: 5.6350027e+08
A120: =A119+1 -> 102 | B120: =+B119+1 -> 45479 | C120: 4.9734997e+08 | D120: =+D119+1 -> 45510 | E120: 5.6236197e+08 | F120: =+F119+1 -> 45541 | G120: 5.7312938e+08
A121: =A120+1 -> 103 | B121: =+B120+1 -> 45480 | C121: 4.9734997e+08 | D121: =+D120+1 -> 45511 | E121: 5.5971947e+08 | F121: =+F120+1 -> 45542 | G121: 5.7312938e+08
A122: =A121+1 -> 104 | B122: =+B121+1 -> 45481 | C122: 4.9596998e+08 | D122: =+D121+1 -> 45512 | E122: 5.594648e+08 | F122: =+F121+1 -> 45543 | G122: 5.7312938e+08
A123: =A122+1 -> 105 | B123: =+B122+1 -> 45482 | C123: 5.0828514e+08 | D123: =+D122+1 -> 45513 | E123: 5.7414384e+08 | F123: =+F122+1 -> 45544 | G123: 5.7287509e+08
A124: =A123+1 -> 106 | B124: =+B123+1 -> 45483 | C124: 5.0733695e+08 | D124: =+D123+1 -> 45514 | E124: 5.7414384e+08 | F124: =+F123+1 -> 45545 | G124: 5.769349e+08
A125: =A124+1 -> 107 | B125: =+B124+1 -> 45484 | C125: 5.0969116e+08 | D125: =+D124+1 -> 45515 | E125: 5.7414384e+08 | F125: =+F124+1 -> 45546 | G125: 5.7961126e+08
A126: =A125+1 -> 108 | B126: =+B125+1 -> 45485 | C126: 5.0669292e+08 | D126: =+D125+1 -> 45516 | E126: 5.7221002e+08 | F126: =+F125+1 -> 45547 | G126: 5.7754105e+08
A127: =A126+1 -> 109 | B127: =+B126+1 -> 45486 | C127: 5.0669292e+08 | D127: =+D126+1 -> 45517 | E127: 5.7008928e+08 | F127: =+F126+1 -> 45548 | G127: 5.7781904e+08
... A144: =A143+1 -> 126 | B144: =+B143+1 -> 45503 | C144: 5.4283353e+08 | D144: =+D143+1 -> 45534 | E144: 5.7465218e+08 | F144: =+F143+1 -> 45565 | G144: 5.803354e+08
A145: =A144+1 -> 127 | B145: =+B144+1 -> 45504 | C145: 5.5627886e+08 | D145: =+D144+1 -> 45535 | E145: 5.7465218e+08 | G145: 0
A146: =A145+1 -> 128 | C146: =SUM(C115:C145) -> 1.6062645e+10 | E146: =SUM(E115:E145) -> 1.7522719e+10 | G146: =SUM(G115:G145) -> 1.7298505e+10
A147: 129
A148: 130 | B148: Source: | C148: Daily Receivable Backup.xlsx | G148: =SUM(C146:G146,C111:G111,C76:G76,C41:G41) -> 1.730205e+11

Sheet 2
A1: 2025 RATE CASE
A2: =' '!A2 -> ONCOR ELECTRIC DELIVERY COMPANY LLC
A3: LABOR - PAYROLL LEAD DAYS
A4: FOR THE LEAD-LAG STUDY-PERIOD ENDING SEPTEMBER 30, 2024
A5: SPONSOR: A. THENMADATHIL
A7: Line No. | B7: Payroll Type | C7: Payroll Expense | D7: Percent | E7: Reference | F7: (Lead)/Lag | G7: Reference | H7: Check Float | I7: Reference | J7: Total (Lead)/Lag | K7: Weighted Dollar Days
B8: (a) | C8: (b) | D8: (c) | E8: (d) | F8: (e) | G8: (f) | H8: (g) | I8: (h) | J8: (i) | K8: (j)
A10: 1 | B10: Bi-Weekly
A11: 2
A12: 3 | B12: Direct Deposit | C12: =+C15*D12 -> 3.2710117e+08 | D12: ='2-1'!F18 -> 0.9995 | E12: WP/II-B-9/2-1 | F12: =-'2-2'!C25 -> -12 | G12: WP/II-B-9/2-2 | H12: 0 | J12: =F12+H12 -> -12 | K12: =C12*J12 -> -3.9252141e+09
A13: 4 | B13: Manual | C13: =C15-C12 -> 163632.4 | D13: ='2-1'!G18 -> 0.0005 | E13: WP/II-B-9/2-1 | F13: =F12 -> -12 | G13: WP/II-B-9/2-2 | H13: ='2-4'!D14 -> 9.02 | I13: WP/II-B-9/2-4 | J13: =F13+H13 -> -2.98 | K13: =C13*J13 -> -487624.56
A14: 5
A15: 6 | B15: Total Bi-Weekly Pay | C15: =+D15*C18 -> 3.272648e+08 | D15: =+'2-6'!E11 -> 1 | E15: WP/II-B-9/2-6 | J15: =K15/C15 -> -11.99549 | K15: =SUM(K12:K13) -> -3.9257017e+09
A16: 7
A17: 8
A18: 9 | B18: Total | C18: 3.272648e+08 | D18: =+D15 -> 1 | E18: Schedule II-D-3 * | F18: =ROUND((C15*F12)/C18,2) -> -12 | J18: =ROUND(K18/C18,2) -> -12 | K18: =+K15 -> -3.9257017e+09
A19: 10 | E19: *Net of Incentive Pay

Sheet 2-1
A1: 2025 RATE CASE
A2: =' '!A2 -> ONCOR ELECTRIC DELIVERY COMPANY LLC
A3: PAYROLL LEAD - DIRECT DEPOSIT CALCULATION
A4: FOR THE LEAD-LAG STUDY-PERIOD ENDING SEPTEMBER 30, 2024
A5: SPONSOR: A. THENMADATHIL
A7: Line No. | B7: Period/Business Unit | C7: Direct Deposit | D7: Manual Checks | E7: Total - Direct Deposit and Manual Checks | F7: Percent Paid via Direct Deposit | G7: Percent Paid via Manual Check
B8: (a) | C8: (b) | D8: (c) | E8: (d) | F8: (e) | G8: (f)
A10: 1 | B10: 45200
A11: =A10+1 -> 2 | B11: Transmission | C11: 9467594.4 | D11: 2176.29 | E11: =+C11+D11 -> 9469770.7
A12: =A11+1 -> 3 | B12: Distribution | C12: 25450128 | D12: 4841.49 | E12: =+C12+D12 -> 25454970
A13: =A12+1 -> 4
A14: =A13+1 -> 5 | B14: 45536
A15: =A14+1 -> 6 | B15: Transmission | C15: 9320372.1 | D15: 133.49 | E15: =+C15+D15 -> 9320505.6
A16: =A15+1 -> 7 | B16: Distribution | C16: 26167254 | D16: 26113.37 | E16: =+C16+D16 -> 26193367
A17: =A16+1 -> 8
A18: =A17+1 -> 9 | B18: Total Payments | C18: =SUM(C10:C16) -> 70405349 | D18: =SUM(D10:D16) -> 33264.64 | E18: =SUM(E10:E16) -> 70438613 | F18: =+ROUND(C18/$E$18,4) -> 0.9995 | G18: =+ROUND(D18/$E$18,4) -> 0.0005
A19: =A18+1 -> 10
A20: =A19+1 -> 11 | F20: (1) | G20: (2)
A21: =A20+1 -> 12 | B21: Note:
A22: =A21+1 -> 13 | B22: (1) The calculation is Col (b) Ln 9 divided by Col (d) Ln 9.
A23: =A22+1 -> 14 | B23: (2) The calculation is Col (c) Ln 9 divided by Col (d) Ln 9.
A24: =A23+1 -> 15
A25: =A24+1 -> 16 | B25: Source: | C25: Payroll direct deposit.xlsx

Sheet 2-2
A1: 2025 RATE CASE
A2: =' '!A2 -> ONCOR ELECTRIC DELIVERY COMPANY LLC
A3: PAYROLL LEAD - BI-WEEKLY PAYROLL CALCULATION
A4: FOR THE LEAD-LAG STUDY-PERIOD ENDING SEPTEMBER 30, 2024
A5: SPONSOR: A. THENMADATHIL
A7: Line No. | B7: Bi-Weekly | C7: Days
B8: (a) | C8: (b)
A10: 1 | B10: Conditions:
A11: 2
A12: 3 | B12: Pay Periods cover 14 days.
A13: 4 | B13: Start on Monday and end on the second following Sunday.
A14: 5 | B14: Payment Checks or Direct Deposits typically are made on Friday, five days after end of pay period.
A15: 6 | B15: (If the scheduled pay date is a holiday, payment is made on the preceding work day. During
A16: 7 | B16: the test period, with the exception of one instance, all paydays fell on the regularly scheduled Friday.)
A17: 8
A18: 9
A19: 10 | B19: Days in Period:
A20: 11
A21: 12 | B21: 14 days. Midpoint = 7
A22: 13
A23: 14 | B23: Payroll Lead Formula:
A24: 15
A25: 16 | B25: (7 days) + (5 days) = | C25: =7+'2-2-1'!G43 -> 12
A27: Sources: | B27: Holidays.xlsx
B28: Bi-Weekly Payroll Calendar 2024.xlsx
B29: Bi-Weekly Payroll Calendar 2023.xlsx

Sheet 2-2-1
A1: 2025 RATE CASE
A2: =' '!A2 -> ONCOR ELECTRIC DELIVERY COMPANY LLC
A3: PAYROLL LEAD - HOLIDAY/WEEKEND FACTOR CALCULATION - BI-WEEKLY
A4: FOR THE LEAD-LAG STUDY-PERIOD ENDING SEPTEMBER 30, 2024
A5: SPONSOR: A. THENMADATHIL
A8: Line No. | B8: Scheduled Payday | C8: Normal Payment Lead Days | E8: Lead Days Reflecting Holiday Adjustments | G8: Total
B9: (a) | C9: (b) | E9: (c) | G9: (d)
A11: 1 | B11: 45177 | C11: 5 | G11: =C11+E11 -> 5
A12: 2 | B12: 45191 | C12: 5 | G12: =C12+E12 -> 5
A13: 3 | B13: 45205 | C13: 5 | G13: =C13+E13 -> 5
A14: 4 | B14: 45219 | C14: 5 | G14: =C14+E14 -> 5
A15: 5 | B15: 45233 | C15: 5 | G15: =C15+E15 -> 5
A16: 6 | B16: 45247 | C16: 5 | G16: =C16+E16 -> 5
A17: 7 | B17: 45261 | C17: 5 | G17: =C17+E17 -> 5
A18: 8 | B18: 45275 | C18: 5 | G18: =C18+E18 -> 5
A19: 9 | B19: 45289 | C19: 5 | G19: =C19+E19 -> 5
A20: 10 | B20: 45303 | C20: 5 | G20: =C20+E20 -> 5
A21: 11 | B21: 45317 | C21: 5 | G21: =C21+E21 -> 5
A22: 12 | B22: 45331 | C22: 5 | G22: =C22+E22 -> 5
... A38: 28 | B38: 45555 | C38: 5 | G38: =C38+E38 -> 5
A39: 29 | B39: Total Days | C39: =SUM(C11:C38) -> 140 | E39: =SUM(E11:E38) -> 0 | G39: =SUM(G11:G38) -> 140
A40: 30
A41: 31
A42: 32 | B42: Number of Annual Payroll Cycles | G42: =A38 -> 28
A43: 33 | B43: Average of Lead Days Before Payment | G43: =ROUND(G39/G42,2) -> 5
A44: 34
A45: 35
A46: 36 | B46: Sources: | C46: Holidays.xlsx
A47: 37 | C47: Bi-Weekly Payroll Calendar 2023.xlsx
A48: 38 | C48: Bi-Weekly Payroll Calendar 2024.xlsx

Sheet 2-3
A1: 2025 RATE CASE
A2: =' '!A2 -> ONCOR ELECTRIC DELIVERY COMPANY LLC
A3: PAYROLL LEAD - SEMI-MONTHLY PAYROLL CALCULATION
A4: FOR THE LEAD-LAG STUDY-PERIOD ENDING SEPTEMBER 30, 2024
A5: SPONSOR: A. THENMADATHIL
A7: Line No. | B7: Semi-Monthly
B8: (a) | C8: (b) | D8: (c) | E8: (d)
A10: 1 | B10: As of the first pay date of January 2024 Oncor moved entire payroll to bi-weekly
A11: 2

Sheet 2-3-1
A1: 2025 RATE CASE
A2: =' '!A2 -> ONCOR ELECTRIC DELIVERY COMPANY LLC
A3: PAYROLL LEAD - HOLIDAY/WEEKEND FACTOR CALCULATION - SEMI MONTHLY
A4: FOR THE LEAD-LAG STUDY-PERIOD ENDING SEPTEMBER 30, 2024
A5: SPONSOR: A. THENMADATHIL
C7: Days Payday Moved Up
A8: Line No. | B8: Scheduled Payday | C8: 1st Pay Period | D8: 2nd Pay Period | F8: Actual Payday | H8: Difference
B9: (a) | C9: (b) | D9: (c) | F9: (d) | H9: (e)
A11: 1 | B11: As of the first pay date of January 2024 Oncor moved entire payroll to bi-weekly
A12: 2

Sheet 2-4
A1: 2025 RATE CASE
A2: =' '!A2 -> ONCOR ELECTRIC DELIVERY COMPANY LLC
A3: PAYROLL LEAD - CHECK FLOAT CALCULATION
A4: FOR THE LEAD-LAG STUDY-PERIOD ENDING SEPTEMBER 30, 2024
A5: SPONSOR: A. THENMADATHIL
E7: Weighted
A8: Line No. | B8: Business Unit | C8: Net Amount | D8: (Lead)/Lag Days | E8: Dollar Days | F8: Total
B9: (a) | C9: (b) | D9: (c) | E9: (d)
A11: 1 | B11: Transmission | C11: 44829.02 | D11: 23.999366 | E11: =+D11*C11 -> 1075868.1
A12: 2 | B12: Distribution | C12: 209872.09 | D12: 5.8149497 | E12: =+D12*C12 -> 1220395.7
A13: 3
A14: 4 | B14: Total | C14: =SUM(C11:C12) -> 254701.11 | D14: =ROUND(E14/C14,2) -> 9.02 | E14: =SUM(E11:E12) -> 2296263.7
A15: 5
A16: 6 | B16: Source: | C16: Payroll manual check sample.xlsx

Sheet 2-5
A1: 2025 RATE CASE
A2: =' '!A2 -> ONCOR ELECTRIC DELIVERY COMPANY LLC
A3: PAYROLL LEAD - PAY CYCLE CALCULATION
A4: FOR THE LEAD-LAG STUDY-PERIOD ENDING SEPTEMBER 30, 2024
A5: SPONSOR: A. THENMADATHIL
A7: Line No. | B7: Description | C7: First Cycle | D7: Second Cycle | E7: Third Cycle | F7: Total
B8: (a) | C8: (b) | D8: (c) | E8: (c) | F8: (d)
B9: Biweekly
A10: 1 | B10: Distribution
A11: 2 | B11: October 2023 | C11: 20148158 | D11: 19036521 | F11: =SUM(C11:E11) -> 39184679
A12: 3 | B12: September 2024 | C12: 20610519 | D12: 19795323 | F12: =SUM(C12:E12) -> 40405842
A13: 4 | B13: Total | C13: =SUM(C11 + C12) -> 40758678 | D13: =SUM(D11 + D12) -> 38831843 | E13: =SUM(E11 + E12) -> 0 | F13: =SUM(F11 + F12) -> 79590521
A14: 5 | B14: Percent | C14: =ROUND(SUM(C13/$F$13),4) -> 0.5121 | D14: =ROUND(SUM(D13/$F$13),4) -> 0.4879 | E14: =ROUND(SUM(E13/$F$13),4) -> 0 | F14: =SUM(C13+D13+E13) / F13 -> 1
A15: 6
A16: 7
A17: 8 | B17: Transmission
A18: 9 | B18: October 2023 | C18: 6980073.6 | D18: 7501641.8 | F18: =SUM(C18:E18) -> 14481715
A19: 10 | B19: September 2024 | C19: 7318260.7 | D19: 6915797 | F19: =SUM(C19:E19) -> 14234058
A20: 11 | B20: Total | C20: =SUM(C18 + C19) -> 14298334 | D20: =SUM(D18 + D19) -> 14417439 | F20: =SUM(F18 + F19) -> 28715773
A21: 12 | B21: Percent | C21: =ROUND(SUM(C20/$F$20),4) -> 0.4979 | D21: =ROUND(SUM(D20/$F$20),4) -> 0.5021 | F21: =SUM(C20+D20+E20) / F20 -> 1
A22: 13
A23: 14 | B23: Total T&D | C23: =C20 -> 14298334 | D23: =D20 -> 14417439 | F23: =SUM(C23:E23) -> 28715773
A24: 15 | B24: Percent | C24: =ROUND(C23/F23,4) -> 0.4979 | D24: =ROUND(D23/F23,4) -> 0.5021 | F24: =SUM(C23+D23+E23) / F23 -> 1
A25: 16
A26: 17 | B26: Source: | C26: Payroll pay cycles.xlsx

Sheet 2-6
A1: 2025 RATE CASE
A2: =' '!A2 -> ONCOR ELECTRIC DELIVERY COMPANY LLC
A3: PAYROLL LEAD - BI-WEEKLY/SEMI-MONTHLY PAY CALCULATION
A4: FOR THE LEAD-LAG STUDY-PERIOD ENDING SEPTEMBER 30, 2024
A5: SPONSOR: A. THENMADATHIL
A7: Line | E7: Bi-Weekly | F7: Semi-Monthly
A8: No. | B8: Description | C8: Total Payroll | D8: Bi-Weekly | E8: Percent | F8: Percent
B9: (a) | C9: (b) | D9: (c) | E9: (d) | F9: (e)
A11: 1 | B11: Payroll | C11: 7.8851023e+08 | D11: =C11 -> 7.8851023e+08 | E11: =ROUND(D11/C11,4) -> 1 | F11: =1-E11 -> 0
A12: 2
A13: 3 | B13: Source: | C13: Payroll semi-monthly & bi-weekly.xlsx

Sheet 3
A1: 2025 RATE CASE
A2: =' '!A2 -> ONCOR ELECTRIC DELIVERY COMPANY LLC
A3: LABOR - INCENTIVE PAY LEAD DAYS
A4: FOR THE LEAD-LAG STUDY-PERIOD ENDING SEPTEMBER 30, 2024
A5: SPONSOR: A. THENMADATHIL
A7: Line No. | B7: Description | C7: Payroll Expense | D7: Percent | E7: Reference | F7: (Lead)/Lag | G7: Reference | H7: Check Float | I7: Reference | J7: Total (Lead)/Lag | K7: Weighted Dollar Days
B8: (a) | C8: (b) | D8: (c) | E8: (d) | F8: (e) | G8: (f) | H8: (g) | I8: (h) | J8: (i) | K8: (j)
A10: 1 | B10: Test Year Incentive | C10: =+C12-C11 -> 68494556
A11: =A10+1 -> 2 | B11: Adjustment Needed | C11: -5816139.7
A12: =A11+1 -> 3 | B12: Adjusted Incentive | C12: 62678416 | E12: Source 1
A14: =A12+1 -> 4
A15: =A14+1 -> 5 | B15: Direct Deposit | C15: =+C17*D15 -> 62647077 | D15: =+'2-1'!F18 -> 0.9995 | E15: WP/II-B-9/2-1 | F15: ='3-1'!F34 -> -255.75 | G15: WP/II-B-9/3-1 | H15: 0 | J15: =+H15+F15 -> -255.75 | K15: =+J15*C15 -> -1.602199e+10
A16: =A15+1 -> 6 | B16: Manual | C16: =+C17*D16 -> 31339.208 | D16: =+'2-1'!G18 -> 0.0005 | E16: WP/II-B-9/2-1 | F16: =F15 -> -255.75 | G16: WP/II-B-9/3-1 | H16: ='2-4'!D14 -> 9.02 | I16: WP/II-B-9/2-4 | J16: =+H16+F16 -> -246.73 | K16: =+J16*C16 -> -7732322.8
A17: =A16+1 -> 7 | B17: Total Adjusted Incentive | C17: =+C12 -> 62678416 | J17: =K17/C17 -> -255.74549 | K17: =+K16+K15 -> -1.6029722e+10
A18: =A17+1 -> 8
A19: =A18+1 -> 9
A20: =A19+1 -> 10 | B20: Source 1: | C20: Iteration "Adjusted Test Year Amount"

Sheet 3-1
A1: 2025 RATE CASE
A2: =' '!A2 -> ONCOR ELECTRIC DELIVERY COMPANY LLC
A3: PEP AWARD LEAD PAYMENT CALCULATION
A4: FOR THE LEAD-LAG STUDY-PERIOD ENDING SEPTEMBER 30, 2024
A5: SPONSOR: A. THENMADATHIL
A7: Line No. | B7: Month | C7: Accrual Date | D7: Mid Month | E7: Payout Date | F7: (Lead)/Lag Days
B8: (a) | C8: (b) | D8: (c) | E8: (d) | F8: (e)
A10: 1 | B10: 45200 | C10: 45230 | D10: =IF(C10=0,"",DATE(YEAR(C10),MONTH(C10),1)+INT(DAY(DATE(YEAR(C10),MONTH(C10)+1,1)-1)/2)-0.5) -> 45214.5 | E10: 45362 | F10: =D10-E10 -> -147.5
A11: 2
A12: 3 | B12: =B10+31 -> 45231 | C12: =C10+30 -> 45260 | D12: =IF(C12=0,"",DATE(YEAR(C12),MONTH(C12),1)+INT(DAY(DATE(YEAR(C12),MONTH(C12)+1,1)-1)/2)-0.5) -> 45245.5 | E12: =$E$10 -> 45362 | F12: =D12-E12 -> -116.5
A13: 4
A14: 5 | B14: =B12+30 -> 45261 | C14: =C12+31 -> 45291 | D14: =IF(C14=0,"",DATE(YEAR(C14),MONTH(C14),1)+INT(DAY(DATE(YEAR(C14),MONTH(C14)+1,1)-1)/2)-0.5) -> 45275.5 | E14: =$E$10 -> 45362 | F14: =D14-E14 -> -86.5
A15: 6
A16: 7 | B16: =B14+31 -> 45292 | C16: =C14+31 -> 45322 | D16: =IF(C16=0,"",DATE(YEAR(C16),MONTH(C16),1)+INT(DAY(DATE(YEAR(C16),MONTH(C16)+1,1)-1)/2)-0.5) -> 45306.5 | E16: 45730 | F16: =D16-E16 -> -423.5
A17: 8
A18: 9 | B18: =B16+31 -> 45323 | C18: 45350 | D18: =IF(C18=0,"",DATE(YEAR(C18),MONTH(C18),1)+INT(DAY(DATE(YEAR(C18),MONTH(C18)+1,1)-1)/2)-0.5) -> 45336.5 | E18: =+E16 -> 45730 | F18: =D18-E18 -> -393.5
A19: 10
A20: 11 | B20: =B18+29 -> 45352 | C20: 45382 | D20: =IF(C20=0,"",DATE(YEAR(C20),MONTH(C20),1)+INT(DAY(DATE(YEAR(C20),MONTH(C20)+1,1)-1)/2)-0.5) -> 45366.5 | E20: =+E18 -> 45730 | F20: =D20-E20 -> -363.5
A21: 12
A22: 13 | B22: =B20+31 -> 45383 | C22: =C20+30 -> 45412 | D22: =IF(C22=0,"",DATE(YEAR(C22),MONTH(C22),1)+INT(DAY(DATE(YEAR(C22),MONTH(C22)+1,1)-1)/2)-0.5) -> 45397.5 | E22: =+E20 -> 45730 | F22: =D22-E22 -> -332.5
A23: 14
A24: 15 | B24: =B22+30 -> 45413 | C24: =C22+31 -> 45443 | D24: =IF(C24=0,"",DATE(YEAR(C24),MONTH(C24),1)+INT(DAY(DATE(YEAR(C24),MONTH(C24)+1,1)-1)/2)-0.5) -> 45427.5 | E24: =E22 -> 45730 | F24: =D24-E24 -> -302.5
A25: 16
A26: 17 | B26: =B24+31 -> 45444 | C26: =C24+30 -> 45473 | D26: =IF(C26=0,"",DATE(YEAR(C26),MONTH(C26),1)+INT(DAY(DATE(YEAR(C26),MONTH(C26)+1,1)-1)/2)-0.5) -> 45458.5 | E26: =E24 -> 45730 | F26: =D26-E26 -> -271.5
A27: 18
A28: 19 | B28: =B26+30 -> 45474 | C28: =C26+31 -> 45504 | D28: =IF(C28=0,"",DATE(YEAR(C28),MONTH(C28),1)+INT(DAY(DATE(YEAR(C28),MONTH(C28)+1,1)-1)/2)-0.5) -> 45488.5 | E28: =E26 -> 45730 | F28: =D28-E28 -> -241.5
A29: 20
A30: 21 | B30: =B28+31 -> 45505 | C30: =C28+31 -> 45535 | D30: =IF(C30=0,"",DATE(YEAR(C30),MONTH(C30),1)+INT(DAY(DATE(YEAR(C30),MONTH(C30)+1,1)-1)/2)-0.5) -> 45519.5 | E30: =E28 -> 45730 | F30: =D30-E30 -> -210.5
A31: 22
A32: 23 | B32: =B30+31 -> 45536 | C32: =C30+30 -> 45565 | D32: =IF(C32=0,"",DATE(YEAR(C32),MONTH(C32),1)+INT(DAY(DATE(YEAR(C32),MONTH(C32)+1,1)-1)/2)-0.5) -> 45550.5 | E32: =E30 -> 45730 | F32: =D32-E32 -> -179.5
A33: 24
A34: 25 | B34: Average | F34: =ROUND(AVERAGE(F10:F32),2) -> -255.75

Sheet 3-2
A1: 2025 RATE CASE
A2: =' '!A2 -> ONCOR ELECTRIC DELIVERY COMPANY LLC
A3: METER READER INCENTIVE LEAD DAYS - PAYMENT CALCULATION
A4: FOR THE LEAD-LAG STUDY-PERIOD ENDING SEPTEMBER 30, 2024
A5: SPONSOR: A. THENMADATHIL
A7: Line No. | B7: Month | C7: Accrual Date | D7: Mid Month | E7: Payout Date | F7: (Lead)/Lag Days
B8: (a) | C8: (b) | D8: (c) | E8: (d) | F8: (e)
A10: 1 | B10: No Longer have Meter Readers thus no incentive effective 1/13.
A11: 2
A12: 3
A13: 4
A14: 5
A15: 6
A16: 7
A17: 8
A18: 9
A19: 10
A20: 11
A21: 12
A22: 13
... A34: 25

Sheet 4
A1: 2025 RATE CASE
A2: =' '!A2 -> ONCOR ELECTRIC DELIVERY COMPANY LLC
A3: NON-LABOR O&M - ONCOR ELECTRIC DELIVERY COMPANY LLC AND OTHER AFFILIATES
A4: FOR THE LEAD-LAG STUDY-PERIOD ENDING SEPTEMBER 30, 2024
A5: SPONSOR: A. THENMADATHIL
A7: Line | G7: Date | H7: Date | I7: Later of Paid | J7: Days Paid | K7: (Lead)/Lag
A8: No. | B8: Month | C8: From | D8: To | E8: Total Days | F8: Mid-Point | G8: Paid | H8: Due | I8: or Due Date | J8: After EOM | K8: Days
B9: (a) | C9: (b) | D9: (c) | E9: (d) | F9: (e) | G9: (f) | H9: (g) | I9: (h) | J9: (i) | K9: (j)
A11: 1 | B11: 45200 | C11: 45200 | D11: 45230 | E11: =D11-C11+1 -> 31 | F11: =E11/2 -> 15.5 | G11: 45260 | H11: 45260 | I11: =MAX(G11:H11) -> 45260 | J11: =+I11-D11 -> 30 | K11: =-J11-F11 -> -45.5 | N11: =H11 -> 45260
A12: =A11+1 -> 2 | B12: 45231 | C12: 45231 | D12: 45260 | E12: =D12-C12+1 -> 30 | F12: =E12/2 -> 15 | G12: 45289 | H12: 45289 | I12: =MAX(G12:H12) -> 45289 | J12: =+I12-D12 -> 29 | K12: =-J12-F12 -> -44 | N12: =H12 -> 45289
A13: =A12+1 -> 3 | B13: 45261 | C13: 45261 | D13: 45291 | E13: =D13-C13+1 -> 31 | F13: =E13/2 -> 15.5 | G13: 45322 | H13: 45322 | I13: =MAX(G13:H13) -> 45322 | J13: =+I13-D13 -> 31 | K13: =-J13-F13 -> -46.5 | N13: =H13 -> 45322
A14: =A13+1 -> 4 | B14: 45292 | C14: 45292 | D14: 45322 | E14: =D14-C14+1 -> 31 | F14: =E14/2 -> 15.5 | G14: 45351 | H14: 45351 | I14: =MAX(G14:H14) -> 45351 | J14: =+I14-D14 -> 29 | K14: =-J14-F14 -> -44.5 | N14: =H14 -> 45351
A15: =A14+1 -> 5 | B15: 45323 | C15: 45323 | D15: 45351 | E15: =D15-C15+1 -> 29 | F15: =E15/2 -> 14.5 | G15: 45380 | H15: 45380 | I15: =MAX(G15:H15) -> 45380 | J15: =+I15-D15 -> 29 | K15: =-J15-F15 -> -43.5 | N15: =H15 -> 45380
A16: =A15+1 -> 6 | B16: 45352 | C16: 45352 | D16: 45382 | E16: =D16-C16+1 -> 31 | F16: =E16/2 -> 15.5 | G16: 45412 | H16: 45412 | I16: =MAX(G16:H16) -> 45412 | J16: =+I16-D16 -> 30 | K16: =-J16-F16 -> -45.5 | N16: =H16 -> 45412
A17: =A16+1 -> 7 | B17: 45383 | C17: 45383 | D17: 45412 | E17: =D17-C17+1 -> 30 | F17: =E17/2 -> 15 | G17: 45443 | H17: 45443 | I17: =MAX(G17:H17) -> 45443 | J17: =+I17-D17 -> 31 | K17: =-J17-F17 -> -46 | N17: =H17 -> 45443
A18: =A17+1 -> 8 | B18: 45413 | C18: 45413 | D18: 45443 | E18: =D18-C18+1 -> 31 | F18: =E18/2 -> 15.5 | G18: 45471 | H18: 45471 | I18: =MAX(G18:H18) -> 45471 | J18: =+I18-D18 -> 28 | K18: =-J18-F18 -> -43.5 | N18: =H18 -> 45471
A19: =A18+1 -> 9 | B19: 45444 | C19: 45444 | D19: 45473 | E19: =D19-C19+1 -> 30 | F19: =E19/2 -> 15 | G19: 45504 | H19: 45504 | I19: =MAX(G19:H19) -> 45504 | J19: =+I19-D19 -> 31 | K19: =-J19-F19 -> -46 | N19: =H19 -> 45504
A20: =A19+1 -> 10 | B20: 45474 | C20: 45474 | D20: 45504 | E20: =D20-C20+1 -> 31 | F20: =E20/2 -> 15.5 | G20: 45534 | H20: 45534 | I20: =MAX(G20:H20) -> 45534 | J20: =+I20-D20 -> 30 | K20: =-J20-F20 -> -45.5 | N20: =H20 -> 45534
A21: =A20+1 -> 11 | B21: 45505 | C21: 45505 | D21: 45535 | E21: =D21-C21+1 -> 31 | F21: =E21/2 -> 15.5 | G21: 45565 | H21: 45565 | I21: =MAX(G21:H21) -> 45565 | J21: =+I21-D21 -> 30 | K21: =-J21-F21 -> -45.5 | N21: =H21 -> 45565
A22: =A21+1 -> 12 | B22: 45536 | C22: 45536 | D22: 45565 | E22: =D22-C22+1 -> 30 | F22: =E22/2 -> 15 | G22: 45596 | H22: 45596 | I22: =MAX(G22:H22) -> 45596 | J22: =+I22-D22 -> 31 | K22: =-J22-F22 -> -46 | N22: =H22 -> 45596
A23: =A22+1 -> 13
A24: =A23+1 -> 14 | G24: Average | K24: =ROUND(AVERAGE(K11:K22),2) -> -45.17
A25: =A24+1 -> 15
A26: =A25+1 -> 16
A27: =A26+1 -> 17 | B27: Source: | C27: Affiliate Payment Dates 12ME 9.30.24

Sheet 5
A1: 2025 RATE CASE
A2: =' '!A2 -> ONCOR ELECTRIC DELIVERY COMPANY LLC
A3: TCOS - NON-ONCOR
A4: FOR THE LEAD-LAG STUDY-PERIOD ENDING SEPTEMBER 30, 2024
A5: SPONSOR: A. THENMADATHIL
A7: Line No. | C7: Description | E7: (Lead)/Lag Days
C8: (a) | E8: (b)
A10: 1 | C10: Average service period
A11: =A10+1 -> 2 | C11: (365.25 days/12 months)/2 | E11: =ROUND(365.25/12/2,3)*-1 -> -15.219
A12: =A11+1 -> 3
A13: =A12+1 -> 4 | C13: Days from end of Service Period to Payment | E13: -35
A14: =A13+1 -> 5
A15: =A14+1 -> 6
A16: =A15+1 -> 7 | C16: Total Lead Days | E16: =ROUND(SUM(E11:E14),2) -> -50.22

Sheet 6
A1: 2025 RATE CASE
A2: =' '!A2 -> ONCOR ELECTRIC DELIVERY COMPANY LLC
A3: NON-LABOR O&M - OTHER THIRD PARTY O&M
A4: FOR THE LEAD-LAG STUDY-PERIOD ENDING SEPTEMBER 30, 2024
A5: SPONSOR: A. THENMADATHIL
A9: Line | D9: Total (Lead)/Lag | F9: Weighted
A10: No. | B10: Business Unit | C10: Amount | D10: Days | E10: Reference | F10: Dollar Days
B11: (a) | C11: (b) | D11: (c) | E11: (d) | F11: (e)
A13: 1 | B13: Transmission | C13: =+'6-1'!C17 -> 90583679 | D13: =+'6-1'!D17 -> -47.609962 | E13: WP/II-B-9/6-1 | F13: =+D13*C13 -> -4.3126855e+09
A14: =A13+1 -> 2 | B14: Distribution | C14: ='6-2'!C17 -> 7.2644002e+08 | D14: =+'6-2'!D17 -> -48.936752 | E14: WP/II-B-9/6-2 | F14: =C14*D14 -> -3.5549615e+10
A15: =A14+1 -> 3 | B15: Corporate | C15: =+'6-3'!C37 -> 1724828.1 | D15: ='6-3'!G37 -> -58.47 | E15: WP/II-B-9/6-3 | F15: =C15*D15 -> -1.008507e+08
A16: =A15+1 -> 4
A17: =A16+1 -> 5 | B17: Total | C17: =SUM(C13:C15) -> 8.1874853e+08 | D17: =ROUND(F17/C17,2) -> -48.81 | F17: =SUM(F13:F15) -> -3.9963152e+10
A18: =A17+1 -> 6
A19: =A18+1 -> 7
A20: =A19+1 -> 8 | B20: Source: | C20: Lead Lag Samples

Sheet 6-1
A1: 2025 RATE CASE
A2: =' '!A2 -> ONCOR ELECTRIC DELIVERY COMPANY LLC
A3: NON-LABOR O&M - THIRD PARTY O&M - TRANSMISSION
A4: FOR THE LEAD-LAG STUDY-PERIOD ENDING SEPTEMBER 30, 2024
A5: SPONSOR: A. THENMADATHIL
A9: Line | C9: Population | D9: (Lead)/Lag | F9: Weighted
A10: No. | B10: Strata | C10: Dollars | D10: Days | E10: Reference | F10: Dollar Days
B11: (a) | C11: (b) | D11: (c) | E11: (d) | F11: (e)
A13: 1 | B13: Item Amount < $10,000 | C13: 21612711 | D13: ='6-1-1'!G43 -> -41.62 | E13: WP/II-B-9/6-1-1 | F13: =C13*D13 -> -8.9952104e+08
A14: =A13+1 -> 2 | B14: Item Amount_>= $10,000 and <= $25,000 | C14: 13680576 | D14: ='6-1-2'!G32 -> -42.2 | E14: WP/II-B-9/6-1-2 | F14: =C14*D14 -> -5.7732032e+08
A15: =A14+1 -> 3 | B15: Item Amount > $25,000 | C15: 55290392 | D15: ='6-1-3'!G89 -> -51.29 | E15: WP/II-B-9/6-1-3 | F15: =C15*D15 -> -2.8358442e+09
A16: =A15+1 -> 4
A17: =A16+1 -> 5 | B17: Total | C17: =SUM(C13:C15) -> 90583679 | D17: =+F17/C17 -> -47.609962 | F17: =SUM(F13:F15) -> -4.3126855e+09
A18: =A17+1 -> 6
A19: =A18+1 -> 7
A20: =A19+1 -> 8
A21: =A20+1 -> 9 | B21: Source: | C21: Lead Lag Samples.xlsx

Sheet 6-1-1
A1: 2025 RATE CASE
A2: ='1-1-3-1-1'!A2 -> ONCOR ELECTRIC DELIVERY COMPANY LLC
A3: NON-LABOR O&M - THIRD PARTY O&M SAMPLE - TRANSMISSION (STRATA 1: <$10,000)
A4: FOR THE LEAD-LAG STUDY-PERIOD ENDING SEPTEMBER 30, 2024
A5: SPONSOR: A. THENMADATHIL
F7: Later of Due Date
A8: Line | D8: Begin | E8: Type of | F8: or Check Clear | G8: (Lead)/Lag | H8: Weighted Dollar
A9: No. | B9: Voucher | C9: Amount | D9: Date | E9: Begin Date | F9: Date | G9: Days | H9: Days
B10: (a) | C10: (b) | D10: (c) | E10: (d) | F10: (e) | G10: (f) | H10: (g)
A12: 1 | B12: 00660495 | C12: 57.64 | D12: 45310.5 | E12: Midpoint of Benefit Period | F12: 45334 | G12: =D12-F12 -> -23.5 | H12: =IF(ISERR(G12*C12),"",G12*C12) -> -1354.54
A13: =A12+1 -> 2 | B13: M1615722 | C13: 37.11 | D13: 45464 | E13: Midpoint of Benefit Period | F13: 45514 | G13: =D13-F13 -> -50 | H13: =IF(ISERR(G13*C13),"",G13*C13) -> -1855.5
A14: =A13+1 -> 3 | B14: 00686901 | C14: 81.19 | D14: 45517 | E14: Invoice Date | F14: 45554 | G14: =D14-F14 -> -37 | H14: =IF(ISERR(G14*C14),"",G14*C14) -> -3004.03
A15: =A14+1 -> 4 | B15: M1634300 | C15: 7473.46 | D15: 45519 | E15: Invoice Date | F15: 45549 | G15: =D15-F15 -> -30 | H15: =IF(ISERR(G15*C15),"",G15*C15) -> -224203.8
A16: =A15+1 -> 5 | B16: M1593450 | C16: 1623.75 | D16: 45468 | E16: Invoice Date | F16: 45498 | G16: =D16-F16 -> -30 | H16: =IF(ISERR(G16*C16),"",G16*C16) -> -48712.5
A17: =A16+1 -> 6 | B17: M1536247 | C17: 1484.91 | D17: 45379 | E17: Invoice Date | F17: 45411 | G17: =D17-F17 -> -32 | H17: =IF(ISERR(G17*C17),"",G17*C17) -> -47517.12
A18: =A17+1 -> 7 | B18: M1524717 | C18: 2587.2 | D18: 45357 | E18: Invoice Date | F18: 45387 | G18: =D18-F18 -> -30 | H18: =IF(ISERR(G18*C18),"",G18*C18) -> -77616
A19: =A18+1 -> 8 | B19: 00684805 | C19: 219.61 | D19: 45489 | E19: Midpoint of Benefit Period | F19: 45527 | G19: =D19-F19 -> -38 | H19: =IF(ISERR(G19*C19),"",G19*C19) -> -8345.18
A20: =A19+1 -> 9 | B20: 00674222 | C20: 65.5 | D20: 45415.5 | E20: Midpoint of Benefit Period | F20: 45434 | G20: =D20-F20 -> -18.5 | H20: =IF(ISERR(G20*C20),"",G20*C20) -> -1211.75
A21: =A20+1 -> 10 | B21: 00677265 | C21: 173.63 | D21: 45428 | E21: Midpoint of Benefit Period | F21: 45467 | G21: =D21-F21 -> -39 | H21: =IF(ISERR(G21*C21),"",G21*C21) -> -6771.57
A22: =A21+1 -> 11 | B22: 00648261 | C22: 2073.92 | D22: 45232 | E22: Midpoint of Benefit Period | F22: 45267 | G22: =D22-F22 -> -35 | H22: =IF(ISERR(G22*C22),"",G22*C22) -> -72587.2
A23: =A22+1 -> 12 | B23: M1569770 | C23: 548 | D23: 45379 | E23: Midpoint of Benefit Period | F23: 45442 | G23: =D23-F23 -> -63 | H23: =IF(ISERR(G23*C23),"",G23*C23) -> -34524
A24: =A23+1 -> 13 | B24: 00641806 | C24: 153.57 | D24: 45550.5 | E24: Midpoint of Benefit Period | F24: 45222 | G24: =D24-F24 -> 328.5 | H24: =IF(ISERR(G24*C24),"",G24*C24) -> 50447.745
... A41: =A40+1 -> 30 | B41: 00687597 | C41: 540.17 | D41: 45489 | E41: Midpoint of Benefit Period | F41: 45554 | G41: =D41-F41 -> -65 | H41: =IF(ISERR(G41*C41),"",G41*C41) -> -35111.05
A42: =A41+1 -> 31
A43: =A42+1 -> 32 | B43: Subtotal | C43: =SUM(C12:C42) -> 43754.31 | G43: =+ROUND(H43/C43,2) -> -41.62 | H43: =SUM(H12:H42) -> -1820850.9
A44: =A43+1 -> 33
A45: =A44+1 -> 34 | B45: Source: | C45: 3rd party O&M - TRN sample.xlsx

Sheet 6-1-2
A1: 2025 RATE CASE
A2: ='1-1-3-1-1'!A2 -> ONCOR ELECTRIC DELIVERY COMPANY LLC
A3: NON-LABOR O&M - THIRD PARTY O&M SAMPLE - TRANSMISSION (STRATA 2: >=$10,000 AND <=$25,000)
A4: FOR THE LEAD-LAG STUDY-PERIOD ENDING SEPTEMBER 30, 2024
A5: SPONSOR: A. THENMADATHIL
F7: Later of Due Date
A8: Line | D8: Begin | E8: Type of | F8: or Check Clear | G8: (Lead)/Lag | H8: Weighted Dollar
A9: No. | B9: Voucher | C9: Amount | D9: Date | E9: Begin Date | F9: Date | G9: Days | H9: Days
B10: (a) | C10: (b) | D10: (c) | E10: (d) | F10: (e) | G10: (f) | H10: (g)
A12: 1 | B12: M1494216 | C12: 13379 | D12: 45313 | E12: Invoice Date | F12: 45353 | G12: =D12-F12 -> -40 | H12: =IF(ISERR(G12*C12),"",G12*C12) -> -535160
A13: =A12+1 -> 2 | B13: M1470433 | C13: 12750 | D13: 45257 | E13: Midpoint of Benefit Period | F13: 45295 | G13: =D13-F13 -> -38 | H13: =IF(ISERR(G13*C13),"",G13*C13) -> -484500
A14: =A13+1 -> 3 | B14: 00681620 | C14: 24998.65 | D14: 45484.5 | E14: Midpoint of Benefit Period | F14: 45518 | G14: =D14-F14 -> -33.5 | H14: =IF(ISERR(G14*C14),"",G14*C14) -> -837454.78
A15: =A14+1 -> 4 | B15: M1468738 | C15: 13800.64 | D15: 45245.5 | E15: Midpoint of Benefit Period | F15: 45291 | G15: =D15-F15 -> -45.5 | H15: =IF(ISERR(G15*C15),"",G15*C15) -> -627929.12
A16: =A15+1 -> 5 | B16: M1613724 | C16: 17768.92 | D16: 45437.5 | E16: Midpoint of Benefit Period | F16: 45519 | G16: =D16-F16 -> -81.5 | H16: =IF(ISERR(G16*C16),"",G16*C16) -> -1448167
A17: =A16+1 -> 6 | B17: 00653111 | C17: 20301.82 | D17: 45274.5 | E17: Midpoint of Benefit Period | F17: 45301 | G17: =D17-F17 -> -26.5 | H17: =IF(ISERR(G17*C17),"",G17*C17) -> -537998.23
A18: =A17+1 -> 7 | B18: M1442179 | C18: 11742.64 | D18: 45216 | E18: Invoice Date | F18: 45246 | G18: =D18-F18 -> -30 | H18: =IF(ISERR(G18*C18),"",G18*C18) -> -352279.2
A19: =A18+1 -> 8 | B19: M1634300 | C19: 10658.07 | D19: 45519 | E19: Invoice Date | F19: 45549 | G19: =D19-F19 -> -30 | H19: =IF(ISERR(G19*C19),"",G19*C19) -> -319742.1
A20: =A19+1 -> 9 | B20: 00651339 | C20: 14289 | D20: 45266 | E20: Invoice Date | F20: 45314 | G20: =D20-F20 -> -48 | H20: =IF(ISERR(G20*C20),"",G20*C20) -> -685872
A21: =A20+1 -> 10 | B21: M1515075 | C21: 24263.8 | D21: 45322 | E21: Midpoint of Benefit Period | F21: 45360 | G21: =D21-F21 -> -38 | H21: =IF(ISERR(G21*C21),"",G21*C21) -> -922024.4
A22: =A21+1 -> 11 | B22: M1436330 | C22: 10473.72 | D22: 45201 | E22: Invoice Date | F22: 45239 | G22: =D22-F22 -> -38 | H22: =IF(ISERR(G22*C22),"",G22*C22) -> -398001.36
A23: =A22+1 -> 12 | B23: M1529360 | C23: 11730 | D23: 45307 | E23: Midpoint of Benefit Period | F23: 45373 | G23: =D23-F23 -> -66 | H23: =IF(ISERR(G23*C23),"",G23*C23) -> -774180
A24: =A23+1 -> 13 | B24: M1446368 | C24: 22060.58 | D24: 45218 | E24: Midpoint of Benefit Period | F24: 45260 | G24: =D24-F24 -> -42 | H24: =IF(ISERR(G24*C24),"",G24*C24) -> -926544.36
... A30: =A29+1 -> 19 | B30: M1434388 | C30: 17604.58 | D30: 45189 | E30: Midpoint of Benefit Period | F30: 45227 | G30: =D30-F30 -> -38 | H30: =IF(ISERR(G30*C30),"",G30*C30) -> -668974.04
A31: =A30+1 -> 20
A32: =A31+1 -> 21 | B32: Total | C32: =SUM(C12:C31) -> 310959.06 | G32: =+ROUND(H32/C32,2) -> -42.2 | H32: =SUM(H12:H31) -> -13122143
A33: =A32+1 -> 22
A34: =A33+1 -> 23 | B34: Source: | C34: 3rd party O&M - TRN sample .xlsx

Sheet 6-1-3
A1: 2025 RATE CASE
A2: ='1-1-3-1-1'!A2 -> ONCOR ELECTRIC DELIVERY COMPANY LLC
A3: NON-LABOR O&M - THIRD PARTY O&M SAMPLE - TRANSMISSION (STRATA 3: >$25,000)
A4: FOR THE LEAD-LAG STUDY-PERIOD ENDING SEPTEMBER 30, 2024
A5: SPONSOR: A. THENMADATHIL
F7: Later of Due Date
A8: Line | D8: Begin | E8: Type of | F8: or Check Clear | G8: (Lead)/Lag | H8: Weighted Dollar
A9: No. | B9: Voucher | C9: Amount | D9: Date | E9: Begin Date | F9: Date | G9: Days | H9: Days
B10: (a) | C10: (b) | D10: (c) | E10: (d) | F10: (e) | G10: (f) | H10: (g)
A12: 1 | B12: M1490389 | C12: 25038.4 | D12: 45273 | E12: Midpoint of Benefit Period | F12: 45314 | G12: =D12-F12 -> -41 | H12: =IF(ISERR(G12*C12),"",G12*C12) -> -1026574.4
A13: =+A12+1 -> 2 | B13: M1531048 | C13: 28910 | D13: 45360 | E13: Midpoint of Benefit Period | F13: 45396 | G13: =D13-F13 -> -36 | H13: =IF(ISERR(G13*C13),"",G13*C13) -> -1040760
A14: =+A13+1 -> 3 | B14: M1475240 | C14: 144571.04 | D14: 45474.5 | E14: Midpoint of Benefit Period | F14: 45335 | G14: =D14-F14 -> 139.5 | H14: =IF(ISERR(G14*C14),"",G14*C14) -> 20167660
A15: =+A14+1 -> 4 | B15: M1632118 | C15: 88400 | D15: 45490 | E15: Midpoint of Benefit Period | F15: 45530 | G15: =D15-F15 -> -40 | H15: =IF(ISERR(G15*C15),"",G15*C15) -> -3536000
A16: =+A15+1 -> 5 | B16: M1654081 | C16: 88087.85 | D16: 45539 | E16: Midpoint of Benefit Period | F16: 45572 | G16: =D16-F16 -> -33 | H16: =IF(ISERR(G16*C16),"",G16*C16) -> -2906899.1
A17: =+A16+1 -> 6 | B17: M1472905 | C17: 85934.22 | D17: 45231 | E17: Invoice Date | F17: 45280 | G17: =D17-F17 -> -49 | H17: =IF(ISERR(G17*C17),"",G17*C17) -> -4210776.8
A18: =+A17+1 -> 7 | B18: M1644341 | C18: 73000 | D18: 45436.5 | E18: removed from sample | F18: 45556 | G18: =D18-F18 -> -119.5 | H18: =IF(ISERR(G18*C18),"",G18*C18) -> -8723500
A19: =+A18+1 -> 8 | B19: 00641525 | C19: 40869.79 | D19: 45221.5 | E19: Midpoint of Benefit Period | F19: 45242 | G19: =D19-F19 -> -20.5 | H19: =IF(ISERR(G19*C19),"",G19*C19) -> -837830.7
A20: =+A19+1 -> 9 | B20: 00649379 | C20: 75000 | D20: 45259 | E20: Invoice Date | F20: 45268 | G20: =D20-F20 -> -9 | H20: =IF(ISERR(G20*C20),"",G20*C20) -> -675000
A21: =+A20+1 -> 10 | B21: 00658838 | C21: 42896.78 | D21: 45307 | E21: Midpoint of Benefit Period | F21: 45341 | G21: =D21-F21 -> -34 | H21: =IF(ISERR(G21*C21),"",G21*C21) -> -1458490.5
A22: =+A21+1 -> 11 | B22: M1478464 | C22: 198926.93 | D22: 45281 | E22: Invoice Date | F22: 45311 | G22: =D22-F22 -> -30 | H22: =IF(ISERR(G22*C22),"",G22*C22) -> -5967807.9
A23: =+A22+1 -> 12 | B23: M1614739 | C23: 37754 | D23: 45416 | E23: Midpoint of Benefit Period | F23: 45528 | G23: =D23-F23 -> -112 | H23: =IF(ISERR(G23*C23),"",G23*C23) -> -4228448
A24: =+A23+1 -> 13 | B24: M1451715 | C24: 26901.34 | D24: 45224 | E24: Midpoint of Benefit Period | F24: 45263 | G24: =D24-F24 -> -39 | H24: =IF(ISERR(G24*C24),"",G24*C24) -> -1049152.3
... A87: =+A86+1 -> 76 | B87: 00684359 | C87: 70823.32 | D87: 45508 | E87: Midpoint of Benefit Period | F87: 45517 | G87: =D87-F87 -> -9 | H87: =IF(ISERR(G87*C87),"",G87*C87) -> -637409.88
A88: =+A87+1 -> 77
A89: =+A88+1 -> 78 | B89: Subtotal | C89: =SUM(C12:C88) -> 4460898.5 | G89: =+ROUND(H89/C89,2) -> -51.29 | H89: =SUM(H12:H88) -> -2.2879577e+08
A90: =+A89+1 -> 79
A91: =+A90+1 -> 80 | B91: Source: | C91: 3rd party O&M - TRN sample.xlsx

Sheet 6-2
A1: 2025 RATE CASE
A2: =' '!A2 -> ONCOR ELECTRIC DELIVERY COMPANY LLC
A3: NON-LABOR O&M - THIRD PARTY O&M - DISTRIBUTION
A4: FOR THE LEAD-LAG STUDY-PERIOD ENDING SEPTEMBER 30, 2024
A5: SPONSOR: A. THENMADATHIL
A9: Line | C9: Population | D9: (Lead)/Lag | F9: Weighted
A10: No. | B10: Strata | C10: Dollars | D10: Days | E10: Reference | F10: Dollar Days
B11: (a) | C11: (b) | D11: (c) | E11: (d) | F11: (e)
A13: 1 | B13: Item Amount < $10,000 | C13: 1.2442204e+08 | D13: =+'6-2-1'!G45 -> -45.44 | E13: WP/II-B-9/6-2-1 | F13: =C13*D13 -> -5.6537377e+09
A14: =A13+1 -> 2 | B14: Item Amount_>= $10,000 and <= $25,000 | C14: 92127281 | D14: ='6-2-2'!G36 -> -56.63 | E14: WP/II-B-9/6-2-2 | F14: =C14*D14 -> -5.2171679e+09
A15: =A14+1 -> 3 | B15: Item Amount > $25,000 | C15: 5.098907e+08 | D15: ='6-2-3'!G143 -> -48.4 | E15: WP/II-B-9/6-2-3 | F15: =C15*D15 -> -2.467871e+10
A16: =A15+1 -> 4
A17: =A16+1 -> 5 | B17: Total | C17: =SUM(C13:C15) -> 7.2644002e+08 | D17: =+F17/C17 -> -48.936752 | F17: =SUM(F13:F15) -> -3.5549615e+10
A18: =A17+1 -> 6
A19: =A18+1 -> 7
A20: =A19+1 -> 8
A21: =A20+1 -> 9 | B21: Source: | C21: Lead Lag Sample.xlsx

Sheet 6-2-1
A1: 2025 RATE CASE
A2: ='1-1-3-1-1'!A2 -> ONCOR ELECTRIC DELIVERY COMPANY LLC
A3: NON-LABOR O&M - THIRD PARTY O&M SAMPLE - DISTRIBUTION (STRATA 1: <$10,000)
A4: FOR THE LEAD-LAG STUDY-PERIOD ENDING SEPTEMBER 30, 2024
A5: SPONSOR: A. THENMADATHIL
F7: Later of Due Date
A8: Line | D8: Begin | E8: Type of | F8: or Check Clear | G8: (Lead)/Lag | H8: Weighted Dollar
A9: No. | B9: Voucher | C9: Amount | D9: Date | E9: Begin Date | F9: Date | G9: Days | H9: Days
B10: (a) | C10: (b) | D10: (c) | E10: (d) | F10: (e) | G10: (f) | H10: (g)
A12: 1 | B12: M1569542 | C12: 40.67 | D12: 45414 | E12: Midpoint of Benefit Period | F12: 45457 | G12: =D12-F12 -> -43 | H12: =IF(ISERR(G12*C12),"",G12*C12) -> -1748.81
A13: 2 | B13: 00640508 | C13: 1732 | D13: 45189 | E13: Midpoint of Benefit Period | F13: 45239 | G13: =D13-F13 -> -50 | H13: =IF(ISERR(G13*C13),"",G13*C13) -> -86600
A14: 3 | B14: M1574543 | C14: 9118.2 | D14: 45409 | E14: Midpoint of Benefit Period | F14: 45463 | G14: =D14-F14 -> -54 | H14: =IF(ISERR(G14*C14),"",G14*C14) -> -492382.8
A15: 4 | B15: M1490747 | C15: 32.55 | D15: 45310 | E15: Invoice Date | F15: 45325 | G15: =D15-F15 -> -15 | H15: =IF(ISERR(G15*C15),"",G15*C15) -> -488.25
A16: 5 | B16: M1447965 | C16: 2.01 | D16: 45234 | E16: Invoice Date | F16: 45264 | G16: =D16-F16 -> -30 | H16: =IF(ISERR(G16*C16),"",G16*C16) -> -60.3
A17: 6 | B17: M1649606 | C17: 84.63 | D17: 45504 | E17: Midpoint of Benefit Period | F17: 45574 | G17: =D17-F17 -> -70 | H17: =IF(ISERR(G17*C17),"",G17*C17) -> -5924.1
A18: 7 | B18: M1619079 | C18: 255.43 | D18: 45418 | E18: Invoice Date | F18: 45513 | G18: =D18-F18 -> -95 | H18: =IF(ISERR(G18*C18),"",G18*C18) -> -24265.85
A19: 8 | B19: M1621645 | C19: 9096.8 | D19: 45458.5 | E19: Midpoint of Benefit Period | F19: 45532 | G19: =D19-F19 -> -73.5 | H19: =IF(ISERR(G19*C19),"",G19*C19) -> -668614.8
A20: 9 | B20: M1459434 | C20: 930.28 | D20: 45157 | E20: Invoice Date | F20: 45282 | G20: =D20-F20 -> -125 | H20: =IF(ISERR(G20*C20),"",G20*C20) -> -116285
A21: 10 | B21: M1429477 | C21: 306.07 | D21: 45206 | E21: Invoice Date | F21: 45236 | G21: =D21-F21 -> -30 | H21: =IF(ISERR(G21*C21),"",G21*C21) -> -9182.1
A22: 11 | B22: M1603287 | C22: 848.68 | D22: 45489 | E22: Invoice Date | F22: 45491 | G22: =D22-F22 -> -2 | H22: =IF(ISERR(G22*C22),"",G22*C22) -> -1697.36
A23: 12 | B23: M1414566 | C23: 1179.64 | D23: 45174 | E23: Invoice Date | F23: 45213 | G23: =D23-F23 -> -39 | H23: =IF(ISERR(G23*C23),"",G23*C23) -> -46005.96
... A43: 32 | B43: M1432060 | C43: 2565 | D43: 45195 | E43: Invoice Date | F43: 45234 | G43: =D43-F43 -> -39 | H43: =IF(ISERR(G43*C43),"",G43*C43) -> -100035
A44: 33
A45: 34 | B45: Total | C45: =SUM(C12:C44) -> 57332.19 | G45: =+ROUND(H45/C45,2) -> -45.44 | H45: =SUM(H12:H44) -> -2605063.5
A46: 35
A47: 36
A48: 37
A49: 38
A50: 39 | B50: Source: | C50: 3rd party O&M - ESD sample.xlsx

Sheet 6-2-2
A1: 2025 RATE CASE
A2: ='1-1-3-1-1'!A2 -> ONCOR ELECTRIC DELIVERY COMPANY LLC
A3: NON-LABOR O&M - THIRD PARTY O&M SAMPLE - DISTRIBUTION (STRATA 2: >=$10,000 AND <=$25,000)
A4: FOR THE LEAD-LAG STUDY-PERIOD ENDING SEPTEMBER 30, 2024
A5: SPONSOR: A. THENMADATHIL
F7: Later of Due Date
A8: Line | D8: Begin | E8: Type of | F8: or Check Clear | G8: (Lead)/Lag | H8: Weighted Dollar
A9: No. | B9: Voucher | C9: Amount | D9: Date | E9: Begin Date | F9: Date | G9: Days | H9: Days
B10: (a) | C10: (b) | D10: (c) | E10: (d) | F10: (e) | G10: (f) | H10: (g)
A12: 1 | B12: M1629327 | C12: 14508 | D12: 45501.5 | E12: Midpoint of Benefit Period | F12: 45546 | G12: =D12-F12 -> -44.5 | H12: =IF(ISERR(G12*C12),"",G12*C12) -> -645606
A13: =+A12+1 -> 2 | B13: 00650921 | C13: 14059.32 | D13: 45245.5 | E13: Midpoint of Benefit Period | F13: 45282 | G13: =D13-F13 -> -36.5 | H13: =IF(ISERR(G13*C13),"",G13*C13) -> -513165.18
A14: 3 | B14: M1537037 | C14: 12078.29 | D14: 45305 | E14: Midpoint of Benefit Period | F14: 45385 | G14: =D14-F14 -> -80 | H14: =IF(ISERR(G14*C14),"",G14*C14) -> -966263.2
A15: 4 | B15: M1613573 | C15: 10631.94 | D15: 45447 | E15: Midpoint of Benefit Period | F15: 45518 | G15: =D15-F15 -> -71 | H15: =IF(ISERR(G15*C15),"",G15*C15) -> -754867.74
A16: 5 | B16: M1597087 | C16: 12157.6 | D16: 45458 | E16: Midpoint of Benefit Period | F16: 45501 | G16: =D16-F16 -> -43 | H16: =IF(ISERR(G16*C16),"",G16*C16) -> -522776.8
A17: 6 | B17: 00653476 | C17: 14669.51 | D17: 45275 | E17: Invoice Date | F17: 45305 | G17: =D17-F17 -> -30 | H17: =IF(ISERR(G17*C17),"",G17*C17) -> -440085.3
A18: 7 | B18: M1607797 | C18: 15402.5 | D18: 45458.5 | E18: Midpoint of Benefit Period | F18: 45526 | G18: =D18-F18 -> -67.5 | H18: =IF(ISERR(G18*C18),"",G18*C18) -> -1039668.8
A19: 8 | B19: M1597781 | C19: 10908.56 | D19: 45455.5 | E19: Midpoint of Benefit Period | F19: 45512 | G19: =D19-F19 -> -56.5 | H19: =IF(ISERR(G19*C19),"",G19*C19) -> -616333.64
A20: 9 | B20: M1550804 | C20: 11609.44 | D20: 45378 | E20: Midpoint of Benefit Period | F20: 45417 | G20: =D20-F20 -> -39 | H20: =IF(ISERR(G20*C20),"",G20*C20) -> -452768.16
A21: 10 | B21: M1507747 | C21: 15129.54 | D21: 45307 | E21: Midpoint of Benefit Period | F21: 45370 | G21: =D21-F21 -> -63 | H21: =IF(ISERR(G21*C21),"",G21*C21) -> -953161.02
A22: 11 | B22: 00665903 | C22: 10620 | D22: 45307 | E22: Midpoint of Benefit Period | F22: 45371 | G22: =D22-F22 -> -64 | H22: =IF(ISERR(G22*C22),"",G22*C22) -> -679680
A23: 12 | B23: 00683506 | C23: 12500 | D23: 45489 | E23: Midpoint of Benefit Period | F23: 45511 | G23: =D23-F23 -> -22 | H23: =IF(ISERR(G23*C23),"",G23*C23) -> -275000
A24: 13 | B24: M1491151 | C24: 16230.4 | D24: 45287 | E24: Midpoint of Benefit Period | F24: 45338 | G24: =D24-F24 -> -51 | H24: =IF(ISERR(G24*C24),"",G24*C24) -> -827750.4
A25: 14 | B25: M1590982 | C25: 12333.15 | D25: 45442 | E25: Midpoint of Benefit Period | F25: 45492 | G25: =D25-F25 -> -50 | H25: =IF(ISERR(G25*C25),"",G25*C25) -> -616657.5
... A34: 23 | B34: M1574169 | C34: 10175.67 | D34: 45436 | E34: Invoice Date | F34: 45469 | G34: =D34-F34 -> -33 | H34: =IF(ISERR(G34*C34),"",G34*C34) -> -335797.11
A35: 24
A36: 25 | B36: Total | C36: =SUM(C12:C35) -> 309849.34 | G36: =+ROUND(H36/C36,2) -> -56.63 | H36: =SUM(H12:H34) -> -17547175
A37: 26
A38: 27
A39: 28
A40: 29
A41: 30 | B41: Source: | C41: 3rd party O&M - ESD sample.XLSX

Sheet 6-2-3
A1: 2025 RATE CASE
A2: ='1-1-3-1-1'!A2 -> ONCOR ELECTRIC DELIVERY COMPANY LLC
A3: NON-LABOR O&M - THIRD PARTY O&M SAMPLE - DISTRIBUTION (STRATA 3: >$25,000)
A4: FOR THE LEAD-LAG STUDY-PERIOD ENDING SEPTEMBER 30, 2024
A5: SPONSOR: A. THENMADATHIL
F7: Later of Due Date
A8: Line | D8: Begin | E8: Type of | F8: or Check Clear | G8: (Lead)/Lag | H8: Weighted Dollar
A9: No. | B9: Voucher | C9: Amount | D9: Date | E9: Begin Date | F9: Date | G9: Days | H9: Days
B10: (a) | C10: (b) | D10: (c) | E10: (d) | F10: (e) | G10: (f) | H10: (g)
A12: 1 | B12: M1527463 | C12: 125225.25 | D12: 45282.5 | E12: =IF(D12=B12,"Invoice Date", "Midpoint of Benefit Period") -> Midpoint of Benefit Period | F12: 45371 | G12: =D12-F12 -> -88.5 | H12: =IF(ISERR(G12*C12),"",G12*C12) -> -11082435
A13: 2 | B13: 00671243 | C13: 44147.81 | D13: 45392 | E13: =IF(D13=B13,"Invoice Date", "Midpoint of Benefit Period") -> Midpoint of Benefit Period | F13: 45433 | G13: =D13-F13 -> -41 | H13: =IF(ISERR(G13*C13),"",G13*C13) -> -1810060.2
A14: 3 | B14: M1631302 | C14: 69397.32 | D14: 45443 | E14: =IF(D14=B14,"Invoice Date", "Midpoint of Benefit Period") -> Midpoint of Benefit Period | F14: 45547 | G14: -8 | H14: =IF(ISERR(G14*C14),"",G14*C14) -> -555178.56
A15: 4 | B15: M1577956 | C15: 97313.1 | D15: 45336 | E15: =IF(D15=B15,"Invoice Date", "Midpoint of Benefit Period") -> Midpoint of Benefit Period | F15: 45450 | G15: =D15-F15 -> -114 | H15: =IF(ISERR(G15*C15),"",G15*C15) -> -11093693
A16: 5 | B16: M1610171 | C16: 100199.63 | D16: 45480.5 | E16: =IF(D16=B16,"Invoice Date", "Midpoint of Benefit Period") -> Midpoint of Benefit Period | F16: 45503 | G16: =D16-F16 -> -22.5 | H16: =IF(ISERR(G16*C16),"",G16*C16) -> -2254491.7
A17: 6 | B17: M1588622 | C17: 36737.86 | D17: 45397.5 | E17: =IF(D17=B17,"Invoice Date", "Midpoint of Benefit Period") -> Midpoint of Benefit Period | F17: 45469 | G17: =D17-F17 -> -71.5 | H17: =IF(ISERR(G17*C17),"",G17*C17) -> -2626757
A18: 7 | B18: M1567767 | C18: 58003.29 | D18: 45415.5 | E18: =IF(D18=B18,"Invoice Date", "Midpoint of Benefit Period") -> Midpoint of Benefit Period | F18: 45453 | G18: =D18-F18 -> -37.5 | H18: =IF(ISERR(G18*C18),"",G18*C18) -> -2175123.4
A19: 8 | B19: M1428240 | C19: 32706.59 | D19: 45120 | E19: =IF(D19=B19,"Invoice Date", "Midpoint of Benefit Period") -> Midpoint of Benefit Period | F19: 45210 | G19: =D19-F19 -> -90 | H19: =IF(ISERR(G19*C19),"",G19*C19) -> -2943593.1
A20: 9 | B20: M1428557 | C20: 26378.23 | D20: 45140 | E20: =IF(D20=B20,"Invoice Date", "Midpoint of Benefit Period") -> Midpoint of Benefit Period | F20: 45209 | G20: =D20-F20 -> -69 | H20: =IF(ISERR(G20*C20),"",G20*C20) -> -1820097.9
A21: 10 | B21: M1608283 | C21: 27426.6 | D21: 45427 | E21: =IF(D21=B21,"Invoice Date", "Midpoint of Benefit Period") -> Midpoint of Benefit Period | F21: 45499 | G21: =D21-F21 -> -72 | H21: =IF(ISERR(G21*C21),"",G21*C21) -> -1974715.2
A22: 11 | B22: M1613231 | C22: 33498.28 | D22: 45436.5 | E22: =IF(D22=B22,"Invoice Date", "Midpoint of Benefit Period") -> Midpoint of Benefit Period | F22: 45511 | G22: =D22-F22 -> -74.5 | H22: =IF(ISERR(G22*C22),"",G22*C22) -> -2495621.9
A23: 12 | B23: M1562816 | C23: 31075.78 | D23: 45410 | E23: =IF(D23=B23,"Invoice Date", "Midpoint of Benefit Period") -> Midpoint of Benefit Period | F23: 45444 | G23: =D23-F23 -> -34 | H23: =IF(ISERR(G23*C23),"",G23*C23) -> -1056576.5
A24: 13 | B24: M1437562 | C24: 54849.62 | D24: 45184.5 | E24: =IF(D24=B24,"Invoice Date", "Midpoint of Benefit Period") -> Midpoint of Benefit Period | F24: 45224 | G24: =D24-F24 -> -39.5 | H24: =IF(ISERR(G24*C24),"",G24*C24) -> -2166560
A25: 14 | B25: M1617758 | C25: 59026.42 | D25: 45436 | E25: =IF(D25=B25,"Invoice Date", "Midpoint of Benefit Period") -> Midpoint of Benefit Period | F25: 45524 | G25: =D25-F25 -> -88 | H25: =IF(ISERR(G25*C25),"",G25*C25) -> -5194325
A26: 15 | B26: M1634739 | C26: 69403.52 | D26: 45435 | E26: =IF(D26=B26,"Invoice Date", "Midpoint of Benefit Period") -> Midpoint of Benefit Period | F26: 45540 | G26: =D26-F26 -> -105 | H26: =IF(ISERR(G26*C26),"",G26*C26) -> -7287369.6
... A41: 30 | B41: M1654067 | C41: 270012 | D41: 45490 | E41: =IF(D41=B41,"Invoice Date", "Midpoint of Benefit Period") -> Midpoint of Benefit Period | F41: 45574 | G41: =D41-F41 -> -84 | H41: =IF(ISERR(G41*C41),"",G41*C41) -> -22681008
A42: 31 | B42: M1506044 | C42: 0 | D42: 0 | E42: =IF(D42=B42,"Invoice Date", "Midpoint of Benefit Period") -> Midpoint of Benefit Period | G42: =D42-F42 -> 0 | H42: =IF(ISERR(G42*C42),"",G42*C42) -> 0
A43: 32 | B43: M1630821 | C43: 62350 | D43: 45448.5 | E43: =IF(D43=B43,"Invoice Date", "Midpoint of Benefit Period") -> Midpoint of Benefit Period | F43: 45548 | G43: =D43-F43 -> -99.5 | H43: =IF(ISERR(G43*C43),"",G43*C43) -> -6203825
A44: =A43+1 -> 33 | B44: 00660121 | C44: 148426.83 | D44: 45307 | E44: =IF(D44=B44,"Invoice Date", "Midpoint of Benefit Period") -> Midpoint of Benefit Period | F44: 45352 | G44: =D44-F44 -> -45 | H44: =IF(ISERR(G44*C44),"",G44*C44) -> -6679207.3
A45: =A44+1 -> 34 | B45: M1613473 | C45: 91835 | D45: 45481.5 | E45: =IF(D45=B45,"Invoice Date", "Midpoint of Benefit Period") -> Midpoint of Benefit Period | F45: 45518 | G45: =D45-F45 -> -36.5 | H45: =IF(ISERR(G45*C45),"",G45*C45) -> -3351977.5
A46: =A45+1 -> 35 | B46: M1471291 | C46: 75110 | D46: 45266 | E46: =IF(D46=B46,"Invoice Date", "Midpoint of Benefit Period") -> Midpoint of Benefit Period | F46: 45299 | G46: =D46-F46 -> -33 | H46: =IF(ISERR(G46*C46),"",G46*C46) -> -2478630
A47: =A46+1 -> 36 | B47: 00645533 | C47: 120637.87 | D47: 45154 | E47: =IF(D47=B47,"Invoice Date", "Midpoint of Benefit Period") -> Midpoint of Benefit Period | F47: 45265 | G47: =D47-F47 -> -111 | H47: =IF(ISERR(G47*C47),"",G47*C47) -> -13390804
A48: =A47+1 -> 37 | B48: M1522004 | C48: 168750 | D48: 45336 | E48: =IF(D48=B48,"Invoice Date", "Midpoint of Benefit Period") -> Midpoint of Benefit Period | F48: 45371 | G48: =D48-F48 -> -35 | H48: =IF(ISERR(G48*C48),"",G48*C48) -> -5906250
A49: =A48+1 -> 38 | B49: M1631101 | C49: 26092.08 | D49: 45482 | E49: =IF(D49=B49,"Invoice Date", "Midpoint of Benefit Period") -> Midpoint of Benefit Period | F49: 45549 | G49: =D49-F49 -> -67 | H49: =IF(ISERR(G49*C49),"",G49*C49) -> -1748169.4
A50: =A49+1 -> 39 | B50: 00675203 | C50: 36684 | D50: 45428 | E50: =IF(D50=B50,"Invoice Date", "Midpoint of Benefit Period") -> Midpoint of Benefit Period | F50: 45443 | G50: =D50-F50 -> -15 | H50: =IF(ISERR(G50*C50),"",G50*C50) -> -550260
A51: =A50+1 -> 40 | B51: M1612543 | C51: 38296.44 | D51: 45445.5 | E51: =IF(D51=B51,"Invoice Date", "Midpoint of Benefit Period") -> Midpoint of Benefit Period | F51: 45528 | G51: =D51-F51 -> -82.5 | H51: =IF(ISERR(G51*C51),"",G51*C51) -> -3159456.3
A52: =A51+1 -> 41 | B52: 00661611 | C52: 42352 | D52: 45307 | E52: =IF(D52=B52,"Invoice Date", "Midpoint of Benefit Period") -> Midpoint of Benefit Period | F52: 45365 | G52: =D52-F52 -> -58 | H52: =IF(ISERR(G52*C52),"",G52*C52) -> -2456416
A53: =A52+1 -> 42 | B53: M1540814 | C53: 115478 | D53: 45371 | E53: =IF(D53=B53,"Invoice Date", "Midpoint of Benefit Period") -> Midpoint of Benefit Period | F53: 45404 | G53: =D53-F53 -> -33 | H53: =IF(ISERR(G53*C53),"",G53*C53) -> -3810774
A54: =A53+1 -> 43 | B54: M1614413 | C54: 45312.5 | D54: 45446 | E54: =IF(D54=B54,"Invoice Date", "Midpoint of Benefit Period") -> Midpoint of Benefit Period | F54: 45526 | G54: =D54-F54 -> -80 | H54: =IF(ISERR(G54*C54),"",G54*C54) -> -3625000
A55: =A54+1 -> 44 | B55: M1498160 | C55: 39655.05 | D55: 45307.5 | E55: =IF(D55=B55,"Invoice Date", "Midpoint of Benefit Period") -> Midpoint of Benefit Period | F55: 45348 | G55: =D55-F55 -> -40.5 | H55: =IF(ISERR(G55*C55),"",G55*C55) -> -1606029.5
... A141: =A140+1 -> 130 | B141: M1587051 | C141: 60974.52 | D141: 45429.5 | E141: =IF(D141=B141,"Invoice Date", "Midpoint of Benefit Period") -> Midpoint of Benefit Period | F141: 45467 | G141: =D141-F141 -> -37.5 | H141: =IF(ISERR(G141*C141),"",G141*C141) -> -2286544.5
A142: =A141+1 -> 131
A143: =A142+1 -> 132 | B143: Total | C143: =SUM(C12:C142) -> 13012318 | G143: =+ROUND(H143/C143,2) -> -48.4 | H143: =SUM(H12:H142) -> -6.2973396e+08
A144: =A143+1 -> 133
A145: =A144+1 -> 134
A146: =A145+1 -> 135
A147: =A146+1 -> 136
A148: =A147+1 -> 137 | B148: Source: | C148: 3rd party O&M - ESD sample.XLSX
A149: =A148+1 -> 138
A150: =A149+1 -> 139 | B150: not included in study due to voucher being cancelled and no payment needed

Sheet 6-3
A1: 2025 RATE CASE
A2: ='1-1-3-1-1'!A2 -> ONCOR ELECTRIC DELIVERY COMPANY LLC
A3: NON-LABOR O&M - THIRD PARTY O&M SAMPLE - CORPORATE (DETAIL)
A4: FOR THE LEAD-LAG STUDY-PERIOD ENDING SEPTEMBER 30, 2024
A5: SPONSOR: A. THENMADATHIL
F7: Later of Due Date
A8: Line | D8: Begin | E8: Type of | F8: or Check Clear | G8: (Lead)/Lag | H8: Weighted Dollar | J8: BU
A9: No. | B9: Voucher | C9: Amount | D9: Date | E9: Begin Date | F9: Date | G9: Days | H9: Days
B10: (a) | C10: (b) | D10: (c) | E10: (d) | F10: (e) | G10: (f) | H10: (g)
A12: 1 | B12: 00661289 | C12: 132.24 | D12: 45322 | E12: Invoice Date | F12: 45367 | G12: =D12-F12 -> -45 | H12: =IF(ISERR(G12*C12),"",G12*C12) -> -5950.8 | J12: TRNDS
A13: =A12+1 -> 2 | B13: 00689575 | C13: 3913.2 | D13: 45520 | E13: Midpoint of Benefit Period | F13: 45583 | G13: =D13-F13 -> -63 | H13: =IF(ISERR(G13*C13),"",G13*C13) -> -246531.6 | J13: TRNDS
A14: =A13+1 -> 3 | B14: 00682342 | C14: 9168.29 | D14: 45458.5 | E14: Midpoint of Benefit Period | F14: 45508 | G14: =D14-F14 -> -49.5 | H14: =IF(ISERR(G14*C14),"",G14*C14) -> -453830.36 | J14: TRNDS
A15: =A14+1 -> 4 | B15: 00648259 | C15: 520.03 | D15: 45276 | E15: Midpoint of Benefit Period | F15: 45265 | G15: =D15-F15 -> 11 | H15: =IF(ISERR(G15*C15),"",G15*C15) -> 5720.33 | J15: TRNDS
A16: =A15+1 -> 5 | B16: 00641206 | C16: 3786.97 | D16: 45184.5 | E16: Midpoint of Benefit Period | F16: 45247 | G16: =D16-F16 -> -62.5 | H16: =IF(ISERR(G16*C16),"",G16*C16) -> -236685.62 | J16: TRNDS
A17: =A16+1 -> 6 | B17: 00675620 | C17: 46061.13 | D17: 45626 | E17: Midpoint of Benefit Period | F17: 45483 | G17: =D17-F17 -> 143 | H17: =IF(ISERR(G17*C17),"",G17*C17) -> 6586741.6 | J17: TRNDS
A18: =A17+1 -> 7 | B18: 00687978 | C18: 40 | D18: 45503 | E18: Invoice Date | F18: 45574 | G18: =D18-F18 -> -71 | H18: =IF(ISERR(G18*C18),"",G18*C18) -> -2840 | J18: TRNDS
A19: =A18+1 -> 8 | B19: 00648299 | C19: 1081.5 | D19: 45276 | E19: Midpoint of Benefit Period | F19: 45272 | G19: =D19-F19 -> 4 | H19: =IF(ISERR(G19*C19),"",G19*C19) -> 4326 | J19: TRNDS
A20: =A19+1 -> 9 | B20: 00678815 | C20: 210 | D20: 44903 | E20: Invoice Date | F20: 45479 | G20: =D20-F20 -> -576 | H20: =IF(ISERR(G20*C20),"",G20*C20) -> -120960 | J20: TRNDS
A21: =A20+1 -> 10 | B21: 00685941 | C21: 7640.5 | D21: 45458.5 | E21: Midpoint of Benefit Period | F21: 45530 | G21: =D21-F21 -> -71.5 | H21: =IF(ISERR(G21*C21),"",G21*C21) -> -546295.75 | J21: TRNDS
A22: =A21+1 -> 11 | B22: 00671306 | C22: 12055.56 | D22: 45367 | E22: Midpoint of Benefit Period | F22: 45436 | G22: =D22-F22 -> -69 | H22: =IF(ISERR(G22*C22),"",G22*C22) -> -831833.64 | J22: TRNDS
A23: =A22+1 -> 12 | B23: 00662095 | C23: 3913.2 | D23: 45307 | E23: Midpoint of Benefit Period | F23: 45368 | G23: =D23-F23 -> -61 | H23: =IF(ISERR(G23*C23),"",G23*C23) -> -238705.2 | J23: TRNDS
A24: =A23+1 -> 13 | B24: 00676589 | C24: 6500 | D24: 45614 | E24: Midpoint of Benefit Period | F24: 45463 | G24: =D24-F24 -> 151 | H24: =IF(ISERR(G24*C24),"",G24*C24) -> 981500 | J24: TRNDS
... A35: =A34+1 -> 24 | B35: 00652159 | C35: 0.01 | D35: 43648 | E35: Midpoint of Benefit Period | F35: 45280 | G35: =D35-F35 -> -1632 | H35: =IF(ISERR(G35*C35),"",G35*C35) -> -16.32 | J35: NTUSU
A36: =A35+1 -> 25
A37: =A36+1 -> 26 | C37: =SUM(C12:C35) -> 1724828.1 | G37: =+ROUND(H37/C37,2) -> -58.47 | H37: =SUM(H12:H35) -> -1.0085228e+08
A38: =A37+1 -> 27
A39: =A38+1 -> 28 | B39: Source: | C39: 3rd party O&M - Corp sample

Sheet 6-4
A1: 2025 RATE CASE
A2: ONCOR ELECTRIC DELIVERY COMPANY LLC
A3: O&M EXPENDITURES - PENSION BENEFITS
A4: FOR THE LEAD-LAG STUDY-PERIOD ENDING SEPTEMBER 30, 2024
A5: SPONSOR: A. THENMADATHIL
F6: Benefit Period Dates
A7: Line No. | B7: Payment Date | C7: Payment Type | D7: Payment Amount | E7: % of Total | F7: Beginning | G7: Ending | H7: Benefit Period Mid-Point | I7: Payment (Lead)/Lag | J7: Weighted Dollar Days
B8: (a) | C8: (b) | D8: (c) | E8: (d) | F8: (e) | G8: (f) | H8: (g) | I8: (h) = (g) - (a) | J8: (i) = (c) * (h)
A9: 1 | B9: 45230 | C9: Supplemental Retirement Plan | D9: 385626.52 | E9: =+D9/$D$22 -> 0.081049096 | F9: 44927 | G9: 45291 | H9: =AVERAGE(F9:G9) -> 45109 | I9: =+H9-B9 -> -121 | J9: =+D9*I9 -> -46660809
A10: 2 | B10: 45260 | C10: Supplemental Retirement Plan | D10: 392653.03 | E10: =+D10/$D$22 -> 0.082525893 | F10: 44927 | G10: 45291 | H10: =AVERAGE(F10:G10) -> 45109 | I10: =+H10-B10 -> -151 | J10: =+D10*I10 -> -59290608
A11: 3 | B11: 45291 | C11: Supplemental Retirement Plan | D11: 389429.41 | E11: =+D11/$D$22 -> 0.081848369 | F11: 44927 | G11: 45291 | H11: =AVERAGE(F11:G11) -> 45109 | I11: =+H11-B11 -> -182 | J11: =+D11*I11 -> -70876153
A12: 4 | B12: 45322 | C12: Supplemental Retirement Plan | D12: 385780.14 | E12: =+D12/$D$22 -> 0.081081383 | F12: 45292 | G12: 45657 | H12: =AVERAGE(F12:G12) -> 45474.5 | I12: =+H12-B12 -> 152.5 | J12: =+D12*I12 -> 58831471
A13: 5 | B13: 45351 | C13: Supplemental Retirement Plan | D13: 384882.14 | E13: =+D13/$D$22 -> 0.080892646 | F13: 45292 | G13: 45657 | H13: =AVERAGE(F13:G13) -> 45474.5 | I13: =+H13-B13 -> 123.5 | J13: =+D13*I13 -> 47532944
A14: 6 | B14: 45382 | C14: Supplemental Retirement Plan | D14: 384882.14 | E14: =+D14/$D$22 -> 0.080892646 | F14: 45292 | G14: 45657 | H14: =AVERAGE(F14:G14) -> 45474.5 | I14: =+H14-B14 -> 92.5 | J14: =+D14*I14 -> 35601598
A15: 7 | B15: 45412 | C15: Supplemental Retirement Plan | D15: 386950.33 | E15: =+D15/$D$22 -> 0.081327328 | F15: 45292 | G15: 45657 | H15: =AVERAGE(F15:G15) -> 45474.5 | I15: =+H15-B15 -> 62.5 | J15: =+D15*I15 -> 24184396
A16: 8 | B16: 45443 | C16: Supplemental Retirement Plan | D16: 386950.33 | E16: =+D16/$D$22 -> 0.081327328 | F16: 45292 | G16: 45657 | H16: =AVERAGE(F16:G16) -> 45474.5 | I16: =+H16-B16 -> 31.5 | J16: =+D16*I16 -> 12188935
A17: 9 | B17: 45473 | C17: Supplemental Retirement Plan | D17: 389070.2 | E17: =+D17/$D$22 -> 0.081772872 | F17: 45292 | G17: 45657 | H17: =AVERAGE(F17:G17) -> 45474.5 | I17: =+H17-B17 -> 1.5 | J17: =+D17*I17 -> 583605.3
A18: 10 | B18: 45504 | C18: Supplemental Retirement Plan | D18: 409102.99 | E18: =+D18/$D$22 -> 0.085983265 | F18: 45292 | G18: 45657 | H18: =AVERAGE(F18:G18) -> 45474.5 | I18: =+H18-B18 -> -29.5 | J18: =+D18*I18 -> -12068538
A19: 11 | B19: 45535 | C19: Supplemental Retirement Plan | D19: 392502.93 | E19: =+D19/$D$22 -> 0.082494346 | F19: 45292 | G19: 45657 | H19: =AVERAGE(F19:G19) -> 45474.5 | I19: =+H19-B19 -> -60.5 | J19: =+D19*I19 -> -23746427
A20: 12 | B20: 45565 | C20: Supplemental Retirement Plan | D20: 470107.19 | E20: =+D20/$D$22 -> 0.09880483 | F20: 45292 | G20: 45657 | H20: =AVERAGE(F20:G20) -> 45474.5 | I20: =+H20-B20 -> -90.5 | J20: =+D20*I20 -> -42544701
A21: 17
A22: 18 | B22: Suppl. Payments and Weighted Dollar Days | D22: =SUM(D9:D21) -> 4757937.4 | E22: =SUM(E9:E21) -> 1 | J22: =SUM(J9:J21) -> -76264285
A23: 19 | B23: Weighted Average Payment Lead = Column (i), Line 18 divided by Column (c), Line 18 | I23: =+J22/D22 -> -16.028854
A24: 20
A25: 21 | B25: Retirement Plan (Pro Forma 2024)
A26: 22 | B26: 45397 | C26: Retirement Plan | D26: 21275000 | E26: =+D26/$D$31 -> 0.25 | F26: 45292 | G26: 45657 | H26: =AVERAGE(F26:G26) -> 45474.5 | I26: =+H26-B26 -> 77.5 | J26: =+D26*I26 -> 1648812500
A27: 23 | B27: 45488 | C27: Retirement Plan | D27: 21275000 | E27: =+D27/$D$31 -> 0.25 | F27: 45292 | G27: 45657 | H27: =AVERAGE(F27:G27) -> 45474.5 | I27: =+H27-B27 -> -13.5 | J27: =+D27*I27 -> -287212500
A28: 24 | B28: 45580 | C28: Retirement Plan | D28: 21275000 | E28: =+D28/$D$31 -> 0.25 | F28: 45292 | G28: 45657 | H28: =AVERAGE(F28:G28) -> 45474.5 | I28: =+H28-B28 -> -105.5 | J28: =+D28*I28 -> -2244512500
A29: 25 | B29: 45672 | C29: Retirement Plan | D29: 21275000 | E29: =+D29/$D$31 -> 0.25 | F29: 45292 | G29: 45657 | H29: =AVERAGE(F29:G29) -> 45474.5 | I29: =+H29-B29 -> -197.5 | J29: =+D29*I29 -> -4201812500
A30: 26
A31: 27 | B31: Retirement Payments and Weighted Dollar Days | D31: =SUM(D26:D30) -> 85100000 | E31: =SUM(E26:E29) -> 1 | J31: =SUM(J26:J30) -> -5084725000
A32: 28 | B32: Weighted Average Payment Lead = Column (i), Line 27 divided by Column (c), Line 27 | I32: =+J31/D31 -> -59.75
A33: 29
A34: 30
A35: 31 | B35: Total Payments and Weighted Dollar Days | D35: =+D31+D22 -> 89857937 | J35: =+J31+J22 -> -5.1609893e+09
A36: 32 | B36: Weighted Average Payment Lead = Column (i), Line 31 divided by Column (c), Line 31 | I36: =+J35/D35 -> -57.434985
A37: 33
A38: 34 | B38: Source: | C38: Pension and OPEB Funding.xlsx

Sheet 6-5
A1: 2025 RATE CASE
A2: ONCOR ELECTRIC DELIVERY COMPANY LLC
A3: O&M EXPENDITURES - OTHER POST-EMPLOYMENT BENEFITS
A4: FOR THE LEAD-LAG STUDY-PERIOD ENDING SEPTEMBER 30, 2024
A5: SPONSOR: A. THENMADATHIL
F6: Benefit Period Dates
A7: Line No. | B7: Payment Date | C7: Payment Type | D7: Payment Amount | E7: % of Total | F7: Beginning | G7: Ending | H7: Benefit Period Mid-Point | I7: Payment (Lead)/Lag | J7: Weighted Dollar Days
B8: (a) | C8: (b) | D8: (c) | E8: (d) | F8: (e) | G8: (f) | H8: (g) | I8: (h) = (g) - (a) | J8: (i) = (c) * (h)
A10: 1 | B10: 45203 | C10: OPEB-FAS 106 | D10: 1713470 | E10: =+D10/$D$22 -> 0.078158559 | F10: 45200 | G10: 45230 | H10: =AVERAGE(F10:G10) -> 45215 | I10: =+H10-B10 -> 12 | J10: =+D10*I10 -> 20561640
A11: =A10+1 -> 2 | B11: 45233 | C11: OPEB-FAS 106 | D11: 1713470 | E11: =+D11/$D$22 -> 0.078158559 | F11: 45231 | G11: 45260 | H11: =AVERAGE(F11:G11) -> 45245.5 | I11: =+H11-B11 -> 12.5 | J11: =+D11*I11 -> 21418375
A12: =A11+1 -> 3 | B12: 45267 | C12: OPEB-FAS 106 | D12: 1713472 | E12: =+D12/$D$22 -> 0.07815865 | F12: 45261 | G12: 45291 | H12: =AVERAGE(F12:G12) -> 45276 | I12: =+H12-B12 -> 9 | J12: =+D12*I12 -> 15421248
A13: =A12+1 -> 4 | B13: 45296 | C13: OPEB-FAS 106 | D13: 1713472 | E13: =+D13/$D$22 -> 0.07815865 | F13: 45292 | G13: 45322 | H13: =AVERAGE(F13:G13) -> 45307 | I13: =+H13-B13 -> 11 | J13: =+D13*I13 -> 18848192
A14: =A13+1 -> 5 | B14: 45328 | C14: OPEB-FAS 106 | D14: 1713472 | E14: =+D14/$D$22 -> 0.07815865 | F14: 45323 | G14: 45351 | H14: =AVERAGE(F14:G14) -> 45337 | I14: =+H14-B14 -> 9 | J14: =+D14*I14 -> 15421248
A15: =A14+1 -> 6 | B15: 45356 | C15: OPEB-FAS 106 | D15: 1907949 | E15: =+D15/$D$22 -> 0.087029562 | F15: 45352 | G15: 45382 | H15: =AVERAGE(F15:G15) -> 45367 | I15: =+H15-B15 -> 11 | J15: =+D15*I15 -> 20987439
A16: =A15+1 -> 7 | B16: 45386 | C16: OPEB-FAS 106 | D16: 1907949 | E16: =+D16/$D$22 -> 0.087029562 | F16: 45383 | G16: 45412 | H16: =AVERAGE(F16:G16) -> 45397.5 | I16: =+H16-B16 -> 11.5 | J16: =+D16*I16 -> 21941413
A17: =A16+1 -> 8 | B17: 45418 | C17: OPEB-FAS 106 | D17: 1907949 | E17: =+D17/$D$22 -> 0.087029562 | F17: 45413 | G17: 45443 | H17: =AVERAGE(F17:G17) -> 45428 | I17: =+H17-B17 -> 10 | J17: =+D17*I17 -> 19079490
A18: =A17+1 -> 9 | B18: 45449 | C18: OPEB-FAS 106 | D18: 1907949 | E18: =+D18/$D$22 -> 0.087029562 | F18: 45444 | G18: 45473 | H18: =AVERAGE(F18:G18) -> 45458.5 | I18: =+H18-B18 -> 9.5 | J18: =+D18*I18 -> 18125515
A19: =A18+1 -> 10 | B19: 45478 | C19: OPEB-FAS 106 | D19: 1907949 | E19: =+D19/$D$22 -> 0.087029562 | F19: 45474 | G19: 45504 | H19: =AVERAGE(F19:G19) -> 45489 | I19: =+H19-B19 -> 11 | J19: =+D19*I19 -> 20987439
A20: =A19+1 -> 11 | B20: 45509 | C20: OPEB-FAS 106 | D20: 1907949 | E20: =+D20/$D$22 -> 0.087029562 | F20: 45505 | G20: 45535 | H20: =AVERAGE(F20:G20) -> 45520 | I20: =+H20-B20 -> 11 | J20: =+D20*I20 -> 20987439
A21: =A20+1 -> 12 | B21: 45540 | C21: OPEB-FAS 106 | D21: 1907949 | E21: =+D21/$D$22 -> 0.087029562 | F21: 45536 | G21: 45565 | H21: =AVERAGE(F21:G21) -> 45550.5 | I21: =+H21-B21 -> 10.5 | J21: =+D21*I21 -> 20033464
A22: =A21+1 -> 13 | B22: Total Payments and Weighted Dollar Days | D22: =SUM(D10:D21) -> 21922999 | E22: =SUM(E10:E21) -> 1 | J22: =SUM(J10:J21) -> 2.338129e+08
A23: =A22+1 -> 14 | B23: Weighted Average Payment Lead = Column (i), Line 13 divided by Column (c), Line 13 | I23: =+J22/D22 -> 10.665188
A24: =A23+1 -> 15
A25: =A24+1 -> 16 | B25: Source: | C25: Pension and OPEB Funding.xlsx

Sheet 7
A1: 2025 RATE CASE
A2: =' '!A2 -> ONCOR ELECTRIC DELIVERY COMPANY LLC
A3: FEDERAL INCOME TAX LEAD DAYS
A4: FOR THE LEAD-LAG STUDY-PERIOD ENDING SEPTEMBER 30, 2024
A5: SPONSOR: A. THENMADATHIL
E7: Statutory %
A8: Line | B8: Statutory Payment | D8: (Lead)/Lag | E8: of Total | F8: Weighted
A9: No. | B9: Due Date | C9: Mid-Year | D9: Days | E9: Taxes for Year | F9: Days
B10: (a) | C10: (b) | D10: (c) | E10: (d) | F10: (e)
A12: 1 | B12: 45275 | C12: 45108 | D12: =C12-B12 -> -167 | E12: 0.25 | F12: =D12*E12 -> -41.75
A13: =A12+1 -> 2
A14: =A13+1 -> 3 | B14: 45397 | C14: 45474 | D14: =C14-B14 -> 77 | E14: 0.25 | F14: =D14*E14 -> 19.25
A15: =A14+1 -> 4
A16: =A15+1 -> 5 | B16: 45458 | C16: =+C14 -> 45474 | D16: =C16-B16 -> 16 | E16: 0.25 | F16: =D16*E16 -> 4
A17: =A16+1 -> 6
A18: =A17+1 -> 7 | B18: 45550 | C18: =C16 -> 45474 | D18: =C18-B18 -> -76 | E18: 0.25 | F18: =D18*E18 -> -19
A19: =A18+1 -> 8
A20: =A19+1 -> 9 | B20: Total | F20: =ROUND(SUM(F12:F18),2) -> -37.5
A21: =A20+1 -> 10
A22: =A21+1 -> 11
A23: =A22+1 -> 12
A24: =A23+1 -> 13 | B24: Source: | C24: FIT Payment Dates.pdf

Sheet 8
A1: 2025 RATE CASE
A2: =' '!A2 -> ONCOR ELECTRIC DELIVERY COMPANY LLC
A3: PAYROLL TAX LEAD DAY CALCULATION
A4: FOR THE LEAD-LAG STUDY-PERIOD ENDING SEPTEMBER 30, 2024
A5: SPONSOR: A. THENMADATHIL
E7: Weighted
A8: Line | D8: (Lead)/Lag | E8: Dollar
A9: No. | B9: Description | C9: Amount | D9: Days | E9: Days | F9: Reference
B10: (a) | C10: (b) | D10: (c) | E10: (d) | F10: (e)
A12: 1 | B12: FICA | C12: ='8-1'!C90 -> 60030179 | D12: ='8-1'!E90 -> -12 | E12: ='8-1'!F90 -> -7.2036214e+08 | F12: WP/II-B-9/8-1
A13: =A12+1 -> 2
A14: =A13+1 -> 3 | B14: Federal & State Unemployment | C14: ='8-2'!E76 -> 534020.05 | D14: =+'8-2'!K76 -> 48.41 | E14: =+'8-2'!L76 -> 25852134 | F14: WP/II-B-9/8-2
A15: =A14+1 -> 4
A16: =A15+1 -> 5 | B16: Total Payroll Related Taxes | C16: =SUM(C12:C14) -> 60564199 | D16: =ROUND(E16/C16,2) -> -11.47 | E16: =SUM(E12:E14) -> -6.9451001e+08

Sheet 8-1
A1: 2025 RATE CASE
A2: =' '!A2 -> ONCOR ELECTRIC DELIVERY COMPANY LLC
A3: PAYROLL TAXES - FICA TAX LEAD DAY CALCULATION - DISTRIBUTION
A4: FOR THE LEAD-LAG STUDY-PERIOD ENDING SEPTEMBER 30, 2024
A5: SPONSOR: A. THENMADATHIL
A7: Line | B7: Payroll | C7: FICA | D7: Deposit | F7: Weighted
A8: No. | B8: Check Date | C8: Amount | D8: Date | E8: (Lead)/Lag | F8: Dollar Days
B9: (a) | C9: (b) | D9: (c) | E9: (d) | F9: (e)
A11: 1 | B11: 45204 | C11: 280641.83 | D11: 45204 | E11: =IF(C11=0,0,-(D11-B11)) -> 0 | F11: =C11*E11 -> 0
A12: =A11+1 -> 2 | B12: 45201 | C12: 33.12 | D12: 45201 | E12: =IF(C12=0,0,-(D12-B12)) -> 0 | F12: =C12*E12 -> 0
A13: =A12+1 -> 3 | B13: 45205 | C13: 26503.9 | D13: 45205 | E13: =IF(C13=0,0,-(D13-B13)) -> 0 | F13: =C13*E13 -> 0
A14: =A13+1 -> 4 | B14: 45211 | C14: 907873.78 | D14: 45211 | E14: =IF(C14=0,0,-(D14-B14)) -> 0 | F14: =C14*E14 -> 0
A15: =A14+1 -> 5 | B15: 45219 | C15: 825.32 | D15: 45219 | E15: =IF(C15=0,0,-(D15-B15)) -> 0 | F15: =C15*E15 -> 0
A16: =A15+1 -> 6 | B16: 45218 | C16: 273097.52 | D16: 45218 | E16: =IF(C16=0,0,-(D16-B16)) -> 0 | F16: =C16*E16 -> 0
A17: =A16+1 -> 7 | B17: 45223 | C17: 1431.69 | D17: 45223 | E17: =IF(C17=0,0,-(D17-B17)) -> 0 | F17: =C17*E17 -> 0
A18: =A17+1 -> 8 | B18: 45229 | C18: 828634.92 | D18: 45229 | E18: =IF(C18=0,0,-(D18-B18)) -> 0 | F18: =C18*E18 -> 0
A19: =A18+1 -> 9 | B19: 45232 | C19: 247882.29 | D19: 45232 | E19: =IF(C19=0,0,-(D19-B19)) -> 0 | F19: =C19*E19 -> 0
A20: =A19+1 -> 10 | B20: 45244 | C20: 855859.01 | D20: 45244 | E20: =IF(C20=0,0,-(D20-B20)) -> 0 | F20: =C20*E20 -> 0
A21: =A20+1 -> 11 | B21: 45246 | C21: 219348.71 | D21: 45246 | E21: =IF(C21=0,0,-(D21-B21)) -> 0 | F21: =C21*E21 -> 0
A22: =A21+1 -> 12 | B22: 45247 | C22: 1695.56 | D22: 45247 | E22: =IF(C22=0,0,-(D22-B22)) -> 0 | F22: =C22*E22 -> 0
A23: =A22+1 -> 13 | B23: 45260 | C23: 195194.02 | D23: 45260 | E23: =IF(C23=0,0,-(D23-B23)) -> 0 | F23: =C23*E23 -> 0
... A81: =A80+1 -> 71 | B81: 45558 | C81: 1048410.6 | D81: 45558 | E81: =IF(C81=0,0,-(D81-B81)) -> 0 | F81: =C81*E81 -> 0
A82: =A81+1 -> 72 | B82: Total Distribution | C82: =SUM(C11:C81) -> 40852149 | E82: =ROUND(F82/C82,2) -> 0 | F82: =SUM(F11:F81) -> 0
A83: =A82+1 -> 73
A84: =A83+1 -> 74 | B84: Transmission (WP/II-B-9/8-1-2) | C84: ='8-1-2'!C57 -> 19178029 | E84: =ROUND(F84/C84,2) -> 0 | F84: ='8-1-2'!F57 -> 0
A85: =A84+1 -> 75
A86: =A85+1 -> 76 | B86: Total Transmission & Distribution | C86: =C82+C84 -> 60030179 | E86: =ROUND(F86/C86,2) -> 0 | F86: =F82+F84 -> 0
A87: =A86+1 -> 77
A88: =A87+1 -> 78 | B88: Lead Days from Midpoint to Payroll Payment Date | E88: =ROUND(+'2'!F18,2) -> -12 | F88: WP/II-B-9/2
A89: =A88+1 -> 79
A90: =A89+1 -> 80 | B90: Total Lead Days | C90: =C86 -> 60030179 | E90: =E86+E88 -> -12 | F90: =C90*E90 -> -7.2036214e+08
A91: =A90+1 -> 81
A92: =A91+1 -> 82 | B92: Source: | C92: Tax Other Than Income - Payroll Taxes.xlsx

Sheet 8-1-2
A1: 2025 RATE CASE
A2: =' '!A2 -> ONCOR ELECTRIC DELIVERY COMPANY LLC
A3: PAYROLL TAXES - FICA TAX LEAD DAY CALCULATION - TRANSMISSION
A4: FOR THE LEAD-LAG STUDY-PERIOD ENDING SEPTEMBER 30, 2024
A5: SPONSOR: A. THENMADATHIL
A7: Line | B7: Payroll | C7: FICA | D7: Deposit | F7: Weighted
A8: No. | B8: Check Date | C8: Amount | D8: Date | E8: (Lead)/Lag | F8: Dollar Days
B9: (a) | C9: (b) | D9: (c) | E9: (d) | F9: (e)
A11: 1 | B11: 45211 | C11: 463582.5 | D11: 45211 | E11: =IF(C11=0,0,-(D11-B11)) -> 0 | F11: =C11*E11 -> 0
A12: =A11+1 -> 2 | B12: 45229 | C12: 480367.57 | D12: 45229 | E12: =IF(C12=0,0,-(D12-B12)) -> 0 | F12: =C12*E12 -> 0
A13: =A12+1 -> 3 | B13: 45244 | C13: 445271.16 | D13: 45244 | E13: =IF(C13=0,0,-(D13-B13)) -> 0 | F13: =C13*E13 -> 0
A14: =A13+1 -> 4 | B14: 45259 | C14: 433688.53 | D14: 45259 | E14: =IF(C14=0,0,-(D14-B14)) -> 0 | F14: =C14*E14 -> 0
A15: =A14+1 -> 5 | B15: 45264 | C15: 1.65 | D15: 45264 | E15: =IF(C15=0,0,-(D15-B15)) -> 0 | F15: =C15*E15 -> 0
A16: =A15+1 -> 6 | B16: 45274 | C16: 411694.7 | D16: 45274 | E16: =IF(C16=0,0,-(D16-B16)) -> 0 | F16: =C16*E16 -> 0
A17: =A16+1 -> 7 | B17: 45286 | C17: 2000.75 | D17: 45286 | E17: =IF(C17=0,0,-(D17-B17)) -> 0 | F17: =C17*E17 -> 0
A18: =A17+1 -> 8 | B18: 45288 | C18: 371024.75 | D18: 45288 | E18: =IF(C18=0,0,-(D18-B18)) -> 0 | F18: =C18*E18 -> 0
A19: =A18+1 -> 9 | B19: 45289 | C19: 887.33 | D19: 45289 | E19: =IF(C19=0,0,-(D19-B19)) -> 0 | F19: =C19*E19 -> 0
A20: =A19+1 -> 10 | B20: 45302 | C20: 427208.65 | D20: 45302 | E20: =IF(C20=0,0,-(D20-B20)) -> 0 | F20: =C20*E20 -> 0
A21: =A20+1 -> 11 | B21: 45309 | C21: 138.39 | D21: 45309 | E21: =IF(C21=0,0,-(D21-B21)) -> 0 | F21: =C21*E21 -> 0
A22: =A21+1 -> 12 | B22: 45303 | C22: 56213.28 | D22: 45303 | E22: =IF(C22=0,0,-(D22-B22)) -> 0 | F22: =C22*E22 -> 0
A23: =A22+1 -> 13 | B23: 45316 | C23: 478734.23 | D23: 45316 | E23: =IF(C23=0,0,-(D23-B23)) -> 0 | F23: =C23*E23 -> 0
... A55: =A54+1 -> 45 | B55: 45558 | C55: 2832281.1 | D55: 45558 | E55: =IF(C55=0,0,-(D55-B55)) -> 0 | F55: =C55*E55 -> 0
A56: =A55+1 -> 46
A57: =A56+1 -> 47 | B57: Total | C57: =SUM(C11:C56) -> 19178029 | E57: =ROUND(F57/C57,2) -> 0 | F57: =SUM(F11:F56) -> 0
A58: =A57+1 -> 48
A59: =A58+1 -> 49 | B59: Source: | C59: Taxes Other Than Income - Payroll Taxes.xlsx

Sheet 8-2
A1: 2025 RATE CASE
A2: =' '!A2 -> ONCOR ELECTRIC DELIVERY COMPANY LLC
A3: PAYROLL TAXES - FEDERAL AND STATE UNEMPLOYMENT TAX LEAD DAY CALCULATION - DISTRIBUTION
A4: FOR THE LEAD-LAG STUDY-PERIOD ENDING SEPTEMBER 30, 2024
A5: SPONSOR: A. THENMADATHIL
A7: Line | B7: Payroll | C7: FUTA | D7: SUTA | E7: Total | F7: Deposit | G7: Service Period | L7: Weighted
A8: No. | B8: Check Date | C8: Amount | D8: Amount | E8: Amount | F8: Date | G8: Beginning | H8: Ending | I8: Mid-Point | J8: Due Date | K8: (Lead)/Lag | L8: Dollar Days
B9: (a) | C9: (b) | D9: (c) | E9: (d) | F9: (e) | G9: (f) | H9: (g) | I9: (h) | J9: (i) | K9: (j) = (h) - (i) | L9: (k) = (d) * (j)
A11: 1 | B11: 45204 | C11: 21.47 | D11: 26.29 | E11: =D11+C11 -> 47.76 | F11: 45204 | G11: 44927 | H11: 45291 | I11: =+(G11+H11)/2 -> 45109 | J11: 45322 | K11: =I11-J11 -> -213 | L11: =E11*K11 -> -10172.88
A12: =A11+1 -> 2 | B12: 45205 | C12: 0 | D12: 3.23 | E12: =D12+C12 -> 3.23 | F12: 45205 | G12: 44927 | H12: 45291 | I12: =+(G12+H12)/2 -> 45109 | J12: 45322 | K12: =I12-J12 -> -213 | L12: =E12*K12 -> -687.99
A13: =A12+1 -> 3 | B13: 45211 | C13: 374.01 | D13: 499.25 | E13: =D13+C13 -> 873.26 | F13: 45211 | G13: 44927 | H13: 45291 | I13: =+(G13+H13)/2 -> 45109 | J13: 45322 | K13: =I13-J13 -> -213 | L13: =E13*K13 -> -186004.38
A14: =A13+1 -> 4 | B14: 45212 | C14: 0 | D14: 18.95 | E14: =D14+C14 -> 18.95 | F14: 45212 | G14: 44927 | H14: 45291 | I14: =+(G14+H14)/2 -> 45109 | J14: 45322 | K14: =I14-J14 -> -213 | L14: =E14*K14 -> -4036.35
A15: =A14+1 -> 5 | B15: 45218 | C15: 11.16 | D15: 17.68 | E15: =D15+C15 -> 28.84 | F15: 45218 | G15: 44927 | H15: 45291 | I15: =+(G15+H15)/2 -> 45109 | J15: 45322 | K15: =I15-J15 -> -213 | L15: =E15*K15 -> -6142.92
A16: =A15+1 -> 6 | B16: 45219 | C16: 18.45 | D16: 18.74 | E16: =D16+C16 -> 37.19 | F16: 45219 | G16: 44927 | H16: 45291 | I16: =+(G16+H16)/2 -> 45109 | J16: 45322 | K16: =I16-J16 -> -213 | L16: =E16*K16 -> -7921.47
A17: =A16+1 -> 7 | B17: 45229 | C17: 371.06 | D17: 472.3 | E17: =D17+C17 -> 843.36 | F17: 45229 | G17: 44927 | H17: 45291 | I17: =+(G17+H17)/2 -> 45109 | J17: 45322 | K17: =I17-J17 -> -213 | L17: =E17*K17 -> -179635.68
A18: =A17+1 -> 8 | B18: 45232 | C18: 79.92 | D18: 90.17 | E18: =D18+C18 -> 170.09 | F18: 45232 | G18: 44927 | H18: 45291 | I18: =+(G18+H18)/2 -> 45109 | J18: 45322 | K18: =I18-J18 -> -213 | L18: =E18*K18 -> -36229.17
A19: =A18+1 -> 9 | B19: 45244 | C19: 397.26 | D19: 584.8 | E19: =D19+C19 -> 982.06 | F19: 45244 | G19: 44927 | H19: 45291 | I19: =+(G19+H19)/2 -> 45109 | J19: 45322 | K19: =I19-J19 -> -213 | L19: =E19*K19 -> -209178.78
A20: =A19+1 -> 10 | B20: 45246 | C20: 70.67 | D20: 88.03 | E20: =D20+C20 -> 158.7 | F20: 45246 | G20: 44927 | H20: 45291 | I20: =+(G20+H20)/2 -> 45109 | J20: 45322 | K20: =I20-J20 -> -213 | L20: =E20*K20 -> -33803.1
A21: =A20+1 -> 11 | B21: 45247 | C21: 18.42 | D21: 18.74 | E21: =D21+C21 -> 37.16 | F21: 45247 | G21: 44927 | H21: 45291 | I21: =+(G21+H21)/2 -> 45109 | J21: 45322 | K21: =I21-J21 -> -213 | L21: =E21*K21 -> -7915.08
A22: =A21+1 -> 12 | B22: 45259 | C22: 423.29 | D22: 549.54 | E22: =D22+C22 -> 972.83 | F22: 45259 | G22: 44927 | H22: 45291 | I22: =+(G22+H22)/2 -> 45109 | J22: 45322 | K22: =I22-J22 -> -213 | L22: =E22*K22 -> -207212.79
A23: =A22+1 -> 13 | B23: 45260 | C23: 99.93 | D23: 113.96 | E23: =D23+C23 -> 213.89 | F23: 45260 | G23: 44927 | H23: 45291 | I23: =+(G23+H23)/2 -> 45109 | J23: 45322 | K23: =I23-J23 -> -213 | L23: =E23*K23 -> -45558.57
... A68: =A67+1 -> 58 | B68: 45554 | C68: 674.67 | D68: 890.84 | E68: =D68+C68 -> 1565.51 | F68: 45554 | G68: 45292 | H68: 45657 | I68: =+(G68+H68)/2 -> 45474.5 | J68: 45596 | K68: =I68-J68 -> -121.5 | L68: =E68*K68 -> -190209.46
A69: =A68+1 -> 59
A70: =A69+1 -> 60 | B70: Total Distrib. | C70: =SUM(C11:C69) -> 171839.33 | D70: =SUM(D11:D69) -> 223610.83 | E70: =SUM(E11:E69) -> 395450.16 | K70: =ROUND(L70/E70,2) -> 49.21 | L70: =SUM(L11:L69) -> 19460903
A71: =A70+1 -> 61
A72: =A71+1 -> 62
A73: =A72+1 -> 63 | B73: Transmission (WP/II-B-9/8-1-2) | E73: =+'8-2-1'!E46 -> 138569.89 | K73: =ROUND(L73/E73,2) -> 46.12 | L73: =+'8-2-1'!L46 -> 6391231.7
A74: =A73+1 -> 64
A75: =A74+1 -> 65
A76: =A75+1 -> 66 | B76: Total Transmission & Distribution | E76: =+E73+E70 -> 534020.05 | K76: =ROUND(L76/E76,2) -> 48.41 | L76: =+L73+L70 -> 25852134
A77: =A76+1 -> 67
A78: =A77+1 -> 68
A79: =A78+1 -> 69 | B79: Source: | C79: Tax Other Than Income - Payroll Taxes.xlsx

Sheet 8-2-1
A1: 2025 RATE CASE
A2: =' '!A2 -> ONCOR ELECTRIC DELIVERY COMPANY LLC
A3: PAYROLL TAXES - FEDERAL AND STATE UNEMPLOYMENT TAX LEAD DAY CALCULATION - TRANSMISSION
A4: FOR THE LEAD-LAG STUDY-PERIOD ENDING SEPTEMBER 30, 2024
A5: SPONSOR: A. THENMADATHIL
A7: Line | B7: Payroll | C7: FUTA | D7: SUTA | E7: Total | F7: Deposit | G7: Service Period | L7: Weighted
A8: No. | B8: Check Date | C8: Amount | D8: Amount | E8: Amount | F8: Date | G8: Beginning | H8: Ending | I8: Mid-Point | J8: Due Date | K8: (Lead)/Lag | L8: Dollar Days
B9: (a) | C9: (b) | D9: (c) | E9: (d) | F9: (e) | G9: (f) | H9: (g) | I9: (h) | J9: (i) | K9: (j) = (h) - (i) | L9: (k) = (d) * (j)
A11: 1 | B11: 45211 | C11: 84.68 | D11: 133.97 | E11: =D11+C11 -> 218.65 | F11: 45211 | G11: 44927 | H11: 45291 | I11: =+(G11+H11)/2 -> 45109 | J11: 45322 | K11: =+I11-J11 -> -213 | L11: =E11*K11 -> -46572.45
A12: =A11+1 -> 2 | B12: 45229 | C12: 163.4 | D12: 202.04 | E12: =D12+C12 -> 365.44 | F12: 45229 | G12: 44927 | H12: 45291 | I12: =+(G12+H12)/2 -> 45109 | J12: 45322 | K12: =+I12-J12 -> -213 | L12: =E12*K12 -> -77838.72
A13: =A12+1 -> 3 | B13: 45244 | C13: 81.37 | D13: 117.81 | E13: =D13+C13 -> 199.18 | F13: 45244 | G13: 44927 | H13: 45291 | I13: =+(G13+H13)/2 -> 45109 | J13: 45322 | K13: =+I13-J13 -> -213 | L13: =E13*K13 -> -42425.34
A14: =A13+1 -> 4 | B14: 45259 | C14: 85.13 | D14: 125.22 | E14: =D14+C14 -> 210.35 | F14: 45259 | G14: 44927 | H14: 45291 | I14: =+(G14+H14)/2 -> 45109 | J14: 45322 | K14: =+I14-J14 -> -213 | L14: =E14*K14 -> -44804.55
A15: =A14+1 -> 5 | B15: 45274 | C15: 111.07 | D15: 135.04 | E15: =D15+C15 -> 246.11 | F15: 45274 | G15: 44927 | H15: 45291 | I15: =+(G15+H15)/2 -> 45109 | J15: 45322 | K15: =+I15-J15 -> -213 | L15: =E15*K15 -> -52421.43
A16: =A15+1 -> 6 | B16: 45286 | C16: 37.75 | D16: 38.4 | E16: =D16+C16 -> 76.15 | F16: 45286 | G16: 44927 | H16: 45291 | I16: =+(G16+H16)/2 -> 45109 | J16: 45322 | K16: =+I16-J16 -> -213 | L16: =E16*K16 -> -16219.95
A17: =A16+1 -> 7 | B17: 45288 | C17: 208 | D17: 225.13 | E17: =D17+C17 -> 433.13 | F17: 45288 | G17: 44927 | H17: 45291 | I17: =+(G17+H17)/2 -> 45109 | J17: 45322 | K17: =+I17-J17 -> -213 | L17: =E17*K17 -> -92256.69
A18: =A17+1 -> 8 | B18: 45302 | C18: 32804.37 | D18: 35105.01 | E18: =D18+C18 -> 67909.38 | F18: 45302 | G18: 45292 | H18: 45657 | I18: =+(G18+H18)/2 -> 45474.5 | J18: 45412 | K18: =+I18-J18 -> 62.5 | L18: =E18*K18 -> 4244336.2
A19: =A18+1 -> 9 | B19: 45309 | C19: 9.94 | D19: 0 | E19: =D19+C19 -> 9.94 | F19: 45309 | G19: 45292 | H19: 45657 | I19: =+(G19+H19)/2 -> 45474.5 | J19: 45412 | K19: =+I19-J19 -> 62.5 | L19: =E19*K19 -> 621.25
A20: =A19+1 -> 10 | B20: 45303 | C20: 586.56 | D20: 850.36 | E20: =D20+C20 -> 1436.92 | F20: 45303 | G20: 45292 | H20: 45657 | I20: =+(G20+H20)/2 -> 45474.5 | J20: 45412 | K20: =+I20-J20 -> 62.5 | L20: =E20*K20 -> 89807.5
A21: =A20+1 -> 11 | B21: 45316 | C21: 16017.36 | D21: 25896.81 | E21: =D21+C21 -> 41914.17 | F21: 45316 | G21: 45292 | H21: 45657 | I21: =+(G21+H21)/2 -> 45474.5 | J21: 45412 | K21: =+I21-J21 -> 62.5 | L21: =E21*K21 -> 2619635.6
A22: =A21+1 -> 12 | B22: 45323 | C22: 84.7 | D22: 90.17 | E22: =D22+C22 -> 174.87 | F22: 45323 | G22: 45292 | H22: 45657 | I22: =+(G22+H22)/2 -> 45474.5 | J22: 45412 | K22: =+I22-J22 -> 62.5 | L22: =E22*K22 -> 10929.375
A23: =A22+1 -> 13 | B23: 45330 | C23: 1472.87 | D23: 4111.39 | E23: =D23+C23 -> 5584.26 | F23: 45330 | G23: 45292 | H23: 45657 | I23: =+(G23+H23)/2 -> 45474.5 | J23: 45412 | K23: =+I23-J23 -> 62.5 | L23: =E23*K23 -> 349016.25
... A44: =A43+1 -> 34 | B44: 45554 | C44: 215.83 | D44: 251.22 | E44: =D44+C44 -> 467.05 | F44: 45554 | G44: 45292 | H44: 45657 | I44: =+(G44+H44)/2 -> 45474.5 | J44: 45596 | K44: =+I44-J44 -> -121.5 | L44: =E44*K44 -> -56746.575
A45: =A44+1 -> 35
A46: =A45+1 -> 36 | B46: Total | C46: =SUM(C11:C45) -> 60147.11 | D46: =SUM(D11:D45) -> 78422.78 | E46: =SUM(E11:E45) -> 138569.89 | K46: =ROUND(L46/E46,2) -> 46.12 | L46: =SUM(L11:L43) -> 6391231.7
A47: =A46+1 -> 37
A48: =A47+1 -> 38
A49: =A48+1 -> 39 | B49: Source: | C49: Tax Other Than Income - Payroll Taxes.xlsx

Sheet 9
A1: 2025 RATE CASE
A2: =' '!A2 -> ONCOR ELECTRIC DELIVERY COMPANY LLC
A3: STATE GROSS MARGIN TAX
A4: FOR THE LEAD-LAG STUDY-PERIOD ENDING SEPTEMBER 30, 2024
A5: SPONSOR: A. THENMADATHIL
A7: Line No. | B7: Month/ Year | C7: Accrual Date | D7: Mid Month | E7: Due Date | F7: (Lead)/Lag Days
B8: (a) | C8: (b) | D8: (c) | E8: (d) | F8: (e)
A10: 1 | B10: 45200 | C10: 45230 | D10: =IF(C10=0,"",DATE(YEAR(C10),MONTH(C10),1)+INT(DAY(DATE(YEAR(C10),MONTH(C10)+1,1)-1)/2))-1 -> 45214 | E10: 45061 | F10: =D10-E10 -> 153
A11: 2 | B11: =B10+31 -> 45231 | C11: 45260 | D11: =IF(C11=0,"",DATE(YEAR(C11),MONTH(C11),1)+INT(DAY(DATE(YEAR(C11),MONTH(C11)+1,1)-1)/2))-1 -> 45245 | E11: 45061 | F11: =D11-E11 -> 184
A12: 3 | B12: =B11+30 -> 45261 | C12: 45291 | D12: =IF(C12=0,"",DATE(YEAR(C12),MONTH(C12),1)+INT(DAY(DATE(YEAR(C12),MONTH(C12)+1,1)-1)/2))-1 -> 45275 | E12: 45061 | F12: =D12-E12 -> 214
A13: 4 | B13: =B12+31 -> 45292 | C13: 45322 | D13: =IF(C13=0,"",DATE(YEAR(C13),MONTH(C13),1)+INT(DAY(DATE(YEAR(C13),MONTH(C13)+1,1)-1)/2))-1 -> 45306 | E13: 45427 | F13: =D13-E13 -> -121
A14: 5 | B14: =B13+31 -> 45323 | C14: 45351 | D14: =IF(C14=0,"",DATE(YEAR(C14),MONTH(C14),1)+INT(DAY(DATE(YEAR(C14),MONTH(C14)+1,1)-1)/2))-1 -> 45336 | E14: 45427 | F14: =D14-E14 -> -91
A15: 6 | B15: =B14+29 -> 45352 | C15: 45382 | D15: =IF(C15=0,"",DATE(YEAR(C15),MONTH(C15),1)+INT(DAY(DATE(YEAR(C15),MONTH(C15)+1,1)-1)/2))-1 -> 45366 | E15: 45427 | F15: =D15-E15 -> -61
A16: 7 | B16: =B15+31 -> 45383 | C16: 45412 | D16: =IF(C16=0,"",DATE(YEAR(C16),MONTH(C16),1)+INT(DAY(DATE(YEAR(C16),MONTH(C16)+1,1)-1)/2))-1 -> 45397 | E16: 45427 | F16: =D16-E16 -> -30
A17: 8 | B17: =B16+30 -> 45413 | C17: 45443 | D17: =IF(C17=0,"",DATE(YEAR(C17),MONTH(C17),1)+INT(DAY(DATE(YEAR(C17),MONTH(C17)+1,1)-1)/2))-1 -> 45427 | E17: 45427 | F17: =D17-E17 -> 0
A18: 9 | B18: =B17+31 -> 45444 | C18: 45473 | D18: =IF(C18=0,"",DATE(YEAR(C18),MONTH(C18),1)+INT(DAY(DATE(YEAR(C18),MONTH(C18)+1,1)-1)/2))-1 -> 45458 | E18: 45427 | F18: =D18-E18 -> 31
A19: 10 | B19: =B18+30 -> 45474 | C19: 45504 | D19: =IF(C19=0,"",DATE(YEAR(C19),MONTH(C19),1)+INT(DAY(DATE(YEAR(C19),MONTH(C19)+1,1)-1)/2))-1 -> 45488 | E19: 45427 | F19: =D19-E19 -> 61
A20: 11 | B20: =B19+31 -> 45505 | C20: 45535 | D20: =IF(C20=0,"",DATE(YEAR(C20),MONTH(C20),1)+INT(DAY(DATE(YEAR(C20),MONTH(C20)+1,1)-1)/2))-1 -> 45519 | E20: 45427 | F20: =D20-E20 -> 92
A21: 12 | B21: =B20+31 -> 45536 | C21: 45565 | D21: =IF(C21=0,"",DATE(YEAR(C21),MONTH(C21),1)+INT(DAY(DATE(YEAR(C21),MONTH(C21)+1,1)-1)/2))-1 -> 45550 | E21: 45427 | F21: =D21-E21 -> 123
A22: 13
A23: 14 | B23: Average | F23: =ROUND(AVERAGE(F10:F21),2) -> 46.25

Sheet 10
A1: 2025 RATE CASE
A2: =' '!A2 -> ONCOR ELECTRIC DELIVERY COMPANY LLC
A3: LOCAL GROSS RECEIPTS TAXES
A4: FOR THE LEAD-LAG STUDY-PERIOD ENDING SEPTEMBER 30, 2024
A5: SPONSOR: A. THENMADATHIL
A7: Line | C7: Total | D7: Amort of | E7: Accrued | G7: Weighted
A8: No. | B8: City | C8: Amount | D8: Prepaid | E8: Portion | F8: (Lead)/Lag | G8: Dollar Days
B9: (a) | C9: (b) | D9: (c) | E9: (d) | F9: (e) | G9: (f)
A11: 1 | B11: DALLAS | C11: 53104778 | D11: 35266448 | E11: =+C11-D11 -> 17838330 | F11: -17.419858 | G11: =+F11*E11 -> -3.1074117e+08
A12: =1+A11 -> 2 | B12: FORT WORTH | C12: 33329287 | D12: 22022490 | E12: =+C12-D12 -> 11306797 | F12: -18.33931 | G12: =+F12*E12 -> -2.0735885e+08
A13: =1+A12 -> 3 | B13: ARLINGTON | C13: 12898385 | D13: 12875715 | E13: =+C13-D13 -> 22669.73 | F13: -293.92315 | G13: =+F13*E13 -> -6663158.5
A14: =1+A13 -> 4 | B14: PLANO | C14: 11288805 | D14: 11272905 | E14: =+C14-D14 -> 15900.35 | F14: -305.30091 | G14: =+F14*E14 -> -4854391.3
A15: =1+A14 -> 5 | B15: IRVING | C15: 9854555.3 | D15: 9838174.6 | E15: =+C15-D15 -> 16380.75 | F15: -302.86654 | G15: =+F15*E15 -> -4961181.1
A16: =1+A15 -> 6 | B16: RICHARDSON | C16: 9124848.3 | D16: 0 | E16: =+C16-D16 -> 9124848.3 | F16: -91.663085 | G16: =+F16*E16 -> -8.3641175e+08
A17: =1+A16 -> 7 | B17: GRAND PRAIRIE | C17: 6739136.4 | D17: 6725465.6 | E17: =+C17-D17 -> 13670.78 | F17: -302.39865 | G17: =+F17*E17 -> -4134025.4
A18: =1+A17 -> 8 | B18: WACO | C18: 5924460.8 | D18: 0 | E18: =+C18-D18 -> 5924460.8 | F18: -92.143617 | G18: =+F18*E18 -> -5.4590125e+08
A19: =1+A18 -> 9 | B19: CARROLLTON | C19: 5502409 | D19: 0 | E19: =+C19-D19 -> 5502409 | F19: -47.137943 | G19: =+F19*E19 -> -2.5937224e+08
A20: =1+A19 -> 10 | B20: MIDLAND | C20: 4984233.1 | D20: 4972720.8 | E20: =+C20-D20 -> 11512.28 | F20: -307.04437 | G20: =+F20*E20 -> -3534780.8
A21: =1+A20 -> 11 | B21: TYLER | C21: 4576589.2 | D21: 0 | E21: =+C21-D21 -> 4576589.2 | F21: -78.111929 | G21: =+F21*E21 -> -3.5748621e+08
A22: =1+A21 -> 12 | B22: TEMPLE | C22: 4391646.9 | D22: 4374359.7 | E22: =+C22-D22 -> 17287.27 | F22: -303.16633 | G22: =+F22*E22 -> -5240918.2
A23: =1+A22 -> 13 | B23: KILLEEN | C23: 4195468.9 | D23: 0 | E23: =+C23-D23 -> 4195468.9 | F23: -47.81995 | G23: =+F23*E23 -> -2.0062712e+08
... A35: =1+A34 -> 25 | B35: FRISCO | C35: 2171035.9 | D35: 0 | E35: =+C35-D35 -> 2171035.9 | F35: -108.27982 | G35: =+F35*E35 -> -2.3507939e+08
A36: =1+A35 -> 26
A37: =1+A36 -> 27 | C37: =SUM(C11:C36) -> 2.0299738e+08 | D37: =SUM(D11:D36) -> 1.2852447e+08 | E37: =SUM(E11:E36) -> 74472906 | F37: =ROUND(G37/E37,2) -> -58.48 | G37: =SUM(G11:G36) -> -4.3552942e+09
A38: =1+A37 -> 28
A39: =1+A38 -> 29
A40: =1+A39 -> 30
A41: =1+A40 -> 31
A42: =1+A41 -> 32 | B42: * Twenty five largest tax payments were used. Top Twenty five = 69% of payments for local gross receipts
A43: =1+A42 -> 33
A44: =1+A43 -> 34 | B44: Discretionary Charges are all paid from account 236.2415 and were paid by check.
A45: =1+A44 -> 35 | B45: Local Gross Receipt Taxes are either prepaid from account 165.9000 or in arrears from Account 236.2410
A46: =1+A45 -> 36
A47: =1+A46 -> 37 | B47: Source: | C47: Taxes other than income - Local Gross Receipts.xlsx
A48: =1+A47 -> 38
A49: =1+A48 -> 39
A50: =1+A49 -> 40
A51: =1+A50 -> 41
A52: =1+A51 -> 42
A53: =1+A52 -> 43

Sheet 11
A1: 2025 RATE CASE
A2: =' '!A2 -> ONCOR ELECTRIC DELIVERY COMPANY LLC
A3: AD VALOREM TAXES
A4: FOR THE LEAD-LAG STUDY-PERIOD ENDING SEPTEMBER 30, 2024
A5: SPONSOR: A. THENMADATHIL
A7: Line | H7: Weighted
A8: No. | B8: County | C8: Collector | D8: Payment | E8: Mid-Year | F8: Check Cleared | G8: Lag/Lead | H8: Dollar Days
B9: (a) | C9: (b) | D9: (c) | E9: (d) | F9: (e) | G9: (f) | H9: (g)
A11: 1 | B11: Dallas | C11: DALLAS COUNTY TAX OFFICE | D11: 44035535 | E11: 45108.5 | F11: 45320 | G11: =-F11+E11 -> -211.5 | H11: =D11*G11 -> -9.3135156e+09
A12: =A11+1 -> 2 | B12: Tarrant | C12: TARRANT COUNTY | D12: 32981216 | E12: 45108.5 | F12: 45320 | G12: =-F12+E12 -> -211.5 | H12: =D12*G12 -> -6.9755273e+09
A13: =A12+1 -> 3 | B13: Collin | C13: COLLIN COUNTY | D13: 14720067 | E13: 45108.5 | F13: 45320 | G13: =-F13+E13 -> -211.5 | H13: =D13*G13 -> -3.1132942e+09 | N13: 45292
A14: =A13+1 -> 4 | B14: Bell | C14: BELL COUNTY TAX APPRAISAL DIST | D14: 7246264.2 | E14: 45108.5 | F14: 45244 | G14: =-F14+E14 -> -135.5 | H14: =D14*G14 -> -9.8186881e+08
A15: =A14+1 -> 5 | B15: Denton | C15: MICHELLE FRENCH, TAX A/C | D15: 6352430.9 | E15: 45108.5 | F15: 45324 | G15: =-F15+E15 -> -215.5 | H15: =D15*G15 -> -1.3689489e+09
A16: =A15+1 -> 6 | B16: Williamson | C16: WILLIAMSON COUNTY | D16: 6188642.1 | E16: 45108.5 | F16: 45320 | G16: =-F16+E16 -> -211.5 | H16: =D16*G16 -> -1.3088978e+09
A17: =A16+1 -> 7 | B17: Ector | C17: ECTOR CAD | D17: 6131876.8 | E17: 45108.5 | F17: 45343 | G17: =-F17+E17 -> -234.5 | H17: =D17*G17 -> -1.4379251e+09
A18: =A17+1 -> 8 | B18: Midland | C18: MIDLAND CAD | D18: 5785502.5 | E18: 45108.5 | F18: 45335 | G18: =-F18+E18 -> -226.5 | H18: =D18*G18 -> -1.3104163e+09
A19: =A18+1 -> 9 | B19: Ellis | C19: ELLIS COUNTY | D19: 5575502.7 | E19: 45108.5 | F19: 45350 | G19: =-F19+E19 -> -241.5 | H19: =D19*G19 -> -1.3464839e+09
A20: =A19+1 -> 10 | B20: McClennan | C20: MCLENNAN COUNTY | D20: 5492451.9 | E20: 45108.5 | F20: 45324 | G20: =-F20+E20 -> -215.5 | H20: =D20*G20 -> -1.1836234e+09
A21: =A20+1 -> 11 | B21: Smith | C21: SMITH COUNTY TAX OFFICE | D21: 4531439 | E21: 45108.5 | F21: 45330 | G21: =-F21+E21 -> -221.5 | H21: =D21*G21 -> -1.0037137e+09
A22: =A21+1 -> 12 | B22: Grayson | C22: GRAYSON COUNTY | D22: 3347119.9 | E22: 45108.5 | F22: 45332 | G22: =-F22+E22 -> -223.5 | H22: =D22*G22 -> -7.480813e+08
A23: =A22+1 -> 13 | B23: Reeves | C23: REEVES COUNTY | D23: 3038460.4 | E23: 45108.5 | F23: 45345 | G23: =-F23+E23 -> -236.5 | H23: =D23*G23 -> -7.1859589e+08
A24: =A23+1 -> 14 | B24: Kaufman | C24: KAUFMAN COUNTY | D24: 2911274.8 | E24: 45108.5 | F24: 45330 | G24: =-F24+E24 -> -221.5 | H24: =D24*G24 -> -6.4484736e+08
A25: =A24+1 -> 15 | B25: Andrews | C25: WARD COUNTY | D25: 2898796.4 | E25: 45108.5 | F25: 45335 | G25: =-F25+E25 -> -226.5 | H25: =D25*G25 -> -6.565774e+08
... A35: =A34+1 -> 25 | B35: Henderson | C35: HENDERSON COUNTY TEXAS | D35: 2016371.5 | E35: 45108.5 | F35: 45330 | G35: =-F35+E35 -> -221.5 | H35: =D35*G35 -> -4.466263e+08
A36: =A35+1 -> 26 | E36: 45108.5
A37: =A36+1 -> 27 | B37: Total | D37: =SUM(D11:D35) -> 1.7419944e+08 | G37: =ROUND(H37/D37,2) -> -212.48 | H37: =SUM(H11:H35) -> -3.701467e+10
A38: =A37+1 -> 28
A39: =A38+1 -> 29 | B39: Note: Top 25 payments to collectors represent approximately 71% of total payments.
A40: =A39+1 -> 30
A41: =A40+1 -> 31 | B41: Source: | C41: Tax other than income - Ad Valorem.xlsx

Sheet 12
A1: 2025 RATE CASE
A2: =' '!A2 -> ONCOR ELECTRIC DELIVERY COMPANY LLC
A3: AVERAGE DAILY BANK BALANCES
A4: FOR THE TEST-YEAR ENDING DECEMBER 31, 2024
A5: SPONSOR: A. THENMADATHIL
C7: Depository Bank Accounts
C8: JPMorgan Chase Bank | D8: BNY Mellon | E8: JPMorgan Chase Bank | F8: JPMorgan Chase Bank | G8: Citibank | H8: Total Monthly
A9: Line No. | B9: Month/Year | C9: Miscellaneous Rcpts Acct | D9: Rep Receipt Account | E9: Cash Concentration Acct | F9: Payroll Account | G9: Credit Card Portal Payments | H9: Daily Average Balances | I9: Days | J9: Total of Daily Balances
B10: (a) | C10: (b) | D10: (c) | E10: (d) | F10: ( e ) | G10: (f) | H10: (g) | I10: (h) | J10: (i)
A12: 1 | B12: 45292 | C12: 661616.36 | D12: 322811.4 | E12: 1172657.2 | F12: 37666.951 | G12: 10229.912 | H12: =SUM(C12:G12) -> 2204981.8 | I12: 31 | J12: =+H12*I12 -> 68354436
A13: =A12+1 -> 2 | B13: 45323 | C13: 2682770.8 | D13: 192339.46 | E13: 72816.877 | F13: 64638.702 | G13: 11622.746 | H13: =SUM(C13:G13) -> 3024188.6 | I13: 29 | J13: =+H13*I13 -> 87701469
A14: =A13+1 -> 3 | B14: 45352 | C14: 406021.3 | D14: 418510.54 | E14: 7533333.7 | F14: 59285.938 | G14: 13485.416 | H14: =SUM(C14:G14) -> 8430636.9 | I14: 31 | J14: =+H14*I14 -> 2.6134974e+08
A15: =A14+1 -> 4 | B15: 45383 | C15: 639988.07 | D15: 0 | E15: 97529.726 | F15: 48598.606 | G15: 12567.112 | H15: =SUM(C15:G15) -> 798683.51 | I15: 30 | J15: =+H15*I15 -> 23960505
A16: =A15+1 -> 5 | B16: 45413 | C16: 1216141.4 | D16: 0 | E16: 134655.01 | F16: 52635.165 | G16: 10615.202 | H16: =SUM(C16:G16) -> 1414046.8 | I16: 31 | J16: =+H16*I16 -> 43835450
A17: =A16+1 -> 6 | B17: 45444 | C17: 321093.54 | D17: 0 | E17: 81767.656 | F17: 53971.54 | G17: 11274.078 | H17: =SUM(C17:G17) -> 468106.82 | I17: 30 | J17: =+H17*I17 -> 14043204
A18: =A17+1 -> 7 | B18: 45474 | C18: 402615.31 | D18: 0 | E18: 278610.17 | F18: 36126.318 | G18: 10551.409 | H18: =SUM(C18:G18) -> 727903.21 | I18: 31 | J18: =+H18*I18 -> 22565000
A19: =A18+1 -> 8 | B19: 45505 | C19: 840091.54 | D19: 0 | E19: 424975.44 | F19: 28854.146 | G19: 11534.253 | H19: =SUM(C19:G19) -> 1305455.4 | I19: 31 | J19: =+H19*I19 -> 40469117
A20: =A19+1 -> 9 | B20: 45536 | C20: 833013.81 | D20: 0 | E20: 602805.09 | F20: 23842.107 | G20: 12288.319 | H20: =SUM(C20:G20) -> 1471949.3 | I20: 30 | J20: =+H20*I20 -> 44158480
A21: =A20+1 -> 10 | B21: 45566 | C21: 915850.45 | D21: 0 | E21: 3507967.6 | F21: 11050.155 | G21: 11031.298 | H21: =SUM(C21:G21) -> 4445899.5 | I21: 31 | J21: =+H21*I21 -> 1.3782288e+08
A22: =A21+1 -> 11 | B22: 45597 | C22: 521091.48 | D22: 0 | E22: 103609.83 | F22: 21606.41 | G22: 12611.012 | H22: =SUM(C22:G22) -> 658918.73 | I22: 30 | J22: =+H22*I22 -> 19767562
A23: =A22+1 -> 12 | B23: 45627 | C23: 589128.8 | D23: 0 | E23: 61157.82 | F23: 22220.104 | G23: 10392.436 | H23: =SUM(C23:G23) -> 682899.16 | I23: 31 | J23: =+H23*I23 -> 21169874
A24: =A23+1 -> 13 | H24: =SUM(H12:H23)/12 -> 2136139.1 | J24: =SUM(J12:J23) -> 7.8519772e+08
A25: =A24+1 -> 14
A26: =A25+1 -> 15 | B26: Avg Bank Bal - Col (i) Ln 13 divided by | D26: 365.25 | J26: =ROUND(J24/365.25,0) -> 2149754
A27: =A26+1 -> 16
A28: =A27+1 -> 17
A29: =A28+1 -> 18 | B29: Source: | C29: Bank balances 12.31.24.xlsx

Sheet 13
A1: 2025 RATE CASE
A2: =' '!A2 -> ONCOR ELECTRIC DELIVERY COMPANY LLC
A3: WORKING FUNDS AND OTHER
A4: FOR THE LEAD-LAG STUDY-PERIOD ENDING SEPTEMBER 30, 2024
A5: SPONSOR: A. THENMADATHIL
A7: Line No. | B7: Description | C7: Amount | D7: Reference
B8: (a) | C8: (b) | D8: (c)
A10: 1 | B10: Payroll Withholdings | C10: ='13-1'!C14 -> -1145710 | D10: WP/II-B-9/13-1
A11: 2 | B11: Misc. Working Funds | C11: ='13-2'!C14 -> 0 | D11: WP/II-B-9/13-2
A12: 3 | B12: Misc. Deferred Debits & Credits | C12: ='13-3'!D14 -> -2898999 | D12: WP/II-B-9/13-3
A13: 4 | B13: Home Purchase Plan | C13: ='13-4'!J26 -> 175686 | D13: WP/II-B-9/13-4
A14: 5 | B14: Other Accounts Receivables | C14: ='13-5'!C12 -> 433213 | D14: WP/II-B-9/13-5
A15: 6
A16: 7 | B16: Misc. Funds | C16: =ROUND(SUM(C10:C15),0) -> -3435810

Sheet 13-1
A1: 2025 RATE CASE
A2: =' '!A2 -> ONCOR ELECTRIC DELIVERY COMPANY LLC
A3: PAYROLL WITHHOLDING BALANCES
A4: FOR THE LEAD-LAG STUDY-PERIOD ENDING SEPTEMBER 30, 2024
A5: SPONSOR: A. THENMADATHIL
A7: Line No. | B7: Description | C7: Total | D7: Reference
B8: (a) | C8: (b) | D8: (c)
A10: 1 | B10: FICA Taxes | C10: ='13-1-2'!E85+'13-1-1'!E59 -> 0 | D10: WP/II-B-9/13-1-1 AND WP/II-B-9/13-1-2
A11: 2 | B11: Federal Income Tax Withholding | C11: ='13-1-3'!E58+'13-1-4'!E75 -> 0 | D11: WP/II-B-9/13-1-3 AND WP/II-B-9/13-1-4
A12: 3 | B12: Thrift Plan Withholding | C12: ='13-1-5'!E71+'13-1-6'!E84 -> -1145710 | D12: WP/II-B-9/13-1-5 AND WP/II-B-9/13-1-6
A13: 4
A14: 5 | B14: Total Payroll Withholding | C14: =SUM(C10:C12) -> -1145710

Sheet 13-1-1
A1: 2025 RATE CASE
A2: =' '!A2 -> ONCOR ELECTRIC DELIVERY COMPANY LLC
A3: PAYROLL WITHHOLDING - TRANSMISSION
A4: FOR THE LEAD-LAG STUDY-PERIOD ENDING SEPTEMBER 30, 2024
A5: SPONSOR: A. THENMADATHIL
A7: Line No. | B7: Payroll Check Date | C7: FICA Amount | D7: Deposit Date | E7: (Lead)/Lag Days | F7: Weighted Dollar Days
B8: (a) | C8: (b) | D8: (c) | E8: (d) | F8: (e)
A10: 1 | B10: 45211 | C10: 466884.36 | D10: 45211 | E10: =IF(C10=0,0,-(D10-B10)) -> 0 | F10: =C10*E10 -> 0
A11: =A10+1 -> 2 | B11: 45229 | C11: 484882.62 | D11: 45229 | E11: =IF(C11=0,0,-(D11-B11)) -> 0 | F11: =C11*E11 -> 0
A12: =A11+1 -> 3 | B12: 45244 | C12: 450486.74 | D12: 45244 | E12: =IF(C12=0,0,-(D12-B12)) -> 0 | F12: =C12*E12 -> 0
A13: =A12+1 -> 4 | B13: 45259 | C13: 439956.74 | D13: 45259 | E13: =IF(C13=0,0,-(D13-B13)) -> 0 | F13: =C13*E13 -> 0
A14: =A13+1 -> 5 | B14: 45264 | C14: 1.65 | D14: 45264 | E14: =IF(C14=0,0,-(D14-B14)) -> 0 | F14: =C14*E14 -> 0
A15: =A14+1 -> 6 | B15: 45274 | C15: 419558.28 | D15: 45274 | E15: =IF(C15=0,0,-(D15-B15)) -> 0 | F15: =C15*E15 -> 0
A16: =A15+1 -> 7 | B16: 45288 | C16: 380642.65 | D16: 45288 | E16: =IF(C16=0,0,-(D16-B16)) -> 0 | F16: =C16*E16 -> 0
A17: =A16+1 -> 8 | B17: 45289 | C17: 1435.15 | D17: 45289 | E17: =IF(C17=0,0,-(D17-B17)) -> 0 | F17: =C17*E17 -> 0
A18: =A17+1 -> 9 | B18: 45302 | C18: 427208.65 | D18: 45302 | E18: =IF(C18=0,0,-(D18-B18)) -> 0 | F18: =C18*E18 -> 0
A19: =A18+1 -> 10 | B19: 45309 | C19: 138.39 | D19: 45309 | E19: =IF(C19=0,0,-(D19-B19)) -> 0 | F19: =C19*E19 -> 0
A20: =A19+1 -> 11 | B20: 45303 | C20: 56213.28 | D20: 45303 | E20: =IF(C20=0,0,-(D20-B20)) -> 0 | F20: =C20*E20 -> 0
A21: =A20+1 -> 12 | B21: 45316 | C21: 478734.23 | D21: 45316 | E21: =IF(C21=0,0,-(D21-B21)) -> 0 | F21: =C21*E21 -> 0
A22: =A21+1 -> 13 | B22: 45323 | C22: 2482.01 | D22: 45323 | E22: =IF(C22=0,0,-(D22-B22)) -> 0 | F22: =C22*E22 -> 0
... A51: =A50+1 -> 42 | B51: 45554 | C51: 461827.7 | D51: 45554 | E51: =IF(C51=0,0,-(D51-B51)) -> 0 | F51: =C51*E51 -> 0
A52: =A51+1 -> 43
A53: =A52+1 -> 44 | B53: Total | C53: =SUM(C10:C52) -> 13594826 | E53: =ROUND(F53/C53,2) -> 0 | F53: =SUM(F10:F52) -> 0
A54: =A53+1 -> 45
A55: =A54+1 -> 46 | B55: Average Daily Amount (Col (b) Ln 41 divided by 365.25): | E55: =+ROUND(C53/365.25,0) -> 37221
A56: =A55+1 -> 47
A57: =A56+1 -> 48 | B57: (Lead)/Lag Days Total (Col (d) Ln 41) | E57: =+E53 -> 0
A58: =A57+1 -> 49
A59: =A58+1 -> 50 | B59: Total Withholding (Col (d) Ln 43 times Ln 45) | E59: =+ROUND(E55*E57,0) -> 0
A60: =A59+1 -> 51
A61: =A60+1 -> 52 | B61: Source: | C61: Taxes Other Than Income - Payroll Taxes.xlsx

Sheet 13-1-2
A1: 2025 RATE CASE
A2: =' '!A2 -> ONCOR ELECTRIC DELIVERY COMPANY LLC
A3: PAYROLL WITHHOLDING - DISTRIBUTION
A4: FOR THE LEAD-LAG STUDY-PERIOD ENDING SEPTEMBER 30, 2024
A5: SPONSOR: A. THENMADATHIL
A7: Line No. | B7: Payroll Check Date | C7: FICA Amount | D7: Deposit Date | E7: (Lead)/Lag Days | F7: Weighted Dollar Days
B8: (a) | C8: (b) | D8: (c) | E8: (d) | F8: (e)
A10: 1 | B10: 45204 | C10: 280989.22 | D10: 45204 | E10: =IF(C10=0,0,-(D10-B10)) -> 0 | F10: =C10*E10 -> 0
A11: 2 | B11: 45201 | C11: 33.12 | D11: 45201 | E11: =IF(C11=0,0,-(D11-B11)) -> 0 | F11: =C11*E11 -> 0
A12: 3 | B12: 45205 | C12: 26610.68 | D12: 45205 | E12: =IF(C12=0,0,-(D12-B12)) -> 0 | F12: =C12*E12 -> 0
A13: 4 | B13: 45211 | C13: 923236.85 | D13: 45211 | E13: =IF(C13=0,0,-(D13-B13)) -> 0 | F13: =C13*E13 -> 0
A14: 5 | B14: 45219 | C14: 825.32 | D14: 45219 | E14: =IF(C14=0,0,-(D14-B14)) -> 0 | F14: =C14*E14 -> 0
A15: 6 | B15: 45218 | C15: 274191.74 | D15: 45218 | E15: =IF(C15=0,0,-(D15-B15)) -> 0 | F15: =C15*E15 -> 0
A16: 7 | B16: 45223 | C16: 2219.86 | D16: 45223 | E16: =IF(C16=0,0,-(D16-B16)) -> 0 | F16: =C16*E16 -> 0
A17: 8 | B17: 45229 | C17: 844429.53 | D17: 45229 | E17: =IF(C17=0,0,-(D17-B17)) -> 0 | F17: =C17*E17 -> 0
A18: 9 | B18: 45232 | C18: 249231.47 | D18: 45232 | E18: =IF(C18=0,0,-(D18-B18)) -> 0 | F18: =C18*E18 -> 0
A19: 10 | B19: 45244 | C19: 876342.63 | D19: 45244 | E19: =IF(C19=0,0,-(D19-B19)) -> 0 | F19: =C19*E19 -> 0
A20: 11 | B20: 45246 | C20: 221634.89 | D20: 45246 | E20: =IF(C20=0,0,-(D20-B20)) -> 0 | F20: =C20*E20 -> 0
A21: 12 | B21: 45247 | C21: 2235.71 | D21: 45247 | E21: =IF(C21=0,0,-(D21-B21)) -> 0 | F21: =C21*E21 -> 0
... A77: 68 | B77: 45554 | C77: 1248723.9 | D77: 45554 | E77: =IF(C77=0,0,-(D77-B77)) -> 0 | F77: =C77*E77 -> 0
A78: 69
A79: 70 | B79: Total | C79: =SUM(C10:C77) -> 39300507 | E79: =ROUND(F79/C79,2) -> 0 | F79: =SUM(F10:F77) -> 0
A80: 71
A81: 72 | B81: Average Daily Amount (Col (b) Ln 85 divided by 365.25): | E81: =+ROUND(C79/365.25,0) -> 107599
A82: 73
A83: 74 | B83: (Lead)/Lag Days Total (Col (d) Ln 85) | E83: =+E79 -> 0
A84: 75
A85: 76 | B85: Total Withholding (Col (d) Ln 87 times Ln 89) | E85: =+ROUND(E81*E83,0) -> 0
A86: 77
A87: 78 | B87: Source: | C87: Taxes Other Than Income - Payroll Taxes.xlsx

Sheet 13-1-3
A1: 2025 RATE CASE
A2: =' '!A2 -> ONCOR ELECTRIC DELIVERY COMPANY LLC
A3: FEDERAL INCOME TAX WITHHOLDING - TRANSMISSION
A4: FOR THE LEAD-LAG STUDY-PERIOD ENDING SEPTEMBER 30, 2024
A5: SPONSOR: A. THENMADATHIL
A7: Line No. | B7: Payroll Check Date | C7: FIT Withholding Amount | D7: Deposit Date | E7: (Lead)/Lag Days | F7: Weighted Dollar Days
B8: (a) | C8: (b) | D8: (c) | E8: (d) | F8: (e)
A10: 1 | B10: 45211 | C10: 928731.8 | D10: 45211 | E10: =IF(C10=0,0,-(D10-B10)) -> 0 | F10: =C10*E10 -> 0
A11: 2 | B11: 45229 | C11: 1073045.5 | D11: 45229 | E11: =IF(C11=0,0,-(D11-B11)) -> 0 | F11: =C11*E11 -> 0
A12: 3 | B12: 45244 | C12: 999102.95 | D12: 45244 | E12: =IF(C12=0,0,-(D12-B12)) -> 0 | F12: =C12*E12 -> 0
A13: 4 | B13: 45259 | C13: 1021304.1 | D13: 45259 | E13: =IF(C13=0,0,-(D13-B13)) -> 0 | F13: =C13*E13 -> 0
A14: 5 | B14: 45264 | C14: 10577.03 | D14: 45264 | E14: =IF(C14=0,0,-(D14-B14)) -> 0 | F14: =C14*E14 -> 0
A15: 6 | B15: 45274 | C15: 1027991.5 | D15: 45274 | E15: =IF(C15=0,0,-(D15-B15)) -> 0 | F15: =C15*E15 -> 0
A16: 7 | B16: 45288 | C16: 929633.73 | D16: 45288 | E16: =IF(C16=0,0,-(D16-B16)) -> 0 | F16: =C16*E16 -> 0
A17: 8 | B17: 45289 | C17: 404.74 | D17: 45289 | E17: =IF(C17=0,0,-(D17-B17)) -> 0 | F17: =C17*E17 -> 0
A18: 9 | B18: 45302 | C18: 657622.99 | D18: 45302 | E18: =IF(C18=0,0,-(D18-B18)) -> 0 | F18: =C18*E18 -> 0
A19: 10 | B19: 45303 | C19: 143137.11 | D19: 45303 | E19: =IF(C19=0,0,-(D19-B19)) -> 0 | F19: =C19*E19 -> 0
A20: 11 | B20: 45316 | C20: 805288.56 | D20: 45316 | E20: =IF(C20=0,0,-(D20-B20)) -> 0 | F20: =C20*E20 -> 0
A21: 12 | B21: 45320 | C21: 9017.21 | D21: 45320 | E21: =IF(C21=0,0,-(D21-B21)) -> 0 | F21: =C21*E21 -> 0
... A36: 27 | B36: 45413 | C36: 396 | D36: 45413 | E36: =IF(C36=0,0,-(D36-B36)) -> 0 | F36: =C36*E36 -> 0
A37: =A36+1 -> 28 | B37: 45428 | C37: 988036.39 | D37: 45428 | E37: =IF(C37=0,0,-(D37-B37)) -> 0 | F37: =C37*E37 -> 0
A38: =A37+1 -> 29 | B38: 45442 | C38: 989267 | D38: 45442 | E38: =IF(C38=0,0,-(D38-B38)) -> 0 | F38: =C38*E38 -> 0
A39: =A38+1 -> 30 | B39: 45441 | C39: 4921.77 | D39: 45441 | E39: =IF(C39=0,0,-(D39-B39)) -> 0 | F39: =C39*E39 -> 0
A40: =A39+1 -> 31 | B40: 45456 | C40: 1009337.2 | D40: 45456 | E40: =IF(C40=0,0,-(D40-B40)) -> 0 | F40: =C40*E40 -> 0
A41: =A40+1 -> 32 | B41: 45463 | C41: 944.63 | D41: 45463 | E41: =IF(C41=0,0,-(D41-B41)) -> 0 | F41: =C41*E41 -> 0
A42: =A41+1 -> 33 | B42: 45470 | C42: 857296.52 | D42: 45470 | E42: =IF(C42=0,0,-(D42-B42)) -> 0 | F42: =C42*E42 -> 0
A43: =A42+1 -> 34 | B43: 45471 | C43: 167980.77 | D43: 45471 | E43: =IF(C43=0,0,-(D43-B43)) -> 0 | F43: =C43*E43 -> 0
A44: =A43+1 -> 35 | B44: 45484 | C44: 835125.36 | D44: 45484 | E44: =IF(C44=0,0,-(D44-B44)) -> 0 | F44: =C44*E44 -> 0
A45: =A44+1 -> 36 | B45: 45498 | C45: 868287.26 | D45: 45498 | E45: =IF(C45=0,0,-(D45-B45)) -> 0 | F45: =C45*E45 -> 0
A46: =A45+1 -> 37 | B46: 45512 | C46: 919985.88 | D46: 45512 | E46: =IF(C46=0,0,-(D46-B46)) -> 0 | F46: =C46*E46 -> 0
A47: =A46+1 -> 38 | B47: 45526 | C47: 962198.29 | D47: 45526 | E47: =IF(C47=0,0,-(D47-B47)) -> 0 | F47: =C47*E47 -> 0
A48: =A47+1 -> 39 | B48: 45540 | C48: 793326.82 | D48: 45540 | E48: =IF(C48=0,0,-(D48-B48)) -> 0 | F48: =C48*E48 -> 0
... A50: =A49+1 -> 41 | B50: 45554 | C50: 864256.91 | D50: 45554 | E50: =IF(C50=0,0,-(D50-B50)) -> 0 | F50: =C50*E50 -> 0
A51: =A50+1 -> 42
A52: =A51+1 -> 43 | B52: Total | C52: =SUM(C10:C50) -> 27567988 | E52: =ROUND(F52/C52,2) -> 0 | F52: =SUM(F10:F50) -> 0
A53: =A52+1 -> 44
A54: =A53+1 -> 45 | B54: Average Daily Amount (Col (b) Ln 43 divided by 365.25) | E54: =+ROUND(C52/365.25,0) -> 75477
A55: =A54+1 -> 46
A56: =A55+1 -> 47 | B56: (Lead)/Lag Days Total (Col (d) Ln 43) | E56: =+E52 -> 0
A57: =A56+1 -> 48
A58: =A57+1 -> 49 | B58: Total Withholding (Col (d) Ln 45 times Ln 47) | E58: =+ROUND(E54*E56,0) -> 0
A59: =A58+1 -> 50
A60: =A59+1 -> 51 | B60: Source: | C60: Taxes Other Than Income - Payroll Taxes.xlsx

Sheet 13-1-4
A1: 2025 RATE CASE
A2: =' '!A2 -> ONCOR ELECTRIC DELIVERY COMPANY LLC
A3: FEDERAL INCOME TAX WITHHOLDING - DISTRIBUTION
A4: FOR THE LEAD-LAG STUDY-PERIOD ENDING SEPTEMBER 30, 2024
A5: SPONSOR: A. THENMADATHIL
A7: Line No. | B7: Payroll Check Date | C7: FIT Withholding Amount | D7: Deposit Date | E7: (Lead)/Lag Days | F7: Weighted Dollar Days
B8: (a) | C8: (b) | D8: (c) | E8: (d) | F8: (e)
A10: 1 | B10: 45204 | C10: 555222.48 | D10: 45204 | E10: =IF(C10=0,0,-(D10-B10)) -> 0 | F10: =C10*E10 -> 0
A11: 2 | B11: 45205 | C11: 36526.19 | D11: 45205 | E11: =IF(C11=0,0,-(D11-B11)) -> 0 | F11: =C11*E11 -> 0
A12: 3 | B12: 45211 | C12: 1990787.3 | D12: 45211 | E12: =IF(C12=0,0,-(D12-B12)) -> 0 | F12: =C12*E12 -> 0
A13: 4 | B13: 45218 | C13: 606090.32 | D13: 45218 | E13: =IF(C13=0,0,-(D13-B13)) -> 0 | F13: =C13*E13 -> 0
A14: 5 | B14: 45223 | C14: 12754.03 | D14: 45223 | E14: =IF(C14=0,0,-(D14-B14)) -> 0 | F14: =C14*E14 -> 0
A15: 6 | B15: 45229 | C15: 1777574.6 | D15: 45229 | E15: =IF(C15=0,0,-(D15-B15)) -> 0 | F15: =C15*E15 -> 0
A16: 7 | B16: 45232 | C16: 612602.78 | D16: 45232 | E16: =IF(C16=0,0,-(D16-B16)) -> 0 | F16: =C16*E16 -> 0
A17: 8 | B17: 45244 | C17: 2010876 | D17: 45244 | E17: =IF(C17=0,0,-(D17-B17)) -> 0 | F17: =C17*E17 -> 0
A18: 9 | B18: 45246 | C18: 590728.2 | D18: 45246 | E18: =IF(C18=0,0,-(D18-B18)) -> 0 | F18: =C18*E18 -> 0
A19: 10 | B19: 45260 | C19: 551126.25 | D19: 45260 | E19: =IF(C19=0,0,-(D19-B19)) -> 0 | F19: =C19*E19 -> 0
A20: 11 | B20: 45259 | C20: 1873287.3 | D20: 45259 | E20: =IF(C20=0,0,-(D20-B20)) -> 0 | F20: =C20*E20 -> 0
A21: 12 | B21: 45264 | C21: 81692.11 | D21: 45264 | E21: =IF(C21=0,0,-(D21-B21)) -> 0 | F21: =C21*E21 -> 0
... A67: 58 | B67: 45554 | C67: 2486374 | D67: 45554 | E67: =IF(C67=0,0,-(D67-B67)) -> 0 | F67: =C67*E67 -> 0
A68: 59
A69: 60 | B69: Total | C69: =SUM(C10:C68) -> 86339014 | E69: =ROUND(F69/C69,2) -> 0 | F69: =SUM(F10:F68) -> 0
A70: 61
A71: 62 | B71: Average Daily Amount (Col (b) Ln 81 divided by 365.25) | E71: =+ROUND(C69/365.25,0) -> 236383
A72: 63
A73: 64 | B73: (Lead)/Lag Days Total (Col (d) Ln 81) | E73: =+E69 -> 0
A74: 65
A75: 66 | B75: Total Withholding (Col (d) Ln 83 times Ln 85) | E75: =+ROUND(E71*E73,0) -> 0
A76: 67
A77: 68 | B77: Source: | C77: Taxes Other Than Income - Payroll Taxes.xlsx

Sheet 13-1-5
A1: 2025 RATE CASE
A2: =' '!A2 -> ONCOR ELECTRIC DELIVERY COMPANY LLC
A3: THRIFT PLAN WITHHOLDING - TRANSMISSION
A4: FOR THE LEAD-LAG STUDY-PERIOD ENDING SEPTEMBER 30, 2024
A5: SPONSOR: A. THENMADATHIL
A7: Line No. | B7: Payroll Period Check Date | C7: Withholding Amount | D7: Deposit Date | E7: (Lead)/Lag Days | F7: Weighted Dollar Days
B8: (a) | C8: (b) | D8: (c) | E8: (d) | F8: (e)
A10: 1 | B10: 45198 | C10: 499424.86 | D10: 45205 | E10: =-D10+B10 -> -7 | F10: =E10*C10 -> -3495974
A11: 2 | B11: 45198 | C11: 113832.51 | D11: 45205 | E11: =-D11+B11 -> -7 | F11: =E11*C11 -> -796827.57
A12: 3 | B12: 45212 | C12: 498203.36 | D12: 45219 | E12: =-D12+B12 -> -7 | F12: =E12*C12 -> -3487423.5
A13: 4 | B13: 45212 | C13: 116010.53 | D13: 45219 | E13: =-D13+B13 -> -7 | F13: =E13*C13 -> -812073.71
A14: 5 | B14: 45230 | C14: 113040.38 | D14: 45237 | E14: =-D14+B14 -> -7 | F14: =E14*C14 -> -791282.66
A15: 6 | B15: 45230 | C15: 499946.3 | D15: 45237 | E15: =-D15+B15 -> -7 | F15: =E15*C15 -> -3499624.1
A16: 7 | B16: 45245 | C16: 113112.26 | D16: 45252 | E16: =-D16+B16 -> -7 | F16: =E16*C16 -> -791785.82
A17: 8 | B17: 45245 | C17: 505379.4 | D17: 45252 | E17: =-D17+B17 -> -7 | F17: =E17*C17 -> -3537655.8
A18: 9 | B18: 45260 | C18: 110319.21 | D18: 45267 | E18: =-D18+B18 -> -7 | F18: =E18*C18 -> -772234.47
A19: 10 | B19: 45260 | C19: 507542.14 | D19: 45267 | E19: =-D19+B19 -> -7 | F19: =E19*C19 -> -3552795
A20: 11 | B20: 45275 | C20: 106485.56 | D20: 45282 | E20: =-D20+B20 -> -7 | F20: =E20*C20 -> -745398.92
A21: 12 | B21: 45275 | C21: 512090.35 | D21: 45282 | E21: =-D21+B21 -> -7 | F21: =E21*C21 -> -3584632.4
... A37: 28 | B37: 45387 | C37: 509345.1 | D37: 45394 | E37: =-D37+B37 -> -7 | F37: =E37*C37 -> -3565415.7
A38: 29 | B38: 45401 | C38: 496116.08 | D38: 45408 | E38: =-D38+B38 -> -7 | F38: =E38*C38 -> -3472812.6
A39: 30 | B39: 45401 | C39: 130087.11 | D39: 45408 | E39: =-D39+B39 -> -7 | F39: =E39*C39 -> -910609.77
A40: 31 | B40: 45415 | C40: 129101.48 | D40: 45422 | E40: =-D40+B40 -> -7 | F40: =E40*C40 -> -903710.36
A41: 32 | B41: 45415 | C41: 501183.92 | D41: 45422 | E41: =-D41+B41 -> -7 | F41: =E41*C41 -> -3508287.4
A42: 33 | B42: 45429 | C42: 499829.88 | D42: 45436 | E42: =-D42+B42 -> -7 | F42: =E42*C42 -> -3498809.2
A43: 34 | B43: 45429 | C43: 132255.82 | D43: 45436 | E43: =-D43+B43 -> -7 | F43: =E43*C43 -> -925790.74
A44: 35 | B44: 45443 | C44: 495618.81 | D44: 45450 | E44: =-D44+B44 -> -7 | F44: =E44*C44 -> -3469331.7
A45: 36 | B45: 45443 | C45: 130185.65 | D45: 45450 | E45: =-D45+B45 -> -7 | F45: =E45*C45 -> -911299.55
A46: 37 | B46: 45457 | C46: 498357.92 | D46: 45464 | E46: =-D46+B46 -> -7 | F46: =E46*C46 -> -3488505.4
A47: 38 | B47: 45457 | C47: 130658.06 | D47: 45464 | E47: =-D47+B47 -> -7 | F47: =E47*C47 -> -914606.42
A48: 39 | B48: 45429 | C48: -251.37 | D48: 45436 | E48: =-D48+B48 -> -7 | F48: =E48*C48 -> 1759.59
A49: 40 | B49: 45471 | C49: 133459.53 | D49: 45476 | E49: =-D49+B49 -> -5 | F49: =E49*C49 -> -667297.65
... A63: 54 | B63: 45555 | C63: 135120.48 | D63: 45562 | E63: =-D63+B63 -> -7 | F63: =E63*C63 -> -945843.36
A64: 55 | C64: =SUM(C10:C63) -> 16248068 | E64: =ROUND(F64/C64,2) -> -6.76 | F64: =SUM(F10:F63) -> -1.0978005e+08
A65: 56
A66: 57
A67: 58 | B67: Average Daily Amount (Col (b) Ln 29 divided by 365.25) | E67: =+ROUND(C64/365.25,0) -> 44485
A68: 59
A69: 60 | B69: (Lead)/Lag Days Total (Col (d) Ln 29) | E69: =+E64 -> -6.76
A70: 61
A71: 62 | B71: Total Withholding (Col (d) Ln 31 times Ln 33) | E71: =+ROUND(E67*E69,0) -> -300719
A72: 63
A73: 64 | B73: Source: | C73: Thrift.xlsx

Sheet 13-1-6
A1: 2025 RATE CASE
A2: =' '!A2 -> ONCOR ELECTRIC DELIVERY COMPANY LLC
A3: THRIFT PLAN WITHHOLDING - DISTRIBUTION
A4: FOR THE LEAD-LAG STUDY-PERIOD ENDING SEPTEMBER 30, 2024
A5: SPONSOR: A. THENMADATHIL
A7: Line No. | B7: Payroll Period Check Date | C7: Withholding Amount | D7: Deposit Date | E7: (Lead)/Lag Days | F7: Weighted Dollar Days
B8: (a) | C8: (b) | D8: (c) | E8: (d) | F8: (e)
A10: 1 | B10: 45198 | C10: 1225981.4 | D10: 45205 | E10: =-D10+B10 -> -7 | F10: =E10*C10 -> -8581869.8
A11: =A10+1 -> 2 | B11: 45198 | C11: 178622.63 | D11: 45205 | E11: =-D11+B11 -> -7 | F11: =E11*C11 -> -1250358.4
A12: =A11+1 -> 3 | B12: 45205 | C12: 45960.25 | D12: 45212 | E12: =-D12+B12 -> -7 | F12: =E12*C12 -> -321721.75
A13: =A12+1 -> 4 | B13: 45205 | C13: 258519.08 | D13: 45212 | E13: =-D13+B13 -> -7 | F13: =E13*C13 -> -1809633.6
A14: =A13+1 -> 5 | B14: 45212 | C14: 174289.66 | D14: 45219 | E14: =-D14+B14 -> -7 | F14: =E14*C14 -> -1220027.6
A15: =A14+1 -> 6 | B15: 45212 | C15: 1233256 | D15: 45219 | E15: =-D15+B15 -> -7 | F15: =E15*C15 -> -8632791.8
A16: =A15+1 -> 7 | B16: 45219 | C16: 259484.48 | D16: 45226 | E16: =-D16+B16 -> -7 | F16: =E16*C16 -> -1816391.4
A17: =A16+1 -> 8 | B17: 45219 | C17: 46200.15 | D17: 45226 | E17: =-D17+B17 -> -7 | F17: =E17*C17 -> -323401.05
A18: =A17+1 -> 9 | B18: 45230 | C18: 1226831.4 | D18: 45237 | E18: =-D18+B18 -> -7 | F18: =E18*C18 -> -8587819.6
A19: =A18+1 -> 10 | B19: 45230 | C19: 167572.42 | D19: 45237 | E19: =-D19+B19 -> -7 | F19: =E19*C19 -> -1173006.9
A20: =A19+1 -> 11 | B20: 45233 | C20: 267739.91 | D20: 45240 | E20: =-D20+B20 -> -7 | F20: =E20*C20 -> -1874179.4
A21: =A20+1 -> 12 | B21: 45233 | C21: 47432.75 | D21: 45240 | E21: =-D21+B21 -> -7 | F21: =E21*C21 -> -332029.25
A22: =A21+1 -> 13 | B22: 45245 | C22: 166979.41 | D22: 45252 | E22: =-D22+B22 -> -7 | F22: =E22*C22 -> -1168855.9
... A77: =A76+1 -> 68 | B77: 45555 | C77: 250143.71 | D77: 45562 | E77: =-D77+B77 -> -7 | F77: =E77*C77 -> -1751006
A78: =A77+1 -> 69 | B78: Total | C78: =SUM(C10:C77) -> 45588348 | E78: =ROUND(F78/C78,2) -> -6.77 | F78: =SUM(F10:F77) -> -3.0862058e+08
A79: =A78+1 -> 70
A80: =A79+1 -> 71 | B80: Average Daily Amount (Col (b) Ln 55 divided by 365.25) | E80: =+ROUND(C78/365.25,0) -> 124814
A81: =A80+1 -> 72
A82: =A81+1 -> 73 | B82: (Lead)/Lag Days Total (Col (d) Ln 55) | E82: =+E78 -> -6.77
A83: =A82+1 -> 74
A84: =A83+1 -> 75 | B84: Total Withholding (Col (d) Ln 57 times Ln 59) | E84: =+ROUND(E80*E82,0) -> -844991
A85: =A84+1 -> 76
A86: =A85+1 -> 77 | B86: Source: | C86: Thrift.xlsx

Sheet 13-2
A1: 2025 RATE CASE
A2: =' '!A2 -> ONCOR ELECTRIC DELIVERY COMPANY LLC
A3: MISCELLANEOUS WORKING FUNDS SUMMARY
A4: FOR THE TEST-YEAR ENDING DECEMBER 31, 2024
A5: SPONSOR: A. THENMADATHIL
A7: Line No. | B7: Description | C7: Amount | D7: Reference
B8: (a) | C8: (b) | D8: (c)
A10: 1 | B10: Transmission | C10: ='13-2-1'!J29 -> 0 | D10: WP/II-B-9/13-2-1
A11: 2 | B11: Distribution | C11: ='13-2-2'!J29 -> 0 | D11: WP/II-B-9/13-2-2
A12: 3 | B12: Corporate | C12: ='13-2-3'!J29 -> 0 | D12: WP/II-B-9/13-2-3
A13: 4
A14: 5 | C14: =ROUND(SUM(C10:C13),0) -> 0

Sheet 13-2-1
A1: 2025 RATE CASE
A2: =' '!A2 -> ONCOR ELECTRIC DELIVERY COMPANY LLC
A3: MISCELLANEOUS WORKING FUNDS - TRANSMISSION
A4: FOR THE TEST-YEAR ENDING DECEMBER 31, 2024
A5: SPONSOR: A. THENMADATHIL
A7: Line | C7: Relocation Advances | F7: Travel Advances | I7: Working Funds - Petty Cash
A8: No. | B8: Period | C8: 1350300 | F8: 1350700 | I8: 1354000
B9: (a) | C9: (b) | D9: (c) | F9: (d) | G9: (e) | I9: (f) | J9: (g)
A11: 1 | B11: Beginning Balance | D11: 0 | G11: 0 | J11: 0
A12: =A11+1 -> 2 | B12: Ending Balance at… | C12: GL Activity | F12: GL Activity | I12: GL Activity
A13: =A12+1 -> 3 | B13: 45292 | C13: 0 | D13: =D11+C13 -> 0 | F13: 0 | G13: =G11+F13 -> 0 | I13: 0 | J13: =J11+I13 -> 0
A14: =A13+1 -> 4 | B14: 45323 | C14: 0 | D14: =D13+C14 -> 0 | F14: 0 | G14: =G13+F14 -> 0 | I14: 0 | J14: =J13+I14 -> 0
A15: =A14+1 -> 5 | B15: 45352 | C15: 0 | D15: =D14+C15 -> 0 | F15: 0 | G15: =G14+F15 -> 0 | I15: 0 | J15: =J14+I15 -> 0
A16: =A15+1 -> 6 | B16: 45383 | C16: 0 | D16: =D15+C16 -> 0 | F16: 0 | G16: =G15+F16 -> 0 | I16: 0 | J16: =J15+I16 -> 0
A17: =A16+1 -> 7 | B17: 45413 | C17: 0 | D17: =D16+C17 -> 0 | F17: 0 | G17: =G16+F17 -> 0 | I17: 0 | J17: =J16+I17 -> 0
A18: =A17+1 -> 8 | B18: 45444 | C18: 0 | D18: =D17+C18 -> 0 | F18: 0 | G18: =G17+F18 -> 0 | I18: 0 | J18: =J17+I18 -> 0
A19: =A18+1 -> 9 | B19: 45474 | C19: 0 | D19: =D18+C19 -> 0 | F19: 0 | G19: =G18+F19 -> 0 | I19: 0 | J19: =J18+I19 -> 0
A20: =A19+1 -> 10 | B20: 45505 | C20: 0 | D20: =D19+C20 -> 0 | F20: 0 | G20: =G19+F20 -> 0 | I20: 0 | J20: =J19+I20 -> 0
A21: =A20+1 -> 11 | B21: 45536 | C21: 0 | D21: =D20+C21 -> 0 | F21: 0 | G21: =G20+F21 -> 0 | I21: 0 | J21: =J20+I21 -> 0
A22: =A21+1 -> 12 | B22: 45566 | C22: 0 | D22: =D21+C22 -> 0 | F22: 0 | G22: =G21+F22 -> 0 | I22: 0 | J22: =J21+I22 -> 0
A23: =A22+1 -> 13 | B23: 45597 | C23: 0 | D23: =D22+C23 -> 0 | F23: 0 | G23: =G22+F23 -> 0 | I23: 0 | J23: =J22+I23 -> 0
A24: =A23+1 -> 14 | B24: 45627 | C24: 0 | D24: =D23+C24 -> 0 | F24: 0 | G24: =G23+F24 -> 0 | I24: 0 | J24: =J23+I24 -> 0
A25: =A24+1 -> 15
A26: =A25+1 -> 16 | B26: 13 Month Total | D26: =SUM(D11:D24) -> 0 | G26: =SUM(G11:G24) -> 0 | J26: =SUM(J11:J24) -> 0
A27: =A26+1 -> 17 | B27: 13 Month Average | D27: =+D26/13 -> 0 | G27: =+G26/13 -> 0 | J27: =+J26/13 -> 0
A28: =A27+1 -> 18
A29: =A28+1 -> 19 | B29: Total | J29: =SUM(D27:J27) -> 0
A30: =A29+1 -> 20
A31: =A30+1 -> 21
A32: =A31+1 -> 22 | B32: Source - Trial Balance - TRN

Sheet 13-2-2
A1: 2025 RATE CASE
A2: =' '!A2 -> ONCOR ELECTRIC DELIVERY COMPANY LLC
A3: MISCELLANEOUS WORKING FUNDS - DISTRIBUTION
A4: FOR THE TEST-YEAR ENDING DECEMBER 31, 2024
A5: SPONSOR: A. THENMADATHIL
A7: Line | C7: Relocation Advances | F7: Travel Advances | I7: Working Funds - Petty Cash
A8: No. | B8: Period | C8: 1350300 | F8: 1350700 | I8: 1354000
B9: (a) | C9: (b) | D9: (c) | F9: (d) | G9: (e) | I9: (f) | J9: (g)
A11: 1 | B11: Beginning Balance | D11: 0 | G11: 0 | J11: 0
A12: =A11+1 -> 2 | B12: Ending Balance at… | C12: GL Activity | F12: GL Activity | I12: GL Activity
A13: =A12+1 -> 3 | B13: 45292 | C13: 0 | D13: =D11+C13 -> 0 | F13: 0 | G13: =G11+F13 -> 0 | I13: 0 | J13: =J11+I13 -> 0
A14: =A13+1 -> 4 | B14: 45323 | C14: 0 | D14: =D13+C14 -> 0 | F14: 0 | G14: =G13+F14 -> 0 | I14: 0 | J14: =J13+I14 -> 0
A15: =A14+1 -> 5 | B15: 45352 | C15: 0 | D15: =D14+C15 -> 0 | F15: 0 | G15: =G14+F15 -> 0 | I15: 0 | J15: =J14+I15 -> 0
A16: =A15+1 -> 6 | B16: 45383 | C16: 0 | D16: =D15+C16 -> 0 | F16: 0 | G16: =G15+F16 -> 0 | I16: 0 | J16: =J15+I16 -> 0
A17: =A16+1 -> 7 | B17: 45413 | C17: 0 | D17: =D16+C17 -> 0 | F17: 0 | G17: =G16+F17 -> 0 | I17: 0 | J17: =J16+I17 -> 0
A18: =A17+1 -> 8 | B18: 45444 | C18: 0 | D18: =D17+C18 -> 0 | F18: 0 | G18: =G17+F18 -> 0 | I18: 0 | J18: =J17+I18 -> 0
A19: =A18+1 -> 9 | B19: 45474 | C19: 0 | D19: =D18+C19 -> 0 | F19: 0 | G19: =G18+F19 -> 0 | I19: 0 | J19: =J18+I19 -> 0
A20: =A19+1 -> 10 | B20: 45505 | C20: 0 | D20: =D19+C20 -> 0 | F20: 0 | G20: =G19+F20 -> 0 | I20: 0 | J20: =J19+I20 -> 0
A21: =A20+1 -> 11 | B21: 45536 | C21: 0 | D21: =D20+C21 -> 0 | F21: 0 | G21: =G20+F21 -> 0 | I21: 0 | J21: =J20+I21 -> 0
A22: =A21+1 -> 12 | B22: 45566 | C22: 0 | D22: =D21+C22 -> 0 | F22: 0 | G22: =G21+F22 -> 0 | I22: 0 | J22: =J21+I22 -> 0
A23: =A22+1 -> 13 | B23: 45597 | D23: =D22+C23 -> 0 | F23: 0 | G23: =G22+F23 -> 0 | I23: 0 | J23: =J22+I23 -> 0
A24: =A23+1 -> 14 | B24: 45627 | C24: 0 | D24: =D23+C24 -> 0 | F24: 0 | G24: =G23+F24 -> 0 | I24: 0 | J24: =J23+I24 -> 0
A25: =A24+1 -> 15
A26: =A25+1 -> 16 | B26: 13 Month Total | D26: =SUM(D11:D24) -> 0 | G26: =SUM(G11:G24) -> 0 | J26: =SUM(J11:J24) -> 0
A27: =A26+1 -> 17 | B27: 13 Month Average | D27: =+D26/13 -> 0 | G27: =+G26/13 -> 0 | J27: =+J26/13 -> 0
A28: =A27+1 -> 18
A29: =A28+1 -> 19 | J29: =SUM(D27:J27) -> 0
A30: =A29+1 -> 20 | B30: Source - Trial Balance - ESD

Sheet 13-2-3
A1: 2025 RATE CASE
A2: =' '!A2 -> ONCOR ELECTRIC DELIVERY COMPANY LLC
A3: MISCELLANEOUS WORKING FUNDS - CORPORATE
A4: FOR THE TEST-YEAR ENDING DECEMBER 31, 2024
A5: SPONSOR: A. THENMADATHIL
A7: Line | C7: Relocation Advances | F7: Travel Advances | I7: Working Funds - Petty Cash
A8: No. | B8: Period | C8: 1350300 | F8: 1350700 | I8: 1354000
B9: (a) | C9: (b) | D9: (c) | F9: (d) | G9: (e) | I9: (f) | J9: (g)
A11: 1 | B11: Beginning Balance | D11: 0 | G11: 0 | J11: 0
A12: =A11+1 -> 2 | B12: Ending Balance at… | C12: GL Activity | F12: GL Activity | I12: GL Activity
A13: =A12+1 -> 3 | B13: 45292 | C13: 0 | D13: =D11+C13 -> 0 | F13: 0 | G13: =G11+F13 -> 0 | I13: 0 | J13: 0
A14: =A13+1 -> 4 | B14: 45323 | C14: 0 | D14: =D13+C14 -> 0 | F14: 0 | G14: =G13+F14 -> 0 | I14: 0 | J14: =J13+I14 -> 0
A15: =A14+1 -> 5 | B15: 45352 | C15: 0 | D15: =D14+C15 -> 0 | F15: 0 | G15: =G14+F15 -> 0 | I15: 0 | J15: =J14+I15 -> 0
A16: =A15+1 -> 6 | B16: 45383 | C16: 0 | D16: =D15+C16 -> 0 | F16: 0 | G16: =G15+F16 -> 0 | I16: 0 | J16: =J15+I16 -> 0
A17: =A16+1 -> 7 | B17: 45413 | C17: 0 | D17: =D16+C17 -> 0 | F17: 0 | G17: =G16+F17 -> 0 | I17: 0 | J17: =J16+I17 -> 0
A18: =A17+1 -> 8 | B18: 45444 | C18: 0 | D18: =D17+C18 -> 0 | F18: 0 | G18: =G17+F18 -> 0 | I18: 0 | J18: =J17+I18 -> 0
A19: =A18+1 -> 9 | B19: 45474 | C19: 0 | D19: =D18+C19 -> 0 | F19: 0 | G19: =G18+F19 -> 0 | I19: 0 | J19: =J18+I19 -> 0
A20: =A19+1 -> 10 | B20: 45505 | C20: 0 | D20: =D19+C20 -> 0 | F20: 0 | G20: =G19+F20 -> 0 | I20: 0 | J20: =J19+I20 -> 0
A21: =A20+1 -> 11 | B21: 45536 | C21: 0 | D21: =D20+C21 -> 0 | F21: 0 | G21: =G20+F21 -> 0 | I21: 0 | J21: =J20+I21 -> 0
A22: =A21+1 -> 12 | B22: 45566 | C22: 0 | D22: =D21+C22 -> 0 | F22: 0 | G22: =G21+F22 -> 0 | I22: 0 | J22: =J21+I22 -> 0
A23: =A22+1 -> 13 | B23: 45597 | C23: 0 | D23: =D22+C23 -> 0 | F23: 0 | G23: =G22+F23 -> 0 | I23: 0 | J23: =J22+I23 -> 0
A24: =A23+1 -> 14 | B24: 45627 | C24: 0 | D24: =D23+C24 -> 0 | F24: 0 | G24: =G23+F24 -> 0 | I24: 0 | J24: =J23+I24 -> 0
A25: =A24+1 -> 15
A26: =A25+1 -> 16 | B26: 13 Month Total | D26: =SUM(D11:D24) -> 0 | G26: =SUM(G11:G24) -> 0 | J26: =SUM(J11:J24) -> 0
A27: =A26+1 -> 17 | B27: 13 Month Average | D27: =+D26/13 -> 0 | G27: =+G26/13 -> 0 | J27: =+J26/13 -> 0
A28: =A27+1 -> 18
A29: =A28+1 -> 19 | J29: =SUM(D27:J27) -> 0
A30: =A29+1 -> 20 | B30: Source - Trial Balance - TRNDS

Sheet 13-3
A1: 2025 RATE CASE
A2: =' '!A2 -> ONCOR ELECTRIC DELIVERY COMPANY LLC
A3: DEFERRED DEBITS/CREDITS SUMMARY
A4: FOR THE TEST-YEAR ENDING DECEMBER 31, 2024
A5: SPONSOR: A. THENMADATHIL
A7: Line
A8: No. | B8: Period | D8: Total | F8: Ref
B9: (a) | D9: (b) | F9: (c)
A11: 1 | B11: Transmission | D11: ='13-3-1'!J26 -> -936312.01 | F11: WP/II-B-9/13-3-1
A12: 2 | B12: Distribution | D12: ='13-3-2'!J27 -> -1962686.9 | F12: WP/II-B-9/13-3-2
A13: =A12+1 -> 3
A14: =A13+1 -> 4 | B14: 13 Month Average | D14: =ROUND(SUM(D11:D12),0) -> -2898999

Sheet 13-3-1
A1: 2025 RATE CASE
A2: =' '!A2 -> ONCOR ELECTRIC DELIVERY COMPANY LLC
A3: DEFERRED DEBITS/CREDITS - TRANSMISSION
A4: FOR THE TEST-YEAR ENDING DECEMBER 31, 2024
A5: SPONSOR: A. THENMADATHIL
A7: Line | D7: Deferred | G7: Deferred
A8: No. | B8: Period | D8: Debits | F8: Ref | G8: Credits | I8: Ref | J8: Total
B9: (a) | D9: (b) | F9: (c) | G9: (d) | I9: (e) | J9: (f)
A10: 1 | B10: Beginning Balance | D10: ='13-3-1-1'!D11 -> 740261.54 | F10: WP/II-B-9/13-3-1-1 | G10: ='13-3-1-2'!K11 -> -1832161.9 | I10: WP/II-B-9/13-3-1-2 | J10: =SUM(D10:G10) -> -1091900.3
A11: =A10+1 -> 2 | B11: Ending Balance at…
A12: =A11+1 -> 3 | B12: 45292 | D12: ='13-3-1-1'!D12 -> 0 | F12: WP/II-B-9/13-3-1-1 | G12: ='13-3-1-2'!K13 -> -1832161.9 | I12: WP/II-B-9/13-3-1-2 | J12: =SUM(D12:G12) -> -1832161.9
A13: =A12+1 -> 4 | B13: 45323 | D13: ='13-3-1-1'!D13 -> 0 | F13: WP/II-B-9/13-3-1-1 | G13: ='13-3-1-2'!K14 -> -1832161.9 | I13: WP/II-B-9/13-3-1-2 | J13: =SUM(D13:G13) -> -1832161.9
A14: =A13+1 -> 5 | B14: 45352 | D14: ='13-3-1-1'!D14 -> 52840.97 | F14: WP/II-B-9/13-3-1-1 | G14: ='13-3-1-2'!K15 -> -1540515.5 | I14: WP/II-B-9/13-3-1-2 | J14: =SUM(D14:G14) -> -1487674.5
A15: =A14+1 -> 6 | B15: 45383 | D15: ='13-3-1-1'!D15 -> 0 | F15: WP/II-B-9/13-3-1-1 | G15: ='13-3-1-2'!K16 -> -1540515.5 | I15: WP/II-B-9/13-3-1-2 | J15: =SUM(D15:G15) -> -1540515.5
A16: =A15+1 -> 7 | B16: 45413 | D16: ='13-3-1-1'!D16 -> 0 | F16: WP/II-B-9/13-3-1-1 | G16: ='13-3-1-2'!K17 -> -1540515.5 | I16: WP/II-B-9/13-3-1-2 | J16: =SUM(D16:G16) -> -1540515.5
A17: =A16+1 -> 8 | B17: 45444 | D17: ='13-3-1-1'!D17 -> 618585.44 | F17: WP/II-B-9/13-3-1-1 | G17: ='13-3-1-2'!K18 -> -1504560.9 | I17: WP/II-B-9/13-3-1-2 | J17: =SUM(D17:G17) -> -885975.44
A18: =A17+1 -> 9 | B18: 45474 | D18: ='13-3-1-1'!D18 -> 0 | F18: WP/II-B-9/13-3-1-1 | G18: ='13-3-1-2'!K19 -> -1504560.9 | I18: WP/II-B-9/13-3-1-2 | J18: =SUM(D18:G18) -> -1504560.9
A19: =A18+1 -> 10 | B19: 45505 | D19: ='13-3-1-1'!D19 -> 0 | F19: WP/II-B-9/13-3-1-1 | G19: ='13-3-1-2'!K20 -> -1504560.9 | I19: WP/II-B-9/13-3-1-2 | J19: =SUM(D19:G19) -> -1504560.9
A20: =A19+1 -> 11 | B20: 45536 | D20: ='13-3-1-1'!D20 -> 1659128.2 | F20: WP/II-B-9/13-3-1-1 | G20: ='13-3-1-2'!K21 -> -1320318.2 | I20: WP/II-B-9/13-3-1-2 | J20: =SUM(D20:G20) -> 338810.03
A21: =A20+1 -> 12 | B21: 45566 | D21: ='13-3-1-1'!D21 -> 0 | F21: WP/II-B-9/13-3-1-1 | G21: ='13-3-1-2'!K22 -> -1320318.2 | I21: WP/II-B-9/13-3-1-2 | J21: =SUM(D21:G21) -> -1320318.2
A22: =A21+1 -> 13 | B22: 45597 | D22: ='13-3-1-1'!D22 -> 0 | F22: WP/II-B-9/13-3-1-1 | G22: ='13-3-1-2'!K23 -> -1320318.2 | I22: WP/II-B-9/13-3-1-2 | J22: =SUM(D22:G22) -> -1320318.2
A23: =A22+1 -> 14 | B23: 45627 | D23: ='13-3-1-1'!D23 -> 20300.29 | F23: WP/II-B-9/13-3-1-1 | G23: ='13-3-1-2'!K24 -> -1616289.7 | I23: WP/II-B-9/13-3-1-2 | J23: =SUM(D23:G23) -> -1595989.4
A24: =A23+1 -> 15
A25: =A24+1 -> 16 | B25: Adjusted Total | D25: =SUM(D10:D23) -> 3091116.4 | G25: =SUM(G10:G23) -> -20208959 | J25: =SUM(J10:J23) -> -17117842
A26: =A25+1 -> 17 | B26: Adjusted Average | D26: =D25/5 -> 618223.29 | G26: =G25/13 -> -1554535.3 | J26: =+G26+D26 -> -936312.01
A27: =A26+1 -> 18
A28: =A27+1 -> 19
A29: =A28+1 -> 20 | B29: Source - Tabs 13-3-1-1 & 13-3-1-2-TRN

Sheet 13-3-1-1
A1: 2025 RATE CASE
A2: =' '!A2 -> ONCOR ELECTRIC DELIVERY COMPANY LLC
A3: DEFERRED DEBITS - TRANSMISSION
A4: FOR THE TEST-YEAR ENDING DECEMBER 31, 2024
A5: SPONSOR: A. THENMADATHIL
A7: Line | C7: Job Orders | D7: Adjusted
A8: No. | B8: Period | C8: 1862700 | D8: Job Orders
B9: (a) | C9: (b) | D9: (c)
A11: 1 | B11: Beg Bal | C11: 740261.54 | D11: 740261.54
A12: =A11+1 -> 2 | B12: 45292 | C12: 689032.96 | D12: 0
A13: =A12+1 -> 3 | B13: 45350 | C13: 763373.25 | D13: 0
A14: =A13+1 -> 4 | B14: 45382 | C14: 52840.97 | D14: 52840.97
A15: =A14+1 -> 5 | B15: 45412 | C15: 355412.66 | D15: 0
A16: =A15+1 -> 6 | B16: 45443 | C16: 1208417.8 | D16: 0
A17: =A16+1 -> 7 | B17: 45473 | C17: 618585.44 | D17: 618585.44
A18: =A17+1 -> 8 | B18: 45504 | C18: 3220065.1 | D18: 0
A19: =A18+1 -> 9 | B19: 45535 | C19: 2826091.5 | D19: 0
A20: =A19+1 -> 10 | B20: 45565 | C20: 1659128.2 | D20: 1659128.2
A21: =A20+1 -> 11 | B21: 45596 | C21: 4641002.3 | D21: 0
A22: =A21+1 -> 12 | B22: 45626 | C22: 5033065.8 | D22: 0
A23: =A22+1 -> 13 | B23: 45657 | C23: 20300.29 | D23: 20300.29
A24: =A23+1 -> 14
A25: =A24+1 -> 15 | B25: Monthly/Quarter Total | C25: =SUM(C11:C23) -> 21827578 | D25: =SUM(D11:D23) -> 3091116.4
A26: =A25+1 -> 16 | B26: 13 Month Average | C26: =+C25/13 -> 1679044.5
A27: =A26+1 -> 17 | B27: Qtr-Ending Average | D27: =+D25/5 -> 618223.29
A28: =A27+1 -> 18 | B28: 1862700 – Job Orders are set up to accumulate job costs and are subsequently cleared to O&M, Capital,
A29: =A28+1 -> 19 | B29: or Regulatory Assets upon completion
A30: =A29+1 -> 20 | B30: Source: | C30: Misc items - TRN.xlsx

Sheet 13-3-1-2
A1: 2025 RATE CASE
A2: =' '!A2 -> ONCOR ELECTRIC DELIVERY COMPANY LLC
A3: DEFERRED CREDITS - TRANSMISSION
A4: FOR THE TEST-YEAR ENDING DECEMBER 31, 2024
A5: SPONSOR: A. THENMADATHIL
A7: Line | D7: IBNR Medical and Dental | G7: IBNR Per Injury Prop Damage
A8: No. | B8: Period | D8: 253.1000 | G8: 253.1010 | K8: Total
B9: (a) | D9: (b) | E9: (c) | G9: (d) | H9: (e) | K9: (f)
A11: 1 | B11: Beginning Balance | E11: -1832161.9 | H11: 0 | K11: =SUM(E11:I11) -> -1832161.9
A12: =A11+1 -> 2 | B12: Ending Balance at… | D12: GL Activity | G12: GL Activity
A13: =A12+1 -> 3 | B13: 45292 | D13: 0 | E13: =E11+D13 -> -1832161.9 | G13: 0 | H13: =G13+H11 -> 0 | K13: =E13+H13 -> -1832161.9
A14: =A13+1 -> 4 | B14: 45323 | D14: 0 | E14: =E13+D14 -> -1832161.9 | G14: 0 | H14: =H13+G14 -> 0 | K14: =E14+H14 -> -1832161.9
A15: =A14+1 -> 5 | B15: 45352 | D15: 391646.35 | E15: =E14+D15 -> -1440515.5 | G15: -100000 | H15: =H14+G15 -> -100000 | K15: =E15+H15 -> -1540515.5
A16: =A15+1 -> 6 | B16: 45383 | D16: 0 | E16: =E15+D16 -> -1440515.5 | G16: 0 | H16: =H15+G16 -> -100000 | K16: =E16+H16 -> -1540515.5
A17: =A16+1 -> 7 | B17: 45413 | D17: 0 | E17: =E16+D17 -> -1440515.5 | G17: 0 | H17: =H16+G17 -> -100000 | K17: =E17+H17 -> -1540515.5
A18: =A17+1 -> 8 | B18: 45444 | D18: -64045.38 | E18: =E17+D18 -> -1504560.9 | G18: 100000 | H18: =H17+G18 -> 0 | K18: =E18+H18 -> -1504560.9
A19: =A18+1 -> 9 | B19: 45474 | D19: 0 | E19: =E18+D19 -> -1504560.9 | G19: 0 | H19: =H18+G19 -> 0 | K19: =E19+H19 -> -1504560.9
A20: =A19+1 -> 10 | B20: 45505 | D20: 0 | E20: =E19+D20 -> -1504560.9 | G20: 0 | H20: =H19+G20 -> 0 | K20: =E20+H20 -> -1504560.9
A21: =A20+1 -> 11 | B21: 45536 | D21: 184242.71 | E21: =E20+D21 -> -1320318.2 | G21: 0 | H21: =H20+G21 -> 0 | K21: =E21+H21 -> -1320318.2
A22: =A21+1 -> 12 | B22: 45566 | D22: 0 | E22: =E21+D22 -> -1320318.2 | G22: 0 | H22: =H21+G22 -> 0 | K22: =E22+H22 -> -1320318.2
A23: =A22+1 -> 13 | B23: 45597 | D23: 0 | E23: =E22+D23 -> -1320318.2 | G23: 0 | H23: =H22+G23 -> 0 | K23: =E23+H23 -> -1320318.2
A24: =A23+1 -> 14 | B24: 45627 | D24: -295971.54 | E24: =E23+D24 -> -1616289.7 | G24: 0 | H24: =H23+G24 -> 0 | K24: =E24+H24 -> -1616289.7
A25: =A24+1 -> 15 | B25: G/L Balance @ 12/31/24 | D25: =SUM(D13:D24)+E11 -> -1616289.7 | G25: 0
A26: =A25+1 -> 16 | B26: 13 Month Total | E26: =SUM(E11:E24) -> -19908959 | H26: =SUM(H11:H24) -> -300000 | K26: =SUM(K11:K24) -> -20208959
A27: =A26+1 -> 17 | B27: 13 Month Average | E27: =E26/13 -> -1531458.4 | H27: =H26/13 -> -23076.923 | K27: =K26/13 -> -1554535.3
A28: =A27+1 -> 18
A29: =A28+1 -> 19 | B29: 2531000 - This is an estimated liability (IBNR) for medical and dental claims incurred by employees but not submitted for processing.
A30: =A29+1 -> 20 | B30: 2531010 – This is an estimated liability (IBNR) for personal injury and property damage claims outstanding.
A31: =A30+1 -> 21
A32: =A31+1 -> 22 | B32: Source: | D32: Misc items - TRN.xlsx

Sheet 13-3-2
A1: 2025 RATE CASE
A2: =' '!A2 -> ONCOR ELECTRIC DELIVERY COMPANY LLC
A3: DEFERRED DEBITS/CREDITS - DISTRIBUTION
A4: FOR THE TEST-YEAR ENDING DECEMBER 31, 2024
A5: SPONSOR: A. THENMADATHIL
A7: Line | D7: Deferred | G7: Deferred
A8: No. | B8: Period | D8: Debits | F8: Ref | G8: Credits | I8: Ref | J8: Total
B9: (a) | D9: (b) | F9: (c) | G9: (d) | I9: (e) | J9: (f)
A11: 1 | B11: Beginning Balance | D11: =+'13-3-2-1'!D11 -> 6945391.5 | F11: WP/II-B-9/13-3-2-1 | G11: ='13-3-2-2'!J11 -> -12605138 | I11: WP/II-B-9/13-3-2-2 | J11: =SUM(D11:I11) -> -5659746.7
A12: =A11+1 -> 2 | B12: Ending Balance at…
A13: =A12+1 -> 3 | B13: 45292 | D13: =+'13-3-2-1'!D12 -> 0 | F13: WP/II-B-9/13-3-2-1 | G13: ='13-3-2-2'!J13 -> -12605138 | I13: WP/II-B-9/13-3-2-2 | J13: =SUM(D13:G13) -> -12605138
A14: =A13+1 -> 4 | B14: 45323 | D14: =+'13-3-2-1'!D13 -> 0 | F14: WP/II-B-9/13-3-2-1 | G14: ='13-3-2-2'!J14 -> -12605138 | I14: WP/II-B-9/13-3-2-2 | J14: =SUM(D14:G14) -> -12605138
A15: =A14+1 -> 5 | B15: 45352 | D15: =+'13-3-2-1'!D14 -> 7136023.3 | F15: WP/II-B-9/13-3-2-1 | G15: ='13-3-2-2'!J15 -> -12559084 | I15: WP/II-B-9/13-3-2-2 | J15: =SUM(D15:G15) -> -5423061.2
A16: =A15+1 -> 6 | B16: 45383 | D16: =+'13-3-2-1'!D15 -> 0 | F16: WP/II-B-9/13-3-2-1 | G16: ='13-3-2-2'!J16 -> -12559084 | I16: WP/II-B-9/13-3-2-2 | J16: =SUM(D16:G16) -> -12559084
A17: =A16+1 -> 7 | B17: 45413 | D17: =+'13-3-2-1'!D16 -> 0 | F17: WP/II-B-9/13-3-2-1 | G17: ='13-3-2-2'!J17 -> -12559084 | I17: WP/II-B-9/13-3-2-2 | J17: =SUM(D17:G17) -> -12559084
A18: =A17+1 -> 8 | B18: 45444 | D18: =+'13-3-2-1'!D17 -> 8066383.6 | F18: WP/II-B-9/13-3-2-1 | G18: ='13-3-2-2'!J18 -> -11343339 | I18: WP/II-B-9/13-3-2-2 | J18: =SUM(D18:G18) -> -3276955.5
A19: =A18+1 -> 9 | B19: 45474 | D19: =+'13-3-2-1'!D18 -> 0 | F19: WP/II-B-9/13-3-2-1 | G19: ='13-3-2-2'!J19 -> -11343339 | I19: WP/II-B-9/13-3-2-2 | J19: =SUM(D19:G19) -> -11343339
A20: =A19+1 -> 10 | B20: 45505 | D20: =+'13-3-2-1'!D19 -> 0 | F20: WP/II-B-9/13-3-2-1 | G20: ='13-3-2-2'!J20 -> -11343339 | I20: WP/II-B-9/13-3-2-2 | J20: =SUM(D20:G20) -> -11343339
A21: =A20+1 -> 11 | B21: 45536 | D21: =+'13-3-2-1'!D20 -> 9033686.1 | F21: WP/II-B-9/13-3-2-1 | G21: ='13-3-2-2'!J21 -> -10214482 | I21: WP/II-B-9/13-3-2-2 | J21: =SUM(D21:G21) -> -1180795.8
A22: =A21+1 -> 12 | B22: 45566 | D22: =+'13-3-2-1'!D21 -> 0 | F22: WP/II-B-9/13-3-2-1 | G22: ='13-3-2-2'!J22 -> -7714481.8 | I22: WP/II-B-9/13-3-2-2 | J22: =SUM(D22:G22) -> -7714481.8
A23: =A22+1 -> 13 | B23: 45597 | D23: =+'13-3-2-1'!D22 -> 0 | F23: WP/II-B-9/13-3-2-1 | G23: ='13-3-2-2'!J23 -> -7714481.8 | I23: WP/II-B-9/13-3-2-2 | J23: =SUM(D23:G23) -> -7714481.8
A24: =A23+1 -> 14 | B24: 45627 | D24: =+'13-3-2-1'!D23 -> 14249635 | F24: WP/II-B-9/13-3-2-1 | G24: ='13-3-2-2'!J24 -> -8469710.3 | I24: WP/II-B-9/13-3-2-2 | J24: =SUM(D24:G24) -> 5779925
A25: =A24+1 -> 15
A26: =A25+1 -> 16 | B26: Adjusted Total | D26: =SUM(D11:D24) -> 45431120 | G26: =SUM(G11:G24) -> -1.4363584e+08 | J26: =SUM(J11:J24) -> -98204721
A27: =A26+1 -> 17 | B27: Adjusted Average | D27: =D26/5 -> 9086223.9 | G27: =G26/13 -> -11048911 | J27: =+D27+G27 -> -1962686.9
A28: =A27+1 -> 18
A29: =A28+1 -> 19
A30: =A29+1 -> 20 | B30: Source - Tabs 13-3-2-1 & 13-3-2-2-ESD

Sheet 13-3-2-1
A1: 2025 RATE CASE
A2: =' '!A2 -> ONCOR ELECTRIC DELIVERY COMPANY LLC
A3: DEFERRED DEBITS - DISTRIBUTION
A4: FOR THE TEST-YEAR ENDING DECEMBER 31, 2024
A5: SPONSOR: A. THENMADATHIL
A7: Line | C7: Job Orders | D7: Adjusted
A8: No. | B8: Period | C8: 1862700 | D8: Job Orders
B9: (a) | C9: (b) | D9: (c)
A11: 1 | B11: Beg Bal | C11: 6945391.5 | D11: 6945391.5
A12: =A11+1 -> 2 | B12: 45292 | C12: 57930872 | D12: 0
A13: =A12+1 -> 3 | B13: 45323 | C13: 56179844 | D13: 0
A14: =A13+1 -> 4 | B14: 45352 | C14: 7136023.3 | D14: 7136023.3
A15: =A14+1 -> 5 | B15: 45383 | C15: 51575014 | D15: 0
A16: =A15+1 -> 6 | B16: 45413 | C16: 1.4330508e+08 | D16: 0
A17: =A16+1 -> 7 | B17: 45444 | C17: 8066383.6 | D17: 8066383.6
A18: =A17+1 -> 8 | B18: 45474 | C18: 3.4456004e+08 | D18: 0
A19: =A18+1 -> 9 | B19: 45505 | C19: 3.27751e+08 | D19: 0
A20: =A19+1 -> 10 | B20: 45536 | C20: 9033686.1 | D20: 9033686.1
A21: =A20+1 -> 11 | B21: 45566 | C21: 2.4885735e+08 | D21: 0
A22: =A21+1 -> 12 | B22: 45597 | C22: 2.6388991e+08 | D22: 0
A23: =A22+1 -> 13 | B23: 45627 | C23: 14249635 | D23: 14249635
A24: =A23+1 -> 14
A25: =A24+1 -> 15 | B25: Monthly/Quarter Total | C25: =SUM(C11:C23) -> 1.5394802e+09 | D25: =SUM(D11:D23) -> 45431120
A26: =A25+1 -> 16 | B26: 13 Month Average | C26: =+C25/13 -> 1.1842156e+08
A27: =A26+1 -> 17 | B27: Qtr-Ending Average | D27: =+D25/5 -> 9086223.9
A28: =A27+1 -> 18 | B28: 1862700 – Job Orders are set up to accumulate job costs and are subsequently cleared to O&M, Capital,
A29: =+A28+1 -> 19 | B29: or Regulatory Assets upon completion
A30: =+A29+1 -> 20 | B30: Source: | C30: Misc items - ESD.xlsx

Sheet 13-3-2-2
A1: 2025 RATE CASE
A2: =' '!A2 -> ONCOR ELECTRIC DELIVERY COMPANY LLC
A3: DEFERRED CREDITS - DISTRIBUTION
A4: FOR THE TEST-YEAR ENDING DECEMBER 31, 2024
A5: SPONSOR: A. THENMADATHIL
A7: Line | D7: IBNR Medical and Dental | G7: IBNR Per Injury Prop Damage
A8: No. | B8: Period | D8: 253.1000 | G8: 253.1010 | J8: Total
B9: (a) | D9: (b) | E9: (c) | G9: (d) | H9: (e) | J9: (f)
A11: 1 | B11: Beginning Balance | E11: -6684438.2 | H11: -5920700 | J11: =E11+H11 -> -12605138
A12: =A11+1 -> 2 | D12: GL Activity | G12: GL Activity
A13: =A12+1 -> 3 | B13: 45292 | D13: 0 | E13: =E11+D13 -> -6684438.2 | G13: 0 | H13: =H11+G13 -> -5920700 | J13: =E13+H13 -> -12605138
A14: =A13+1 -> 4 | B14: 45323 | D14: 0 | E14: =E13+D14 -> -6684438.2 | G14: 0 | H14: =H13+G14 -> -5920700 | J14: =E14+H14 -> -12605138
A15: =A14+1 -> 5 | B15: 45352 | D15: 1080353.6 | E15: =E14+D15 -> -5604084.5 | G15: -1034300 | H15: =H14+G15 -> -6955000 | J15: =E15+H15 -> -12559084
A16: =A15+1 -> 6 | B16: 45383 | D16: 0 | E16: =E15+D16 -> -5604084.5 | G16: 0 | H16: =H15+G16 -> -6955000 | J16: =E16+H16 -> -12559084
A17: =A16+1 -> 7 | B17: 45413 | D17: 0 | E17: =E16+D17 -> -5604084.5 | G17: 0 | H17: =H16+G17 -> -6955000 | J17: =E17+H17 -> -12559084
A18: =A17+1 -> 8 | B18: 45444 | D18: 150745.38 | E18: =E17+D18 -> -5453339.1 | G18: 1065000 | H18: =H17+G18 -> -5890000 | J18: =E18+H18 -> -11343339
A19: =A18+1 -> 9 | B19: 45474 | D19: 0 | E19: =E18+D19 -> -5453339.1 | G19: 0 | H19: =H18+G19 -> -5890000 | J19: =E19+H19 -> -11343339
A20: =A19+1 -> 10 | B20: 45505 | D20: 0 | E20: =E19+D20 -> -5453339.1 | G20: 0 | H20: =H19+G20 -> -5890000 | J20: =E20+H20 -> -11343339
A21: =A20+1 -> 11 | B21: 45536 | D21: 843857.29 | E21: =E20+D21 -> -4609481.8 | G21: 285000 | H21: =H20+G21 -> -5605000 | J21: =E21+H21 -> -10214482
A22: =A21+1 -> 12 | B22: 45566 | D22: 0 | E22: =E21+D22 -> -4609481.8 | G22: 2500000 | H22: =H21+G22 -> -3105000 | J22: =E22+H22 -> -7714481.8
A23: =A22+1 -> 13 | B23: 45597 | D23: 0 | E23: =E22+D23 -> -4609481.8 | G23: 0 | H23: =H22+G23 -> -3105000 | J23: =E23+H23 -> -7714481.8
A24: =A23+1 -> 14 | B24: 45627 | D24: -755228.46 | E24: =E23+D24 -> -5364710.3 | G24: 0 | H24: =H23+G24 -> -3105000 | J24: =E24+H24 -> -8469710.3
A25: =A24+1 -> 15 | B25: G/L Balance @ 12/31/24 | D25: =E11+D15+D18+D21+D24 -> -5364710.3 | G25: =+H11+G13+G14+G15+G16+G17+G18+G19+G20+G21+G22+G23+G24 -> -3105000
A26: =A25+1 -> 16 | B26: 13 Month Total | E26: =SUM(E11:E24) -> -72418741 | H26: =SUM(H11:H24) -> -71217100 | J26: =SUM(J11:J24) -> -1.4363584e+08
A27: =A26+1 -> 17 | B27: 13 Month Average | E27: =E26/13 -> -5570672.4 | H27: =H26/13 -> -5478238.5 | J27: =J26/13 -> -11048911
A28: =A27+1 -> 18
A29: =A28+1 -> 19 | B29: 2531000 - This is an estimated liability (IBNR) for medical and dental claims incurred by employees but not submitted for processing.
A30: =A29+1 -> 20 | B30: 2531010 – This is an estimated liability (IBNR) for personal injury and property damage claims outstanding adjusted for self insurance and 3rd party insurance claims.
A31: =A30+1 -> 21
A32: =A31+1 -> 22 | B32: Source: | D32: Misc items - ESD.xlsx

Sheet 13-4
A1: 2025 RATE CASE
A2: =' '!A2 -> ONCOR ELECTRIC DELIVERY COMPANY LLC
A3: HOME PURCHASE PLAN
A4: FOR THE TEST-YEAR ENDING DECEMBER 31, 2024
A5: SPONSOR: A. THENMADATHIL
A7: Line No. | B7: Period | D7: Transmission Activity | E7: Transmission | G7: Distribution Activity | H7: Distribution | J7: Total
E8: 174.6000 | H8: 174.6000
B9: (a) | E9: (b) | H9: (c) | J9: (d)
A11: 1 | B11: Beg Bal. | D11: 482279.57 | E11: =+D11 -> 482279.57 | G11: 0 | H11: =+G11 -> 0 | J11: =+H11+E11 -> 482279.57
A12: =A11+1 -> 2 | B12: 45292 | D12: -482279.57 | E12: =E11+D12 -> 0 | G12: 0 | H12: =H11+G12 -> 0 | J12: =+H12+E12 -> 0
A13: =A12+1 -> 3 | B13: 45323 | D13: 0 | E13: =E12+D13 -> 0 | G13: 124793.74 | H13: =H12+G13 -> 124793.74 | J13: =+H13+E13 -> 124793.74
A14: =A13+1 -> 4 | B14: 45352 | D14: 0 | E14: =E13+D14 -> 0 | G14: 17775.03 | H14: =H13+G14 -> 142568.77 | J14: =+H14+E14 -> 142568.77
A15: =A14+1 -> 5 | B15: 45383 | D15: 0 | E15: =E14+D15 -> 0 | G15: -60920.01 | H15: =H14+G15 -> 81648.76 | J15: =+H15+E15 -> 81648.76
A16: =A15+1 -> 6 | B16: 45413 | D16: 0 | E16: =E15+D16 -> 0 | G16: 148315.4 | H16: =H15+G16 -> 229964.16 | J16: =+H16+E16 -> 229964.16
A17: =A16+1 -> 7 | B17: 45444 | D17: 0 | E17: =E16+D17 -> 0 | G17: 408996.82 | H17: =H16+G17 -> 638960.98 | J17: =+H17+E17 -> 638960.98
A18: =A17+1 -> 8 | B18: 45474 | D18: 0 | E18: =E17+D18 -> 0 | G18: -638960.98 | H18: =H17+G18 -> 0 | J18: =+H18+E18 -> 0
A19: =A18+1 -> 9 | B19: 45505 | D19: 201260.11 | E19: =E18+D19 -> 201260.11 | G19: 0 | H19: =H18+G19 -> 0 | J19: =+H19+E19 -> 201260.11
A20: =A19+1 -> 10 | B20: 45536 | D20: -108039.36 | E20: =E19+D20 -> 93220.75 | G20: 0 | H20: =H19+G20 -> 0 | J20: =+H20+E20 -> 93220.75
A21: =A20+1 -> 11 | B21: 45566 | D21: -93220.75 | E21: =E20+D21 -> 0 | G21: 0 | H21: =H20+G21 -> 0 | J21: =+H21+E21 -> 0
A22: =A21+1 -> 12 | B22: 45597 | D22: 0 | E22: =E21+D22 -> 0 | G22: 289218.52 | H22: =H21+G22 -> 289218.52 | J22: =+H22+E22 -> 289218.52
A23: =A22+1 -> 13 | B23: 45627 | D23: 0 | E23: =E22+D23 -> 0 | G23: -289218.52 | H23: =H22+G23 -> 0 | J23: =+H23+E23 -> 0
A24: =A23+1 -> 14 | B24: G/L Balance @ 12/31/24 | D24: =SUM(D11:D23) -> 1.4551915e-11 | G24: =SUM(G11:G23) -> 0
A25: =A24+1 -> 15 | B25: 13 Month Total | E25: =SUM(E11:E23) -> 776760.43 | H25: =SUM(H11:H23) -> 1507154.9 | J25: =SUM(J11:J23) -> 2283915.4
A26: =A25+1 -> 16 | B26: 13 Month Avg. | E26: =E25/13 -> 59750.802 | H26: =H25/13 -> 115934.99 | J26: =ROUND(J25/13,0) -> 175686
A27: =A26+1 -> 17
A28: =A27+1 -> 18
A29: =A28+1 -> 19 | B29: Source: | D29: Misc items - TRN.xlsx
A30: =A29+1 -> 20 | D30: Misc items - ESD.xlsx

Sheet 13-5
A1: 2025 RATE CASE
A2: =' '!A2 -> ONCOR ELECTRIC DELIVERY COMPANY LLC
A3: SUMMARY OF EMPLOYEE ACCOUNT RECEIVABLE
A4: FOR THE TEST-YEAR ENDING DECEMBER 31, 2024
A5: SPONSOR: A. THENMADATHIL
A7: Line No. | B7: Description | C7: Amount | D7: Reference
B8: (a) | C8: (b) | D8: (c)
A10: 1 | B10: Transmission Division | C10: ='13-5-1'!K26 -> 88130.15 | D10: WP/II-B-9/13-5-1
A11: 2 | B11: Distribution Division | C11: ='13-5-2'!K26 -> 345083.26 | D11: WP/II-B-9/13-5-2
A12: =A11+1 -> 3 | B12: 13 Month Average | C12: =ROUND(SUM(C10:C11),0) -> 433213

Sheet 13-5-1
A1: 2025 RATE CASE
A2: =' '!A2 -> ONCOR ELECTRIC DELIVERY COMPANY LLC
A3: EMPLOYEE ACCOUNT RECEIVABLE - TRANSMISSION
A4: FOR THE TEST-YEAR ENDING DECEMBER 31, 2024
A5: SPONSOR: A. THENMADATHIL
A7: Line | C7: Energy Cons. Activity | D7: Energy Cons. | E7: Payroll Deduction - Other Activity | F7: Payroll Deduction - Other | G7: Appliances Activity | H7: Appliances | I7: Payroll Adv. Activity | J7: Payroll Adv.
A8: No. | B8: Period | C8: 1431060 | D8: 1431060 | E8: 1431000 | F8: 1431000 | G8: 1431110 | H8: 1431110 | I8: 1431600 | J8: 1431600 | K8: Total
B9: (a) | D9: (b) | F9: (c) | H9: (d) | J9: (e) | K9: (f)
A11: 1 | B11: Beg Bal. | C11: 43238.05 | D11: =C11 -> 43238.05 | E11: -3334.59 | F11: =+E11 -> -3334.59 | G11: 55051.69 | H11: =G11 -> 55051.69 | J11: 0 | K11: =D11+F11+H11+J11 -> 94955.15
A12: =A11+1 -> 2 | B12: 45292 | C12: -2000.9 | D12: =D11+C12 -> 41237.15 | E12: 3570.93 | F12: =F11+E12 -> 236.34 | G12: 783.53 | H12: =H11+G12 -> 55835.22 | J12: 0 | K12: =D12+F12+H12+J12 -> 97308.71
A13: =A12+1 -> 3 | B13: 45323 | C13: -1616.02 | D13: =D12+C13 -> 39621.13 | E13: -236.34 | F13: =F12+E13 -> 0 | G13: -1913.09 | H13: =H12+G13 -> 53922.13 | J13: 0 | K13: =D13+F13+H13+J13 -> 93543.26
A14: =A13+1 -> 4 | B14: 45352 | C14: -1500.17 | D14: =D13+C14 -> 38120.96 | E14: 0 | F14: =F13+E14 -> 0 | G14: 497.24 | H14: =H13+G14 -> 54419.37 | J14: 0 | K14: =D14+F14+H14+J14 -> 92540.33
A15: =A14+1 -> 5 | B15: 45383 | C15: -1528.54 | D15: =D14+C15 -> 36592.42 | E15: 0 | F15: =F14+E15 -> 0 | G15: 278.51 | H15: =H14+G15 -> 54697.88 | J15: 0 | K15: =D15+F15+H15+J15 -> 91290.3
A16: =A15+1 -> 6 | B16: 45413 | C16: -1557.7 | D16: =D15+C16 -> 35034.72 | E16: 0 | F16: =F15+E16 -> 0 | G16: -4107.5 | H16: =H15+G16 -> 50590.38 | J16: 0 | K16: =D16+F16+H16+J16 -> 85625.1
A17: =A16+1 -> 7 | B17: 45444 | C17: 1856.6 | D17: =D16+C17 -> 36891.32 | E17: 0 | F17: =F16+E17 -> 0 | G17: 1166.82 | H17: =H16+G17 -> 51757.2 | J17: 0 | K17: =D17+F17+H17+J17 -> 88648.52
A18: =A17+1 -> 8 | B18: 45474 | C18: -1584.38 | D18: =D17+C18 -> 35306.94 | E18: 220 | F18: =F17+E18 -> 220 | G18: 1975.36 | H18: =H17+G18 -> 53732.56 | J18: 0 | K18: =D18+F18+H18+J18 -> 89259.5
A19: =A18+1 -> 9 | B19: 45505 | C19: -96.09 | D19: =D18+C19 -> 35210.85 | E19: -220 | F19: =F18+E19 -> 0 | G19: -2739.01 | H19: =H18+G19 -> 50993.55 | J19: 0 | K19: =D19+F19+H19+J19 -> 86204.4
A20: =A19+1 -> 10 | B20: 45536 | C20: -490.54 | D20: =D19+C20 -> 34720.31 | E20: -803.19 | F20: =F19+E20 -> -803.19 | G20: 1550.4 | H20: =H19+G20 -> 52543.95 | J20: 0 | K20: =D20+F20+H20+J20 -> 86461.07
A21: =A20+1 -> 11 | B21: 45566 | C21: -857.4 | D21: =D20+C21 -> 33862.91 | E21: 0.01 | F21: =F20+E21 -> -803.18 | G21: -2256.31 | H21: =H20+G21 -> 50287.64 | J21: 0 | K21: =D21+F21+H21+J21 -> 83347.37
A22: =A21+1 -> 12 | B22: 45597 | C22: -1465.7 | D22: =D21+C22 -> 32397.21 | E22: 2155.05 | F22: =F21+E22 -> 1351.87 | G22: -4198.8 | H22: =H21+G22 -> 46088.84 | J22: 0 | K22: =D22+F22+H22+J22 -> 79837.92
A23: =A22+1 -> 13 | B23: 45627 | C23: 1911.62 | D23: =D22+C23 -> 34308.83 | E23: -1309.87 | F23: =F22+E23 -> 42 | G23: -3769.35 | H23: =H22+G23 -> 42319.49 | J23: 0 | K23: =D23+F23+H23+J23 -> 76670.32
A24: =A23+1 -> 14 | B24: G/L Balance @ 12/31/24 | C24: =SUM(C11:C23) -> 34308.83 | E24: =SUM(E11:E23) -> 42 | G24: =SUM(G11:G23) -> 42319.49
A25: =A24+1 -> 15 | B25: 13 Month Total | D25: =SUM(D11:D23) -> 476542.8 | F25: =SUM(F11:F23) -> -3090.75 | H25: =SUM(H11:H23) -> 672239.9 | J25: =SUM(J11:J23) -> 0 | K25: =SUM(D25:J25) -> 1145692
A26: =A25+1 -> 16 | B26: 13 Month Avg. | D26: =D25/13 -> 36657.138 | F26: =F25/13 -> -237.75 | H26: =H25/13 -> 51710.762 | J26: =J25/13 -> 0 | K26: =K25/13 -> 88130.15
A27: =A26+1 -> 17
A28: =A27+1 -> 18 | B28: 1431060 | C28: Loans to employees to purchase qualifying "energy efficient" items. The Company pays 90% of the total cost and an amount
A29: =A28+1 -> 19 | C29: is deducted from the employee's check.
A30: =A29+1 -> 20 | B30: 1431000 | C30: Outstanding balances of employee miscellaneous receivables.
A31: =A30+1 -> 21 | B31: 1431110 | C31: Employee loan used for the purchase of appliances.
A32: =A31+1 -> 22 | B32: 1431600 | C32: Includes temporary advances to employees for emergency purposes, EXPAT, overtime not paid correctly, etc.
A33: =A32+1 -> 23
A34: =A33+1 -> 24
A35: =A34+1 -> 25 | B35: Source: | C35: Misc. items - TRN.xlsx

Sheet 13-5-2
A1: 2025 RATE CASE
A2: =' '!A2 -> ONCOR ELECTRIC DELIVERY COMPANY LLC
A3: EMPLOYEE ACCOUNT RECEIVABLE - DISTRIBUTION
A4: FOR THE TEST-YEAR ENDING DECEMBER 31, 2024
A5: SPONSOR: A. THENMADATHIL
A7: Line | C7: Energy Cons. Activity | D7: Energy Cons. | E7: Payroll Deduction - Other Activity | F7: Payroll Deduction - Other | G7: Appliances Activity | H7: Appliances | I7: Payroll Adv. Activity | J7: Payroll Adv.
A8: No. | B8: Period | C8: 1431060 | D8: 1431060 | E8: 1431000 | F8: 1431000 | G8: 1431110 | H8: 1431110 | I8: 1431600 | J8: 1431600 | K8: Total
B9: (a) | D9: (b) | F9: (c) | H9: (d) | J9: (e) | K9: (f)
A11: 1 | B11: Beg Bal. | C11: 140724.22 | D11: =C11 -> 140724.22 | E11: -1624.25 | F11: =E11 -> -1624.25 | G11: 247980.04 | H11: =G11 -> 247980.04 | J11: 0 | K11: =D11+F11+H11+J11 -> 387080.01
A12: =A11+1 -> 2 | B12: 45292 | C12: -5518.3 | D12: =D11+C12 -> 135205.92 | E12: -1606.43 | F12: =F11+E12 -> -3230.68 | G12: -10787.97 | H12: =H11+G12 -> 237192.07 | J12: 0 | K12: =D12+F12+H12+J12 -> 369167.31
A13: =A12+1 -> 3 | B13: 45323 | C13: -736.5 | D13: =D12+C13 -> 134469.42 | E13: 1593.95 | F13: =F12+E13 -> -1636.73 | G13: -4791.65 | H13: =H12+G13 -> 232400.42 | J13: 0 | K13: =D13+F13+H13+J13 -> 365233.11
A14: =A13+1 -> 4 | B14: 45352 | C14: -2020.9 | D14: =D13+C14 -> 132448.52 | E14: 1633.34 | F14: =F13+E14 -> -3.39 | G14: -13075.5 | H14: =H13+G14 -> 219324.92 | J14: 0 | K14: =D14+F14+H14+J14 -> 351770.05
A15: =A14+1 -> 5 | B15: 45383 | C15: 889.14 | D15: =D14+C15 -> 133337.66 | E15: -397.81 | F15: =F14+E15 -> -401.2 | G15: -6969.09 | H15: =H14+G15 -> 212355.83 | J15: 0 | K15: =D15+F15+H15+J15 -> 345292.29
A16: =A15+1 -> 6 | B16: 45413 | C16: -1759.17 | D16: =D15+C16 -> 131578.49 | E16: 231.25 | F16: =F15+E16 -> -169.95 | G16: 19.09 | H16: =H15+G16 -> 212374.92 | J16: 0 | K16: =D16+F16+H16+J16 -> 343783.46
A17: =A16+1 -> 7 | B17: 45444 | C17: -1322.69 | D17: =D16+C17 -> 130255.8 | E17: -882.96 | F17: =F16+E17 -> -1052.91 | G17: -2587.26 | H17: =H16+G17 -> 209787.66 | J17: 0 | K17: =D17+F17+H17+J17 -> 338990.55
A18: =A17+1 -> 8 | B18: 45474 | C18: -6625.48 | D18: =D17+C18 -> 123630.32 | E18: -1428.03 | F18: =F17+E18 -> -2480.94 | G18: 1207.51 | H18: =H17+G18 -> 210995.17 | J18: 0 | K18: =D18+F18+H18+J18 -> 332144.55
A19: =A18+1 -> 9 | B19: 45505 | C19: 4507.68 | D19: =D18+C19 -> 128138 | E19: -1317.24 | F19: =F18+E19 -> -3798.18 | G19: -8408.71 | H19: =H18+G19 -> 202586.46 | J19: 0 | K19: =D19+F19+H19+J19 -> 326926.28
A20: =A19+1 -> 10 | B20: 45536 | C20: -1366.22 | D20: =D19+C20 -> 126771.78 | E20: 2634.48 | F20: =F19+E20 -> -1163.7 | G20: -3579.42 | H20: =H19+G20 -> 199007.04 | J20: 0 | K20: =D20+F20+H20+J20 -> 324615.12
A21: =A20+1 -> 11 | B21: 45566 | C21: -2820.01 | D21: =D20+C21 -> 123951.77 | E21: 0 | F21: =F20+E21 -> -1163.7 | G21: 7536.28 | H21: =H20+G21 -> 206543.32 | J21: 0 | K21: =D21+F21+H21+J21 -> 329331.39
A22: =A21+1 -> 12 | B22: 45597 | C22: -3373.76 | D22: =D21+C22 -> 120578.01 | E22: 504 | F22: =F21+E22 -> -659.7 | G22: 6760.9 | H22: =H21+G22 -> 213304.22 | J22: 0 | K22: =D22+F22+H22+J22 -> 333222.53
A23: =A22+1 -> 13 | B23: 45627 | C23: -2056.34 | D23: =D22+C23 -> 118521.67 | E23: 258.5 | F23: =F22+E23 -> -401.2 | G23: 7101.04 | H23: =H22+G23 -> 220405.26 | J23: 0 | K23: =D23+F23+H23+J23 -> 338525.73
A24: =A23+1 -> 14 | B24: G/L Balance @ 12/31/24 | C24: =SUM(C11:C23) -> 118521.67 | E24: =SUM(E11:E23) -> -401.2 | G24: =SUM(G11:G23) -> 220405.26
A25: =A24+1 -> 15 | B25: 13 Month Total | D25: =SUM(D11:D23) -> 1679611.6 | F25: =SUM(F11:F23) -> -17786.53 | H25: =SUM(H11:H23) -> 2824257.3 | J25: =SUM(J11:J23) -> 0 | K25: =SUM(D25:J25) -> 4486082.4
A26: =A25+1 -> 16 | B26: 13 Month Avg. | D26: =D25/13 -> 129200.89 | F26: =F25/13 -> -1368.1946 | H26: =H25/13 -> 217250.56 | J26: =J25/13 -> 0 | K26: =K25/13 -> 345083.26
A27: =A26+1 -> 17
A28: =A27+1 -> 18 | B28: 1431060 | D28: Loans to employees to purchase qualifying "energy efficient" items. The Company pays 90% of the total cost and
A29: =A28+1 -> 19 | D29: an amount is deducted from the employee's check.
A30: =A29+1 -> 20 | B30: 1431000 | D30: Outstanding balances of employee miscellaneous receivables.
A31: =A30+1 -> 21 | B31: 1431110 | D31: Employee loan used for the purchase of appliances.
A32: =A31+1 -> 22 | B32: 1431600 | D32: Includes temporary advances to employees for emergency purposes, EXPAT, overtime not paid correctly, etc.
A33: =A32+1 -> 23
A34: =A33+1 -> 24
A35: =A34+1 -> 25 | B35: Source: | C35: Misc items - ESD.xlsx

Sheet 14
A1: 2025 RATE CASE
A2: =' '!A2 -> ONCOR ELECTRIC DELIVERY COMPANY LLC
A3: PREPAID O&M AMORTIZATION
A4: FOR THE TEST-YEAR ENDING DECEMBER 31, 2024
A5: SPONSOR: A. THENMADATHIL
A7: Line No. | B7: Description | D7: FERC Account No. | F7: Twelve-Month Amortization
B8: (a) | D8: (b) | F8: (c)
A10: 1 | B10: Insurance
A11: =A10+1 -> 2 | B11: Transmission | D11: 9240000 | F11: 2689258.6
A12: =A11+1 -> 3 | D12: 9250000 | F12: 19838562
A13: =A12+1 -> 4 | B13: Distribution | D13: 9240000 | F13: 1883542.4
A14: =A13+1 -> 5 | D14: 9250000 | F14: 28994754
A15: =A14+1 -> 6 | B15: Total | F15: =SUM(F11:F14) -> 53406117
A16: =A15+1 -> 7
A17: =A16+1 -> 8 | B17: Membership Dues
A18: =A17+1 -> 9 | B18: Transmission | D18: 9302000 | F18: 0
A19: =A18+1 -> 10 | B19: Distribution | D19: 9302000 | F19: 1514312.9
A20: =A19+1 -> 11 | B20: Total | F20: =SUM(F18:F19) -> 1514312.9
A21: =A20+1 -> 12
A22: =A21+1 -> 13 | B22: Current Software Services & Maintenance
A23: =A22+1 -> 14 | B23: Transmission | D23: 9230000 | F23: 1339266
A24: =A23+1 -> 15 | B24: Distribution | D24: 9230000 | F24: 21011967
A25: =A24+1 -> 16 | B25: Total | F25: =SUM(F23:F24) -> 22351233
A26: =A25+1 -> 17
A27: =A26+1 -> 18 | B27: Total | F27: =+F15+F20+F25 -> 77271663
A28: =A27+1 -> 19
A29: =A28+1 -> 20 | B29: Prepaid Affiliate Charges - Other | F29: 117329.1
A30: =A29+1 -> 21 | B30: Prepaid Non-labor (Third Party) O&M | F30: 77154334
A31: =A30+1 -> 22
A32: =A31+1 -> 23
A33: =A32+1 -> 24 | B33: Source: | D33: Amortization of Prepaids.xlsx

Sheet 15
A1: 2025 RATE CASE
A2: =' '!A2 -> ONCOR ELECTRIC DELIVERY COMPANY LLC
A3: PREPAID TAX AMORTIZATION
A4: FOR THE TEST-YEAR ENDING DECEMBER 31, 2024
A5: SPONSOR: A. THENMADATHIL
A7: Line No. | B7: Description | C7: FERC Account No. | E7: Twelve-Month Amortization
B8: (a) | C8: (b) | E8: (c)
A10: 1 | B10: Local Gross Receipt Tax Amortization
A11: =A10+1 -> 2 | B11: Distribution | C11: 4082410 | E11: 2.175037e+08
A12: =A11+1 -> 3 | B12: Transmission | C12: 4082410 | E12: 0
A13: =A12+1 -> 4 | B13: Corporate | C13: 4082500 | E13: 0
A14: =A13+1 -> 5 | B14: Total | E14: =ROUND(SUM(E11:E12),0) -> 217503701
A15: =A14+1 -> 6
A16: =A15+1 -> 7 | B16: Source:
A17: =A16+1 -> 8 | B17: Amortization of prepaids - Local Gross Receipts tax.xlsx
