Workbook
Name AFT_DIST: 'II-I-Total'!#REF!
Name Assign_Tbl: #REF!
Name Assign_Tbl_2016: #REF!
Name DA: #REF!
Name DA_0222: #REF!
Name DA_2: #REF!
Name FactorTable: 'II-I-MET'!$G$1354:$T$1448
Name FactorTable: 'II-I-TBILLTDCS'!$G$1354:$T$1448
Name FactorTable: 'II-I-Total'!#REF!
Name FactorTable: 'II-I-DIST'!$G$1354:$T$1448
Name FFT_D: 'II-I-DIST'!$B$1042:$L$1195
Name x: 'II-I-TBILLTDCS'!$G$1354:$T$1448
Name xx: #REF!

Sheet LinkSheet
D4: Description | F4: Total | G4: Residential | H4: Secondary | I4: Secondary | J4: Primary DL | K4: Primary DL | L4: Primary | M4: Transmission | N4: Lighting | O4: Wholesale | P4: Wholesale
H5: <=10kW | I5: >10kW | J5: <=10kW | K5: >10kW | L5: Substation | O5: Substation | P5: DLS
D8: DIST Function Revenue ex 565 & A928 | F8: =SUM(G8:P8) -> 3.4592512e+09 | G8: ='WP II-I-1.7'!E23 -> 1.808863e+09 | H8: ='WP II-I-1.7'!F23 -> 51193085 | I8: ='WP II-I-1.7'!G23 -> 1.2075801e+09 | J8: ='WP II-I-1.7'!H23 -> 533883.98 | K8: ='WP II-I-1.7'!I23 -> 2.3514573e+08 | L8: ='WP II-I-1.7'!J23 -> 26160818 | M8: ='WP II-I-1.7'!K23 -> 26746602 | N8: ='WP II-I-1.7'!L23 -> 92687433 | ... P8: ='WP II-I-1.7'!N23 -> 8506147.8 | S8: =IF(ROUND(F45+F46+F8-'WP II-I-1.1'!G489,1)=0,TRUE,F45+F46+F8-'WP II-I-1.1'!G489) -> TRUE
D10: MET Function Revenue Req | F10: =SUM(G10:P10) -> 2.0524261e+08 | G10: ='WP II-I-1.7'!E25 -> 1.0712837e+08 | H10: ='WP II-I-1.7'!F25 -> 15024827 | I10: ='WP II-I-1.7'!G25 -> 59094145 | J10: ='WP II-I-1.7'!H25 -> 2487758.3 | K10: ='WP II-I-1.7'!I25 -> 19159478 | L10: ='WP II-I-1.7'!J25 -> 628890.65 | M10: ='WP II-I-1.7'!K25 -> 1312242.3 | N10: ='WP II-I-1.7'!L25 -> 144408.86 | ... P10: ='WP II-I-1.7'!N25 -> 188303.24 | S10: =IF(ROUND(F10-'WP II-I-1.1'!H489,1)=0,TRUE,F10-'WP II-I-1.1'!H489) -> TRUE
D12: CUSTOMER Function Revenue Req | F12: =SUM(G12:P12) -> 1.2166435e+08 | G12: ='WP II-I-1.7'!E27 -> 61413320 | H12: ='WP II-I-1.7'!F27 -> 8072044.4 | I12: ='WP II-I-1.7'!G27 -> 33901631 | J12: ='WP II-I-1.7'!H27 -> 1296712.2 | K12: ='WP II-I-1.7'!I27 -> 10639950 | L12: ='WP II-I-1.7'!J27 -> 465386.72 | M12: ='WP II-I-1.7'!K27 -> 1055899.5 | N12: ='WP II-I-1.7'!L27 -> 4692562 | ... P12: ='WP II-I-1.7'!N27 -> 90978.282 | S12: =IF(ROUND(F12-'WP II-I-1.1'!I489,1)=0,TRUE,F12-'WP II-I-1.1'!I489) -> TRUE
D14: DIST+MET+CUST:
D15: Total Plant: Gross | F15: =SUM(G15:P15) -> 2.1831887e+10 | G15: ='II-I-Total'!J60 -> 1.1697829e+10 | H15: ='II-I-Total'!K60 -> 4.4820417e+08 | I15: ='II-I-Total'!L60 -> 7.3425889e+09 | J15: ='II-I-Total'!M60 -> 17112245 | K15: ='II-I-Total'!N60 -> 1.3861023e+09 | L15: ='II-I-Total'!O60 -> 1.4192862e+08 | M15: ='II-I-Total'!P60 -> 31880329 | N15: ='II-I-Total'!Q60 -> 7.0647831e+08 | ... P15: ='II-I-Total'!S60 -> 49795240
D16: Return on Rate Base (cost-based) | F16: =SUM(G16:P16) -> 1.0591573e+09 | G16: ='II-I-Total'!J83 -> 5.7528199e+08 | H16: ='II-I-Total'!K83 -> 18004272 | I16: ='II-I-Total'!L83 -> 3.6570944e+08 | J16: ='II-I-Total'!M83 -> 698376.14 | K16: ='II-I-Total'!N83 -> 71151671 | L16: ='II-I-Total'!O83 -> 7977532.6 | M16: ='II-I-Total'!P83 -> 2278161.3 | N16: ='II-I-Total'!Q83 -> 14910476 | ... P16: ='II-I-Total'!S83 -> 2584084.4 | S16: =IF(F16-(SUM('WP II-I-1.1'!G494:I494))=0,TRUE,F16-(SUM('WP II-I-1.1'!G494:I494))) -> -1.1920929e-07
D17: Depreciation Expense | F17: =SUM(G17:P17) -> 7.6213691e+08 | G17: ='II-I-Total'!J22 -> 4.016133e+08 | H17: ='II-I-Total'!K22 -> 18899507 | I17: ='II-I-Total'!L22 -> 2.4937832e+08 | J17: ='II-I-Total'!M22 -> 1187788.3 | K17: ='II-I-Total'!N22 -> 49419746 | L17: ='II-I-Total'!O22 -> 4133939.8 | M17: ='II-I-Total'!P22 -> 1259119.8 | N17: ='II-I-Total'!Q22 -> 34303678 | ... P17: ='II-I-Total'!S22 -> 1644034.4
D18: Federal Income Tax (cost-based) | F18: =SUM(G18:P18) -> 1.4473902e+08 | G18: ='II-I-Total'!J25 -> 78668226 | H18: ='II-I-Total'!K25 -> 2333594.4 | I18: ='II-I-Total'!L25 -> 50108868 | J18: ='II-I-Total'!M25 -> 68143.324 | K18: ='II-I-Total'!N25 -> 9622190.5 | L18: ='II-I-Total'!O25 -> 1093406.3 | M18: ='II-I-Total'!P25 -> 303017.14 | N18: ='II-I-Total'!Q25 -> 2109357.1 | ... P18: ='II-I-Total'!S25 -> 355506.44 | S18: =IF(ROUND(F18-(SUM('WP II-I-1.1'!G498:I498)-'WP II-I-1.1'!F498),1)=0,TRUE,F18-(SUM('WP II-I-1.1'!G498:I498)-'WP II-I-1.1'!F39)) -> 0
D19: Taxes Other Than FIT | F19: =SUM(G19:P19) -> 4.9498676e+08 | G19: ='II-I-Total'!J24 -> 2.2223392e+08 | H19: ='II-I-Total'!K24 -> 7470560.3 | I19: ='II-I-Total'!L24 -> 1.9103386e+08 | J19: ='II-I-Total'!M24 -> 174043.73 | K19: ='II-I-Total'!N24 -> 33593410 | L19: ='II-I-Total'!O24 -> 5306944 | M19: ='II-I-Total'!P24 -> 27571464 | N19: ='II-I-Total'!Q24 -> 6397694.4 | ... P19: ='II-I-Total'!S24 -> 810743.42
C21: DIST Plant Function:
D22: Distribution Plant - Net | F22: =SUM(G22:P22) -> 1.3196087e+10 | G22: ='II-I-DIST'!J325 -> 7.2105294e+09 | H22: ='II-I-DIST'!K325 -> 1.9216964e+08 | I22: ='II-I-DIST'!L325 -> 4.5895967e+09 | J22: ='II-I-DIST'!M325 -> 1364418.2 | K22: ='II-I-DIST'!N325 -> 8.5765566e+08 | L22: ='II-I-DIST'!O325 -> 90070166 | M22: ='II-I-DIST'!P325 -> 17552732 | N22: ='II-I-DIST'!Q325 -> 1.980141e+08 | ... P22: ='II-I-DIST'!S325 -> 32908463
C23: A360 | D23: Land and Land Rights - Net | F23: =SUM(G23:P23) -> 16818708 | G23: ='II-I-DIST'!J136-'II-I-DIST'!J290 -> 9040973.5 | H23: ='II-I-DIST'!K136-'II-I-DIST'!K290 -> 296691.8 | I23: ='II-I-DIST'!L136-'II-I-DIST'!L290 -> 5713094.6 | J23: ='II-I-DIST'!M136-'II-I-DIST'!M290 -> 1626.3533 | K23: ='II-I-DIST'!N136-'II-I-DIST'!N290 -> 1022304.7 | L23: ='II-I-DIST'!O136-'II-I-DIST'!O290 -> 98265.926 | M23: ='II-I-DIST'!P136-'II-I-DIST'!P290 -> 19970.074 | N23: ='II-I-DIST'!Q136-'II-I-DIST'!Q290 -> 579762.97 | ... P23: ='II-I-DIST'!S136-'II-I-DIST'!S290 -> 39226.087
C24: A361 | D24: Structures and Improvements - Net | F24: =SUM(G24:P24) -> 2.1261803e+08 | G24: ='II-I-DIST'!J137-'II-I-DIST'!J291 -> 1.1429379e+08 | H24: ='II-I-DIST'!K137-'II-I-DIST'!K291 -> 3750705.8 | I24: ='II-I-DIST'!L137-'II-I-DIST'!L291 -> 72223556 | J24: ='II-I-DIST'!M137-'II-I-DIST'!M291 -> 20559.964 | K24: ='II-I-DIST'!N137-'II-I-DIST'!N291 -> 12923728 | L24: ='II-I-DIST'!O137-'II-I-DIST'!O291 -> 1242254 | M24: ='II-I-DIST'!P137-'II-I-DIST'!P291 -> 252456.83 | N24: ='II-I-DIST'!Q137-'II-I-DIST'!Q291 -> 7329222.9 | ... P24: ='II-I-DIST'!S137-'II-I-DIST'!S291 -> 495886.68
C25: A362 | D25: Station Equipment - Net | F25: =SUM(G25:P25) -> 1.9689289e+09 | G25: ='II-I-DIST'!J138-'II-I-DIST'!J292 -> 1.0096008e+09 | H25: ='II-I-DIST'!K138-'II-I-DIST'!K292 -> 19074051 | I25: ='II-I-DIST'!L138-'II-I-DIST'!L292 -> 6.4847084e+08 | J25: ='II-I-DIST'!M138-'II-I-DIST'!M292 -> 303445.91 | K25: ='II-I-DIST'!N138-'II-I-DIST'!N292 -> 1.9074218e+08 | L25: ='II-I-DIST'!O138-'II-I-DIST'!O292 -> 81984743 | M25: ='II-I-DIST'!P138-'II-I-DIST'!P292 -> 0 | N25: ='II-I-DIST'!Q138-'II-I-DIST'!Q292 -> 5766896 | ... P25: ='II-I-DIST'!S138-'II-I-DIST'!S292 -> 7318825.2
D26: 4CP Retail Allocation Factor | F26: =SUM(G26:P26) -> 1 | G26: ='II-I-DIST'!J1377 -> 0.43858854 | H26: ='II-I-DIST'!K1377 -> 0.0088416368 | I26: ='II-I-DIST'!L1377 -> 0.30533457 | J26: ='II-I-DIST'!M1377 -> 9.6594337e-05 | K26: ='II-I-DIST'!N1377 -> 0.094937872 | L26: ='II-I-DIST'!O1377 -> 0.034466235 | M26: ='II-I-DIST'!P1377 -> 0.11773456 | N26: ='II-I-DIST'!Q1377 -> 0 | O26: 0 | P26: 0
D28: NCP (kW) | G28: ='WP II-I-2.2'!E37 -> 15919714 | H28: ='WP II-I-2.2'!F37 -> 300765.85 | I28: ='WP II-I-2.2'!G37 -> 10225299 | J28: ='WP II-I-2.2'!H37 -> 4784.8339 | K28: ='WP II-I-2.2'!I37 -> 3007684.8 | L28: ='WP II-I-2.2'!J37 -> 1292762.1 | M28: ='WP II-I-2.2'!K37 -> 4728173.4 | N28: ='WP II-I-2.2'!L37 -> 90934.293 | ... P28: ='WP II-I-2.2'!N37 -> 115405.62
D30: DIST Function Revenue: Proposed | F30: =SUM(G30:P30) -> 5.5600926e+09 | G30: ='II-I-DIST'!J37 -> 2.730268e+09 | H30: ='II-I-DIST'!K37 -> 69767963 | I30: ='II-I-DIST'!L37 -> 1.8490396e+09 | J30: ='II-I-DIST'!M37 -> 736813.37 | K30: ='II-I-DIST'!N37 -> 4.3459515e+08 | L30: ='II-I-DIST'!O37 -> 98568914 | M30: ='II-I-DIST'!P37 -> 2.7408825e+08 | N30: ='II-I-DIST'!Q37 -> 92687433 | ... P30: ='II-I-DIST'!S37 -> 8506147.8 | S30: =IF(ROUND(F30-'WP II-I-1.1'!G489,2)=0,TRUE,F30-'WP II-I-1.1'!G489) -> TRUE
D31: TRAN Function Revenue Requirement | F31: ='WP II-I-1.1'!F489 -> 1.9114562e+09
C34: DIST Function:
D35: O&M Expenses | F35: =SUM(G35:P35) -> 2.4658459e+09 | G35: ='II-I-DIST'!J15 -> 1.1125812e+09 | H35: ='II-I-DIST'!K15 -> 22758119 | I35: ='II-I-DIST'!L15 -> 7.6382629e+08 | J35: ='II-I-DIST'!M15 -> 359979.97 | K35: ='II-I-DIST'!N15 -> 2.3027371e+08 | L35: ='II-I-DIST'!O15 -> 75448315 | M35: ='II-I-DIST'!P15 -> 2.4742689e+08 | N35: ='II-I-DIST'!Q15 -> 11812787 | ... P35: ='II-I-DIST'!S15 -> 1150425.1
D36: Customer Expenses | F36: =SUM(G36:P36) -> 339790.12 | G36: ='II-I-DIST'!J16 -> 254774.27 | H36: ='II-I-DIST'!K16 -> 24361.403 | I36: ='II-I-DIST'!L16 -> 44514.918 | J36: ='II-I-DIST'!M16 -> 1487.8884 | K36: ='II-I-DIST'!N16 -> 10475.931 | L36: ='II-I-DIST'!O16 -> 339.88168 | M36: ='II-I-DIST'!P16 -> 708.95565 | N36: ='II-I-DIST'!Q16 -> 2993.6929 | ... P36: ='II-I-DIST'!S16 -> 95.644139
D37: A&G Expenses | F37: =SUM(G37:P37) -> 8.6225408e+08 | G37: ='II-I-DIST'!J17 -> 4.5986261e+08 | H37: ='II-I-DIST'!K17 -> 13373498 | I37: ='II-I-DIST'!L17 -> 2.9176041e+08 | J37: ='II-I-DIST'!M17 -> 182914.3 | K37: ='II-I-DIST'!N17 -> 59664370 | L37: ='II-I-DIST'!O17 -> 6384539.4 | M37: ='II-I-DIST'!P17 -> 825460.58 | N37: ='II-I-DIST'!Q17 -> 27500799 | ... P37: ='II-I-DIST'!S17 -> 2260998.9
D38: Depreciation & Amortization Expense | F38: =SUM(G38:P38) -> 6.5141705e+08 | G38: ='II-I-DIST'!J20 -> 3.4461415e+08 | H38: ='II-I-DIST'!K20 -> 11876247 | I38: ='II-I-DIST'!L20 -> 2.1734221e+08 | J38: ='II-I-DIST'!M20 -> 63251.401 | K38: ='II-I-DIST'!N20 -> 39759013 | L38: ='II-I-DIST'!O20 -> 3731667.6 | M38: ='II-I-DIST'!P20 -> 647373.09 | N38: ='II-I-DIST'!Q20 -> 31599630 | ... P38: ='II-I-DIST'!S20 -> 1525563.3
D39: Other Expenses (II-E-4) | F39: =SUM(G39:P39) -> 15428626 | G39: ='II-I-DIST'!J21 -> 8417584.3 | H39: ='II-I-DIST'!K21 -> 222821.52 | I39: ='II-I-DIST'!L21 -> 5359035.8 | J39: ='II-I-DIST'!M21 -> 1614.6021 | K39: ='II-I-DIST'!N21 -> 1014918 | L39: ='II-I-DIST'!O21 -> 118589.03 | M39: ='II-I-DIST'!P21 -> 20014.916 | N39: ='II-I-DIST'!Q21 -> 226907.56 | ... P39: ='II-I-DIST'!S21 -> 38942.659
D40: Taxes Other Than Federal Income Tax | F40: =SUM(G40:P40) -> 4.8252028e+08 | G40: ='II-I-DIST'!J24 -> 2.1582799e+08 | H40: ='II-I-DIST'!K24 -> 6574075.1 | I40: ='II-I-DIST'!L24 -> 1.8750928e+08 | J40: ='II-I-DIST'!M24 -> 25914.634 | K40: ='II-I-DIST'!N24 -> 32451644 | L40: ='II-I-DIST'!O24 -> 5269286.3 | M40: ='II-I-DIST'!P24 -> 27492618 | N40: ='II-I-DIST'!Q24 -> 6179210.6 | ... P40: ='II-I-DIST'!S24 -> 800274.8 | S40: =IF(ROUND(F40-'WP II-I-1.1'!G497,2)=0,TRUE,F40-'WP II-I-1.1'!G497) -> TRUE
D41: Federal Income Tax | F41: =SUM(G41:P41) -> 1.4008147e+08 | G41: ='II-I-DIST'!J25 -> 76325937 | H41: ='II-I-DIST'!K25 -> 2004781.4 | I41: ='II-I-DIST'!L25 -> 48825552 | J41: ='II-I-DIST'!M25 -> 13856.399 | K41: ='II-I-DIST'!N25 -> 9205940.8 | L41: ='II-I-DIST'!O25 -> 1080092.5 | M41: ='II-I-DIST'!P25 -> 274962.9 | N41: ='II-I-DIST'!Q25 -> 1923365.5 | ... P41: ='II-I-DIST'!S25 -> 351755.95 | S41: =IF(ROUND(F41-'WP II-I-1.1'!G498,2)=0,TRUE,F41-'WP II-I-1.1'!G498) -> TRUE
D42: Return on Rate Base | F42: =SUM(G42:P42) -> 1.0090184e+09 | G42: ='II-I-DIST'!J27 -> 5.4961144e+08 | H42: ='II-I-DIST'!K27 -> 14413199 | I42: ='II-I-DIST'!L27 -> 3.5158328e+08 | J42: ='II-I-DIST'!M27 -> 105279.47 | K42: ='II-I-DIST'!N27 -> 66579264 | L42: ='II-I-DIST'!O27 -> 7827010.9 | M42: ='II-I-DIST'!P27 -> 1959955 | N42: ='II-I-DIST'!Q27 -> 13851283 | ... P42: ='II-I-DIST'!S27 -> 2542656.6
D43: Minus Other Revenues | F43: =SUM(G43:P43) -> 66812956 | G43: ='II-I-DIST'!J31 -> 37227660 | H43: ='II-I-DIST'!K31 -> 1479140 | I43: ='II-I-DIST'!L31 -> 17210937 | J43: ='II-I-DIST'!M31 -> 17485.299 | K43: ='II-I-DIST'!N31 -> 4364179.9 | L43: ='II-I-DIST'!O31 -> 1290926.5 | M43: ='II-I-DIST'!P31 -> 4559734.3 | N43: ='II-I-DIST'!Q31 -> 409541.83 | ... P43: ='II-I-DIST'!S31 -> 164565.08
D45: Rate Case Expense A928 | F45: =SUM(G45:P45) -> 0 | G45: ='WP II-I-1.7'!E21 -> 0 | H45: ='WP II-I-1.7'!F21 -> 0 | I45: ='WP II-I-1.7'!G21 -> 0 | J45: ='WP II-I-1.7'!H21 -> 0 | K45: ='WP II-I-1.7'!I21 -> 0 | L45: ='WP II-I-1.7'!J21 -> 0 | M45: ='WP II-I-1.7'!K21 -> 0 | N45: ='WP II-I-1.7'!L21 -> 0 | ... P45: ='WP II-I-1.7'!N21 -> 0
D46: A565 Transmission of Electricity by Others | F46: =SUM(G46:P46) -> 2.1008415e+09 | G46: ='II-I-DIST'!J645 -> 9.2140499e+08 | H46: ='II-I-DIST'!K645 -> 18574877 | I46: ='II-I-DIST'!L645 -> 6.4145952e+08 | J46: ='II-I-DIST'!M645 -> 202929.39 | K46: ='II-I-DIST'!N645 -> 1.9944942e+08 | L46: ='II-I-DIST'!O645 -> 72408096 | M46: ='II-I-DIST'!P645 -> 2.4734164e+08 | N46: ='II-I-DIST'!Q645 -> 0 | ... P46: ='II-I-DIST'!S645 -> 0
D47: Total Distribution Facilities Less A565 & A928 | F47: =SUM(G47:P47) -> 3.4592512e+09 | G47: ='WP II-I-1.7'!E23 -> 1.808863e+09 | H47: ='WP II-I-1.7'!F23 -> 51193085 | I47: ='WP II-I-1.7'!G23 -> 1.2075801e+09 | J47: ='WP II-I-1.7'!H23 -> 533883.98 | K47: ='WP II-I-1.7'!I23 -> 2.3514573e+08 | L47: ='WP II-I-1.7'!J23 -> 26160818 | M47: ='WP II-I-1.7'!K23 -> 26746602 | N47: ='WP II-I-1.7'!L23 -> 92687433 | ... P47: ='WP II-I-1.7'!N23 -> 8506147.8

Sheet WP II-I-1.1
B3: ='II-I-1'!B2 -> 2025 RATE CASE
B4: ='II-I-1'!B3 -> ONCOR ELECTRIC DELIVERY COMPANY LLC
B5: II-I-1: CLASS REVENUE REQUIREMENT ANALYSIS
B6: ='II-I-1'!B5 -> TEST YEAR ENDING 12/31/2024
B7: ='II-I-1'!B6 -> SPONSOR: MATTHEW A. TROXLE
B10: WORKPAPER 1.1 - CONSOLIDATION OF FUNCTIONALIZED COST OF SERVICE
B13: Line | C13: Account | D13: Description | E13: Reference | F13: TRAN | G13: DIST | H13: MET | I13: TDCS | J13: Total
C14: Number | E14: Schedule
C15: (a) | D15: (b) | E15: (c) | F15: (d) | G15: (e) | H15: (f) | I15: (i) | J15: (j)
B17: =B16+1 -> 1 | C17: Intangible Plant - Gross | E17: II-B-1
B18: 2 | C18: A301 | D18: Organization | F18: 0 | G18: 0 | H18: 0 | I18: 0 | J18: 0 | K18: =J18-SUM(F18:I18) -> 0
B19: 3 | C19: A302 | D19: Franchise & Consents | F19: 0 | G19: 0 | H19: 0 | I19: 0 | J19: 0 | K19: =J19-SUM(F19:I19) -> 0
B20: 4 | C20: A303 | D20: Miscellaneous Intangible Plant | F20: 6784530 | G20: 8645784 | H20: 324360 | I20: 145326 | J20: 15900000 | K20: =J20-SUM(F20:I20) -> 0
B21: 5 | C21: Intangible plant - Accumulated Depreciation | E21: II-B-5 | K21: =J21-SUM(F21:I21) -> 0
B22: 6 | C22: A301 | D22: Organization | F22: 0 | G22: 0 | H22: 0 | I22: 0 | J22: 0 | K22: =J22-SUM(F22:I22) -> 0
B23: 7 | C23: A302 | D23: Franchise and Consents | F23: 0 | G23: 0 | H23: 0 | I23: 0 | J23: 0 | K23: =J23-SUM(F23:I23) -> 0
B24: 8 | C24: A303 | D24: Miscellaneous Intangible Plant | F24: 2514612.3 | G24: 3204465.8 | H24: 120220.51 | I24: 53863.5 | J24: 5893162.1 | K24: =J24-SUM(F24:I24) -> 0
B25: 9 | C25: Transmission Plant - Gross | E25: II-B-1 | K25: =J25-SUM(F25:I25) -> 0
B26: 10 | C26: A349 | D26: Land Owned in Fee | F26: 1.5984856e+08 | G26: 0 | H26: 0 | I26: 0 | J26: 1.5984856e+08 | K26: =J26-SUM(F26:I26) -> 0
B27: 11 | C27: A350 | D27: Land and Land Rights | F27: 6.7572377e+08 | G27: 0 | H27: 0 | I27: 0 | J27: 6.7572377e+08 | K27: =J27-SUM(F27:I27) -> 0
B28: 12 | C28: A351.1 | D28: Computer Hardware | F28: 0 | G28: 0 | H28: 0 | I28: 0 | J28: 0 | K28: =J28-SUM(F28:I28) -> 0
B29: 13 | C29: A351.2 | D29: Computer Software | F29: 1.5082575e+08 | G29: 0 | H29: 0 | I29: 0 | J29: 1.5082575e+08 | K29: =J29-SUM(F29:I29) -> 0
B30: 14 | C30: A351.3 | D30: Communication Equipment | F30: 3528604.2 | G30: 0 | H30: 0 | I30: 0 | J30: 3528604.2 | K30: =J30-SUM(F30:I30) -> 0
B31: 15 | C31: A352 | D31: Structures and Improvements | F31: 6.5478537e+08 | G31: 0 | H31: 0 | I31: 0 | J31: 6.5478537e+08 | K31: =J31-SUM(F31:I31) -> 0
B32: 16 | C32: A353 | D32: Station Equipment | F32: 4.4997751e+09 | G32: 4.6897613e+08 | H32: 0 | I32: 0 | J32: 4.9687512e+09 | K32: =J32-SUM(F32:I32) -> 0
B33: 17 | C33: A354 | D33: Towers and Fixtures | F33: 2.1534233e+09 | G33: 0 | H33: 0 | I33: 0 | J33: 2.1534233e+09 | K33: =J33-SUM(F33:I33) -> 0
B34: 18 | C34: A355 | D34: Poles and Fixtures | F34: 4.0735736e+09 | G34: 0 | H34: 0 | I34: 0 | J34: 4.0735736e+09 | K34: =J34-SUM(F34:I34) -> 0
B35: 19 | C35: A356 | D35: Overhead Conductors and Devices | F35: 3.7347934e+09 | G35: 0 | H35: 0 | I35: 0 | J35: 3.7347934e+09 | K35: =J35-SUM(F35:I35) -> 0
B36: 20 | C36: A357 | D36: Underground Conduit | F36: 61796401 | G36: 0 | H36: 0 | I36: 0 | J36: 61796401 | K36: =J36-SUM(F36:I36) -> 0
B37: 21 | C37: A358 | D37: Underground Conductors and Devices | F37: 96633109 | G37: 0 | H37: 0 | I37: 0 | J37: 96633109 | K37: =J37-SUM(F37:I37) -> 0
B38: 22 | C38: A359 | D38: Roads and Trails | F38: 0 | G38: 0 | H38: 0 | I38: 0 | J38: 0 | K38: =J38-SUM(F38:I38) -> 0
B39: 23 | C39: Transmission Plant - Accumulated Depreciation | E39: II-B-5 | K39: =J39-SUM(F39:I39) -> 0
B40: 24 | C40: A349 | D40: Land Owned in Fee | F40: 0 | G40: 0 | H40: 0 | I40: 0 | J40: 0 | K40: =J40-SUM(F40:I40) -> 0
B41: 25 | C41: A350 | D41: Land and Land Rights | F41: 1.4077873e+08 | G41: 0 | H41: 0 | I41: 0 | J41: 1.4077873e+08 | K41: =J41-SUM(F41:I41) -> 0
B42: 26 | C42: A351.1 | D42: Computer Hardware | F42: 0 | G42: 0 | H42: 0 | I42: 0 | J42: 0 | K42: =J42-SUM(F42:I42) -> 0
B43: 27 | C43: A351.2 | D43: Computer Software | F43: 56291413 | G43: 0 | H43: 0 | I43: 0 | J43: 56291413 | K43: =J43-SUM(F43:I43) -> 0
B44: 28 | C44: A351.3 | D44: Communication Equipment | F44: 1213664.3 | G44: 0 | H44: 0 | I44: 0 | J44: 1213664.3 | K44: =J44-SUM(F44:I44) -> 0
B45: 29 | C45: A352 | D45: Structures and Improvements | F45: 1.6443899e+08 | G45: 0 | H45: 0 | I45: 0 | J45: 1.6443899e+08 | K45: =J45-SUM(F45:I45) -> 0
B46: 30 | C46: A353 | D46: Station Equipment | F46: 9.6296508e+08 | G46: 1.3442784e+08 | H46: 0 | I46: 0 | J46: 1.0973929e+09 | K46: =J46-SUM(F46:I46) -> 0
B47: 31 | C47: A354 | D47: Towers and Fixtures | F47: 6.4803222e+08 | G47: 0 | H47: 0 | I47: 0 | J47: 6.4803222e+08 | K47: =J47-SUM(F47:I47) -> 0
B48: 32 | C48: A355 | D48: Poles and Fixtures | F48: 1.0244216e+09 | G48: 0 | H48: 0 | I48: 0 | J48: 1.0244216e+09 | K48: =J48-SUM(F48:I48) -> 0
B49: 33 | C49: A356 | D49: Overhead Conductors and Devices | F49: 8.6967001e+08 | G49: 0 | H49: 0 | I49: 0 | J49: 8.6967001e+08 | K49: =J49-SUM(F49:I49) -> 0
B50: 34 | C50: A357 | D50: Underground Conduit | F50: 24828551 | G50: 0 | H50: 0 | I50: 0 | J50: 24828551 | K50: =J50-SUM(F50:I50) -> 0
B51: 35 | C51: A358 | D51: Underground Conductors and Devices | F51: 35777645 | G51: 0 | H51: 0 | I51: 0 | J51: 35777645 | K51: =J51-SUM(F51:I51) -> 0
B52: 36 | C52: A359 | D52: Roads and Trails | F52: 0 | G52: 0 | H52: 0 | I52: 0 | J52: 0 | K52: =J52-SUM(F52:I52) -> 0
K53: =J53-SUM(F53:I53) -> 0
K54: =J54-SUM(F54:I54) -> 0
B55: 1 | C55: Distribution Plant - Gross | E55: II-B-1 | K55: =J55-SUM(F55:I55) -> 0
B56: 2 | C56: A360 | D56: Land and Land Rights | F56: 2551204.7 | G56: 26320548 | H56: 0 | I56: 0 | J56: 28871753 | K56: =J56-SUM(F56:I56) -> 0
B57: 3 | C57: A361 | D57: Structures and Improvements | F57: 1.3509365e+08 | G57: 2.6261664e+08 | H57: 0 | I57: 0 | J57: 3.9771029e+08 | K57: =J57-SUM(F57:I57) -> 0
B58: 4 | C58: A362 | D58: Station Equipment | F58: 9.0962532e+08 | G58: 2.4751282e+09 | H58: 0 | I58: 0 | J58: 3.3847535e+09 | K58: =J58-SUM(F58:I58) -> 0
B59: 5 | C59: A363.1 | D59: Computer Hardware | F59: 0 | G59: 0 | H59: 0 | I59: 0 | J59: 0 | K59: =J59-SUM(F59:I59) -> 0
B60: 6 | C60: A363.2 | D60: Computer Software | F60: 0 | G60: 3.2758042e+08 | H60: 1.2107389e+08 | I60: 3.3487324e+08 | J60: 7.8352755e+08 | K60: =J60-SUM(F60:I60) -> 0
B61: 7 | C61: A363.3 | D61: Communication Equipment | F61: 0 | G61: 0 | H61: 38191350 | I61: 0 | J61: 38191350 | K61: =J61-SUM(F61:I61) -> 0
B62: 8 | C62: A364 | D62: Poles,Towers & Fixtures-Total | F62: 0 | G62: 3.5234113e+09 | H62: 0 | I62: 0 | J62: 3.5234113e+09 | K62: =J62-SUM(F62:I62) -> 0
B63: 9 | C63: A365 | D63: O.H. Conductors & Devices-Total | F63: 0 | G63: 2.1826184e+09 | H63: 0 | I63: 0 | J63: 2.1826184e+09 | K63: =J63-SUM(F63:I63) -> 0
B64: 10 | C64: A366 | D64: Underground Conduits-Total | F64: 0 | G64: 1.6373228e+09 | H64: 0 | I64: 0 | J64: 1.6373228e+09 | K64: =J64-SUM(F64:I64) -> 0
B65: 11 | C65: A367 | D65: U.G. Conductors & Devices-Total | F65: 0 | G65: 3.1769233e+09 | H65: 0 | I65: 0 | J65: 3.1769233e+09 | K65: =J65-SUM(F65:I65) -> 0
B66: 12 | C66: A368 | D66: Line Transformers-Total | F66: 0 | G66: 3.1676659e+09 | H66: 0 | I66: 0 | J66: 3.1676659e+09 | K66: =J66-SUM(F66:I66) -> 0
B67: 13 | C67: A369 | D67: Services | F67: 0 | G67: 1.9703439e+09 | H67: 0 | I67: 0 | J67: 1.9703439e+09 | K67: =J67-SUM(F67:I67) -> 0
... B72: 18 | C72: A374 | D72: Land Owned in Fee | F72: 35890398 | G72: 88171655 | H72: 0 | I72: 0 | J72: 1.2406205e+08 | K72: =J72-SUM(F72:I72) -> 0
B73: 19 | C73: Distribution Plant - Accumulated Depreciation | E73: II-B-5 | K73: =J73-SUM(F73:I73) -> 0
B74: 20 | C74: A360 | D74: Land and Land Rights | F74: 339719.3 | G74: 9501839.8 | H74: 0 | I74: 0 | J74: 9841559.2 | K74: =J74-SUM(F74:I74) -> 0
B75: 21 | C75: A361 | D75: Structures and Improvements | F75: 22759235 | G75: 49998606 | H75: 0 | I75: 0 | J75: 72757841 | K75: =J75-SUM(F75:I75) -> 0
B76: 22 | C76: A362 | D76: Station Equipment | F76: 1.4162885e+08 | G76: 5.0619935e+08 | H76: 0 | I76: 0 | J76: 6.478282e+08 | K76: =J76-SUM(F76:I76) -> 0
B77: 23 | C77: A363.1 | D77: Computer Hardware | F77: 0 | G77: 0 | H77: 0 | I77: 0 | J77: 0 | K77: =J77-SUM(F77:I77) -> 0
B78: 24 | C78: A363.2 | D78: Computer Software | F78: 0 | G78: 90241525 | H78: 89519193 | I78: 1.08843e+08 | J78: 2.8860372e+08 | K78: =J78-SUM(F78:I78) -> 0
B79: 25 | C79: A363.3 | D79: Communication Equipment | F79: 0 | G79: 0 | H79: 39392673 | I79: 0 | J79: 39392673 | K79: =J79-SUM(F79:I79) -> 0
B80: 26 | C80: A364 | D80: Poles,Towers & Fixtures-Total | F80: 0 | G80: 1.2025566e+09 | H80: 0 | I80: 0 | J80: 1.2025566e+09 | K80: =J80-SUM(F80:I80) -> 0
B81: 27 | C81: A365 | D81: O.H. Conductors & Devices-Total | F81: 0 | G81: 6.8915546e+08 | H81: 0 | I81: 0 | J81: 6.8915546e+08 | K81: =J81-SUM(F81:I81) -> 0
B82: 28 | C82: A366 | D82: Underground Conduits-Total | F82: 0 | G82: 5.502411e+08 | H82: 0 | I82: 0 | J82: 5.502411e+08 | K82: =J82-SUM(F82:I82) -> 0
B83: 29 | C83: A367 | D83: U.G. Conductors & Devices-Total | F83: 0 | G83: 6.9124546e+08 | H83: 0 | I83: 0 | J83: 6.9124546e+08 | K83: =J83-SUM(F83:I83) -> 0
B84: 30 | C84: A368 | D84: Line Transformers-Total | F84: 0 | G84: 7.6162719e+08 | H84: 0 | I84: 0 | J84: 7.6162719e+08 | K84: =J84-SUM(F84:I84) -> 0
B85: 31 | C85: A369 | D85: Services | F85: 0 | G85: 1.2373138e+09 | H85: 0 | I85: 0 | J85: 1.2373138e+09 | K85: =J85-SUM(F85:I85) -> 0
... B89: 35 | C89: A373 | D89: Street Lights | F89: 0 | G89: 3.7925174e+08 | H89: 0 | I89: 0 | J89: 3.7925174e+08 | K89: =J89-SUM(F89:I89) -> 0
K90: =J90-SUM(F90:I90) -> 0
K91: =J91-SUM(F91:I91) -> 0
B92: 1 | C92: General Plant - Gross | E92: II-B-2 | K92: =J92-SUM(F92:I92) -> 0
B93: 2 | C93: A388 | D93: Land Owned in Fee | F93: 9811323.6 | G93: 25309318 | H93: 4008542.7 | I93: 2615601.5 | J93: 41744785 | K93: =J93-SUM(F93:I93) -> 0
B94: 3 | C94: A389 | D94: Land and Land Rights | F94: 60382.02 | G94: 77649.91 | H94: 3248.17 | I94: 1318.1 | J94: 142598.2 | K94: =J94-SUM(F94:I94) -> 0
B95: 4 | C95: A390 | D95: Structures and Improvements | F95: 1.20851e+08 | G95: 2.1232994e+08 | H95: 32267268 | I95: 18151522 | J95: 3.8359973e+08 | K95: =J95-SUM(F95:I95) -> 0
B96: 5 | C96: A391 | D96: Office Furniture & Equip. | F96: 12493434 | G96: 13217078 | H96: 1565800.9 | I96: 1076747.4 | J96: 28353060 | K96: =J96-SUM(F96:I96) -> 0
B97: 6 | C97: A392 | D97: Transportation Equipment | F97: 10018624 | G97: 10180664 | H97: 0 | I97: 0 | J97: 20199288 | K97: =J97-SUM(F97:I97) -> 0
B98: 7 | C98: A393 | D98: Stores Equipment | F98: 3579102.6 | G98: 5998112.8 | H98: 468889.48 | I98: 0 | J98: 10046105 | K98: =J98-SUM(F98:I98) -> 0
B99: 8 | C99: A394 | D99: Tools, Shop and Garage Equipment | F99: 13465046 | G99: 21790023 | H99: 1794789.6 | I99: 0 | J99: 37049859 | K99: =J99-SUM(F99:I99) -> 0
B100: 9 | C100: A395 | D100: Laboratory Equipment | F100: 35716452 | G100: 22852989 | H100: 2971389.5 | I100: 0 | J100: 61540831 | K100: =J100-SUM(F100:I100) -> 0
B101: 10 | C101: A396 | D101: Power Operated Equipment | F101: 2683861.8 | G101: 8159482.3 | H101: 910269.58 | I101: 0 | J101: 11753614 | K101: =J101-SUM(F101:I101) -> 0
B102: 11 | C102: A397.1 | D102: Computer Hardware | E102: II-B-3 | F102: 42064361 | G102: 68043569 | H102: 16420909 | I102: 43509119 | J102: 1.7003796e+08 | K102: =J102-SUM(F102:I102) -> 0
B103: 12 | C103: A397.2 | D103: Computer Software | F103: 1.6663376e+08 | G103: 1.882108e+08 | H103: 5189735.5 | I103: 364002.32 | J103: 3.603983e+08 | K103: =J103-SUM(F103:I103) -> 0
B104: 13 | C104: A397.3 | D104: Communication Equipment | F104: 42536571 | G104: 58294862 | H104: 11299013 | I104: 7491197.5 | J104: 1.1962164e+08 | K104: =J104-SUM(F104:I104) -> 0
B105: 14 | C105: A398 | D105: Miscellaneous Equipment | F105: 6510164.6 | G105: 9639077.6 | H105: 1521329.4 | I105: 0 | J105: 17670572 | K105: =J105-SUM(F105:I105) -> 0
B106: 15 | C106: A399 | D106: Other Tangible Property | F106: 0 | G106: 0 | H106: 0 | I106: 0 | J106: 0 | K106: =J106-SUM(F106:I106) -> 0
B107: 16 | C107: General Plant - Accumulated Depreciation | E107: II-B-5 | K107: =J107-SUM(F107:I107) -> 0
B108: 17 | C108: A388 | D108: Land Owned in Fee | F108: 0 | G108: 0 | H108: 0 | I108: 0 | J108: 0 | K108: =J108-SUM(F108:I108) -> 0
B109: 18 | C109: A389 | D109: Land and Land Rights | F109: 14265.92 | G109: 18457.99 | H109: 799.17 | I109: 315.04 | J109: 33838.12 | K109: =J109-SUM(F109:I109) -> 0
B110: 19 | C110: A390 | D110: Structures and Improvements | F110: 11952441 | G110: 21370930 | H110: 2970219.5 | I110: 1393657 | J110: 37687247 | K110: =J110-SUM(F110:I110) -> 0
B111: 20 | C111: A391 | D111: Office Furniture & Equip. | F111: 2480124.2 | G111: 2172899.6 | H111: 240727.43 | I111: 164071.5 | J111: 5057822.7 | K111: =J111-SUM(F111:I111) -> 0
B112: 21 | C112: A392 | D112: Transportation Equipment | F112: 2447749.2 | G112: 1911251 | H112: 0 | I112: 0 | J112: 4359000.2 | K112: =J112-SUM(F112:I112) -> 0
B113: 22 | C113: A393 | D113: Stores Equipment | F113: 327968.01 | G113: 897247.06 | H113: 85306.45 | I113: 0 | J113: 1310521.5 | K113: =J113-SUM(F113:I113) -> 0
B114: 23 | C114: A394 | D114: Tools, Shop and Garage Equipment | F114: 3335625.4 | G114: 5513977.5 | H114: 452222.55 | I114: 0 | J114: 9301825.5 | K114: =J114-SUM(F114:I114) -> 0
...

Sheet  WP II-I-1.4
M2: =" "
B4: ='WP II-I-1.1'!B3 -> 2025 RATE CASE
B5: ='WP II-I-1.1'!B4 -> ONCOR ELECTRIC DELIVERY COMPANY LLC
B6: CONSOLIDATED FUNCTIONALIZED COST OF SERVICE
B7: ='WP II-I-1.1'!B6 -> TEST YEAR ENDING 12/31/2024
B8: ='WP II-I-2.2'!$B$7 -> SPONSOR: MATTHEW A. TROXLE
F10: TRAN | G10: DIST | H10: MET | I10: TDCS | J10: Total | L10: DIST + MET
B11: Line | D11: Revenue Requirement | E11: Source | L11: + TBILLTDCS
B13: (a) | D13: (b) | E13: (c) | F13: (d) | G13: (e) | H13: (f) | I13: (i) | J13: (j) | L13: (l)
B15: =B14+1 -> 1 | D15: O&M Expenses | E15: II-D-2 | F15: =F661+F709 -> 1.4103893e+08 | G15: =G661+G709 -> 2.4658459e+09 | H15: =H661+H709 -> 61551893 | I15: =I661+I709 -> 189681.03 | J15: =SUM(F15:I15) -> 2.6686264e+09 | L15: =SUM(G15:I15) -> 2.5275875e+09
B16: =B15+1 -> 2 | D16: Customer Expenses | E16: II-D-2 | F16: =F729+F739+F749 -> -153231.79 | G16: =G729+G739+G749 -> 339790.12 | H16: =H729+H739+H749 -> 9809696.2 | I16: =I729+I739+I749 -> 17097126 | J16: =SUM(F16:I16) -> 27093381 | L16: =SUM(G16:I16) -> 27246613
B17: =B16+1 -> 3 | D17: A&G Expenses | E17: II-D-2 | F17: =F783 -> 1.4971493e+08 | G17: =G783 -> 8.6225408e+08 | H17: =H783 -> 49056190 | I17: =I783 -> 40849532 | J17: =SUM(F17:I17) -> 1.1018747e+09 | L17: =SUM(G17:I17) -> 9.521598e+08
B18: =B17+1 -> 4 | D18: O&M + Customer + A&G Expenses | F18: =SUM(F15:F17) -> 2.9060063e+08 | G18: =SUM(G15:G17) -> 3.3284398e+09 | H18: =SUM(H15:H17) -> 1.2041778e+08 | I18: =SUM(I15:I17) -> 58136339 | J18: =SUM(F18:I18) -> 3.7975946e+09 | L18: =SUM(G18:I18) -> 3.5069939e+09 | N18: ='WP II-I-1.1'!J495=J18 -> TRUE | P18: ='WP II-I-1.1'!F495=F18 -> TRUE | Q18: ='WP II-I-1.1'!G495=G18 -> TRUE | R18: ='WP II-I-1.1'!H495=H18 -> TRUE | S18: ='WP II-I-1.1'!I495=I18 -> TRUE | T18: ='WP II-I-1.1'!J495=J18 -> TRUE
B19: =B18+1 -> 5
B20: =B19+1 -> 6 | D20: Depreciation & Amortization (II-E-1) | E20: II-E-1 | F20: =F1065 -> 4.7003129e+08 | G20: =G1065 -> 6.5141705e+08 | H20: =H1065 -> 29837696 | I20: =I1065 -> 39993574 | J20: =SUM(F20:I20) -> 1.1912796e+09 | L20: =SUM(G20:I20) -> 7.2124832e+08
B21: =B20+1 -> 7 | D21: Other (II-E-4) | E21: II-E-4 | F21: =F1067+F1068 -> 10313432 | G21: =G1067+G1068 -> 15428626 | H21: =H1067+H1068 -> 25459958 | I21: =I1067+I1068 -> 0 | J21: =SUM(F21:I21) -> 51202016 | L21: =SUM(G21:I21) -> 40888584
B22: =B21+1 -> 8 | D22: Depreciation, Amortization & Other Expenses | F22: =SUM(F20:F21) -> 4.8034473e+08 | G22: =SUM(G20:G21) -> 6.6684568e+08 | H22: =SUM(H20:H21) -> 55297654 | I22: =SUM(I20:I21) -> 39993574 | J22: =SUM(F22:I22) -> 1.2424816e+09 | L22: =SUM(G22:I22) -> 7.6213691e+08 | N22: ='WP II-I-1.1'!J496=J22 -> TRUE | P22: ='WP II-I-1.1'!F496=F22 -> TRUE | Q22: ='WP II-I-1.1'!G496=G22 -> TRUE | R22: ='WP II-I-1.1'!H496=H22 -> TRUE | S22: ='WP II-I-1.1'!I496=I22 -> TRUE | T22: ='WP II-I-1.1'!J496=J22 -> TRUE
B23: =B22+1 -> 9
B24: =B23+1 -> 10 | D24: Taxes Other Than Federal Income Tax | E24: II-E-2 | F24: =+F1103 -> 1.4708187e+08 | G24: =+G1103 -> 4.8252028e+08 | H24: =+H1103 -> 8908968.6 | I24: =+I1103 -> 3557512.7 | J24: =SUM(F24:I24) -> 6.4206863e+08 | L24: =SUM(G24:I24) -> 4.9498676e+08 | N24: ='WP II-I-1.1'!J497=J24 -> TRUE | P24: ='WP II-I-1.1'!F497=F24 -> TRUE | Q24: ='WP II-I-1.1'!G497=G24 -> TRUE | R24: ='WP II-I-1.1'!H497=H24 -> TRUE | S24: ='WP II-I-1.1'!I497-I24 -> 0 | T24: ='WP II-I-1.1'!J497=J24 -> TRUE
B25: =B24+1 -> 11 | D25: Federal Income Tax | E25: II-E-3 | F25: =+F1163 -> 1.2867713e+08 | G25: =+G1163 -> 1.4008147e+08 | H25: =+H1163 -> 1780846.8 | I25: =+I1163 -> 2876698.2 | J25: =SUM(F25:I25) -> 2.7341615e+08 | L25: =SUM(G25:I25) -> 1.4473902e+08 | N25: ='WP II-I-1.1'!J498-J25 -> 0 | P25: ='WP II-I-1.1'!F498-F25 -> 0 | Q25: ='WP II-I-1.1'!G498-G25 -> 0 | R25: ='WP II-I-1.1'!H498-H25 -> 0 | S25: ='WP II-I-1.1'!I498-I25 -> 0 | T25: ='WP II-I-1.1'!J498-J25 -> 0
B26: =B25+1 -> 12
B27: =B26+1 -> 13 | D27: Return on Rate Base | E27: II-B | F27: =+F83 -> 9.1088358e+08 | G27: =+G83 -> 1.0090184e+09 | H27: =+H83 -> 32952956 | I27: =+I83 -> 17186005 | J27: =SUM(F27:I27) -> 1.9700409e+09 | L27: =SUM(G27:I27) -> 1.0591573e+09 | N27: ='WP II-I-1.1'!J494-J27 -> 0 | P27: ='WP II-I-1.1'!F494-F27 -> 0 | Q27: ='WP II-I-1.1'!G494-G27 -> 0 | R27: ='WP II-I-1.1'!H494-H27 -> 0 | S27: ='WP II-I-1.1'!I494-I27 -> 0 | T27: ='WP II-I-1.1'!J494-J27 -> 0
B28: =B27+1 -> 14
B29: =B28+1 -> 15 | D29: TOTAL COST OF SERVICE | F29: =+F18+F22+F24+F25+F27 -> 1.9575879e+09 | G29: =+G18+G22+G24+G25+G27 -> 5.6269056e+09 | H29: =+H18+H22+H24+H25+H27 -> 2.193582e+08 | I29: =+I18+I22+I24+I25+I27 -> 1.2175013e+08 | J29: =SUM(F29:I29) -> 7.9256019e+09 | L29: =SUM(G29:I29) -> 5.9680139e+09 | N29: =ROUND('WP II-I-1.1'!$J$509,0)=ROUND(J29,0) -> TRUE
B30: 16
B31: =B30+1 -> 17 | D31: Minus: Other Revenues | E31: II-E-5 | F31: =+F1223 -> 46131717 | G31: =+G1223 -> 66812956 | H31: =+H1223 -> 14115591 | I31: =+I1223 -> 85782 | J31: =SUM(F31:I31) -> 1.2714605e+08 | L31: =SUM(G31:I31) -> 81014329 | N31: ='WP II-I-1.1'!J499--J31 -> 0
B32: =B31+1 -> 18
B33: =B32+1 -> 19 | D33: COST-BASED Revenue Requirement | F33: =+F29-F31 -> 1.9114562e+09 | G33: =+G29-G31 -> 5.5600926e+09 | H33: =+H29-H31 -> 2.0524261e+08 | I33: =+I29-I31 -> 1.2166435e+08 | J33: =SUM(F33:I33) -> 7.7984558e+09 | L33: =G33+H33+I33 -> 5.8869996e+09 | N33: =ROUND('WP II-I-1.1'!$J$510,0)=ROUND(J33,0) -> TRUE | P33: ='WP II-I-1.1'!$G$489+'WP II-I-1.1'!$H$489+'WP II-I-1.1'!$I$489-L33 -> -0.0020475388
B42: =$B$4 -> 2025 RATE CASE
B43: =$B$5 -> ONCOR ELECTRIC DELIVERY COMPANY LLC
B44: =$B$6 -> CONSOLIDATED FUNCTIONALIZED COST OF SERVICE
B45: =$B$7 -> TEST YEAR ENDING 12/31/2024
B46: =$B$8 -> SPONSOR: MATTHEW A. TROXLE
F48: TRAN | G48: DIST | H48: MET | I48: TDCS | J48: Total | L48: =L$10 -> DIST + MET
B49: Line | D49: Return On Rate Base | E49: Source | L49: =L$11 -> + TBILLTDCS
B51: (a) | D51: (b) | E51: (c) | F51: (d) | G51: (e) | H51: (f) | I51: (i) | J51: (j) | L51: (l)
B53: =B52+1 -> 1 | D53: Intangible Plant: Original Cost | E53: II-B-1 | F53: =F106 -> 6784530 | G53: =G106 -> 8645784 | H53: =H106 -> 324360 | I53: =I106 -> 145326 | J53: =SUM(F53:I53) -> 15900000 | L53: =SUM(G53:I53) -> 9115470 | N53: =SUM('WP II-I-1.1'!F18:I20)=J53 -> TRUE
B54: =B53+1 -> 2 | D54: Transmission Plant: Original Cost | E54: II-B-1 | F54: =F121 -> 1.6264707e+10 | G54: =G121 -> 4.6897613e+08 | H54: =H121 -> 0 | I54: =I121 -> 0 | J54: =SUM(F54:I54) -> 1.6733683e+10 | L54: =SUM(G54:I54) -> 4.6897613e+08 | N54: =SUM('WP II-I-1.1'!F26:I38)=J54 -> TRUE
B55: =B54+1 -> 3 | D55: Distribution Plant: Original Cost | E55: II-B-1 | F55: =F159 -> 1.0831606e+09 | G55: =G159 -> 1.9438204e+10 | H55: =H159 -> 7.8498359e+08 | I55: =I159 -> 3.3487324e+08 | J55: =SUM(F55:I55) -> 2.1641222e+10 | L55: =SUM(G55:I55) -> 2.0558061e+10 | N55: =SUM('WP II-I-1.1'!F56:I72)=J55 -> TRUE
B56: =B55+1 -> 4 | D56: Intangible, Transmission, Distribution Plant: Original Cost | F56: =SUM(F53:F55) -> 1.7354652e+10 | G56: =SUM(G53:G55) -> 1.9915826e+10 | H56: =SUM(H53:H55) -> 7.8530795e+08 | I56: =SUM(I53:I55) -> 3.3501856e+08 | J56: =SUM(F56:I56) -> 3.8390805e+10 | L56: =SUM(G56:I56) -> 2.1036153e+10 | N56: =SUM(F56:I56)=J56 -> TRUE
B57: =B56+1 -> 5 | L57: =SUM(G57:I57) -> 0
B58: =B57+1 -> 6 | D58: General Plant: Original Cost | E58: II-B-2 | F58: =+F199 -> 2.1518939e+08 | G58: =+G199 -> 3.2955433e+08 | H58: =+H199 -> 45511527 | I58: =+I199 -> 21845189 | J58: =SUM(F58:I58) -> 6.1210044e+08 | L58: =SUM(G58:I58) -> 3.9691105e+08 | N58: =SUM('WP II-I-1.1'!F93:I101)+SUM('WP II-I-1.1'!F105:I106)=J58 -> TRUE
B59: =B58+1 -> 7 | D59: Communication Equipment: Original Cost | E59: II-B-3 | F59: =+F219 -> 2.5123469e+08 | G59: =+G219 -> 3.1454923e+08 | H59: =+H219 -> 32909657 | I59: =+I219 -> 51364319 | J59: =SUM(F59:I59) -> 6.500579e+08 | L59: =SUM(G59:I59) -> 3.9882321e+08 | N59: =SUM('WP II-I-1.1'!F102:I104)=J59 -> TRUE
B60: =B59+1 -> 8 | D60: Total Plant | F60: =+F56+F58+F59 -> 1.7821076e+10 | G60: =+G56+G58+G59 -> 2.055993e+10 | H60: =+H56+H58+H59 -> 8.6372914e+08 | I60: =+I56+I58+I59 -> 4.0822807e+08 | J60: =SUM(F60:I60) -> 3.9652963e+10 | L60: =SUM(G60:I60) -> 2.1831887e+10 | N60: =SUM(F60:I60)=J60 -> TRUE
B61: =B60+1 -> 9 | L61: =SUM(G61:I61) -> 0
B62: =B61+1 -> 10 | D62: Minus: Accumulated Depreciation | E62: II-B-5 | F62: =+F363+F320 -> 4.1970689e+09 | G62: =+G363+G320 -> 6.5088395e+09 | H62: =+H363+H320 -> 4.4259116e+08 | I62: =+I363+I320 -> 1.2982432e+08 | J62: =SUM(F62:I62) -> 1.1278324e+10 | L62: =SUM(G62:I62) -> 7.081255e+09 | N62: =SUM('WP II-I-1.1'!F22:I24)+SUM('WP II-I-1.1'!F40:I52)+SUM('WP II-I-1.1'!F74:I89)+SUM('WP II-I-1.1'!F108:I121)-J62 -> 0
B63: =B62+1 -> 11
B64: =B63+1 -> 12 | D64: NET PLANT IN SERVICE | F64: =+F60-F62 -> 1.3624007e+10 | G64: =+G60-G62 -> 1.405109e+10 | H64: =+H60-H62 -> 4.2113798e+08 | I64: =+I60-I62 -> 2.7840375e+08 | J64: =SUM(F64:I64) -> 2.8374639e+10 | L64: =SUM(G64:I64) -> 1.4750632e+10
B65: =B64+1 -> 13
B66: =B65+1 -> 14 | D66: Other Rate Base Items:
B67: =B66+1 -> 15
B68: =B67+1 -> 16 | D68: CWIP | E68: II-B-4 | F68: =+F244 -> 0 | G68: =+G244 -> 0 | H68: =+H244 -> 0 | I68: =+I244 -> 0 | J68: =SUM(F68:I68) -> 0 | L68: =SUM(G68:I68) -> 0
B69: =B68+1 -> 17 | D69: Plant Held for Future Use | E69: II-B-6 | F69: =+F388 -> 61450358 | G69: =+G388 -> 6705448.4 | H69: =+H388 -> 0 | I69: =+I388 -> 0 | J69: =SUM(F69:I69) -> 68155806 | L69: =SUM(G69:I69) -> 6705448.4
B70: =B69+1 -> 18 | D70: Accumulated Provisions ex ADFIT | E70: II-B-7 | F70: =F409 -> 0 | G70: =G409 -> 0 | H70: =H409 -> 0 | I70: =I409 -> 0 | J70: =SUM(F70:I70) -> 0 | L70: =SUM(G70:I70) -> 0
B71: =B70+1 -> 19 | D71: Materials & Supplies | E71: II-B-8 | F71: =+F435 -> 2.1912871e+08 | G71: =+G435 -> 1.5795807e+08 | H71: =+H435 -> 1241799.5 | I71: =+I435 -> 0 | J71: =SUM(F71:I71) -> 3.7832857e+08 | L71: =SUM(G71:I71) -> 1.5919987e+08
B72: =B71+1 -> 20 | D72: Cash Working Capital | E72: II-B-9 | F72: =+F455 -> -56089574 | G72: =+G455 -> -25613472 | H72: =+H455 -> -298798.52 | I72: =+I455 -> 175757.58 | J72: =SUM(F72:I72) -> -81826087 | L72: =SUM(G72:I72) -> -25736513
B73: =B72+1 -> 21 | D73: Prepayments | E73: II-B-10 | F73: =+F476 -> 17382401 | G73: =+G476 -> 1.2774296e+08 | H73: =+H476 -> 584939.39 | I73: =+I476 -> 529501.18 | J73: =SUM(F73:I73) -> 1.462398e+08 | L73: =SUM(G73:I73) -> 1.288574e+08
B74: =B73+1 -> 22 | D74: Misc Other Rate Base | E74: II-B-11 | F74: =F499 -> 517979.78 | G74: =G499 -> -1977961.9 | H74: =H499 -> -302530.2 | I74: =I499 -> 0 | J74: =SUM(F74:I74) -> -1762512.3 | L74: =SUM(G74:I74) -> -2280492.1
B75: =B74+1 -> 23 | D75: Regulatory Assets | E75: II-B-12 | F75: =F614 -> -4.1355084e+08 | G75: =G614 -> 6.260253e+08 | H75: =H614 -> 30745550 | I75: =I614 -> 2989198.3 | J75: =SUM(F75:I75) -> 2.4620921e+08 | L75: =SUM(G75:I75) -> 6.5976005e+08
B76: =B75+1 -> 24 | D76: Accumulated Deferred Income Taxes | E76: II-E3.7 | F76: =+F413 -> -1.2589562e+09 | G76: =+G413 -> -1.4343219e+09 | H76: =+H413 -> -11971648 | I76: =+I413 -> -52031200 | J76: =SUM(F76:I76) -> -2.757281e+09 | L76: =SUM(G76:I76) -> -1.4983248e+09
B77: =B76+1 -> 25 | D77: Subtotal | F77: =SUM(F68:F76) -> -1.4301172e+09 | G77: =SUM(G68:G76) -> -5.4348158e+08 | H77: =SUM(H68:H76) -> 19999312 | I77: =SUM(I68:I76) -> -48336743 | J77: =SUM(F77:I77) -> -2.0019362e+09 | L77: =SUM(G77:I77) -> -5.7181901e+08
B78: =B77+1 -> 26
B79: =B78+1 -> 27 | D79: TOTAL RATE BASE | F79: =+F64+F77 -> 1.219389e+10 | G79: =+G64+G77 -> 1.3507609e+10 | H79: =+H64+H77 -> 4.4113729e+08 | I79: =+I64+I77 -> 2.3006701e+08 | J79: =SUM(F79:I79) -> 2.6372703e+10 | L79: =SUM(G79:I79) -> 1.4178813e+10 | N79: =SUM(G79:I79)=L79 -> TRUE | P79: ='WP II-I-1.1'!$J$492-J79 -> 0
B80: =B79+1 -> 28
B81: =B80+1 -> 29 | D81: COST-BASED Rate of Return | F81: =F620 -> 0.0747 | G81: =G620 -> 0.0747 | H81: =H620 -> 0.0747 | I81: =I620 -> 0.0747 | J81: =J83/J79 -> 0.0747 | L81: =L83/L79 -> 0.0747
B82: =B81+1 -> 30
B83: =B82+1 -> 31 | D83: COST-BASED Return On Rate Base | F83: =+F79*F81 -> 9.1088358e+08 | G83: =+G79*G81 -> 1.0090184e+09 | H83: =+H79*H81 -> 32952956 | I83: =+I79*I81 -> 17186005 | J83: =SUM(F83:I83) -> 1.9700409e+09 | L83: =SUM(G83:I83) -> 1.0591573e+09 | N83: =IF(ROUND(J83-'WP II-I-1.1'!J494,2)=0,TRUE,J83-'WP II-I-1.1'!J494) -> TRUE
N84: =ROUND('WP II-I-1.1'!F494,0)-ROUND(F83,0) -> 0 | O84: ='WP II-I-1.1'!G494 -> 1.0090184e+09 | P84: ='WP II-I-1.1'!G494-G83 -> 0 | Q84: ='WP II-I-1.1'!H494-H83 -> 0 | R84: ='WP II-I-1.1'!I494=I83 -> TRUE
B91: =$B$4 -> 2025 RATE CASE | M91: =$M$2
B92: =$B$5 -> ONCOR ELECTRIC DELIVERY COMPANY LLC
B93: =$B$6 -> CONSOLIDATED FUNCTIONALIZED COST OF SERVICE
B94: =$B$7 -> TEST YEAR ENDING 12/31/2024
B95: =$B$8 -> SPONSOR: MATTHEW A. TROXLE
F97: TRAN | G97: DIST | H97: MET | I97: TDCS | J97: Total | L97: DIST + MET
B98: Line | C98: Acct | D98: Intangible and Transmission Plant Gross | E98: Source | L98: + TBILLTDCS
C100: (a) | D100: (b) | E100: (c) | F100: (d) | G100: (e) | H100: (f) | I100: (i) | J100: (j) | L100: (k)
B102: =B101+1 -> 1 | C102: Intangible Plant Gross | E102: II-B-1
B103: =B102+1 -> 2 | C103: A301 | D103: Organization | F103: ='WP II-I-1.1'!F18 -> 0 | G103: ='WP II-I-1.1'!G18 -> 0 | H103: ='WP II-I-1.1'!H18 -> 0 | I103: ='WP II-I-1.1'!I18 -> 0 | J103: =SUM(F103:I103) -> 0 | L103: =SUM(G103:I103) -> 0 | N103: =J103-L103-F103 -> 0
B104: =B103+1 -> 3 | C104: A302 | D104: Franchise & Consents | F104: ='WP II-I-1.1'!F19 -> 0 | G104: ='WP II-I-1.1'!G19 -> 0 | H104: ='WP II-I-1.1'!H19 -> 0 | I104: ='WP II-I-1.1'!I19 -> 0 | J104: =SUM(F104:I104) -> 0 | L104: =SUM(G104:I104) -> 0 | N104: =J104-L104-F104 -> 0
B105: =B104+1 -> 4 | C105: A303 | D105: Miscellaneous Intangible Plant | F105: ='WP II-I-1.1'!F20 -> 6784530 | G105: ='WP II-I-1.1'!G20 -> 8645784 | H105: ='WP II-I-1.1'!H20 -> 324360 | I105: ='WP II-I-1.1'!I20 -> 145326 | J105: =SUM(F105:I105) -> 15900000 | L105: =SUM(G105:I105) -> 9115470 | N105: =J105-L105-F105 -> 0
B106: =B105+1 -> 5 | D106: Subtotal | F106: =SUM(F103:F105) -> 6784530 | G106: =SUM(G103:G105) -> 8645784 | H106: =SUM(H103:H105) -> 324360 | I106: =SUM(I103:I105) -> 145326 | J106: =SUM(F106:I106) -> 15900000 | L106: =SUM(G106:I106) -> 9115470 | N106: =J106-L106-F106 -> 0
B107: =B106+1 -> 6 | C107: Transmission Plant Gross | E107: II-B-1 | N107: =J107-L107-F107 -> 0
B108: =B107+1 -> 7 | C108: A349 | D108: Land Owned in Fee | F108: ='WP II-I-1.1'!F26 -> 1.5984856e+08 | G108: ='WP II-I-1.1'!G26 -> 0 | H108: ='WP II-I-1.1'!H26 -> 0 | I108: ='WP II-I-1.1'!I26 -> 0 | J108: =SUM(F108:I108) -> 1.5984856e+08 | L108: =SUM(G108:I108) -> 0 | N108: =J108-L108-F108 -> 0
B109: =B108+1 -> 8 | C109: A350 | D109: Land and Land Rights | F109: ='WP II-I-1.1'!F27 -> 6.7572377e+08 | G109: ='WP II-I-1.1'!G27 -> 0 | H109: ='WP II-I-1.1'!H27 -> 0 | I109: ='WP II-I-1.1'!I27 -> 0 | J109: =SUM(F109:I109) -> 6.7572377e+08 | L109: =SUM(G109:I109) -> 0 | N109: =J109-L109-F109 -> 0
B110: =B109+1 -> 9 | C110: A351.1 | D110: Computer Hardware | F110: ='WP II-I-1.1'!F28 -> 0 | G110: ='WP II-I-1.1'!G28 -> 0 | H110: ='WP II-I-1.1'!H28 -> 0 | I110: ='WP II-I-1.1'!I28 -> 0 | J110: =SUM(F110:I110) -> 0 | L110: =SUM(G110:I110) -> 0
B111: =B110+1 -> 10 | C111: A351.2 | D111: Computer Software | F111: ='WP II-I-1.1'!F29 -> 1.5082575e+08 | G111: ='WP II-I-1.1'!G29 -> 0 | H111: ='WP II-I-1.1'!H29 -> 0 | I111: ='WP II-I-1.1'!I29 -> 0 | J111: =SUM(F111:I111) -> 1.5082575e+08 | L111: =SUM(G111:I111) -> 0
B112: =B111+1 -> 11 | C112: A351.3 | D112: Communication Equipment | F112: ='WP II-I-1.1'!F30 -> 3528604.2 | G112: ='WP II-I-1.1'!G30 -> 0 | H112: ='WP II-I-1.1'!H30 -> 0 | I112: ='WP II-I-1.1'!I30 -> 0 | J112: =SUM(F112:I112) -> 3528604.2 | L112: =SUM(G112:I112) -> 0
B113: =B112+1 -> 12 | C113: A352 | D113: Structures and Improvements | F113: ='WP II-I-1.1'!F31 -> 6.5478537e+08 | G113: ='WP II-I-1.1'!G31 -> 0 | H113: ='WP II-I-1.1'!H31 -> 0 | I113: ='WP II-I-1.1'!I31 -> 0 | J113: =SUM(F113:I113) -> 6.5478537e+08 | L113: =SUM(G113:I113) -> 0 | N113: =J113-L113-F113 -> 0
B114: =B113+1 -> 13 | C114: A353 | D114: Station Equipment | F114: ='WP II-I-1.1'!F32 -> 4.4997751e+09 | G114: ='WP II-I-1.1'!G32 -> 4.6897613e+08 | H114: ='WP II-I-1.1'!H32 -> 0 | I114: ='WP II-I-1.1'!I32 -> 0 | J114: =SUM(F114:I114) -> 4.9687512e+09 | L114: =SUM(G114:I114) -> 4.6897613e+08 | N114: =J114-L114-F114 -> 0
B115: =B114+1 -> 14 | C115: A354 | D115: Towers and Fixtures | F115: ='WP II-I-1.1'!F33 -> 2.1534233e+09 | G115: ='WP II-I-1.1'!G33 -> 0 | H115: ='WP II-I-1.1'!H33 -> 0 | I115: ='WP II-I-1.1'!I33 -> 0 | J115: =SUM(F115:I115) -> 2.1534233e+09 | L115: =SUM(G115:I115) -> 0 | N115: =J115-L115-F115 -> 0
B116: =B115+1 -> 15 | C116: A355 | D116: Poles and Fixtures | F116: ='WP II-I-1.1'!F34 -> 4.0735736e+09 | G116: ='WP II-I-1.1'!G34 -> 0 | H116: ='WP II-I-1.1'!H34 -> 0 | I116: ='WP II-I-1.1'!I34 -> 0 | J116: =SUM(F116:I116) -> 4.0735736e+09 | L116: =SUM(G116:I116) -> 0 | N116: =J116-L116-F116 -> 0
B117: =B116+1 -> 16 | C117: A356 | D117: O.H. Conductors & Devices | F117: ='WP II-I-1.1'!F35 -> 3.7347934e+09 | G117: ='WP II-I-1.1'!G35 -> 0 | H117: ='WP II-I-1.1'!H35 -> 0 | I117: ='WP II-I-1.1'!I35 -> 0 | J117: =SUM(F117:I117) -> 3.7347934e+09 | L117: =SUM(G117:I117) -> 0 | N117: =J117-L117-F117 -> 0
B118: =B117+1 -> 17 | C118: A357 | D118: Underground Conduit | F118: ='WP II-I-1.1'!F36 -> 61796401 | G118: ='WP II-I-1.1'!G36 -> 0 | H118: ='WP II-I-1.1'!H36 -> 0 | I118: ='WP II-I-1.1'!I36 -> 0 | J118: =SUM(F118:I118) -> 61796401 | L118: =SUM(G118:I118) -> 0 | N118: =J118-L118-F118 -> 0
B119: =B118+1 -> 18 | C119: A358 | D119: Underground Conductors | F119: ='WP II-I-1.1'!F37 -> 96633109 | G119: ='WP II-I-1.1'!G37 -> 0 | H119: ='WP II-I-1.1'!H37 -> 0 | I119: ='WP II-I-1.1'!I37 -> 0 | J119: =SUM(F119:I119) -> 96633109 | L119: =SUM(G119:I119) -> 0 | N119: =J119-L119-F119 -> 0
B120: =B119+1 -> 19 | C120: A359 | D120: Roads and Trails | F120: ='WP II-I-1.1'!F38 -> 0 | G120: ='WP II-I-1.1'!G38 -> 0 | H120: ='WP II-I-1.1'!H38 -> 0 | I120: ='WP II-I-1.1'!I38 -> 0 | J120: =SUM(F120:I120) -> 0 | L120: =SUM(G120:I120) -> 0 | N120: =J120-L120-F120 -> 0
B121: =B120+1 -> 20 | D121: Subtotal | F121: =SUM(F108:F120) -> 1.6264707e+10 | G121: =SUM(G108:G120) -> 4.6897613e+08 | H121: =SUM(H108:H120) -> 0 | I121: =SUM(I108:I120) -> 0 | J121: =SUM(F121:I121) -> 1.6733683e+10 | L121: =SUM(G121:I121) -> 4.6897613e+08 | N121: =J121-L121-F121 -> 0
M122: =$M$2
B124: =$B$4 -> 2025 RATE CASE
B125: =$B$5 -> ONCOR ELECTRIC DELIVERY COMPANY LLC
B126: =$B$6 -> CONSOLIDATED FUNCTIONALIZED COST OF SERVICE
...

Sheet II-I-DIST
B4: ='WP II-I-1.1'!B3 -> 2025 RATE CASE
B5: ='WP II-I-1.1'!B4 -> ONCOR ELECTRIC DELIVERY COMPANY LLC
B6: ="II-I-1-DIST: CLASS REVENUE REQUIREMENT" -> II-I-1-DIST: CLASS REVENUE REQUIREMENT
B7: ='WP II-I-1.1'!B6 -> TEST YEAR ENDING 12/31/2024
B8: ='WP II-I-2.2'!$B$7 -> SPONSOR: MATTHEW A. TROXLE
R10: =" "
B11: Line | D11: I-A-1 by Rate Class | E11: Source | F11: DIST | J11: Residential | K11: Secondary | L11: Secondary | M11: Primary | N11: Primary | O11: Primary | P11: Transmission | Q11: Lighting | R11: Wholesale | S11: Wholesale | U11: Total
K12: <=10 kW | L12: > 10 kW | M12: <=10 kW | N12: > 10 kW | O12: Substation | R12: XFMR | S12: DLS
F13: (a) | G13: (b) | H13: (c) | J13: (d) | K13: (e) | L13: (f) | M13: (g) | N13: (h) | O13: (i) | P13: (j) | Q13: (k) | R13: (l) | S13: (m) | U13: (n)
B15: =B14+1 -> 1 | D15: O&M Expenses | E15: II-D-2 | F15: =F661+F709 -> 2.4658459e+09 | J15: =J661+J709 -> 1.1125812e+09 | K15: =K661+K709 -> 22758119 | L15: =L661+L709 -> 7.6382629e+08 | M15: =M661+M709 -> 359979.97 | N15: =N661+N709 -> 2.3027371e+08 | O15: =O661+O709 -> 75448315 | P15: =P661+P709 -> 2.4742689e+08 | Q15: =Q661+Q709 -> 11812787 | ... S15: =S661+S709 -> 1150425.1 | U15: =SUM(I15:T15) -> 2.4658459e+09 | X15: =U15-F15 -> 0
B16: =B15+1 -> 2 | D16: Customer Expenses | E16: II-D-2 | F16: =F729+F739+F749 -> 339790.12 | J16: =J729+J739+J749 -> 254774.27 | K16: =K729+K739+K749 -> 24361.403 | L16: =L729+L739+L749 -> 44514.918 | M16: =M729+M739+M749 -> 1487.8884 | N16: =N729+N739+N749 -> 10475.931 | O16: =O729+O739+O749 -> 339.88168 | P16: =P729+P739+P749 -> 708.95565 | Q16: =Q729+Q739+Q749 -> 2993.6929 | ... S16: =S729+S739+S749 -> 95.644139 | U16: =SUM(I16:T16) -> 339790.12 | X16: =U16-F16 -> 0
B17: =B16+1 -> 3 | D17: A&G Expenses | E17: II-D-2 | F17: =F783 -> 8.6225408e+08 | J17: =J783 -> 4.5986261e+08 | K17: =K783 -> 13373498 | L17: =L783 -> 2.9176041e+08 | M17: =M783 -> 182914.3 | N17: =N783 -> 59664370 | O17: =O783 -> 6384539.4 | P17: =P783 -> 825460.58 | Q17: =Q783 -> 27500799 | ... S17: =S783 -> 2260998.9 | U17: =SUM(I17:T17) -> 8.6225408e+08 | X17: =U17-F17 -> 0
B18: =B17+1 -> 4 | D18: O&M + Customer + A&G Expenses | F18: =SUM(F15:F17) -> 3.3284398e+09 | J18: =SUM(J15:J17) -> 1.5726986e+09 | K18: =SUM(K15:K17) -> 36155979 | L18: =SUM(L15:L17) -> 1.0556312e+09 | M18: =SUM(M15:M17) -> 544382.16 | N18: =SUM(N15:N17) -> 2.8994855e+08 | O18: =SUM(O15:O17) -> 81833194 | P18: =SUM(P15:P17) -> 2.4825306e+08 | Q18: =SUM(Q15:Q17) -> 39316579 | ... S18: =SUM(S15:S17) -> 3411519.6 | U18: =SUM(I18:T18) -> 3.3284398e+09 | X18: =U18-F18 -> 0 | Y18: ='WP II-I-1.1'!$G$495=U18 -> TRUE | Z18: should match schedule D
B19: =B18+1 -> 5 | X19: =U19-F19 -> 0
B20: =B19+1 -> 6 | D20: Depreciation & Amortization (II-E-1) | E20: II-E-1 | F20: =F1065 -> 6.5141705e+08 | J20: =J1065 -> 3.4461415e+08 | K20: =K1065 -> 11876247 | L20: =L1065 -> 2.1734221e+08 | M20: =M1065 -> 63251.401 | N20: =N1065 -> 39759013 | O20: =O1065 -> 3731667.6 | P20: =P1065 -> 647373.09 | Q20: =Q1065 -> 31599630 | ... S20: =S1065 -> 1525563.3 | U20: =SUM(I20:T20) -> 6.5141705e+08 | X20: =U20-F20 -> 0
B21: =B20+1 -> 7 | D21: Other (II-E-4) | E21: II-E-4 | F21: =F1067+F1068 -> 15428626 | J21: =J1067+J1068 -> 8417584.3 | K21: =K1067+K1068 -> 222821.52 | L21: =L1067+L1068 -> 5359035.8 | M21: =M1067+M1068 -> 1614.6021 | N21: =N1067+N1068 -> 1014918 | O21: =O1067+O1068 -> 118589.03 | P21: =P1067+P1068 -> 20014.916 | Q21: =Q1067+Q1068 -> 226907.56 | ... S21: =S1067+S1068 -> 38942.659 | U21: =SUM(I21:T21) -> 15428626 | X21: =U21-F21 -> 0
B22: =B21+1 -> 8 | D22: Depreciation, Amortization & Other Expenses | F22: =SUM(F20:F21) -> 6.6684568e+08 | J22: =SUM(J20:J21) -> 3.5303173e+08 | K22: =SUM(K20:K21) -> 12099069 | L22: =SUM(L20:L21) -> 2.2270124e+08 | M22: =SUM(M20:M21) -> 64866.003 | N22: =SUM(N20:N21) -> 40773931 | O22: =SUM(O20:O21) -> 3850256.6 | P22: =SUM(P20:P21) -> 667388.01 | Q22: =SUM(Q20:Q21) -> 31826537 | ... S22: =SUM(S20:S21) -> 1564506 | U22: =SUM(I22:T22) -> 6.6684568e+08 | X22: =U22-F22 -> 0 | Y22: ='WP II-I-1.1'!$G$496=U22 -> TRUE
B23: =B22+1 -> 9 | X23: =U23-F23 -> 0
B24: =B23+1 -> 10 | D24: Taxes Other Than Federal Income Tax | E24: II-E-2 | F24: =+F1103 -> 4.8252028e+08 | J24: =+J1103 -> 2.1582799e+08 | K24: =+K1103 -> 6574075.1 | L24: =+L1103 -> 1.8750928e+08 | M24: =+M1103 -> 25914.634 | N24: =+N1103 -> 32451644 | O24: =+O1103 -> 5269286.3 | P24: =+P1103 -> 27492618 | Q24: =+Q1103 -> 6179210.6 | ... S24: =+S1103 -> 800274.8 | U24: =SUM(I24:T24) -> 4.8252028e+08 | X24: =U24-F24 -> 0 | Y24: ='WP II-I-1.1'!$G$497=U24 -> TRUE
B25: =B24+1 -> 11 | D25: Federal Income Tax | E25: II-E-3 | F25: =+F1162 -> 1.4008147e+08 | J25: =+J1162 -> 76325937 | K25: =+K1162 -> 2004781.4 | L25: =+L1162 -> 48825552 | M25: =+M1162 -> 13856.399 | N25: =+N1162 -> 9205940.8 | O25: =+O1162 -> 1080092.5 | P25: =+P1162 -> 274962.9 | Q25: =+Q1162 -> 1923365.5 | ... S25: =+S1162 -> 351755.95 | U25: =SUM(I25:T25) -> 1.4008147e+08 | X25: =U25-F25 -> 0 | Y25: ='WP II-I-1.1'!$G$498-U25 -> 0
B26: =B25+1 -> 12 | X26: =U26-F26 -> 0
B27: =B26+1 -> 13 | D27: Return on Rate Base | E27: II-B | F27: =+F83 -> 1.0090184e+09 | J27: =+J83 -> 5.4961144e+08 | K27: =+K83 -> 14413199 | L27: =+L83 -> 3.5158328e+08 | M27: =+M83 -> 105279.47 | N27: =+N83 -> 66579264 | O27: =+O83 -> 7827010.9 | P27: =+P83 -> 1959955 | Q27: =+Q83 -> 13851283 | ... S27: =+S83 -> 2542656.6 | U27: =SUM(I27:T27) -> 1.0090184e+09 | X27: =U27-F27 -> 0 | Y27: ='WP II-I-1.1'!$G$494=U27 -> TRUE
B28: =B27+1 -> 14 | X28: =U28-F28 -> 0
B29: =B28+1 -> 15 | D29: TOTAL COST OF SERVICE | F29: =+F18+F22+F24+F25+F27 -> 5.6269056e+09 | J29: =+J18+J22+J24+J25+J27 -> 2.7674957e+09 | K29: =+K18+K22+K24+K25+K27 -> 71247103 | L29: =+L18+L22+L24+L25+L27 -> 1.8662506e+09 | M29: =+M18+M22+M24+M25+M27 -> 754298.66 | N29: =+N18+N22+N24+N25+N27 -> 4.3895933e+08 | O29: =+O18+O22+O24+O25+O27 -> 99859840 | P29: =+P18+P22+P24+P25+P27 -> 2.7864798e+08 | Q29: =+Q18+Q22+Q24+Q25+Q27 -> 93096975 | ... S29: =+S18+S22+S24+S25+S27 -> 8670712.8 | U29: =SUM(I29:T29) -> 5.6269056e+09 | X29: =U29-F29 -> 0 | Y29: ='WP II-I-1.1'!$G$509=U29 -> TRUE
B30: =B29+1 -> 16 | X30: =U30-F30 -> 0
B31: =B30+1 -> 17 | D31: Minus: Other Revenues | E31: II-E-5 | F31: =+F1222 -> 66812956 | J31: =+J1222 -> 37227660 | K31: =+K1222 -> 1479140 | L31: =+L1222 -> 17210937 | M31: =+M1222 -> 17485.299 | N31: =+N1222 -> 4364179.9 | O31: =+O1222 -> 1290926.5 | P31: =+P1222 -> 4559734.3 | Q31: =+Q1222 -> 409541.83 | ... S31: =+S1222 -> 164565.08 | U31: =SUM(I31:T31) -> 66812956 | X31: =U31-F31 -> 0 | Y31: ='WP II-I-1.1'!$G$499=-U31 -> TRUE
B32: =B31+1 -> 18 | X32: =U32-F32 -> 0
B33: =B32+1 -> 19 | D33: COST-BASED Revenue Requirement | F33: =+F29-F31 -> 5.5600926e+09 | J33: =+J29-J31 -> 2.730268e+09 | K33: =+K29-K31 -> 69767963 | L33: =+L29-L31 -> 1.8490396e+09 | M33: =+M29-M31 -> 736813.37 | N33: =+N29-N31 -> 4.3459515e+08 | O33: =+O29-O31 -> 98568914 | P33: =+P29-P31 -> 2.7408825e+08 | Q33: =+Q29-Q31 -> 92687433 | ... S33: =+S29-S31 -> 8506147.8 | U33: =SUM(I33:T33) -> 5.5600926e+09 | W33: =IF(' WP II-I-1.4'!G33=U33,TRUE,' WP II-I-1.4'!G33-G33) -> TRUE | X33: =U33-F33 -> 0 | Y33: ='WP II-I-1.1'!$G$500=U33 -> TRUE
B34: =B33+1 -> 20 | X34: =U34-F34 -> 0
B35: =B34+1 -> 21 | X35: =U35-F35 -> 0
B36: =B35+1 -> 22 | X36: =U36-F36 -> 0
B37: =B36+1 -> 23 | D37: PROPOSED Revenue | F37: =F33 -> 5.5600926e+09 | J37: =J33 -> 2.730268e+09 | K37: =K33 -> 69767963 | L37: =L33 -> 1.8490396e+09 | M37: =M33 -> 736813.37 | N37: =N33 -> 4.3459515e+08 | O37: =O33 -> 98568914 | P37: =P33 -> 2.7408825e+08 | Q37: =Q33 -> 92687433 | ... S37: =S33 -> 8506147.8 | U37: =SUM(I37:T37) -> 5.5600926e+09 | X37: =U37-F37 -> 0
B38: =B37+1 -> 24 | X38: =U38-F38 -> 0 | Y38: ='WP II-I-2.2'!$P$45 -> 0
B39: =B38+1 -> 25 | D39: PROPOSED Revenue Excl 565 and A928 RCE | F39: =+F37-F645-('WP II-I-2.2'!$P$45)*F776 -> 3.4592512e+09 | J39: =+J37-J645-('WP II-I-2.2'!$P$45)*J776 -> 1.808863e+09 | K39: =+K37-K645-('WP II-I-2.2'!$P$45)*K776 -> 51193085 | L39: =+L37-L645-('WP II-I-2.2'!$P$45)*L776 -> 1.2075801e+09 | M39: =+M37-M645-('WP II-I-2.2'!$P$45)*M776 -> 533883.98 | N39: =+N37-N645-('WP II-I-2.2'!$P$45)*N776 -> 2.3514573e+08 | O39: =+O37-O645-('WP II-I-2.2'!$P$45)*O776 -> 26160818 | P39: =+P37-P645-('WP II-I-2.2'!$P$45)*P776 -> 26746602 | Q39: =+Q37-Q645-('WP II-I-2.2'!$P$45)*Q776 -> 92687433 | ... S39: =+S37-S645-('WP II-I-2.2'!$P$45)*S776 -> 8506147.8 | U39: =SUM(I39:T39) -> 3.4592512e+09 | X39: =U39-F39 -> 0 | Y39: =ROUND('WP II-I-1.1'!$G$500-'WP II-I-1.1'!$G$220-('WP II-I-1.1'!$G$279*'WP II-I-2.2'!$P$45),0)-U39 -> 0.40673065
W40: =U39-F39 -> 0 | X40: =U40-F40 -> 0
V41: =$H$2 -> 0
B42: =+$B$4 -> 2025 RATE CASE | X42: =U42-F42 -> 0
B43: =+$B$5 -> ONCOR ELECTRIC DELIVERY COMPANY LLC | X43: =U43-F43 -> 0
B44: =+$B$6 -> II-I-1-DIST: CLASS REVENUE REQUIREMENT | X44: =U44-F44 -> 0
B45: =+$B$7 -> TEST YEAR ENDING 12/31/2024 | X45: =U45-F45 -> 0
B46: =+$B$8 -> SPONSOR: MATTHEW A. TROXLE | X46: =U46-F46 -> 0
X47: =U47-F47 -> 0
R48: =R$10 | X48: =U48-F48 -> 0
B49: Line | D49: II-B by Rate Class | E49: Source | F49: =F$11 -> DIST | J49: Residential | K49: Secondary | L49: Secondary | M49: Primary | N49: Primary | O49: Primary | P49: Transmission | Q49: Lighting | R49: =R$11 -> Wholesale | S49: =S$11 -> Wholesale | U49: Total
K50: <=10 kW | L50: > 10 kW | M50: <=10 kW | N50: > 10 kW | O50: Substation | R50: =R$12 -> XFMR | S50: =S$12 -> DLS | X50: =U50-F50 -> 0
F51: (a) | G51: (b) | H51: (c) | J51: =J$13 -> (d) | K51: =K$13 -> (e) | L51: =L$13 -> (f) | M51: =M$13 -> (g) | N51: =N$13 -> (h) | O51: =O$13 -> (i) | P51: =P$13 -> (j) | Q51: =Q$13 -> (k) | ... S51: =S$13 -> (m) | U51: (n)
X52: =U52-F52 -> 0
B53: =B52+1 -> 1 | D53: Intangible Plant: Original Cost | E53: II-B-1 | F53: =F106 -> 8645784 | J53: =J106 -> 4716986.3 | K53: =K106 -> 124863.15 | L53: =L106 -> 3003058.5 | M53: =M106 -> 904.77929 | N53: =N106 -> 568732.57 | O53: =O106 -> 66454.08 | P53: =P106 -> 11215.817 | Q53: =Q106 -> 127152.85 | ... S53: =S106 -> 21822.411 | U53: =SUM(I53:T53) -> 8645784 | X53: =U53-F53 -> 0
B54: =B53+1 -> 2 | D54: Transmission Plant: Original Cost | E54: II-B-1 | F54: =F121 -> 4.6897613e+08 | J54: =J121 -> 2.4047525e+08 | K54: =K121 -> 4543218.9 | L54: =L121 -> 1.5445827e+08 | M54: =M121 -> 72277.313 | N54: =N121 -> 45432585 | O54: =O121 -> 19527819 | P54: =P121 -> 0 | Q54: =Q121 -> 1373608.1 | ... S54: =S121 -> 1743259.7 | U54: =SUM(I54:T54) -> 4.6897613e+08 | X54: =U54-F54 -> 0
B55: =B54+1 -> 3 | D55: Distribution Plant: Original Cost | E55: II-B-1 | F55: =F159 -> 1.9438204e+10 | J55: =J159 -> 1.0449095e+10 | K55: =K159 -> 3.4290123e+08 | L55: =L159 -> 6.6029029e+09 | M55: =M159 -> 1879656.1 | N55: =N159 -> 1.1815275e+09 | O55: =O159 -> 1.1357074e+08 | P55: =P159 -> 23080391 | Q55: =Q159 -> 6.7006043e+08 | ... S55: =S159 -> 45335508 | U55: =SUM(I55:T55) -> 1.9438204e+10 | X55: =U55-F55 -> 0
B56: =B55+1 -> 4 | D56: Intangible, Transmission, Distribution Plant: Original Cost | F56: =SUM(F53:F55) -> 1.9915826e+10 | J56: =SUM(J53:J55) -> 1.0694288e+10 | K56: =SUM(K53:K55) -> 3.4756931e+08 | L56: =SUM(L53:L55) -> 6.7603642e+09 | M56: =SUM(M53:M55) -> 1952838.2 | N56: =SUM(N53:N55) -> 1.2275289e+09 | O56: =SUM(O53:O55) -> 1.3316501e+08 | P56: =SUM(P53:P55) -> 23091607 | Q56: =SUM(Q53:Q55) -> 6.7156119e+08 | ... S56: =SUM(S53:S55) -> 47100590 | U56: =SUM(I56:T56) -> 1.9915826e+10 | X56: =U56-F56 -> 0
B57: =B56+1 -> 5 | X57: =U57-F57 -> 0
B58: =B57+1 -> 6 | D58: General Plant: Original Cost | E58: II-B-2 | F58: =+F199 -> 3.2955433e+08 | J58: =+J199 -> 1.7979899e+08 | K58: =+K199 -> 4759451.6 | L58: =+L199 -> 1.1446862e+08 | M58: =+M199 -> 34487.785 | N58: =+N199 -> 21678576 | O58: =+O199 -> 2533053.1 | P58: =+P199 -> 427517.15 | Q58: =+Q199 -> 4846729.2 | ... S58: =+S199 -> 831812.39 | U58: =SUM(I58:T58) -> 3.2955433e+08 | X58: =U58-F58 -> 0
B59: =B58+1 -> 7 | D59: Communication Equipment: Original Cost | E59: II-B-3 | F59: =+F219 -> 3.1454923e+08 | J59: =+J219 -> 1.7161248e+08 | K59: =+K219 -> 4542746.7 | L59: =+L219 -> 1.0925669e+08 | M59: =+M219 -> 32917.505 | N59: =+N219 -> 20691518 | O59: =+O219 -> 2417719.4 | P59: =+P219 -> 408051.66 | Q59: =+Q219 -> 4626050.4 | ... S59: =+S219 -> 793938.73 | U59: =SUM(I59:T59) -> 3.1454923e+08 | X59: =U59-F59 -> 0
B60: =B59+1 -> 8 | D60: Total Plant | F60: =+F56+F58+F59 -> 2.055993e+10 | J60: =+J56+J58+J59 -> 1.1045699e+10 | K60: =+K56+K58+K59 -> 3.5687151e+08 | L60: =+L56+L58+L59 -> 6.9840895e+09 | M60: =+M56+M58+M59 -> 2020243.5 | N60: =+N56+N58+N59 -> 1.269899e+09 | O60: =+O56+O58+O59 -> 1.3811578e+08 | P60: =+P56+P58+P59 -> 23927176 | Q60: =+Q56+Q58+Q59 -> 6.8103397e+08 | ... S60: =+S56+S58+S59 -> 48726341 | U60: =SUM(I60:T60) -> 2.055993e+10 | X60: =U60-F60 -> 0
B61: =B60+1 -> 9 | X61: =U61-F61 -> 0
B62: =B61+1 -> 10 | D62: Minus: Accumulated Depreciation | E62: II-B-5 | F62: =+F363+F320 -> 6.5088395e+09 | J62: =+J363+J320 -> 3.3796737e+09 | K62: =+K363+K320 -> 1.5394447e+08 | L62: =+L363+L320 -> 2.103532e+09 | M62: =+M363+M320 -> 549800.16 | N62: =+N363+N320 -> 3.4559728e+08 | O62: =+O363+O320 -> 30114905 | P62: =+P363+P320 -> 5699280.1 | Q62: =+Q363+Q320 -> 4.7438571e+08 | ... S62: =+S363+S320 -> 13260654 | U62: =SUM(I62:T62) -> 6.5088395e+09 | X62: =U62-F62 -> 0
B63: =B62+1 -> 11 | X63: =U63-F63 -> 0
B64: =B63+1 -> 12 | D64: NET PLANT IN SERVICE | F64: =+F60-F62 -> 1.405109e+10 | J64: =+J60-J62 -> 7.6660254e+09 | K64: =+K60-K62 -> 2.0292704e+08 | L64: =+L60-L62 -> 4.8805575e+09 | M64: =+M60-M62 -> 1470443.3 | N64: =+N60-N62 -> 9.2430168e+08 | O64: =+O60-O62 -> 1.0800088e+08 | P64: =+P60-P62 -> 18227896 | Q64: =+Q60-Q62 -> 2.0664826e+08 | ... S64: =+S60-S62 -> 35465687 | U64: =SUM(I64:T64) -> 1.405109e+10 | X64: =U64-F64 -> 0
B65: =B64+1 -> 13 | X65: =U65-F65 -> 0
B66: =B65+1 -> 14 | D66: Other Rate Base Items: | X66: =U66-F66 -> 0
B67: =B66+1 -> 15 | X67: =U67-F67 -> 0
B68: =B67+1 -> 16 | D68: CWIP | E68: II-B-4 | F68: =+F244 -> 0 | J68: =+J244 -> 0 | K68: =+K244 -> 0 | L68: =+L244 -> 0 | M68: =+M244 -> 0 | N68: =+N244 -> 0 | O68: =+O244 -> 0 | P68: =+P244 -> 0 | Q68: =+Q244 -> 0 | ... S68: =+S244 -> 0 | U68: =SUM(I68:T68) -> 0 | X68: =U68-F68 -> 0
B69: =B68+1 -> 17 | D69: Plant Held for Future Use | E69: II-B-6 | F69: =+F388 -> 6705448.4 | J69: =+J388 -> 3438329.3 | K69: =+K388 -> 64959.212 | L69: =+L388 -> 2208453.5 | M69: =+M388 -> 1033.4253 | N69: =+N388 -> 649597.79 | O69: =+O388 -> 279209.92 | P69: =+P388 -> 0 | Q69: =+Q388 -> 19639.929 | ... S69: =+S388 -> 24925.23 | U69: =SUM(I69:T69) -> 6705448.4 | X69: =U69-F69 -> 0
B70: =B69+1 -> 18 | D70: Accumulated Provisions ex ADFIT | E70: II-B-7 | F70: =F409 -> 0 | J70: =J409 -> 0 | K70: =K409 -> 0 | L70: =L409 -> 0 | M70: =M409 -> 0 | N70: =N409 -> 0 | O70: =O409 -> 0 | P70: =P409 -> 0 | Q70: =Q409 -> 0 | ... S70: =S409 -> 0 | U70: =SUM(I70:T70) -> 0 | X70: =U70-F70 -> 0
B71: =B70+1 -> 19 | D71: Materials & Supplies | E71: II-B-8 | F71: =+F435 -> 1.5795807e+08 | J71: =+J435 -> 84862025 | K71: =+K435 -> 2741776.6 | L71: =+L435 -> 53657444 | M71: =+M435 -> 15521.15 | N71: =+N435 -> 9756394.4 | O71: =+O435 -> 1061117.5 | P71: =+P435 -> 183827.98 | Q71: =+Q435 -> 5232255.7 | ... S71: =+S435 -> 374355.3 | U71: =SUM(I71:T71) -> 1.5795807e+08 | X71: =U71-F71 -> 0
B72: =B71+1 -> 20 | D72: Cash Working Capital | E72: II-B-9 | F72: =+F455 -> -25613472 | J72: =+J455 -> -11557764 | K72: =+K455 -> -236615.77 | L72: =+L455 -> -7933459.1 | M72: =+M455 -> -3754.1564 | N72: =+N455 -> -2391700.5 | O72: =+O455 -> -783599.55 | P72: =+P455 -> -2569749.6 | Q72: =+Q455 -> -122717.1 | ... S72: =+S455 -> -11949.153 | U72: =SUM(I72:T72) -> -25613472 | X72: =U72-F72 -> 0
B73: =B72+1 -> 21 | D73: Prepayments | E73: II-B-10 | F73: =+F476 -> 1.2774296e+08 | J73: =+J476 -> 50085293 | K73: =+K476 -> 1517383.2 | L73: =+L476 -> 53329041 | M73: =+M476 -> 1026.7885 | N73: =+N476 -> 8830441.4 | O73: =+O476 -> 1683243.4 | P73: =+P476 -> 11609227 | Q73: =+Q476 -> 409815.29 | ... S73: =+S476 -> 150181.63 | U73: =SUM(I73:T73) -> 1.2774296e+08 | X73: =U73-F73 -> 0
B74: =B73+1 -> 22 | D74: Misc Other Rate Base | E74: II-B-11 | F74: =F499 -> -1977961.9 | J74: =J499 -> -880186.95 | K74: =K499 -> -16629.079 | L74: =L499 -> -565347.8 | M74: =M499 -> -264.54926 | N74: =N499 -> -166292.24 | O74: =O499 -> -71475.68 | P74: =P499 -> -261416.54 | Q74: =Q499 -> -5027.6771 | ... S74: =S499 -> -6380.6751 | U74: =SUM(I74:T74) -> -1977961.9 | X74: =U74-F74 -> 0
B75: =B74+1 -> 23 | D75: Regulatory Assets | E75: II-B-12 | F75: =F614 -> 6.260253e+08 | J75: =J614 -> 3.3619067e+08 | K75: =K614 -> 10846282 | L75: =L614 -> 2.1258079e+08 | M75: =M614 -> 66295.923 | N75: =N614 -> 38900488 | O75: =O614 -> 4245256 | P75: =P614 -> 717130.51 | Q75: =Q614 -> 20754209 | ... S75: =S614 -> 1440715.6 | U75: =SUM(I75:T75) -> 6.260253e+08 | X75: =U75-F75 -> 0
B76: =B75+1 -> 24 | D76: Acuumulated Deferred Income Taxes | E76: II-E3.7 | F76: =+F413 -> -1.4343219e+09 | J76: =+J413 -> -7.7058086e+08 | K76: =+K413 -> -24896419 | L76: =+L413 -> -4.8723088e+08 | M76: =+M413 -> -140938.2 | N76: =+N413 -> -88591933 | O76: =+O413 -> -9635368.4 | P76: =+P413 -> -1669231 | Q76: =+Q413 -> -47510957 | ... S76: =+S413 -> -3399294.7 | U76: =SUM(I76:T76) -> -1.4343219e+09 | X76: =U76-F76 -> 0
B77: =B76+1 -> 25 | D77: Subtotal | F77: =SUM(F68:F76) -> -5.4348158e+08 | J77: =SUM(J68:J76) -> -3.0844249e+08 | K77: =SUM(K68:K76) -> -9979263 | L77: =SUM(L68:L76) -> -1.7395396e+08 | M77: =SUM(M68:M76) -> -61079.62 | N77: =SUM(N68:N76) -> -33013004 | O77: =SUM(O68:O76) -> -3221616.7 | P77: =SUM(P68:P76) -> 8009788.7 | Q77: =SUM(Q68:Q76) -> -21222783 | ... S77: =SUM(S68:S76) -> -1427446.7 | U77: =SUM(I77:T77) -> -5.4348158e+08 | X77: =U77-F77 -> 0
B78: =B77+1 -> 26 | X78: =U78-F78 -> 0
B79: =B78+1 -> 27 | D79: TOTAL RATE BASE | F79: =+F64+F77 -> 1.3507609e+10 | J79: =+J64+J77 -> 7.3575829e+09 | K79: =+K64+K77 -> 1.9294777e+08 | L79: =+L64+L77 -> 4.7066035e+09 | M79: =+M64+M77 -> 1409363.7 | N79: =+N64+N77 -> 8.9128868e+08 | O79: =+O64+O77 -> 1.0477926e+08 | P79: =+P64+P77 -> 26237684 | Q79: =+Q64+Q77 -> 1.8542547e+08 | ... S79: =+S64+S77 -> 34038240 | U79: =SUM(I79:T79) -> 1.3507609e+10 | X79: =U79-F79 -> 0
B80: =B79+1 -> 28 | X80: =U80-F80 -> 0
B81: =B80+1 -> 29 | D81: COST-BASED Rate of Return | F81: =F620 -> 0.0747 | J81: =J620 -> 0.0747 | K81: =K620 -> 0.0747 | L81: =L620 -> 0.0747 | M81: =M620 -> 0.0747 | N81: =N620 -> 0.0747 | O81: =O620 -> 0.0747 | P81: =P620 -> 0.0747 | Q81: =Q620 -> 0.0747 | ... S81: =S620 -> 0.0747 | U81: =U83/U79 -> 0.0747 | X81: =U81-F81 -> 0
B82: =B81+1 -> 30
B83: =B82+1 -> 31 | D83: COST-BASED Return On Rate Base | F83: =+F79*F81 -> 1.0090184e+09 | J83: =+J79*J81 -> 5.4961144e+08 | K83: =+K79*K81 -> 14413199 | L83: =+L79*L81 -> 3.5158328e+08 | M83: =+M79*M81 -> 105279.47 | N83: =+N79*N81 -> 66579264 | O83: =+O79*O81 -> 7827010.9 | P83: =+P79*P81 -> 1959955 | Q83: =+Q79*Q81 -> 13851283 | ... S83: =+S79*S81 -> 2542656.6 | U83: =SUM(I83:T83) -> 1.0090184e+09 | X83: =IF(ROUND(U83-'WP II-I-1.1'!G494,2)=0,TRUE,U83-'WP II-I-1.1'!G494) -> TRUE
B84: =B83+1 -> 32
B85: =B84+1 -> 33 | X85: =U85-F85 -> 0
B86: =B85+1 -> 34 | X86: =U86-F86 -> 0
B87: =B86+1 -> 35 | D87: PROPOSED Return On Rate Base | F87: =F83 -> 1.0090184e+09 | J87: =J83 -> 5.4961144e+08 | K87: =K83 -> 14413199 | L87: =L83 -> 3.5158328e+08 | M87: =M83 -> 105279.47 | N87: =N83 -> 66579264 | O87: =O83 -> 7827010.9 | P87: =P83 -> 1959955 | Q87: =Q83 -> 13851283 | ... S87: =S83 -> 2542656.6 | U87: =SUM(I87:T87) -> 1.0090184e+09 | X87: =U87-F87 -> 0
B88: =B87+1 -> 36 | X88: =U88-F88 -> 0
B89: =B88+1 -> 37 | D89: PROPOSED Rate Of Return | F89: =F87/F79 -> 0.0747 | J89: =J87/J79 -> 0.0747 | K89: =K87/K79 -> 0.0747 | L89: =L87/L79 -> 0.0747 | M89: =M87/M79 -> 0.0747 | N89: =N87/N79 -> 0.0747 | O89: =O87/O79 -> 0.0747 | P89: =P87/P79 -> 0.0747 | Q89: =Q87/Q79 -> 0.0747 | ... S89: =S87/S79 -> 0.0747 | U89: =U87/U79 -> 0.0747 | X89: =U89-F89 -> 0
X90: =U90-F90 -> 0
B91: =+$B$4 -> 2025 RATE CASE | V91: =$H$2 -> 0
B92: =+$B$5 -> ONCOR ELECTRIC DELIVERY COMPANY LLC | X92: =U92-F92 -> 0
B93: =+$B$6 -> II-I-1-DIST: CLASS REVENUE REQUIREMENT | X93: =U93-F93 -> 0
B94: =+$B$7 -> TEST YEAR ENDING 12/31/2024 | X94: =U94-F94 -> 0
B95: =+$B$8 -> SPONSOR: MATTHEW A. TROXLE | X95: =U95-F95 -> 0
X96: =U96-F96 -> 0
R97: =R$10 | X97: =U97-F97 -> 0
B98: Line | C98: Acct | D98: Intangible and Transmission Plant Gross | E98: Source | F98: =F$11 -> DIST | G98: Alloc | H98: Allocation | J98: Residential | K98: Secondary | L98: Secondary | M98: Primary | N98: Primary | O98: Primary | P98: Transmission | Q98: Lighting | R98: =R$11 -> Wholesale | S98: =S$11 -> Wholesale | U98: Total
G99: # | H99: Factor | K99: <=10 kW | L99: > 10 kW | M99: <=10 kW | N99: > 10 kW | O99: Substation | R99: =R$12 -> XFMR | S99: =S$12 -> DLS | X99: =U99-F99 -> 0
F100: (a) | G100: (b) | H100: (c) | J100: =J$13 -> (d) | K100: =K$13 -> (e) | L100: =L$13 -> (f) | M100: =M$13 -> (g) | N100: =N$13 -> (h) | O100: =O$13 -> (i) | P100: =P$13 -> (j) | Q100: =Q$13 -> (k) | ... S100: =S$13 -> (m) | U100: (n)
X101: =U101-F101 -> 0
B102: =B101+1 -> 1 | C102: Intangible Plant Gross | E102: II-B-1 | X102: =U102-F102 -> 0
B103: =B102+1 -> 2 | C103: A301 | D103: Organization | F103: =' WP II-I-1.4'!G103 -> 0 | G103: 65 | H103: =VLOOKUP(G103,FactorTable,2) -> PLT_N XINT | J103: =$F103*HLOOKUP(J$1354,FactorTable,$G103+1) -> 0 | K103: =$F103*HLOOKUP(K$1354,FactorTable,$G103+1) -> 0 | L103: =$F103*HLOOKUP(L$1354,FactorTable,$G103+1) -> 0 | M103: =$F103*HLOOKUP(M$1354,FactorTable,$G103+1) -> 0 | N103: =$F103*HLOOKUP(N$1354,FactorTable,$G103+1) -> 0 | O103: =$F103*HLOOKUP(O$1354,FactorTable,$G103+1) -> 0 | P103: =$F103*HLOOKUP(P$1354,FactorTable,$G103+1) -> 0 | Q103: =$F103*HLOOKUP(Q$1354,FactorTable,$G103+1) -> 0 | ... S103: =$F103*HLOOKUP(S$1354,FactorTable,$G103+1) -> 0 | U103: =SUM(I103:T103) -> 0 | X103: =U103-F103 -> 0
B104: =B103+1 -> 3 | C104: A302 | D104: Franchise & Consents | F104: =' WP II-I-1.4'!G104 -> 0 | G104: 65 | H104: =VLOOKUP(G104,FactorTable,2) -> PLT_N XINT | J104: =$F104*HLOOKUP(J$1354,FactorTable,$G104+1) -> 0 | K104: =$F104*HLOOKUP(K$1354,FactorTable,$G104+1) -> 0 | L104: =$F104*HLOOKUP(L$1354,FactorTable,$G104+1) -> 0 | M104: =$F104*HLOOKUP(M$1354,FactorTable,$G104+1) -> 0 | N104: =$F104*HLOOKUP(N$1354,FactorTable,$G104+1) -> 0 | O104: =$F104*HLOOKUP(O$1354,FactorTable,$G104+1) -> 0 | P104: =$F104*HLOOKUP(P$1354,FactorTable,$G104+1) -> 0 | Q104: =$F104*HLOOKUP(Q$1354,FactorTable,$G104+1) -> 0 | ... S104: =$F104*HLOOKUP(S$1354,FactorTable,$G104+1) -> 0 | U104: =SUM(I104:T104) -> 0 | X104: =U104-F104 -> 0
B105: =B104+1 -> 4 | C105: A303 | D105: Miscellaneous Intangible Plant | F105: =' WP II-I-1.4'!G105 -> 8645784 | G105: 65 | H105: =VLOOKUP(G105,FactorTable,2) -> PLT_N XINT | J105: =$F105*HLOOKUP(J$1354,FactorTable,$G105+1) -> 4716986.3 | K105: =$F105*HLOOKUP(K$1354,FactorTable,$G105+1) -> 124863.15 | L105: =$F105*HLOOKUP(L$1354,FactorTable,$G105+1) -> 3003058.5 | M105: =$F105*HLOOKUP(M$1354,FactorTable,$G105+1) -> 904.77929 | N105: =$F105*HLOOKUP(N$1354,FactorTable,$G105+1) -> 568732.57 | O105: =$F105*HLOOKUP(O$1354,FactorTable,$G105+1) -> 66454.08 | P105: =$F105*HLOOKUP(P$1354,FactorTable,$G105+1) -> 11215.817 | Q105: =$F105*HLOOKUP(Q$1354,FactorTable,$G105+1) -> 127152.85 | ... S105: =$F105*HLOOKUP(S$1354,FactorTable,$G105+1) -> 21822.411 | U105: =SUM(I105:T105) -> 8645784 | X105: =U105-F105 -> 0
...

Sheet II-I-MET
B4: ='WP II-I-1.1'!B3 -> 2025 RATE CASE
B5: ='WP II-I-1.1'!B4 -> ONCOR ELECTRIC DELIVERY COMPANY LLC
B6: ="II-I-1-MET: CLASS REVENUE REQUIREMENT" -> II-I-1-MET: CLASS REVENUE REQUIREMENT
B7: ='WP II-I-1.1'!B6 -> TEST YEAR ENDING 12/31/2024
B8: ='WP II-I-2.2'!$B$7 -> SPONSOR: MATTHEW A. TROXLE
R10: =" "
B11: Line | D11: I-A-1 by Rate Class | E11: Source | F11: MET | J11: Residential | K11: Secondary | L11: Secondary | M11: Primary | N11: Primary | O11: Primary | P11: Transmission | Q11: Lighting | R11: Wholesale | S11: Wholesale | U11: Total
K12: <=10 kW | L12: > 10 kW | M12: <=10 kW | N12: > 10 kW | O12: Substation | R12: XFMR | S12: DLS
F13: (a) | G13: (b) | H13: (c) | J13: (d) | K13: (e) | L13: (f) | M13: (g) | N13: (h) | O13: (i) | P13: (j) | Q13: (k) | R13: (l) | S13: (m) | U13: (n)
B15: =B14+1 -> 1 | D15: O&M Expenses | E15: II-D-2 | F15: =F661+F709 -> 61551893 | J15: =J661+J709 -> 32121019 | K15: =K661+K709 -> 4505538.9 | L15: =L661+L709 -> 17721446 | M15: =M661+M709 -> 746162.92 | N15: =N661+N709 -> 5746710.5 | O15: =O661+O709 -> 188908.74 | P15: =P661+P709 -> 393260.2 | Q15: =Q661+Q709 -> 55113.711 | ... S15: =S661+S709 -> 52887.16 | U15: =SUM(I15:T15) -> 61551893 | W15: =U15-F15 -> 0
B16: =B15+1 -> 2 | D16: Customer Expenses | E16: II-D-2 | F16: =F729+F739+F749 -> 9809696.2 | J16: =J729+J739+J749 -> 5121177.3 | K16: =K729+K739+K749 -> 718411.62 | L16: =L729+L739+L749 -> 2825220.4 | M16: =M729+M739+M749 -> 118975.39 | N16: =N729+N739+N749 -> 916172.16 | O16: =O729+O739+O749 -> 30061.618 | P16: =P729+P739+P749 -> 62705.216 | Q16: =Q729+Q739+Q749 -> 5225.2973 | ... S16: =S729+S739+S749 -> 8427.5014 | U16: =SUM(I16:T16) -> 9809696.2 | W16: =U16-F16 -> 0
B17: =B16+1 -> 3 | D17: A&G Expenses | E17: II-D-2 | F17: =F783 -> 49056190 | J17: =J783 -> 25617232 | K17: =K783 -> 3591351.3 | L17: =L783 -> 14115714 | M17: =M783 -> 594305.55 | N17: =N783 -> 4576748.8 | O17: =O783 -> 150357.56 | P17: =P783 -> 313211.33 | Q17: =Q783 -> 38560.809 | ... S17: =S783 -> 42112.616 | U17: =SUM(I17:T17) -> 49056190 | W17: =U17-F17 -> 0
B18: =B17+1 -> 4 | D18: O&M + Customer + A&G Expenses | F18: =SUM(F15:F17) -> 1.2041778e+08 | J18: =SUM(J15:J17) -> 62859429 | K18: =SUM(K15:K17) -> 8815301.8 | L18: =SUM(L15:L17) -> 34662381 | M18: =SUM(M15:M17) -> 1459443.9 | N18: =SUM(N15:N17) -> 11239632 | O18: =SUM(O15:O17) -> 369327.91 | P18: =SUM(P15:P17) -> 769176.74 | Q18: =SUM(Q15:Q17) -> 98899.817 | ... S18: =SUM(S15:S17) -> 103427.28 | U18: =SUM(I18:T18) -> 1.2041778e+08 | W18: =U18-F18 -> 0 | X18: ='WP II-I-1.1'!$H$495=U18 -> TRUE
B19: =B18+1 -> 5 | W19: =U19-F19 -> 0
B20: =B19+1 -> 6 | D20: Depreciation & Amortization (II-E-1) | E20: II-E-1 | F20: =F1065 -> 29837696 | J20: =J1065 -> 15576574 | K20: =K1065 -> 2185161 | L20: =L1065 -> 8593528.8 | M20: =M1065 -> 361891.15 | N20: =N1065 -> 2786752.9 | O20: =O1065 -> 91439.488 | P20: =P1065 -> 190732.68 | Q20: =Q1065 -> 15883.657 | ... S20: =S1065 -> 25634.228 | U20: =SUM(I20:T20) -> 29837696 | W20: =U20-F20 -> 0
B21: =B20+1 -> 7 | D21: Other (II-E-4) | E21: II-E-4 | F21: =F1067+F1068 -> 25459958 | J21: =J1067+J1068 -> 13291205 | K21: =K1067+K1068 -> 1864557.8 | L21: =L1067+L1068 -> 7332700.4 | M21: =M1067+M1068 -> 308795.08 | N21: =N1067+N1068 -> 2377885.1 | O21: =O1067+O1068 -> 78023.637 | P21: =P1067+P1068 -> 162748.69 | Q21: =Q1067+Q1068 -> 13553.233 | ... S21: =S1067+S1068 -> 21873.216 | U21: =SUM(I21:T21) -> 25459958 | W21: =U21-F21 -> 0
B22: =B21+1 -> 8 | D22: Depreciation, Amortization & Other Expenses | F22: =SUM(F20:F21) -> 55297654 | J22: =SUM(J20:J21) -> 28867779 | K22: =SUM(K20:K21) -> 4049718.7 | L22: =SUM(L20:L21) -> 15926229 | M22: =SUM(M20:M21) -> 670686.22 | N22: =SUM(N20:N21) -> 5164638 | O22: =SUM(O20:O21) -> 169463.13 | P22: =SUM(P20:P21) -> 353481.37 | Q22: =SUM(Q20:Q21) -> 29436.89 | ... S22: =SUM(S20:S21) -> 47507.444 | U22: =SUM(I22:T22) -> 55297654 | W22: =U22-F22 -> 0 | X22: ='WP II-I-1.1'!$H$496=U22 -> TRUE
B23: =B22+1 -> 9 | W23: =U23-F23 -> 0
B24: =B23+1 -> 10 | D24: Taxes Other Than Federal Income Tax | E24: II-E-2 | F24: =+F1103 -> 8908968.6 | J24: =+J1103 -> 4650532.4 | K24: =+K1103 -> 652364.62 | L24: =+L1103 -> 2566000.3 | M24: =+M1103 -> 108037.54 | N24: =+N1103 -> 832005.46 | O24: =+O1103 -> 27294.193 | P24: =+P1103 -> 56980.518 | Q24: =+Q1103 -> 5090.8397 | ... S24: =+S1103 -> 7649.4534 | U24: =SUM(I24:T24) -> 8908968.6 | W24: =U24-F24 -> 0 | X24: ='WP II-I-1.1'!$H$497=U24 -> TRUE
B25: =B24+1 -> 11 | D25: Federal Income Tax | E25: II-E-3 | F25: =+F1162 -> 1780846.8 | J25: =+J1162 -> 929427.38 | K25: =+K1162 -> 130337.52 | L25: =+L1162 -> 513341.73 | M25: =+M1162 -> 21581.42 | N25: =+N1162 -> 166270 | O25: =+O1162 -> 5434.1612 | P25: =+P1162 -> 11447.121 | Q25: =+Q1162 -> 886.91611 | ... S25: =+S1162 -> 1521.5944 | U25: =SUM(I25:T25) -> 1780846.8 | W25: =U25-F25 -> 0 | X25: ='WP II-I-1.1'!$H$498-U25 -> 0
B26: =B25+1 -> 12 | W26: =U26-F26 -> 0
B27: =B26+1 -> 13 | D27: Return on Rate Base | E27: II-B | F27: =+F83 -> 32952956 | J27: =+J83 -> 17198989 | K27: =+K83 -> 2412097.9 | L27: =+L83 -> 9496486.7 | M27: =+M83 -> 399417.7 | N27: =+N83 -> 3076868.4 | O27: =+O83 -> 100681.23 | P27: =+P83 -> 211496.43 | Q27: =+Q83 -> 17617.634 | ... S27: =+S83 -> 28197.472 | U27: =SUM(I27:T27) -> 32952956 | W27: =U27-F27 -> 0 | X27: ='WP II-I-1.1'!$H$494-U27 -> 0
B28: =B27+1 -> 14 | W28: =U28-F28 -> 0
B29: =B28+1 -> 15 | D29: TOTAL COST OF SERVICE | F29: =+F18+F22+F24+F25+F27 -> 2.193582e+08 | J29: =+J18+J22+J24+J25+J27 -> 1.1450616e+08 | K29: =+K18+K22+K24+K25+K27 -> 16059821 | L29: =+L18+L22+L24+L25+L27 -> 63164439 | M29: =+M18+M22+M24+M25+M27 -> 2659166.7 | N29: =+N18+N22+N24+N25+N27 -> 20479413 | O29: =+O18+O22+O24+O25+O27 -> 672200.63 | P29: =+P18+P22+P24+P25+P27 -> 1402582.2 | Q29: =+Q18+Q22+Q24+Q25+Q27 -> 151932.1 | ... S29: =+S18+S22+S24+S25+S27 -> 188303.24 | U29: =SUM(I29:T29) -> 2.193582e+08 | W29: =U29-F29 -> 0 | X29: ='WP II-I-1.1'!$H$509=U29 -> TRUE
B30: =B29+1 -> 16
B31: =B30+1 -> 17 | D31: Minus: Other Revenues | E31: II-E-5 | F31: =+F1222 -> 14115591 | J31: =+J1222 -> 7377787.4 | K31: =+K1222 -> 1034993.5 | L31: =+L1222 -> 4070293.4 | M31: =+M1222 -> 171408.42 | N31: =+N1222 -> 1319935.3 | O31: =+O1222 -> 43309.979 | P31: =+P1222 -> 90339.832 | Q31: =+Q1222 -> 7523.236 | ... S31: =+S1222 -> 0 | U31: =SUM(I31:T31) -> 14115591 | X31: ='WP II-I-1.1'!$H$499=-U31 -> TRUE
B32: =B31+1 -> 18
B33: =B32+1 -> 19 | D33: COST-BASED Revenue Requirement | F33: =+F29-F31 -> 2.0524261e+08 | J33: =+J29-J31 -> 1.0712837e+08 | K33: =+K29-K31 -> 15024827 | L33: =+L29-L31 -> 59094145 | M33: =+M29-M31 -> 2487758.3 | N33: =+N29-N31 -> 19159478 | O33: =+O29-O31 -> 628890.65 | P33: =+P29-P31 -> 1312242.3 | Q33: =+Q29-Q31 -> 144408.86 | ... S33: =+S29-S31 -> 188303.24 | U33: =SUM(I33:T33) -> 2.0524261e+08 | W33: =IF(ROUND(U33-'WP II-I-1.1'!H500,2)=0,TRUE,U33-'WP II-I-1.1'!H500) -> TRUE | X33: ='WP II-I-1.1'!$H$500=U33 -> TRUE
B42: =+$B$4 -> 2025 RATE CASE
B43: =+$B$5 -> ONCOR ELECTRIC DELIVERY COMPANY LLC
B44: =+$B$6 -> II-I-1-MET: CLASS REVENUE REQUIREMENT
B45: =+$B$7 -> TEST YEAR ENDING 12/31/2024
B46: =+$B$8 -> SPONSOR: MATTHEW A. TROXLE
R48: =R$10
B49: Line | D49: II-B by Rate Class | E49: Source | F49: =F$11 -> MET | J49: Residential | K49: Secondary | L49: Secondary | M49: Primary | N49: Primary | O49: Primary | P49: Transmission | Q49: Lighting | R49: =R$11 -> Wholesale | S49: =S$11 -> Wholesale | U49: Total
K50: <=10 kW | L50: > 10 kW | M50: <=10 kW | N50: > 10 kW | O50: Substation | R50: =R$12 -> XFMR | S50: =S$12 -> DLS
F51: (a) | G51: (b) | H51: (c) | J51: =J$13 -> (d) | K51: =K$13 -> (e) | L51: =L$13 -> (f) | M51: =M$13 -> (g) | N51: =N$13 -> (h) | O51: =O$13 -> (i) | P51: =P$13 -> (j) | Q51: =Q$13 -> (k) | ... S51: =S$13 -> (m) | U51: (n)
B53: =B52+1 -> 1 | D53: Intangible Plant: Original Cost | E53: II-B-1 | F53: =F106 -> 324360 | J53: =J106 -> 169330.02 | K53: =K106 -> 23754.475 | L53: =L106 -> 93418.641 | M53: =M106 -> 3934.0509 | N53: =N106 -> 30294.268 | O53: =O106 -> 994.02154 | P53: =P106 -> 2073.4192 | Q53: =Q106 -> 172.66826 | ... S53: =S106 -> 278.66489 | U53: =SUM(I53:T53) -> 324360 | W53: =U53-F53 -> 0
B54: =B53+1 -> 2 | D54: Transmission Plant: Original Cost | E54: II-B-1 | F54: =F121 -> 0 | J54: =J121 -> 0 | K54: =K121 -> 0 | L54: =L121 -> 0 | M54: =M121 -> 0 | N54: =N121 -> 0 | O54: =O121 -> 0 | P54: =P121 -> 0 | Q54: =Q121 -> 0 | ... S54: =S121 -> 0 | U54: =SUM(I54:T54) -> 0 | W54: =U54-F54 -> 0
B55: =B54+1 -> 3 | D55: Distribution Plant: Original Cost | E55: II-B-1 | F55: =F159 -> 7.8498359e+08 | J55: =J159 -> 4.0979556e+08 | K55: =K159 -> 57488203 | L55: =L159 -> 2.2608244e+08 | M55: =M159 -> 9520796 | N55: =N159 -> 73315155 | O55: =O159 -> 2405631.4 | P55: =P159 -> 5017881.5 | Q55: =Q159 -> 417874.44 | ... S55: =S159 -> 674396.86 | U55: =SUM(I55:T55) -> 7.8498359e+08 | W55: =U55-F55 -> 0
B56: =B55+1 -> 4 | D56: Intangible, Transmission, Distribution Plant: Original Cost | F56: =SUM(F53:F55) -> 7.8530795e+08 | J56: =SUM(J53:J55) -> 4.0996489e+08 | K56: =SUM(K53:K55) -> 57511958 | L56: =SUM(L53:L55) -> 2.2617586e+08 | M56: =SUM(M53:M55) -> 9524730 | N56: =SUM(N53:N55) -> 73345449 | O56: =SUM(O53:O55) -> 2406625.4 | P56: =SUM(P53:P55) -> 5019954.9 | Q56: =SUM(Q53:Q55) -> 418047.1 | ... S56: =SUM(S53:S55) -> 674675.53 | U56: =SUM(I56:T56) -> 7.8530795e+08 | W56: =U56-F56 -> 0
B57: =B56+1 -> 5 | W57: =U57-F57 -> 0
B58: =B57+1 -> 6 | D58: General Plant: Original Cost | E58: II-B-2 | F58: =+F199 -> 45511527 | J58: =+J199 -> 23758996 | K58: =+K199 -> 3333032.6 | L58: =+L199 -> 13107735 | M58: =+M199 -> 551993.65 | N58: =+N199 -> 4250642.5 | O58: =+O199 -> 139472.93 | P58: =+P199 -> 290925.12 | Q58: =+Q199 -> 24227.39 | ... S58: =+S199 -> 39099.965 | U58: =SUM(I58:T58) -> 45511527 | W58: =U58-F58 -> 0
B59: =B58+1 -> 7 | D59: Communication Equipment: Original Cost | E59: II-B-3 | F59: =+F219 -> 32909657 | J59: =+J219 -> 17180272 | K59: =+K219 -> 2410135.8 | L59: =+L219 -> 9478281.8 | M59: =+M219 -> 399149.91 | N59: =+N219 -> 3073665 | O59: =+O219 -> 100853.71 | P59: =+P219 -> 210369.7 | Q59: =+Q219 -> 17518.971 | ... S59: =+S219 -> 28273.419 | U59: =SUM(I59:T59) -> 32909657 | W59: =U59-F59 -> 0
B60: =B59+1 -> 8 | D60: Total Plant | F60: =+F56+F58+F59 -> 8.6372914e+08 | J60: =+J56+J58+J59 -> 4.5090416e+08 | K60: =+K56+K58+K59 -> 63255126 | L60: =+L56+L58+L59 -> 2.4876188e+08 | M60: =+M56+M58+M59 -> 10475874 | N60: =+N56+N58+N59 -> 80669757 | O60: =+O56+O58+O59 -> 2646952.1 | P60: =+P56+P58+P59 -> 5521249.7 | Q60: =+Q56+Q58+Q59 -> 459793.47 | ... S60: =+S56+S58+S59 -> 742048.91 | U60: =SUM(I60:T60) -> 8.6372914e+08 | W60: =U60-F60 -> 0
B61: =B60+1 -> 9 | W61: =U61-F61 -> 0
B62: =B61+1 -> 10 | D62: Minus: Accumulated Depreciation | E62: II-B-5 | F62: =+F363+F320 -> 4.4259116e+08 | J62: =+J363+J320 -> 2.3105183e+08 | K62: =+K363+K320 -> 32413124 | L62: =+L363+L320 -> 1.2747029e+08 | M62: =+M363+M320 -> 5368035.9 | N62: =+N363+N320 -> 41336710 | O62: =+O363+O320 -> 1356348.3 | P62: =+P363+P320 -> 2829192.9 | Q62: =+Q363+Q320 -> 235606.88 | ... S62: =+S363+S320 -> 380239.91 | U62: =SUM(I62:T62) -> 4.4259116e+08 | W62: =U62-F62 -> 0
B63: =B62+1 -> 11 | W63: =U63-F63 -> 0
B64: =B63+1 -> 12 | D64: NET PLANT IN SERVICE | F64: =+F60-F62 -> 4.2113798e+08 | J64: =+J60-J62 -> 2.1985233e+08 | K64: =+K60-K62 -> 30842002 | L64: =+L60-L62 -> 1.2129158e+08 | M64: =+M60-M62 -> 5107837.7 | N64: =+N60-N62 -> 39333046 | O64: =+O60-O62 -> 1290603.7 | P64: =+P60-P62 -> 2692056.8 | Q64: =+Q60-Q62 -> 224186.59 | ... S64: =+S60-S62 -> 361809 | U64: =SUM(I64:T64) -> 4.2113798e+08 | W64: =U64-F64 -> 0
B65: =B64+1 -> 13 | W65: =U65-F65 -> 0
B66: =B65+1 -> 14 | D66: Other Rate Base Items: | W66: =U66-F66 -> 0
B67: =B66+1 -> 15 | W67: =U67-F67 -> 0
B68: =B67+1 -> 16 | D68: CWIP | E68: II-B-4 | F68: =+F244 -> 0 | J68: =+J244 -> 0 | K68: =+K244 -> 0 | L68: =+L244 -> 0 | M68: =+M244 -> 0 | N68: =+N244 -> 0 | O68: =+O244 -> 0 | P68: =+P244 -> 0 | Q68: =+Q244 -> 0 | ... S68: =+S244 -> 0 | U68: =SUM(I68:T68) -> 0 | W68: =U68-F68 -> 0
B69: =B68+1 -> 17 | D69: Plant Held for Future Use | E69: II-B-6 | F69: =+F388 -> 0 | J69: =+J388 -> 0 | K69: =+K388 -> 0 | L69: =+L388 -> 0 | M69: =+M388 -> 0 | N69: =+N388 -> 0 | O69: =+O388 -> 0 | P69: =+P388 -> 0 | Q69: =+Q388 -> 0 | ... S69: =+S388 -> 0 | U69: =SUM(I69:T69) -> 0 | W69: =U69-F69 -> 0
B70: =B69+1 -> 18 | D70: Accumulated Provisions ex ADFIT | E70: II-B-7 | F70: =F409 -> 0 | J70: =J409 -> 0 | K70: =K409 -> 0 | L70: =L409 -> 0 | M70: =M409 -> 0 | N70: =N409 -> 0 | O70: =O409 -> 0 | P70: =P409 -> 0 | Q70: =Q409 -> 0 | ... S70: =S409 -> 0 | U70: =SUM(I70:T70) -> 0 | W70: =U70-F70 -> 0
B71: =B70+1 -> 19 | D71: Materials & Supplies | E71: II-B-8 | F71: =+F435 -> 1241799.5 | J71: =+J435 -> 648273.31 | K71: =+K435 -> 90943.073 | L71: =+L435 -> 357649.58 | M71: =+M435 -> 15061.359 | N71: =+N435 -> 115980.41 | O71: =+O435 -> 3805.5723 | P71: =+P435 -> 7938.0035 | Q71: =+Q435 -> 661.05363 | ... S71: =+S435 -> 1066.8575 | U71: =SUM(I71:T71) -> 1241799.5 | W71: =U71-F71 -> 0
B72: =B71+1 -> 20 | D72: Cash Working Capital | E72: II-B-9 | F72: =+F455 -> -298798.52 | J72: =+J455 -> -155937.01 | K72: =+K455 -> -21873.233 | L72: =+L455 -> -86031.065 | M72: =+M455 -> -3622.4256 | N72: =+N455 -> -27898.194 | O72: =+O455 -> -916.85203 | P72: =+P455 -> -1909.1754 | Q72: =+Q455 -> -252.64581 | ... S72: =+S455 -> -256.73097 | U72: =SUM(I72:T72) -> -298798.52 | W72: =U72-F72 -> 0
B73: =B72+1 -> 21 | D73: Prepayments | E73: II-B-10 | F73: =+F476 -> 584939.39 | J73: =+J476 -> 229342.28 | K73: =+K476 -> 6948.15 | L73: =+L476 -> 244195.52 | M73: =+M476 -> 4.7016999 | N73: =+N476 -> 40434.895 | O73: =+O476 -> 7707.6295 | P73: =+P476 -> 53159.051 | Q73: =+Q476 -> 1876.5583 | ... S73: =+S476 -> 687.68685 | U73: =SUM(I73:T73) -> 584939.39 | W73: =U73-F73 -> 0
B74: =B73+1 -> 22 | D74: Misc Other Rate Base | E74: II-B-11 | F74: =F499 -> -302530.2 | J74: =J499 -> -134625.01 | K74: =K499 -> -2543.4255 | L74: =L499 -> -86470.212 | M74: =M499 -> -40.462933 | N74: =N499 -> -25434.477 | O74: =O499 -> -10932.239 | P74: =P499 -> -39983.783 | Q74: =Q499 -> -768.98557 | ... S74: =S499 -> -975.92726 | U74: =SUM(I74:T74) -> -302530.2 | W74: =U74-F74 -> 0
B75: =B74+1 -> 23 | D75: Regulatory Assets | E75: II-B-12 | F75: =F614 -> 30745550 | J75: =J614 -> 16051153 | K75: =K614 -> 2251733.5 | L75: =L614 -> 8855354 | M75: =M614 -> 372916.33 | N75: =N614 -> 2871658.3 | O75: =O614 -> 94227.711 | P75: =P614 -> 196543.43 | Q75: =Q614 -> 16515.52 | ... S75: =S614 -> 25430.423 | U75: =SUM(I75:T75) -> 30745550 | W75: =U75-F75 -> 0
B76: =B75+1 -> 24 | D76: Accumulated Deferred Income Taxes | E76: II-E3.7 | F76: =+F413 -> -11971648 | J76: =+J413 -> -6249720.8 | K76: =+K413 -> -876742.58 | L76: =+L413 -> -3447944 | M76: =+M413 -> -145200 | N76: =+N413 -> -1118116.7 | O76: =+O413 -> -36687.866 | P76: =+P413 -> -76526.837 | Q76: =+Q413 -> -6372.9303 | ... S76: =+S413 -> -10285.109 | U76: =SUM(I76:T76) -> -11971648 | W76: =U76-F76 -> 0
B77: =B76+1 -> 25 | D77: Subtotal | F77: =SUM(F68:F76) -> 19999312 | J77: =SUM(J68:J76) -> 10388486 | K77: =SUM(K68:K76) -> 1448465.5 | L77: =SUM(L68:L76) -> 5836753.9 | M77: =SUM(M68:M76) -> 239119.5 | N77: =SUM(N68:N76) -> 1856624.2 | O77: =SUM(O68:O76) -> 57203.956 | P77: =SUM(P68:P76) -> 139220.69 | Q77: =SUM(Q68:Q76) -> 11658.571 | ... S77: =SUM(S68:S76) -> 15667.2 | U77: =SUM(I77:T77) -> 19999312 | W77: =U77-F77 -> 0
B78: =B77+1 -> 26 | W78: =U78-F78 -> 0
B79: =B78+1 -> 27 | D79: TOTAL RATE BASE | F79: =+F64+F77 -> 4.4113729e+08 | J79: =+J64+J77 -> 2.3024082e+08 | K79: =+K64+K77 -> 32290468 | L79: =+L64+L77 -> 1.2712834e+08 | M79: =+M64+M77 -> 5346957.1 | N79: =+N64+N77 -> 41189671 | O79: =+O64+O77 -> 1347807.7 | P79: =+P64+P77 -> 2831277.5 | Q79: =+Q64+Q77 -> 235845.16 | ... S79: =+S64+S77 -> 377476.2 | U79: =SUM(I79:T79) -> 4.4113729e+08 | W79: =U79-F79 -> 0
B80: =B79+1 -> 28 | W80: =U80-F80 -> 0
B81: =B80+1 -> 29 | D81: COST-BASED Rate of Return | F81: =F620 -> 0.0747 | J81: =J620 -> 0.0747 | K81: =K620 -> 0.0747 | L81: =L620 -> 0.0747 | M81: =M620 -> 0.0747 | N81: =N620 -> 0.0747 | O81: =O620 -> 0.0747 | P81: =P620 -> 0.0747 | Q81: =Q620 -> 0.0747 | ... S81: =S620 -> 0.0747 | U81: =U83/U79 -> 0.0747 | W81: =U81-F81 -> 0
B82: =B81+1 -> 30 | W82: =U82-F82 -> 0
B83: =B82+1 -> 31 | D83: COST-BASED Return On Rate Base | F83: =+F79*F81 -> 32952956 | J83: =+J79*J81 -> 17198989 | K83: =+K79*K81 -> 2412097.9 | L83: =+L79*L81 -> 9496486.7 | M83: =+M79*M81 -> 399417.7 | N83: =+N79*N81 -> 3076868.4 | O83: =+O79*O81 -> 100681.23 | P83: =+P79*P81 -> 211496.43 | Q83: =+Q79*Q81 -> 17617.634 | ... S83: =+S79*S81 -> 28197.472 | U83: =SUM(I83:T83) -> 32952956 | W83: =IF(ROUND(U83-'WP II-I-1.1'!H494,2)=0,TRUE,U83-'WP II-I-1.1'!H494) -> TRUE
W86: =U86-F86 -> 0
W87: =U87-F87 -> 0
W88: =U88-F88 -> 0
W89: =U89-F89 -> 0
W90: =U90-F90 -> 0
B91: =+$B$4 -> 2025 RATE CASE | V91: =$H$2 -> 0
B92: =+$B$5 -> ONCOR ELECTRIC DELIVERY COMPANY LLC | W92: =U92-F92 -> 0
B93: =+$B$6 -> II-I-1-MET: CLASS REVENUE REQUIREMENT | W93: =U93-F93 -> 0
B94: =+$B$7 -> TEST YEAR ENDING 12/31/2024 | W94: =U94-F94 -> 0
B95: =+$B$8 -> SPONSOR: MATTHEW A. TROXLE | W95: =U95-F95 -> 0
W96: =U96-F96 -> 0
R97: =R$10 | W97: =U97-F97 -> 0
B98: Line | C98: Acct | D98: Intangible and Transmission Plant Gross | E98: Source | F98: =F$11 -> MET | G98: Alloc | H98: Allocation | J98: Residential | K98: Secondary | L98: Secondary | M98: Primary | N98: Primary | O98: Primary | P98: Transmission | Q98: Lighting | R98: =R$11 -> Wholesale | S98: =S$11 -> Wholesale | U98: Total
G99: # | H99: Factor | K99: <=10 kW | L99: > 10 kW | M99: <=10 kW | N99: > 10 kW | O99: Substation | R99: =R$12 -> XFMR | S99: =S$12 -> DLS | W99: =U99-F99 -> 0
F100: (a) | G100: (b) | H100: (c) | J100: =J$13 -> (d) | K100: =K$13 -> (e) | L100: =L$13 -> (f) | M100: =M$13 -> (g) | N100: =N$13 -> (h) | O100: =O$13 -> (i) | P100: =P$13 -> (j) | Q100: =Q$13 -> (k) | ... S100: =S$13 -> (m) | U100: (n)
W101: =U101-F101 -> 0
B102: =B101+1 -> 1 | C102: Intangible Plant Gross | E102: II-B-1 | W102: =U102-F102 -> 0
B103: =B102+1 -> 2 | C103: A301 | D103: Organization | F103: =' WP II-I-1.4'!H103 -> 0 | G103: 65 | H103: =VLOOKUP(G103,FactorTable,2) -> PLT_N XINT | J103: =$F103*HLOOKUP(J$1354,FactorTable,$G103+1) -> 0 | K103: =$F103*HLOOKUP(K$1354,FactorTable,$G103+1) -> 0 | L103: =$F103*HLOOKUP(L$1354,FactorTable,$G103+1) -> 0 | M103: =$F103*HLOOKUP(M$1354,FactorTable,$G103+1) -> 0 | N103: =$F103*HLOOKUP(N$1354,FactorTable,$G103+1) -> 0 | O103: =$F103*HLOOKUP(O$1354,FactorTable,$G103+1) -> 0 | P103: =$F103*HLOOKUP(P$1354,FactorTable,$G103+1) -> 0 | Q103: =$F103*HLOOKUP(Q$1354,FactorTable,$G103+1) -> 0 | ... S103: =$F103*HLOOKUP(S$1354,FactorTable,$G103+1) -> 0 | U103: =SUM(I103:T103) -> 0 | W103: =U103-F103 -> 0
B104: =B103+1 -> 3 | C104: A302 | D104: Franchise & Consents | F104: =' WP II-I-1.4'!H104 -> 0 | G104: 65 | H104: =VLOOKUP(G104,FactorTable,2) -> PLT_N XINT | J104: =$F104*HLOOKUP(J$1354,FactorTable,$G104+1) -> 0 | K104: =$F104*HLOOKUP(K$1354,FactorTable,$G104+1) -> 0 | L104: =$F104*HLOOKUP(L$1354,FactorTable,$G104+1) -> 0 | M104: =$F104*HLOOKUP(M$1354,FactorTable,$G104+1) -> 0 | N104: =$F104*HLOOKUP(N$1354,FactorTable,$G104+1) -> 0 | O104: =$F104*HLOOKUP(O$1354,FactorTable,$G104+1) -> 0 | P104: =$F104*HLOOKUP(P$1354,FactorTable,$G104+1) -> 0 | Q104: =$F104*HLOOKUP(Q$1354,FactorTable,$G104+1) -> 0 | ... S104: =$F104*HLOOKUP(S$1354,FactorTable,$G104+1) -> 0 | U104: =SUM(I104:T104) -> 0 | W104: =U104-F104 -> 0
B105: =B104+1 -> 4 | C105: A303 | D105: Miscellaneous Intangible Plant | F105: =' WP II-I-1.4'!H105 -> 324360 | G105: 65 | H105: =VLOOKUP(G105,FactorTable,2) -> PLT_N XINT | J105: =$F105*HLOOKUP(J$1354,FactorTable,$G105+1) -> 169330.02 | K105: =$F105*HLOOKUP(K$1354,FactorTable,$G105+1) -> 23754.475 | L105: =$F105*HLOOKUP(L$1354,FactorTable,$G105+1) -> 93418.641 | M105: =$F105*HLOOKUP(M$1354,FactorTable,$G105+1) -> 3934.0509 | N105: =$F105*HLOOKUP(N$1354,FactorTable,$G105+1) -> 30294.268 | O105: =$F105*HLOOKUP(O$1354,FactorTable,$G105+1) -> 994.02154 | P105: =$F105*HLOOKUP(P$1354,FactorTable,$G105+1) -> 2073.4192 | Q105: =$F105*HLOOKUP(Q$1354,FactorTable,$G105+1) -> 172.66826 | ... S105: =$F105*HLOOKUP(S$1354,FactorTable,$G105+1) -> 278.66489 | U105: =SUM(I105:T105) -> 324360 | W105: =U105-F105 -> 0
B106: =B105+1 -> 5 | D106: Subtotal | F106: =SUM(F103:F105) -> 324360 | J106: =SUM(J103:J105) -> 169330.02 | K106: =SUM(K103:K105) -> 23754.475 | L106: =SUM(L103:L105) -> 93418.641 | M106: =SUM(M103:M105) -> 3934.0509 | N106: =SUM(N103:N105) -> 30294.268 | O106: =SUM(O103:O105) -> 994.02154 | P106: =SUM(P103:P105) -> 2073.4192 | Q106: =SUM(Q103:Q105) -> 172.66826 | ... S106: =SUM(S103:S105) -> 278.66489 | U106: =SUM(I106:T106) -> 324360 | W106: =U106-F106 -> 0
B107: =B106+1 -> 6 | C107: Transmission Plant Gross | E107: II-B-1 | W107: =U107-F107 -> 0
B108: =B107+1 -> 7 | C108: A349 | D108: Land Owned in Fee | F108: =' WP II-I-1.4'!H108 -> 0 | G108: 28 | H108: =VLOOKUP(G108,FactorTable,2) -> NCP XHV | J108: =$F108*HLOOKUP(J$1354,FactorTable,$G108+1) -> 0 | K108: =$F108*HLOOKUP(K$1354,FactorTable,$G108+1) -> 0 | L108: =$F108*HLOOKUP(L$1354,FactorTable,$G108+1) -> 0 | M108: =$F108*HLOOKUP(M$1354,FactorTable,$G108+1) -> 0 | N108: =$F108*HLOOKUP(N$1354,FactorTable,$G108+1) -> 0 | O108: =$F108*HLOOKUP(O$1354,FactorTable,$G108+1) -> 0 | P108: =$F108*HLOOKUP(P$1354,FactorTable,$G108+1) -> 0 | Q108: =$F108*HLOOKUP(Q$1354,FactorTable,$G108+1) -> 0 | ... S108: =$F108*HLOOKUP(S$1354,FactorTable,$G108+1) -> 0 | U108: =SUM(I108:T108) -> 0 | W108: =U108-F108 -> 0
B109: =B108+1 -> 8 | C109: A350 | D109: Land and Land Rights | F109: =' WP II-I-1.4'!H109 -> 0 | G109: 28 | H109: =VLOOKUP(G109,FactorTable,2) -> NCP XHV | J109: =$F109*HLOOKUP(J$1354,FactorTable,$G109+1) -> 0 | K109: =$F109*HLOOKUP(K$1354,FactorTable,$G109+1) -> 0 | L109: =$F109*HLOOKUP(L$1354,FactorTable,$G109+1) -> 0 | M109: =$F109*HLOOKUP(M$1354,FactorTable,$G109+1) -> 0 | N109: =$F109*HLOOKUP(N$1354,FactorTable,$G109+1) -> 0 | O109: =$F109*HLOOKUP(O$1354,FactorTable,$G109+1) -> 0 | P109: =$F109*HLOOKUP(P$1354,FactorTable,$G109+1) -> 0 | Q109: =$F109*HLOOKUP(Q$1354,FactorTable,$G109+1) -> 0 | ... S109: =$F109*HLOOKUP(S$1354,FactorTable,$G109+1) -> 0 | U109: =SUM(I109:T109) -> 0 | W109: =U109-F109 -> 0
B110: =B109+1 -> 9 | C110: A351.1 | D110: Computer Hardware | F110: =' WP II-I-1.4'!H110 -> 0 | G110: 67 | H110: =VLOOKUP(G110,FactorTable,2) -> PLTTRAN_N | J110: =$F110*HLOOKUP(J$1354,FactorTable,$G110+1) -> 0 | K110: =$F110*HLOOKUP(K$1354,FactorTable,$G110+1) -> 0 | L110: =$F110*HLOOKUP(L$1354,FactorTable,$G110+1) -> 0 | M110: =$F110*HLOOKUP(M$1354,FactorTable,$G110+1) -> 0 | N110: =$F110*HLOOKUP(N$1354,FactorTable,$G110+1) -> 0 | O110: =$F110*HLOOKUP(O$1354,FactorTable,$G110+1) -> 0 | P110: =$F110*HLOOKUP(P$1354,FactorTable,$G110+1) -> 0 | Q110: =$F110*HLOOKUP(Q$1354,FactorTable,$G110+1) -> 0 | ... S110: =$F110*HLOOKUP(S$1354,FactorTable,$G110+1) -> 0 | U110: =SUM(I110:T110) -> 0
B111: =B110+1 -> 10 | C111: A351.2 | D111: Computer Software | F111: =' WP II-I-1.4'!H111 -> 0 | G111: 67 | H111: =VLOOKUP(G111,FactorTable,2) -> PLTTRAN_N | J111: =$F111*HLOOKUP(J$1354,FactorTable,$G111+1) -> 0 | K111: =$F111*HLOOKUP(K$1354,FactorTable,$G111+1) -> 0 | L111: =$F111*HLOOKUP(L$1354,FactorTable,$G111+1) -> 0 | M111: =$F111*HLOOKUP(M$1354,FactorTable,$G111+1) -> 0 | N111: =$F111*HLOOKUP(N$1354,FactorTable,$G111+1) -> 0 | O111: =$F111*HLOOKUP(O$1354,FactorTable,$G111+1) -> 0 | P111: =$F111*HLOOKUP(P$1354,FactorTable,$G111+1) -> 0 | Q111: =$F111*HLOOKUP(Q$1354,FactorTable,$G111+1) -> 0 | ... S111: =$F111*HLOOKUP(S$1354,FactorTable,$G111+1) -> 0 | U111: =SUM(I111:T111) -> 0
B112: =B111+1 -> 11 | C112: A351.3 | D112: Communication Equipment | F112: =' WP II-I-1.4'!H112 -> 0 | G112: 67 | H112: =VLOOKUP(G112,FactorTable,2) -> PLTTRAN_N | J112: =$F112*HLOOKUP(J$1354,FactorTable,$G112+1) -> 0 | K112: =$F112*HLOOKUP(K$1354,FactorTable,$G112+1) -> 0 | L112: =$F112*HLOOKUP(L$1354,FactorTable,$G112+1) -> 0 | M112: =$F112*HLOOKUP(M$1354,FactorTable,$G112+1) -> 0 | N112: =$F112*HLOOKUP(N$1354,FactorTable,$G112+1) -> 0 | O112: =$F112*HLOOKUP(O$1354,FactorTable,$G112+1) -> 0 | P112: =$F112*HLOOKUP(P$1354,FactorTable,$G112+1) -> 0 | Q112: =$F112*HLOOKUP(Q$1354,FactorTable,$G112+1) -> 0 | ... S112: =$F112*HLOOKUP(S$1354,FactorTable,$G112+1) -> 0 | U112: =SUM(I112:T112) -> 0
B113: =B112+1 -> 12 | C113: A352 | D113: Structures and Improvements | F113: =' WP II-I-1.4'!H113 -> 0 | G113: 28 | H113: =VLOOKUP(G113,FactorTable,2) -> NCP XHV | J113: =$F113*HLOOKUP(J$1354,FactorTable,$G113+1) -> 0 | K113: =$F113*HLOOKUP(K$1354,FactorTable,$G113+1) -> 0 | L113: =$F113*HLOOKUP(L$1354,FactorTable,$G113+1) -> 0 | M113: =$F113*HLOOKUP(M$1354,FactorTable,$G113+1) -> 0 | N113: =$F113*HLOOKUP(N$1354,FactorTable,$G113+1) -> 0 | O113: =$F113*HLOOKUP(O$1354,FactorTable,$G113+1) -> 0 | P113: =$F113*HLOOKUP(P$1354,FactorTable,$G113+1) -> 0 | Q113: =$F113*HLOOKUP(Q$1354,FactorTable,$G113+1) -> 0 | ... S113: =$F113*HLOOKUP(S$1354,FactorTable,$G113+1) -> 0 | U113: =SUM(I113:T113) -> 0 | W113: =U113-F113 -> 0
B114: =B113+1 -> 13 | C114: A353 | D114: Station Equipment | F114: =' WP II-I-1.4'!H114 -> 0 | G114: 28 | H114: =VLOOKUP(G114,FactorTable,2) -> NCP XHV | J114: =$F114*HLOOKUP(J$1354,FactorTable,$G114+1) -> 0 | K114: =$F114*HLOOKUP(K$1354,FactorTable,$G114+1) -> 0 | L114: =$F114*HLOOKUP(L$1354,FactorTable,$G114+1) -> 0 | M114: =$F114*HLOOKUP(M$1354,FactorTable,$G114+1) -> 0 | N114: =$F114*HLOOKUP(N$1354,FactorTable,$G114+1) -> 0 | O114: =$F114*HLOOKUP(O$1354,FactorTable,$G114+1) -> 0 | P114: =$F114*HLOOKUP(P$1354,FactorTable,$G114+1) -> 0 | Q114: =$F114*HLOOKUP(Q$1354,FactorTable,$G114+1) -> 0 | ... S114: =$F114*HLOOKUP(S$1354,FactorTable,$G114+1) -> 0 | U114: =SUM(I114:T114) -> 0 | W114: =U114-F114 -> 0
B115: =B114+1 -> 14 | C115: A354 | D115: Towers and Fixtures | F115: =' WP II-I-1.4'!H115 -> 0 | G115: 28 | H115: =VLOOKUP(G115,FactorTable,2) -> NCP XHV | J115: =$F115*HLOOKUP(J$1354,FactorTable,$G115+1) -> 0 | K115: =$F115*HLOOKUP(K$1354,FactorTable,$G115+1) -> 0 | L115: =$F115*HLOOKUP(L$1354,FactorTable,$G115+1) -> 0 | M115: =$F115*HLOOKUP(M$1354,FactorTable,$G115+1) -> 0 | N115: =$F115*HLOOKUP(N$1354,FactorTable,$G115+1) -> 0 | O115: =$F115*HLOOKUP(O$1354,FactorTable,$G115+1) -> 0 | P115: =$F115*HLOOKUP(P$1354,FactorTable,$G115+1) -> 0 | Q115: =$F115*HLOOKUP(Q$1354,FactorTable,$G115+1) -> 0 | ... S115: =$F115*HLOOKUP(S$1354,FactorTable,$G115+1) -> 0 | U115: =SUM(I115:T115) -> 0 | W115: =U115-F115 -> 0
B116: =B115+1 -> 15 | C116: A355 | D116: Poles and Fixtures | F116: =' WP II-I-1.4'!H116 -> 0 | G116: 28 | H116: =VLOOKUP(G116,FactorTable,2) -> NCP XHV | J116: =$F116*HLOOKUP(J$1354,FactorTable,$G116+1) -> 0 | K116: =$F116*HLOOKUP(K$1354,FactorTable,$G116+1) -> 0 | L116: =$F116*HLOOKUP(L$1354,FactorTable,$G116+1) -> 0 | M116: =$F116*HLOOKUP(M$1354,FactorTable,$G116+1) -> 0 | N116: =$F116*HLOOKUP(N$1354,FactorTable,$G116+1) -> 0 | O116: =$F116*HLOOKUP(O$1354,FactorTable,$G116+1) -> 0 | P116: =$F116*HLOOKUP(P$1354,FactorTable,$G116+1) -> 0 | Q116: =$F116*HLOOKUP(Q$1354,FactorTable,$G116+1) -> 0 | ... S116: =$F116*HLOOKUP(S$1354,FactorTable,$G116+1) -> 0 | U116: =SUM(I116:T116) -> 0 | W116: =U116-F116 -> 0
B117: =B116+1 -> 16 | C117: A356 | D117: O.H. Conductors & Devices | F117: =' WP II-I-1.4'!H117 -> 0 | G117: 28 | H117: =VLOOKUP(G117,FactorTable,2) -> NCP XHV | J117: =$F117*HLOOKUP(J$1354,FactorTable,$G117+1) -> 0 | K117: =$F117*HLOOKUP(K$1354,FactorTable,$G117+1) -> 0 | L117: =$F117*HLOOKUP(L$1354,FactorTable,$G117+1) -> 0 | M117: =$F117*HLOOKUP(M$1354,FactorTable,$G117+1) -> 0 | N117: =$F117*HLOOKUP(N$1354,FactorTable,$G117+1) -> 0 | O117: =$F117*HLOOKUP(O$1354,FactorTable,$G117+1) -> 0 | P117: =$F117*HLOOKUP(P$1354,FactorTable,$G117+1) -> 0 | Q117: =$F117*HLOOKUP(Q$1354,FactorTable,$G117+1) -> 0 | ... S117: =$F117*HLOOKUP(S$1354,FactorTable,$G117+1) -> 0 | U117: =SUM(I117:T117) -> 0 | W117: =U117-F117 -> 0
...

Sheet II-I-TBILLTDCS
B4: ='WP II-I-1.1'!B3 -> 2025 RATE CASE
B5: ='WP II-I-1.1'!B4 -> ONCOR ELECTRIC DELIVERY COMPANY LLC
B6: ="II-I-1-TBILLTDCS: CLASS REVENUE REQUIREMENT" -> II-I-1-TBILLTDCS: CLASS REVENUE REQUIREMENT
B7: ='WP II-I-1.1'!B6 -> TEST YEAR ENDING 12/31/2024
B8: ='WP II-I-2.2'!$B$7 -> SPONSOR: MATTHEW A. TROXLE
R10: =" "
B11: Line | D11: I-A-1 by Rate Class | E11: Source | F11: TBILLTDCS | J11: Residential | K11: Secondary | L11: Secondary | M11: Primary | N11: Primary | O11: Primary | P11: Transmission | Q11: Lighting | R11: Wholesale | S11: Wholesale | U11: Total
K12: <=10 kW | L12: > 10 kW | M12: <=10 kW | N12: > 10 kW | O12: Substation | R12: XFMR | S12: DLS
F13: (a) | G13: (b) | H13: (c) | J13: (d) | K13: (e) | L13: (f) | M13: (g) | N13: (h) | O13: (i) | P13: (j) | Q13: (k) | R13: (l) | S13: (m) | U13: (n)
B15: =B14+1 -> 1 | D15: O&M Expenses | E15: II-D-2 | F15: =F661+F709 -> 189681.03 | J15: =J661+J709 -> 27.5612 | K15: =K661+K709 -> 0.52070457 | L15: =L661+L709 -> 17.702675 | M15: =M661+M709 -> 0.0082838025 | N15: =N661+N709 -> 5.2070912 | O15: =O661+O709 -> 2.2381103 | P15: =P661+P709 -> 0 | Q15: =Q661+Q709 -> 189627.44 | ... S15: =S661+S709 -> 0.19979739 | U15: =SUM(I15:T15) -> 189681.03 | W15: =F15-U15 -> 0
B16: =B15+1 -> 2 | D16: Customer Expenses | E16: II-D-2 | F16: =F729+F739+F749 -> 17097126 | J16: =J729+J739+J749 -> 8911343.2 | K16: =K729+K739+K749 -> 1100131.8 | L16: =L729+L739+L749 -> 5033112.3 | M16: =M729+M739+M749 -> 173119.83 | N16: =N729+N739+N749 -> 1530953.5 | O16: =O729+O739+O749 -> 85191.227 | P16: =P729+P739+P749 -> 202491.26 | Q16: =Q729+Q739+Q749 -> 43791.364 | ... S16: =S729+S739+S749 -> 12190.098 | U16: =SUM(I16:T16) -> 17097126 | W16: =F16-U16 -> 0
B17: =B16+1 -> 3 | D17: A&G Expenses | E17: II-D-2 | F17: =F783 -> 40849532 | J17: =J783 -> 21221743 | K17: =K783 -> 2605710 | L17: =L783 -> 11764409 | M17: =M783 -> 404946.71 | N17: =N783 -> 3572683.2 | O17: =O783 -> 197893.07 | P17: =P783 -> 469983.12 | Q17: =Q783 -> 572452.8 | ... S17: =S783 -> 28488.566 | U17: =SUM(I17:T17) -> 40849532 | W17: =F17-U17 -> 0
B18: =B17+1 -> 4 | D18: O&M + Customer + A&G Expenses | F18: =SUM(F15:F17) -> 58136339 | J18: =SUM(J15:J17) -> 30133114 | K18: =SUM(K15:K17) -> 3705842.3 | L18: =SUM(L15:L17) -> 16797539 | M18: =SUM(M15:M17) -> 578066.54 | N18: =SUM(N15:N17) -> 5103641.9 | O18: =SUM(O15:O17) -> 283086.53 | P18: =SUM(P15:P17) -> 672474.38 | Q18: =SUM(Q15:Q17) -> 805871.61 | ... S18: =SUM(S15:S17) -> 40678.863 | U18: =SUM(I18:T18) -> 58136339 | V18: ='WP II-I-1.1'!$I$495=U18 -> TRUE | W18: =F18-U18 -> 0
B19: =B18+1 -> 5 | W19: =F19-U19 -> 0
B20: =B19+1 -> 6 | D20: Depreciation & Amortization (II-E-1) | E20: II-E-1 | F20: =F1065 -> 39993574 | J20: =J1065 -> 19713789 | K20: =K1065 -> 2750719.8 | L20: =L1065 -> 10750843 | M20: =M1065 -> 452236.06 | N20: =N1065 -> 3481177.1 | O20: =O1065 -> 114220.05 | P20: =P1065 -> 238250.4 | Q20: =Q1065 -> 2447703.8 | ... S20: =S1065 -> 32021.021 | U20: =SUM(I20:T20) -> 39993573 | W20: =F20-U20 -> 0
B21: =B20+1 -> 7 | D21: Other (II-E-4) | E21: II-E-4 | F21: =F1067+F1068 -> 0 | J21: =J1067+J1068 -> 0 | K21: =K1067+K1068 -> 0 | L21: =L1067+L1068 -> 0 | M21: =M1067+M1068 -> 0 | N21: =N1067+N1068 -> 0 | O21: =O1067+O1068 -> 0 | P21: =P1067+P1068 -> 0 | Q21: =Q1067+Q1068 -> 0 | ... S21: =S1067+S1068 -> 0 | U21: =SUM(I21:T21) -> 0 | W21: =F21-U21 -> 0
B22: =B21+1 -> 8 | D22: Depreciation, Amortization & Other Expenses | F22: =SUM(F20:F21) -> 39993574 | J22: =SUM(J20:J21) -> 19713789 | K22: =SUM(K20:K21) -> 2750719.8 | L22: =SUM(L20:L21) -> 10750843 | M22: =SUM(M20:M21) -> 452236.06 | N22: =SUM(N20:N21) -> 3481177.1 | O22: =SUM(O20:O21) -> 114220.05 | P22: =SUM(P20:P21) -> 238250.4 | Q22: =SUM(Q20:Q21) -> 2447703.8 | ... S22: =SUM(S20:S21) -> 32021.021 | U22: =SUM(I22:T22) -> 39993573 | V22: ='WP II-I-1.1'!$I$496=U22 -> TRUE | W22: =F22-U22 -> 0
B23: =B22+1 -> 9 | W23: =F23-U23 -> 0
B24: =B23+1 -> 10 | D24: Taxes Other Than Federal Income Tax | E24: II-E-2 | F24: =+F1103 -> 3557512.7 | J24: =+J1103 -> 1755406.2 | K24: =+K1103 -> 244120.54 | L24: =+L1103 -> 958581.12 | M24: =+M1103 -> 40091.561 | N24: =+N1103 -> 309761.07 | O24: =+O1103 -> 10363.499 | P24: =+P1103 -> 21865.027 | Q24: =+Q1103 -> 213393.03 | ... S24: =+S1103 -> 2819.1681 | U24: =SUM(I24:T24) -> 3557512.7 | V24: ='WP II-I-1.1'!$I$497-U24 -> 0 | W24: =F24-U24 -> 0
B25: =B24+1 -> 11 | D25: Federal Income Tax | E25: II-E-3 | F25: =+F1162 -> 2876698.2 | J25: =+J1162 -> 1412861.3 | K25: =+K1162 -> 198475.47 | L25: =+L1162 -> 769974.22 | M25: =+M1162 -> 32705.505 | N25: =+N1162 -> 249979.64 | O25: =+O1162 -> 7879.6009 | P25: =+P1162 -> 16607.117 | Q25: =+Q1162 -> 185104.67 | ... S25: =+S1162 -> 2228.8905 | U25: =SUM(I25:T25) -> 2876698.2 | V25: ='WP II-I-1.1'!$I$498-U25 -> 0 | W25: =F25-U25 -> 0
B26: =B25+1 -> 12 | W26: =F26-U26 -> 0
B27: =B26+1 -> 13 | D27: Return on Rate Base | E27: II-B | F27: =+F83 -> 17186005 | J27: =+J83 -> 8471555.4 | K27: =+K83 -> 1178975.1 | L27: =+L83 -> 4629669 | M27: =+M83 -> 193678.98 | N27: =+N83 -> 1495538.9 | O27: =+O83 -> 49840.5 | P27: =+P83 -> 106709.79 | Q27: =+Q83 -> 1041574.9 | ... S27: =+S83 -> 13230.338 | U27: =SUM(I27:T27) -> 17186005 | V27: =ROUND('WP II-I-1.1'!$I$494,0)=ROUND(U27,0) -> TRUE | W27: =F27-U27 -> 0
B28: =B27+1 -> 14 | W28: =F28-U28 -> 0
B29: =B28+1 -> 15 | D29: TOTAL COST OF SERVICE | F29: =+F18+F22+F24+F25+F27 -> 1.2175013e+08 | J29: =+J18+J22+J24+J25+J27 -> 61486726 | K29: =+K18+K22+K24+K25+K27 -> 8078133.2 | L29: =+L18+L22+L24+L25+L27 -> 33906606 | M29: =+M18+M22+M24+M25+M27 -> 1296778.6 | N29: =+N18+N22+N24+N25+N27 -> 10640099 | O29: =+O18+O22+O24+O25+O27 -> 465390.18 | P29: =+P18+P22+P24+P25+P27 -> 1055906.7 | Q29: =+Q18+Q22+Q24+Q25+Q27 -> 4693648 | ... S29: =+S18+S22+S24+S25+S27 -> 90978.282 | U29: =SUM(I29:T29) -> 1.2175013e+08 | V29: ='WP II-I-1.1'!$I$509=U29 -> TRUE | W29: =F29-U29 -> 0
B30: =B29+1 -> 16
B31: =B30+1 -> 17 | D31: Minus: Other Revenues | E31: II-E-5 | F31: =+F1222 -> 85782 | J31: =+J1222 -> 73406.182 | K31: =+K1222 -> 6088.8709 | L31: =+L1222 -> 4974.9858 | M31: =+M1222 -> 66.470538 | N31: =+N1222 -> 148.80071 | O31: =+O1222 -> 3.4560439 | P31: =+P1222 -> 7.208926 | Q31: =+Q1222 -> 1086.0247 | ... S31: =+S1222 -> 0 | U31: =SUM(I31:T31) -> 85782 | V31: ='WP II-I-1.1'!$I$499=-U31 -> TRUE | W31: =F31-U31 -> 0
B32: =B31+1 -> 18
B33: =B32+1 -> 19 | D33: COST-BASED Revenue Requirement | F33: =+F29-F31 -> 1.2166435e+08 | J33: =+J29-J31 -> 61413320 | K33: =+K29-K31 -> 8072044.4 | L33: =+L29-L31 -> 33901631 | M33: =+M29-M31 -> 1296712.2 | N33: =+N29-N31 -> 10639950 | O33: =+O29-O31 -> 465386.72 | P33: =+P29-P31 -> 1055899.5 | Q33: =+Q29-Q31 -> 4692562 | ... S33: =+S29-S31 -> 90978.282 | U33: =SUM(I33:T33) -> 1.2166435e+08 | V33: ='WP II-I-1.1'!$I$500=U33 -> TRUE | W33: =F33-U33 -> 0
V41: =$H$2 -> 0
B42: =+$B$4 -> 2025 RATE CASE
B43: =+$B$5 -> ONCOR ELECTRIC DELIVERY COMPANY LLC
B44: =+$B$6 -> II-I-1-TBILLTDCS: CLASS REVENUE REQUIREMENT
B45: =+$B$7 -> TEST YEAR ENDING 12/31/2024
B46: =+$B$8 -> SPONSOR: MATTHEW A. TROXLE
R48: =R$10
B49: Line | D49: II-B by Rate Class | E49: Source | F49: =F$11 -> TBILLTDCS | J49: Residential | K49: Secondary | L49: Secondary | M49: Primary | N49: Primary | O49: Primary | P49: Transmission | Q49: Lighting | R49: =R$11 -> Wholesale | S49: =S$11 -> Wholesale | U49: Total
K50: <=10 kW | L50: > 10 kW | M50: <=10 kW | N50: > 10 kW | O50: Substation | R50: =R$12 -> XFMR | S50: =S$12 -> DLS
F51: (a) | G51: (b) | H51: (c) | J51: =J$13 -> (d) | K51: =K$13 -> (e) | L51: =L$13 -> (f) | M51: =M$13 -> (g) | N51: =N$13 -> (h) | O51: =O$13 -> (i) | P51: =P$13 -> (j) | Q51: =Q$13 -> (k) | ... S51: =S$13 -> (m) | U51: (n)
B53: =B52+1 -> 1 | D53: Intangible Plant: Original Cost | E53: II-B-1 | F53: =F106 -> 145326 | J53: =J106 -> 71634.663 | K53: =K106 -> 9995.3835 | L53: =L106 -> 39065.7 | M53: =M106 -> 1643.3054 | N53: =N106 -> 12649.671 | O53: =O106 -> 415.04525 | P53: =P106 -> 865.73855 | Q53: =Q106 -> 8894.304 | ... S53: =S106 -> 116.35587 | U53: =SUM(I53:T53) -> 145326 | W53: =F53-U53 -> 0
B54: =B53+1 -> 2 | D54: Transmission Plant: Original Cost | E54: II-B-1 | F54: =F121 -> 0 | J54: =J121 -> 0 | K54: =K121 -> 0 | L54: =L121 -> 0 | M54: =M121 -> 0 | N54: =N121 -> 0 | O54: =O121 -> 0 | P54: =P121 -> 0 | Q54: =Q121 -> 0 | ... S54: =S121 -> 0 | U54: =SUM(I54:T54) -> 0 | W54: =F54-U54 -> 0
B55: =B54+1 -> 3 | D55: Distribution Plant: Original Cost | E55: II-B-1 | F55: =F159 -> 3.3487324e+08 | J55: =J159 -> 1.6506703e+08 | K55: =K159 -> 23032261 | L55: =L159 -> 90018699 | M55: =M159 -> 3786652.2 | N55: =N159 -> 29148509 | O55: =O159 -> 956384.57 | P55: =P159 -> 1994912.6 | Q55: =Q159 -> 20495055 | ... S55: =S159 -> 268117.65 | U55: =SUM(I55:T55) -> 3.3487324e+08 | W55: =F55-U55 -> 0
B56: =B55+1 -> 4 | D56: Intangible, Transmission, Distribution Plant: Original Cost | F56: =SUM(F53:F55) -> 3.3501856e+08 | J56: =SUM(J53:J55) -> 1.6513867e+08 | K56: =SUM(K53:K55) -> 23042257 | L56: =SUM(L53:L55) -> 90057765 | M56: =SUM(M53:M55) -> 3788295.5 | N56: =SUM(N53:N55) -> 29161159 | O56: =SUM(O53:O55) -> 956799.62 | P56: =SUM(P53:P55) -> 1995778.3 | Q56: =SUM(Q53:Q55) -> 20503949 | ... S56: =SUM(S53:S55) -> 268234.01 | U56: =SUM(I56:T56) -> 3.3501856e+08 | W56: =F56-U56 -> 0
B57: =B56+1 -> 5 | W57: =F57-U57 -> 0
B58: =B57+1 -> 6 | D58: General Plant: Original Cost | E58: II-B-2 | F58: =+F199 -> 21845189 | J58: =+J199 -> 10768016 | K58: =+K199 -> 1502491.2 | L58: =+L199 -> 5872298.2 | M58: =+M199 -> 247019.24 | N58: =+N199 -> 1901479.8 | O58: =+O199 -> 62388.987 | P58: =+P199 -> 130136.54 | Q58: =+Q199 -> 1336978.6 | ... S58: =+S199 -> 17490.442 | U58: =SUM(I58:T58) -> 21845189 | W58: =F58-U58 -> 0
B59: =B58+1 -> 7 | D59: Communication Equipment: Original Cost | E59: II-B-3 | F59: =+F219 -> 51364319 | J59: =+J219 -> 25318702 | K59: =+K219 -> 3532788.8 | L59: =+L219 -> 13807461 | M59: =+M219 -> 580813.24 | N59: =+N219 -> 4470925.5 | O59: =+O219 -> 146694.44 | P59: =+P219 -> 305988.4 | Q59: =+Q219 -> 3143621 | ... S59: =+S219 -> 41125.056 | U59: =SUM(I59:T59) -> 51364319 | W59: =F59-U59 -> 0
B60: =B59+1 -> 8 | D60: Total Plant | F60: =+F56+F58+F59 -> 4.0822807e+08 | J60: =+J56+J58+J59 -> 2.0122538e+08 | K60: =+K56+K58+K59 -> 28077537 | L60: =+L56+L58+L59 -> 1.0973752e+08 | M60: =+M56+M58+M59 -> 4616127.9 | N60: =+N56+N58+N59 -> 35533564 | O60: =+O56+O58+O59 -> 1165883 | P60: =+P56+P58+P59 -> 2431903.3 | Q60: =+Q56+Q58+Q59 -> 24984549 | ... S60: =+S56+S58+S59 -> 326849.5 | U60: =SUM(I60:T60) -> 4.0822807e+08 | W60: =F60-U60 -> 0
B61: =B60+1 -> 9 | W61: =F61-U61 -> 0
B62: =B61+1 -> 10 | D62: Minus: Accumulated Depreciation | E62: II-B-5 | F62: =+F363+F320 -> 1.2982432e+08 | J62: =+J363+J320 -> 63993513 | K62: =+K363+K320 -> 8929192.7 | L62: =+L363+L320 -> 34898627 | M62: =+M363+M320 -> 1468016.8 | N62: =+N363+N320 -> 11300352 | O62: =+O363+O320 -> 370773.06 | P62: =+P363+P320 -> 773391.67 | Q62: =+Q363+Q320 -> 7945563.4 | ... S62: =+S363+S320 -> 103944.38 | U62: =SUM(I62:T62) -> 1.2982432e+08 | W62: =F62-U62 -> 0
B63: =B62+1 -> 11 | W63: =F63-U63 -> 0
B64: =B63+1 -> 12 | D64: NET PLANT IN SERVICE | F64: =+F60-F62 -> 2.7840375e+08 | J64: =+J60-J62 -> 1.3723187e+08 | K64: =+K60-K62 -> 19148344 | L64: =+L60-L62 -> 74838897 | M64: =+M60-M62 -> 3148111.1 | N64: =+N60-N62 -> 24233212 | O64: =+O60-O62 -> 795109.98 | P64: =+P60-P62 -> 1658511.6 | Q64: =+Q60-Q62 -> 17038985 | ... S64: =+S60-S62 -> 222905.12 | U64: =SUM(I64:T64) -> 2.7840375e+08 | W64: =F64-U64 -> 0
B65: =B64+1 -> 13 | W65: =F65-U65 -> 0
B66: =B65+1 -> 14 | D66: Other Rate Base Items: | W66: =F66-U66 -> 0
B67: =B66+1 -> 15 | W67: =F67-U67 -> 0
B68: =B67+1 -> 16 | D68: CWIP | E68: II-B-4 | F68: =+F244 -> 0 | J68: =+J244 -> 0 | K68: =+K244 -> 0 | L68: =+L244 -> 0 | M68: =+M244 -> 0 | N68: =+N244 -> 0 | O68: =+O244 -> 0 | P68: =+P244 -> 0 | Q68: =+Q244 -> 0 | ... S68: =+S244 -> 0 | U68: =SUM(I68:T68) -> 0 | W68: =F68-U68 -> 0
B69: =B68+1 -> 17 | D69: Plant Held for Future Use | E69: II-B-6 | F69: =+F388 -> 0 | J69: =+J388 -> 0 | K69: =+K388 -> 0 | L69: =+L388 -> 0 | M69: =+M388 -> 0 | N69: =+N388 -> 0 | O69: =+O388 -> 0 | P69: =+P388 -> 0 | Q69: =+Q388 -> 0 | ... S69: =+S388 -> 0 | U69: =SUM(I69:T69) -> 0 | W69: =F69-U69 -> 0
B70: =B69+1 -> 18 | D70: Accumulated Provisions ex ADFIT | E70: II-B-7 | F70: =F409 -> 0 | J70: =J409 -> 0 | K70: =K409 -> 0 | L70: =L409 -> 0 | M70: =M409 -> 0 | N70: =N409 -> 0 | O70: =O409 -> 0 | P70: =P409 -> 0 | Q70: =Q409 -> 0 | ... S70: =S409 -> 0 | U70: =SUM(I70:T70) -> 0 | W70: =F70-U70 -> 0
B71: =B70+1 -> 19 | D71: Materials & Supplies | E71: II-B-8 | F71: =+F435 -> 0 | J71: =+J435 -> 0 | K71: =+K435 -> 0 | L71: =+L435 -> 0 | M71: =+M435 -> 0 | N71: =+N435 -> 0 | O71: =+O435 -> 0 | P71: =+P435 -> 0 | Q71: =+Q435 -> 0 | ... S71: =+S435 -> 0 | U71: =SUM(I71:T71) -> 0 | W71: =F71-U71 -> 0
B72: =B71+1 -> 20 | D72: Cash Working Capital | E72: II-B-9 | F72: =+F455 -> 175757.58 | J72: =+J455 -> 90603.252 | K72: =+K455 -> 11185.211 | L72: =+L455 -> 51172.593 | M72: =+M455 -> 1760.1355 | N72: =+N455 -> 15565.488 | O72: =+O455 -> 866.17482 | P72: =+P455 -> 2058.7592 | Q72: =+Q455 -> 2373.2042 | ... S72: =+S455 -> 123.9406 | U72: =SUM(I72:T72) -> 175757.58 | W72: =F72-U72 -> 0
B73: =B72+1 -> 21 | D73: Prepayments | E73: II-B-10 | F73: =+F476 -> 529501.18 | J73: =+J476 -> 207606.14 | K73: =+K476 -> 6289.6322 | L73: =+L476 -> 221051.64 | M73: =+M476 -> 4.2560916 | N73: =+N476 -> 36602.638 | O73: =+O476 -> 6977.1312 | P73: =+P476 -> 48120.849 | Q73: =+Q476 -> 1698.7056 | ... S73: =+S476 -> 622.51064 | U73: =SUM(I73:T73) -> 529501.18 | W73: =F73-U73 -> 0
B74: =B73+1 -> 22 | D74: Misc Other Rate Base | E74: II-B-11 | F74: =F499 -> 0 | J74: =J499 -> 0 | K74: =K499 -> 0 | L74: =L499 -> 0 | M74: =M499 -> 0 | N74: =N499 -> 0 | O74: =O499 -> 0 | P74: =P499 -> 0 | Q74: =Q499 -> 0 | ... S74: =S499 -> 0 | U74: =SUM(I74:T74) -> 0 | W74: =F74-U74 -> 0
B75: =B74+1 -> 23 | D75: Regulatory Assets | E75: II-B-12 | F75: =F614 -> 2989198.3 | J75: =J614 -> 1525046.4 | K75: =K614 -> 195636.11 | L75: =L614 -> 852434.46 | M75: =M614 -> 31235.993 | N75: =N614 -> 264193.25 | O75: =O614 -> 12854.575 | P75: =P614 -> 29781.16 | Q75: =Q614 -> 84818.154 | ... S75: =S614 -> -4879.6132 | U75: =SUM(I75:T75) -> 2989198.3 | W75: =F75-U75 -> 5.1222742e-09
B76: =B75+1 -> 24 | D76: Accumulated Deferred Income Taxes | E76: II-E3.7 | F76: =+F413 -> -52031200 | J76: =+J413 -> -25647424 | K76: =+K413 -> -3578656.3 | L76: =+L413 -> -13986728 | M76: =+M413 -> -588354.15 | N76: =+N413 -> -4528973.2 | O76: =+O413 -> -148599.03 | P76: =+P413 -> -309961.16 | Q76: =+Q413 -> -3184435.8 | ... S76: =+S413 -> -41658.997 | U76: =SUM(I76:T76) -> -52031200 | W76: =F76-U76 -> 0
B77: =B76+1 -> 25 | D77: Subtotal | F77: =SUM(F68:F76) -> -48336743 | J77: =SUM(J68:J76) -> -23824168 | K77: =SUM(K68:K76) -> -3365545.3 | L77: =SUM(L68:L76) -> -12862070 | M77: =SUM(M68:M76) -> -555353.76 | N77: =SUM(N68:N76) -> -4212611.8 | O77: =SUM(O68:O76) -> -127901.15 | P77: =SUM(P68:P76) -> -230000.4 | Q77: =SUM(Q68:Q76) -> -3095545.7 | ... S77: =SUM(S68:S76) -> -45792.159 | U77: =SUM(I77:T77) -> -48336743 | W77: =F77-U77 -> 0
B78: =B77+1 -> 26 | W78: =F78-U78 -> 0
B79: =B78+1 -> 27 | D79: TOTAL RATE BASE | F79: =+F64+F77 -> 2.3006701e+08 | J79: =+J64+J77 -> 1.134077e+08 | K79: =+K64+K77 -> 15782799 | L79: =+L64+L77 -> 61976827 | M79: =+M64+M77 -> 2592757.4 | N79: =+N64+N77 -> 20020600 | O79: =+O64+O77 -> 667208.83 | P79: =+P64+P77 -> 1428511.2 | Q79: =+Q64+Q77 -> 13943440 | ... S79: =+S64+S77 -> 177112.96 | U79: =SUM(I79:T79) -> 2.3006701e+08 | V79: =IF(ROUND(U79-'WP II-I-1.1'!I492,2)=0,TRUE,U79-'WP II-I-1.1'!I492) -> TRUE | W79: =F79-U79 -> 0
B80: =B79+1 -> 28 | W80: =F80-U80 -> 0
B81: =B80+1 -> 29 | D81: COST-BASED Rate of Return | F81: =F620 -> 0.0747 | J81: =J620 -> 0.0747 | K81: =K620 -> 0.0747 | L81: =L620 -> 0.0747 | M81: =M620 -> 0.0747 | N81: =N620 -> 0.0747 | O81: =O620 -> 0.0747 | P81: =P620 -> 0.0747 | Q81: =Q620 -> 0.0747 | ... S81: =S620 -> 0.0747 | U81: =U83/U79 -> 0.0747 | W81: =F81-U81 -> 0
B82: =B81+1 -> 30 | W82: =F82-U82 -> 0
B83: =B82+1 -> 31 | D83: COST-BASED Return On Rate Base | F83: =+F79*F81 -> 17186005 | J83: =+J79*J81 -> 8471555.4 | K83: =+K79*K81 -> 1178975.1 | L83: =+L79*L81 -> 4629669 | M83: =+M79*M81 -> 193678.98 | N83: =+N79*N81 -> 1495538.9 | O83: =+O79*O81 -> 49840.5 | P83: =+P79*P81 -> 106709.79 | Q83: =+Q79*Q81 -> 1041574.9 | ... S83: =+S79*S81 -> 13230.338 | U83: =SUM(I83:T83) -> 17186005 | V83: =IF(ROUND(U83-'WP II-I-1.1'!I494,2)=0,TRUE,U83-'WP II-I-1.1'!I494) -> TRUE | W83: =F83-U83 -> 0
B91: =+$B$4 -> 2025 RATE CASE | V91: =$H$2 -> 0
B92: =+$B$5 -> ONCOR ELECTRIC DELIVERY COMPANY LLC
B93: =+$B$6 -> II-I-1-TBILLTDCS: CLASS REVENUE REQUIREMENT
B94: =+$B$7 -> TEST YEAR ENDING 12/31/2024
B95: =+$B$8 -> SPONSOR: MATTHEW A. TROXLE
R97: =R$10
B98: Line | C98: Acct | D98: Intangible and Transmission Plant Gross | E98: Source | F98: =F$11 -> TBILLTDCS | G98: Alloc | H98: Allocation | J98: Residential | K98: Secondary | L98: Secondary | M98: Primary | N98: Primary | O98: Primary | P98: Transmission | Q98: Lighting | R98: =R$11 -> Wholesale | S98: =S$11 -> Wholesale | U98: Total
G99: # | H99: Factor | K99: <=10 kW | L99: > 10 kW | M99: <=10 kW | N99: > 10 kW | O99: Substation | R99: =R$12 -> XFMR | S99: =S$12 -> DLS
F100: (a) | G100: (b) | H100: (c) | J100: =J$13 -> (d) | K100: =K$13 -> (e) | L100: =L$13 -> (f) | M100: =M$13 -> (g) | N100: =N$13 -> (h) | O100: =O$13 -> (i) | P100: =P$13 -> (j) | Q100: =Q$13 -> (k) | ... S100: =S$13 -> (m) | U100: (n)
W101: =F101-U101 -> 0
B102: =B101+1 -> 1 | C102: Intangible Plant Gross | E102: II-B-1 | W102: =F102-U102 -> 0
B103: =B102+1 -> 2 | C103: A301 | D103: Organization | F103: =' WP II-I-1.4'!I103 -> 0 | G103: 65 | H103: =VLOOKUP(G103,FactorTable,2) -> PLT_N XINT | J103: =$F103*HLOOKUP(J$1354,FactorTable,$G103+1) -> 0 | K103: =$F103*HLOOKUP(K$1354,FactorTable,$G103+1) -> 0 | L103: =$F103*HLOOKUP(L$1354,FactorTable,$G103+1) -> 0 | M103: =$F103*HLOOKUP(M$1354,FactorTable,$G103+1) -> 0 | N103: =$F103*HLOOKUP(N$1354,FactorTable,$G103+1) -> 0 | O103: =$F103*HLOOKUP(O$1354,FactorTable,$G103+1) -> 0 | P103: =$F103*HLOOKUP(P$1354,FactorTable,$G103+1) -> 0 | Q103: =$F103*HLOOKUP(Q$1354,FactorTable,$G103+1) -> 0 | ... S103: =$F103*HLOOKUP(S$1354,FactorTable,$G103+1) -> 0 | U103: =SUM(I103:T103) -> 0 | W103: =F103-U103 -> 0
B104: =B103+1 -> 3 | C104: A302 | D104: Franchise & Consents | F104: =' WP II-I-1.4'!I104 -> 0 | G104: 65 | H104: =VLOOKUP(G104,FactorTable,2) -> PLT_N XINT | J104: =$F104*HLOOKUP(J$1354,FactorTable,$G104+1) -> 0 | K104: =$F104*HLOOKUP(K$1354,FactorTable,$G104+1) -> 0 | L104: =$F104*HLOOKUP(L$1354,FactorTable,$G104+1) -> 0 | M104: =$F104*HLOOKUP(M$1354,FactorTable,$G104+1) -> 0 | N104: =$F104*HLOOKUP(N$1354,FactorTable,$G104+1) -> 0 | O104: =$F104*HLOOKUP(O$1354,FactorTable,$G104+1) -> 0 | P104: =$F104*HLOOKUP(P$1354,FactorTable,$G104+1) -> 0 | Q104: =$F104*HLOOKUP(Q$1354,FactorTable,$G104+1) -> 0 | ... S104: =$F104*HLOOKUP(S$1354,FactorTable,$G104+1) -> 0 | U104: =SUM(I104:T104) -> 0 | W104: =F104-U104 -> 0
B105: =B104+1 -> 4 | C105: A303 | D105: Miscellaneous Intangible Plant | F105: =' WP II-I-1.4'!I105 -> 145326 | G105: 65 | H105: =VLOOKUP(G105,FactorTable,2) -> PLT_N XINT | J105: =$F105*HLOOKUP(J$1354,FactorTable,$G105+1) -> 71634.663 | K105: =$F105*HLOOKUP(K$1354,FactorTable,$G105+1) -> 9995.3835 | L105: =$F105*HLOOKUP(L$1354,FactorTable,$G105+1) -> 39065.7 | M105: =$F105*HLOOKUP(M$1354,FactorTable,$G105+1) -> 1643.3054 | N105: =$F105*HLOOKUP(N$1354,FactorTable,$G105+1) -> 12649.671 | O105: =$F105*HLOOKUP(O$1354,FactorTable,$G105+1) -> 415.04525 | P105: =$F105*HLOOKUP(P$1354,FactorTable,$G105+1) -> 865.73855 | Q105: =$F105*HLOOKUP(Q$1354,FactorTable,$G105+1) -> 8894.304 | ... S105: =$F105*HLOOKUP(S$1354,FactorTable,$G105+1) -> 116.35587 | U105: =SUM(I105:T105) -> 145326 | W105: =F105-U105 -> 0
B106: =B105+1 -> 5 | D106: Subtotal | F106: =SUM(F103:F105) -> 145326 | J106: =SUM(J103:J105) -> 71634.663 | K106: =SUM(K103:K105) -> 9995.3835 | L106: =SUM(L103:L105) -> 39065.7 | M106: =SUM(M103:M105) -> 1643.3054 | N106: =SUM(N103:N105) -> 12649.671 | O106: =SUM(O103:O105) -> 415.04525 | P106: =SUM(P103:P105) -> 865.73855 | Q106: =SUM(Q103:Q105) -> 8894.304 | ... S106: =SUM(S103:S105) -> 116.35587 | U106: =SUM(I106:T106) -> 145326 | W106: =F106-U106 -> 0
B107: =B106+1 -> 6 | C107: Transmission Plant Gross | E107: II-B-1 | W107: =F107-U107 -> 0
B108: =B107+1 -> 7 | C108: A349 | D108: Land Owned in Fee | F108: =' WP II-I-1.4'!I108 -> 0 | G108: 28 | H108: =VLOOKUP(G108,FactorTable,2) -> NCP XHV | J108: =$F108*HLOOKUP(J$1354,FactorTable,$G108+1) -> 0 | K108: =$F108*HLOOKUP(K$1354,FactorTable,$G108+1) -> 0 | L108: =$F108*HLOOKUP(L$1354,FactorTable,$G108+1) -> 0 | M108: =$F108*HLOOKUP(M$1354,FactorTable,$G108+1) -> 0 | N108: =$F108*HLOOKUP(N$1354,FactorTable,$G108+1) -> 0 | O108: =$F108*HLOOKUP(O$1354,FactorTable,$G108+1) -> 0 | P108: =$F108*HLOOKUP(P$1354,FactorTable,$G108+1) -> 0 | Q108: =$F108*HLOOKUP(Q$1354,FactorTable,$G108+1) -> 0 | ... S108: =$F108*HLOOKUP(S$1354,FactorTable,$G108+1) -> 0 | U108: =SUM(I108:T108) -> 0 | W108: =F108-U108 -> 0
B109: =B108+1 -> 8 | C109: A350 | D109: Land and Land Rights | F109: =' WP II-I-1.4'!I109 -> 0 | G109: 28 | H109: =VLOOKUP(G109,FactorTable,2) -> NCP XHV | J109: =$F109*HLOOKUP(J$1354,FactorTable,$G109+1) -> 0 | K109: =$F109*HLOOKUP(K$1354,FactorTable,$G109+1) -> 0 | L109: =$F109*HLOOKUP(L$1354,FactorTable,$G109+1) -> 0 | M109: =$F109*HLOOKUP(M$1354,FactorTable,$G109+1) -> 0 | N109: =$F109*HLOOKUP(N$1354,FactorTable,$G109+1) -> 0 | O109: =$F109*HLOOKUP(O$1354,FactorTable,$G109+1) -> 0 | P109: =$F109*HLOOKUP(P$1354,FactorTable,$G109+1) -> 0 | Q109: =$F109*HLOOKUP(Q$1354,FactorTable,$G109+1) -> 0 | ... S109: =$F109*HLOOKUP(S$1354,FactorTable,$G109+1) -> 0 | U109: =SUM(I109:T109) -> 0 | W109: =F109-U109 -> 0
B110: =B109+1 -> 9 | C110: A351.1 | D110: Computer Hardware | F110: =' WP II-I-1.4'!I110 -> 0 | G110: 67 | H110: =VLOOKUP(G110,FactorTable,2) -> PLTTRAN_N | J110: =$F110*HLOOKUP(J$1354,FactorTable,$G110+1) -> 0 | K110: =$F110*HLOOKUP(K$1354,FactorTable,$G110+1) -> 0 | L110: =$F110*HLOOKUP(L$1354,FactorTable,$G110+1) -> 0 | M110: =$F110*HLOOKUP(M$1354,FactorTable,$G110+1) -> 0 | N110: =$F110*HLOOKUP(N$1354,FactorTable,$G110+1) -> 0 | O110: =$F110*HLOOKUP(O$1354,FactorTable,$G110+1) -> 0 | P110: =$F110*HLOOKUP(P$1354,FactorTable,$G110+1) -> 0 | Q110: =$F110*HLOOKUP(Q$1354,FactorTable,$G110+1) -> 0 | ... S110: =$F110*HLOOKUP(S$1354,FactorTable,$G110+1) -> 0 | U110: =SUM(I110:T110) -> 0
B111: =B110+1 -> 10 | C111: A351.2 | D111: Computer Software | F111: =' WP II-I-1.4'!I111 -> 0 | G111: 67 | H111: =VLOOKUP(G111,FactorTable,2) -> PLTTRAN_N | J111: =$F111*HLOOKUP(J$1354,FactorTable,$G111+1) -> 0 | K111: =$F111*HLOOKUP(K$1354,FactorTable,$G111+1) -> 0 | L111: =$F111*HLOOKUP(L$1354,FactorTable,$G111+1) -> 0 | M111: =$F111*HLOOKUP(M$1354,FactorTable,$G111+1) -> 0 | N111: =$F111*HLOOKUP(N$1354,FactorTable,$G111+1) -> 0 | O111: =$F111*HLOOKUP(O$1354,FactorTable,$G111+1) -> 0 | P111: =$F111*HLOOKUP(P$1354,FactorTable,$G111+1) -> 0 | Q111: =$F111*HLOOKUP(Q$1354,FactorTable,$G111+1) -> 0 | ... S111: =$F111*HLOOKUP(S$1354,FactorTable,$G111+1) -> 0 | U111: =SUM(I111:T111) -> 0
B112: =B111+1 -> 11 | C112: A351.3 | D112: Communication Equipment | F112: =' WP II-I-1.4'!I112 -> 0 | G112: 67 | H112: =VLOOKUP(G112,FactorTable,2) -> PLTTRAN_N | J112: =$F112*HLOOKUP(J$1354,FactorTable,$G112+1) -> 0 | K112: =$F112*HLOOKUP(K$1354,FactorTable,$G112+1) -> 0 | L112: =$F112*HLOOKUP(L$1354,FactorTable,$G112+1) -> 0 | M112: =$F112*HLOOKUP(M$1354,FactorTable,$G112+1) -> 0 | N112: =$F112*HLOOKUP(N$1354,FactorTable,$G112+1) -> 0 | O112: =$F112*HLOOKUP(O$1354,FactorTable,$G112+1) -> 0 | P112: =$F112*HLOOKUP(P$1354,FactorTable,$G112+1) -> 0 | Q112: =$F112*HLOOKUP(Q$1354,FactorTable,$G112+1) -> 0 | ... S112: =$F112*HLOOKUP(S$1354,FactorTable,$G112+1) -> 0 | U112: =SUM(I112:T112) -> 0
B113: =B112+1 -> 12 | C113: A352 | D113: Structures and Improvements | F113: =' WP II-I-1.4'!I113 -> 0 | G113: 28 | H113: =VLOOKUP(G113,FactorTable,2) -> NCP XHV | J113: =$F113*HLOOKUP(J$1354,FactorTable,$G113+1) -> 0 | K113: =$F113*HLOOKUP(K$1354,FactorTable,$G113+1) -> 0 | L113: =$F113*HLOOKUP(L$1354,FactorTable,$G113+1) -> 0 | M113: =$F113*HLOOKUP(M$1354,FactorTable,$G113+1) -> 0 | N113: =$F113*HLOOKUP(N$1354,FactorTable,$G113+1) -> 0 | O113: =$F113*HLOOKUP(O$1354,FactorTable,$G113+1) -> 0 | P113: =$F113*HLOOKUP(P$1354,FactorTable,$G113+1) -> 0 | Q113: =$F113*HLOOKUP(Q$1354,FactorTable,$G113+1) -> 0 | ... S113: =$F113*HLOOKUP(S$1354,FactorTable,$G113+1) -> 0 | U113: =SUM(I113:T113) -> 0 | W113: =F113-U113 -> 0
B114: =B113+1 -> 13 | C114: A353 | D114: Station Equipment | F114: =' WP II-I-1.4'!I114 -> 0 | G114: 28 | H114: =VLOOKUP(G114,FactorTable,2) -> NCP XHV | J114: =$F114*HLOOKUP(J$1354,FactorTable,$G114+1) -> 0 | K114: =$F114*HLOOKUP(K$1354,FactorTable,$G114+1) -> 0 | L114: =$F114*HLOOKUP(L$1354,FactorTable,$G114+1) -> 0 | M114: =$F114*HLOOKUP(M$1354,FactorTable,$G114+1) -> 0 | N114: =$F114*HLOOKUP(N$1354,FactorTable,$G114+1) -> 0 | O114: =$F114*HLOOKUP(O$1354,FactorTable,$G114+1) -> 0 | P114: =$F114*HLOOKUP(P$1354,FactorTable,$G114+1) -> 0 | Q114: =$F114*HLOOKUP(Q$1354,FactorTable,$G114+1) -> 0 | ... S114: =$F114*HLOOKUP(S$1354,FactorTable,$G114+1) -> 0 | U114: =SUM(I114:T114) -> 0 | W114: =F114-U114 -> 0
B115: =B114+1 -> 14 | C115: A354 | D115: Towers and Fixtures | F115: =' WP II-I-1.4'!I115 -> 0 | G115: 28 | H115: =VLOOKUP(G115,FactorTable,2) -> NCP XHV | J115: =$F115*HLOOKUP(J$1354,FactorTable,$G115+1) -> 0 | K115: =$F115*HLOOKUP(K$1354,FactorTable,$G115+1) -> 0 | L115: =$F115*HLOOKUP(L$1354,FactorTable,$G115+1) -> 0 | M115: =$F115*HLOOKUP(M$1354,FactorTable,$G115+1) -> 0 | N115: =$F115*HLOOKUP(N$1354,FactorTable,$G115+1) -> 0 | O115: =$F115*HLOOKUP(O$1354,FactorTable,$G115+1) -> 0 | P115: =$F115*HLOOKUP(P$1354,FactorTable,$G115+1) -> 0 | Q115: =$F115*HLOOKUP(Q$1354,FactorTable,$G115+1) -> 0 | ... S115: =$F115*HLOOKUP(S$1354,FactorTable,$G115+1) -> 0 | U115: =SUM(I115:T115) -> 0 | W115: =F115-U115 -> 0
B116: =B115+1 -> 15 | C116: A355 | D116: Poles and Fixtures | F116: =' WP II-I-1.4'!I116 -> 0 | G116: 28 | H116: =VLOOKUP(G116,FactorTable,2) -> NCP XHV | J116: =$F116*HLOOKUP(J$1354,FactorTable,$G116+1) -> 0 | K116: =$F116*HLOOKUP(K$1354,FactorTable,$G116+1) -> 0 | L116: =$F116*HLOOKUP(L$1354,FactorTable,$G116+1) -> 0 | M116: =$F116*HLOOKUP(M$1354,FactorTable,$G116+1) -> 0 | N116: =$F116*HLOOKUP(N$1354,FactorTable,$G116+1) -> 0 | O116: =$F116*HLOOKUP(O$1354,FactorTable,$G116+1) -> 0 | P116: =$F116*HLOOKUP(P$1354,FactorTable,$G116+1) -> 0 | Q116: =$F116*HLOOKUP(Q$1354,FactorTable,$G116+1) -> 0 | ... S116: =$F116*HLOOKUP(S$1354,FactorTable,$G116+1) -> 0 | U116: =SUM(I116:T116) -> 0 | W116: =F116-U116 -> 0
B117: =B116+1 -> 16 | C117: A356 | D117: O.H. Conductors & Devices | F117: =' WP II-I-1.4'!I117 -> 0 | G117: 28 | H117: =VLOOKUP(G117,FactorTable,2) -> NCP XHV | J117: =$F117*HLOOKUP(J$1354,FactorTable,$G117+1) -> 0 | K117: =$F117*HLOOKUP(K$1354,FactorTable,$G117+1) -> 0 | L117: =$F117*HLOOKUP(L$1354,FactorTable,$G117+1) -> 0 | M117: =$F117*HLOOKUP(M$1354,FactorTable,$G117+1) -> 0 | N117: =$F117*HLOOKUP(N$1354,FactorTable,$G117+1) -> 0 | O117: =$F117*HLOOKUP(O$1354,FactorTable,$G117+1) -> 0 | P117: =$F117*HLOOKUP(P$1354,FactorTable,$G117+1) -> 0 | Q117: =$F117*HLOOKUP(Q$1354,FactorTable,$G117+1) -> 0 | ... S117: =$F117*HLOOKUP(S$1354,FactorTable,$G117+1) -> 0 | U117: =SUM(I117:T117) -> 0 | W117: =F117-U117 -> 0
B118: =B117+1 -> 17 | C118: A357 | D118: Underground Conduit | F118: =' WP II-I-1.4'!I118 -> 0 | G118: 28 | H118: =VLOOKUP(G118,FactorTable,2) -> NCP XHV | J118: =$F118*HLOOKUP(J$1354,FactorTable,$G118+1) -> 0 | K118: =$F118*HLOOKUP(K$1354,FactorTable,$G118+1) -> 0 | L118: =$F118*HLOOKUP(L$1354,FactorTable,$G118+1) -> 0 | M118: =$F118*HLOOKUP(M$1354,FactorTable,$G118+1) -> 0 | N118: =$F118*HLOOKUP(N$1354,FactorTable,$G118+1) -> 0 | O118: =$F118*HLOOKUP(O$1354,FactorTable,$G118+1) -> 0 | P118: =$F118*HLOOKUP(P$1354,FactorTable,$G118+1) -> 0 | Q118: =$F118*HLOOKUP(Q$1354,FactorTable,$G118+1) -> 0 | ... S118: =$F118*HLOOKUP(S$1354,FactorTable,$G118+1) -> 0 | U118: =SUM(I118:T118) -> 0 | W118: =F118-U118 -> 0
B119: =B118+1 -> 18 | C119: A358 | D119: Underground Conductors | F119: =' WP II-I-1.4'!I119 -> 0 | G119: 28 | H119: =VLOOKUP(G119,FactorTable,2) -> NCP XHV | J119: =$F119*HLOOKUP(J$1354,FactorTable,$G119+1) -> 0 | K119: =$F119*HLOOKUP(K$1354,FactorTable,$G119+1) -> 0 | L119: =$F119*HLOOKUP(L$1354,FactorTable,$G119+1) -> 0 | M119: =$F119*HLOOKUP(M$1354,FactorTable,$G119+1) -> 0 | N119: =$F119*HLOOKUP(N$1354,FactorTable,$G119+1) -> 0 | O119: =$F119*HLOOKUP(O$1354,FactorTable,$G119+1) -> 0 | P119: =$F119*HLOOKUP(P$1354,FactorTable,$G119+1) -> 0 | Q119: =$F119*HLOOKUP(Q$1354,FactorTable,$G119+1) -> 0 | ... S119: =$F119*HLOOKUP(S$1354,FactorTable,$G119+1) -> 0 | U119: =SUM(I119:T119) -> 0 | W119: =F119-U119 -> 0
B120: =B119+1 -> 19 | C120: A359 | D120: Roads and Trails | F120: =' WP II-I-1.4'!I120 -> 0 | G120: 28 | H120: =VLOOKUP(G120,FactorTable,2) -> NCP XHV | J120: =$F120*HLOOKUP(J$1354,FactorTable,$G120+1) -> 0 | K120: =$F120*HLOOKUP(K$1354,FactorTable,$G120+1) -> 0 | L120: =$F120*HLOOKUP(L$1354,FactorTable,$G120+1) -> 0 | M120: =$F120*HLOOKUP(M$1354,FactorTable,$G120+1) -> 0 | N120: =$F120*HLOOKUP(N$1354,FactorTable,$G120+1) -> 0 | O120: =$F120*HLOOKUP(O$1354,FactorTable,$G120+1) -> 0 | P120: =$F120*HLOOKUP(P$1354,FactorTable,$G120+1) -> 0 | Q120: =$F120*HLOOKUP(Q$1354,FactorTable,$G120+1) -> 0 | ... S120: =$F120*HLOOKUP(S$1354,FactorTable,$G120+1) -> 0 | U120: =SUM(I120:T120) -> 0 | W120: =F120-U120 -> 0
B121: =B120+1 -> 20 | D121: Subtotal | F121: =SUM(F108:F120) -> 0 | J121: =SUM(J108:J120) -> 0 | K121: =SUM(K108:K120) -> 0 | L121: =SUM(L108:L120) -> 0 | M121: =SUM(M108:M120) -> 0 | N121: =SUM(N108:N120) -> 0 | O121: =SUM(O108:O120) -> 0 | P121: =SUM(P108:P120) -> 0 | Q121: =SUM(Q108:Q120) -> 0 | ... S121: =SUM(S108:S120) -> 0 | U121: =SUM(I121:T121) -> 0 | W121: =F121-U121 -> 0
V122: =$H$2 -> 0
...

Sheet II-I-Total
B4: ='WP II-I-1.1'!B3 -> 2025 RATE CASE
B5: ='WP II-I-1.1'!B4 -> ONCOR ELECTRIC DELIVERY COMPANY LLC
B6: ="II-I-1-TOT: CLASS REVENUE REQUIREMENT" -> II-I-1-TOT: CLASS REVENUE REQUIREMENT
B7: ='WP II-I-1.1'!B6 -> TEST YEAR ENDING 12/31/2024
B8: ='WP II-I-2.2'!$B$7 -> SPONSOR: MATTHEW A. TROXLE
R10: =" "
B11: Line | D11: I-A-1 by Rate Class | E11: Source | F11: TOTAL | J11: Residential | K11: Secondary | L11: Secondary | M11: Primary | N11: Primary | O11: Primary | P11: Transmission | Q11: Lighting | R11: Wholesale | S11: Wholesale | U11: Total
F12: (Dist+Met+Cust) | K12: <=10 kW | L12: > 10 kW | M12: <=10 kW | N12: > 10 kW | O12: Substation | R12: XFMR | S12: DLS
F13: (a) | G13: (b) | H13: (c) | J13: (d) | K13: (e) | L13: (f) | M13: (g) | N13: (h) | O13: (i) | P13: (j) | Q13: (k) | R13: (l) | S13: (m) | U13: (n)
B15: =B14+1 -> 1 | D15: O&M Expenses | E15: II-D-2 | F15: =F661+F709 -> 2.5275875e+09 | J15: =J661+J709 -> 1.1447022e+09 | K15: =K661+K709 -> 27263658 | L15: =L661+L709 -> 7.8154775e+08 | M15: =M661+M709 -> 1106142.9 | N15: =N661+N709 -> 2.3602042e+08 | O15: =O661+O709 -> 75637226 | P15: =P661+P709 -> 2.4782015e+08 | Q15: =Q661+Q709 -> 12057528 | ... S15: =S661+S709 -> 1203312.4 | U15: =SUM(I15:T15) -> 2.5275875e+09 | X15: =U15-F15 -> 0
B16: =B15+1 -> 2 | D16: Customer Expenses | E16: II-D-2 | F16: =F729+F739+F749 -> 27246613 | J16: =J729+J739+J749 -> 14287295 | K16: =K729+K739+K749 -> 1842904.8 | L16: =L729+L739+L749 -> 7902847.7 | M16: =M729+M739+M749 -> 293583.11 | N16: =N729+N739+N749 -> 2457601.6 | O16: =O729+O739+O749 -> 115592.73 | P16: =P729+P739+P749 -> 265905.43 | Q16: =Q729+Q739+Q749 -> 52010.354 | ... S16: =S729+S739+S749 -> 20713.243 | U16: =SUM(I16:T16) -> 27246613 | X16: =U16-F16 -> 0
B17: =B16+1 -> 3 | D17: A&G Expenses | E17: II-D-2 | F17: =F783 -> 9.521598e+08 | J17: =J783 -> 5.0670158e+08 | K17: =K783 -> 19570559 | L17: =L783 -> 3.1764053e+08 | M17: =M783 -> 1182166.6 | N17: =N783 -> 67813802 | O17: =O783 -> 6732790.1 | P17: =P783 -> 1608655 | Q17: =Q783 -> 28111812 | ... S17: =S783 -> 2331600 | U17: =SUM(I17:T17) -> 9.521598e+08 | X17: =U17-F17 -> 0
B18: =B17+1 -> 4 | D18: O&M + Customer + A&G Expenses | F18: =SUM(F15:F17) -> 3.5069939e+09 | J18: =SUM(J15:J17) -> 1.6656911e+09 | K18: =SUM(K15:K17) -> 48677123 | L18: =SUM(L15:L17) -> 1.1070911e+09 | M18: =SUM(M15:M17) -> 2581892.6 | N18: =SUM(N15:N17) -> 3.0629183e+08 | O18: =SUM(O15:O17) -> 82485609 | P18: =SUM(P15:P17) -> 2.4969471e+08 | Q18: =SUM(Q15:Q17) -> 40221350 | ... S18: =SUM(S15:S17) -> 3555625.7 | U18: =SUM(I18:T18) -> 3.5069939e+09 | W18: =' WP II-I-1.4'!$L$18=F18 -> TRUE | X18: =U18-F18 -> 0
B19: =B18+1 -> 5 | X19: =U19-F19 -> 0
B20: =B19+1 -> 6 | D20: Depreciation & Amortization (II-E-1) | E20: II-E-1 | F20: =F1065 -> 7.2124832e+08 | J20: =J1065 -> 3.7990451e+08 | K20: =K1065 -> 16812128 | L20: =L1065 -> 2.3668658e+08 | M20: =M1065 -> 877378.61 | N20: =N1065 -> 46026943 | O20: =O1065 -> 3937327.1 | P20: =P1065 -> 1076356.2 | Q20: =Q1065 -> 34063217 | ... S20: =S1065 -> 1583218.6 | U20: =SUM(I20:T20) -> 7.2124832e+08 | X20: =U20-F20 -> 0
B21: =B20+1 -> 7 | D21: Other (II-E-4) | E21: II-E-4 | F21: =F1067+F1068 -> 40888584 | J21: =J1067+J1068 -> 21708789 | K21: =K1067+K1068 -> 2087379.3 | L21: =L1067+L1068 -> 12691736 | M21: =M1067+M1068 -> 310409.68 | N21: =N1067+N1068 -> 3392803.1 | O21: =O1067+O1068 -> 196612.67 | P21: =P1067+P1068 -> 182763.61 | Q21: =Q1067+Q1068 -> 240460.8 | ... S21: =S1067+S1068 -> 60815.875 | U21: =SUM(I21:T21) -> 40888584 | X21: =U21-F21 -> 0
B22: =B21+1 -> 8 | D22: Depreciation, Amortization & Other Expenses | F22: =SUM(F20:F21) -> 7.6213691e+08 | J22: =SUM(J20:J21) -> 4.016133e+08 | K22: =SUM(K20:K21) -> 18899507 | L22: =SUM(L20:L21) -> 2.4937832e+08 | M22: =SUM(M20:M21) -> 1187788.3 | N22: =SUM(N20:N21) -> 49419746 | O22: =SUM(O20:O21) -> 4133939.8 | P22: =SUM(P20:P21) -> 1259119.8 | Q22: =SUM(Q20:Q21) -> 34303678 | ... S22: =SUM(S20:S21) -> 1644034.4 | U22: =SUM(I22:T22) -> 7.6213691e+08 | W22: =' WP II-I-1.4'!$L$22=F22 -> TRUE | X22: =U22-F22 -> 0
B23: =B22+1 -> 9 | X23: =U23-F23 -> 0
B24: =B23+1 -> 10 | D24: Taxes Other Than Federal Income Tax | E24: II-E-2 | F24: =+F1103 -> 4.9498676e+08 | J24: =+J1103 -> 2.2223392e+08 | K24: =+K1103 -> 7470560.3 | L24: =+L1103 -> 1.9103386e+08 | M24: =+M1103 -> 174043.73 | N24: =+N1103 -> 33593410 | O24: =+O1103 -> 5306944 | P24: =+P1103 -> 27571464 | Q24: =+Q1103 -> 6397694.4 | ... S24: =+S1103 -> 810743.42 | U24: =SUM(I24:T24) -> 4.9498676e+08 | W24: =' WP II-I-1.4'!$L$24=F24 -> TRUE | X24: =U24-F24 -> 0
B25: =B24+1 -> 11 | D25: Federal Income Tax | E25: II-E-3 | F25: =+F1162 -> 1.4473902e+08 | J25: =+J1162 -> 78668226 | K25: =+K1162 -> 2333594.4 | L25: =+L1162 -> 50108868 | M25: =+M1162 -> 68143.324 | N25: =+N1162 -> 9622190.5 | O25: =+O1162 -> 1093406.3 | P25: =+P1162 -> 303017.14 | Q25: =+Q1162 -> 2109357.1 | ... S25: =+S1162 -> 355506.44 | U25: =SUM(I25:T25) -> 1.4473902e+08 | W25: =' WP II-I-1.4'!$L$25-F25 -> 0 | X25: =U25-F25 -> 0
B26: =B25+1 -> 12 | X26: =U26-F26 -> 0
B27: =B26+1 -> 13 | D27: Return on Rate Base | E27: II-B | F27: =+F83 -> 1.0591573e+09 | J27: =+J83 -> 5.7528199e+08 | K27: =+K83 -> 18004272 | L27: =+L83 -> 3.6570944e+08 | M27: =+M83 -> 698376.14 | N27: =+N83 -> 71151671 | O27: =+O83 -> 7977532.6 | P27: =+P83 -> 2278161.3 | Q27: =+Q83 -> 14910476 | ... S27: =+S83 -> 2584084.4 | U27: =SUM(I27:T27) -> 1.0591573e+09 | W27: =' WP II-I-1.4'!$L$27=F27 -> TRUE | X27: =U27-F27 -> 0
B28: =B27+1 -> 14 | X28: =U28-F28 -> 0
B29: =B28+1 -> 15 | D29: TOTAL COST OF SERVICE | F29: =+F18+F22+F24+F25+F27 -> 5.9680139e+09 | J29: =+J18+J22+J24+J25+J27 -> 2.9434885e+09 | K29: =+K18+K22+K24+K25+K27 -> 95385056 | L29: =+L18+L22+L24+L25+L27 -> 1.9633216e+09 | M29: =+M18+M22+M24+M25+M27 -> 4710244 | N29: =+N18+N22+N24+N25+N27 -> 4.7007885e+08 | O29: =+O18+O22+O24+O25+O27 -> 1.0099743e+08 | P29: =+P18+P22+P24+P25+P27 -> 2.8110647e+08 | Q29: =+Q18+Q22+Q24+Q25+Q27 -> 97942555 | ... S29: =+S18+S22+S24+S25+S27 -> 8949994.4 | U29: =SUM(I29:T29) -> 5.9680139e+09 | W29: =' WP II-I-1.4'!$L$29-F29 -> 0 | X29: =U29-F29 -> 0
B30: =B29+1 -> 16 | X30: =U30-F30 -> 0
B31: =B30+1 -> 17 | D31: Minus: Other Revenues | E31: II-E-5 | F31: =+F1222 -> 81014329 | J31: =+J1222 -> 44678854 | K31: =+K1222 -> 2520222.3 | L31: =+L1222 -> 21286205 | M31: =+M1222 -> 188960.18 | N31: =+N1222 -> 5684264 | O31: =+O1222 -> 1334239.9 | P31: =+P1222 -> 4650081.3 | Q31: =+Q1222 -> 418151.09 | ... S31: =+S1222 -> 164565.08 | U31: =SUM(I31:T31) -> 81014329 | W31: =' WP II-I-1.4'!$L$31=F31 -> TRUE | X31: =U31-F31 -> 0
B32: =B31+1 -> 18 | X32: =U32-F32 -> 0
B33: =B32+1 -> 19 | D33: COST_BASED Revenue Requirement | F33: =+F29-F31 -> 5.8869996e+09 | J33: =+J29-J31 -> 2.8988097e+09 | K33: =+K29-K31 -> 92864834 | L33: =+L29-L31 -> 1.9420354e+09 | M33: =+M29-M31 -> 4521283.9 | N33: =+N29-N31 -> 4.6439458e+08 | O33: =+O29-O31 -> 99663191 | P33: =+P29-P31 -> 2.7645639e+08 | Q33: =+Q29-Q31 -> 97524404 | ... S33: =+S29-S31 -> 8785429.3 | U33: =SUM(I33:T33) -> 5.8869996e+09 | W33: =' WP II-I-1.4'!$L$33-F33 -> 0 | X33: =U33-F33 -> 0
B34: =B33+1 -> 20 | X34: =U34-F34 -> 0
B35: =B34+1 -> 21 | X35: =U35-F35 -> 0
B36: =B35+1 -> 22 | X36: =U36-F36 -> 0
B37: =B36+1 -> 23 | D37: PROPOSED Revenue | F37: =F33 -> 5.8869996e+09 | J37: =J33 -> 2.8988097e+09 | K37: =K33 -> 92864834 | L37: =L33 -> 1.9420354e+09 | M37: =M33 -> 4521283.9 | N37: =N33 -> 4.6439458e+08 | O37: =O33 -> 99663191 | P37: =P33 -> 2.7645639e+08 | Q37: =Q33 -> 97524404 | ... S37: =S33 -> 8785429.3 | U37: =SUM(I37:T37) -> 5.8869996e+09 | X37: =U37-F37 -> 0
B38: =B37+1 -> 24 | X38: =U38-F38 -> 0
B39: =B38+1 -> 25 | D39: PROPOSED Revenue Excl 565 & RCE A928 | F39: =+F37-F645-('II-I-DIST'!F776*('WP II-I-2.2'!$P$45)) -> 3.7861581e+09 | J39: =+J37-J645-('II-I-DIST'!J776*('WP II-I-2.2'!$P$45)) -> 1.9774047e+09 | K39: =+K37-K645-('II-I-DIST'!K776*('WP II-I-2.2'!$P$45)) -> 74289957 | L39: =+L37-L645-('II-I-DIST'!L776*('WP II-I-2.2'!$P$45)) -> 1.3005759e+09 | M39: =+M37-M645-('II-I-DIST'!M776*('WP II-I-2.2'!$P$45)) -> 4318354.5 | N39: =+N37-N645-('II-I-DIST'!N776*('WP II-I-2.2'!$P$45)) -> 2.6494516e+08 | O39: =+O37-O645-('II-I-DIST'!O776*('WP II-I-2.2'!$P$45)) -> 27255096 | P39: =+P37-P645-('II-I-DIST'!P776*('WP II-I-2.2'!$P$45)) -> 29114744 | Q39: =+Q37-Q645-('II-I-DIST'!Q776*('WP II-I-2.2'!$P$45)) -> 97524404 | ... S39: =+S37-S645-('II-I-DIST'!S776*('WP II-I-2.2'!$P$45)) -> 8785429.3 | U39: =SUM(I39:T39) -> 3.7861581e+09 | W39: ='II-I-DIST'!$J$39+'II-I-MET'!$J$33+'II-I-TBILLTDCS'!$J$33-J39 -> 0 | X39: =U39-F39 -> 0
X40: =U40-F40 -> 0
B42: =+$B$4 -> 2025 RATE CASE | X42: =U42-F42 -> 0
B43: =+$B$5 -> ONCOR ELECTRIC DELIVERY COMPANY LLC | X43: =U43-F43 -> 0
B44: =+$B$6 -> II-I-1-TOT: CLASS REVENUE REQUIREMENT | X44: =U44-F44 -> 0
B45: =+$B$7 -> TEST YEAR ENDING 12/31/2024 | X45: =U45-F45 -> 0
B46: =+$B$8 -> SPONSOR: MATTHEW A. TROXLE | X46: =U46-F46 -> 0
X47: =U47-F47 -> 0
R48: =R$10 | X48: =U48-F48 -> 0
B49: Line | D49: II-B by Rate Class | E49: Source | F49: =F$11 -> TOTAL | J49: Residential | K49: Secondary | L49: Secondary | M49: Primary | N49: Primary | O49: Primary | P49: Transmission | Q49: Lighting | R49: =R$11 -> Wholesale | S49: =S$11 -> Wholesale | U49: Total
F50: =F$12 -> (Dist+Met+Cust) | K50: <=10 kW | L50: > 10 kW | M50: <=10 kW | N50: > 10 kW | O50: Substation | R50: =R$12 -> XFMR | S50: =S$12 -> DLS
F51: (a) | G51: (b) | H51: (c) | J51: =J$13 -> (d) | K51: =K$13 -> (e) | L51: =L$13 -> (f) | M51: =M$13 -> (g) | N51: =N$13 -> (h) | O51: =O$13 -> (i) | P51: =P$13 -> (j) | Q51: =Q$13 -> (k) | ... S51: =S$13 -> (m) | U51: (n)
X52: =U52-F52 -> 0
B53: =B52+1 -> 1 | D53: Intangible Plant: Original Cost | E53: II-B-1 | F53: =F106 -> 9115470 | J53: =J106 -> 4957951 | K53: =K106 -> 158613 | L53: =L106 -> 3135542.8 | M53: =M106 -> 6482.1356 | N53: =N106 -> 611676.51 | O53: =O106 -> 67863.147 | P53: =P106 -> 14154.974 | Q53: =Q106 -> 136219.82 | ... S53: =S106 -> 22217.432 | U53: =SUM(I53:T53) -> 9115470 | X53: =U53-F53 -> 0
B54: =B53+1 -> 2 | D54: Transmission Plant: Original Cost | E54: II-B-1 | F54: =F121 -> 4.6897613e+08 | J54: =J121 -> 2.4047525e+08 | K54: =K121 -> 4543218.9 | L54: =L121 -> 1.5445827e+08 | M54: =M121 -> 72277.313 | N54: =N121 -> 45432585 | O54: =O121 -> 19527819 | P54: =P121 -> 0 | Q54: =Q121 -> 1373608.1 | ... S54: =S121 -> 1743259.7 | U54: =SUM(I54:T54) -> 4.6897613e+08 | X54: =U54-F54 -> 0
B55: =B54+1 -> 3 | D55: Distribution Plant: Original Cost | E55: II-B-1 | F55: =F159 -> 2.0558061e+10 | J55: =J159 -> 1.1023958e+10 | K55: =K159 -> 4.2342169e+08 | L55: =L159 -> 6.919004e+09 | M55: =M159 -> 15187104 | N55: =N159 -> 1.2839912e+09 | O55: =O159 -> 1.1693275e+08 | P55: =P159 -> 30093185 | Q55: =Q159 -> 6.9097336e+08 | ... S55: =S159 -> 46278023 | U55: =SUM(I55:T55) -> 2.0558061e+10 | X55: =U55-F55 -> 0
B56: =B55+1 -> 4 | D56: Intangible, Transmission, Distribution Plant: Original Cost | F56: =SUM(F53:F55) -> 2.1036153e+10 | J56: =SUM(J53:J55) -> 1.1269391e+10 | K56: =SUM(K53:K55) -> 4.2812352e+08 | L56: =SUM(L53:L55) -> 7.0765978e+09 | M56: =SUM(M53:M55) -> 15265864 | N56: =SUM(N53:N55) -> 1.3300355e+09 | O56: =SUM(O53:O55) -> 1.3652844e+08 | P56: =SUM(P53:P55) -> 30107340 | Q56: =SUM(Q53:Q55) -> 6.9248318e+08 | ... S56: =SUM(S53:S55) -> 48043500 | U56: =SUM(I56:T56) -> 2.1036153e+10 | W56: =' WP II-I-1.4'!$L$56=F56 -> TRUE | X56: =U56-F56 -> 0
B57: =B56+1 -> 5 | X57: =U57-F57 -> 0
B58: =B57+1 -> 6 | D58: General Plant: Original Cost | E58: II-B-2 | F58: =+F199 -> 3.9691105e+08 | J58: =+J199 -> 2.1432601e+08 | K58: =+K199 -> 9594975.4 | L58: =+L199 -> 1.3344865e+08 | M58: =+M199 -> 833500.68 | N58: =+N199 -> 27830698 | O58: =+O199 -> 2734915 | P58: =+P199 -> 848578.81 | Q58: =+Q199 -> 6207935.1 | ... S58: =+S199 -> 888402.79 | U58: =SUM(I58:T58) -> 3.9691105e+08 | X58: =U58-F58 -> 0
B59: =B58+1 -> 7 | D59: Communication Equipment: Original Cost | E59: II-B-3 | F59: =+F219 -> 3.9882321e+08 | J59: =+J219 -> 2.1411145e+08 | K59: =+K219 -> 10485671 | L59: =+L219 -> 1.3254243e+08 | M59: =+M219 -> 1012880.7 | N59: =+N219 -> 28236109 | O59: =+O219 -> 2665267.6 | P59: =+P219 -> 924409.76 | Q59: =+Q219 -> 7787190.3 | ... S59: =+S219 -> 863337.21 | U59: =SUM(I59:T59) -> 3.9882321e+08 | X59: =U59-F59 -> 0
B60: =B59+1 -> 8 | D60: Total Plant | F60: =+F56+F58+F59 -> 2.1831887e+10 | J60: =+J56+J58+J59 -> 1.1697829e+10 | K60: =+K56+K58+K59 -> 4.4820417e+08 | L60: =+L56+L58+L59 -> 7.3425889e+09 | M60: =+M56+M58+M59 -> 17112245 | N60: =+N56+N58+N59 -> 1.3861023e+09 | O60: =+O56+O58+O59 -> 1.4192862e+08 | P60: =+P56+P58+P59 -> 31880329 | Q60: =+Q56+Q58+Q59 -> 7.0647831e+08 | ... S60: =+S56+S58+S59 -> 49795240 | U60: =SUM(I60:T60) -> 2.1831887e+10 | W60: =' WP II-I-1.4'!$L$60=F60 -> TRUE | X60: =U60-F60 -> 0
B61: =B60+1 -> 9 | X61: =U61-F61 -> 0
B62: =B61+1 -> 10 | D62: Minus: Accumulated Depreciation | E62: II-B-5 | F62: =+F363+F320 -> 7.081255e+09 | J62: =+J363+J320 -> 3.674719e+09 | K62: =+K363+K320 -> 1.9528679e+08 | L62: =+L363+L320 -> 2.265901e+09 | M62: =+M363+M320 -> 7385852.9 | N62: =+N363+N320 -> 3.9823434e+08 | O62: =+O363+O320 -> 31842026 | P62: =+P363+P320 -> 9301864.6 | Q62: =+Q363+Q320 -> 4.8256688e+08 | ... S62: =+S363+S320 -> 13744838 | U62: =SUM(I62:T62) -> 7.081255e+09 | X62: =U62-F62 -> 0
B63: =B62+1 -> 11 | X63: =U63-F63 -> 0
B64: =B63+1 -> 12 | D64: NET PLANT IN SERVICE | F64: =+F60-F62 -> 1.4750632e+10 | J64: =+J60-J62 -> 8.0231096e+09 | K64: =+K60-K62 -> 2.5291738e+08 | L64: =+L60-L62 -> 5.076688e+09 | M64: =+M60-M62 -> 9726392.1 | N64: =+N60-N62 -> 9.8786794e+08 | O64: =+O60-O62 -> 1.1008659e+08 | P64: =+P60-P62 -> 22578464 | Q64: =+Q60-Q62 -> 2.2391143e+08 | ... S64: =+S60-S62 -> 36050401 | U64: =SUM(I64:T64) -> 1.4750632e+10 | W64: =' WP II-I-1.4'!$L$64=F64 -> TRUE | X64: =U64-F64 -> 0
B65: =B64+1 -> 13 | X65: =U65-F65 -> 0
B66: =B65+1 -> 14 | D66: Other Rate Base Items: | X66: =U66-F66 -> 0
B67: =B66+1 -> 15 | X67: =U67-F67 -> 0
B68: =B67+1 -> 16 | D68: CWIP | E68: II-B-4 | F68: =+F244 -> 0 | J68: =+J244 -> 0 | K68: =+K244 -> 0 | L68: =+L244 -> 0 | M68: =+M244 -> 0 | N68: =+N244 -> 0 | O68: =+O244 -> 0 | P68: =+P244 -> 0 | Q68: =+Q244 -> 0 | ... S68: =+S244 -> 0 | U68: =SUM(I68:T68) -> 0 | X68: =U68-F68 -> 0
B69: =B68+1 -> 17 | D69: Plant Held for Future Use | E69: II-B-6 | F69: =+F388 -> 6705448.4 | J69: =+J388 -> 3438329.3 | K69: =+K388 -> 64959.212 | L69: =+L388 -> 2208453.5 | M69: =+M388 -> 1033.4253 | N69: =+N388 -> 649597.79 | O69: =+O388 -> 279209.92 | P69: =+P388 -> 0 | Q69: =+Q388 -> 19639.929 | ... S69: =+S388 -> 24925.23 | U69: =SUM(I69:T69) -> 6705448.4 | X69: =U69-F69 -> 0
B70: =B69+1 -> 18 | D70: Accumulated Provisions ex ADFIT | E70: II-B-7 | F70: =F409 -> 0 | J70: =J409 -> 0 | K70: =K409 -> 0 | L70: =L409 -> 0 | M70: =M409 -> 0 | N70: =N409 -> 0 | O70: =O409 -> 0 | P70: =P409 -> 0 | Q70: =Q409 -> 0 | ... S70: =S409 -> 0 | U70: =SUM(I70:T70) -> 0 | X70: =U70-F70 -> 0
B71: =B70+1 -> 19 | D71: Materials & Supplies | E71: II-B-8 | F71: =+F435 -> 1.5919987e+08 | J71: =+J435 -> 85510298 | K71: =+K435 -> 2832719.6 | L71: =+L435 -> 54015093 | M71: =+M435 -> 30582.509 | N71: =+N435 -> 9872374.8 | O71: =+O435 -> 1064923.1 | P71: =+P435 -> 191765.99 | Q71: =+Q435 -> 5232916.7 | ... S71: =+S435 -> 375422.16 | U71: =SUM(I71:T71) -> 1.5919987e+08 | X71: =U71-F71 -> 0
B72: =B71+1 -> 20 | D72: Cash Working Capital | E72: II-B-9 | F72: =+F455 -> -25736513 | J72: =+J455 -> -11623098 | K72: =+K455 -> -247303.79 | L72: =+L455 -> -7968317.6 | M72: =+M455 -> -5616.4464 | N72: =+N455 -> -2404033.2 | O72: =+O455 -> -783650.22 | P72: =+P455 -> -2569600 | Q72: =+Q455 -> -120596.54 | ... S72: =+S455 -> -12081.943 | U72: =SUM(I72:T72) -> -25736513 | X72: =U72-F72 -> 0
B73: =B72+1 -> 21 | D73: Prepayments | E73: II-B-10 | F73: =+F476 -> 1.288574e+08 | J73: =+J476 -> 50522241 | K73: =+K476 -> 1530621 | L73: =+L476 -> 53794289 | M73: =+M476 -> 1035.7463 | N73: =+N476 -> 8907478.9 | O73: =+O476 -> 1697928.2 | P73: =+P476 -> 11710507 | Q73: =+Q476 -> 413390.56 | ... S73: =+S476 -> 151491.83 | U73: =SUM(I73:T73) -> 1.288574e+08 | X73: =U73-F73 -> 0
B74: =B73+1 -> 22 | D74: Misc Other Rate Base | E74: II-B-11 | F74: =F499 -> -2280492.1 | J74: =J499 -> -1014812 | K74: =K499 -> -19172.505 | L74: =L499 -> -651818.01 | M74: =M499 -> -305.01219 | N74: =N499 -> -191726.72 | O74: =O499 -> -82407.919 | P74: =P499 -> -301400.33 | Q74: =Q499 -> -5796.6626 | ... S74: =S499 -> -7356.6023 | U74: =SUM(I74:T74) -> -2280492.1 | X74: =U74-F74 -> 0
B75: =B74+1 -> 23 | D75: Regulatory Assets | E75: II-B-12 | F75: =F614 -> 6.5976005e+08 | J75: =J614 -> 3.5376687e+08 | K75: =K614 -> 13293652 | L75: =L614 -> 2.2228858e+08 | M75: =M614 -> 470448.24 | N75: =N614 -> 42036339 | O75: =O614 -> 4352338.3 | P75: =P614 -> 943455.1 | Q75: =Q614 -> 20855542 | ... S75: =S614 -> 1461266.4 | U75: =SUM(I75:T75) -> 6.5976005e+08 | X75: =U75-F75 -> 0
B76: =B75+1 -> 24 | D76: Accumulated Deferred Income Taxes | E76: II-E3.7 | F76: =+F413 -> -1.4983248e+09 | J76: =+J413 -> -8.02478e+08 | K76: =+K413 -> -29351818 | L76: =+L413 -> -5.0466555e+08 | M76: =+M413 -> -874492.35 | N76: =+N413 -> -94239023 | O76: =+O413 -> -9820655.3 | P76: =+P413 -> -2055719 | Q76: =+Q413 -> -50701766 | ... S76: =+S413 -> -3451238.8 | U76: =SUM(I76:T76) -> -1.4983248e+09 | X76: =U76-F76 -> 0
B77: =B76+1 -> 25 | D77: Subtotal | F77: =SUM(F68:F76) -> -5.7181901e+08 | J77: =SUM(J68:J76) -> -3.2187817e+08 | K77: =SUM(K68:K76) -> -11896343 | L77: =SUM(L68:L76) -> -1.8097927e+08 | M77: =SUM(M68:M76) -> -377313.89 | N77: =SUM(N68:N76) -> -35368991 | O77: =SUM(O68:O76) -> -3292313.9 | P77: =SUM(P68:P76) -> 7919008.9 | Q77: =SUM(Q68:Q76) -> -24306670 | ... S77: =SUM(S68:S76) -> -1457571.7 | U77: =SUM(I77:T77) -> -5.7181901e+08 | X77: =U77-F77 -> 0
B78: =B77+1 -> 26 | X78: =U78-F78 -> 0
B79: =B78+1 -> 27 | D79: TOTAL RATE BASE | F79: =+F64+F77 -> 1.4178813e+10 | J79: =+J64+J77 -> 7.7012314e+09 | K79: =+K64+K77 -> 2.4102104e+08 | L79: =+L64+L77 -> 4.8957087e+09 | M79: =+M64+M77 -> 9349078.2 | N79: =+N64+N77 -> 9.5249895e+08 | O79: =+O64+O77 -> 1.0679428e+08 | P79: =+P64+P77 -> 30497473 | Q79: =+Q64+Q77 -> 1.9960476e+08 | ... S79: =+S64+S77 -> 34592830 | U79: =SUM(I79:T79) -> 1.4178813e+10 | W79: =' WP II-I-1.4'!$L$79-ROUND(F79,0) -> -0.44621849 | X79: =U79-F79 -> 0
B80: =B79+1 -> 28 | X80: =U80-F80 -> 0
B81: =B80+1 -> 29 | D81: COST-BASED Rate of Return | F81: =F620 -> 0.0747 | J81: =J620 -> 0.0747 | K81: =K620 -> 0.0747 | L81: =L620 -> 0.0747 | M81: =M620 -> 0.0747 | N81: =N620 -> 0.0747 | O81: =O620 -> 0.0747 | P81: =P620 -> 0.0747 | Q81: =Q620 -> 0.0747 | ... S81: =S620 -> 0.0747 | U81: =U83/U79 -> 0.0747 | X81: =U81-F81 -> 0
B82: =B81+1 -> 30 | X82: =U82-F82 -> 0
B83: =B82+1 -> 31 | D83: COST-BASED Return On Rate Base | F83: =+F79*F81 -> 1.0591573e+09 | J83: =+J79*J81 -> 5.7528199e+08 | K83: =+K79*K81 -> 18004272 | L83: =+L79*L81 -> 3.6570944e+08 | M83: =+M79*M81 -> 698376.14 | N83: =+N79*N81 -> 71151671 | O83: =+O79*O81 -> 7977532.6 | P83: =+P79*P81 -> 2278161.3 | Q83: =+Q79*Q81 -> 14910476 | ... S83: =+S79*S81 -> 2584084.4 | U83: =SUM(I83:T83) -> 1.0591573e+09 | W83: =' WP II-I-1.4'!$L$83=F83 -> TRUE | X83: =U83-F83 -> 0
B84: =B83+1 -> 32 | X84: =U84-F84 -> 0
B85: =B84+1 -> 33 | X85: =U85-F85 -> 0
B86: =B85+1 -> 34 | X86: =U86-F86 -> 0
B87: =B86+1 -> 35 | D87: PROPOSED Return On Rate Base | F87: =F83 -> 1.0591573e+09 | J87: =J83 -> 5.7528199e+08 | K87: =K83 -> 18004272 | L87: =L83 -> 3.6570944e+08 | M87: =M83 -> 698376.14 | N87: =N83 -> 71151671 | O87: =O83 -> 7977532.6 | P87: =P83 -> 2278161.3 | Q87: =Q83 -> 14910476 | ... S87: =S83 -> 2584084.4 | U87: =SUM(I87:T87) -> 1.0591573e+09 | X87: =U87-F87 -> 0
B88: =B87+1 -> 36 | X88: =U88-F88 -> 0
B89: =B88+1 -> 37 | D89: PROPOSED Rate Of Return | F89: =F87/F79 -> 0.0747 | J89: =J87/J79 -> 0.0747 | K89: =K87/K79 -> 0.0747 | L89: =L87/L79 -> 0.0747 | M89: =M87/M79 -> 0.0747 | N89: =N87/N79 -> 0.0747 | O89: =O87/O79 -> 0.0747 | P89: =P87/P79 -> 0.0747 | Q89: =Q87/Q79 -> 0.0747 | ... S89: =S87/S79 -> 0.0747 | U89: =U87/U79 -> 0.0747 | W89: =' WP II-I-1.4'!$L$81=F89 -> TRUE | X89: =U89-F89 -> 0
X90: =U90-F90 -> 0
B91: =+$B$4 -> 2025 RATE CASE
B92: =+$B$5 -> ONCOR ELECTRIC DELIVERY COMPANY LLC | X92: =U92-F92 -> 0
B93: =+$B$6 -> II-I-1-TOT: CLASS REVENUE REQUIREMENT | X93: =U93-F93 -> 0
B94: =+$B$7 -> TEST YEAR ENDING 12/31/2024 | X94: =U94-F94 -> 0
B95: =+$B$8 -> SPONSOR: MATTHEW A. TROXLE | X95: =U95-F95 -> 0
X96: =U96-F96 -> 0
R97: =R$10 | X97: =U97-F97 -> 0
B98: Line | C98: Acct | D98: Intangible and Transmission Plant Gross | E98: Source | F98: =F$11 -> TOTAL | G98: Alloc | H98: Allocation | J98: Residential | K98: Secondary | L98: Secondary | M98: Primary | N98: Primary | O98: Primary | P98: Transmission | Q98: Lighting | R98: =R$11 -> Wholesale | S98: =S$11 -> Wholesale | U98: Total
F99: =F$12 -> (Dist+Met+Cust) | G99: # | H99: Factor | K99: <=10 kW | L99: > 10 kW | M99: <=10 kW | N99: > 10 kW | O99: Substation | R99: =R$12 -> XFMR | S99: =S$12 -> DLS
F100: (a) | G100: (b) | H100: (c) | J100: =J$13 -> (d) | K100: =K$13 -> (e) | L100: =L$13 -> (f) | M100: =M$13 -> (g) | N100: =N$13 -> (h) | O100: =O$13 -> (i) | P100: =P$13 -> (j) | Q100: =Q$13 -> (k) | ... S100: =S$13 -> (m) | U100: (n)
X101: =U101-F101 -> 0
B102: =B101+1 -> 1 | C102: Intangible Plant Gross | E102: II-B-1 | X102: =U102-F102 -> 0
B103: =B102+1 -> 2 | C103: A301 | D103: Organization | F103: =' WP II-I-1.4'!L103 -> 0 | G103: N / A | H103: see functions | J103: ='II-I-DIST'!J103+'II-I-MET'!J103+'II-I-TBILLTDCS'!J103 -> 0 | K103: ='II-I-DIST'!K103+'II-I-MET'!K103+'II-I-TBILLTDCS'!K103 -> 0 | L103: ='II-I-DIST'!L103+'II-I-MET'!L103+'II-I-TBILLTDCS'!L103 -> 0 | M103: ='II-I-DIST'!M103+'II-I-MET'!M103+'II-I-TBILLTDCS'!M103 -> 0 | N103: ='II-I-DIST'!N103+'II-I-MET'!N103+'II-I-TBILLTDCS'!N103 -> 0 | O103: ='II-I-DIST'!O103+'II-I-MET'!O103+'II-I-TBILLTDCS'!O103 -> 0 | P103: ='II-I-DIST'!P103+'II-I-MET'!P103+'II-I-TBILLTDCS'!P103 -> 0 | Q103: ='II-I-DIST'!Q103+'II-I-MET'!Q103+'II-I-TBILLTDCS'!Q103 -> 0 | ... S103: ='II-I-DIST'!S103+'II-I-MET'!S103+'II-I-TBILLTDCS'!S103 -> 0 | U103: =SUM(I103:T103) -> 0 | X103: =U103-F103 -> 0
B104: =B103+1 -> 3 | C104: A302 | D104: Franchise & Consents | F104: =' WP II-I-1.4'!L104 -> 0 | G104: N / A | H104: see functions | J104: ='II-I-DIST'!J104+'II-I-MET'!J104+'II-I-TBILLTDCS'!J104 -> 0 | K104: ='II-I-DIST'!K104+'II-I-MET'!K104+'II-I-TBILLTDCS'!K104 -> 0 | L104: ='II-I-DIST'!L104+'II-I-MET'!L104+'II-I-TBILLTDCS'!L104 -> 0 | M104: ='II-I-DIST'!M104+'II-I-MET'!M104+'II-I-TBILLTDCS'!M104 -> 0 | N104: ='II-I-DIST'!N104+'II-I-MET'!N104+'II-I-TBILLTDCS'!N104 -> 0 | O104: ='II-I-DIST'!O104+'II-I-MET'!O104+'II-I-TBILLTDCS'!O104 -> 0 | P104: ='II-I-DIST'!P104+'II-I-MET'!P104+'II-I-TBILLTDCS'!P104 -> 0 | Q104: ='II-I-DIST'!Q104+'II-I-MET'!Q104+'II-I-TBILLTDCS'!Q104 -> 0 | ... S104: ='II-I-DIST'!S104+'II-I-MET'!S104+'II-I-TBILLTDCS'!S104 -> 0 | U104: =SUM(I104:T104) -> 0 | X104: =U104-F104 -> 0
B105: =B104+1 -> 4 | C105: A303 | D105: Miscellaneous Intangible Plant | F105: =' WP II-I-1.4'!L105 -> 9115470 | G105: N / A | H105: see functions | J105: ='II-I-DIST'!J105+'II-I-MET'!J105+'II-I-TBILLTDCS'!J105 -> 4957951 | K105: ='II-I-DIST'!K105+'II-I-MET'!K105+'II-I-TBILLTDCS'!K105 -> 158613 | L105: ='II-I-DIST'!L105+'II-I-MET'!L105+'II-I-TBILLTDCS'!L105 -> 3135542.8 | M105: ='II-I-DIST'!M105+'II-I-MET'!M105+'II-I-TBILLTDCS'!M105 -> 6482.1356 | N105: ='II-I-DIST'!N105+'II-I-MET'!N105+'II-I-TBILLTDCS'!N105 -> 611676.51 | O105: ='II-I-DIST'!O105+'II-I-MET'!O105+'II-I-TBILLTDCS'!O105 -> 67863.147 | P105: ='II-I-DIST'!P105+'II-I-MET'!P105+'II-I-TBILLTDCS'!P105 -> 14154.974 | Q105: ='II-I-DIST'!Q105+'II-I-MET'!Q105+'II-I-TBILLTDCS'!Q105 -> 136219.82 | ... S105: ='II-I-DIST'!S105+'II-I-MET'!S105+'II-I-TBILLTDCS'!S105 -> 22217.432 | U105: =SUM(I105:T105) -> 9115470 | X105: =U105-F105 -> 0
B106: =B105+1 -> 5 | D106: Subtotal | F106: =SUM(F103:F105) -> 9115470 | J106: =SUM(J103:J105) -> 4957951 | K106: =SUM(K103:K105) -> 158613 | L106: =SUM(L103:L105) -> 3135542.8 | M106: =SUM(M103:M105) -> 6482.1356 | N106: =SUM(N103:N105) -> 611676.51 | O106: =SUM(O103:O105) -> 67863.147 | P106: =SUM(P103:P105) -> 14154.974 | Q106: =SUM(Q103:Q105) -> 136219.82 | ... S106: =SUM(S103:S105) -> 22217.432 | U106: =SUM(I106:T106) -> 9115470 | W106: =' WP II-I-1.4'!$L$106=F106 -> TRUE | X106: =U106-F106 -> 0
...

Sheet II-I-2.1f
B4: ='WP II-I-1.1'!B3 -> 2025 RATE CASE
B5: ='WP II-I-1.1'!B4 -> ONCOR ELECTRIC DELIVERY COMPANY LLC
B6: II-I-2.1f: CONSOLIDATED FUNCTIONALIZED COST OF SERVICE
B7: ='WP II-I-1.1'!B6 -> TEST YEAR ENDING 12/31/2024
B8: ='WP II-I-2.2'!$B$7 -> SPONSOR: MATTHEW A. TROXLE
B11: Line | D11: Revenue Requirement | E11: Source | F11: ='II-I-DIST'!F11 -> DIST | H11: ='II-I-MET'!F11 -> MET | J11: ='II-I-TBILLTDCS'!F11 -> TBILLTDCS | L11: TOTAL | M11: RATIONALE FOR CLASSIFICATION
L12: (Dist+Met+Cust) | O12: checks:
F13: ='II-I-DIST'!F13 -> (a) | H13: ='II-I-MET'!F13 -> (a) | J13: ='II-I-TBILLTDCS'!F13 -> (a) | L13: (g) | M13: (h)
B15: =B14+1 -> 1 | D15: O&M Expenses | E15: II-D-2 | F15: ='II-I-DIST'!F15 -> 2.4658459e+09 | H15: ='II-I-MET'!F15 -> 61551893 | J15: ='II-I-TBILLTDCS'!F15 -> 189681.03 | L15: =F15+H15+J15 -> 2.5275875e+09 | M15: See detail
B16: =B15+1 -> 2 | D16: Customer Expenses | E16: II-D-2 | F16: ='II-I-DIST'!F16 -> 339790.12 | H16: ='II-I-MET'!F16 -> 9809696.2 | J16: ='II-I-TBILLTDCS'!F16 -> 17097126 | L16: =F16+H16+J16 -> 27246613 | M16: See detail
B17: =B16+1 -> 3 | D17: A&G Expenses | E17: II-D-2 | F17: ='II-I-DIST'!F17 -> 8.6225408e+08 | H17: ='II-I-MET'!F17 -> 49056190 | J17: ='II-I-TBILLTDCS'!F17 -> 40849532 | L17: =F17+H17+J17 -> 9.521598e+08 | M17: See detail
B18: =B17+1 -> 4 | D18: O&M + Customer + A&G Expenses | F18: ='II-I-DIST'!F18 -> 3.3284398e+09 | H18: ='II-I-MET'!F18 -> 1.2041778e+08 | J18: ='II-I-TBILLTDCS'!F18 -> 58136339 | L18: =F18+H18+J18 -> 3.5069939e+09 | O18: ='II-I-DIST'!$F$18=F18 -> TRUE | P18: ='II-I-MET'!$F$18=H18 -> TRUE | Q18: ='II-I-TBILLTDCS'!$F$18=J18 -> TRUE
B19: =B18+1 -> 5 | F19: ='II-I-DIST'!F19 -> 0 | H19: ='II-I-MET'!F19 -> 0 | J19: ='II-I-TBILLTDCS'!F19 -> 0
B20: =B19+1 -> 6 | D20: Depreciation & Amortization (II-E-1) | E20: II-E-1 | F20: ='II-I-DIST'!F20 -> 6.5141705e+08 | H20: ='II-I-MET'!F20 -> 29837696 | J20: ='II-I-TBILLTDCS'!F20 -> 39993574 | L20: =F20+H20+J20 -> 7.2124832e+08 | M20: See detail
B21: =B20+1 -> 7 | D21: Other (II-E-4) | E21: II-E-4 | F21: ='II-I-DIST'!F21 -> 15428626 | H21: ='II-I-MET'!F21 -> 25459958 | J21: ='II-I-TBILLTDCS'!F21 -> 0 | L21: =F21+H21+J21 -> 40888584 | M21: See detail
B22: =B21+1 -> 8 | D22: Depreciation, Amortization & Other Expenses | F22: ='II-I-DIST'!F22 -> 6.6684568e+08 | H22: ='II-I-MET'!F22 -> 55297654 | J22: ='II-I-TBILLTDCS'!F22 -> 39993574 | L22: =F22+H22+J22 -> 7.6213691e+08 | O22: ='II-I-DIST'!$F$22=F22 -> TRUE | P22: ='II-I-MET'!$F$22=H22 -> TRUE | Q22: ='II-I-TBILLTDCS'!$F$22=J22 -> TRUE
B23: =B22+1 -> 9 | F23: ='II-I-DIST'!F23 -> 0 | H23: ='II-I-MET'!F23 -> 0 | J23: ='II-I-TBILLTDCS'!F23 -> 0
B24: =B23+1 -> 10 | D24: Taxes Other Than Federal Income Tax | E24: II-E-2 | F24: ='II-I-DIST'!F24 -> 4.8252028e+08 | H24: ='II-I-MET'!F24 -> 8908968.6 | J24: ='II-I-TBILLTDCS'!F24 -> 3557512.7 | L24: =F24+H24+J24 -> 4.9498676e+08 | M24: See detail
B25: =B24+1 -> 11 | D25: Federal Income Tax | E25: II-E-3 | F25: ='II-I-DIST'!F25 -> 1.4008147e+08 | H25: ='II-I-MET'!F25 -> 1780846.8 | J25: ='II-I-TBILLTDCS'!F25 -> 2876698.2 | L25: =F25+H25+J25 -> 1.4473902e+08 | M25: See detail
B26: =B25+1 -> 12 | F26: ='II-I-DIST'!F26 -> 0 | H26: ='II-I-MET'!F26 -> 0 | J26: ='II-I-TBILLTDCS'!F26 -> 0
B27: =B26+1 -> 13 | D27: Return on Rate Base | E27: II-B | F27: ='II-I-DIST'!F27 -> 1.0090184e+09 | H27: ='II-I-MET'!F27 -> 32952956 | J27: ='II-I-TBILLTDCS'!F27 -> 17186005 | L27: =F27+H27+J27 -> 1.0591573e+09 | M27: See detail | O27: ='II-I-DIST'!$F$27=F27 -> TRUE | P27: ='II-I-MET'!$F$27=H27 -> TRUE | Q27: ='II-I-TBILLTDCS'!$F$27=J27 -> TRUE
B28: =B27+1 -> 14
B29: =B28+1 -> 15 | D29: TOTAL COST OF SERVICE | F29: ='II-I-DIST'!F29 -> 5.6269056e+09 | H29: ='II-I-MET'!F29 -> 2.193582e+08 | J29: ='II-I-TBILLTDCS'!F29 -> 1.2175013e+08 | L29: =F29+H29+J29 -> 5.9680139e+09 | O29: ='II-I-DIST'!$F$29=F29 -> TRUE | P29: ='II-I-MET'!$F$29=H29 -> TRUE | Q29: ='II-I-TBILLTDCS'!$F$29=J29 -> TRUE
B30: =B29+1 -> 16
B31: =B30+1 -> 17 | D31: Minus: Other Revenues | E31: II-E-5 | F31: ='II-I-DIST'!F31 -> 66812956 | H31: ='II-I-MET'!F31 -> 14115591 | J31: ='II-I-TBILLTDCS'!F31 -> 85782 | L31: =F31+H31+J31 -> 81014329 | M31: See detail | O31: ='II-I-DIST'!$F$31=F31 -> TRUE | P31: ='II-I-MET'!$F$31=H31 -> TRUE | Q31: ='II-I-TBILLTDCS'!$F$31=J31 -> TRUE
B32: =B31+1 -> 18
B33: =B32+1 -> 19 | D33: COST-BASED Revenue Requirement | F33: ='II-I-DIST'!F33 -> 5.5600926e+09 | H33: ='II-I-MET'!F33 -> 2.0524261e+08 | J33: ='II-I-TBILLTDCS'!F33 -> 1.2166435e+08 | L33: =F33+H33+J33 -> 5.8869996e+09 | O33: ='II-I-DIST'!$F$33=F33 -> TRUE | P33: ='II-I-MET'!$F$33=H33 -> TRUE | Q33: ='II-I-TBILLTDCS'!$F$33=J33 -> TRUE
B42: =$B$4 -> 2025 RATE CASE
B43: =$B$5 -> ONCOR ELECTRIC DELIVERY COMPANY LLC
B44: =$B$6 -> II-I-2.1f: CONSOLIDATED FUNCTIONALIZED COST OF SERVICE
B45: =$B$7 -> TEST YEAR ENDING 12/31/2024
B46: =$B$8 -> SPONSOR: MATTHEW A. TROXLE
B49: Line | D49: Return On Rate Base | E49: Source | F49: ='II-I-DIST'!F49 -> DIST | H49: ='II-I-MET'!F49 -> MET | J49: ='II-I-TBILLTDCS'!F49 -> TBILLTDCS | L49: TOTAL | M49: RATIONALE FOR CLASSIFICATION
L50: (Dist+Met+Cust)
F51: ='II-I-DIST'!F51 -> (a) | H51: ='II-I-MET'!F51 -> (a) | J51: ='II-I-TBILLTDCS'!F51 -> (a) | L51: (g) | M51: (h)
B53: =B52+1 -> 1 | D53: Intangible Plant: Original Cost | E53: II-B-1 | F53: ='II-I-DIST'!F53 -> 8645784 | H53: ='II-I-MET'!F53 -> 324360 | J53: ='II-I-TBILLTDCS'!F53 -> 145326 | L53: =F53+H53+J53 -> 9115470 | M53: See detail
B54: =B53+1 -> 2 | D54: Transmission Plant: Original Cost | E54: II-B-1 | F54: ='II-I-DIST'!F54 -> 4.6897613e+08 | H54: ='II-I-MET'!F54 -> 0 | J54: ='II-I-TBILLTDCS'!F54 -> 0 | L54: =F54+H54+J54 -> 4.6897613e+08 | M54: See detail
B55: =B54+1 -> 3 | D55: Distribution Plant: Original Cost | E55: II-B-1 | F55: ='II-I-DIST'!F55 -> 1.9438204e+10 | H55: ='II-I-MET'!F55 -> 7.8498359e+08 | J55: ='II-I-TBILLTDCS'!F55 -> 3.3487324e+08 | L55: =F55+H55+J55 -> 2.0558061e+10 | M55: See detail
B56: =B55+1 -> 4 | D56: Intangible, Transmission, Distribution Plant: Original Cost | F56: ='II-I-DIST'!F56 -> 1.9915826e+10 | H56: ='II-I-MET'!F56 -> 7.8530795e+08 | J56: ='II-I-TBILLTDCS'!F56 -> 3.3501856e+08 | L56: =F56+H56+J56 -> 2.1036153e+10 | O56: ='II-I-DIST'!$F$56=F56 -> TRUE | P56: ='II-I-MET'!$F$56=H56 -> TRUE | Q56: ='II-I-TBILLTDCS'!$F$56=J56 -> TRUE
B57: =B56+1 -> 5 | F57: ='II-I-DIST'!F57 -> 0 | H57: ='II-I-MET'!F57 -> 0 | J57: ='II-I-TBILLTDCS'!F57 -> 0
B58: =B57+1 -> 6 | D58: General Plant: Original Cost | E58: II-B-2 | F58: ='II-I-DIST'!F58 -> 3.2955433e+08 | H58: ='II-I-MET'!F58 -> 45511527 | J58: ='II-I-TBILLTDCS'!F58 -> 21845189 | L58: =F58+H58+J58 -> 3.9691105e+08 | M58: See detail | O58: ='II-I-DIST'!$F$58=F58 -> TRUE | P58: ='II-I-MET'!$F$58=H58 -> TRUE | Q58: ='II-I-TBILLTDCS'!$F$58=J58 -> TRUE
B59: =B58+1 -> 7 | D59: Communication Equipment: Original Cost | E59: II-B-3 | F59: ='II-I-DIST'!F59 -> 3.1454923e+08 | H59: ='II-I-MET'!F59 -> 32909657 | J59: ='II-I-TBILLTDCS'!F59 -> 51364319 | L59: =F59+H59+J59 -> 3.9882321e+08 | M59: See detail | O59: ='II-I-DIST'!$F$59=F59 -> TRUE | P59: ='II-I-MET'!$F$59=H59 -> TRUE | Q59: ='II-I-TBILLTDCS'!$F$59=J59 -> TRUE
B60: =B59+1 -> 8 | D60: Total Plant | F60: ='II-I-DIST'!F60 -> 2.055993e+10 | H60: ='II-I-MET'!F60 -> 8.6372914e+08 | J60: ='II-I-TBILLTDCS'!F60 -> 4.0822807e+08 | L60: =F60+H60+J60 -> 2.1831887e+10 | O60: ='II-I-DIST'!$F$60=F60 -> TRUE | P60: ='II-I-MET'!$F$60=H60 -> TRUE | Q60: ='II-I-TBILLTDCS'!$F$60=J60 -> TRUE
B61: =B60+1 -> 9 | F61: ='II-I-DIST'!F61 -> 0 | H61: ='II-I-MET'!F61 -> 0 | J61: ='II-I-TBILLTDCS'!F61 -> 0
B62: =B61+1 -> 10 | D62: Minus: Accumulated Depreciation | E62: II-B-5 | F62: ='II-I-DIST'!F62 -> 6.5088395e+09 | H62: ='II-I-MET'!F62 -> 4.4259116e+08 | J62: ='II-I-TBILLTDCS'!F62 -> 1.2982432e+08 | L62: =F62+H62+J62 -> 7.081255e+09 | M62: See detail | O62: ='II-I-DIST'!$F$62=F62 -> TRUE | P62: ='II-I-MET'!$F$62=H62 -> TRUE | Q62: ='II-I-TBILLTDCS'!$F$62=J62 -> TRUE
B63: =B62+1 -> 11
B64: =B63+1 -> 12 | D64: NET PLANT IN SERVICE | F64: ='II-I-DIST'!F64 -> 1.405109e+10 | H64: ='II-I-MET'!F64 -> 4.2113798e+08 | J64: ='II-I-TBILLTDCS'!F64 -> 2.7840375e+08 | L64: =F64+H64+J64 -> 1.4750632e+10 | O64: ='II-I-DIST'!$F$64=F64 -> TRUE | P64: ='II-I-MET'!$F$64=H64 -> TRUE | Q64: ='II-I-TBILLTDCS'!$F$64=J64 -> TRUE
B65: =B64+1 -> 13
B66: =B65+1 -> 14 | D66: Other Rate Base Items:
B67: =B66+1 -> 15
B68: =B67+1 -> 16 | D68: CWIP | E68: II-B-4 | F68: ='II-I-DIST'!F68 -> 0 | H68: ='II-I-MET'!F68 -> 0 | J68: ='II-I-TBILLTDCS'!F68 -> 0 | L68: =F68+H68+J68 -> 0 | M68: See detail | O68: ='II-I-DIST'!$F$68=F68 -> TRUE | P68: ='II-I-MET'!$F$68=H68 -> TRUE | Q68: ='II-I-TBILLTDCS'!$F$68=J68 -> TRUE
B69: =B68+1 -> 17 | D69: Plant Held for Future Use | E69: II-B-6 | F69: ='II-I-DIST'!F69 -> 6705448.4 | H69: ='II-I-MET'!F69 -> 0 | J69: ='II-I-TBILLTDCS'!F69 -> 0 | L69: =F69+H69+J69 -> 6705448.4 | M69: See detail | O69: ='II-I-DIST'!$F$69=F69 -> TRUE | P69: ='II-I-MET'!$F$69=H69 -> TRUE | Q69: ='II-I-TBILLTDCS'!$F$69=J69 -> TRUE
B70: =B69+1 -> 18 | D70: Accumulated Provisions ex ADFIT | E70: II-B-7 | F70: ='II-I-DIST'!F70 -> 0 | H70: ='II-I-MET'!F70 -> 0 | J70: ='II-I-TBILLTDCS'!F70 -> 0 | L70: =F70+H70+J70 -> 0 | M70: See detail | O70: ='II-I-DIST'!$F$70=F70 -> TRUE | P70: ='II-I-MET'!$F$70=H70 -> TRUE | Q70: ='II-I-TBILLTDCS'!$F$70=J70 -> TRUE
B71: =B70+1 -> 19 | D71: Materials & Supplies | E71: II-B-8 | F71: ='II-I-DIST'!F71 -> 1.5795807e+08 | H71: ='II-I-MET'!F71 -> 1241799.5 | J71: ='II-I-TBILLTDCS'!F71 -> 0 | L71: =F71+H71+J71 -> 1.5919987e+08 | M71: See detail | O71: ='II-I-DIST'!$F$71=F71 -> TRUE | P71: ='II-I-MET'!$F$71=H71 -> TRUE | Q71: ='II-I-TBILLTDCS'!$F$71=J71 -> TRUE
B72: =B71+1 -> 20 | D72: Cash Working Capital | E72: II-B-9 | F72: ='II-I-DIST'!F72 -> -25613472 | H72: ='II-I-MET'!F72 -> -298798.52 | J72: ='II-I-TBILLTDCS'!F72 -> 175757.58 | L72: =F72+H72+J72 -> -25736513 | M72: See detail | O72: ='II-I-DIST'!$F$72=F72 -> TRUE | P72: ='II-I-MET'!$F$72=H72 -> TRUE | Q72: ='II-I-TBILLTDCS'!$F$72=J72 -> TRUE
B73: =B72+1 -> 21 | D73: Prepayments | E73: II-B-10 | F73: ='II-I-DIST'!F73 -> 1.2774296e+08 | H73: ='II-I-MET'!F73 -> 584939.39 | J73: ='II-I-TBILLTDCS'!F73 -> 529501.18 | L73: =F73+H73+J73 -> 1.288574e+08 | M73: See detail | O73: ='II-I-DIST'!$F$73=F73 -> TRUE | P73: ='II-I-MET'!$F$73=H73 -> TRUE | Q73: ='II-I-TBILLTDCS'!$F$73=J73 -> TRUE
B74: =B73+1 -> 22 | D74: Misc Other Rate Base | E74: II-B-11 | F74: ='II-I-DIST'!F74 -> -1977961.9 | H74: ='II-I-MET'!F74 -> -302530.2 | J74: ='II-I-TBILLTDCS'!F74 -> 0 | L74: =F74+H74+J74 -> -2280492.1 | M74: See detail | O74: ='II-I-DIST'!$F74=F74 -> TRUE | P74: ='II-I-MET'!$F74=H74 -> TRUE | Q74: ='II-I-TBILLTDCS'!$F$74=J74 -> TRUE
B75: =B74+1 -> 23 | D75: Regulatory Assets | E75: II-B-12 | F75: ='II-I-DIST'!F75 -> 6.260253e+08 | H75: ='II-I-MET'!F75 -> 30745550 | J75: ='II-I-TBILLTDCS'!F75 -> 2989198.3 | L75: =F75+H75+J75 -> 6.5976005e+08 | M75: See detail | O75: ='II-I-DIST'!$F$75=F75 -> TRUE | P75: ='II-I-MET'!$F$75=H75 -> TRUE | Q75: ='II-I-TBILLTDCS'!$F$75=J75 -> TRUE
B76: =B75+1 -> 24 | D76: Accumulated Deferred Income Taxes | E76: II-E3.7 | F76: ='II-I-DIST'!F76 -> -1.4343219e+09 | H76: ='II-I-MET'!F76 -> -11971648 | J76: ='II-I-TBILLTDCS'!F76 -> -52031200 | L76: =F76+H76+J76 -> -1.4983248e+09 | M76: See detail | O76: ='II-I-DIST'!$F$76=F76 -> TRUE | P76: ='II-I-MET'!$F$76=H76 -> TRUE | Q76: ='II-I-TBILLTDCS'!$F$76=J76 -> TRUE
B77: =B76+1 -> 25 | D77: Subtotal | F77: ='II-I-DIST'!F77 -> -5.4348158e+08 | H77: ='II-I-MET'!F77 -> 19999312 | J77: ='II-I-TBILLTDCS'!F77 -> -48336743 | L77: =F77+H77+J77 -> -5.7181901e+08 | O77: ='II-I-DIST'!$F$77=F77 -> TRUE | P77: ='II-I-MET'!$F$77=H77 -> TRUE | Q77: ='II-I-TBILLTDCS'!$F$77=J77 -> TRUE
B78: =B77+1 -> 26
B79: =B78+1 -> 27 | D79: TOTAL RATE BASE | F79: ='II-I-DIST'!F79 -> 1.3507609e+10 | H79: ='II-I-MET'!F79 -> 4.4113729e+08 | J79: ='II-I-TBILLTDCS'!F79 -> 2.3006701e+08 | L79: =F79+H79+J79 -> 1.4178813e+10 | O79: ='II-I-DIST'!$F$79=F79 -> TRUE | P79: ='II-I-MET'!$F$79=H79 -> TRUE | Q79: ='II-I-TBILLTDCS'!$F$79=J79 -> TRUE
B80: =B79+1 -> 28 | F80: ='II-I-DIST'!F80 -> 0 | H80: ='II-I-MET'!F80 -> 0 | J80: ='II-I-TBILLTDCS'!F80 -> 0
B81: =B80+1 -> 29 | D81: COST-BASED Rate of Return | F81: ='II-I-DIST'!F81 -> 0.0747 | H81: ='II-I-MET'!F81 -> 0.0747 | J81: ='II-I-TBILLTDCS'!F81 -> 0.0747 | L81: ='WP II-I-1.1'!$G$211 -> 0.0747 | M81: See Schedule II-C | O81: ='II-I-DIST'!$F$81=F81 -> TRUE | P81: ='II-I-MET'!$F$81=H81 -> TRUE | Q81: ='II-I-TBILLTDCS'!$F$81=J81 -> TRUE
B82: =B81+1 -> 30 | F82: ='II-I-DIST'!F82 -> 0 | H82: ='II-I-MET'!F82 -> 0 | J82: ='II-I-TBILLTDCS'!F82 -> 0
B83: =B82+1 -> 31 | D83: COST-BASED Return On Rate Base | F83: ='II-I-DIST'!F83 -> 1.0090184e+09 | H83: ='II-I-MET'!F83 -> 32952956 | J83: ='II-I-TBILLTDCS'!F83 -> 17186005 | L83: =F83+H83+J83 -> 1.0591573e+09 | O83: ='II-I-DIST'!$F$83=F83 -> TRUE | P83: ='II-I-MET'!$F$83=H83 -> TRUE | Q83: ='II-I-TBILLTDCS'!$F$83=J83 -> TRUE
B91: =$B$4 -> 2025 RATE CASE
B92: =$B$5 -> ONCOR ELECTRIC DELIVERY COMPANY LLC
B93: =$B$6 -> II-I-2.1f: CONSOLIDATED FUNCTIONALIZED COST OF SERVICE
B94: =$B$7 -> TEST YEAR ENDING 12/31/2024
B95: =$B$8 -> SPONSOR: MATTHEW A. TROXLE
B98: Line | C98: Acct | D98: Intangible and Transmission Plant Gross | E98: Source | F98: ='II-I-DIST'!F98 -> DIST | G98: ='II-I-DIST'!H98 -> Allocation | H98: ='II-I-MET'!F98 -> MET | I98: ='II-I-MET'!H98 -> Allocation | J98: ='II-I-TBILLTDCS'!F98 -> TBILLTDCS | K98: ='II-I-TBILLTDCS'!H98 -> Allocation | L98: TOTAL | M98: RATIONALE FOR CLASSIFICATION
G99: ='II-I-DIST'!H99 -> Factor | I99: ='II-I-MET'!H99 -> Factor | K99: ='II-I-TBILLTDCS'!H99 -> Factor | L99: (Dist+Met+Cust)
F100: ='II-I-DIST'!F100 -> (a) | G100: ='II-I-DIST'!H100 -> (c) | H100: ='II-I-MET'!F100 -> (a) | I100: ='II-I-MET'!H100 -> (c) | J100: ='II-I-TBILLTDCS'!F100 -> (a) | K100: ='II-I-TBILLTDCS'!H100 -> (c) | L100: (g) | M100: (h)
B102: =B101+1 -> 1 | C102: Intangible Plant Gross | E102: II-B-1
B103: =B102+1 -> 2 | C103: A301 | D103: Organization | F103: ='II-I-DIST'!F103 -> 0 | G103: ='II-I-DIST'!H103 -> PLT_N XINT | H103: ='II-I-MET'!F103 -> 0 | I103: ='II-I-MET'!H103 -> PLT_N XINT | J103: ='II-I-TBILLTDCS'!F103 -> 0 | K103: ='II-I-TBILLTDCS'!H103 -> PLT_N XINT | L103: 0 | N103: ='II-I-DIST'!$C$103=C103 -> TRUE | O103: ='II-I-DIST'!$F$103=F103 -> TRUE
B104: =B103+1 -> 3 | C104: A302 | D104: Franchise & Consents | F104: ='II-I-DIST'!F104 -> 0 | G104: ='II-I-DIST'!H104 -> PLT_N XINT | H104: ='II-I-MET'!F104 -> 0 | I104: ='II-I-MET'!H104 -> PLT_N XINT | J104: ='II-I-TBILLTDCS'!F104 -> 0 | K104: ='II-I-TBILLTDCS'!H104 -> PLT_N XINT | L104: 0 | N104: ='II-I-DIST'!$D$104=D104 -> TRUE
B105: =B104+1 -> 4 | C105: A303 | D105: Miscellaneous Intangible Plant | F105: ='II-I-DIST'!F105 -> 8645784 | G105: ='II-I-DIST'!H105 -> PLT_N XINT | H105: ='II-I-MET'!F105 -> 324360 | I105: ='II-I-MET'!H105 -> PLT_N XINT | J105: ='II-I-TBILLTDCS'!F105 -> 145326 | K105: ='II-I-TBILLTDCS'!H105 -> PLT_N XINT | L105: =F105+H105+J105 -> 9115470 | M105: Classified on a composite basis derived from all tangible plant, since intangible plant is a common cost.
B106: =B105+1 -> 5 | D106: Subtotal | F106: ='II-I-DIST'!F106 -> 8645784 | H106: ='II-I-MET'!F106 -> 324360 | J106: ='II-I-TBILLTDCS'!F106 -> 145326 | L106: =F106+H106+J106 -> 9115470 | O106: ='II-I-DIST'!$F$106=F106 -> TRUE | P106: ='II-I-MET'!$F$106=H106 -> TRUE | Q106: ='II-I-TBILLTDCS'!$F$106=J106 -> TRUE
B107: =B106+1 -> 6 | C107: Transmission Plant Gross | E107: II-B-1
B108: =B107+1 -> 7 | C108: A349 | D108: Land Owned in Fee | F108: ='II-I-DIST'!F108 -> 0 | G108: ='II-I-DIST'!H108 -> NCP XHV | H108: ='II-I-MET'!F108 -> 0 | I108: ='II-I-MET'!H108 -> NCP XHV | J108: ='II-I-TBILLTDCS'!F108 -> 0 | K108: ='II-I-TBILLTDCS'!H108 -> NCP XHV | L108: =F108+H108+J108 -> 0
B109: =B108+1 -> 8 | C109: A350 | D109: Land and Land Rights | F109: ='II-I-DIST'!F109 -> 0 | G109: ='II-I-DIST'!H109 -> NCP XHV | H109: ='II-I-MET'!F109 -> 0 | I109: ='II-I-MET'!H109 -> NCP XHV | J109: ='II-I-TBILLTDCS'!F109 -> 0 | K109: ='II-I-TBILLTDCS'!H109 -> NCP XHV | L109: =F109+H109+J109 -> 0
B110: 9 | C110: A351.1 | D110: Computer Hardware | F110: ='II-I-DIST'!F110 -> 0 | G110: ='II-I-DIST'!H110 -> PLTTRAN_N | H110: ='II-I-MET'!F110 -> 0 | I110: ='II-I-MET'!H110 -> PLTTRAN_N | J110: ='II-I-TBILLTDCS'!F110 -> 0 | K110: ='II-I-TBILLTDCS'!H110 -> PLTTRAN_N | L110: =F110+H110+J110 -> 0 | M110: Computer Hardware/Software/Communication Equipment serving Transmission function only.
B111: 10 | C111: A351.2 | D111: Computer Software | F111: ='II-I-DIST'!F111 -> 0 | G111: ='II-I-DIST'!H111 -> PLTTRAN_N | H111: ='II-I-MET'!F111 -> 0 | I111: ='II-I-MET'!H111 -> PLTTRAN_N | J111: ='II-I-TBILLTDCS'!F111 -> 0 | K111: ='II-I-TBILLTDCS'!H111 -> PLTTRAN_N | L111: =F111+H111+J111 -> 0 | M111: See Above.
B112: 11 | C112: A351.3 | D112: Communication Equipment | F112: ='II-I-DIST'!F112 -> 0 | G112: ='II-I-DIST'!H112 -> PLTTRAN_N | H112: ='II-I-MET'!F112 -> 0 | I112: ='II-I-MET'!H112 -> PLTTRAN_N | J112: ='II-I-TBILLTDCS'!F112 -> 0 | K112: ='II-I-TBILLTDCS'!H112 -> PLTTRAN_N | L112: =F112+H112+J112 -> 0 | M112: See Above.
B113: 12 | C113: A352 | D113: Structures and Improvements | F113: ='II-I-DIST'!F113 -> 0 | G113: ='II-I-DIST'!H113 -> NCP XHV | H113: ='II-I-MET'!F113 -> 0 | I113: ='II-I-MET'!H113 -> NCP XHV | J113: ='II-I-TBILLTDCS'!F113 -> 0 | K113: ='II-I-TBILLTDCS'!H113 -> NCP XHV | L113: 0 | M113: Most transmission plant accounts are demand related, because the capacity of the equipment required to serve the system load represents a fixed investment.
B114: 13 | C114: A353 | D114: Station Equipment | F114: ='II-I-DIST'!F114 -> 4.6897613e+08 | G114: ='II-I-DIST'!H114 -> NCP XHV | H114: ='II-I-MET'!F114 -> 0 | I114: ='II-I-MET'!H114 -> NCP XHV | J114: ='II-I-TBILLTDCS'!F114 -> 0 | K114: ='II-I-TBILLTDCS'!H114 -> NCP XHV | L114: =F114+H114+J114 -> 4.6897613e+08
B115: 14 | C115: A354 | D115: Towers and Fixtures | F115: ='II-I-DIST'!F115 -> 0 | G115: ='II-I-DIST'!H115 -> NCP XHV | H115: ='II-I-MET'!F115 -> 0 | I115: ='II-I-MET'!H115 -> NCP XHV | J115: ='II-I-TBILLTDCS'!F115 -> 0 | K115: ='II-I-TBILLTDCS'!H115 -> NCP XHV | L115: 0
B116: 15 | C116: A355 | D116: Poles and Fixtures | F116: ='II-I-DIST'!F116 -> 0 | G116: ='II-I-DIST'!H116 -> NCP XHV | H116: ='II-I-MET'!F116 -> 0 | I116: ='II-I-MET'!H116 -> NCP XHV | J116: ='II-I-TBILLTDCS'!F116 -> 0 | K116: ='II-I-TBILLTDCS'!H116 -> NCP XHV | L116: 0
B117: 16 | C117: A356 | D117: O.H. Conductors & Devices | F117: ='II-I-DIST'!F117 -> 0 | G117: ='II-I-DIST'!H117 -> NCP XHV | H117: ='II-I-MET'!F117 -> 0 | I117: ='II-I-MET'!H117 -> NCP XHV | J117: ='II-I-TBILLTDCS'!F117 -> 0 | K117: ='II-I-TBILLTDCS'!H117 -> NCP XHV | L117: 0
B118: 17 | C118: A357 | D118: Underground Conduit | F118: ='II-I-DIST'!F118 -> 0 | G118: ='II-I-DIST'!H118 -> NCP XHV | H118: ='II-I-MET'!F118 -> 0 | I118: ='II-I-MET'!H118 -> NCP XHV | J118: ='II-I-TBILLTDCS'!F118 -> 0 | K118: ='II-I-TBILLTDCS'!H118 -> NCP XHV | L118: 0
B119: 18 | C119: A358 | D119: Underground Conductors | F119: ='II-I-DIST'!F119 -> 0 | G119: ='II-I-DIST'!H119 -> NCP XHV | H119: ='II-I-MET'!F119 -> 0 | I119: ='II-I-MET'!H119 -> NCP XHV | J119: ='II-I-TBILLTDCS'!F119 -> 0 | K119: ='II-I-TBILLTDCS'!H119 -> NCP XHV | L119: 0
B120: 19 | C120: A359 | D120: Roads and Trails | F120: ='II-I-DIST'!F120 -> 0 | G120: ='II-I-DIST'!H120 -> NCP XHV | H120: ='II-I-MET'!F120 -> 0 | I120: ='II-I-MET'!H120 -> NCP XHV | J120: ='II-I-TBILLTDCS'!F120 -> 0 | K120: ='II-I-TBILLTDCS'!H120 -> NCP XHV | L120: 0
B121: 20 | D121: Subtotal | F121: ='II-I-DIST'!F121 -> 4.6897613e+08 | L121: =F121+H121+J121 -> 4.6897613e+08 | O121: ='II-I-DIST'!$F$120=F120 -> TRUE | P121: ='II-I-MET'!$F$120=H120 -> TRUE | Q121: ='II-I-TBILLTDCS'!$F$120=J120 -> TRUE
B124: =$B$4 -> 2025 RATE CASE
B125: =$B$5 -> ONCOR ELECTRIC DELIVERY COMPANY LLC
B126: =$B$6 -> II-I-2.1f: CONSOLIDATED FUNCTIONALIZED COST OF SERVICE
B127: =$B$7 -> TEST YEAR ENDING 12/31/2024
B128: =$B$8 -> SPONSOR: MATTHEW A. TROXLE
B131: Line | C131: Acct | D131: Distribution Plant Gross | E131: Source | F131: ='II-I-DIST'!F131 -> DIST | G131: ='II-I-DIST'!H131 -> Allocation | H131: ='II-I-MET'!F131 -> MET | I131: ='II-I-MET'!H131 -> Allocation | J131: ='II-I-TBILLTDCS'!F131 -> TBILLTDCS | K131: ='II-I-TBILLTDCS'!H131 -> Allocation | L131: TOTAL | M131: RATIONALE FOR CLASSIFICATION
...

Sheet WP II-I-2.1
B3: ='II-I-1'!B2 -> 2025 RATE CASE
B4: ='II-I-1'!B3 -> ONCOR ELECTRIC DELIVERY COMPANY LLC
B5: II-I-2: CLASS ALLOCATION FACTORS
B6: ='II-I-1'!B5 -> TEST YEAR ENDING 12/31/2024
B7: ='II-I-1'!B6 -> SPONSOR: MATTHEW A. TROXLE
B10: WORKPAPER 2.1 - SUMMARY VOLTAGE ALLOCATION FACTORS
B13: Line | C13: Ref | D13: Account | E13: Description | G13: XFMR | H13: Allocation
B17: 1 | C17: WP/II-I-2.4
B18: =B17+1 -> 2
B19: =B18+1 -> 3 | D19: A364 | E19: Poles, Towers & Fixtures-Total | G19: =SUM(G20:G21) -> 0.957 | H19: =SUM(H20:H21) -> 1 | I19: =IF(H19=1,TRUE,H19-1) -> TRUE
B20: =B19+1 -> 4 | E20: Poles, Towers & Fixtures-Primary | G20: 0.677 | H20: =[1]Summary!$D$17 -> 0.84374659
B21: =B20+1 -> 5 | E21: Poles, Towers & Fixtures-Secondary | G21: 0.28 | H21: =[1]Summary!$E$17 -> 0.15625341
B22: =B21+1 -> 6 | D22: A365 | E22: O.H. Conductors & Devices-Total | G22: =SUM(G23:G24) -> 1 | H22: =SUM(H23:H24) -> 1 | I22: =IF(H22=1,TRUE,H22-1) -> TRUE
B23: =B22+1 -> 7 | E23: O.H. Conductors & Devices-Primary | G23: 0.834 | H23: =[1]Summary!$D$26 -> 0.87322965
B24: =B23+1 -> 8 | E24: O.H. Conductors & Devices-Secondary | G24: 0.166 | H24: =[1]Summary!$E$26 -> 0.12677035
B25: =B24+1 -> 9 | D25: A366 | E25: Underground Conduits-Total | G25: =SUM(G26:G27) -> 1 | H25: =SUM(H26:H27) -> 1 | I25: =IF(H25=1,TRUE,H25-1) -> TRUE
B26: =B25+1 -> 10 | E26: Underground Conduits-Primary | G26: 0.726 | H26: =[1]Summary!$D$50 -> 0.65957424
B27: =B26+1 -> 11 | E27: Underground Conduits-Secondary | G27: 0.274 | H27: =[1]Summary!$E$50 -> 0.34042576
B28: =B27+1 -> 12 | D28: A367 | E28: U.G. Conductors & Devices-Total | G28: =SUM(G29:G30) -> 1 | H28: =SUM(H29:H30) -> 1 | I28: =IF(H28=1,TRUE,H28-1) -> TRUE
B29: =B28+1 -> 13 | E29: U.G. Conductors & Devices-Primary | G29: 0.778 | H29: =[1]Summary!$D$37 -> 0.79817703
B30: =B29+1 -> 14 | E30: U.G. Conductors & Devices-Secondary | G30: 0.222 | H30: =[1]Summary!$E$37 -> 0.20182297
B31: =B30+1 -> 15 | D31: A368 | E31: Line Transformers-Total | G31: =SUM(G32:G34) -> 1 | H31: =SUM(H32:H34) -> 1 | I31: =IF(H31=1,TRUE,H31-1) -> TRUE
B32: =B31+1 -> 16 | E32: Line Transformers-Primary | G32: 0.042 | H32: =[1]Summary!$D$59 -> 0.069002743
B33: =B32+1 -> 17 | E33: Line Transformers-Secondary | G33: 0.894 | H33: =[1]Summary!$E$59 -> 0.87797751
B34: =B33+1 -> 18 | E34: Capacitors & Voltage Regulators | G34: 0.064 | H34: =[1]Summary!$F$59 -> 0.053019747

Sheet II-I Summary
B3: ='WP II-I-1.1'!B3 -> 2025 RATE CASE
B4: ='WP II-I-1.1'!B4 -> ONCOR ELECTRIC DELIVERY COMPANY LLC
B5: ='WP II-I-1.1'!B5 -> II-I-1: CLASS REVENUE REQUIREMENT ANALYSIS
B6: ='WP II-I-1.1'!B6 -> TEST YEAR ENDING 12/31/2024
B7: ='WP II-I-1.1'!B7 -> SPONSOR: MATTHEW A. TROXLE
B10: II-I SUMMARY
B13: Line | C13: Description | D13: Total | F13: Residential | G13: Secondary | H13: Secondary | I13: Primary DL | J13: Primary DL | K13: Primary | L13: Transmission | M13: Lighting | N13: Wholesale | O13: Wholesale
D14: TX | G14: <=10kW | H14: >10kW | I14: <=10kW | J14: >10kW | K14: Substation | N14: Substation | O14: DLS
C15: (a) | D15: (b) | F15: (c) | G15: (d) | H15: (e) | I15: (f) | J15: (g) | K15: (h) | L15: (i) | M15: (j) | N15: (k) | O15: (l) | Q15: Checks | S15: Check2
B17: =B16+1 -> 1 | C17: O&M and A&G Expenses (less Acct 565 & RCE A928 ) | D17: =SUM(E17:P17) -> 1.4061524e+09 | F17: ='II-I-Total'!J787 -> 7.4428612e+08 | G17: ='II-I-Total'!K787 -> 30102246 | H17: ='II-I-Total'!L787 -> 4.6563161e+08 | I17: ='II-I-Total'!M787 -> 2378963.2 | J17: ='II-I-Total'!N787 -> 1.0684241e+08 | K17: ='II-I-Total'!O787 -> 10077513 | L17: ='II-I-Total'!P787 -> 2353063.4 | M17: ='II-I-Total'!Q787 -> 40221350 | ... O17: ='II-I-Total'!S787 -> 3555625.7 | Q17: =IF(' WP II-I-1.4'!L787=D17,TRUE,' WP II-I-1.4'!L787-D17) -> TRUE | S17: =SUM(F17:O17)-D17 -> 0
B18: =B17+1 -> 2 | C18: Transmission of Electricity Costs (Acct 565) | D18: =SUM(E18:P18) -> 2.1008415e+09 | F18: ='II-I-Total'!J645 -> 9.2140499e+08 | G18: ='II-I-Total'!K645 -> 18574877 | H18: ='II-I-Total'!L645 -> 6.4145952e+08 | I18: ='II-I-Total'!M645 -> 202929.39 | J18: ='II-I-Total'!N645 -> 1.9944942e+08 | K18: ='II-I-Total'!O645 -> 72408096 | L18: ='II-I-Total'!P645 -> 2.4734164e+08 | M18: ='II-I-Total'!Q645 -> 0 | ... O18: ='II-I-Total'!S645 -> 0 | Q18: =IF(('WP II-I-1.1'!G220+'WP II-I-1.1'!H220+'WP II-I-1.1'!I220)=D18,TRUE,('WP II-I-1.1'!G220+'WP II-I-1.1'!H220+'WP II-I-1.1'!I220)-D18) -> TRUE | S18: =SUM(F18:O18)-D18 -> 0
B19: =B18+1 -> 3 | C19: RateCaseExpense A928 | D19: =SUM(E19:P19) -> 0 | F19: ='II-I-DIST'!J776*('WP II-I-2.2'!$P$45) -> 0 | G19: ='II-I-DIST'!K776*('WP II-I-2.2'!$P$45) -> 0 | H19: ='II-I-DIST'!L776*('WP II-I-2.2'!$P$45) -> 0 | I19: ='II-I-DIST'!M776*('WP II-I-2.2'!$P$45) -> 0 | J19: ='II-I-DIST'!N776*('WP II-I-2.2'!$P$45) -> 0 | K19: ='II-I-DIST'!O776*('WP II-I-2.2'!$P$45) -> 0 | L19: ='II-I-DIST'!P776*('WP II-I-2.2'!$P$45) -> 0 | M19: ='II-I-DIST'!Q776*('WP II-I-2.2'!$P$45) -> 0 | ... O19: ='II-I-DIST'!S776*('WP II-I-2.2'!$P$45) -> 0
B20: =B19+1 -> 4 | C20: Total O&M and A&G Expenses | D20: =SUM(E20:P20) -> 3.5069939e+09 | F20: =SUM(F17:F19) -> 1.6656911e+09 | G20: =SUM(G17:G19) -> 48677123 | H20: =SUM(H17:H19) -> 1.1070911e+09 | I20: =SUM(I17:I19) -> 2581892.6 | J20: =SUM(J17:J19) -> 3.0629183e+08 | K20: =SUM(K17:K19) -> 82485609 | L20: =SUM(L17:L19) -> 2.4969471e+08 | M20: =SUM(M17:M19) -> 40221350 | ... O20: =SUM(O17:O19) -> 3555625.7 | Q20: ='II-I-Total'!$F$18-D20 -> 0 | S20: =SUM(F20:O20)-D20 -> 0
B21: =B20+1 -> 5 | C21: Depreciation, Amortization, & Other Expenses | D21: =SUM(E21:P21) -> 7.6213691e+08 | F21: ='II-I-Total'!J22 -> 4.016133e+08 | G21: ='II-I-Total'!K22 -> 18899507 | H21: ='II-I-Total'!L22 -> 2.4937832e+08 | I21: ='II-I-Total'!M22 -> 1187788.3 | J21: ='II-I-Total'!N22 -> 49419746 | K21: ='II-I-Total'!O22 -> 4133939.8 | L21: ='II-I-Total'!P22 -> 1259119.8 | M21: ='II-I-Total'!Q22 -> 34303678 | ... O21: ='II-I-Total'!S22 -> 1644034.4 | Q21: =IF(' WP II-I-1.4'!L22=D21,TRUE,' WP II-I-1.4'!L22-D21) -> TRUE | S21: =SUM(F21:O21)-D21 -> 0
B22: =B21+1 -> 6 | C22: Taxes Other Than FIT | D22: =SUM(E22:P22) -> 4.9498676e+08 | F22: ='II-I-Total'!J24 -> 2.2223392e+08 | G22: ='II-I-Total'!K24 -> 7470560.3 | H22: ='II-I-Total'!L24 -> 1.9103386e+08 | I22: ='II-I-Total'!M24 -> 174043.73 | J22: ='II-I-Total'!N24 -> 33593410 | K22: ='II-I-Total'!O24 -> 5306944 | L22: ='II-I-Total'!P24 -> 27571464 | M22: ='II-I-Total'!Q24 -> 6397694.4 | ... O22: ='II-I-Total'!S24 -> 810743.42 | Q22: =IF(' WP II-I-1.4'!L24=D22,TRUE,' WP II-I-1.4'!L24-D22) -> TRUE | S22: =SUM(F22:O22)-D22 -> 0
B23: =B22+1 -> 7 | C23: Subtotal | D23: =SUM(E23:P23) -> 4.7641176e+09 | F23: =SUM(F20:F22) -> 2.2895383e+09 | G23: =SUM(G20:G22) -> 75047190 | H23: =SUM(H20:H22) -> 1.5475033e+09 | I23: =SUM(I20:I22) -> 3943724.6 | J23: =SUM(J20:J22) -> 3.8930498e+08 | K23: =SUM(K20:K22) -> 91926492 | L23: =SUM(L20:L22) -> 2.7852529e+08 | M23: =SUM(M20:M22) -> 80922723 | ... O23: =SUM(O20:O22) -> 6010403.6 | S23: =SUM(F23:O23)-D23 -> 0
B24: =B23+1 -> 8 | C24: Cost-Based Return on Rate Base | D24: =SUM(E24:P24) -> 1.0591573e+09 | F24: ='II-I-Total'!J27 -> 5.7528199e+08 | G24: ='II-I-Total'!K27 -> 18004272 | H24: ='II-I-Total'!L27 -> 3.6570944e+08 | I24: ='II-I-Total'!M27 -> 698376.14 | J24: ='II-I-Total'!N27 -> 71151671 | K24: ='II-I-Total'!O27 -> 7977532.6 | L24: ='II-I-Total'!P27 -> 2278161.3 | M24: ='II-I-Total'!Q27 -> 14910476 | ... O24: ='II-I-Total'!S27 -> 2584084.4 | Q24: =IF(ROUND(' WP II-I-1.4'!L27-D24,2)=0,TRUE,' WP II-I-1.4'!L27-D24) -> TRUE | S24: =SUM(F24:O24)-D24 -> 0
B25: =B24+1 -> 9 | C25: Cost-Based Federal Income Tax | D25: =SUM(E25:P25) -> 1.4473902e+08 | F25: ='II-I-Total'!J25 -> 78668226 | G25: ='II-I-Total'!K25 -> 2333594.4 | H25: ='II-I-Total'!L25 -> 50108868 | I25: ='II-I-Total'!M25 -> 68143.324 | J25: ='II-I-Total'!N25 -> 9622190.5 | K25: ='II-I-Total'!O25 -> 1093406.3 | L25: ='II-I-Total'!P25 -> 303017.14 | M25: ='II-I-Total'!Q25 -> 2109357.1 | ... O25: ='II-I-Total'!S25 -> 355506.44 | Q25: =IF(ROUND(' WP II-I-1.4'!L25-D25,0)=0,TRUE,' WP II-I-1.4'!L25-D25) -> TRUE | S25: =SUM(F25:O25)-D25 -> 0
B26: =B25+1 -> 10 | C26: COST OF SERVICE | D26: =SUM(E26:P26) -> 5.9680139e+09 | F26: =SUM(F23:F25) -> 2.9434885e+09 | G26: =SUM(G23:G25) -> 95385056 | H26: =SUM(H23:H25) -> 1.9633216e+09 | I26: =SUM(I23:I25) -> 4710244 | J26: =SUM(J23:J25) -> 4.7007885e+08 | K26: =SUM(K23:K25) -> 1.0099743e+08 | L26: =SUM(L23:L25) -> 2.8110647e+08 | M26: =SUM(M23:M25) -> 97942555 | ... O26: =SUM(O23:O25) -> 8949994.4 | Q26: =IF(ROUND(' WP II-I-1.4'!L1225-D26,0)=0,TRUE,' WP II-I-1.4'!L1225-D26) -> TRUE | S26: =SUM(F26:O26)-D26 -> 0
B27: =B26+1 -> 11 | S27: =SUM(F27:O27)-D27 -> 0
B28: =B27+1 -> 12 | C28: Minus: Other Revenues | D28: =SUM(E28:P28) -> 81014329 | F28: ='II-I-Total'!J31 -> 44678854 | G28: ='II-I-Total'!K31 -> 2520222.3 | H28: ='II-I-Total'!L31 -> 21286205 | I28: ='II-I-Total'!M31 -> 188960.18 | J28: ='II-I-Total'!N31 -> 5684264 | K28: ='II-I-Total'!O31 -> 1334239.9 | L28: ='II-I-Total'!P31 -> 4650081.3 | M28: ='II-I-Total'!Q31 -> 418151.09 | ... O28: ='II-I-Total'!S31 -> 164565.08 | Q28: =IF(' WP II-I-1.4'!L31=D28,TRUE,' WP II-I-1.4'!L31-D28) -> TRUE | S28: =SUM(F28:O28)-D28 -> 0
B29: =B28+1 -> 13 | S29: =SUM(F29:O29)-D29 -> 0
B30: =B29+1 -> 14 | C30: COST-BASED REVENUE REQUIREMENT | D30: =SUM(E30:P30) -> 5.8869996e+09 | F30: =F26-F28 -> 2.8988097e+09 | G30: =G26-G28 -> 92864834 | H30: =H26-H28 -> 1.9420354e+09 | I30: =I26-I28 -> 4521283.9 | J30: =J26-J28 -> 4.6439458e+08 | K30: =K26-K28 -> 99663191 | L30: =L26-L28 -> 2.7645639e+08 | M30: =M26-M28 -> 97524404 | ... O30: =O26-O28 -> 8785429.3 | Q30: =IF('II-I-Total'!U1226=D30,TRUE,'II-I-Total'!U1226-D30) -> TRUE | S30: =SUM(F30:O30)-D30 -> 0
B31: =B30+1 -> 15 | S31: =SUM(F31:O31)-D31 -> 0
B32: =B31+1 -> 16 | S32: =SUM(F32:O32)-D32 -> 0
B33: =B32+1 -> 17 | S33: =SUM(F33:O33)-D33 -> 0
B34: =B33+1 -> 18 | S34: =SUM(F34:O34)-D34 -> 0
B35: =B34+1 -> 19 | S35: =SUM(F35:O35)-D35 -> 0
B36: =B35+1 -> 20 | C36: PROPOSED REVENUE | D36: =SUM(E36:P36) -> 5.8869996e+09 | F36: =F30 -> 2.8988097e+09 | G36: =G30 -> 92864834 | H36: =H30 -> 1.9420354e+09 | I36: =I30 -> 4521283.9 | J36: =J30 -> 4.6439458e+08 | K36: =K30 -> 99663191 | L36: =L30 -> 2.7645639e+08 | M36: =M30 -> 97524404 | ... O36: =O30 -> 8785429.3 | Q36: ='WP II-I-1.1'!$G$510+'WP II-I-1.1'!$H$510+'WP II-I-1.1'!$I$510-D36-D34 -> 1.9073486e-06 | S36: =SUM(F36:O36)-D36 -> 0
B37: =B36+1 -> 21 | S37: =SUM(F37:O37)-D37 -> 0
B38: =B37+1 -> 22 | C38: TOTAL PRESENT REVENUES (Incl PF) | D38: =SUM(E38:P38) -> 5.2027177e+09 | F38: ='II-I Summary'!F112 -> 2.5809053e+09 | G38: ='II-I Summary'!G112 -> 93725157 | H38: ='II-I Summary'!H112 -> 1.7722781e+09 | I38: ='II-I Summary'!I112 -> 1756235 | J38: ='II-I Summary'!J112 -> 3.8871792e+08 | K38: ='II-I Summary'!K112 -> 78824111 | L38: ='II-I Summary'!L112 -> 2.1127132e+08 | M38: ='II-I Summary'!M112 -> 64581935 | ... O38: ='II-I Summary'!O112 -> 8861400.8 | S38: =SUM(F38:O38)-D38 -> 0
B39: =B38+1 -> 23 | S39: =SUM(F39:O39)-D39 -> 0
B40: =B39+1 -> 24 | C40: COST-BASED REVENUE REQUIREMENT | D40: =SUM(E40:P40) -> 5.8869996e+09 | F40: =F30 -> 2.8988097e+09 | G40: =G30 -> 92864834 | H40: =H30 -> 1.9420354e+09 | I40: =I30 -> 4521283.9 | J40: =J30 -> 4.6439458e+08 | K40: =K30 -> 99663191 | L40: =L30 -> 2.7645639e+08 | M40: =M30 -> 97524404 | ... O40: =O30 -> 8785429.3 | S40: =SUM(F40:O40)-D40 -> 0
B41: =B40+1 -> 25 | C41: Shortfall / (Surplus) vs Cost-Based Revenues | D41: =SUM(E41:P41) -> 6.8428193e+08 | F41: =F40-F38 -> 3.1790442e+08 | G41: =G40-G38 -> -860322.91 | H41: =H40-H38 -> 1.6975731e+08 | I41: =I40-I38 -> 2765048.8 | J41: =J40-J38 -> 75676667 | K41: =K40-K38 -> 20839081 | L41: =L40-L38 -> 65185067 | M41: =M40-M38 -> 32942469 | ... O41: =O40-O38 -> -75971.485 | S41: =SUM(F41:O41)-D41 -> 0
B42: =B41+1 -> 26 | C42: Change from Present Revenues | D42: =D41/D38 -> 0.13152394 | F42: =F41/F38 -> 0.12317555 | G42: =G41/G38 -> -0.0091792101 | H42: =H41/H38 -> 0.095784801 | I42: =I41/I38 -> 1.5744184 | J42: =J41/J38 -> 0.19468273 | K42: =K41/K38 -> 0.26437444 | L42: =L41/L38 -> 0.30853722 | M42: =M41/M38 -> 0.51008799 | ... O42: =O41/O38 -> -0.0085733043 | S42: =SUM(F42:O42)-D42 -> 3.0042719
B43: =B42+1 -> 27 | S43: =SUM(F43:O43)-D43 -> 0
B44: =B43+1 -> 28 | C44: PROPOSED REVENUE | D44: =SUM(E44:P44) -> 5.8869996e+09 | F44: =F36 -> 2.8988097e+09 | G44: =G36 -> 92864834 | H44: =H36 -> 1.9420354e+09 | I44: =I36 -> 4521283.9 | J44: =J36 -> 4.6439458e+08 | K44: =K36 -> 99663191 | L44: =L36 -> 2.7645639e+08 | M44: =M36 -> 97524404 | ... O44: =O36 -> 8785429.3 | S44: =SUM(F44:O44)-D44 -> 0
B45: =B44+1 -> 29 | C45: Shortfall / (Surplus) vs Proposed Revenue | D45: =SUM(E45:P45) -> 6.8428193e+08 | F45: =F44-F38 -> 3.1790442e+08 | G45: =G44-G38 -> -860322.91 | H45: =H44-H38 -> 1.6975731e+08 | I45: =I44-I38 -> 2765048.8 | J45: =J44-J38 -> 75676667 | K45: =K44-K38 -> 20839081 | L45: =L44-L38 -> 65185067 | M45: =M44-M38 -> 32942469 | ... O45: =O44-O38 -> -75971.485 | S45: =SUM(F45:O45)-D45 -> 0
B46: =B45+1 -> 30 | C46: Change from Present Revenues | D46: =D45/D38 -> 0.13152394 | F46: =F45/F38 -> 0.12317555 | G46: =G45/G38 -> -0.0091792101 | H46: =H45/H38 -> 0.095784801 | I46: =I45/I38 -> 1.5744184 | J46: =J45/J38 -> 0.19468273 | K46: =K45/K38 -> 0.26437444 | L46: =L45/L38 -> 0.30853722 | M46: =M45/M38 -> 0.51008799 | ... O46: =O45/O38 -> -0.0085733043 | S46: =SUM(F46:O46)-D46 -> 3.0042719
B47: =B46+1 -> 31 | S47: =SUM(F47:O47)-D47 -> 0
B48: =B47+1 -> 32 | C48: Rate Base | D48: =SUM(E48:P48) -> 1.4178813e+10 | F48: ='II-I-Total'!J618 -> 7.7012314e+09 | G48: ='II-I-Total'!K618 -> 2.4102104e+08 | H48: ='II-I-Total'!L618 -> 4.8957087e+09 | I48: ='II-I-Total'!M618 -> 9349078.2 | J48: ='II-I-Total'!N618 -> 9.5249895e+08 | K48: ='II-I-Total'!O618 -> 1.0679428e+08 | L48: ='II-I-Total'!P618 -> 30497473 | M48: ='II-I-Total'!Q618 -> 1.9960476e+08 | ... O48: ='II-I-Total'!S618 -> 34592830 | Q48: =IF(('WP II-I-1.1'!G492+'WP II-I-1.1'!H492+'WP II-I-1.1'!I492)=D48,TRUE,('WP II-I-1.1'!G492+'WP II-I-1.1'!H492+'WP II-I-1.1'!I492)-D48) -> TRUE | S48: =SUM(F48:O48)-D48 -> 0
B49: =B48+1 -> 33 | S49: =SUM(F49:O49)-D49 -> 0
B50: =B49+1 -> 34 | C50: Return at Present Rates | D50: =SUM(E50:P50) -> 4.9457523e+08 | F50: ='II-I Summary'!F135 -> 3.0939293e+08 | G50: ='II-I Summary'!G135 -> 24473647 | H50: ='II-I Summary'!H135 -> 2.2400115e+08 | I50: ='II-I Summary'!I135 -> -1603929.2 | J50: ='II-I Summary'!J135 -> 8369370.9 | K50: ='II-I Summary'!K135 -> -9392908.8 | L50: ='II-I Summary'!L135 -> -52688904 | M50: ='II-I Summary'!M135 -> -10879896 | ... O50: ='II-I Summary'!O135 -> 2526825.7 | S50: =SUM(F50:O50)-D50 -> 0
B51: =B50+1 -> 35 | C51: Present Rate of Return | D51: =D50/D48 -> 0.034881286 | F51: =F50/F48 -> 0.040174475 | G51: =G50/G48 -> 0.10154154 | H51: =H50/H48 -> 0.045754591 | I51: =I50/I48 -> -0.17156015 | J51: =J50/J48 -> 0.0087867508 | K51: =K50/K48 -> -0.087953296 | L51: =L50/L48 -> -1.7276482 | M51: =M50/M48 -> -0.054507197 | ... O51: =O50/O48 -> 0.073044783 | S51: =SUM(F51:O51)-D51 -> -1.7570852
B52: =B51+1 -> 36 | C52: Present Relative Rate of Return | D52: =D51/$D$51 -> 1 | F52: =F51/$D$51 -> 1.1517487 | G52: =G51/$D$51 -> 2.9110606 | H52: =H51/$D$51 -> 1.3117232 | I52: =I51/$D$51 -> -4.9184008 | J52: =J51/$D$51 -> 0.25190444 | K52: =K51/$D$51 -> -2.5215038 | L52: =L51/$D$51 -> -49.529371 | M52: =M51/$D$51 -> -1.5626487 | ... O52: =O51/$D$51 -> 2.0940966 | S52: =SUM(F52:O52)-D52 -> -50.373292
B53: =B52+1 -> 37 | S53: =SUM(F53:O53)-D53 -> 0
B54: =B53+1 -> 38 | C54: Cost-Based Return on Rate Base | D54: =SUM(E54:P54) -> 1.0591573e+09 | F54: =F24 -> 5.7528199e+08 | G54: =G24 -> 18004272 | H54: =H24 -> 3.6570944e+08 | I54: =I24 -> 698376.14 | J54: =J24 -> 71151671 | K54: =K24 -> 7977532.6 | L54: =L24 -> 2278161.3 | M54: =M24 -> 14910476 | ... O54: =O24 -> 2584084.4 | Q54: =IF(D$24=D54,TRUE,D$24-D54) -> TRUE | S54: =SUM(F54:O54)-D54 -> 0
B55: =B54+1 -> 39 | C55: Cost-Based Rate of Return | D55: =D24/D48 -> 0.0747 | F55: =F24/F48 -> 0.0747 | G55: =G24/G48 -> 0.0747 | H55: =H24/H48 -> 0.0747 | I55: =I24/I48 -> 0.0747 | J55: =J24/J48 -> 0.0747 | K55: =K24/K48 -> 0.0747 | L55: =L24/L48 -> 0.0747 | M55: =M24/M48 -> 0.0747 | ... O55: =O24/O48 -> 0.0747 | S55: =SUM(F55:O55)-D55 -> 0.6723
B56: =B55+1 -> 40 | C56: Cost-Based Relative Rate of Return | D56: =D55/$D$55 -> 1 | F56: =F55/$D$55 -> 1 | G56: =G55/$D$55 -> 1 | H56: =H55/$D$55 -> 1 | I56: =I55/$D$55 -> 1 | J56: =J55/$D$55 -> 1 | K56: =K55/$D$55 -> 1 | L56: =L55/$D$55 -> 1 | M56: =M55/$D$55 -> 1 | ... O56: =O55/$D$55 -> 1 | S56: =SUM(F56:O56)-D56 -> 9
B57: =B56+1 -> 41 | S57: =SUM(F57:O57)-D57 -> 0
B58: =B57+1 -> 42 | C58: Proposed Return on Rate Base | D58: =SUM(E58:P58) -> 1.0591573e+09 | F58: =F24+F32 -> 5.7528199e+08 | G58: =G24+G32 -> 18004272 | H58: =H24+H32 -> 3.6570944e+08 | I58: =I24+I32 -> 698376.14 | J58: =J24+J32 -> 71151671 | K58: =K24+K32 -> 7977532.6 | L58: =L24+L32 -> 2278161.3 | M58: =M24+M32 -> 14910476 | ... O58: =O24+O32 -> 2584084.4 | Q58: =IF(D$24=D58,TRUE,D$24-D58) -> TRUE | S58: =SUM(F58:O58)-D58 -> 0
B59: =B58+1 -> 43 | C59: Proposed Rate of Return | D59: =D58/D48 -> 0.0747 | F59: =F58/F48 -> 0.0747 | G59: =G58/G48 -> 0.0747 | H59: =H58/H48 -> 0.0747 | I59: =I58/I48 -> 0.0747 | J59: =J58/J48 -> 0.0747 | K59: =K58/K48 -> 0.0747 | L59: =L58/L48 -> 0.0747 | M59: =M58/M48 -> 0.0747 | ... O59: =O58/O48 -> 0.0747 | S59: =SUM(F59:O59)-D59 -> 0.6723
B60: =B59+1 -> 44 | C60: Proposed Relative Rate of Return | D60: =D59/$D$59 -> 1 | F60: =F59/$D$59 -> 1 | G60: =G59/$D$59 -> 1 | H60: =H59/$D$59 -> 1 | I60: =I59/$D$59 -> 1 | J60: =J59/$D$59 -> 1 | K60: =K59/$D$59 -> 1 | L60: =L59/$D$59 -> 1 | M60: =M59/$D$59 -> 1 | ... O60: =O59/$D$59 -> 1 | S60: =SUM(F60:O60)-D60 -> 9
B61: =B60+1 -> 45 | C61: Differential vs Cost-Based | D61: =SUM(E61:P61) -> 0 | F61: =F58-F54 -> 0 | G61: =G58-G54 -> 0 | H61: =H58-H54 -> 0 | I61: =I58-I54 -> 0 | J61: =J58-J54 -> 0 | K61: =K58-K54 -> 0 | L61: =L58-L54 -> 0 | M61: =M58-M54 -> 0 | ... O61: =O58-O54 -> 0 | S61: =SUM(F61:O61)-D61 -> 0
S62: =SUM(F62:O62)-D62 -> 0
B63: =B62+1 -> 1 | C63: RATE BASE | S63: =SUM(F63:O63)-D63 -> 0
B64: =B63+1 -> 2 | S64: =SUM(F64:O64)-D64 -> 0
B65: =B64+1 -> 3 | C65: Intangible, Transmission, Distribution Plant: Orig Cost | D65: =SUM(E65:P65) -> 2.1036153e+10 | F65: ='II-I-Total'!J56 -> 1.1269391e+10 | G65: ='II-I-Total'!K56 -> 4.2812352e+08 | H65: ='II-I-Total'!L56 -> 7.0765978e+09 | I65: ='II-I-Total'!M56 -> 15265864 | J65: ='II-I-Total'!N56 -> 1.3300355e+09 | K65: ='II-I-Total'!O56 -> 1.3652844e+08 | L65: ='II-I-Total'!P56 -> 30107340 | M65: ='II-I-Total'!Q56 -> 6.9248318e+08 | ... O65: ='II-I-Total'!S56 -> 48043500 | Q65: =IF(' WP II-I-1.4'!L56=D65,TRUE,' WP II-I-1.4'!L56-D65) -> TRUE | S65: =SUM(F65:O65)-D65 -> 0
B66: =B65+1 -> 4 | C66: General Plant: Original Cost | D66: =SUM(E66:P66) -> 3.9691105e+08 | F66: ='II-I-Total'!J58 -> 2.1432601e+08 | G66: ='II-I-Total'!K58 -> 9594975.4 | H66: ='II-I-Total'!L58 -> 1.3344865e+08 | I66: ='II-I-Total'!M58 -> 833500.68 | J66: ='II-I-Total'!N58 -> 27830698 | K66: ='II-I-Total'!O58 -> 2734915 | L66: ='II-I-Total'!P58 -> 848578.81 | M66: ='II-I-Total'!Q58 -> 6207935.1 | ... O66: ='II-I-Total'!S58 -> 888402.79 | Q66: =IF(' WP II-I-1.4'!L58=D66,TRUE,' WP II-I-1.4'!L58-D66) -> TRUE | S66: =SUM(F66:O66)-D66 -> 0
B67: =B66+1 -> 5 | C67: Communication Equipment: Original Cost | D67: =SUM(E67:P67) -> 3.9882321e+08 | F67: ='II-I-Total'!J59 -> 2.1411145e+08 | G67: ='II-I-Total'!K59 -> 10485671 | H67: ='II-I-Total'!L59 -> 1.3254243e+08 | I67: ='II-I-Total'!M59 -> 1012880.7 | J67: ='II-I-Total'!N59 -> 28236109 | K67: ='II-I-Total'!O59 -> 2665267.6 | L67: ='II-I-Total'!P59 -> 924409.76 | M67: ='II-I-Total'!Q59 -> 7787190.3 | ... O67: ='II-I-Total'!S59 -> 863337.21 | Q67: =IF(' WP II-I-1.4'!L59=D67,TRUE,' WP II-I-1.4'!L59-D67) -> TRUE | S67: =SUM(F67:O67)-D67 -> 0
B68: =B67+1 -> 6 | C68: Total Plant | D68: =SUM(E68:P68) -> 2.1831887e+10 | F68: =SUM(F65:F67) -> 1.1697829e+10 | G68: =SUM(G65:G67) -> 4.4820417e+08 | H68: =SUM(H65:H67) -> 7.3425889e+09 | I68: =SUM(I65:I67) -> 17112245 | J68: =SUM(J65:J67) -> 1.3861023e+09 | K68: =SUM(K65:K67) -> 1.4192862e+08 | L68: =SUM(L65:L67) -> 31880329 | M68: =SUM(M65:M67) -> 7.0647831e+08 | ... O68: =SUM(O65:O67) -> 49795240 | S68: =SUM(F68:O68)-D68 -> 0
B69: =B68+1 -> 7 | S69: =SUM(F69:O69)-D69 -> 0
B70: =B69+1 -> 8 | C70: Minus: Accumulated Depreciation | D70: =SUM(E70:P70) -> 7.081255e+09 | F70: ='II-I-Total'!J62 -> 3.674719e+09 | G70: ='II-I-Total'!K62 -> 1.9528679e+08 | H70: ='II-I-Total'!L62 -> 2.265901e+09 | I70: ='II-I-Total'!M62 -> 7385852.9 | J70: ='II-I-Total'!N62 -> 3.9823434e+08 | K70: ='II-I-Total'!O62 -> 31842026 | L70: ='II-I-Total'!P62 -> 9301864.6 | M70: ='II-I-Total'!Q62 -> 4.8256688e+08 | ... O70: ='II-I-Total'!S62 -> 13744838 | Q70: =IF(' WP II-I-1.4'!L62=D70,TRUE,' WP II-I-1.4'!L62-D70) -> TRUE | S70: =SUM(F70:O70)-D70 -> 0
B71: =B70+1 -> 9 | S71: =SUM(F71:O71)-D71 -> 0
B72: =B71+1 -> 10 | C72: Net Plant In Service | D72: =SUM(E72:P72) -> 1.4750632e+10 | F72: =+F68-F70 -> 8.0231096e+09 | G72: =+G68-G70 -> 2.5291738e+08 | H72: =+H68-H70 -> 5.076688e+09 | I72: =+I68-I70 -> 9726392.1 | J72: =+J68-J70 -> 9.8786794e+08 | K72: =+K68-K70 -> 1.1008659e+08 | L72: =+L68-L70 -> 22578464 | M72: =+M68-M70 -> 2.2391143e+08 | ... O72: =+O68-O70 -> 36050401 | S72: =SUM(F72:O72)-D72 -> 0
B73: =B72+1 -> 11 | S73: =SUM(F73:O73)-D73 -> 0
B74: =B73+1 -> 12 | C74: Other Rate Base Items: | S74: =SUM(F74:O74)-D74 -> 0
B75: =B74+1 -> 13 | C75: CWIP | D75: =SUM(E75:P75) -> 0 | F75: ='II-I-Total'!J68 -> 0 | G75: ='II-I-Total'!K68 -> 0 | H75: ='II-I-Total'!L68 -> 0 | I75: ='II-I-Total'!M68 -> 0 | J75: ='II-I-Total'!N68 -> 0 | K75: ='II-I-Total'!O68 -> 0 | L75: ='II-I-Total'!P68 -> 0 | M75: ='II-I-Total'!Q68 -> 0 | ... O75: ='II-I-Total'!S68 -> 0 | Q75: =IF(' WP II-I-1.4'!L68=D75,TRUE,' WP II-I-1.4'!L68-D75) -> TRUE | S75: =SUM(F75:O75)-D75 -> 0
B76: =B75+1 -> 14 | C76: Plant Held for Future Use | D76: =SUM(E76:P76) -> 6705448.4 | F76: ='II-I-Total'!J69 -> 3438329.3 | G76: ='II-I-Total'!K69 -> 64959.212 | H76: ='II-I-Total'!L69 -> 2208453.5 | I76: ='II-I-Total'!M69 -> 1033.4253 | J76: ='II-I-Total'!N69 -> 649597.79 | K76: ='II-I-Total'!O69 -> 279209.92 | L76: ='II-I-Total'!P69 -> 0 | M76: ='II-I-Total'!Q69 -> 19639.929 | ... O76: ='II-I-Total'!S69 -> 24925.23 | Q76: =IF(' WP II-I-1.4'!L69=D76,TRUE,' WP II-I-1.4'!L69-D76) -> TRUE | S76: =SUM(F76:O76)-D76 -> 0
B77: =B76+1 -> 15 | C77: Accumulated Provisions ex ADFIT | D77: =SUM(E77:P77) -> 0 | F77: ='II-I-Total'!J70 -> 0 | G77: ='II-I-Total'!K70 -> 0 | H77: ='II-I-Total'!L70 -> 0 | I77: ='II-I-Total'!M70 -> 0 | J77: ='II-I-Total'!N70 -> 0 | K77: ='II-I-Total'!O70 -> 0 | L77: ='II-I-Total'!P70 -> 0 | M77: ='II-I-Total'!Q70 -> 0 | ... O77: ='II-I-Total'!S70 -> 0 | Q77: =IF(' WP II-I-1.4'!L70=D77,TRUE,' WP II-I-1.4'!L70-D77) -> TRUE | S77: =SUM(F77:O77)-D77 -> 0
B78: =B77+1 -> 16 | C78: Materials & Supplies | D78: =SUM(E78:P78) -> 1.5919987e+08 | F78: ='II-I-Total'!J71 -> 85510298 | G78: ='II-I-Total'!K71 -> 2832719.6 | H78: ='II-I-Total'!L71 -> 54015093 | I78: ='II-I-Total'!M71 -> 30582.509 | J78: ='II-I-Total'!N71 -> 9872374.8 | K78: ='II-I-Total'!O71 -> 1064923.1 | L78: ='II-I-Total'!P71 -> 191765.99 | M78: ='II-I-Total'!Q71 -> 5232916.7 | ... O78: ='II-I-Total'!S71 -> 375422.16 | Q78: =IF(' WP II-I-1.4'!L71=D78,TRUE,' WP II-I-1.4'!L71-D78) -> TRUE | S78: =SUM(F78:O78)-D78 -> 0
B79: =B78+1 -> 17 | C79: Cash Working Capital | D79: =SUM(E79:P79) -> -25736513 | F79: ='II-I-Total'!J72 -> -11623098 | G79: ='II-I-Total'!K72 -> -247303.79 | H79: ='II-I-Total'!L72 -> -7968317.6 | I79: ='II-I-Total'!M72 -> -5616.4464 | J79: ='II-I-Total'!N72 -> -2404033.2 | K79: ='II-I-Total'!O72 -> -783650.22 | L79: ='II-I-Total'!P72 -> -2569600 | M79: ='II-I-Total'!Q72 -> -120596.54 | ... O79: ='II-I-Total'!S72 -> -12081.943 | Q79: =IF(' WP II-I-1.4'!L72=D79,TRUE,' WP II-I-1.4'!L72-D79) -> TRUE | S79: =SUM(F79:O79)-D79 -> 0
B80: =B79+1 -> 18 | C80: Prepayments | D80: =SUM(E80:P80) -> 1.288574e+08 | F80: ='II-I-Total'!J73 -> 50522241 | G80: ='II-I-Total'!K73 -> 1530621 | H80: ='II-I-Total'!L73 -> 53794289 | I80: ='II-I-Total'!M73 -> 1035.7463 | J80: ='II-I-Total'!N73 -> 8907478.9 | K80: ='II-I-Total'!O73 -> 1697928.2 | L80: ='II-I-Total'!P73 -> 11710507 | M80: ='II-I-Total'!Q73 -> 413390.56 | ... O80: ='II-I-Total'!S73 -> 151491.83 | Q80: =IF(' WP II-I-1.4'!L73=D80,TRUE,' WP II-I-1.4'!L73-D80) -> TRUE | S80: =SUM(F80:O80)-D80 -> 0
B81: =B80+1 -> 19 | C81: Misc Other Rate Base | D81: =SUM(E81:P81) -> -2280492.1 | F81: ='II-I-Total'!J74 -> -1014812 | G81: ='II-I-Total'!K74 -> -19172.505 | H81: ='II-I-Total'!L74 -> -651818.01 | I81: ='II-I-Total'!M74 -> -305.01219 | J81: ='II-I-Total'!N74 -> -191726.72 | K81: ='II-I-Total'!O74 -> -82407.919 | L81: ='II-I-Total'!P74 -> -301400.33 | M81: ='II-I-Total'!Q74 -> -5796.6626 | ... O81: ='II-I-Total'!S74 -> -7356.6023 | Q81: =IF(' WP II-I-1.4'!L74=D81,TRUE,' WP II-I-1.4'!L74-D81) -> TRUE | S81: =SUM(F81:O81)-D81 -> 0
B82: =B81+1 -> 20 | C82: Regulatory Assets | D82: =SUM(E82:P82) -> 6.5976005e+08 | F82: ='II-I-Total'!J75 -> 3.5376687e+08 | G82: ='II-I-Total'!K75 -> 13293652 | H82: ='II-I-Total'!L75 -> 2.2228858e+08 | I82: ='II-I-Total'!M75 -> 470448.24 | J82: ='II-I-Total'!N75 -> 42036339 | K82: ='II-I-Total'!O75 -> 4352338.3 | L82: ='II-I-Total'!P75 -> 943455.1 | M82: ='II-I-Total'!Q75 -> 20855542 | ... O82: ='II-I-Total'!S75 -> 1461266.4 | Q82: =IF(' WP II-I-1.4'!L75=D82,TRUE,' WP II-I-1.4'!L75-D82) -> TRUE | S82: =SUM(F82:O82)-D82 -> 0
B83: =B82+1 -> 21 | C83: Acuumulated Deferred Income Taxes | D83: =SUM(E83:P83) -> -1.4983248e+09 | F83: ='II-I-Total'!J76 -> -8.02478e+08 | G83: ='II-I-Total'!K76 -> -29351818 | H83: ='II-I-Total'!L76 -> -5.0466555e+08 | I83: ='II-I-Total'!M76 -> -874492.35 | J83: ='II-I-Total'!N76 -> -94239023 | K83: ='II-I-Total'!O76 -> -9820655.3 | L83: ='II-I-Total'!P76 -> -2055719 | M83: ='II-I-Total'!Q76 -> -50701766 | ... O83: ='II-I-Total'!S76 -> -3451238.8 | Q83: =IF(ROUND(' WP II-I-1.4'!L76-D83,2)=0,TRUE,' WP II-I-1.4'!L76-D83) -> TRUE | S83: =SUM(F83:O83)-D83 -> 0
B84: =B83+1 -> 22 | S84: =SUM(F84:O84)-D84 -> 0
B85: =B84+1 -> 23 | C85: Subtotal | D85: =SUM(E85:P85) -> -5.7181901e+08 | F85: =SUM(F74:F83) -> -3.2187817e+08 | G85: =SUM(G74:G83) -> -11896343 | H85: =SUM(H74:H83) -> -1.8097927e+08 | I85: =SUM(I74:I83) -> -377313.89 | J85: =SUM(J74:J83) -> -35368991 | K85: =SUM(K74:K83) -> -3292313.9 | L85: =SUM(L74:L83) -> 7919008.9 | M85: =SUM(M74:M83) -> -24306670 | ... O85: =SUM(O74:O83) -> -1457571.7 | S85: =SUM(F85:O85)-D85 -> 0
B86: =B85+1 -> 24 | S86: =SUM(F86:O86)-D86 -> 0
B87: =B86+1 -> 25 | C87: TOTAL RATE BASE | D87: =SUM(E87:P87) -> 1.4178813e+10 | F87: =+F72+F85 -> 7.7012314e+09 | G87: =+G72+G85 -> 2.4102104e+08 | H87: =+H72+H85 -> 4.8957087e+09 | I87: =+I72+I85 -> 9349078.2 | J87: =+J72+J85 -> 9.5249895e+08 | K87: =+K72+K85 -> 1.0679428e+08 | L87: =+L72+L85 -> 30497473 | M87: =+M72+M85 -> 1.9960476e+08 | ... O87: =+O72+O85 -> 34592830 | Q87: =D48=D87 -> TRUE | S87: =SUM(F87:O87)-D87 -> 0
B88: =B87+1 -> 26 | S88: =SUM(F88:O88)-D88 -> 0
B89: =B88+1 -> 27 | S89: =SUM(F89:O89)-D89 -> 0
B90: =B89+1 -> 28 | C90: COST-BASED | S90: =SUM(F90:O90)-D90 -> 0
B91: =B90+1 -> 29 | S91: =SUM(F91:O91)-D91 -> 0
B92: =B91+1 -> 30 | C92: Cost-Based Rate of Return | D92: =' WP II-I-1.4'!L620 -> 0.0747 | F92: =$D$92 -> 0.0747 | G92: =$D$92 -> 0.0747 | H92: =$D$92 -> 0.0747 | I92: =$D$92 -> 0.0747 | J92: =$D$92 -> 0.0747 | K92: =$D$92 -> 0.0747 | L92: =$D$92 -> 0.0747 | M92: =$D$92 -> 0.0747 | ... O92: =$D$92 -> 0.0747 | S92: =SUM(F92:O92)-D92 -> 0.6723
B93: =B92+1 -> 31 | S93: =SUM(F93:O93)-D93 -> 0
B94: =B93+1 -> 32 | C94: Cost-Based Return on Rate Base | D94: =SUM(E94:P94) -> 1.0591573e+09 | F94: =F87*F92 -> 5.7528199e+08 | G94: =G87*G92 -> 18004272 | H94: =H87*H92 -> 3.6570944e+08 | I94: =I87*I92 -> 698376.14 | J94: =J87*J92 -> 71151671 | K94: =K87*K92 -> 7977532.6 | L94: =L87*L92 -> 2278161.3 | M94: =M87*M92 -> 14910476 | ... O94: =O87*O92 -> 2584084.4 | Q94: =IF(ROUND('II-I-Total'!U622-D94,2)=0,TRUE,'II-I-Total'!U622-D94) -> TRUE | S94: =SUM(F94:O94)-D94 -> 0
B95: =B94+1 -> 33 | S95: =SUM(F95:O95)-D95 -> 0
B96: =B95+1 -> 34 | S96: =SUM(F96:O96)-D96 -> 0
B97: =B96+1 -> 35 | C97: PROPOSED | S97: =SUM(F97:O97)-D97 -> 0
B98: =B97+1 -> 36 | S98: =SUM(F98:O98)-D98 -> 0
B99: =B98+1 -> 37 | C99: Proposed Rate of Return | D99: =D101/D87 -> 0.0747 | F99: =F101/F87 -> 0.0747 | G99: =G101/G87 -> 0.0747 | H99: =H101/H87 -> 0.0747 | I99: =I101/I87 -> 0.0747 | J99: =J101/J87 -> 0.0747 | K99: =K101/K87 -> 0.0747 | L99: =L101/L87 -> 0.0747 | M99: =M101/M87 -> 0.0747 | ... O99: =O101/O87 -> 0.0747 | S99: =SUM(F99:O99)-D99 -> 0.6723
B100: =B99+1 -> 38 | S100: =SUM(F100:O100)-D100 -> 0
B101: =B100+1 -> 39 | C101: Proposed Return on Rate Base | D101: =SUM(E101:P101) -> 1.0591573e+09 | F101: =F94 -> 5.7528199e+08 | G101: =G94 -> 18004272 | H101: =H94 -> 3.6570944e+08 | I101: =I94 -> 698376.14 | J101: =J94 -> 71151671 | K101: =K94 -> 7977532.6 | L101: =L94 -> 2278161.3 | M101: =M94 -> 14910476 | ... O101: =O94 -> 2584084.4 | Q101: =IF(ROUND(' WP II-I-1.4'!L622-D101,2)=0,TRUE,' WP II-I-1.4'!L622-D101) -> TRUE | S101: =SUM(F101:O101)-D101 -> 0
B102: =B101+1 -> 40 | S102: =SUM(F102:O102)-D102 -> 0
B103: =B102+1 -> 41 | S103: =SUM(F103:O103)-D103 -> 0
S104: =SUM(F104:O104)-D104 -> 0
