Workbook

Sheet Prop Tax Estimate (WP1)
A1: 2025 RATE CASE
A2: ONCOR ELECTRIC DELIVERY COMPANY LLC
A3: REQUESTED AD VALOREM TAX EXPENSE ON TEST YEAR NET UTILITY PLANT
A4: TEST YEAR ENDING DECEMBER 31, 2024
A5: SPONSOR: B. L. CLUTTER
C9: YE2023 | D9: YE2024 | F9: Net Plant | G9: Taxable | H9: Taxable Value | J9: Tax Expense
B10: Source | C10: Tax Year 2024 | D10: Tax Year 2025 | F10: Increase | G10: Value Factor | H10: Increase | J10: Increase
A11: Net Utility Plant Subject to Tax | B11: II-B-5,6,8,11 | C11: =+'Book Plant Bals (WP1)'!E19 -> 2.5155277e+10 | D11: =+D26 -> 2.806372e+10 | F11: =+D11-C11 -> 2.9084431e+09 | G11: =+'Book Plant Bals (WP1)'!E25 -> 0.55299205 | H11: =ROUND(F11*G11,2) -> 1.6083459e+09
A13: Adjusted Taxable Value (owned) | B13: TPT | C13: =+C34 -> 1.3910668e+10 | D13: =+C13+H11 -> 1.5519014e+10
A14: Effective Tax Rate | C14: =+C15/C13 -> 0.01829744 | D14: =+C14 -> 0.01829744
A15: Tax, before discount | B15: TPT | C15: =+C39+C43 -> 2.5452962e+08 | D15: =+ROUND(D13*D14,2) -> 2.8395823e+08
A16: Discount | C16: =+C43 -> 363157 | D16: =+C45 -> 404497.65
A17: Net Tax Expense | C17: =+C15-C16 -> 2.5416646e+08 | D17: =+D15-D16 -> 2.8355374e+08 | J17: =+D17-C17 -> 29387272
A18: *Values above do not include non-utility plant, SPS acquisition adj, or computer software
A21: Plant in Service Net (excl. Intangibles) | B21: II-B-5 | D21: =+'[1]II-B-5'!$I$95 -> 2.8469314e+10
A22: Plant Held for Future Use | B22: II-B-6 | D22: =+'[1]II-B-6'!$I$20 -> 68155806
A23: Acquisition Adjustment | B23: II-B-11 | D23: =+'[1]II-B-11'!$I$17+'[1]II-B-11'!$I$18 -> -1453572.2
A24: Materials & Supplies | B24: II-B-8 | D24: =+'[1]II-B-8'!$I$60 -> 3.7832857e+08
A25: Less: Computer Software | B25: II-B-1,3,5 | D25: =+'[1]II-B-1'!$I$26+'[1]II-B-1'!$I$44+'[1]II-B-3'!$I$17-'[1]II-B-5'!$H$28-'[1]II-B-5'!$H$47-'[1]II-B-5'!$H$83 -> 8.5062452e+08
D26: =+D21+D22+D23+D24-D25 -> 2.806372e+10
A29: To Remove NUP, Disallowed Plant from 2024 Taxable Value and Tax Expense
A30: Total Taxable Value (owned) | C30: =+'Book Plant Bals (WP1)'!E27 -> 13932932940
A31: Non-Utility Plant | B31: Acct 121 | C31: =+'Book Plant Bals (WP1)'!E23 -> 18675708
A32: Disallowed Plant | C32: 21586318
A33: At Market Value | C33: =+ROUND((C31+C32)*'Book Plant Bals (WP1)'!E25,2) -> 22264580
A34: Taxable Value (owned), excl NUP, Disallowance | C34: =+C30-C33 -> 1.3910668e+10
A35: NUP, Disallowance % of total | C35: =+C33/C30 -> 0.0015979823
A37: Tax Expense, excl PPA | C37: =+'Book Plant Bals (WP1)'!E35-'Book Plant Bals (WP1)'!E36 -> 2.5457327e+08
A38: Tax Expense on NUP, Disallowance | C38: =+ROUND(C35*C37,2) -> 406803.58
A39: Tax Expense, excl NUP, Disallowance | C39: =+C37-C38 -> 2.5416646e+08
A42: To Adjust Discount
A43: Discount on 2024 taxes paid | B43: TPT | C43: 363157
A44: Percentage of Total Taxable Value | C44: =+C43/C30 -> 2.6064649e-05
A45: Discount on 2025 tax due | C45: =ROUND(C44*D13,2) -> 404497.65

Sheet Book Plant Bals (WP1)
A1: 2025 RATE CASE
A2: ONCOR ELECTRIC DELIVERY COMPANY LLC
A3: ESTIMATED AD VALOREM TAX EXPENSE ON TEST YEAR NET UTILITY PLANT
A4: TEST YEAR ENDING DECEMBER 31, 2024
A5: SPONSOR: B. L. CLUTTER
A10: Beginning Balance for | B10: Tax Year 2021 | C10: Tax Year 2022 | D10: Tax Year 2023 | E10: Tax Year 2024
A11: Property, plant and equipment | B11: 2.800636e+10 | C11: 3.0079014e+10 | D11: 3.2226783e+10 | E11: 3.4871792e+10
A12: Less accumulated depreciation | B12: 9.1183235e+09 | C12: 9.5615256e+09 | D12: 1.0051836e+10 | E12: 1.0414018e+10
A13: Utility plant, less accumulated depreciation | B13: =+B11-B12 -> 1.8888036e+10 | C13: =+C11-C12 -> 2.0517489e+10 | D13: =+D11-D12 -> 2.2174947e+10 | E13: =+E11-E12 -> 2.4457774e+10
A15: New CWIP (exclude replacements) | B15: 199734843 | C15: 242323424 | D15: 363433325 | E15: 356305067
A16: Materials & Supplies | B16: 1.4421177e+08 | C16: 1.7149031e+08 | D16: 2.0362596e+08 | E16: 3.4119836e+08
A18: Gross plant subject to ad valorem taxes | B18: =+B11+B15+B16 -> 2.8350307e+10 | C18: =+C11+C15+C16 -> 3.0492828e+10 | D18: =+D11+D15+D16 -> 3.2793842e+10 | E18: =+E11+E15+E16 -> 3.5569296e+10
A19: Net plant subject to ad valorem taxes | B19: =+B18-B12 -> 1.9231983e+10 | C19: =+C18-C12 -> 2.0931303e+10 | D19: =+D18-D12 -> 2.2742007e+10 | E19: =+E18-E12 -> 2.5155277e+10
A22: SPS Acquisition Adjustment (excluded) | B22: 24430547 | C22: =23452667.34 -> 23452667 | D22: =22474787.94 -> 22474788 | E22: =21586318.22 -> 21586318
A23: Non-utility Plant (excluded) | B23: 16610527 | C23: 20285171 | D23: 11912225 | E23: 18675708
A25: Book to Taxable Value % (owned) | B25: =+B30/B19 -> 0.6265507 | C25: =+C30/C19 -> 0.60298497 | D25: =+D30/D19 -> 0.59162297 | E25: =+E30/E19 -> 0.55299205
A27: Taxable Value (owned) | B27: 12075526728 | C27: 12647634069 | D27: 13475037521 | E27: 13932932940
A28: Less: SPS Acquisition Adjustment | B28: =+B22*B25 -> 15306976 | C28: =+C22*C25 -> 14141606 | D28: =+D22*D25 -> 13296601 | E28: =+E22*E25 -> 11937062
A29: Less: Non-utility plant | B29: =+B23*B25 -> 10407337 | C29: =+C23*C25 -> 12231653 | D29: =+D23*D25 -> 7047545.7 | E29: =+E23*E25 -> 10327518
A30: Taxable Value (owned), excl NUP, Acq Adj | B30: =+B27-B28-B29 -> 1.2049812e+10 | C30: =+C27-C28-C29 -> 1.2621261e+10 | D30: =+D27-D28-D29 -> 1.3454693e+10 | E30: =+E27-E28-E29 -> 1.3910668e+10
A31: Taxable Value (leased) | B31: 85223140 | C31: 99937425 | D31: 115020101 | E31: 109718055
A32: Total Taxable Value, excl NUP | B32: =+B30+B31 -> 1.2135036e+10 | C32: =+C30+C31 -> 1.2721198e+10 | D32: =+D30+D31 -> 1.3569713e+10 | E32: =+E30+E31 -> 1.4020386e+10
A35: Total Ad Valorem Tax Expense (4082602) | B35: 2.6178317e+08 | C35: 2.5788081e+08 | D35: 2.4103612e+08 | E35: =254333384.25 -> 2.5433338e+08
A36: Less: Prior Period Adjustments | B36: 5972.95 | C36: -36086.78 | D36: -3324919.3 | E36: -239884.31
A37: Less: SPS Acquisition Adjustment | B37: =ROUND(+(B28/B27)*(B35-B36),2) -> 331829.61 | C37: =ROUND(+(C28/C27)*(C35-C36),2) -> 288382.72 | D37: =ROUND(+(D28/D27)*(D35-D36),2) -> 241125.2 | E37: =ROUND(+(E28/E27)*(E35-E36),2) -> 218106.05
A38: Less: Non-utility Plant | B38: =ROUND(+(B29/B27)*(B35-B36-B37),2) -> 225327.65 | C38: =ROUND(+(C29/C27)*(C35-C36),2) -> 249434.01 | D38: =ROUND(+(D29/D27)*(D35-D36),2) -> 127802.65 | E38: =ROUND(+(E29/E27)*(E35-E36),2) -> 188697.53
A39: Ad Valorem Tax Expense (owned) | B39: =+B35-B36-B37-B38 -> 2.6122004e+08 | C39: =+C35-C36-C37-C38 -> 2.5737908e+08 | D39: =+D35-D36-D37-D38 -> 2.4399211e+08 | E39: =+E35-E36-E37-E38 -> 2.5416646e+08
A41: Effective Tax Rate | B41: =+B39/B30 -> 0.021678349 | C41: =+C39/C30 -> 0.020392501 | D41: =+D39/D30 -> 0.018134349 | E41: =+E39/E30 -> 0.018271334

Sheet Ad Valorem Exp by Month (WP2)
A1: 2025 RATE CASE
A2: ONCOR ELECTRIC DELIVERY COMPANY LLC
A3: AD VALOREM TAX EXPENSE BY MONTH
A4: TEST YEAR ENDING DECEMBER 31, 2024
A5: SPONSOR: B. L. CLUTTER
A10: Line No | B10: Month | C10: Expense | D10: FERC Account
B11: (a) | C11: (b) | D11: (c)
A13: 1 | B13: January | C13: 22514219 | D13: 408
A14: =+A13+1 -> 2 | B14: February | C14: 22439110 | D14: 408
A15: =+A14+1 -> 3 | B15: March | C15: 22538585 | D15: 408
A16: =+A15+1 -> 4 | B16: April | C16: 22564079 | D16: 408
A17: =+A16+1 -> 5 | B17: May | C17: 22526652 | D17: 408
A18: =+A17+1 -> 6 | B18: June | C18: 21135507 | D18: 408
A19: =+A18+1 -> 7 | B19: July | C19: 21137159 | D19: 408
A20: =+A19+1 -> 8 | B20: August | C20: 21135507 | D20: 408
A21: =+A20+1 -> 9 | B21: September | C21: 21137578 | D21: 408
A22: =+A21+1 -> 10 | B22: October | C22: 21135659 | D22: 408
A23: =+A22+1 -> 11 | B23: November | C23: 21135507 | D23: 408
A24: =+A23+1 -> 12 | B24: December | C24: 14933820 | D24: 408
A25: =+A24+1 -> 13
A26: =+A25+1 -> 14 | B26: Total | C26: =SUM(C13:C25) -> 2.5433338e+08
