Workbook
Name AFT_DIST: 'II-I-Total'!#REF!
Name Assign_Tbl: #REF!
Name Assign_Tbl_2016: #REF!
Name DA: #REF!
Name DA_0222: #REF!
Name DA_2: #REF!
Name FactorTable: 'II-I-MET'!$G$1318:$T$1412
Name FactorTable: 'II-I-TBILLTDCS'!$G$1318:$T$1412
Name FactorTable: 'II-I-Total'!#REF!
Name FactorTable: 'II-I-DIST'!$G$1318:$T$1412
Name FFT_D: 'II-I-DIST'!$B$1014:$L$1163
Name x: 'II-I-TBILLTDCS'!$G$1318:$T$1412

Sheet LinkSheet
D4: Description | F4: Total | G4: Residential | H4: Secondary | I4: Secondary | J4: Primary DL | K4: Primary DL | L4: Primary | M4: Transmission | N4: Lighting | O4: Wholesale | P4: Wholesale
H5: <=10kW | I5: >10kW | J5: <=10kW | K5: >10kW | L5: Substation | O5: Substation | P5: DLS
D8: DIST Function Revenue ex 565 & A928: Adjusted | F8: =SUM(G8:P8) -> 2.3066259e+09 | G8: ='WP II-I-1.7'!E23 -> 1.2075454e+09 | H8: ='WP II-I-1.7'!F23 -> 41122596 | I8: ='WP II-I-1.7'!G23 -> 8.1825418e+08 | J8: ='WP II-I-1.7'!H23 -> 295364.15 | K8: ='WP II-I-1.7'!I23 -> 1.3369402e+08 | L8: ='WP II-I-1.7'!J23 -> 13404715 | M8: ='WP II-I-1.7'!K23 -> 24606815 | N8: ='WP II-I-1.7'!L23 -> 59672372 | ... P8: ='WP II-I-1.7'!N23 -> 6549864 | S8: =IF(ROUND(F45+F46+F8-'WP II-I-1.1'!G456,1)=0,TRUE,F45+F46+F8-'WP II-I-1.1'!G456) -> TRUE
D10: MET Function Revenue Req | F10: =SUM(G10:P10) -> 2.0034106e+08 | G10: ='WP II-I-1.7'!E25 -> 1.1168499e+08 | H10: ='WP II-I-1.7'!F25 -> 17198917 | I10: ='WP II-I-1.7'!G25 -> 53110886 | J10: ='WP II-I-1.7'!H25 -> 744278.79 | K10: ='WP II-I-1.7'!I25 -> 15544460 | L10: ='WP II-I-1.7'!J25 -> 532402.95 | M10: ='WP II-I-1.7'!K25 -> 1172829.3 | N10: ='WP II-I-1.7'!L25 -> 142786.02 | ... P10: ='WP II-I-1.7'!N25 -> 146686.46 | S10: =IF(ROUND(F10-'WP II-I-1.1'!H456,1)=0,TRUE,F10-'WP II-I-1.1'!H456) -> TRUE
D12: CUSTOMER Function Revenue Req | F12: =SUM(G12:P12) -> 1.0437939e+08 | G12: ='WP II-I-1.7'!E27 -> 57205975 | H12: ='WP II-I-1.7'!F27 -> 8455436.7 | I12: ='WP II-I-1.7'!G27 -> 27857670 | J12: ='WP II-I-1.7'!H27 -> 359398.35 | K12: ='WP II-I-1.7'!I27 -> 7883822.9 | L12: ='WP II-I-1.7'!J27 -> 305330.92 | M12: ='WP II-I-1.7'!K27 -> 741936.81 | N12: ='WP II-I-1.7'!L27 -> 1471849 | ... P12: ='WP II-I-1.7'!N27 -> 68580.765 | S12: =IF(ROUND(F12-'WP II-I-1.1'!I456,1)=0,TRUE,F12-'WP II-I-1.1'!I456) -> TRUE
D14: DIST+MET+CUST:
D15: Total Plant: Gross | F15: =SUM(G15:P15) -> 1.7037413e+10 | G15: ='II-I-Total'!J60 -> 9.2980892e+09 | H15: ='II-I-Total'!K60 -> 4.5976014e+08 | I15: ='II-I-Total'!L60 -> 5.6849262e+09 | J15: ='II-I-Total'!M60 -> 6766368 | K15: ='II-I-Total'!N60 -> 8.8403031e+08 | L15: ='II-I-Total'!O60 -> 75057775 | M15: ='II-I-Total'!P60 -> 21799669 | N15: ='II-I-Total'!Q60 -> 5.5464338e+08 | ... P15: ='II-I-Total'!S60 -> 43359630
D16: Return on Rate Base (cost-based) | F16: =SUM(G16:P16) -> 6.8300051e+08 | G16: ='II-I-Total'!J83 -> 3.7983407e+08 | H16: ='II-I-Total'!K83 -> 15300982 | I16: ='II-I-Total'!L83 -> 2.3799621e+08 | J16: ='II-I-Total'!M83 -> 245203.7 | K16: ='II-I-Total'!N83 -> 38356623 | L16: ='II-I-Total'!O83 -> 3620199.3 | M16: ='II-I-Total'!P83 -> 1383463.3 | N16: ='II-I-Total'!Q83 -> 3922745.9 | ... P16: ='II-I-Total'!S83 -> 1908877.7 | S16: =IF(F16-(SUM('WP II-I-1.1'!G461:I461))=0,TRUE,F16-(SUM('WP II-I-1.1'!G461:I461))) -> TRUE
D17: Depreciation Expense | F17: =SUM(G17:P17) -> 5.4634784e+08 | G17: ='II-I-Total'!J22 -> 2.9377371e+08 | H17: ='II-I-Total'!K22 -> 17898989 | I17: ='II-I-Total'!L22 -> 1.7524036e+08 | J17: ='II-I-Total'!M22 -> 385591.23 | K17: ='II-I-Total'!N22 -> 29457396 | L17: ='II-I-Total'!O22 -> 1951234.2 | M17: ='II-I-Total'!P22 -> 869060.79 | N17: ='II-I-Total'!Q22 -> 25252299 | ... P17: ='II-I-Total'!S22 -> 1286394.1
D18: Federal Income Tax (cost-based) | F18: =SUM(G18:P18) -> 82404686 | G18: ='II-I-Total'!J25 -> 45850278 | H18: ='II-I-Total'!K25 -> 1770897.1 | I18: ='II-I-Total'!L25 -> 28788315 | J18: ='II-I-Total'!M25 -> 25535.902 | K18: ='II-I-Total'!N25 -> 4606241.1 | L18: ='II-I-Total'!O25 -> 442044.23 | M18: ='II-I-Total'!P25 -> 162487.89 | N18: ='II-I-Total'!Q25 -> 473466.34 | ... P18: ='II-I-Total'!S25 -> 232790.75 | S18: =IF(ROUND(F18-(SUM('WP II-I-1.1'!G465:I465)-'WP II-I-1.1'!F465),1)=0,TRUE,F18-(SUM('WP II-I-1.1'!G465:I465)-'WP II-I-1.1'!F36)) -> 2.9802322e-08
D19: Taxes Other Than FIT | F19: =SUM(G19:P19) -> 4.604982e+08 | G19: ='II-I-Total'!J24 -> 2.10698e+08 | H19: ='II-I-Total'!K24 -> 8641668.9 | I19: ='II-I-Total'!L24 -> 1.7865294e+08 | J19: ='II-I-Total'!M24 -> 71539.685 | K19: ='II-I-Total'!N24 -> 28656332 | L19: ='II-I-Total'!O24 -> 3850802.2 | M19: ='II-I-Total'!P24 -> 22791529 | N19: ='II-I-Total'!Q24 -> 5993922.6 | ... P19: ='II-I-Total'!S24 -> 811399.08
C21: DIST Plant Function:
D22: Distribution Plant - Net | F22: =SUM(G22:P22) -> 9.0423092e+09 | G22: ='II-I-DIST'!J313 -> 5.0415428e+09 | H22: ='II-I-DIST'!K313 -> 1.6891482e+08 | I22: ='II-I-DIST'!L313 -> 3.1866993e+09 | J22: ='II-I-DIST'!M313 -> 1134336 | K22: ='II-I-DIST'!N313 -> 4.8010812e+08 | L22: ='II-I-DIST'!O313 -> 41534062 | M22: ='II-I-DIST'!P313 -> 9445430.7 | N22: ='II-I-DIST'!Q313 -> 81890651 | ... P22: ='II-I-DIST'!S313 -> 26061601
C23: A360 | D23: Land and Land Rights - Net | F23: =SUM(G23:P23) -> 13350684 | G23: ='II-I-DIST'!J133-'II-I-DIST'!J280 -> 7271694.3 | H23: ='II-I-DIST'!K133-'II-I-DIST'!K280 -> 299569.28 | I23: ='II-I-DIST'!L133-'II-I-DIST'!L280 -> 4523793.9 | J23: ='II-I-DIST'!M133-'II-I-DIST'!M280 -> 1535.9234 | K23: ='II-I-DIST'!N133-'II-I-DIST'!N280 -> 650080.09 | L23: ='II-I-DIST'!O133-'II-I-DIST'!O280 -> 51624.716 | M23: ='II-I-DIST'!P133-'II-I-DIST'!P280 -> 12272.058 | N23: ='II-I-DIST'!Q133-'II-I-DIST'!Q280 -> 498637.69 | ... P23: ='II-I-DIST'!S133-'II-I-DIST'!S280 -> 35288.15
C24: A361 | D24: Structures and Improvements - Net | F24: =SUM(G24:P24) -> 95316076 | G24: ='II-I-DIST'!J134-'II-I-DIST'!J281 -> 51915646 | H24: ='II-I-DIST'!K134-'II-I-DIST'!K281 -> 2138749.5 | I24: ='II-I-DIST'!L134-'II-I-DIST'!L281 -> 32297244 | J24: ='II-I-DIST'!M134-'II-I-DIST'!M281 -> 10965.595 | K24: ='II-I-DIST'!N134-'II-I-DIST'!N281 -> 4641191.8 | L24: ='II-I-DIST'!O134-'II-I-DIST'!O281 -> 368570.29 | M24: ='II-I-DIST'!P134-'II-I-DIST'!P281 -> 87615.321 | N24: ='II-I-DIST'!Q134-'II-I-DIST'!Q281 -> 3559981.6 | ... P24: ='II-I-DIST'!S134-'II-I-DIST'!S281 -> 251936.76
C25: A362 | D25: Station Equipment - Net | F25: =SUM(G25:P25) -> 1.2965161e+09 | G25: ='II-I-DIST'!J135-'II-I-DIST'!J282 -> 6.8238622e+08 | H25: ='II-I-DIST'!K135-'II-I-DIST'!K282 -> 16664019 | I25: ='II-I-DIST'!L135-'II-I-DIST'!L282 -> 4.3936961e+08 | J25: ='II-I-DIST'!M135-'II-I-DIST'!M282 -> 248393.75 | K25: ='II-I-DIST'!N135-'II-I-DIST'!N282 -> 1.0513274e+08 | L25: ='II-I-DIST'!O135-'II-I-DIST'!O282 -> 38019650 | M25: ='II-I-DIST'!P135-'II-I-DIST'!P282 -> 0 | N25: ='II-I-DIST'!Q135-'II-I-DIST'!Q282 -> 4431672.8 | ... P25: ='II-I-DIST'!S135-'II-I-DIST'!S282 -> 5706896.8
D26: 4CP Retail Allocation Factor | F26: =SUM(G26:P26) -> 1 | G26: ='II-I-DIST'!J1341 -> 0.45880672 | H26: ='II-I-DIST'!K1341 -> 0.012824408 | I26: ='II-I-DIST'!L1341 -> 0.33353593 | J26: ='II-I-DIST'!M1341 -> 0.00013264334 | K26: ='II-I-DIST'!N1341 -> 0.083853975 | L26: ='II-I-DIST'!O1341 -> 0.027463664 | M26: ='II-I-DIST'!P1341 -> 0.083382661 | N26: ='II-I-DIST'!Q1341 -> 0 | O26: 0 | P26: 0
D28: NCP (kW) | G28: ='WP II-I-2.2'!E37 -> 15210693 | H28: ='WP II-I-2.2'!F37 -> 371448.4 | I28: ='WP II-I-2.2'!G37 -> 9793744.4 | J28: ='WP II-I-2.2'!H37 -> 5536.8074 | K28: ='WP II-I-2.2'!I37 -> 2343455.6 | L28: ='WP II-I-2.2'!J37 -> 847474.94 | M28: ='WP II-I-2.2'!K37 -> 2790485.9 | N28: ='WP II-I-2.2'!L37 -> 98783.961 | ... P28: ='WP II-I-2.2'!N37 -> 127209.27
D30: DIST Function Revenue: Adjusted | F30: =SUM(G30:P30) -> 3.9607946e+09 | G30: ='II-I-DIST'!J37 -> 1.9665583e+09 | H30: ='II-I-DIST'!K37 -> 62349174 | I30: ='II-I-DIST'!L37 -> 1.3699899e+09 | J30: ='II-I-DIST'!M37 -> 515183.39 | K30: ='II-I-DIST'!N37 -> 2.7237864e+08 | L30: ='II-I-DIST'!O37 -> 58811986 | M30: ='II-I-DIST'!P37 -> 1.6246169e+08 | N30: ='II-I-DIST'!Q37 -> 59696005 | ... P30: ='II-I-DIST'!S37 -> 6552465.6 | S30: =IF(ROUND(F30-'WP II-I-1.1'!G456,2)=0,TRUE,F30-'WP II-I-1.1'!G456) -> TRUE
D31: TRAN Function Revenue Requirement | F31: ='WP II-I-1.1'!F456 -> 1.4451764e+09
C34: DIST Function:
D35: O&M Expenses | F35: =SUM(G35:P35) -> 1.9676251e+09 | G35: ='II-I-DIST'!J15 -> 9.2562883e+08 | H35: ='II-I-DIST'!K15 -> 25721821 | I35: ='II-I-DIST'!L15 -> 6.5841473e+08 | J35: ='II-I-DIST'!M15 -> 291840.01 | K35: ='II-I-DIST'!N15 -> 1.6020127e+08 | L35: ='II-I-DIST'!O15 -> 47191842 | M35: ='II-I-DIST'!P15 -> 1.3785413e+08 | N35: ='II-I-DIST'!Q15 -> 10957441 | ... P35: ='II-I-DIST'!S15 -> 1148504.9
D36: Customer Expenses | F36: =SUM(G36:P36) -> 245305.53 | G36: ='II-I-DIST'!J16 -> 211382.27 | H36: ='II-I-DIST'!K16 -> 20459.035 | I36: ='II-I-DIST'!L16 -> 10111.178 | J36: ='II-I-DIST'!M16 -> 238.26144 | K36: ='II-I-DIST'!N16 -> 203.54548 | L36: ='II-I-DIST'!O16 -> -91.058921 | M36: ='II-I-DIST'!P16 -> -384.8685 | N36: ='II-I-DIST'!Q16 -> 3371.9531 | ... P36: ='II-I-DIST'!S16 -> 10.906226
D37: A&G Expenses | F37: =SUM(G37:P37) -> 4.2312645e+08 | G37: ='II-I-DIST'!J17 -> 2.283512e+08 | H37: ='II-I-DIST'!K17 -> 7879417.5 | I37: ='II-I-DIST'!L17 -> 1.4405275e+08 | J37: ='II-I-DIST'!M17 -> 73200.4 | K37: ='II-I-DIST'!N17 -> 24811551 | L37: ='II-I-DIST'!O17 -> 2275901 | M37: ='II-I-DIST'!P17 -> 333312.72 | N37: ='II-I-DIST'!Q17 -> 13755289 | ... P37: ='II-I-DIST'!S17 -> 1325254.8
D38: Depreciation & Amortization Expense | F38: =SUM(G38:P38) -> 4.5981714e+08 | G38: ='II-I-DIST'!J20 -> 2.4554112e+08 | H38: ='II-I-DIST'!K20 -> 10276121 | I38: ='II-I-DIST'!L20 -> 1.5254519e+08 | J38: ='II-I-DIST'!M20 -> 53564.308 | K38: ='II-I-DIST'!N20 -> 22671112 | L38: ='II-I-DIST'!O20 -> 1729044.2 | M38: ='II-I-DIST'!P20 -> 355894.65 | N38: ='II-I-DIST'!Q20 -> 25207217 | ... P38: ='II-I-DIST'!S20 -> 1230650.8
D39: Other Expenses (II-E-4) | F39: =SUM(G39:P39) -> -2772903.9 | G39: ='II-I-DIST'!J21 -> -1543390.6 | H39: ='II-I-DIST'!K21 -> -51305.984 | I39: ='II-I-DIST'!L21 -> -976083.78 | J39: ='II-I-DIST'!M21 -> -353.45194 | K39: ='II-I-DIST'!N21 -> -149598.65 | L39: ='II-I-DIST'!O21 -> -14829.983 | M39: ='II-I-DIST'!P21 -> -2808.1134 | N39: ='II-I-DIST'!Q21 -> -24635.28 | ... P39: ='II-I-DIST'!S21 -> -8120.6299
D40: Taxes Other Than Federal Income Tax | F40: =SUM(G40:P40) -> 4.474502e+08 | G40: ='II-I-DIST'!J24 -> 2.0342872e+08 | H40: ='II-I-DIST'!K24 -> 7522309.1 | I40: ='II-I-DIST'!L24 -> 1.7519255e+08 | J40: ='II-I-DIST'!M24 -> 23085.31 | K40: ='II-I-DIST'!N24 -> 27643694 | L40: ='II-I-DIST'!O24 -> 3816059.2 | M40: ='II-I-DIST'!P24 -> 22715111 | N40: ='II-I-DIST'!Q24 -> 5980508.8 | ... P40: ='II-I-DIST'!S24 -> 802088.52 | S40: =IF(ROUND(F40-'WP II-I-1.1'!G464,2)=0,TRUE,F40-'WP II-I-1.1'!G464) -> TRUE
D41: Federal Income Tax | F41: =SUM(G41:P41) -> 78221385 | G41: ='II-I-DIST'!J25 -> 43523262 | H41: ='II-I-DIST'!K25 -> 1413378.3 | I41: ='II-I-DIST'!L25 -> 27675494 | J41: ='II-I-DIST'!M25 -> 10069.517 | K41: ='II-I-DIST'!N25 -> 4281733.1 | L41: ='II-I-DIST'!O25 -> 430785.89 | M41: ='II-I-DIST'!P25 -> 136515.79 | N41: ='II-I-DIST'!Q25 -> 468980.55 | ... P41: ='II-I-DIST'!S25 -> 229814.61 | S41: =IF(ROUND(F41-'WP II-I-1.1'!G465,2)=0,TRUE,F41-'WP II-I-1.1'!G465) -> TRUE
D42: Return on Rate Base | F42: =SUM(G42:P42) -> 6.3883984e+08 | G42: ='II-I-DIST'!J27 -> 3.5527283e+08 | H42: ='II-I-DIST'!K27 -> 11529737 | I42: ='II-I-DIST'!L27 -> 2.2624227e+08 | J42: ='II-I-DIST'!M27 -> 82109.809 | K42: ='II-I-DIST'!N27 -> 34931887 | L42: ='II-I-DIST'!O27 -> 3501360.2 | M42: ='II-I-DIST'!P27 -> 1107731.7 | N42: ='II-I-DIST'!Q27 -> 3875733.7 | ... P42: ='II-I-DIST'!S27 -> 1877498.1
D43: Minus Other Revenues | F43: =SUM(G43:P43) -> 51757982 | G43: ='II-I-DIST'!J31 -> 33855633 | H43: ='II-I-DIST'!K31 -> 1962762 | I43: ='II-I-DIST'!L31 -> 13167153 | J43: ='II-I-DIST'!M31 -> 18570.774 | K43: ='II-I-DIST'!N31 -> 2013214.5 | L43: ='II-I-DIST'!O31 -> 118085.83 | M43: ='II-I-DIST'!P31 -> 37812.6 | N43: ='II-I-DIST'!Q31 -> 527901.22 | ... P43: ='II-I-DIST'!S31 -> 53236.441
D44: Proposed Adjustment to Return On Rate Base | F44: =SUM(G44:P44) -> 0 | G44: ='II-I-DIST'!J35 -> 0 | H44: ='II-I-DIST'!K35 -> 0 | I44: ='II-I-DIST'!L35 -> 0 | J44: ='II-I-DIST'!M35 -> 0 | K44: ='II-I-DIST'!N35 -> 0 | L44: ='II-I-DIST'!O35 -> 0 | M44: ='II-I-DIST'!P35 -> 0 | N44: ='II-I-DIST'!Q35 -> 0 | ... P44: ='II-I-DIST'!S35 -> 0
D45: RateCaseExpense A928 | F45: =SUM(G45:P45) -> 1646625.8 | G45: ='WP II-I-1.7'!E18 -> 824746.22 | H45: ='WP II-I-1.7'!F18 -> 33960.679 | I45: ='WP II-I-1.7'!G18 -> 560215.85 | J45: ='WP II-I-1.7'!H18 -> 623.20619 | K45: ='WP II-I-1.7'!I18 -> 114082.03 | L45: ='WP II-I-1.7'!J18 -> 22961.48 | M45: ='WP II-I-1.7'!K18 -> 63196.956 | N45: ='WP II-I-1.7'!L18 -> 23632.914 | ... P45: ='WP II-I-1.7'!N18 -> 2601.5728
D46: A565 Transmission of Eletricity by Others | F46: =SUM(G46:P46) -> 1.652522e+09 | G46: ='II-I-DIST'!J622 -> 7.5818821e+08 | H46: ='II-I-DIST'!K622 -> 21192617 | I46: ='II-I-DIST'!L622 -> 5.5117546e+08 | J46: ='II-I-DIST'!M622 -> 219196.04 | K46: ='II-I-DIST'!N622 -> 1.3857054e+08 | L46: ='II-I-DIST'!O622 -> 45384309 | M46: ='II-I-DIST'!P622 -> 1.3779168e+08 | N46: ='II-I-DIST'!Q622 -> 0 | ... P46: ='II-I-DIST'!S622 -> 0
D47: Total Distribution Facilities Less A565 & A928 | F47: =SUM(G47:P47) -> 2.3066259e+09 | G47: ='WP II-I-1.7'!E23 -> 1.2075454e+09 | H47: ='WP II-I-1.7'!F23 -> 41122596 | I47: ='WP II-I-1.7'!G23 -> 8.1825418e+08 | J47: ='WP II-I-1.7'!H23 -> 295364.15 | K47: ='WP II-I-1.7'!I23 -> 1.3369402e+08 | L47: ='WP II-I-1.7'!J23 -> 13404715 | M47: ='WP II-I-1.7'!K23 -> 24606815 | N47: ='WP II-I-1.7'!L23 -> 59672372 | ... P47: ='WP II-I-1.7'!N23 -> 6549864

Sheet II-I-1
B2: 2022 RATE CASE
B3: ONCOR ELECTRIC DELIVERY COMPANY LLC
B4: II-I-1: CLASS REVENUE REQUIREMENT ANALYSIS
B5: TEST YEAR ENDING 12/31/2021
B6: SPONSOR: MATTHEW A. TROXLE
F9: 1 | H9: 3 | I9: 4 | J9: 5 | K9: 6 | L9: 7 | M9: 8 | N9: 9 | O9: 10 | P9: 11 | Q9: 12 | R9: 13
F10: Test Year
D11: Line | E11: Description | F11: Revenue | H11: Residential | I11: Secondary | J11: Secondary | K11: Primary | L11: Primary | M11: Primary | N11: Transmission | O11: Lighting | P11: Wholesale | Q11: Wholesale | R11: Total
F12: Requirement | I12: ≤ 10 kW | J12: > 10 kW | K12: ≤ 10 kW | L12: > 10 kW | M12: Substation | P12: XFMR | Q12: DLS | R12: TX- Retail
F13: Total | R13: =3+4+5+6+7+8+9+10
T15: check:
D16: 1 | E16: Distribution (Includes A565 & DIST RCE A928) | F16: ='II-I-DIST'!$F$33 -> 3.9607946e+09 | H16: ='II-I-DIST'!$J$33 -> 1.9665583e+09 | I16: ='II-I-DIST'!$K$33 -> 62349174 | J16: ='II-I-DIST'!$L$33 -> 1.3699899e+09 | K16: ='II-I-DIST'!$M$33 -> 515183.39 | L16: ='II-I-DIST'!$N$33 -> 2.7237864e+08 | M16: ='II-I-DIST'!$O$33 -> 58811986 | N16: ='II-I-DIST'!$P$33 -> 1.6246169e+08 | O16: ='II-I-DIST'!$Q$33 -> 59696005 | P16: ='II-I-DIST'!$R$33 -> 1481240.3 | Q16: ='II-I-DIST'!$S$33 -> 6552465.6 | R16: =SUM(H16+I16+J16+K16+L16+M16+N16+O16) -> 3.9527609e+09 | T16: =F16-P16-Q16-R16 -> 0
D17: 2 | E17: Metering | F17: ='II-I-MET'!$F$33 -> 2.0034106e+08 | H17: ='II-I-MET'!J33 -> 1.1168499e+08 | I17: ='II-I-MET'!K33 -> 17198917 | J17: ='II-I-MET'!L33 -> 53110886 | K17: ='II-I-MET'!M33 -> 744278.79 | L17: ='II-I-MET'!N33 -> 15544460 | M17: ='II-I-MET'!O33 -> 532402.95 | N17: ='II-I-MET'!P33 -> 1172829.3 | O17: ='II-I-MET'!Q33 -> 142786.02 | ... Q17: ='II-I-MET'!S33 -> 146686.46 | R17: =SUM(H17+I17+J17+K17+L17+M17+N17+O17) -> 2.0013155e+08 | T17: =F17-P17-Q17-R17 -> 0
D18: 3 | E18: Customer Function (TBILL+TDCS) | F18: ='II-I-TBILLTDCS'!$F$33 -> 1.0437939e+08 | H18: ='II-I-TBILLTDCS'!J33 -> 57205975 | I18: ='II-I-TBILLTDCS'!K33 -> 8455436.7 | J18: ='II-I-TBILLTDCS'!L33 -> 27857670 | K18: ='II-I-TBILLTDCS'!M33 -> 359398.35 | L18: ='II-I-TBILLTDCS'!N33 -> 7883822.9 | M18: ='II-I-TBILLTDCS'!O33 -> 305330.92 | N18: ='II-I-TBILLTDCS'!P33 -> 741936.81 | O18: ='II-I-TBILLTDCS'!Q33 -> 1471849 | ... Q18: ='II-I-TBILLTDCS'!S33 -> 68580.765 | R18: =SUM(H18+I18+J18+K18+L18+M18+N18+O18) -> 1.0428142e+08 | T18: =F18-P18-Q18-R18 -> 0
D19: 4 | E19: Total: | F19: =SUM(F16:F18) -> 4.265515e+09 | H19: =SUM(H16:H18) -> 2.1354493e+09 | I19: =SUM(I16:I18) -> 88003528 | J19: =SUM(J16:J18) -> 1.4509584e+09 | K19: =SUM(K16:K18) -> 1618860.5 | L19: =SUM(L16:L18) -> 2.9580692e+08 | M19: =SUM(M16:M18) -> 59649719 | N19: =SUM(N16:N18) -> 1.6437646e+08 | O19: =SUM(O16:O18) -> 61310640 | ... Q19: =SUM(Q16:Q18) -> 6767732.8 | R19: =SUM(H19+I19+J19+K19+L19+M19+N19+O19) -> 4.2571738e+09 | T19: =H19+I19+J19+K19+L19+M19+N19+O19-R19 -> 0
E22: Check: | F22: =IF('II-I-DIST'!F33='WP II-I-1.1'!G456,TRUE,'II-I-DIST'!F33-'WP II-I-1.1'!G456) -> 0.0041480064
F23: =IF('II-I-MET'!F33='WP II-I-1.1'!H456,TRUE,'II-I-MET'!F33-'WP II-I-1.1'!H456) -> -0.0024909377
F24: =IF('II-I-TBILLTDCS'!F33='WP II-I-1.1'!I456,TRUE,'II-I-TBILLTDCS'!F33-'WP II-I-1.1'!I456) -> 0.0029119849
F25: =IF(SUM(F16:F18)='II-I-Total'!F33,TRUE,SUM(F16:F18)-'II-I-Total'!F33) -> TRUE | H25: =IF(SUM(H16:H18)='II-I-Total'!J33,TRUE,SUM(H16:H18)-'II-I-Total'!J33) -> TRUE | I25: =IF(SUM(I16:I18)='II-I-Total'!K33,TRUE,SUM(I16:I18)-'II-I-Total'!K33) -> TRUE | J25: =IF(SUM(J16:J18)='II-I-Total'!L33,TRUE,SUM(J16:J18)-'II-I-Total'!L33) -> TRUE | K25: =IF(SUM(K16:K18)='II-I-Total'!M33,TRUE,SUM(K16:K18)-'II-I-Total'!M33) -> TRUE | L25: =IF(SUM(L16:L18)='II-I-Total'!N33,TRUE,SUM(L16:L18)-'II-I-Total'!N33) -> -1.1920929e-07 | M25: =IF(SUM(M16:M18)='II-I-Total'!O33,TRUE,SUM(M16:M18)-'II-I-Total'!O33) -> TRUE | N25: =IF(SUM(N16:N18)='II-I-Total'!P33,TRUE,SUM(N16:N18)-'II-I-Total'!P33) -> TRUE | O25: =IF(SUM(O16:O18)='II-I-Total'!Q33,TRUE,SUM(O16:O18)-'II-I-Total'!Q33) -> TRUE | ... Q25: =IF(SUM(Q16:Q18)='II-I-Total'!S33,TRUE,SUM(Q16:Q18)-'II-I-Total'!S33) -> TRUE | R25: =F19-P19-Q19-R19 -> 0

Sheet WP II-I-1.1
B3: ='II-I-1'!B2 -> 2022 RATE CASE
B4: ='II-I-1'!B3 -> ONCOR ELECTRIC DELIVERY COMPANY LLC
B5: II-I-1: CLASS REVENUE REQUIREMENT ANALYSIS
B6: ='II-I-1'!B5 -> TEST YEAR ENDING 12/31/2021
B7: ='II-I-1'!B6 -> SPONSOR: MATTHEW A. TROXLE
B10: WORKPAPER 1.1 - CONSOLIDATION OF FUNCTIONALIZED COST OF SERVICE
B13: Line | C13: Account | D13: Description | E13: Reference | F13: TRAN | G13: DIST | H13: MET | I13: TDCS | J13: Total
C14: Number | E14: Schedule
C15: (a) | D15: (b) | E15: (c) | F15: (d) | G15: (e) | H15: (f) | I15: (i) | J15: (j)
B17: =B16+1 -> 1 | C17: Intangible Plant - Gross | E17: II-B-1
B18: =B17+1 -> 2 | C18: A301 | D18: Organization | F18: 0 | G18: 0 | H18: 0 | I18: 0 | J18: =SUM(F18:I18) -> 0 | K18: =J18-SUM(F18:I18) -> 0 | V18: 0 | W18: 0 | X18: 0 | Y18: 0
B19: =B18+1 -> 3 | C19: A302 | D19: Franchise & Consents | F19: 0 | G19: 0 | H19: 0 | I19: 0 | J19: =SUM(F19:I19) -> 0 | K19: =J19-SUM(F19:I19) -> 0 | V19: 0 | W19: 0 | X19: 0 | Y19: 0
B20: =B19+1 -> 4 | C20: A303 | D20: Miscellaneous Intangible Plant | F20: 2.4730602e+08 | G20: 3.2333337e+08 | H20: 1.8530171e+08 | I20: 3.1040917e+08 | J20: =SUM(F20:I20) -> 1.0663503e+09 | K20: =J20-SUM(F20:I20) -> 0 | V20: 2.4730602e+08 | W20: 3.2333337e+08 | X20: 1.8530171e+08 | Y20: 3.1040917e+08
B21: =B20+1 -> 5 | C21: Intangible plant - Accumulated Depreciation | E21: II-B-5 | K21: =J21-SUM(F21:I21) -> 0
B22: =B21+1 -> 6 | C22: A301 | D22: Organization | F22: 0 | G22: 0 | H22: 0 | I22: 0 | J22: =SUM(F22:I22) -> 0 | K22: =J22-SUM(F22:I22) -> 0 | V22: 0 | W22: 0 | X22: 0 | Y22: 0
B23: =B22+1 -> 7 | C23: A302 | D23: Franchise and Consents | F23: 0 | G23: 0 | H23: 0 | I23: 0 | J23: =SUM(F23:I23) -> 0 | K23: =J23-SUM(F23:I23) -> 0 | V23: 0 | W23: 0 | X23: 0 | Y23: 0
B24: =B23+1 -> 8 | C24: A303 | D24: Miscellaneous Intangible Plant | F24: 99337446 | G24: 1.1412285e+08 | H24: 1.5516142e+08 | I24: 84146160 | J24: =SUM(F24:I24) -> 4.5276788e+08 | K24: =J24-SUM(F24:I24) -> 0 | V24: 99337446 | W24: 1.1412285e+08 | X24: 1.5516142e+08 | Y24: 84146160
B25: =B24+1 -> 9 | C25: Transmission Plant - Gross | E25: II-B-1 | K25: =J25-SUM(F25:I25) -> 0
B26: =B25+1 -> 10 | C26: A349 | D26: Land Owned in Fee | F26: 1.1590633e+08 | G26: 0 | H26: 0 | I26: 0 | J26: =SUM(F26:I26) -> 1.1590633e+08 | K26: =J26-SUM(F26:I26) -> 0 | V26: 1.1590633e+08 | W26: 0 | X26: 0 | Y26: 0
B27: =B26+1 -> 11 | C27: A350 | D27: Land and Land Rights | F27: 6.159264e+08 | G27: 0 | H27: 0 | I27: 0 | J27: =SUM(F27:I27) -> 6.159264e+08 | K27: =J27-SUM(F27:I27) -> 0 | V27: 6.159264e+08 | W27: 0 | X27: 0 | Y27: 0
B28: =B27+1 -> 12 | C28: A352 | D28: Structures and Improvements | F28: 4.2004589e+08 | G28: 0 | H28: 0 | I28: 0 | J28: =SUM(F28:I28) -> 4.2004589e+08 | K28: =J28-SUM(F28:I28) -> 0 | V28: 4.2004589e+08 | W28: 0 | X28: 0 | Y28: 0
B29: =B28+1 -> 13 | C29: A353 | D29: Station Equipment | F29: 3.4952984e+09 | G29: 3.8186065e+08 | H29: 0 | I29: 0 | J29: =SUM(F29:I29) -> 3.8771591e+09 | K29: =J29-SUM(F29:I29) -> 0 | V29: 3.4952984e+09 | W29: 3.8186065e+08 | X29: 0 | Y29: 0
B30: =B29+1 -> 14 | C30: A354 | D30: Towers and Fixtures | F30: 1.9296528e+09 | G30: 0 | H30: 0 | I30: 0 | J30: =SUM(F30:I30) -> 1.9296528e+09 | K30: =J30-SUM(F30:I30) -> 0 | V30: 1.9296528e+09 | W30: 0 | X30: 0 | Y30: 0
B31: =B30+1 -> 15 | C31: A355 | D31: Poles and Fixtures | F31: 2.8707703e+09 | G31: 0 | H31: 0 | I31: 0 | J31: =SUM(F31:I31) -> 2.8707703e+09 | K31: =J31-SUM(F31:I31) -> 0 | V31: 2.8707703e+09 | W31: 0 | X31: 0 | Y31: 0
B32: =B31+1 -> 16 | C32: A356 | D32: Overhead Conductors and Devices | F32: 3.0445813e+09 | G32: 0 | H32: 0 | I32: 0 | J32: =SUM(F32:I32) -> 3.0445813e+09 | K32: =J32-SUM(F32:I32) -> 0 | V32: 3.0445813e+09 | W32: 0 | X32: 0 | Y32: 0
B33: =B32+1 -> 17 | C33: A357 | D33: Undergound Conduit | F33: 60197135 | G33: 0 | H33: 0 | I33: 0 | J33: =SUM(F33:I33) -> 60197135 | K33: =J33-SUM(F33:I33) -> 0 | V33: 60197135 | W33: 0 | X33: 0 | Y33: 0
B34: =B33+1 -> 18 | C34: A358 | D34: Underground Conductors and Devices | F34: 84097343 | G34: 0 | H34: 0 | I34: 0 | J34: =SUM(F34:I34) -> 84097343 | K34: =J34-SUM(F34:I34) -> 0 | V34: 84097343 | W34: 0 | X34: 0 | Y34: 0
B35: =B34+1 -> 19 | C35: A359 | D35: Roads and Trails | F35: 0 | G35: 0 | H35: 0 | I35: 0 | J35: =SUM(F35:I35) -> 0 | K35: =J35-SUM(F35:I35) -> 0 | V35: 0 | W35: 0 | X35: 0 | Y35: 0
B36: =B35+1 -> 20 | C36: Transmission Plant - Accumulated Depreciation | E36: II-B-5 | K36: =J36-SUM(F36:I36) -> 0
B37: =B36+1 -> 21 | C37: A349 | D37: Land Owned in Fee | F37: 0 | G37: 0 | H37: 0 | I37: 0 | J37: =SUM(F37:I37) -> 0 | K37: =J37-SUM(F37:I37) -> 0 | V37: 0 | W37: 0 | X37: 0 | Y37: 0
B38: =B37+1 -> 22 | C38: A350 | D38: Land and Land Rights | F38: 1.067855e+08 | G38: 0 | H38: 0 | I38: 0 | J38: =SUM(F38:I38) -> 1.067855e+08 | K38: =J38-SUM(F38:I38) -> 0 | V38: 1.067855e+08 | W38: 0 | X38: 0 | Y38: 0
B39: =B38+1 -> 23 | C39: A352 | D39: Structures and Improvements | F39: 1.2805711e+08 | G39: 0 | H39: 0 | I39: 0 | J39: =SUM(F39:I39) -> 1.2805711e+08 | K39: =J39-SUM(F39:I39) -> 0 | V39: 1.2805711e+08 | W39: 0 | X39: 0 | Y39: 0
B40: =B39+1 -> 24 | C40: A353 | D40: Station Equipment | F40: 6.9304648e+08 | G40: 97170477 | H40: 0 | I40: 0 | J40: =SUM(F40:I40) -> 7.9021695e+08 | K40: =J40-SUM(F40:I40) -> 0 | V40: 6.9304648e+08 | W40: 97170477 | X40: 0 | Y40: 0
B41: =B40+1 -> 25 | C41: A354 | D41: Towers and Fixtures | F41: 4.6758005e+08 | G41: 0 | H41: 0 | I41: 0 | J41: =SUM(F41:I41) -> 4.6758005e+08 | K41: =J41-SUM(F41:I41) -> 0 | V41: 4.6758005e+08 | W41: 0 | X41: 0 | Y41: 0
B42: =B41+1 -> 26 | C42: A355 | D42: Poles and Fixtures | F42: 6.648537e+08 | G42: 0 | H42: 0 | I42: 0 | J42: =SUM(F42:I42) -> 6.648537e+08 | K42: =J42-SUM(F42:I42) -> 0 | V42: 6.648537e+08 | W42: 0 | X42: 0 | Y42: 0
B43: =B42+1 -> 27 | C43: A356 | D43: Overhead Conductors and Devices | F43: 9.7899905e+08 | G43: 0 | H43: 0 | I43: 0 | J43: =SUM(F43:I43) -> 9.7899905e+08 | K43: =J43-SUM(F43:I43) -> 0 | V43: 9.7899905e+08 | W43: 0 | X43: 0 | Y43: 0
B44: =B43+1 -> 28 | C44: A357 | D44: Undergound Conduit | F44: 19336448 | G44: 0 | H44: 0 | I44: 0 | J44: =SUM(F44:I44) -> 19336448 | K44: =J44-SUM(F44:I44) -> 0 | V44: 19336448 | W44: 0 | X44: 0 | Y44: 0
B45: =B44+1 -> 29 | C45: A358 | D45: Underground Conductors and Devices | F45: 33548402 | G45: 0 | H45: 0 | I45: 0 | J45: =SUM(F45:I45) -> 33548402 | K45: =J45-SUM(F45:I45) -> 0 | V45: 33548402 | W45: 0 | X45: 0 | Y45: 0
B46: =B45+1 -> 30 | C46: A359 | D46: Roads and Trails | F46: 0 | G46: 0 | H46: 0 | I46: 0 | J46: =SUM(F46:I46) -> 0 | K46: =J46-SUM(F46:I46) -> 0 | V46: 0 | W46: 0 | X46: 0 | Y46: 0
K47: =J47-SUM(F47:I47) -> 0
K48: =J48-SUM(F48:I48) -> 0
B49: =B48+1 -> 1 | C49: Distribution Plant - Gross | E49: II-B-1 | K49: =J49-SUM(F49:I49) -> 0
B50: =B49+1 -> 2 | C50: A360 | D50: Land and Land Rights | F50: 1320894.7 | G50: 23046028 | H50: 0 | I50: 0 | J50: =SUM(F50:I50) -> 24366923 | K50: =J50-SUM(F50:I50) -> 0 | V50: 1320894.7 | W50: 23046028 | X50: 0 | Y50: 0
B51: =B50+1 -> 3 | C51: A361 | D51: Structures and Improvements | F51: 69201900 | G51: 1.3706205e+08 | H51: 0 | I51: 0 | J51: =SUM(F51:I51) -> 2.0626395e+08 | K51: =J51-SUM(F51:I51) -> 0 | V51: 69201900 | W51: 1.3706205e+08 | X51: 0 | Y51: 0
B52: =B51+1 -> 4 | C52: A362 | D52: Station Equipment | F52: 6.102704e+08 | G52: 1.7602e+09 | H52: 0 | I52: 0 | J52: =SUM(F52:I52) -> 2.3704704e+09 | K52: =J52-SUM(F52:I52) -> 0 | V52: 6.102704e+08 | W52: 1.7602e+09 | X52: 0 | Y52: 0
B53: =B52+1 -> 5 | C53: A363 | D53: Storage Battery Equipment | F53: 0 | G53: 0 | H53: 0 | I53: 0 | J53: =SUM(F53:I53) -> 0 | K53: =J53-SUM(F53:I53) -> 0 | V53: 0 | W53: 0 | X53: 0 | Y53: 0
B54: =B53+1 -> 6 | C54: A364 | D54: Poles,Towers & Fixtures-Total | F54: 0 | G54: 2.6783583e+09 | H54: 0 | I54: 0 | J54: =SUM(F54:I54) -> 2.6783583e+09 | K54: =J54-SUM(F54:I54) -> 0 | V54: 0 | W54: 2.6783583e+09 | X54: 0 | Y54: 0
B55: =B54+1 -> 7 | C55: A365 | D55: O.H. Conductors & Devices-Total | F55: 0 | G55: 1.6754109e+09 | H55: 0 | I55: 0 | J55: =SUM(F55:I55) -> 1.6754109e+09 | K55: =J55-SUM(F55:I55) -> 0 | V55: 0 | W55: 1.6754109e+09 | X55: 0 | Y55: 0
B56: =B55+1 -> 8 | C56: A366 | D56: Underground Conduits-Total | F56: 0 | G56: 1.0821185e+09 | H56: 0 | I56: 0 | J56: =SUM(F56:I56) -> 1.0821185e+09 | K56: =J56-SUM(F56:I56) -> 0 | V56: 0 | W56: 1.0821185e+09 | X56: 0 | Y56: 0
B57: =B56+1 -> 9 | C57: A367 | D57: U.G. Conductors & Devices-Total | F57: 0 | G57: 2.5539275e+09 | H57: 0 | I57: 0 | J57: =SUM(F57:I57) -> 2.5539275e+09 | K57: =J57-SUM(F57:I57) -> 0 | V57: 0 | W57: 2.5539275e+09 | X57: 0 | Y57: 0
B58: =B57+1 -> 10 | C58: A368 | D58: Line Transformers-Total | F58: 0 | G58: 2.4930778e+09 | H58: 0 | I58: 0 | J58: =SUM(F58:I58) -> 2.4930778e+09 | K58: =J58-SUM(F58:I58) -> 0 | V58: 0 | W58: 2.4930778e+09 | X58: 0 | Y58: 0
B59: =B58+1 -> 11 | C59: A369 | D59: Services | F59: 0 | G59: 1.652239e+09 | H59: 0 | I59: 0 | J59: =SUM(F59:I59) -> 1.652239e+09 | K59: =J59-SUM(F59:I59) -> 0 | V59: 0 | W59: 1.652239e+09 | X59: 0 | Y59: 0
B60: =B59+1 -> 12 | C60: A370 | D60: Meters | F60: 0 | G60: 0 | H60: 5.7414748e+08 | I60: 0 | J60: =SUM(F60:I60) -> 5.7414748e+08 | K60: =J60-SUM(F60:I60) -> 0 | V60: 0 | W60: 0 | X60: 5.7414748e+08 | Y60: 0
B61: =B60+1 -> 13 | C61: A371 | D61: Installations on Customers' Premises | F61: 0 | G61: 54631097 | H61: 0 | I61: 0 | J61: =SUM(F61:I61) -> 54631097 | K61: =J61-SUM(F61:I61) -> 0 | V61: 0 | W61: 54631097 | X61: 0 | Y61: 0
... B64: =B63+1 -> 16 | C64: A374 | D64: Land Owned in Fee | F64: 24640358 | G64: 71344821 | H64: 0 | I64: 0 | J64: =SUM(F64:I64) -> 95985179 | K64: =J64-SUM(F64:I64) -> 0 | V64: 24640358 | W64: 71344821 | X64: 0 | Y64: 0
B65: =B64+1 -> 17 | C65: Distribution Plant - Accumulated Depreciation | E65: II-B-5 | K65: =J65-SUM(F65:I65) -> 0
B66: =B65+1 -> 18 | C66: A360 | D66: Land and Land Rights | F66: 238774.93 | G66: 9695344.4 | H66: 0 | I66: 0 | J66: =SUM(F66:I66) -> 9934119.3 | K66: =J66-SUM(F66:I66) -> 0 | V66: 238774.93 | W66: 9695344.4 | X66: 0 | Y66: 0
B67: =B66+1 -> 19 | C67: A361 | D67: Structures and Improvements | F67: 18051484 | G67: 41745978 | H67: 0 | I67: 0 | J67: =SUM(F67:I67) -> 59797462 | K67: =J67-SUM(F67:I67) -> 0 | V67: 18051484 | W67: 41745978 | X67: 0 | Y67: 0
B68: =B67+1 -> 20 | C68: A362 | D68: Station Equipment | F68: 1.2272287e+08 | G68: 4.6368393e+08 | H68: 0 | I68: 0 | J68: =SUM(F68:I68) -> 5.864068e+08 | K68: =J68-SUM(F68:I68) -> 0 | V68: 1.2272287e+08 | W68: 4.6368393e+08 | X68: 0 | Y68: 0
B69: =B68+1 -> 21 | C69: A363 | D69: Storage Battery Equipment | F69: 0 | G69: 0 | H69: 0 | I69: 0 | J69: =SUM(F69:I69) -> 0 | K69: =J69-SUM(F69:I69) -> 0 | V69: 0 | W69: 0 | X69: 0 | Y69: 0
B70: =B69+1 -> 22 | C70: A364 | D70: Poles,Towers & Fixtures-Total | F70: 0 | G70: 1.1077196e+09 | H70: 0 | I70: 0 | J70: =SUM(F70:I70) -> 1.1077196e+09 | K70: =J70-SUM(F70:I70) -> 0 | V70: 0 | W70: 1.1077196e+09 | X70: 0 | Y70: 0
B71: =B70+1 -> 23 | C71: A365 | D71: O.H. Conductors & Devices-Total | F71: 0 | G71: 6.3532801e+08 | H71: 0 | I71: 0 | J71: =SUM(F71:I71) -> 6.3532801e+08 | K71: =J71-SUM(F71:I71) -> 0 | V71: 0 | W71: 6.3532801e+08 | X71: 0 | Y71: 0
B72: =B71+1 -> 24 | C72: A366 | D72: Underground Conduits-Total | F72: 0 | G72: 4.5219352e+08 | H72: 0 | I72: 0 | J72: =SUM(F72:I72) -> 4.5219352e+08 | K72: =J72-SUM(F72:I72) -> 0 | V72: 0 | W72: 4.5219352e+08 | X72: 0 | Y72: 0
B73: =B72+1 -> 25 | C73: A367 | D73: U.G. Conductors & Devices-Total | F73: 0 | G73: 5.7804131e+08 | H73: 0 | I73: 0 | J73: =SUM(F73:I73) -> 5.7804131e+08 | K73: =J73-SUM(F73:I73) -> 0 | V73: 0 | W73: 5.7804131e+08 | X73: 0 | Y73: 0
B74: =B73+1 -> 26 | C74: A368 | D74: Line Transformers-Total | F74: 0 | G74: 7.4368699e+08 | H74: 0 | I74: 0 | J74: =SUM(F74:I74) -> 7.4368699e+08 | K74: =J74-SUM(F74:I74) -> 0 | V74: 0 | W74: 7.4368699e+08 | X74: 0 | Y74: 0
B75: =B74+1 -> 27 | C75: A369 | D75: Services | F75: 0 | G75: 1.0973141e+09 | H75: 0 | I75: 0 | J75: =SUM(F75:I75) -> 1.0973141e+09 | K75: =J75-SUM(F75:I75) -> 0 | V75: 0 | W75: 1.0973141e+09 | X75: 0 | Y75: 0
B76: =B75+1 -> 28 | C76: A370 | D76: Meters | F76: 0 | G76: 0 | H76: 3.3623986e+08 | I76: 0 | J76: =SUM(F76:I76) -> 3.3623986e+08 | K76: =J76-SUM(F76:I76) -> 0 | V76: 0 | W76: 0 | X76: 3.3623986e+08 | Y76: 0
B77: =B76+1 -> 29 | C77: A371 | D77: Installations on Customers' Premises | F77: 0 | G77: 75069053 | H77: 0 | I77: 0 | J77: =SUM(F77:I77) -> 75069053 | K77: =J77-SUM(F77:I77) -> 0 | V77: 0 | W77: 75069053 | X77: 0 | Y77: 0
... B79: =B78+1 -> 31 | C79: A373 | D79: Street Lights | F79: 0 | G79: 3.7203266e+08 | H79: 0 | I79: 0 | J79: =SUM(F79:I79) -> 3.7203266e+08 | K79: =J79-SUM(F79:I79) -> 0 | V79: 0 | W79: 3.7203266e+08 | X79: 0 | Y79: 0
K80: =J80-SUM(F80:I80) -> 0
K81: =J81-SUM(F81:I81) -> 0
B82: =B81+1 -> 1 | C82: General Plant - Gross | E82: II-B-2 | K82: =J82-SUM(F82:I82) -> 0
B83: =B82+1 -> 2 | C83: A388 | D83: Land Owned in Fee | F83: 7795889.1 | G83: 19410066 | H83: 3908190.5 | I83: 2557941 | J83: =SUM(F83:I83) -> 33672086 | K83: =J83-SUM(F83:I83) -> 0 | V83: 7795889.1 | W83: 19410066 | X83: 3908190.5 | Y83: 2557941
B84: =B83+1 -> 3 | C84: A389 | D84: Land and Land Rights | F84: 60493.9 | G84: 78748.83 | H84: 3342.98 | I84: 12.49 | J84: =SUM(F84:I84) -> 142598.2 | K84: =J84-SUM(F84:I84) -> 0 | V84: 60493.9 | W84: 78748.83 | X84: 3342.98 | Y84: 12.49
B85: =B84+1 -> 4 | C85: A390 | D85: Structures and Improvements | F85: 80530915 | G85: 141498136 | H85: 24868885 | I85: 13542694 | J85: =SUM(F85:I85) -> 2.6044063e+08 | K85: =J85-SUM(F85:I85) -> 0 | V85: 80530915 | W85: 141498136 | X85: 24868885 | Y85: 13542694
B86: =B85+1 -> 5 | C86: A391 | D86: Office Furniture & Equip. | F86: 77149138 | G86: 96093234 | H86: 66950478 | I86: 84000108 | J86: =SUM(F86:I86) -> 3.2419296e+08 | K86: =J86-SUM(F86:I86) -> 0 | V86: 77149138 | W86: 96093234 | X86: 66950478 | Y86: 84000108
B87: =B86+1 -> 6 | C87: A392 | D87: Transportation Equipment | F87: 10146633 | G87: 12716429 | H87: 0 | I87: 0 | J87: =SUM(F87:I87) -> 22863062 | K87: =J87-SUM(F87:I87) -> 0 | V87: 10146633 | W87: 12716429 | X87: 0 | Y87: 0
B88: =B87+1 -> 7 | C88: A393 | D88: Stores Equipment | F88: 1193181.8 | G88: 3228206.2 | H88: 575148.54 | I88: 0 | J88: =SUM(F88:I88) -> 4996536.6 | K88: =J88-SUM(F88:I88) -> 0 | V88: 1193181.8 | W88: 3228206.2 | X88: 575148.54 | Y88: 0
B89: =B88+1 -> 8 | C89: A394 | D89: Tools, Shop and Garage Equipment | F89: 14877076 | G89: 25982536 | H89: 2568972 | I89: 0 | J89: =SUM(F89:I89) -> 43428585 | K89: =J89-SUM(F89:I89) -> 0 | V89: 14877076 | W89: 25982536 | X89: 2568972 | Y89: 0
B90: =B89+1 -> 9 | C90: A395 | D90: Laboratory Equipment | F90: 30439016 | G90: 17734119 | H90: 3737188.6 | I90: 0 | J90: =SUM(F90:I90) -> 51910324 | K90: =J90-SUM(F90:I90) -> 0 | V90: 30439016 | W90: 17734119 | X90: 3737188.6 | Y90: 0
B91: =B90+1 -> 10 | C91: A396 | D91: Power Operated Equipment | F91: 4340670.8 | G91: 7626625.3 | H91: 930590.35 | I91: 0 | J91: =SUM(F91:I91) -> 12897886 | K91: =J91-SUM(F91:I91) -> 0 | V91: 4340670.8 | W91: 7626625.3 | X91: 930590.35 | Y91: 0
B92: =B91+1 -> 11 | C92: A397 | D92: Communication Equipment | E92: II-B-3 | F92: 81760693 | G92: 61337953 | H92: 45688861 | I92: 1554894.4 | J92: =SUM(F92:I92) -> 1.903424e+08 | K92: =J92-SUM(F92:I92) -> 0 | V92: 81760693 | W92: 61337953 | X92: 45688861 | Y92: 1554894.4
B93: =B92+1 -> 12 | C93: A398 | D93: Miscellaneous Equipment | F93: 5820094.3 | G93: 5763893.7 | H93: 1183825.7 | I93: 0 | J93: =SUM(F93:I93) -> 12767814 | K93: =J93-SUM(F93:I93) -> 0 | V93: 5820094.3 | W93: 5763893.7 | X93: 1183825.7 | Y93: 0
B94: =B93+1 -> 13 | C94: A399 | D94: Other Tangible Property | F94: 0 | G94: 0 | H94: 0 | I94: 0 | J94: =SUM(F94:I94) -> 0 | K94: =J94-SUM(F94:I94) -> 0 | V94: 0 | W94: 0 | X94: 0 | Y94: 0
B95: =B94+1 -> 14 | C95: General Plant - Accumulated Depreciation | J95: =SUM(F95:I95) -> 0 | K95: =J95-SUM(F95:I95) -> 0
B96: =B95+1 -> 15 | C96: A388 | D96: Land Owned in Fee | F96: 0 | G96: 0 | H96: 0 | I96: 0 | J96: =SUM(F96:I96) -> 0 | K96: =J96-SUM(F96:I96) -> 0 | V96: 0 | W96: 0 | X96: 0 | Y96: 0
B97: =B96+1 -> 16 | C97: A389 | D97: Land and Land Rights | F97: 10107.89 | G97: 13158.09 | H97: 558.58 | I97: 2.09 | J97: =SUM(F97:I97) -> 23826.65 | K97: =J97-SUM(F97:I97) -> 0 | V97: 10107.89 | W97: 13158.09 | X97: 558.58 | Y97: 2.09
B98: =B97+1 -> 17 | C98: A390 | D98: Structures and Improvements | F98: 6701895.4 | G98: 11904359 | H98: 2097789.6 | I98: 1141161.6 | J98: =SUM(F98:I98) -> 21845206 | K98: =J98-SUM(F98:I98) -> 0 | V98: 6701895.4 | W98: 11904359 | X98: 2097789.6 | Y98: 1141161.6
B99: =B98+1 -> 18 | C99: A391 | D99: Office Furniture & Equip. | F99: 33976470 | G99: 43244355 | H99: 37302658 | I99: 40970025 | J99: =SUM(F99:I99) -> 1.5549351e+08 | K99: =J99-SUM(F99:I99) -> 0 | V99: 33976470 | W99: 43244355 | X99: 37302658 | Y99: 40970025
B100: =B99+1 -> 19 | C100: A392 | D100: Transportation Equipment | F100: 1936739.2 | G100: 2889835.2 | H100: 0 | I100: 0 | J100: =SUM(F100:I100) -> 4826574.4 | K100: =J100-SUM(F100:I100) -> 0 | V100: 1936739.2 | W100: 2889835.2 | X100: 0 | Y100: 0
B101: =B100+1 -> 20 | C101: A393 | D101: Stores Equipment | F101: 237481.1 | G101: 642515.64 | H101: 114472.84 | I101: 0 | J101: =SUM(F101:I101) -> 994469.58 | K101: =J101-SUM(F101:I101) -> 0 | V101: 237481.1 | W101: 642515.64 | X101: 114472.84 | Y101: 0
B102: =B101+1 -> 21 | C102: A394 | D102: Tools, Shop and Garage Equipment | F102: 5850180 | G102: 10062139 | H102: 959169.15 | I102: 0 | J102: =SUM(F102:I102) -> 16871489 | K102: =J102-SUM(F102:I102) -> 0 | V102: 5850180 | W102: 10062139 | X102: 959169.15 | Y102: 0
B103: =B102+1 -> 22 | C103: A395 | D103: Laboratory Equipment | F103: 4825932.7 | G103: 2811643.6 | H103: 592509.97 | I103: 0 | J103: =SUM(F103:I103) -> 8230086.3 | K103: =J103-SUM(F103:I103) -> 0 | V103: 4825932.7 | W103: 2811643.6 | X103: 592509.97 | Y103: 0
B104: =B103+1 -> 23 | C104: A396 | D104: Power Operated Equipment | F104: 1344996.9 | G104: 2373053.9 | H104: 289556.78 | I104: 0 | J104: =SUM(F104:I104) -> 4007607.5 | K104: =J104-SUM(F104:I104) -> 0 | V104: 1344996.9 | W104: 2373053.9 | X104: 289556.78 | Y104: 0
B105: =B104+1 -> 24 | C105: A397 | D105: Communication Equipment | F105: 11568805 | G105: 7510868.4 | H105: 42151878 | I105: 274004.38 | J105: =SUM(F105:I105) -> 61505556 | K105: =J105-SUM(F105:I105) -> 0 | V105: 11568805 | W105: 7510868.4 | X105: 42151878 | Y105: 274004.38
B106: =B105+1 -> 25 | C106: A398 | D106: Miscellaneous Equipment | F106: 574284.69 | G106: 565246.04 | H106: 116093.88 | I106: 0 | J106: =SUM(F106:I106) -> 1255624.6 | K106: =J106-SUM(F106:I106) -> 0 | V106: 574284.69 | W106: 565246.04 | X106: 116093.88 | Y106: 0
B107: =B106+1 -> 26 | C107: A399 | D107: Other Tangible Property | F107: 0 | G107: 0 | H107: 0 | I107: 0 | J107: =SUM(F107:I107) -> 0 | K107: =J107-SUM(F107:I107) -> 0 | V107: 0 | W107: 0 | X107: 0 | Y107: 0
K108: =J108-SUM(F108:I108) -> 0
K109: =J109-SUM(F109:I109) -> 0
B110: =B109+1 -> 1 | C110: Other Rate Base Items | K110: =J110-SUM(F110:I110) -> 0
...

Sheet changes
A1: tbills column removed in wp ii I 1.1
E2: Row additions | H2: Row Deletions
B3: Prev | C3: New | E3: 186 | F3: Rate Case Expenses - Non-std Metering Tariff (Dkt 41890)
B4: Accumulated Deferred State Income Tax | C4: Deferred Margin Tax | E4: 186 | F4: Rate Case Expenses - Final AMS Rec Dkt 49721 | H4: 189 | I4: Gains/Losses on Reacquired Debt Post-Industry Restructure
E5: 186 | F5: Rate Case Expenses - 2018 DCRF Dkt 48231 | H5: 182 | I5: Gains/Losses on Reacquired Debt Pre-Industry Restructure
E6: 186 | F6: Rate Case Expenses - 2019 DCRF Dkt 49427 | H6: 182 | I6: Retrospective Franchise Fees
E7: 186 | F7: Rate Case Expenses - 2017 ED DOCKET 46957
E8: 186 | F8: Rate Case Expenses - 2018 TCJA Dkt 48325 | H8: 186 | I8: Rate Case Expenses - 2008 Dkt 35717 Appeals
E9: 186 | F9: Rate Case Expenses - 2021 Base Rate Case | H9: 186 | I9: Rate Case Expenses - 2010 ED RT CS Dkt 38928
E10: 189 | F10: Unamortized Losses - Reacquired Debt | H10: 186 | I10: Rate Case Expenses - 2017 Municipal Case
E11: 182 | F11: Rocky Mound Series Compensator | H11: 182 | I11: Deferred-Mtr Eqt Substations
E12: 182 | F12: COVID19-ERP Proceeds and Expenses Dkt 50664 & 50719 | H12: 182 | I12: Deferred Depr-Conv/BPL/PLC Meters
E13: 182 | F13: COVID19-Incremental Expense Dkt 50664
E14: 182 | F14: CWIP Tran & Dist Non-Service Cost Pension/OPEBs | H14: 186 | I14: Under/Over-Collected Transition Cost Revenues
E15: 182 | F15: Plant in service Tran & Dist Non-Service Cost Pension/OPEBs | H15: 182 | I15: Asset Retirement Obligations
E16: 182 | F16: TCRF Update 16 TAC 25.193 | H16: 228 | I16: Self Insurance Reserve (Transmission) (a)
E17: 186 | F17: Workers Compensation | H17: 254 | I17: Over Recovered AMS

Sheet  WP II-I-1.4
M2: =" "
B4: ='WP II-I-1.1'!B3 -> 2022 RATE CASE
B5: ='WP II-I-1.1'!B4 -> ONCOR ELECTRIC DELIVERY COMPANY LLC
B6: CONSOLIDATED FUNCTIONALIZED COST OF SERVICE
B7: ='WP II-I-1.1'!B6 -> TEST YEAR ENDING 12/31/2021
B8: ='WP II-I-2.2'!$B$7 -> SPONSOR: MATTHEW A. TROXLE
F10: TRAN | G10: DIST | H10: MET | I10: TDCS | J10: Total | L10: DIST + MET
B11: Line | D11: Revenue Requirement | E11: Source | L11: + TBILLTDCS
B13: (a) | D13: (b) | E13: (c) | F13: (d) | G13: (e) | H13: (f) | I13: (i) | J13: (j) | L13: (l)
B15: =B14+1 -> 1 | D15: O&M Expenses | E15: II-D-2 | F15: =F638+F686 -> 1.2775292e+08 | G15: =G638+G686 -> 1.9676251e+09 | H15: =H638+H686 -> 50235236 | I15: =I638+I686 -> 343150.73 | J15: =SUM(F15:I15) -> 2.1459564e+09 | L15: =SUM(G15:I15) -> 2.0182035e+09
B16: =B15+1 -> 2 | D16: Customer Expenses | E16: II-D-2 | F16: =F706+F716+F726 -> 87420.86 | G16: =G706+G716+G726 -> 245305.53 | H16: =H706+H716+H726 -> 8799722.5 | I16: =I706+I716+I726 -> 13109328 | J16: =SUM(F16:I16) -> 22241777 | L16: =SUM(G16:I16) -> 22154357
B17: =B16+1 -> 3 | D17: A&G Expenses | E17: II-D-2 | F17: =F760 -> 1.1555308e+08 | G17: =G760 -> 4.2312645e+08 | H17: =H760 -> 50135759 | I17: =I760 -> 36701329 | J17: =SUM(F17:I17) -> 6.2551662e+08 | L17: =SUM(G17:I17) -> 5.0996354e+08
B18: =B17+1 -> 4 | D18: O&M + Customer + A&G Expenses | F18: =SUM(F15:F17) -> 2.4339342e+08 | G18: =SUM(G15:G17) -> 2.3909969e+09 | H18: =SUM(H15:H17) -> 1.0917072e+08 | I18: =SUM(I15:I17) -> 50153808 | J18: =SUM(F18:I18) -> 2.7937148e+09 | L18: =SUM(G18:I18) -> 2.5503214e+09 | N18: ='WP II-I-1.1'!J462=J18 -> TRUE | P18: ='WP II-I-1.1'!F462=F18 -> TRUE | Q18: ='WP II-I-1.1'!G462=G18 -> TRUE | R18: ='WP II-I-1.1'!H462=H18 -> TRUE | S18: ='WP II-I-1.1'!I462=I18 -> TRUE | T18: ='WP II-I-1.1'!J462=J18 -> TRUE
B19: =B18+1 -> 5
B20: =B19+1 -> 6 | D20: Depreciation & Amortization (II-E-1) | E20: II-E-1 | F20: =F1035 -> 3.741449e+08 | G20: =G1035 -> 4.5981714e+08 | H20: =H1035 -> 30914364 | I20: =I1035 -> 32929277 | J20: =SUM(F20:I20) -> 8.9780568e+08 | L20: =SUM(G20:I20) -> 5.2366079e+08
B21: =B20+1 -> 7 | D21: Other (II-E-4) | E21: II-E-4 | F21: =F1037+F1038 -> 1167765.4 | G21: =G1037+G1038 -> -2772903.9 | H21: =H1037+H1038 -> 25459958 | I21: =I1037+I1038 -> 0 | J21: =SUM(F21:I21) -> 23854820 | L21: =SUM(G21:I21) -> 22687054
B22: =B21+1 -> 8 | D22: Depreciation, Amortization & Other Expenses | F22: =SUM(F20:F21) -> 3.7531266e+08 | G22: =SUM(G20:G21) -> 4.5704424e+08 | H22: =SUM(H20:H21) -> 56374322 | I22: =SUM(I20:I21) -> 32929277 | J22: =SUM(F22:I22) -> 9.216605e+08 | L22: =SUM(G22:I22) -> 5.4634784e+08 | N22: ='WP II-I-1.1'!J463=J22 -> TRUE | P22: ='WP II-I-1.1'!F463=F22 -> TRUE | Q22: ='WP II-I-1.1'!G463=G22 -> TRUE | R22: ='WP II-I-1.1'!H463=H22 -> TRUE | S22: ='WP II-I-1.1'!I463=I22 -> TRUE | T22: ='WP II-I-1.1'!J463=J22 -> TRUE
B23: =B22+1 -> 9
B24: =B23+1 -> 10 | D24: Taxes Other Than Federal Income Tax | E24: II-E-2 | F24: =+F1072 -> 1.5029276e+08 | G24: =+G1072 -> 4.474502e+08 | H24: =+H1072 -> 8538460.4 | I24: =+I1072 -> 4509539.8 | J24: =SUM(F24:I24) -> 6.1079096e+08 | L24: =SUM(G24:I24) -> 4.604982e+08 | N24: ='WP II-I-1.1'!J464=J24 -> TRUE | P24: ='WP II-I-1.1'!F464=F24 -> TRUE | Q24: ='WP II-I-1.1'!G464=G24 -> TRUE | R24: ='WP II-I-1.1'!H464=H24 -> TRUE | S24: ='WP II-I-1.1'!I464-I24 -> 0 | T24: ='WP II-I-1.1'!J464=J24 -> TRUE
B25: =B24+1 -> 11 | D25: Federal Income Tax | E25: II-E-3 | F25: =+F1132 -> 82799350 | G25: =+G1132 -> 78221385 | H25: =+H1132 -> 1649124.5 | I25: =+I1132 -> 2534176.5 | J25: =SUM(F25:I25) -> 1.6520404e+08 | L25: =SUM(G25:I25) -> 82404686 | N25: ='WP II-I-1.1'!J465=J25 -> TRUE | P25: ='WP II-I-1.1'!F465-F25 -> 0 | Q25: ='WP II-I-1.1'!G465-G25 -> 0 | R25: ='WP II-I-1.1'!H465-H25 -> 0 | S25: ='WP II-I-1.1'!I465-I25 -> 0 | T25: ='WP II-I-1.1'!J465-J25 -> 0
B26: =B25+1 -> 12
B27: =B26+1 -> 13 | D27: Return on Rate Base | E27: II-B | F27: =+F83 -> 6.364015e+08 | G27: =+G83 -> 6.3883984e+08 | H27: =+H83 -> 29703070 | I27: =+I83 -> 14457605 | J27: =SUM(F27:I27) -> 1.319402e+09 | L27: =SUM(G27:I27) -> 6.8300051e+08 | N27: ='WP II-I-1.1'!J461=J27 -> TRUE | P27: ='WP II-I-1.1'!F461-F27 -> 0 | Q27: ='WP II-I-1.1'!G461-G27 -> 0 | R27: ='WP II-I-1.1'!H461-H27 -> 0 | S27: ='WP II-I-1.1'!I461-I27 -> 0 | T27: ='WP II-I-1.1'!J461-J27 -> 0
B28: =B27+1 -> 14
B29: =B28+1 -> 15 | D29: TOTAL COST OF SERVICE | F29: =+F18+F22+F24+F25+F27 -> 1.4881997e+09 | G29: =+G18+G22+G24+G25+G27 -> 4.0125525e+09 | H29: =+H18+H22+H24+H25+H27 -> 2.0543569e+08 | I29: =+I18+I22+I24+I25+I27 -> 1.0458441e+08 | J29: =SUM(F29:I29) -> 5.8107723e+09 | L29: =SUM(G29:I29) -> 4.3225726e+09
B30: 16
B31: =B30+1 -> 17 | D31: Minus: Other Revenues | E31: II-E-5 | F31: =+F1188 -> 43023335 | G31: =+G1188 -> 51757982 | H31: =+H1188 -> 5094631 | I31: =+I1188 -> 205014.65 | J31: =SUM(F31:I31) -> 1.0008096e+08 | L31: =SUM(G31:I31) -> 57057628 | N31: ='WP II-I-1.1'!J466=-J31 -> TRUE
B32: =B31+1 -> 18
B33: =B32+1 -> 19 | D33: COST-BASED Revenue Requirement | F33: =+F29-F31 -> 1.4451764e+09 | G33: =+G29-G31 -> 3.9607946e+09 | H33: =+H29-H31 -> 2.0034106e+08 | I33: =+I29-I31 -> 1.0437939e+08 | J33: =SUM(F33:I33) -> 5.7106914e+09 | L33: =G33+H33+I33 -> 4.265515e+09 | N33: ='WP II-I-1.1'!$J$467-J33 -> 0
B42: =$B$4 -> 2022 RATE CASE
B43: =$B$5 -> ONCOR ELECTRIC DELIVERY COMPANY LLC
B44: =$B$6 -> CONSOLIDATED FUNCTIONALIZED COST OF SERVICE
B45: =$B$7 -> TEST YEAR ENDING 12/31/2021
B46: =$B$8 -> SPONSOR: MATTHEW A. TROXLE
F48: TRAN | G48: DIST | H48: MET | I48: TDCS | J48: Total | L48: =L$10 -> DIST + MET
B49: Line | D49: Return On Rate Base | E49: Source | L49: =L$11 -> + TBILLTDCS
B51: (a) | D51: (b) | E51: (c) | F51: (d) | G51: (e) | H51: (f) | I51: (i) | J51: (j) | L51: (l)
B53: =B52+1 -> 1 | D53: Intangible Plant: Original Cost | E53: II-B-1 | F53: =F106 -> 2.4730602e+08 | G53: =G106 -> 3.2333337e+08 | H53: =H106 -> 1.8530171e+08 | I53: =I106 -> 3.1040917e+08 | J53: =SUM(F53:I53) -> 1.0663503e+09 | L53: =SUM(G53:I53) -> 8.1904426e+08 | N53: =SUM('WP II-I-1.1'!F18:I20)=J53 -> TRUE
B54: =B53+1 -> 2 | D54: Transmission Plant: Original Cost | E54: II-B-1 | F54: =F118 -> 1.2636476e+10 | G54: =G118 -> 3.8186065e+08 | H54: =H118 -> 0 | I54: =I118 -> 0 | J54: =SUM(F54:I54) -> 1.3018337e+10 | L54: =SUM(G54:I54) -> 3.8186065e+08 | N54: =SUM('WP II-I-1.1'!F26:I35)=J54 -> TRUE
B55: =B54+1 -> 3 | D55: Distribution Plant: Original Cost | E55: II-B-1 | F55: =F154 -> 7.0543355e+08 | G55: =G154 -> 1.461882e+10 | H55: =H154 -> 5.7414748e+08 | I55: =I154 -> 0 | J55: =SUM(F55:I55) -> 1.5898401e+10 | L55: =SUM(G55:I55) -> 1.5192967e+10 | N55: =SUM('WP II-I-1.1'!F50:I64)=J55 -> TRUE
B56: =B55+1 -> 4 | D56: Intangible, Transmission, Distribution Plant: Original Cost | F56: =SUM(F53:F55) -> 1.3589215e+10 | G56: =SUM(G53:G55) -> 1.5324014e+10 | H56: =SUM(H53:H55) -> 7.594492e+08 | I56: =SUM(I53:I55) -> 3.1040917e+08 | J56: =SUM(F56:I56) -> 2.9983088e+10 | L56: =SUM(G56:I56) -> 1.6393872e+10 | N56: =SUM(F56:I56)=J56 -> TRUE
B57: =B56+1 -> 5 | L57: =SUM(G57:I57) -> 0
B58: =B57+1 -> 6 | D58: General Plant: Original Cost | E58: II-B-2 | F58: =+F194 -> 2.3235311e+08 | G58: =+G194 -> 3.3013199e+08 | H58: =+H194 -> 1.0472662e+08 | I58: =+I194 -> 1.0010076e+08 | J58: =SUM(F58:I58) -> 7.6731248e+08 | L58: =SUM(G58:I58) -> 5.3495937e+08 | N58: =SUM('WP II-I-1.1'!F83:I91)+SUM('WP II-I-1.1'!F93:I94)=J58 -> TRUE
B59: =B58+1 -> 7 | D59: Communication Equipment: Original Cost | E59: II-B-3 | F59: =+F212 -> 81760693 | G59: =+G212 -> 61337953 | H59: =+H212 -> 45688861 | I59: =+I212 -> 1554894.4 | J59: =SUM(F59:I59) -> 1.903424e+08 | L59: =SUM(G59:I59) -> 1.0858171e+08 | N59: =SUM('WP II-I-1.1'!F92:I92)=J59 -> TRUE
B60: =B59+1 -> 8 | D60: Total Plant | F60: =+F56+F58+F59 -> 1.3903329e+10 | G60: =+G56+G58+G59 -> 1.5715484e+10 | H60: =+H56+H58+H59 -> 9.0986468e+08 | I60: =+I56+I58+I59 -> 4.1206483e+08 | J60: =SUM(F60:I60) -> 3.0940742e+10 | L60: =SUM(G60:I60) -> 1.7037413e+10 | N60: =SUM(F60:I60)=J60 -> TRUE
B61: =B60+1 -> 9 | L61: =SUM(G61:I61) -> 0
B62: =B61+1 -> 10 | D62: Minus: Accumulated Depreciation | E62: II-B-5 | F62: =+F349+F308 -> 3.3995842e+09 | G62: =+G349+G308 -> 5.869821e+09 | H62: =+H349+H308 -> 5.7502597e+08 | I62: =+I349+I308 -> 1.2653135e+08 | J62: =SUM(F62:I62) -> 9.9709625e+09 | L62: =SUM(G62:I62) -> 6.5713783e+09 | N62: =SUM('WP II-I-1.1'!F22:I24)+SUM('WP II-I-1.1'!F37:I46)+SUM('WP II-I-1.1'!F66:I79)+SUM('WP II-I-1.1'!F96:I107)=J62 -> TRUE
B63: =B62+1 -> 11
B64: =B63+1 -> 12 | D64: NET PLANT IN SERVICE | F64: =+F60-F62 -> 1.0503745e+10 | G64: =+G60-G62 -> 9.8456627e+09 | H64: =+H60-H62 -> 3.3483871e+08 | I64: =+I60-I62 -> 2.8553347e+08 | J64: =SUM(F64:I64) -> 2.096978e+10 | L64: =SUM(G64:I64) -> 1.0466035e+10
B65: =B64+1 -> 13
B66: =B65+1 -> 14 | D66: Other Rate Base Items:
B67: =B66+1 -> 15
B68: =B67+1 -> 16 | D68: CWIP | E68: II-B-4 | F68: =+F237 -> 0 | G68: =+G237 -> 0 | H68: =+H237 -> 0 | I68: =+I237 -> 0 | J68: =SUM(F68:I68) -> 0 | L68: =SUM(G68:I68) -> 0
B69: =B68+1 -> 17 | D69: Plant Held for Future Use | E69: II-B-6 | F69: =+F374 -> 21469068 | G69: =+G374 -> 1745979.3 | H69: =+H374 -> 0 | I69: =+I374 -> 0 | J69: =SUM(F69:I69) -> 23215048 | L69: =SUM(G69:I69) -> 1745979.3
B70: =B69+1 -> 18 | D70: Accumulated Provisions ex ADFIT | E70: II-B-7 | F70: =F395 -> 0 | G70: =G395 -> 0 | H70: =H395 -> 0 | I70: =I395 -> 0 | J70: =SUM(F70:I70) -> 0 | L70: =SUM(G70:I70) -> 0
B71: =B70+1 -> 19 | D71: Materials & Supplies | E71: II-B-8 | F71: =+F421 -> 77242553 | G71: =+G421 -> 74690404 | H71: =+H421 -> 105783.33 | I71: =+I421 -> 0 | J71: =SUM(F71:I71) -> 1.5203874e+08 | L71: =SUM(G71:I71) -> 74796188
B72: =B71+1 -> 20 | D72: Cash Working Capital | E72: II-B-9 | F72: =+F441 -> -56535862 | G72: =+G441 -> -16695372 | H72: =+H441 -> 273938.61 | I72: =+I441 -> 141339.78 | J72: =SUM(F72:I72) -> -72815955 | L72: =SUM(G72:I72) -> -16280094
B73: =B72+1 -> 21 | D73: Prepayments | E73: II-B-10 | F73: =+F462 -> 10576723 | G73: =+G462 -> 1.0012167e+08 | H73: =+H462 -> 3524809.2 | I73: =+I462 -> 930191.57 | J73: =SUM(F73:I73) -> 1.151534e+08 | L73: =SUM(G73:I73) -> 1.0457667e+08
B74: =B73+1 -> 22 | D74: Misc Other Rate Base | E74: II-B-11 | F74: =F483 -> 24173335 | G74: =G483 -> -2428360.5 | H74: =H483 -> -668323.9 | I74: =I483 -> 0 | J74: =SUM(F74:I74) -> 21076650 | L74: =SUM(G74:I74) -> -3096684.4
B75: =B74+1 -> 23 | D75: Regulatory Assets | E75: II-B-12 | F75: =F591 -> -4.7091702e+08 | G75: =G591 -> 1.9052011e+08 | H75: =H591 -> 1.199017e+08 | I75: =I591 -> 4277692.2 | J75: =SUM(F75:I75) -> -1.5621753e+08 | L75: =SUM(G75:I75) -> 3.146995e+08
B76: =B75+1 -> 24 | D76: Acuumulated Deferred Income Taxes | E76: II-E3.7 | F76: =+F399 -> -1.0827823e+09 | G76: =+G399 -> -1.1320592e+09 | H76: =+H399 -> -36656474 | I76: =+I399 -> -85810289 | J76: =SUM(F76:I76) -> -2.3373082e+09 | L76: =SUM(G76:I76) -> -1.254526e+09
B77: =B76+1 -> 25 | D77: Subtotal | F77: =SUM(F68:F76) -> -1.4767735e+09 | G77: =SUM(G68:G76) -> -7.8410476e+08 | H77: =SUM(H68:H76) -> 86481429 | I77: =SUM(I68:I76) -> -80461066 | J77: =SUM(F77:I77) -> -2.2548579e+09 | L77: =SUM(G77:I77) -> -7.780844e+08
B78: =B77+1 -> 26
B79: =B78+1 -> 27 | D79: TOTAL RATE BASE | F79: =+F64+F77 -> 9.0269716e+09 | G79: =+G64+G77 -> 9.0615579e+09 | H79: =+H64+H77 -> 4.2132014e+08 | I79: =+I64+I77 -> 2.0507241e+08 | J79: =SUM(F79:I79) -> 1.8714922e+10 | L79: =SUM(G79:I79) -> 9.6879505e+09 | N79: =SUM(G79:I79)=L79 -> TRUE | P79: ='WP II-I-1.1'!$J$459=J79 -> FALSE
B80: =B79+1 -> 28
B81: =B80+1 -> 29 | D81: COST-BASED Rate of Return | F81: =F597 -> 0.0705 | G81: =G597 -> 0.0705 | H81: =H597 -> 0.0705 | I81: =I597 -> 0.0705 | J81: =J83/J79 -> 0.0705 | L81: =L83/L79 -> 0.0705
B82: =B81+1 -> 30
B83: =B82+1 -> 31 | D83: COST-BASED Return On Rate Base | F83: =+F79*F81 -> 6.364015e+08 | G83: =+G79*G81 -> 6.3883984e+08 | H83: =+H79*H81 -> 29703070 | I83: =+I79*I81 -> 14457605 | J83: =SUM(F83:I83) -> 1.319402e+09 | L83: =SUM(G83:I83) -> 6.8300051e+08 | N83: =IF(ROUND(J83-'WP II-I-1.1'!J461,2)=0,TRUE,J83-'WP II-I-1.1'!J461) -> TRUE
N84: ='WP II-I-1.1'!F461=F83 -> TRUE | O84: ='WP II-I-1.1'!G461 -> 6.3883984e+08 | P84: ='WP II-I-1.1'!G461=G83 -> FALSE | Q84: ='WP II-I-1.1'!H461=H83 -> TRUE | R84: ='WP II-I-1.1'!I461=I83 -> TRUE
B91: =$B$4 -> 2022 RATE CASE | M91: =$M$2
B92: =$B$5 -> ONCOR ELECTRIC DELIVERY COMPANY LLC
B93: =$B$6 -> CONSOLIDATED FUNCTIONALIZED COST OF SERVICE
B94: =$B$7 -> TEST YEAR ENDING 12/31/2021
B95: =$B$8 -> SPONSOR: MATTHEW A. TROXLE
F97: TRAN | G97: DIST | H97: MET | I97: TDCS | J97: Total | L97: DIST + MET
B98: Line | C98: Acct | D98: Intangible and Transmission Plant Gross | E98: Source | L98: + TBILLTDCS
C100: (a) | D100: (b) | E100: (c) | F100: (d) | G100: (e) | H100: (f) | I100: (i) | J100: (j) | L100: (k)
B102: =B101+1 -> 1 | C102: Intangible Plant Gross | E102: II-B-1
B103: =B102+1 -> 2 | C103: A301 | D103: Organization | F103: ='WP II-I-1.1'!F18 -> 0 | G103: ='WP II-I-1.1'!G18 -> 0 | H103: ='WP II-I-1.1'!H18 -> 0 | I103: ='WP II-I-1.1'!I18 -> 0 | J103: =SUM(F103:I103) -> 0 | L103: =SUM(G103:I103) -> 0 | N103: =J103-L103-F103 -> 0
B104: =B103+1 -> 3 | C104: A302 | D104: Franchise & Consents | F104: ='WP II-I-1.1'!F19 -> 0 | G104: ='WP II-I-1.1'!G19 -> 0 | H104: ='WP II-I-1.1'!H19 -> 0 | I104: ='WP II-I-1.1'!I19 -> 0 | J104: =SUM(F104:I104) -> 0 | L104: =SUM(G104:I104) -> 0 | N104: =J104-L104-F104 -> 0
B105: =B104+1 -> 4 | C105: A303 | D105: Miscellaneous Intangible Plant | F105: ='WP II-I-1.1'!F20 -> 2.4730602e+08 | G105: ='WP II-I-1.1'!G20 -> 3.2333337e+08 | H105: ='WP II-I-1.1'!H20 -> 1.8530171e+08 | I105: ='WP II-I-1.1'!I20 -> 3.1040917e+08 | J105: =SUM(F105:I105) -> 1.0663503e+09 | L105: =SUM(G105:I105) -> 8.1904426e+08 | N105: =J105-L105-F105 -> 0
B106: =B105+1 -> 5 | D106: Subtotal | F106: =SUM(F103:F105) -> 2.4730602e+08 | G106: =SUM(G103:G105) -> 3.2333337e+08 | H106: =SUM(H103:H105) -> 1.8530171e+08 | I106: =SUM(I103:I105) -> 3.1040917e+08 | J106: =SUM(F106:I106) -> 1.0663503e+09 | L106: =SUM(G106:I106) -> 8.1904426e+08 | N106: =J106-L106-F106 -> 0
B107: =B106+1 -> 6 | C107: Transmission Plant Gross | E107: II-B-1 | N107: =J107-L107-F107 -> 0
B108: =B107+1 -> 7 | C108: A349 | D108: Land Owned in Fee | F108: ='WP II-I-1.1'!F26 -> 1.1590633e+08 | G108: ='WP II-I-1.1'!G26 -> 0 | H108: ='WP II-I-1.1'!H26 -> 0 | I108: ='WP II-I-1.1'!I26 -> 0 | J108: =SUM(F108:I108) -> 1.1590633e+08 | L108: =SUM(G108:I108) -> 0 | N108: =J108-L108-F108 -> 0
B109: =B108+1 -> 8 | C109: A350 | D109: Land and Land Rights | F109: ='WP II-I-1.1'!F27 -> 6.159264e+08 | G109: ='WP II-I-1.1'!G27 -> 0 | H109: ='WP II-I-1.1'!H27 -> 0 | I109: ='WP II-I-1.1'!I27 -> 0 | J109: =SUM(F109:I109) -> 6.159264e+08 | L109: =SUM(G109:I109) -> 0 | N109: =J109-L109-F109 -> 0
B110: =B109+1 -> 9 | C110: A352 | D110: Structures and Improvements | F110: ='WP II-I-1.1'!F28 -> 4.2004589e+08 | G110: ='WP II-I-1.1'!G28 -> 0 | H110: ='WP II-I-1.1'!H28 -> 0 | I110: ='WP II-I-1.1'!I28 -> 0 | J110: =SUM(F110:I110) -> 4.2004589e+08 | L110: =SUM(G110:I110) -> 0 | N110: =J110-L110-F110 -> 0
B111: =B110+1 -> 10 | C111: A353 | D111: Station Equipment | F111: ='WP II-I-1.1'!F29 -> 3.4952984e+09 | G111: ='WP II-I-1.1'!G29 -> 3.8186065e+08 | H111: ='WP II-I-1.1'!H29 -> 0 | I111: ='WP II-I-1.1'!I29 -> 0 | J111: =SUM(F111:I111) -> 3.8771591e+09 | L111: =SUM(G111:I111) -> 3.8186065e+08 | N111: =J111-L111-F111 -> 0
B112: =B111+1 -> 11 | C112: A354 | D112: Towers and Fixtures | F112: ='WP II-I-1.1'!F30 -> 1.9296528e+09 | G112: ='WP II-I-1.1'!G30 -> 0 | H112: ='WP II-I-1.1'!H30 -> 0 | I112: ='WP II-I-1.1'!I30 -> 0 | J112: =SUM(F112:I112) -> 1.9296528e+09 | L112: =SUM(G112:I112) -> 0 | N112: =J112-L112-F112 -> 0
B113: =B112+1 -> 12 | C113: A355 | D113: Poles and Fixtures | F113: ='WP II-I-1.1'!F31 -> 2.8707703e+09 | G113: ='WP II-I-1.1'!G31 -> 0 | H113: ='WP II-I-1.1'!H31 -> 0 | I113: ='WP II-I-1.1'!I31 -> 0 | J113: =SUM(F113:I113) -> 2.8707703e+09 | L113: =SUM(G113:I113) -> 0 | N113: =J113-L113-F113 -> 0
B114: =B113+1 -> 13 | C114: A356 | D114: O.H. Conductors & Devices | F114: ='WP II-I-1.1'!F32 -> 3.0445813e+09 | G114: ='WP II-I-1.1'!G32 -> 0 | H114: ='WP II-I-1.1'!H32 -> 0 | I114: ='WP II-I-1.1'!I32 -> 0 | J114: =SUM(F114:I114) -> 3.0445813e+09 | L114: =SUM(G114:I114) -> 0 | N114: =J114-L114-F114 -> 0
B115: =B114+1 -> 14 | C115: A357 | D115: Undergound Conduit | F115: ='WP II-I-1.1'!F33 -> 60197135 | G115: ='WP II-I-1.1'!G33 -> 0 | H115: ='WP II-I-1.1'!H33 -> 0 | I115: ='WP II-I-1.1'!I33 -> 0 | J115: =SUM(F115:I115) -> 60197135 | L115: =SUM(G115:I115) -> 0 | N115: =J115-L115-F115 -> 0
B116: =B115+1 -> 15 | C116: A358 | D116: Underground Conductors | F116: ='WP II-I-1.1'!F34 -> 84097343 | G116: ='WP II-I-1.1'!G34 -> 0 | H116: ='WP II-I-1.1'!H34 -> 0 | I116: ='WP II-I-1.1'!I34 -> 0 | J116: =SUM(F116:I116) -> 84097343 | L116: =SUM(G116:I116) -> 0 | N116: =J116-L116-F116 -> 0
B117: =B116+1 -> 16 | C117: A359 | D117: Roads and Trails | F117: ='WP II-I-1.1'!F35 -> 0 | G117: ='WP II-I-1.1'!G35 -> 0 | H117: ='WP II-I-1.1'!H35 -> 0 | I117: ='WP II-I-1.1'!I35 -> 0 | J117: =SUM(F117:I117) -> 0 | L117: =SUM(G117:I117) -> 0 | N117: =J117-L117-F117 -> 0
B118: =B117+1 -> 17 | D118: Subtotal | F118: =SUM(F108:F117) -> 1.2636476e+10 | G118: =SUM(G108:G117) -> 3.8186065e+08 | H118: =SUM(H108:H117) -> 0 | I118: =SUM(I108:I117) -> 0 | J118: =SUM(F118:I118) -> 1.3018337e+10 | L118: =SUM(G118:I118) -> 3.8186065e+08 | N118: =J118-L118-F118 -> 0
M119: =$M$2
B121: =$B$4 -> 2022 RATE CASE
B122: =$B$5 -> ONCOR ELECTRIC DELIVERY COMPANY LLC
B123: =$B$6 -> CONSOLIDATED FUNCTIONALIZED COST OF SERVICE
B124: =$B$7 -> TEST YEAR ENDING 12/31/2021
B125: =$B$8 -> SPONSOR: MATTHEW A. TROXLE
F127: TRAN | G127: DIST | H127: MET | I127: TDCS | J127: Total | L127: DIST + MET
...

Sheet II-I-DIST
B4: ='WP II-I-1.1'!B3 -> 2022 RATE CASE
B5: ='WP II-I-1.1'!B4 -> ONCOR ELECTRIC DELIVERY COMPANY LLC
B6: ="II-I-1-DIST: CLASS REVENUE REQUIREMENT" -> II-I-1-DIST: CLASS REVENUE REQUIREMENT
B7: ='WP II-I-1.1'!B6 -> TEST YEAR ENDING 12/31/2021
B8: ='WP II-I-2.2'!$B$7 -> SPONSOR: MATTHEW A. TROXLE
R10: =" "
B11: Line | D11: I-A-1 by Rate Class | E11: Source | F11: DIST | J11: Residential | K11: Secondary | L11: Secondary | M11: Primary | N11: Primary | O11: Primary | P11: Transmission | Q11: Lighting | R11: Wholesale | S11: Wholesale | U11: Total
K12: <=10 kW | L12: > 10 kW | M12: <=10 kW | N12: > 10 kW | O12: Substation | R12: XFMR | S12: DLS
F13: (a) | G13: (b) | H13: (c) | J13: (d) | K13: (e) | L13: (f) | M13: (g) | N13: (h) | O13: (i) | P13: (j) | Q13: (k) | R13: (l) | S13: (m) | U13: (n)
B15: =B14+1 -> 1 | D15: O&M Expenses | E15: II-D-2 | F15: =F638+F686 -> 1.9676251e+09 | J15: =J638+J686 -> 9.2562883e+08 | K15: =K638+K686 -> 25721821 | L15: =L638+L686 -> 6.5841473e+08 | M15: =M638+M686 -> 291840.01 | N15: =N638+N686 -> 1.6020127e+08 | O15: =O638+O686 -> 47191842 | P15: =P638+P686 -> 1.3785413e+08 | Q15: =Q638+Q686 -> 10957441 | ... S15: =S638+S686 -> 1148504.9 | U15: =SUM(I15:T15) -> 1.9676251e+09 | X15: =U15-F15 -> 0
B16: =B15+1 -> 2 | D16: Customer Expenses | E16: II-D-2 | F16: =F706+F716+F726 -> 245305.53 | J16: =J706+J716+J726 -> 211382.27 | K16: =K706+K716+K726 -> 20459.035 | L16: =L706+L716+L726 -> 10111.178 | M16: =M706+M716+M726 -> 238.26144 | N16: =N706+N716+N726 -> 203.54548 | O16: =O706+O716+O726 -> -91.058921 | P16: =P706+P716+P726 -> -384.8685 | Q16: =Q706+Q716+Q726 -> 3371.9531 | ... S16: =S706+S716+S726 -> 10.906226 | U16: =SUM(I16:T16) -> 245305.53 | X16: =U16-F16 -> 0
B17: =B16+1 -> 3 | D17: A&G Expenses | E17: II-D-2 | F17: =F760 -> 4.2312645e+08 | J17: =J760 -> 2.283512e+08 | K17: =K760 -> 7879417.5 | L17: =L760 -> 1.4405275e+08 | M17: =M760 -> 73200.4 | N17: =N760 -> 24811551 | O17: =O760 -> 2275901 | P17: =P760 -> 333312.72 | Q17: =Q760 -> 13755289 | ... S17: =S760 -> 1325254.8 | U17: =SUM(I17:T17) -> 4.2312645e+08 | X17: =U17-F17 -> 0
B18: =B17+1 -> 4 | D18: O&M + Customer + A&G Expenses | F18: =SUM(F15:F17) -> 2.3909969e+09 | J18: =SUM(J15:J17) -> 1.1541914e+09 | K18: =SUM(K15:K17) -> 33621697 | L18: =SUM(L15:L17) -> 8.0247759e+08 | M18: =SUM(M15:M17) -> 365278.68 | N18: =SUM(N15:N17) -> 1.8501303e+08 | O18: =SUM(O15:O17) -> 49467652 | P18: =SUM(P15:P17) -> 1.3818706e+08 | Q18: =SUM(Q15:Q17) -> 24716102 | ... S18: =SUM(S15:S17) -> 2473770.6 | U18: =SUM(I18:T18) -> 2.3909969e+09 | X18: =U18-F18 -> 0 | Y18: ='WP II-I-1.1'!$G$462=U18 -> TRUE | Z18: should match schedule D
B19: =B18+1 -> 5 | X19: =U19-F19 -> 0
B20: =B19+1 -> 6 | D20: Depreciation & Amortization (II-E-1) | E20: II-E-1 | F20: =F1035 -> 4.5981714e+08 | J20: =J1035 -> 2.4554112e+08 | K20: =K1035 -> 10276121 | L20: =L1035 -> 1.5254519e+08 | M20: =M1035 -> 53564.308 | N20: =N1035 -> 22671112 | O20: =O1035 -> 1729044.2 | P20: =P1035 -> 355894.65 | Q20: =Q1035 -> 25207217 | ... S20: =S1035 -> 1230650.8 | U20: =SUM(I20:T20) -> 4.5981714e+08 | X20: =U20-F20 -> 0
B21: =B20+1 -> 7 | D21: Other (II-E-4) | E21: II-E-4 | F21: =F1037+F1038 -> -2772903.9 | J21: =J1037+J1038 -> -1543390.6 | K21: =K1037+K1038 -> -51305.984 | L21: =L1037+L1038 -> -976083.78 | M21: =M1037+M1038 -> -353.45194 | N21: =N1037+N1038 -> -149598.65 | O21: =O1037+O1038 -> -14829.983 | P21: =P1037+P1038 -> -2808.1134 | Q21: =Q1037+Q1038 -> -24635.28 | ... S21: =S1037+S1038 -> -8120.6299 | U21: =SUM(I21:T21) -> -2772903.9 | X21: =U21-F21 -> 0
B22: =B21+1 -> 8 | D22: Depreciation, Amortization & Other Expenses | F22: =SUM(F20:F21) -> 4.5704424e+08 | J22: =SUM(J20:J21) -> 2.4399773e+08 | K22: =SUM(K20:K21) -> 10224815 | L22: =SUM(L20:L21) -> 1.515691e+08 | M22: =SUM(M20:M21) -> 53210.856 | N22: =SUM(N20:N21) -> 22521513 | O22: =SUM(O20:O21) -> 1714214.2 | P22: =SUM(P20:P21) -> 353086.53 | Q22: =SUM(Q20:Q21) -> 25182582 | ... S22: =SUM(S20:S21) -> 1222530.2 | U22: =SUM(I22:T22) -> 4.5704424e+08 | X22: =U22-F22 -> 0 | Y22: ='WP II-I-1.1'!$G$463=U22 -> TRUE
B23: =B22+1 -> 9 | X23: =U23-F23 -> 0
B24: =B23+1 -> 10 | D24: Taxes Other Than Federal Income Tax | E24: II-E-2 | F24: =+F1072 -> 4.474502e+08 | J24: =+J1072 -> 2.0342872e+08 | K24: =+K1072 -> 7522309.1 | L24: =+L1072 -> 1.7519255e+08 | M24: =+M1072 -> 23085.31 | N24: =+N1072 -> 27643694 | O24: =+O1072 -> 3816059.2 | P24: =+P1072 -> 22715111 | Q24: =+Q1072 -> 5980508.8 | ... S24: =+S1072 -> 802088.52 | U24: =SUM(I24:T24) -> 4.474502e+08 | X24: =U24-F24 -> 0 | Y24: ='WP II-I-1.1'!$G$464=U24 -> TRUE
B25: =B24+1 -> 11 | D25: Federal Income Tax | E25: II-E-3 | F25: =+F1130 -> 78221385 | J25: =+J1130 -> 43523262 | K25: =+K1130 -> 1413378.3 | L25: =+L1130 -> 27675494 | M25: =+M1130 -> 10069.517 | N25: =+N1130 -> 4281733.1 | O25: =+O1130 -> 430785.89 | P25: =+P1130 -> 136515.79 | Q25: =+Q1130 -> 468980.55 | ... S25: =+S1130 -> 229814.61 | U25: =SUM(I25:T25) -> 78221385 | X25: =U25-F25 -> 0 | Y25: ='WP II-I-1.1'!$G$465-U25 -> 0
B26: =B25+1 -> 12 | X26: =U26-F26 -> 0
B27: =B26+1 -> 13 | D27: Return on Rate Base | E27: II-B | F27: =+F83 -> 6.3883984e+08 | J27: =+J83 -> 3.5527283e+08 | K27: =+K83 -> 11529737 | L27: =+L83 -> 2.2624227e+08 | M27: =+M83 -> 82109.809 | N27: =+N83 -> 34931887 | O27: =+O83 -> 3501360.2 | P27: =+P83 -> 1107731.7 | Q27: =+Q83 -> 3875733.7 | ... S27: =+S83 -> 1877498.1 | U27: =SUM(I27:T27) -> 6.3883984e+08 | X27: =U27-F27 -> 0 | Y27: ='WP II-I-1.1'!$G$461=U27 -> TRUE
B28: =B27+1 -> 14 | X28: =U28-F28 -> 0
B29: =B28+1 -> 15 | D29: TOTAL COST OF SERVICE | F29: =+F18+F22+F24+F25+F27 -> 4.0125525e+09 | J29: =+J18+J22+J24+J25+J27 -> 2.0004139e+09 | K29: =+K18+K22+K24+K25+K27 -> 64311936 | L29: =+L18+L22+L24+L25+L27 -> 1.383157e+09 | M29: =+M18+M22+M24+M25+M27 -> 533754.17 | N29: =+N18+N22+N24+N25+N27 -> 2.7439186e+08 | O29: =+O18+O22+O24+O25+O27 -> 58930071 | P29: =+P18+P22+P24+P25+P27 -> 1.6249951e+08 | Q29: =+Q18+Q22+Q24+Q25+Q27 -> 60223906 | ... S29: =+S18+S22+S24+S25+S27 -> 6605702.1 | U29: =SUM(I29:T29) -> 4.0125525e+09 | X29: =U29-F29 -> 0 | Y29: ='WP II-I-1.1'!$G$476=U29 -> TRUE
B30: =B29+1 -> 16 | X30: =U30-F30 -> 0
B31: =B30+1 -> 17 | D31: Minus: Other Revenues | E31: II-E-5 | F31: =+F1186 -> 51757982 | J31: =+J1186 -> 33855633 | K31: =+K1186 -> 1962762 | L31: =+L1186 -> 13167153 | M31: =+M1186 -> 18570.774 | N31: =+N1186 -> 2013214.5 | O31: =+O1186 -> 118085.83 | P31: =+P1186 -> 37812.6 | Q31: =+Q1186 -> 527901.22 | ... S31: =+S1186 -> 53236.441 | U31: =SUM(I31:T31) -> 51757982 | X31: =U31-F31 -> 0 | Y31: ='WP II-I-1.1'!$G$466=-U31 -> TRUE
B32: =B31+1 -> 18 | X32: =U32-F32 -> 0
B33: =B32+1 -> 19 | D33: COST-BASED Revenue Requirement | F33: =+F29-F31 -> 3.9607946e+09 | J33: =+J29-J31 -> 1.9665583e+09 | K33: =+K29-K31 -> 62349174 | L33: =+L29-L31 -> 1.3699899e+09 | M33: =+M29-M31 -> 515183.39 | N33: =+N29-N31 -> 2.7237864e+08 | O33: =+O29-O31 -> 58811986 | P33: =+P29-P31 -> 1.6246169e+08 | Q33: =+Q29-Q31 -> 59696005 | ... S33: =+S29-S31 -> 6552465.6 | U33: =SUM(I33:T33) -> 3.9607946e+09 | W33: =IF(' WP II-I-1.4'!G33=U33,TRUE,' WP II-I-1.4'!G33-G33) -> TRUE | X33: =U33-F33 -> 0 | Y33: ='WP II-I-1.1'!$G$467=U33 -> TRUE
B34: =B33+1 -> 20 | X34: =U34-F34 -> 0
B35: =B34+1 -> 21 | D35: Proposed Adjustment to Return On Rate Base | F35: ='WP II-I-1.5'!D54 -> 0 | J35: ='WP II-I-1.5'!F54 -> 0 | K35: ='WP II-I-1.5'!G54 -> 0 | L35: ='WP II-I-1.5'!H54 -> 0 | M35: ='WP II-I-1.5'!I54 -> 0 | N35: ='WP II-I-1.5'!J54 -> 0 | O35: ='WP II-I-1.5'!K54 -> 0 | P35: ='WP II-I-1.5'!L54 -> 0 | Q35: ='WP II-I-1.5'!M54 -> 0 | ... S35: ='WP II-I-1.5'!O54 -> 0 | U35: =SUM(I35:T35) -> 0 | X35: =U35-F35 -> 0
B36: =B35+1 -> 22 | D36: (WP II-I-1.5) | X36: =U36-F36 -> 0
B37: =B36+1 -> 23 | D37: PROPOSED Revenue | F37: =F33+F35 -> 3.9607946e+09 | J37: =J33+J35 -> 1.9665583e+09 | K37: =K33+K35 -> 62349174 | L37: =L33+L35 -> 1.3699899e+09 | M37: =M33+M35 -> 515183.39 | N37: =N33+N35 -> 2.7237864e+08 | O37: =O33+O35 -> 58811986 | P37: =P33+P35 -> 1.6246169e+08 | Q37: =Q33+Q35 -> 59696005 | ... S37: =S33+S35 -> 6552465.6 | U37: =SUM(I37:T37) -> 3.9607946e+09 | X37: =U37-F37 -> 0
B38: =B37+1 -> 24 | X38: =U38-F38 -> 0
B39: =B38+1 -> 25 | D39: PROPOSED Revenue Excl 565 & A928 | F39: =+F37-F622-(0.727923)*F753 -> 2.3066259e+09 | J39: =+J37-J622-(0.727923)*J753 -> 1.2075454e+09 | K39: =+K37-K622-(0.727923)*K753 -> 41122596 | L39: =+L37-L622-(0.727923)*L753 -> 8.1825418e+08 | M39: =+M37-M622-(0.727923)*M753 -> 295364.15 | N39: =+N37-N622-(0.727923)*N753 -> 1.3369402e+08 | O39: =+O37-O622-(0.727923)*O753 -> 13404715 | P39: =+P37-P622-(0.727923)*P753 -> 24606815 | Q39: =+Q37-Q622-(0.727923)*Q753 -> 59672372 | ... S39: =+S37-S622-(0.727923)*S753 -> 6549864 | U39: =SUM(I39:T39) -> 2.3066259e+09 | X39: =U39-F39 -> 0 | Y39: =ROUND('WP II-I-1.1'!$G$467-'WP II-I-1.1'!$G$199-('WP II-I-1.1'!$G$258*(0.727923)),0)-U39 -> 0.14142847
W40: =U39-F39 -> 0 | X40: =U40-F40 -> 0
V41: =$H$2 -> 0
B42: =+$B$4 -> 2022 RATE CASE | X42: =U42-F42 -> 0
B43: =+$B$5 -> ONCOR ELECTRIC DELIVERY COMPANY LLC | X43: =U43-F43 -> 0
B44: =+$B$6 -> II-I-1-DIST: CLASS REVENUE REQUIREMENT | X44: =U44-F44 -> 0
B45: =+$B$7 -> TEST YEAR ENDING 12/31/2021 | X45: =U45-F45 -> 0
B46: =+$B$8 -> SPONSOR: MATTHEW A. TROXLE | X46: =U46-F46 -> 0
X47: =U47-F47 -> 0
R48: =R$10 | X48: =U48-F48 -> 0
B49: Line | D49: II-B by Rate Class | E49: Source | F49: =F$11 -> DIST | J49: Residential | K49: Secondary | L49: Secondary | M49: Primary | N49: Primary | O49: Primary | P49: Transmission | Q49: Lighting | R49: =R$11 -> Wholesale | S49: =S$11 -> Wholesale | U49: Total
K50: <=10 kW | L50: > 10 kW | M50: <=10 kW | N50: > 10 kW | O50: Substation | R50: =R$12 -> XFMR | S50: =S$12 -> DLS | X50: =U50-F50 -> 0
F51: (a) | G51: (b) | H51: (c) | J51: =J$13 -> (d) | K51: =K$13 -> (e) | L51: =L$13 -> (f) | M51: =M$13 -> (g) | N51: =N$13 -> (h) | O51: =O$13 -> (i) | P51: =P$13 -> (j) | Q51: =Q$13 -> (k) | ... S51: =S$13 -> (m) | U51: (n)
X52: =U52-F52 -> 0
B53: =B52+1 -> 1 | D53: Intangible Plant: Original Cost | E53: II-B-1 | F53: =F106 -> 3.2333337e+08 | J53: =J106 -> 1.7996645e+08 | K53: =K106 -> 5982514.2 | L53: =L106 -> 1.1381587e+08 | M53: =M106 -> 41214.125 | N53: =N106 -> 17443892 | O53: =O106 -> 1729244.4 | P53: =P106 -> 327438.96 | Q53: =Q106 -> 2872587.2 | ... S53: =S106 -> 946902.87 | U53: =SUM(I53:T53) -> 3.2333337e+08 | X53: =U53-F53 -> 0
B54: =B53+1 -> 2 | D54: Transmission Plant: Original Cost | E54: II-B-1 | F54: =F118 -> 3.8186065e+08 | J54: =J118 -> 2.0098204e+08 | K54: =K118 -> 4908024.7 | L54: =L118 -> 1.2940677e+08 | M54: =M118 -> 73158.983 | N54: =N118 -> 30964565 | O54: =O118 -> 11197862 | P54: =P118 -> 0 | Q54: =Q118 -> 1305252.9 | ... S54: =S118 -> 1680842.5 | U54: =SUM(I54:T54) -> 3.8186065e+08 | X54: =U54-F54 -> 0
B55: =B54+1 -> 3 | D55: Distribution Plant: Original Cost | E55: II-B-1 | F55: =F154 -> 1.461882e+10 | J55: =J154 -> 7.9624078e+09 | K55: =K154 -> 3.2802435e+08 | L55: =L154 -> 4.9534937e+09 | M55: =M154 -> 1681815.5 | N55: =N154 -> 7.1182899e+08 | O55: =O154 -> 56528373 | P55: =P154 -> 13437739 | Q55: =Q154 -> 5.4600159e+08 | ... S55: =S154 -> 38640052 | U55: =SUM(I55:T55) -> 1.461882e+10 | X55: =U55-F55 -> 0
B56: =B55+1 -> 4 | D56: Intangible, Transmission, Distribution Plant: Original Cost | F56: =SUM(F53:F55) -> 1.5324014e+10 | J56: =SUM(J53:J55) -> 8.3433563e+09 | K56: =SUM(K53:K55) -> 3.3891489e+08 | L56: =SUM(L53:L55) -> 5.1967164e+09 | M56: =SUM(M53:M55) -> 1796188.6 | N56: =SUM(N53:N55) -> 7.6023745e+08 | O56: =SUM(O53:O55) -> 69455479 | P56: =SUM(P53:P55) -> 13765178 | Q56: =SUM(Q53:Q55) -> 5.5017943e+08 | ... S56: =SUM(S53:S55) -> 41267797 | U56: =SUM(I56:T56) -> 1.5324014e+10 | X56: =U56-F56 -> 0
B57: =B56+1 -> 5 | X57: =U57-F57 -> 0
B58: =B57+1 -> 6 | D58: General Plant: Original Cost | E58: II-B-2 | F58: =+F194 -> 3.3013199e+08 | J58: =+J194 -> 1.8375055e+08 | K58: =+K194 -> 6108306.5 | L58: =+L194 -> 1.1620903e+08 | M58: =+M194 -> 42080.72 | N58: =+N194 -> 17810679 | O58: =+O194 -> 1765604.6 | P58: =+P194 -> 334323.91 | Q58: =+Q194 -> 2932988.2 | ... S58: =+S194 -> 966813.08 | U58: =SUM(I58:T58) -> 3.3013199e+08 | X58: =U58-F58 -> 0
B59: =B58+1 -> 7 | D59: Communication Equipment: Original Cost | E59: II-B-3 | F59: =+F212 -> 61337953 | J59: =+J212 -> 34140533 | K59: =+K212 -> 1134912.8 | L59: =+L212 -> 21591437 | M59: =+M212 -> 7818.525 | N59: =+N212 -> 3309193.4 | O59: =+O212 -> 328046.28 | P59: =+P212 -> 62116.803 | Q59: =+Q212 -> 544944.12 | ... S59: =+S212 -> 179632.2 | U59: =SUM(I59:T59) -> 61337953 | X59: =U59-F59 -> 0
B60: =B59+1 -> 8 | D60: Total Plant | F60: =+F56+F58+F59 -> 1.5715484e+10 | J60: =+J56+J58+J59 -> 8.5612474e+09 | K60: =+K56+K58+K59 -> 3.4615811e+08 | L60: =+L56+L58+L59 -> 5.3345168e+09 | M60: =+M56+M58+M59 -> 1846087.8 | N60: =+N56+N58+N59 -> 7.8135732e+08 | O60: =+O56+O58+O59 -> 71549130 | P60: =+P56+P58+P59 -> 14161619 | Q60: =+Q56+Q58+Q59 -> 5.5365736e+08 | ... S60: =+S56+S58+S59 -> 42414243 | U60: =SUM(I60:T60) -> 1.5715484e+10 | X60: =U60-F60 -> 0
B61: =B60+1 -> 9 | X61: =U61-F61 -> 0
B62: =B61+1 -> 10 | D62: Minus: Accumulated Depreciation | E62: II-B-5 | F62: =+F349+F308 -> 5.869821e+09 | J62: =+J349+J308 -> 3.081179e+09 | K62: =+K349+K308 -> 1.6398756e+08 | L62: =+L349+L308 -> 1.8687668e+09 | M62: =+M349+M308 -> 591097.17 | N62: =+N349+N308 -> 2.5018208e+08 | O62: =+O349+O308 -> 18892775 | P62: =+P349+P308 -> 4190939.2 | Q62: =+Q349+Q308 -> 4.6618565e+08 | ... S62: =+S349+S308 -> 13580577 | U62: =SUM(I62:T62) -> 5.869821e+09 | X62: =U62-F62 -> 0
B63: =B62+1 -> 11 | X63: =U63-F63 -> 0
B64: =B63+1 -> 12 | D64: NET PLANT IN SERVICE | F64: =+F60-F62 -> 9.8456627e+09 | J64: =+J60-J62 -> 5.4800683e+09 | K64: =+K60-K62 -> 1.8217055e+08 | L64: =+L60-L62 -> 3.46575e+09 | M64: =+M60-M62 -> 1254990.7 | N64: =+N60-N62 -> 5.3117524e+08 | O64: =+O60-O62 -> 52656355 | P64: =+P60-P62 -> 9970679.9 | Q64: =+Q60-Q62 -> 87471716 | ... S64: =+S60-S62 -> 28833665 | U64: =SUM(I64:T64) -> 9.8456627e+09 | X64: =U64-F64 -> 0
B65: =B64+1 -> 13 | X65: =U65-F65 -> 0
B66: =B65+1 -> 14 | D66: Other Rate Base Items: | X66: =U66-F66 -> 0
B67: =B66+1 -> 15 | X67: =U67-F67 -> 0
B68: =B67+1 -> 16 | D68: CWIP | E68: II-B-4 | F68: =+F237 -> 0 | J68: =+J237 -> 0 | K68: =+K237 -> 0 | L68: =+L237 -> 0 | M68: =+M237 -> 0 | N68: =+N237 -> 0 | O68: =+O237 -> 0 | P68: =+P237 -> 0 | Q68: =+Q237 -> 0 | ... S68: =+S237 -> 0 | U68: =SUM(I68:T68) -> 0 | X68: =U68-F68 -> 0
B69: =B68+1 -> 17 | D69: Plant Held for Future Use | E69: II-B-6 | F69: =+F374 -> 1745979.3 | J69: =+J374 -> 918949.06 | K69: =+K374 -> 22440.934 | L69: =+L374 -> 591685.88 | M69: =+M374 -> 334.50441 | N69: =+N374 -> 141579.11 | O69: =+O374 -> 51199.923 | P69: =+P374 -> 0 | Q69: =+Q374 -> 5968.0008 | ... S69: =+S374 -> 7685.3067 | U69: =SUM(I69:T69) -> 1745979.3 | X69: =U69-F69 -> 0
B70: =B69+1 -> 18 | D70: Accumulated Provisions ex ADFIT | E70: II-B-7 | F70: =F395 -> 0 | J70: =J395 -> 0 | K70: =K395 -> 0 | L70: =L395 -> 0 | M70: =M395 -> 0 | N70: =N395 -> 0 | O70: =O395 -> 0 | P70: =P395 -> 0 | Q70: =Q395 -> 0 | ... S70: =S395 -> 0 | U70: =SUM(I70:T70) -> 0 | X70: =U70-F70 -> 0
B71: =B70+1 -> 19 | D71: Materials & Supplies | E71: II-B-8 | F71: =+F421 -> 74690404 | J71: =+J421 -> 40688727 | K71: =+K421 -> 1645173 | L71: =+L421 -> 25353163 | M71: =+M421 -> 8773.8342 | N71: =+N421 -> 3713528.3 | O71: =+O421 -> 340048.93 | P71: =+P421 -> 67305.409 | Q71: =+Q421 -> 2631347.1 | ... S71: =+S421 -> 201580.62 | U71: =SUM(I71:T71) -> 74690404 | X71: =U71-F71 -> 0
B72: =B71+1 -> 20 | D72: Cash Working Capital | E72: II-B-9 | F72: =+F441 -> -16695372 | J72: =+J441 -> -7854809.2 | K72: =+K441 -> -218396.97 | L72: =+L441 -> -5586062.7 | M72: =+M441 -> -2477.986 | N72: =+N441 -> -1359146 | O72: =+O441 -> -400373.84 | P72: =+P441 -> -1169548.4 | Q72: =+Q441 -> -92991.309 | ... S72: =+S441 -> -9743.9842 | U72: =SUM(I72:T72) -> -16695372 | X72: =U72-F72 -> 0
B73: =B72+1 -> 21 | D73: Prepayments | E73: II-B-10 | F73: =+F462 -> 1.0012167e+08 | J73: =+J462 -> 40207408 | K73: =+K462 -> 1436286.4 | L73: =+L462 -> 42096747 | M73: =+M462 -> 726.60193 | N73: =+N462 -> 6768844.4 | O73: =+O462 -> 1065032.2 | P73: =+P462 -> 7977831.5 | Q73: =+Q462 -> 366503.43 | ... S73: =+S462 -> 121027.12 | U73: =SUM(I73:T73) -> 1.0012167e+08 | X73: =U73-F73 -> 0
B74: =B73+1 -> 22 | D74: Misc Other Rate Base | E74: II-B-11 | F74: =F483 -> -2428360.5 | J74: =J483 -> -1165559.2 | K74: =K483 -> -28463.208 | L74: =L483 -> -750471.34 | M74: =M483 -> -424.27238 | N74: =N483 -> -179573.43 | O74: =O483 -> -64939.989 | P74: =P483 -> -213828.3 | Q74: =Q483 -> -7569.58 | ... S74: =S483 -> -9747.744 | U74: =SUM(I74:T74) -> -2428360.5 | X74: =U74-F74 -> 0
B75: =B74+1 -> 23 | D75: Regulatory Assets | E75: II-B-12 | F75: =F591 -> 1.9052011e+08 | J75: =J591 -> 1.0317427e+08 | K75: =K591 -> 3450150.6 | L75: =L591 -> 65925144 | M75: =M591 -> 35737.045 | N75: =N591 -> 11512083 | O75: =O591 -> 1171377.9 | P75: =P591 -> 100193.36 | Q75: =Q591 -> 4482480.1 | ... S75: =S591 -> 542006.94 | U75: =SUM(I75:T75) -> 1.9052011e+08 | X75: =U75-F75 -> 0
B76: =B75+1 -> 24 | D76: Acuumulated Deferred Income Taxes | E76: II-E3.7 | F76: =+F399 -> -1.1320592e+09 | J76: =+J399 -> -6.1670636e+08 | K76: =+K399 -> -24935374 | L76: =+L399 -> -3.8426999e+08 | M76: =+M399 -> -132982.27 | N76: =+N399 -> -56284792 | O76: =+O399 -> -5154015.8 | P76: =+P399 -> -1020127.1 | Q76: =+Q399 -> -39882508 | ... S76: =+S399 -> -3055294.7 | U76: =SUM(I76:T76) -> -1.1320592e+09 | X76: =U76-F76 -> 0
B77: =B76+1 -> 25 | D77: Subtotal | F77: =SUM(F68:F76) -> -7.8410476e+08 | J77: =SUM(J68:J76) -> -4.4073738e+08 | K77: =SUM(K68:K76) -> -18628184 | L77: =SUM(L68:L76) -> -2.5663979e+08 | M77: =SUM(M68:M76) -> -90312.545 | N77: =SUM(N68:N76) -> -35687477 | O77: =SUM(O68:O76) -> -2991670.7 | P77: =SUM(P68:P76) -> 5741826.5 | Q77: =SUM(Q68:Q76) -> -32496771 | ... S77: =SUM(S68:S76) -> -2202486.4 | U77: =SUM(I77:T77) -> -7.8410476e+08 | X77: =U77-F77 -> 0
B78: =B77+1 -> 26 | X78: =U78-F78 -> 0
B79: =B78+1 -> 27 | D79: TOTAL RATE BASE | F79: =+F64+F77 -> 9.0615579e+09 | J79: =+J64+J77 -> 5.039331e+09 | K79: =+K64+K77 -> 1.6354236e+08 | L79: =+L64+L77 -> 3.2091102e+09 | M79: =+M64+M77 -> 1164678.1 | N79: =+N64+N77 -> 4.9548776e+08 | O79: =+O64+O77 -> 49664684 | P79: =+P64+P77 -> 15712506 | Q79: =+Q64+Q77 -> 54974946 | ... S79: =+S64+S77 -> 26631179 | U79: =SUM(I79:T79) -> 9.0615579e+09 | X79: =U79-F79 -> 0
B80: =B79+1 -> 28 | X80: =U80-F80 -> 0
B81: =B80+1 -> 29 | D81: COST-BASED Rate of Return | F81: =F597 -> 0.0705 | J81: =J597 -> 0.0705 | K81: =K597 -> 0.0705 | L81: =L597 -> 0.0705 | M81: =M597 -> 0.0705 | N81: =N597 -> 0.0705 | O81: =O597 -> 0.0705 | P81: =P597 -> 0.0705 | Q81: =Q597 -> 0.0705 | ... S81: =S597 -> 0.0705 | U81: =U83/U79 -> 0.0705 | X81: =U81-F81 -> 0
B82: =B81+1 -> 30
B83: =B82+1 -> 31 | D83: COST-BASED Return On Rate Base | F83: =+F79*F81 -> 6.3883984e+08 | J83: =+J79*J81 -> 3.5527283e+08 | K83: =+K79*K81 -> 11529737 | L83: =+L79*L81 -> 2.2624227e+08 | M83: =+M79*M81 -> 82109.809 | N83: =+N79*N81 -> 34931887 | O83: =+O79*O81 -> 3501360.2 | P83: =+P79*P81 -> 1107731.7 | Q83: =+Q79*Q81 -> 3875733.7 | ... S83: =+S79*S81 -> 1877498.1 | U83: =SUM(I83:T83) -> 6.3883984e+08 | X83: =IF(ROUND(U83-'WP II-I-1.1'!G461,2)=0,TRUE,U83-'WP II-I-1.1'!G461) -> TRUE
B84: =B83+1 -> 32
B85: =B84+1 -> 33 | D85: Proposed Adjustment to Return On Rate Base | F85: ='WP II-I-1.5'!D54 -> 0 | J85: ='WP II-I-1.5'!F54 -> 0 | K85: ='WP II-I-1.5'!G54 -> 0 | L85: ='WP II-I-1.5'!H54 -> 0 | M85: ='WP II-I-1.5'!I54 -> 0 | N85: ='WP II-I-1.5'!J54 -> 0 | O85: ='WP II-I-1.5'!K54 -> 0 | P85: ='WP II-I-1.5'!L54 -> 0 | Q85: ='WP II-I-1.5'!M54 -> 0 | ... S85: ='WP II-I-1.5'!O54 -> 0 | U85: =SUM(I85:T85) -> 0 | X85: =U85-F85 -> 0
B86: =B85+1 -> 34 | D86: (WP II-I-1.5) | X86: =U86-F86 -> 0
B87: =B86+1 -> 35 | D87: PROPOSED Return On Rate Base | F87: =F83+F85 -> 6.3883984e+08 | J87: =J83+J85 -> 3.5527283e+08 | K87: =K83+K85 -> 11529737 | L87: =L83+L85 -> 2.2624227e+08 | M87: =M83+M85 -> 82109.809 | N87: =N83+N85 -> 34931887 | O87: =O83+O85 -> 3501360.2 | P87: =P83+P85 -> 1107731.7 | Q87: =Q83+Q85 -> 3875733.7 | ... S87: =S83+S85 -> 1877498.1 | U87: =SUM(I87:T87) -> 6.3883984e+08 | X87: =U87-F87 -> 0
B88: =B87+1 -> 36 | X88: =U88-F88 -> 0
B89: =B88+1 -> 37 | D89: PROPOSED Rate Of Return | F89: =F87/F79 -> 0.0705 | J89: =J87/J79 -> 0.0705 | K89: =K87/K79 -> 0.0705 | L89: =L87/L79 -> 0.0705 | M89: =M87/M79 -> 0.0705 | N89: =N87/N79 -> 0.0705 | O89: =O87/O79 -> 0.0705 | P89: =P87/P79 -> 0.0705 | Q89: =Q87/Q79 -> 0.0705 | ... S89: =S87/S79 -> 0.0705 | U89: =U87/U79 -> 0.0705 | X89: =U89-F89 -> 0
X90: =U90-F90 -> 0
B91: =+$B$4 -> 2022 RATE CASE | V91: =$H$2 -> 0
B92: =+$B$5 -> ONCOR ELECTRIC DELIVERY COMPANY LLC | X92: =U92-F92 -> 0
B93: =+$B$6 -> II-I-1-DIST: CLASS REVENUE REQUIREMENT | X93: =U93-F93 -> 0
B94: =+$B$7 -> TEST YEAR ENDING 12/31/2021 | X94: =U94-F94 -> 0
B95: =+$B$8 -> SPONSOR: MATTHEW A. TROXLE | X95: =U95-F95 -> 0
X96: =U96-F96 -> 0
R97: =R$10 | X97: =U97-F97 -> 0
B98: Line | C98: Acct | D98: Intangible and Transmission Plant Gross | E98: Source | F98: =F$11 -> DIST | G98: Alloc | H98: Allocation | J98: Residential | K98: Secondary | L98: Secondary | M98: Primary | N98: Primary | O98: Primary | P98: Transmission | Q98: Lighting | R98: =R$11 -> Wholesale | S98: =S$11 -> Wholesale | U98: Total
G99: # | H99: Factor | K99: <=10 kW | L99: > 10 kW | M99: <=10 kW | N99: > 10 kW | O99: Substation | R99: =R$12 -> XFMR | S99: =S$12 -> DLS | X99: =U99-F99 -> 0
F100: (a) | G100: (b) | H100: (c) | J100: =J$13 -> (d) | K100: =K$13 -> (e) | L100: =L$13 -> (f) | M100: =M$13 -> (g) | N100: =N$13 -> (h) | O100: =O$13 -> (i) | P100: =P$13 -> (j) | Q100: =Q$13 -> (k) | ... S100: =S$13 -> (m) | U100: (n)
X101: =U101-F101 -> 0
B102: =B101+1 -> 1 | C102: Intangible Plant Gross | E102: II-B-1 | X102: =U102-F102 -> 0
B103: =B102+1 -> 2 | C103: A301 | D103: Organization | F103: =' WP II-I-1.4'!G103 -> 0 | G103: 65 | H103: =VLOOKUP(G103,FactorTable,2) -> PLT_N XINT | J103: =$F103*HLOOKUP(J$1318,FactorTable,$G103+1) -> 0 | K103: =$F103*HLOOKUP(K$1318,FactorTable,$G103+1) -> 0 | L103: =$F103*HLOOKUP(L$1318,FactorTable,$G103+1) -> 0 | M103: =$F103*HLOOKUP(M$1318,FactorTable,$G103+1) -> 0 | N103: =$F103*HLOOKUP(N$1318,FactorTable,$G103+1) -> 0 | O103: =$F103*HLOOKUP(O$1318,FactorTable,$G103+1) -> 0 | P103: =$F103*HLOOKUP(P$1318,FactorTable,$G103+1) -> 0 | Q103: =$F103*HLOOKUP(Q$1318,FactorTable,$G103+1) -> 0 | ... S103: =$F103*HLOOKUP(S$1318,FactorTable,$G103+1) -> 0 | U103: =SUM(I103:T103) -> 0 | X103: =U103-F103 -> 0
B104: =B103+1 -> 3 | C104: A302 | D104: Franchise & Consents | F104: =' WP II-I-1.4'!G104 -> 0 | G104: 65 | H104: =VLOOKUP(G104,FactorTable,2) -> PLT_N XINT | J104: =$F104*HLOOKUP(J$1318,FactorTable,$G104+1) -> 0 | K104: =$F104*HLOOKUP(K$1318,FactorTable,$G104+1) -> 0 | L104: =$F104*HLOOKUP(L$1318,FactorTable,$G104+1) -> 0 | M104: =$F104*HLOOKUP(M$1318,FactorTable,$G104+1) -> 0 | N104: =$F104*HLOOKUP(N$1318,FactorTable,$G104+1) -> 0 | O104: =$F104*HLOOKUP(O$1318,FactorTable,$G104+1) -> 0 | P104: =$F104*HLOOKUP(P$1318,FactorTable,$G104+1) -> 0 | Q104: =$F104*HLOOKUP(Q$1318,FactorTable,$G104+1) -> 0 | ... S104: =$F104*HLOOKUP(S$1318,FactorTable,$G104+1) -> 0 | U104: =SUM(I104:T104) -> 0 | X104: =U104-F104 -> 0
B105: =B104+1 -> 4 | C105: A303 | D105: Miscellaneous Intangible Plant | F105: =' WP II-I-1.4'!G105 -> 3.2333337e+08 | G105: 65 | H105: =VLOOKUP(G105,FactorTable,2) -> PLT_N XINT | J105: =$F105*HLOOKUP(J$1318,FactorTable,$G105+1) -> 1.7996645e+08 | K105: =$F105*HLOOKUP(K$1318,FactorTable,$G105+1) -> 5982514.2 | L105: =$F105*HLOOKUP(L$1318,FactorTable,$G105+1) -> 1.1381587e+08 | M105: =$F105*HLOOKUP(M$1318,FactorTable,$G105+1) -> 41214.125 | N105: =$F105*HLOOKUP(N$1318,FactorTable,$G105+1) -> 17443892 | O105: =$F105*HLOOKUP(O$1318,FactorTable,$G105+1) -> 1729244.4 | P105: =$F105*HLOOKUP(P$1318,FactorTable,$G105+1) -> 327438.96 | Q105: =$F105*HLOOKUP(Q$1318,FactorTable,$G105+1) -> 2872587.2 | ... S105: =$F105*HLOOKUP(S$1318,FactorTable,$G105+1) -> 946902.87 | U105: =SUM(I105:T105) -> 3.2333337e+08 | X105: =U105-F105 -> 0
...

Sheet II-I-MET
B4: ='WP II-I-1.1'!B3 -> 2022 RATE CASE
B5: ='WP II-I-1.1'!B4 -> ONCOR ELECTRIC DELIVERY COMPANY LLC
B6: ="II-I-1-MET: CLASS REVENUE REQUIREMENT" -> II-I-1-MET: CLASS REVENUE REQUIREMENT
B7: ='WP II-I-1.1'!B6 -> TEST YEAR ENDING 12/31/2021
B8: ='WP II-I-2.2'!$B$7 -> SPONSOR: MATTHEW A. TROXLE
R10: =" "
B11: Line | D11: I-A-1 by Rate Class | E11: Source | F11: MET | J11: Residential | K11: Secondary | L11: Secondary | M11: Primary | N11: Primary | O11: Primary | P11: Transmission | Q11: Lighting | R11: Wholesale | S11: Wholesale | U11: Total
K12: <=10 kW | L12: > 10 kW | M12: <=10 kW | N12: > 10 kW | O12: Substation | R12: XFMR | S12: DLS
F13: (a) | G13: (b) | H13: (c) | J13: (d) | K13: (e) | L13: (f) | M13: (g) | N13: (h) | O13: (i) | P13: (j) | Q13: (k) | R13: (l) | S13: (m) | U13: (n)
B15: =B14+1 -> 1 | D15: O&M Expenses | E15: II-D-2 | F15: =F638+F686 -> 50235236 | J15: =J638+J686 -> 27996970 | K15: =K638+K686 -> 4316260.1 | L15: =L638+L686 -> 13314318 | M15: =M638+M686 -> 186943.1 | N15: =N638+N686 -> 3901170.2 | O15: =O638+O686 -> 133373.69 | P15: =P638+P686 -> 290202.47 | Q15: =Q638+Q686 -> 44680.3 | ... S15: =S638+S686 -> 35928.033 | U15: =SUM(I15:T15) -> 50235236 | W15: =U15-F15 -> 0
B16: =B15+1 -> 2 | D16: Customer Expenses | E16: II-D-2 | F16: =F706+F716+F726 -> 8799722.5 | J16: =J706+J716+J726 -> 4937125.1 | K16: =K706+K716+K726 -> 755666.43 | L16: =L706+L716+L726 -> 2310400.2 | M16: =M706+M716+M726 -> 32448.274 | N16: =N706+N716+N726 -> 675505.49 | O16: =O706+O716+O726 -> 23080.862 | P16: =P706+P716+P726 -> 50245.26 | Q16: =Q706+Q716+Q726 -> 6368.3216 | ... S16: =S706+S716+S726 -> 6219.3896 | U16: =SUM(I16:T16) -> 8799722.5 | W16: =U16-F16 -> 0
B17: =B16+1 -> 3 | D17: A&G Expenses | E17: II-D-2 | F17: =F760 -> 50135759 | J17: =J760 -> 27963844 | K17: =K760 -> 4306829.4 | L17: =L760 -> 13276535 | M17: =M760 -> 186341.24 | N17: =N760 -> 3888500.7 | O17: =O760 -> 133007.13 | P17: =P760 -> 289638.31 | Q17: =Q760 -> 39921.963 | ... S17: =S760 -> 35806.816 | U17: =SUM(I17:T17) -> 50135759 | W17: =U17-F17 -> 0
B18: =B17+1 -> 4 | D18: O&M + Customer + A&G Expenses | F18: =SUM(F15:F17) -> 1.0917072e+08 | J18: =SUM(J15:J17) -> 60897939 | K18: =SUM(K15:K17) -> 9378755.9 | L18: =SUM(L15:L17) -> 28901253 | M18: =SUM(M15:M17) -> 405732.61 | N18: =SUM(N15:N17) -> 8465176.4 | O18: =SUM(O15:O17) -> 289461.69 | P18: =SUM(P15:P17) -> 630086.05 | Q18: =SUM(Q15:Q17) -> 90970.585 | ... S18: =SUM(S15:S17) -> 77954.238 | U18: =SUM(I18:T18) -> 1.0917072e+08 | W18: =U18-F18 -> 0 | X18: ='WP II-I-1.1'!$H$462=U18 -> TRUE
B19: =B18+1 -> 5 | W19: =U19-F19 -> 0
B20: =B19+1 -> 6 | D20: Depreciation & Amortization (II-E-1) | E20: II-E-1 | F20: =F1035 -> 30914364 | J20: =J1035 -> 17234907 | K20: =K1035 -> 2657178.7 | L20: =L1035 -> 8196159.8 | M20: =M1035 -> 115086.53 | N20: =N1035 -> 2401545.8 | O20: =O1035 -> 82068.039 | P20: =P1035 -> 178655.81 | Q20: =Q1035 -> 17180.136 | ... S20: =S1035 -> 22112.843 | U20: =SUM(I20:T20) -> 30914364 | W20: =U20-F20 -> 0
B21: =B20+1 -> 7 | D21: Other (II-E-4) | E21: II-E-4 | F21: =F1037+F1038 -> 25459958 | J21: =J1037+J1038 -> 14194049 | K21: =K1037+K1038 -> 2188356.9 | L21: =L1037+L1038 -> 6750062.4 | M21: =M1037+M1038 -> 94781.126 | N21: =N1037+N1038 -> 1977826.8 | O21: =O1037+O1038 -> 67588.286 | P21: =P1037+P1038 -> 147134.5 | Q21: =Q1037+Q1038 -> 14148.942 | ... S21: =S1037+S1038 -> 18211.342 | U21: =SUM(I21:T21) -> 25459958 | W21: =U21-F21 -> 0
B22: =B21+1 -> 8 | D22: Depreciation, Amortization & Other Expenses | F22: =SUM(F20:F21) -> 56374322 | J22: =SUM(J20:J21) -> 31428956 | K22: =SUM(K20:K21) -> 4845535.6 | L22: =SUM(L20:L21) -> 14946222 | M22: =SUM(M20:M21) -> 209867.65 | N22: =SUM(N20:N21) -> 4379372.6 | O22: =SUM(O20:O21) -> 149656.33 | P22: =SUM(P20:P21) -> 325790.31 | Q22: =SUM(Q20:Q21) -> 31329.078 | ... S22: =SUM(S20:S21) -> 40324.185 | U22: =SUM(I22:T22) -> 56374322 | W22: =U22-F22 -> 0 | X22: ='WP II-I-1.1'!$H$463=U22 -> TRUE
B23: =B22+1 -> 9 | W23: =U23-F23 -> 0
B24: =B23+1 -> 10 | D24: Taxes Other Than Federal Income Tax | E24: II-E-2 | F24: =+F1072 -> 8538460.4 | J24: =+J1072 -> 4759243.1 | K24: =+K1072 -> 733334.04 | L24: =+L1072 -> 2264727.3 | M24: =+M1072 -> 31752.473 | N24: =+N1072 -> 663072.55 | O24: =+O1072 -> 22694.899 | P24: =+P1072 -> 49877.895 | Q24: =+Q1072 -> 5042.9021 | ... S24: =+S1072 -> 6102.0186 | U24: =SUM(I24:T24) -> 8538460.4 | W24: =U24-F24 -> 0 | X24: ='WP II-I-1.1'!$H$464=U24 -> TRUE
B25: =B24+1 -> 11 | D25: Federal Income Tax | E25: II-E-3 | F25: =+F1130 -> 1649124.5 | J25: =+J1130 -> 917265.06 | K25: =+K1130 -> 140880.77 | L25: =+L1130 -> 439447.33 | M25: =+M1130 -> 6093.5196 | N25: =+N1130 -> 127971.6 | O25: =+O1130 -> 4429.4797 | P25: =+P1130 -> 10409.508 | Q25: =+Q1130 -> 952.02616 | ... S25: =+S1130 -> 1172.8056 | U25: =SUM(I25:T25) -> 1649124.5 | W25: =U25-F25 -> 0 | X25: ='WP II-I-1.1'!$H$465=U25 -> TRUE
B26: =B25+1 -> 12 | W26: =U26-F26 -> 0
B27: =B26+1 -> 13 | D27: Return on Rate Base | E27: II-B | F27: =+F83 -> 29703070 | J27: =+J83 -> 16524775 | K27: =+K83 -> 2538756.4 | L27: =+L83 -> 7911329.3 | M27: =+M83 -> 109817.98 | N27: =+N83 -> 2305042.3 | O27: =+O83 -> 79699.057 | P27: =+P83 -> 186137.83 | Q27: =+Q83 -> 17325.576 | ... S27: =+S83 -> 21133.209 | U27: =SUM(I27:T27) -> 29703070 | W27: =U27-F27 -> 0 | X27: ='WP II-I-1.1'!$H$461=U27 -> TRUE
B28: =B27+1 -> 14 | W28: =U28-F28 -> 0
B29: =B28+1 -> 15 | D29: TOTAL COST OF SERVICE | F29: =+F18+F22+F24+F25+F27 -> 2.0543569e+08 | J29: =+J18+J22+J24+J25+J27 -> 1.1452818e+08 | K29: =+K18+K22+K24+K25+K27 -> 17637263 | L29: =+L18+L22+L24+L25+L27 -> 54462979 | M29: =+M18+M22+M24+M25+M27 -> 763264.24 | N29: =+N18+N22+N24+N25+N27 -> 15940635 | O29: =+O18+O22+O24+O25+O27 -> 545941.45 | P29: =+P18+P22+P24+P25+P27 -> 1202301.6 | Q29: =+Q18+Q22+Q24+Q25+Q27 -> 145620.17 | ... S29: =+S18+S22+S24+S25+S27 -> 146686.46 | U29: =SUM(I29:T29) -> 2.0543569e+08 | W29: =U29-F29 -> 0 | X29: ='WP II-I-1.1'!$H$476=U29 -> TRUE
B30: =B29+1 -> 16
B31: =B30+1 -> 17 | D31: Minus: Other Revenues | E31: II-E-5 | F31: =+F1186 -> 5094631 | J31: =+J1186 -> 2843185.9 | K31: =+K1186 -> 438346.05 | L31: =+L1186 -> 1352093.5 | M31: =+M1186 -> 18985.446 | N31: =+N1186 -> 396175.12 | O31: =+O1186 -> 13538.495 | P31: =+P1186 -> 29472.262 | Q31: =+Q1186 -> 2834.1505 | ... S31: =+S1186 -> 0 | U31: =SUM(I31:T31) -> 5094631 | X31: ='WP II-I-1.1'!$H$466=-U31 -> TRUE
B32: =B31+1 -> 18
B33: =B32+1 -> 19 | D33: COST-BASED Revenue Requirement | F33: =+F29-F31 -> 2.0034106e+08 | J33: =+J29-J31 -> 1.1168499e+08 | K33: =+K29-K31 -> 17198917 | L33: =+L29-L31 -> 53110886 | M33: =+M29-M31 -> 744278.79 | N33: =+N29-N31 -> 15544460 | O33: =+O29-O31 -> 532402.95 | P33: =+P29-P31 -> 1172829.3 | Q33: =+Q29-Q31 -> 142786.02 | ... S33: =+S29-S31 -> 146686.46 | U33: =SUM(I33:T33) -> 2.0034106e+08 | W33: =IF(ROUND(U33-'WP II-I-1.1'!H467,2)=0,TRUE,U33-'WP II-I-1.1'!H467) -> TRUE | X33: ='WP II-I-1.1'!$H$467=U33 -> TRUE
B42: =+$B$4 -> 2022 RATE CASE
B43: =+$B$5 -> ONCOR ELECTRIC DELIVERY COMPANY LLC
B44: =+$B$6 -> II-I-1-MET: CLASS REVENUE REQUIREMENT
B45: =+$B$7 -> TEST YEAR ENDING 12/31/2021
B46: =+$B$8 -> SPONSOR: MATTHEW A. TROXLE
R48: =R$10
B49: Line | D49: II-B by Rate Class | E49: Source | F49: =F$11 -> MET | J49: Residential | K49: Secondary | L49: Secondary | M49: Primary | N49: Primary | O49: Primary | P49: Transmission | Q49: Lighting | R49: =R$11 -> Wholesale | S49: =S$11 -> Wholesale | U49: Total
K50: <=10 kW | L50: > 10 kW | M50: <=10 kW | N50: > 10 kW | O50: Substation | R50: =R$12 -> XFMR | S50: =S$12 -> DLS
F51: (a) | G51: (b) | H51: (c) | J51: =J$13 -> (d) | K51: =K$13 -> (e) | L51: =L$13 -> (f) | M51: =M$13 -> (g) | N51: =N$13 -> (h) | O51: =O$13 -> (i) | P51: =P$13 -> (j) | Q51: =Q$13 -> (k) | ... S51: =S$13 -> (m) | U51: (n)
B53: =B52+1 -> 1 | D53: Intangible Plant: Original Cost | E53: II-B-1 | F53: =F106 -> 1.8530171e+08 | J53: =J106 -> 1.033066e+08 | K53: =K106 -> 15927217 | L53: =L106 -> 49128051 | M53: =M106 -> 689832.43 | N53: =N106 -> 14394945 | O53: =O106 -> 491918.53 | P53: =P106 -> 1070868.8 | Q53: =Q106 -> 102978.3 | ... S53: =S106 -> 132545.11 | U53: =SUM(I53:T53) -> 1.8530171e+08 | W53: =U53-F53 -> 0
B54: =B53+1 -> 2 | D54: Transmission Plant: Original Cost | E54: II-B-1 | F54: =F118 -> 0 | J54: =J118 -> 0 | K54: =K118 -> 0 | L54: =L118 -> 0 | M54: =M118 -> 0 | N54: =N118 -> 0 | O54: =O118 -> 0 | P54: =P118 -> 0 | Q54: =Q118 -> 0 | ... S54: =S118 -> 0 | U54: =SUM(I54:T54) -> 0 | W54: =U54-F54 -> 0
B55: =B54+1 -> 3 | D55: Distribution Plant: Original Cost | E55: II-B-1 | F55: =F154 -> 5.7414748e+08 | J55: =J154 -> 3.2008999e+08 | K55: =K154 -> 49349633 | L55: =L154 -> 1.5222065e+08 | M55: =M154 -> 2137409 | N55: =N154 -> 44601969 | O55: =O154 -> 1524183.3 | P55: =P154 -> 3318029.9 | Q55: =Q154 -> 319072.77 | ... S55: =S154 -> 410683.95 | U55: =SUM(I55:T55) -> 5.7414748e+08 | W55: =U55-F55 -> 0
B56: =B55+1 -> 4 | D56: Intangible, Transmission, Distribution Plant: Original Cost | F56: =SUM(F53:F55) -> 7.594492e+08 | J56: =SUM(J53:J55) -> 4.2339658e+08 | K56: =SUM(K53:K55) -> 65276849 | L56: =SUM(L53:L55) -> 2.013487e+08 | M56: =SUM(M53:M55) -> 2827241.5 | N56: =SUM(N53:N55) -> 58996913 | O56: =SUM(O53:O55) -> 2016101.9 | P56: =SUM(P53:P55) -> 4388898.7 | Q56: =SUM(Q53:Q55) -> 422051.07 | ... S56: =SUM(S53:S55) -> 543229.06 | U56: =SUM(I56:T56) -> 7.594492e+08 | W56: =U56-F56 -> 0
B57: =B56+1 -> 5 | W57: =U57-F57 -> 0
B58: =B57+1 -> 6 | D58: General Plant: Original Cost | E58: II-B-2 | F58: =+F194 -> 1.0472662e+08 | J58: =+J194 -> 58385596 | K58: =+K194 -> 9001555.3 | L58: =+L194 -> 27765609 | M58: =+M194 -> 389871.3 | N58: =+N194 -> 8135563.9 | O58: =+O194 -> 278016.67 | P58: =+P194 -> 605220.91 | Q58: =+Q194 -> 58200.052 | ... S58: =+S194 -> 74910.27 | U58: =SUM(I58:T58) -> 1.0472662e+08 | W58: =U58-F58 -> 0
B59: =B58+1 -> 7 | D59: Communication Equipment: Original Cost | E59: II-B-3 | F59: =+F212 -> 45688861 | J59: =+J212 -> 25471760 | K59: =+K212 -> 3927089.4 | L59: =+L212 -> 12113243 | M59: =+M212 -> 170088.33 | N59: =+N212 -> 3549285.2 | O59: =+O212 -> 121289.74 | P59: =+P212 -> 264038.44 | Q59: =+Q212 -> 25390.813 | ... S59: =+S212 -> 32680.944 | U59: =SUM(I59:T59) -> 45688861 | W59: =U59-F59 -> 0
B60: =B59+1 -> 8 | D60: Total Plant | F60: =+F56+F58+F59 -> 9.0986468e+08 | J60: =+J56+J58+J59 -> 5.0725394e+08 | K60: =+K56+K58+K59 -> 78205494 | L60: =+L56+L58+L59 -> 2.4122755e+08 | M60: =+M56+M58+M59 -> 3387201.1 | N60: =+N56+N58+N59 -> 70681763 | O60: =+O56+O58+O59 -> 2415408.3 | P60: =+P56+P58+P59 -> 5258158 | Q60: =+Q56+Q58+Q59 -> 505641.93 | ... S60: =+S56+S58+S59 -> 650820.27 | U60: =SUM(I60:T60) -> 9.0986468e+08 | W60: =U60-F60 -> 0
B61: =B60+1 -> 9 | W61: =U61-F61 -> 0
B62: =B61+1 -> 10 | D62: Minus: Accumulated Depreciation | E62: II-B-5 | F62: =+F349+F308 -> 5.7502597e+08 | J62: =+J349+J308 -> 3.2057975e+08 | K62: =+K349+K308 -> 49425141 | L62: =+L349+L308 -> 1.5245356e+08 | M62: =+M349+M308 -> 2140679.4 | N62: =+N349+N308 -> 44670213 | O62: =+O349+O308 -> 1526515.4 | P62: =+P349+P308 -> 3323106.7 | Q62: =+Q349+Q308 -> 319560.97 | ... S62: =+S349+S308 -> 411312.33 | U62: =SUM(I62:T62) -> 5.7502597e+08 | W62: =U62-F62 -> 0
B63: =B62+1 -> 11 | W63: =U63-F63 -> 0
B64: =B63+1 -> 12 | D64: NET PLANT IN SERVICE | F64: =+F60-F62 -> 3.3483871e+08 | J64: =+J60-J62 -> 1.8667419e+08 | K64: =+K60-K62 -> 28780353 | L64: =+L60-L62 -> 88773995 | M64: =+M60-M62 -> 1246521.7 | N64: =+N60-N62 -> 26011550 | O64: =+O60-O62 -> 888892.84 | P64: =+P60-P62 -> 1935051.3 | Q64: =+Q60-Q62 -> 186080.96 | ... S64: =+S60-S62 -> 239507.95 | U64: =SUM(I64:T64) -> 3.3483871e+08 | W64: =U64-F64 -> 0
B65: =B64+1 -> 13 | W65: =U65-F65 -> 0
B66: =B65+1 -> 14 | D66: Other Rate Base Items: | W66: =U66-F66 -> 0
B67: =B66+1 -> 15 | W67: =U67-F67 -> 0
B68: =B67+1 -> 16 | D68: CWIP | E68: II-B-4 | F68: =+F237 -> 0 | J68: =+J237 -> 0 | K68: =+K237 -> 0 | L68: =+L237 -> 0 | M68: =+M237 -> 0 | N68: =+N237 -> 0 | O68: =+O237 -> 0 | P68: =+P237 -> 0 | Q68: =+Q237 -> 0 | ... S68: =+S237 -> 0 | U68: =SUM(I68:T68) -> 0 | W68: =U68-F68 -> 0
B69: =B68+1 -> 17 | D69: Plant Held for Future Use | E69: II-B-6 | F69: =+F374 -> 0 | J69: =+J374 -> 0 | K69: =+K374 -> 0 | L69: =+L374 -> 0 | M69: =+M374 -> 0 | N69: =+N374 -> 0 | O69: =+O374 -> 0 | P69: =+P374 -> 0 | Q69: =+Q374 -> 0 | ... S69: =+S374 -> 0 | U69: =SUM(I69:T69) -> 0 | W69: =U69-F69 -> 0
B70: =B69+1 -> 18 | D70: Accumulated Provisions ex ADFIT | E70: II-B-7 | F70: =F395 -> 0 | J70: =J395 -> 0 | K70: =K395 -> 0 | L70: =L395 -> 0 | M70: =M395 -> 0 | N70: =N395 -> 0 | O70: =O395 -> 0 | P70: =P395 -> 0 | Q70: =Q395 -> 0 | ... S70: =S395 -> 0 | U70: =SUM(I70:T70) -> 0 | W70: =U70-F70 -> 0
B71: =B70+1 -> 19 | D71: Materials & Supplies | E71: II-B-8 | F71: =+F421 -> 105783.33 | J71: =+J421 -> 58974.716 | K71: =+K421 -> 9092.3824 | L71: =+L421 -> 28045.768 | M71: =+M421 -> 393.80517 | N71: =+N421 -> 8217.653 | O71: =+O421 -> 280.8219 | P71: =+P421 -> 611.32769 | Q71: =+Q421 -> 58.7873 | ... S71: =+S421 -> 75.666126 | U71: =SUM(I71:T71) -> 105783.33 | W71: =U71-F71 -> 0
B72: =B71+1 -> 20 | D72: Cash Working Capital | E72: II-B-9 | F72: =+F441 -> 273938.61 | J72: =+J441 -> 152823.35 | K72: =+K441 -> 23535.149 | L72: =+L441 -> 72503.036 | M72: =+M441 -> 1018.0369 | N72: =+N441 -> 21237.047 | O72: =+O441 -> 725.9926 | P72: =+P441 -> 1579.7721 | Q72: =+Q441 -> 236.87979 | ... S72: =+S441 -> 195.57575 | U72: =SUM(I72:T72) -> 273938.61 | W72: =U72-F72 -> 0
B73: =B72+1 -> 21 | D73: Prepayments | E73: II-B-10 | F73: =+F462 -> 3524809.2 | J73: =+J462 -> 1415512.1 | K73: =+K462 -> 50564.832 | L73: =+L462 -> 1482026.8 | M73: =+M462 -> 25.580208 | N73: =+N462 -> 238298.91 | O73: =+O462 -> 37494.731 | P73: =+P462 -> 280861.61 | Q73: =+Q462 -> 12902.848 | ... S73: =+S462 -> 4260.7907 | U73: =SUM(I73:T73) -> 3524809.2 | W73: =U73-F73 -> 0
B74: =B73+1 -> 22 | D74: Misc Other Rate Base | E74: II-B-11 | F74: =F483 -> -668323.9 | J74: =J483 -> -320780.65 | K74: =K483 -> -7833.5328 | L74: =L483 -> -206541.79 | M74: =M483 -> -116.76659 | N74: =N483 -> -49421.498 | O74: =O483 -> -17872.53 | P74: =P483 -> -58848.988 | Q74: =Q483 -> -2083.2702 | ... S74: =S483 -> -2682.736 | U74: =SUM(I74:T74) -> -668323.9 | W74: =U74-F74 -> 0
B75: =B74+1 -> 23 | D75: Regulatory Assets | E75: II-B-12 | F75: =F591 -> 1.199017e+08 | J75: =J591 -> 66849413 | K75: =K591 -> 10305747 | L75: =L591 -> 31785943 | M75: =M591 -> 446322.48 | N75: =N591 -> 9313368 | O75: =O591 -> 318272.79 | P75: =P591 -> 692837.57 | Q75: =Q591 -> 68927.866 | ... S75: =S591 -> 84624.718 | U75: =SUM(I75:T75) -> 1.199017e+08 | W75: =U75-F75 -> 0
B76: =B75+1 -> 24 | D76: Acuumulated Deferred Income Taxes | E76: II-E3.7 | F76: =+F399 -> -36656474 | J76: =+J399 -> -20436161 | K76: =+K399 -> -3150729.7 | L76: =+L399 -> -9718534.8 | M76: =+M399 -> -136462.98 | N76: =+N399 -> -2847614.9 | O76: =+O399 -> -97311.56 | P76: =+P399 -> -211839.78 | Q76: =+Q399 -> -20371.217 | ... S76: =+S399 -> -26220.137 | U76: =SUM(I76:T76) -> -36656474 | W76: =U76-F76 -> 0
B77: =B76+1 -> 25 | D77: Subtotal | F77: =SUM(F68:F76) -> 86481429 | J77: =SUM(J68:J76) -> 47719782 | K77: =SUM(K68:K76) -> 7230375.7 | L77: =SUM(L68:L76) -> 23443442 | M77: =SUM(M68:M76) -> 311180.15 | N77: =SUM(N68:N76) -> 6684085.2 | O77: =SUM(O68:O76) -> 241590.24 | P77: =SUM(P68:P76) -> 705201.5 | Q77: =SUM(Q68:Q76) -> 59671.894 | ... S77: =SUM(S68:S76) -> 60253.878 | U77: =SUM(I77:T77) -> 86481429 | W77: =U77-F77 -> 0
B78: =B77+1 -> 26 | W78: =U78-F78 -> 0
B79: =B78+1 -> 27 | D79: TOTAL RATE BASE | F79: =+F64+F77 -> 4.2132014e+08 | J79: =+J64+J77 -> 2.3439398e+08 | K79: =+K64+K77 -> 36010729 | L79: =+L64+L77 -> 1.1221744e+08 | M79: =+M64+M77 -> 1557701.8 | N79: =+N64+N77 -> 32695635 | O79: =+O64+O77 -> 1130483.1 | P79: =+P64+P77 -> 2640252.8 | Q79: =+Q64+Q77 -> 245752.85 | ... S79: =+S64+S77 -> 299761.83 | U79: =SUM(I79:T79) -> 4.2132014e+08 | W79: =U79-F79 -> 0
B80: =B79+1 -> 28 | W80: =U80-F80 -> 0
B81: =B80+1 -> 29 | D81: COST-BASED Rate of Return | F81: =F597 -> 0.0705 | J81: =J597 -> 0.0705 | K81: =K597 -> 0.0705 | L81: =L597 -> 0.0705 | M81: =M597 -> 0.0705 | N81: =N597 -> 0.0705 | O81: =O597 -> 0.0705 | P81: =P597 -> 0.0705 | Q81: =Q597 -> 0.0705 | ... S81: =S597 -> 0.0705 | U81: =U83/U79 -> 0.0705 | W81: =U81-F81 -> 0
B82: =B81+1 -> 30 | W82: =U82-F82 -> 0
B83: =B82+1 -> 31 | D83: COST-BASED Return On Rate Base | F83: =+F79*F81 -> 29703070 | J83: =+J79*J81 -> 16524775 | K83: =+K79*K81 -> 2538756.4 | L83: =+L79*L81 -> 7911329.3 | M83: =+M79*M81 -> 109817.98 | N83: =+N79*N81 -> 2305042.3 | O83: =+O79*O81 -> 79699.057 | P83: =+P79*P81 -> 186137.83 | Q83: =+Q79*Q81 -> 17325.576 | ... S83: =+S79*S81 -> 21133.209 | U83: =SUM(I83:T83) -> 29703070 | W83: =IF(ROUND(U83-'WP II-I-1.1'!H461,2)=0,TRUE,U83-'WP II-I-1.1'!H461) -> TRUE
W86: =U86-F86 -> 0
W87: =U87-F87 -> 0
W88: =U88-F88 -> 0
W89: =U89-F89 -> 0
W90: =U90-F90 -> 0
B91: =+$B$4 -> 2022 RATE CASE | V91: =$H$2 -> 0
B92: =+$B$5 -> ONCOR ELECTRIC DELIVERY COMPANY LLC | W92: =U92-F92 -> 0
B93: =+$B$6 -> II-I-1-MET: CLASS REVENUE REQUIREMENT | W93: =U93-F93 -> 0
B94: =+$B$7 -> TEST YEAR ENDING 12/31/2021 | W94: =U94-F94 -> 0
B95: =+$B$8 -> SPONSOR: MATTHEW A. TROXLE | W95: =U95-F95 -> 0
W96: =U96-F96 -> 0
R97: =R$10 | W97: =U97-F97 -> 0
B98: Line | C98: Acct | D98: Intangible and Transmission Plant Gross | E98: Source | F98: =F$11 -> MET | G98: Alloc | H98: Allocation | J98: Residential | K98: Secondary | L98: Secondary | M98: Primary | N98: Primary | O98: Primary | P98: Transmission | Q98: Lighting | R98: =R$11 -> Wholesale | S98: =S$11 -> Wholesale | U98: Total
G99: # | H99: Factor | K99: <=10 kW | L99: > 10 kW | M99: <=10 kW | N99: > 10 kW | O99: Substation | R99: =R$12 -> XFMR | S99: =S$12 -> DLS | W99: =U99-F99 -> 0
F100: (a) | G100: (b) | H100: (c) | J100: =J$13 -> (d) | K100: =K$13 -> (e) | L100: =L$13 -> (f) | M100: =M$13 -> (g) | N100: =N$13 -> (h) | O100: =O$13 -> (i) | P100: =P$13 -> (j) | Q100: =Q$13 -> (k) | ... S100: =S$13 -> (m) | U100: (n)
W101: =U101-F101 -> 0
B102: =B101+1 -> 1 | C102: Intangible Plant Gross | E102: II-B-1 | W102: =U102-F102 -> 0
B103: =B102+1 -> 2 | C103: A301 | D103: Organization | F103: =' WP II-I-1.4'!H103 -> 0 | G103: 65 | H103: =VLOOKUP(G103,FactorTable,2) -> PLT_N XINT | J103: =$F103*HLOOKUP(J$1318,FactorTable,$G103+1) -> 0 | K103: =$F103*HLOOKUP(K$1318,FactorTable,$G103+1) -> 0 | L103: =$F103*HLOOKUP(L$1318,FactorTable,$G103+1) -> 0 | M103: =$F103*HLOOKUP(M$1318,FactorTable,$G103+1) -> 0 | N103: =$F103*HLOOKUP(N$1318,FactorTable,$G103+1) -> 0 | O103: =$F103*HLOOKUP(O$1318,FactorTable,$G103+1) -> 0 | P103: =$F103*HLOOKUP(P$1318,FactorTable,$G103+1) -> 0 | Q103: =$F103*HLOOKUP(Q$1318,FactorTable,$G103+1) -> 0 | ... S103: =$F103*HLOOKUP(S$1318,FactorTable,$G103+1) -> 0 | U103: =SUM(I103:T103) -> 0 | W103: =U103-F103 -> 0
B104: =B103+1 -> 3 | C104: A302 | D104: Franchise & Consents | F104: =' WP II-I-1.4'!H104 -> 0 | G104: 65 | H104: =VLOOKUP(G104,FactorTable,2) -> PLT_N XINT | J104: =$F104*HLOOKUP(J$1318,FactorTable,$G104+1) -> 0 | K104: =$F104*HLOOKUP(K$1318,FactorTable,$G104+1) -> 0 | L104: =$F104*HLOOKUP(L$1318,FactorTable,$G104+1) -> 0 | M104: =$F104*HLOOKUP(M$1318,FactorTable,$G104+1) -> 0 | N104: =$F104*HLOOKUP(N$1318,FactorTable,$G104+1) -> 0 | O104: =$F104*HLOOKUP(O$1318,FactorTable,$G104+1) -> 0 | P104: =$F104*HLOOKUP(P$1318,FactorTable,$G104+1) -> 0 | Q104: =$F104*HLOOKUP(Q$1318,FactorTable,$G104+1) -> 0 | ... S104: =$F104*HLOOKUP(S$1318,FactorTable,$G104+1) -> 0 | U104: =SUM(I104:T104) -> 0 | W104: =U104-F104 -> 0
B105: =B104+1 -> 4 | C105: A303 | D105: Miscellaneous Intangible Plant | F105: =' WP II-I-1.4'!H105 -> 1.8530171e+08 | G105: 65 | H105: =VLOOKUP(G105,FactorTable,2) -> PLT_N XINT | J105: =$F105*HLOOKUP(J$1318,FactorTable,$G105+1) -> 1.033066e+08 | K105: =$F105*HLOOKUP(K$1318,FactorTable,$G105+1) -> 15927217 | L105: =$F105*HLOOKUP(L$1318,FactorTable,$G105+1) -> 49128051 | M105: =$F105*HLOOKUP(M$1318,FactorTable,$G105+1) -> 689832.43 | N105: =$F105*HLOOKUP(N$1318,FactorTable,$G105+1) -> 14394945 | O105: =$F105*HLOOKUP(O$1318,FactorTable,$G105+1) -> 491918.53 | P105: =$F105*HLOOKUP(P$1318,FactorTable,$G105+1) -> 1070868.8 | Q105: =$F105*HLOOKUP(Q$1318,FactorTable,$G105+1) -> 102978.3 | ... S105: =$F105*HLOOKUP(S$1318,FactorTable,$G105+1) -> 132545.11 | U105: =SUM(I105:T105) -> 1.8530171e+08 | W105: =U105-F105 -> 0
B106: =B105+1 -> 5 | D106: Subtotal | F106: =SUM(F103:F105) -> 1.8530171e+08 | J106: =SUM(J103:J105) -> 1.033066e+08 | K106: =SUM(K103:K105) -> 15927217 | L106: =SUM(L103:L105) -> 49128051 | M106: =SUM(M103:M105) -> 689832.43 | N106: =SUM(N103:N105) -> 14394945 | O106: =SUM(O103:O105) -> 491918.53 | P106: =SUM(P103:P105) -> 1070868.8 | Q106: =SUM(Q103:Q105) -> 102978.3 | ... S106: =SUM(S103:S105) -> 132545.11 | U106: =SUM(I106:T106) -> 1.8530171e+08 | W106: =U106-F106 -> 0
B107: =B106+1 -> 6 | C107: Transmission Plant Gross | E107: II-B-1 | W107: =U107-F107 -> 0
B108: =B107+1 -> 7 | C108: A349 | D108: Land Owned in Fee | F108: =' WP II-I-1.4'!H108 -> 0 | G108: 28 | H108: =VLOOKUP(G108,FactorTable,2) -> NCP XHV | J108: =$F108*HLOOKUP(J$1318,FactorTable,$G108+1) -> 0 | K108: =$F108*HLOOKUP(K$1318,FactorTable,$G108+1) -> 0 | L108: =$F108*HLOOKUP(L$1318,FactorTable,$G108+1) -> 0 | M108: =$F108*HLOOKUP(M$1318,FactorTable,$G108+1) -> 0 | N108: =$F108*HLOOKUP(N$1318,FactorTable,$G108+1) -> 0 | O108: =$F108*HLOOKUP(O$1318,FactorTable,$G108+1) -> 0 | P108: =$F108*HLOOKUP(P$1318,FactorTable,$G108+1) -> 0 | Q108: =$F108*HLOOKUP(Q$1318,FactorTable,$G108+1) -> 0 | ... S108: =$F108*HLOOKUP(S$1318,FactorTable,$G108+1) -> 0 | U108: =SUM(I108:T108) -> 0 | W108: =U108-F108 -> 0
B109: =B108+1 -> 8 | C109: A350 | D109: Land and Land Rights | F109: =' WP II-I-1.4'!H109 -> 0 | G109: 28 | H109: =VLOOKUP(G109,FactorTable,2) -> NCP XHV | J109: =$F109*HLOOKUP(J$1318,FactorTable,$G109+1) -> 0 | K109: =$F109*HLOOKUP(K$1318,FactorTable,$G109+1) -> 0 | L109: =$F109*HLOOKUP(L$1318,FactorTable,$G109+1) -> 0 | M109: =$F109*HLOOKUP(M$1318,FactorTable,$G109+1) -> 0 | N109: =$F109*HLOOKUP(N$1318,FactorTable,$G109+1) -> 0 | O109: =$F109*HLOOKUP(O$1318,FactorTable,$G109+1) -> 0 | P109: =$F109*HLOOKUP(P$1318,FactorTable,$G109+1) -> 0 | Q109: =$F109*HLOOKUP(Q$1318,FactorTable,$G109+1) -> 0 | ... S109: =$F109*HLOOKUP(S$1318,FactorTable,$G109+1) -> 0 | U109: =SUM(I109:T109) -> 0 | W109: =U109-F109 -> 0
B110: =B109+1 -> 9 | C110: A352 | D110: Structures and Improvements | F110: =' WP II-I-1.4'!H110 -> 0 | G110: 28 | H110: =VLOOKUP(G110,FactorTable,2) -> NCP XHV | J110: =$F110*HLOOKUP(J$1318,FactorTable,$G110+1) -> 0 | K110: =$F110*HLOOKUP(K$1318,FactorTable,$G110+1) -> 0 | L110: =$F110*HLOOKUP(L$1318,FactorTable,$G110+1) -> 0 | M110: =$F110*HLOOKUP(M$1318,FactorTable,$G110+1) -> 0 | N110: =$F110*HLOOKUP(N$1318,FactorTable,$G110+1) -> 0 | O110: =$F110*HLOOKUP(O$1318,FactorTable,$G110+1) -> 0 | P110: =$F110*HLOOKUP(P$1318,FactorTable,$G110+1) -> 0 | Q110: =$F110*HLOOKUP(Q$1318,FactorTable,$G110+1) -> 0 | ... S110: =$F110*HLOOKUP(S$1318,FactorTable,$G110+1) -> 0 | U110: =SUM(I110:T110) -> 0 | W110: =U110-F110 -> 0
B111: =B110+1 -> 10 | C111: A353 | D111: Station Equipment | F111: =' WP II-I-1.4'!H111 -> 0 | G111: 28 | H111: =VLOOKUP(G111,FactorTable,2) -> NCP XHV | J111: =$F111*HLOOKUP(J$1318,FactorTable,$G111+1) -> 0 | K111: =$F111*HLOOKUP(K$1318,FactorTable,$G111+1) -> 0 | L111: =$F111*HLOOKUP(L$1318,FactorTable,$G111+1) -> 0 | M111: =$F111*HLOOKUP(M$1318,FactorTable,$G111+1) -> 0 | N111: =$F111*HLOOKUP(N$1318,FactorTable,$G111+1) -> 0 | O111: =$F111*HLOOKUP(O$1318,FactorTable,$G111+1) -> 0 | P111: =$F111*HLOOKUP(P$1318,FactorTable,$G111+1) -> 0 | Q111: =$F111*HLOOKUP(Q$1318,FactorTable,$G111+1) -> 0 | ... S111: =$F111*HLOOKUP(S$1318,FactorTable,$G111+1) -> 0 | U111: =SUM(I111:T111) -> 0 | W111: =U111-F111 -> 0
B112: =B111+1 -> 11 | C112: A354 | D112: Towers and Fixtures | F112: =' WP II-I-1.4'!H112 -> 0 | G112: 28 | H112: =VLOOKUP(G112,FactorTable,2) -> NCP XHV | J112: =$F112*HLOOKUP(J$1318,FactorTable,$G112+1) -> 0 | K112: =$F112*HLOOKUP(K$1318,FactorTable,$G112+1) -> 0 | L112: =$F112*HLOOKUP(L$1318,FactorTable,$G112+1) -> 0 | M112: =$F112*HLOOKUP(M$1318,FactorTable,$G112+1) -> 0 | N112: =$F112*HLOOKUP(N$1318,FactorTable,$G112+1) -> 0 | O112: =$F112*HLOOKUP(O$1318,FactorTable,$G112+1) -> 0 | P112: =$F112*HLOOKUP(P$1318,FactorTable,$G112+1) -> 0 | Q112: =$F112*HLOOKUP(Q$1318,FactorTable,$G112+1) -> 0 | ... S112: =$F112*HLOOKUP(S$1318,FactorTable,$G112+1) -> 0 | U112: =SUM(I112:T112) -> 0 | W112: =U112-F112 -> 0
B113: =B112+1 -> 12 | C113: A355 | D113: Poles and Fixtures | F113: =' WP II-I-1.4'!H113 -> 0 | G113: 28 | H113: =VLOOKUP(G113,FactorTable,2) -> NCP XHV | J113: =$F113*HLOOKUP(J$1318,FactorTable,$G113+1) -> 0 | K113: =$F113*HLOOKUP(K$1318,FactorTable,$G113+1) -> 0 | L113: =$F113*HLOOKUP(L$1318,FactorTable,$G113+1) -> 0 | M113: =$F113*HLOOKUP(M$1318,FactorTable,$G113+1) -> 0 | N113: =$F113*HLOOKUP(N$1318,FactorTable,$G113+1) -> 0 | O113: =$F113*HLOOKUP(O$1318,FactorTable,$G113+1) -> 0 | P113: =$F113*HLOOKUP(P$1318,FactorTable,$G113+1) -> 0 | Q113: =$F113*HLOOKUP(Q$1318,FactorTable,$G113+1) -> 0 | ... S113: =$F113*HLOOKUP(S$1318,FactorTable,$G113+1) -> 0 | U113: =SUM(I113:T113) -> 0 | W113: =U113-F113 -> 0
B114: =B113+1 -> 13 | C114: A356 | D114: O.H. Conductors & Devices | F114: =' WP II-I-1.4'!H114 -> 0 | G114: 28 | H114: =VLOOKUP(G114,FactorTable,2) -> NCP XHV | J114: =$F114*HLOOKUP(J$1318,FactorTable,$G114+1) -> 0 | K114: =$F114*HLOOKUP(K$1318,FactorTable,$G114+1) -> 0 | L114: =$F114*HLOOKUP(L$1318,FactorTable,$G114+1) -> 0 | M114: =$F114*HLOOKUP(M$1318,FactorTable,$G114+1) -> 0 | N114: =$F114*HLOOKUP(N$1318,FactorTable,$G114+1) -> 0 | O114: =$F114*HLOOKUP(O$1318,FactorTable,$G114+1) -> 0 | P114: =$F114*HLOOKUP(P$1318,FactorTable,$G114+1) -> 0 | Q114: =$F114*HLOOKUP(Q$1318,FactorTable,$G114+1) -> 0 | ... S114: =$F114*HLOOKUP(S$1318,FactorTable,$G114+1) -> 0 | U114: =SUM(I114:T114) -> 0 | W114: =U114-F114 -> 0
B115: =B114+1 -> 14 | C115: A357 | D115: Undergound Conduit | F115: =' WP II-I-1.4'!H115 -> 0 | G115: 28 | H115: =VLOOKUP(G115,FactorTable,2) -> NCP XHV | J115: =$F115*HLOOKUP(J$1318,FactorTable,$G115+1) -> 0 | K115: =$F115*HLOOKUP(K$1318,FactorTable,$G115+1) -> 0 | L115: =$F115*HLOOKUP(L$1318,FactorTable,$G115+1) -> 0 | M115: =$F115*HLOOKUP(M$1318,FactorTable,$G115+1) -> 0 | N115: =$F115*HLOOKUP(N$1318,FactorTable,$G115+1) -> 0 | O115: =$F115*HLOOKUP(O$1318,FactorTable,$G115+1) -> 0 | P115: =$F115*HLOOKUP(P$1318,FactorTable,$G115+1) -> 0 | Q115: =$F115*HLOOKUP(Q$1318,FactorTable,$G115+1) -> 0 | ... S115: =$F115*HLOOKUP(S$1318,FactorTable,$G115+1) -> 0 | U115: =SUM(I115:T115) -> 0 | W115: =U115-F115 -> 0
B116: =B115+1 -> 15 | C116: A358 | D116: Underground Conductors | F116: =' WP II-I-1.4'!H116 -> 0 | G116: 28 | H116: =VLOOKUP(G116,FactorTable,2) -> NCP XHV | J116: =$F116*HLOOKUP(J$1318,FactorTable,$G116+1) -> 0 | K116: =$F116*HLOOKUP(K$1318,FactorTable,$G116+1) -> 0 | L116: =$F116*HLOOKUP(L$1318,FactorTable,$G116+1) -> 0 | M116: =$F116*HLOOKUP(M$1318,FactorTable,$G116+1) -> 0 | N116: =$F116*HLOOKUP(N$1318,FactorTable,$G116+1) -> 0 | O116: =$F116*HLOOKUP(O$1318,FactorTable,$G116+1) -> 0 | P116: =$F116*HLOOKUP(P$1318,FactorTable,$G116+1) -> 0 | Q116: =$F116*HLOOKUP(Q$1318,FactorTable,$G116+1) -> 0 | ... S116: =$F116*HLOOKUP(S$1318,FactorTable,$G116+1) -> 0 | U116: =SUM(I116:T116) -> 0 | W116: =U116-F116 -> 0
B117: =B116+1 -> 16 | C117: A359 | D117: Roads and Trails | F117: =' WP II-I-1.4'!H117 -> 0 | G117: 28 | H117: =VLOOKUP(G117,FactorTable,2) -> NCP XHV | J117: =$F117*HLOOKUP(J$1318,FactorTable,$G117+1) -> 0 | K117: =$F117*HLOOKUP(K$1318,FactorTable,$G117+1) -> 0 | L117: =$F117*HLOOKUP(L$1318,FactorTable,$G117+1) -> 0 | M117: =$F117*HLOOKUP(M$1318,FactorTable,$G117+1) -> 0 | N117: =$F117*HLOOKUP(N$1318,FactorTable,$G117+1) -> 0 | O117: =$F117*HLOOKUP(O$1318,FactorTable,$G117+1) -> 0 | P117: =$F117*HLOOKUP(P$1318,FactorTable,$G117+1) -> 0 | Q117: =$F117*HLOOKUP(Q$1318,FactorTable,$G117+1) -> 0 | ... S117: =$F117*HLOOKUP(S$1318,FactorTable,$G117+1) -> 0 | U117: =SUM(I117:T117) -> 0 | W117: =U117-F117 -> 0
...

Sheet II-I-TBILLTDCS
B4: ='WP II-I-1.1'!B3 -> 2022 RATE CASE
B5: ='WP II-I-1.1'!B4 -> ONCOR ELECTRIC DELIVERY COMPANY LLC
B6: ="II-I-1-TBILLTDCS: CLASS REVENUE REQUIREMENT" -> II-I-1-TBILLTDCS: CLASS REVENUE REQUIREMENT
B7: ='WP II-I-1.1'!B6 -> TEST YEAR ENDING 12/31/2021
B8: ='WP II-I-2.2'!$B$7 -> SPONSOR: MATTHEW A. TROXLE
R10: =" "
B11: Line | D11: I-A-1 by Rate Class | E11: Source | F11: TBILLTDCS | J11: Residential | K11: Secondary | L11: Secondary | M11: Primary | N11: Primary | O11: Primary | P11: Transmission | Q11: Lighting | R11: Wholesale | S11: Wholesale | U11: Total
K12: <=10 kW | L12: > 10 kW | M12: <=10 kW | N12: > 10 kW | O12: Substation | R12: XFMR | S12: DLS
F13: (a) | G13: (b) | H13: (c) | J13: (d) | K13: (e) | L13: (f) | M13: (g) | N13: (h) | O13: (i) | P13: (j) | Q13: (k) | R13: (l) | S13: (m) | U13: (n)
B15: =B14+1 -> 1 | D15: O&M Expenses | E15: II-D-2 | F15: =F638+F686 -> 343150.73 | J15: =J638+J686 -> 0 | K15: =K638+K686 -> 0 | L15: =L638+L686 -> 0 | M15: =M638+M686 -> 0 | N15: =N638+N686 -> 0 | O15: =O638+O686 -> 0 | P15: =P638+P686 -> 0 | Q15: =Q638+Q686 -> 343150.73 | ... S15: =S638+S686 -> 0 | U15: =SUM(I15:T15) -> 343150.73 | W15: =F15-U15 -> 0
B16: =B15+1 -> 2 | D16: Customer Expenses | E16: II-D-2 | F16: =F706+F716+F726 -> 13109328 | J16: =J706+J716+J726 -> 7247520.3 | K16: =K706+K716+K726 -> 1019822.5 | L16: =L706+L716+L726 -> 3611980.2 | M16: =M706+M716+M726 -> 42313.5 | N16: =N706+N716+N726 -> 984478.35 | O16: =O706+O716+O726 -> 43110.051 | P16: =P706+P716+P726 -> 113383 | Q16: =Q706+Q716+Q726 -> 35301.089 | ... S16: =S706+S716+S726 -> 7995.7219 | U16: =SUM(I16:T16) -> 13109328 | W16: =F16-U16 -> 0
B17: =B16+1 -> 3 | D17: A&G Expenses | E17: II-D-2 | F17: =F760 -> 36701329 | J17: =J760 -> 19829491 | K17: =K760 -> 2788109 | L17: =L760 -> 9819896.6 | M17: =M760 -> 115387.34 | N17: =N760 -> 2677421.6 | O17: =O760 -> 116847.22 | P17: =P760 -> 306688.91 | Q17: =Q760 -> 1016370.9 | ... S17: =S760 -> 21787.096 | U17: =SUM(I17:T17) -> 36701329 | W17: =F17-U17 -> 0
B18: =B17+1 -> 4 | D18: O&M + Customer + A&G Expenses | F18: =SUM(F15:F17) -> 50153808 | J18: =SUM(J15:J17) -> 27077011 | K18: =SUM(K15:K17) -> 3807931.5 | L18: =SUM(L15:L17) -> 13431877 | M18: =SUM(M15:M17) -> 157700.84 | N18: =SUM(N15:N17) -> 3661900 | O18: =SUM(O15:O17) -> 159957.27 | P18: =SUM(P15:P17) -> 420071.91 | Q18: =SUM(Q15:Q17) -> 1394822.7 | ... S18: =SUM(S15:S17) -> 29782.818 | U18: =SUM(I18:T18) -> 50153808 | V18: ='WP II-I-1.1'!$I$462=U18 -> TRUE | W18: =F18-U18 -> 0
B19: =B18+1 -> 5 | W19: =F19-U19 -> 0
B20: =B19+1 -> 6 | D20: Depreciation & Amortization (II-E-1) | E20: II-E-1 | F20: =F1035 -> 32929277 | J20: =J1035 -> 18347025 | K20: =K1035 -> 2828638.7 | L20: =L1035 -> 8725034 | M20: =M1035 -> 122512.73 | N20: =N1035 -> 2556510.6 | O20: =O1035 -> 87363.65 | P20: =P1035 -> 190183.95 | Q20: =Q1035 -> 38388.521 | ... S20: =S1035 -> 23539.72 | U20: =SUM(I20:T20) -> 32929277 | W20: =F20-U20 -> 0
B21: =B20+1 -> 7 | D21: Other (II-E-4) | E21: II-E-4 | F21: =F1037+F1038 -> 0 | J21: =J1037+J1038 -> 0 | K21: =K1037+K1038 -> 0 | L21: =L1037+L1038 -> 0 | M21: =M1037+M1038 -> 0 | N21: =N1037+N1038 -> 0 | O21: =O1037+O1038 -> 0 | P21: =P1037+P1038 -> 0 | Q21: =Q1037+Q1038 -> 0 | ... S21: =S1037+S1038 -> 0 | U21: =SUM(I21:T21) -> 0 | W21: =F21-U21 -> 0
B22: =B21+1 -> 8 | D22: Depreciation, Amortization & Other Expenses | F22: =SUM(F20:F21) -> 32929277 | J22: =SUM(J20:J21) -> 18347025 | K22: =SUM(K20:K21) -> 2828638.7 | L22: =SUM(L20:L21) -> 8725034 | M22: =SUM(M20:M21) -> 122512.73 | N22: =SUM(N20:N21) -> 2556510.6 | O22: =SUM(O20:O21) -> 87363.65 | P22: =SUM(P20:P21) -> 190183.95 | Q22: =SUM(Q20:Q21) -> 38388.521 | ... S22: =SUM(S20:S21) -> 23539.72 | U22: =SUM(I22:T22) -> 32929277 | V22: ='WP II-I-1.1'!$I$463=U22 -> TRUE | W22: =F22-U22 -> 0
B23: =B22+1 -> 9 | W23: =F23-U23 -> 0
B24: =B23+1 -> 10 | D24: Taxes Other Than Federal Income Tax | E24: II-E-2 | F24: =+F1072 -> 4509539.8 | J24: =+J1072 -> 2510037.6 | K24: =+K1072 -> 386025.82 | L24: =+L1072 -> 1195666.6 | M24: =+M1072 -> 16701.902 | N24: =+N1072 -> 349565.77 | O24: =+O1072 -> 12048.112 | P24: =+P1072 -> 26539.762 | Q24: =+Q1072 -> 8370.8789 | ... S24: =+S1072 -> 3208.5373 | U24: =SUM(I24:T24) -> 4509539.8 | V24: ='WP II-I-1.1'!$I$464=U24 -> TRUE | W24: =F24-U24 -> 0
B25: =B24+1 -> 11 | D25: Federal Income Tax | E25: II-E-3 | F25: =+F1130 -> 2534176.5 | J25: =+J1130 -> 1409750.9 | K25: =+K1130 -> 216638 | L25: =+L1130 -> 673374.07 | M25: =+M1130 -> 9372.8659 | N25: =+N1130 -> 196536.41 | O25: =+O1130 -> 6828.8633 | P25: =+P1130 -> 15562.589 | Q25: =+Q1130 -> 3533.7599 | ... S25: =+S1130 -> 1803.3297 | U25: =SUM(I25:T25) -> 2534176.5 | V25: ='WP II-I-1.1'!$I$465-U25 -> 0 | W25: =F25-U25 -> 0
B26: =B25+1 -> 12 | W26: =F26-U26 -> 0
B27: =B26+1 -> 13 | D27: Return on Rate Base | E27: II-B | F27: =+F83 -> 14457605 | J27: =+J83 -> 8036462.2 | K27: =+K83 -> 1232489.1 | L27: =+L83 -> 3842610.5 | M27: =+M83 -> 53275.908 | N27: =+N83 -> 1119693.2 | O27: =+O83 -> 39139.978 | P27: =+P83 -> 89593.74 | Q27: =+Q83 -> 29686.704 | ... S27: =+S83 -> 10246.36 | U27: =SUM(I27:T27) -> 14457605 | V27: ='WP II-I-1.1'!$I$461=U27 -> TRUE | W27: =F27-U27 -> 0
B28: =B27+1 -> 14 | W28: =F28-U28 -> 0
B29: =B28+1 -> 15 | D29: TOTAL COST OF SERVICE | F29: =+F18+F22+F24+F25+F27 -> 1.0458441e+08 | J29: =+J18+J22+J24+J25+J27 -> 57380287 | K29: =+K18+K22+K24+K25+K27 -> 8471723.2 | L29: =+L18+L22+L24+L25+L27 -> 27868562 | M29: =+M18+M22+M24+M25+M27 -> 359564.24 | N29: =+N18+N22+N24+N25+N27 -> 7884205.9 | O29: =+O18+O22+O24+O25+O27 -> 305337.88 | P29: =+P18+P22+P24+P25+P27 -> 741951.95 | Q29: =+Q18+Q22+Q24+Q25+Q27 -> 1474802.5 | ... S29: =+S18+S22+S24+S25+S27 -> 68580.765 | U29: =SUM(I29:T29) -> 1.0458441e+08 | V29: ='WP II-I-1.1'!$I$476=U29 -> TRUE | W29: =F29-U29 -> 0
B30: =B29+1 -> 16
B31: =B30+1 -> 17 | D31: Minus: Other Revenues | E31: II-E-5 | F31: =+F1186 -> 205014.65 | J31: =+J1186 -> 174312.16 | K31: =+K1186 -> 16286.446 | L31: =+L1186 -> 10891.584 | M31: =+M1186 -> 165.89781 | N31: =+N1186 -> 382.93986 | O31: =+O1186 -> 6.9547614 | P31: =+P1186 -> 15.139981 | Q31: =+Q1186 -> 2953.5267 | ... S31: =+S1186 -> 0 | U31: =SUM(I31:T31) -> 205014.65 | V31: ='WP II-I-1.1'!$I$466=-U31 -> TRUE | W31: =F31-U31 -> 0
B32: =B31+1 -> 18
B33: =B32+1 -> 19 | D33: COST-BASED Revenue Requirement | F33: =+F29-F31 -> 1.0437939e+08 | J33: =+J29-J31 -> 57205975 | K33: =+K29-K31 -> 8455436.7 | L33: =+L29-L31 -> 27857670 | M33: =+M29-M31 -> 359398.35 | N33: =+N29-N31 -> 7883822.9 | O33: =+O29-O31 -> 305330.92 | P33: =+P29-P31 -> 741936.81 | Q33: =+Q29-Q31 -> 1471849 | ... S33: =+S29-S31 -> 68580.765 | U33: =SUM(I33:T33) -> 1.0437939e+08 | V33: ='WP II-I-1.1'!$I$467=U33 -> TRUE | W33: =F33-U33 -> 0
V41: =$H$2 -> 0
B42: =+$B$4 -> 2022 RATE CASE
B43: =+$B$5 -> ONCOR ELECTRIC DELIVERY COMPANY LLC
B44: =+$B$6 -> II-I-1-TBILLTDCS: CLASS REVENUE REQUIREMENT
B45: =+$B$7 -> TEST YEAR ENDING 12/31/2021
B46: =+$B$8 -> SPONSOR: MATTHEW A. TROXLE
R48: =R$10
B49: Line | D49: II-B by Rate Class | E49: Source | F49: =F$11 -> TBILLTDCS | J49: Residential | K49: Secondary | L49: Secondary | M49: Primary | N49: Primary | O49: Primary | P49: Transmission | Q49: Lighting | R49: =R$11 -> Wholesale | S49: =S$11 -> Wholesale | U49: Total
K50: <=10 kW | L50: > 10 kW | M50: <=10 kW | N50: > 10 kW | O50: Substation | R50: =R$12 -> XFMR | S50: =S$12 -> DLS
F51: (a) | G51: (b) | H51: (c) | J51: =J$13 -> (d) | K51: =K$13 -> (e) | L51: =L$13 -> (f) | M51: =M$13 -> (g) | N51: =N$13 -> (h) | O51: =O$13 -> (i) | P51: =P$13 -> (j) | Q51: =Q$13 -> (k) | ... S51: =S$13 -> (m) | U51: (n)
B53: =B52+1 -> 1 | D53: Intangible Plant: Original Cost | E53: II-B-1 | F53: =F106 -> 3.1040917e+08 | J53: =J106 -> 1.7294898e+08 | K53: =K106 -> 26664279 | L53: =L106 -> 82246889 | M53: =M106 -> 1154871.2 | N53: =N106 -> 24099051 | O53: =O106 -> 823537.02 | P53: =P106 -> 1792776.7 | Q53: =Q106 -> 361870.96 | ... S53: =S106 -> 221898.13 | U53: =SUM(I53:T53) -> 3.1040917e+08 | W53: =F53-U53 -> 0
B54: =B53+1 -> 2 | D54: Transmission Plant: Original Cost | E54: II-B-1 | F54: =F118 -> 0 | J54: =J118 -> 0 | K54: =K118 -> 0 | L54: =L118 -> 0 | M54: =M118 -> 0 | N54: =N118 -> 0 | O54: =O118 -> 0 | P54: =P118 -> 0 | Q54: =Q118 -> 0 | ... S54: =S118 -> 0 | U54: =SUM(I54:T54) -> 0 | W54: =F54-U54 -> 0
B55: =B54+1 -> 3 | D55: Distribution Plant: Original Cost | E55: II-B-1 | F55: =F154 -> 0 | J55: =J154 -> 0 | K55: =K154 -> 0 | L55: =L154 -> 0 | M55: =M154 -> 0 | N55: =N154 -> 0 | O55: =O154 -> 0 | P55: =P154 -> 0 | Q55: =Q154 -> 0 | ... S55: =S154 -> 0 | U55: =SUM(I55:T55) -> 0 | W55: =F55-U55 -> 0
B56: =B55+1 -> 4 | D56: Intangible, Transmission, Distribution Plant: Original Cost | F56: =SUM(F53:F55) -> 3.1040917e+08 | J56: =SUM(J53:J55) -> 1.7294898e+08 | K56: =SUM(K53:K55) -> 26664279 | L56: =SUM(L53:L55) -> 82246889 | M56: =SUM(M53:M55) -> 1154871.2 | N56: =SUM(N53:N55) -> 24099051 | O56: =SUM(O53:O55) -> 823537.02 | P56: =SUM(P53:P55) -> 1792776.7 | Q56: =SUM(Q53:Q55) -> 361870.96 | ... S56: =SUM(S53:S55) -> 221898.13 | U56: =SUM(I56:T56) -> 3.1040917e+08 | W56: =F56-U56 -> 0
B57: =B56+1 -> 5 | W57: =F57-U57 -> 0
B58: =B57+1 -> 6 | D58: General Plant: Original Cost | E58: II-B-2 | F58: =+F194 -> 1.0010076e+08 | J58: =+J194 -> 55772589 | K58: =+K194 -> 8598697 | L58: =+L194 -> 26522978 | M58: =+M194 -> 372422.89 | N58: =+N194 -> 7771462.4 | O58: =+O194 -> 265574.23 | P58: =+P194 -> 578134.67 | Q58: =+Q194 -> 116696.15 | ... S58: =+S194 -> 71557.713 | U58: =SUM(I58:T58) -> 1.0010076e+08 | W58: =F58-U58 -> 0
B59: =B58+1 -> 7 | D59: Communication Equipment: Original Cost | E59: II-B-3 | F59: =+F212 -> 1554894.4 | J59: =+J212 -> 866332 | K59: =+K212 -> 133566.08 | L59: =+L212 -> 411989.21 | M59: =+M212 -> 5784.954 | N59: =+N212 -> 120716.41 | O59: =+O212 -> 4125.2425 | P59: =+P212 -> 8980.3355 | Q59: =+Q212 -> 1812.6756 | ... S59: =+S212 -> 1111.527 | U59: =SUM(I59:T59) -> 1554894.4 | W59: =F59-U59 -> 0
B60: =B59+1 -> 8 | D60: Total Plant | F60: =+F56+F58+F59 -> 4.1206483e+08 | J60: =+J56+J58+J59 -> 2.295879e+08 | K60: =+K56+K58+K59 -> 35396542 | L60: =+L56+L58+L59 -> 1.0918186e+08 | M60: =+M56+M58+M59 -> 1533079 | N60: =+N56+N58+N59 -> 31991230 | O60: =+O56+O58+O59 -> 1093236.5 | P60: =+P56+P58+P59 -> 2379891.7 | Q60: =+Q56+Q58+Q59 -> 480379.79 | ... S60: =+S56+S58+S59 -> 294567.37 | U60: =SUM(I60:T60) -> 4.1206483e+08 | W60: =F60-U60 -> 0
B61: =B60+1 -> 9 | W61: =F61-U61 -> 0
B62: =B61+1 -> 10 | D62: Minus: Accumulated Depreciation | E62: II-B-5 | F62: =+F349+F308 -> 1.2653135e+08 | J62: =+J349+J308 -> 70498780 | K62: =+K349+K308 -> 10869096 | L62: =+L349+L308 -> 33526104 | M62: =+M349+M308 -> 470757.4 | N62: =+N349+N308 -> 9823438.8 | O62: =+O349+O308 -> 335696.43 | P62: =+P349+P308 -> 730785.31 | Q62: =+Q349+Q308 -> 147508.6 | ... S62: =+S349+S308 -> 90451.807 | U62: =SUM(I62:T62) -> 1.2653135e+08 | W62: =F62-U62 -> 0
B63: =B62+1 -> 11 | W63: =F63-U63 -> 0
B64: =B63+1 -> 12 | D64: NET PLANT IN SERVICE | F64: =+F60-F62 -> 2.8553347e+08 | J64: =+J60-J62 -> 1.5908912e+08 | K64: =+K60-K62 -> 24527445 | L64: =+L60-L62 -> 75655753 | M64: =+M60-M62 -> 1062321.6 | N64: =+N60-N62 -> 22167791 | O64: =+O60-O62 -> 757540.06 | P64: =+P60-P62 -> 1649106.4 | Q64: =+Q60-Q62 -> 332871.19 | ... S64: =+S60-S62 -> 204115.56 | U64: =SUM(I64:T64) -> 2.8553347e+08 | W64: =F64-U64 -> 0
B65: =B64+1 -> 13 | W65: =F65-U65 -> 0
B66: =B65+1 -> 14 | D66: Other Rate Base Items: | W66: =F66-U66 -> 0
B67: =B66+1 -> 15 | W67: =F67-U67 -> 0
B68: =B67+1 -> 16 | D68: CWIP | E68: II-B-4 | F68: =+F237 -> 0 | J68: =+J237 -> 0 | K68: =+K237 -> 0 | L68: =+L237 -> 0 | M68: =+M237 -> 0 | N68: =+N237 -> 0 | O68: =+O237 -> 0 | P68: =+P237 -> 0 | Q68: =+Q237 -> 0 | ... S68: =+S237 -> 0 | U68: =SUM(I68:T68) -> 0 | W68: =F68-U68 -> 0
B69: =B68+1 -> 17 | D69: Plant Held for Future Use | E69: II-B-6 | F69: =+F374 -> 0 | J69: =+J374 -> 0 | K69: =+K374 -> 0 | L69: =+L374 -> 0 | M69: =+M374 -> 0 | N69: =+N374 -> 0 | O69: =+O374 -> 0 | P69: =+P374 -> 0 | Q69: =+Q374 -> 0 | ... S69: =+S374 -> 0 | U69: =SUM(I69:T69) -> 0 | W69: =F69-U69 -> 0
B70: =B69+1 -> 18 | D70: Accumulated Provisions ex ADFIT | E70: II-B-7 | F70: =F395 -> 0 | J70: =J395 -> 0 | K70: =K395 -> 0 | L70: =L395 -> 0 | M70: =M395 -> 0 | N70: =N395 -> 0 | O70: =O395 -> 0 | P70: =P395 -> 0 | Q70: =Q395 -> 0 | ... S70: =S395 -> 0 | U70: =SUM(I70:T70) -> 0 | W70: =F70-U70 -> 0
B71: =B70+1 -> 19 | D71: Materials & Supplies | E71: II-B-8 | F71: =+F421 -> 0 | J71: =+J421 -> 0 | K71: =+K421 -> 0 | L71: =+L421 -> 0 | M71: =+M421 -> 0 | N71: =+N421 -> 0 | O71: =+O421 -> 0 | P71: =+P421 -> 0 | Q71: =+Q421 -> 0 | ... S71: =+S421 -> 0 | U71: =SUM(I71:T71) -> 0 | W71: =F71-U71 -> 0
B72: =B71+1 -> 20 | D72: Cash Working Capital | E72: II-B-9 | F72: =+F441 -> 141339.78 | J72: =+J441 -> 76146.777 | K72: =+K441 -> 10714.865 | L72: =+L441 -> 37949.621 | M72: =+M441 -> 444.5709 | N72: =+N441 -> 10343.517 | O72: =+O441 -> 452.93994 | P72: =+P441 -> 1191.2695 | Q72: =+Q441 -> 3976.2408 | ... S72: =+S441 -> 84.007829 | U72: =SUM(I72:T72) -> 141339.78 | W72: =F72-U72 -> 0
B73: =B72+1 -> 21 | D73: Prepayments | E73: II-B-10 | F73: =+F462 -> 930191.57 | J73: =+J462 -> 373551.42 | K73: =+K462 -> 13343.979 | L73: =+L462 -> 391104.53 | M73: =+M462 -> 6.7505763 | N73: =+N462 -> 62886.705 | O73: =+O462 -> 9894.8003 | P73: =+P462 -> 74118.934 | Q73: =+Q462 -> 3405.0411 | ... S73: =+S462 -> 1124.4159 | U73: =SUM(I73:T73) -> 930191.57 | W73: =F73-U73 -> 0
B74: =B73+1 -> 22 | D74: Misc Other Rate Base | E74: II-B-11 | F74: =F483 -> 0 | J74: =J483 -> 0 | K74: =K483 -> 0 | L74: =L483 -> 0 | M74: =M483 -> 0 | N74: =N483 -> 0 | O74: =O483 -> 0 | P74: =P483 -> 0 | Q74: =Q483 -> 0 | ... S74: =S483 -> 0 | U74: =SUM(I74:T74) -> 0 | W74: =F74-U74 -> 0
B75: =B74+1 -> 23 | D75: Regulatory Assets | E75: II-B-12 | F75: =F591 -> 4277692.2 | J75: =J591 -> 2264002.1 | K75: =K591 -> 301750.95 | L75: =L591 -> 1156841.5 | M75: =M591 -> 12169.157 | N75: =N591 -> 303153.05 | O75: =O591 -> 14949.823 | P75: =P591 -> 42016.249 | Q75: =Q591 -> 180872.04 | ... S75: =S591 -> 1356.527 | U75: =SUM(I75:T75) -> 4277692.2 | W75: =F75-U75 -> 0
B76: =B75+1 -> 24 | D76: Acuumulated Deferred Income Taxes | E76: II-E3.7 | F76: =+F399 -> -85810289 | J76: =+J399 -> -47810448 | K76: =+K399 -> -7371139.9 | L76: =+L399 -> -22736536 | M76: =+M399 -> -319255.49 | N76: =+N399 -> -6662002 | O76: =+O399 -> -227660.63 | P76: =+P399 -> -495599.69 | Q76: =+Q399 -> -100036.51 | ... S76: =+S399 -> -61342.075 | U76: =SUM(I76:T76) -> -85810289 | W76: =F76-U76 -> 0
B77: =B76+1 -> 25 | D77: Subtotal | F77: =SUM(F68:F76) -> -80461066 | J77: =SUM(J68:J76) -> -45096748 | K77: =SUM(K68:K76) -> -7045330.1 | L77: =SUM(L68:L76) -> -21150640 | M77: =SUM(M68:M76) -> -306635.01 | N77: =SUM(N68:N76) -> -6285618.7 | O77: =SUM(O68:O76) -> -202363.07 | P77: =SUM(P68:P76) -> -378273.23 | Q77: =SUM(Q68:Q76) -> 88216.803 | ... S77: =SUM(S68:S76) -> -58777.124 | U77: =SUM(I77:T77) -> -80461066 | W77: =F77-U77 -> 0
B78: =B77+1 -> 26 | W78: =F78-U78 -> 0
B79: =B78+1 -> 27 | D79: TOTAL RATE BASE | F79: =+F64+F77 -> 2.0507241e+08 | J79: =+J64+J77 -> 1.1399237e+08 | K79: =+K64+K77 -> 17482115 | L79: =+L64+L77 -> 54505113 | M79: =+M64+M77 -> 755686.64 | N79: =+N64+N77 -> 15882172 | O79: =+O64+O77 -> 555176.99 | P79: =+P64+P77 -> 1270833.2 | Q79: =+Q64+Q77 -> 421087.99 | ... S79: =+S64+S77 -> 145338.44 | U79: =SUM(I79:T79) -> 2.0507241e+08 | V79: =IF(ROUND(U79-'WP II-I-1.1'!I459,2)=0,TRUE,U79-'WP II-I-1.1'!I459) -> TRUE | W79: =F79-U79 -> 0
B80: =B79+1 -> 28 | W80: =F80-U80 -> 0
B81: =B80+1 -> 29 | D81: COST-BASED Rate of Return | F81: =F597 -> 0.0705 | J81: =J597 -> 0.0705 | K81: =K597 -> 0.0705 | L81: =L597 -> 0.0705 | M81: =M597 -> 0.0705 | N81: =N597 -> 0.0705 | O81: =O597 -> 0.0705 | P81: =P597 -> 0.0705 | Q81: =Q597 -> 0.0705 | ... S81: =S597 -> 0.0705 | U81: =U83/U79 -> 0.0705 | W81: =F81-U81 -> 0
B82: =B81+1 -> 30 | W82: =F82-U82 -> 0
B83: =B82+1 -> 31 | D83: COST-BASED Return On Rate Base | F83: =+F79*F81 -> 14457605 | J83: =+J79*J81 -> 8036462.2 | K83: =+K79*K81 -> 1232489.1 | L83: =+L79*L81 -> 3842610.5 | M83: =+M79*M81 -> 53275.908 | N83: =+N79*N81 -> 1119693.2 | O83: =+O79*O81 -> 39139.978 | P83: =+P79*P81 -> 89593.74 | Q83: =+Q79*Q81 -> 29686.704 | ... S83: =+S79*S81 -> 10246.36 | U83: =SUM(I83:T83) -> 14457605 | V83: =IF(ROUND(U83-'WP II-I-1.1'!I461,2)=0,TRUE,U83-'WP II-I-1.1'!I461) -> TRUE | W83: =F83-U83 -> 0
B91: =+$B$4 -> 2022 RATE CASE | V91: =$H$2 -> 0
B92: =+$B$5 -> ONCOR ELECTRIC DELIVERY COMPANY LLC
B93: =+$B$6 -> II-I-1-TBILLTDCS: CLASS REVENUE REQUIREMENT
B94: =+$B$7 -> TEST YEAR ENDING 12/31/2021
B95: =+$B$8 -> SPONSOR: MATTHEW A. TROXLE
R97: =R$10
B98: Line | C98: Acct | D98: Intangible and Transmission Plant Gross | E98: Source | F98: =F$11 -> TBILLTDCS | G98: Alloc | H98: Allocation | J98: Residential | K98: Secondary | L98: Secondary | M98: Primary | N98: Primary | O98: Primary | P98: Transmission | Q98: Lighting | R98: =R$11 -> Wholesale | S98: =S$11 -> Wholesale | U98: Total
G99: # | H99: Factor | K99: <=10 kW | L99: > 10 kW | M99: <=10 kW | N99: > 10 kW | O99: Substation | R99: =R$12 -> XFMR | S99: =S$12 -> DLS
F100: (a) | G100: (b) | H100: (c) | J100: =J$13 -> (d) | K100: =K$13 -> (e) | L100: =L$13 -> (f) | M100: =M$13 -> (g) | N100: =N$13 -> (h) | O100: =O$13 -> (i) | P100: =P$13 -> (j) | Q100: =Q$13 -> (k) | ... S100: =S$13 -> (m) | U100: (n)
W101: =F101-U101 -> 0
B102: =B101+1 -> 1 | C102: Intangible Plant Gross | E102: II-B-1 | W102: =F102-U102 -> 0
B103: =B102+1 -> 2 | C103: A301 | D103: Organization | F103: =' WP II-I-1.4'!I103 -> 0 | G103: 65 | H103: =VLOOKUP(G103,FactorTable,2) -> PLT_N XINT | J103: =$F103*HLOOKUP(J$1318,FactorTable,$G103+1) -> 0 | K103: =$F103*HLOOKUP(K$1318,FactorTable,$G103+1) -> 0 | L103: =$F103*HLOOKUP(L$1318,FactorTable,$G103+1) -> 0 | M103: =$F103*HLOOKUP(M$1318,FactorTable,$G103+1) -> 0 | N103: =$F103*HLOOKUP(N$1318,FactorTable,$G103+1) -> 0 | O103: =$F103*HLOOKUP(O$1318,FactorTable,$G103+1) -> 0 | P103: =$F103*HLOOKUP(P$1318,FactorTable,$G103+1) -> 0 | Q103: =$F103*HLOOKUP(Q$1318,FactorTable,$G103+1) -> 0 | ... S103: =$F103*HLOOKUP(S$1318,FactorTable,$G103+1) -> 0 | U103: =SUM(I103:T103) -> 0 | W103: =F103-U103 -> 0
B104: =B103+1 -> 3 | C104: A302 | D104: Franchise & Consents | F104: =' WP II-I-1.4'!I104 -> 0 | G104: 65 | H104: =VLOOKUP(G104,FactorTable,2) -> PLT_N XINT | J104: =$F104*HLOOKUP(J$1318,FactorTable,$G104+1) -> 0 | K104: =$F104*HLOOKUP(K$1318,FactorTable,$G104+1) -> 0 | L104: =$F104*HLOOKUP(L$1318,FactorTable,$G104+1) -> 0 | M104: =$F104*HLOOKUP(M$1318,FactorTable,$G104+1) -> 0 | N104: =$F104*HLOOKUP(N$1318,FactorTable,$G104+1) -> 0 | O104: =$F104*HLOOKUP(O$1318,FactorTable,$G104+1) -> 0 | P104: =$F104*HLOOKUP(P$1318,FactorTable,$G104+1) -> 0 | Q104: =$F104*HLOOKUP(Q$1318,FactorTable,$G104+1) -> 0 | ... S104: =$F104*HLOOKUP(S$1318,FactorTable,$G104+1) -> 0 | U104: =SUM(I104:T104) -> 0 | W104: =F104-U104 -> 0
B105: =B104+1 -> 4 | C105: A303 | D105: Miscellaneous Intangible Plant | F105: =' WP II-I-1.4'!I105 -> 3.1040917e+08 | G105: 65 | H105: =VLOOKUP(G105,FactorTable,2) -> PLT_N XINT | J105: =$F105*HLOOKUP(J$1318,FactorTable,$G105+1) -> 1.7294898e+08 | K105: =$F105*HLOOKUP(K$1318,FactorTable,$G105+1) -> 26664279 | L105: =$F105*HLOOKUP(L$1318,FactorTable,$G105+1) -> 82246889 | M105: =$F105*HLOOKUP(M$1318,FactorTable,$G105+1) -> 1154871.2 | N105: =$F105*HLOOKUP(N$1318,FactorTable,$G105+1) -> 24099051 | O105: =$F105*HLOOKUP(O$1318,FactorTable,$G105+1) -> 823537.02 | P105: =$F105*HLOOKUP(P$1318,FactorTable,$G105+1) -> 1792776.7 | Q105: =$F105*HLOOKUP(Q$1318,FactorTable,$G105+1) -> 361870.96 | ... S105: =$F105*HLOOKUP(S$1318,FactorTable,$G105+1) -> 221898.13 | U105: =SUM(I105:T105) -> 3.1040917e+08 | W105: =F105-U105 -> 0
B106: =B105+1 -> 5 | D106: Subtotal | F106: =SUM(F103:F105) -> 3.1040917e+08 | J106: =SUM(J103:J105) -> 1.7294898e+08 | K106: =SUM(K103:K105) -> 26664279 | L106: =SUM(L103:L105) -> 82246889 | M106: =SUM(M103:M105) -> 1154871.2 | N106: =SUM(N103:N105) -> 24099051 | O106: =SUM(O103:O105) -> 823537.02 | P106: =SUM(P103:P105) -> 1792776.7 | Q106: =SUM(Q103:Q105) -> 361870.96 | ... S106: =SUM(S103:S105) -> 221898.13 | U106: =SUM(I106:T106) -> 3.1040917e+08 | W106: =F106-U106 -> 0
B107: =B106+1 -> 6 | C107: Transmission Plant Gross | E107: II-B-1 | W107: =F107-U107 -> 0
B108: =B107+1 -> 7 | C108: A349 | D108: Land Owned in Fee | F108: =' WP II-I-1.4'!I108 -> 0 | G108: 28 | H108: =VLOOKUP(G108,FactorTable,2) -> NCP XHV | J108: =$F108*HLOOKUP(J$1318,FactorTable,$G108+1) -> 0 | K108: =$F108*HLOOKUP(K$1318,FactorTable,$G108+1) -> 0 | L108: =$F108*HLOOKUP(L$1318,FactorTable,$G108+1) -> 0 | M108: =$F108*HLOOKUP(M$1318,FactorTable,$G108+1) -> 0 | N108: =$F108*HLOOKUP(N$1318,FactorTable,$G108+1) -> 0 | O108: =$F108*HLOOKUP(O$1318,FactorTable,$G108+1) -> 0 | P108: =$F108*HLOOKUP(P$1318,FactorTable,$G108+1) -> 0 | Q108: =$F108*HLOOKUP(Q$1318,FactorTable,$G108+1) -> 0 | ... S108: =$F108*HLOOKUP(S$1318,FactorTable,$G108+1) -> 0 | U108: =SUM(I108:T108) -> 0 | W108: =F108-U108 -> 0
B109: =B108+1 -> 8 | C109: A350 | D109: Land and Land Rights | F109: =' WP II-I-1.4'!I109 -> 0 | G109: 28 | H109: =VLOOKUP(G109,FactorTable,2) -> NCP XHV | J109: =$F109*HLOOKUP(J$1318,FactorTable,$G109+1) -> 0 | K109: =$F109*HLOOKUP(K$1318,FactorTable,$G109+1) -> 0 | L109: =$F109*HLOOKUP(L$1318,FactorTable,$G109+1) -> 0 | M109: =$F109*HLOOKUP(M$1318,FactorTable,$G109+1) -> 0 | N109: =$F109*HLOOKUP(N$1318,FactorTable,$G109+1) -> 0 | O109: =$F109*HLOOKUP(O$1318,FactorTable,$G109+1) -> 0 | P109: =$F109*HLOOKUP(P$1318,FactorTable,$G109+1) -> 0 | Q109: =$F109*HLOOKUP(Q$1318,FactorTable,$G109+1) -> 0 | ... S109: =$F109*HLOOKUP(S$1318,FactorTable,$G109+1) -> 0 | U109: =SUM(I109:T109) -> 0 | W109: =F109-U109 -> 0
B110: =B109+1 -> 9 | C110: A352 | D110: Structures and Improvements | F110: =' WP II-I-1.4'!I110 -> 0 | G110: 28 | H110: =VLOOKUP(G110,FactorTable,2) -> NCP XHV | J110: =$F110*HLOOKUP(J$1318,FactorTable,$G110+1) -> 0 | K110: =$F110*HLOOKUP(K$1318,FactorTable,$G110+1) -> 0 | L110: =$F110*HLOOKUP(L$1318,FactorTable,$G110+1) -> 0 | M110: =$F110*HLOOKUP(M$1318,FactorTable,$G110+1) -> 0 | N110: =$F110*HLOOKUP(N$1318,FactorTable,$G110+1) -> 0 | O110: =$F110*HLOOKUP(O$1318,FactorTable,$G110+1) -> 0 | P110: =$F110*HLOOKUP(P$1318,FactorTable,$G110+1) -> 0 | Q110: =$F110*HLOOKUP(Q$1318,FactorTable,$G110+1) -> 0 | ... S110: =$F110*HLOOKUP(S$1318,FactorTable,$G110+1) -> 0 | U110: =SUM(I110:T110) -> 0 | W110: =F110-U110 -> 0
B111: =B110+1 -> 10 | C111: A353 | D111: Station Equipment | F111: =' WP II-I-1.4'!I111 -> 0 | G111: 28 | H111: =VLOOKUP(G111,FactorTable,2) -> NCP XHV | J111: =$F111*HLOOKUP(J$1318,FactorTable,$G111+1) -> 0 | K111: =$F111*HLOOKUP(K$1318,FactorTable,$G111+1) -> 0 | L111: =$F111*HLOOKUP(L$1318,FactorTable,$G111+1) -> 0 | M111: =$F111*HLOOKUP(M$1318,FactorTable,$G111+1) -> 0 | N111: =$F111*HLOOKUP(N$1318,FactorTable,$G111+1) -> 0 | O111: =$F111*HLOOKUP(O$1318,FactorTable,$G111+1) -> 0 | P111: =$F111*HLOOKUP(P$1318,FactorTable,$G111+1) -> 0 | Q111: =$F111*HLOOKUP(Q$1318,FactorTable,$G111+1) -> 0 | ... S111: =$F111*HLOOKUP(S$1318,FactorTable,$G111+1) -> 0 | U111: =SUM(I111:T111) -> 0 | W111: =F111-U111 -> 0
B112: =B111+1 -> 11 | C112: A354 | D112: Towers and Fixtures | F112: =' WP II-I-1.4'!I112 -> 0 | G112: 28 | H112: =VLOOKUP(G112,FactorTable,2) -> NCP XHV | J112: =$F112*HLOOKUP(J$1318,FactorTable,$G112+1) -> 0 | K112: =$F112*HLOOKUP(K$1318,FactorTable,$G112+1) -> 0 | L112: =$F112*HLOOKUP(L$1318,FactorTable,$G112+1) -> 0 | M112: =$F112*HLOOKUP(M$1318,FactorTable,$G112+1) -> 0 | N112: =$F112*HLOOKUP(N$1318,FactorTable,$G112+1) -> 0 | O112: =$F112*HLOOKUP(O$1318,FactorTable,$G112+1) -> 0 | P112: =$F112*HLOOKUP(P$1318,FactorTable,$G112+1) -> 0 | Q112: =$F112*HLOOKUP(Q$1318,FactorTable,$G112+1) -> 0 | ... S112: =$F112*HLOOKUP(S$1318,FactorTable,$G112+1) -> 0 | U112: =SUM(I112:T112) -> 0 | W112: =F112-U112 -> 0
B113: =B112+1 -> 12 | C113: A355 | D113: Poles and Fixtures | F113: =' WP II-I-1.4'!I113 -> 0 | G113: 28 | H113: =VLOOKUP(G113,FactorTable,2) -> NCP XHV | J113: =$F113*HLOOKUP(J$1318,FactorTable,$G113+1) -> 0 | K113: =$F113*HLOOKUP(K$1318,FactorTable,$G113+1) -> 0 | L113: =$F113*HLOOKUP(L$1318,FactorTable,$G113+1) -> 0 | M113: =$F113*HLOOKUP(M$1318,FactorTable,$G113+1) -> 0 | N113: =$F113*HLOOKUP(N$1318,FactorTable,$G113+1) -> 0 | O113: =$F113*HLOOKUP(O$1318,FactorTable,$G113+1) -> 0 | P113: =$F113*HLOOKUP(P$1318,FactorTable,$G113+1) -> 0 | Q113: =$F113*HLOOKUP(Q$1318,FactorTable,$G113+1) -> 0 | ... S113: =$F113*HLOOKUP(S$1318,FactorTable,$G113+1) -> 0 | U113: =SUM(I113:T113) -> 0 | W113: =F113-U113 -> 0
B114: =B113+1 -> 13 | C114: A356 | D114: O.H. Conductors & Devices | F114: =' WP II-I-1.4'!I114 -> 0 | G114: 28 | H114: =VLOOKUP(G114,FactorTable,2) -> NCP XHV | J114: =$F114*HLOOKUP(J$1318,FactorTable,$G114+1) -> 0 | K114: =$F114*HLOOKUP(K$1318,FactorTable,$G114+1) -> 0 | L114: =$F114*HLOOKUP(L$1318,FactorTable,$G114+1) -> 0 | M114: =$F114*HLOOKUP(M$1318,FactorTable,$G114+1) -> 0 | N114: =$F114*HLOOKUP(N$1318,FactorTable,$G114+1) -> 0 | O114: =$F114*HLOOKUP(O$1318,FactorTable,$G114+1) -> 0 | P114: =$F114*HLOOKUP(P$1318,FactorTable,$G114+1) -> 0 | Q114: =$F114*HLOOKUP(Q$1318,FactorTable,$G114+1) -> 0 | ... S114: =$F114*HLOOKUP(S$1318,FactorTable,$G114+1) -> 0 | U114: =SUM(I114:T114) -> 0 | W114: =F114-U114 -> 0
B115: =B114+1 -> 14 | C115: A357 | D115: Undergound Conduit | F115: =' WP II-I-1.4'!I115 -> 0 | G115: 28 | H115: =VLOOKUP(G115,FactorTable,2) -> NCP XHV | J115: =$F115*HLOOKUP(J$1318,FactorTable,$G115+1) -> 0 | K115: =$F115*HLOOKUP(K$1318,FactorTable,$G115+1) -> 0 | L115: =$F115*HLOOKUP(L$1318,FactorTable,$G115+1) -> 0 | M115: =$F115*HLOOKUP(M$1318,FactorTable,$G115+1) -> 0 | N115: =$F115*HLOOKUP(N$1318,FactorTable,$G115+1) -> 0 | O115: =$F115*HLOOKUP(O$1318,FactorTable,$G115+1) -> 0 | P115: =$F115*HLOOKUP(P$1318,FactorTable,$G115+1) -> 0 | Q115: =$F115*HLOOKUP(Q$1318,FactorTable,$G115+1) -> 0 | ... S115: =$F115*HLOOKUP(S$1318,FactorTable,$G115+1) -> 0 | U115: =SUM(I115:T115) -> 0 | W115: =F115-U115 -> 0
B116: =B115+1 -> 15 | C116: A358 | D116: Underground Conductors | F116: =' WP II-I-1.4'!I116 -> 0 | G116: 28 | H116: =VLOOKUP(G116,FactorTable,2) -> NCP XHV | J116: =$F116*HLOOKUP(J$1318,FactorTable,$G116+1) -> 0 | K116: =$F116*HLOOKUP(K$1318,FactorTable,$G116+1) -> 0 | L116: =$F116*HLOOKUP(L$1318,FactorTable,$G116+1) -> 0 | M116: =$F116*HLOOKUP(M$1318,FactorTable,$G116+1) -> 0 | N116: =$F116*HLOOKUP(N$1318,FactorTable,$G116+1) -> 0 | O116: =$F116*HLOOKUP(O$1318,FactorTable,$G116+1) -> 0 | P116: =$F116*HLOOKUP(P$1318,FactorTable,$G116+1) -> 0 | Q116: =$F116*HLOOKUP(Q$1318,FactorTable,$G116+1) -> 0 | ... S116: =$F116*HLOOKUP(S$1318,FactorTable,$G116+1) -> 0 | U116: =SUM(I116:T116) -> 0 | W116: =F116-U116 -> 0
B117: =B116+1 -> 16 | C117: A359 | D117: Roads and Trails | F117: =' WP II-I-1.4'!I117 -> 0 | G117: 28 | H117: =VLOOKUP(G117,FactorTable,2) -> NCP XHV | J117: =$F117*HLOOKUP(J$1318,FactorTable,$G117+1) -> 0 | K117: =$F117*HLOOKUP(K$1318,FactorTable,$G117+1) -> 0 | L117: =$F117*HLOOKUP(L$1318,FactorTable,$G117+1) -> 0 | M117: =$F117*HLOOKUP(M$1318,FactorTable,$G117+1) -> 0 | N117: =$F117*HLOOKUP(N$1318,FactorTable,$G117+1) -> 0 | O117: =$F117*HLOOKUP(O$1318,FactorTable,$G117+1) -> 0 | P117: =$F117*HLOOKUP(P$1318,FactorTable,$G117+1) -> 0 | Q117: =$F117*HLOOKUP(Q$1318,FactorTable,$G117+1) -> 0 | ... S117: =$F117*HLOOKUP(S$1318,FactorTable,$G117+1) -> 0 | U117: =SUM(I117:T117) -> 0 | W117: =F117-U117 -> 0
B118: =B117+1 -> 17 | D118: Subtotal | F118: =SUM(F108:F117) -> 0 | J118: =SUM(J108:J117) -> 0 | K118: =SUM(K108:K117) -> 0 | L118: =SUM(L108:L117) -> 0 | M118: =SUM(M108:M117) -> 0 | N118: =SUM(N108:N117) -> 0 | O118: =SUM(O108:O117) -> 0 | P118: =SUM(P108:P117) -> 0 | Q118: =SUM(Q108:Q117) -> 0 | ... S118: =SUM(S108:S117) -> 0 | U118: =SUM(I118:T118) -> 0 | W118: =F118-U118 -> 0
V119: =$H$2 -> 0
B121: =+$B$4 -> 2022 RATE CASE
B122: =+$B$5 -> ONCOR ELECTRIC DELIVERY COMPANY LLC
B123: =+$B$6 -> II-I-1-TBILLTDCS: CLASS REVENUE REQUIREMENT
...

Sheet II-I-Total
B4: ='WP II-I-1.1'!B3 -> 2022 RATE CASE
B5: ='WP II-I-1.1'!B4 -> ONCOR ELECTRIC DELIVERY COMPANY LLC
B6: ="II-I-1-TOT: CLASS REVENUE REQUIREMENT" -> II-I-1-TOT: CLASS REVENUE REQUIREMENT
B7: ='WP II-I-1.1'!B6 -> TEST YEAR ENDING 12/31/2021
B8: ='WP II-I-2.2'!$B$7 -> SPONSOR: MATTHEW A. TROXLE
R10: =" "
B11: Line | D11: I-A-1 by Rate Class | E11: Source | F11: TOTAL | J11: Residential | K11: Secondary | L11: Secondary | M11: Primary | N11: Primary | O11: Primary | P11: Transmission | Q11: Lighting | R11: Wholesale | S11: Wholesale | U11: Total
F12: (Dist+Met+Cust) | K12: <=10 kW | L12: > 10 kW | M12: <=10 kW | N12: > 10 kW | O12: Substation | R12: XFMR | S12: DLS
F13: (a) | G13: (b) | H13: (c) | J13: (d) | K13: (e) | L13: (f) | M13: (g) | N13: (h) | O13: (i) | P13: (j) | Q13: (k) | R13: (l) | S13: (m) | U13: (n)
B15: =B14+1 -> 1 | D15: O&M Expenses | E15: II-D-2 | F15: =F638+F686 -> 2.0182035e+09 | J15: =J638+J686 -> 9.536258e+08 | K15: =K638+K686 -> 30038081 | L15: =L638+L686 -> 6.7172905e+08 | M15: =M638+M686 -> 478783.12 | N15: =N638+N686 -> 1.6410244e+08 | O15: =O638+O686 -> 47325216 | P15: =P638+P686 -> 1.3814434e+08 | Q15: =Q638+Q686 -> 11345272 | ... S15: =S638+S686 -> 1184432.9 | U15: =SUM(I15:T15) -> 2.0182035e+09 | X15: =U15-F15 -> 0
B16: =B15+1 -> 2 | D16: Customer Expenses | E16: II-D-2 | F16: =F706+F716+F726 -> 22154357 | J16: =J706+J716+J726 -> 12396028 | K16: =K706+K716+K726 -> 1795948 | L16: =L706+L716+L726 -> 5932491.6 | M16: =M706+M716+M726 -> 75000.036 | N16: =N706+N716+N726 -> 1660187.4 | O16: =O706+O716+O726 -> 66099.854 | P16: =P706+P716+P726 -> 163243.4 | Q16: =Q706+Q716+Q726 -> 45041.364 | ... S16: =S706+S716+S726 -> 14226.018 | U16: =SUM(I16:T16) -> 22154357 | X16: =U16-F16 -> 0
B17: =B16+1 -> 3 | D17: A&G Expenses | E17: II-D-2 | F17: =F760 -> 5.0996354e+08 | J17: =J760 -> 2.7614453e+08 | K17: =K760 -> 14974356 | L17: =L760 -> 1.6714918e+08 | M17: =M760 -> 374928.98 | N17: =N760 -> 31377473 | O17: =O760 -> 2525755.3 | P17: =P760 -> 929639.94 | Q17: =Q760 -> 14811582 | ... S17: =S760 -> 1382848.7 | U17: =SUM(I17:T17) -> 5.0996354e+08 | X17: =U17-F17 -> 0
B18: =B17+1 -> 4 | D18: O&M + Customer + A&G Expenses | F18: =SUM(F15:F17) -> 2.5503214e+09 | J18: =SUM(J15:J17) -> 1.2421664e+09 | K18: =SUM(K15:K17) -> 46808385 | L18: =SUM(L15:L17) -> 8.4481072e+08 | M18: =SUM(M15:M17) -> 928712.13 | N18: =SUM(N15:N17) -> 1.971401e+08 | O18: =SUM(O15:O17) -> 49917071 | P18: =SUM(P15:P17) -> 1.3923722e+08 | Q18: =SUM(Q15:Q17) -> 26201895 | ... S18: =SUM(S15:S17) -> 2581507.7 | U18: =SUM(I18:T18) -> 2.5503214e+09 | W18: =' WP II-I-1.4'!$L$18=F18 -> TRUE | X18: =U18-F18 -> 0
B19: =B18+1 -> 5 | X19: =U19-F19 -> 0
B20: =B19+1 -> 6 | D20: Depreciation & Amortization (II-E-1) | E20: II-E-1 | F20: =F1035 -> 5.2366079e+08 | J20: =J1035 -> 2.8112305e+08 | K20: =K1035 -> 15761938 | L20: =L1035 -> 1.6946638e+08 | M20: =M1035 -> 291163.56 | N20: =N1035 -> 27629168 | O20: =O1035 -> 1898475.8 | P20: =P1035 -> 724734.4 | Q20: =Q1035 -> 25262786 | ... S20: =S1035 -> 1276303.4 | U20: =SUM(I20:T20) -> 5.2366079e+08 | X20: =U20-F20 -> 0
B21: =B20+1 -> 7 | D21: Other (II-E-4) | E21: II-E-4 | F21: =F1037+F1038 -> 22687054 | J21: =J1037+J1038 -> 12650659 | K21: =K1037+K1038 -> 2137050.9 | L21: =L1037+L1038 -> 5773978.7 | M21: =M1037+M1038 -> 94427.674 | N21: =N1037+N1038 -> 1828228.1 | O21: =O1037+O1038 -> 52758.303 | P21: =P1037+P1038 -> 144326.39 | Q21: =Q1037+Q1038 -> -10486.339 | ... S21: =S1037+S1038 -> 10090.712 | U21: =SUM(I21:T21) -> 22687054 | X21: =U21-F21 -> 0
B22: =B21+1 -> 8 | D22: Depreciation, Amortization & Other Expenses | F22: =SUM(F20:F21) -> 5.4634784e+08 | J22: =SUM(J20:J21) -> 2.9377371e+08 | K22: =SUM(K20:K21) -> 17898989 | L22: =SUM(L20:L21) -> 1.7524036e+08 | M22: =SUM(M20:M21) -> 385591.23 | N22: =SUM(N20:N21) -> 29457396 | O22: =SUM(O20:O21) -> 1951234.2 | P22: =SUM(P20:P21) -> 869060.79 | Q22: =SUM(Q20:Q21) -> 25252299 | ... S22: =SUM(S20:S21) -> 1286394.1 | U22: =SUM(I22:T22) -> 5.4634784e+08 | W22: =' WP II-I-1.4'!$L$22=F22 -> TRUE | X22: =U22-F22 -> 0
B23: =B22+1 -> 9 | X23: =U23-F23 -> 0
B24: =B23+1 -> 10 | D24: Taxes Other Than Federal Income Tax | E24: II-E-2 | F24: =+F1072 -> 4.604982e+08 | J24: =+J1072 -> 2.10698e+08 | K24: =+K1072 -> 8641668.9 | L24: =+L1072 -> 1.7865294e+08 | M24: =+M1072 -> 71539.685 | N24: =+N1072 -> 28656332 | O24: =+O1072 -> 3850802.2 | P24: =+P1072 -> 22791529 | Q24: =+Q1072 -> 5993922.6 | ... S24: =+S1072 -> 811399.08 | U24: =SUM(I24:T24) -> 4.604982e+08 | W24: =' WP II-I-1.4'!$L$24=F24 -> TRUE | X24: =U24-F24 -> 0
B25: =B24+1 -> 11 | D25: Federal Income Tax | E25: II-E-3 | F25: =+F1130 -> 82404686 | J25: =+J1130 -> 45850278 | K25: =+K1130 -> 1770897.1 | L25: =+L1130 -> 28788315 | M25: =+M1130 -> 25535.902 | N25: =+N1130 -> 4606241.1 | O25: =+O1130 -> 442044.23 | P25: =+P1130 -> 162487.89 | Q25: =+Q1130 -> 473466.34 | ... S25: =+S1130 -> 232790.75 | U25: =SUM(I25:T25) -> 82404686 | W25: =' WP II-I-1.4'!$L$25-F25 -> 0 | X25: =U25-F25 -> 0
B26: =B25+1 -> 12 | X26: =U26-F26 -> 0
B27: =B26+1 -> 13 | D27: Return on Rate Base | E27: II-B | F27: =+F83 -> 6.8300051e+08 | J27: =+J83 -> 3.7983407e+08 | K27: =+K83 -> 15300982 | L27: =+L83 -> 2.3799621e+08 | M27: =+M83 -> 245203.7 | N27: =+N83 -> 38356623 | O27: =+O83 -> 3620199.3 | P27: =+P83 -> 1383463.3 | Q27: =+Q83 -> 3922745.9 | ... S27: =+S83 -> 1908877.7 | U27: =SUM(I27:T27) -> 6.8300051e+08 | W27: =' WP II-I-1.4'!$L$27=F27 -> TRUE | X27: =U27-F27 -> 0
B28: =B27+1 -> 14 | X28: =U28-F28 -> 0
B29: =B28+1 -> 15 | D29: TOTAL COST OF SERVICE | F29: =+F18+F22+F24+F25+F27 -> 4.3225726e+09 | J29: =+J18+J22+J24+J25+J27 -> 2.1723224e+09 | K29: =+K18+K22+K24+K25+K27 -> 90420922 | L29: =+L18+L22+L24+L25+L27 -> 1.4654886e+09 | M29: =+M18+M22+M24+M25+M27 -> 1656582.6 | N29: =+N18+N22+N24+N25+N27 -> 2.982167e+08 | O29: =+O18+O22+O24+O25+O27 -> 59781351 | P29: =+P18+P22+P24+P25+P27 -> 1.6444376e+08 | Q29: =+Q18+Q22+Q24+Q25+Q27 -> 61844329 | ... S29: =+S18+S22+S24+S25+S27 -> 6820969.3 | U29: =SUM(I29:T29) -> 4.3225726e+09 | W29: =' WP II-I-1.4'!$L$29=F29 -> TRUE | X29: =U29-F29 -> 0
B30: =B29+1 -> 16 | X30: =U30-F30 -> 0
B31: =B30+1 -> 17 | D31: Minus: Other Revenues | E31: II-E-5 | F31: =+F1186 -> 57057628 | J31: =+J1186 -> 36873131 | K31: =+K1186 -> 2417394.5 | L31: =+L1186 -> 14530138 | M31: =+M1186 -> 37722.118 | N31: =+N1186 -> 2409772.5 | O31: =+O1186 -> 131631.28 | P31: =+P1186 -> 67300.002 | Q31: =+Q1186 -> 533688.9 | ... S31: =+S1186 -> 53236.441 | U31: =SUM(I31:T31) -> 57057628 | W31: =' WP II-I-1.4'!$L$31=F31 -> TRUE | X31: =U31-F31 -> 0
B32: =B31+1 -> 18 | X32: =U32-F32 -> 0
B33: =B32+1 -> 19 | D33: COST_BASED Revenue Requirement | F33: =+F29-F31 -> 4.265515e+09 | J33: =+J29-J31 -> 2.1354493e+09 | K33: =+K29-K31 -> 88003528 | L33: =+L29-L31 -> 1.4509584e+09 | M33: =+M29-M31 -> 1618860.5 | N33: =+N29-N31 -> 2.9580692e+08 | O33: =+O29-O31 -> 59649719 | P33: =+P29-P31 -> 1.6437646e+08 | Q33: =+Q29-Q31 -> 61310640 | ... S33: =+S29-S31 -> 6767732.8 | U33: =SUM(I33:T33) -> 4.265515e+09 | W33: =' WP II-I-1.4'!$L$33-F33 -> 0 | X33: =U33-F33 -> 0
B34: =B33+1 -> 20 | X34: =U34-F34 -> 0
B35: =B34+1 -> 21 | D35: Proposed Adjustment to Return On Rate Base | F35: ='WP II-I-1.5'!D54 -> 0 | J35: ='WP II-I-1.5'!F54 -> 0 | K35: ='WP II-I-1.5'!G54 -> 0 | L35: ='WP II-I-1.5'!H54 -> 0 | M35: ='WP II-I-1.5'!I54 -> 0 | N35: ='WP II-I-1.5'!J54 -> 0 | O35: ='WP II-I-1.5'!K54 -> 0 | P35: ='WP II-I-1.5'!L54 -> 0 | Q35: ='WP II-I-1.5'!M54 -> 0 | ... S35: ='WP II-I-1.5'!O54 -> 0 | U35: =SUM(I35:T35) -> 0 | X35: =U35-F35 -> 0
B36: =B35+1 -> 22 | D36: (WP II-I-1.5) | X36: =U36-F36 -> 0
B37: =B36+1 -> 23 | D37: PROPOSED Revenue | F37: =F33+F35 -> 4.265515e+09 | J37: =J33+J35 -> 2.1354493e+09 | K37: =K33+K35 -> 88003528 | L37: =L33+L35 -> 1.4509584e+09 | M37: =M33+M35 -> 1618860.5 | N37: =N33+N35 -> 2.9580692e+08 | O37: =O33+O35 -> 59649719 | P37: =P33+P35 -> 1.6437646e+08 | Q37: =Q33+Q35 -> 61310640 | ... S37: =S33+S35 -> 6767732.8 | U37: =SUM(I37:T37) -> 4.265515e+09 | X37: =U37-F37 -> 0
B38: =B37+1 -> 24 | X38: =U38-F38 -> 0
B39: =B38+1 -> 25 | D39: PROPOSED Revenue Excl 565 & RCE A928 | F39: =+F37-F622-('II-I-DIST'!F753*0.727923) -> 2.6113464e+09 | J39: =+J37-J622-('II-I-DIST'!J753*0.727923) -> 1.3764363e+09 | K39: =+K37-K622-('II-I-DIST'!K753*0.727923) -> 66776950 | L39: =+L37-L622-('II-I-DIST'!L753*0.727923) -> 8.9922273e+08 | M39: =+M37-M622-('II-I-DIST'!M753*0.727923) -> 1399041.3 | N39: =+N37-N622-('II-I-DIST'!N753*0.727923) -> 1.571223e+08 | O39: =+O37-O622-('II-I-DIST'!O753*0.727923) -> 14242449 | P39: =+P37-P622-('II-I-DIST'!P753*0.727923) -> 26521581 | Q39: =+Q37-Q622-('II-I-DIST'!Q753*0.727923) -> 61287007 | ... S39: =+S37-S622-('II-I-DIST'!S753*0.727923) -> 6765131.3 | U39: =SUM(I39:T39) -> 2.6113464e+09 | W39: =U37-F622-1646626-U39 -> -0.22596502 | X39: =U39-F39 -> 0
X40: =U40-F40 -> 0
B42: =+$B$4 -> 2022 RATE CASE | X42: =U42-F42 -> 0
B43: =+$B$5 -> ONCOR ELECTRIC DELIVERY COMPANY LLC | X43: =U43-F43 -> 0
B44: =+$B$6 -> II-I-1-TOT: CLASS REVENUE REQUIREMENT | X44: =U44-F44 -> 0
B45: =+$B$7 -> TEST YEAR ENDING 12/31/2021 | X45: =U45-F45 -> 0
B46: =+$B$8 -> SPONSOR: MATTHEW A. TROXLE | X46: =U46-F46 -> 0
X47: =U47-F47 -> 0
R48: =R$10 | X48: =U48-F48 -> 0
B49: Line | D49: II-B by Rate Class | E49: Source | F49: =F$11 -> TOTAL | J49: Residential | K49: Secondary | L49: Secondary | M49: Primary | N49: Primary | O49: Primary | P49: Transmission | Q49: Lighting | R49: =R$11 -> Wholesale | S49: =S$11 -> Wholesale | U49: Total
F50: =F$12 -> (Dist+Met+Cust) | K50: <=10 kW | L50: > 10 kW | M50: <=10 kW | N50: > 10 kW | O50: Substation | R50: =R$12 -> XFMR | S50: =S$12 -> DLS
F51: (a) | G51: (b) | H51: (c) | J51: =J$13 -> (d) | K51: =K$13 -> (e) | L51: =L$13 -> (f) | M51: =M$13 -> (g) | N51: =N$13 -> (h) | O51: =O$13 -> (i) | P51: =P$13 -> (j) | Q51: =Q$13 -> (k) | ... S51: =S$13 -> (m) | U51: (n)
X52: =U52-F52 -> 0
B53: =B52+1 -> 1 | D53: Intangible Plant: Original Cost | E53: II-B-1 | F53: =F106 -> 8.1904426e+08 | J53: =J106 -> 4.5622203e+08 | K53: =K106 -> 48574010 | L53: =L106 -> 2.4519081e+08 | M53: =M106 -> 1885917.8 | N53: =N106 -> 55937888 | O53: =O106 -> 3044699.9 | P53: =P106 -> 3191084.5 | Q53: =Q106 -> 3337436.5 | ... S53: =S106 -> 1301346.1 | U53: =SUM(I53:T53) -> 8.1904426e+08 | X53: =U53-F53 -> 0
B54: =B53+1 -> 2 | D54: Transmission Plant: Original Cost | E54: II-B-1 | F54: =F118 -> 3.8186065e+08 | J54: =J118 -> 2.0098204e+08 | K54: =K118 -> 4908024.7 | L54: =L118 -> 1.2940677e+08 | M54: =M118 -> 73158.983 | N54: =N118 -> 30964565 | O54: =O118 -> 11197862 | P54: =P118 -> 0 | Q54: =Q118 -> 1305252.9 | ... S54: =S118 -> 1680842.5 | U54: =SUM(I54:T54) -> 3.8186065e+08 | X54: =U54-F54 -> 0
B55: =B54+1 -> 3 | D55: Distribution Plant: Original Cost | E55: II-B-1 | F55: =F154 -> 1.5192967e+10 | J55: =J154 -> 8.2824978e+09 | K55: =K154 -> 3.7737398e+08 | L55: =L154 -> 5.1057144e+09 | M55: =M154 -> 3819224.5 | N55: =N154 -> 7.5643096e+08 | O55: =O154 -> 58052556 | P55: =P154 -> 16755769 | Q55: =Q154 -> 5.4632066e+08 | ... S55: =S154 -> 39050736 | U55: =SUM(I55:T55) -> 1.5192967e+10 | X55: =U55-F55 -> 0
B56: =B55+1 -> 4 | D56: Intangible, Transmission, Distribution Plant: Original Cost | F56: =SUM(F53:F55) -> 1.6393872e+10 | J56: =SUM(J53:J55) -> 8.9397019e+09 | K56: =SUM(K53:K55) -> 4.3085602e+08 | L56: =SUM(L53:L55) -> 5.480312e+09 | M56: =SUM(M53:M55) -> 5778301.3 | N56: =SUM(N53:N55) -> 8.4333341e+08 | O56: =SUM(O53:O55) -> 72295118 | P56: =SUM(P53:P55) -> 19946854 | Q56: =SUM(Q53:Q55) -> 5.5096335e+08 | ... S56: =SUM(S53:S55) -> 42032925 | U56: =SUM(I56:T56) -> 1.6393872e+10 | W56: =' WP II-I-1.4'!$L$56=F56 -> TRUE | X56: =U56-F56 -> 0
B57: =B56+1 -> 5 | X57: =U57-F57 -> 0
B58: =B57+1 -> 6 | D58: General Plant: Original Cost | E58: II-B-2 | F58: =+F194 -> 5.3495937e+08 | J58: =+J194 -> 2.9790873e+08 | K58: =+K194 -> 23708559 | L58: =+L194 -> 1.7049762e+08 | M58: =+M194 -> 804374.91 | N58: =+N194 -> 33717706 | O58: =+O194 -> 2309195.5 | P58: =+P194 -> 1517679.5 | Q58: =+Q194 -> 3107884.4 | ... S58: =+S194 -> 1113281.1 | U58: =SUM(I58:T58) -> 5.3495937e+08 | X58: =U58-F58 -> 0
B59: =B58+1 -> 7 | D59: Communication Equipment: Original Cost | E59: II-B-3 | F59: =+F212 -> 1.0858171e+08 | J59: =+J212 -> 60478625 | K59: =+K212 -> 5195568.3 | L59: =+L212 -> 34116670 | M59: =+M212 -> 183691.81 | N59: =+N212 -> 6979195 | O59: =+O212 -> 453461.27 | P59: =+P212 -> 335135.58 | Q59: =+Q212 -> 572147.61 | ... S59: =+S212 -> 213424.67 | U59: =SUM(I59:T59) -> 1.0858171e+08 | X59: =U59-F59 -> 0
B60: =B59+1 -> 8 | D60: Total Plant | F60: =+F56+F58+F59 -> 1.7037413e+10 | J60: =+J56+J58+J59 -> 9.2980892e+09 | K60: =+K56+K58+K59 -> 4.5976014e+08 | L60: =+L56+L58+L59 -> 5.6849262e+09 | M60: =+M56+M58+M59 -> 6766368 | N60: =+N56+N58+N59 -> 8.8403031e+08 | O60: =+O56+O58+O59 -> 75057775 | P60: =+P56+P58+P59 -> 21799669 | Q60: =+Q56+Q58+Q59 -> 5.5464338e+08 | ... S60: =+S56+S58+S59 -> 43359630 | U60: =SUM(I60:T60) -> 1.7037413e+10 | W60: =' WP II-I-1.4'!$L$60=F60 -> TRUE | X60: =U60-F60 -> 0
B61: =B60+1 -> 9 | X61: =U61-F61 -> 0
B62: =B61+1 -> 10 | D62: Minus: Accumulated Depreciation | E62: II-B-5 | F62: =+F349+F308 -> 6.5713783e+09 | J62: =+J349+J308 -> 3.4722576e+09 | K62: =+K349+K308 -> 2.242818e+08 | L62: =+L349+L308 -> 2.0547465e+09 | M62: =+M349+M308 -> 3202534 | N62: =+N349+N308 -> 3.0467573e+08 | O62: =+O349+O308 -> 20754987 | P62: =+P349+P308 -> 8244831.2 | Q62: =+Q349+Q308 -> 4.6665272e+08 | ... S62: =+S349+S308 -> 14082341 | U62: =SUM(I62:T62) -> 6.5713783e+09 | X62: =U62-F62 -> 0
B63: =B62+1 -> 11 | X63: =U63-F63 -> 0
B64: =B63+1 -> 12 | D64: NET PLANT IN SERVICE | F64: =+F60-F62 -> 1.0466035e+10 | J64: =+J60-J62 -> 5.8258316e+09 | K64: =+K60-K62 -> 2.3547835e+08 | L64: =+L60-L62 -> 3.6301797e+09 | M64: =+M60-M62 -> 3563834 | N64: =+N60-N62 -> 5.7935458e+08 | O64: =+O60-O62 -> 54302788 | P64: =+P60-P62 -> 13554838 | Q64: =+Q60-Q62 -> 87990668 | ... S64: =+S60-S62 -> 29277289 | U64: =SUM(I64:T64) -> 1.0466035e+10 | W64: =' WP II-I-1.4'!$L$64=F64 -> TRUE | X64: =U64-F64 -> 0
B65: =B64+1 -> 13 | X65: =U65-F65 -> 0
B66: =B65+1 -> 14 | D66: Other Rate Base Items: | X66: =U66-F66 -> 0
B67: =B66+1 -> 15 | X67: =U67-F67 -> 0
B68: =B67+1 -> 16 | D68: CWIP | E68: II-B-4 | F68: =+F237 -> 0 | J68: =+J237 -> 0 | K68: =+K237 -> 0 | L68: =+L237 -> 0 | M68: =+M237 -> 0 | N68: =+N237 -> 0 | O68: =+O237 -> 0 | P68: =+P237 -> 0 | Q68: =+Q237 -> 0 | ... S68: =+S237 -> 0 | U68: =SUM(I68:T68) -> 0 | X68: =U68-F68 -> 0
B69: =B68+1 -> 17 | D69: Plant Held for Future Use | E69: II-B-6 | F69: =+F374 -> 1745979.3 | J69: =+J374 -> 918949.06 | K69: =+K374 -> 22440.934 | L69: =+L374 -> 591685.88 | M69: =+M374 -> 334.50441 | N69: =+N374 -> 141579.11 | O69: =+O374 -> 51199.923 | P69: =+P374 -> 0 | Q69: =+Q374 -> 5968.0008 | ... S69: =+S374 -> 7685.3067 | U69: =SUM(I69:T69) -> 1745979.3 | X69: =U69-F69 -> 0
B70: =B69+1 -> 18 | D70: Accumulated Provisions ex ADFIT | E70: II-B-7 | F70: =F395 -> 0 | J70: =J395 -> 0 | K70: =K395 -> 0 | L70: =L395 -> 0 | M70: =M395 -> 0 | N70: =N395 -> 0 | O70: =O395 -> 0 | P70: =P395 -> 0 | Q70: =Q395 -> 0 | ... S70: =S395 -> 0 | U70: =SUM(I70:T70) -> 0 | X70: =U70-F70 -> 0
B71: =B70+1 -> 19 | D71: Materials & Supplies | E71: II-B-8 | F71: =+F421 -> 74796188 | J71: =+J421 -> 40747702 | K71: =+K421 -> 1654265.4 | L71: =+L421 -> 25381209 | M71: =+M421 -> 9167.6393 | N71: =+N421 -> 3721746 | O71: =+O421 -> 340329.76 | P71: =+P421 -> 67916.737 | Q71: =+Q421 -> 2631405.9 | ... S71: =+S421 -> 201656.29 | U71: =SUM(I71:T71) -> 74796188 | X71: =U71-F71 -> 0
B72: =B71+1 -> 20 | D72: Cash Working Capital | E72: II-B-9 | F72: =+F441 -> -16280094 | J72: =+J441 -> -7625839.1 | K72: =+K441 -> -184146.95 | L72: =+L441 -> -5475610.1 | M72: =+M441 -> -1015.3782 | N72: =+N441 -> -1327565.4 | O72: =+O441 -> -399194.9 | P72: =+P441 -> -1166777.3 | Q72: =+Q441 -> -88778.188 | ... S72: =+S441 -> -9464.4007 | U72: =SUM(I72:T72) -> -16280094 | X72: =U72-F72 -> 0
B73: =B72+1 -> 21 | D73: Prepayments | E73: II-B-10 | F73: =+F462 -> 1.0457667e+08 | J73: =+J462 -> 41996472 | K73: =+K462 -> 1500195.2 | L73: =+L462 -> 43969879 | M73: =+M462 -> 758.93271 | N73: =+N462 -> 7070030 | O73: =+O462 -> 1112421.7 | P73: =+P462 -> 8332812.1 | Q73: =+Q462 -> 382811.32 | ... S73: =+S462 -> 126412.32 | U73: =SUM(I73:T73) -> 1.0457667e+08 | X73: =U73-F73 -> 0
B74: =B73+1 -> 22 | D74: Misc Other Rate Base | E74: II-B-11 | F74: =F483 -> -3096684.4 | J74: =J483 -> -1486339.9 | K74: =K483 -> -36296.74 | L74: =L483 -> -957013.13 | M74: =M483 -> -541.03897 | N74: =N483 -> -228994.93 | O74: =O483 -> -82812.519 | P74: =P483 -> -272677.28 | Q74: =Q483 -> -9652.8502 | ... S74: =S483 -> -12430.48 | U74: =SUM(I74:T74) -> -3096684.4 | X74: =U74-F74 -> 0
B75: =B74+1 -> 23 | D75: Regulatory Assets | E75: II-B-12 | F75: =F591 -> 3.146995e+08 | J75: =J591 -> 1.7228768e+08 | K75: =K591 -> 14057648 | L75: =L591 -> 98867929 | M75: =M591 -> 494228.68 | N75: =N591 -> 21128604 | O75: =O591 -> 1504600.5 | P75: =P591 -> 835047.18 | Q75: =Q591 -> 4732280 | ... S75: =S591 -> 627988.19 | U75: =SUM(I75:T75) -> 3.146995e+08 | X75: =U75-F75 -> 0
B76: =B75+1 -> 24 | D76: Acuumulated Deferred Income Taxes | E76: II-E3.7 | F76: =+F399 -> -1.254526e+09 | J76: =+J399 -> -6.8495297e+08 | K76: =+K399 -> -35457244 | L76: =+L399 -> -4.1672507e+08 | M76: =+M399 -> -588700.74 | N76: =+N399 -> -65794409 | O76: =+O399 -> -5478988 | P76: =+P399 -> -1727566.6 | Q76: =+Q399 -> -40002916 | ... S76: =+S399 -> -3142856.9 | U76: =SUM(I76:T76) -> -1.254526e+09 | X76: =U76-F76 -> 0
B77: =B76+1 -> 25 | D77: Subtotal | F77: =SUM(F68:F76) -> -7.780844e+08 | J77: =SUM(J68:J76) -> -4.3811435e+08 | K77: =SUM(K68:K76) -> -18443138 | L77: =SUM(L68:L76) -> -2.5434699e+08 | M77: =SUM(M68:M76) -> -85767.405 | N77: =SUM(N68:N76) -> -35289011 | O77: =SUM(O68:O76) -> -2952443.5 | P77: =SUM(P68:P76) -> 6068754.8 | Q77: =SUM(Q68:Q76) -> -32348882 | ... S77: =SUM(S68:S76) -> -2201009.6 | U77: =SUM(I77:T77) -> -7.780844e+08 | X77: =U77-F77 -> 0
B78: =B77+1 -> 26 | X78: =U78-F78 -> 0
B79: =B78+1 -> 27 | D79: TOTAL RATE BASE | F79: =+F64+F77 -> 9.6879505e+09 | J79: =+J64+J77 -> 5.3877173e+09 | K79: =+K64+K77 -> 2.1703521e+08 | L79: =+L64+L77 -> 3.3758328e+09 | M79: =+M64+M77 -> 3478066.6 | N79: =+N64+N77 -> 5.4406557e+08 | O79: =+O64+O77 -> 51350344 | P79: =+P64+P77 -> 19623592 | Q79: =+Q64+Q77 -> 55641786 | ... S79: =+S64+S77 -> 27076279 | U79: =SUM(I79:T79) -> 9.6879505e+09 | W79: =' WP II-I-1.4'!$L$79-ROUND(F79,0) -> -0.43066025 | X79: =U79-F79 -> 0
B80: =B79+1 -> 28 | X80: =U80-F80 -> 0
B81: =B80+1 -> 29 | D81: COST-BASED Rate of Return | F81: =F597 -> 0.0705 | J81: =J597 -> 0.0705 | K81: =K597 -> 0.0705 | L81: =L597 -> 0.0705 | M81: =M597 -> 0.0705 | N81: =N597 -> 0.0705 | O81: =O597 -> 0.0705 | P81: =P597 -> 0.0705 | Q81: =Q597 -> 0.0705 | ... S81: =S597 -> 0.0705 | U81: =U83/U79 -> 0.0705 | X81: =U81-F81 -> 0
B82: =B81+1 -> 30 | X82: =U82-F82 -> 0
B83: =B82+1 -> 31 | D83: COST-BASED Return On Rate Base | F83: =+F79*F81 -> 6.8300051e+08 | J83: =+J79*J81 -> 3.7983407e+08 | K83: =+K79*K81 -> 15300982 | L83: =+L79*L81 -> 2.3799621e+08 | M83: =+M79*M81 -> 245203.7 | N83: =+N79*N81 -> 38356623 | O83: =+O79*O81 -> 3620199.3 | P83: =+P79*P81 -> 1383463.3 | Q83: =+Q79*Q81 -> 3922745.9 | ... S83: =+S79*S81 -> 1908877.7 | U83: =SUM(I83:T83) -> 6.8300051e+08 | W83: =' WP II-I-1.4'!$L$83=F83 -> TRUE | X83: =U83-F83 -> 0
B84: =B83+1 -> 32 | X84: =U84-F84 -> 0
B85: =B84+1 -> 33 | D85: Proposed Adjustment to Return On Rate Base | F85: ='WP II-I-1.5'!D54 -> 0 | J85: ='WP II-I-1.5'!F54 -> 0 | K85: ='WP II-I-1.5'!G54 -> 0 | L85: ='WP II-I-1.5'!H54 -> 0 | M85: ='WP II-I-1.5'!I54 -> 0 | N85: ='WP II-I-1.5'!J54 -> 0 | O85: ='WP II-I-1.5'!K54 -> 0 | P85: ='WP II-I-1.5'!L54 -> 0 | Q85: ='WP II-I-1.5'!M54 -> 0 | ... S85: ='WP II-I-1.5'!O54 -> 0 | U85: =SUM(I85:T85) -> 0 | X85: =U85-F85 -> 0
B86: =B85+1 -> 34 | D86: (WP II-I-1.5) | X86: =U86-F86 -> 0
B87: =B86+1 -> 35 | D87: PROPOSED Return On Rate Base | F87: =F83+F85 -> 6.8300051e+08 | J87: =J83+J85 -> 3.7983407e+08 | K87: =K83+K85 -> 15300982 | L87: =L83+L85 -> 2.3799621e+08 | M87: =M83+M85 -> 245203.7 | N87: =N83+N85 -> 38356623 | O87: =O83+O85 -> 3620199.3 | P87: =P83+P85 -> 1383463.3 | Q87: =Q83+Q85 -> 3922745.9 | ... S87: =S83+S85 -> 1908877.7 | U87: =SUM(I87:T87) -> 6.8300051e+08 | X87: =U87-F87 -> 0
B88: =B87+1 -> 36 | X88: =U88-F88 -> 0
B89: =B88+1 -> 37 | D89: PROPOSED Rate Of Return | F89: =F87/F79 -> 0.0705 | J89: =J87/J79 -> 0.0705 | K89: =K87/K79 -> 0.0705 | L89: =L87/L79 -> 0.0705 | M89: =M87/M79 -> 0.0705 | N89: =N87/N79 -> 0.0705 | O89: =O87/O79 -> 0.0705 | P89: =P87/P79 -> 0.0705 | Q89: =Q87/Q79 -> 0.0705 | ... S89: =S87/S79 -> 0.0705 | U89: =U87/U79 -> 0.0705 | W89: =' WP II-I-1.4'!$L$81=F89 -> TRUE | X89: =U89-F89 -> 0
X90: =U90-F90 -> 0
B91: =+$B$4 -> 2022 RATE CASE
B92: =+$B$5 -> ONCOR ELECTRIC DELIVERY COMPANY LLC | X92: =U92-F92 -> 0
B93: =+$B$6 -> II-I-1-TOT: CLASS REVENUE REQUIREMENT | X93: =U93-F93 -> 0
B94: =+$B$7 -> TEST YEAR ENDING 12/31/2021 | X94: =U94-F94 -> 0
B95: =+$B$8 -> SPONSOR: MATTHEW A. TROXLE | X95: =U95-F95 -> 0
X96: =U96-F96 -> 0
R97: =R$10 | X97: =U97-F97 -> 0
B98: Line | C98: Acct | D98: Intangible and Transmission Plant Gross | E98: Source | F98: =F$11 -> TOTAL | G98: Alloc | H98: Allocation | J98: Residential | K98: Secondary | L98: Secondary | M98: Primary | N98: Primary | O98: Primary | P98: Transmission | Q98: Lighting | R98: =R$11 -> Wholesale | S98: =S$11 -> Wholesale | U98: Total
F99: =F$12 -> (Dist+Met+Cust) | G99: # | H99: Factor | K99: <=10 kW | L99: > 10 kW | M99: <=10 kW | N99: > 10 kW | O99: Substation | R99: =R$12 -> XFMR | S99: =S$12 -> DLS
F100: (a) | G100: (b) | H100: (c) | J100: =J$13 -> (d) | K100: =K$13 -> (e) | L100: =L$13 -> (f) | M100: =M$13 -> (g) | N100: =N$13 -> (h) | O100: =O$13 -> (i) | P100: =P$13 -> (j) | Q100: =Q$13 -> (k) | ... S100: =S$13 -> (m) | U100: (n)
X101: =U101-F101 -> 0
B102: =B101+1 -> 1 | C102: Intangible Plant Gross | E102: II-B-1 | X102: =U102-F102 -> 0
B103: =B102+1 -> 2 | C103: A301 | D103: Organization | F103: =' WP II-I-1.4'!L103 -> 0 | G103: N / A | H103: see functions | J103: ='II-I-DIST'!J103+'II-I-MET'!J103+'II-I-TBILLTDCS'!J103 -> 0 | K103: ='II-I-DIST'!K103+'II-I-MET'!K103+'II-I-TBILLTDCS'!K103 -> 0 | L103: ='II-I-DIST'!L103+'II-I-MET'!L103+'II-I-TBILLTDCS'!L103 -> 0 | M103: ='II-I-DIST'!M103+'II-I-MET'!M103+'II-I-TBILLTDCS'!M103 -> 0 | N103: ='II-I-DIST'!N103+'II-I-MET'!N103+'II-I-TBILLTDCS'!N103 -> 0 | O103: ='II-I-DIST'!O103+'II-I-MET'!O103+'II-I-TBILLTDCS'!O103 -> 0 | P103: ='II-I-DIST'!P103+'II-I-MET'!P103+'II-I-TBILLTDCS'!P103 -> 0 | Q103: ='II-I-DIST'!Q103+'II-I-MET'!Q103+'II-I-TBILLTDCS'!Q103 -> 0 | ... S103: ='II-I-DIST'!S103+'II-I-MET'!S103+'II-I-TBILLTDCS'!S103 -> 0 | U103: =SUM(I103:T103) -> 0 | X103: =U103-F103 -> 0
B104: =B103+1 -> 3 | C104: A302 | D104: Franchise & Consents | F104: =' WP II-I-1.4'!L104 -> 0 | G104: N / A | H104: see functions | J104: ='II-I-DIST'!J104+'II-I-MET'!J104+'II-I-TBILLTDCS'!J104 -> 0 | K104: ='II-I-DIST'!K104+'II-I-MET'!K104+'II-I-TBILLTDCS'!K104 -> 0 | L104: ='II-I-DIST'!L104+'II-I-MET'!L104+'II-I-TBILLTDCS'!L104 -> 0 | M104: ='II-I-DIST'!M104+'II-I-MET'!M104+'II-I-TBILLTDCS'!M104 -> 0 | N104: ='II-I-DIST'!N104+'II-I-MET'!N104+'II-I-TBILLTDCS'!N104 -> 0 | O104: ='II-I-DIST'!O104+'II-I-MET'!O104+'II-I-TBILLTDCS'!O104 -> 0 | P104: ='II-I-DIST'!P104+'II-I-MET'!P104+'II-I-TBILLTDCS'!P104 -> 0 | Q104: ='II-I-DIST'!Q104+'II-I-MET'!Q104+'II-I-TBILLTDCS'!Q104 -> 0 | ... S104: ='II-I-DIST'!S104+'II-I-MET'!S104+'II-I-TBILLTDCS'!S104 -> 0 | U104: =SUM(I104:T104) -> 0 | X104: =U104-F104 -> 0
B105: =B104+1 -> 4 | C105: A303 | D105: Miscellaneous Intangible Plant | F105: =' WP II-I-1.4'!L105 -> 8.1904426e+08 | G105: N / A | H105: see functions | J105: ='II-I-DIST'!J105+'II-I-MET'!J105+'II-I-TBILLTDCS'!J105 -> 4.5622203e+08 | K105: ='II-I-DIST'!K105+'II-I-MET'!K105+'II-I-TBILLTDCS'!K105 -> 48574010 | L105: ='II-I-DIST'!L105+'II-I-MET'!L105+'II-I-TBILLTDCS'!L105 -> 2.4519081e+08 | M105: ='II-I-DIST'!M105+'II-I-MET'!M105+'II-I-TBILLTDCS'!M105 -> 1885917.8 | N105: ='II-I-DIST'!N105+'II-I-MET'!N105+'II-I-TBILLTDCS'!N105 -> 55937888 | O105: ='II-I-DIST'!O105+'II-I-MET'!O105+'II-I-TBILLTDCS'!O105 -> 3044699.9 | P105: ='II-I-DIST'!P105+'II-I-MET'!P105+'II-I-TBILLTDCS'!P105 -> 3191084.5 | Q105: ='II-I-DIST'!Q105+'II-I-MET'!Q105+'II-I-TBILLTDCS'!Q105 -> 3337436.5 | ... S105: ='II-I-DIST'!S105+'II-I-MET'!S105+'II-I-TBILLTDCS'!S105 -> 1301346.1 | U105: =SUM(I105:T105) -> 8.1904426e+08 | X105: =U105-F105 -> 0
B106: =B105+1 -> 5 | D106: Subtotal | F106: =SUM(F103:F105) -> 8.1904426e+08 | J106: =SUM(J103:J105) -> 4.5622203e+08 | K106: =SUM(K103:K105) -> 48574010 | L106: =SUM(L103:L105) -> 2.4519081e+08 | M106: =SUM(M103:M105) -> 1885917.8 | N106: =SUM(N103:N105) -> 55937888 | O106: =SUM(O103:O105) -> 3044699.9 | P106: =SUM(P103:P105) -> 3191084.5 | Q106: =SUM(Q103:Q105) -> 3337436.5 | ... S106: =SUM(S103:S105) -> 1301346.1 | U106: =SUM(I106:T106) -> 8.1904426e+08 | W106: =' WP II-I-1.4'!$L$106=F106 -> TRUE | X106: =U106-F106 -> 0
...

Sheet II-I Summary
B3: ='WP II-I-1.1'!B3 -> 2022 RATE CASE
B4: ='WP II-I-1.1'!B4 -> ONCOR ELECTRIC DELIVERY COMPANY LLC
B5: ='WP II-I-1.1'!B5 -> II-I-1: CLASS REVENUE REQUIREMENT ANALYSIS
B6: ='WP II-I-1.1'!B6 -> TEST YEAR ENDING 12/31/2021
B7: ='WP II-I-1.1'!B7 -> SPONSOR: MATTHEW A. TROXLE
B10: II-I SUMMARY
B13: Line | C13: Description | D13: Total | F13: Residential | G13: Secondary | H13: Secondary | I13: Primary DL | J13: Primary DL | K13: Primary | L13: Transmission | M13: Lighting | N13: Wholesale | O13: Wholesale
D14: TX | G14: <=10kW | H14: >10kW | I14: <=10kW | J14: >10kW | K14: Substation | N14: Substation | O14: DLS
C15: (a) | D15: (b) | F15: (c) | G15: (d) | H15: (e) | I15: (f) | J15: (g) | K15: (h) | L15: (i) | M15: (j) | N15: (k) | O15: (l) | Q15: Checks | S15: Check2
B17: =B16+1 -> 1 | C17: O&M and A&G Expenses (less Acct 565 & RCE A928 ) | D17: =SUM(E17:P17) -> 8.9615276e+08 | F17: ='II-I-Total'!J764 -> 4.831534e+08 | G17: ='II-I-Total'!K764 -> 25581807 | H17: ='II-I-Total'!L764 -> 2.9307504e+08 | I17: ='II-I-Total'!M764 -> 708892.89 | J17: ='II-I-Total'!N764 -> 58455483 | K17: ='II-I-Total'!O764 -> 4509800.3 | L17: ='II-I-Total'!P764 -> 1382339.9 | M17: ='II-I-Total'!Q764 -> 26178262 | ... O17: ='II-I-Total'!S764 -> 2578906.1 | Q17: =IF(' WP II-I-1.4'!L764=D17,TRUE,' WP II-I-1.4'!L764-D17) -> 2.3841858e-07 | S17: =SUM(F17:O17)-D17 -> 0
B18: =B17+1 -> 2 | C18: Transmission of Electricity Costs (Acct 565) | D18: =SUM(E18:P18) -> 1.652522e+09 | F18: ='II-I-Total'!J622 -> 7.5818821e+08 | G18: ='II-I-Total'!K622 -> 21192617 | H18: ='II-I-Total'!L622 -> 5.5117546e+08 | I18: ='II-I-Total'!M622 -> 219196.04 | J18: ='II-I-Total'!N622 -> 1.3857054e+08 | K18: ='II-I-Total'!O622 -> 45384309 | L18: ='II-I-Total'!P622 -> 1.3779168e+08 | M18: ='II-I-Total'!Q622 -> 0 | ... O18: ='II-I-Total'!S622 -> 0 | Q18: =IF(('WP II-I-1.1'!G199+'WP II-I-1.1'!H199+'WP II-I-1.1'!I199)=D18,TRUE,('WP II-I-1.1'!G199+'WP II-I-1.1'!H199+'WP II-I-1.1'!I199)-D18) -> TRUE | S18: =SUM(F18:O18)-D18 -> 0
B19: =B18+1 -> 3 | C19: RateCaseExpense A928 | D19: =SUM(E19:P19) -> 1646625.8 | F19: ='II-I-DIST'!J753*0.727923 -> 824746.22 | G19: ='II-I-DIST'!K753*0.727923 -> 33960.679 | H19: ='II-I-DIST'!L753*0.727923 -> 560215.85 | I19: ='II-I-DIST'!M753*0.727923 -> 623.20619 | J19: ='II-I-DIST'!N753*0.727923 -> 114082.03 | K19: ='II-I-DIST'!O753*0.727923 -> 22961.48 | L19: ='II-I-DIST'!P753*0.727923 -> 63196.956 | M19: ='II-I-DIST'!Q753*0.727923 -> 23632.914 | ... O19: ='II-I-DIST'!S753*0.727923 -> 2601.5728
B20: =B19+1 -> 4 | C20: Total O&M and A&G Expenses | D20: =SUM(E20:P20) -> 2.5503214e+09 | F20: =SUM(F17:F19) -> 1.2421664e+09 | G20: =SUM(G17:G19) -> 46808385 | H20: =SUM(H17:H19) -> 8.4481072e+08 | I20: =SUM(I17:I19) -> 928712.13 | J20: =SUM(J17:J19) -> 1.971401e+08 | K20: =SUM(K17:K19) -> 49917071 | L20: =SUM(L17:L19) -> 1.3923722e+08 | M20: =SUM(M17:M19) -> 26201895 | ... O20: =SUM(O17:O19) -> 2581507.7 | Q20: ='II-I-Total'!$F$18-D20 -> 0 | S20: =SUM(F20:O20)-D20 -> 0
B21: =B20+1 -> 5 | C21: Depreciation, Amortization, & Other Expenses | D21: =SUM(E21:P21) -> 5.4634784e+08 | F21: ='II-I-Total'!J22 -> 2.9377371e+08 | G21: ='II-I-Total'!K22 -> 17898989 | H21: ='II-I-Total'!L22 -> 1.7524036e+08 | I21: ='II-I-Total'!M22 -> 385591.23 | J21: ='II-I-Total'!N22 -> 29457396 | K21: ='II-I-Total'!O22 -> 1951234.2 | L21: ='II-I-Total'!P22 -> 869060.79 | M21: ='II-I-Total'!Q22 -> 25252299 | ... O21: ='II-I-Total'!S22 -> 1286394.1 | Q21: =IF(' WP II-I-1.4'!L22=D21,TRUE,' WP II-I-1.4'!L22-D21) -> TRUE | S21: =SUM(F21:O21)-D21 -> 0
B22: =B21+1 -> 6 | C22: Taxes Other Than FIT | D22: =SUM(E22:P22) -> 4.604982e+08 | F22: ='II-I-Total'!J24 -> 2.10698e+08 | G22: ='II-I-Total'!K24 -> 8641668.9 | H22: ='II-I-Total'!L24 -> 1.7865294e+08 | I22: ='II-I-Total'!M24 -> 71539.685 | J22: ='II-I-Total'!N24 -> 28656332 | K22: ='II-I-Total'!O24 -> 3850802.2 | L22: ='II-I-Total'!P24 -> 22791529 | M22: ='II-I-Total'!Q24 -> 5993922.6 | ... O22: ='II-I-Total'!S24 -> 811399.08 | Q22: =IF(' WP II-I-1.4'!L24=D22,TRUE,' WP II-I-1.4'!L24-D22) -> TRUE | S22: =SUM(F22:O22)-D22 -> 0
B23: =B22+1 -> 7 | C23: Subtotal | D23: =SUM(E23:P23) -> 3.5571674e+09 | F23: =SUM(F20:F22) -> 1.7466381e+09 | G23: =SUM(G20:G22) -> 73349043 | H23: =SUM(H20:H22) -> 1.198704e+09 | I23: =SUM(I20:I22) -> 1385843 | J23: =SUM(J20:J22) -> 2.5525383e+08 | K23: =SUM(K20:K22) -> 55719107 | L23: =SUM(L20:L22) -> 1.6289781e+08 | M23: =SUM(M20:M22) -> 57448117 | ... O23: =SUM(O20:O22) -> 4679300.8 | S23: =SUM(F23:O23)-D23 -> 0
B24: =B23+1 -> 8 | C24: Cost-Based Return on Rate Base | D24: =SUM(E24:P24) -> 6.8300051e+08 | F24: ='II-I-Total'!J27 -> 3.7983407e+08 | G24: ='II-I-Total'!K27 -> 15300982 | H24: ='II-I-Total'!L27 -> 2.3799621e+08 | I24: ='II-I-Total'!M27 -> 245203.7 | J24: ='II-I-Total'!N27 -> 38356623 | K24: ='II-I-Total'!O27 -> 3620199.3 | L24: ='II-I-Total'!P27 -> 1383463.3 | M24: ='II-I-Total'!Q27 -> 3922745.9 | ... O24: ='II-I-Total'!S27 -> 1908877.7 | Q24: =IF(ROUND(' WP II-I-1.4'!L27-D24,2)=0,TRUE,' WP II-I-1.4'!L27-D24) -> TRUE | S24: =SUM(F24:O24)-D24 -> 0
B25: =B24+1 -> 9 | C25: Cost-Based Federal Income Tax | D25: =SUM(E25:P25) -> 82404686 | F25: ='II-I-Total'!J25 -> 45850278 | G25: ='II-I-Total'!K25 -> 1770897.1 | H25: ='II-I-Total'!L25 -> 28788315 | I25: ='II-I-Total'!M25 -> 25535.902 | J25: ='II-I-Total'!N25 -> 4606241.1 | K25: ='II-I-Total'!O25 -> 442044.23 | L25: ='II-I-Total'!P25 -> 162487.89 | M25: ='II-I-Total'!Q25 -> 473466.34 | ... O25: ='II-I-Total'!S25 -> 232790.75 | Q25: =IF(ROUND(' WP II-I-1.4'!L25-D25,0)=0,TRUE,' WP II-I-1.4'!L25-D25) -> TRUE | S25: =SUM(F25:O25)-D25 -> 0
B26: =B25+1 -> 10 | C26: COST OF SERVICE | D26: =SUM(E26:P26) -> 4.3225726e+09 | F26: =SUM(F23:F25) -> 2.1723224e+09 | G26: =SUM(G23:G25) -> 90420922 | H26: =SUM(H23:H25) -> 1.4654886e+09 | I26: =SUM(I23:I25) -> 1656582.6 | J26: =SUM(J23:J25) -> 2.982167e+08 | K26: =SUM(K23:K25) -> 59781351 | L26: =SUM(L23:L25) -> 1.6444376e+08 | M26: =SUM(M23:M25) -> 61844329 | ... O26: =SUM(O23:O25) -> 6820969.3 | Q26: =IF(ROUND(' WP II-I-1.4'!L1190-D26,0)=0,TRUE,' WP II-I-1.4'!L1190-D26) -> TRUE | S26: =SUM(F26:O26)-D26 -> 0
B27: =B26+1 -> 11 | S27: =SUM(F27:O27)-D27 -> 0
B28: =B27+1 -> 12 | C28: Minus: Other Revenues | D28: =SUM(E28:P28) -> 57057628 | F28: ='II-I-Total'!J31 -> 36873131 | G28: ='II-I-Total'!K31 -> 2417394.5 | H28: ='II-I-Total'!L31 -> 14530138 | I28: ='II-I-Total'!M31 -> 37722.118 | J28: ='II-I-Total'!N31 -> 2409772.5 | K28: ='II-I-Total'!O31 -> 131631.28 | L28: ='II-I-Total'!P31 -> 67300.002 | M28: ='II-I-Total'!Q31 -> 533688.9 | ... O28: ='II-I-Total'!S31 -> 53236.441 | Q28: =IF(' WP II-I-1.4'!L31=D28,TRUE,' WP II-I-1.4'!L31-D28) -> TRUE | S28: =SUM(F28:O28)-D28 -> 0
B29: =B28+1 -> 13 | S29: =SUM(F29:O29)-D29 -> 0
B30: =B29+1 -> 14 | C30: COST-BASED REVENUE REQUIREMENT | D30: =SUM(E30:P30) -> 4.265515e+09 | F30: =F26-F28 -> 2.1354493e+09 | G30: =G26-G28 -> 88003528 | H30: =H26-H28 -> 1.4509584e+09 | I30: =I26-I28 -> 1618860.5 | J30: =J26-J28 -> 2.9580692e+08 | K30: =K26-K28 -> 59649719 | L30: =L26-L28 -> 1.6437646e+08 | M30: =M26-M28 -> 61310640 | ... O30: =O26-O28 -> 6767732.8 | Q30: =IF('II-I-Total'!U1190=D30,TRUE,'II-I-Total'!U1190-D30) -> TRUE | S30: =SUM(F30:O30)-D30 -> 0
B31: =B30+1 -> 15 | S31: =SUM(F31:O31)-D31 -> 0
B32: =B31+1 -> 16 | C32: Proposed Adjustment to Return (WP/ II-I-1.5) | D32: =SUM(E32:P32) -> 0 | F32: ='II-I Summary'!F103 -> 0 | G32: ='II-I Summary'!G103 -> 0 | H32: ='II-I Summary'!H103 -> 0 | I32: ='II-I Summary'!I103 -> 0 | J32: ='II-I Summary'!J103 -> 0 | K32: ='II-I Summary'!K103 -> 0 | L32: ='II-I Summary'!L103 -> 0 | M32: ='II-I Summary'!M103 -> 0 | ... O32: ='II-I Summary'!O103 -> 0 | S32: =SUM(F32:O32)-D32 -> 0
B33: =B32+1 -> 17 | C33: Proposed Adj for Federal Income Tax (WP/ II-I-1.5) | D33: =SUM(E33:P33) -> 0 | F33: ='WP II-I-1.5'!F44 -> 0 | G33: ='WP II-I-1.5'!G44 -> 0 | H33: ='WP II-I-1.5'!H44 -> 0 | I33: ='WP II-I-1.5'!I44 -> 0 | J33: ='WP II-I-1.5'!J44 -> 0 | K33: ='WP II-I-1.5'!K44 -> 0 | L33: ='WP II-I-1.5'!L44 -> 0 | M33: ='WP II-I-1.5'!M44 -> 0 | ... O33: ='WP II-I-1.5'!O44 -> 0 | S33: =SUM(F33:O33)-D33 -> 0
B34: =B33+1 -> 18 | C34: Proposed Adj to Cost-Based Revenue | D34: =SUM(E34:P34) -> 0 | F34: =SUM(F32:F33) -> 0 | G34: =SUM(G32:G33) -> 0 | H34: =SUM(H32:H33) -> 0 | I34: =SUM(I32:I33) -> 0 | J34: =SUM(J32:J33) -> 0 | K34: =SUM(K32:K33) -> 0 | L34: =SUM(L32:L33) -> 0 | M34: =SUM(M32:M33) -> 0 | ... O34: =SUM(O32:O33) -> 0 | S34: =SUM(F34:O34)-D34 -> 0
B35: =B34+1 -> 19 | S35: =SUM(F35:O35)-D35 -> 0
B36: =B35+1 -> 20 | C36: PROPOSED REVENUE | D36: =SUM(E36:P36) -> 4.265515e+09 | F36: =F30+F34 -> 2.1354493e+09 | G36: =G30+G34 -> 88003528 | H36: =H30+H34 -> 1.4509584e+09 | I36: =I30+I34 -> 1618860.5 | J36: =J30+J34 -> 2.9580692e+08 | K36: =K30+K34 -> 59649719 | L36: =L30+L34 -> 1.6437646e+08 | M36: =M30+M34 -> 61310640 | ... O36: =O30+O34 -> 6767732.8 | Q36: ='WP II-I-1.1'!$G$477+'WP II-I-1.1'!$H$477+'WP II-I-1.1'!$I$477-D36-D34 -> 0 | S36: =SUM(F36:O36)-D36 -> 0
B37: =B36+1 -> 21 | S37: =SUM(F37:O37)-D37 -> 0
B38: =B37+1 -> 22 | C38: TOTAL PRESENT REVENUES (Incl PF) | D38: =SUM(E38:P38) -> 3.9959658e+09 | F38: ='II-I Summary'!F112 -> 1921088302 | G38: ='II-I Summary'!G112 -> 95557181 | H38: ='II-I Summary'!H112 -> 1.4962804e+09 | I38: ='II-I Summary'!I112 -> 1232285 | J38: ='II-I Summary'!J112 -> 2.724807e+08 | K38: ='II-I Summary'!K112 -> 31568643 | L38: ='II-I Summary'!L112 -> 1.1461514e+08 | M38: ='II-I Summary'!M112 -> 60374542 | ... O38: ='II-I Summary'!O112 -> 2160192 | S38: =SUM(F38:O38)-D38 -> 0
B39: =B38+1 -> 23 | S39: =SUM(F39:O39)-D39 -> 0
B40: =B39+1 -> 24 | C40: COST-BASED REVENUE REQUIREMENT | D40: =SUM(E40:P40) -> 4.265515e+09 | F40: =F30 -> 2.1354493e+09 | G40: =G30 -> 88003528 | H40: =H30 -> 1.4509584e+09 | I40: =I30 -> 1618860.5 | J40: =J30 -> 2.9580692e+08 | K40: =K30 -> 59649719 | L40: =L30 -> 1.6437646e+08 | M40: =M30 -> 61310640 | ... O40: =O30 -> 6767732.8 | S40: =SUM(F40:O40)-D40 -> 0
B41: =B40+1 -> 25 | C41: Shortfall / (Surplus) vs Cost-Based Revenues | D41: =SUM(E41:P41) -> 2.6954926e+08 | F41: =F40-F38 -> 2.1436098e+08 | G41: =G40-G38 -> -7553653.5 | H41: =H40-H38 -> -45322005 | I41: =I40-I38 -> 386575.53 | J41: =J40-J38 -> 23326226 | K41: =K40-K38 -> 28081077 | L41: =L40-L38 -> 49761323 | M41: =M40-M38 -> 936098.17 | ... O41: =O40-O38 -> 4607540.8 | S41: =SUM(F41:O41)-D41 -> 0
B42: =B41+1 -> 26 | C42: Change from Present Revenues | D42: =D41/D38 -> 0.067455348 | F42: =F41/F38 -> 0.1115831 | G42: =G41/G38 -> -0.079048517 | H42: =H41/H38 -> -0.030289781 | I42: =I41/I38 -> 0.31370627 | J42: =J41/J38 -> 0.085606895 | K42: =K41/K38 -> 0.88952435 | L42: =L41/L38 -> 0.43416013 | M42: =M41/M38 -> 0.015504849 | ... O42: =O41/O38 -> 2.1329312 | S42: =SUM(F42:O42)-D42 -> 5.392627
B43: =B42+1 -> 27 | S43: =SUM(F43:O43)-D43 -> 0
B44: =B43+1 -> 28 | C44: PROPOSED REVENUE | D44: =SUM(E44:P44) -> 4.265515e+09 | F44: =F36 -> 2.1354493e+09 | G44: =G36 -> 88003528 | H44: =H36 -> 1.4509584e+09 | I44: =I36 -> 1618860.5 | J44: =J36 -> 2.9580692e+08 | K44: =K36 -> 59649719 | L44: =L36 -> 1.6437646e+08 | M44: =M36 -> 61310640 | ... O44: =O36 -> 6767732.8 | S44: =SUM(F44:O44)-D44 -> 0
B45: =B44+1 -> 29 | C45: Shortfall / (Surplus) vs Proposed Revenue | D45: =SUM(E45:P45) -> 2.6954926e+08 | F45: =F44-F38 -> 2.1436098e+08 | G45: =G44-G38 -> -7553653.5 | H45: =H44-H38 -> -45322005 | I45: =I44-I38 -> 386575.53 | J45: =J44-J38 -> 23326226 | K45: =K44-K38 -> 28081077 | L45: =L44-L38 -> 49761323 | M45: =M44-M38 -> 936098.17 | ... O45: =O44-O38 -> 4607540.8 | S45: =SUM(F45:O45)-D45 -> 0
B46: =B45+1 -> 30 | C46: Change from Present Revenues | D46: =D45/D38 -> 0.067455348 | F46: =F45/F38 -> 0.1115831 | G46: =G45/G38 -> -0.079048517 | H46: =H45/H38 -> -0.030289781 | I46: =I45/I38 -> 0.31370627 | J46: =J45/J38 -> 0.085606895 | K46: =K45/K38 -> 0.88952435 | L46: =L45/L38 -> 0.43416013 | M46: =M45/M38 -> 0.015504849 | ... O46: =O45/O38 -> 2.1329312 | S46: =SUM(F46:O46)-D46 -> 5.392627
B47: =B46+1 -> 31 | S47: =SUM(F47:O47)-D47 -> 0
B48: =B47+1 -> 32 | C48: Rate Base | D48: =SUM(E48:P48) -> 9.6879505e+09 | F48: ='II-I-Total'!J595 -> 5.3877173e+09 | G48: ='II-I-Total'!K595 -> 2.1703521e+08 | H48: ='II-I-Total'!L595 -> 3.3758328e+09 | I48: ='II-I-Total'!M595 -> 3478066.6 | J48: ='II-I-Total'!N595 -> 5.4406557e+08 | K48: ='II-I-Total'!O595 -> 51350344 | L48: ='II-I-Total'!P595 -> 19623592 | M48: ='II-I-Total'!Q595 -> 55641786 | ... O48: ='II-I-Total'!S595 -> 27076279 | Q48: =IF(('WP II-I-1.1'!G459+'WP II-I-1.1'!H459+'WP II-I-1.1'!I459)=D48,TRUE,('WP II-I-1.1'!G459+'WP II-I-1.1'!H459+'WP II-I-1.1'!I459)-D48) -> TRUE | S48: =SUM(F48:O48)-D48 -> 0
B49: =B48+1 -> 33 | S49: =SUM(F49:O49)-D49 -> 0
B50: =B49+1 -> 34 | C50: Return at Present Rates | D50: =SUM(E50:P50) -> 4.6223917e+08 | F50: ='II-I Summary'!F135 -> 1.9913879e+08 | G50: ='II-I Summary'!G135 -> 27361090 | H50: ='II-I Summary'!H135 -> 2.7151511e+08 | I50: ='II-I Summary'!I135 -> -56398.22 | J50: ='II-I Summary'!J135 -> 19463852 | K50: ='II-I Summary'!K135 -> -18593427 | L50: ='II-I Summary'!L135 -> -37890640 | M50: ='II-I Summary'!M135 -> 3386603.3 | ... O50: ='II-I Summary'!O135 -> -1756464.7 | S50: =SUM(F50:O50)-D50 -> 0
B51: =B50+1 -> 35 | C51: Present Rate of Return | D51: =D50/D48 -> 0.047712793 | F51: =F50/F48 -> 0.036961626 | G51: =G50/G48 -> 0.12606752 | H51: =H50/H48 -> 0.080429076 | I51: =I50/I48 -> -0.016215394 | J51: =J50/J48 -> 0.035774828 | K51: =K50/K48 -> -0.36208963 | L51: =L50/L48 -> -1.9308717 | M51: =M50/M48 -> 0.060864389 | ... O51: =O50/O48 -> -0.064870979 | S51: =SUM(F51:O51)-D51 -> -2.1353935
B52: =B51+1 -> 36 | C52: Present Relative Rate of Return | D52: =D51/$D$51 -> 1 | F52: =F51/$D$51 -> 0.77466911 | G52: =G51/$D$51 -> 2.6422163 | H52: =H51/$D$51 -> 1.6856921 | I52: =I51/$D$51 -> -0.33985422 | J52: =J51/$D$51 -> 0.74979532 | K52: =K51/$D$51 -> -7.5889423 | L52: =L51/$D$51 -> -40.468638 | M52: =M51/$D$51 -> 1.2756409 | ... O52: =O51/$D$51 -> -1.359614 | S52: =SUM(F52:O52)-D52 -> -44.755157
B53: =B52+1 -> 37 | S53: =SUM(F53:O53)-D53 -> 0
B54: =B53+1 -> 38 | C54: Cost-Based Return on Rate Base | D54: =SUM(E54:P54) -> 6.8300051e+08 | F54: =F24 -> 3.7983407e+08 | G54: =G24 -> 15300982 | H54: =H24 -> 2.3799621e+08 | I54: =I24 -> 245203.7 | J54: =J24 -> 38356623 | K54: =K24 -> 3620199.3 | L54: =L24 -> 1383463.3 | M54: =M24 -> 3922745.9 | ... O54: =O24 -> 1908877.7 | Q54: =IF(D$24=D54,TRUE,D$24-D54) -> TRUE | S54: =SUM(F54:O54)-D54 -> 0
B55: =B54+1 -> 39 | C55: Cost-Based Rate of Return | D55: =D24/D48 -> 0.0705 | F55: =F24/F48 -> 0.0705 | G55: =G24/G48 -> 0.0705 | H55: =H24/H48 -> 0.0705 | I55: =I24/I48 -> 0.0705 | J55: =J24/J48 -> 0.0705 | K55: =K24/K48 -> 0.0705 | L55: =L24/L48 -> 0.0705 | M55: =M24/M48 -> 0.0705 | ... O55: =O24/O48 -> 0.0705 | S55: =SUM(F55:O55)-D55 -> 0.6345
B56: =B55+1 -> 40 | C56: Cost-Based Relative Rate of Return | D56: =D55/$D$55 -> 1 | F56: =F55/$D$55 -> 1 | G56: =G55/$D$55 -> 1 | H56: =H55/$D$55 -> 1 | I56: =I55/$D$55 -> 1 | J56: =J55/$D$55 -> 1 | K56: =K55/$D$55 -> 1 | L56: =L55/$D$55 -> 1 | M56: =M55/$D$55 -> 1 | ... O56: =O55/$D$55 -> 1 | S56: =SUM(F56:O56)-D56 -> 9
B57: =B56+1 -> 41 | S57: =SUM(F57:O57)-D57 -> 0
B58: =B57+1 -> 42 | C58: Proposed Return on Rate Base | D58: =SUM(E58:P58) -> 6.8300051e+08 | F58: =F24+F32 -> 3.7983407e+08 | G58: =G24+G32 -> 15300982 | H58: =H24+H32 -> 2.3799621e+08 | I58: =I24+I32 -> 245203.7 | J58: =J24+J32 -> 38356623 | K58: =K24+K32 -> 3620199.3 | L58: =L24+L32 -> 1383463.3 | M58: =M24+M32 -> 3922745.9 | ... O58: =O24+O32 -> 1908877.7 | Q58: =IF(D$24=D58,TRUE,D$24-D58) -> TRUE | S58: =SUM(F58:O58)-D58 -> 0
B59: =B58+1 -> 43 | C59: Proposed Rate of Return | D59: =D58/D48 -> 0.0705 | F59: =F58/F48 -> 0.0705 | G59: =G58/G48 -> 0.0705 | H59: =H58/H48 -> 0.0705 | I59: =I58/I48 -> 0.0705 | J59: =J58/J48 -> 0.0705 | K59: =K58/K48 -> 0.0705 | L59: =L58/L48 -> 0.0705 | M59: =M58/M48 -> 0.0705 | ... O59: =O58/O48 -> 0.0705 | S59: =SUM(F59:O59)-D59 -> 0.6345
B60: =B59+1 -> 44 | C60: Proposed Relative Rate of Return | D60: =D59/$D$59 -> 1 | F60: =F59/$D$59 -> 1 | G60: =G59/$D$59 -> 1 | H60: =H59/$D$59 -> 1 | I60: =I59/$D$59 -> 1 | J60: =J59/$D$59 -> 1 | K60: =K59/$D$59 -> 1 | L60: =L59/$D$59 -> 1 | M60: =M59/$D$59 -> 1 | ... O60: =O59/$D$59 -> 1 | S60: =SUM(F60:O60)-D60 -> 9
B61: =B60+1 -> 45 | C61: Differential vs Cost-Based | D61: =SUM(E61:P61) -> 0 | F61: =F58-F54 -> 0 | G61: =G58-G54 -> 0 | H61: =H58-H54 -> 0 | I61: =I58-I54 -> 0 | J61: =J58-J54 -> 0 | K61: =K58-K54 -> 0 | L61: =L58-L54 -> 0 | M61: =M58-M54 -> 0 | ... O61: =O58-O54 -> 0 | S61: =SUM(F61:O61)-D61 -> 0
S62: =SUM(F62:O62)-D62 -> 0
B63: =B62+1 -> 1 | C63: RATE BASE | S63: =SUM(F63:O63)-D63 -> 0
B64: =B63+1 -> 2 | S64: =SUM(F64:O64)-D64 -> 0
B65: =B64+1 -> 3 | C65: Intangible, Transmission, Distribution Plant: Orig Cost | D65: =SUM(E65:P65) -> 1.6393872e+10 | F65: ='II-I-Total'!J56 -> 8.9397019e+09 | G65: ='II-I-Total'!K56 -> 4.3085602e+08 | H65: ='II-I-Total'!L56 -> 5.480312e+09 | I65: ='II-I-Total'!M56 -> 5778301.3 | J65: ='II-I-Total'!N56 -> 8.4333341e+08 | K65: ='II-I-Total'!O56 -> 72295118 | L65: ='II-I-Total'!P56 -> 19946854 | M65: ='II-I-Total'!Q56 -> 5.5096335e+08 | ... O65: ='II-I-Total'!S56 -> 42032925 | Q65: =IF(' WP II-I-1.4'!L56=D65,TRUE,' WP II-I-1.4'!L56-D65) -> TRUE | S65: =SUM(F65:O65)-D65 -> 0
B66: =B65+1 -> 4 | C66: General Plant: Original Cost | D66: =SUM(E66:P66) -> 5.3495937e+08 | F66: ='II-I-Total'!J58 -> 2.9790873e+08 | G66: ='II-I-Total'!K58 -> 23708559 | H66: ='II-I-Total'!L58 -> 1.7049762e+08 | I66: ='II-I-Total'!M58 -> 804374.91 | J66: ='II-I-Total'!N58 -> 33717706 | K66: ='II-I-Total'!O58 -> 2309195.5 | L66: ='II-I-Total'!P58 -> 1517679.5 | M66: ='II-I-Total'!Q58 -> 3107884.4 | ... O66: ='II-I-Total'!S58 -> 1113281.1 | Q66: =IF(' WP II-I-1.4'!L58=D66,TRUE,' WP II-I-1.4'!L58-D66) -> TRUE | S66: =SUM(F66:O66)-D66 -> 0
B67: =B66+1 -> 5 | C67: Communication Equipment: Original Cost | D67: =SUM(E67:P67) -> 1.0858171e+08 | F67: ='II-I-Total'!J59 -> 60478625 | G67: ='II-I-Total'!K59 -> 5195568.3 | H67: ='II-I-Total'!L59 -> 34116670 | I67: ='II-I-Total'!M59 -> 183691.81 | J67: ='II-I-Total'!N59 -> 6979195 | K67: ='II-I-Total'!O59 -> 453461.27 | L67: ='II-I-Total'!P59 -> 335135.58 | M67: ='II-I-Total'!Q59 -> 572147.61 | ... O67: ='II-I-Total'!S59 -> 213424.67 | Q67: =IF(' WP II-I-1.4'!L59=D67,TRUE,' WP II-I-1.4'!L59-D67) -> TRUE | S67: =SUM(F67:O67)-D67 -> 0
B68: =B67+1 -> 6 | C68: Total Plant | D68: =SUM(E68:P68) -> 1.7037413e+10 | F68: =SUM(F65:F67) -> 9.2980892e+09 | G68: =SUM(G65:G67) -> 4.5976014e+08 | H68: =SUM(H65:H67) -> 5.6849262e+09 | I68: =SUM(I65:I67) -> 6766368 | J68: =SUM(J65:J67) -> 8.8403031e+08 | K68: =SUM(K65:K67) -> 75057775 | L68: =SUM(L65:L67) -> 21799669 | M68: =SUM(M65:M67) -> 5.5464338e+08 | ... O68: =SUM(O65:O67) -> 43359630 | S68: =SUM(F68:O68)-D68 -> 0
B69: =B68+1 -> 7 | S69: =SUM(F69:O69)-D69 -> 0
B70: =B69+1 -> 8 | C70: Minus: Accumulated Depreciation | D70: =SUM(E70:P70) -> 6.5713783e+09 | F70: ='II-I-Total'!J62 -> 3.4722576e+09 | G70: ='II-I-Total'!K62 -> 2.242818e+08 | H70: ='II-I-Total'!L62 -> 2.0547465e+09 | I70: ='II-I-Total'!M62 -> 3202534 | J70: ='II-I-Total'!N62 -> 3.0467573e+08 | K70: ='II-I-Total'!O62 -> 20754987 | L70: ='II-I-Total'!P62 -> 8244831.2 | M70: ='II-I-Total'!Q62 -> 4.6665272e+08 | ... O70: ='II-I-Total'!S62 -> 14082341 | Q70: =IF(' WP II-I-1.4'!L62=D70,TRUE,' WP II-I-1.4'!L62-D70) -> TRUE | S70: =SUM(F70:O70)-D70 -> 0
B71: =B70+1 -> 9 | S71: =SUM(F71:O71)-D71 -> 0
B72: =B71+1 -> 10 | C72: Net Plant In Service | D72: =SUM(E72:P72) -> 1.0466035e+10 | F72: =+F68-F70 -> 5.8258316e+09 | G72: =+G68-G70 -> 2.3547835e+08 | H72: =+H68-H70 -> 3.6301797e+09 | I72: =+I68-I70 -> 3563834 | J72: =+J68-J70 -> 5.7935458e+08 | K72: =+K68-K70 -> 54302788 | L72: =+L68-L70 -> 13554838 | M72: =+M68-M70 -> 87990668 | ... O72: =+O68-O70 -> 29277289 | S72: =SUM(F72:O72)-D72 -> 0
B73: =B72+1 -> 11 | S73: =SUM(F73:O73)-D73 -> 0
B74: =B73+1 -> 12 | C74: Other Rate Base Items: | S74: =SUM(F74:O74)-D74 -> 0
B75: =B74+1 -> 13 | C75: CWIP | D75: =SUM(E75:P75) -> 0 | F75: ='II-I-Total'!J68 -> 0 | G75: ='II-I-Total'!K68 -> 0 | H75: ='II-I-Total'!L68 -> 0 | I75: ='II-I-Total'!M68 -> 0 | J75: ='II-I-Total'!N68 -> 0 | K75: ='II-I-Total'!O68 -> 0 | L75: ='II-I-Total'!P68 -> 0 | M75: ='II-I-Total'!Q68 -> 0 | ... O75: ='II-I-Total'!S68 -> 0 | Q75: =IF(' WP II-I-1.4'!L68=D75,TRUE,' WP II-I-1.4'!L68-D75) -> TRUE | S75: =SUM(F75:O75)-D75 -> 0
B76: =B75+1 -> 14 | C76: Plant Held for Future Use | D76: =SUM(E76:P76) -> 1745979.3 | F76: ='II-I-Total'!J69 -> 918949.06 | G76: ='II-I-Total'!K69 -> 22440.934 | H76: ='II-I-Total'!L69 -> 591685.88 | I76: ='II-I-Total'!M69 -> 334.50441 | J76: ='II-I-Total'!N69 -> 141579.11 | K76: ='II-I-Total'!O69 -> 51199.923 | L76: ='II-I-Total'!P69 -> 0 | M76: ='II-I-Total'!Q69 -> 5968.0008 | ... O76: ='II-I-Total'!S69 -> 7685.3067 | Q76: =IF(' WP II-I-1.4'!L69=D76,TRUE,' WP II-I-1.4'!L69-D76) -> TRUE | S76: =SUM(F76:O76)-D76 -> 0
B77: =B76+1 -> 15 | C77: Accumulated Provisions ex ADFIT | D77: =SUM(E77:P77) -> 0 | F77: ='II-I-Total'!J70 -> 0 | G77: ='II-I-Total'!K70 -> 0 | H77: ='II-I-Total'!L70 -> 0 | I77: ='II-I-Total'!M70 -> 0 | J77: ='II-I-Total'!N70 -> 0 | K77: ='II-I-Total'!O70 -> 0 | L77: ='II-I-Total'!P70 -> 0 | M77: ='II-I-Total'!Q70 -> 0 | ... O77: ='II-I-Total'!S70 -> 0 | Q77: =IF(' WP II-I-1.4'!L70=D77,TRUE,' WP II-I-1.4'!L70-D77) -> TRUE | S77: =SUM(F77:O77)-D77 -> 0
B78: =B77+1 -> 16 | C78: Materials & Supplies | D78: =SUM(E78:P78) -> 74796188 | F78: ='II-I-Total'!J71 -> 40747702 | G78: ='II-I-Total'!K71 -> 1654265.4 | H78: ='II-I-Total'!L71 -> 25381209 | I78: ='II-I-Total'!M71 -> 9167.6393 | J78: ='II-I-Total'!N71 -> 3721746 | K78: ='II-I-Total'!O71 -> 340329.76 | L78: ='II-I-Total'!P71 -> 67916.737 | M78: ='II-I-Total'!Q71 -> 2631405.9 | ... O78: ='II-I-Total'!S71 -> 201656.29 | Q78: =IF(' WP II-I-1.4'!L71=D78,TRUE,' WP II-I-1.4'!L71-D78) -> 4.4703484e-08 | S78: =SUM(F78:O78)-D78 -> 0
B79: =B78+1 -> 17 | C79: Cash Working Capital | D79: =SUM(E79:P79) -> -16280094 | F79: ='II-I-Total'!J72 -> -7625839.1 | G79: ='II-I-Total'!K72 -> -184146.95 | H79: ='II-I-Total'!L72 -> -5475610.1 | I79: ='II-I-Total'!M72 -> -1015.3782 | J79: ='II-I-Total'!N72 -> -1327565.4 | K79: ='II-I-Total'!O72 -> -399194.9 | L79: ='II-I-Total'!P72 -> -1166777.3 | M79: ='II-I-Total'!Q72 -> -88778.188 | ... O79: ='II-I-Total'!S72 -> -9464.4007 | Q79: =IF(' WP II-I-1.4'!L72=D79,TRUE,' WP II-I-1.4'!L72-D79) -> TRUE | S79: =SUM(F79:O79)-D79 -> 0
B80: =B79+1 -> 18 | C80: Prepayments | D80: =SUM(E80:P80) -> 1.0457667e+08 | F80: ='II-I-Total'!J73 -> 41996472 | G80: ='II-I-Total'!K73 -> 1500195.2 | H80: ='II-I-Total'!L73 -> 43969879 | I80: ='II-I-Total'!M73 -> 758.93271 | J80: ='II-I-Total'!N73 -> 7070030 | K80: ='II-I-Total'!O73 -> 1112421.7 | L80: ='II-I-Total'!P73 -> 8332812.1 | M80: ='II-I-Total'!Q73 -> 382811.32 | ... O80: ='II-I-Total'!S73 -> 126412.32 | Q80: =IF(' WP II-I-1.4'!L73=D80,TRUE,' WP II-I-1.4'!L73-D80) -> TRUE | S80: =SUM(F80:O80)-D80 -> 0
B81: =B80+1 -> 19 | C81: Misc Other Rate Base | D81: =SUM(E81:P81) -> -3096684.4 | F81: ='II-I-Total'!J74 -> -1486339.9 | G81: ='II-I-Total'!K74 -> -36296.74 | H81: ='II-I-Total'!L74 -> -957013.13 | I81: ='II-I-Total'!M74 -> -541.03897 | J81: ='II-I-Total'!N74 -> -228994.93 | K81: ='II-I-Total'!O74 -> -82812.519 | L81: ='II-I-Total'!P74 -> -272677.28 | M81: ='II-I-Total'!Q74 -> -9652.8502 | ... O81: ='II-I-Total'!S74 -> -12430.48 | Q81: =IF(' WP II-I-1.4'!L74=D81,TRUE,' WP II-I-1.4'!L74-D81) -> TRUE | S81: =SUM(F81:O81)-D81 -> 0
B82: =B81+1 -> 20 | C82: Regulatory Assets | D82: =SUM(E82:P82) -> 3.146995e+08 | F82: ='II-I-Total'!J75 -> 1.7228768e+08 | G82: ='II-I-Total'!K75 -> 14057648 | H82: ='II-I-Total'!L75 -> 98867929 | I82: ='II-I-Total'!M75 -> 494228.68 | J82: ='II-I-Total'!N75 -> 21128604 | K82: ='II-I-Total'!O75 -> 1504600.5 | L82: ='II-I-Total'!P75 -> 835047.18 | M82: ='II-I-Total'!Q75 -> 4732280 | ... O82: ='II-I-Total'!S75 -> 627988.19 | Q82: =IF(' WP II-I-1.4'!L75=D82,TRUE,' WP II-I-1.4'!L75-D82) -> TRUE | S82: =SUM(F82:O82)-D82 -> 0
B83: =B82+1 -> 21 | C83: Acuumulated Deferred Income Taxes | D83: =SUM(E83:P83) -> -1.254526e+09 | F83: ='II-I-Total'!J76 -> -6.8495297e+08 | G83: ='II-I-Total'!K76 -> -35457244 | H83: ='II-I-Total'!L76 -> -4.1672507e+08 | I83: ='II-I-Total'!M76 -> -588700.74 | J83: ='II-I-Total'!N76 -> -65794409 | K83: ='II-I-Total'!O76 -> -5478988 | L83: ='II-I-Total'!P76 -> -1727566.6 | M83: ='II-I-Total'!Q76 -> -40002916 | ... O83: ='II-I-Total'!S76 -> -3142856.9 | Q83: =IF(ROUND(' WP II-I-1.4'!L76-D83,2)=0,TRUE,' WP II-I-1.4'!L76-D83) -> TRUE | S83: =SUM(F83:O83)-D83 -> 0
B84: =B83+1 -> 22 | S84: =SUM(F84:O84)-D84 -> 0
B85: =B84+1 -> 23 | C85: Subtotal | D85: =SUM(E85:P85) -> -7.780844e+08 | F85: =SUM(F74:F83) -> -4.3811435e+08 | G85: =SUM(G74:G83) -> -18443138 | H85: =SUM(H74:H83) -> -2.5434699e+08 | I85: =SUM(I74:I83) -> -85767.405 | J85: =SUM(J74:J83) -> -35289011 | K85: =SUM(K74:K83) -> -2952443.5 | L85: =SUM(L74:L83) -> 6068754.8 | M85: =SUM(M74:M83) -> -32348882 | ... O85: =SUM(O74:O83) -> -2201009.6 | S85: =SUM(F85:O85)-D85 -> 0
B86: =B85+1 -> 24 | S86: =SUM(F86:O86)-D86 -> 0
B87: =B86+1 -> 25 | C87: TOTAL RATE BASE | D87: =SUM(E87:P87) -> 9.6879505e+09 | F87: =+F72+F85 -> 5.3877173e+09 | G87: =+G72+G85 -> 2.1703521e+08 | H87: =+H72+H85 -> 3.3758328e+09 | I87: =+I72+I85 -> 3478066.6 | J87: =+J72+J85 -> 5.4406557e+08 | K87: =+K72+K85 -> 51350344 | L87: =+L72+L85 -> 19623592 | M87: =+M72+M85 -> 55641786 | ... O87: =+O72+O85 -> 27076279 | Q87: =D48=D87 -> TRUE | S87: =SUM(F87:O87)-D87 -> 0
B88: =B87+1 -> 26 | S88: =SUM(F88:O88)-D88 -> 0
B89: =B88+1 -> 27 | S89: =SUM(F89:O89)-D89 -> 0
B90: =B89+1 -> 28 | C90: COST-BASED | S90: =SUM(F90:O90)-D90 -> 0
B91: =B90+1 -> 29 | S91: =SUM(F91:O91)-D91 -> 0
B92: =B91+1 -> 30 | C92: Cost-Based Rate of Return | D92: =' WP II-I-1.4'!L597 -> 0.0705 | F92: =$D$92 -> 0.0705 | G92: =$D$92 -> 0.0705 | H92: =$D$92 -> 0.0705 | I92: =$D$92 -> 0.0705 | J92: =$D$92 -> 0.0705 | K92: =$D$92 -> 0.0705 | L92: =$D$92 -> 0.0705 | M92: =$D$92 -> 0.0705 | ... O92: =$D$92 -> 0.0705 | S92: =SUM(F92:O92)-D92 -> 0.6345
B93: =B92+1 -> 31 | S93: =SUM(F93:O93)-D93 -> 0
B94: =B93+1 -> 32 | C94: Cost-Based Return on Rate Base | D94: =SUM(E94:P94) -> 6.8300051e+08 | F94: =F87*F92 -> 3.7983407e+08 | G94: =G87*G92 -> 15300982 | H94: =H87*H92 -> 2.3799621e+08 | I94: =I87*I92 -> 245203.7 | J94: =J87*J92 -> 38356623 | K94: =K87*K92 -> 3620199.3 | L94: =L87*L92 -> 1383463.3 | M94: =M87*M92 -> 3922745.9 | ... O94: =O87*O92 -> 1908877.7 | Q94: =IF(ROUND('II-I-Total'!U599-D94,2)=0,TRUE,'II-I-Total'!U599-D94) -> TRUE | S94: =SUM(F94:O94)-D94 -> 0
B95: =B94+1 -> 33 | S95: =SUM(F95:O95)-D95 -> 0
B96: =B95+1 -> 34 | S96: =SUM(F96:O96)-D96 -> 0
B97: =B96+1 -> 35 | C97: PROPOSED | S97: =SUM(F97:O97)-D97 -> 0
B98: =B97+1 -> 36 | S98: =SUM(F98:O98)-D98 -> 0
B99: =B98+1 -> 37 | C99: Proposed Rate of Return | D99: =D101/D87 -> 0.0705 | F99: =F101/F87 -> 0.0705 | G99: =G101/G87 -> 0.0705 | H99: =H101/H87 -> 0.0705 | I99: =I101/I87 -> 0.0705 | J99: =J101/J87 -> 0.0705 | K99: =K101/K87 -> 0.0705 | L99: =L101/L87 -> 0.0705 | M99: =M101/M87 -> 0.0705 | ... O99: =O101/O87 -> 0.0705 | S99: =SUM(F99:O99)-D99 -> 0.6345
B100: =B99+1 -> 38 | S100: =SUM(F100:O100)-D100 -> 0
B101: =B100+1 -> 39 | C101: Proposed Return on Rate Base | D101: =SUM(E101:P101) -> 6.8300051e+08 | F101: ='WP II-I-1.5'!F51 -> 3.7983407e+08 | G101: ='WP II-I-1.5'!G51 -> 15300982 | H101: ='WP II-I-1.5'!H51 -> 2.3799621e+08 | I101: ='WP II-I-1.5'!I51 -> 245203.7 | J101: ='WP II-I-1.5'!J51 -> 38356623 | K101: ='WP II-I-1.5'!K51 -> 3620199.3 | L101: ='WP II-I-1.5'!L51 -> 1383463.3 | M101: ='WP II-I-1.5'!M51 -> 3922745.9 | ... O101: ='WP II-I-1.5'!O51 -> 1908877.7 | Q101: =IF(ROUND(' WP II-I-1.4'!L599-D101,2)=0,TRUE,' WP II-I-1.4'!L599-D101) -> TRUE | S101: =SUM(F101:O101)-D101 -> 0
B102: =B101+1 -> 40 | C102: (WP/ II-I-1.5) | S102: =SUM(F102:O102)-D102 -> 0
B103: =B102+1 -> 41 | C103: Differential vs Cost-Based | D103: =SUM(E103:P103) -> 0 | F103: =F101-F94 -> 0 | G103: =G101-G94 -> 0 | H103: =H101-H94 -> 0 | I103: =I101-I94 -> 0 | J103: =J101-J94 -> 0 | K103: =K101-K94 -> 0 | L103: =L101-L94 -> 0 | M103: =M101-M94 -> 0 | ... O103: =O101-O94 -> 0 | S103: =SUM(F103:O103)-D103 -> 0
S104: =SUM(F104:O104)-D104 -> 0
B105: 1 | C105: PRESENT REVENUE | S105: =SUM(F105:O105)-D105 -> 0
B106: =B105+1 -> 2 | S106: =SUM(F106:O106)-D106 -> 0
B107: =B106+1 -> 3 | Q107: =IF('WP II-I-2.2'!P72=D107,TRUE,'WP II-I-2.2'!P72-D107) -> TRUE | S107: =SUM(F107:O107)-D107 -> 0
...

Sheet WP II-I-1.9 
B1: 2022 RATE CASE
B2: ONCOR ELECTRIC DELIVERY COMPANY LLC
B3: II-I-1: CLASS REVENUE REQUIREMENT ANALYSIS
B4: TEST YEAR ENDING 12/31/2021
B5: SPONSOR: MATTHEW A. TROXLE
B7: WORKPAPER 1.9 -DCRF BASELINE
D9: (1) | F9: (2) | H9: (3) = (1) * (2) | J9: (4) | L9: (5) | N9: (6) | P9: (7) = (3)+(4)+(5)+(6) | R9: (8) = Sch H col (9) | T9: (9) = (7)*(8) | V9: (10) | X9: (11)=(10)/∑(10)
A10: Line | B10: Rate Class | D10: DICRC | F10: RORAT | H10: Return | J10: DEPRRC-CLASS | L10: FITRC-CLASS | N10: OTRC-CLASS | P10: DISTREVRC-CLASS | R10: % GROWTHCLASS | T10: DISTREV*GROWTH | V10: TNETDISTPLTCLASS | X10: ALLOCCLASS
A12: 1 | B12: Residential | D12: ='II-I-Total'!J79 -> 5.3877173e+09 | H12: ='II-I-Total'!J83 -> 3.7983407e+08 | J12: ='II-I-Total'!J22 -> 2.9377371e+08 | L12: ='II-I-Total'!J25 -> 45850278 | N12: ='II-I-Total'!J1064+'II-I-Total'!J1068 -> 89438446 | P12: =SUM(H12:N12) -> 8.088965e+08 | T12: =ROUND(P12*R12,0) -> 0 | V12: ='II-I-Total'!J352 -> 5.8258316e+09 | X12: =V12/$V$32 -> 0.55664172
A14: =A12+1 -> 2 | B14: Sec < 10 kW | D14: ='II-I-Total'!K79 -> 2.1703521e+08 | H14: ='II-I-Total'!K83 -> 15300982 | J14: ='II-I-Total'!K22 -> 17898989 | L14: ='II-I-Total'!K25 -> 1770897.1 | N14: ='II-I-Total'!K1064+'II-I-Total'!K1068 -> 4154562.8 | P14: =SUM(H14:N14) -> 39125431 | T14: =ROUND(P14*R14,0) -> 0 | V14: ='II-I-Total'!K352 -> 2.3547835e+08 | X14: =V14/$V$32 -> 0.022499289
A16: =A14+1 -> 3 | B16: Sec > 10 kW | D16: ='II-I-Total'!L79 -> 3.3758328e+09 | H16: ='II-I-Total'!L83 -> 2.3799621e+08 | J16: ='II-I-Total'!L22 -> 1.7524036e+08 | L16: ='II-I-Total'!L25 -> 28788315 | N16: ='II-I-Total'!L1064+'II-I-Total'!L1068 -> 55064232 | P16: =SUM(H16:N16) -> 4.9708912e+08 | T16: =ROUND(P16*R16,0) -> 0 | V16: ='II-I-Total'!L352 -> 3.6301797e+09 | X16: =V16/$V$32 -> 0.3468534
A18: =A16+1 -> 4 | B18: Pri < 10 kW | D18: ='II-I-Total'!M79 -> 3478066.6 | H18: ='II-I-Total'!M83 -> 245203.7 | J18: ='II-I-Total'!M22 -> 385591.23 | L18: ='II-I-Total'!M25 -> 25535.902 | N18: ='II-I-Total'!M1064+'II-I-Total'!M1068 -> 55351.814 | P18: =SUM(H18:N18) -> 711682.65 | T18: =ROUND(P18*R18,0) -> 0 | V18: ='II-I-Total'!M352 -> 3563834 | X18: =V18/$V$32 -> 0.00034051425
A20: =A18+1 -> 5 | B20: Pri > 10 kW | D20: ='II-I-Total'!N79 -> 5.4406557e+08 | H20: ='II-I-Total'!N83 -> 38356623 | J20: ='II-I-Total'!N22 -> 29457396 | L20: ='II-I-Total'!N25 -> 4606241.1 | N20: ='II-I-Total'!N1064+'II-I-Total'!N1068 -> 8513196.2 | P20: =SUM(H20:N20) -> 80933456 | T20: =ROUND(P20*R20,0) -> 0 | V20: ='II-I-Total'!N352 -> 5.7935458e+08 | X20: =V20/$V$32 -> 0.05535569
A22: =A20+1 -> 6 | B22: Pri > 10 kW Sub | D22: ='II-I-Total'!O79 -> 51350344 | H22: ='II-I-Total'!O83 -> 3620199.3 | J22: ='II-I-Total'!O22 -> 1951234.2 | L22: ='II-I-Total'!O25 -> 442044.23 | N22: ='II-I-Total'!O1064+'II-I-Total'!O1068 -> 745471.27 | P22: =SUM(H22:N22) -> 6758948.9 | T22: =ROUND(P22*R22,0) -> 0 | V22: ='II-I-Total'!O352 -> 54302788 | X22: =V22/$V$32 -> 0.0051884776
A24: =A22+1 -> 7 | B24: Transmission | D24: ='II-I-Total'!P79 -> 19623592 | H24: ='II-I-Total'!P83 -> 1383463.3 | J24: ='II-I-Total'!P22 -> 869060.79 | L24: ='II-I-Total'!P25 -> 162487.89 | N24: ='II-I-Total'!P1064+'II-I-Total'!P1068 -> 214413.11 | P24: =SUM(H24:N24) -> 2629425 | T24: =ROUND(P24*R24,0) -> 0 | V24: ='II-I-Total'!P352 -> 13554838 | X24: =V24/$V$32 -> 0.0012951264
A26: =A24+1 -> 8 | B26: Lighting | D26: ='II-I-Total'!Q79 -> 55641786 | H26: ='II-I-Total'!Q83 -> 3922745.9 | J26: ='II-I-Total'!Q22 -> 25252299 | L26: ='II-I-Total'!Q25 -> 473466.34 | N26: ='II-I-Total'!Q1064+'II-I-Total'!Q1068 -> 4801841.6 | P26: =SUM(H26:N26) -> 34450353 | T26: =ROUND(P26*R26,0) -> 0 | V26: ='II-I-Total'!Q352 -> 87990668 | X26: =V26/$V$32 -> 0.0084072592
A28: =A26+1 -> 9 | B28: Wh Subst | D28: ='II-I-Total'!R79 -> 6129597.2 | H28: ='II-I-Total'!R83 -> 432136.6 | J28: ='II-I-Total'!R22 -> 232807.76 | L28: ='II-I-Total'!R25 -> 52629.279 | N28: ='II-I-Total'!R1064+'II-I-Total'!R1068 -> 89158.03 | P28: =SUM(H28:N28) -> 806731.67 | T28: =ROUND(P28*R28,0) -> 0 | V28: ='II-I-Total'!R352 -> 6501166.7 | X28: =V28/$V$32 -> 0.00062116807
A30: =A28+1 -> 10 | B30: Wh DLS | D30: ='II-I-Total'!S79 -> 27076279 | H30: ='II-I-Total'!S83 -> 1908877.7 | J30: ='II-I-Total'!S22 -> 1286394.1 | L30: ='II-I-Total'!S25 -> 232790.75 | N30: ='II-I-Total'!S1064+'II-I-Total'!S1068 -> 426525.28 | P30: =SUM(H30:N30) -> 3854587.8 | T30: =ROUND(P30*R30,0) -> 0 | V30: ='II-I-Total'!S352 -> 29277289 | X30: =V30/$V$32 -> 0.0027973621
A32: =A30+1 -> 11 | B32: Total | D32: =SUM(D12:D30) -> 9.6879505e+09 | F32: ='II-I-Total'!F81 -> 0.0705 | H32: =SUM(H12:H30) -> 6.8300051e+08 | J32: =SUM(J12:J30) -> 5.4634784e+08 | L32: =SUM(L12:L30) -> 82404686 | N32: =SUM(N12:N30) -> 1.635032e+08 | P32: =SUM(P12:P30) -> 1.4752562e+09 | T32: =SUM(T12:T30) -> 0 | V32: =SUM(V12:V30) -> 1.0466035e+10
L33: =L32/H32 -> 0.12065099 | N33: =D58/D32 -> 0.027086458
A34: =A32+1 -> 12 | B34: DCRF Exclusions | L34: =H58*L33 -> 2232051.1 | N34: =N32*N33 -> 4428722.6 | V34: DCRF Exclusions
D35: (1) | F35: (2) | H35: (3) = (1) * (2) | J35: (4) | L35: (5) | N35: (6) | P35: (7) = (3)+(4)+(5)+(6) | R35: (8) = Sch H col (9) | T35: (9) = (7)*(8) | V35: (10)
A36: =A34+1 -> 13 | B36: Rate Class | D36: DICRC | F36: RORAT | H36: Return | J36: DEPRRC-CLASS | L36: FITRC-CLASS | N36: OTRC-CLASS | P36: DISTREVRC-CLASS | R36: % GROWTHCLASS | T36: DISTREV*GROWTH | V36: TNETDISTPLTCLASS
A38: =A36+1 -> 14 | B38: Residential | D38: =D153 -> 1.4610176e+08 | H38: =D38/$D$58*$H$58 -> 10300174 | J38: =D185 -> 18091931 | L38: =H38/$H$58*$L$34 -> 1242726.1 | N38: =D38/$D$58*$N$34 -> 2465754.2 | P38: =SUM(H38:N38) -> 32100585 | V38: =D38 -> 1.4610176e+08
D39: =D38/D12 -> 0.027117562
A40: =A38+1 -> 15 | B40: Sec < 10 kW | D40: =D155 -> 8584573.6 | H40: =D40/$D$58*$H$58 -> 605212.44 | J40: =D187 -> 2440500.3 | L40: =H40/$H$58*$L$34 -> 73019.478 | N40: =D40/$D$58*$N$34 -> 144881.55 | P40: =SUM(H40:N40) -> 3263613.8 | V40: =D40 -> 8584573.6
D41: =D40/D14 -> 0.03955383
A42: =A40+1 -> 16 | B42: Sec > 10 kW | D42: =D157 -> 87563183 | H42: =D42/$D$58*$H$58 -> 6173204.4 | J42: =D189 -> 9056197.5 | L42: =H42/$H$58*$L$34 -> 744803.2 | N42: =D42/$D$58*$N$34 -> 1477800.7 | P42: =SUM(H42:N42) -> 17452006 | V42: =D42 -> 87563183
D43: =D42/D16 -> 0.025938247
A44: =A42+1 -> 17 | B44: Pri < 10 kW | D44: =D159 -> 232238.42 | H44: =D44/$D$58*$H$58 -> 16372.808 | J44: =D191 -> 102209.57 | L44: =H44/$H$58*$L$34 -> 1975.3955 | N44: =D44/$D$58*$N$34 -> 3919.4796 | P44: =SUM(H44:N44) -> 124477.25 | V44: =D44 -> 232238.42
D45: =D44/D18 -> 0.066772274
A46: =A44+1 -> 18 | B46: Pri > 10 kW | D46: =D161 -> 15468856 | H46: =D46/$D$58*$H$58 -> 1090554.3 | J46: =D193 -> 2398630.3 | L46: =H46/$H$58*$L$34 -> 131576.46 | N46: =D46/$D$58*$N$34 -> 261067.33 | P46: =SUM(H46:N46) -> 3881828.5 | V46: =D46 -> 15468856
D47: =D46/D20 -> 0.02843197
A48: =A46+1 -> 19 | B48: Pri > 10 kW Sub | D48: =D163 -> 1254437.6 | H48: =D48/$D$58*$H$58 -> 88437.848 | J48: =D195 -> 100129.31 | L48: =H48/$H$58*$L$34 -> 10670.114 | N48: =D48/$D$58*$N$34 -> 21171.098 | P48: =SUM(H48:N48) -> 220408.37 | V48: =D48 -> 1254437.6
D49: =D48/D22 -> 0.024429
A50: =A48+1 -> 20 | B50: Transmission | D50: =D165 -> 529274.91 | H50: =D50/$D$58*$H$58 -> 37313.881 | J50: =D197 -> 162888.63 | L50: =H50/$H$58*$L$34 -> 4501.9566 | N50: =D50/$D$58*$N$34 -> 8932.554 | P50: =SUM(H50:N50) -> 213637.02 | V50: =D50 -> 529274.91
D51: =D50/D24 -> 0.026971357
A52: =A50+1 -> 21 | B52: Lighting | D52: =D167 -> 1882171.2 | H52: =D52/$D$58*$H$58 -> 132693.07 | J52: =D199 -> 61527.073 | L52: =H52/$H$58*$L$34 -> 16009.55 | N52: =D52/$D$58*$N$34 -> 31765.337 | P52: =SUM(H52:N52) -> 241995.03 | V52: =D52 -> 1882171.2
D53: =D52/D26 -> 0.033826577
A54: =A52+1 -> 22 | B54: Wh Subst | D54: =D169 -> 149695.83 | H54: =D54/$D$58*$H$58 -> 10553.556 | J54: =D201 -> 11677.313 | L54: =H54/$H$58*$L$34 -> 1273.2969 | N54: =D54/$D$58*$N$34 -> 2526.4112 | P54: =SUM(H54:N54) -> 26030.577 | V54: =D54 -> 149695.83
D55: =D54/D28 -> 0.024421805
A56: =A54+1 -> 23 | B56: Wh DLS | D56: =D171 -> 646081.39 | H56: =D56/$D$58*$H$58 -> 45548.738 | J56: =D203 -> 34687.879 | L56: =H56/$H$58*$L$34 -> 5495.5002 | N56: =D56/$D$58*$N$34 -> 10903.893 | P56: =SUM(H56:N56) -> 96636.011 | V56: =D56 -> 646081.39
D57: =D56/D30 -> 0.023861528
A58: =A56+1 -> 24 | B58: Total | D58: =SUM(D38:D56) -> 2.6241227e+08 | F58: =F32 -> 0.0705 | H58: =D58*F58 -> 18500065 | J58: =SUM(J38:J56) -> 32460379 | L58: =SUM(L38:L56) -> 2232051.1 | N58: =SUM(N38:N56) -> 4428722.6 | P58: =SUM(P38:P56) -> 57621218 | V58: =D58 -> 2.6241227e+08
D59: =D58/D32 -> 0.027086458
B60: DISTREV After DCRF Exclusions | V60: After DCRF Exclusions
D62: (1) | F62: (2) | H62: (3) = (1) * (2) | J62: (4) | L62: (5) | N62: (6) | P62: (7) = (3)+(4)+(5)+(6) | R62: (8) = Sch H col (9) | T62: (9) = (7)*(8) | V62: (10) | X62: (11)=(10)/∑(10)
A63: 1 | B63: Rate Class | D63: DICRC | F63: RORAT | H63: Return | J63: DEPRRC-CLASS | L63: FITRC-CLASS | N63: OTRC-CLASS | P63: DISTREVRC-CLASS | R63: % GROWTHCLASS | T63: DISTREV*GROWTH | V63: TNETDISTPLTCLASS | X63: ALLOCCLASS
A65: =A63+1 -> 2 | B65: Residential | D65: =D12-D38 -> 5.2416155e+09 | H65: =H12-H38 -> 3.695339e+08 | J65: =J12-J38 -> 2.7568177e+08 | L65: =L12-L38 -> 44607552 | N65: =N12-N38 -> 86972692 | P65: =SUM(H65:N65) -> 7.7679592e+08 | R65: =R12 -> 0 | T65: =ROUND(P65*R65,0) -> 0 | V65: =V12-V38 -> 5.6797299e+09 | X65: =V65/$V$85 -> 0.55663857
A67: =A65+1 -> 3 | B67: Sec < 10 kW | D67: =D14-D40 -> 2.0845063e+08 | H67: =H14-H40 -> 14695770 | J67: =J14-J40 -> 15458489 | L67: =L14-L40 -> 1697877.6 | N67: =N14-N40 -> 4009681.2 | P67: =SUM(H67:N67) -> 35861817 | R67: =R14 -> 0 | T67: =ROUND(P67*R67,0) -> 0 | V67: =V14-V40 -> 2.2689377e+08 | X67: =V67/$V$85 -> 0.02223659
A69: =A67+1 -> 4 | B69: Sec > 10 kW | D69: =D16-D42 -> 3.2882696e+09 | H69: =H16-H42 -> 2.31823e+08 | J69: =J16-J42 -> 1.6618416e+08 | L69: =L16-L42 -> 28043512 | N69: =N16-N42 -> 53586431 | P69: =SUM(H69:N69) -> 4.7963711e+08 | R69: =R16 -> 0 | T69: =ROUND(P69*R69,0) -> 0 | V69: =V16-V42 -> 3.5426166e+09 | X69: =V69/$V$85 -> 0.34719204
A71: =A69+1 -> 5 | B71: Pri < 10 kW | D71: =D18-D44 -> 3245828.2 | H71: =H18-H44 -> 228830.89 | J71: =J18-J44 -> 283381.66 | L71: =L18-L44 -> 23560.507 | N71: =N18-N44 -> 51432.335 | P71: =SUM(H71:N71) -> 587205.39 | R71: =R18 -> 0 | T71: =ROUND(P71*R71,0) -> 0 | V71: =V18-V44 -> 3331595.6 | X71: =V71/$V$85 -> 0.00032651106
