Workbook

Sheet Cover
H1: Exhibit R
H2: Page 1 of
H3: Witness: Jim Adkins
A8: BLUE GRASS ENERGY
A9: COOPERATIVE
A11: CASE NO, 2014-00339
A13: COST OF SERVICE STUDY
A30: October 2014 - Mary Elizabeth Purvis & James Adkins

Sheet 1TestYr
D4: TEST YEAR EXPENSES
A5: 1
A6: 2 | G6: Purchased | H6: Total
A7: 3 | B7: Acct | C7: Description | D7: Actual | F7: GTCCs | G7: Power | H7: Amount of | J7: Adjusted
A8: 4 | B8: No. | D8: Test Year | F8: Adjustment | G8: Adjustment | H8: Adjusments | J8: Test Year
A9: 5 | G9: (a)
A10: 6 | B10: 555 | C10: Purchased Power
A11: 7 | C11: Demand Charges | J11: =[1]Sheet1!$E$20 -> 13020019
C12: Metering Point & Substations Charges | J12: =[1]Sheet1!$G$20+[1]Sheet1!$H$20 -> 1321044
A13: 8 | C13: Energy Charges | H13: 0 | J13: =[1]Sheet1!$F$20-[1]Sheet1!$O$20-[1]Sheet1!$R$20 -> 44259636 | M13: 75910446 | N13: =(M13-J13) -> 31650810
A14: 9 | C14: Renewable Resource Energy | H14: 0 | J14: =[1]Sheet1!$O$20 -> 4430
C15: WellHeads | J15: =[1]Sheet1!$R$20 -> 146741.2
A16: 10 | C16: Total Purchased Power | D16: =57651734+8614470+146741.2 -> 66412945 | G16: =(J16-D16) -> -7661075 | H16: 0 | J16: =SUM(J11:J15) -> 58751870 | L16: =SUM(J11:J14) -> 58605129
A17: 11
A18: 12 | B18: 580 | C18: Operations Supv & Eng | D18: =87147.95 -> 87147.95 | J18: =SUM(D18,F18:H18) -> 87147.95
B19: 581 | C19: Load Dispatching | D19: 0 | J19: =SUM(D19,F19:H19) -> 0
A20: 13 | B20: 582 | C20: Station Expense | D20: 24929.3 | J20: =SUM(D20,F20:H20) -> 24929.3
A21: 14 | B21: 583 | C21: Overhead Line Exp. | D21: =1615846.25+171637.1+97902.87+0+0 -> 1885386.2 | J21: =SUM(D21,F21:H21) -> 1885386.2
A22: 15 | B22: 584 | C22: Underground Line Exp | D22: =24039.57+32871.13 -> 56910.7 | J22: =SUM(D22,F22:H22) -> 56910.7
A23: 16 | B23: 585 | C23: Street Lights | D23: 0 | J23: =SUM(D23,F23:H23) -> 0
A24: 17 | B24: 586 | C24: Meter Expense | D24: =832056.07+711787.3+62955.17+0 -> 1606798.5 | J24: =SUM(D24,F24:H24) -> 1606798.5
A25: 18 | B25: 587 | C25: Consumer Installations | D25: 181345.26 | J25: =SUM(D25,F25:H25) -> 181345.26
A26: 19 | B26: 588 | C26: Misc. Distribution Exp | D26: =508362.91+0+283764.37+14620.11+0+0+218806.08+0 -> 1025553.5 | J26: =SUM(D26,F26:H26) -> 1025553.5
A27: 20 | B27: 589 | C27: Rents | D27: 0 | G27: 0 | J27: =SUM(D27,F27:H27) -> 0
A28: 21 | C28: Total Dist. Operations | D28: =SUM(D18:D27) -> 4868071.4 | G28: =SUM(G18:G27) -> 0 | H28: 0 | I28: =SUM(I18:I27) -> 0 | J28: =SUM(D28,F28:H28) -> 4868071.4 | L28: =SUM(J18:J27) -> 4868071.4
A29: 22
A30: 23 | B30: 590 | C30: Maint Supv & Eng | D30: =0 -> 0 | J30: =SUM(D30,F30:H30) -> 0
A31: 24 | B31: 592 | C31: Maint of Station Equip | D31: 0 | J31: =SUM(D31,F31:H31) -> 0
A32: 25 | B32: 593 | C32: Maint. Overhead Lines | D32: =906159.18+1396601.11+6045.96+0+110453.58+0+0+0+200+351683.32+0+122971.15+416120.71+600+0+2340384.82+0+0+9440+0 -> 5660659.8 | H32: 0 | J32: =SUM(D32,F32:H32) -> 5660659.8
A33: 26 | B33: 594 | C33: Maint of Underground Lines | D33: =5730.59+0 -> 5730.59 | J33: =SUM(D33,F33:H33) -> 5730.59
A34: 27 | B34: 595 | C34: Maint Line Transformers | D34: =16590.86 -> 16590.86 | J34: =SUM(D34,F34:H34) -> 16590.86
A35: 28 | B35: 596 | C35: Maint of Street Lights | D35: =23457.92 -> 23457.92 | J35: =SUM(D35,F35:H35) -> 23457.92
A36: 29 | B36: 597 | C36: Maintenance of Meters | D36: =0 -> 0 | J36: =SUM(D36,F36:H36) -> 0
A37: 30 | B37: 598 | C37: Maint Misc Distrib Plant | D37: 245520.58 | J37: =SUM(D37,F37:H37) -> 245520.58
A38: 31 | C38: Total Dist. Maint. | D38: =SUM(D30:D37) -> 5951959.8 | G38: =SUM(G30:G37) -> 0 | H38: 0 | I38: =SUM(I30:I37) -> 0 | J38: =SUM(D38,F38:H38) -> 5951959.8 | L38: =SUM(J30:J37) -> 5951959.8 | M38: =(J38-L38) -> 0
A39: 32 | J39: =SUM(D39,F39:H39) -> 0
A40: 33 | B40: 901 | C40: Supervision | D40: =75527.05 -> 75527.05 | J40: =SUM(D40,F40:H40) -> 75527.05
A41: 34 | B41: 902 | C41: Meter Reading Expense | D41: =37553.07 -> 37553.07 | J41: =SUM(D41,F41:H41) -> 37553.07
A42: 35 | B42: 903 | C42: Cons Recds & Collections | D42: =165933.06+11393.05+407214.84+602586.78+533854.83+5922.44+563.84+54629.61+15795.41+2620.79+8827.92+0+25204.52+330487.73+215950.72+30815.92+699376.25 -> 3111177.7 | J42: =SUM(D42,F42:H42) -> 3111177.7
A43: 36 | B43: 904 | C43: Uncollectible Accounts | D43: =-104074.25 -> -104074.25 | G43: 0 | J43: =SUM(D43,F43:H43) -> -104074.25
A44: 37 | C44: Total Consumer Accts | D44: =SUM(D40:D43) -> 3120183.6 | G44: =SUM(G40:G43) -> 0 | H44: 0 | I44: =SUM(I40:I43) -> 0 | J44: =SUM(D44,F44:H44) -> 3120183.6 | L44: =SUM(J40:J43) -> 3120183.6
A45: 38 | J45: =SUM(D45,F45:H45) -> 0
A46: 39 | B46: 907 | C46: Customer Information | D46: =3544.27+0 -> 3544.27 | J46: =SUM(D46,F46:H46) -> 3544.27
A47: 40 | B47: 908 | C47: Customer Accounting | D47: =0+104.09+(-21181.76)+6528.37+0+0+126.25+0+(-5510.04)+(-1077.13)+67009.73+40108.55+16532.53+0+7194.31+10088.8+82915.94+49860.1+30+0+0+0+0 -> 252729.74 | J47: =SUM(D47,F47:H47) -> 252729.74
A48: 41 | B48: 909 | C48: Consumer Information | D48: =21655.34+2288.98+12806.56 -> 36750.88 | J48: =SUM(D48,F48:H48) -> 36750.88
A49: 42 | B49: 910 | C49: Mis. Customer Information | D49: =31839.84+5441.62+37551.37+124708.59+0+1907.02+44443.43+24234.44+0+99916.01 -> 370042.32 | J49: =SUM(D49,F49:H49) -> 370042.32
A50: 43 | B50: 912 | C50: Key Accounts Expneses | D50: 0 | J50: =SUM(D50,F50:H50) -> 0
B51: 913 | C51: Advertising | D51: 148618.07
A52: 44 | C52: Total Customer Serv. | D52: =SUM(D46:D51) -> 811685.28 | G52: =SUM(G46:G50) -> 0 | H52: 0 | I52: =SUM(I46:I50) -> 0 | J52: =SUM(D52,F52:H52) -> 811685.28 | L52: =SUM(J46:J50) -> 663067.21
A53: 45 | J53: =SUM(D53,F53:H53) -> 0
A54: 46 | B54: 920 | C54: Administrative Salaries | D54: =179937+115994.25+0+12402.39+0+6344.99+7778.01+589792.19+0+0+0+139205.29+370512.35+18239.76+156609.98+2262.14+0+499235.58+5883.6+12643.75+0 -> 2116841.3 | J54: =SUM(D54,F54:H54) -> 2116841.3
A55: 47 | B55: 921 | C55: Office Supplies | D55: =343536.25+38.35+0+44.76+0+0+14855.05+29312.21+180804.55+16955.86+0+3345.51+0+43562.85+38311.96+26280.67+16552.91+12413.24+6600.69+11635.14+0 -> 744250 | G55: 0 | J55: =SUM(D55,F55:H55) -> 744250
A56: 48 | B56: 923 | C56: Outside Services | D56: =118341.33+0 -> 118341.33 | J56: =SUM(D56,F56:H56) -> 118341.33
A57: 49 | B57: 924 | C57: Property Ins | D57: 0 | G57: =(D57/$D$65)*(11175) -> 0 | J57: =SUM(D57,F57:H57) -> 0
A58: 50 | B58: 925 | C58: Injuries & Damages | D58: =26498.25 -> 26498.25 | J58: =SUM(D58,F58:H58) -> 26498.25
A59: 51 | B59: 926 | C59: Employ Pensions & Benef | D59: =8264+149548.92+0+0-3345.36 -> 154467.56 | J59: =SUM(D59,F59:H59) -> 154467.56
A60: 52 | B60: 928 | C60: Regulatory Exp | D60: =16364.41 -> 16364.41 | J60: =SUM(D60,F60:H60) -> 16364.41
A61: 53 | B61: 929 | C61: Duplicate Charges | D61: -84878.35 | J61: =SUM(D61,F61:H61) -> -84878.35
A62: 54 | B62: 930 | C62: Misc General Exp | D62: =0+2273.86+0+13498.16+212245.86+172745.63+115543.34+57935.86+276265.25+23043.99+3484.12+0+99.09 -> 877135.16 | J62: =SUM(D62,F62:H62) -> 877135.16
A63: 55 | B63: 931 | C63: Rents | D63: 22200 | J63: =SUM(D63,F63:H63) -> 22200
A64: 56 | B64: 935 | C64: Maintenance of Gen. Plant | D64: =306167.78+0+98439.78+118534.38+34101.56+26390.44 -> 583633.94 | J64: =SUM(D64,F64:H64) -> 583633.94
A65: 57 | C65: Total Admin & General | D65: =SUM(D54:D64) -> 4574853.6 | F65: =SUM(F54:F64) -> 0 | G65: =SUM(G54:G64) -> 0 | H65: 0 | J65: =SUM(D65,F65:H65) -> 4574853.6 | L65: =SUM(J54:J64) -> 4574853.6 | M65: =(J65-L65) -> 0 | N65: =(3502109-J65) -> -1072744.6
A66: 58 | J66: =SUM(D66,F66:H66) -> 0
A67: 59 | B67: 403.6 | C67: Deprec. Distribution Plant | D67: 7662550.6 | J67: =SUM(D67,F67:H67) -> 7662550.6
A68: 60 | B68: 403.7 | C68: Deprec. General Plant | D68: 593330.59 | J68: =SUM(D68,F68:H68) -> 593330.59
B69: 407 | C69: Amort of Prop Loasses and Undercovery | D69: 470772
A70: 61 | C70: Total Depreciation | D70: =SUM(D67:D69) -> 8726653.2 | G70: =SUM(G67:G68) -> 0 | H70: 0 | J70: =SUM(D70,F70:H70) -> 8726653.2 | L70: =SUM(J67:J68) -> 8255881.2
A71: 62 | J71: =SUM(D71,F71:H71) -> 0
A72: 63 | B72: 408.71 | C72: PSC Assessment & Sales Taxes | D72: 120557.14 | J72: =SUM(D72,F72:H72) -> 120557.14
A73: 64 | B73: 408.5 | C73: Miscellaneous Amortization | D73: 0 | J73: =SUM(D73,F73:H73) -> 0
A74: 65 | B74: 425-426 | C74: Contributions | D74: =17181.01+63715.14 -> 80896.15 | J74: =SUM(D74,F74:H74) -> 80896.15
A75: 66 | C75: Total Miscellaneous | D75: =SUM(D72:D74) -> 201453.29 | F75: =SUM(F72:F74) -> 0 | G75: =SUM(G72:G74) -> 0 | H75: 0 | J75: =SUM(D75,F75:H75) -> 201453.29 | L75: =SUM(J72:J74) -> 201453.29
A76: 67 | J76: =SUM(D76,F76:H76) -> 0
A77: 68 | B77: 427.1 | C77: Interest - RUS Constuc | D77: 1391391.6 | J77: =SUM(D77,F77:H77) -> 1391391.6
A78: 69 | B78: 427.2 | C78: Interest - CFC | D78: 1390363.2 | G78: 0 | J78: =SUM(D78,F78:H78) -> 1390363.2
A79: 70 | B79: 427.4 | C79: Interest - FFB | D79: 2621589.4 | J79: =SUM(D79,F79:H79) -> 2621589.4
A80: 71 | C80: Total Interest on LTD | D80: =SUM(D77:D79) -> 5403344.2 | G80: =SUM(G77:G79) -> 0 | H80: 0 | J80: =SUM(D80,F80:H80) -> 5403344.2 | L80: =SUM(J77:J79) -> 5403344.2
A81: 72
A82: 73 | B82: 431 | C82: Other Interest Expense | D82: 54021.35 | H82: 0 | J82: =SUM(D82,F82:H82) -> 54021.35
A83: 74 | G83: 0 | J83: =SUM(D83,F83:H83) -> 0
A84: 75 | D84: 0 | H84: 0 | J84: =SUM(D84,F84:H84) -> 0
A85: 76 | C85: Total ST Interest | D85: =SUM(D82:D84) -> 54021.35 | G85: =SUM(G82:G84) -> 0 | H85: =SUM(F85:G85) -> 0 | J85: =SUM(D85,F85:H85) -> 54021.35 | L85: =SUM(J82:J84) -> 54021.35
A86: 77 | J86: =SUM(D86,F86:H86) -> 0
A87: 78 | C87: Total Costs | D87: =SUM(D16,D28,D38,D44,D52,D65,D70,D75,D80,D85) -> 1.0012517e+08 | E87: =SUM(E16,E28,E38,E44,E52,E65,E70,E75,E80,E85) -> 0 | F87: =SUM(F16,F28,F38,F44,F52,F65,F70,F75,F80,F85) -> 0 | G87: =SUM(G16,G28,G38,G44,G52,G65,G70,G75,G80,G85) -> -7661075 | H87: 0 | I87: =SUM(I16,I28,I38,I44,I52,I65,I70,I75,I80,I85) -> 0 | J87: =SUM(J16,J28,J38,J44,J52,J65,J70,J75,J80,J85) -> 92464096 | L87: =SUM(L16,L28,L38,L44,L52,L65,L70,L75,L80,L85) -> 91697965 | M87: =(J87-L87) -> 766131.27 | N87: =(J87-M87) -> 91697965
A88: 79 | C88: Margin Requirements | D88: 3617966 | G88: =(G80) -> 0 | H88: =(H80*1.32) -> 0 | J88: =SUM(D88,F88:H88) -> 3617966 | L88: =(J88) -> 3617966
A89: 80 | C89: Total Revenue Require. | D89: =(D87+D88) -> 1.0374314e+08 | E89: =(E87+E88) -> 0 | F89: =(F87+F88) -> 0 | G89: =(G87+G88) -> -7661075 | H89: =(H87+H88) -> 0 | I89: =(I87+I88) -> 0 | J89: =SUM(D89,F89:H89) -> 96082062 | L89: =(L87+L88) -> 95315931 | M89: =(M97) -> 0
A90: 81
A91: 82 | C91: Less; Misc Income | J91: =SUM(D91,F91:H91) -> 0
A92: 83 | B92: 450 | C92: Forfeited Discounts | D92: 1124919.2 | J92: =SUM(D92,F92:H92) -> 1124919.2
A93: 84 | B93: 451 | C93: Misc Service Revenue | D93: 326809.63 | H93: 0 | J93: =SUM(D93,F93:H93) -> 326809.63
A94: 85 | B94: 452 | C94: Return Check Charge | D94: 0 | J94: =SUM(D94,F94:H94) -> 0
A95: 86 | B95: 454 | C95: Rent from Electric Prop. | D95: 915266.04 | H95: 0 | J95: =SUM(D95,F95:H95) -> 915266.04
B96: 456 | C96: Other Electric Revenue | D96: 233945.2 | J96: =SUM(D96,F96:H96) -> 233945.2
A97: 87 | C97: Total Misc Income | D97: =SUM(D92:D96) -> 2600940 | G97: =SUM(G92:G95) -> 0 | H97: =SUM(H92:H95) -> 0 | J97: =SUM(D97,F97:H97) -> 2600940 | L97: =SUM(J91:J96) -> 2600940
A98: 88 | J98: =SUM(D98,F98:H98) -> 0
A99: 89 | C99: Less: Other Income | J99: =SUM(D99,F99:H99) -> 0
A100: 90 | B100: 415 | C100: Net Revenue from Merchandising | D100: 8776.37 | J100: =SUM(D100,F100:H100) -> 8776.37
B101: 416 | C101: Cost of Merchandising | D101: =3365.55-8092.82 -> -4727.27 | J101: =SUM(D101,F101:H101) -> -4727.27
B102: 417 | C102: Revenue fron Non-utility Operations | D102: =5100+9240 -> 14340 | J102: =SUM(D102,F102:H102) -> 14340
B103: 418 | C103: Revenue from Non-operating rentals | D103: 124271.41 | J103: =SUM(D103,F103:H103) -> 124271.41
...

Sheet 1TestYr_adj
D4: TEST YEAR EXPENSES
G6: Payroll | J6: Retirement | O6: G&T | P6: Purchased | Q6: Total
B7: Acct | C7: Description | D7: Actual | F7: Wages | G7: Taxes | H7: Depreciaton | I7: Interest | J7: & Security | K7: Property | M7: Administrative | N7: Other | O7: Capital Credits | P7: Power | Q7: Amount of | S7: Adjusted
B8: No. | D8: Test Year | F8: Adjustment | G8: Adjustment | H8: Adjustment | I8: Adjustment | J8: Adjustment | K8: Taxes | L8: Donations | M8: & General | N8: Income | O8: Adjustment | P8: Adjustment | Q8: Adjusments | S8: Test Year
P9: (a)
B10: 555 | C10: Purchased Power
C11: Demand Charges | P11: =(T11-U11) -> 51687.096 | Q11: =P11 -> 51687.096 | S11: =(U11+Q11) -> 18577420 | T11: =SUM('Power Cost'!H92:K92) -> 18577420 | U11: 18525733
C12: Metering Point & Substations Charges | P12: =(T12-U12) -> 57024 | Q12: =P12 -> 57024 | S12: =(U12+Q12) -> 1545492 | T12: =('Power Cost'!U90) -> 1545492 | U12: 1488468
C13: Energy Charges | P13: =(T13-U13) -> -269797.22 | Q13: =P13 -> -269797.22 | S13: =(U13+Q13) -> 63975166 | T13: =SUM('Power Cost'!N93)-(T14) -> 63975166 | U13: 64244963 | V13: 75910446 | W13: =(V13-S13) -> 11935280
C14: Renewable Resource Energy | P14: =(T14-U14) -> 0 | Q14: =P14 -> 0 | S14: =(U14+Q14) -> 6455.25 | T14: =('Power Cost'!U91) -> 6455.25 | U14: 6455.25
C15: By Thru and Metering Point Charges | P15: 0 | Q15: =P15 -> 0 | S15: =(U15+Q15) -> 0 | T15: 0 | U15: 0
C16: Total Purchased Power | D16: 96070322 | P16: =(S16-D16) -> -11965789 | Q16: =SUM(F16:P16) -> -11965789 | S16: =SUM(S11:S15) -> 84104533 | T16: =SUM(T11:T15) -> 84104533 | U16: =SUM(U11:U15) -> 84265620
B18: 580 | C18: Operations Supv & Eng | D18: 234904.52 | F18: ='1.1TYAdj.'!U4 -> 941.74454 | G18: ='1.1TYAdj.'!V4 -> 165.76384 | J18: ='1.1TYAdj.'!X4 -> 751.53893 | Q18: =SUM(F18:P18) -> 1859.0473 | S18: =SUM(D18,F18:P18) -> 236763.57
B19: 581 | C19: Load Dispatching | D19: 0 | Q19: =SUM(F19:P19) -> 0 | S19: =SUM(D19,F19:P19) -> 0 | U19: =SUM(Q11:Q15) -> -161086.12
B20: 582 | C20: Station Expense | D20: 50572.11 | F20: ='1.1TYAdj.'!U5 -> 202.74624 | G20: ='1.1TYAdj.'!V5 -> 35.686955 | J20: ='1.1TYAdj.'!X5 -> 161.79727 | Q20: =SUM(F20:P20) -> 400.23046 | S20: =SUM(D20,F20:P20) -> 50972.34
B21: 583 | C21: Overhead Line Exp. | D21: 1260597.8 | F21: ='1.1TYAdj.'!U6 -> 5053.8028 | G21: ='1.1TYAdj.'!V6 -> 889.55943 | J21: ='1.1TYAdj.'!X6 -> 4033.0783 | Q21: =SUM(F21:P21) -> 9976.4405 | S21: =SUM(D21,F21:P21) -> 1270574.3
B22: 584 | C22: Underground Line Exp | D22: 120534.27 | F22: ='1.1TYAdj.'!U7 -> 483.22821 | G22: ='1.1TYAdj.'!V7 -> 85.056785 | J22: ='1.1TYAdj.'!X7 -> 385.62986 | Q22: =SUM(F22:P22) -> 953.91485 | S22: =SUM(D22,F22:P22) -> 121488.18
B23: 585 | C23: Street Lights | D23: 26089.27 | F23: ='1.1TYAdj.'!U8 -> 104.59325 | G23: ='1.1TYAdj.'!V8 -> 18.410278 | J23: ='1.1TYAdj.'!X8 -> 83.46839 | Q23: =SUM(F23:P23) -> 206.47192 | S23: =SUM(D23,F23:P23) -> 26295.742
B24: 586 | C24: Meter Expense | D24: 517709.94 | F24: ='1.1TYAdj.'!U9 -> 2075.5263 | G24: ='1.1TYAdj.'!V9 -> 365.32965 | J24: ='1.1TYAdj.'!X9 -> 1656.329 | Q24: =SUM(F24:P24) -> 4097.185 | S24: =SUM(D24,F24:P24) -> 521807.12
B25: 587 | C25: Consumer Installations | D25: 305880.98 | F25: ='1.1TYAdj.'!U10 -> 1226.2929 | G25: ='1.1TYAdj.'!V10 -> 215.84942 | J25: ='1.1TYAdj.'!X10 -> 978.61661 | Q25: =SUM(F25:P25) -> 2420.7589 | S25: =SUM(D25,F25:P25) -> 308301.74
B26: 588 | C26: Misc. Distribution Exp | D26: 181456.8 | F26: ='1.1TYAdj.'!U11 -> 727.46983 | G26: ='1.1TYAdj.'!V11 -> 128.04767 | H26: =[3]adjustments!$F$21 -> 846.49746 | J26: ='1.1TYAdj.'!X11 -> 580.54161 | K26: =[3]adjustments!$I$21 -> 16382.168 | Q26: =SUM(F26:P26) -> 18664.725 | S26: =SUM(D26,F26:P26) -> 200121.52
B27: 589 | C27: Rents | D27: 0 | P27: 0 | S27: =SUM(D27,F27:P27) -> 0
C28: Total Dist. Operations | D28: =SUM(D18:D27) -> 2697745.7 | F28: =SUM(F18:F27) -> 10815.404 | G28: =SUM(G18:G27) -> 1903.704 | H28: =SUM(H18:H27) -> 846.49746 | I28: =SUM(I18:I27) -> 0 | J28: =SUM(J18:J27) -> 8631 | K28: =SUM(K18:K27) -> 16382.168 | P28: =SUM(P18:P27) -> 0 | Q28: =SUM(F28:P28) -> 38578.774 | R28: =SUM(R18:R27) -> 0 | S28: =SUM(D28,F28:P28) -> 2736324.5 | U28: =SUM(S18:S27) -> 2736324.5
B30: 590 | C30: Maint Supv & Eng | D30: =24036.59+280697.28 -> 304733.87 | F30: ='1.1TYAdj.'!U15 -> 1738.44 | G30: ='1.1TYAdj.'!V15 -> 305.99645 | J30: ='1.1TYAdj.'!X15 -> 1387.2974 | Q30: =SUM(F30:P30) -> 3431.7339 | S30: =SUM(D30,F30:P30) -> 308165.6
B31: 592 | C31: Maint of Station Equip | D31: 149.99 | F31: ='1.1TYAdj.'!U16 -> 0.85566012 | G31: ='1.1TYAdj.'!V16 -> 0.15061144 | J31: ='1.1TYAdj.'!X16 -> 0.68282775 | Q31: =SUM(F31:P31) -> 1.6890993 | S31: =SUM(D31,F31:P31) -> 151.6791
B32: 593 | C32: Maint. Overhead Lines | D32: =1416756.57+2823570.35+572737.64+0 -> 4813064.6 | F32: ='1.1TYAdj.'!U17 -> 27457.48 | G32: ='1.1TYAdj.'!V17 -> 4833.0062 | J32: ='1.1TYAdj.'!X17 -> 21911.421 | Q32: =SUM(F32:P32) -> 54201.907 | S32: =SUM(D32,F32:P32) -> 4867266.5
B33: 594 | C33: Maint of Underground Lines | D33: =284957.92+17476.89 -> 302434.81 | F33: ='1.1TYAdj.'!U18 -> 1725.3244 | G33: ='1.1TYAdj.'!V18 -> 303.68787 | J33: ='1.1TYAdj.'!X18 -> 1376.831 | Q33: =SUM(F33:P33) -> 3405.8433 | S33: =SUM(D33,F33:P33) -> 305840.65
B34: 595 | C34: Maint Line Transformers | D34: =16801.08 -> 16801.08 | F34: ='1.1TYAdj.'!U19 -> 95.846484 | G34: ='1.1TYAdj.'!V19 -> 16.870691 | J34: ='1.1TYAdj.'!X19 -> 76.486724 | Q34: =SUM(F34:P34) -> 189.2039 | S34: =SUM(D34,F34:P34) -> 16990.284
B35: 596 | C35: Maint of Street Lights | D35: =195353.39 -> 195353.39 | F35: ='1.1TYAdj.'!U20 -> 1114.4483 | G35: ='1.1TYAdj.'!V20 -> 196.16278 | J35: ='1.1TYAdj.'!X20 -> 889.34407 | Q35: =SUM(F35:P35) -> 2199.9552 | S35: =SUM(D35,F35:P35) -> 197553.35
B36: 597 | C36: Maintenance of Meters | D36: =193445.15 -> 193445.15 | F36: ='1.1TYAdj.'!U21 -> 1103.5622 | G36: ='1.1TYAdj.'!V21 -> 194.24664 | J36: ='1.1TYAdj.'!X21 -> 880.65683 | Q36: =SUM(F36:P36) -> 2178.4657 | S36: =SUM(D36,F36:P36) -> 195623.62
B37: 598 | C37: Maint Misc Distrib Plant | D37: 349101.35 | F37: ='1.1TYAdj.'!U22 -> 1991.5468 | G37: ='1.1TYAdj.'!V22 -> 350.54776 | H37: =[3]adjustments!$F$22 -> 1513.4122 | J37: ='1.1TYAdj.'!X22 -> 1589.2799 | Q37: =SUM(F37:P37) -> 5444.7867 | S37: =SUM(D37,F37:P37) -> 354546.14
C38: Total Dist. Maint. | D38: =SUM(D30:D37) -> 6175084.2 | F38: =SUM(F30:F37) -> 35227.504 | G38: =SUM(G30:G37) -> 6200.669 | H38: =SUM(H30:H37) -> 1513.4122 | I38: =SUM(I30:I37) -> 0 | J38: =SUM(J30:J37) -> 28112 | P38: =SUM(P30:P37) -> 0 | Q38: =SUM(E38:P38) -> 71053.585 | R38: =SUM(R30:R37) -> 0 | S38: =SUM(D38,F38:P38) -> 6246137.8 | U38: =SUM(S30:S37) -> 6246137.8 | V38: =(S38-U38) -> 0
S39: =SUM(D39,F39:Q39) -> 0
B40: 901 | C40: Supervision | D40: 140605.04 | F40: ='1.1TYAdj.'!U26 -> 1185.2476 | G40: ='1.1TYAdj.'!V26 -> 208.62472 | H40: =[3]adjustments!$F$23 -> 388.88015 | J40: ='1.1TYAdj.'!X26 -> 945.86103 | Q40: =SUM(F40:P40) -> 2728.6135 | S40: =SUM(D40,F40:P40) -> 143333.65
B41: 902 | C41: Meter Reading Expense | D41: 100208.98 | F41: ='1.1TYAdj.'!U27 -> 844.72401 | G41: ='1.1TYAdj.'!V27 -> 148.68649 | J41: ='1.1TYAdj.'!X27 -> 674.1136 | Q41: =SUM(F41:P41) -> 1667.5241 | S41: =SUM(D41,F41:P41) -> 101876.5
B42: 903 | C42: Cons Recds & Collections | D42: =2281600.99+225.68 -> 2281826.7 | F42: ='1.1TYAdj.'!U28 -> 19234.941 | G42: ='1.1TYAdj.'!V28 -> 3385.6926 | J42: ='1.1TYAdj.'!X28 -> 15350.025 | Q42: =SUM(F42:P42) -> 37970.659 | S42: =SUM(D42,F42:P42) -> 2319797.3
B43: 904 | C43: Uncollectible Accounts | D43: 340357.45 | P43: 0 | Q43: =SUM(F43:P43) -> 0 | S43: =SUM(D43,F43:P43) -> 340357.45
C44: Total Consumer Accts | D44: =SUM(D40:D43) -> 2862998.1 | F44: =SUM(F40:F43) -> 21264.912 | G44: =SUM(G40:G43) -> 3743.0038 | H44: =SUM(H40:H43) -> 388.88015 | J44: =SUM(J40:J43) -> 16970 | K44: =SUM(K40:K43) -> 0 | P44: =SUM(P40:P43) -> 0 | Q44: =SUM(F44:P44) -> 42366.796 | R44: =SUM(R40:R43) -> 0 | S44: =SUM(D44,F44:P44) -> 2905364.9 | U44: =SUM(S40:S43) -> 2905364.9
B46: 907 | C46: Customer Information | D46: 0 | F46: ='1.1TYAdj.'!U32 -> 0 | G46: ='1.1TYAdj.'!V32 -> 0 | J46: ='1.1TYAdj.'!X32 -> 0 | Q46: =SUM(F46:P46) -> 0 | S46: =SUM(D46,F46:P46) -> 0
B47: 908 | C47: Customer Accounting | D47: 944348.21 | F47: ='1.1TYAdj.'!U33 -> 16145.418 | G47: ='1.1TYAdj.'!V33 -> 2841.8816 | J47: ='1.1TYAdj.'!X33 -> 12883.853 | Q47: =SUM(F47:P47) -> 31871.152 | S47: =SUM(D47,F47:P47) -> 976219.36
B48: 909 | C48: Consumer Information | D48: 0 | F48: ='1.1TYAdj.'!U34 -> 0 | G48: ='1.1TYAdj.'!V34 -> 0 | H48: =[3]adjustments!$F$24 -> 321.18822 | J48: ='1.1TYAdj.'!X34 -> 0 | Q48: =SUM(F48:P48) -> 321.18822 | S48: =SUM(D48,F48:P48) -> 321.18822
B49: 910 | C49: Mis. Customer Information | D49: 0 | F49: ='1.1TYAdj.'!U35 -> 0 | G49: ='1.1TYAdj.'!V35 -> 0 | J49: ='1.1TYAdj.'!X35 -> 0 | Q49: =SUM(F49:P49) -> 0 | S49: =SUM(D49,F49:P49) -> 0
B50: 912 | C50: Key Accounts Expneses | D50: =247481.46-259344.79 -> -11863.33 | F50: ='1.1TYAdj.'!U36 -> -202.82605 | G50: ='1.1TYAdj.'!V36 -> -35.701003 | J50: ='1.1TYAdj.'!X36 -> -161.8528 | Q50: =SUM(F50:P50) -> -400.37985 | S50: =SUM(D50,F50:P50) -> -12263.71
B51: 913 | C51: Advertising | D51: 60695.81 | Q51: =SUM(F51:P51) -> 0 | S51: =SUM(D51,F51:P51) -> 60695.81
C52: Total Customer Serv. | D52: =SUM(D46:D51) -> 993180.69 | F52: =SUM(F46:F50) -> 15942.592 | G52: =SUM(G46:G50) -> 2806.1805 | H52: =SUM(H46:H50) -> 321.18822 | J52: =SUM(J46:J50) -> 12722 | P52: =SUM(P46:P50) -> 0 | Q52: =SUM(F52:P52) -> 31791.961 | R52: =SUM(R46:R50) -> 0 | S52: =SUM(D52,F52:P52) -> 1024972.7 | U52: =SUM(S46:S51) -> 1024972.7
B54: 920 | C54: Administrative Salaries | D54: =2413480.73+177043.6 -> 2590524.3 | F54: ='1.1TYAdj.'!U41 -> 30679.832 | G54: ='1.1TYAdj.'!V41 -> 5400.1977 | J54: ='1.1TYAdj.'!X41 -> 24482.782 | Q54: =SUM(F54:P54) -> 60562.812 | S54: =SUM(D54,F54:P54) -> 2651087.1
B55: 921 | C55: Office Supplies | D55: 388751.32 | P55: 0 | Q55: =SUM(F55:P55) -> 0 | S55: =SUM(D55,F55:P55) -> 388751.32
B56: 923 | C56: Outside Services | D56: 131999.24 | Q56: =SUM(F56:P56) -> 0 | S56: =SUM(D56,F56:P56) -> 131999.24
B57: 924 | C57: Property Ins | D57: 0 | P57: =(D57/$D$65)*(11175) -> 0 | Q57: =SUM(F57:P57) -> 0 | S57: =SUM(D57,F57:P57) -> 0
B58: 925 | C58: Injuries & Damages | D58: 0 | Q58: =SUM(F58:P58) -> 0 | S58: =SUM(D58,F58:P58) -> 0
B59: 926 | C59: Employ Pensions & Benef | D59: 0 | F59: ='1.1TYAdj.'!U42 -> 0 | G59: ='1.1TYAdj.'!V42 -> 0 | J59: ='1.1TYAdj.'!X42 -> 0 | Q59: =SUM(F59:P59) -> 0 | S59: =SUM(D59,F59:P59) -> 0
B60: 928 | C60: Regulatory Exp | D60: 135353.92 | Q60: =SUM(F60:P60) -> 0 | S60: =SUM(D60,F60:P60) -> 135353.92
B61: 929 | C61: Duplicate Charges | D61: -140016.4 | Q61: =SUM(F61:P61) -> 0 | S61: =SUM(D61,F61:P61) -> -140016.4
B62: 930 | C62: Misc General Exp | D62: =263706.17+112616.43+180491.92+201889.46+0+130534.3 -> 889238.28 | F62: ='1.1TYAdj.'!U43 -> 10531.336 | G62: ='1.1TYAdj.'!V43 -> 1853.7029 | J62: ='1.1TYAdj.'!X43 -> 8404.1005 | K62: =[3]adjustments!$I$26 -> 506.66499 | M62: -92292 | Q62: =SUM(F62:P62) -> -70996.196 | S62: =SUM(D62,F62:P62) -> 818242.08
B63: 931 | C63: Rents | D63: 0 | Q63: =SUM(F63:P63) -> 0 | S63: =SUM(D63,F63:P63) -> 0
B64: 935 | C64: Maintenance of Gen. Plant | D64: 408862.49 | F64: ='1.1TYAdj.'!U44 -> 4842.1983 | G64: ='1.1TYAdj.'!V44 -> 852.31328 | H64: =[3]adjustments!$F$26 -> 551.93805 | J64: ='1.1TYAdj.'!X44 -> 3864.1178 | Q64: =SUM(F64:P64) -> 10110.567 | S64: =SUM(D64,F64:P64) -> 418973.06
C65: Total Admin & General | D65: =SUM(D54:D64) -> 4404713.2 | F65: =SUM(F54:F64) -> 46053.366 | G65: =SUM(G54:G64) -> 8106.2139 | H65: =SUM(H54:H64) -> 551.93805 | I65: =SUM(I54:I64) -> 0 | J65: =SUM(J54:J64) -> 36751 | K65: =SUM(K54:K64) -> 506.66499 | M65: =SUM(M54:M64) -> -92292 | O65: =SUM(O54:O64) -> 0 | P65: =SUM(P54:P64) -> 0 | Q65: =SUM(F65:P65) -> -322.81674 | S65: =SUM(D65,F65:P65) -> 4404390.4 | U65: =SUM(S54:S64) -> 4404390.4 | V65: =(S65-U65) -> -9.3132257e-10
S66: =SUM(D66,F66:Q66) -> 0 | T66: .
B67: 403.6 | C67: Deprec. Distribution Plant | D67: 7774404.5 | H67: =[4]adjustment!$K$15 -> 116920.87 | Q67: =SUM(F67:P67) -> 116920.87 | S67: =SUM(D67,F67:P67) -> 7891325.3
B68: 403.7 | C68: Deprec. General Plant | D68: 478637.41 | H68: =[4]adjustment!$K$16 -> 14331.137 | Q68: =SUM(F68:P68) -> 14331.137 | S68: =SUM(D68,F68:P68) -> 492968.55
B69: 407 | C69: Amort of Prop Losses and Undercovery | D69: 0 | Q69: =SUM(F69:P69) -> 0 | S69: =SUM(D69,F69:P69) -> 0
C70: Total Depreciation | D70: =SUM(D67:D69) -> 8253041.9 | H70: =SUM(H67:H68) -> 131252 | P70: =SUM(P67:P68) -> 0 | Q70: =SUM(F70:P70) -> 131252 | S70: =SUM(D70,F70:P70) -> 8384293.9 | U70: =SUM(S67:S68) -> 8384293.9
S71: =SUM(D71,F71:Q71) -> 0
B72: 408.71 | C72: PSC Assessment & Sales Taxes | D72: 160.49 | Q72: =SUM(F72:P72) -> 0 | S72: =SUM(D72,F72:P72) -> 160.49
B73: 408.5 | C73: Miscellaneous Amortization | D73: 0 | Q73: =SUM(F73:P73) -> 0 | S73: =SUM(D73,F73:P73) -> 0
B74: 425-426 | C74: Contributions | D74: =2986.68+20111.08+0 -> 23097.76 | L74: =[3]adjustments!$J$34 -> -2987 | Q74: =SUM(F74:P74) -> -2987 | S74: =SUM(D74,F74:P74) -> 20110.76
C75: Total Miscellaneous | D75: =SUM(D72:D74) -> 23258.25 | L75: =SUM(L72:L74) -> -2987 | O75: =SUM(O72:O74) -> 0 | P75: =SUM(P72:P74) -> 0 | Q75: =SUM(F75:P75) -> -2987 | S75: =SUM(D75,F75:P75) -> 20271.25 | U75: =SUM(S72:S74) -> 20271.25
S76: =SUM(D76,F76:Q76) -> 0
B77: 427.1 | C77: Interest - RUS Constuc | D77: 3128863 | Q77: =SUM(F77:P77) -> 0 | S77: =SUM(D77,F77:P77) -> 3128863
B78: 427.2 | C78: Interest - CFC | D78: 655206.95 | P78: 0 | Q78: =SUM(F78:P78) -> 0 | S78: =SUM(D78,F78:P78) -> 655206.95
B79: 427.4 | C79: Interest - FFB | D79: 435252.82 | I79: 482472 | Q79: =SUM(F79:P79) -> 482472 | S79: =SUM(D79,F79:P79) -> 917724.82
C80: Total Interest on LTD | D80: =SUM(D77:D79) -> 4219322.8 | I80: 482472 | P80: =SUM(P77:P79) -> 0 | Q80: =SUM(F80:P80) -> 482472 | S80: =SUM(D80,F80:P80) -> 4701794.8 | U80: =SUM(S77:S79) -> 4701794.8
B82: 431 | C82: Other Interest Expense | D82: 2878.86 | Q82: 0 | S82: =SUM(D82,F82:Q82) -> 2878.86
P83: 0 | S83: =SUM(D83,F83:Q83) -> 0
D84: 0 | Q84: 0 | S84: =SUM(D84,F84:Q84) -> 0
C85: Total ST Interest | D85: =SUM(D82:D84) -> 2878.86 | P85: =SUM(P82:P84) -> 0 | Q85: =SUM(F85:P85) -> 0 | S85: =SUM(D85,F85:Q85) -> 2878.86 | U85: =SUM(S82:S84) -> 2878.86
S86: =SUM(D86,F86:Q86) -> 0
C87: Total Costs | D87: =SUM(D16,D28,D38,D44,D52,D65,D70,D75,D80,D85) -> 1.2570255e+08 | E87: =SUM(E16,E28,E38,E44,E52,E65,E70,E75,E80,E85) -> 0 | F87: =SUM(F16,F28,F38,F44,F52,F65,F70,F75,F80,F85) -> 129303.78 | G87: =SUM(G16,G28,G38,G44,G52,G65,G70,G75,G80,G85) -> 22759.771 | H87: =SUM(H16,H28,H38,H44,H52,H65,H70,H75,H80,H85) -> 134873.92 | I87: =SUM(I16,I28,I38,I44,I52,I65,I70,I75,I80,I85) -> 482472 | J87: =SUM(J16,J28,J38,J44,J52,J65,J70,J75,J80,J85) -> 103186 | K87: =SUM(K16,K28,K38,K44,K52,K65,K70,K75,K80,K85) -> 16888.833 | ... M87: =SUM(M16,M28,M38,M44,M52,M65,M70,M75,M80,M85) -> -92292 | O87: =SUM(O16,O28,O38,O44,O52,O65,O70,O75,O80,O85) -> 0 | P87: =SUM(P16,P28,P38,P44,P52,P65,P70,P75,P80,P85) -> -11965789 | Q87: =SUM(F87:P87) -> -11171583 | R87: =SUM(R16,R28,R38,R44,R52,R65,R70,R75,R80,R85) -> 0 | S87: =SUM(S16,S28,S38,S44,S52,S65,S70,S75,S80,S85) -> 1.1453096e+08 | U87: =SUM(F87:P87)+D87 -> 1.1453096e+08 | V87: =(S87-U87) -> 0 | W87: =(S87-V87) -> 1.1453096e+08
C88: Margin Requirements | D88: 4219323 | I88: 482472 | P88: =(P80) -> 0 | Q88: =SUM(F88:P88) -> 482472 | S88: =SUM(D88,F88:P88) -> 4701795 | U88: =(S88) -> 4701795
C89: Total Revenue Require. | D89: =(D87+D88) -> 1.2992187e+08 | E89: =(E87+E88) -> 0 | F89: =(F87+F88) -> 129303.78 | G89: =(G87+G88) -> 22759.771 | H89: =(H87+H88) -> 134873.92 | I89: =(I87+I88) -> 964944 | J89: =(J87+J88) -> 103186 | K89: =(K87+K88) -> 16888.833 | ... M89: =(M87+M88) -> -92292 | O89: =(O87+O88) -> 0 | P89: =(P87+P88) -> -11965789 | Q89: =(Q87+Q88) -> -10689111 | R89: =(R87+R88) -> 0 | S89: =SUM(D89,F89:P89) -> 1.1923276e+08 | U89: =(U87+U88) -> 1.1923276e+08 | V89: =(V97) -> 0
C91: Less; Misc Income | S91: =SUM(D91,F91:P91) -> 0
B92: 450 | C92: Forfeited Discounts | D92: 1385477.8 | S92: =SUM(D92,F92:P92) -> 1385477.8
B93: 451 | C93: Misc Service Revenue | D93: 233075.17 | Q93: 0 | S93: =SUM(D93,F93:P93) -> 233075.17
B94: 452 | C94: Return Check Charge | D94: 0 | S94: =SUM(D94,F94:P94) -> 0
B95: 454 | C95: Rent from Electric Prop. | D95: 1330885.1 | Q95: 0 | S95: =SUM(D95,F95:P95) -> 1330885.1
B96: 456 | C96: Other Electric Revenue | D96: 85029.09 | N96: =[3]adjustments!$P$13+[3]adjustments!$Q$13+[3]adjustments!$T$13 -> 181397 | Q96: =SUM(F96:P96) -> 181397 | S96: =SUM(D96,F96:P96) -> 266426.09
C97: Total Misc Income | D97: =SUM(D92:D96) -> 3034467.1 | I97: =SUM(I92:I96) -> 0 | N97: =SUM(N92:N96) -> 181397 | P97: =SUM(P92:P95) -> 0 | Q97: =SUM(Q92:Q96) -> 181397 | S97: =SUM(D97,F97:P97) -> 3215864.1 | U97: =SUM(S91:S96) -> 3215864.1
C99: Less: Other Income
B100: 415 | C100: Net Revenue from Merchandising | D100: 163037.09 | S100: =SUM(D100,F100:P100) -> 163037.09
B101: 416 | C101: Cost of Merchandising | D101: -114546.33 | S101: =SUM(D101,F101:P101) -> -114546.33
B102: 417 | C102: Revenue fron Non-utility Operations | D102: 0 | S102: =SUM(D102,F102:P102) -> 0
B103: 418 | C103: Revenue from Non-operating rentals | D103: 0 | S103: =SUM(D103,F103:P103) -> 0
B104: 419 | C104: Interest Income | D104: 260388.91 | S104: =SUM(D104,F104:P104) -> 260388.91 | V104: =(47984+50722+441865-116105) -> 424466
B105: 421 | C105: Misc. Non-operating Income | D105: =44105.11-6591.22 -> 37513.89 | S105: =SUM(D105,F105:P105) -> 37513.89 | U105: =S105+S101+S100 -> 86004.65
B106: 423 | C106: G&T Capital Credits | D106: 7776965 | O106: =-(D106) -> -7776965 | Q106: =SUM(F106:P106) -> -7776965 | S106: =SUM(D106,F106:P106) -> 0
B107: 424 | C107: Other Capital Credits | D107: 171272.45 | Q107: 0 | S107: =SUM(D107,F107:P107) -> 171272.45 | V107: =('[2]income statement'!$O$27) -> 3729639
C108: Total Other Income | D108: =SUM(D100:D107) -> 8294631 | N108: =SUM(N100:N107) -> 0 | O108: =SUM(O100:O107) -> -7776965 | P108: =SUM(P100:P107) -> 0 | Q108: =SUM(Q100:Q107) -> -7776965 | S108: =SUM(D108,F108:P108) -> 517666.01 | U108: =SUM(S99:S107) -> 517666.01 | V108: =SUM(U97,U108) -> 3733530.1
S109: =SUM(D109,P109,Q109) -> 0 | V109: =(V107-V108) -> -3891.14
C110: Revenue Requirements | S110: =SUM(D110,P110,Q110) -> 0
C111: from Rates | D111: =(D89-D97-D108) -> 1.1859277e+08 | E111: =(E89-E97-E108) -> 0 | F111: =(F89-F97-F108) -> 129303.78 | G111: =(G89-G97-G108) -> 22759.771 | H111: =(H89-H97-H108) -> 134873.92 | I111: =(I89-I97-I108) -> 964944 | J111: =(J89-J97-J108) -> 103186 | K111: =(K89-K97-K108) -> 16888.833 | ... P111: =(P89-P97-P108) -> -11965789 | Q111: =SUM(F111:P111) -> -3093543.2 | S111: =SUM(D111,F111:P111) -> 1.1549923e+08 | U111: =SUM(U87,U88,-U97,-U108) -> 1.1549923e+08 | V111: =S111-U111 -> 0
...

Sheet 1.1TYAdj.
U1: Wages & | V1: Payroll | W1: FAS | Y1: Health
E2: Wages & | F2: Payroll | G2: FAS | I2: Health | U2: Salaries | V2: Tax | W2: 106 | X2: Retirement | Y2: Insurance
E3: Salaries | F3: Tax | G3: 106 | H3: Retirement | I3: Insurance | S3: Amount | T3: Percent | U3: Adj. | V3: Adj. | W3: Adj. | X3: Adj. | Y3: Adj. | AA3: Total
C4: Amount | D4: Percent | E4: Adj. | F4: Adj. | G4: Adj. | H4: Adj. | I4: Adj. | K4: Total | Q4: 580 | R4: Supervision, operations | S4: =C5 -> 234904.52 | T4: =S4/$S$12 -> 0.087074375 | U4: =T4*$U$13 -> 941.74454 | V4: =$V$13*T4 -> 165.76384 | W4: =T4*$W$13 -> 0 | X4: =T4*$X$13 -> 751.53893 | Y4: =T4*$Y$13 -> 0 | AA4: =SUM(U4:Y4) -> 1859.0473
A5: 580 | B5: Supervision, operations | C5: ='1TestYr_adj'!D18 -> 234904.52 | D5: =C5/$C$34 -> 0.014485453 | E5: =(D5*$E$34) -> 1873.0238 | F5: =(D5*$F$34) -> 329.6856 | G5: =(D5*$G$34) -> 0 | H5: =(D5*$H$34) -> 1494.696 | I5: =(D5*$I$34) -> 0 | K5: =SUM(E5:I5) -> 3697.4054 | Q5: 582 | R5: Station | S5: =C6 -> 50572.11 | T5: =S5/$S$12 -> 0.018746063 | U5: =T5*$U$13 -> 202.74624 | V5: =$V$13*T5 -> 35.686955 | W5: =T5*$W$13 -> 0 | X5: =T5*$X$13 -> 161.79727 | Y5: =T5*$Y$13 -> 0 | AA5: =SUM(U5:Y5) -> 400.23046
A6: 582 | B6: Station | C6: ='1TestYr_adj'!D20 -> 50572.11 | D6: =C6/$C$34 -> 0.0031185434 | E6: =(D6*$E$34) -> 403.23944 | F6: =(D6*$F$34) -> 70.977334 | G6: =(D6*$G$34) -> 0 | H6: =(D6*$H$34) -> 321.79002 | I6: =(D6*$I$34) -> 0 | K6: =SUM(E6:I6) -> 796.00679 | Q6: 583 | R6: Overhead line | S6: =C7 -> 1260597.8 | T6: =S6/$S$12 -> 0.46727822 | U6: =T6*$U$13 -> 5053.8028 | V6: =$V$13*T6 -> 889.55943 | W6: =T6*$W$13 -> 0 | X6: =T6*$X$13 -> 4033.0783 | Y6: =T6*$Y$13 -> 0 | AA6: =SUM(U6:Y6) -> 9976.4405
A7: 583 | B7: Overhead line | C7: ='1TestYr_adj'!D21 -> 1260597.8 | D7: =C7/$C$34 -> 0.077735118 | E7: =(D7*$E$34) -> 10051.444 | F7: =(D7*$F$34) -> 1769.2335 | G7: =(D7*$G$34) -> 0 | H7: =(D7*$H$34) -> 8021.1759 | I7: =(D7*$I$34) -> 0 | K7: =SUM(E7:I7) -> 19841.854 | Q7: 584 | R7: Underground Lines | S7: =C8 -> 120534.27 | T7: =S7/$S$12 -> 0.044679626 | U7: =T7*$U$13 -> 483.22821 | V7: =$V$13*T7 -> 85.056785 | W7: =T7*$W$13 -> 0 | X7: =T7*$X$13 -> 385.62986 | Y7: =T7*$Y$13 -> 0 | AA7: =SUM(U7:Y7) -> 953.91485
A8: 584 | B8: Undergound Lines | C8: ='1TestYr_adj'!D22 -> 120534.27 | D8: =C8/$C$34 -> 0.0074327796 | E8: =(D8*$E$34) -> 961.08649 | F8: =(D8*$F$34) -> 169.16837 | G8: =(D8*$G$34) -> 0 | H8: =(D8*$H$34) -> 766.9588 | I8: =(D8*$I$34) -> 0 | K8: =SUM(E8:I8) -> 1897.2137 | Q8: 585 | R8: Street Light Expense | S8: =C9 -> 26089.27 | T8: =S8/$S$12 -> 0.009670767 | U8: =T8*$U$13 -> 104.59325 | V8: =$V$13*T8 -> 18.410278 | W8: =T8*$W$13 -> 0 | X8: =T8*$X$13 -> 83.46839 | Y8: =T8*$Y$13 -> 0 | AA8: =SUM(U8:Y8) -> 206.47192
A9: 585 | B9: Street Lighting | C9: ='1TestYr_adj'!D23 -> 26089.27 | D9: =C9/$C$34 -> 0.0016088022 | E9: =(D9*$E$34) -> 208.0242 | F9: =(D9*$F$34) -> 36.615969 | G9: =(D9*$G$34) -> 0 | H9: =(D9*$H$34) -> 166.00586 | I9: =(D9*$I$34) -> 0 | K9: =SUM(E9:I9) -> 410.64603 | Q9: 586 | R9: Meter | S9: =C10 -> 517709.94 | T9: =S9/$S$12 -> 0.19190465 | U9: =T9*$U$13 -> 2075.5263 | V9: =$V$13*T9 -> 365.32965 | W9: =T9*$W$13 -> 0 | X9: =T9*$X$13 -> 1656.329 | Y9: =T9*$Y$13 -> 0 | AA9: =SUM(U9:Y9) -> 4097.185
A10: 586 | B10: Meter | C10: ='1TestYr_adj'!D24 -> 517709.94 | D10: =C10/$C$34 -> 0.031924729 | E10: =(D10*$E$34) -> 4127.9881 | F10: =(D10*$F$34) -> 726.59953 | G10: =(D10*$G$34) -> 0 | H10: =(D10*$H$34) -> 3294.1851 | I10: =(D10*$I$34) -> 0 | K10: =SUM(E10:I10) -> 8148.7727 | Q10: 587 | R10: Installations | S10: =C11 -> 305880.98 | T10: =S10/$S$12 -> 0.11338392 | U10: =T10*$U$13 -> 1226.2929 | V10: =$V$13*T10 -> 215.84942 | W10: =T10*$W$13 -> 0 | X10: =T10*$X$13 -> 978.61661 | Y10: =T10*$Y$13 -> 0 | AA10: =SUM(U10:Y10) -> 2420.7589
A11: 587 | B11: Installations | C11: ='1TestYr_adj'!D25 -> 305880.98 | D11: =C11/$C$34 -> 0.018862237 | E11: =(D11*$E$34) -> 2438.9585 | F11: =(D11*$F$34) -> 429.30019 | G11: =(D11*$G$34) -> 0 | H11: =(D11*$H$34) -> 1946.3187 | I11: =(D11*$I$34) -> 0 | K11: =SUM(E11:I11) -> 4814.5774 | Q11: 588 | R11: Miscellaneous distribution | S11: =C12 -> 181456.8 | T11: =S11/$S$12 -> 0.067262381 | U11: =T11*$U$13 -> 727.46983 | V11: =$V$13*T11 -> 128.04767 | W11: =T11*$W$13 -> 0 | X11: =T11*$X$13 -> 580.54161 | Y11: =T11*$Y$13 -> 0 | AA11: =SUM(U11:Y11) -> 1436.0591
A12: 588 | B12: Miscellaneous distribution | C12: ='1TestYr_adj'!D26 -> 181456.8 | D12: =C12/$C$34 -> 0.011189585 | E12: =(D12*$E$34) -> 1446.8556 | F12: =(D12*$F$34) -> 254.67239 | G12: =(D12*$G$34) -> 0 | H12: =(D12*$H$34) -> 1154.6085 | I12: =(D12*$I$34) -> 0 | K12: =SUM(E12:I12) -> 2856.1364 | S12: =SUM(S4:S11) -> 2697745.7 | T12: =SUM(T4:T11) -> 1 | U12: =SUM(U4:U11) -> 10815.404 | V12: =SUM(V4:V11) -> 1903.704 | W12: =SUM(W4:W11) -> 0 | X12: =SUM(X4:X11) -> 8631 | Y12: =SUM(Y4:Y11) -> 0 | AA12: =SUM(U12:Y12) -> 21350.108
A13: 590 | B13: Supervision, maintenance | C13: ='1TestYr_adj'!D30 -> 304733.87 | D13: =C13/$C$34 -> 0.0187915 | E13: =(D13*$E$34) -> 2429.8119 | F13: =(D13*$F$34) -> 427.69024 | G13: =(D13*$G$34) -> 0 | H13: =(D13*$H$34) -> 1939.0197 | I13: =(D13*$I$34) -> 0 | K13: =SUM(E13:I13) -> 4796.5218 | U13: =[3]adjustments!$D$21 -> 10815.404 | V13: =[3]adjustments!$E$21 -> 1903.704 | W13: 0 | X13: =[3]adjustments!$H$21 -> 8631 | Y13: 0 | AA13: =SUM(AA4:AA11) -> 21350.108
A14: 592 | B14: Maintenance Station Equip | C14: ='1TestYr_adj'!D31 -> 149.99 | D14: =C14/$C$34 -> 9.2491755e-06 | E14: =(D14*$E$34) -> 1.1959533 | F14: =(D14*$F$34) -> 0.21050912 | G14: =(D14*$G$34) -> 0 | H14: =(D14*$H$34) -> 0.95438543 | I14: =(D14*$I$34) -> 0 | K14: =SUM(E14:I14) -> 2.3608479
A15: 593 | B15: Maintenance | C15: ='1TestYr_adj'!D32 -> 4813064.6 | D15: =C15/$C$34 -> 0.29679898 | E15: =(D15*$E$34) -> 38377.229 | F15: =(D15*$F$34) -> 6755.0769 | G15: =(D15*$G$34) -> 0 | H15: =(D15*$H$34) -> 30625.499 | I15: =(D15*$I$34) -> 0 | K15: =SUM(E15:I15) -> 75757.806 | Q15: 590 | R15: Supervision, maintenance | S15: =C13 -> 304733.87 | T15: =S15/$S$23 -> 0.049348942 | U15: =T15*$U$24 -> 1738.44 | V15: =T15*$V$24 -> 305.99645 | W15: =T15*$W$24 -> 0 | X15: =T15*$X$24 -> 1387.2974 | Y15: =T15*$Y$24 -> 0 | AA15: =SUM(U15:Y15) -> 3431.7339
A16: 594 | B16: Underground | C16: ='1TestYr_adj'!D33 -> 302434.81 | D16: =C16/$C$34 -> 0.018649728 | E16: =(D16*$E$34) -> 2411.4802 | F16: =(D16*$F$34) -> 424.46354 | G16: =(D16*$G$34) -> 0 | H16: =(D16*$H$34) -> 1924.3908 | I16: =(D16*$I$34) -> 0 | K16: =SUM(E16:I16) -> 4760.3346 | Q16: 592 | R16: Maintenance Station Equip | S16: =C14 -> 149.99 | T16: =S16/$S$23 -> 2.4289547e-05 | U16: =T16*$U$24 -> 0.85566012 | V16: =T16*$V$24 -> 0.15061144 | W16: =T16*$W$24 -> 0 | X16: =T16*$X$24 -> 0.68282775 | Y16: =T16*$Y$24 -> 0
A17: 595 | B17: Transformers | C17: ='1TestYr_adj'!D34 -> 16801.08 | D17: =C17/$C$34 -> 0.0010360433 | E17: =(D17*$E$34) -> 133.96432 | F17: =(D17*$F$34) -> 23.580109 | G17: =(D17*$G$34) -> 0 | H17: =(D17*$H$34) -> 106.90517 | I17: =(D17*$I$34) -> 0 | K17: =SUM(E17:I17) -> 264.44959 | Q17: 593 | R17: Maintenance | S17: =C15 -> 4813064.6 | T17: =S17/$S$23 -> 0.77943303 | U17: =T17*$U$24 -> 27457.48 | V17: =T17*$V$24 -> 4833.0062 | W17: =T17*$W$24 -> 0 | X17: =T17*$X$24 -> 21911.421 | Y17: =T17*$Y$24 -> 0 | AA17: =SUM(U17:Y17) -> 54201.907
A18: 596 | B18: Street lights | C18: ='1TestYr_adj'!D35 -> 195353.39 | D18: =C18/$C$34 -> 0.012046522 | E18: =(D18*$E$34) -> 1557.6608 | F18: =(D18*$F$34) -> 274.17608 | G18: =(D18*$G$34) -> 0 | H18: =(D18*$H$34) -> 1243.0324 | I18: =(D18*$I$34) -> 0 | K18: =SUM(E18:I18) -> 3074.8692 | Q18: 594 | R18: Underground | S18: =C16 -> 302434.81 | T18: =S18/$S$23 -> 0.048976629 | U18: =T18*$U$24 -> 1725.3244 | V18: =T18*$V$24 -> 303.68787 | W18: =T18*$W$24 -> 0 | X18: =T18*$X$24 -> 1376.831 | Y18: =T18*$Y$24 -> 0 | AA18: =SUM(U18:Y18) -> 3405.8433
A19: 597 | B19: Meters | C19: ='1TestYr_adj'!D36 -> 193445.15 | D19: =C19/$C$34 -> 0.01192885 | E19: =(D19*$E$34) -> 1542.4453 | F19: =(D19*$F$34) -> 271.49789 | G19: =(D19*$G$34) -> 0 | H19: =(D19*$H$34) -> 1230.8903 | I19: =(D19*$I$34) -> 0 | K19: =SUM(E19:I19) -> 3044.8335 | Q19: 595 | R19: Transformers | S19: =C17 -> 16801.08 | T19: =S19/$S$23 -> 0.0027207856 | U19: =T19*$U$24 -> 95.846484 | V19: =T19*$V$24 -> 16.870691 | W19: =T19*$W$24 -> 0 | X19: =T19*$X$24 -> 76.486724 | Y19: =T19*$Y$24 -> 0 | AA19: =SUM(U19:Y19) -> 189.2039
A20: 598 | B20: Miscellaneous maintenance | C20: ='1TestYr_adj'!D37 -> 349101.35 | D20: =C20/$C$34 -> 0.021527433 | E20: =(D20*$E$34) -> 2783.5784 | F20: =(D20*$F$34) -> 489.95945 | G20: =(D20*$G$34) -> 0 | H20: =(D20*$H$34) -> 2221.3297 | I20: =(D20*$I$34) -> 0 | K20: =SUM(E20:I20) -> 5494.8675 | Q20: 596 | R20: Street lights | S20: =C18 -> 195353.39 | T20: =S20/$S$23 -> 0.031635745 | U20: =T20*$U$24 -> 1114.4483 | V20: =T20*$V$24 -> 196.16278 | W20: =T20*$W$24 -> 0 | X20: =T20*$X$24 -> 889.34407 | Y20: =T20*$Y$24 -> 0 | AA20: =SUM(U20:Y20) -> 2199.9552
A21: 901 | B21: Supervision | C21: ='1TestYr_adj'!D40 -> 140605.04 | D21: =C21/$C$34 -> 0.0086704493 | E21: =(D21*$E$34) -> 1121.1219 | F21: =(D21*$F$34) -> 197.33744 | G21: =(D21*$G$34) -> 0 | H21: =(D21*$H$34) -> 894.66898 | I21: =(D21*$I$34) -> 0 | K21: =SUM(E21:I21) -> 2213.1283 | Q21: 597 | R21: Meters | S21: =C19 -> 193445.15 | T21: =S21/$S$23 -> 0.031326723 | U21: =T21*$U$24 -> 1103.5622 | V21: =T21*$V$24 -> 194.24664 | W21: =T21*$W$24 -> 0 | X21: =T21*$X$24 -> 880.65683 | Y21: =T21*$Y$24 -> 0 | AA21: =SUM(U21:Y21) -> 2178.4657
A22: 902 | B22: Meter reading | C22: ='1TestYr_adj'!D41 -> 100208.98 | D22: =C22/$C$34 -> 0.0061794149 | E22: =(D22*$E$34) -> 799.0217 | F22: =(D22*$F$34) -> 140.64207 | G22: =(D22*$G$34) -> 0 | H22: =(D22*$H$34) -> 637.62911 | I22: =(D22*$I$34) -> 0 | K22: =SUM(E22:I22) -> 1577.2929 | Q22: 598 | R22: Miscellaneous maintenance | S22: =C20 -> 349101.35 | T22: =S22/$S$23 -> 0.056533861 | U22: =T22*$U$24 -> 1991.5468 | V22: =T22*$V$24 -> 350.54776 | W22: =T22*$W$24 -> 0 | X22: =T22*$X$24 -> 1589.2799 | Y22: =T22*$Y$24 -> 0 | AA22: =SUM(U22:Y22) -> 3931.3744
A23: 903 | B23: Consumer records | C23: ='1TestYr_adj'!D42 -> 2281826.7 | D23: =C23/$C$34 -> 0.14070948 | E23: =(D23*$E$34) -> 18194.268 | F23: =(D23*$F$34) -> 3202.5157 | G23: =(D23*$G$34) -> 0 | H23: =(D23*$H$34) -> 14519.249 | I23: =(D23*$I$34) -> 0 | K23: =SUM(E23:I23) -> 35916.032 | S23: =SUM(S15:S22) -> 6175084.2 | T23: =SUM(T15:T22) -> 1 | U23: =SUM(U15:U22) -> 35227.504 | V23: =SUM(V15:V22) -> 6200.669 | W23: =SUM(W15:W22) -> 0 | X23: =SUM(X15:X22) -> 28112 | Y23: =SUM(Y15:Y22) -> 0 | AA23: =SUM(U23:Y23) -> 69540.173
A24: 907 | B24: Supervision, Customer service | C24: ='1TestYr_adj'!D46 -> 0 | D24: =C24/$C$34 -> 0 | E24: =(D24*$E$34) -> 0 | F24: =(D24*$F$34) -> 0 | G24: =(D24*$G$34) -> 0 | H24: =(D24*$H$34) -> 0 | I24: =(D24*$I$34) -> 0 | K24: =SUM(E24:I24) -> 0 | U24: =[3]adjustments!$D$22 -> 35227.504 | V24: =[3]adjustments!$E$22 -> 6200.669 | W24: 0 | X24: =[3]adjustments!$H$22 -> 28112 | Y24: 0
A25: 908 | B25: Consumer accounting | C25: ='1TestYr_adj'!D47 -> 944348.21 | D25: =C25/$C$34 -> 0.058233498 | E25: =(D25*$E$34) -> 7529.8113 | F25: =(D25*$F$34) -> 1325.3811 | G25: =(D25*$G$34) -> 0 | H25: =(D25*$H$34) -> 6008.8817 | I25: =(D25*$I$34) -> 0 | K25: =SUM(E25:I25) -> 14864.074
A26: 909 | B26: Consumer information | C26: ='1TestYr_adj'!D48 -> 0 | D26: =C26/$C$34 -> 0 | E26: =(D26*$E$34) -> 0 | F26: =(D26*$F$34) -> 0 | G26: =(D26*$G$34) -> 0 | H26: =(D26*$H$34) -> 0 | I26: =(D26*$I$34) -> 0 | K26: =SUM(E26:I26) -> 0 | Q26: 901 | R26: Supervision | S26: =C21 -> 140605.04 | T26: =S26/$S$29 -> 0.055737244 | U26: =T26*$U$30 -> 1185.2476 | V26: =T26*$V$30 -> 208.62472 | W26: =T26*$W$30 -> 0 | X26: =T26*$X$30 -> 945.86103 | Y26: =T26*$Y$30 -> 0 | AA26: =SUM(U26:Y26) -> 2339.7334
A27: 910 | B27: Misc customer information | C27: ='1TestYr_adj'!D49 -> 0 | D27: =C27/$C$34 -> 0 | E27: =(D27*$E$34) -> 0 | F27: =(D27*$F$34) -> 0 | G27: =(D27*$G$34) -> 0 | H27: =(D27*$H$34) -> 0 | I27: =(D27*$I$34) -> 0 | K27: =SUM(E27:I27) -> 0 | Q27: 902 | R27: Meter reading | S27: =C22 -> 100208.98 | T27: =S27/$S$29 -> 0.039723842 | U27: =T27*$U$30 -> 844.72401 | V27: =T27*$V$30 -> 148.68649 | W27: =T27*$W$30 -> 0 | X27: =T27*$X$30 -> 674.1136 | Y27: =T27*$Y$30 -> 0 | AA27: =SUM(U27:Y27) -> 1667.5241
A28: 912 | B28: Key Accounts Expenses | C28: ='1TestYr_adj'!D50 -> -11863.33 | D28: =C28/$C$34 -> -0.00073155558 | E28: =(D28*$E$34) -> -94.5929 | F28: =(D28*$F$34) -> -16.650038 | G28: =(D28*$G$34) -> 0 | H28: =(D28*$H$34) -> -75.486294 | I28: =(D28*$I$34) -> 0 | K28: =SUM(E28:I28) -> -186.72923 | Q28: 903 | R28: Consumer records | S28: =C23 -> 2281826.7 | T28: =S28/$S$29 -> 0.90453891 | U28: =T28*$U$30 -> 19234.941 | V28: =T28*$V$30 -> 3385.6926 | W28: =T28*$W$30 -> 0 | X28: =T28*$X$30 -> 15350.025 | Y28: =T28*$Y$30 -> 0 | AA28: =SUM(U28:Y28) -> 37970.659
A29: 920 | B29: Administrative | C29: ='1TestYr_adj'!D54 -> 2590524.3 | D29: =C29/$C$34 -> 0.15974541 | E29: =(D29*$E$34) -> 20655.685 | F29: =(D29*$F$34) -> 3635.769 | G29: =(D29*$G$34) -> 0 | H29: =(D29*$H$34) -> 16483.49 | I29: =(D29*$I$34) -> 0 | K29: =SUM(E29:I29) -> 40774.944 | S29: =SUM(S26:S28) -> 2522640.7 | T29: =SUM(T26:T28) -> 1 | U29: =SUM(U26:U28) -> 21264.912 | V29: =SUM(V26:V28) -> 3743.0038 | W29: =SUM(W26:W28) -> 0 | X29: =SUM(X26:X28) -> 16970 | Y29: =SUM(Y26:Y28) -> 0 | AA29: =SUM(U29:Y29) -> 41977.916
A30: 926 | B30: Emp Pensions & Benefits | C30: ='1TestYr_adj'!D59 -> 0 | D30: =C30/$C$34 -> 0 | E30: =(D30*$E$34) -> 0 | F30: =(D30*$F$34) -> 0 | G30: =(D30*$G$34) -> 0 | H30: =(D30*$H$34) -> 0 | I30: =(D30*$I$34) -> 0 | K30: =SUM(E30:I30) -> 0 | U30: =[3]adjustments!$D$23 -> 21264.912 | V30: =[3]adjustments!$E$23 -> 3743.0038 | W30: 0 | X30: =[3]adjustments!$H$23 -> 16970 | Y30: 0
A31: 930 | B31: Miscellaneous | C31: ='1TestYr_adj'!D62 -> 889238.28 | D31: =C31/$C$34 -> 0.054835129 | E31: =(D31*$E$34) -> 7090.3893 | F31: =(D31*$F$34) -> 1248.035 | G31: =(D31*$G$34) -> 0 | H31: =(D31*$H$34) -> 5658.2176 | I31: =(D31*$I$34) -> 0 | K31: =SUM(E31:I31) -> 13996.642
A32: 935 | B32: Maintenance general plant | C32: ='1TestYr_adj'!D64 -> 408862.49 | D32: =C32/$C$34 -> 0.02521262 | E32: =(D32*$E$34) -> 3260.0871 | F32: =(D32*$F$34) -> 573.83347 | G32: =(D32*$G$34) -> 0 | H32: =(D32*$H$34) -> 2601.5894 | I32: =(D32*$I$34) -> 0 | K32: =SUM(E32:I32) -> 6435.51 | Q32: 907 | R32: Supervision, Customer service | S32: =C24 -> 0 | T32: =S32/$S$37 -> 0 | U32: =T32*$U$38 -> 0 | V32: =T32*$V$38 -> 0 | W32: =T32*$W$38 -> 0 | X32: =T32*$X$38 -> 0 | Y32: =T32*$Y$38 -> 0 | AA32: =SUM(U32:Y32) -> 0
Q33: 908 | R33: Consumer accounting | S33: =C25 -> 944348.21 | T33: =S33/$S$37 -> 1.0127223 | U33: =T33*$U$38 -> 16145.418 | V33: =T33*$V$38 -> 2841.8816 | W33: =T33*$W$38 -> 0 | X33: =T33*$X$38 -> 12883.853 | Y33: =T33*$Y$38 -> 0 | AA33: =SUM(U33:Y33) -> 31871.152
B34: Total | C34: =SUM(C5:C32) -> 16216581 | D34: =SUM(D5:D32) -> 1 | E34: =U49 -> 129303.78 | F34: =V49 -> 22759.771 | G34: =W49 -> 0 | H34: =X49 -> 103186 | I34: =Y49 -> 0 | J34: =SUM(D34:H34) -> 255250.55 | K34: =SUM(E34:I34) -> 255249.55 | Q34: 909 | R34: Consumer information | S34: =C26 -> 0 | T34: =S34/$S$37 -> 0 | U34: =T34*$U$38 -> 0 | V34: =T34*$V$38 -> 0 | W34: =T34*$W$38 -> 0 | X34: =T34*$X$38 -> 0 | Y34: =T34*$Y$38 -> 0 | AA34: =SUM(U34:Y34) -> 0
Q35: 910 | R35: Misc Customer Info | S35: =C27 -> 0 | T35: =S35/$S$37 -> 0 | U35: =T35*$U$38 -> 0 | V35: =T35*$V$38 -> 0 | W35: =T35*$W$38 -> 0 | X35: =T35*$X$38 -> 0 | Y35: =T35*$Y$38 -> 0 | AA35: =SUM(U35:Y35) -> 0
D36: =SUM(D5:D32) -> 1 | E36: =SUM(E5:E32) -> 129303.78 | F36: =SUM(F5:F32) -> 22759.771 | G36: =SUM(G5:G32) -> 0 | H36: =SUM(H5:H32) -> 103186 | I36: =SUM(I5:I32) -> 0 | K36: =SUM(K5:K32) -> 255249.55 | Q36: 912 | R36: Key Accounts expenses | S36: =C28 -> -11863.33 | T36: =S36/$S$37 -> -0.012722276 | U36: =T36*$U$38 -> -202.82605 | V36: =T36*$V$38 -> -35.701003 | W36: =T36*$W$38 -> 0 | X36: =T36*$X$38 -> -161.8528 | Y36: =T36*$Y$38 -> 0 | AA36: =SUM(U36:Y36) -> -400.37985
S37: =SUM(S32:S36) -> 932484.88 | T37: =SUM(T32:T36) -> 1 | U37: =T37*$U$38 -> 15942.592 | V37: =T37*$V$38 -> 2806.1805 | W37: =T37*$W$38 -> 0 | X37: =T37*$X$38 -> 12722 | Y37: =T37*$Y$38 -> 0 | AA37: =SUM(U37:Y37) -> 31470.772
U38: =[3]adjustments!$D$24 -> 15942.592 | V38: =[3]adjustments!$E$24 -> 2806.1805 | W38: 0 | X38: =[3]adjustments!$H$24 -> 12722 | Y38: 0 | AA38: =SUM(U38:Y38) -> 31470.772
Q41: 920 | R41: Administrative | S41: =C29 -> 2590524.3 | T41: =S41/$S$45 -> 0.66618002 | U41: =T41*$U$46 -> 30679.832 | V41: =T41*$V$46 -> 5400.1977 | W41: =T41*$W$46 -> 0 | X41: =T41*$X$46 -> 24482.782 | Y41: =T41*$Y$46 -> 0 | AA41: =SUM(U41:Y41) -> 60562.812
Q42: 926 | R42: Employee Benefits | S42: =C30 -> 0 | T42: =S42/$S$45 -> 0 | U42: =T42*$U$46 -> 0 | V42: =T42*$V$46 -> 0 | W42: =T42*$W$46 -> 0 | X42: =T42*$X$46 -> 0 | Y42: =T42*$Y$46 -> 0 | AA42: =SUM(U42:Y42) -> 0
Q43: 930 | R43: Miscellaneous | S43: =C31 -> 889238.28 | T43: =S43/$S$45 -> 0.22867678 | U43: =T43*$U$46 -> 10531.336 | V43: =T43*$V$46 -> 1853.7029 | W43: =T43*$W$46 -> 0 | X43: =T43*$X$46 -> 8404.1005 | Y43: =T43*$Y$46 -> 0 | AA43: =SUM(U43:Y43) -> 20789.139
Q44: 935 | R44: Maintenance general plant | S44: =C32 -> 408862.49 | T44: =S44/$S$45 -> 0.1051432 | U44: =T44*$U$46 -> 4842.1983 | V44: =T44*$V$46 -> 852.31328 | W44: =T44*$W$46 -> 0 | X44: =T44*$X$46 -> 3864.1178 | Y44: =T44*$Y$46 -> 0 | AA44: =SUM(U44:Y44) -> 9558.6294
S45: =SUM(S41:S44) -> 3888625.1 | T45: =SUM(T41:T44) -> 1 | U45: =SUM(U41:U44) -> 46053.366 | V45: =SUM(V41:V44) -> 8106.2139 | W45: =SUM(W41:W44) -> 0 | X45: =SUM(X41:X44) -> 36751 | Y45: =SUM(Y41:Y44) -> 0 | AA45: =SUM(U45:Y45) -> 90910.58
U46: =[3]adjustments!$D$26 -> 46053.366 | V46: =[3]adjustments!$E$26 -> 8106.2139 | W46: 0 | X46: =[3]adjustments!$H$26 -> 36751 | Y46: 0 | AA46: =SUM(U46:Y46) -> 90910.58
R49: Total | S49: =SUM(S45+S29+S23+S12+S37) -> 16216581 | U49: =SUM(U45+U29+U23+U12+U37) -> 129303.78 | V49: =SUM(V45+V29+V23+V12+V37) -> 22759.771 | W49: =SUM(W45+W29+W23+W12+W37) -> 0 | X49: =SUM(X45+X29+X23+X12+X37) -> 103186 | Y49: =SUM(Y45+Y29+Y23+Y12+Y37) -> 0 | AA49: =SUM(AA45+AA29+AA23+AA12+AA37) -> 255249.55
U50: =[5]adjustments!$D$28 -> 129303.78 | V50: =[5]adjustments!$E$28 -> 22759.771 | W50: 0 | X50: =[5]adjustments!$H$28 -> 103186 | Y50: 0 | AA50: =SUM(U50:Y50) -> 255249.55

Sheet 2 Functionalization2
C1: Expenses | G1: FUNCTIONALIZATION | R1: FOOTNOTES
M2: Consumer
A3: Acct | B3: Description | C3: Actual | D3: Adjust | E3: Adjusted | G3: Puchased | J3: Trans- | M3: Services & | N3: Security | O3: Street | Q3: Alloc.
A4: No. | C4: Test Year | D4: ments | E4: Test Year | G4: Power | H4: Stations | I4: Lines | J4: formers | K4: Services | L4: Meters | M4: Accounting | N4: Lighting | O4: Lighting | P4: Total | Q4: Basis
A6: 555 | B6: ='1TestYr_adj'!C10 -> Purchased Power | C6: =('1TestYr'!D10) -> 0 | D6: =('1TestYr'!E10) -> 0
B7: ='1TestYr_adj'!C11 -> Demand Charges | C7: 14211359 | D7: 1465107 | E7: ='1TestYr_adj'!S11 -> 18577420 | G7: =(E7) -> 18577420 | P7: =SUM(G7:N7) -> 18577420 | S7: 1 | T7: Line Expenses are Allocated between Lines and Services Based on Plant Investment.
B8: ='1TestYr_adj'!C12 -> Metering Point & Substations Charges | E8: ='1TestYr_adj'!S12 -> 1545492 | G8: =(E8) -> 1545492 | P8: =SUM(G8:N8) -> 1545492 | W8: $$$ | X8: %
B9: ='1TestYr_adj'!C13 -> Energy Charges | C9: 2758291 | D9: =-(C9) -> -2758291 | E9: ='1TestYr_adj'!S13 -> 63975166 | G9: =(E9) -> 63975166 | P9: =SUM(G9:N9) -> 63975166 | T9: Poles and Conductor | W9: =('2.22Rate Base'!H18) -> 1.2268778e+08 | X9: =(W9/$W$11) -> 0.80522155
B10: ='1TestYr_adj'!C14 -> Renewable Resource Energy | C10: =SUM(C7:C9) -> 16969650 | D10: =SUM(D7:D9) -> -1293184 | E10: ='1TestYr_adj'!S14 -> 6455.25 | G10: =(E10) -> 6455.25 | P10: =SUM(G10:N10) -> 6455.25 | T10: Services | W10: =('2.22Rate Base'!J18) -> 29677466 | X10: =(W10/$W$11) -> 0.19477845
B11: ='1TestYr_adj'!C15 -> By Thru and Metering Point Charges | C11: =SUM(C8:C10) -> 19727941 | D11: =SUM(D8:D10) -> -4051475 | E11: ='1TestYr_adj'!S15 -> 0 | G11: =(E11) -> 0 | P11: =SUM(G11:N11) -> 0 | T11: Total | W11: =SUM(W9:W10) -> 1.5236524e+08 | X11: =SUM(X9:X10) -> 1
B12: ='1TestYr_adj'!C16 -> Total Purchased Power | E12: =SUM(E7:E11) -> 84104533 | G12: =SUM(G7:G11) -> 84104533 | P12: =SUM(G12:O12) -> 84104533 | Q12: DA | AC12: Miscell.
C13: 76777.74 | D13: =(#REF!) -> #REF! | P13: =SUM(G13:O13) -> 0 | S13: 2 | T13: Allocation of Dist. Oper. Supervision & Miscellaneous Expenses | Y13: Actual | Z13: % | AB13: Superv | AC13: Exp. | AD13: Rents
A14: 580 | B14: ='1TestYr_adj'!C18 -> Operations Supv & Eng | C14: 0 | D14: =(#REF!) -> #REF! | E14: ='1TestYr_adj'!S18 -> 236763.57 | H14: =AB14 -> 5248.4067 | I14: =AB15 -> 115416.26 | J14: =AB16 -> 0 | K14: =AB17 -> 27918.53 | L14: =AB18 -> 53728.277 | M14: =AB19 -> 0 | N14: =AB20 -> 31744.529 | O14: =AB21 -> 2707.5616 | P14: =SUM(H14:O14) -> 236763.57 | Q14: 2 | T14: Stations | Y14: =E16 -> 50972.34 | Z14: =Y14/$Y$23 -> 0.02216729 | AB14: =(Z14*$AB$23) -> 5248.4067 | AC14: =(Z14*$AC$23) -> 4436.1519 | AD14: =$AD$24*Z14 -> 0
A15: 581 | B15: ='1TestYr_adj'!C19 -> Load Dispatching | C15: 189903.91 | D15: =(#REF!) -> #REF! | E15: ='1TestYr_adj'!S19 -> 0 | H15: =(E15) -> 0 | P15: =SUM(H15:O15) -> 0 | Q15: DA | T15: Lines | Y15: =I17+I18 -> 1120918.7 | Z15: =Y15/$Y$23 -> 0.48747476 | AB15: =(Z15*$AB$23) -> 115416.26 | AC15: =(Z15*$AC$23) -> 97554.193 | AD15: =$AD$24*Z15 -> 0
A16: =('1TestYr'!B20) -> 582 | B16: ='1TestYr_adj'!C20 -> Station Expense | C16: 0 | D16: =(#REF!) -> #REF! | E16: ='1TestYr_adj'!S20 -> 50972.34 | H16: =(E16) -> 50972.34 | P16: =SUM(H16:O16) -> 50972.34 | Q16: DA | T16: Transformers | Y16: =0 -> 0 | Z16: =Y16/$Y$23 -> 0 | AB16: =(Z16*$AB$23) -> 0 | AC16: =(Z16*$AC$23) -> 0 | AD16: =$AD$24*Z16 -> 0
A17: =('1TestYr'!B21) -> 583 | B17: ='1TestYr_adj'!C21 -> Overhead Line Exp. | C17: =(354789.72+70911.29) -> 425701.01 | D17: =(#REF!) -> #REF! | E17: ='1TestYr_adj'!S21 -> 1270574.3 | I17: =(X9*E17) -> 1023093.8 | K17: =E17*X10 -> 247480.49 | P17: =SUM(H17:O17) -> 1270574.3 | Q17: 1 | T17: Services | Y17: =K17+K18 -> 271143.77 | Z17: =Y17/$Y$23 -> 0.11791734 | AB17: =(Z17*$AB$23) -> 27918.53 | AC17: =(Z17*$AC$23) -> 23597.797 | AD17: =$AD$24*Z17 -> 0
A18: =('1TestYr'!B22) -> 584 | B18: ='1TestYr_adj'!C22 -> Underground Line Exp | E18: ='1TestYr_adj'!S22 -> 121488.18 | I18: =(X9*E18) -> 97824.904 | K18: =E18*X10 -> 23663.281 | P18: =SUM(H18:O18) -> 121488.18 | Q18: 1 | T18: Meters | Y18: =L20 -> 521807.12 | Z18: =Y18/$Y$23 -> 0.22692798 | AB18: =(Z18*$AB$23) -> 53728.277 | AC18: =(Z18*$AC$23) -> 45413.173 | AD18: =$AD$24*Z18 -> 0
A19: =('1TestYr'!B23) -> 585 | B19: ='1TestYr_adj'!C23 -> Street Lights | C19: 42228.91 | D19: =(#REF!) -> #REF! | E19: ='1TestYr_adj'!S23 -> 26295.742 | O19: =E19 -> 26295.742 | P19: =SUM(H19:O19) -> 26295.742 | Q19: DA | T19: Cunsumer Services & Acct | Y19: 0 | Z19: =Y19/$Y$23 -> 0 | AB19: =(Z19*$AB$23) -> 0 | AC19: =(Z19*$AC$23) -> 0 | AD19: =$AD$24*Z19 -> 0 | AG19: =SUM(AD17:AD22) -> 0
A20: =('1TestYr'!B24) -> 586 | B20: ='1TestYr_adj'!C24 -> Meter Expense | C20: =(101430.3+63260.76) -> 164691.06 | D20: =(#REF!) -> #REF! | E20: ='1TestYr_adj'!S24 -> 521807.12 | L20: =(E20) -> 521807.12 | P20: =SUM(H20:O20) -> 521807.12 | Q20: DA | T20: Security Lighting | Y20: =N21 -> 308301.74 | Z20: =Y20/$Y$23 -> 0.13407692 | AB20: =(Z20*$AB$23) -> 31744.529 | AC20: =(Z20*$AC$23) -> 26831.677 | AD20: =$AD$24*Z20 -> 0
A21: =('1TestYr'!B25) -> 587 | B21: ='1TestYr_adj'!C25 -> Consumer Installations | C21: 0 | D21: =(C21/$C$22)*(103795) -> 0 | E21: ='1TestYr_adj'!S25 -> 308301.74 | M21: 0 | N21: =(E21) -> 308301.74 | O21: 0 | P21: =SUM(H21:O21) -> 308301.74 | Q21: DA | T21: Street Lighting | Y21: =O19 -> 26295.742 | Z21: =Y21/$Y$23 -> 0.011435719 | AB21: =(Z21*$AB$23) -> 2707.5616 | AC21: =(Z21*$AC$23) -> 2288.5335 | AD21: =$AD$24*Z21 -> 0
A22: =('1TestYr'!B26) -> 588 | B22: ='1TestYr_adj'!C26 -> Misc. Distribution Exp | C22: =SUM(C13:C21) -> 899302.63 | D22: =SUM(D13:D21) -> #REF! | E22: ='1TestYr_adj'!S26 -> 200121.52 | H22: =AC14 -> 4436.1519 | I22: =AC15 -> 97554.193 | J22: =AC16 -> 0 | K22: =AC17 -> 23597.797 | L22: =AC18 -> 45413.173 | M22: =AC19 -> 0 | N22: =AC20 -> 26831.677 | O22: =AC21 -> 2288.5335 | P22: =SUM(H22:O22) -> 200121.52 | Q22: 2
A23: =('1TestYr'!B27) -> 589 | B23: ='1TestYr_adj'!C27 -> Rents | E23: ='1TestYr_adj'!S27 -> 0 | P23: =SUM(H23:O23) -> 0 | Q23: DA | Y23: =SUM(Y13:Y22) -> 2299439.4 | Z23: =SUM(Z14:Z22) -> 1 | AB23: =(E14) -> 236763.57 | AC23: =(E22) -> 200121.52 | AD23: 0 | AE23: =SUM(Y23+AB23+AC23) -> 2736324.5
B24: ='1TestYr_adj'!C28 -> Total Dist. Operations | E24: =SUM(E14:E23) -> 2736324.5 | H24: =SUM(H14:H23) -> 60656.899 | I24: =SUM(I14:I23) -> 1333889.1 | J24: =SUM(J14:J23) -> 0 | K24: =SUM(K14:K23) -> 322660.1 | L24: =SUM(L14:L23) -> 620948.57 | M24: =SUM(M14:M23) -> 0 | N24: =SUM(N14:N23) -> 366877.94 | O24: =SUM(O14:O23) -> 31291.837 | P24: =SUM(P14:P23) -> 2736324.5 | AB24: =SUM(AB14:AB22) -> 236763.57 | AC24: =SUM(AC14:AC22) -> 200121.52 | AD24: =E23 -> 0
C25: 75345.47 | D25: =(#REF!) -> #REF! | S25: 3 | T25: Allocation of Dist. Maint. Supervision & Miscellaneous Expenses | Y25: Actual | Z25: % | AB25: Superv | AC25: Misc. Exp.
A26: 590 | B26: ='1TestYr_adj'!C30 -> Maint Supv & Eng | C26: 3408.56 | D26: =(#REF!) -> #REF! | E26: ='1TestYr_adj'!S30 -> 308165.6 | H26: =(AB26) -> 8.3716129 | I26: =+AB27 -> 229905.97 | J26: =+AB28 -> 937.74343 | K26: =+AB29 -> 55612.931 | L26: =+AB30 -> 10797.039 | N26: =+AB31 -> 0 | O26: =+AB33 -> 10903.547 | P26: =SUM(G26:O26) -> 308165.6 | Q26: 3 | T26: Stations | Y26: =H27 -> 151.6791 | Z26: =(Y26/$Y$34) -> 2.7165955e-05 | AB26: =($AB$34*Z26) -> 8.3716129 | AC26: =Z26*$AC$35 -> 9.6315843
A27: 592 | B27: ='1TestYr_adj'!C31 -> Maint of Station Equip | C27: =(367239.65+75667.75+334721.48) -> 777628.88 | D27: =(#REF!)+(417787) -> #REF! | E27: ='1TestYr_adj'!S31 -> 151.6791 | H27: =E27 -> 151.6791 | P27: =SUM(G27:O27) -> 151.6791 | Q27: DA | T27: Lines | Y27: =I28+I29 -> 4165497.3 | Z27: =(Y27/$Y$34) -> 0.74604683 | AB27: =($AB$34*Z27) -> 229905.97 | AC27: =Z27*$AC$35 -> 264508.02
A28: 593 | B28: ='1TestYr_adj'!C32 -> Maint. Overhead Lines | C28: 0 | D28: 0 | E28: ='1TestYr_adj'!S32 -> 4867266.5 | I28: =E28*X9 -> 3919227.8 | K28: =E28*X10 -> 948038.64 | P28: =SUM(G28:O28) -> 4867266.5 | Q28: 1 | T28: Transformers | Y28: =J30 -> 16990.284 | Z28: =(Y28/$Y$34) -> 0.0030429854 | AB28: =($AB$34*Z28) -> 937.74343 | AC28: =Z28*$AC$35 -> 1078.8787
A29: 594 | B29: ='1TestYr_adj'!C33 -> Maint of Underground Lines | C29: 52902.09 | D29: =(#REF!) -> #REF! | E29: ='1TestYr_adj'!S33 -> 305840.65 | I29: =E29*X9 -> 246269.48 | K29: =E29*X10 -> 59571.17 | P29: =SUM(G29:O29) -> 305840.65 | Q29: 1 | T29: Services | Y29: =K28+K29 -> 1007609.8 | Z29: =(Y29/$Y$34) -> 0.18046443 | AB29: =($AB$34*Z29) -> 55612.931 | AC29: =Z29*$AC$35 -> 63982.967
A30: 595 | B30: ='1TestYr_adj'!C34 -> Maint Line Transformers | C30: 0 | D30: 0 | E30: ='1TestYr_adj'!S34 -> 16990.284 | J30: =(E30) -> 16990.284 | P30: =SUM(G30:O30) -> 16990.284 | Q30: DA | T30: Meters | Y30: =L32 -> 195623.62 | Z30: =(Y30/$Y$34) -> 0.035036484 | AB30: =($AB$34*Z30) -> 10797.039 | AC30: =Z30*$AC$35 -> 12422.05
A31: 596 | B31: ='1TestYr_adj'!C35 -> Maint of Street Lights | C31: 1001 | D31: =(#REF!) -> #REF! | E31: ='1TestYr_adj'!S35 -> 197553.35 | O31: =E31 -> 197553.35 | P31: =SUM(G31:O31) -> 197553.35 | Q31: DA | T31: Cunsumer Services & Acct | Y31: 0 | Z31: =(Y31/$Y$34) -> 0 | AB31: =($AB$34*Z31) -> 0 | AC31: =Z31*$AC$35 -> 0
A32: 597 | B32: ='1TestYr_adj'!C36 -> Maintenance of Meters | C32: 72405.6 | D32: =(#REF!) -> #REF! | E32: ='1TestYr_adj'!S36 -> 195623.62 | L32: =E32 -> 195623.62 | P32: =SUM(G32:O32) -> 195623.62 | Q32: DA | T32: Security Lighting | Y32: =0 -> 0 | Z32: =(Y32/$Y$34) -> 0 | AB32: 0 | AC32: =Z32*$AC$35 -> 0
A33: 598 | B33: ='1TestYr_adj'!C37 -> Maint Misc Distrib Plant | E33: ='1TestYr_adj'!S37 -> 354546.14 | H33: =AC26 -> 9.6315843 | I33: =AC27 -> 264508.02 | J33: =AC28 -> 1078.8787 | K33: =AC29 -> 63982.967 | L33: =AC30 -> 12422.05 | M33: =AC31 -> 0 | N33: =AC32 -> 0 | O33: =AC33 -> 12544.587 | P33: =SUM(G33:O33) -> 354546.14 | Q33: 3 | T33: Street Lighting | Y33: =O31 -> 197553.35 | Z33: =(Y33/$Y$34) -> 0.035382101 | AB33: =($AB$34*Z33) -> 10903.547 | AC33: =Z33*$AC$35 -> 12544.587
B34: ='1TestYr_adj'!C38 -> Total Dist. Maint. | E34: =SUM(E26:E33) -> 6246137.8 | G34: =SUM(G26:G33) -> 0 | H34: =SUM(H26:H33) -> 169.6823 | I34: =SUM(I26:I33) -> 4659911.3 | J34: =SUM(J26:J33) -> 19006.906 | K34: =SUM(K26:K33) -> 1127205.7 | L34: =SUM(L26:L33) -> 218842.7 | M34: =SUM(M26:M33) -> 0 | N34: =SUM(N26:N33) -> 0 | ... P34: =SUM(P26:P33) -> 6246137.8 | Y34: =SUM(Y26:Y33) -> 5583426 | Z34: =SUM(Z26:Z33) -> 1 | AB34: =(E26) -> 308165.6 | AC34: =SUM(AC26:AC33) -> 354546.14 | AE34: =SUM(AC34,AB34,Y34) -> 6246137.8
A35: =('1TestYr'!B38) | C35: 0 | P35: =SUM(G35:O35) -> 0 | AB35: =E26 -> 308165.6 | AC35: =E33 -> 354546.14
A36: 901 | B36: ='1TestYr_adj'!C40 -> Supervision | C36: 57203.53 | E36: ='1TestYr_adj'!S40 -> 143333.65 | M36: =(E36) -> 143333.65 | P36: =SUM(G36:O36) -> 143333.65 | Q36: DA | S36: 4 | T36: General Plant Allocation Comes From the Rate Base Schedule Line General Plant Percent
A37: 902 | B37: ='1TestYr_adj'!C41 -> Meter Reading Expense | C37: =(467413.25+813.58) -> 468226.83 | D37: 35476 | E37: ='1TestYr_adj'!S41 -> 101876.5 | M37: =(E37) -> 101876.5 | P37: =SUM(G37:O37) -> 101876.5 | Q37: DA
A38: 903 | B38: ='1TestYr_adj'!C42 -> Cons Recds & Collections | C38: 84000 | E38: ='1TestYr_adj'!S42 -> 2319797.3 | M38: =(E38) -> 2319797.3 | P38: =SUM(G38:O38) -> 2319797.3 | Q38: DA | S38: 5 | T38: Rate Base Allocation Comes from the Rate Base Schedule Line Rate Base Percent.
A39: 904 | B39: ='1TestYr_adj'!C43 -> Uncollectible Accounts | C39: =SUM(C36:C38) -> 609430.36 | D39: 35476 | E39: ='1TestYr_adj'!S43 -> 340357.45 | M39: =(E39) -> 340357.45 | P39: =SUM(G39:O39) -> 340357.45 | Q39: DA
B40: ='1TestYr_adj'!C44 -> Total Consumer Accts | E40: =SUM(E36:E39) -> 2905364.9 | M40: =SUM(M36:M39) -> 2905364.9 | P40: =SUM(G40:O40) -> 2905364.9 | S40: 6 | T40: Depreciation Expense Allocation Comes from the Distribution Plant Percent in Rate Base
A41: =('1TestYr'!B44) | C41: 0 | P41: =SUM(G41:O41) -> 0
A42: ='1TestYr'!B46 -> 907 | B42: ='1TestYr_adj'!C46 -> Customer Information | C42: 84141.05 | D42: 8826 | E42: ='1TestYr_adj'!S46 -> 0 | M42: =(E42) -> 0 | P42: =SUM(G42:O42) -> 0 | Q42: DA
A43: ='1TestYr'!B47 -> 908 | B43: ='1TestYr_adj'!C47 -> Customer Accounting | C43: 960 | E43: ='1TestYr_adj'!S47 -> 976219.36 | M43: =(E43) -> 976219.36 | P43: =SUM(G43:O43) -> 976219.36 | Q43: DA
A44: ='1TestYr'!B48 -> 909 | B44: ='1TestYr_adj'!C48 -> Consumer Information | C44: 0 | E44: ='1TestYr_adj'!S48 -> 321.18822 | M44: =(E44) -> 321.18822 | P44: =SUM(G44:O44) -> 321.18822 | Q44: DA
A45: ='1TestYr'!B49 -> 910 | B45: ='1TestYr_adj'!C49 -> Mis. Customer Information | E45: ='1TestYr_adj'!S49 -> 0 | M45: =(E45) -> 0 | P45: =SUM(G45:O45) -> 0 | Q45: DA
A46: ='1TestYr'!B50 -> 912 | B46: ='1TestYr_adj'!C50 -> Key Accounts Expneses | C46: =SUM(C41:C44) -> 85101.05 | D46: =SUM(D41:D44) -> 8826 | E46: ='1TestYr_adj'!S50 -> -12263.71 | M46: =(E46) -> -12263.71 | P46: =SUM(G46:O46) -> -12263.71 | Q46: DA
A47: ='1TestYr'!B51 -> 913 | B47: ='1TestYr_adj'!C51 -> Advertising | E47: ='1TestYr_adj'!S51 -> 60695.81 | M47: =E47 -> 60695.81 | P47: =SUM(G47:O47) -> 60695.81 | Q47: DA
B48: ='1TestYr_adj'!C52 -> Total Customer Serv. | E48: =SUM(E42:E47) -> 1024972.7 | M48: =SUM(M42:M47) -> 1024972.7 | P48: =SUM(G48:O48) -> 1024972.7
B49: =('1TestYr'!C53) | C49: 618796.41 | D49: =(C49/$C$60)*(24277) -> 13029.667
A50: =('1TestYr'!B54) -> 920 | B50: ='1TestYr_adj'!C54 -> Administrative Salaries | C50: 114229.51 | D50: =(C50/$C$60)*(24277) -> 2405.27 | E50: ='1TestYr_adj'!S54 -> 2651087.1 | H50: =($E$50*U91) -> 12488.118 | I50: =($E$50*V91) -> 1230568.7 | J50: =($E$50*W91) -> 3902.2493 | K50: =($E$50*X91) -> 297667.48 | L50: =($E$50*Y91) -> 172414.96 | M50: =($E$50*Z91) -> 806925.5 | N50: =($E$50*AA91) -> 75322.58 | O50: =($E$50*AB91) -> 51797.563 | P50: =SUM(H50:O50) -> 2651087.1 | Q50: 7 | Z50: Consumer
A51: =('1TestYr'!B55) -> 921 | B51: ='1TestYr_adj'!C55 -> Office Supplies | C51: 61723.83 | D51: =(C51/$C$60)*(24277) -> 1299.6859 | E51: ='1TestYr_adj'!S55 -> 388751.32 | H51: =($E$51*U91) -> 1831.2383 | I51: =($E$51*V91) -> 180448.69 | J51: =($E$51*W91) -> 572.21981 | K51: =($E$51*X91) -> 43649.499 | L51: =($E$51*Y91) -> 25282.663 | M51: =($E$51*Z91) -> 118326.31 | N51: =($E$51*AA91) -> 11045.187 | O51: =($E$51*AB91) -> 7595.5146 | P51: =SUM(H51:O51) -> 388751.32 | Q51: 7 | S51: 7 | T51: Admin & General Expense Allocation except General Plant | W51: Trans- | Z51: Services & | AA51: Security | AB51: Street
A52: =('1TestYr'!B56) -> 923 | B52: ='1TestYr_adj'!C56 -> Outside Services | C52: 0 | D52: =(C52/$C$60)*(24277) -> 0 | E52: ='1TestYr_adj'!S56 -> 131999.24 | H52: =($E$52*U91) -> 621.79098 | I52: =($E$52*V91) -> 61270.763 | J52: =($E$52*W91) -> 194.29536 | K52: =($E$52*X91) -> 14821.045 | L52: =($E$52*Y91) -> 8584.6456 | M52: =($E$52*Z91) -> 40177.311 | N52: =($E$52*AA91) -> 3750.357 | O52: =($E$52*AB91) -> 2579.0322 | P52: =SUM(H52:O52) -> 131999.24 | Q52: 7 | S52: Acct. | T52: Description | U52: Stations | V52: Lines | W52: formers | X52: Services | Y52: Meters | Z52: Accounting | AA52: Lighting | AB52: Lighting | AC52: Total
A53: =('1TestYr'!B57) -> 924 | B53: ='1TestYr_adj'!C57 -> Property Ins | C53: 32598.94 | D53: =(C53/$C$60)*(24277) -> 686.41854 | E53: ='1TestYr_adj'!S57 -> 0 | H53: =($E$53*U91) -> 0 | I53: =($E$53*V91) -> 0 | J53: =($E$53*W91) -> 0 | K53: =($E$53*X91) -> 0 | L53: =($E$53*Y91) -> 0 | M53: =($E$53*Z91) -> 0 | N53: =($E$53*AA91) -> 0 | O53: =($E$53*AB91) -> 0 | P53: =SUM(H53:O53) -> 0 | Q53: 7
A54: =('1TestYr'!B58) -> 925 | B54: ='1TestYr_adj'!C58 -> Injuries & Damages | C54: -382.05 | D54: =(C54/$C$60)*(24277) -> -8.0446237 | E54: ='1TestYr_adj'!S58 -> 0 | H54: =($E$54*U91) -> 0 | I54: =($E$54*V91) -> 0 | J54: =($E$54*W91) -> 0 | K54: =($E$54*X91) -> 0 | L54: =($E$54*Y91) -> 0 | M54: =($E$54*Z91) -> 0 | N54: =($E$54*AA91) -> 0 | O54: =($E$54*AB91) -> 0 | P54: =SUM(H54:O54) -> 0 | Q54: 7 | S54: 580 | T54: =(B14) -> Operations Supv & Eng | U54: =(H14) -> 5248.4067 | V54: =(I14) -> 115416.26 | W54: =(J14) -> 0 | X54: =(K14) -> 27918.53 | Y54: =(L14) -> 53728.277 | Z54: =(M14) -> 0 | AA54: =(N14) -> 31744.529 | AB54: =(O14) -> 2707.5616 | AC54: =SUM(U54:AB54) -> 236763.57
A55: =('1TestYr'!B59) -> 926 | B55: ='1TestYr_adj'!C59 -> Employ Pensions & Benef | C55: 0 | D55: =(C55/$C$60)*(24277) -> 0 | E55: ='1TestYr_adj'!S59 -> 0 | H55: =($E$55*U91) -> 0 | I55: =($E$55*V91) -> 0 | J55: =($E$55*W91) -> 0 | K55: =($E$55*X91) -> 0 | L55: =($E$55*Y91) -> 0 | M55: =($E$55*Z91) -> 0 | N55: =($E$55*AA91) -> 0 | O55: =($E$55*AB91) -> 0 | P55: =SUM(H55:O55) -> 0 | Q55: 7 | S55: 581 | T55: =(B15) -> Load Dispatching | U55: =(H15) -> 0 | V55: =(I15) | W55: =(J15) -> 0 | X55: =(K15) | Y55: =(L15) -> 0 | Z55: =(M15) -> 0 | AA55: =(N15) -> 0 | AB55: =(O15) -> 0 | AC55: =SUM(U55:AB55) -> 0
A56: =('1TestYr'!B60) -> 928 | B56: ='1TestYr_adj'!C60 -> Regulatory Exp | C56: -1303.9 | D56: =(C56/$C$60)*(24277) -> -27.455529 | E56: ='1TestYr_adj'!S60 -> 135353.92 | H56: =($E$56*U91) -> 637.59342 | I56: =($E$56*V91) -> 62827.922 | J56: =($E$56*W91) -> 199.23326 | K56: =($E$56*X91) -> 15197.713 | L56: =($E$56*Y91) -> 8802.8191 | M56: =($E$56*Z91) -> 41198.393 | N56: =($E$56*AA91) -> 3845.6701 | O56: =($E$56*AB91) -> 2644.5767 | P56: =SUM(H56:O56) -> 135353.92 | Q56: 7 | S56: 582 | T56: =(B16) -> Station Expense | U56: =(H16) -> 50972.34 | V56: =(I16) | W56: =(J16) -> 0 | X56: =(K16) | Y56: =(L16) -> 0 | Z56: =(M16) -> 0 | AA56: =(N16) -> 0 | AB56: =(O16) -> 0 | AC56: =SUM(U56:AB56) -> 50972.34
A57: =('1TestYr'!B61) -> 929 | B57: ='1TestYr_adj'!C61 -> Duplicate Charges | C57: =SUM(831.5,41445,1870.42,34240.47,197309.71) -> 275697.1 | D57: =(C57/$C$60)*(24277) -> 5805.2072 | E57: ='1TestYr_adj'!S61 -> -140016.4 | H57: =($E$57*U91) -> -659.55634 | I57: =($E$57*V91) -> -64992.129 | J57: =($E$57*W91) -> -206.09617 | K57: =($E$57*X91) -> -15721.222 | L57: =($E$57*Y91) -> -9106.0462 | M57: =($E$57*Z91) -> -42617.537 | N57: =($E$57*AA91) -> -3978.1403 | O57: =($E$57*AB91) -> -2735.6733 | P57: =SUM(H57:O57) -> -140016.4 | Q57: 7 | S57: 583 | T57: =(B17) -> Overhead Line Exp. | U57: =(H17) -> 0 | V57: =(I17) -> 1023093.8 | W57: =(J17) -> 0 | X57: =(K17) -> 247480.49 | Y57: =(L17) | Z57: =(M17) -> 0 | AA57: =(N17) -> 0 | AB57: =(O17) -> 0 | AC57: =SUM(U57:AB57) -> 1270574.3
A58: =('1TestYr'!B62) -> 930 | B58: ='1TestYr_adj'!C62 -> Misc General Exp | C58: 21502.5 | D58: =(C58/$C$60)*(24277) -> 452.76671 | E58: ='1TestYr_adj'!S62 -> 818242.08 | H58: =($E$58*U91) -> 3854.3824 | I58: =($E$58*V91) -> 379807.62 | J58: =($E$58*W91) -> 1204.4058 | K58: =($E$58*X91) -> 91873.276 | L58: =($E$58*Y91) -> 53214.839 | M58: =($E$58*Z91) -> 249052.7 | N58: =($E$58*AA91) -> 23247.861 | O58: =($E$58*AB91) -> 15987.006 | P58: =SUM(H58:O58) -> 818242.08 | Q58: 7 | S58: 584 | T58: =(B18) -> Underground Line Exp | U58: =(H18) -> 0 | V58: =(I18) -> 97824.904 | W58: =(J18) -> 0 | X58: =(K18) -> 23663.281 | Y58: =(L18) | Z58: =(M18) -> 0 | AA58: =(N18) -> 0 | AB58: =(O18) -> 0 | AC58: =SUM(U58:AB58) -> 121488.18
A59: =('1TestYr'!B63) -> 931 | B59: ='1TestYr_adj'!C63 -> Rents | C59: 30085.05 | D59: =(C59/$C$60)*(24277) -> 633.4849 | E59: ='1TestYr_adj'!S63 -> 0 | H59: =($E$59*U91) -> 0 | I59: =($E$59*V91) -> 0 | J59: =($E$59*W91) -> 0 | K59: =($E$59*X91) -> 0 | L59: =($E$59*Y91) -> 0 | M59: =($E$59*Z91) -> 0 | N59: =($E$59*AA91) -> 0 | O59: =($E$59*AB91) -> 0 | P59: =SUM(H59:O59) -> 0 | Q59: 7 | S59: 585 | T59: =(B19) -> Street Lights | U59: =(H19) -> 0 | V59: =(I19) -> 0 | W59: =(J19) -> 0 | X59: =(K19) -> 0 | Y59: =(L19) -> 0 | Z59: =(M19) -> 0 | AA59: =(N19) | AB59: =(O19) -> 26295.742 | AC59: =SUM(U59:AB59) -> 26295.742
A60: =('1TestYr'!B64) -> 935 | B60: ='1TestYr_adj'!C64 -> Maintenance of Gen. Plant | C60: =SUM(C49:C59) -> 1152947.4 | D60: =SUM(D49:D59) -> 24277 | E60: ='1TestYr_adj'!S64 -> 418973.06 | H60: =($E$60*'2.22Rate Base'!G22) -> 1973.5998 | I60: =($E$60*'2.22Rate Base'!H22) -> 194476.87 | J60: =($E$60*'2.22Rate Base'!I22) -> 616.70448 | K60: =($E$60*'2.22Rate Base'!J22) -> 47042.835 | L60: =($E$60*'2.22Rate Base'!K22) -> 27248.151 | M60: =($E$60*'2.22Rate Base'!L22) -> 127525.06 | N60: =($E$60*'2.22Rate Base'!M22) -> 11903.845 | O60: =($E$60*'2.22Rate Base'!N22) -> 8185.994 | P60: =SUM(H60:O60) -> 418973.06 | Q60: 4 | S60: 586 | T60: =(B20) -> Meter Expense | U60: =(H20) -> 0 | V60: =(I20) -> 0 | W60: =(J20) -> 0 | X60: =(K20) | Y60: =(L20) -> 521807.12 | Z60: =(M20) -> 0 | AA60: =(N20) -> 0 | AB60: =(O20) -> 0 | AC60: =SUM(U60:AB60) -> 521807.12
B61: ='1TestYr_adj'!C65 -> Total Admin & General | E61: =SUM(E50:E60) -> 4404390.4 | G61: =SUM(G50:G60) -> 0 | H61: =SUM(H50:H60) -> 20747.167 | I61: =SUM(I50:I60) -> 2044408.4 | J61: =SUM(J50:J60) -> 6483.0118 | K61: =SUM(K50:K60) -> 494530.63 | L61: =SUM(L50:L60) -> 286442.03 | M61: =SUM(M50:M60) -> 1340587.7 | N61: =SUM(N50:N60) -> 125137.36 | ... P61: =SUM(P50:P60) -> 4404390.4 | S61: 587 | T61: =(B21) -> Consumer Installations | U61: =(H21) | V61: =(I21) | W61: =(J21) -> 0 | X61: =(K21) | Y61: =(L21) | Z61: =(M21) -> 0 | AA61: =(N21) -> 308301.74 | AB61: =(O21) -> 0 | AC61: =SUM(U61:AB61) -> 308301.74
B62: =('1TestYr'!C66) | C62: 1202310.7 | D62: =(1708797-1202311) -> 506486 | S62: 588 | T62: =(B22) -> Misc. Distribution Exp | U62: =(H22) -> 4436.1519 | V62: =(I22) -> 97554.193 | W62: =(J22) -> 0 | X62: =(K22) -> 23597.797 | Y62: =(L22) -> 45413.173 | Z62: =(M22) -> 0 | AA62: =(N22) -> 26831.677 | AB62: =(O22) -> 2288.5335 | AC62: =SUM(U62:AB62) -> 200121.52
A63: ='1TestYr_adj'!B67 -> 403.6 | B63: ='1TestYr_adj'!C67 -> Deprec. Distribution Plant | C63: 64164.72 | D63: =(189533-133585)-(237146-174354) -> -6844 | E63: ='1TestYr_adj'!S67 -> 7891325.3 | H63: =($E$63*'2.22Rate Base'!G19) -> 73622.23 | I63: =($E$63*'2.22Rate Base'!H19) -> 4776054.2 | J63: =($E$63*'2.22Rate Base'!I19) -> 1270681.1 | K63: =($E$63*'2.22Rate Base'!J19) -> 1155300 | L63: =($E$63*'2.22Rate Base'!K19) -> 287690.45 | M63: =($E$63*'2.22Rate Base'!L19) -> 0 | N63: =($E$63*'2.22Rate Base'!M19) -> 210962.57 | O63: =($E$63*'2.22Rate Base'!N19) -> 117014.76 | P63: =SUM(H63:O63) -> 7891325.3 | Q63: 6 | S63: 589 | T63: =(B23) -> Rents | U63: =(H23) -> 0 | V63: =(I23) -> 0 | W63: =(J23) -> 0 | X63: =(K23) | Y63: =(L23) | Z63: =(M23) | AA63: =(N23) | AB63: =(O23) -> 0 | AC63: =SUM(U63:AB63) -> 0
A64: ='1TestYr'!B68 -> 403.7 | B64: ='1TestYr_adj'!C68 -> Deprec. General Plant | C64: =SUM(C62:C63) -> 1266475.4 | D64: =SUM(D62:D63) -> 499642 | E64: ='1TestYr_adj'!S68 -> 492968.55 | H64: =($E$64*'2.22Rate Base'!G22) -> 2322.1603 | I64: =($E$64*'2.22Rate Base'!H22) -> 228823.73 | J64: =($E$64*'2.22Rate Base'!I22) -> 725.62163 | K64: =($E$64*'2.22Rate Base'!J22) -> 55351.144 | L64: =($E$64*'2.22Rate Base'!K22) -> 32060.49 | M64: =($E$64*'2.22Rate Base'!L22) -> 150047.46 | N64: =($E$64*'2.22Rate Base'!M22) -> 14006.202 | O64: =($E$64*'2.22Rate Base'!N22) -> 9631.7352 | P64: =SUM(G64:O64) -> 492968.55 | Q64: 4 | U64: =SUM(U54:U63) -> 60656.899 | V64: =SUM(V54:V63) -> 1333889.1 | W64: =SUM(W54:W63) -> 0 | X64: =SUM(X54:X63) -> 322660.1 | Y64: =SUM(Y54:Y63) -> 620948.57 | Z64: =SUM(Z54:Z63) -> 0 | AA64: =SUM(AA54:AA63) -> 366877.94 | AB64: =SUM(AB54:AB63) -> 31291.837 | AC64: =SUM(AC54:AC63) -> 2736324.5
A65: ='1TestYr'!B69 -> 407 | B65: ='1TestYr_adj'!C69 -> Amort of Prop Losses and Undercovery | E65: ='1TestYr_adj'!S69 -> 0 | H65: =($E$65*'2.22Rate Base'!G32) -> 0 | I65: =($E$65*'2.22Rate Base'!H32) -> 0 | J65: =($E$65*'2.22Rate Base'!I32) -> 0 | K65: =($E$65*'2.22Rate Base'!J32) -> 0 | L65: =($E$65*'2.22Rate Base'!K32) -> 0 | M65: =($E$65*'2.22Rate Base'!L32) -> 0 | N65: =($E$65*'2.22Rate Base'!M32) -> 0 | O65: =($E$65*'2.22Rate Base'!N32) -> 0 | P65: =SUM(G65:O65) -> 0
B66: ='1TestYr_adj'!C70 -> Total Depreciation | E66: =SUM(E63:E65) -> 8384293.9 | H66: =SUM(H63:H65) -> 75944.39 | I66: =SUM(I63:I65) -> 5004877.9 | J66: =SUM(J63:J65) -> 1271406.8 | K66: =SUM(K63:K65) -> 1210651.1 | L66: =SUM(L63:L65) -> 319750.94 | M66: =SUM(M63:M65) -> 150047.46 | N66: =SUM(N63:N65) -> 224968.77 | O66: =SUM(O63:O65) -> 126646.5 | P66: =SUM(P63:P65) -> 8384293.9 | S66: =(A26) -> 590 | T66: =(B26) -> Maint Supv & Eng | U66: =(H26) -> 8.3716129 | V66: =(I26) -> 229905.97 | W66: =(J26) -> 937.74343 | X66: =(K26) -> 55612.931 | Y66: =(L26) -> 10797.039 | Z66: =(M26) -> 0 | AA66: =(N26) -> 0 | AB66: =(O26) -> 10903.547 | AC66: =SUM(U66:AB66) -> 308165.6
C67: 21911 | S67: =(A27) -> 592 | T67: =(B27) -> Maint of Station Equip | U67: =(H27) -> 151.6791 | V67: =(I27) -> 0 | W67: =(J27) -> 0 | X67: =(K27) -> 0 | Y67: =(L27) -> 0 | Z67: =(M27) -> 0 | AA67: =(N27) | AB67: =(O27) -> 0 | AC67: =SUM(U67:AB67) -> 151.6791
A68: ='1TestYr'!B72 -> 408.71 | B68: ='1TestYr_adj'!C72 -> PSC Assessment & Sales Taxes | E68: ='1TestYr_adj'!S72 -> 160.49 | S68: =(A28) -> 593 | T68: =(B28) -> Maint. Overhead Lines | U68: =(H28) -> 0 | V68: =(I28) -> 3919227.8 | W68: =(J28) -> 0 | X68: =(K28) -> 948038.64 | Y68: =(L28) -> 0 | Z68: =(M28) -> 0 | AA68: =(N28) -> 0 | AB68: =(O28) -> 0 | AC68: =SUM(U68:AB68) -> 4867266.5
A69: ='1TestYr'!B73 -> 408.5 | B69: ='1TestYr_adj'!C73 -> Miscellaneous Amortization | C69: =(6790.94+879.77) -> 7670.71 | D69: -7471 | E69: ='1TestYr_adj'!S73 -> 0 | S69: =(A29) -> 594 | T69: =(B29) -> Maint of Underground Lines | U69: =(H29) -> 0 | V69: =(I29) -> 246269.48 | W69: =(J29) -> 0 | X69: =(K29) -> 59571.17 | Y69: =(L29) -> 0 | Z69: =(M29) -> 0 | AA69: =(N29) -> 0 | AB69: =(O29) -> 0 | AC69: =SUM(U69:AB69) -> 305840.65
A70: ='1TestYr'!B74 -> 425-426 | B70: ='1TestYr_adj'!C74 -> Contributions | C70: =SUM(C67:C69) -> 29581.71 | D70: =SUM(D67:D69) -> -7471 | E70: ='1TestYr_adj'!S74 -> 20110.76 | S70: =(A30) -> 595 | T70: =(B30) -> Maint Line Transformers | U70: =(H30) -> 0 | V70: =(I30) -> 0 | W70: =(J30) -> 16990.284 | X70: =(K30) -> 0 | Y70: =(L30) -> 0 | Z70: =(M30) -> 0 | AA70: =(N30) -> 0 | AB70: =(O30) -> 0 | AC70: =SUM(U70:AB70) -> 16990.284
B71: ='1TestYr_adj'!C75 -> Total Miscellaneous | E71: =SUM(E68:E70) -> 20271.25 | H71: =($E$71*'2.22Rate Base'!G44) -> 185.7659 | I71: =($E$71*'2.22Rate Base'!H44) -> 12166.281 | J71: =($E$71*'2.22Rate Base'!I44) -> 3148.2372 | K71: =($E$71*'2.22Rate Base'!J44) -> 2942.9533 | L71: =($E$71*'2.22Rate Base'!K44) -> 759.77829 | M71: =($E$71*'2.22Rate Base'!L44) -> 221.0852 | N71: =($E$71*'2.22Rate Base'!M44) -> 543.14019 | O71: =($E$71*'2.22Rate Base'!N44) -> 304.00884 | P71: =SUM(G71:O71) -> 20271.25 | Q71: 5 | S71: =(A31) -> 596 | T71: =(B31) -> Maint of Street Lights | U71: =(H31) -> 0 | V71: =(I31) -> 0 | W71: =(J31) -> 0 | X71: =(K31) -> 0 | Y71: =(L31) -> 0 | Z71: =(M31) -> 0 | AA71: =(N31) -> 0 | AB71: =(O31) -> 197553.35 | AC71: =SUM(U71:AB71) -> 197553.35
C72: 334909.24 | S72: =(A32) -> 597 | T72: =(B32) -> Maintenance of Meters | U72: =(H32) -> 0 | V72: =(I32) -> 0 | W72: =(J32) -> 0 | X72: =(K32) -> 0 | Y72: =(L32) -> 195623.62 | Z72: =(M32) -> 0 | AA72: =(N32) -> 0 | AB72: =(O32) -> 0 | AC72: =SUM(U72:AB72) -> 195623.62
A73: ='1TestYr'!B77 -> 427.1 | B73: ='1TestYr_adj'!C77 -> Interest - RUS Constuc | C73: 301500 | E73: ='1TestYr_adj'!S77 -> 3128863 | S73: =(A33) -> 598 | T73: =(B33) -> Maint Misc Distrib Plant | U73: =(H33) -> 9.6315843 | V73: =(I33) -> 264508.02 | W73: =(J33) -> 1078.8787 | X73: =(K33) -> 63982.967 | Y73: =(L33) -> 12422.05 | Z73: =(M33) -> 0 | AA73: =(N33) -> 0 | AB73: =(O33) -> 12544.587 | AC73: =SUM(U73:AB73) -> 354546.14
A74: ='1TestYr'!B78 -> 427.2 | B74: ='1TestYr_adj'!C78 -> Interest - CFC | C74: 372800 | E74: ='1TestYr_adj'!S78 -> 655206.95 | T74: =(B34) -> Total Dist. Maint. | U74: =SUM(U66:U73) -> 169.6823 | V74: =SUM(V66:V73) -> 4659911.3 | W74: =SUM(W66:W73) -> 19006.906 | X74: =SUM(X66:X73) -> 1127205.7 | Y74: =SUM(Y66:Y73) -> 218842.7 | Z74: =SUM(Z66:Z73) -> 0 | AA74: =SUM(AA66:AA73) -> 0 | AB74: =SUM(AB66:AB73) -> 221001.48 | AC74: =SUM(U74:AB74) -> 6246137.8
A75: ='1TestYr'!B79 -> 427.4 | B75: ='1TestYr_adj'!C79 -> Interest - FFB | C75: =SUM(C72:C74) -> 1009209.2 | D75: 73120 | E75: ='1TestYr_adj'!S79 -> 917724.82
B76: ='1TestYr_adj'!C80 -> Total Interest on LTD | E76: =SUM(E73:E75) -> 4701794.8 | G76: 0 | H76: =($E$76*'2.22Rate Base'!G44) -> 43087.286 | I76: =($E$76*'2.22Rate Base'!H44) -> 2821895.9 | J76: =($E$76*'2.22Rate Base'!I44) -> 730214.72 | K76: =($E$76*'2.22Rate Base'!J44) -> 682600.36 | L76: =($E$76*'2.22Rate Base'!K44) -> 176226.01 | M76: =($E$76*'2.22Rate Base'!L44) -> 51279.386 | N76: =($E$76*'2.22Rate Base'!M44) -> 125978.11 | O76: =($E$76*'2.22Rate Base'!N44) -> 70513.025 | P76: =SUM(H76:O76) -> 4701794.8 | Q76: 5 | S76: 901 | T76: Supervision | Z76: =(M36) -> 143333.65 | AC76: =SUM(U76:AA76) -> 143333.65
C77: 32877.12 | E77: =('1TestYr'!J81) | S77: 902 | T77: Meter Reading Expense | Z77: =(M37) -> 101876.5 | AC77: =SUM(U77:AA77) -> 101876.5
A78: =('1TestYr'!B82) -> 431 | B78: ='1TestYr_adj'!C82 -> Other Interest Expense | C78: 26952.1 | E78: ='1TestYr_adj'!S82 -> 2878.86 | S78: 903 | T78: Cons Recds & Collections | Z78: =(M38) -> 2319797.3 | AC78: =SUM(U78:AA78) -> 2319797.3
A79: =('1TestYr'!B84) | B79: ='1TestYr_adj'!C85 -> Total ST Interest | E79: =SUM(E78) -> 2878.86 | H79: =($E$79*'2.22Rate Base'!G44) -> 26.381897 | I79: =($E$79*'2.22Rate Base'!H44) -> 1727.8175 | J79: =($E$79*'2.22Rate Base'!I44) -> 447.10287 | K79: =($E$79*'2.22Rate Base'!J44) -> 417.9491 | L79: =($E$79*'2.22Rate Base'!K44) -> 107.90135 | M79: =($E$79*'2.22Rate Base'!L44) -> 31.397834 | N79: =($E$79*'2.22Rate Base'!M44) -> 77.135083 | O79: =($E$79*'2.22Rate Base'!N44) -> 43.174391 | P79: =SUM(G79:O79) -> 2878.86 | Q79: 5 | S79: 904 | T79: Uncollectible Accounts | Z79: =(M39) -> 340357.45 | AC79: =SUM(U79:AA79) -> 340357.45
B80: =('1TestYr'!C86) | C80: =SUM(C10,C22,#REF!,C39,C46,C60,C64,C70,C75,#REF!) -> #REF! | D80: =SUM(D10,D22,#REF!,D39,D46,D60,D64,D70,D75,#REF!) -> #REF! | E80: =('1TestYr'!J86) -> 0 | T80: Total Consum Accts | Z80: =SUM(Z76:Z79) -> 2905364.9 | AC80: =SUM(AC76:AC79) -> 2905364.9
B81: ='1TestYr_adj'!C87 -> Total Costs | C81: =(C75) -> 1009209.2 | D81: =(D75) -> 73120 | E81: =SUM(E12,E24,E34,E61,E66,E71,E79,E48,E40,E76) -> 1.1453096e+08 | G81: =SUM(G12,G24,G34,G61,G66,G71,G79,G48,G40,G76) -> 84104533 | H81: =SUM(H12,H24,H34,H61,H66,H71,H79,H48,H40,H76) -> 200817.57 | I81: =SUM(I12,I24,I34,I61,I66,I71,I79,I48,I40,I76) -> 15878877 | J81: =SUM(J12,J24,J34,J61,J66,J71,J79,J48,J40,J76) -> 2030706.7 | K81: =SUM(K12,K24,K34,K61,K66,K71,K79,K48,K40,K76) -> 3841008.8 | L81: =SUM(L12,L24,L34,L61,L66,L71,L79,L48,L40,L76) -> 1623077.9 | M81: =SUM(M12,M24,M34,M61,M66,M71,M79,M48,M40,M76) -> 5472504.6 | N81: =SUM(N12,N24,N34,N61,N66,N71,N79,N48,N40,N76) -> 843582.46 | ... P81: =SUM(P12,P24,P34,P61,P66,P71,P79,P48,P40,P76) -> 1.1453096e+08
B82: ='1TestYr_adj'!C88 -> Margin Requirements | C82: =(C80+C81) -> #REF! | D82: =(D80+D81) -> #REF! | E82: ='1TestYr_adj'!S88 -> 4701795 | G82: =(G76) -> 0 | H82: =($E$82*'2.22Rate Base'!G44) -> 43087.288 | I82: =($E$82*'2.22Rate Base'!H44) -> 2821896 | J82: =($E$82*'2.22Rate Base'!I44) -> 730214.76 | K82: =($E$82*'2.22Rate Base'!J44) -> 682600.39 | L82: =($E$82*'2.22Rate Base'!K44) -> 176226.02 | M82: =($E$82*'2.22Rate Base'!L44) -> 51279.388 | N82: =($E$82*'2.22Rate Base'!M44) -> 125978.11 | O82: =($E$82*'2.22Rate Base'!N44) -> 70513.028 | P82: =SUM(H82:O82) -> 4701795 | Q82: 5 | S82: =A42 -> 907 | T82: =B42 -> Customer Information | Z82: =(M42) -> 0 | AC82: =SUM(U82:AA82) -> 0
B83: ='1TestYr_adj'!C89 -> Total Revenue Require. | E83: =(E81+E82) -> 1.1923276e+08 | G83: =(G81+G82) -> 84104533 | H83: =(H81+H82) -> 243904.86 | I83: =(I81+I82) -> 18700773 | J83: =(J81+J82) -> 2760921.5 | K83: =(K81+K82) -> 4523609.2 | L83: =(L81+L82) -> 1799304 | M83: =(M81+M82) -> 5523784 | N83: =(N81+N82) -> 969560.57 | ... P83: =(P81+P82) -> 1.1923276e+08 | S83: =A43 -> 908 | T83: =B43 -> Customer Accounting | Z83: =(M43) -> 976219.36 | AC83: =SUM(U83:AA83) -> 976219.36
F84: =(E83-P83) -> 0 | S84: =A44 -> 909 | T84: =B44 -> Consumer Information | Z84: =(M44) -> 321.18822 | AC84: =SUM(U84:AA84) -> 321.18822
P85: =SUM(G83:O83) -> 1.1923276e+08 | S85: =A45 -> 910 | T85: =B45 -> Mis. Customer Information | Z85: =(M45) -> 0 | AC85: =SUM(U85:AA85) -> 0
E86: =('1TestYr'!J89-'2 Functionalization2'!E83) -> -23150695 | S86: =A46 -> 912 | T86: =B46 -> Key Accounts Expneses | Z86: =(M46) -> -12263.71 | AC86: =SUM(U86:AA86) -> -12263.71 | AE86: =SUM(V88:AA88) -> 1024972.7
S87: =A47 -> 913 | T87: =B47 -> Advertising | Z87: =(M47) -> 60695.81 | AC87: =SUM(U87:AA87) -> 60695.81
T88: =B48 -> Total Customer Serv. | Z88: =SUM(Z82:Z87) -> 1024972.7 | AC88: =SUM(AC82:AC87) -> 1024972.7 | AE88: =SUM(U89:AB90) -> 12912800
Z89: =(U89) | AE89: =SUM(U90:AB91) -> 12912801
T90: Total all Expenses | U90: =SUM(U64,U74,U88,U80) -> 60826.581 | V90: =SUM(V64,V74,V88,V80) -> 5993800.4 | W90: =SUM(W64,W74,W88,W80) -> 19006.906 | X90: =SUM(X64,X74,X88,X80) -> 1449865.8 | Y90: =SUM(Y64,Y74,Y88,Y80) -> 839791.28 | Z90: =SUM(Z64,Z74,Z88,Z80) -> 3930337.6 | AA90: =SUM(AA64,AA74,AA88,AA80) -> 366877.94 | AB90: =SUM(AB64,AB74,AB88,AB80) -> 252293.32 | AC90: =SUM(AC64,AC74,AC88,AC80) -> 12912800 | AE90: =(AC90-AE88) -> -3.7252903e-09
T91: Functions as % of Total | U91: =(U90/$AC$90) -> 0.0047105649 | V91: =(V90/$AC$90) -> 0.46417512 | W91: =(W90/$AC$90) -> 0.0014719431 | X91: =(X90/$AC$90) -> 0.11228129 | Y91: =(Y90/$AC$90) -> 0.065035569 | Z91: =(Z90/$AC$90) -> 0.30437532 | AA91: =(AA90/$AC$90) -> 0.028411959 | AB91: =(AB90/$AC$90) -> 0.019538235 | AC91: =SUM(U91:AB91) -> 1
H92: =(H82/H83) -> 0.17665613 | I92: =(I82/I83) -> 0.15089729 | J92: =(J82/J83) -> 0.26448226 | K92: =(K82/K83) -> 0.15089729 | L92: =(L82/L83) -> 0.097941219 | M92: =(M82/M83) -> 0.0092833804 | N92: =(N82/N83) -> 0.12993321 | O92: =(O82/O83) -> 0.1162877 | P92: =(P82/P83) -> 0.039433752
A93: =('1TestYr'!B90) -> 0 | B93: =('1TestYr'!C91) -> Less; Misc Income | E93: =('1TestYr'!J91) -> 0
A94: =('1TestYr'!B91) -> 0 | B94: =('1TestYr'!C92) -> Forfeited Discounts | C94: =('1TestYr'!D92) -> 1124919.2 | D94: =('1TestYr'!E92) -> 0 | E94: =('1TestYr'!J92) -> 1124919.2 | P94: =(P81-P12) -> 30426429
A95: =('1TestYr'!B92) -> 450 | B95: =('1TestYr'!C93) -> Misc Service Revenue | E95: =('1TestYr'!J93) -> 326809.63
A96: =('1TestYr'!B93) -> 451 | B96: =('1TestYr'!C94) -> Return Check Charge | E96: =('1TestYr'!J94) -> 0
A97: =('1TestYr'!B94) -> 452 | B97: =('1TestYr'!C95) -> Rent from Electric Prop. | E97: =('1TestYr'!J95) -> 915266.04
A98: =('1TestYr'!B95) -> 454 | B98: =('1TestYr'!C97) -> Total Misc Income | E98: =('1TestYr'!J97) -> 2600940
A99: =('1TestYr'!B97) -> 0 | C99: 249793.5 | E99: =('1TestYr'!J98) -> 0 | T99: =(B22) -> Misc. Distribution Exp
A100: =('1TestYr'!B98) -> 0 | B100: =('1TestYr'!C99) -> Less: Other Income | C100: 70175.22 | E100: =('1TestYr'!J99) -> 0 | T100: =(#REF!) -> #REF!
A101: =('1TestYr'!B99) -> 0 | B101: =('1TestYr'!C100) -> Net Revenue from Merchandising | C101: 282821.45 | D101: 10755 | E101: =('1TestYr'!J100) -> 8776.37 | T101: =(B39) -> Uncollectible Accounts
...

Sheet 2.1 SummaryFunc.
J2: Consumer
D3: Purchased | J3: Services & | K3: Security | L3: Street
B4: Expense | D4: Power | E4: Stations | F4: Lines | G4: Transformers | H4: Services | I4: Meters | J4: Accounting | K4: Lighting | L4: Lighting | M4: Total
B5: Purchased Power | D5: =('2 Functionalization2'!G12) -> 84104533 | M5: =SUM(D5:L5) -> 84104533
B6: Distibution Operations | E6: =('2 Functionalization2'!H24) -> 60656.899 | F6: =('2 Functionalization2'!I24) -> 1333889.1 | G6: =('2 Functionalization2'!J24) -> 0 | H6: =('2 Functionalization2'!K24) -> 322660.1 | I6: =('2 Functionalization2'!L24) -> 620948.57 | J6: =('2 Functionalization2'!M24) -> 0 | K6: =('2 Functionalization2'!N24) -> 366877.94 | L6: =('2 Functionalization2'!O24) -> 31291.837 | M6: =SUM(D6:L6) -> 2736324.5
B7: Distribution Maintenance | E7: =('2 Functionalization2'!H34) -> 169.6823 | F7: =('2 Functionalization2'!I34) -> 4659911.3 | G7: =('2 Functionalization2'!J34) -> 19006.906 | H7: =('2 Functionalization2'!K34) -> 1127205.7 | I7: =('2 Functionalization2'!L34) -> 218842.7 | J7: =('2 Functionalization2'!M34) -> 0 | K7: =('2 Functionalization2'!N34) -> 0 | L7: =('2 Functionalization2'!O34) -> 221001.48 | M7: =SUM(D7:L7) -> 6246137.8
B8: Consumer Accounts | E8: ='2 Functionalization2'!H40 -> 0 | F8: ='2 Functionalization2'!I40 -> 0 | G8: ='2 Functionalization2'!J40 -> 0 | H8: ='2 Functionalization2'!K40 -> 0 | I8: ='2 Functionalization2'!L40 -> 0 | J8: ='2 Functionalization2'!M40 -> 2905364.9 | K8: ='2 Functionalization2'!N40 -> 0 | L8: ='2 Functionalization2'!O40 -> 0 | M8: =SUM(D8:L8) -> 2905364.9
B9: Customer Service | E9: ='2 Functionalization2'!H48 -> 0 | F9: ='2 Functionalization2'!I48 -> 0 | G9: ='2 Functionalization2'!J48 -> 0 | H9: ='2 Functionalization2'!K48 -> 0 | I9: ='2 Functionalization2'!L48 -> 0 | J9: ='2 Functionalization2'!M48 -> 1024972.7 | K9: ='2 Functionalization2'!N48 -> 0 | L9: ='2 Functionalization2'!O48 -> 0 | M9: =SUM(D9:L9) -> 1024972.7
B10: Administative & General | E10: =('2 Functionalization2'!H61) -> 20747.167 | F10: =('2 Functionalization2'!I61) -> 2044408.4 | G10: =('2 Functionalization2'!J61) -> 6483.0118 | H10: =('2 Functionalization2'!K61) -> 494530.63 | I10: =('2 Functionalization2'!L61) -> 286442.03 | J10: =('2 Functionalization2'!M61) -> 1340587.7 | K10: =('2 Functionalization2'!N61) -> 125137.36 | L10: =('2 Functionalization2'!O61) -> 86054.013 | M10: =SUM(D10:L10) -> 4404390.4
B11: Depreciation | E11: =('2 Functionalization2'!H66) -> 75944.39 | F11: =('2 Functionalization2'!I66) -> 5004877.9 | G11: =('2 Functionalization2'!J66) -> 1271406.8 | H11: =('2 Functionalization2'!K66) -> 1210651.1 | I11: =('2 Functionalization2'!L66) -> 319750.94 | J11: =('2 Functionalization2'!M66) -> 150047.46 | K11: =('2 Functionalization2'!N66) -> 224968.77 | L11: =('2 Functionalization2'!O66) -> 126646.5 | M11: =SUM(D11:L11) -> 8384293.9
B12: Miscellaneous | E12: =('2 Functionalization2'!H71) -> 185.7659 | F12: =('2 Functionalization2'!I71) -> 12166.281 | G12: =('2 Functionalization2'!J71) -> 3148.2372 | H12: =('2 Functionalization2'!K71) -> 2942.9533 | I12: =('2 Functionalization2'!L71) -> 759.77829 | J12: =('2 Functionalization2'!M71) -> 221.0852 | K12: =('2 Functionalization2'!N71) -> 543.14019 | L12: =('2 Functionalization2'!O71) -> 304.00884 | M12: =SUM(D12:L12) -> 20271.25
B13: Interest on Long Term Debt | E13: =('2 Functionalization2'!H76) -> 43087.286 | F13: =('2 Functionalization2'!I76) -> 2821895.9 | G13: =('2 Functionalization2'!J76) -> 730214.72 | H13: =('2 Functionalization2'!K76) -> 682600.36 | I13: =('2 Functionalization2'!L76) -> 176226.01 | J13: =('2 Functionalization2'!M76) -> 51279.386 | K13: =('2 Functionalization2'!N76) -> 125978.11 | L13: =('2 Functionalization2'!O76) -> 70513.025 | M13: =SUM(D13:L13) -> 4701794.8
B14: Short Term Interest | E14: =('2 Functionalization2'!H79) -> 26.381897 | F14: =('2 Functionalization2'!I79) -> 1727.8175 | G14: =('2 Functionalization2'!J79) -> 447.10287 | H14: =('2 Functionalization2'!K79) -> 417.9491 | I14: =('2 Functionalization2'!L79) -> 107.90135 | J14: =('2 Functionalization2'!M79) -> 31.397834 | K14: =('2 Functionalization2'!N79) -> 77.135083 | L14: =('2 Functionalization2'!O79) -> 43.174391 | M14: =SUM(D14:L14) -> 2878.86
B15: Total Costs | D15: =SUM(D5:D14) -> 84104533 | E15: =SUM(E5:E14) -> 200817.57 | F15: =SUM(F5:F14) -> 15878877 | G15: =SUM(G5:G14) -> 2030706.7 | H15: =SUM(H5:H14) -> 3841008.8 | I15: =SUM(I5:I14) -> 1623077.9 | J15: =SUM(J5:J14) -> 5472504.6 | K15: =SUM(K5:K14) -> 843582.46 | L15: =SUM(L5:L14) -> 535854.04 | M15: =SUM(D15:L15) -> 1.1453096e+08
B16: Margin Requirements | D16: =(D13) -> 0 | E16: =('2 Functionalization2'!H82) -> 43087.288 | F16: =('2 Functionalization2'!I82) -> 2821896 | G16: =('2 Functionalization2'!J82) -> 730214.76 | H16: =('2 Functionalization2'!K82) -> 682600.39 | I16: =('2 Functionalization2'!L82) -> 176226.02 | J16: =('2 Functionalization2'!M82) -> 51279.388 | K16: =('2 Functionalization2'!N82) -> 125978.11 | L16: =('2 Functionalization2'!O82) -> 70513.028 | M16: =SUM(D16:L16) -> 4701795
B17: Revenue Requirements | D17: =SUM(D15:D16) -> 84104533 | E17: =SUM(E15:E16) -> 243904.86 | F17: =SUM(F15:F16) -> 18700773 | G17: =SUM(G15:G16) -> 2760921.5 | H17: =SUM(H15:H16) -> 4523609.2 | I17: =SUM(I15:I16) -> 1799304 | J17: =SUM(J15:J16) -> 5523784 | K17: =SUM(K15:K16) -> 969560.57 | L17: =SUM(L15:L16) -> 606367.06 | M17: =SUM(D17:L17) -> 1.1923276e+08
E19: =(E16/E17) -> 0.17665613 | M19: =SUM(M5:M14) -> 1.1453096e+08

Sheet 2.22Rate Base
A1: FUNCTIONALIZATION OF RATE BASE
H2: Distribution Plant Balances
L3: Consumer
B4: Plant | L4: & Accounting | M4: Security | N4: Street
B5: Account | C5: Description | E5: $$$$ | G5: Stations | H5: Lines | I5: Transformers | J5: Services | K5: Meters | L5: Services | M5: Lighting | N5: Lighting
A6: 1 | B6: =([6]adjustment!B36) -> 301 | C6: =([6]adjustment!C36) -> Organization | E6: 0 | H6: =(E6) -> 0 | P6: =SUM(H6:N6) -> 0
A7: 2 | B7: 389 | C7: Land and Land Rights | H7: =(E7) -> 0 | P7: =SUM(G7:N7) -> 0
A8: 3 | B8: 362 | C8: Station Equipment | E8: =1345642.26+545573.23 -> 1891215.5 | G8: =(E8) -> 1891215.5 | P8: =SUM(G8:N8) -> 1891215.5
A9: 4 | B9: =([6]adjustment!B38) -> 364 | C9: Poles, Towers & Fixtures | E9: 57805699 | H9: =(E9) -> 57805699 | P9: =SUM(G9:N9) -> 57805699
A10: 5 | B10: =([6]adjustment!B39) -> 365 | C10: Overhead Conductor & Devices | E10: 50743404 | H10: =(E10-M10) -> 50743404 | P10: =SUM(G10:N10) -> 50743404
B11: 366 | C11: Underground Conduit | E11: 0 | H11: =(E11-M11) -> 0
A12: 6 | B12: 367 | C12: Underground Conductor | E12: 14138673 | H12: =(E12) -> 14138673 | P12: =SUM(G12:N12) -> 14138673
A13: 7 | B13: =([6]adjustment!B42) -> 368 | C13: Line Transformers | E13: =22840564.83+9800824.43 -> 32641389 | I13: =(E13) -> 32641389 | P13: =SUM(G13:N13) -> 32641389 | R13: 370 | S13: 450100.68
A14: 8 | B14: =([6]adjustment!B43) -> 369 | C14: Services | E14: =10324375.44+19353090.97 -> 29677466 | J14: =(E14) -> 29677466 | P14: =SUM(G14:N14) -> 29677466 | R14: 370.1 | S14: 6940121.4
A15: 9 | B15: =([6]adjustment!B44) -> 370 | C15: Meters | E15: =450100.68+6940121.39 -> 7390222.1 | K15: =(E15) -> 7390222.1 | P15: =SUM(G15:N15) -> 7390222.1 | R15: 370.2
A16: 10 | B16: =([6]adjustment!B46) -> 371 | C16: Security Lights | E16: 5419228.4 | M16: =(E16) -> 5419228.4 | P16: =SUM(G16:N16) -> 5419228.4 | R16: 370.3
A17: 11 | B17: =([6]adjustment!B47) -> 373 | C17: Street Lights | E17: 3005887.4 | N17: =(E17) -> 3005887.4 | P17: =SUM(G17:N17) -> 3005887.4 | S17: =SUM(S13:S16) -> 7390222.1
A18: 12 | C18: Total Distribution Plant | E18: =SUM(E6:E17) -> 2.0271318e+08 | G18: =SUM(G6:G17) -> 1891215.5 | H18: =SUM(H6:H17) -> 1.2268778e+08 | I18: =SUM(I7:I17) -> 32641389 | J18: =SUM(J7:J17) -> 29677466 | K18: =SUM(K7:K17) -> 7390222.1 | L18: =SUM(L7:L17) -> 0 | M18: =SUM(M7:M17) -> 5419228.4 | N18: =SUM(N7:N17) -> 3005887.4 | P18: =SUM(G18:N18) -> 2.0271318e+08
A19: 13 | C19: Distibution Plant Percent | E19: =(E18/$E$18) -> 1 | G19: =(G18/$E$18) -> 0.009329514 | H19: =(H18/$E$18) -> 0.6052284 | I19: =(I18/$E$18) -> 0.16102253 | J19: =(J18/$E$18) -> 0.14640126 | K19: =(K18/$E$18) -> 0.036456544 | L19: =(L18/$E$18) -> 0 | M19: =(M18/$E$18) -> 0.026733478 | N19: =(N18/$E$18) -> 0.014828278 | P19: =SUM(G19:N19) -> 1
A20: 14 | T20: 108.7 | U20: 2408194.7 | W20: 108.6 | X20: 16403586 | Z20: 108.54 | AA20: 2610145.7 | AC20: 108.8 | AD20: -150372.41
A21: 15 | C21: Total General Plant | E21: =9491445+8067755 -> 17559200 | G21: =($E$21*'2 Functionalization2'!U91) -> 82713.751 | H21: =($E$21*'2 Functionalization2'!V91) -> 8150543.8 | I21: =($E$21*'2 Functionalization2'!W91) -> 25846.142 | J21: =($E$21*'2 Functionalization2'!X91) -> 1971569.6 | K21: =($E$21*'2 Functionalization2'!Y91) -> 1141972.6 | L21: =($E$21*'2 Functionalization2'!Z91) -> 5344587.1 | M21: =($E$21*'2 Functionalization2'!AA91) -> 498891.28 | N21: =($E$21*'2 Functionalization2'!AB91) -> 343075.77 | P21: =SUM(G21:N21) -> 17559200 | T21: 108.71 | U21: 220990.02 | W21: 108.61 | X21: 11845342 | Z21: 108.55 | AA21: 3488.88 | AC21: 108.81
A22: 16 | C22: General Plant Percent | E22: =(E21/$E$21) -> 1 | G22: =(G21/$E$21) -> 0.0047105649 | H22: =(H21/$E$21) -> 0.46417512 | I22: =(I21/$E$21) -> 0.0014719431 | J22: =(J21/$E$21) -> 0.11228129 | K22: =(K21/$E$21) -> 0.065035569 | L22: =(L21/$E$21) -> 0.30437532 | M22: =(M21/$E$21) -> 0.028411959 | N22: =(N21/$E$21) -> 0.019538235 | P22: =SUM(G22:N22) -> 1 | T22: 108.72 | U22: 986635.75 | W22: 108.62 | X22: 3411482.4 | Z22: 108.56 | AA22: 7448.99 | AC22: 108.9
A23: 17 | T23: 108.73 | U23: 1289079.9 | W23: 108.63 | X23: 7773861.5 | Z23: 108.57 | AA23: 292660.3
A24: 18 | C24: Total Utility Plant | E24: =(E18+E21) -> 2.2027238e+08 | G24: =(G18+G21) -> 1973929.2 | H24: =(H18+H21) -> 1.3083832e+08 | I24: =(I18+I21) -> 32667235 | J24: =(J18+J21) -> 31649036 | K24: =(K18+K21) -> 8532194.6 | L24: =(L18+L21) -> 5344587.1 | M24: =(M18+M21) -> 5918119.7 | N24: =(N18+N21) -> 3348963.2 | P24: =SUM(G24:N24) -> 2.2027238e+08 | T24: 108.74 | U24: 273721.82 | W24: 108.64 | X24: 2889538.6 | Z24: 108.58 | AA24: 703827.15
A25: 19 | C25: Utility Plant Percent | E25: =(E24/$E$24) -> 1 | G25: =(G24/$E$24) -> 0.0089613105 | H25: =(H24/$E$24) -> 0.59398421 | I25: =(I24/$E$24) -> 0.14830382 | J25: =(J24/$E$24) -> 0.14368136 | K25: =(K24/$E$24) -> 0.038734745 | L25: =(L24/$E$24) -> 0.024263537 | M25: =(M24/$E$24) -> 0.026867279 | N25: =(N24/$E$24) -> 0.015203736 | P25: =SUM(G25:N25) -> 1 | T25: 108.75 | U25: 154309.72 | W25: 108.65 | X25: 2957191.2 | Z25: 108.59 | AA25: 1701892.7
A26: 20 | T26: 108.76 | U26: 288227.84 | W26: 108.66 | X26: 6805979.4
A27: 21 | C27: Accum. Depreciation | T27: 108.77 | U27: 802207.07 | W27: 108.67 | X27: 332260.67
A28: 22 | C28: Distribution Plant | E28: =X30+AD30 -> 54621212 | G28: =(G19*$E$28) -> 509589.36 | H28: =(H19*$E$28) -> 33058309 | I28: =(I19*$E$28) -> 8795245.6 | J28: =(J19*$E$28) -> 7996614.5 | K28: =(K19*$E$28) -> 1991300.6 | L28: =(L19*$E$28) -> 0 | M28: =(M19*$E$28) -> 1460215 | N28: =(N19*$E$28) -> 809938.51 | P28: =SUM(G28:N28) -> 54621212 | T28: 108.78 | U28: 164796.08 | W28: 108.68 | X28: 1079865.5
A29: 23 | C29: General Plant | E29: =U30+AA30 -> 11977110 | G29: =($E$29*G22) -> 56418.953 | H29: =($E$29*H22) -> 5559476.4 | I29: =($E$29*I22) -> 17629.624 | J29: =($E$29*J22) -> 1344805.3 | K29: =($E$29*K22) -> 778938.15 | L29: =($E$29*L22) -> 3645536.7 | M29: =($E$29*M22) -> 340293.16 | N29: =($E$29*N22) -> 234011.59 | P29: =SUM(G29:N29) -> 11977110 | Q29: =SUM(P28:P29) -> 66598322 | R29: 57505856 | T29: 108.79 | U29: 69483.17 | W29: 108.69 | X29: 1272477.4
A30: 24 | R30: =R29-Q29 -> -9092466.3 | U30: =SUM(U20:U29) -> 6657646.1 | X30: =SUM(X20:X29) -> 54771585 | AA30: =SUM(AA20:AA29) -> 5319463.8 | AD30: =SUM(AD20:AD29) -> -150372.41 | AE30: =SUM(U30:AD30) -> 66598322
A31: 25 | C31: Net Plant | E31: =(E24-E28-E29) -> 1.5367406e+08 | G31: =(G24-G28-G29) -> 1407920.9 | H31: =(H24-H28-H29) -> 92220534 | I31: =(I24-I28-I29) -> 23854360 | J31: =(J24-J28-J29) -> 22307616 | K31: =(K24-K28-K29) -> 5761955.9 | L31: =(L24-L28-L29) -> 1699050.5 | M31: =(M24-M28-M29) -> 4117611.6 | N31: =(N24-N28-N29) -> 2305013.1 | P31: =SUM(G31:N31) -> 1.5367406e+08
A32: 26 | C32: Net Plant Percent | E32: =(E31/$E$31) -> 1 | G32: =(G31/$E$31) -> 0.0091617343 | H32: =(H31/$E$31) -> 0.60010475 | I32: =(I31/$E$31) -> 0.15522698 | J32: =(J31/$E$31) -> 0.14516188 | K32: =(K31/$E$31) -> 0.037494654 | L32: =(L31/$E$31) -> 0.011056195 | M32: =(M31/$E$31) -> 0.026794447 | N32: =(N31/$E$31) -> 0.014999363 | P32: =SUM(G32:N32) -> 1 | U32: CWIP | W32: Cash Working capital | Z32: Materials and Supplies | AC32: Prepayments | AF32: Consumer Advances
A33: 27 | P33: =SUM(H33:N33) -> 0 | T33: 107.2 | U33: 1731296.6 | W33: 131.2 | X33: 6023 | Z33: 154 | AA33: 1378197.1 | AC33: 165.12 | AD33: -4257.23 | AF33: 252 | AG33: -384769.68
A34: 28 | C34: CWIP | E34: 1731297 | G34: =(G18/$E$18)*($E$34) -> 16152.16 | H34: =(H18/$E$18)*($E$34) -> 1047830.1 | I34: =(I18/$E$18)*($E$34) -> 278777.82 | J34: =(J18/$E$18)*($E$34) -> 253464.07 | K34: =(K18/$E$18)*($E$34) -> 63117.105 | L34: =(L18/$E$18)*($E$34) -> 0 | M34: =(M18/$E$18)*($E$34) -> 46283.59 | N34: =(N18/$E$18)*($E$34) -> 25672.153 | P34: =SUM(G34:N34) -> 1731297 | T34: 107.21 | W34: 131.31 | X34: 100 | Z34: 154.01 | AA34: -22171.72 | AC34: 165.14 | AD34: 179338 | AF34: 252.1
A35: 29 | C35: Subtotal | E35: =(E31+E34) -> 1.5540536e+08 | G35: =(G31+G34) -> 1424073.1 | H35: =(H31+H34) -> 93268364 | I35: =(I31+I34) -> 24133138 | J35: =(J31+J34) -> 22561080 | K35: =(K31+K34) -> 5825073 | L35: =(L31+L34) -> 1699050.5 | M35: =(M31+M34) -> 4163895.1 | N35: =(N31+N34) -> 2330685.2 | P35: =SUM(G35:N35) -> 1.5540536e+08 | T35: 107.22 | W35: 131.4 | X35: 109067.99 | Z35: 154.1 | AA35: 14899.26 | AC35: 165.15 | AD35: 120.95
A36: 30 | C36: Plus | P36: =SUM(G36:N36) -> 0 | T36: 107.3 | W36: 131.85 | X36: 53825.98 | Z36: 154.6 | AA36: 0 | AC36: 165.16 | AD36: -233.09
A37: 31 | C37: Cash Working Capital | E37: =X54 -> 205662.54 | G37: =(G35/$E$35)*($E$37) -> 1884.61 | H37: =(H35/$E$35)*($E$37) -> 123430.81 | I37: =(I35/$E$35)*($E$37) -> 31937.653 | J37: =(J35/$E$35)*($E$37) -> 29857.201 | K37: =(K35/$E$35)*($E$37) -> 7708.8673 | L37: =(L35/$E$35)*($E$37) -> 2248.5134 | M37: =(M35/$E$35)*($E$37) -> 5510.4744 | N37: =(N35/$E$35)*($E$37) -> 3084.4151 | P37: =SUM(G37:N37) -> 205662.54 | T37: 107.31 | W37: 131.9 | X37: 28902 | AC37: 165.2 | AD37: 44674.16
A38: 32 | C38: Materials & Supplies | E38: =AA54 -> 1370924.6 | G38: =(G35/$E$35)*($E$38) -> 12562.61 | H38: =(H35/$E$35)*($E$38) -> 822776.63 | I38: =(I35/$E$35)*($E$38) -> 212893 | J38: =(J35/$E$35)*($E$38) -> 199024.93 | K38: =(K35/$E$35)*($E$38) -> 51386.49 | L38: =(L35/$E$35)*($E$38) -> 14988.351 | M38: =(M35/$E$35)*($E$38) -> 36732.236 | N38: =(N35/$E$35)*($E$38) -> 20560.384 | P38: =SUM(G38:N38) -> 1370924.6 | T38: 107.32 | W38: 131.95 | X38: 7743.57 | AC38: 165.21 | AD38: 10067
A39: 33 | C39: Prepayments | E39: =AD54 -> 301267.41 | G39: =(G35/$E$35)*($E$39) -> 2760.6951 | H39: =(H35/$E$35)*($E$39) -> 180809.2 | I39: =(I35/$E$35)*($E$39) -> 46784.281 | J39: =(J35/$E$35)*($E$39) -> 43736.704 | K39: =(K35/$E$35)*($E$39) -> 11292.433 | L39: =(L35/$E$35)*($E$39) -> 3293.7637 | M39: =(M35/$E$35)*($E$39) -> 8072.0891 | N39: =(N35/$E$35)*($E$39) -> 4518.2451 | P39: =SUM(G39:N39) -> 301267.41 | U39: =SUM(U33:U38) -> 1731296.6 | W39: 131.16 | X39: 0 | AC39: 165.22 | AD39: 3547.03
A40: 34 | C40: Minus: Consumer Advances | E40: =AG54 -> -384769.68 | G40: =(G18/$E$18)*($E$40) -> -3589.7141 | H40: =(H18/$E$18)*($E$40) -> -232873.54 | I40: =(I18/$E$18)*($E$40) -> -61956.586 | J40: =(J18/$E$18)*($E$40) -> -56330.767 | K40: =(K18/$E$18)*($E$40) -> -14027.373 | L40: =(L18/$E$18)*($E$40) -> 0 | M40: =(M18/$E$18)*($E$40) -> -10286.232 | N40: =(N18/$E$18)*($E$40) -> -5705.4717 | P40: =SUM(G40:N40) -> -384769.68 | W40: 131.17 | X40: 0 | AC40: 165.23 | AD40: 12954.98
A41: 35 | P41: =SUM(N41:N41) -> 0 | W41: 131.18 | X41: 0 | AC41: 165.24 | AD41: 3167.28
A42: 36 | C42: Net Investment Rate Base | E42: =SUM(E35,E37,E38,E39)-E40 -> 1.5766798e+08 | G42: =SUM(G35,G37,G38,G39)-G40 -> 1444870.7 | H42: =SUM(H35,H37,H38,H39)-H40 -> 94628255 | I42: =SUM(I35,I37,I38,I39)-I40 -> 24486709 | J42: =SUM(J35,J37,J38,J39)-J40 -> 22890030 | K42: =SUM(K35,K37,K38,K39)-K40 -> 5909488.1 | L42: =SUM(L35,L37,L38,L39)-L40 -> 1719581.1 | M42: =SUM(M35,M37,M38,M39)-M40 -> 4224496.2 | N42: =SUM(N35,N37,N38,N39)-N40 -> 2364553.7 | P42: =SUM(G42:N42) -> 1.5766798e+08 | W42: 131.19 | X42: 0 | AC42: 165.25 | AD42: 3980.32
A43: 37 | W43: 131.2 | AC43: 165.26 | AD43: 35342.01
A44: 38 | C44: Rate Base Percent | E44: =(E42/$E$42) -> 1 | G44: =(G42/$E$42) -> 0.0091640083 | H44: =(H42/$E$42) -> 0.60017419 | I44: =(I42/$E$42) -> 0.15530553 | J44: =(J42/$E$42) -> 0.14517868 | K44: =(K42/$E$42) -> 0.037480584 | L44: =(L42/$E$42) -> 0.010906343 | M44: =(M42/$E$42) -> 0.026793621 | N44: =(N42/$E$42) -> 0.014997044 | P44: =SUM(G44,H44,I44,J44,K44,L44,M44,N44) -> 1 | W44: 131.21 | X44: 0 | AC44: 165.27 | AD44: 12566
A45: 39 | W45: 131.22 | X45: 0
A46: 40 | W46: 131.23 | X46: 0
T47: Materials | W47: 131.4 | X47: 0
C48: CLASSIFICATION OF RATE BASE | R48: Prepayments | T48: & Supplies | W48: 135 | X48: 0
P49: December 2012 | W49: 135.1 | X49: 0
G50: Consumer | H50: Demand | I50: Energy | J50: Lighting | P50: January 2013 | W50: 135.15 | X50: 0
E51: Total | G51: Related | H51: Related | I51: Related | J51: Related | M51: Total | P51: February
P52: March
B53: Stations | E53: =(G42) -> 1444870.7 | H53: =(E53) -> 1444870.7 | K53: =SUM(G53:J53) -> 1444870.7 | P53: April
B54: Lines | E54: =(H42) -> 94628255 | G54: =($E$54)*('3.1 PlantClass.'!D100) -> 32178189 | H54: =(E54-G54) -> 62450065 | K54: =SUM(G54:J54) -> 94628255 | P54: May | X54: =SUM(X33:X53) -> 205662.54 | AA54: =SUM(AA33:AA53) -> 1370924.6 | AD54: =SUM(AD33:AD53) -> 301267.41 | AG54: =SUM(AG33:AG53) -> -384769.68
B55: Transformers | E55: =(I42) -> 24486709 | G55: =(E55*'3.1 PlantClass.'!E172) -> 5102078.6 | H55: =(E55-G55) -> 19384631 | K55: =SUM(G55:J55) -> 24486709 | P55: June
B56: Services | E56: =(J42) -> 22890030 | G56: =(E56) -> 22890030 | K56: =SUM(G56:J56) -> 22890030 | P56: July
B57: Meters | E57: =(K42) -> 5909488.1 | G57: =(E57) -> 5909488.1 | K57: =SUM(G57:J57) -> 5909488.1 | P57: August
B58: Consumer & Accounting Services | E58: =(L42) -> 1719581.1 | G58: =(E58) -> 1719581.1 | K58: =SUM(G58:J58) -> 1719581.1 | P58: September
B59: Lighting | E59: =(M42+N42) -> 6589049.9 | J59: =(E59) -> 6589049.9 | K59: =SUM(G59:J59) -> 6589049.9 | P59: October
E60: =SUM(E53:E59) -> 1.5766798e+08 | G60: =SUM(G53:G59) -> 67799367 | H60: =SUM(H53:H59) -> 83279567 | I60: =SUM(I53:I59) -> 0 | J60: =SUM(J53:J59) -> 6589049.9 | K60: =SUM(K53:K59) -> 1.5766798e+08 | L60: =SUM(L53:L59) -> 0 | M60: =SUM(M53:M59) -> 0 | P60: November
P61: December
R62: =SUM(R49:R61) -> 0 | T62: =SUM(T49:T61) -> 0
R63: =(R62/13) -> 0 | T63: =(T62/13) -> 0
B65: ALLOCATION OF RATE BASE TO RATE CLASSES
J68: =('4 Allocation'!E3) -> GS 1 | K68: =('4 Allocation'!F3) -> GS 1 | L68: =('4 Allocation'!G3) -> SC1 | M68: =('4 Allocation'!H3) -> SC2 | N68: =('4 Allocation'!I3) -> LP1 | O68: =('4 Allocation'!J3) -> LP2 | P68: =('4 Allocation'!K3) -> 0 | Q68: =('4 Allocation'!L3) -> Total | ... T68: =('4 Allocation'!O3) -> Total
D69: Classi- | J69: =('4 Allocation'!E4) -> Residential | K69: =('4 Allocation'!F4) -> Residential | L69: =('4 Allocation'!G4) -> Gen Service | M69: =('4 Allocation'!H4) -> Gen Service | N69: =('4 Allocation'!I4) -> Large Power | O69: =('4 Allocation'!J4) -> Large Power | P69: =('4 Allocation'!K4) -> Outdoor | Q69: =('4 Allocation'!L4) -> EKPC Sched | ... T69: =('4 Allocation'!O4) -> for All
C70: Function | D70: fication | H70: Amount | J70: =('4 Allocation'!E5) -> & Farm | K70: =('4 Allocation'!F5) -> & Farm TOD | L70: =('4 Allocation'!G5) -> 0-100 kW | M70: =('4 Allocation'!H5) -> 0-100 kW TOD | N70: =('4 Allocation'!I5) -> under 500 kW | O70: =('4 Allocation'!J5) -> over 500 kW | P70: =('4 Allocation'!K5) -> Lights | Q70: =('4 Allocation'!L5) -> E Rates | ... T70: =('4 Allocation'!O5) -> Rate Classes
C72: Stations | D72: Demand | H72: =(H53) -> 1444870.7 | J72: =($H$72*'4.1 kW & kWh'!C82) -> 1028717.2 | K72: =($H$72*'4.1 kW & kWh'!D82) -> 1237.0436 | L72: =($H$72*'4.1 kW & kWh'!E82) -> 176869.64 | M72: =($H$72*'4.1 kW & kWh'!F82) -> 4760.8402 | N72: =($H$72*'4.1 kW & kWh'!G82) -> 39949.982 | O72: =($H$72*'4.1 kW & kWh'!H82) -> 56168.866 | P72: =($H$72*'4.1 kW & kWh'!I82) -> 16686.556 | Q72: =SUM(J72:P72) -> 1324390.1 | R72: =($H$72*'4.1 kW & kWh'!K82) -> 82441.874 | S72: =($H$72*'4.1 kW & kWh'!L82) -> 38038.694 | T72: =SUM(Q72:S72) -> 1444870.7
C73: Lines | D73: Consumer | H73: =(G54) -> 32178189 | J73: =($H$73*'4.21 Consumer Alloc'!I4) -> 30510054 | K73: =($H$73*'4.21 Consumer Alloc'!I5) -> 21903.649 | L73: =($H$73*'4.21 Consumer Alloc'!I6) -> 1472155.8 | M73: =($H$73*'4.21 Consumer Alloc'!I7) -> 24785.708 | N73: =($H$73*'4.21 Consumer Alloc'!I8) -> 32855.473 | O73: =($H$73*'4.21 Consumer Alloc'!I9) -> 13833.883 | P73: =($H$73*'4.21 Consumer Alloc'!I12) -> 99142.831 | Q73: =SUM(J73:P73) -> 32174731 | R73: =($H$73*'4.21 Consumer Alloc'!I10) -> 2882.059 | S73: =($H$73*'4.21 Consumer Alloc'!I11) -> 576.41181 | T73: =SUM(Q73:S73) -> 32178189
C74: Lines | D74: Demand | H74: =(H54) -> 62450065 | J74: =($H$74*'4.1 kW & kWh'!C82) -> 44463118 | K74: =($H$74*'4.1 kW & kWh'!D82) -> 53467.383 | L74: =($H$74*'4.1 kW & kWh'!E82) -> 7644643 | M74: =($H$74*'4.1 kW & kWh'!F82) -> 205772.58 | N74: =($H$74*'4.1 kW & kWh'!G82) -> 1726714.3 | O74: =($H$74*'4.1 kW & kWh'!H82) -> 2427725.4 | P74: =($H$74*'4.1 kW & kWh'!I82) -> 721224.77 | Q74: =SUM(J74:P74) -> 57242666 | R74: =($H$74*'4.1 kW & kWh'!K82) -> 3563294.9 | S74: =($H$74*'4.1 kW & kWh'!L82) -> 1644104.8 | T74: =SUM(Q74:S74) -> 62450065
C75: Transformers | D75: Consumer | H75: =(G55) -> 5102078.6 | J75: =($H$75*'4.21 Consumer Alloc'!I20) -> 4796894.5 | K75: =($H$75*'4.21 Consumer Alloc'!I21) -> 3443.7662 | L75: =($H$75*'4.21 Consumer Alloc'!I22) -> 231457.34 | M75: =($H$75*'4.21 Consumer Alloc'!I23) -> 3896.8934 | N75: =($H$75*'4.21 Consumer Alloc'!I24) -> 9279.2285 | O75: =($H$75*'4.21 Consumer Alloc'!I25) -> 52819.447 | P75: =($H$75*'4.21 Consumer Alloc'!I28) -> 4287.4873 | Q75: =SUM(J75:P75) -> 5102078.6 | R75: =($H$75*'4.21 Consumer Alloc'!I26) -> 0 | S75: =($H$75*'4.21 Consumer Alloc'!I27) -> 0 | T75: =SUM(Q75:S75) -> 5102078.6
C76: Transformers | D76: Demand | H76: =(H55) -> 19384631 | J76: =($H$76*'4.1 kW & kWh'!C110) -> 16616553 | K76: =($H$76*'4.1 kW & kWh'!D110) -> 14245.101 | L76: =($H$76*'4.1 kW & kWh'!E110) -> 1565812.1 | M76: =($H$76*'4.1 kW & kWh'!F110) -> 16003.755 | N76: =($H$76*'4.1 kW & kWh'!G110) -> 390037.31 | O76: =($H$76*'4.1 kW & kWh'!H110) -> 619700 | P76: =($H$76*'4.1 kW & kWh'!I110) -> 162279.84 | Q76: =SUM(J76:P76) -> 19384631 | R76: =($H$76*'4.1 kW & kWh'!K110) -> 0 | S76: =($H$76*'4.1 kW & kWh'!L110) -> 0 | T76: =SUM(Q76:S76) -> 19384631
C77: Services | D77: Consumer | H77: =(G56) -> 22890030 | J77: =($H$77*'4.21 Consumer Alloc'!J37) -> 21267352 | K77: =($H$77*'4.21 Consumer Alloc'!J38) -> 15268.168 | L77: =($H$77*'4.21 Consumer Alloc'!J39) -> 1231417.9 | M77: =($H$77*'4.21 Consumer Alloc'!J40) -> 20732.564 | N77: =($H$77*'4.21 Consumer Alloc'!J41) -> 32005.541 | O77: =($H$77*'4.21 Consumer Alloc'!J45) -> 323253.62 | P77: =($H$77*'4.21 Consumer Alloc'!P37) -> 0 | Q77: =SUM(J77:P77) -> 22890030 | R77: =($H$77*'4.21 Consumer Alloc'!J43) -> 0 | S77: =($H$77*'4.21 Consumer Alloc'!J44) -> 0 | T77: =SUM(Q77:S77) -> 22890030
C78: Meters | D78: Consumer | H78: =(G57) -> 5909488.1 | J78: =($H$78*'4.21 Consumer Alloc'!I54) -> 5068967.6 | K78: =($H$78*'4.21 Consumer Alloc'!I55) -> 3639.0918 | L78: =($H$78*'4.21 Consumer Alloc'!I56) -> 818155.19 | M78: =($H$78*'4.21 Consumer Alloc'!I57) -> 4117.9196 | N78: =($H$78*'4.21 Consumer Alloc'!I58) -> 9571.0007 | O78: =($H$78*'4.21 Consumer Alloc'!I59) -> 4029.895 | P78: =($H$78*'4.21 Consumer Alloc'!I62) -> 0 | Q78: =SUM(J78:P78) -> 5908480.7 | R78: =($H$78*'4.21 Consumer Alloc'!I60) -> 839.56146 | S78: =($H$78*'4.21 Consumer Alloc'!I61) -> 167.91229 | T78: =SUM(Q78:S78) -> 5909488.1
C79: Consum. & Acct. Serives | D79: Consumer | H79: =(G58) -> 1719581.1 | J79: =($H$79*'4.21 Consumer Alloc'!I71) -> 1552439.3 | K79: =($H$79*'4.21 Consumer Alloc'!I72) -> 1393.1508 | L79: =($H$79*'4.21 Consumer Alloc'!I73) -> 117043 | M79: =($H$79*'4.21 Consumer Alloc'!I74) -> 1970.5752 | N79: =($H$79*'4.21 Consumer Alloc'!I75) -> 4179.4525 | O79: =($H$79*'4.21 Consumer Alloc'!I76) -> 1759.7695 | P79: =($H$79*'4.21 Consumer Alloc'!I79) -> 33096.864 | Q79: =SUM(J79:P79) -> 1711882.1 | R79: =($H$79*'4.21 Consumer Alloc'!I77) -> 5499.2795 | S79: =($H$79*'4.21 Consumer Alloc'!I78) -> 2199.7118 | T79: =SUM(Q79:S79) -> 1719581.1
C80: Lighting | D80: Lighting | H80: =(J59) -> 6589049.9 | P80: =(H80) -> 6589049.9 | Q80: =SUM(J80:P80) -> 6589049.9 | T80: =SUM(Q80:S80) -> 6589049.9
H81: =SUM(H72:H80) -> 1.5766798e+08 | J81: =SUM(J72:J80) -> 1.2530409e+08 | K81: =SUM(K72:K80) -> 114597.35 | L81: =SUM(L72:L80) -> 13257554 | M81: =SUM(M72:M80) -> 282040.84 | N81: =SUM(N72:N80) -> 2244592.3 | O81: =SUM(O72:O80) -> 3499290.9 | P81: =SUM(P72:P80) -> 7625768.3 | Q81: =SUM(Q72:Q80) -> 1.5232794e+08 | ... V81: =SUM(V72:V80) -> 0
C83: Percent of Total | J83: =(J81/$H$81) -> 0.79473392 | K83: =(K81/$H$81) -> 0.00072682703 | L83: =(L81/$H$81) -> 0.084085264 | M83: =(M81/$H$81) -> 0.0017888276 | N83: =(N81/$H$81) -> 0.014236196
I89: =('4 Allocation'!J3) -> LP2 | J89: =('4 Allocation'!M3) -> B-2 | K89: =('4 Allocation'!#REF!) -> #REF! | L89: =('4 Allocation'!N3) -> G-1 | M89: =('4 Allocation'!O3) -> Total | N89: =('4 Allocation'!#REF!) -> #REF!
D90: Classi- | I90: =('4 Allocation'!J4) -> Large Power | J90: =('4 Allocation'!M4) -> Large Indust. | K90: =('4 Allocation'!#REF!) -> #REF! | L90: =('4 Allocation'!N4) -> Large Indust. | M90: =('4 Allocation'!O4) -> for All | N90: =('4 Allocation'!#REF!) -> #REF!
C91: Function | D91: fication | I91: =('4 Allocation'!J5) -> over 500 kW | J91: =('4 Allocation'!M5) -> Rate | K91: =('4 Allocation'!#REF!) -> #REF! | L91: =('4 Allocation'!N5) -> Rate | M91: =('4 Allocation'!O5) -> Rate Classes | N91: =('4 Allocation'!#REF!) -> #REF!
C93: Stations | D93: Demand | I93: =($H$72*'4.1 kW & kWh'!H55) -> #VALUE! | J93: =($H$72*'4.1 kW & kWh'!#REF!) -> #REF! | K93: =($H$72*'4.1 kW & kWh'!J55) -> #VALUE! | L93: =($H$72*'4.1 kW & kWh'!K55) -> #VALUE! | M93: =($H$72*'4.1 kW & kWh'!L55) -> #VALUE! | N93: =SUM(J72:N72)+SUM(I93:M93) -> #VALUE!
C94: Lines | D94: Consumer | I94: =($H$73*#REF!) -> #REF! | J94: =($H$73*#REF!) -> #REF! | K94: =($H$73*#REF!) -> #REF! | L94: =($H$73*#REF!) -> #REF! | M94: =($H$73*#REF!) -> #REF! | N94: =SUM(J73:N73)+SUM(I94:M94) -> #REF!
C95: Lines | D95: Demand | I95: =($H$74*'4.1 kW & kWh'!H84) -> 2427725.4 | J95: =($H$74*'4.1 kW & kWh'!#REF!) -> #REF! | K95: =($H$74*'4.1 kW & kWh'!J84) -> #VALUE! | L95: =($H$74*'4.1 kW & kWh'!K84) -> 3563294.9 | M95: =($H$74*'4.1 kW & kWh'!L84) -> 1644104.8 | N95: =SUM(J74:N74)+SUM(I95:M95) -> #REF!
C96: Transformers | D96: Consumer | I96: =($H$75*#REF!) -> #REF! | J96: =($H$75*#REF!) -> #REF! | K96: =($H$75*#REF!) -> #REF! | L96: =($H$75*#REF!) -> #REF! | M96: =($H$75*#REF!) -> #REF! | N96: =SUM(J75:N75)+SUM(I96:M96) -> #REF!
C97: Transformers | D97: Demand | I97: =($H$76*'4.1 kW & kWh'!H110) -> 619700 | J97: =($H$76*'4.1 kW & kWh'!#REF!) -> #REF! | K97: =($H$76*'4.1 kW & kWh'!J110) -> 19384631 | L97: =($H$76*'4.1 kW & kWh'!K110) -> 0 | M97: =($H$76*'4.1 kW & kWh'!L110) -> 0 | N97: =SUM(J76:N76)+SUM(I97:M97) -> #REF!
C98: Services | D98: Consumer | I98: =($H$77*#REF!) -> #REF! | J98: =($H$77*#REF!) -> #REF! | K98: =($H$77*#REF!) -> #REF! | L98: =($H$77*#REF!) -> #REF! | M98: =($H$77*#REF!) -> #REF! | N98: =SUM(J77:N77)+SUM(I98:M98) -> #REF!
C99: Meters | D99: Consumer | I99: =($H$78*#REF!) -> #REF! | J99: =($H$78*#REF!) -> #REF! | K99: =($H$78*#REF!) -> #REF! | L99: =($H$78*#REF!) -> #REF! | M99: =($H$78*#REF!) -> #REF! | N99: =SUM(J78:N78)+SUM(I99:M99) -> #REF!
C100: Consum. & Acct. Serives | D100: Consumer | I100: =($H$79*#REF!) -> #REF! | J100: =($H$79*#REF!) -> #REF! | K100: =($H$79*#REF!) -> #REF! | L100: =($H$79*#REF!) -> #REF! | M100: =($H$79*#REF!) -> #REF! | N100: =SUM(J79:N79)+SUM(I100:M100) -> #REF!
C101: Lighting | D101: Lighting | M101: =(H80) -> 6589049.9 | N101: =SUM(J80:N80)+SUM(I101:M101) -> 6589049.9
I102: =SUM(I93:I101) -> #VALUE! | J102: =SUM(J93:J101) -> #REF! | K102: =SUM(K93:K101) -> #VALUE! | L102: =SUM(L93:L101) -> #VALUE! | M102: =SUM(M93:M101) -> #VALUE! | N102: =SUM(N93:N101) -> #VALUE!
I104: =(I102/$H$81) -> #VALUE! | J104: =(J102/$H$81) -> #REF! | K104: =(K102/$H$81) -> #VALUE! | L104: =(L102/$H$81) -> #VALUE! | M104: =(M102/$H$81) -> #VALUE! | N104: =(N102/$H$81) -> #VALUE!

Sheet 3Classific. Summary
A2: SUMMARY OF CLASSIFICATION OF EXPENSES
D5: Consumer | E5: Demand | F5: Energy
D6: Related | E6: Related | F6: Related | G6: Security | H6: Street
D7: Costs | E7: Costs | F7: Costs | G7: Lighting | H7: Lighting | I7: Total
B9: Purchased Power | D9: 0 | E9: =('3.2 Classific. 2'!G41) -> 20122912 | F9: =('3.2 Classific. 2'!F41) -> 63981621 | G9: 0 | H9: 0 | I9: =SUM(D9:H9) -> 84104533
B10: Stations | E10: =('3.2 Classific. 2'!K36) -> 243904.86 | I10: =SUM(D10:H10) -> 243904.86
B11: Lines | D11: =('3.2 Classific. 2'!F18) -> 6359168.4 | E11: =('3.2 Classific. 2'!G18) -> 12341604 | F11: 0 | G11: 0 | H11: 0 | I11: =SUM(D11:H11) -> 18700773
B12: Transformers | D12: =('3.2 Classific. 2'!F36) -> 575268.74 | E12: =('3.2 Classific. 2'!G36) -> 2185652.8 | F12: 0 | G12: 0 | H12: 0 | I12: =SUM(D12:H12) -> 2760921.5
B13: Services | D13: =('3.2 Classific. 2'!K18) -> 4523609.2 | E13: 0 | F13: 0 | G13: 0 | H13: 0 | I13: =SUM(D13:H13) -> 4523609.2
B14: Meters | D14: =('3.2 Classific. 2'!L18) -> 1799304 | E14: 0 | G14: 0 | H14: 0 | I14: =SUM(D14:H14) -> 1799304
B15: Consumer Services | I15: =SUM(D15:H15) -> 0
B16: & Accounting | D16: =('3.2 Classific. 2'!M18) -> 5523784 | E16: 0 | F16: 0 | I16: =SUM(D16:H16) -> 5523784
B17: Lighting | G17: =('3.2 Classific. 2'!L36) -> 969560.57 | H17: =('3.2 Classific. 2'!M36) -> 606367.06 | I17: =SUM(D17:H17) -> 1575927.6
D18: =SUM(D9:D17) -> 18781134 | E18: =SUM(E9:E17) -> 34894074 | F18: =SUM(F9:F17) -> 63981621 | G18: =SUM(G9:G17) -> 969560.57 | H18: =SUM(H9:H17) -> 606367.06 | I18: =SUM(D18:H18) -> 1.1923276e+08
K38: =SUM('2.22Rate Base'!G66:J66) -> 0

Sheet 3.2 Classific. 2
K1: Consumer Related Costs
F3: Consumer | G3: Demand | M3: Consumer
D4: 2 | F4: Related | G4: Related | M4: Services &
B5: =('2.1 SummaryFunc.'!B4) -> Expense | D5: =('2.1 SummaryFunc.'!F4) -> Lines | F5: Costs | G5: Costs | H5: Total | I5: =(B5) -> Expense | K5: Services | L5: Meters | M5: Accounting | N5: Total
B6: =('2.1 SummaryFunc.'!B5) -> Purchased Power | D6: =('2.1 SummaryFunc.'!F5) -> 0 | F6: =(D6*'3.1 PlantClass.'!$D$100) -> 0 | G6: =(D6*'3.1 PlantClass.'!$F$100) -> 0 | H6: =(F6+G6) -> 0 | I6: =(B6) -> Purchased Power | K6: =('2.1 SummaryFunc.'!H5) -> 0 | L6: =('2.1 SummaryFunc.'!I5) -> 0 | M6: =('2.1 SummaryFunc.'!J5) -> 0 | N6: =SUM(K6:M6) -> 0
B7: =('2.1 SummaryFunc.'!B6) -> Distibution Operations | D7: =('2.1 SummaryFunc.'!F6) -> 1333889.1 | F7: =(D7*'3.1 PlantClass.'!$D$100) -> 453586.9 | G7: =(D7*'3.1 PlantClass.'!$F$100) -> 880302.22 | H7: =(F7+G7) -> 1333889.1 | I7: =(B7) -> Distibution Operations | K7: =('2.1 SummaryFunc.'!H6) -> 322660.1 | L7: =('2.1 SummaryFunc.'!I6) -> 620948.57 | M7: =('2.1 SummaryFunc.'!J6) -> 0 | N7: =SUM(K7:M7) -> 943608.67 | Q7: =SUM(H7,H25,N7,N25) -> 2736324.5
B8: =('2.1 SummaryFunc.'!B7) -> Distribution Maintenance | D8: =('2.1 SummaryFunc.'!F7) -> 4659911.3 | F8: =(D8*'3.1 PlantClass.'!$D$100) -> 1584595.5 | G8: =(D8*'3.1 PlantClass.'!$F$100) -> 3075315.8 | H8: =(F8+G8) -> 4659911.3 | I8: =(B8) -> Distribution Maintenance | K8: =('2.1 SummaryFunc.'!H7) -> 1127205.7 | L8: =('2.1 SummaryFunc.'!I7) -> 218842.7 | M8: =('2.1 SummaryFunc.'!J7) -> 0 | N8: =SUM(K8:M8) -> 1346048.4 | Q8: =SUM(H8,H26,N8,N26) -> 6246137.8
B9: =('2.1 SummaryFunc.'!B8) -> Consumer Accounts | D9: =('2.1 SummaryFunc.'!F8) -> 0 | F9: =(D9*'3.1 PlantClass.'!$D$100) -> 0 | G9: =(D9*'3.1 PlantClass.'!$F$100) -> 0 | H9: =(F9+G9) -> 0 | I9: =(B9) -> Consumer Accounts | K9: =('2.1 SummaryFunc.'!H8) -> 0 | L9: =('2.1 SummaryFunc.'!I8) -> 0 | M9: =('2.1 SummaryFunc.'!J8) -> 2905364.9 | N9: =SUM(K9:M9) -> 2905364.9 | Q9: =SUM(H9,H27,N9,N27) -> 2905364.9
B10: =('2.1 SummaryFunc.'!B9) -> Customer Service | D10: =('2.1 SummaryFunc.'!F9) -> 0 | F10: =(D10*'3.1 PlantClass.'!$D$100) -> 0 | G10: =(D10*'3.1 PlantClass.'!$F$100) -> 0 | H10: =(F10+G10) -> 0 | I10: =(B10) -> Customer Service | K10: =('2.1 SummaryFunc.'!H9) -> 0 | L10: =('2.1 SummaryFunc.'!I9) -> 0 | M10: =('2.1 SummaryFunc.'!J9) -> 1024972.7 | N10: =SUM(K10:M10) -> 1024972.7 | Q10: =SUM(H10,H28,N10,N28) -> 1024972.7
B11: =('2.1 SummaryFunc.'!B10) -> Administative & General | D11: =('2.1 SummaryFunc.'!F10) -> 2044408.4 | F11: =(D11*'3.1 PlantClass.'!$D$100) -> 695197.87 | G11: =(D11*'3.1 PlantClass.'!$F$100) -> 1349210.6 | H11: =(F11+G11) -> 2044408.4 | I11: =(B11) -> Administative & General | K11: =('2.1 SummaryFunc.'!H10) -> 494530.63 | L11: =('2.1 SummaryFunc.'!I10) -> 286442.03 | M11: =('2.1 SummaryFunc.'!J10) -> 1340587.7 | N11: =SUM(K11:M11) -> 2121560.4 | Q11: =SUM(H11,H29,N11,N29) -> 4404390.4
B12: =('2.1 SummaryFunc.'!B11) -> Depreciation | D12: =('2.1 SummaryFunc.'!F11) -> 5004877.9 | F12: =(D12*'3.1 PlantClass.'!$D$100) -> 1701900.9 | G12: =(D12*'3.1 PlantClass.'!$F$100) -> 3302977 | H12: =(F12+G12) -> 5004877.9 | I12: =(B12) -> Depreciation | K12: =('2.1 SummaryFunc.'!H11) -> 1210651.1 | L12: =('2.1 SummaryFunc.'!I11) -> 319750.94 | M12: =('2.1 SummaryFunc.'!J11) -> 150047.46 | N12: =SUM(K12:M12) -> 1680449.5 | Q12: =SUM(H12,H30,N12,N30) -> 8384293.9
B13: =('2.1 SummaryFunc.'!B12) -> Miscellaneous | D13: =('2.1 SummaryFunc.'!F12) -> 12166.281 | F13: =(D13*'3.1 PlantClass.'!$D$100) -> 4137.1248 | G13: =(D13*'3.1 PlantClass.'!$F$100) -> 8029.1563 | H13: =(F13+G13) -> 12166.281 | I13: =(B13) -> Miscellaneous | K13: =('2.1 SummaryFunc.'!H12) -> 2942.9533 | L13: =('2.1 SummaryFunc.'!I12) -> 759.77829 | M13: =('2.1 SummaryFunc.'!J12) -> 221.0852 | N13: =SUM(K13:M13) -> 3923.8168 | Q13: =SUM(H13,H31,N13,N31) -> 20271.25
B14: =('2.1 SummaryFunc.'!B13) -> Interest on Long Term Debt | D14: =('2.1 SummaryFunc.'!F13) -> 2821895.9 | F14: =(D14*'3.1 PlantClass.'!$D$100) -> 959581.25 | G14: =(D14*'3.1 PlantClass.'!$F$100) -> 1862314.6 | H14: =(F14+G14) -> 2821895.9 | I14: =(B14) -> Interest on Long Term Debt | K14: =('2.1 SummaryFunc.'!H13) -> 682600.36 | L14: =('2.1 SummaryFunc.'!I13) -> 176226.01 | M14: =('2.1 SummaryFunc.'!J13) -> 51279.386 | N14: =SUM(K14:M14) -> 910105.76 | Q14: =SUM(H14,H32,N14,N32) -> 4701794.8
B15: =('2.1 SummaryFunc.'!B14) -> Short Term Interest | D15: =('2.1 SummaryFunc.'!F14) -> 1727.8175 | F15: =(D15*'3.1 PlantClass.'!$D$100) -> 587.54162 | G15: =(D15*'3.1 PlantClass.'!$F$100) -> 1140.2759 | H15: =(F15+G15) -> 1727.8175 | I15: =(B15) -> Short Term Interest | K15: =('2.1 SummaryFunc.'!H14) -> 417.9491 | L15: =('2.1 SummaryFunc.'!I14) -> 107.90135 | M15: =('2.1 SummaryFunc.'!J14) -> 31.397834 | N15: =SUM(K15:M15) -> 557.24828 | Q15: =SUM(H15,H33,N15,N33) -> 2878.86
B16: =('2.1 SummaryFunc.'!B15) -> Total Costs | D16: =('2.1 SummaryFunc.'!F15) -> 15878877 | F16: =(D16*'3.1 PlantClass.'!$D$100) -> 5399587.1 | G16: =(D16*'3.1 PlantClass.'!$F$100) -> 10479290 | H16: =(F16+G16) -> 15878877 | I16: =(B16) -> Total Costs | K16: =('2.1 SummaryFunc.'!H15) -> 3841008.8 | L16: =('2.1 SummaryFunc.'!I15) -> 1623077.9 | M16: =('2.1 SummaryFunc.'!J15) -> 5472504.6 | N16: =SUM(K16:M16) -> 10936591
B17: =('2.1 SummaryFunc.'!B16) -> Margin Requirements | D17: =('2.1 SummaryFunc.'!F16) -> 2821896 | F17: =(D17*'3.1 PlantClass.'!$D$100) -> 959581.3 | G17: =(D17*'3.1 PlantClass.'!$F$100) -> 1862314.7 | H17: =(F17+G17) -> 2821896 | I17: =(B17) -> Margin Requirements | K17: =('2.1 SummaryFunc.'!H16) -> 682600.39 | L17: =('2.1 SummaryFunc.'!I16) -> 176226.02 | M17: =('2.1 SummaryFunc.'!J16) -> 51279.388 | N17: =SUM(K17:M17) -> 910105.81
B18: =('2.1 SummaryFunc.'!B17) -> Revenue Requirements | D18: =(D16+D17) -> 18700773 | F18: =(F16+F17) -> 6359168.4 | G18: =(G16+G17) -> 12341604 | H18: =(F18+G18) -> 18700773 | I18: =(B18) -> Revenue Requirements | K18: =('2.1 SummaryFunc.'!H17) -> 4523609.2 | L18: =('2.1 SummaryFunc.'!I17) -> 1799304 | M18: =('2.1 SummaryFunc.'!J17) -> 5523784 | N18: =SUM(K18:M18) -> 11846697
B19: =('2.1 SummaryFunc.'!B18)
F21: =(F3) -> Consumer | G21: =(G3) -> Demand | L21: Outdoor | M21: Street
D22: 3 | F22: =(F4) -> Related | G22: =(G4) -> Related | K22: Stations | L22: Lighting | M22: Lighting | N22: Total
B23: =(B5) -> Expense | D23: Transformers | F23: =(F5) -> Costs | G23: =(G5) -> Costs | H23: =(H5) -> Total | I23: =(B23) -> Expense
B24: =(B6) -> Purchased Power | D24: 0 | F24: 0 | G24: 0 | H24: =(F24+G24) -> 0 | I24: =(B24) -> Purchased Power | L24: =('2.1 SummaryFunc.'!K5) -> 0
B25: =(B7) -> Distibution Operations | D25: =('2.1 SummaryFunc.'!G6) -> 0 | F25: 0 | G25: 0 | H25: =(F25+G25) -> 0 | I25: =(B25) -> Distibution Operations | K25: =('2.1 SummaryFunc.'!E6) -> 60656.899 | L25: =('2.1 SummaryFunc.'!K6) -> 366877.94 | M25: =('2.1 SummaryFunc.'!L6) -> 31291.837 | N25: =SUM(K25:M25) -> 458826.68 | Q25: =SUM(L25:M25) -> 398169.78 | AB25: =SUM(#REF!,#REF!,#REF!,#REF!,#REF!,#REF!,#REF!,#REF!) -> #REF!
B26: =(B8) -> Distribution Maintenance | D26: =('2.1 SummaryFunc.'!G7) -> 19006.906 | F26: =(D26*'3.1 PlantClass.'!$E$172) -> 3960.3006 | G26: =(D26*'3.1 PlantClass.'!$E$173) -> 15046.605 | H26: =(F26+G26) -> 19006.906 | I26: =(B26) -> Distribution Maintenance | K26: =('2.1 SummaryFunc.'!E7) -> 169.6823 | L26: =('2.1 SummaryFunc.'!K7) -> 0 | M26: =('2.1 SummaryFunc.'!L7) -> 221001.48 | N26: =SUM(K26:M26) -> 221171.16 | Q26: =SUM(L26:M26) -> 221001.48
B27: =(B9) -> Consumer Accounts | D27: =('2.1 SummaryFunc.'!G8) -> 0 | F27: =(D27*'3.1 PlantClass.'!$E$172) -> 0 | G27: =(D27*'3.1 PlantClass.'!$E$173) -> 0 | H27: =(F27+G27) -> 0 | I27: =(B27) -> Consumer Accounts | K27: =('2.1 SummaryFunc.'!E8) -> 0 | L27: =('2.1 SummaryFunc.'!K8) -> 0 | M27: =('2.1 SummaryFunc.'!L8) -> 0 | N27: =SUM(K27:M27) -> 0 | Q27: =SUM(L27:M27) -> 0
B28: =(B10) -> Customer Service | D28: =('2.1 SummaryFunc.'!G9) -> 0 | F28: =(D28*'3.1 PlantClass.'!$E$172) -> 0 | G28: =(D28*'3.1 PlantClass.'!$E$173) -> 0 | H28: =(F28+G28) -> 0 | I28: =(B28) -> Customer Service | K28: =('2.1 SummaryFunc.'!E9) -> 0 | L28: =('2.1 SummaryFunc.'!K9) -> 0 | M28: =('2.1 SummaryFunc.'!L9) -> 0 | N28: =SUM(K28:M28) -> 0 | Q28: =SUM(L28:M28) -> 0
B29: =(B11) -> Administative & General | D29: =('2.1 SummaryFunc.'!G10) -> 6483.0118 | F29: =(D29*'3.1 PlantClass.'!$E$172) -> 1350.8077 | G29: =(D29*'3.1 PlantClass.'!$E$173) -> 5132.2041 | H29: =(F29+G29) -> 6483.0118 | I29: =(B29) -> Administative & General | K29: =('2.1 SummaryFunc.'!E10) -> 20747.167 | L29: =('2.1 SummaryFunc.'!K10) -> 125137.36 | M29: =('2.1 SummaryFunc.'!L10) -> 86054.013 | N29: =SUM(K29:M29) -> 231938.54 | Q29: =SUM(L29:M29) -> 211191.37
B30: =(B12) -> Depreciation | D30: =('2.1 SummaryFunc.'!G11) -> 1271406.8 | F30: =(D30*'3.1 PlantClass.'!$E$172) -> 264911.76 | G30: =(D30*'3.1 PlantClass.'!$E$173) -> 1006495 | H30: =(F30+G30) -> 1271406.8 | I30: =(B30) -> Depreciation | K30: =('2.1 SummaryFunc.'!E11) -> 75944.39 | L30: =('2.1 SummaryFunc.'!K11) -> 224968.77 | M30: =('2.1 SummaryFunc.'!L11) -> 126646.5 | N30: =SUM(K30:M30) -> 427559.66 | Q30: =SUM(L30:M30) -> 351615.27
B31: =(B13) -> Miscellaneous | D31: =('2.1 SummaryFunc.'!G12) -> 3148.2372 | F31: =(D31*'3.1 PlantClass.'!$E$172) -> 655.97028 | G31: =(D31*'3.1 PlantClass.'!$E$173) -> 2492.2669 | H31: =(F31+G31) -> 3148.2372 | I31: =(B31) -> Miscellaneous | K31: =('2.1 SummaryFunc.'!E12) -> 185.7659 | L31: =('2.1 SummaryFunc.'!K12) -> 543.14019 | M31: =('2.1 SummaryFunc.'!L12) -> 304.00884 | N31: =SUM(K31:M31) -> 1032.9149 | Q31: =SUM(L31:M31) -> 847.14902
B32: =(B14) -> Interest on Long Term Debt | D32: =('2.1 SummaryFunc.'!G13) -> 730214.72 | F32: =(D32*'3.1 PlantClass.'!$E$172) -> 152148.37 | G32: =(D32*'3.1 PlantClass.'!$E$173) -> 578066.35 | H32: =(F32+G32) -> 730214.72 | I32: =(B32) -> Interest on Long Term Debt | K32: =('2.1 SummaryFunc.'!E13) -> 43087.286 | L32: =('2.1 SummaryFunc.'!K13) -> 125978.11 | M32: =('2.1 SummaryFunc.'!L13) -> 70513.025 | N32: =SUM(K32:M32) -> 239578.42 | Q32: =SUM(L32:M32) -> 196491.13
B33: =(B15) -> Short Term Interest | D33: =('2.1 SummaryFunc.'!G14) -> 447.10287 | F33: =(D33*'3.1 PlantClass.'!$E$172) -> 93.158863 | G33: =(D33*'3.1 PlantClass.'!$E$173) -> 353.94401 | H33: =(F33+G33) -> 447.10287 | I33: =(B33) -> Short Term Interest | K33: =('2.1 SummaryFunc.'!E14) -> 26.381897 | L33: =('2.1 SummaryFunc.'!K14) -> 77.135083 | M33: =('2.1 SummaryFunc.'!L14) -> 43.174391 | N33: =SUM(K33:M33) -> 146.69137 | Q33: =SUM(L33:M33) -> 120.30947
B34: =(B16) -> Total Costs | D34: =('2.1 SummaryFunc.'!G15) -> 2030706.7 | F34: =(D34*'3.1 PlantClass.'!$E$172) -> 423120.37 | G34: =(D34*'3.1 PlantClass.'!$E$173) -> 1607586.4 | H34: =(F34+G34) -> 2030706.7 | I34: =(B34) -> Total Costs | K34: =SUM(K25:K33) -> 200817.57 | L34: =SUM(L25:L33) -> 843582.46 | M34: =SUM(M25:M33) -> 535854.04 | N34: =SUM(K34:M34) -> 1580254.1 | Q34: =SUM(L34:M34) -> 1379436.5
B35: =(B17) -> Margin Requirements | D35: =('2.1 SummaryFunc.'!G16) -> 730214.76 | F35: =(D35*'3.1 PlantClass.'!$E$172) -> 152148.38 | G35: =(D35*'3.1 PlantClass.'!$E$173) -> 578066.38 | H35: =(F35+G35) -> 730214.76 | I35: =(B35) -> Margin Requirements | K35: =('2.1 SummaryFunc.'!E16) -> 43087.288 | L35: =('2.1 SummaryFunc.'!K16) -> 125978.11 | M35: =('2.1 SummaryFunc.'!L16) -> 70513.028 | N35: =SUM(K35:M35) -> 239578.43 | Q35: =SUM(L35:M35) -> 196491.14
B36: =(B18) -> Revenue Requirements | D36: =SUM(D34:D35) -> 2760921.5 | F36: =(D36*'3.1 PlantClass.'!$E$172) -> 575268.74 | G36: =(D36*'3.1 PlantClass.'!$E$173) -> 2185652.8 | H36: =(F36+G36) -> 2760921.5 | I36: =(B36) -> Revenue Requirements | K36: =SUM(K34:K35) -> 243904.86 | L36: =SUM(L34:L35) -> 969560.57 | M36: =SUM(M34:M35) -> 606367.06 | N36: =SUM(K36:M36) -> 1819832.5 | Q36: =SUM(L36:M36) -> 1575927.6
F38: Energy | G38: Demand
F39: Related | G39: Related
F40: Costs | G40: Costs
B41: Purchased Power | D41: =('2.1 SummaryFunc.'!D5) -> 84104533 | F41: =('2 Functionalization2'!E9+'2 Functionalization2'!E10) -> 63981621 | G41: =(D41-F41) -> 20122912 | H41: =(F41+G41) -> 84104533
B46: Lines | H46: =(H18) -> 18700773
B47: Transformers | H47: =(H36) -> 2760921.5
B48: Purchased Power | H48: =(H41) -> 84104533
B49: Consumer Related | H49: =(N18) -> 11846697
B50: Lighting | H50: =(L36) -> 969560.57
B51: Stations | H51: =(K36) -> 243904.86
H52: =SUM(H46:H51) -> 1.1862639e+08
H54: =('2.1 SummaryFunc.'!M17-'3.2 Classific. 2'!H52) -> 606367.06

Sheet 3.1 PlantClass.
A1: ACCOUNT 364 - POLES
B2: 1. Actual Data
B3: Poles | C3: Size | D3: Investment | E3: Number | F3: Unit Cost
E4: of Units
B5: 35' Pole and under | C5: 35 | D5: 6746445 | E5: 35343 | F5: =(D5/E5) -> 190.8849
B6: 40' -45' Pole | C6: 42.5 | D6: 27431997 | E6: 55439 | F6: =(D6/E6) -> 494.81407
B7: 50' Pole and over | C7: 50 | D7: 2445520.2 | E7: 3477 | F7: =(D7/E7) -> 703.34201
D9: 0
B10: Subtotal | D10: =SUM(D5:D9) -> 36623962 | E10: =SUM(E5:E9) -> 94259
B11: All other items | D11: =3779766.07+14605299.56+272020.81+106048.94 -> 18763135
B12: Total Investment in Poles | D12: =SUM(D10:D11) -> 55387098
B15: 2. Determination of Demand and Consumer Related Investment
D17: Formula | E17: Slope | F17: Y intercept
B18: Linear Curve | D18: y=mx+b | E18: =(B39) -> 34.163807 | F18: =(C39) -> -988.94815
B20: Use Actual Value to 35 foot poles | F20: =F5 -> 190.8849
B21: Number of poles | F21: =(E10) -> 94259
B22: Consumer Related Investment | F22: =(F20*F21) -> 17992620
B23: Total Investment in poles | F23: =D12 -> 55387098
B24: Percent Customer Related | F24: =(F22/F23) -> 0.32485219
B25: Percent Demand Related | F25: =(1-F24) -> 0.67514781
B29: Data For Analysis | D29: Relevant Data
B30: Used linear | E30: Average Cost | F30: Predicted
D31: Size of Pole | E31: Per Unit | F31: Cost
D32: =C5 -> 35 | E32: =F5 -> 190.8849 | F32: =$B$39*D32+$C$39 -> 206.7851
D33: =C6 -> 42.5 | E33: =F6 -> 494.81407 | F33: =$B$39*D33+$C$39 -> 463.01366
D34: =C7 -> 50 | E34: =F7 -> 703.34201 | F34: =$B$39*D34+$C$39 -> 719.24221
B36: LINEAR CURVE DATA
B37: Formula | C37: y=mx+b
B38: SLOPE - m | C38: Zero Intercept - b
B39: =INDEX(LINEST(E32:E34,D32:D34),1) -> 34.163807 | C39: =INDEX(LINEST(E32:E34,D32:D34),2) -> -988.94815
B40: REGRESSION LINE DATA
A42: ACCOUNT 365 - CONDUCTOR
B43: 1. Actual Data
D44: Number
B45: Conductor | C45: Investment | D45: of Units | E45: Unit Cost | F45: Amps
B46: #2 ACSR | C46: 7377935.4 | D46: 8599915 | E46: =(C46/D46) -> 0.85790794 | F46: 180
B47: #4 ACSR | C47: 2318726.9 | D47: 13017732 | E47: =(C47/D47) -> 0.17812065 | F47: 140
B48: #1/0 ACSR | C48: 6432100.2 | D48: 8842042 | E48: =(C48/D48) -> 0.7274451 | F48: 230
B49: #2/0 ACSR | C49: 62273.64 | D49: 189062 | E49: =(C49/D49) -> 0.32938211 | F49: 270
B50: #3/0 ACSR | C50: 840195.76 | D50: 1386287 | E50: =(C50/D50) -> 0.60607635 | F50: 300
B51: #4/0 ACSR | C51: 1944344.8 | D51: 2590666 | E51: =(C51/D51) -> 0.7505193 | F51: 340
B52: #6 ACWC | C52: -22216.76 | D52: -272425 | E52: =(C52/D52) -> 0.08155184 | F52: 140 | J52: {=LOGEST(C86:C89,D86:D89)} -> #VALUE! | K52: #VALUE!
B53: #8 ACWC | C53: 193417.42 | D53: 3115791 | E53: =(C53/D53) -> 0.062076506 | F53: 100
B54: 336.4 MCM ACSR | C54: 7416917.3 | D54: 4989425 | E54: =(C54/D54) -> 1.4865275 | F54: 530
B55: #556.1 ACSR | C55: 189440.28 | D55: 83755 | E55: =(C55/D55) -> 2.2618385 | F55: 730 | K55: {=INDEX(LINEST(C86:C89,D86:D89),2)} -> #VALUE!
B59: SUBTOTAL | C59: =SUM(C46:C56) -> 26753135 | D59: =SUM(D46:D56) -> 42542250 | E59: =(C59/D59) -> 0.62886037
B60: All other OH Conductor Invest. | C60: =(C61-C59) -> 16129443
B61: TOTAL | C61: 42882578 | E61: =(E59) -> 0.62886037
B63: 2. Demand and Consumer Investment Percents
B64: Use linest Line
B66: Formula | F66: y=b*m^x
B67: Intercept | F67: =INDEX(LOGEST($C$81:$C$86,$D$81:$D$86),2) -> 0.22618591
B68: Slope | F68: =INDEX(LOGEST($C$82:$C$86,$D$82:$D$86),1) -> 1.0018519
B70: Use zero intercept | E70: =D67 | F70: =(F67) -> 0.22618591
B71: Amount of Conduit | F71: =(D59) -> 42542250
B72: Consumer Related Investment | F72: =(F70*F71) -> 9622457.4
B73: Total Investment in conductor | F73: =(C59) -> 26753135
B74: Percent Customer Related | F74: =(F72/F73) -> 0.35967588
B75: Percent Demand Related | F75: =(1-F74) -> 0.64032412
B79: Data for Analysis
B80: Conuctor | C80: Per Unit Cost | D80: Amp Size
B81: #4ACSR | C81: =(E47) -> 0.17812065 | D81: =(F47) -> 140
B82: =B46 -> #2 ACSR | C82: =E46 -> 0.85790794 | D82: =F46 -> 180
B83: 1/0 ACSR | C83: =(E48) -> 0.7274451 | D83: =(F48) -> 230
B84: 3/0 ACSR | C84: =(E50) -> 0.60607635 | D84: =(F50) -> 300
B85: =B51 -> #4/0 ACSR | C85: =E51 -> 0.7505193 | D85: =F51 -> 340
B86: =B54 -> 336.4 MCM ACSR | C86: =E54 -> 1.4865275 | D86: =F54 -> 530
A91: Breakdown of Lines into Demand Related and Consumer Related Components
A94: Acct | B94: Total | C94: Consumer-Related | E94: Demand-Related
A95: No. | B95: Investment | C95: Percent | D95: Amount | E95: Percent | F95: Amount
A96: 364 | B96: =D12 -> 55387098 | C96: =F24 -> 0.32485219 | D96: =(C96*B96) -> 17992620 | E96: =F25 -> 0.67514781 | F96: =(E96*B96) -> 37394478
A97: 365 | B97: =C61 -> 42882578 | C97: =F74 -> 0.35967588 | D97: =(C97*B97) -> 15423829 | E97: =F75 -> 0.64032412 | F97: =(E97*B97) -> 27458749
B98: =(B96+B97) -> 98269676 | D98: =(D96+D97) -> 33416449 | F98: =(F96+F97) -> 64853227
A100: % | B100: =(D100+F100) -> 1 | D100: =(D98/B98) -> 0.34004843 | F100: =(F98/B98) -> 0.65995157
A104: ACCOUNT 368 - TRANSFORMERS
C106: Size In | D106: Number of | E106: Total | F106: Per Unit | H106: Transformer | I106: Conventilan | K106: CSP | O106: SP
B107: Type of Transfomer | C107: KVA | D107: Transfomers | E107: Cost | F107: Cost | H107: KVA | I107: Number | J107: Investment | K107: Number | L107: Investment | O107: Number | P107: Investment
B108: 1.5 KVA CONV | C108: 1.5 | D108: 91 | E108: 3610.63 | F108: =(E108/D108) -> 39.677253 | H108: 1.5 | I108: =(D108) -> 91 | J108: =(E108) -> 3610.63 | K108: =(D109) -> 460 | L108: =(E109) -> 35606.78 | M108: =(L108/K108) -> 77.406043
B109: 1.5 KVA CSP | C109: 1.5 | D109: 460 | E109: 35606.78 | F109: =(E109/D109) -> 77.406043 | H109: 3 | K109: =(D110) -> 882 | L109: =(E110) -> 99946.91 | M109: =(L109/K109) -> 113.31849
B110: 3 KVA CSP | C110: 3 | D110: 882 | E110: 99946.91 | F110: =(E110/D110) -> 113.31849 | H110: 5 | I110: =(D111) -> 1339 | J110: =(E111) -> 196856.5 | K110: =(D112) -> 1231 | L110: =(E112) -> 202205.59 | M110: =(L110/K110) -> 164.26124
B111: 5 KVA CONV | C111: 5 | D111: 1339 | E111: 196856.5 | F111: =(E111/D111) -> 147.01755 | H111: 7.5 | K111: =(D113) -> 216 | L111: =(E113) -> 44477.85 | M111: =(L111/K111) -> 205.91597
B112: 5 KVA CSP | C112: 5 | D112: 1231 | E112: 202205.59 | F112: =(E112/D112) -> 164.26124 | H112: 10 | I112: =(D115) -> 1290 | J112: =(E115) -> 839957.8 | K112: =(D114) -> 4668 | L112: =(E114) -> 1769056 | M112: =(L112/K112) -> 378.97514 | O112: =(D116) -> 2789 | P112: =(E116) -> 967853.7
B113: 7.5 KVA CSP | C113: 7.5 | D113: 216 | E113: 44477.85 | F113: =(E113/D113) -> 205.91597 | H113: 15 | I113: =(D117) -> 3048 | J113: =(E117) -> 2446321.6 | K113: =(D118) -> 12284 | L113: =(E118) -> 6565864.2 | M113: =(L113/K113) -> 534.50539 | O113: =(D119) -> 1483 | P113: =(E119) -> 695485.29
B114: 10 KVA CSP | C114: 10 | D114: 4668 | E114: 1769056 | F114: =(E114/D114) -> 378.97514 | H114: 25 | I114: =(D122) -> 1709 | J114: =(E122) -> 1416872.2 | K114: =(D120) -> 6738 | L114: =(E120) -> 4683795.2 | M114: =(L114/K114) -> 695.13137 | O114: =(D121) -> 304 | P114: =(E121) -> 169846.57
B115: 10 KVA CONV | C115: 10 | D115: 1290 | E115: 839957.8 | F115: =(E115/D115) -> 651.13008 | H115: 37.5 | I115: =(D124) -> 203 | J115: =(E124) -> 112392.57 | K115: =(D123) -> 72 | L115: =(E123) -> 56306.17 | M115: =(L115/K115) -> 782.03014
B116: 10 KVA SP | C116: 10 | D116: 2789 | E116: 967853.7 | F116: =(E116/D116) -> 347.02535 | H116: 50 | I116: =(D126) -> 1066 | J116: =(E126) -> 1023519.8 | K116: =(D125) -> 809 | L116: =(E125) -> 739693.49 | M116: =(L116/K116) -> 914.33064
B117: 15 KVA CONV | C117: 15 | D117: 3048 | E117: 2446321.6 | F117: =(E117/D117) -> 802.59895
B118: 15 KVA CSP | C118: 15 | D118: 12284 | E118: 6565864.2 | F118: =(E118/D118) -> 534.50539
B119: 15 KVA SP | C119: 15 | D119: 1483 | E119: 695485.29 | F119: =(E119/D119) -> 468.97187 | I119: Padmount | L119: Total | N119: Average
B120: 25 KVA CSP | C120: 25 | D120: 6738 | E120: 4683795.2 | F120: =(E120/D120) -> 695.13137 | I120: Number | J120: Investment | L120: Number | M120: Investment | N120: Cost
B121: 25 KVA SP | C121: 25 | D121: 304 | E121: 169846.57 | F121: =(E121/D121) -> 558.70582 | H121: 1.5 | L121: =SUM(I108,K108,O108) -> 551 | M121: =SUM(J108,L108,P108) -> 39217.41 | N121: =(M121/L121) -> 71.174973
B122: 25 KVA CONV | C122: 25 | D122: 1709 | E122: 1416872.2 | F122: =(E122/D122) -> 829.0651 | H122: 3 | L122: =SUM(I109,K109,O109) -> 882 | M122: =SUM(J109,L109,P109) -> 99946.91 | N122: =(M122/L122) -> 113.31849
B123: 37.5 KVA CSP | C123: 37.5 | D123: 72 | E123: 56306.17 | F123: =(E123/D123) -> 782.03014 | H123: 5 | L123: =SUM(I110,K110,O110) -> 2570 | M123: =SUM(J110,L110,P110) -> 399062.09 | N123: =(M123/L123) -> 155.27708
B124: 37.5 KVA CONV | C124: 37.5 | D124: 203 | E124: 112392.57 | F124: =(E124/D124) -> 553.65798 | H124: 7.5 | L124: =SUM(I111,K111,O111) -> 216 | M124: =SUM(J111,L111,P111) -> 44477.85 | N124: =(M124/L124) -> 205.91597
B125: 50 KVA CSP | C125: 50 | D125: 809 | E125: 739693.49 | F125: =(E125/D125) -> 914.33064 | H125: 10 | L125: =SUM(I112,K112,O112) -> 8747 | M125: =SUM(J112,L112,P112) -> 3576867.5 | N125: =(M125/L125) -> 408.92506
B126: 50 KVA CONV | C126: 50 | D126: 1066 | E126: 1023519.8 | F126: =(E126/D126) -> 960.14989 | H126: 15 | I126: =(D148) -> 23 | J126: =(E148) -> 31338.42 | L126: =SUM(I113,K113,O113)+I126 -> 16838 | M126: =SUM(J113,L113,P113)+J126 -> 9739009.5 | N126: =(M126/L126) -> 578.39467
B127: 75 KVA CONV | C127: 75 | D127: 181 | E127: 243914.24 | F127: =(E127/D127) -> 1347.5925 | H127: 25 | I127: =(D149) -> 2476 | J127: =(E149) -> 3287784.2 | L127: =SUM(I114,K114,O114)+I127 -> 11227 | M127: =SUM(J114,L114,P114)+J127 -> 9558298.2 | N127: =(M127/L127) -> 851.36708
B128: 100 KVA CONV | C128: 100 | D128: 77 | E128: 156788.9 | F128: =(E128/D128) -> 2036.2195 | H128: 37.5 | I128: =(D150) -> 48 | J128: =(E150) -> 39712.25 | L128: =SUM(I115,K115,O115)+I128 -> 323 | M128: =SUM(J115,L115,P115)+J128 -> 208410.99 | N128: =(M128/L128) -> 645.23526
B129: 167 KVA CONV | C129: 167 | D129: 44 | E129: 93800.83 | F129: =(E129/D129) -> 2131.837 | H129: 50 | I129: =(D151) -> 2344 | J129: =(E151) -> 3505309.5 | L129: =SUM(I116,K116,O116)+I129 -> 4219 | M129: =SUM(J116,L116,P116)+J129 -> 5268522.8 | N129: =(M129/L129) -> 1248.761
B130: 250 KVA CONV | C130: 250 | D130: 4 | E130: 14768 | F130: =(E130/D130) -> 3692
...

Sheet 4 Allocation
E3: GS 1 | F3: GS 1 | G3: SC1 | H3: SC2 | I3: LP1 | J3: LP2 | L3: Total | M3: B-2 | N3: G-1 | O3: Total
B4: Classifi- | D4: Enviro | E4: Residential | F4: Residential | G4: Gen Service | H4: Gen Service | I4: Large Power | J4: Large Power | K4: Outdoor | L4: EKPC Sched | M4: Large Indust. | N4: Large Indust. | O4: for All
A5: Function | B5: cation | C5: Amount | D5: watts | E5: & Farm | F5: & Farm TOD | G5: 0-100 kW | H5: 0-100 kW TOD | I5: under 500 kW | J5: over 500 kW | K5: Lights | L5: E Rates | M5: Rate | N5: Rate | O5: Rate Classes
A6: Purchased Power | B6: Demand | C6: =('2 Functionalization2'!G7) -> 18577420 | D6: 0 | E6: =('Power Cost'!$I$88+'Power Cost'!$H$88)*'4.1 kW & kWh'!C53 -> 11812563 | F6: =('Power Cost'!$I$88+'Power Cost'!$H$88)*'4.1 kW & kWh'!D53 -> 14124.3 | G6: =('Power Cost'!$I$88+'Power Cost'!$H$88)*'4.1 kW & kWh'!E53 -> 1996883.1 | H6: =('Power Cost'!$I$88+'Power Cost'!$H$88)*'4.1 kW & kWh'!F53 -> 24717.525 | I6: =('Power Cost'!$I$88+'Power Cost'!$H$88)*'4.1 kW & kWh'!G53 -> 422554.21 | J6: =('Power Cost'!$I$88+'Power Cost'!$H$88)*'4.1 kW & kWh'!H53 -> 892232.81 | K6: =('Power Cost'!$I$88+'Power Cost'!$H$88)*'4.1 kW & kWh'!I53 -> 134616.66 | L6: =SUM(D6:K6) -> 15297692 | M6: =('Power Cost'!I87+'Power Cost'!J87+'Power Cost'!K87) -> 2145306.9 | N6: =('Power Cost'!I89) -> 1134421.9 | O6: =SUM(L6:N6) -> 18577420 | P6: =(O6-C6) -> 0
A7: Purchased Power | B7: Energy | C7: =('3Classific. Summary'!F9) -> 63981621 | D7: =('Power Cost'!U91) -> 6455.25 | E7: =('Power Cost'!$M$88+'Power Cost'!$N$88)*('4.1 kW & kWh'!C24) -> 41269234 | F7: =('Power Cost'!$M$88+'Power Cost'!$N$88)*('4.1 kW & kWh'!D24) -> 22738.629 | G7: =('Power Cost'!$M$88+'Power Cost'!$N$88)*('4.1 kW & kWh'!E24) -> 3659720.5 | H7: =('Power Cost'!$M$88+'Power Cost'!$N$88)*('4.1 kW & kWh'!F24) -> 34263.286 | I7: =('Power Cost'!$M$88+'Power Cost'!$N$88)*('4.1 kW & kWh'!G24) -> 1949315.9 | J7: =('Power Cost'!$M$88+'Power Cost'!$N$88)*('4.1 kW & kWh'!H24) -> 4207349.6 | K7: =('Power Cost'!$M$88+'Power Cost'!$N$88)*('4.1 kW & kWh'!I24) -> 468275.34 | L7: =SUM(D7:K7) -> 51617352 | M7: =('Power Cost'!L87+'Power Cost'!M87) -> 8505282.9 | N7: =('Power Cost'!M89) -> 3858985.9 | O7: =SUM(L7:N7) -> 63981621 | P7: =(O7-C7) -> 1.4901161e-08
A8: Metering & Substation | B8: Demand | C8: =('2 Functionalization2'!G8)+'2 Functionalization2'!E11 -> 1545492 | E8: =($C$8-$M$8-$N$8)*'4.1 kW & kWh'!C83 -> 1015352.4 | F8: =($C$8-$M$8-$N$8)*'4.1 kW & kWh'!D83 -> 1220.9723 | G8: =($C$8-$M$8-$N$8)*'4.1 kW & kWh'!E83 -> 174571.8 | H8: =($C$8-$M$8-$N$8)*'4.1 kW & kWh'!F83 -> 4698.9886 | I8: =($C$8-$M$8-$N$8)*'4.1 kW & kWh'!G83 -> 39430.962 | J8: =($C$8-$M$8-$N$8)*'4.1 kW & kWh'!H83 -> 55439.134 | K8: =($C$8-$M$8-$N$8)*'4.1 kW & kWh'!I83 -> 16469.769 | L8: =SUM(D8:K8) -> 1307184 | M8: =(60*('Power Cost'!C49+'Power Cost'!C52)) -> 172860 | N8: =('Power Cost'!C51*12)+(12*'Power Cost'!C52) -> 65448 | O8: =SUM(L8:N8) -> 1545492 | P8: =(O8-C8) -> 0 | Q8: =SUM(O6:O8) -> 84104533
A9: Stations | B9: Demand | C9: =('3Classific. Summary'!E10) -> 243904.86 | E9: =($C$9*'4.1 kW & kWh'!C84) -> 173655.07 | F9: =($C$9*'4.1 kW & kWh'!D84) -> 208.82211 | G9: =($C$9*'4.1 kW & kWh'!E84) -> 29856.904 | H9: =($C$9*'4.1 kW & kWh'!F84) -> 803.66503 | I9: =($C$9*'4.1 kW & kWh'!G84) -> 6743.8524 | J9: =($C$9*'4.1 kW & kWh'!H84) -> 9481.7199 | K9: =($C$9*'4.1 kW & kWh'!I84) -> 2816.8141 | L9: =SUM(D9:K9) -> 223566.85 | M9: =($C$9*'4.1 kW & kWh'!K84) -> 13916.798 | N9: =($C$9*'4.1 kW & kWh'!L84) -> 6421.2128 | O9: =SUM(L9:N9) -> 243904.86 | P9: =(O9-C9) -> 0 | Q9: =SUM(O6,O8) -> 20122912
A10: Lines | B10: Consumer | C10: =('3Classific. Summary'!D11) -> 6359168.4 | E10: =($C$10*'4.21 Consumer Alloc'!I4) -> 6029505.4 | F10: =($C$10*'4.21 Consumer Alloc'!I5) -> 4328.6771 | G10: =($C$10*'4.21 Consumer Alloc'!I6) -> 290932.67 | H10: =($C$10*'4.21 Consumer Alloc'!I7) -> 4898.2399 | I10: =($C$10*'4.21 Consumer Alloc'!I8) -> 6493.0156 | J10: =($C$10*'4.21 Consumer Alloc'!I9) -> 2733.9013 | K10: =($C$10*'4.21 Consumer Alloc'!I12) -> 19592.959 | L10: =SUM(D10:K10) -> 6358484.9 | M10: =($C$10*'4.21 Consumer Alloc'!I10) -> 569.56277 | N10: =($C$10*'4.21 Consumer Alloc'!I11) -> 113.91255 | O10: =SUM(L10:N10) -> 6359168.4 | P10: =(O10-C10) -> 9.3132257e-10
A11: Lines | B11: Demand | C11: =('3Classific. Summary'!E11) -> 12341604 | E11: =($C$11*'4.1 kW & kWh'!C82) -> 8786959.8 | F11: =($C$11*'4.1 kW & kWh'!D82) -> 10566.415 | G11: =($C$11*'4.1 kW & kWh'!E82) -> 1510761.6 | H11: =($C$11*'4.1 kW & kWh'!F82) -> 40665.511 | I11: =($C$11*'4.1 kW & kWh'!G82) -> 341239.44 | J11: =($C$11*'4.1 kW & kWh'!H82) -> 479775.74 | K11: =($C$11*'4.1 kW & kWh'!I82) -> 142531.01 | L11: =SUM(D11:K11) -> 11312499 | M11: =($C$11*'4.1 kW & kWh'!K82) -> 704191.03 | N11: =($C$11*'4.1 kW & kWh'!L82) -> 324913.85 | O11: =SUM(L11:N11) -> 12341604 | P11: =(O11-C11) -> -1.8626451e-09
A12: Transformers | B12: Consumer | C12: =('3Classific. Summary'!D12) -> 575268.74 | E12: =($C$12*'4.21 Consumer Alloc'!I20) -> 540858.67 | F12: =($C$12*'4.21 Consumer Alloc'!I21) -> 388.29097 | G12: =($C$12*'4.21 Consumer Alloc'!I22) -> 26097.241 | H12: =($C$12*'4.21 Consumer Alloc'!I23) -> 439.38189 | I12: =($C$12*'4.21 Consumer Alloc'!I24) -> 1046.2501 | J12: =($C$12*'4.21 Consumer Alloc'!I25) -> 5955.4897 | K12: =($C$12*'4.21 Consumer Alloc'!I28) -> 483.42207 | L12: =SUM(D12:K12) -> 575268.74 | M12: =($C$12*'4.21 Consumer Alloc'!R20) -> 0 | N12: =($C$12*'4.21 Consumer Alloc'!U20) -> 0 | O12: =SUM(L12:N12) -> 575268.74 | P12: =(O12-C12) -> -1.1641532e-10
A13: Transformers | B13: Demand | C13: =('3Classific. Summary'!E12) -> 2185652.8 | E13: =($C$13*'4.1 kW & kWh'!C110) -> 1873546.9 | F13: =($C$13*'4.1 kW & kWh'!D110) -> 1606.1613 | G13: =($C$13*'4.1 kW & kWh'!E110) -> 176548.19 | H13: =($C$13*'4.1 kW & kWh'!F110) -> 1804.4528 | I13: =($C$13*'4.1 kW & kWh'!G110) -> 43977.424 | J13: =($C$13*'4.1 kW & kWh'!H110) -> 69872.314 | K13: =($C$13*'4.1 kW & kWh'!I110) -> 18297.35 | L13: =SUM(D13:K13) -> 2185652.8 | M13: 0 | N13: 0 | O13: =SUM(L13:N13) -> 2185652.8 | P13: =(O13-C13) -> 0
A14: Services | B14: Consumer | C14: =('3Classific. Summary'!D13) -> 4523609.2 | E14: =($C$14*'4.21 Consumer Alloc'!J37) -> 4202929.9 | F14: =($C$14*'4.21 Consumer Alloc'!J38) -> 3017.3497 | G14: =($C$14*'4.21 Consumer Alloc'!J39) -> 243357.19 | H14: =($C$14*'4.21 Consumer Alloc'!J40) -> 4097.2432 | I14: =($C$14*'4.21 Consumer Alloc'!J41) -> 6325.049 | J14: =($C$14*'4.21 Consumer Alloc'!J42) -> 0 | K14: =($C$14*'4.21 Consumer Alloc'!J45) -> 63882.532 | L14: =SUM(D14:K14) -> 4523609.2 | M14: 0 | O14: =SUM(L14:N14) -> 4523609.2 | P14: =(O14-C14) -> -9.3132257e-10
A15: Meters | B15: Consumer | C15: =('3Classific. Summary'!D14) -> 1799304 | E15: =($C$15*'4.21 Consumer Alloc'!I54) -> 1543384.7 | F15: =($C$15*'4.21 Consumer Alloc'!I55) -> 1108.0202 | G15: =($C$15*'4.21 Consumer Alloc'!I56) -> 249109.54 | H15: =($C$15*'4.21 Consumer Alloc'!I57) -> 1253.8123 | I15: =($C$15*'4.21 Consumer Alloc'!I58) -> 2914.1508 | J15: =($C$15*'4.21 Consumer Alloc'!I59) -> 1227.0109 | K15: 0 | L15: =SUM(D15:K15) -> 1798997.2 | M15: =($C$15*'4.21 Consumer Alloc'!I60) -> 255.62726 | N15: =($C$15*'4.21 Consumer Alloc'!I61) -> 51.125452 | O15: =SUM(L15:N15) -> 1799304 | P15: =(O15-C15) -> 2.3283064e-10
A16: Consumer Services | J16: =SUM(D16:I16) -> 0 | L16: =SUM(D16:K16) -> 0 | O16: =SUM(L16:N16) -> 0 | P16: =(O16-C16) -> 0
A17: & Accounting | B17: Consumer | C17: =('3Classific. Summary'!D16) -> 5523784 | E17: =($C$17*'4.21 Consumer Alloc'!I71) -> 4986877 | F17: =($C$17*'4.21 Consumer Alloc'!I72) -> 4475.1971 | G17: =($C$17*'4.21 Consumer Alloc'!I73) -> 375975.44 | H17: =($C$17*'4.21 Consumer Alloc'!I74) -> 6330.0485 | I17: =($C$17*'4.21 Consumer Alloc'!I75) -> 13425.591 | J17: =($C$17*'4.21 Consumer Alloc'!I76) -> 5652.8805 | K17: =($C$17*'4.21 Consumer Alloc'!I79) -> 106316.55 | L17: =SUM(D17:K17) -> 5499052.7 | M17: =($C$17*'4.21 Consumer Alloc'!I77) -> 17665.252 | N17: =($C$17*'4.21 Consumer Alloc'!I78) -> 7066.1006 | O17: =SUM(L17:N17) -> 5523784 | P17: =(O17-C17) -> 0
A18: Lighting | B18: Lighting | C18: =('3Classific. Summary'!I17) -> 1575927.6 | K18: =(C18) -> 1575927.6 | L18: =SUM(D18:K18) -> 1575927.6 | O18: =SUM(L18:N18) -> 1575927.6 | P18: =(O18-C18) -> 0
A19: Revenue Requirements | C19: =SUM(C6:C18) -> 1.1923276e+08 | D19: =SUM(D6:D18) -> 6455.25 | E19: =SUM(E6:E18) -> 82234866 | F19: =SUM(F6:F18) -> 63782.834 | G19: =SUM(G6:G18) -> 8733814.1 | H19: =SUM(H6:H18) -> 123972.15 | I19: =SUM(I6:I18) -> 2833465.8 | J19: =SUM(J6:J18) -> 5729720.6 | ... O19: =SUM(O6:O18) -> 1.1923276e+08 | P19: =(O19-C19) -> 1.4901161e-08 | Q19: =SUM(O9:O18) -> 35128224
P20: =(O20-C20) -> 0 | Q20: =(O19-Q8) -> 35128224
D21: SUMMARY | J21: SUMMARY
D22: =D3 -> 0 | E22: =E3 -> GS 1 | F22: =F3 -> GS 1 | G22: =G3 -> SC1 | H22: =H3 -> SC2 | I22: =I3 -> LP1 | J22: =J3 -> LP2 | K22: =K3 -> 0 | ... O22: =O3 -> Total
D23: =D4 -> Enviro | E23: =E4 -> Residential | F23: =F4 -> Residential | G23: =G4 -> Gen Service | H23: =H4 -> Gen Service | I23: =I4 -> Large Power | J23: =J4 -> Large Power | K23: =K4 -> Outdoor | ... O23: =O4 -> for All
C24: Amount | D24: =D5 -> watts | E24: =E5 -> & Farm | F24: =F5 -> & Farm TOD | G24: =G5 -> 0-100 kW | H24: =H5 -> 0-100 kW TOD | I24: =I5 -> under 500 kW | J24: =J5 -> over 500 kW | K24: =K5 -> Lights | ... O24: =O5 -> Rate Classes
A25: Consumer Related | C25: =SUM(C10,C12,C14,C15,C17) -> 18781134 | D25: =SUM(D10,D12,D14,D15,D17) -> 0 | E25: =SUM(E10,E12,E14,E15,E17) -> 17303556 | F25: =SUM(F10,F12,F14,F15,F17) -> 13317.535 | G25: =SUM(G10,G12,G14,G15,G17) -> 1185472.1 | H25: =SUM(H10,H12,H14,H15,H17) -> 17018.726 | I25: =SUM(I10,I12,I14,E15,I17) -> 1570674.6 | J25: =SUM(J10,J12,J14,J15,J17) -> 15569.282 | K25: =SUM(K10,K12,K14,K15,K17) -> 190275.46 | L25: =SUM(L10,L12,L14,L15,L17) -> 18755413 | M25: =SUM(M10,M12,M14,M15,M17) -> 18490.442 | N25: =SUM(N10,N12,N14,N15,N17) -> 7231.1386 | O25: =SUM(O10,O12,O14,O15,O17) -> 18781134
A26: Demand Related | C26: =SUM(C6,C8,C11,C13,C9) -> 34894074 | D26: =SUM(D11,D13,D15,D16,D18) -> 0 | E26: =SUM(E6,E11,E13,E9,E8) -> 23662077 | F26: =SUM(F6,F11,F13,F9,F8) -> 27726.67 | G26: =SUM(G6,G11,G13,G9,G8) -> 3888621.6 | H26: =SUM(H6,H11,H13,H9,H8) -> 72690.142 | I26: =SUM(I6,I11,I13,I9,I8) -> 853945.89 | J26: =SUM(J6,J11,J13,J9,J8) -> 1506801.7 | K26: =SUM(K11,K13,K15,K16,K18) -> 1736756 | L26: =SUM(L11,L13,L15,L16,L18) -> 16873077 | M26: =SUM(M6,M11,M13,M9,M8) -> 3036274.7 | N26: =SUM(N6,N11,N13,N9,N8) -> 1531205 | O26: =SUM(O6,O11,O13,O9,O8) -> 34894074
A27: Energy Related | C27: =(C7) -> 63981621 | D27: =D7 -> 6455.25 | E27: =(E7) -> 41269234 | F27: =(F7) -> 22738.629 | G27: =(G7) -> 3659720.5 | H27: =(H7) -> 34263.286 | I27: =(I7) -> 1949315.9 | J27: =(J7) -> 4207349.6 | K27: =SUM(K12,K14,K16,K17,K19) -> 2719892.5 | L27: =SUM(L12,L14,L16,L17,L19) -> 1.1287322e+08 | M27: =(M7) -> 8505282.9 | N27: =(N7) -> 3858985.9 | O27: =(O7) -> 63981621
A28: Lighting | C28: =(C18) -> 1575927.6 | I28: =(I18) | J28: =(J18) | K28: =SUM(K13,K15,K17,K18,K20) -> 1700541.5 | L28: =SUM(L13,L15,L17,L18,L20) -> 11059630 | M28: =(M18) -> 0 | N28: =(N18) -> 0 | O28: =(O18) -> 1575927.6
A29: =(A19) -> Revenue Requirements | C29: =SUM(C25:C28) -> 1.1923276e+08 | D29: =SUM(D25:D28) -> 6455.25 | E29: =SUM(E25:E28) -> 82234866 | F29: =SUM(F25:F28) -> 63782.834 | G29: =SUM(G25:G28) -> 8733814.1 | H29: =SUM(H25:H28) -> 123972.15 | I29: =SUM(I25:I28) -> 4373936.4 | J29: =SUM(J25:J28) -> 5729720.6 | K29: =SUM(K25:K28) -> 6347465.5 | L29: =SUM(L14,L16,L18,L19,L21) -> 1.0837482e+08 | M29: =SUM(M25:M28) -> 11560048 | N29: =SUM(N25:N28) -> 5397422.1 | O29: =SUM(O25:O28) -> 1.1923276e+08
E31: =SUM(E25:H25) -> 18519364 | I31: =SUM(I25:M25) -> 20550423
E32: =SUM(E27:H27) -> 44985956 | I32: =SUM(I29:M29) -> 1.3638599e+08
C33: =C10+C12+C14+C15+C17 -> 18781134
E35: =SUM(E12,E14,E15)+(0.5*E17) -> 8780611.7
E36: =(E35/'12 Inc Stmt Func'!G43) -> 13.852976
D37: =SUM(D8:D18) -> 0 | E37: =SUM(E8:E18) -> 29153070 | F37: =SUM(F8:F18) -> 26919.905 | G37: =SUM(G8:G18) -> 3077210.6 | H37: =SUM(H8:H18) -> 64991.343 | I37: =SUM(I8:I18) -> 461595.73 | J37: =SUM(J8:J18) -> 630138.19 | K37: =SUM(K8:K18) -> 1946318 | ... O37: =SUM(O8:O18) -> 36673716
M39: =SUM('2.22Rate Base'!K80:N80) -> 0
M40: =SUM('2.22Rate Base'!K81:N81) -> 15898785
M41: =SUM('2.22Rate Base'!H82:L82) -> 0
M42: =SUM('2.22Rate Base'!H83:L83) -> 0.87954601
M43: =SUM('2.22Rate Base'!H84:L84) -> 0
M44: =SUM('2.22Rate Base'!H85:L85) -> 0
M45: =SUM('2.22Rate Base'!H86:L86) -> 0
M46: =SUM('2.22Rate Base'!H87:L87) -> 0
M47: =SUM('2.22Rate Base'!H88:L88) -> 0
M48: =SUM('2.22Rate Base'!H89:H89) -> 0
M49: =SUM('2.22Rate Base'!H90:H90) -> 0
E54: =(E25) -> 17303556 | F54: =(F25) -> 13317.535 | G54: =(G25) -> 1185472.1 | H54: =(H25) -> 17018.726
E56: =([8]monthly!$AL$14) -> 311873 | F56: =([8]monthly!$AL$44) -> 20425 | G56: =([8]monthly!$AL$75) -> 4153 | M56: 311873
M57: =(E25/M56) -> 55.482698
E58: =(E54/E56) -> 55.482698 | F58: =(F54/F56) -> 0.6520213 | G58: =(G54/G56) -> 285.44957

Sheet 4.1 kW & kWh
A4: ENERGY KWH | I4: ENERGY KWH
B6: ='4 Allocation'!D3 -> 0 | C6: ='4 Allocation'!E3 -> GS 1 | D6: ='4 Allocation'!F3 -> GS 1 | E6: ='4 Allocation'!G3 -> SC1 | F6: ='4 Allocation'!H3 -> SC2 | G6: ='4 Allocation'!I3 -> LP1 | H6: ='4 Allocation'!J3 -> LP2 | J6: Total | K6: B-2 | L6: ='4 Allocation'!N3 -> G-1 | M6: ='4 Allocation'!O3 -> Total
B7: ='4 Allocation'!D4 -> Enviro | C7: ='4 Allocation'!E4 -> Residential | D7: ='4 Allocation'!F4 -> Residential | E7: ='4 Allocation'!G4 -> Gen Service | F7: ='4 Allocation'!H4 -> Gen Service | G7: ='4 Allocation'!I4 -> Large Power | H7: ='4 Allocation'!J4 -> Large Power | I7: Outdoor | J7: for Sched E | K7: Large Indust | L7: ='4 Allocation'!N4 -> Large Indust. | M7: ='4 Allocation'!O4 -> for All
A8: Month | B8: ='4 Allocation'!D5 -> watts | C8: ='4 Allocation'!E5 -> & Farm | D8: ='4 Allocation'!F5 -> & Farm TOD | E8: ='4 Allocation'!G5 -> 0-100 kW | F8: 0 -100 kW TOD | G8: ='4 Allocation'!I5 -> under 500 kW | H8: ='4 Allocation'!J5 -> over 500 kW | I8: Lights | J8: Rate Classes | K8: Rate | L8: ='4 Allocation'!N5 -> Rate | M8: ='4 Allocation'!O5 -> Rate Classes
A10: January | B10: ='[9]power cost'!$K11 -> 22400 | C10: =[9]monthly!$D$5-B10+9967232 -> 94791278 | D10: =[9]monthly!$D$6 -> 68264 | E10: 6297194.6 | F10: 27586.422 | G10: 3088098.5 | H10: 8860060.6 | I10: 761783 | J10: =SUM(C10:I10) -> 1.1389427e+08 | K10: 14910659 | L10: 7693517.5 | M10: =[9]monthly!$D$16 -> 8193000
A11: February | B11: ='[9]power cost'!$K12 -> 22300 | C11: =[9]monthly!$D$28-B11 -> 91210021 | D11: =[9]monthly!$D$29 -> 79940 | E11: 6698555.8 | F11: 28681.671 | G11: 3519045.6 | H11: 8959354.8 | I11: 757450 | J11: =SUM(C11:I11) -> 1.1125305e+08 | K11: 15686841 | L11: 8652944.4 | M11: =[9]monthly!$D$39 -> 9202200
A12: March | B12: ='[9]power cost'!$K13 -> 22300 | C12: =[9]monthly!$D$51-B12 -> 77569528 | D12: =[9]monthly!$D$52 -> 69966 | E12: 5881176.6 | F12: 38826.063 | G12: 3104981.3 | H12: 8407181.9 | I12: 757303 | J12: =SUM(C12:I12) -> 95828963 | K12: 14024180 | L12: 8442956.6 | M12: =[9]monthly!$D$62 -> 6657086
A13: April | B13: ='[9]power cost'!$K14 -> 22300 | C13: =[9]monthly!$D$74-B13 -> 70192095 | D13: =[9]monthly!$D$75 -> 61586 | E13: 6115516.9 | F13: 28926.179 | G13: 3383527.4 | H13: 7568428.1 | I13: 754585 | J13: =SUM(C13:I13) -> 88104665 | K13: 15181989 | L13: 9029474.2 | M13: =[9]monthly!$D$85 -> 9608403
A14: May | B14: ='[9]power cost'!$K15 -> 22300 | C14: =[9]monthly!$D$97-B14 -> 45494862 | D14: =[9]monthly!$D$98 -> 23880 | E14: 4832354.2 | F14: 29596.162 | G14: 2696909.2 | H14: 6180999.5 | I14: 751816 | J14: =SUM(C14:I14) -> 60010417 | K14: 14983340 | L14: 7939710.1 | M14: =[9]monthly!$D$108 -> 10207157
A15: June | B15: ='[9]power cost'!$K16 -> 22900 | C15: =[9]monthly!$D$120-B15 -> 52727753 | D15: =[9]monthly!$D$121 -> 9575 | E15: 5314498.9 | F15: 44547.508 | G15: 2902577.6 | H15: 6253384.8 | I15: 750281 | J15: =SUM(C15:I15) -> 68002618 | K15: 16663436 | L15: 7603005.5 | M15: =[9]monthly!$D$131 -> 10335610
A16: July | B16: ='[9]power cost'!$K17 -> 22900 | C16: =[9]monthly!$D$143-B16 -> 60554570 | D16: =[9]monthly!$D$144 -> 8960 | E16: 5836864.9 | F16: 55765.486 | G16: 3276981.4 | H16: 5759604.4 | I16: 748732 | J16: =SUM(C16:I16) -> 76241478 | K16: 17689008 | L16: 7385776.8 | M16: =[9]monthly!$D$154 -> 9445089
A17: August | B17: ='[9]power cost'!$K18 -> 22900 | C17: =[9]monthly!$D$166-B17 -> 62816785 | D17: =[9]monthly!$D$167 -> 8429 | E17: 6107165.9 | F17: 60631.36 | G17: 3377909.1 | H17: 6113996.1 | I17: 746269 | J17: =SUM(C17:I17) -> 79231185 | K17: 19233929 | L17: 8290896.5 | M17: =[9]monthly!$D$177 -> 4067400
A18: September | B18: ='[9]power cost'!$K19 -> 22900 | C18: =[9]monthly!$D$189-B18 -> 61312321 | D18: =[9]monthly!$D$190 -> 7870 | E18: 6159317.3 | F18: 57660.078 | G18: 3425672.7 | H18: 5320987.6 | I18: 745410 | J18: =SUM(C18:I18) -> 77029239 | K18: 20015988 | L18: 9503756.9 | M18: =[9]monthly!$D$200 -> 4721100
A19: October | B19: ='[9]power cost'!$K20 -> 22900 | C19: =[9]monthly!$D$212-B19 -> 45844768 | D19: =[9]monthly!$D$213 -> 5719 | E19: 4853487.5 | F19: 67313.038 | G19: 2996739.6 | H19: 4623506.1 | I19: 744042 | J19: =SUM(C19:I19) -> 59135575 | K19: 17964061 | L19: 9945455.3 | M19: =[9]monthly!$D$223 -> 4230000
A20: November | B20: ='[9]power cost'!$K21 -> 22900 | C20: =[9]monthly!$D$235-B20 -> 53321987 | D20: =[9]monthly!$D$236 -> 32885 | E20: 5080669.8 | F20: 101784.94 | G20: 2853472.5 | H20: 5671342.9 | I20: 744423 | J20: =SUM(C20:I20) -> 67806565 | K20: 16496328 | L20: 10025106 | M20: =[9]monthly!$D$246 -> 4396200
A21: December | B21: ='[9]power cost'!$K22 -> 22800 | C21: =[9]monthly!$D$258-B21 -> 78103838 | D21: =[9]monthly!$D$259 -> 60373 | E21: 7229102.4 | F21: 117840.09 | G21: 2875132.1 | H21: 7222378.2 | I21: 746813 | J21: =SUM(C21:I21) -> 96355477 | K21: 15244288 | L21: 9554443.6 | M21: =[9]monthly!$D$269 -> 4043400
B22: =SUM(B10:B21) -> 271800 | C22: =([10]summary!$C$10) -> 793939806 | D22: =SUM(D10:D21) -> 437447 | E22: 70405905 | F22: 659159 | G22: =34051767+3449280 -> 37501047 | H22: 80941225 | I22: 9008707 | J22: =SUM(C22:I22) -> 992893296 | K22: =34208283+26012696+49843353+43068317+44961398 -> 198094047 | L22: =('[10]rate schedules'!$B$244) -> 1.0406704e+08 | M22: =SUM(J22:L22) -> 1.2950544e+09
A24: Percentage | B24: 0 | C24: =(C22/($J$22)) -> 0.79962249 | D24: =(D22/($J$22)) -> 0.00044057806 | E24: =(E22/($J$22)) -> 0.07090984 | F24: =(F22/($J$22)) -> 0.00066387698 | G24: =(G22/($J$22)) -> 0.037769463 | H24: =(H22/($J$22)) -> 0.081520568 | I24: =(I22/($J$22)) -> 0.0090731875 | J24: =J22/$J$22 -> 1
A33: MONTHLY CONTRIBUTIONS TO EKPC COINCIDENT PEAK DEMAND - KW | I33: MONTHLY CONTRIBUTIONS TO EKPC COINCIDENT PEAK DEMAND - KW
B35: =(B6) -> 0 | C35: =(C6) -> GS 1 | D35: =(D6) -> GS 1 | E35: =(E6) -> SC1 | F35: =(F6) -> SC2 | G35: =(G6) -> LP1 | H35: =(H6) -> LP2 | J35: Total | K35: B-2 | L35: =(L6) -> G-1 | M35: Total
B36: =(B7) -> Enviro | C36: =(C7) -> Residential | D36: =(D7) -> Residential | E36: =(E7) -> Gen Service | F36: =(F7) -> Gen Service | G36: =(G7) -> Large Power | H36: =(H7) -> Large Power | I36: Outdoor | J36: for Sched E | K36: Large Indust. | L36: =(L7) -> Large Indust. | M36: for All Rate
A37: =(A8) -> Month | B37: =(B8) -> watts | C37: =(C8) -> & Farm | D37: =(D8) -> & Farm TOD | E37: =(E8) -> 0-100 kW | F37: 0-100 kW TOD | G37: =(G8) -> under 500 kW | H37: =(H8) -> over 500 kW | I37: Lights | J37: Rate Classes | K37: Rate | L37: =(L8) -> Rate | M37: Schedules
A39: =A10 -> January | B39: 0 | C39: =201121+119+1327 -> 202567 | D39: =[11]CP!$D$12 -> 276.95247 | E39: =(36582+391) -> 36973 | F39: =(D39*1.75) -> 484.66682 | G39: =8013+852 -> 8865 | H39: =3510+8273+1068 -> 12851 | I39: 5978 | J39: =SUM(B39:I39) -> 267995.62 | K39: =3960+4593+5996+4993+5138 -> 24680 | L39: 15000 | M39: =SUM(J39,K39,L39) -> 307675.62
A40: =A11 -> February | B40: 0 | C40: =208901+123+1621 -> 210645 | D40: =[11]CP!$E$12 -> 240.94535 | E40: =28533+347 -> 28880 | F40: =(D40*1.75) -> 421.65437 | G40: =5630+592 -> 6222 | H40: =3340+6654+944 -> 10938 | I40: 5300 | J40: =SUM(B40:I40) -> 262647.6 | K40: =(4380+4197+6636+5144+5345) -> 25702 | L40: 15000 | M40: =SUM(J40,K40,L40) -> 303349.6
A41: =A12 -> March | B41: 0 | C41: =178038+104+1708 -> 179850 | D41: =[11]CP!$F$12 -> 233.67017 | E41: =27338+383 -> 27721 | F41: =(D41*1.75) -> 408.9228 | G41: =5204+705 -> 5909 | H41: =3227+7947+979 -> 12153 | I41: 5500 | J41: =SUM(B41:I41) -> 231775.59 | K41: =SUM([12]CP!F23,[12]CP!F25,[12]CP!F26,[12]CP!F27,[12]CP!F28) -> 25102.56 | L41: 15000 | M41: =SUM(J41,K41,L41) -> 271878.15
A42: =A13 -> April | B42: 0 | C42: =130114+76+1629 -> 131819 | D42: =[11]CP!$G$12 -> 157.57925 | E42: =26167+326 -> 26493 | F42: =(D42*1.75) -> 275.76368 | G42: =4485+596 -> 5081 | H42: =3059+7071+989 -> 11119 | I42: 0 | J42: =SUM(B42:I42) -> 174945.34 | K42: =3685+4360+6364+5124+6121 -> 25654 | L42: 15000 | M42: =SUM(J42,K42,L42) -> 215599.34
A43: =A14 -> May | B43: 0 | C43: =113971+67+1651 -> 115689 | D43: =[11]CP!$H$12 -> 162.14346 | E43: =28446+369 -> 28815 | F43: =(D43*1.75) -> 283.75106 | G43: =4911+465 -> 5376 | H43: =3702+8143+1186 -> 13031 | I43: 0 | J43: =SUM(B43:I43) -> 163356.89 | K43: =4514+3287+5339+847+6322 -> 20309 | L43: 15000 | M43: =SUM(J43,K43,L43) -> 198665.89
A44: =A15 -> June | B44: 0 | C44: =145922+85+2492 -> 148499 | D44: =[11]CP!$I$12 -> 158.51317 | E44: =27078+330 -> 27408 | F44: =(D44*1.75) -> 277.39805 | G44: =4538+412 -> 4950 | H44: =3976+7950+1075 -> 13001 | I44: 0 | J44: =SUM(B44:I44) -> 194293.91 | K44: =4859+3239+6047+4902+7080 -> 26127 | L44: 15000 | M44: =SUM(J44,K44,L44) -> 235420.91
A45: =A16 -> July | B45: 0 | C45: =153107+90+2600 -> 155797 | D45: =[11]CP!$J$12 -> 174.58084 | E45: =28973+335 -> 29308 | F45: =(D45*1.75) -> 305.51647 | G45: =5013+378 -> 5391 | H45: =3829+8446+1044 -> 13319 | I45: 0 | J45: =SUM(B45:I45) -> 204295.1 | K45: =4566+3377+6275+5345+6211 -> 25774 | L45: 15000 | M45: =SUM(J45,K45,L45) -> 245069.1
A46: =A17 -> August | B46: 0 | C46: =141312+83+3090 -> 144485 | D46: =[11]CP!$K$12 -> 173.58257 | E46: =27409+327 -> 27736 | F46: =(D46*1.75) -> 303.76949 | G46: =4963+502 -> 5465 | H46: =4118+8663+941 -> 13722 | I46: 0 | J46: =SUM(B46:I46) -> 191885.35 | K46: =4444+2993+6710+4242+5668 -> 24057 | L46: 15000 | M46: =SUM(J46,K46,L46) -> 230942.35
A47: =A18 -> September | B47: 0 | C47: =139011+81+3283 -> 142375 | D47: =[11]CP!$L$12 -> 164.56963 | E47: =31255+407 -> 31662 | F47: =(D47*1.75) -> 287.99686 | G47: =5563+535 -> 6098 | H47: =4110+9054+1007 -> 14171 | I47: 0 | J47: =SUM(B47:I47) -> 194758.57 | K47: =4740+3298+6165+5210+6536 -> 25949 | L47: 15000 | M47: =SUM(J47,K47,L47) -> 235707.57
A48: =A19 -> October | B48: 0 | C48: =124769+73+3245 -> 128087 | D48: =[11]CP!$M$12 -> 135.78874 | E48: =20675+215 -> 20890 | F48: =(D48*1.75) -> 237.6303 | G48: =4428+597 -> 5025 | H48: =3333+7439+945 -> 11717 | I48: 0 | J48: =SUM(B48:I48) -> 166092.42 | K48: =4350+3652+6443+4380+5773 -> 24598 | L48: 15000 | M48: =SUM(J48,K48,L48) -> 205690.42
A49: =A20 -> November | B49: 0 | C49: =169874+99+4720 -> 174693 | D49: =[11]CP!$N$12 -> 204.99635 | E49: =15288+345 -> 15633 | F49: =(D49*1.75) -> 358.7436 | G49: =3766+351 -> 4117 | H49: =2194+3947+988 -> 7129 | I49: 0 | J49: =SUM(B49:I49) -> 202135.74 | K49: =1296+1572+2368+3779+2197 -> 11212 | L49: 15000 | M49: =SUM(J49,K49,L49) -> 228347.74
A50: =A21 -> December | B50: 0 | C50: =191871+112+5407 -> 197390 | D50: =[11]CP!$O$12 -> 226.64906 | E50: =24585+478 -> 25063 | F50: =(D50*1.75) -> 396.63585 | G50: =5769+839 -> 6608 | H50: =3480+8202+1088 -> 12770 | I50: 5238 | J50: =SUM(B50:I50) -> 247692.28 | K50: =4303+4137+6772+1080+5892 -> 22184 | L50: 15000 | M50: =SUM(J50,K50,L50) -> 284876.28
B51: =SUM(B39:B50) -> 0 | C51: =SUM(C39:C50) -> 1931896 | D51: =SUM(D39:D50) -> 2309.9711 | E51: =SUM(E39:E50) -> 326582 | F51: =SUM(F39:F50) -> 4042.4493 | G51: =SUM(G39:G50) -> 69107 | H51: =SUM(H39:H50) -> 145921 | I51: =SUM(I39:I50) -> 22016 | ... L51: =SUM(L39:L50) -> 180000 | M51: =SUM(J51,K51,L51) -> 2963223
C52: =1898007+1111+32873 -> 1931991 | E52: =322280+4251 -> 326531
A53: Allocation % | C53: =C51/$J$51 -> 0.77217944 | D53: =D51/$J$51 -> 0.00092329616 | E53: =E51/$J$51 -> 0.13053493 | F53: =F51/$J$51 -> 0.0016157683 | G53: =G51/$J$51 -> 0.02762209 | H53: =H51/$J$51 -> 0.05832467 | I53: =I51/$J$51 -> 0.0087998022 | J53: =SUM(B53:I53) -> 1 | M53: =M51/$M$51 -> 1
A62: MONTHLY PEAK DEMANDS FOR EACH RATE CLASS | I62: MONTHLY PEAK DEMANDS FOR EACH RATE CLASS
B64: =(B35) -> 0 | C64: =(C35) -> GS 1 | D64: =(D35) -> GS 1 | E64: =(E35) -> SC1 | F64: =(F35) -> SC2 | G64: =(G35) -> LP1 | H64: =(H35) -> LP2 | J64: Total | K64: B-2 | L64: =(L35) -> G-1 | M64: =(M35) -> Total
B65: =(B36) -> Enviro | C65: =(C36) -> Residential | D65: =(D36) -> Residential | E65: =(E36) -> Gen Service | F65: =(F36) -> Gen Service | G65: =(G36) -> Large Power | H65: =(H36) -> Large Power | I65: Outdoor | J65: for Sched E | K65: Large Indust. | L65: =(L36) -> Large Indust. | M65: =(M36) -> for All Rate
A66: =(A37) -> Month | B66: =(B37) -> watts | C66: =(C37) -> & Farm | D66: =(D37) -> & Farm TOD | E66: =(E37) -> 0-100 kW | F66: =(F37) -> 0-100 kW TOD | G66: =(G37) -> under 500 kW | H66: =(H37) -> over 500 kW | I66: Lights | J66: Rate Classes | K66: Rate | L66: =(L37) -> Rate | M66: =(M37) -> Schedules
A67: =(A38)
A68: =(A39) -> January | B68: 0 | C68: =201121+119+1327 -> 202567 | D68: =(D39) -> 276.95247 | E68: =36532+391-124 -> 36799 | F68: 800 | G68: =8013+852 -> 8865 | H68: =3510+8273+1068 -> 12851 | I68: 5978 | J68: =SUM(B68:I68) -> 268136.95 | K68: =3960+4593+5999+5515+5270 -> 25337 | L68: 9576 | M68: =SUM(J68:L68) -> 303049.95
A69: =(A40) -> February | B69: 0 | C69: =208901+123+1621-356 -> 210289 | D69: =(D40) -> 240.94535 | E69: =28533+347 -> 28880 | F69: 584 | G69: =6459+592 -> 7051 | H69: =3340+6654+944 -> 10938 | I69: 5300 | J69: =SUM(B69:I69) -> 263282.95 | K69: =4380+4197+6636+5144+5345 -> 25702 | L69: 9288 | M69: =SUM(J69:L69) -> 298272.95
A70: =(A41) -> March | B70: 0 | C70: =178784+105+1715 -> 180604 | D70: =(D41) -> 233.67017 | E70: =30274+381 -> 30655 | F70: 800 | G70: =6638+702 -> 7340 | H70: =3379+7947+1027 -> 12353 | I70: 5500 | J70: =SUM(B70:I70) -> 237485.67 | K70: =4694+4305+6552+5242+5472 -> 26265 | L70: 12571 | M70: =SUM(J70:L70) -> 276321.67
A71: =(A42) -> April | B71: 0 | C71: =130113+76+1529 -> 131718 | D71: =(D42) -> 157.57925 | E71: =26269+326 -> 26595 | F71: 655 | G71: =5841+596 -> 6437 | H71: =3059+7071+989 -> 11119 | I71: 4615 | J71: =SUM(B71:I71) -> 181296.58 | K71: =3685+4360+6364+5124+6121 -> 25654 | L71: 11065 | M71: =SUM(J71:L71) -> 218015.58
A72: =(A43) -> May | B72: 0 | C72: =114587+87+1660 -> 116334 | D72: =(D43) -> 162.14346 | E72: =28434+369 -> 28803 | F72: 866 | G72: =5452+465 -> 5917 | H72: =3702+6143+1166 -> 11011 | I72: 4611 | J72: =SUM(B72:I72) -> 167704.14 | K72: =4514+3298+5954+847+6525 -> 21138 | L72: 13837 | M72: =SUM(J72:L72) -> 202679.14
A73: =(A44) -> June | B73: 0 | C73: =145923+85+2492 -> 148500 | D73: =(D44) -> 158.51317 | E73: =27078+330 -> 27408 | F73: 694 | G73: =4646+412 -> 5058 | H73: =3976+8123+1075 -> 13174 | I73: 4615 | J73: =SUM(B73:I73) -> 199607.51 | K73: =4893+3239+6348+5060+7080 -> 26620 | L73: 11789 | M73: =SUM(J73:L73) -> 238016.51
A74: =(A45) -> July | B74: 0 | C74: =153107+90+2800 -> 155997 | D74: =(D45) -> 174.58084 | E74: =28973+335 -> 29308 | F74: 825 | G74: =5059+382 -> 5441 | H74: =3829+8446+1044 -> 13319 | I74: 4609 | J74: =SUM(B74:I74) -> 209673.58 | K74: =4811+3377+8413+6429+6211 -> 29241 | L74: 11939 | M74: =SUM(J74:L74) -> 250853.58
A75: =(A46) -> August | B75: 0 | C75: =143407+84+3136 -> 146627 | D75: =(D46) -> 173.58257 | E75: =27414+327 -> 27741 | F75: 843 | G75: =4896+502 -> 5398 | H75: =4118+8663+941 -> 13722 | I75: 4607 | J75: =SUM(B75:I75) -> 199111.58 | K75: =4444+2993+6780+4242+5668 -> 24127 | L75: 11896 | M75: =SUM(J75:L75) -> 235134.58
A76: =(A47) -> September | B76: 0 | C76: =140506+82+3317 -> 143905 | D76: =(D47) -> 164.56963 | E76: =31281+407 -> 31688 | F76: 912 | G76: =5451+535 -> 5986 | H76: =4110+9054+1026 -> 14190 | I76: 4609 | J76: =SUM(B76:I76) -> 201454.57 | K76: =4765+3297+6587+5282+6536 -> 26467 | L76: 12580 | M76: =SUM(J76:L76) -> 240501.57
A77: =(A48) -> October | B77: 0 | C77: =124827+73+3247 -> 128147 | D77: =(D48) -> 135.78874 | E77: =20685+215 -> 20900 | F77: 486 | G77: =4359+597 -> 4956 | H77: =333+7439+951 -> 8723 | I77: 4611 | J77: =SUM(B77:I77) -> 167958.79 | K77: =4408+3652+6445+4951+5820 -> 25276 | L77: 11785 | M77: =SUM(J77:L77) -> 205019.79
A78: =(A49) -> November | B78: 0 | C78: =169355+99+4706 -> 174160 | D78: =(D49) -> 204.99635 | E78: =19012+344 -> 19356 | F78: 635 | G78: =4792+668 -> 5460 | H78: =3112+7653+988 -> 11753 | I78: 4615 | J78: =SUM(B78:I78) -> 216184 | K78: =5080+3696+6390+6330+5200 -> 26696 | L78: 14756 | M78: =SUM(J78:L78) -> 257636
A79: =(A50) -> December | B79: 0 | C79: =193692+446+5458 -> 199596 | D79: =(D50) -> 226.64906 | E79: =24670+478 -> 25148 | F79: 870 | G79: =6531+838 -> 7369 | H79: =3565+8314+1088 -> 12967 | I79: 5238 | J79: =SUM(B79:I79) -> 251414.65 | K79: =4303+4137+6772+2223+5892 -> 23327 | L79: 12273 | M79: =SUM(J79:L79) -> 287014.65
B80: =SUM(B68:B79) -> 0 | C80: =1904321+1115+33008 -> 1938444 | D80: 2331 | E80: =329033+4248 -> 333281 | F80: 8971 | G80: =68137+7142 -> 75279 | H80: =(43033+95781+2307)*0.75 -> 105840.75 | I80: 31443 | J80: =SUM(C80:I80) -> 2495589.8 | K80: =(45143+77240+65388+71142)*0.6 -> 155347.8 | L80: =143355*0.5 -> 71677.5 | M80: =SUM(C80,D80,E80,F80,G80,H80,I80,K80,L80) -> 2722615
G81: =SUM(G68:G79) -> 75278 | H81: =SUM(H68:H79) -> 146120 | I81: =SUM(I68:I79) -> 58908 | J81: =SUM(J68:J79) -> 2563311 | K81: =SUM(K68:K79) -> 305850 | L81: =SUM(L68:L79) -> 143355
A82: =A53 -> Allocation % | C82: =C80/$M$80 -> 0.71197873 | D82: =D80/$M$80 -> 0.00085616217 | E82: =E80/$M$80 -> 0.12241209 | F82: =F80/$M$80 -> 0.0032949939 | G82: =G80/$M$80 -> 0.02764952 | H82: =H80/$M$80 -> 0.038874666 | I82: =I80/$M$80 -> 0.011548823 | J82: 0 | K82: =K80/$M$80 -> 0.057058305 | L82: =L80/$M$80 -> 0.026326711 | M82: =M80/$M$80 -> 1 | N82: =N80/$M$80 -> 0
C83: =(C80/$J$80) -> 0.77674786 | D83: =(D80/$J$80) -> 0.00093404775 | E83: =(E80/$J$80) -> 0.13354799 | F83: =(F80/$J$80) -> 0.0035947415 | G83: =(G80/$J$80) -> 0.030164814 | H83: =(H80/$J$80) -> 0.042411117 | I83: =(I80/$J$80) -> 0.012599427 | J83: =SUM(C83:I83) -> 1 | M83: =SUM(C82:L82) -> 1
C84: =C80/$M$80 -> 0.71197873 | D84: =D80/$M$80 -> 0.00085616217 | E84: =E80/$M$80 -> 0.12241209 | F84: =F80/$M$80 -> 0.0032949939 | G84: =G80/$M$80 -> 0.02764952 | H84: =H80/$M$80 -> 0.038874666 | I84: =I80/$M$80 -> 0.011548823 | K84: =K80/$M$80 -> 0.057058305 | L84: =L80/$M$80 -> 0.026326711 | M84: =M80/$M$80 -> 1
M85: =SUM(C84:L84) -> 1
A90: SUM OF MONTHLY CUSTOMER DEMANDS FOR EACH CLASS - KW | I90: SUM OF MONTHLY CUSTOMER DEMANDS FOR EACH CLASS - KW
B92: =(B35) -> 0 | C92: =(C35) -> GS 1 | D92: =(D35) -> GS 1 | E92: =(E35) -> SC1 | F92: =(F35) -> SC2 | G92: =(G35) -> LP1 | H92: =(H35) -> LP2 | J92: Total | K92: B-2 | L92: =(L63) -> 0 | M92: =(M35) -> Total
B93: =(B36) -> Enviro | C93: =(C36) -> Residential | D93: =(D36) -> Residential | E93: =(E36) -> Gen Service | F93: =(F36) -> Gen Service | G93: =(G36) -> Large Power | H93: =(H36) -> Large Power | I93: Outdoor | J93: for Sched E | K93: Large Indust. | L93: =(L64) -> G-1 | M93: =(M36) -> for All Rate
A94: =(A37) -> Month | B94: =(B37) -> watts | C94: =(C37) -> & Farm | D94: =(D37) -> & Farm TOD | E94: =(E37) -> 0-100 kW | F94: =(F37) -> 0-100 kW TOD | G94: =(G37) -> under 500 kW | H94: =(H37) -> over 500 kW | I94: Lights | J94: Rate Classes | K94: Rate | L94: =(L65) -> Large Indust. | M94: =(M37) -> Schedules
A95: =(A38)
A96: =(A39) -> January | B96: 0 | C96: =501355+296+3308 -> 504959 | D96: 451 | E96: =44520+900 -> 45420 | F96: 392 | G96: =11362+971 -> 12333 | H96: =4376+11222+1189 -> 16787 | I96: 4619 | J96: =SUM(C96:I96) -> 584961 | L96: =(L68) -> 9576 | M96: =SUM(J96,#REF!,L96) -> #REF!
A97: =(A40) -> February | B97: 0 | C97: =475528+280+3690 -> 479498 | D97: 425 | E97: =45065+945 -> 46010 | F97: 363 | G97: =10654+973 -> 11627 | H97: =4516+10593+1073 -> 16182 | I97: 4619 | J97: =SUM(C97:I97) -> 558724 | L97: =(L69) -> 9288 | M97: =SUM(J97,#REF!,L97) -> #REF!
A98: =(A41) -> March | B98: 0 | C98: =494907+289+4748 -> 499944 | D98: 462 | E98: =44626+952 -> 45578 | F98: 420 | G98: =10521+929 -> 11450 | H98: =4437+11401+1141 -> 16979 | I98: 4613 | J98: =SUM(C98:I98) -> 579446 | L98: =(L70) -> 12571 | M98: =SUM(J98,#REF!,L98) -> #REF!
A99: =(A42) -> April | B99: 0 | C99: =469064+273+5513 -> 474850 | D99: 405 | E99: =44310+958 -> 45268 | F99: 456 | G99: =10109+823 -> 10932 | H99: =4971+11019+1182 -> 17172 | I99: 4615 | J99: =SUM(C99:I99) -> 553698 | L99: =(L71) -> 11065 | M99: =SUM(J99,#REF!,L99) -> #REF!
A100: =(A43) -> May | B100: 0 | C100: =446331+260+6466 -> 453057 | D100: 375 | E100: =45074+1061 -> 46135 | F100: 506 | G100: =9560+898 -> 10458 | H100: =5365+12031+1195 -> 18591 | I100: 4611 | J100: =SUM(C100:I100) -> 533733 | L100: =(L72) -> 13837 | M100: =SUM(J100,#REF!,L100) -> #REF!
A101: =(A44) -> June | B101: 0 | C101: =417868+344+7136 -> 425348 | D101: 351 | E101: =38169+885 -> 39054 | F101: 458 | G101: =8685+749 -> 9434 | H101: =5346+11357+1194 -> 17897 | I101: 4615 | J101: =SUM(C101:I101) -> 497157 | L101: =(L73) -> 11789 | M101: =SUM(J101,#REF!,L101) -> #REF!
A102: =(A45) -> July | B102: 0 | C102: =424218+247+7760 -> 432225 | D102: 356 | E102: =38669+930 -> 39599 | F102: 433 | G102: =8844+754 -> 9598 | H102: =5636+11480+1177 -> 18293 | I102: 4609 | J102: =SUM(C102:I102) -> 505113 | L102: =(L74) -> 11939 | M102: =SUM(J102,#REF!,L102) -> #REF!
A103: =(A46) -> August | B103: 0 | C103: =422771+247+9245 -> 432263 | D103: 355 | E103: =41626+938 -> 42564 | F103: 474 | G103: =10269+946 -> 11215 | H103: =6001+12533+1199 -> 19733 | I103: 4607 | J103: =SUM(C103:I103) -> 511211 | L103: =(L75) -> 11896 | M103: =SUM(J103,#REF!,L103) -> #REF!
A104: =(A47) -> September | B104: 0 | C104: =411799+240+9723 -> 421762 | D104: 346 | E104: =42288+951 -> 43239 | F104: 475 | G104: =9750+904 -> 10654 | H104: =5996+12185+1174 -> 19355 | I104: 4609 | J104: =SUM(C104:I104) -> 500440 | L104: =(L76) -> 12580 | M104: =SUM(J104,#REF!,L104) -> #REF!
A105: =(A48) -> October | B105: 0 | C105: =486540+264+12655 -> 499459 | D105: 409 | E105: =48486+1074 -> 49560 | F105: 531 | G105: =10266+870 -> 11136 | H105: =5431+11116+1177 -> 17724 | I105: 4611 | J105: =SUM(C105:I105) -> 583430 | L105: =(L77) -> 11785 | M105: =SUM(J105,#REF!,L105) -> #REF!
A106: =(A49) -> November | B106: 0 | C106: =501957+293+13948 -> 516198 | D106: 468 | E106: =45114+893 -> 46007 | F106: 463 | G106: =11433+876 -> 12309 | H106: =4757+10437+1172 -> 16366 | I106: 4615 | J106: =SUM(C106:I106) -> 596426 | L106: =(L78) -> 14756 | M106: =SUM(J106,#REF!,L106) -> #REF!
A107: =(A50) -> December | B107: 0 | C107: =514700+300+14505 -> 529505 | D107: 457 | E107: =44873+901 -> 45774 | F107: 489 | G107: =11024+899 -> 11923 | H107: =4471+10703+1170 -> 16344 | I107: 4622 | J107: =SUM(C107:I107) -> 609114 | L107: =(L79) -> 12273 | M107: =SUM(J107,#REF!,L107) -> #REF!
B108: =SUM(B96:B107) -> 0 | C108: =SUM(C96:C107) -> 5669068 | D108: =SUM(D96:D107) -> 4860 | E108: =SUM(E96:E107) -> 534208 | F108: =SUM(F96:F107) -> 5460 | G108: =SUM(G96:G107) -> 133069 | H108: =SUM(H96:H107) -> 211423 | I108: =SUM(I96:I107) -> 55365 | ... L108: =SUM(L96:L107) -> 143355 | M108: =SUM(I108:J108) -> 6668818
A110: =A82 -> Allocation % | C110: =C108/$J$108 -> 0.85720243 | D110: =D108/$J$108 -> 0.00073486574 | E110: =E108/$J$108 -> 0.080775958 | F110: =F108/$J$108 -> 0.0008255899 | G110: =G108/$J$108 -> 0.020120956 | H110: =H108/$J$108 -> 0.031968625 | I110: =I108/$J$108 -> 0.0083715723 | J110: =J108/$J$108 -> 1 | K110: =K108/$M$108 -> 0 | L110: 0 | M110: =M108/$M$108 -> 1
J111: =SUM(C110:I110) -> 1 | M111: =SUM(C110:L110) -> 2
J112: 6613453 | K112: 0 | L112: 180674.88 | M112: 6668818

Sheet -5 IncStmt
B1: =('4 Allocation'!D3) -> 0 | C1: =('4 Allocation'!E3) -> GS 1 | D1: =('4 Allocation'!F3) -> GS 1 | E1: =('4 Allocation'!G3) -> SC1 | F1: =('4 Allocation'!H3) -> SC2 | G1: =('4 Allocation'!I3) -> LP1 | H1: =('4 Allocation'!J3) -> LP2 | I1: =('4 Allocation'!K3) -> 0 | ... M1: =('4 Allocation'!O3) -> Total
B2: =('4 Allocation'!D4) -> Enviro | C2: =('4 Allocation'!E4) -> Residential | D2: =('4 Allocation'!F4) -> Residential | E2: =('4 Allocation'!G4) -> Gen Service | F2: =('4 Allocation'!H4) -> Gen Service | G2: =('4 Allocation'!I4) -> Large Power | H2: =('4 Allocation'!J4) -> Large Power | I2: =('4 Allocation'!K4) -> Outdoor | ... M2: =('4 Allocation'!O4) -> for All
B3: =('4 Allocation'!D5) -> watts | C3: =('4 Allocation'!E5) -> & Farm | D3: =('4 Allocation'!F5) -> & Farm TOD | E3: =('4 Allocation'!G5) -> 0-100 kW | F3: =('4 Allocation'!H5) -> 0-100 kW TOD | G3: =('4 Allocation'!I5) -> under 500 kW | H3: =('4 Allocation'!J5) -> over 500 kW | I3: =('4 Allocation'!K5) -> Lights | ... M3: =('4 Allocation'!O5) -> Rate Classes
A4: Revenue from Rates | B4: =('12 Inc Stmt Func'!F8) -> 7678.35 | C4: =('12 Inc Stmt Func'!G8) -> 77312671 | D4: =('12 Inc Stmt Func'!H8) -> 37530.453 | E4: =('12 Inc Stmt Func'!I8) -> 7980425.2 | F4: =('12 Inc Stmt Func'!J8) -> 78246.04 | G4: =('12 Inc Stmt Func'!K8) -> 3052922.7 | H4: =('12 Inc Stmt Func'!L8) -> 5573017.8 | I4: =('12 Inc Stmt Func'!M8) -> 2045660.1 | ... M4: =('12 Inc Stmt Func'!Q8) -> 1.1304633e+08
A6: Purchased Power | B6: =('12 Inc Stmt Func'!F13) -> 6455.25 | C6: =('12 Inc Stmt Func'!G13) -> 54097149 | D6: =('12 Inc Stmt Func'!H13) -> 38083.901 | E6: =('12 Inc Stmt Func'!I13) -> 5831175.3 | F6: =('12 Inc Stmt Func'!J13) -> 63679.8 | G6: =('12 Inc Stmt Func'!K13) -> 2411301.1 | H6: =('12 Inc Stmt Func'!L13) -> 5155021.6 | I6: =('12 Inc Stmt Func'!M13) -> 619361.77 | ... M6: =('12 Inc Stmt Func'!Q13) -> 84104533
A7: Distibution Operations | C7: =(Sheet2!J9) -> 1932431.4 | D7: =(Sheet2!J32) -> 1711.9743 | E7: =(Sheet2!J55) -> 239263.53 | F7: =(Sheet2!J78) -> 4174.7813 | G7: =(Sheet2!J101) -> 27937.043 | H7: =(Sheet2!J124) -> 37197.923 | I7: =(Sheet2!J147) -> 414990.89 | J7: =SUM(C7:I7) -> 2657707.5 | K7: =(Sheet2!J170) -> 53818.377 | L7: =(Sheet2!J193) -> 24798.128 | M7: =SUM(J7:L7) -> 2736324
A8: Distribution Maintenance | C8: =(Sheet2!J10) -> 4943745 | D8: =(Sheet2!J33) -> 4612.1127 | E8: =(Sheet2!J56) -> 541305.8 | F8: =(Sheet2!J79) -> 12543.169 | G8: =(Sheet2!J102) -> 88914.294 | H8: =(Sheet2!J125) -> 120910.97 | I8: =(Sheet2!J148) -> 277449.67 | J8: =SUM(C8:I8) -> 5989481 | K8: =(Sheet2!J171) -> 175655 | L8: =(Sheet2!J194) -> 81002.021 | M8: =SUM(J8:L8) -> 6246138
A9: Consumer Accounts | C9: =(Sheet2!J11) -> 2622966 | D9: =(Sheet2!J34) -> 2353.8358 | E9: =(Sheet2!J57) -> 197753.18 | F9: =(Sheet2!J80) -> 3329.4388 | G9: =(Sheet2!J103) -> 7061.5074 | H9: =(Sheet2!J126) -> 2973.2663 | I9: =(Sheet2!J149) -> 55919.706 | J9: =SUM(C9:I9) -> 2892357 | K9: =(Sheet2!J172) -> 9291.4571 | L9: =(Sheet2!J195) -> 3716.5829 | M9: =SUM(J9:L9) -> 2905365
A10: Customer Service | C10: =(Sheet2!J12) -> 925346.54 | D10: =(Sheet2!J35) -> 830.40079 | E10: =(Sheet2!J58) -> 69764.592 | F10: =(Sheet2!J81) -> 1174.5801 | G10: =(Sheet2!J104) -> 2491.2024 | H10: =(Sheet2!J127) -> 1048.9273 | I10: =(Sheet2!J150) -> 19727.7 | J10: =SUM(C10:I10) -> 1020383.9 | K10: =(Sheet2!J173) -> 3277.8978 | L10: =(Sheet2!J196) -> 1311.1591 | M10: =SUM(J10:L10) -> 1024973
A11: Administative & General | C11: =(Sheet2!J13) -> 3555659 | D11: =(Sheet2!J36) -> 3243.1672 | E11: =(Sheet2!J59) -> 357489.06 | F11: =(Sheet2!J82) -> 7238.5416 | G11: =(Sheet2!J105) -> 43114.799 | H11: =(Sheet2!J128) -> 55300.832 | I11: =(Sheet2!J151) -> 261984.95 | J11: =SUM(C11:I11) -> 4284030.4 | K11: =(Sheet2!J174) -> 82557.672 | L11: =(Sheet2!J197) -> 37801.972 | M11: =SUM(J11:L11) -> 4404390
A12: Depreciation | C12: =(Sheet2!J14) -> 6664443.7 | D12: =(Sheet2!J37) -> 6095.8329 | E12: =(Sheet2!J60) -> 704412.69 | F12: =(Sheet2!J83) -> 14969.031 | G12: =(Sheet2!J106) -> 119820.78 | H12: =(Sheet2!J129) -> 167376.49 | I12: =(Sheet2!J152) -> 424514.87 | J12: =SUM(C12:I12) -> 8101633.4 | K12: =(Sheet2!J175) -> 193473.25 | L12: =(Sheet2!J198) -> 89187.403 | M12: =SUM(J12:L12) -> 8384294
A13: Miscellaneous | C13: =(Sheet2!J15) -> 16106.66 | D13: =(Sheet2!J38) -> 14.733693 | E13: =(Sheet2!J61) -> 1704.5134 | F13: =(Sheet2!J84) -> 36.261771 | G13: =(Sheet2!J107) -> 291.92519 | H13: =(Sheet2!J130) -> 408.34064 | I13: =(Sheet2!J153) -> 1021.9996 | J13: =SUM(C13:I13) -> 19584.435 | K13: =(Sheet2!J176) -> 469.91506 | L13: =(Sheet2!J199) -> 216.6504 | M13: =SUM(J13:L13) -> 20271
A14: Interest on Long Term Debt | C14: =(Sheet2!J16) -> 3735901.4 | D14: =(Sheet2!J39) -> 3417.3915 | E14: =(Sheet2!J62) -> 395351.65 | F14: =(Sheet2!J85) -> 8410.7002 | G14: =(Sheet2!J108) -> 67710.296 | H14: =(Sheet2!J131) -> 94712.16 | I14: =(Sheet2!J154) -> 237046.66 | J14: =SUM(C14:I14) -> 4542550.3 | K14: =(Sheet2!J177) -> 108993.98 | L14: =(Sheet2!J200) -> 50250.759 | M14: =SUM(J14:L14) -> 4701795
A15: Short Term Interest | C15: =(Sheet2!J17) -> 2287.5934 | D15: =(Sheet2!J40) -> 2.0924333 | E15: =(Sheet2!J63) -> 242.0697 | F15: =(Sheet2!J86) -> 5.1497842 | G15: =(Sheet2!J109) -> 41.458309 | H15: =(Sheet2!J132) -> 57.99127 | I15: =(Sheet2!J155) -> 145.14121 | J15: =SUM(C15:I15) -> 2781.4961 | K15: =(Sheet2!J178) -> 66.735878 | L15: =(Sheet2!J201) -> 30.768017 | M15: =SUM(J15:L15) -> 2879
A16: Total Costs | B16: =SUM(B6:B15) -> 6455.25 | C16: =SUM(C6:C15) -> 78496036 | D16: =SUM(D6:D15) -> 60365.442 | E16: =SUM(E6:E15) -> 8338462.4 | F16: =SUM(F6:F15) -> 115561.45 | G16: =SUM(G6:G15) -> 2768684.4 | H16: =SUM(H6:H15) -> 5635008.5 | I16: =SUM(I6:I15) -> 2312163.4 | J16: =SUM(C16:I16) -> 97726282 | K16: =SUM(K6:K15) -> 11451054 | L16: =SUM(L6:L15) -> 5347171.3 | M16: =SUM(M6:M15) -> 1.1453096e+08
A18: Margins before Other Revenue | B18: =(B4-B16) -> 1223.1 | C18: =(C4-C16) -> -1183365.6 | D18: =(D4-D16) -> -22834.99 | E18: =(E4-E16) -> -358037.26 | F18: =(F4-F16) -> -37315.414 | G18: =(G4-G16) -> 284238.3 | H18: =(H4-H16) -> -61990.678 | I18: =(I4-I16) -> -266503.26 | ... M18: =(M4-M16) -> -1484635.2
A19: Other Revenue | B19: =('12 Inc Stmt Func'!F38) -> 0 | C19: =('12 Inc Stmt Func'!G38) -> 2553544.2 | D19: =('12 Inc Stmt Func'!H38) -> 1239.5856 | E19: =('12 Inc Stmt Func'!I38) -> 263583.81 | F19: =('12 Inc Stmt Func'!J38) -> 2584.3723 | G19: =('12 Inc Stmt Func'!K38) -> 100834.35 | H19: =('12 Inc Stmt Func'!L38) -> 184070.05 | I19: =('12 Inc Stmt Func'!M38) -> 67565.684 | ... M19: =('12 Inc Stmt Func'!Q38) -> 3733530.1
A20: Net Margins | B20: =(B18+B19) -> 1223.1 | C20: =(C18+C19) -> 1370178.6 | D20: =(D18+D19) -> -21595.404 | E20: =(E18+E19) -> -94453.447 | F20: =(F18+F19) -> -34731.042 | G20: =(G18+G19) -> 385072.65 | H20: =(H18+H19) -> 122079.37 | I20: =(I18+I19) -> -198937.57 | ... M20: =(M18+M19) -> 2248894.9
A21: TIER | C21: =(C14+C20)/(C14) -> 1.3667598 | D21: =(D14+D20)/(D14) -> -5.3192654 | E21: =(E14+E20)/(E14) -> 0.76109004 | F21: =(F14+F20)/(F14) -> -3.1293877 | G21: =(G14+G20)/(G14) -> 6.6870621 | H21: =(H14+H20)/(H14) -> 2.2889514 | I21: =(I14+I20)/(I14) -> 0.1607662 | J21: =(J14+J20)/(J14) -> 1.3379801 | ... M21: =(M14+M20)/(M14) -> 1.4783056
A23: Net Investment Rate Base | B23: =('2.22Rate Base'!I81) -> 0 | C23: =('2.22Rate Base'!J81) -> 1.2530409e+08 | D23: =('2.22Rate Base'!K81) -> 114597.35 | E23: =('2.22Rate Base'!L81) -> 13257554 | F23: =('2.22Rate Base'!M81) -> 282040.84 | G23: =('2.22Rate Base'!N81) -> 2244592.3 | H23: =('2.22Rate Base'!O81) -> 3499290.9 | I23: =('2.22Rate Base'!P81) -> 7625768.3 | ... M23: =('2.22Rate Base'!T81) -> 1.5766798e+08
A24: Return on Rate Base | C24: =(C20+C14)/(C23) -> 0.040749506 | D24: =(D20+D14)/(D23) -> -0.15862506 | E24: =(E20+E14)/(E23) -> 0.022696359 | F24: =(F20+F14)/(F23) -> -0.093321029 | G24: =(G20+G14)/(G23) -> 0.20172169 | H24: =(H20+H14)/(H23) -> 0.06195299 | I24: =(I20+I14)/(I23) -> 0.0049974102 | J24: =(J20+J14)/(J23) -> 0.039899718 | ... M24: =(M20+M14)/(M23) -> 0.044084346
A26: Increase in Revenue | C26: =('-6 Increase'!E19) -> 2010129.4 | D26: =('-6 Increase'!F19) -> 975.79177 | E26: =('-6 Increase'!G19) -> 279314.88 | F26: =('-6 Increase'!H19) -> 2738.6114 | G26: =('-6 Increase'!I19) -> 0 | H26: =('-6 Increase'!J19) -> 0 | I26: =('-6 Increase'!K19) -> 159741 | J26: =('-6 Increase'!L19) -> 2452899.7 | ... M26: =('-6 Increase'!O19) -> 2452899.7
A27: Return on Rate Base | C27: =(C14+C20+C26)/(C23) -> 0.056791515 | D27: =(D14+D20+D26)/(D23) -> -0.1501101 | E27: =(E14+E20+E26)/(E23) -> 0.043764716 | F27: =(F14+F20+F26)/(F23) -> -0.083611047 | G27: =(G14+G20+G26)/(G23) -> 0.20172169 | H27: =(H14+H20+H26)/(H23) -> 0.06195299 | I27: =(I14+I20+I26)/(I23) -> 0.025944939 | J27: =(J14+J20+J26)/(J23) -> 0.056002474 | ... M27: =(M14+M20+M26)/(M23) -> 0.059641719
C38: =SUM(C7:C15) -> 24398887 | D38: =SUM(D7:D15) -> 22281.541 | E38: =SUM(E7:E15) -> 2507287.1 | F38: =SUM(F7:F15) -> 51881.654 | G38: =SUM(G7:G15) -> 357383.3 | H38: =SUM(H7:H15) -> 479986.89 | I38: =SUM(I7:I15) -> 1692801.6 | J38: =SUM(J7:J15) -> 29510509 | ... L38: =SUM(L7:L15) -> 288315.44

Sheet 12 Inc Stmt Func
G4: =('4 Allocation'!E3) -> GS 1 | H4: =('4 Allocation'!F3) -> GS 1 | I4: =('4 Allocation'!G3) -> SC1 | J4: =('4 Allocation'!H3) -> SC2 | K4: =('4 Allocation'!I3) -> LP1 | L4: =('4 Allocation'!J3) -> LP2 | M4: =('4 Allocation'!K3) -> 0 | N4: =('4 Allocation'!L3) -> Total | ... Q4: =('4 Allocation'!O3) -> Total
E5: =('-5 IncStmt'!B2) -> Enviro | F5: Envirowatts | G5: =('4 Allocation'!E4) -> Residential | H5: =('4 Allocation'!F4) -> Residential | I5: =('4 Allocation'!G4) -> Gen Service | J5: =('4 Allocation'!H4) -> Gen Service | K5: =('4 Allocation'!I4) -> Large Power | L5: =('4 Allocation'!J4) -> Large Power | M5: =('4 Allocation'!K4) -> Outdoor | N5: =('4 Allocation'!L4) -> EKPC Sched | ... Q5: =('4 Allocation'!O4) -> for All
E6: =('-5 IncStmt'!B3) -> watts | G6: =('4 Allocation'!E5) -> & Farm | H6: =('4 Allocation'!F5) -> & Farm TOD | I6: =('4 Allocation'!G5) -> 0-100 kW | J6: =('4 Allocation'!H5) -> 0-100 kW TOD | K6: =('4 Allocation'!I5) -> under 500 kW | L6: =('4 Allocation'!J5) -> over 500 kW | M6: =('4 Allocation'!K5) -> Lights | N6: =('4 Allocation'!L5) -> E Rates | ... Q6: =('4 Allocation'!O5) -> Rate Classes
B8: Revenue from Rates | F8: =([13]summary!$F$19) -> 7678.35 | G8: =([13]summary!$F$10) -> 77312671 | H8: =([13]summary!$F$11) -> 37530.453 | I8: =([13]summary!$F$12) -> 7980425.2 | J8: =([13]summary!$F$13) -> 78246.04 | K8: =([13]summary!$F$14) -> 3052922.7 | L8: =([13]summary!$F$15) -> 5573017.8 | M8: =([13]summary!$F$18) -> 2045660.1 | N8: =SUM(F8:M8) -> 96088151 | O8: =([13]summary!$F$16) -> 11705947 | P8: =([13]summary!$F$17) -> 5252228.5 | Q8: =SUM(N8:P8) -> 1.1304633e+08
B10: Less Purchased Power Costs | L10: =SUM(E10:K10) -> 0
C11: Demand | G11: =('4 Allocation'!E6+'4 Allocation'!E8) -> 12827915 | H11: =('4 Allocation'!F6+'4 Allocation'!F8) -> 15345.272 | I11: =('4 Allocation'!G6+'4 Allocation'!G8) -> 2171454.9 | J11: =('4 Allocation'!H6+'4 Allocation'!H8) -> 29416.513 | K11: =('4 Allocation'!I6+'4 Allocation'!I8) -> 461985.17 | L11: =('4 Allocation'!J6+'4 Allocation'!J8) -> 947671.95 | M11: =('4 Allocation'!K6+'4 Allocation'!K8) -> 151086.43 | N11: =SUM(F11:M11) -> 16604876 | O11: =('4 Allocation'!M6+'4 Allocation'!M8) -> 2318166.9 | P11: =('4 Allocation'!N6+'4 Allocation'!N8) -> 1199869.9 | Q11: =SUM(N11:P11) -> 20122912
C12: Energy | F12: =('4 Allocation'!D7) -> 6455.25 | G12: =('4 Allocation'!E7) -> 41269234 | H12: =('4 Allocation'!F7) -> 22738.629 | I12: =('4 Allocation'!G7) -> 3659720.5 | J12: =('4 Allocation'!H7) -> 34263.286 | K12: =('4 Allocation'!I7) -> 1949315.9 | L12: =('4 Allocation'!J7) -> 4207349.6 | M12: =('4 Allocation'!K7) -> 468275.34 | N12: =SUM(F12:M12) -> 51617352 | O12: =('4 Allocation'!M7) -> 8505282.9 | P12: =('4 Allocation'!N7) -> 3858985.9 | Q12: =SUM(N12:P12) -> 63981621
D13: Total | F13: =SUM(F11:F12) -> 6455.25 | G13: =SUM(G11:G12) -> 54097149 | H13: =SUM(H11:H12) -> 38083.901 | I13: =SUM(I11:I12) -> 5831175.3 | J13: =SUM(J11:J12) -> 63679.8 | K13: =SUM(K11:K12) -> 2411301.1 | L13: =SUM(L11:L12) -> 5155021.6 | M13: =SUM(M11:M12) -> 619361.77 | N13: =SUM(F13:M13) -> 68222228 | O13: =SUM(O11:O12) -> 10823450 | P13: =SUM(P11:P12) -> 5058855.9 | Q13: =SUM(Q11:Q12) -> 84104533
B15: Gross Margin | F15: =(F8-F13) -> 1223.1 | G15: =(G8-G13) -> 23215522 | H15: =(H8-H13) -> -553.44813 | I15: =(I8-I13) -> 2149249.8 | J15: =(J8-J13) -> 14566.24 | K15: =(K8-K13) -> 641621.61 | L15: =(L8-L13) -> 417996.22 | M15: =(M8-M13) -> 1426298.3 | N15: =SUM(F15:M15) -> 27865923 | O15: =(O8-O13) -> 882497.68 | P15: =(P8-P13) -> 193372.63 | Q15: =(Q8-Q13) -> 28941794
N16: =SUM(G16:M16) -> 0
B17: Less Distribution Costs | N17: =SUM(G17:M17) -> 0
C18: Demand Related
D19: Stations | G19: =('4 Allocation'!E9) -> 173655.07 | H19: =('4 Allocation'!F9) -> 208.82211 | I19: =('4 Allocation'!G9) -> 29856.904 | J19: =('4 Allocation'!H9) -> 803.66503 | K19: =('4 Allocation'!I9) -> 6743.8524 | L19: =('4 Allocation'!J9) -> 9481.7199 | M19: =('4 Allocation'!K9) -> 2816.8141 | N19: =SUM(G19:M19) -> 223566.85 | O19: =('4 Allocation'!M9) -> 13916.798 | P19: =('4 Allocation'!N9) -> 6421.2128 | Q19: =('4 Allocation'!O9) -> 243904.86
D20: Lines | G20: =('4 Allocation'!E11) -> 8786959.8 | H20: =('4 Allocation'!F11) -> 10566.415 | I20: =('4 Allocation'!G11) -> 1510761.6 | J20: =('4 Allocation'!H11) -> 40665.511 | K20: =('4 Allocation'!I11) -> 341239.44 | L20: =('4 Allocation'!J11) -> 479775.74 | M20: =('4 Allocation'!K11) -> 142531.01 | N20: =SUM(G20:M20) -> 11312499 | O20: =('4 Allocation'!M11) -> 704191.03 | P20: =('4 Allocation'!N11) -> 324913.85 | Q20: =('4 Allocation'!O11) -> 12341604
D21: Transformers | G21: =('4 Allocation'!E13) -> 1873546.9 | H21: =('4 Allocation'!F13) -> 1606.1613 | I21: =('4 Allocation'!G13) -> 176548.19 | J21: =('4 Allocation'!H13) -> 1804.4528 | K21: =('4 Allocation'!I13) -> 43977.424 | L21: =('4 Allocation'!J13) -> 69872.314 | M21: =('4 Allocation'!K13) -> 18297.35 | N21: =SUM(G21:M21) -> 2185652.8 | O21: =('4 Allocation'!M13) -> 0 | P21: =('4 Allocation'!N13) -> 0 | Q21: =('4 Allocation'!O13) -> 2185652.8
G22: =SUM(G19:G21) -> 10834162 | H22: =SUM(H19:H21) -> 12381.398 | I22: =SUM(I19:I21) -> 1717166.7 | J22: =SUM(J19:J21) -> 43273.629 | K22: =SUM(K19:K21) -> 391960.72 | L22: =SUM(L19:L21) -> 559129.78 | M22: =SUM(M19:M21) -> 163645.17 | N22: =SUM(G22:M22) -> 13721719 | O22: =SUM(O19:O21) -> 718107.82 | P22: =SUM(P19:P21) -> 331335.07 | Q22: =SUM(Q19:Q21) -> 14771162
N23: =SUM(G23:M23) -> 0
C24: Consumer Related | N24: =SUM(G24:M24) -> 0
D25: Lines | G25: =('4 Allocation'!E10) -> 6029505.4 | H25: =('4 Allocation'!F10) -> 4328.6771 | I25: =('4 Allocation'!G10) -> 290932.67 | J25: =('4 Allocation'!H10) -> 4898.2399 | K25: =('4 Allocation'!I10) -> 6493.0156 | L25: =('4 Allocation'!J10) -> 2733.9013 | M25: =('4 Allocation'!K10) -> 19592.959 | N25: =SUM(G25:M25) -> 6358484.9 | O25: =('4 Allocation'!M10) -> 569.56277 | P25: =('4 Allocation'!N10) -> 113.91255 | Q25: =('4 Allocation'!O10) -> 6359168.4
D26: Transformers | G26: =('4 Allocation'!E12) -> 540858.67 | H26: =('4 Allocation'!F12) -> 388.29097 | I26: =('4 Allocation'!G12) -> 26097.241 | J26: =('4 Allocation'!H12) -> 439.38189 | K26: =('4 Allocation'!I12) -> 1046.2501 | L26: =('4 Allocation'!J12) -> 5955.4897 | M26: =('4 Allocation'!K12) -> 483.42207 | N26: =SUM(G26:M26) -> 575268.74 | O26: =('4 Allocation'!M12) -> 0 | P26: =('4 Allocation'!N12) -> 0 | Q26: =('4 Allocation'!O12) -> 575268.74
D27: Services | G27: =('4 Allocation'!E14) -> 4202929.9 | H27: =('4 Allocation'!F14) -> 3017.3497 | I27: =('4 Allocation'!G14) -> 243357.19 | J27: =('4 Allocation'!H14) -> 4097.2432 | K27: =('4 Allocation'!I14) -> 6325.049 | L27: =('4 Allocation'!J14) -> 0 | M27: =('4 Allocation'!K14) -> 63882.532 | N27: =SUM(G27:M27) -> 4523609.2 | O27: =('4 Allocation'!M14) -> 0 | P27: =('4 Allocation'!N14) | Q27: =('4 Allocation'!O14) -> 4523609.2
D28: Meters | G28: =('4 Allocation'!E15) -> 1543384.7 | H28: =('4 Allocation'!F15) -> 1108.0202 | I28: =('4 Allocation'!G15) -> 249109.54 | J28: =('4 Allocation'!H15) -> 1253.8123 | K28: =('4 Allocation'!I15) -> 2914.1508 | L28: =('4 Allocation'!J15) -> 1227.0109 | M28: =('4 Allocation'!K15) -> 0 | N28: =SUM(G28:M28) -> 1798997.2 | O28: =('4 Allocation'!M15) -> 255.62726 | P28: =('4 Allocation'!N15) -> 51.125452 | Q28: =('4 Allocation'!O15) -> 1799304
D29: Consumer Svc | N29: =SUM(G29:M29) -> 0
D30: & Accouting | G30: =('4 Allocation'!E17) -> 4986877 | H30: =('4 Allocation'!F17) -> 4475.1971 | I30: =('4 Allocation'!G17) -> 375975.44 | J30: =('4 Allocation'!H17) -> 6330.0485 | K30: =('4 Allocation'!I17) -> 13425.591 | L30: =('4 Allocation'!J17) -> 5652.8805 | M30: =('4 Allocation'!K17) -> 106316.55 | N30: =SUM(G30:M30) -> 5499052.7 | O30: =('4 Allocation'!M17) -> 17665.252 | P30: =('4 Allocation'!N17) -> 7066.1006 | Q30: =('4 Allocation'!O17) -> 5523784
D31: Outdoor Lighting | K31: =('4 Allocation'!I18) | M31: =('4 Allocation'!O18) -> 1575927.6 | N31: =('4 Allocation'!N18) -> 0 | Q31: =('4 Allocation'!O18) -> 1575927.6
C32: Total Consumer Related | G32: =SUM(G25:G31) -> 17303556 | H32: =SUM(H25:H31) -> 13317.535 | I32: =SUM(I25:I31) -> 1185472.1 | J32: =SUM(J25:J31) -> 17018.726 | K32: =SUM(K25:K31) -> 30204.057 | L32: =SUM(L25:L31) -> 15569.282 | M32: =SUM(M25:M31) -> 1766203.1 | N32: =SUM(G32:M32) -> 20331340 | O32: =SUM(O25:O31) -> 18490.442 | P32: =SUM(P25:P31) -> 7231.1386 | Q32: =SUM(Q25:Q31) -> 20357062
N33: =SUM(G33:M33) -> 0
B34: Total Distribution Costs | E34: 0 | F34: =SUM(F22,F32) -> 0 | G34: =SUM(G22,G32) -> 28137717 | H34: =SUM(H22,H32) -> 25698.933 | I34: =SUM(I22,I32) -> 2902638.8 | J34: =SUM(J22,J32) -> 60292.355 | K34: =SUM(K22,K32) -> 422164.77 | L34: =SUM(L22,L32) -> 574699.06 | M34: =SUM(M22,M32) -> 1929848.3 | N34: =SUM(G34:M34) -> 34053059 | O34: =SUM(O22,O32) -> 736598.27 | P34: =SUM(P22,P32) -> 338566.2 | Q34: =SUM(Q22,Q32) -> 35128224 | S34: =(Q13+Q34) -> 1.1923276e+08
L35: =SUM(E35:K35) -> 0
B36: Income from Rate Revenue | F36: =(F15-F34) -> 1223.1 | G36: =(G15-G34) -> -4922195.8 | H36: =(H15-H34) -> -26252.381 | I36: =(I15-I34) -> -753388.93 | J36: =(J15-J34) -> -45726.115 | K36: =(K15-K34) -> 219456.83 | L36: =(L15-L34) -> -156702.84 | M36: =(M15-M34) -> -503549.93 | ... Q36: =(Q15-Q34) -> -6186430.2
Q37: =(Q16-Q35) -> 0
B38: Other Revenue | E38: =('-6 Increase'!D13) -> 0 | G38: =(G8/($Q$8-$F$8))*($S$38) -> 2553544.2 | H38: =(H8/($Q$8-$F$8))*($S$38) -> 1239.5856 | I38: =(I8/($Q$8-$F$8))*($S$38) -> 263583.81 | J38: =(J8/($Q$8-$F$8))*($S$38) -> 2584.3723 | K38: =(K8/($Q$8-$F$8))*($S$38) -> 100834.35 | L38: =(L8/($Q$8-$F$8))*($S$38) -> 184070.05 | M38: =(M8/($Q$8-$F$8))*($S$38) -> 67565.684 | N38: =SUM(G38:M38) -> 3173422.1 | O38: =(O8/($Q$8-$F$8))*($S$38) -> 386633.32 | P38: =(P8/($Q$8-$F$8))*($S$38) -> 173474.77 | Q38: =SUM(N38:P38) -> 3733530.1 | S38: =('1TestYr_adj'!S97+'1TestYr_adj'!S108) -> 3733530.1
B40: Net Margins | F40: =(F36+F38) -> 1223.1 | G40: =(G36+G38) -> -2368651.6 | H40: =(H36+H38) -> -25012.796 | I40: =(I36+I38) -> -489805.12 | J40: =(J36+J38) -> -43141.742 | K40: =(K36+K38) -> 320291.19 | L40: =(L36+L38) -> 27367.207 | M40: =(M36+M38) -> -435984.25 | ... Q40: =(Q36+Q38) -> -2452900
S41: =SUM(G40,H40,I40,J40,L40)/(SUM(G8,H8,I8,J8,L8,)) -> -0.031866166
B42: BILLING UNITS
B43: Consumer Charge Units | G43: =('[10]rate schedules'!$B$12+'[10]rate schedules'!$B$13) -> 633843 | H43: =('[10]rate schedules'!$B$43) -> 447 | I43: =('[10]rate schedules'!$B$75) -> 30758 | J43: =('[10]rate schedules'!$B$106) -> 323 | K43: =('[10]rate schedules'!$B$140) -> 673 | L43: =('[10]rate schedules'!$B$173) -> 276 | M43: =('[10]rate schedules'!$B$303) -> 180862 | O43: 60 | P43: =[9]monthly!$C$294 -> 12
B45: Energy kWh | G45: ='4.1 kW & kWh'!C22 -> 793939806 | H45: ='4.1 kW & kWh'!D22 -> 437447 | I45: ='4.1 kW & kWh'!E22 -> 70405905 | J45: ='4.1 kW & kWh'!F22 -> 659159 | K45: ='4.1 kW & kWh'!G22 -> 37501047 | L45: ='4.1 kW & kWh'!H22 -> 80941225 | M45: ='4.1 kW & kWh'!I22 -> 9008707 | O45: ='4.1 kW & kWh'!K22 -> 198094047 | P45: ='4.1 kW & kWh'!L22 -> 1.0406704e+08
B47: Demand kW | K47: =('[10]rate schedules'!$B$141) -> 110568 | L47: =('[10]rate schedules'!$B$175) -> 208910.72 | O47: =('[10]rate schedules'!$B$208+'[10]rate schedules'!$B$209) -> 379595.29 | P47: =('[10]rate schedules'!$B$243) -> 181668
B50: COST BASED RATES
B51: Customer Charge | G51: =(G32/G43) -> 27.299435 | H51: =(H32/H43) -> 29.793143 | I51: =(I32/I43) -> 38.54191 | J51: =(J32/J43) -> 52.689554 | K51: =(K32/K43) -> 44.879728 | L51: =(L32/L43) -> 56.410443 | M51: =(M32/M43) -> 9.7654737 | O51: =(O32/O43) -> 308.17403 | P51: =(P32/P43) -> 602.59489
B52: Energy Charge | G52: =(G34+G13-G32)/(G45) -> 0.08178367 | H52: =(H34+H13-H32)/(H45) -> 0.11536323 | I52: =(I34+I13-I32)/(I45) -> 0.10721177 | J52: =(J34+J13-J32)/(J45) -> 0.1622574 | K52: =(K34+K13-K32)/(K45) -> 0.07475156 | L52: =(L34+L13-L32)/(L45) -> 0.070596304 | M52: =(M34+M13-M32)/(M45) -> 0.086916684 | O52: =(O34+O13-O32)/(O45) -> 0.058263021 | P52: =(P34+P13-P32)/(P45) -> 0.051795369
B53: Demand Charge | K53: =(K11+K22)/(K47) -> 7.7232643 | L53: =(L11+L22)/(L47) -> 7.2126586 | O53: =SUM(O11+O22)/(O47) -> 7.9987155 | P53: =SUM(P11+P22)/(P47) -> 8.4285895

Sheet -6 Increase
D3: =('12 Inc Stmt Func'!E4) | E3: =('12 Inc Stmt Func'!G4) -> GS 1 | F3: =('12 Inc Stmt Func'!H4) -> GS 1 | G3: =('12 Inc Stmt Func'!I4) -> SC1 | H3: =('12 Inc Stmt Func'!J4) -> SC2 | I3: =('12 Inc Stmt Func'!K4) -> LP1 | J3: =('12 Inc Stmt Func'!L4) -> LP2 | K3: =('12 Inc Stmt Func'!M4) -> 0 | L3: =('12 Inc Stmt Func'!N4) -> Total | ... O3: =('12 Inc Stmt Func'!Q4) -> Total
D4: =('12 Inc Stmt Func'!E5) -> Enviro | E4: =('12 Inc Stmt Func'!G5) -> Residential | F4: =('12 Inc Stmt Func'!H5) -> Residential | G4: =('12 Inc Stmt Func'!I5) -> Gen Service | H4: =('12 Inc Stmt Func'!J5) -> Gen Service | I4: =('12 Inc Stmt Func'!K5) -> Large Power | J4: =('12 Inc Stmt Func'!L5) -> Large Power | K4: =('12 Inc Stmt Func'!M5) -> Outdoor | L4: =('12 Inc Stmt Func'!N5) -> EKPC Sched | ... O4: =('12 Inc Stmt Func'!Q5) -> for All
D5: =('12 Inc Stmt Func'!E6) -> watts | E5: =('12 Inc Stmt Func'!G6) -> & Farm | F5: =('12 Inc Stmt Func'!H6) -> & Farm TOD | G5: =('12 Inc Stmt Func'!I6) -> 0-100 kW | H5: =('12 Inc Stmt Func'!J6) -> 0-100 kW TOD | I5: =('12 Inc Stmt Func'!K6) -> under 500 kW | J5: =('12 Inc Stmt Func'!L6) -> over 500 kW | K5: =('12 Inc Stmt Func'!M6) -> Lights | L5: =('12 Inc Stmt Func'!N6) -> E Rates | ... O5: =('12 Inc Stmt Func'!Q6) -> Rate Classes
A7: Total Revenue
A8: Requirements | D8: =('4 Allocation'!D19) -> 6455.25 | E8: =('4 Allocation'!E19) -> 82234866 | F8: =('4 Allocation'!F19) -> 63782.834 | G8: =('4 Allocation'!G19) -> 8733814.1 | H8: =('4 Allocation'!H19) -> 123972.15 | I8: =('4 Allocation'!I19) -> 2833465.8 | J8: =('4 Allocation'!J19) -> 5729720.6 | K8: =('4 Allocation'!K19) -> 2549210 | ... O8: =('4 Allocation'!O19) -> 1.1923276e+08
A9: Actual Revenue from Rates | D9: =('12 Inc Stmt Func'!F8) -> 7678.35 | E9: =('12 Inc Stmt Func'!G8) -> 77312671 | F9: =('12 Inc Stmt Func'!H8) -> 37530.453 | G9: =('12 Inc Stmt Func'!I8) -> 7980425.2 | H9: =('12 Inc Stmt Func'!J8) -> 78246.04 | I9: =('12 Inc Stmt Func'!K8) -> 3052922.7 | J9: =('12 Inc Stmt Func'!L8) -> 5573017.8 | K9: =('12 Inc Stmt Func'!M8) -> 2045660.1 | ... O9: =('12 Inc Stmt Func'!Q8) -> 1.1304633e+08 | Q9: =SUM(L9:N9) -> 1.1304633e+08
A10: Under (Over) | D10: =(D8-D9) -> -1223.1 | E10: =(E8-E9) -> 4922195.8 | F10: =(F8-F9) -> 26252.381 | G10: =(G8-G9) -> 753388.93 | H10: =(H8-H9) -> 45726.115 | I10: =(I8-I9) -> -219456.83 | J10: =(J8-J9) -> 156702.84 | K10: =(K8-K9) -> 503549.93 | ... P10: =(P8-P9) -> 0
A12: Rate Revenue Percent | E12: =(E9)/($O$9-$D$9) -> 0.683949 | F12: =(F9)/($O$9-$D$9) -> 0.00033201434 | G12: =(G9)/($O$9-$D$9) -> 0.070599085 | H12: =(H9)/($O$9-$D$9) -> 0.00069220608 | I12: =(I9)/($O$9-$D$9) -> 0.027007777 | J12: =(J9)/($O$9-$D$9) -> 0.049301879 | K12: =(K9)/($O$9-$D$9) -> 0.018096997 | L12: =(L9)/($O$9-$D$9) -> 0.85004688 | ... O12: =(O9)/($O$9-$D$9) -> 1.0000679
A13: Less Other Revenue | E13: =(E12*$Q$26) -> 2553544.2 | F13: =(F12*$Q$26) -> 1239.5856 | G13: =(G12*$Q$26) -> 263583.81 | H13: =(H12*$Q$26) -> 2584.3723 | I13: =(I12*$Q$26) -> 100834.35 | J13: =(J12*$Q$26) -> 184070.05 | K13: =(K12*$Q$26) -> 67565.684 | L13: =SUM(E13:K13) -> 3173422.1 | M13: =(M12*$Q$26) -> 386633.32 | N13: =(N12*$Q$26) -> 173474.77 | O13: =SUM(L13:N13) -> 3733530.1
A15: COSS Suggested | D15: =(D10-D13) -> -1223.1 | E15: =(E10-E13) -> 2368651.6 | F15: =(F10-F13) -> 25012.796 | G15: =(G10-G13) -> 489805.12 | H15: =(H10-H13) -> 43141.742 | I15: =(I10-I13) -> -320291.19 | J15: =(J10-J13) -> -27367.207 | K15: =(K10-K13) -> 435984.25 | L15: =SUM(D15:K15) -> 3013714 | M15: =(M10-M13) -> -532532.74 | N15: =(N10-N13) -> -28281.195 | O15: =SUM(L15:N15) -> 2452900
A16: Revenue Increase
A17: Percent | D17: =(D15/D9) -> -0.15929204 | E17: =(E15/E9) -> 0.030637301 | F17: =(F15/F9) -> 0.66646666 | G17: =(G15/G9) -> 0.061375818 | H17: =(H15/H9) -> 0.55136007 | I17: =(I15/I9) -> -0.10491297 | J17: =(J15/J9) -> -0.0049106621 | K17: =(K15/K9) -> 0.21312643 | ... O17: =(O15/O9) -> 0.021698184
A19: Recommended Increase | D19: 0 | E19: =(E9*$D$45) -> 2010129.4 | F19: =(F9*$D$45) -> 975.79177 | G19: =(G9*$E$45) -> 279314.88 | H19: =(H9*$E$45) -> 2738.6114 | I19: 0 | J19: 0 | K19: =(2452900-2293159) -> 159741 | L19: =SUM(E19:K19) -> 2452899.7 | M19: 0 | N19: 0 | O19: =SUM(L19:N19) -> 2452899.7
A21: Percent Increase | D21: 0 | E21: =(E19/E9) -> 0.026 | F21: =(F19/F9) -> 0.026 | G21: =(G19/G9) -> 0.035 | H21: =(H19/H9) -> 0.035 | I21: =(I19/I9) -> 0 | J21: =(J19/J9) -> 0 | K21: =(K19/K9) -> 0.078087752 | L21: =(L19/L9) -> 0.025527598 | ... O21: =(O19/O9) -> 0.021698181
A24: New Revenue Require. | E24: =(E9+E19) -> 79322800 | F24: =(F9+F19) -> 38506.245 | G24: =(G9+G19) -> 8259740.1 | H24: =(H9+H19) -> 80984.651 | I24: =(I9+I19) -> 3052922.7 | J24: =(J9+J19) -> 5573017.8 | K24: =(K9+K19) -> 2205401.1 | L24: =SUM(E24:K24) -> 98533373 | M24: =(M9+M19) -> 11705947 | N24: =(N9+N19) -> 5252228.5 | O24: =SUM(L24:N24) -> 1.1549155e+08
A26: Billing Determinants | E26: 0 | F26: 0 | G26: 0 | H26: 0 | I26: 0 | J26: 0 | K26: 0 | L26: 0 | M26: 0 | N26: 0 | Q26: ='1TestYr_adj'!S97+'1TestYr_adj'!S108 -> 3733530.1
A27: Customer Charges | E27: =('12 Inc Stmt Func'!G43) -> 633843 | F27: =('12 Inc Stmt Func'!H43) -> 447 | G27: =('12 Inc Stmt Func'!I43) -> 30758 | H27: =('12 Inc Stmt Func'!J43) -> 323 | I27: =('12 Inc Stmt Func'!K43) -> 673 | J27: =('12 Inc Stmt Func'!L43) -> 276 | K27: =('12 Inc Stmt Func'!M43) -> 180862 | M27: =('12 Inc Stmt Func'!O43) -> 60 | N27: =('12 Inc Stmt Func'!P43) -> 12 | O27: =('12 Inc Stmt Func'!Q43)
