Workbook
Name \0: #REF!
Name \F: #REF!
Name \S: #REF!
Name \V: #REF!
Name \Y: #REF!
Name _\4: #REF!
Name _0: #REF!
Name _2_ALT_Y_: #REF!
Name _3_ALT_F: #REF!
Name _P: #REF!
Name A_R_INTERCOMPANY: #REF!
Name Account: #REF!
Name Account2: #REF!
Name AccountDescr: #REF!
Name AccountDescr2: #REF!
Name acct: #REF!
Name acct_mo: #REF!
Name Activity: #REF!
Name Activity2: #REF!
Name ActivityDescr: #REF!
Name ActivityDescr2: #REF!
Name Affiliate: #REF!
Name Affiliate2: #REF!
Name AffiliateDescr: #REF!
Name APN: #REF!
Name arintercompany: #REF!
Name ASD: '[1]FIM trial bal'!$M$5
Name backup_servicer_start_date: [2]Main!#REF!
Name Backup_Servicing_Trigger: [2]Main!#REF!
Name Bond_Cashflows: #REF!
Name BU: #REF!
Name BUDGET: #REF!
Name BUNODE: #REF!
Name BusinessUnit: #REF!
Name BusinessUnit2: #REF!
Name By_Summary_Ledger: #REF!
Name calc_method: [2]Main!#REF!
Name calc_res: [2]Main!#REF!
Name Cancel: [3]!Cancel
Name Choice_Period_Lag: [2]Main!#REF!
Name Class_A1: #REF!
Name Class_A2: #REF!
Name Class_A3: #REF!
Name colcurve: '[4]Classes & Groups'!$C$89
Name Completed: #REF!
Name COPY: #REF!
Name Credit: [5]JOURNAL!#REF!
Name Credit: [5]JOURNAL!#REF!
Name Credit: [6]JOURNAL!#REF!
Name D: 41291.2506944444
Name Date: #REF!
Name Date_Choice: [2]Main!#REF!
Name Date_Closing: [7]Main!$B$7
Name Date_First_Payment: [7]Main!$B$8
Name Date_Interim_TrueUp: [2]Main!#REF!
Name Date1: #REF!
Name Date2: #REF!
Name DATES: #REF!
Name Debit: [5]JOURNAL!#REF!
Name Debit: [5]JOURNAL!#REF!

Sheet Coversheet

Sheet Connect Information
A7: Web Server Machine Name: | B7: fimprod.corp.oncor.com
A8: Portal: | B8: EMPLOYEE
A9: HTTP Port: | B9: 44300
A10: Protocol: | B10: https
A11: PeopleSoft Site Name: | B11: fimprod
A12: Node: | B12: PSFT_EP
A13: Blocking Factor: | B13: 40
A15: Action: | B15: CREATE
A16: Chunking | B16: 50
A20: TU_ACCT_REC_ENTRY

Sheet Template
A2: TU_ACCT_REC_ENTRY
A5: Collection | D5: TU_ACCT_REC_ENTRY | E5: TU_ACCT_REC_ENTRY | F5: TU_ACCT_REC_ENTRY | G5: TU_ACCT_REC_ENTRY | H5: TU_ACCT_REC_ENTRY | I5: TU_ACCT_REC_ENTRY | J5: TU_ACCT_REC_ENTRY | K5: TU_ACCT_REC_ENTRY | L5: TU_ACCT_REC_ENTRY | M5: TU_ACCT_REC_ENTRY | N5: TU_ACCT_REC_ENTRY | O5: TU_ACCT_REC_ENTRY | P5: TU_ACCT_REC_ENTRY | Q5: TU_ACCT_REC_ENTRY | R5: TU_ACCT_REC_ENTRY | S5: TU_ACCT_REC_ENTRY | T5: TU_ACCT_REC_LN | U5: TU_ACCT_REC_LN | V5: TU_ACCT_REC_LN | W5: TU_ACCT_REC_LN | X5: TU_ACCT_REC_LN | Y5: TU_ACCT_REC_LN | Z5: TU_ACCT_REC_LN | AA5: TU_ACCT_REC_LN | AB5: TU_ACCT_REC_LN | AC5: TU_ACCT_REC_LN | AD5: TU_ACCT_REC_LN
A6: Property | D6: BUSINESS_UNIT | E6: MONTH | F6: YEAR | G6: TU_ACCT_REF_NUM | H6: TU_BU_TYPE | I6: TU_BU_GROUP | J6: TU_RECON_FREQ | K6: TU_SOURCE_OF_INFO | L6: TU_BAL_PER_GL | M6: TU_BAL_PER_SYS | N6: TU_TOT_HRS_ACCTRCN | O6: OPRID | P6: TU_REC_PREP_DT | Q6: TU_APPROVER_ID | R6: TU_REC_APPRV_DT | S6: TU_ACCOUNTINGOWNER | T6: SEQNBR | U6: TU_ACCT_REC_DTL_BU | V6: ACCOUNT | W6: DEPTID | X6: AFFILIATE | Y6: TU_EC | Z6: TU_ACTIVITY | AA6: TU_LOCATION | AB6: PROJECT_ID | AC6: MONETARY_AMOUNT | AD6: TU_ACCT_REC_DTLCMT
A7: Record Type | D7: 000 | E7: 000 | F7: 000 | G7: 000 | H7: 000 | I7: 000 | J7: 000 | K7: 000 | L7: 000 | M7: 000 | N7: 000 | O7: 000 | P7: 000 | Q7: 000 | R7: 000 | S7: 000 | T7: 100 | U7: 100 | V7: 100 | W7: 100 | X7: 100 | Y7: 100 | Z7: 100 | AA7: 100 | AB7: 100 | AC7: 100 | AD7: 100
A8: Field Type | P8: CHAR | R8: CHAR
A9: Key / Required | D9: Y/R | E9: Y/R | F9: Y/R | G9: Y/R | H9: Y/R | I9: Y/R | J9: / | K9: / | L9: / | M9: / | N9: / | O9: / | P9: / | Q9: / | R9: / | S9: / | T9: Y/ | U9: / | V9: / | W9: / | X9: / | Y9: / | Z9: / | AA9: / | AB9: / | AC9: / | AD9: /
A10: Sequence | D10: 1 | E10: 2 | F10: 3 | G10: 4 | H10: 5 | I10: 6 | J10: 7 | K10: 8 | L10: 9 | M10: 10 | N10: 11 | O10: 12 | P10: 13 | Q10: 14 | R10: 15 | S10: 16 | T10: 17 | U10: 18 | V10: 19 | W10: 20 | X10: 21 | Y10: 22 | Z10: 23 | AA10: 24 | AB10: 25 | AC10: 26 | AD10: 27
A11: Status | B11: Line No | C11: Record type | D11: Business Unit | E11: Month | F11: Year | G11: Account Recon Reference Group | H11: Business Unit Type | I11: Business Unit Recon Group | J11: Reconcile Frequency | K11: Source of Information | L11: General Ledger Balance | M11: Balance Per System/WorkSheet | N11: Total Hours Doing Acct Recon | O11: User ID | P11: Account Recon Prep Date | Q11: Approver ID | R11: Account Recon Approved Date | S11: Accounting Owner | T11: Sequence Number | U11: Acct Recon Detail Line BU | V11: Account | W11: Department | X11: Affiliate | Y11: Expense Code | Z11: Activity | AA11: Location | AB11: Project | AC11: Monetary Amount | AD11: Acct Recon Detail Line Comment
A12: Template | C12: 000
A13: Template | C13: 100

Sheet Data Input
A2: Business Unit | B2: Month | C2: Year | D2: Account Recon Reference Group | E2: Business Unit Type | F2: Business Unit Recon Group | G2: Reconcile Frequency | H2: Source of Information | I2: General Ledger Balance | J2: Balance Per System/WorkSheet | K2: Total Hours Doing Acct Recon | L2: User ID | M2: Account Recon Prep Date | N2: Approver ID | O2: Account Recon Approved Date | P2: Accounting Owner | Q2: Acct Recon Detail Line BU | R2: Account | S2: Department | T2: Affiliate | U2: Expense Code | V2: Activity | W2: Location | X2: Project | Y2: Monetary Amount | Z2: Acct Recon Detail Line Comment

Sheet WP II-E-4.1.1 AMS RCE
I6: 5
E7: Approved | F7: Amortizations | G7: At 12-31-2021 | I7: year | K7: Account 928
A8: Unit | B8: Account | C8: Project | D8: Description | E8: Rate Case Expenses | F8: through 12-31-2021 | G8: Reconciled Balance | I8: Amortization | J8: Test year amortizations | K8: K&M adjustment #36
A9: ESD | B9: 1861101 | C9: 11AMSREC | D9: 2011 AMS Reconciliation Case | E9: ='11AMSREC'!B22+SUM('11AMSREC'!F22:F25)+'11AMSREC'!F46 -> 608959.52 | F9: =ROUND(SUM('11AMSREC'!D17:D144),2) -> 580688.66 | G9: =+E9-F9 -> 28270.86 | I9: =ROUND(G9/I$6,2) -> 5654.17 | J9: =SUM('11AMSREC'!D133:D144) -> 31219.68 | K9: =I9-J9 -> -25565.51
A10: ESD | B10: 1861101 | C10: 13AMSREC | D10: 2013 AMS Reconciliation Expense | E10: ='13AMSREC'!B48+'13AMSREC'!F49+'13AMSREC'!F51+'13AMSREC'!F52 -> 312730.25 | F10: =SUM('13AMSREC'!D48:D145) -> 293148.48 | G10: =+E10-F10 -> 19581.768 | I10: =ROUND(G10/I$6,2) -> 3916.35 | J10: =SUM('13AMSREC'!D134:D145) -> 21624 | K10: =I10-J10 -> -17707.65
A11: ESD | B11: 1861101 | C11: DOC35718 | D11: Rate Case Expenses for AMS | E11: ='DOC35718'!B12+SUM('DOC35718'!F12:F71) -> 921535.55 | F11: =ROUND(SUM('DOC35718'!D11:D168),2) -> 889308.49 | G11: =+E11-F11 -> 32227.06 | I11: =ROUND(G11/I$6,2) -> 6445.41 | J11: =SUM('DOC35718'!D157:D168) -> 35588.28 | K11: =I11-J11 -> -29142.87
E12: =SUM(E9:E11) -> 1843225.3 | F12: =SUM(F9:F11) -> 1763145.6 | G12: =SUM(G9:G11) -> 80079.688 | I12: =SUM(I9:I11) -> 16015.93 | J12: =SUM(J9:J11) -> 88431.96 | K12: =SUM(K9:K11) -> -72416.03
A14: These rate case expenses were approved in Docket No. 46957. Reference Docket No. 46957 Finding of Fact Nos.:
A15: 36. All Oncor investment, including advanced metering system (AMS) investment, through
A16: the end of the test year (December 31, 2016) of $10,989,502,464, including
A17: $12,570,327,998 of net plant in service, as presented in Oncor's RFP, is prudent and
A18: includable in rate base, except that the six neighborhood reliability lithium-ion batteries
A19: used by Oncor are not included in this finding. Oncor can seek a prudence finding related
A20: to these batteries in a future proceeding.
A21: 37. All investment in the distribution and transmission assets that are provided to Oncor in the
A22: Sharyland Transaction are used by and useful to Oncor in providing service, are prudent,
A23: reasonable, and necessary, and are includable in Oncor's rate base, which with the
A24: inclusion of those assets is $10,991,993,213.
A26: Five-year amortizations were approved in Docket No. 46957 and began 11-27-2017 when rates were effective. In this case, requesting five-year amortization of unamortized balances at 12-31-2021 that were previously approved.

Sheet 11AMSREC
A10: Date | B10: Beginning Balance | D10: Monthly Amortization | F10: Adjustments | H10: Ending Balance | J10: Periods Remaining
A12: 40544 | D12: =B12/J12 -> 0 | H12: =B12-D12+F12 -> 0 | J12: 108
A13: 40575 | D13: =B13/J13 -> 0 | H13: =B13-D13+F13 -> 0 | J13: 107
A14: 40603 | D14: =B14/J14 -> 0 | H14: =B14-D14+F14 -> 0 | J14: 106
A15: 40634 | D15: =B15/J15 -> 0 | H15: =B15-D15+F15 -> 0 | J15: 105
A16: 40664 | D16: =B16/J16 -> 0 | H16: =B16-D16+F16 -> 0 | J16: 104
A17: 40695 | D17: =B17/J17 -> 0 | H17: =B17-D17+F17 -> 0 | J17: 103
A18: 40725 | D18: =B18/J18 -> 0 | H18: =B18-D18+F18 -> 0 | J18: 102
A19: 40756 | D19: =B19/J19 -> 0 | H19: =B19-D19+F19 -> 0 | J19: 101
A20: 40787 | D20: =B20/J20 -> 0 | H20: =B20-D20+F20 -> 0 | J20: 100
A21: 40817 | D21: =B21/J21 -> 0 | H21: =B21-D21+F21 -> 0 | J21: 99
A22: 40848 | B22: 597920.8 | D22: =B22/J22 -> 6101.2327 | F22: 52254.57 | H22: =B22-D22+F22 -> 644074.14 | J22: 98
A23: 40878 | B23: =H22 -> 644074.14 | D23: =B23/J23 -> 6639.9396 | F23: -55795.45 | H23: =B23-D23+F23 -> 581638.75 | J23: 97
A24: 40909 | B24: =H23 -> 581638.75 | D24: =B24/J24 -> 6058.737 | F24: 14624.96 | H24: =B24-D24+F24 -> 590204.97 | J24: 96
A25: 40940 | B25: =H24 -> 590204.97 | D25: =B25/J25 -> 6212.6839 | F25: 381.04 | H25: =B25-D25+F25 -> 584373.33 | J25: 95
A26: 40969 | B26: =H25 -> 584373.33 | D26: =ROUND((B26/J26),2) -> 6216.74 | F26: 0 | H26: =B26-D26+F26 -> 578156.59 | J26: 94
A27: 41000 | B27: =H26 -> 578156.59 | D27: =ROUND((B27/J27),2) -> 6216.74 | H27: =B27-D27+F27 -> 571939.85 | J27: 93
A28: 41030 | B28: =H27 -> 571939.85 | D28: =ROUND((B28/J28),2) -> 6216.74 | H28: =B28-D28+F28 -> 565723.11 | J28: 92
A29: 41061 | B29: =H28 -> 565723.11 | D29: =ROUND((B29/J29),2) -> 6216.74 | H29: =B29-D29+F29 -> 559506.37 | J29: 91
A30: 41091 | B30: =H29 -> 559506.37 | D30: =ROUND((B30/J30),2) -> 6216.74 | H30: =B30-D30+F30 -> 553289.63 | J30: 90
A31: 41122 | B31: =H30 -> 553289.63 | D31: =ROUND((B31/J31),2) -> 6216.74 | H31: =B31-D31+F31 -> 547072.89 | J31: 89
A32: 41153 | B32: =H31 -> 547072.89 | D32: =ROUND((B32/J32),2) -> 6216.74 | F32: 719.55 | H32: =B32-D32+F32 -> 541575.7 | J32: 88
A33: 41183 | B33: =H32 -> 541575.7 | D33: =ROUND((B33/J33),2) -> 6225.01 | F33: -719.55 | H33: =B33-D33+F33 -> 534631.14 | J33: 87
A34: 41214 | B34: =H33 -> 534631.14 | D34: =ROUND((B34/J34),2) -> 6216.64 | H34: =B34-D34+F34 -> 528414.5 | J34: 86
A35: 41244 | B35: =H34 -> 528414.5 | D35: =ROUND((B35/J35),2) -> 6216.64 | H35: =B35-D35+F35 -> 522197.86 | J35: 85
A36: 41275 | B36: =H35 -> 522197.86 | D36: =ROUND((B36/J36),2) -> 6216.64 | H36: =B36-D36+F36 -> 515981.22 | J36: 84
A37: 41306 | B37: =H36 -> 515981.22 | D37: =ROUND((B37/J37),2) -> 6216.64 | H37: =B37-D37+F37 -> 509764.58 | J37: 83
A38: 41334 | B38: =H37 -> 509764.58 | D38: =ROUND((B38/J38),2) -> 6216.64 | H38: =B38-D38+F38 -> 503547.94 | J38: 82
A39: 41365 | B39: =H38 -> 503547.94 | D39: =ROUND((B39/J39),2) -> 6216.64 | H39: =B39-D39+F39 -> 497331.3 | J39: 81
A40: 41395 | B40: =H39 -> 497331.3 | D40: =ROUND(B40/J40,2) -> 6216.64 | H40: =B40-D40+F40 -> 491114.66 | J40: 80
A41: 41426 | B41: =H40 -> 491114.66 | D41: =B41/J41 -> 6216.6412 | H41: =B41-D41+F41 -> 484898.02 | J41: 79
A42: 41456 | B42: =H41 -> 484898.02 | D42: =B42/J42 -> 6216.6412 | H42: =B42-D42+F42+0.01 -> 478681.38 | J42: 78
A43: 41487 | B43: =H42 -> 478681.38 | D43: =B43/J43 -> 6216.6414 | H43: =B43-D43+F43 -> 472464.74 | J43: 77
A44: 41518 | B44: =H43 -> 472464.74 | D44: =B44/J44 -> 6216.6414 | H44: =B44-D44+F44 -> 466248.1 | J44: 76
A45: 41548 | B45: =H44 -> 466248.1 | D45: =B45/J45 -> 6216.6414 | H45: =B45-D45+F45 -> 460031.46 | J45: 75
A46: 41579 | B46: =H45 -> 460031.46 | D46: =B46/J46 -> 6216.6414 | F46: =-636.55+210.15 -> -426.4 | H46: =B46-D46+F46 -> 453388.42 | J46: 74
A47: 41609 | B47: =H46 -> 453388.42 | D47: =B47/J47 -> 6210.8003 | F47: 0 | H47: =B47-D47+F47 -> 447177.62 | J47: 73
A48: 41640 | B48: =H47 -> 447177.62 | D48: =B48/J48 -> 6210.8003 | H48: =B48-D48+F48 -> 440966.82 | J48: 72
A49: 41671 | B49: =H48 -> 440966.82 | D49: =B49/J49 -> 6210.8003 | H49: =B49-D49+F49 -> 434756.02 | J49: 71
A50: 41699 | B50: =H49 -> 434756.02 | D50: =B50/J50 -> 6210.8003 | H50: =B50-D50+F50 -> 428545.22 | J50: 70
A51: 41730 | B51: =H50 -> 428545.22 | D51: =B51/J51 -> 6210.8003 | H51: =B51-D51+F51 -> 422334.42 | J51: 69
A52: 41760 | B52: =H51 -> 422334.42 | D52: =B52/J52 -> 6210.8003 | H52: =B52-D52+F52 -> 416123.62 | J52: 68
A53: 41791 | B53: =H52 -> 416123.62 | D53: =B53/J53 -> 6210.8003 | H53: =B53-D53+F53 -> 409912.82 | J53: 67
A54: 41821 | B54: =H53 -> 409912.82 | D54: =B54/J54 -> 6210.8003 | H54: =B54-D54+F54 -> 403702.02 | J54: 66
A55: 41852 | B55: =H54 -> 403702.02 | D55: =B55/J55 -> 6210.8003 | H55: =B55-D55+F55 -> 397491.22 | J55: 65
A56: 41883 | B56: =H55 -> 397491.22 | D56: =B56/J56 -> 6210.8003 | H56: =B56-D56+F56 -> 391280.42 | J56: 64
A57: 41913 | B57: =H56 -> 391280.42 | D57: =B57/J57 -> 6210.8003 | H57: =B57-D57+F57 -> 385069.62 | J57: 63
A58: 41944 | B58: =H57 -> 385069.62 | D58: =B58/J58 -> 6210.8003 | H58: =B58-D58+F58 -> 378858.82 | J58: 62
A59: 41974 | B59: =H58 -> 378858.82 | D59: =B59/J59 -> 6210.8003 | H59: =B59-D59+F59 -> 372648.02 | J59: 61
... A93: 43009 | B93: =H92 -> 167691.61 | D93: =B93/J93 -> 6210.8003 | H93: =B93-D93+F93 -> 161480.81 | J93: 27
A94: 43065 | B94: =H93 -> 161480.81 | D94: =ROUND(B94/J94,2)*26/30 -> 5382.6933 | H94: =B94-D94+F94 -> 156098.11 | J94: 26
A95: 43069 | B95: =H94 -> 156098.11 | D95: =ROUND(+$B$164,2)*4/30 -> 346.88533 | H95: =B95-D95+F95 -> 155751.23 | J95: 60
A96: 43070 | B96: =H95 -> 155751.23 | D96: =ROUND(+$B$164,2) -> 2601.64 | H96: =B96-D96+F96 -> 153149.59 | J96: 60
A97: 43101 | B97: =H96 -> 153149.59 | D97: =ROUND(+$B$164,2) -> 2601.64 | H97: =B97-D97+F97 -> 150547.95 | J97: =+J96-1 -> 59
A98: 43132 | B98: =H97 -> 150547.95 | D98: =ROUND(+$B$164,2) -> 2601.64 | H98: =B98-D98+F98 -> 147946.31 | J98: =+J97-1 -> 58
A99: 43160 | B99: =H98 -> 147946.31 | D99: =ROUND(+$B$164,2) -> 2601.64 | H99: =B99-D99+F99 -> 145344.67 | J99: =+J98-1 -> 57
A100: 43191 | B100: =H99 -> 145344.67 | D100: =ROUND(+$B$164,2) -> 2601.64 | H100: =B100-D100+F100 -> 142743.03 | J100: =+J99-1 -> 56
A101: 43221 | B101: =H100 -> 142743.03 | D101: =ROUND(+$B$164,2) -> 2601.64 | H101: =B101-D101+F101 -> 140141.39 | J101: =+J100-1 -> 55
A102: 43252 | B102: =H101 -> 140141.39 | D102: =ROUND(+$B$164,2) -> 2601.64 | H102: =B102-D102+F102 -> 137539.75 | J102: =+J101-1 -> 54
A103: 43282 | B103: =H102 -> 137539.75 | D103: =ROUND(+$B$164,2) -> 2601.64 | H103: =B103-D103+F103 -> 134938.11 | J103: =+J102-1 -> 53
A104: 43313 | B104: =H103 -> 134938.11 | D104: =ROUND(+$B$164,2) -> 2601.64 | H104: =B104-D104+F104 -> 132336.47 | J104: =+J103-1 -> 52
A105: 43344 | B105: =H104 -> 132336.47 | D105: =ROUND(+$B$164,2) -> 2601.64 | H105: =B105-D105+F105 -> 129734.83 | J105: =+J104-1 -> 51
A106: 43374 | B106: =H105 -> 129734.83 | D106: =ROUND(+$B$164,2) -> 2601.64 | H106: =B106-D106+F106 -> 127133.19 | J106: =+J105-1 -> 50
A107: 43405 | B107: =H106 -> 127133.19 | D107: =ROUND(+$B$164,2) -> 2601.64 | H107: =B107-D107+F107 -> 124531.55 | J107: =+J106-1 -> 49
A108: 43435 | B108: =H107 -> 124531.55 | D108: =ROUND(+$B$164,2) -> 2601.64 | H108: =B108-D108+F108 -> 121929.91 | J108: =+J107-1 -> 48
... A132: 44166 | B132: =H131 -> 62092.188 | D132: =ROUND(+$B$164,2) -> 2601.64 | H132: =B132-D132+F132 -> 59490.548 | J132: =+J131-1 -> 24
A133: =+A132+31 -> 44197 | B133: =H132 -> 59490.548 | D133: =ROUND(+$B$164,2) -> 2601.64 | H133: =B133-D133+F133 -> 56888.908 | J133: =+J132-1 -> 23
A134: =+A133+31 -> 44228 | B134: =H133 -> 56888.908 | D134: =ROUND(+$B$164,2) -> 2601.64 | H134: =B134-D134+F134 -> 54287.268 | J134: =+J133-1 -> 22
A135: =+A134+31 -> 44259 | B135: =H134 -> 54287.268 | D135: =ROUND(+$B$164,2) -> 2601.64 | H135: =B135-D135+F135 -> 51685.628 | J135: =+J134-1 -> 21
A136: =+A135+31 -> 44290 | B136: =H135 -> 51685.628 | D136: =ROUND(+$B$164,2) -> 2601.64 | H136: =B136-D136+F136 -> 49083.988 | J136: =+J135-1 -> 20
A137: =+A136+31 -> 44321 | B137: =H136 -> 49083.988 | D137: =ROUND(+$B$164,2) -> 2601.64 | H137: =B137-D137+F137 -> 46482.348 | J137: =+J136-1 -> 19
A138: =+A137+31 -> 44352 | B138: =H137 -> 46482.348 | D138: =ROUND(+$B$164,2) -> 2601.64 | H138: =B138-D138+F138 -> 43880.708 | J138: =+J137-1 -> 18
A139: =+A138+31 -> 44383 | B139: =H138 -> 43880.708 | D139: =ROUND(+$B$164,2) -> 2601.64 | H139: =B139-D139+F139 -> 41279.068 | J139: =+J138-1 -> 17
A140: =+A139+31 -> 44414 | B140: =H139 -> 41279.068 | D140: =ROUND(+$B$164,2) -> 2601.64 | H140: =B140-D140+F140 -> 38677.428 | J140: =+J139-1 -> 16
A141: =+A140+31 -> 44445 | B141: =H140 -> 38677.428 | D141: =ROUND(+$B$164,2) -> 2601.64 | H141: =B141-D141+F141 -> 36075.788 | J141: =+J140-1 -> 15
A142: =+A141+31 -> 44476 | B142: =H141 -> 36075.788 | D142: =ROUND(+$B$164,2) -> 2601.64 | H142: =B142-D142+F142 -> 33474.148 | J142: =+J141-1 -> 14
A143: =+A142+31 -> 44507 | B143: =H142 -> 33474.148 | D143: =ROUND(+$B$164,2) -> 2601.64 | H143: =B143-D143+F143 -> 30872.508 | J143: =+J142-1 -> 13
A144: =+A143+31 -> 44538 | B144: =H143 -> 30872.508 | D144: =ROUND(+$B$164,2) -> 2601.64 | H144: =B144-D144+F144 -> 28270.868 | J144: =+J143-1 -> 12
... A154: =+A153+31 -> 44848 | B154: =H153 -> 4856.1081 | D154: =ROUND(+$B$164,2) -> 2601.64 | H154: =B154-D154+F154 -> 2254.4681 | J154: =+J153-1 -> 2
A155: =+A154+31 -> 44879 | B155: =H154 -> 2254.4681 | D155: =ROUND(+$B$164,2)*26/30-0.29 -> 2254.4647 | H155: =B155-D155+F155 -> 0.0034501879 | J155: =+J154-1 -> 1
A157: These rate case expenses were approved in Docket No. 46957.
A158: Five-year amortization was approved in Docket No. 46957 and began 11-27-2017 when rates were effective.
A160: 26 days of amort based on prior rate case amortization of 11 years
A161: 4 days of amortization based on Dkt 46957 amort of 5 years
B162: =+H94 -> 156098.11 | C162: November 26, 2017 Unamortized Bal
B163: 60 | C163: months (five-year amortization)
B164: =ROUND(+B162/B163,2) -> 2601.64 | C164: Monthly Amortization
A166: Requesting five-year amortization in the 2022 base rate case
A167: If approved in 2022 base rate case, amortization schedule
A168: will be revised to reflect approved recovery.

Sheet 13AMSREC
A11: Date | B11: Beginning Balance | D11: Monthly Amortization | F11: Adjustments | H11: Ending Balance | J11: Periods Remaining
A13: 40544 | D13: =B13/J13 -> 0 | H13: =B13-D13+F13 -> 0 | J13: 108
A14: 40575 | D14: =B14/J14 -> 0 | H14: =B14-D14+F14 -> 0 | J14: 107
A15: 40603 | D15: =B15/J15 -> 0 | H15: =B15-D15+F15 -> 0 | J15: 106
A16: 40634 | D16: =B16/J16 -> 0 | H16: =B16-D16+F16 -> 0 | J16: 105
A17: 40664 | D17: =B17/J17 -> 0 | H17: =B17-D17+F17 -> 0 | J17: 104
A18: 40695 | D18: =B18/J18 -> 0 | H18: =B18-D18+F18 -> 0 | J18: 103
A19: 40725 | D19: =B19/J19 -> 0 | H19: =B19-D19+F19 -> 0 | J19: 102
A20: 40756 | D20: =B20/J20 -> 0 | H20: =B20-D20+F20 -> 0 | J20: 101
A21: 40787 | D21: =B21/J21 -> 0 | H21: =B21-D21+F21 -> 0 | J21: 100
A22: 40817 | D22: =B22/J22 -> 0 | H22: =B22-D22+F22 -> 0 | J22: 99
A23: 40848 | B23: 0 | D23: =B23/J23 -> 0 | H23: =B23-D23+F23 -> 0 | J23: 98
A24: 40878 | B24: 0 | D24: =B24/J24 -> 0 | H24: =B24-D24+F24 -> 0 | J24: 97
A25: 40909 | B25: 0 | D25: =B25/J25 -> 0 | H25: =B25-D25+F25 -> 0 | J25: 96
A26: 40940 | B26: 0 | D26: =B26/J26 -> 0 | H26: =B26-D26+F26 -> 0 | J26: 95
A27: 40969 | B27: 0 | D27: =ROUND((B27/J27),2) -> 0 | H27: =B27-D27+F27 -> 0 | J27: 94
A28: 41000 | B28: 0 | D28: =ROUND((B28/J28),2) -> 0 | H28: =B28-D28+F28 -> 0 | J28: 93
A29: 41030 | B29: 0 | D29: =ROUND((B29/J29),2) -> 0 | H29: =B29-D29+F29 -> 0 | J29: 92
A30: 41061 | B30: 0 | D30: =ROUND((B30/J30),2) -> 0 | H30: =B30-D30+F30 -> 0 | J30: 91
A31: 41091 | B31: 0 | D31: =ROUND((B31/J31),2) -> 0 | H31: =B31-D31+F31 -> 0 | J31: 90
A32: 41122 | B32: 0 | D32: =ROUND((B32/J32),2) -> 0 | H32: =B32-D32+F32 -> 0 | J32: 89
A33: 41153 | B33: 0 | D33: =ROUND((B33/J33),2) -> 0 | H33: =B33-D33+F33 -> 0 | J33: 88
A34: 41183 | B34: 0 | D34: =ROUND((B34/J34),2) -> 0 | H34: =B34-D34+F34 -> 0 | J34: 87
A35: 41214 | B35: 0 | D35: =ROUND((B35/J35),2) -> 0 | H35: =B35-D35+F35 -> 0 | J35: 86
A36: 41244 | B36: 0 | D36: =ROUND((B36/J36),2) -> 0 | H36: =B36-D36+F36 -> 0 | J36: 85
A37: 41275 | B37: 0 | D37: =ROUND((B37/J37),2) -> 0 | H37: =B37-D37+F37 -> 0 | J37: 84
A38: 41306 | B38: 0 | D38: =ROUND((B38/J38),2) -> 0 | H38: =B38-D38+F38 -> 0 | J38: 83
... A40: 41365 | B40: 0 | D40: =ROUND((B40/J40),2) -> 0 | H40: =B40-D40+F40 -> 0 | J40: 81
A41: 41395 | B41: 0 | D41: =ROUND(B41/J41,2) -> 0 | H41: =B41-D41+F41 -> 0 | J41: 80
A42: 41426 | B42: 0 | D42: =B42/J42 -> 0 | H42: =B42-D42+F42 -> 0 | J42: 79
A43: 41456 | B43: 0 | D43: =B43/J43 -> 0 | H43: =B43-D43+F43+0.01 -> 0.01 | J43: 78
A44: 41487 | B44: 0 | D44: =B44/J44 -> 0 | H44: =B44-D44+F44 -> 0 | J44: 77
A45: 41518 | B45: 0 | D45: =B45/J45 -> 0 | H45: =B45-D45+F45 -> 0 | J45: 76
A46: 41548 | B46: 0 | D46: =B46/J46 -> 0 | H46: =B46-D46+F46 -> 0 | J46: 75
A47: 41579 | B47: 0 | D47: =B47/J47 -> 0 | H47: =B47-D47+F47 -> 0 | J47: 74
A48: 41609 | B48: 276508.26 | D48: =B48/J48 -> 3787.7844 | H48: =B48-D48+F48 -> 272720.48 | J48: 73
A49: 41640 | B49: =H48 -> 272720.48 | D49: =B49/J49 -> 3787.7844 | F49: 26733 | H49: =B49-D49+F49 -> 295665.69 | J49: 72
A50: 41671 | B50: =H49 -> 295665.69 | D50: =B50/J50 -> 4164.3055 | H50: =B50-D50+F50 -> 291501.39 | J50: 71
A51: 41699 | B51: =H50 -> 291501.39 | D51: =B51/J51 -> 4164.3055 | F51: 9342.99 | H51: =B51-D51+F51 -> 296680.07 | J51: 70
A52: 41730 | B52: =H51 -> 296680.07 | D52: =B52/J52 -> 4299.7112 | F52: 146 | H52: =B52-D52+F52 -> 292526.36 | J52: 69
A53: 41760 | B53: =H52 -> 292526.36 | D53: =B53/J53 -> 4301.8582 | H53: =B53-D53+F53 -> 288224.5 | J53: 68
A54: 41791 | B54: =H53 -> 288224.5 | D54: =B54/J54 -> 4301.8582 | H54: =B54-D54+F54 -> 283922.64 | J54: 67
A55: 41821 | B55: =H54 -> 283922.64 | D55: =B55/J55 -> 4301.8582 | H55: =B55-D55+F55 -> 279620.78 | J55: 66
A56: 41852 | B56: =H55 -> 279620.78 | D56: =B56/J56 -> 4301.8582 | H56: =B56-D56+F56 -> 275318.93 | J56: 65
A57: 41883 | B57: =H56 -> 275318.93 | D57: =B57/J57 -> 4301.8582 | H57: =B57-D57+F57 -> 271017.07 | J57: 64
A58: 41913 | B58: =H57 -> 271017.07 | D58: =B58/J58 -> 4301.8582 | H58: =B58-D58+F58 -> 266715.21 | J58: 63
A59: 41944 | B59: =H58 -> 266715.21 | D59: =B59/J59 -> 4301.8582 | H59: =B59-D59+F59 -> 262413.35 | J59: 62
A60: 41974 | B60: =H59 -> 262413.35 | D60: =B60/J60 -> 4301.8582 | H60: =B60-D60+F60 -> 258111.49 | J60: 61
A61: 42005 | B61: =H60 -> 258111.49 | D61: =B61/J61 -> 4301.8582 | H61: =B61-D61+F61 -> 253809.64 | J61: 60
A62: 42036 | B62: =H61 -> 253809.64 | D62: =B62/J62 -> 4301.8582 | H62: =B62-D62+F62 -> 249507.78 | J62: 59
A63: 42064 | B63: =H62 -> 249507.78 | D63: =B63/J63 -> 4301.8582 | H63: =B63-D63+F63 -> 245205.92 | J63: 58
A64: 42095 | B64: =H63 -> 245205.92 | D64: =B64/J64 -> 4301.8582 | H64: =B64-D64+F64 -> 240904.06 | J64: 57
... A94: 43009 | B94: =H93 -> 116150.17 | D94: =B94/J94 -> 4301.8582 | H94: =B94-D94+F94 -> 111848.31 | J94: 27
A95: 43065 | B95: =H94 -> 111848.31 | D95: =ROUND((B95/J95),2)*26/30 -> 3728.2787 | H95: =B95-D95+F95 -> 108120.04 | J95: 26
A96: 43069 | B96: =H95 -> 108120.04 | D96: =ROUND(+B165,2)*4/30 -> 240.26667 | H96: =B96-D96+F96 -> 107879.77 | J96: 60
A97: 43070 | B97: =H96 -> 107879.77 | D97: =+$B$165 -> 1802 | H97: =B97-D97+F97 -> 106077.77 | J97: 60
A98: 43101 | B98: =H97 -> 106077.77 | D98: =+$B$165 -> 1802 | H98: =B98-D98+F98 -> 104275.77 | J98: =+J97-1 -> 59
A99: 43132 | B99: =H98 -> 104275.77 | D99: =+$B$165 -> 1802 | H99: =B99-D99+F99 -> 102473.77 | J99: =+J98-1 -> 58
A100: 43160 | B100: =H99 -> 102473.77 | D100: =+$B$165 -> 1802 | H100: =B100-D100+F100 -> 100671.77 | J100: =+J99-1 -> 57
A101: 43191 | B101: =H100 -> 100671.77 | D101: =+$B$165 -> 1802 | H101: =B101-D101+F101 -> 98869.768 | J101: =+J100-1 -> 56
A102: 43221 | B102: =H101 -> 98869.768 | D102: =+$B$165 -> 1802 | H102: =B102-D102+F102 -> 97067.768 | J102: =+J101-1 -> 55
A103: 43252 | B103: =H102 -> 97067.768 | D103: =+$B$165 -> 1802 | H103: =B103-D103+F103 -> 95265.768 | J103: =+J102-1 -> 54
A104: 43282 | B104: =H103 -> 95265.768 | D104: =+$B$165 -> 1802 | H104: =B104-D104+F104 -> 93463.768 | J104: =+J103-1 -> 53
A105: 43313 | B105: =H104 -> 93463.768 | D105: =+$B$165 -> 1802 | H105: =B105-D105+F105 -> 91661.768 | J105: =+J104-1 -> 52
A106: 43344 | B106: =H105 -> 91661.768 | D106: =+$B$165 -> 1802 | H106: =B106-D106+F106 -> 89859.768 | J106: =+J105-1 -> 51
A107: 43374 | B107: =H106 -> 89859.768 | D107: =+$B$165 -> 1802 | H107: =B107-D107+F107 -> 88057.768 | J107: =+J106-1 -> 50
A108: 43405 | B108: =H107 -> 88057.768 | D108: =+$B$165 -> 1802 | H108: =B108-D108+F108 -> 86255.768 | J108: =+J107-1 -> 49
A109: 43435 | B109: =H108 -> 86255.768 | D109: =+$B$165 -> 1802 | H109: =B109-D109+F109 -> 84453.768 | J109: =+J108-1 -> 48
... A133: 44166 | B133: =H132 -> 43007.768 | D133: =+$B$165 -> 1802 | H133: =B133-D133+F133 -> 41205.768 | J133: =+J132-1 -> 24
A134: =+A133+31 -> 44197 | B134: =H133 -> 41205.768 | D134: =+$B$165 -> 1802 | H134: =B134-D134+F134 -> 39403.768 | J134: =+J133-1 -> 23
A135: =+A134+31 -> 44228 | B135: =H134 -> 39403.768 | D135: =+$B$165 -> 1802 | H135: =B135-D135+F135 -> 37601.768 | J135: =+J134-1 -> 22
A136: =+A135+31 -> 44259 | B136: =H135 -> 37601.768 | D136: =+$B$165 -> 1802 | H136: =B136-D136+F136 -> 35799.768 | J136: =+J135-1 -> 21
A137: =+A136+31 -> 44290 | B137: =H136 -> 35799.768 | D137: =+$B$165 -> 1802 | H137: =B137-D137+F137 -> 33997.768 | J137: =+J136-1 -> 20
A138: =+A137+31 -> 44321 | B138: =H137 -> 33997.768 | D138: =+$B$165 -> 1802 | H138: =B138-D138+F138 -> 32195.768 | J138: =+J137-1 -> 19
A139: =+A138+31 -> 44352 | B139: =H138 -> 32195.768 | D139: =+$B$165 -> 1802 | H139: =B139-D139+F139 -> 30393.768 | J139: =+J138-1 -> 18
A140: =+A139+31 -> 44383 | B140: =H139 -> 30393.768 | D140: =+$B$165 -> 1802 | H140: =B140-D140+F140 -> 28591.768 | J140: =+J139-1 -> 17
A141: =+A140+31 -> 44414 | B141: =H140 -> 28591.768 | D141: =+$B$165 -> 1802 | H141: =B141-D141+F141 -> 26789.768 | J141: =+J140-1 -> 16
A142: =+A141+31 -> 44445 | B142: =H141 -> 26789.768 | D142: =+$B$165 -> 1802 | H142: =B142-D142+F142 -> 24987.768 | J142: =+J141-1 -> 15
A143: =+A142+31 -> 44476 | B143: =H142 -> 24987.768 | D143: =+$B$165 -> 1802 | H143: =B143-D143+F143 -> 23185.768 | J143: =+J142-1 -> 14
A144: =+A143+31 -> 44507 | B144: =H143 -> 23185.768 | D144: =+$B$165 -> 1802 | H144: =B144-D144+F144 -> 21383.768 | J144: =+J143-1 -> 13
A145: =+A144+31 -> 44538 | B145: =H144 -> 21383.768 | D145: =+$B$165 -> 1802 | H145: =B145-D145+F145 -> 19581.768 | J145: =+J144-1 -> 12
... A155: =+A154+31 -> 44848 | B155: =H154 -> 3363.7684 | D155: =+$B$165 -> 1802 | H155: =B155-D155+F155 -> 1561.7684 | J155: =+J154-1 -> 2
A156: =+A155+31 -> 44879 | B156: =H155 -> 1561.7684 | D156: =+$B$165*26/30+0.04 -> 1561.7733 | H156: =B156-D156+F156 -> -0.0049123558 | J156: =+J155-1 -> 1
A158: These rate case expenses were approved in Docket No. 46957.
A159: Five-year amortization was approved in Docket No. 46957 and began 11-27-2017 when rates were effective.
A161: 26 days of amort based on prior rate case amortization of 11 years
A162: 4 days of amortization based on Dkt 46957 amort of 5 years
B163: =+H95 -> 108120.04 | C163: November 26, 2017 Unamortized Bal
B164: 60 | C164: months (five-year amortization)
B165: =ROUND(+B163/B164,2) -> 1802 | C165: Monthly Amortization
A167: Requesting five-year amortization in the 2022 base rate case
A168: If approved in 2022 base rate case, amortization schedule will be revised to reflect approved recovery.

Sheet DOC35718
A10: Date | B10: Beginning Balance | D10: Monthly Amortization | F10: Adjustments | H10: Ending Balance | J10: Periods Remaining
A12: 39814 | B12: 889574.23 | D12: =ROUND(B12/J12,2) -> 6739.2 | F12: 3044.78 | H12: =B12-D12+F12 -> 885879.81 | J12: 132
A13: 39845 | B13: =H12 -> 885879.81 | D13: =ROUND(B13/J13,2) -> 6762.44 | F13: 18469.94 | H13: =B13-D13+F13 -> 897587.31 | J13: 131
A14: 39873 | B14: =H13 -> 897587.31 | D14: =ROUND(B14/J14,2) -> 6904.52 | F14: -58992.68 | H14: =B14-D14+F14 -> 831690.11 | J14: 130
A15: 39904 | B15: =H14 -> 831690.11 | D15: =ROUND(B15/J15,2) -> 6447.21 | F15: 3613.81 | H15: =B15-D15+F15 -> 828856.71 | J15: 129
A16: 39934 | B16: =H15 -> 828856.71 | D16: =ROUND(B16/J16,2) -> 6475.44 | F16: 13496.48 | H16: =B16-D16+F16 -> 835877.75 | J16: 128
A17: 39965 | B17: =H16 -> 835877.75 | D17: =ROUND(B17/J17,2) -> 6581.71 | F17: 1882.57 | H17: =B17-D17+F17 -> 831178.61 | J17: 127
A18: 39995 | B18: =H17 -> 831178.61 | D18: =ROUND(B18/J18,2) -> 6596.66 | F18: 1558.99 | H18: =B18-D18+F18 -> 826140.94 | J18: 126
A19: 40026 | B19: =H18 -> 826140.94 | D19: =ROUND(B19/J19,2) -> 6609.13 | F19: 1306.99 | H19: =B19-D19+F19 -> 820838.8 | J19: 125
A20: 40057 | B20: =H19 -> 820838.8 | D20: =ROUND(B20/J20,2) -> 6619.67 | F20: 1233.88 | H20: =B20-D20+F20 -> 815453.01 | J20: 124
A21: 40087 | B21: =H20 -> 815453.01 | D21: =ROUND(B21/J21,2) -> 6629.7 | F21: 137.18 | H21: =B21-D21+F21 -> 808960.49 | J21: 123
A22: 40118 | B22: =H21 -> 808960.49 | D22: =ROUND(B22/J22,2) -> 6630.82 | F22: 315.91 | H22: =B22-D22+F22 -> 802645.58 | J22: 122
A23: 40148 | B23: =H22 -> 802645.58 | D23: =ROUND(B23/J23,2) -> 6633.43 | F23: 703.74 | H23: =B23-D23+F23 -> 796715.89 | J23: 121
A24: 40179 | B24: =H23 -> 796715.89 | D24: =ROUND(B24/J24,2) -> 6639.3 | F24: 403.11 | H24: =B24-D24+F24 -> 790479.7 | J24: 120
... A59: 41244 | B59: =H58 -> 601166.91 | D59: =ROUND(B59/J59,2) -> 7072.55 | F59: 626.96 | H59: =B59-D59+F59 -> 594721.32 | J59: 85
A60: 41275 | B60: =H59 -> 594721.32 | D60: =ROUND(B60/J60,2) -> 7080.02 | H60: =B60-D60+F60 -> 587641.3 | J60: 84
A61: 41306 | B61: =H60 -> 587641.3 | D61: =ROUND(B61/J61,2) -> 7080.02 | H61: =B61-D61+F61 -> 580561.28 | J61: 83
A62: 41334 | B62: =H61 -> 580561.28 | D62: =ROUND(B62/J62,2) -> 7080.02 | H62: =B62-D62+F62 -> 573481.26 | J62: 82
A63: 41365 | B63: =H62 -> 573481.26 | D63: =ROUND(B63/J63,2) -> 7080.02 | H63: =B63-D63+F63 -> 566401.24 | J63: 81
A64: 41395 | B64: =H63 -> 566401.24 | D64: =ROUND(B64/J64,2) -> 7080.02 | H64: =B64-D64+F64 -> 559321.22 | J64: 80
A65: 41426 | B65: =H64 -> 559321.22 | D65: =ROUND(B65/J65,2) -> 7080.02 | H65: =B65-D65+F65 -> 552241.2 | J65: 79
A66: 41456 | B66: =H65 -> 552241.2 | D66: =ROUND(B66/J66,2) -> 7080.02 | H66: =B66-D66+F66 -> 545161.18 | J66: 78
A67: 41487 | B67: =H66 -> 545161.18 | D67: =B67/J67 -> 7080.0153 | H67: =B67-D67+F67 -> 538081.16 | J67: 77
A68: 41518 | B68: =H67 -> 538081.16 | D68: =B68/J68 -> 7080.0153 | H68: =B68-D68+F68-0.01 -> 531001.14 | J68: 76
A69: 41548 | B69: =H68 -> 531001.14 | D69: =B69/J69 -> 7080.0152 | H69: =B69-D69+F69 -> 523921.12 | J69: 75
A70: 41579 | B70: =H69 -> 523921.12 | D70: =B70/J70 -> 7080.0152 | F70: -9 | H70: =B70-D70+F70-0.01 -> 516832.1 | J70: 74
A71: 41609 | B71: =H70 -> 516832.1 | D71: =B71/J71 -> 7079.8918 | F71: 0 | H71: =B71-D71+F71 -> 509752.21 | J71: 73
A72: 41640 | B72: =H71 -> 509752.21 | D72: =B72/J72 -> 7079.8918 | H72: =B72-D72+F72 -> 502672.32 | J72: 72
A73: 41671 | B73: =H72 -> 502672.32 | D73: =B73/J73 -> 7079.8918 | H73: =B73-D73+F73+0.01 -> 495592.43 | J73: 71
A74: 41699 | B74: =H73 -> 495592.43 | D74: =B74/J74 -> 7079.8919 | H74: =B74-D74+F74 -> 488512.54 | J74: 70
A75: 41730 | B75: =H74 -> 488512.54 | D75: =B75/J75 -> 7079.8919 | H75: =B75-D75+F75 -> 481432.65 | J75: 69
A76: 41760 | B76: =H75 -> 481432.65 | D76: =B76/J76 -> 7079.8919 | H76: =B76-D76+F76 -> 474352.76 | J76: 68
A77: 41791 | B77: =H76 -> 474352.76 | D77: =B77/J77 -> 7079.8919 | H77: =B77-D77+F77 -> 467272.87 | J77: 67
A78: 41821 | B78: =H77 -> 467272.87 | D78: =B78/J78 -> 7079.8919 | H78: =B78-D78+F78 -> 460192.97 | J78: 66
A79: 41852 | B79: =H78 -> 460192.97 | D79: =B79/J79 -> 7079.8919 | H79: =B79-D79+F79 -> 453113.08 | J79: 65
A80: 41883 | B80: =H79 -> 453113.08 | D80: =B80/J80-0.01 -> 7079.8819 | H80: =B80-D80+F80 -> 446033.2 | J80: 64
A81: 41913 | B81: =H80 -> 446033.2 | D81: =B81/J81 -> 7079.8921 | H81: =B81-D81+F81 -> 438953.31 | J81: 63
A82: 41944 | B82: =H81 -> 438953.31 | D82: =B82/J82 -> 7079.8921 | H82: =B82-D82+F82 -> 431873.42 | J82: 62
A83: 41974 | B83: =H82 -> 431873.42 | D83: =B83/J83 -> 7079.8921 | H83: =B83-D83+F83 -> 424793.52 | J83: 61
A84: 42005 | B84: =H83 -> 424793.52 | D84: =B84/J84 -> 7079.8921 | H84: =B84-D84+F84 -> 417713.63 | J84: 60
A85: 42036 | B85: =H84 -> 417713.63 | D85: =B85/J85 -> 7079.8921 | H85: =B85-D85+F85 -> 410633.74 | J85: 59
A86: 42064 | B86: =H85 -> 410633.74 | D86: =B86/J86 -> 7079.8921 | H86: =B86-D86+F86 -> 403553.85 | J86: 58
A87: 42095 | B87: =H86 -> 403553.85 | D87: =B87/J87 -> 7079.8921 | H87: =B87-D87+F87 -> 396473.96 | J87: 57
A88: 42125 | B88: =H87 -> 396473.96 | D88: =B88/J88 -> 7079.8921 | H88: =B88-D88+F88 -> 389394.06 | J88: 56
A89: 42156 | B89: =H88 -> 389394.06 | D89: =B89/J89 -> 7079.8921 | H89: =B89-D89+F89 -> 382314.17 | J89: 55
A90: 42186 | B90: =H89 -> 382314.17 | D90: =B90/J90 -> 7079.8921 | H90: =B90-D90+F90 -> 375234.28 | J90: 54
A91: 42217 | B91: =H90 -> 375234.28 | D91: =B91/J91 -> 7079.8921 | H91: =B91-D91+F91 -> 368154.39 | J91: 53
A92: 42248 | B92: =H91 -> 368154.39 | D92: =B92/J92 -> 7079.8921 | H92: =B92-D92+F92 -> 361074.5 | J92: 52
... A117: 43009 | B117: =H116 -> 191157.09 | D117: =B117/J117 -> 7079.8921 | H117: =B117-D117+F117 -> 184077.19 | J117: 27
A118: 43065 | B118: =H117 -> 184077.19 | D118: =B118/J118*26/30 -> 6135.9065 | H118: =B118-D118+F118 -> 177941.29 | J118: 26
A119: 43069 | B119: =+H118 -> 177941.29 | D119: =ROUND(+B188*0.133333333333333,2) -> 395.43 | H119: =B119-D119+F119 -> 177545.86 | J119: 60
A120: 43070 | B120: =+H119 -> 177545.86 | D120: =+$B$188 -> 2965.69 | H120: =B120-D120+F120 -> 174580.17 | J120: 60
A121: 43101 | B121: =+H120 -> 174580.17 | D121: =+$B$188 -> 2965.69 | H121: =B121-D121+F121 -> 171614.48 | J121: =+J120-1 -> 59
A122: 43132 | B122: =+H121 -> 171614.48 | D122: =+$B$188 -> 2965.69 | H122: =B122-D122+F122 -> 168648.79 | J122: =+J121-1 -> 58
A123: 43160 | B123: =+H122 -> 168648.79 | D123: =+$B$188 -> 2965.69 | H123: =B123-D123+F123 -> 165683.1 | J123: =+J122-1 -> 57
A124: 43191 | B124: =+H123 -> 165683.1 | D124: =+$B$188 -> 2965.69 | H124: =B124-D124+F124 -> 162717.41 | J124: =+J123-1 -> 56
A125: 43221 | B125: =+H124 -> 162717.41 | D125: =+$B$188 -> 2965.69 | H125: =B125-D125+F125 -> 159751.72 | J125: =+J124-1 -> 55
A126: 43252 | B126: =+H125 -> 159751.72 | D126: =+$B$188 -> 2965.69 | H126: =B126-D126+F126 -> 156786.03 | J126: =+J125-1 -> 54
A127: 43282 | B127: =+H126 -> 156786.03 | D127: =+$B$188 -> 2965.69 | H127: =B127-D127+F127 -> 153820.34 | J127: =+J126-1 -> 53
A128: 43313 | B128: =+H127 -> 153820.34 | D128: =+$B$188 -> 2965.69 | H128: =B128-D128+F128 -> 150854.65 | J128: =+J127-1 -> 52
A129: 43344 | B129: =+H128 -> 150854.65 | D129: =+$B$188 -> 2965.69 | H129: =B129-D129+F129 -> 147888.96 | J129: =+J128-1 -> 51
A130: 43374 | B130: =+H129 -> 147888.96 | D130: =+$B$188 -> 2965.69 | H130: =B130-D130+F130 -> 144923.27 | J130: =+J129-1 -> 50
A131: 43405 | B131: =+H130 -> 144923.27 | D131: =+$B$188 -> 2965.69 | H131: =B131-D131+F131 -> 141957.58 | J131: =+J130-1 -> 49
A132: 43435 | B132: =+H131 -> 141957.58 | D132: =+$B$188 -> 2965.69 | H132: =B132-D132+F132 -> 138991.89 | J132: =+J131-1 -> 48
... A156: 44166 | B156: =+H155 -> 70781.017 | D156: =+$B$188 -> 2965.69 | H156: =B156-D156+F156 -> 67815.327 | J156: =+J155-1 -> 24
A157: =+A156+31 -> 44197 | B157: =+H156 -> 67815.327 | D157: =+$B$188 -> 2965.69 | H157: =B157-D157+F157 -> 64849.637 | J157: =+J156-1 -> 23
A158: =+A157+31 -> 44228 | B158: =+H157 -> 64849.637 | D158: =+$B$188 -> 2965.69 | H158: =B158-D158+F158 -> 61883.947 | J158: =+J157-1 -> 22
A159: =+A158+31 -> 44259 | B159: =+H158 -> 61883.947 | D159: =+$B$188 -> 2965.69 | H159: =B159-D159+F159 -> 58918.257 | J159: =+J158-1 -> 21
A160: =+A159+31 -> 44290 | B160: =+H159 -> 58918.257 | D160: =+$B$188 -> 2965.69 | H160: =B160-D160+F160 -> 55952.567 | J160: =+J159-1 -> 20
A161: =+A160+31 -> 44321 | B161: =+H160 -> 55952.567 | D161: =+$B$188 -> 2965.69 | H161: =B161-D161+F161 -> 52986.877 | J161: =+J160-1 -> 19
A162: =+A161+31 -> 44352 | B162: =+H161 -> 52986.877 | D162: =+$B$188 -> 2965.69 | H162: =B162-D162+F162 -> 50021.187 | J162: =+J161-1 -> 18
A163: =+A162+31 -> 44383 | B163: =+H162 -> 50021.187 | D163: =+$B$188 -> 2965.69 | H163: =B163-D163+F163 -> 47055.497 | J163: =+J162-1 -> 17
A164: =+A163+31 -> 44414 | B164: =+H163 -> 47055.497 | D164: =+$B$188 -> 2965.69 | H164: =B164-D164+F164 -> 44089.807 | J164: =+J163-1 -> 16
A165: =+A164+31 -> 44445 | B165: =+H164 -> 44089.807 | D165: =+$B$188 -> 2965.69 | H165: =B165-D165+F165 -> 41124.117 | J165: =+J164-1 -> 15
A166: =+A165+31 -> 44476 | B166: =+H165 -> 41124.117 | D166: =+$B$188 -> 2965.69 | H166: =B166-D166+F166 -> 38158.427 | J166: =+J165-1 -> 14
A167: =+A166+31 -> 44507 | B167: =+H166 -> 38158.427 | D167: =+$B$188 -> 2965.69 | H167: =B167-D167+F167 -> 35192.737 | J167: =+J166-1 -> 13
A168: =+A167+31 -> 44538 | B168: =+H167 -> 35192.737 | D168: =+$B$188 -> 2965.69 | H168: =B168-D168+F168 -> 32227.047 | J168: =+J167-1 -> 12
... A178: =+A177+31 -> 44848 | B178: =+H177 -> 5535.8373 | D178: =+$B$188 -> 2965.69 | H178: =B178-D178+F178 -> 2570.1473 | J178: =+J177-1 -> 2
A179: =+A178+31 -> 44879 | B179: =+H178 -> 2570.1473 | D179: =+$B$188*26/30-0.12 -> 2570.1447 | H179: =B179-D179+F179 -> 0.0026492299 | J179: =+J178-1 -> 1
A181: These rate case expenses were approved in Docket No. 46957.
A182: Five-year amortization was approved in Docket No. 46957 and began 11-27-2017 when rates were effective.
A184: 26 days of amort based on prior rate case amortization of 11 years
A185: 4 days of amortization based on Dkt 46957 amort of 5 years
B186: =+H118 -> 177941.29 | C186: November 26, 2017 Unamortized Bal
B187: 60 | C187: months (five-year amortization)
B188: =ROUND(+B186/B187,2) -> 2965.69 | C188: Monthly Amortization
A190: Requesting five-year amortization in the 2022 base rate case
A191: If approved in 2022 base rate case, amortization schedule will be revised to reflect approved recovery.
