Workbook

Sheet Prop Tax Estimate (WP1)
A1: 2022 RATE CASE
A2: ONCOR ELECTRIC DELIVERY COMPANY LLC
A3: REQUESTED AD VALOREM TAX EXPENSE ON TEST YEAR NET UTILITY PLANT
A4: TEST YEAR ENDING DECEMBER 31, 2021
A5: SPONSOR: B. L. CLUTTER
C9: YE2020 | D9: YE2021 | F9: Net Plant | G9: Taxable | H9: Taxable Value | J9: Tax Expense
B10: Source | C10: Tax Year 2021 | D10: Tax Year 2022 | F10: Increase | G10: Value Factor | H10: Increase | J10: Increase
A11: Net Utility Plant | B11: II-B-5,6,11 | C11: =+'Book Plant Bals (WP1)'!F13 -> 1.8912467e+10 | D11: =+'[1]II-B-5'!$I$88+'[1]II-B-6'!$I$20+'[1]II-B-11'!$I$17+'[1]II-B-11'!$I$18+'[1]II-B-11'!$I$19+'[1]II-B-11'!$I$19 -> 2.0540363e+10 | F11: =+D11-C11 -> 1.6278957e+09 | G11: =+'Book Plant Bals (WP1)'!F24 -> 0.62709116 | H11: =ROUND(F11*G11,2) -> 1.020839e+09
A13: Taxable Value (owned) | B13: V-Tax, TPT | C13: =+C26 -> 1.206511e+10 | D13: =+C13+H11 -> 1.3085949e+10
A14: Effective Tax Rate | C14: =+C15/C13 -> 0.021715102 | D14: =+C14 -> 0.021715102
A15: Tax, before discount | B15: V-Tax, TPT | C15: =+C31+C35 -> 2.6199511e+08 | D15: =+ROUND(D13*D14,2) -> 2.8416273e+08
A16: Discount | C16: =+C35 -> 443717.57 | D16: =+C37 -> 480845.75
A17: Net Tax Expense | C17: =+C15-C16 -> 2.6155139e+08 | D17: =+D15-D16 -> 2.8368188e+08 | J17: =+D17-C17 -> 22130495
A18: *Values above do not include non-utility plant
A22: To Remove NUP from 2021 Taxable Value and Tax Expense
A23: Total Taxable Value (owned) | C23: =+'Book Plant Bals (WP1)'!F26 -> 12075526728
A24: Non-Utility Plant | B24: Acct 121 | C24: =+'Book Plant Bals (WP1)'!F22 -> 16610527
A25: At Market Value | C25: =+ROUND(C24*G11,2) -> 10416314
A26: Taxable Value (owned), excl NUP | C26: =+C23-C25 -> 1.206511e+10
A27: NUP % of total | C27: =+C25/C23 -> 0.0008625971
A29: Tax Expense, excl PPA | C29: =+'Book Plant Bals (WP1)'!F33-'Book Plant Bals (WP1)'!F35 -> 2.617772e+08
A30: Tax Expense on NUP | C30: =+ROUND(C27*C29,2) -> 225808.25
A31: Tax Expense, excl NUP | C31: =+C29-C30 -> 2.6155139e+08
A34: To Adjust Discount
A35: Discount on 2021 taxes paid | B35: TPT | C35: 443717.57
A36: Percentage of Total Taxable Value | C36: =+C35/C23 -> 3.6745194e-05
A37: Discount on 2022 tax due | C37: =ROUND(C36*D13,2) -> 480845.75

Sheet Book Plant Bals (WP1)
A1: 2022 RATE CASE
A2: ONCOR ELECTRIC DELIVERY COMPANY LLC
A3: ESTIMATED AD VALOREM TAX EXPENSE ON TEST YEAR NET UTILITY PLANT
A4: TEST YEAR ENDING DECEMBER 31, 2021
A5: SPONSOR: B. L. CLUTTER
A10: Beginning Balance for | B10: TY2017 | C10: TY2018 | D10: TY2019 | E10: TY2020 | F10: TY2021
A11: Property, plant and equipment | B11: 1.977144e+10 | C11: 2.1045217e+10 | D11: 2.2433378e+10 | E11: 2.5902971e+10 | F11: 2.8030791e+10
A12: Less accumulated depreciation | B12: 7.3289729e+09 | C12: 7.8705817e+09 | D12: 8.1510224e+09 | E12: 8.7364716e+09 | F12: 9.1183235e+09
A13: Utility plant, less accumulated depreciation | B13: =+B11-B12 -> 1.2442467e+10 | C13: =+C11-C12 -> 1.3174635e+10 | D13: =+D11-D12 -> 1.4282356e+10 | E13: =+E11-E12 -> 1.71665e+10 | F13: =+F11-F12 -> 1.8912467e+10
A15: New CWIP (exclude replacements) | B15: 230235023 | C15: 118233168 | D15: 142340598 | E15: 247875266 | F15: 199734843
A16: Materials & Supplies | B16: 89545514 | C16: 90762588 | D16: 1.1585717e+08 | E16: 1.48364e+08 | F16: 1.4421177e+08
A18: Gross plant subject to ad valorem taxes | B18: =+B11+B15+B16 -> 2.0091221e+10 | C18: =+C11+C15+C16 -> 2.1254213e+10 | D18: =+D11+D15+D16 -> 2.2691576e+10 | E18: =+E11+E15+E16 -> 2.629921e+10 | F18: =+F11+F15+F16 -> 2.8374737e+10
A19: Net plant subject to ad valorem taxes | B19: =+B18-B12 -> 1.2762248e+10 | C19: =+C18-C12 -> 1.3383631e+10 | D19: =+D18-D12 -> 1.4540553e+10 | E19: =+E18-E12 -> 1.7562739e+10 | F19: =+F18-F12 -> 1.9256414e+10
A22: Non-utility Plant (excluded) | B22: 2492824.5 | C22: 2578170 | D22: 11779350 | E22: 11779350 | F22: 16610527
A24: Book to Taxable Value % (owned) | B24: =+B26/B19 -> 0.58450192 | C24: =+C26/C19 -> 0.57215145 | D24: =+D26/D19 -> 0.58985477 | E24: =+E26/E19 -> 0.62674044 | F24: =+F26/F19 -> 0.62709116
A26: Taxable Value (owned) | B26: 7459558389 | C26: 7657463757 | D26: 8576814860 | E26: 11007278660 | F26: 12075526728
A27: Less Non-utility plant | B27: =+B22*B24 -> 1457060.7 | C27: =+C22*C24 -> 1475103.7 | D27: =+D22*D24 -> 6948105.7 | E27: =+E22*E24 -> 7382594.9 | F27: =+F22*F24 -> 10416314
A28: Taxable Value (owned), excl NUP | B28: =+B26-B27 -> 7.4581013e+09 | C28: =+C26-C27 -> 7.6559887e+09 | D28: =+D26-D27 -> 8.5698668e+09 | E28: =+E26-E27 -> 1.0999896e+10 | F28: =+F26-F27 -> 1.206511e+10
A29: Taxable Value (leased) | B29: 41402158 | C29: 70919376 | D29: 68764060 | E29: 76090318 | F29: 85223140
A30: Total Taxable Value, excl NUP | B30: =+B28+B29 -> 7.4995035e+09 | C30: =+C28+C29 -> 7.726908e+09 | D30: =+D28+D29 -> 8.6386308e+09 | E30: =+E28+E29 -> 1.1075986e+10 | F30: =+F28+F29 -> 1.2150334e+10
A33: Total Ad Valorem Tax Expense (4082602) | B33: 1.7642432e+08 | C33: 1.8315867e+08 | D33: 2.116271e+08 | E33: 2.4305962e+08 | F33: 2.6178317e+08
A34: Less: TY2019 NTU | B34: 0 | C34: 0 | D34: =11885841.26+4552175.77 -> 16438017 | E34: 0 | F34: 0
A35: Less: Prior Period Adjustments | B35: 36659.92 | C35: 99158.97 | D35: -184134.88 | E35: -26359.03 | F35: 5972.95
A36: Less: Non-utility Plant | B36: =+ROUND((B27/B26)*(B33-B34-B35),2) -> 34453.45 | C36: =ROUND(+(C27/C26)*(C33-C34-C35),2) -> 35263.86 | D36: =ROUND(+(D27/D26)*(D33-D34-D35),2) -> 158272.48 | E36: =+ROUND((E27/E26)*(E33-E34-E35),2) -> 163038.05 | F36: =ROUND(+(F27/F26)*(F33-F34-F35),2) -> 225808.25
A37: Ad Valorem Tax Expense (owned) | B37: =+B33-B34-B35-B36 -> 1.7635321e+08 | C37: =+C33-C34-C35-C36 -> 1.8302425e+08 | D37: =+D33-D34-D35-D36 -> 1.9521495e+08 | E37: =+E33-E34-E35-E36 -> 2.4292294e+08 | F37: =+F33-F34-F35-F36 -> 2.6155139e+08
A39: Effective Tax Rate | B39: =+B37/B28 -> 0.023645859 | C39: =+C37/C28 -> 0.023906024 | D39: =+D37/D28 -> 0.022779228 | E39: =+E37/E28 -> 0.022084112 | F39: =+F37/F28 -> 0.021678325

Sheet Ad Valorem Exp by Month (WP2)
A1: 2022 RATE CASE
A2: ONCOR ELECTRIC DELIVERY COMPANY LLC
A3: AD VALOREM TAX EXPENSE BY MONTH
A4: TEST YEAR ENDING DECEMBER 31, 2021
A5: SPONSOR: B. L. CLUTTER
A10: Line No | B10: Month | C10: Expense | D10: FERC Account
B11: (a) | C11: (b) | D11: (c)
A13: 1 | B13: January | C13: 22865175 | D13: 408
A14: =+A13+1 -> 2 | B14: February | C14: 22863796 | D14: 408
A15: =+A14+1 -> 3 | B15: March | C15: 22795899 | D15: 408
A16: =+A15+1 -> 4 | B16: April | C16: 22863732 | D16: 408
A17: =+A16+1 -> 5 | B17: May | C17: 22863883 | D17: 408
A18: =+A17+1 -> 6 | B18: June | C18: 21863956 | D18: 408
A19: =+A18+1 -> 7 | B19: July | C19: 21872504 | D19: 408
A20: =+A19+1 -> 8 | B20: August | C20: 21863907 | D20: 408
A21: =+A20+1 -> 9 | B21: September | C21: 22232601 | D21: 408
A22: =+A21+1 -> 10 | B22: October | C22: 22232601 | D22: 408
A23: =+A22+1 -> 11 | B23: November | C23: 22296089 | D23: 408
A24: =+A23+1 -> 12 | B24: December | C24: 15169026 | D24: 408
A25: =+A24+1 -> 13
A26: =+A25+1 -> 14 | B26: Total | C26: =SUM(C13:C25) -> 2.6178317e+08
