Workbook
Name a: #REF!
Name a: #REF!
Name H_Rate_Class: 'Tariff Mapping'!$E$5:$E$114
Name page1: #REF!
Name page10: #REF!
Name page2: #REF!
Name page3: #REF!
Name page4: #REF!
Name page5: #REF!
Name page6: #REF!
Name page7: #REF!
Name page8: #REF!
Name page9: #REF!
Name q: [2]Summary!#REF!
Name q: [2]Summary!#REF!
Name Rate_Class2: '[3]Tariff Mapping'!$E$5:$E$59
Name ResBasic: [4]Summary!#REF!
Name ResBasic: [4]Summary!#REF!
Name ResEconomy1: [4]Summary!#REF!
Name ResEconomy1: [4]Summary!#REF!
Name ResEconomy2: [4]Summary!#REF!
Name ResEconomy2: [4]Summary!#REF!
Name ResWaterHeating: [4]Summary!#REF!
Name ResWaterHeating: [4]Summary!#REF!
Name test: [2]Summary!#REF!
Name test: [2]Summary!#REF!
Name test1: [2]Summary!#REF!
Name test1: [2]Summary!#REF!
Name total: #REF!
Name w: [2]Summary!#REF!
Name w: [2]Summary!#REF!

Sheet II-H-1
B2: PUBLIC UTILITY COMMISSION OF TEXAS
B3: AEP TEXAS INC
B4: II-H-1 SUMMARY OF TEST YEAR ADJUSTMENTS
B5: TEST YEAR ENDING 9/30/2023
B6: DOCKET 56165
B9: Refer to Schedule II-H-1.1 for the summary of test year adjustments

Sheet II-H-1.1
B2: PUBLIC UTILITY COMMISSION OF TEXAS
B3: AEP TEXAS INC
B4: II-H-1.1 TEST YEAR SALES DATA
B5: ='II-H-1'!B5 -> TEST YEAR ENDING 9/30/2023
B6: =+'II-H-1'!B6 -> DOCKET 56165
A8: AEP TEXAS
A9: TEST YEAR DATA BY RATE CLASS
D10: FOR TEST YEAR ENDED SEPTEMBER 30, 2023
D12: Average | E12: Year-end | F12: Unadjusted | G12: Weather kWh | H12: Customer kWh | I12: Other kWh | J12: Adjusted
A13: LINE | B13: DESCRIPTION | C13: VOLT | D13: Customers | E13: Customers | F13: kWh at Meter | G13: Adjustment | H13: Adjustment | I13: Adjustment | J13: kWh
A15: 1 | B15: RESIDENTIAL SERVICE | C15: SEC | D15: ='II-H-3.1-3'!Q14 -> 926197.58 | E15: ='II-H-3.1-3'!O14 -> 935238 | F15: ='II-H-1.2'!P14 -> 12797050643 | G15: ='II-H-1.2'!P46 -> -3.1306872e+08 | H15: ='II-H-1.2'!P78 -> 1.0590063e+08 | I15: ='II-H-1.2'!P112 -> 0 | J15: ='II-H-1.2'!P144 -> 1.2589883e+10
A17: 2 | B17: SECONDARY < 10 kW | C17: SEC | D17: ='II-H-3.1-3'!Q16 -> 98796.167 | E17: ='II-H-3.1-3'!O16 -> 99366 | F17: ='II-H-1.2'!P16 -> 678758664 | G17: ='II-H-1.2'!P48 -> -8767706.8 | H17: ='II-H-1.2'!P80 -> 2109148.9 | I17: ='II-H-1.2'!P114 -> 0 | J17: ='II-H-1.2'!P146 -> 6.7210011e+08
A19: 3 | B19: SECONDARY > 10 kW NCP | C19: SEC | D19: ='II-H-3.1-3'!Q18 -> 71496.417 | E19: ='II-H-3.1-3'!O18 -> 71833 | F19: ='II-H-1.2'!P18 -> 7956360402 | G19: ='II-H-1.2'!P50 -> -1.1227043e+08 | H19: ='II-H-1.2'!P82 -> 51400456 | I19: ='II-H-1.2'!P116 -> 0 | J19: ='II-H-1.2'!P148 -> 7.8954904e+09
A20: 4 | B20: SECONDARY > 10 kW 4CP | C20: SEC | D20: ='II-H-3.1-3'!Q19 -> 570.66667 | E20: ='II-H-3.1-3'!O19 -> 576 | F20: ='II-H-1.2'!P19 -> 1307495001 | G20: ='II-H-1.2'!P51 -> -8524699.1 | H20: ='II-H-1.2'!P83 -> 10596481 | I20: ='II-H-1.2'!P117 -> 0 | J20: ='II-H-1.2'!P149 -> 1.3095668e+09
A21: 5 | B21: TOTAL SECONDARY > 10 kW | D21: =SUM(D19:D20) -> 72067.083 | E21: =SUM(E19:E20) -> 72409 | F21: =SUM(F19:F20) -> 9263855403 | G21: =SUM(G19:G20) -> -1.2079513e+08 | H21: =SUM(H19:H20) -> 61996937 | I21: =SUM(I19:I20) -> 0 | J21: =SUM(J19:J20) -> 9.2050572e+09
A23: 6 | B23: PRIMARY NCP | C23: PRI | D23: ='II-H-3.1-3'!Q22 -> 550.33333 | E23: ='II-H-3.1-3'!O22 -> 550 | F23: ='II-H-1.2'!P22 -> 263796669 | G23: ='II-H-1.2'!P54 -> -2124654.5 | H23: ='II-H-1.2'!P86 -> -514363.46 | I23: ='II-H-1.2'!P120 -> 0 | J23: ='II-H-1.2'!P152 -> 2.6115765e+08
A24: 7 | B24: PRIMARY 4CP | C24: PRI | D24: ='II-H-3.1-3'!Q23 -> 475.08333 | E24: ='II-H-3.1-3'!O23 -> 469 | F24: ='II-H-1.2'!P23 -> 3828118181 | G24: ='II-H-1.2'!P55 -> -29574766 | H24: ='II-H-1.2'!P87 -> -40429397 | I24: ='II-H-1.2'!P121 -> 0 | J24: ='II-H-1.2'!P153 -> 3.758114e+09
A25: 8 | B25: PRIMARY SUB NCP | C25: PRI | D25: ='II-H-3.1-3'!Q24 -> 9 | E25: ='II-H-3.1-3'!O24 -> 9 | F25: ='II-H-1.2'!P24 -> 5880600 | G25: ='II-H-1.2'!P56 -> 0 | H25: ='II-H-1.2'!P88 -> 0 | I25: ='II-H-1.2'!P122 -> 0 | J25: ='II-H-1.2'!P154 -> 5880600
A26: 9 | B26: PRIMARY SUB 4CP | C26: PRI | D26: ='II-H-3.1-3'!Q25 -> 58 | E26: ='II-H-3.1-3'!O25 -> 58 | F26: ='II-H-1.2'!P25 -> 499919380 | G26: ='II-H-1.2'!P57 -> 0 | H26: ='II-H-1.2'!P89 -> 0 | I26: ='II-H-1.2'!P123 -> 0 | J26: ='II-H-1.2'!P155 -> 499919380
A27: 10 | B27: TOTAL PRIMARY | D27: =SUM(D23:D26) -> 1092.4167 | E27: =SUM(E23:E26) -> 1086 | F27: =SUM(F23:F26) -> 4597714830 | G27: =SUM(G23:G26) -> -31699420 | H27: =SUM(H23:H26) -> -40943761 | I27: =SUM(I23:I26) -> 0 | J27: =SUM(J23:J26) -> 4.5250716e+09
A29: 11 | B29: TRANSMISSION | C29: TRA | D29: ='II-H-3.1-3'!Q28 -> 124.16667 | E29: ='II-H-3.1-3'!O28 -> 123 | F29: ='II-H-1.2'!P28 -> 11207029849 | G29: ='II-H-1.2'!P60 -> -1282930 | H29: ='II-H-1.2'!P92 -> -1.7005016e+08 | I29: ='II-H-1.2'!P126 -> 0 | J29: ='II-H-1.2'!P158 -> 1.1035697e+10
A31: 12 | B31: LIGHTING | C31: SEC | D31: ='II-H-3.1-3'!Q30 -> 221912.58 | E31: ='II-H-3.1-3'!O30 -> 221390 | F31: ='II-H-1.2'!P30 -> 240936337 | G31: ='II-H-1.2'!P62 -> 39 | H31: ='II-H-1.2'!P94 -> -2551478.4 | I31: ='II-H-1.2'!P128 -> 0 | J31: ='II-H-1.2'!P160 -> 2.383849e+08
A33: 13 | B33: TOTAL RETAIL | D33: =D31+D29+D27+D21+D17+D15 -> 1320190 | E33: =E31+E29+E27+E21+E17+E15 -> 1329612 | F33: =F31+F29+F27+F21+F17+F15 -> 38785345726 | G33: =G31+G29+G27+G21+G17+G15 -> -4.7561387e+08 | H33: =H31+H29+H27+H21+H17+H15 -> -43538688 | I33: =I31+I29+I27+I21+I17+I15 -> 0 | J33: =J31+J29+J27+J21+J17+J15 -> 3.8266193e+10
A35: 14 | B35: WHOLESALE PRI | C35: PRI | D35: ='II-H-3.1-3'!Q34 -> 0 | E35: ='II-H-3.1-3'!O34 -> 0 | F35: ='II-H-1.2'!P34 -> 0 | G35: ='II-H-1.2'!P66 -> 0 | H35: ='II-H-1.2'!P98 -> 0 | I35: ='II-H-1.2'!P132 -> 0 | J35: ='II-H-1.2'!P164 -> 0
A36: 15 | B36: WHOLESALE TRANS | C36: TRA | D36: ='II-H-3.1-3'!Q35 -> 0 | E36: ='II-H-3.1-3'!O35 -> 0 | F36: ='II-H-1.2'!P35 -> 0 | G36: ='II-H-1.2'!P67 -> 0 | H36: ='II-H-1.2'!P99 -> 0 | I36: ='II-H-1.2'!P133 -> 0
A37: 16 | B37: TOTAL WHOLESALE | D37: ='II-H-3.1-3'!Q139 -> 0 | E37: ='II-H-3.1-3'!O139 -> 0 | F37: =SUM(F35:F36) -> 0 | G37: =SUM(G35:G36) -> 0 | H37: =SUM(H35:H36) -> 0 | I37: =SUM(I35:I36) -> 0 | J37: =SUM(J35:J36) -> 0
A39: 17 | B39: TOTAL AEP TEXAS | D39: =+D37+D33 -> 1320190 | E39: =+E37+E33 -> 1329612 | F39: =+F37+F33 -> 38785345726 | G39: =+G37+G33 -> -4.7561387e+08 | H39: =+H37+H33 -> -43538688 | I39: =+I37+I33 -> 0 | J39: =+J37+J33 -> 3.8266193e+10
B41: Note: Secondary < 10 kW includes Unmetered service; Lighting customers are fixture counts.

Sheet II-H-1.2
B2: PUBLIC UTILITY COMMISSION OF TEXAS
B3: AEP TEXAS INC
B4: II-H-1.2 MONTHLY SALES DATA
B5: ='II-H-1.1'!B5 -> TEST YEAR ENDING 9/30/2023
B6: =+'II-H-1'!B6 -> DOCKET 56165
B7: AEP TEXAS
B8: UNADJUSTED BILLING KWH AT METER
G9: FOR TEST YEAR ENDED SEPTEMBER 30, 2023
A12: LINE | B12: DESCRIPTION | C12: VOLT | D12: Oct-22 | E12: Nov-22 | F12: Dec-22 | G12: Jan-23 | H12: Feb-23 | I12: Mar-23 | J12: Apr-23 | K12: May-23 | L12: Jun-23 | M12: Jul-23 | N12: Aug-23 | O12: Sep-23 | P12: TOTAL
Q13: dist rate | R13: trans rate
A14: 1 | B14: RESIDENTIAL SERVICE | C14: SEC | D14: {=SUMPRODUCT((H_Rate_Class=$B14)*[5]Energy!D$9:D$118)} -> 1030830606 | E14: {=SUMPRODUCT((H_Rate_Class=$B14)*[5]Energy!E$9:E$118)} -> 795799107 | F14: {=SUMPRODUCT((H_Rate_Class=$B14)*[5]Energy!F$9:F$118)} -> 926112371 | G14: {=SUMPRODUCT((H_Rate_Class=$B14)*[5]Energy!G$9:G$118)} -> 993225833 | H14: {=SUMPRODUCT((H_Rate_Class=$B14)*[5]Energy!H$9:H$118)} -> 874152468 | I14: {=SUMPRODUCT((H_Rate_Class=$B14)*[5]Energy!I$9:I$118)} -> 802450848 | J14: {=SUMPRODUCT((H_Rate_Class=$B14)*[5]Energy!J$9:J$118)} -> 790703542 | K14: {=SUMPRODUCT((H_Rate_Class=$B14)*[5]Energy!K$9:K$118)} -> 863356125 | ... O14: {=SUMPRODUCT((H_Rate_Class=$B14)*[5]Energy!O$9:O$118)} -> 1492215334 | P14: =SUM(D14:O14) -> 12797050643 | Q14: ='II-H-4.1 Functions'!F15/'II-H-1.2'!P14 -> 0.021785842 | R14: ='II-H-4.1 Functions'!I15/'II-H-1.2'!P14 -> 0.015254793
A16: 2 | B16: SECONDARY < 10 kW | C16: SEC | D16: {=SUMPRODUCT((H_Rate_Class=$B16)*[5]Energy!D$9:D$118)} -> 57029485 | E16: {=SUMPRODUCT((H_Rate_Class=$B16)*[5]Energy!E$9:E$118)} -> 50491315 | F16: {=SUMPRODUCT((H_Rate_Class=$B16)*[5]Energy!F$9:F$118)} -> 53528583 | G16: {=SUMPRODUCT((H_Rate_Class=$B16)*[5]Energy!G$9:G$118)} -> 54161558 | H16: {=SUMPRODUCT((H_Rate_Class=$B16)*[5]Energy!H$9:H$118)} -> 49615650 | I16: {=SUMPRODUCT((H_Rate_Class=$B16)*[5]Energy!I$9:I$118)} -> 48863762 | J16: {=SUMPRODUCT((H_Rate_Class=$B16)*[5]Energy!J$9:J$118)} -> 48592645 | K16: {=SUMPRODUCT((H_Rate_Class=$B16)*[5]Energy!K$9:K$118)} -> 50905532 | ... O16: {=SUMPRODUCT((H_Rate_Class=$B16)*[5]Energy!O$9:O$118)} -> 69458368 | P16: =SUM(D16:O16) -> 678758664 | Q16: ='II-H-4.1 Functions'!F17/'II-H-1.2'!P16 -> 0.021063902 | R16: ='II-H-4.1 Functions'!I17/'II-H-1.2'!P16 -> 0.009622364
A18: 3 | B18: SECONDARY > 10 kW NCP | C18: SEC | D18: {=SUMPRODUCT((H_Rate_Class=$B18)*[5]Energy!D$9:D$118)} -> 677255540 | E18: {=SUMPRODUCT((H_Rate_Class=$B18)*[5]Energy!E$9:E$118)} -> 581315754 | F18: {=SUMPRODUCT((H_Rate_Class=$B18)*[5]Energy!F$9:F$118)} -> 584049090 | G18: {=SUMPRODUCT((H_Rate_Class=$B18)*[5]Energy!G$9:G$118)} -> 586060179 | H18: {=SUMPRODUCT((H_Rate_Class=$B18)*[5]Energy!H$9:H$118)} -> 535341103 | I18: {=SUMPRODUCT((H_Rate_Class=$B18)*[5]Energy!I$9:I$118)} -> 564700229 | J18: {=SUMPRODUCT((H_Rate_Class=$B18)*[5]Energy!J$9:J$118)} -> 580527274 | K18: {=SUMPRODUCT((H_Rate_Class=$B18)*[5]Energy!K$9:K$118)} -> 612828213 | ... O18: {=SUMPRODUCT((H_Rate_Class=$B18)*[5]Energy!O$9:O$118)} -> 847276494 | P18: =SUM(D18:O18) -> 7956360402
A19: 4 | B19: SECONDARY > 10 kW 4CP | C19: SEC | D19: {=SUMPRODUCT((H_Rate_Class=$B19)*[5]Energy!D$9:D$118)} -> 112154601 | E19: {=SUMPRODUCT((H_Rate_Class=$B19)*[5]Energy!E$9:E$118)} -> 99177738 | F19: {=SUMPRODUCT((H_Rate_Class=$B19)*[5]Energy!F$9:F$118)} -> 103548456 | G19: {=SUMPRODUCT((H_Rate_Class=$B19)*[5]Energy!G$9:G$118)} -> 98923977 | H19: {=SUMPRODUCT((H_Rate_Class=$B19)*[5]Energy!H$9:H$118)} -> 90170835 | I19: {=SUMPRODUCT((H_Rate_Class=$B19)*[5]Energy!I$9:I$118)} -> 95019133 | J19: {=SUMPRODUCT((H_Rate_Class=$B19)*[5]Energy!J$9:J$118)} -> 101144648 | K19: {=SUMPRODUCT((H_Rate_Class=$B19)*[5]Energy!K$9:K$118)} -> 101827371 | ... O19: {=SUMPRODUCT((H_Rate_Class=$B19)*[5]Energy!O$9:O$118)} -> 138130242 | P19: =SUM(D19:O19) -> 1307495001
A20: 5 | B20: TOTAL SECONDARY > 10 kW | D20: =SUM(D18:D19) -> 789410141 | E20: =SUM(E18:E19) -> 680493492 | F20: =SUM(F18:F19) -> 687597546 | G20: =SUM(G18:G19) -> 684984156 | H20: =SUM(H18:H19) -> 625511938 | I20: =SUM(I18:I19) -> 659719362 | J20: =SUM(J18:J19) -> 681671922 | K20: =SUM(K18:K19) -> 714655584 | ... P20: =SUM(P18:P19) -> 9263855403
A22: 6 | B22: PRIMARY NCP | C22: PRI | D22: {=SUMPRODUCT((H_Rate_Class=$B22)*[5]Energy!D$9:D$118)-D24} -> 19380025 | E22: {=SUMPRODUCT((H_Rate_Class=$B22)*[5]Energy!E$9:E$118)-E24} -> 19173997 | F22: {=SUMPRODUCT((H_Rate_Class=$B22)*[5]Energy!F$9:F$118)-F24} -> 21118424 | G22: {=SUMPRODUCT((H_Rate_Class=$B22)*[5]Energy!G$9:G$118)-G24} -> 19277379 | H22: {=SUMPRODUCT((H_Rate_Class=$B22)*[5]Energy!H$9:H$118)-H24} -> 19145834 | I22: {=SUMPRODUCT((H_Rate_Class=$B22)*[5]Energy!I$9:I$118)-I24} -> 20878902 | J22: {=SUMPRODUCT((H_Rate_Class=$B22)*[5]Energy!J$9:J$118)-J24} -> 22537497 | K22: {=SUMPRODUCT((H_Rate_Class=$B22)*[5]Energy!K$9:K$118)-K24} -> 24721739 | ... O22: {=SUMPRODUCT((H_Rate_Class=$B22)*[5]Energy!O$9:O$118)-O24} -> 25271869 | P22: =SUM(D22:O22) -> 263796669
A23: 7 | B23: PRIMARY 4CP | C23: PRI | D23: {=SUMPRODUCT((H_Rate_Class=$B23)*[5]Energy!D$9:D$118)-D25} -> 308798023 | E23: {=SUMPRODUCT((H_Rate_Class=$B23)*[5]Energy!E$9:E$118)-E25} -> 300702542 | F23: {=SUMPRODUCT((H_Rate_Class=$B23)*[5]Energy!F$9:F$118)-F25} -> 309414261 | G23: {=SUMPRODUCT((H_Rate_Class=$B23)*[5]Energy!G$9:G$118)-G25} -> 317946576 | H23: {=SUMPRODUCT((H_Rate_Class=$B23)*[5]Energy!H$9:H$118)-H25} -> 290350982 | I23: {=SUMPRODUCT((H_Rate_Class=$B23)*[5]Energy!I$9:I$118)-I25} -> 296423645 | J23: {=SUMPRODUCT((H_Rate_Class=$B23)*[5]Energy!J$9:J$118)-J25} -> 308572852 | K23: {=SUMPRODUCT((H_Rate_Class=$B23)*[5]Energy!K$9:K$118)-K25} -> 312036499 | ... O23: {=SUMPRODUCT((H_Rate_Class=$B23)*[5]Energy!O$9:O$118)-O25} -> 350324818 | P23: =SUM(D23:O23) -> 3828118181
A24: 8 | B24: PRIMARY SUB NCP | C24: PRI | D24: =+'Primary Sub'!C18 -> 431400 | E24: =+'Primary Sub'!D18 -> 410400 | F24: =+'Primary Sub'!E18 -> 467000 | G24: =+'Primary Sub'!F18 -> 366800 | H24: =+'Primary Sub'!G18 -> 371400 | I24: =+'Primary Sub'!H18 -> 472200 | J24: =+'Primary Sub'!I18 -> 495400 | K24: =+'Primary Sub'!J18 -> 550400 | ... O24: =+'Primary Sub'!N18 -> 578000 | P24: =IF(SUM(D24:O24)='Primary Sub'!O18,SUM(D24:O24),0) -> 5880600
A25: 9 | B25: PRIMARY SUB 4CP | C25: PRI | D25: =+'Primary Sub'!C19 -> 47509460 | E25: =+'Primary Sub'!D19 -> 42370760 | F25: =+'Primary Sub'!E19 -> 45245780 | G25: =+'Primary Sub'!F19 -> 48271520 | H25: =+'Primary Sub'!G19 -> 46462940 | I25: =+'Primary Sub'!H19 -> 39455100 | J25: =+'Primary Sub'!I19 -> 44769280 | K25: =+'Primary Sub'!J19 -> 41432480 | ... O25: =+'Primary Sub'!N19 -> 37295980 | P25: =IF(SUM(D25:O25)='Primary Sub'!O19,SUM(D25:O25),0) -> 499919380
A26: 10 | B26: TOTAL PRIMARY | D26: =SUM(D22:D25) -> 376118908 | E26: =SUM(E22:E25) -> 362657699 | F26: =SUM(F22:F25) -> 376245465 | G26: =SUM(G22:G25) -> 385862275 | H26: =SUM(H22:H25) -> 356331156 | I26: =SUM(I22:I25) -> 357229847 | J26: =SUM(J22:J25) -> 376375029 | K26: =SUM(K22:K25) -> 378741118 | ... P26: =SUM(P22:P25) -> 4597714830
A28: 11 | B28: TRANSMISSION | C28: TRA | D28: {=SUMPRODUCT((H_Rate_Class=$B28)*[5]Energy!D$9:D$118)} -> 748095972 | E28: {=SUMPRODUCT((H_Rate_Class=$B28)*[5]Energy!E$9:E$118)} -> 953393948 | F28: {=SUMPRODUCT((H_Rate_Class=$B28)*[5]Energy!F$9:F$118)} -> 832830028 | G28: {=SUMPRODUCT((H_Rate_Class=$B28)*[5]Energy!G$9:G$118)} -> 982961652 | H28: {=SUMPRODUCT((H_Rate_Class=$B28)*[5]Energy!H$9:H$118)} -> 900610195 | I28: {=SUMPRODUCT((H_Rate_Class=$B28)*[5]Energy!I$9:I$118)} -> 959433826 | J28: {=SUMPRODUCT((H_Rate_Class=$B28)*[5]Energy!J$9:J$118)} -> 908905693 | K28: {=SUMPRODUCT((H_Rate_Class=$B28)*[5]Energy!K$9:K$118)} -> 967240722 | ... O28: {=SUMPRODUCT((H_Rate_Class=$B28)*[5]Energy!O$9:O$118)} -> 976672890 | P28: =SUM(D28:O28) -> 11207029849
A30: 12 | B30: LIGHTING | C30: SEC | D30: {=SUMPRODUCT((H_Rate_Class=$B30)*[5]Energy!D$9:D$118)} -> 20205776 | E30: {=SUMPRODUCT((H_Rate_Class=$B30)*[5]Energy!E$9:E$118)} -> 20288043 | F30: {=SUMPRODUCT((H_Rate_Class=$B30)*[5]Energy!F$9:F$118)} -> 20121015 | G30: {=SUMPRODUCT((H_Rate_Class=$B30)*[5]Energy!G$9:G$118)} -> 20163075 | H30: {=SUMPRODUCT((H_Rate_Class=$B30)*[5]Energy!H$9:H$118)} -> 20042292 | I30: {=SUMPRODUCT((H_Rate_Class=$B30)*[5]Energy!I$9:I$118)} -> 20100508 | J30: {=SUMPRODUCT((H_Rate_Class=$B30)*[5]Energy!J$9:J$118)} -> 20075515 | K30: {=SUMPRODUCT((H_Rate_Class=$B30)*[5]Energy!K$9:K$118)} -> 20064594 | ... O30: {=SUMPRODUCT((H_Rate_Class=$B30)*[5]Energy!O$9:O$118)} -> 19927259 | P30: =SUM(D30:O30) -> 240936337 | Q30: ='II-H-4.1 Functions'!F31/'II-H-1.2'!P30 -> 0.089806652 | R30: ='II-H-4.1 Functions'!I31/'II-H-1.2'!P30 -> 0.0095956343
A32: 13 | B32: TOTAL RETAIL | D32: =D30+D28+D26+D20+D16+D14 -> 3021690888 | E32: =E30+E28+E26+E20+E16+E14 -> 2863123604 | F32: =F30+F28+F26+F20+F16+F14 -> 2896435008 | G32: =G30+G28+G26+G20+G16+G14 -> 3121358549 | H32: =H30+H28+H26+H20+H16+H14 -> 2826263699 | I32: =I30+I28+I26+I20+I16+I14 -> 2847798153 | J32: =J30+J28+J26+J20+J16+J14 -> 2826324346 | K32: =K30+K28+K26+K20+K16+K14 -> 2994963675 | ... P32: =P30+P28+P26+P20+P16+P14 -> 38785345726
A34: 14 | B34: WHOLESALE PRI | C34: PRI | D34: 0 | E34: 0 | F34: 0 | G34: 0 | H34: 0 | I34: 0 | J34: 0 | K34: 0 | L34: 0 | M34: 0 | N34: 0 | O34: 0 | P34: =SUM(D34:O34) -> 0
A35: 15 | B35: WHOLESALE TRANS | C35: TRA | P35: =SUM(D35:O35) -> 0
A36: 16 | B36: TOTAL WHOLESALE | D36: =SUM(D34:D35) -> 0 | E36: =SUM(E34:E35) -> 0 | F36: =SUM(F34:F35) -> 0 | G36: =SUM(G34:G35) -> 0 | H36: =SUM(H34:H35) -> 0 | I36: =SUM(I34:I35) -> 0 | J36: =SUM(J34:J35) -> 0 | K36: =SUM(K34:K35) -> 0 | ... P36: =SUM(P34:P35) -> 0
A38: 17 | B38: TOTAL AEP TEXAS | D38: =+D36+D32 -> 3021690888 | E38: =+E36+E32 -> 2863123604 | F38: =+F36+F32 -> 2896435008 | G38: =+G36+G32 -> 3121358549 | H38: =+H36+H32 -> 2826263699 | I38: =+I36+I32 -> 2847798153 | J38: =+J36+J32 -> 2826324346 | K38: =+K36+K32 -> 2994963675 | ... P38: =+P36+P32 -> 38785345726
B39: =+B7 -> AEP TEXAS
B40: WEATHER ADJUSTMENTS TO KWH AT METER
B41: =+G9 -> FOR TEST YEAR ENDED SEPTEMBER 30, 2023
A44: LINE | B44: DESCRIPTION | C44: VOLT | D44: =D12 -> Oct-22 | E44: =E12 -> Nov-22 | F44: =F12 -> Dec-22 | G44: =G12 -> Jan-23 | H44: =H12 -> Feb-23 | I44: =I12 -> Mar-23 | J44: =J12 -> Apr-23 | K44: =K12 -> May-23 | ... O44: =O12 -> Sep-23 | P44: =+P12 -> TOTAL
A46: 1 | B46: RESIDENTIAL SERVICE | C46: SEC | D46: {=SUMPRODUCT((H_Rate_Class=$B46)*[5]Energy!D$249:D$358)} -> 17189148 | E46: {=SUMPRODUCT((H_Rate_Class=$B46)*[5]Energy!E$249:E$358)} -> 15633310 | F46: {=SUMPRODUCT((H_Rate_Class=$B46)*[5]Energy!F$249:F$358)} -> -47947373 | G46: {=SUMPRODUCT((H_Rate_Class=$B46)*[5]Energy!G$249:G$358)} -> -27919851 | H46: {=SUMPRODUCT((H_Rate_Class=$B46)*[5]Energy!H$249:H$358)} -> 26733188 | I46: {=SUMPRODUCT((H_Rate_Class=$B46)*[5]Energy!I$249:I$358)} -> -14331354 | J46: {=SUMPRODUCT((H_Rate_Class=$B46)*[5]Energy!J$249:J$358)} -> -37905950 | K46: {=SUMPRODUCT((H_Rate_Class=$B46)*[5]Energy!K$249:K$358)} -> 39401720 | ... O46: {=SUMPRODUCT((H_Rate_Class=$B46)*[5]Energy!O$249:O$358)} -> -1.002524e+08 | P46: =SUM(D46:O46) -> -3.1306872e+08
A48: 2 | B48: SECONDARY < 10 kW | C48: SEC | D48: {=SUMPRODUCT((H_Rate_Class=$B48)*[5]Energy!D$249:D$358)} -> 394320.47 | E48: {=SUMPRODUCT((H_Rate_Class=$B48)*[5]Energy!E$249:E$358)} -> 557596.02 | F48: {=SUMPRODUCT((H_Rate_Class=$B48)*[5]Energy!F$249:F$358)} -> -465909.78 | G48: {=SUMPRODUCT((H_Rate_Class=$B48)*[5]Energy!G$249:G$358)} -> -207014.55 | H48: {=SUMPRODUCT((H_Rate_Class=$B48)*[5]Energy!H$249:H$358)} -> 30275.713 | I48: {=SUMPRODUCT((H_Rate_Class=$B48)*[5]Energy!I$249:I$358)} -> -1450271.7 | J48: {=SUMPRODUCT((H_Rate_Class=$B48)*[5]Energy!J$249:J$358)} -> -669167.44 | K48: {=SUMPRODUCT((H_Rate_Class=$B48)*[5]Energy!K$249:K$358)} -> 826854.58 | ... O48: {=SUMPRODUCT((H_Rate_Class=$B48)*[5]Energy!O$249:O$358)} -> -2815636.2 | P48: =SUM(D48:O48) -> -8767706.8
A50: 3 | B50: SECONDARY > 10 kW NCP | C50: SEC | D50: {=SUMPRODUCT((H_Rate_Class=$B50)*[5]Energy!D$249:D$358)} -> 5817363.6 | E50: {=SUMPRODUCT((H_Rate_Class=$B50)*[5]Energy!E$249:E$358)} -> 7553430.9 | F50: {=SUMPRODUCT((H_Rate_Class=$B50)*[5]Energy!F$249:F$358)} -> -5625246.1 | G50: {=SUMPRODUCT((H_Rate_Class=$B50)*[5]Energy!G$249:G$358)} -> -3726325.8 | H50: {=SUMPRODUCT((H_Rate_Class=$B50)*[5]Energy!H$249:H$358)} -> 104767.9 | I50: {=SUMPRODUCT((H_Rate_Class=$B50)*[5]Energy!I$249:I$358)} -> -21904165 | J50: {=SUMPRODUCT((H_Rate_Class=$B50)*[5]Energy!J$249:J$358)} -> -9875784.2 | K50: {=SUMPRODUCT((H_Rate_Class=$B50)*[5]Energy!K$249:K$358)} -> 12362465 | ... O50: {=SUMPRODUCT((H_Rate_Class=$B50)*[5]Energy!O$249:O$358)} -> -34765280 | P50: =SUM(D50:O50) -> -1.1227043e+08
A51: 4 | B51: SECONDARY > 10 kW 4CP | C51: SEC | D51: {=SUMPRODUCT((H_Rate_Class=$B51)*[5]Energy!D$249:D$358)} -> 966162.22 | E51: {=SUMPRODUCT((H_Rate_Class=$B51)*[5]Energy!E$249:E$358)} -> 1070592 | F51: {=SUMPRODUCT((H_Rate_Class=$B51)*[5]Energy!F$249:F$358)} -> -454323.46 | G51: {=SUMPRODUCT((H_Rate_Class=$B51)*[5]Energy!G$249:G$358)} -> -555951.68 | H51: {=SUMPRODUCT((H_Rate_Class=$B51)*[5]Energy!H$249:H$358)} -> 98748.563 | I51: {=SUMPRODUCT((H_Rate_Class=$B51)*[5]Energy!I$249:I$358)} -> -2960432.5 | J51: {=SUMPRODUCT((H_Rate_Class=$B51)*[5]Energy!J$249:J$358)} -> -1165612.6 | K51: {=SUMPRODUCT((H_Rate_Class=$B51)*[5]Energy!K$249:K$358)} -> 1886488.8 | ... O51: {=SUMPRODUCT((H_Rate_Class=$B51)*[5]Energy!O$249:O$358)} -> -2488630.1 | P51: =SUM(D51:O51) -> -8524699.1
A52: 5 | B52: TOTAL SECONDARY > 10 kW | D52: =SUM(D50:D51) -> 6783525.8 | E52: =SUM(E50:E51) -> 8624022.9 | F52: =SUM(F50:F51) -> -6079569.6 | G52: =SUM(G50:G51) -> -4282277.5 | H52: =SUM(H50:H51) -> 203516.46 | I52: =SUM(I50:I51) -> -24864598 | J52: =SUM(J50:J51) -> -11041397 | K52: =SUM(K50:K51) -> 14248954 | ... P52: =SUM(P50:P51) -> -1.2079513e+08
A54: 6 | B54: PRIMARY NCP | C54: PRI | D54: {=SUMPRODUCT((H_Rate_Class=$B54)*[5]Energy!D$249:D$358)} -> 31000.271 | E54: {=SUMPRODUCT((H_Rate_Class=$B54)*[5]Energy!E$249:E$358)} -> 46161.732 | F54: {=SUMPRODUCT((H_Rate_Class=$B54)*[5]Energy!F$249:F$358)} -> -119421.47 | G54: {=SUMPRODUCT((H_Rate_Class=$B54)*[5]Energy!G$249:G$358)} -> -134194.54 | H54: {=SUMPRODUCT((H_Rate_Class=$B54)*[5]Energy!H$249:H$358)} -> -54882.845 | I54: {=SUMPRODUCT((H_Rate_Class=$B54)*[5]Energy!I$249:I$358)} -> -515031.11 | J54: {=SUMPRODUCT((H_Rate_Class=$B54)*[5]Energy!J$249:J$358)} -> -275766.07 | K54: {=SUMPRODUCT((H_Rate_Class=$B54)*[5]Energy!K$249:K$358)} -> 284859.35 | ... O54: {=SUMPRODUCT((H_Rate_Class=$B54)*[5]Energy!O$249:O$358)} -> -417713.56 | P54: =SUM(D54:O54) -> -2124654.5
A55: 7 | B55: PRIMARY 4CP | C55: PRI | D55: {=SUMPRODUCT((H_Rate_Class=$B55)*[5]Energy!D$249:D$358)} -> 697003.47 | E55: {=SUMPRODUCT((H_Rate_Class=$B55)*[5]Energy!E$249:E$358)} -> 1138237.3 | F55: {=SUMPRODUCT((H_Rate_Class=$B55)*[5]Energy!F$249:F$358)} -> -1770534.2 | G55: {=SUMPRODUCT((H_Rate_Class=$B55)*[5]Energy!G$249:G$358)} -> -1775289.4 | H55: {=SUMPRODUCT((H_Rate_Class=$B55)*[5]Energy!H$249:H$358)} -> -332037.33 | I55: {=SUMPRODUCT((H_Rate_Class=$B55)*[5]Energy!I$249:I$358)} -> -5834055.5 | J55: {=SUMPRODUCT((H_Rate_Class=$B55)*[5]Energy!J$249:J$358)} -> -2861691.6 | K55: {=SUMPRODUCT((H_Rate_Class=$B55)*[5]Energy!K$249:K$358)} -> 2342914.4 | ... O55: {=SUMPRODUCT((H_Rate_Class=$B55)*[5]Energy!O$249:O$358)} -> -7127486.3 | P55: =SUM(D55:O55) -> -29574766
A56: 8 | B56: PRIMARY SUB NCP | C56: PRI | D56: {=SUMPRODUCT((H_Rate_Class=$B56)*[5]Energy!D$249:D$358)} -> 0 | E56: {=SUMPRODUCT((H_Rate_Class=$B56)*[5]Energy!E$249:E$358)} -> 0 | F56: {=SUMPRODUCT((H_Rate_Class=$B56)*[5]Energy!F$249:F$358)} -> 0 | G56: {=SUMPRODUCT((H_Rate_Class=$B56)*[5]Energy!G$249:G$358)} -> 0 | H56: {=SUMPRODUCT((H_Rate_Class=$B56)*[5]Energy!H$249:H$358)} -> 0 | I56: {=SUMPRODUCT((H_Rate_Class=$B56)*[5]Energy!I$249:I$358)} -> 0 | J56: {=SUMPRODUCT((H_Rate_Class=$B56)*[5]Energy!J$249:J$358)} -> 0 | K56: {=SUMPRODUCT((H_Rate_Class=$B56)*[5]Energy!K$249:K$358)} -> 0 | ... O56: {=SUMPRODUCT((H_Rate_Class=$B56)*[5]Energy!O$249:O$358)} -> 0 | P56: =SUM(D56:O56) -> 0
A57: 9 | B57: PRIMARY SUB 4CP | C57: PRI | D57: {=SUMPRODUCT((H_Rate_Class=$B57)*[5]Energy!D$249:D$358)} -> 0 | E57: {=SUMPRODUCT((H_Rate_Class=$B57)*[5]Energy!E$249:E$358)} -> 0 | F57: {=SUMPRODUCT((H_Rate_Class=$B57)*[5]Energy!F$249:F$358)} -> 0 | G57: {=SUMPRODUCT((H_Rate_Class=$B57)*[5]Energy!G$249:G$358)} -> 0 | H57: {=SUMPRODUCT((H_Rate_Class=$B57)*[5]Energy!H$249:H$358)} -> 0 | I57: {=SUMPRODUCT((H_Rate_Class=$B57)*[5]Energy!I$249:I$358)} -> 0 | J57: {=SUMPRODUCT((H_Rate_Class=$B57)*[5]Energy!J$249:J$358)} -> 0 | K57: {=SUMPRODUCT((H_Rate_Class=$B57)*[5]Energy!K$249:K$358)} -> 0 | ... O57: {=SUMPRODUCT((H_Rate_Class=$B57)*[5]Energy!O$249:O$358)} -> 0 | P57: =SUM(D57:O57) -> 0
A58: 10 | B58: TOTAL PRIMARY | D58: =SUM(D54:D57) -> 728003.74 | E58: =SUM(E54:E57) -> 1184399.1 | F58: =SUM(F54:F57) -> -1889955.6 | G58: =SUM(G54:G57) -> -1909484 | H58: =SUM(H54:H57) -> -386920.17 | I58: =SUM(I54:I57) -> -6349086.6 | J58: =SUM(J54:J57) -> -3137457.7 | K58: =SUM(K54:K57) -> 2627773.8 | ... P58: =SUM(P54:P57) -> -31699420
A60: 11 | B60: TRANSMISSION | C60: TRA | D60: {=SUMPRODUCT((H_Rate_Class=$B60)*[5]Energy!D$249:D$358)} -> -95380 | E60: {=SUMPRODUCT((H_Rate_Class=$B60)*[5]Energy!E$249:E$358)} -> -97792 | F60: {=SUMPRODUCT((H_Rate_Class=$B60)*[5]Energy!F$249:F$358)} -> -98166 | G60: {=SUMPRODUCT((H_Rate_Class=$B60)*[5]Energy!G$249:G$358)} -> -105190 | H60: {=SUMPRODUCT((H_Rate_Class=$B60)*[5]Energy!H$249:H$358)} -> -67134 | I60: {=SUMPRODUCT((H_Rate_Class=$B60)*[5]Energy!I$249:I$358)} -> -100186 | J60: {=SUMPRODUCT((H_Rate_Class=$B60)*[5]Energy!J$249:J$358)} -> -123000 | K60: {=SUMPRODUCT((H_Rate_Class=$B60)*[5]Energy!K$249:K$358)} -> -106492 | ... O60: {=SUMPRODUCT((H_Rate_Class=$B60)*[5]Energy!O$249:O$358)} -> -123458 | P60: =SUM(D60:O60) -> -1282930
A62: 12 | B62: LIGHTING | C62: SEC | D62: {=SUMPRODUCT((H_Rate_Class=$B62)*[5]Energy!D$249:D$358)} -> 0 | E62: {=SUMPRODUCT((H_Rate_Class=$B62)*[5]Energy!E$249:E$358)} -> 0 | F62: {=SUMPRODUCT((H_Rate_Class=$B62)*[5]Energy!F$249:F$358)} -> 0 | G62: {=SUMPRODUCT((H_Rate_Class=$B62)*[5]Energy!G$249:G$358)} -> 0 | H62: {=SUMPRODUCT((H_Rate_Class=$B62)*[5]Energy!H$249:H$358)} -> 0 | I62: {=SUMPRODUCT((H_Rate_Class=$B62)*[5]Energy!I$249:I$358)} -> 0 | J62: {=SUMPRODUCT((H_Rate_Class=$B62)*[5]Energy!J$249:J$358)} -> 0 | K62: {=SUMPRODUCT((H_Rate_Class=$B62)*[5]Energy!K$249:K$358)} -> 0 | ... O62: {=SUMPRODUCT((H_Rate_Class=$B62)*[5]Energy!O$249:O$358)} -> 0 | P62: =SUM(D62:O62) -> 39
G63: 0
A64: 13 | B64: TOTAL RETAIL | D64: =D62+D60+D58+D52+D48+D46 -> 24999618 | E64: =E62+E60+E58+E52+E48+E46 -> 25901536 | F64: =F62+F60+F58+F52+F48+F46 -> -56480974 | G64: =G62+G60+G58+G52+G48+G46 -> -34423817 | H64: =H62+H60+H58+H52+H48+H46 -> 26512926 | I64: =I62+I60+I58+I52+I48+I46 -> -47095496 | J64: =J62+J60+J58+J52+J48+J46 -> -52876972 | K64: =K62+K60+K58+K52+K48+K46 -> 56998810 | ... P64: =P62+P60+P58+P52+P48+P46 -> -4.7561387e+08
A66: 14 | B66: WHOLESALE PRI | C66: PRI | P66: =SUM(D66:O66) -> 0
A67: 15 | B67: WHOLESALE TRANS | C67: TRA | P67: =SUM(D67:O67) -> 0
A68: 16 | B68: TOTAL WHOLESALE | D68: =SUM(D66:D67) -> 0 | E68: =SUM(E66:E67) -> 0 | F68: =SUM(F66:F67) -> 0 | G68: =SUM(G66:G67) -> 0 | H68: =SUM(H66:H67) -> 0 | I68: =SUM(I66:I67) -> 0 | J68: =SUM(J66:J67) -> 0 | K68: =SUM(K66:K67) -> 0 | ... P68: =SUM(P66:P67) -> 0
A70: 17 | B70: TOTAL AEP TEXAS | D70: =+D68+D64 -> 24999618 | E70: =+E68+E64 -> 25901536 | F70: =+F68+F64 -> -56480974 | G70: =+G68+G64 -> -34423817 | H70: =+H68+H64 -> 26512926 | I70: =+I68+I64 -> -47095496 | J70: =+J68+J64 -> -52876972 | K70: =+K68+K64 -> 56998810 | ... P70: =+P68+P64 -> -4.7561387e+08
B71: =B7 -> AEP TEXAS
B72: KWH CUSTOMER ADJUSTMENTS AT METER
B73: =+B41 -> FOR TEST YEAR ENDED SEPTEMBER 30, 2023
A76: LINE | B76: DESCRIPTION | C76: VOLT | D76: =D12 -> Oct-22 | E76: =E12 -> Nov-22 | F76: =F12 -> Dec-22 | G76: =G12 -> Jan-23 | H76: =H12 -> Feb-23 | I76: =I12 -> Mar-23 | J76: =J12 -> Apr-23 | K76: =K12 -> May-23 | ... O76: =O12 -> Sep-23 | P76: =+P12 -> TOTAL
A78: 1 | B78: RESIDENTIAL SERVICE | C78: SEC | D78: {=SUMPRODUCT((H_Rate_Class=$B78)*[5]Energy!D$129:D$238)} -> 19960537 | E78: {=SUMPRODUCT((H_Rate_Class=$B78)*[5]Energy!E$129:E$238)} -> 14284317 | F78: {=SUMPRODUCT((H_Rate_Class=$B78)*[5]Energy!F$129:F$238)} -> 15681793 | G78: {=SUMPRODUCT((H_Rate_Class=$B78)*[5]Energy!G$129:G$238)} -> 15640050 | H78: {=SUMPRODUCT((H_Rate_Class=$B78)*[5]Energy!H$129:H$238)} -> 12549690 | I78: {=SUMPRODUCT((H_Rate_Class=$B78)*[5]Energy!I$129:I$238)} -> 10448080 | J78: {=SUMPRODUCT((H_Rate_Class=$B78)*[5]Energy!J$129:J$238)} -> 8515308 | K78: {=SUMPRODUCT((H_Rate_Class=$B78)*[5]Energy!K$129:K$238)} -> 5323658.2 | ... O78: {=SUMPRODUCT((H_Rate_Class=$B78)*[5]Energy!O$129:O$238)} -> 0 | P78: =SUM(D78:O78) -> 1.0590063e+08
A80: 2 | B80: SECONDARY < 10 kW | C80: SEC | D80: {=SUMPRODUCT((H_Rate_Class=$B80)*[5]Energy!D$129:D$238)} -> 6473.4922 | E80: {=SUMPRODUCT((H_Rate_Class=$B80)*[5]Energy!E$129:E$238)} -> -111757.38 | F80: {=SUMPRODUCT((H_Rate_Class=$B80)*[5]Energy!F$129:F$238)} -> -27088.664 | G80: {=SUMPRODUCT((H_Rate_Class=$B80)*[5]Energy!G$129:G$238)} -> 507216 | H80: {=SUMPRODUCT((H_Rate_Class=$B80)*[5]Energy!H$129:H$238)} -> 683496.08 | I80: {=SUMPRODUCT((H_Rate_Class=$B80)*[5]Energy!I$129:I$238)} -> 582455.7 | J80: {=SUMPRODUCT((H_Rate_Class=$B80)*[5]Energy!J$129:J$238)} -> 315811.55 | K80: {=SUMPRODUCT((H_Rate_Class=$B80)*[5]Energy!K$129:K$238)} -> 92913.926 | ... O80: {=SUMPRODUCT((H_Rate_Class=$B80)*[5]Energy!O$129:O$238)} -> 0 | P80: =SUM(D80:O80) -> 2109148.9
A82: 3 | B82: SECONDARY > 10 kW NCP | C82: SEC | D82: {=SUMPRODUCT((H_Rate_Class=$B82)*[5]Energy!D$129:D$238)} -> 14581040 | E82: {=SUMPRODUCT((H_Rate_Class=$B82)*[5]Energy!E$129:E$238)} -> 14141231 | F82: {=SUMPRODUCT((H_Rate_Class=$B82)*[5]Energy!F$129:F$238)} -> 13059059 | G82: {=SUMPRODUCT((H_Rate_Class=$B82)*[5]Energy!G$129:G$238)} -> 3395042.3 | H82: {=SUMPRODUCT((H_Rate_Class=$B82)*[5]Energy!H$129:H$238)} -> -847648.41 | I82: {=SUMPRODUCT((H_Rate_Class=$B82)*[5]Energy!I$129:I$238)} -> -1323212.7 | J82: {=SUMPRODUCT((H_Rate_Class=$B82)*[5]Energy!J$129:J$238)} -> 3301435.5 | K82: {=SUMPRODUCT((H_Rate_Class=$B82)*[5]Energy!K$129:K$238)} -> 2838818 | ... O82: {=SUMPRODUCT((H_Rate_Class=$B82)*[5]Energy!O$129:O$238)} -> 0 | P82: =SUM(D82:O82) -> 51400456
A83: 4 | B83: SECONDARY > 10 kW 4CP | C83: SEC | D83: {=SUMPRODUCT((H_Rate_Class=$B83)*[5]Energy!D$129:D$238)} -> 3645124.2 | E83: {=SUMPRODUCT((H_Rate_Class=$B83)*[5]Energy!E$129:E$238)} -> 2037092 | F83: {=SUMPRODUCT((H_Rate_Class=$B83)*[5]Energy!F$129:F$238)} -> 1893472.1 | G83: {=SUMPRODUCT((H_Rate_Class=$B83)*[5]Energy!G$129:G$238)} -> 1988271.7 | H83: {=SUMPRODUCT((H_Rate_Class=$B83)*[5]Energy!H$129:H$238)} -> 1256470.7 | I83: {=SUMPRODUCT((H_Rate_Class=$B83)*[5]Energy!I$129:I$238)} -> 1097270.7 | J83: {=SUMPRODUCT((H_Rate_Class=$B83)*[5]Energy!J$129:J$238)} -> 734239.39 | K83: {=SUMPRODUCT((H_Rate_Class=$B83)*[5]Energy!K$129:K$238)} -> -11757.994 | ... O83: {=SUMPRODUCT((H_Rate_Class=$B83)*[5]Energy!O$129:O$238)} -> 0 | P83: =SUM(D83:O83) -> 10596481
A84: 5 | B84: TOTAL SECONDARY > 10 kW | D84: =SUM(D82:D83) -> 18226164 | E84: =SUM(E82:E83) -> 16178323 | F84: =SUM(F82:F83) -> 14952531 | G84: =SUM(G82:G83) -> 5383314 | H84: =SUM(H82:H83) -> 408822.25 | I84: =SUM(I82:I83) -> -225941.99 | J84: =SUM(J82:J83) -> 4035674.9 | K84: =SUM(K82:K83) -> 2827060 | ... P84: =SUM(P82:P83) -> 61996937
A86: 6 | B86: PRIMARY NCP | C86: PRI | D86: {=SUMPRODUCT((H_Rate_Class=$B86)*[5]Energy!D$129:D$238)} -> -66981.41 | E86: {=SUMPRODUCT((H_Rate_Class=$B86)*[5]Energy!E$129:E$238)} -> -84307.822 | F86: {=SUMPRODUCT((H_Rate_Class=$B86)*[5]Energy!F$129:F$238)} -> -76939.014 | G86: {=SUMPRODUCT((H_Rate_Class=$B86)*[5]Energy!G$129:G$238)} -> -40331.941 | H86: {=SUMPRODUCT((H_Rate_Class=$B86)*[5]Energy!H$129:H$238)} -> -22058.135 | I86: {=SUMPRODUCT((H_Rate_Class=$B86)*[5]Energy!I$129:I$238)} -> 73082.654 | J86: {=SUMPRODUCT((H_Rate_Class=$B86)*[5]Energy!J$129:J$238)} -> 0 | K86: {=SUMPRODUCT((H_Rate_Class=$B86)*[5]Energy!K$129:K$238)} -> -87616.274 | ... O86: {=SUMPRODUCT((H_Rate_Class=$B86)*[5]Energy!O$129:O$238)} -> 0 | P86: =SUM(D86:O86) -> -514363.46
A87: 7 | B87: PRIMARY 4CP | C87: PRI | D87: {=SUMPRODUCT((H_Rate_Class=$B87)*[5]Energy!D$129:D$238)} -> 6857713.2 | E87: {=SUMPRODUCT((H_Rate_Class=$B87)*[5]Energy!E$129:E$238)} -> 195728.83 | F87: {=SUMPRODUCT((H_Rate_Class=$B87)*[5]Energy!F$129:F$238)} -> -4232239.9 | G87: {=SUMPRODUCT((H_Rate_Class=$B87)*[5]Energy!G$129:G$238)} -> -1533538 | H87: {=SUMPRODUCT((H_Rate_Class=$B87)*[5]Energy!H$129:H$238)} -> -6591863.1 | I87: {=SUMPRODUCT((H_Rate_Class=$B87)*[5]Energy!I$129:I$238)} -> -2791306.5 | J87: {=SUMPRODUCT((H_Rate_Class=$B87)*[5]Energy!J$129:J$238)} -> -129391.07 | K87: {=SUMPRODUCT((H_Rate_Class=$B87)*[5]Energy!K$129:K$238)} -> -9564559.8 | ... O87: {=SUMPRODUCT((H_Rate_Class=$B87)*[5]Energy!O$129:O$238)} -> 0 | P87: =SUM(D87:O87) -> -40429397
A88: 8 | B88: PRIMARY SUB NCP | C88: PRI | D88: {=SUMPRODUCT((H_Rate_Class=$B88)*[5]Energy!D$129:D$238)} -> 0 | E88: {=SUMPRODUCT((H_Rate_Class=$B88)*[5]Energy!E$129:E$238)} -> 0 | F88: {=SUMPRODUCT((H_Rate_Class=$B88)*[5]Energy!F$129:F$238)} -> 0 | G88: {=SUMPRODUCT((H_Rate_Class=$B88)*[5]Energy!G$129:G$238)} -> 0 | H88: {=SUMPRODUCT((H_Rate_Class=$B88)*[5]Energy!H$129:H$238)} -> 0 | I88: {=SUMPRODUCT((H_Rate_Class=$B88)*[5]Energy!I$129:I$238)} -> 0 | J88: {=SUMPRODUCT((H_Rate_Class=$B88)*[5]Energy!J$129:J$238)} -> 0 | K88: {=SUMPRODUCT((H_Rate_Class=$B88)*[5]Energy!K$129:K$238)} -> 0 | ... O88: {=SUMPRODUCT((H_Rate_Class=$B88)*[5]Energy!O$129:O$238)} -> 0 | P88: =SUM(D88:O88) -> 0
A89: 9 | B89: PRIMARY SUB 4CP | C89: PRI | D89: {=SUMPRODUCT((H_Rate_Class=$B89)*[5]Energy!D$129:D$238)} -> 0 | E89: {=SUMPRODUCT((H_Rate_Class=$B89)*[5]Energy!E$129:E$238)} -> 0 | F89: {=SUMPRODUCT((H_Rate_Class=$B89)*[5]Energy!F$129:F$238)} -> 0 | G89: {=SUMPRODUCT((H_Rate_Class=$B89)*[5]Energy!G$129:G$238)} -> 0 | H89: {=SUMPRODUCT((H_Rate_Class=$B89)*[5]Energy!H$129:H$238)} -> 0 | I89: {=SUMPRODUCT((H_Rate_Class=$B89)*[5]Energy!I$129:I$238)} -> 0 | J89: {=SUMPRODUCT((H_Rate_Class=$B89)*[5]Energy!J$129:J$238)} -> 0 | K89: {=SUMPRODUCT((H_Rate_Class=$B89)*[5]Energy!K$129:K$238)} -> 0 | ... O89: {=SUMPRODUCT((H_Rate_Class=$B89)*[5]Energy!O$129:O$238)} -> 0 | P89: =SUM(D89:O89) -> 0
A90: 10 | B90: TOTAL PRIMARY | D90: =SUM(D86:D89) -> 6790731.8 | E90: =SUM(E86:E89) -> 111421.01 | F90: =SUM(F86:F89) -> -4309178.9 | G90: =SUM(G86:G89) -> -1573870 | H90: =SUM(H86:H89) -> -6613921.2 | I90: =SUM(I86:I89) -> -2718223.8 | J90: =SUM(J86:J89) -> -129391.07 | K90: =SUM(K86:K89) -> -9652176.1 | ... P90: =SUM(P86:P89) -> -40943761
A92: 11 | B92: TRANSMISSION | C92: TRA | D92: {=SUMPRODUCT((H_Rate_Class=$B92)*[5]Energy!D$129:D$238)} -> -10147537 | E92: {=SUMPRODUCT((H_Rate_Class=$B92)*[5]Energy!E$129:E$238)} -> -6228831.2 | F92: {=SUMPRODUCT((H_Rate_Class=$B92)*[5]Energy!F$129:F$238)} -> 12218567 | G92: {=SUMPRODUCT((H_Rate_Class=$B92)*[5]Energy!G$129:G$238)} -> -26394580 | H92: {=SUMPRODUCT((H_Rate_Class=$B92)*[5]Energy!H$129:H$238)} -> -7031500.3 | I92: {=SUMPRODUCT((H_Rate_Class=$B92)*[5]Energy!I$129:I$238)} -> -14456609 | J92: {=SUMPRODUCT((H_Rate_Class=$B92)*[5]Energy!J$129:J$238)} -> -7191787.6 | K92: {=SUMPRODUCT((H_Rate_Class=$B92)*[5]Energy!K$129:K$238)} -> -25535893 | ... O92: {=SUMPRODUCT((H_Rate_Class=$B92)*[5]Energy!O$129:O$238)} -> 0 | P92: =SUM(D92:O92) -> -1.7005016e+08
A94: 12 | B94: LIGHTING | C94: SEC | D94: {=SUMPRODUCT((H_Rate_Class=$B94)*[5]Energy!D$129:D$238)} -> -327560.94 | E94: {=SUMPRODUCT((H_Rate_Class=$B94)*[5]Energy!E$129:E$238)} -> -410879.6 | F94: {=SUMPRODUCT((H_Rate_Class=$B94)*[5]Energy!F$129:F$238)} -> -301982.17 | G94: {=SUMPRODUCT((H_Rate_Class=$B94)*[5]Energy!G$129:G$238)} -> -287693.75 | H94: {=SUMPRODUCT((H_Rate_Class=$B94)*[5]Energy!H$129:H$238)} -> -256429.65 | I94: {=SUMPRODUCT((H_Rate_Class=$B94)*[5]Energy!I$129:I$238)} -> -160196 | J94: {=SUMPRODUCT((H_Rate_Class=$B94)*[5]Energy!J$129:J$238)} -> -174572.49 | K94: {=SUMPRODUCT((H_Rate_Class=$B94)*[5]Energy!K$129:K$238)} -> -238758.73 | ... O94: {=SUMPRODUCT((H_Rate_Class=$B94)*[5]Energy!O$129:O$238)} -> 0 | P94: =SUM(D94:O94) -> -2551478.4
A96: 13 | B96: TOTAL RETAIL | D96: =D94+D92+D90+D84+D80+D78 -> 34508808 | E96: =E94+E92+E90+E84+E80+E78 -> 23822593 | F96: =F94+F92+F90+F84+F80+F78 -> 38214642 | G96: =G94+G92+G90+G84+G80+G78 -> -6725564 | H96: =H94+H92+H90+H84+H80+H78 -> -259843.06 | I96: =I94+I92+I90+I84+I80+I78 -> -6530434.7 | J96: =J94+J92+J90+J84+J80+J78 -> 5371043.3 | K96: =K94+K92+K90+K84+K80+K78 -> -27183196 | ... P96: =P94+P92+P90+P84+P80+P78 -> -43538688
A98: 14 | B98: WHOLESALE PRI | C98: PRI | D98: {=SUMPRODUCT((H_Rate_Class=$B98)*[5]Energy!D$129:D$238)} -> 0 | E98: {=SUMPRODUCT((H_Rate_Class=$B98)*[5]Energy!E$129:E$238)} -> 0 | F98: {=SUMPRODUCT((H_Rate_Class=$B98)*[5]Energy!F$129:F$238)} -> 0 | G98: {=SUMPRODUCT((H_Rate_Class=$B98)*[5]Energy!G$129:G$238)} -> 0 | H98: {=SUMPRODUCT((H_Rate_Class=$B98)*[5]Energy!H$129:H$238)} -> 0 | I98: {=SUMPRODUCT((H_Rate_Class=$B98)*[5]Energy!I$129:I$238)} -> 0 | J98: {=SUMPRODUCT((H_Rate_Class=$B98)*[5]Energy!J$129:J$238)} -> 0 | K98: {=SUMPRODUCT((H_Rate_Class=$B98)*[5]Energy!K$129:K$238)} -> 0 | ... O98: {=SUMPRODUCT((H_Rate_Class=$B98)*[5]Energy!O$129:O$238)} -> 0 | P98: =SUM(D98:O98) -> 0
A99: 15 | B99: WHOLESALE TRANS | C99: TRA | D99: {=SUMPRODUCT((H_Rate_Class=$B99)*[5]Energy!D$129:D$238)} -> 0 | E99: {=SUMPRODUCT((H_Rate_Class=$B99)*[5]Energy!E$129:E$238)} -> 0 | F99: {=SUMPRODUCT((H_Rate_Class=$B99)*[5]Energy!F$129:F$238)} -> 0 | G99: {=SUMPRODUCT((H_Rate_Class=$B99)*[5]Energy!G$129:G$238)} -> 0 | H99: {=SUMPRODUCT((H_Rate_Class=$B99)*[5]Energy!H$129:H$238)} -> 0 | I99: {=SUMPRODUCT((H_Rate_Class=$B99)*[5]Energy!I$129:I$238)} -> 0 | J99: {=SUMPRODUCT((H_Rate_Class=$B99)*[5]Energy!J$129:J$238)} -> 0 | K99: {=SUMPRODUCT((H_Rate_Class=$B99)*[5]Energy!K$129:K$238)} -> 0 | ... O99: {=SUMPRODUCT((H_Rate_Class=$B99)*[5]Energy!O$129:O$238)} -> 0 | P99: =SUM(D99:O99) -> 0
A100: 16 | B100: TOTAL WHOLESALE | D100: =SUM(D98:D99) -> 0 | E100: =SUM(E98:E99) -> 0 | F100: =SUM(F98:F99) -> 0 | G100: =SUM(G98:G99) -> 0 | H100: =SUM(H98:H99) -> 0 | I100: =SUM(I98:I99) -> 0 | J100: =SUM(J98:J99) -> 0 | K100: =SUM(K98:K99) -> 0 | ... P100: =SUM(P98:P99) -> 0
A102: 17 | B102: TOTAL AEP TEXAS | D102: =+D100+D96 -> 34508808 | E102: =+E100+E96 -> 23822593 | F102: =+F100+F96 -> 38214642 | G102: =+G100+G96 -> -6725564 | H102: =+H100+H96 -> -259843.06 | I102: =+I100+I96 -> -6530434.7 | J102: =+J100+J96 -> 5371043.3 | K102: =+K100+K96 -> -27183196 | ... P102: =+P100+P96 -> -43538688
B105: =+B7 -> AEP TEXAS
B106: OTHER KWH ADJUSTMENTS AT METER
B107: =+B41 -> FOR TEST YEAR ENDED SEPTEMBER 30, 2023
A110: LINE | B110: =+B44 -> DESCRIPTION | C110: =+C44 -> VOLT | D110: =+D44 -> Oct-22 | E110: =+E44 -> Nov-22 | F110: =+F44 -> Dec-22 | G110: =+G44 -> Jan-23 | H110: =+H44 -> Feb-23 | I110: =+I44 -> Mar-23 | ... P110: =+P44 -> TOTAL
A112: 1 | B112: RESIDENTIAL SERVICE | C112: SEC | D112: {=SUMPRODUCT((H_Rate_Class=$B112)*[5]Energy!D$369:D$478)} -> 0 | E112: {=SUMPRODUCT((H_Rate_Class=$B112)*[5]Energy!E$369:E$478)} -> 0 | F112: {=SUMPRODUCT((H_Rate_Class=$B112)*[5]Energy!F$369:F$478)} -> 0 | G112: {=SUMPRODUCT((H_Rate_Class=$B112)*[5]Energy!G$369:G$478)} -> 0 | H112: {=SUMPRODUCT((H_Rate_Class=$B112)*[5]Energy!H$369:H$478)} -> 0 | I112: {=SUMPRODUCT((H_Rate_Class=$B112)*[5]Energy!I$369:I$478)} -> 0 | J112: {=SUMPRODUCT((H_Rate_Class=$B112)*[5]Energy!J$369:J$478)} -> 0 | K112: {=SUMPRODUCT((H_Rate_Class=$B112)*[5]Energy!K$369:K$478)} -> 0 | ... O112: {=SUMPRODUCT((H_Rate_Class=$B112)*[5]Energy!O$369:O$478)} -> 0 | P112: =SUM(D112:O112) -> 0
A114: 2 | B114: SECONDARY < 10 kW | C114: SEC | D114: {=SUMPRODUCT((H_Rate_Class=$B114)*[5]Energy!D$369:D$478)} -> 0 | E114: {=SUMPRODUCT((H_Rate_Class=$B114)*[5]Energy!E$369:E$478)} -> 0 | F114: {=SUMPRODUCT((H_Rate_Class=$B114)*[5]Energy!F$369:F$478)} -> 0 | G114: {=SUMPRODUCT((H_Rate_Class=$B114)*[5]Energy!G$369:G$478)} -> 0 | H114: {=SUMPRODUCT((H_Rate_Class=$B114)*[5]Energy!H$369:H$478)} -> 0 | I114: {=SUMPRODUCT((H_Rate_Class=$B114)*[5]Energy!I$369:I$478)} -> 0 | J114: {=SUMPRODUCT((H_Rate_Class=$B114)*[5]Energy!J$369:J$478)} -> 0 | K114: {=SUMPRODUCT((H_Rate_Class=$B114)*[5]Energy!K$369:K$478)} -> 0 | ... O114: {=SUMPRODUCT((H_Rate_Class=$B114)*[5]Energy!O$369:O$478)} -> 0 | P114: =SUM(D114:O114) -> 0
A116: 3 | B116: SECONDARY > 10 kW NCP | C116: SEC | D116: {=SUMPRODUCT((H_Rate_Class=$B116)*[5]Energy!D$369:D$478)} -> 0 | E116: {=SUMPRODUCT((H_Rate_Class=$B116)*[5]Energy!E$369:E$478)} -> 0 | F116: {=SUMPRODUCT((H_Rate_Class=$B116)*[5]Energy!F$369:F$478)} -> 0 | G116: {=SUMPRODUCT((H_Rate_Class=$B116)*[5]Energy!G$369:G$478)} -> 0 | H116: {=SUMPRODUCT((H_Rate_Class=$B116)*[5]Energy!H$369:H$478)} -> 0 | I116: {=SUMPRODUCT((H_Rate_Class=$B116)*[5]Energy!I$369:I$478)} -> 0 | J116: {=SUMPRODUCT((H_Rate_Class=$B116)*[5]Energy!J$369:J$478)} -> 0 | K116: {=SUMPRODUCT((H_Rate_Class=$B116)*[5]Energy!K$369:K$478)} -> 0 | ... O116: {=SUMPRODUCT((H_Rate_Class=$B116)*[5]Energy!O$369:O$478)} -> 0 | P116: =SUM(D116:O116) -> 0
A117: 4 | B117: SECONDARY > 10 kW 4CP | C117: SEC | D117: {=SUMPRODUCT((H_Rate_Class=$B117)*[5]Energy!D$369:D$478)} -> 0 | E117: {=SUMPRODUCT((H_Rate_Class=$B117)*[5]Energy!E$369:E$478)} -> 0 | F117: {=SUMPRODUCT((H_Rate_Class=$B117)*[5]Energy!F$369:F$478)} -> 0 | G117: {=SUMPRODUCT((H_Rate_Class=$B117)*[5]Energy!G$369:G$478)} -> 0 | H117: {=SUMPRODUCT((H_Rate_Class=$B117)*[5]Energy!H$369:H$478)} -> 0 | I117: {=SUMPRODUCT((H_Rate_Class=$B117)*[5]Energy!I$369:I$478)} -> 0 | J117: {=SUMPRODUCT((H_Rate_Class=$B117)*[5]Energy!J$369:J$478)} -> 0 | K117: {=SUMPRODUCT((H_Rate_Class=$B117)*[5]Energy!K$369:K$478)} -> 0 | ... O117: {=SUMPRODUCT((H_Rate_Class=$B117)*[5]Energy!O$369:O$478)} -> 0 | P117: =SUM(D117:O117) -> 0
A118: 5 | B118: TOTAL SECONDARY > 10 kW | P118: =SUM(P116:P117) -> 0
A120: 6 | B120: PRIMARY NCP | C120: PRI | D120: {=SUMPRODUCT((H_Rate_Class=$B120)*[5]Energy!D$369:D$478)} -> 0 | E120: {=SUMPRODUCT((H_Rate_Class=$B120)*[5]Energy!E$369:E$478)} -> 0 | F120: {=SUMPRODUCT((H_Rate_Class=$B120)*[5]Energy!F$369:F$478)} -> 0 | G120: {=SUMPRODUCT((H_Rate_Class=$B120)*[5]Energy!G$369:G$478)} -> 0 | H120: {=SUMPRODUCT((H_Rate_Class=$B120)*[5]Energy!H$369:H$478)} -> 0 | I120: {=SUMPRODUCT((H_Rate_Class=$B120)*[5]Energy!I$369:I$478)} -> 0 | J120: {=SUMPRODUCT((H_Rate_Class=$B120)*[5]Energy!J$369:J$478)} -> 0 | K120: {=SUMPRODUCT((H_Rate_Class=$B120)*[5]Energy!K$369:K$478)} -> 0 | ... O120: {=SUMPRODUCT((H_Rate_Class=$B120)*[5]Energy!O$369:O$478)} -> 0 | P120: =SUM(D120:O120) -> 0
A121: 7 | B121: PRIMARY 4CP | C121: PRI | D121: {=SUMPRODUCT((H_Rate_Class=$B121)*[5]Energy!D$369:D$478)} -> 0 | E121: {=SUMPRODUCT((H_Rate_Class=$B121)*[5]Energy!E$369:E$478)} -> 0 | F121: {=SUMPRODUCT((H_Rate_Class=$B121)*[5]Energy!F$369:F$478)} -> 0 | G121: {=SUMPRODUCT((H_Rate_Class=$B121)*[5]Energy!G$369:G$478)} -> 0 | H121: {=SUMPRODUCT((H_Rate_Class=$B121)*[5]Energy!H$369:H$478)} -> 0 | I121: {=SUMPRODUCT((H_Rate_Class=$B121)*[5]Energy!I$369:I$478)} -> 0 | J121: {=SUMPRODUCT((H_Rate_Class=$B121)*[5]Energy!J$369:J$478)} -> 0 | K121: {=SUMPRODUCT((H_Rate_Class=$B121)*[5]Energy!K$369:K$478)} -> 0 | ... O121: {=SUMPRODUCT((H_Rate_Class=$B121)*[5]Energy!O$369:O$478)} -> 0 | P121: =SUM(D121:O121) -> 0
A122: 8 | B122: PRIMARY SUB NCP | C122: PRI | D122: {=SUMPRODUCT((H_Rate_Class=$B122)*[5]Energy!D$369:D$478)} -> 0 | E122: {=SUMPRODUCT((H_Rate_Class=$B122)*[5]Energy!E$369:E$478)} -> 0 | F122: {=SUMPRODUCT((H_Rate_Class=$B122)*[5]Energy!F$369:F$478)} -> 0 | G122: {=SUMPRODUCT((H_Rate_Class=$B122)*[5]Energy!G$369:G$478)} -> 0 | H122: {=SUMPRODUCT((H_Rate_Class=$B122)*[5]Energy!H$369:H$478)} -> 0 | I122: {=SUMPRODUCT((H_Rate_Class=$B122)*[5]Energy!I$369:I$478)} -> 0 | J122: {=SUMPRODUCT((H_Rate_Class=$B122)*[5]Energy!J$369:J$478)} -> 0 | K122: {=SUMPRODUCT((H_Rate_Class=$B122)*[5]Energy!K$369:K$478)} -> 0 | ... O122: {=SUMPRODUCT((H_Rate_Class=$B122)*[5]Energy!O$369:O$478)} -> 0 | P122: =SUM(D122:O122) -> 0
A123: 9 | B123: PRIMARY SUB 4CP | C123: PRI | D123: {=SUMPRODUCT((H_Rate_Class=$B123)*[5]Energy!D$369:D$478)} -> 0 | E123: {=SUMPRODUCT((H_Rate_Class=$B123)*[5]Energy!E$369:E$478)} -> 0 | F123: {=SUMPRODUCT((H_Rate_Class=$B123)*[5]Energy!F$369:F$478)} -> 0 | G123: {=SUMPRODUCT((H_Rate_Class=$B123)*[5]Energy!G$369:G$478)} -> 0 | H123: {=SUMPRODUCT((H_Rate_Class=$B123)*[5]Energy!H$369:H$478)} -> 0 | I123: {=SUMPRODUCT((H_Rate_Class=$B123)*[5]Energy!I$369:I$478)} -> 0 | J123: {=SUMPRODUCT((H_Rate_Class=$B123)*[5]Energy!J$369:J$478)} -> 0 | K123: {=SUMPRODUCT((H_Rate_Class=$B123)*[5]Energy!K$369:K$478)} -> 0 | ... O123: {=SUMPRODUCT((H_Rate_Class=$B123)*[5]Energy!O$369:O$478)} -> 0 | P123: =SUM(D123:O123) -> 0
A124: 10 | B124: TOTAL PRIMARY | P124: =SUM(P120:P123) -> 0
A126: 11 | B126: TRANSMISSION | C126: TRA | D126: {=SUMPRODUCT((H_Rate_Class=$B126)*[5]Energy!D$369:D$478)} -> 0 | E126: {=SUMPRODUCT((H_Rate_Class=$B126)*[5]Energy!E$369:E$478)} -> 0 | F126: {=SUMPRODUCT((H_Rate_Class=$B126)*[5]Energy!F$369:F$478)} -> 0 | G126: {=SUMPRODUCT((H_Rate_Class=$B126)*[5]Energy!G$369:G$478)} -> 0 | H126: {=SUMPRODUCT((H_Rate_Class=$B126)*[5]Energy!H$369:H$478)} -> 0 | I126: {=SUMPRODUCT((H_Rate_Class=$B126)*[5]Energy!I$369:I$478)} -> 0 | J126: {=SUMPRODUCT((H_Rate_Class=$B126)*[5]Energy!J$369:J$478)} -> 0 | K126: {=SUMPRODUCT((H_Rate_Class=$B126)*[5]Energy!K$369:K$478)} -> 0 | ... O126: {=SUMPRODUCT((H_Rate_Class=$B126)*[5]Energy!O$369:O$478)} -> 0 | P126: =SUM(D126:O126) -> 0
A128: 12 | B128: LIGHTING | C128: SEC | D128: {=SUMPRODUCT((H_Rate_Class=$B128)*[5]Energy!D$369:D$478)} -> 0 | E128: {=SUMPRODUCT((H_Rate_Class=$B128)*[5]Energy!E$369:E$478)} -> 0 | F128: {=SUMPRODUCT((H_Rate_Class=$B128)*[5]Energy!F$369:F$478)} -> 0 | G128: {=SUMPRODUCT((H_Rate_Class=$B128)*[5]Energy!G$369:G$478)} -> 0 | H128: {=SUMPRODUCT((H_Rate_Class=$B128)*[5]Energy!H$369:H$478)} -> 0 | I128: {=SUMPRODUCT((H_Rate_Class=$B128)*[5]Energy!I$369:I$478)} -> 0 | J128: {=SUMPRODUCT((H_Rate_Class=$B128)*[5]Energy!J$369:J$478)} -> 0 | K128: {=SUMPRODUCT((H_Rate_Class=$B128)*[5]Energy!K$369:K$478)} -> 0 | ... O128: {=SUMPRODUCT((H_Rate_Class=$B128)*[5]Energy!O$369:O$478)} -> 0 | P128: =SUM(D128:O128) -> 0
A130: 13 | B130: TOTAL RETAIL | D130: =D128+D126+D124+D118+D114+D112 -> 0 | E130: =E128+E126+E124+E118+E114+E112 -> 0 | F130: =F128+F126+F124+F118+F114+F112 -> 0 | G130: =G128+G126+G124+G118+G114+G112 -> 0 | H130: =H128+H126+H124+H118+H114+H112 -> 0 | I130: =I128+I126+I124+I118+I114+I112 -> 0 | J130: =J128+J126+J124+J118+J114+J112 -> 0 | K130: =K128+K126+K124+K118+K114+K112 -> 0 | ... P130: =P128+P126+P124+P118+P114+P112 -> 0
A132: 14 | B132: WHOLESALE PRI | C132: PRI | P132: =SUM(D132:O132) -> 0
A133: 15 | B133: WHOLESALE TRANS | C133: TRA | P133: =SUM(D133:O133) -> 0
A134: 16 | B134: TOTAL WHOLESALE | D134: =SUM(D132:D133) -> 0 | E134: =SUM(E132:E133) -> 0 | F134: =SUM(F132:F133) -> 0 | G134: =SUM(G132:G133) -> 0 | H134: =SUM(H132:H133) -> 0 | I134: =SUM(I132:I133) -> 0 | J134: =SUM(J132:J133) -> 0 | K134: =SUM(K132:K133) -> 0 | ... P134: =SUM(P132:P133) -> 0
A136: 17 | B136: TOTAL AEP TEXAS | D136: =+D134+D130 -> 0 | E136: =+E134+E130 -> 0 | F136: =+F134+F130 -> 0 | G136: =+G134+G130 -> 0 | H136: =+H134+H130 -> 0 | I136: =+I134+I130 -> 0 | J136: =+J134+J130 -> 0 | K136: =+K134+K130 -> 0 | ... P136: =+P134+P130 -> 0
B137: =B7 -> AEP TEXAS
B138: ADJUSTED BILLING KWH AT METER
B139: =G9 -> FOR TEST YEAR ENDED SEPTEMBER 30, 2023
A142: LINE | B142: DESCRIPTION | C142: VOLT | D142: =D12 -> Oct-22 | E142: =E12 -> Nov-22 | F142: =F12 -> Dec-22 | G142: =G12 -> Jan-23 | H142: =H12 -> Feb-23 | I142: =I12 -> Mar-23 | J142: =J12 -> Apr-23 | K142: =K12 -> May-23 | ... O142: =O12 -> Sep-23 | P142: TOTAL
A144: 1 | B144: RESIDENTIAL SERVICE | C144: SEC | D144: =D112+D78+D46+D14 -> 1.0679803e+09 | E144: =E112+E78+E46+E14 -> 8.2571673e+08 | F144: =F112+F78+F46+F14 -> 8.9384679e+08 | G144: =G112+G78+G46+G14 -> 9.8094603e+08 | H144: =H112+H78+H46+H14 -> 9.1343535e+08 | I144: =I112+I78+I46+I14 -> 7.9856757e+08 | J144: =J112+J78+J46+J14 -> 7.613129e+08 | K144: =K112+K78+K46+K14 -> 9.080815e+08 | ... O144: =O112+O78+O46+O14 -> 1391962932 | P144: =SUM(D144:O144) -> 1.2589883e+10
A146: 2 | B146: SECONDARY < 10 kW | C146: SEC | D146: =D114+D80+D48+D16 -> 57430279 | E146: =E114+E80+E48+E16 -> 50937154 | F146: =F114+F80+F48+F16 -> 53035585 | G146: =G114+G80+G48+G16 -> 54461759 | H146: =H114+H80+H48+H16 -> 50329422 | I146: =I114+I80+I48+I16 -> 47995946 | J146: =J114+J80+J48+J16 -> 48239289 | K146: =K114+K80+K48+K16 -> 51825301 | ... O146: =O114+O80+O48+O16 -> 66642732 | P146: =SUM(D146:O146) -> 6.7210011e+08
A148: 3 | B148: SECONDARY > 10 kW NCP | C148: SEC | D148: =D116+D82+D50+D18 -> 6.9765394e+08 | E148: =E116+E82+E50+E18 -> 6.0301042e+08 | F148: =F116+F82+F50+F18 -> 5.914829e+08 | G148: =G116+G82+G50+G18 -> 5.857289e+08 | H148: =H116+H82+H50+H18 -> 5.3459822e+08 | I148: =I116+I82+I50+I18 -> 5.4147285e+08 | J148: =J116+J82+J50+J18 -> 5.7395293e+08 | K148: =K116+K82+K50+K18 -> 6.280295e+08 | ... O148: =O116+O82+O50+O18 -> 8.1251121e+08 | P148: =SUM(D148:O148) -> 7.8954904e+09
A149: 4 | B149: SECONDARY > 10 kW 4CP | C149: SEC | D149: =D117+D83+D51+D19 -> 1.1676589e+08 | E149: =E117+E83+E51+E19 -> 1.0228542e+08 | F149: =F117+F83+F51+F19 -> 1.049876e+08 | G149: =G117+G83+G51+G19 -> 1.003563e+08 | H149: =H117+H83+H51+H19 -> 91526054 | I149: =I117+I83+I51+I19 -> 93155971 | J149: =J117+J83+J51+J19 -> 1.0071327e+08 | K149: =K117+K83+K51+K19 -> 1.037021e+08 | ... O149: =O117+O83+O51+O19 -> 1.3564161e+08 | P149: =SUM(D149:O149) -> 1.3095668e+09
A150: 5 | B150: TOTAL SECONDARY > 10 kW | D150: =SUM(D148:D149) -> 8.1441983e+08 | E150: =SUM(E148:E149) -> 7.0529584e+08 | F150: =SUM(F148:F149) -> 6.9647051e+08 | G150: =SUM(G148:G149) -> 6.8608519e+08 | H150: =SUM(H148:H149) -> 6.2612428e+08 | I150: =SUM(I148:I149) -> 6.3462882e+08 | J150: =SUM(J148:J149) -> 6.746662e+08 | K150: =SUM(K148:K149) -> 7.317316e+08 | ... P150: =SUM(P148:P149) -> 9.2050572e+09
...

Sheet II-H-1.3
B2: PUBLIC UTILITY COMMISSION OF TEXAS
B3: AEP TEXAS INC
B4: II-H-1.3 UNADJUSTED TEST YEAR KWH DATA
B5: ='II-H-1.2'!B5 -> TEST YEAR ENDING 9/30/2023
B6: =+'II-H-1'!B6 -> DOCKET 56165
A7: AEP TEXAS
A8: UNADJUSTED BILLING KWH
A9: FOR TEST YEAR ENDED SEPTEMBER 30, 2023
A12: LINE | B12: DESCRIPTION | C12: VOLT | D12: KWH @ Source | E12: Percentage | F12: KWH @ Meter | G12: Percentage
A14: 1 | B14: RESIDENTIAL SERVICE | C14: SEC | D14: =+'II-H-1.2'!P177 -> 1.3761948e+10 | E14: =+D14/$D$38 -> 0.33608277 | F14: ='II-H-1.2'!P14 -> 12797050643 | G14: =F14/$F$38 -> 0.32994551
A16: 2 | B16: SECONDARY < 10 kW | C16: SEC | D16: =+'II-H-1.2'!P179 -> 7.2993707e+08 | E16: =+D16/$D$38 -> 0.017825912 | F16: ='II-H-1.2'!P16 -> 678758664 | G16: =F16/$F$38 -> 0.01750039
A18: 3 | B18: SECONDARY > 10 kW NCP | C18: SEC | D18: =+'II-H-1.2'!P181 -> 8.55627e+09 | E18: =+D18/$D$38 -> 0.20895406 | F18: ='II-H-1.2'!P18 -> 7956360402 | G18: =F18/$F$38 -> 0.20513831
A19: 4 | B19: SECONDARY > 10 kW 4CP | C19: SEC | D19: =+'II-H-1.2'!P182 -> 1.4060801e+09 | E19: =+D19/$D$38 -> 0.034338111 | F19: ='II-H-1.2'!P19 -> 1307495001 | G19: =F19/$F$38 -> 0.033711057
A20: 5 | B20: TOTAL SECONDARY > 10 kW | D20: =SUM(D18:D19) -> 9.9623501e+09 | E20: =SUM(E18:E19) -> 0.24329217 | F20: ='II-H-1.2'!P20 -> 9263855403 | G20: =F20/$F$38 -> 0.23884937
A22: 6 | B22: PRIMARY NCP | C22: PRI | D22: =+'II-H-1.2'!P185 -> 2.7556991e+08 | E22: =+D22/$D$38 -> 0.0067297376 | F22: ='II-H-1.2'!P22 -> 263796669 | G22: =F22/$F$38 -> 0.006801452
A23: 7 | B23: PRIMARY 4CP | C23: PRI | D23: =+'II-H-1.2'!P186 -> 3.9989671e+09 | E23: =+D23/$D$38 -> 0.097659424 | F23: ='II-H-1.2'!P23 -> 3828118181 | G23: =F23/$F$38 -> 0.098700118
A24: 8 | B24: PRIMARY SUB NCP | C24: PRI | D24: =+'II-H-1.2'!P187 -> 6143051.2 | E24: =+D24/$D$38 -> 0.00015002045 | F24: ='II-H-1.2'!P24 -> 5880600 | G24: =F24/$F$38 -> 0.00015161912
A25: 9 | B25: PRIMARY SUB 4CP | C25: PRI | D25: =+'II-H-1.2'!P188 -> 5.2223078e+08 | E25: =+D25/$D$38 -> 0.012753483 | F25: ='II-H-1.2'!P25 -> 499919380 | G25: =F25/$F$38 -> 0.012889388
A26: 10 | B26: TOTAL PRIMARY | D26: =SUM(D22:D25) -> 4.8029108e+09 | E26: =SUM(E22:E23) -> 0.10438916 | F26: =SUM(F22:F25) -> 4597714830 | G26: =F26/$F$38 -> 0.11854258
A28: 11 | B28: TRANSMISSION | C28: TRA | D28: =+'II-H-1.2'!P191 -> 1.1431843e+10 | E28: =+D28/$D$38 -> 0.27917889 | F28: ='II-H-1.2'!P28 -> 11207029849 | G28: =F28/$F$38 -> 0.28895011
A30: 12 | B30: LIGHTING | C30: SEC | D30: =+'II-H-1.2'!P193 -> 2.5910294e+08 | E30: =+D30/$D$38 -> 0.0063275949 | F30: ='II-H-1.2'!P30 -> 240936337 | G30: =F30/$F$38 -> 0.0062120456
A32: 13 | B32: TOTAL RETAIL | D32: =+D14+D16+D20+D26+D28+D30 -> 4.0948092e+10 | E32: =+E14+E16+E20+E26+E28+E30 -> 0.9870965 | F32: =+F14+F16+F20+F26+F28+F30 -> 38785345726 | G32: =F32/$F$38 -> 1
A34: 14 | B34: WHOLESALE PRI | C34: PRI | D34: 0 | F34: ='II-H-1.2'!P34 -> 0 | G34: =F34/$F$38 -> 0
A35: 15 | B35: WHOLESALE TRANS | C35: TRA | D35: 0 | F35: ='II-H-1.2'!P35 -> 0 | G35: =F35/$F$38 -> 0
A36: 16 | B36: TOTAL WHOLESALE | D36: =SUM(D34:D35) -> 0 | F36: ='II-H-1.2'!P36 -> 0 | G36: =F36/$F$38 -> 0
A38: 17 | B38: TOTAL AEP TEXAS | D38: =+D32+D36 -> 4.0948092e+10 | E38: =+E32+E36 -> 0.9870965 | F38: =+F32+F36 -> 38785345726 | G38: =+G32+G36 -> 1

Sheet Sch II-H-1.5
B2: PUBLIC UTILITY COMMISSION OF TEXAS
B3: AEP TEXAS INC
B4: II-H-1.5 ADJUSTMENTS TO OPERATING STATISTICS
B5: ='II-H-1'!B5 -> TEST YEAR ENDING 9/30/2023
B6: =+'II-H-1'!B6 -> DOCKET 56165
A9: Line | B9: Description
A10: 1 | B10: This schedule provides a narrative explanation of all adjustments made to Test Year operating
B11: statistics provided in RFP Schedule II-H-1.
A13: 2 | B13: Residential Service: adjustment made for weather normalized kWh sales; annualize to
B14: year-end customer count and associated kWh sales.
A16: 3 | B16: Secondary ≤ 10 kW Service: adjustment made for weather normalized kWh sales; annualize to
B17: year-end customer count and associated kWh sales.
A19: 4 | B19: Secondary ≥10 kW Service: adjustment made for weather normalized kWh sales; annualize to
B20: year-end customer count and associated kWh sales.
A22: 5 | B22: Primary Service: Segmented into primary line and primary substation; adjustment made for weather normalized kWh sales; annualize to year-end
B23: customer count and associated kWh sales.
A25: 6 | B25: Transmission Service: annualize to year-end customer count and associated kWh sales.
A27: 7 | B27: Lighting Service: annualize to year-end customer count and associated kWh sales.

Sheet II-H-3.1-3
B2: PUBLIC UTILITY COMMISSION OF TEXAS
B3: AEP TEXAS INC
B4: II-H-3.1-3 CUSTOMER ADJUSTMENTS
B5: ='II-H-1'!B5 -> TEST YEAR ENDING 9/30/2023
B6: =+'II-H-1'!B6 -> DOCKET 56165
B7: ='II-H-1.2'!B7:O7 -> AEP TEXAS
B8: BOOKED CUSTOMER COUNT
B9: ='II-H-1.1'!D10 -> FOR TEST YEAR ENDED SEPTEMBER 30, 2023
A12: LINE | B12: DESCRIPTION | C12: VOLT | D12: ='II-H-1.2'!D12 -> Oct-22 | E12: ='II-H-1.2'!E12 -> Nov-22 | F12: ='II-H-1.2'!F12 -> Dec-22 | G12: ='II-H-1.2'!G12 -> Jan-23 | H12: ='II-H-1.2'!H12 -> Feb-23 | I12: ='II-H-1.2'!I12 -> Mar-23 | J12: ='II-H-1.2'!J12 -> Apr-23 | K12: ='II-H-1.2'!K12 -> May-23 | ... O12: ='II-H-1.2'!O12 -> Sep-23 | P12: TOTAL | Q12: AVERAGE
R13: cust | S13: meter | T13: Dist
A14: 1 | B14: RESIDENTIAL SERVICE | C14: SEC | D14: {=SUMPRODUCT((H_Rate_Class=$B14)*[5]Customer!D$9:D$118)} -> 917398 | E14: {=SUMPRODUCT((H_Rate_Class=$B14)*[5]Customer!E$9:E$118)} -> 918668 | F14: {=SUMPRODUCT((H_Rate_Class=$B14)*[5]Customer!F$9:F$118)} -> 919604 | G14: {=SUMPRODUCT((H_Rate_Class=$B14)*[5]Customer!G$9:G$118)} -> 920684 | H14: {=SUMPRODUCT((H_Rate_Class=$B14)*[5]Customer!H$9:H$118)} -> 921997 | I14: {=SUMPRODUCT((H_Rate_Class=$B14)*[5]Customer!I$9:I$118)} -> 923215 | J14: {=SUMPRODUCT((H_Rate_Class=$B14)*[5]Customer!J$9:J$118)} -> 925269 | K14: {=SUMPRODUCT((H_Rate_Class=$B14)*[5]Customer!K$9:K$118)} -> 929499 | ... O14: {=SUMPRODUCT((H_Rate_Class=$B14)*[5]Customer!O$9:O$118)} -> 935238 | P14: =SUM(D14:O14) -> 11114371 | Q14: =P14/12 -> 926197.58 | R14: =+'II-H-4.1 Functions'!D15/'II-H-3.1-3'!P14 -> 1.3996686 | S14: =+'II-H-4.1 Functions'!E15/'II-H-3.1-3'!P14 -> 3.3891976 | T14: 0.021791
A16: 2 | B16: SECONDARY < 10 kW | C16: SEC | D16: {=SUMPRODUCT((H_Rate_Class=$B16)*[5]Customer!D$9:D$118)} -> 99093 | E16: {=SUMPRODUCT((H_Rate_Class=$B16)*[5]Customer!E$9:E$118)} -> 99298 | F16: {=SUMPRODUCT((H_Rate_Class=$B16)*[5]Customer!F$9:F$118)} -> 99126 | G16: {=SUMPRODUCT((H_Rate_Class=$B16)*[5]Customer!G$9:G$118)} -> 98051 | H16: {=SUMPRODUCT((H_Rate_Class=$B16)*[5]Customer!H$9:H$118)} -> 97626 | I16: {=SUMPRODUCT((H_Rate_Class=$B16)*[5]Customer!I$9:I$118)} -> 97730 | J16: {=SUMPRODUCT((H_Rate_Class=$B16)*[5]Customer!J$9:J$118)} -> 98315 | K16: {=SUMPRODUCT((H_Rate_Class=$B16)*[5]Customer!K$9:K$118)} -> 99018 | ... O16: {=SUMPRODUCT((H_Rate_Class=$B16)*[5]Customer!O$9:O$118)} -> 99366 | P16: =SUM(D16:O16) -> 1185554 | Q16: =P16/12 -> 98796.167 | R16: 1.4 | S16: 4.39 | T16: 0.021093
A18: 3 | B18: SECONDARY > 10 kW NCP | C18: SEC | D18: {=SUMPRODUCT((H_Rate_Class=$B18)*[5]Customer!D$9:D$118)} -> 70606 | E18: {=SUMPRODUCT((H_Rate_Class=$B18)*[5]Customer!E$9:E$118)} -> 70437 | F18: {=SUMPRODUCT((H_Rate_Class=$B18)*[5]Customer!F$9:F$118)} -> 70560 | G18: {=SUMPRODUCT((H_Rate_Class=$B18)*[5]Customer!G$9:G$118)} -> 71618 | H18: {=SUMPRODUCT((H_Rate_Class=$B18)*[5]Customer!H$9:H$118)} -> 72104 | I18: {=SUMPRODUCT((H_Rate_Class=$B18)*[5]Customer!I$9:I$118)} -> 72136 | J18: {=SUMPRODUCT((H_Rate_Class=$B18)*[5]Customer!J$9:J$118)} -> 71584 | K18: {=SUMPRODUCT((H_Rate_Class=$B18)*[5]Customer!K$9:K$118)} -> 71627 | ... O18: {=SUMPRODUCT((H_Rate_Class=$B18)*[5]Customer!O$9:O$118)} -> 71833 | P18: =SUM(D18:O18) -> 857957 | Q18: =P18/12 -> 71496.417 | R18: =+'II-H-4.1 Functions'!D19/'II-H-3.1-3'!P18 -> 2.0102705 | S18: 12.67 | T18: 4.869
A19: 4 | B19: SECONDARY > 10 kW 4CP | C19: SEC | D19: {=SUMPRODUCT((H_Rate_Class=$B19)*[5]Customer!D$9:D$118)} -> 556 | E19: {=SUMPRODUCT((H_Rate_Class=$B19)*[5]Customer!E$9:E$118)} -> 564 | F19: {=SUMPRODUCT((H_Rate_Class=$B19)*[5]Customer!F$9:F$118)} -> 565 | G19: {=SUMPRODUCT((H_Rate_Class=$B19)*[5]Customer!G$9:G$118)} -> 564 | H19: {=SUMPRODUCT((H_Rate_Class=$B19)*[5]Customer!H$9:H$118)} -> 568 | I19: {=SUMPRODUCT((H_Rate_Class=$B19)*[5]Customer!I$9:I$118)} -> 571 | J19: {=SUMPRODUCT((H_Rate_Class=$B19)*[5]Customer!J$9:J$118)} -> 571 | K19: {=SUMPRODUCT((H_Rate_Class=$B19)*[5]Customer!K$9:K$118)} -> 574 | ... O19: {=SUMPRODUCT((H_Rate_Class=$B19)*[5]Customer!O$9:O$118)} -> 576 | P19: =SUM(D19:O19) -> 6848 | Q19: =P19/12 -> 570.66667 | R19: 2.02 | S19: 12.67 | T19: 4.869
A20: 5 | B20: TOTAL SECONDARY > 10 kW | D20: =SUM(D18:D19) -> 71162 | E20: =SUM(E18:E19) -> 71001 | F20: =SUM(F18:F19) -> 71125 | G20: =SUM(G18:G19) -> 72182 | H20: =SUM(H18:H19) -> 72672 | I20: =SUM(I18:I19) -> 72707 | J20: =SUM(J18:J19) -> 72155 | K20: =SUM(K18:K19) -> 72201 | ... O20: =SUM(O18:O19) -> 72409 | P20: =SUM(D20:O20) -> 864805 | Q20: =P20/12 -> 72067.083
A22: 6 | B22: PRIMARY NCP | C22: PRI | D22: {=SUMPRODUCT((H_Rate_Class=$B22)*[5]Customer!D$9:D$118)-D24} -> 550 | E22: {=SUMPRODUCT((H_Rate_Class=$B22)*[5]Customer!E$9:E$118)-E24} -> 550 | F22: {=SUMPRODUCT((H_Rate_Class=$B22)*[5]Customer!F$9:F$118)-F24} -> 550 | G22: {=SUMPRODUCT((H_Rate_Class=$B22)*[5]Customer!G$9:G$118)-G24} -> 550 | H22: {=SUMPRODUCT((H_Rate_Class=$B22)*[5]Customer!H$9:H$118)-H24} -> 549 | I22: {=SUMPRODUCT((H_Rate_Class=$B22)*[5]Customer!I$9:I$118)-I24} -> 548 | J22: {=SUMPRODUCT((H_Rate_Class=$B22)*[5]Customer!J$9:J$118)-J24} -> 550 | K22: {=SUMPRODUCT((H_Rate_Class=$B22)*[5]Customer!K$9:K$118)-K24} -> 552 | ... O22: {=SUMPRODUCT((H_Rate_Class=$B22)*[5]Customer!O$9:O$118)-O24} -> 550 | P22: =SUM(D22:O22) -> 6604 | Q22: =P22/12 -> 550.33333 | R22: =+'II-H-4.1 Functions'!D23/'II-H-3.1-3'!P22 -> 7.2940636 | S22: 126.87 | T22: 3.112
A23: 7 | B23: PRIMARY 4CP | C23: PRI | D23: {=SUMPRODUCT((H_Rate_Class=$B23)*[5]Customer!D$9:D$118)-D25} -> 459 | E23: {=SUMPRODUCT((H_Rate_Class=$B23)*[5]Customer!E$9:E$118)-E25} -> 472 | F23: {=SUMPRODUCT((H_Rate_Class=$B23)*[5]Customer!F$9:F$118)-F25} -> 477 | G23: {=SUMPRODUCT((H_Rate_Class=$B23)*[5]Customer!G$9:G$118)-G25} -> 473 | H23: {=SUMPRODUCT((H_Rate_Class=$B23)*[5]Customer!H$9:H$118)-H25} -> 481 | I23: {=SUMPRODUCT((H_Rate_Class=$B23)*[5]Customer!I$9:I$118)-I25} -> 475 | J23: {=SUMPRODUCT((H_Rate_Class=$B23)*[5]Customer!J$9:J$118)-J25} -> 471 | K23: {=SUMPRODUCT((H_Rate_Class=$B23)*[5]Customer!K$9:K$118)-K25} -> 485 | ... O23: {=SUMPRODUCT((H_Rate_Class=$B23)*[5]Customer!O$9:O$118)-O25} -> 469 | P23: =SUM(D23:O23) -> 5701 | Q23: =P23/12 -> 475.08333 | R23: =+'II-H-4.1 Functions'!D24/'II-H-3.1-3'!P23 -> 7.341047 | S23: 126.87 | T23: 3.112
A24: 8 | B24: PRIMARY SUB NCP | C24: PRI | D24: 9 | E24: 9 | F24: 9 | G24: 9 | H24: 9 | I24: 9 | J24: 9 | K24: 9 | L24: 9 | M24: 9 | N24: 9 | O24: 9 | P24: =SUM(D24:O24) -> 108 | Q24: =P24/12 -> 9 | R24: =+'II-H-4.1 Functions'!D25/'II-H-3.1-3'!P24 -> 7.3373322 | S24: 126.87 | T24: 3.112
A25: 9 | B25: PRIMARY SUB 4CP | C25: PRI | D25: 58 | E25: 58 | F25: 58 | G25: 58 | H25: 58 | I25: 58 | J25: 58 | K25: 58 | L25: 58 | M25: 58 | N25: 58 | O25: 58 | P25: =SUM(D25:O25) -> 696 | Q25: =P25/12 -> 58 | R25: 735 | S25: 126.87 | T25: 3.112
A26: 10 | B26: TOTAL PRIMARY | D26: =SUM(D22:D25) -> 1076 | E26: =SUM(E22:E25) -> 1089 | F26: =SUM(F22:F25) -> 1094 | G26: =SUM(G22:G25) -> 1090 | H26: =SUM(H22:H25) -> 1097 | I26: =SUM(I22:I25) -> 1090 | J26: =SUM(J22:J25) -> 1088 | K26: =SUM(K22:K25) -> 1104 | ... P26: =SUM(P22:P25) -> 13109 | Q26: =P26/12 -> 1092.4167
A28: 11 | B28: TRANSMISSION | C28: TRA | D28: {=SUMPRODUCT((H_Rate_Class=$B28)*[5]Customer!D$9:D$118)} -> 124 | E28: {=SUMPRODUCT((H_Rate_Class=$B28)*[5]Customer!E$9:E$118)} -> 121 | F28: {=SUMPRODUCT((H_Rate_Class=$B28)*[5]Customer!F$9:F$118)} -> 119 | G28: {=SUMPRODUCT((H_Rate_Class=$B28)*[5]Customer!G$9:G$118)} -> 122 | H28: {=SUMPRODUCT((H_Rate_Class=$B28)*[5]Customer!H$9:H$118)} -> 122 | I28: {=SUMPRODUCT((H_Rate_Class=$B28)*[5]Customer!I$9:I$118)} -> 124 | J28: {=SUMPRODUCT((H_Rate_Class=$B28)*[5]Customer!J$9:J$118)} -> 122 | K28: {=SUMPRODUCT((H_Rate_Class=$B28)*[5]Customer!K$9:K$118)} -> 127 | ... O28: {=SUMPRODUCT((H_Rate_Class=$B28)*[5]Customer!O$9:O$118)} -> 123 | P28: =SUM(D28:O28) -> 1490 | Q28: =P28/12 -> 124.16667 | R28: 7.48 | S28: 761.5 | T28: 0.249
A30: 12 | B30: LIGHTING | C30: SEC | D30: {=SUMPRODUCT((H_Rate_Class=$B30)*[5]Customer!D$9:D$118)} -> 221814 | E30: {=SUMPRODUCT((H_Rate_Class=$B30)*[5]Customer!E$9:E$118)} -> 222695 | F30: {=SUMPRODUCT((H_Rate_Class=$B30)*[5]Customer!F$9:F$118)} -> 221811 | G30: {=SUMPRODUCT((H_Rate_Class=$B30)*[5]Customer!G$9:G$118)} -> 220960 | H30: {=SUMPRODUCT((H_Rate_Class=$B30)*[5]Customer!H$9:H$118)} -> 223166 | I30: {=SUMPRODUCT((H_Rate_Class=$B30)*[5]Customer!I$9:I$118)} -> 220819 | J30: {=SUMPRODUCT((H_Rate_Class=$B30)*[5]Customer!J$9:J$118)} -> 221724 | K30: {=SUMPRODUCT((H_Rate_Class=$B30)*[5]Customer!K$9:K$118)} -> 222243 | ... O30: {=SUMPRODUCT((H_Rate_Class=$B30)*[5]Customer!O$9:O$118)} -> 221390 | P30: =SUM(D30:O30) -> 2662951 | Q30: =P30/12 -> 221912.58 | T30: 0.021093
A32: 13 | B32: TOTAL RETAIL | D32: =D30+D28+D26+D20+D16+D14 -> 1310667 | E32: =E30+E28+E26+E20+E16+E14 -> 1312872 | F32: =F30+F28+F26+F20+F16+F14 -> 1312879 | G32: =G30+G28+G26+G20+G16+G14 -> 1313089 | H32: =H30+H28+H26+H20+H16+H14 -> 1316680 | I32: =I30+I28+I26+I20+I16+I14 -> 1315685 | J32: =J30+J28+J26+J20+J16+J14 -> 1318673 | K32: =K30+K28+K26+K20+K16+K14 -> 1324192 | ... O32: =O30+O28+O26+O20+O16+O14 -> 1329612 | P32: =SUM(D32:O32) -> 15842280 | Q32: =P32/12 -> 1320190
A34: 14 | B34: WHOLESALE PRI | C34: PRI
A35: 15 | B35: WHOLESALE TRANS | C35: TRA
A36: 16 | B36: TOTAL WHOLESALE
A38: 17 | B38: TOTAL AEP TEXAS | D38: =D36+D32 -> 1310667 | E38: =+E36+E32 -> 1312872 | F38: =+F36+F32 -> 1312879 | G38: =+G36+G32 -> 1313089 | H38: =+H36+H32 -> 1316680 | I38: =+I36+I32 -> 1315685 | J38: =+J36+J32 -> 1318673 | K38: =+K36+K32 -> 1324192 | L38: =+L36+L32 -> 1326629 | ... O38: =+O36+O32 -> 1329612 | P38: =SUM(D38:O38) -> 15842280 | Q38: =+Q36+Q32 -> 1320190
B39: Note: Secondary < 10 kW includes Unmetered service; Lighting customers are fixture counts.
B41: =+B7 -> AEP TEXAS
B42: CUSTOMER COUNT ADJUSTMENT
B43: =B9 -> FOR TEST YEAR ENDED SEPTEMBER 30, 2023
D45: =D11 -> 0 | G45: =G11 -> 0
A46: LINE | B46: DESCRIPTION | C46: VOLT | D46: =+D12 -> Oct-22 | E46: =+E12 -> Nov-22 | F46: =+F12 -> Dec-22 | G46: =+G12 -> Jan-23 | H46: =+H12 -> Feb-23 | I46: =+I12 -> Mar-23 | J46: =+J12 -> Apr-23 | K46: =+K12 -> May-23 | ... O46: =+O12 -> Sep-23 | P46: TOTAL | Q46: AVERAGE
A48: =A14 -> 1 | B48: =B14 -> RESIDENTIAL SERVICE | C48: =C14 -> SEC | D48: {=SUMPRODUCT((H_Rate_Class=$B48)*[5]Customer!D$129:D$238)} -> 17840 | E48: {=SUMPRODUCT((H_Rate_Class=$B48)*[5]Customer!E$129:E$238)} -> 16570 | F48: {=SUMPRODUCT((H_Rate_Class=$B48)*[5]Customer!F$129:F$238)} -> 15634 | G48: {=SUMPRODUCT((H_Rate_Class=$B48)*[5]Customer!G$129:G$238)} -> 14554 | H48: {=SUMPRODUCT((H_Rate_Class=$B48)*[5]Customer!H$129:H$238)} -> 13241 | I48: {=SUMPRODUCT((H_Rate_Class=$B48)*[5]Customer!I$129:I$238)} -> 12023 | J48: {=SUMPRODUCT((H_Rate_Class=$B48)*[5]Customer!J$129:J$238)} -> 9969 | K48: {=SUMPRODUCT((H_Rate_Class=$B48)*[5]Customer!K$129:K$238)} -> 5739 | ... O48: {=SUMPRODUCT((H_Rate_Class=$B48)*[5]Customer!O$129:O$238)} -> 0 | P48: =SUM(D48:O48) -> 108485 | Q48: =P48/12 -> 9040.4167
A50: =A16 -> 2 | B50: =B16 -> SECONDARY < 10 kW | C50: =C16 -> SEC | D50: {=SUMPRODUCT((H_Rate_Class=$B50)*[5]Customer!D$129:D$238)} -> 273 | E50: {=SUMPRODUCT((H_Rate_Class=$B50)*[5]Customer!E$129:E$238)} -> 68 | F50: {=SUMPRODUCT((H_Rate_Class=$B50)*[5]Customer!F$129:F$238)} -> 240 | G50: {=SUMPRODUCT((H_Rate_Class=$B50)*[5]Customer!G$129:G$238)} -> 1315 | H50: {=SUMPRODUCT((H_Rate_Class=$B50)*[5]Customer!H$129:H$238)} -> 1740 | I50: {=SUMPRODUCT((H_Rate_Class=$B50)*[5]Customer!I$129:I$238)} -> 1636 | J50: {=SUMPRODUCT((H_Rate_Class=$B50)*[5]Customer!J$129:J$238)} -> 1051 | K50: {=SUMPRODUCT((H_Rate_Class=$B50)*[5]Customer!K$129:K$238)} -> 348 | ... O50: {=SUMPRODUCT((H_Rate_Class=$B50)*[5]Customer!O$129:O$238)} -> 0 | P50: =SUM(D50:O50) -> 6838 | Q50: =P50/12 -> 569.83333
A52: =A18 -> 3 | B52: =B18 -> SECONDARY > 10 kW NCP | C52: =C18 -> SEC | D52: {=SUMPRODUCT((H_Rate_Class=$B52)*[5]Customer!D$129:D$238)} -> 1227 | E52: {=SUMPRODUCT((H_Rate_Class=$B52)*[5]Customer!E$129:E$238)} -> 1396 | F52: {=SUMPRODUCT((H_Rate_Class=$B52)*[5]Customer!F$129:F$238)} -> 1273 | G52: {=SUMPRODUCT((H_Rate_Class=$B52)*[5]Customer!G$129:G$238)} -> 215 | H52: {=SUMPRODUCT((H_Rate_Class=$B52)*[5]Customer!H$129:H$238)} -> -271 | I52: {=SUMPRODUCT((H_Rate_Class=$B52)*[5]Customer!I$129:I$238)} -> -303 | J52: {=SUMPRODUCT((H_Rate_Class=$B52)*[5]Customer!J$129:J$238)} -> 249 | K52: {=SUMPRODUCT((H_Rate_Class=$B52)*[5]Customer!K$129:K$238)} -> 206 | ... O52: {=SUMPRODUCT((H_Rate_Class=$B52)*[5]Customer!O$129:O$238)} -> 0 | P52: =SUM(D52:O52) -> 4039 | Q52: =P52/12 -> 336.58333
A53: =A19 -> 4 | B53: =B19 -> SECONDARY > 10 kW 4CP | C53: =C19 -> SEC | D53: {=SUMPRODUCT((H_Rate_Class=$B53)*[5]Customer!D$129:D$238)} -> 20 | E53: {=SUMPRODUCT((H_Rate_Class=$B53)*[5]Customer!E$129:E$238)} -> 12 | F53: {=SUMPRODUCT((H_Rate_Class=$B53)*[5]Customer!F$129:F$238)} -> 11 | G53: {=SUMPRODUCT((H_Rate_Class=$B53)*[5]Customer!G$129:G$238)} -> 12 | H53: {=SUMPRODUCT((H_Rate_Class=$B53)*[5]Customer!H$129:H$238)} -> 8 | I53: {=SUMPRODUCT((H_Rate_Class=$B53)*[5]Customer!I$129:I$238)} -> 5 | J53: {=SUMPRODUCT((H_Rate_Class=$B53)*[5]Customer!J$129:J$238)} -> 5 | K53: {=SUMPRODUCT((H_Rate_Class=$B53)*[5]Customer!K$129:K$238)} -> 2 | ... O53: {=SUMPRODUCT((H_Rate_Class=$B53)*[5]Customer!O$129:O$238)} -> 0 | P53: =SUM(D53:O53) -> 64 | Q53: =P53/12 -> 5.3333333
A54: =A20 -> 5 | B54: =B20 -> TOTAL SECONDARY > 10 kW | D54: =SUM(D52:D53) -> 1247 | E54: =SUM(E52:E53) -> 1408 | F54: =SUM(F52:F53) -> 1284 | G54: =SUM(G52:G53) -> 227 | H54: =SUM(H52:H53) -> -263 | I54: =SUM(I52:I53) -> -298 | J54: =SUM(J52:J53) -> 254 | K54: =SUM(K52:K53) -> 208 | ... O54: =SUM(O52:O53) -> 0 | P54: =SUM(D54:O54) -> 4103 | Q54: =SUM(Q52:Q53) -> 341.91667
A56: =A22 -> 6 | B56: =B22 -> PRIMARY NCP | C56: =C22 -> PRI | D56: {=SUMPRODUCT((H_Rate_Class=$B56)*[5]Customer!D$129:D$238)} -> -3.0642155e-14 | E56: {=SUMPRODUCT((H_Rate_Class=$B56)*[5]Customer!E$129:E$238)} -> -3.0642155e-14 | F56: {=SUMPRODUCT((H_Rate_Class=$B56)*[5]Customer!F$129:F$238)} -> -3.0642155e-14 | G56: {=SUMPRODUCT((H_Rate_Class=$B56)*[5]Customer!G$129:G$238)} -> -3.0642155e-14 | H56: {=SUMPRODUCT((H_Rate_Class=$B56)*[5]Customer!H$129:H$238)} -> 1 | I56: {=SUMPRODUCT((H_Rate_Class=$B56)*[5]Customer!I$129:I$238)} -> 2 | J56: {=SUMPRODUCT((H_Rate_Class=$B56)*[5]Customer!J$129:J$238)} -> 0 | K56: {=SUMPRODUCT((H_Rate_Class=$B56)*[5]Customer!K$129:K$238)} -> -2 | ... O56: {=SUMPRODUCT((H_Rate_Class=$B56)*[5]Customer!O$129:O$238)} -> 0 | P56: =SUM(D56:O56) -> -4 | Q56: =P56/12 -> -0.33333333
A57: =A23 -> 7 | B57: =B23 -> PRIMARY 4CP | C57: =C23 -> PRI | D57: {=SUMPRODUCT((H_Rate_Class=$B57)*[5]Customer!D$129:D$238)} -> 10 | E57: {=SUMPRODUCT((H_Rate_Class=$B57)*[5]Customer!E$129:E$238)} -> -3 | F57: {=SUMPRODUCT((H_Rate_Class=$B57)*[5]Customer!F$129:F$238)} -> -8 | G57: {=SUMPRODUCT((H_Rate_Class=$B57)*[5]Customer!G$129:G$238)} -> -4 | H57: {=SUMPRODUCT((H_Rate_Class=$B57)*[5]Customer!H$129:H$238)} -> -12 | I57: {=SUMPRODUCT((H_Rate_Class=$B57)*[5]Customer!I$129:I$238)} -> -6 | J57: {=SUMPRODUCT((H_Rate_Class=$B57)*[5]Customer!J$129:J$238)} -> -2 | K57: {=SUMPRODUCT((H_Rate_Class=$B57)*[5]Customer!K$129:K$238)} -> -16 | ... O57: {=SUMPRODUCT((H_Rate_Class=$B57)*[5]Customer!O$129:O$238)} -> 0 | P57: =SUM(D57:O57) -> -73 | Q57: =P57/12 -> -6.0833333
A58: =A24 -> 8 | B58: =B24 -> PRIMARY SUB NCP | C58: =C24 -> PRI | D58: {=SUMPRODUCT((H_Rate_Class=$B58)*[5]Customer!D$129:D$238)} -> 0 | E58: {=SUMPRODUCT((H_Rate_Class=$B58)*[5]Customer!E$129:E$238)} -> 0 | F58: {=SUMPRODUCT((H_Rate_Class=$B58)*[5]Customer!F$129:F$238)} -> 0 | G58: {=SUMPRODUCT((H_Rate_Class=$B58)*[5]Customer!G$129:G$238)} -> 0 | H58: {=SUMPRODUCT((H_Rate_Class=$B58)*[5]Customer!H$129:H$238)} -> 0 | I58: {=SUMPRODUCT((H_Rate_Class=$B58)*[5]Customer!I$129:I$238)} -> 0 | J58: {=SUMPRODUCT((H_Rate_Class=$B58)*[5]Customer!J$129:J$238)} -> 0 | K58: {=SUMPRODUCT((H_Rate_Class=$B58)*[5]Customer!K$129:K$238)} -> 0 | ... O58: {=SUMPRODUCT((H_Rate_Class=$B58)*[5]Customer!O$129:O$238)} -> 0 | P58: =SUM(D58:O58) -> 0 | Q58: =P58/12 -> 0
A59: =A25 -> 9 | B59: =B25 -> PRIMARY SUB 4CP | C59: =C25 -> PRI | D59: {=SUMPRODUCT((H_Rate_Class=$B59)*[5]Customer!D$129:D$238)} -> 0 | E59: {=SUMPRODUCT((H_Rate_Class=$B59)*[5]Customer!E$129:E$238)} -> 0 | F59: {=SUMPRODUCT((H_Rate_Class=$B59)*[5]Customer!F$129:F$238)} -> 0 | G59: {=SUMPRODUCT((H_Rate_Class=$B59)*[5]Customer!G$129:G$238)} -> 0 | H59: {=SUMPRODUCT((H_Rate_Class=$B59)*[5]Customer!H$129:H$238)} -> 0 | I59: {=SUMPRODUCT((H_Rate_Class=$B59)*[5]Customer!I$129:I$238)} -> 0 | J59: {=SUMPRODUCT((H_Rate_Class=$B59)*[5]Customer!J$129:J$238)} -> 0 | K59: {=SUMPRODUCT((H_Rate_Class=$B59)*[5]Customer!K$129:K$238)} -> 0 | ... O59: {=SUMPRODUCT((H_Rate_Class=$B59)*[5]Customer!O$129:O$238)} -> 0 | P59: =SUM(D59:O59) -> 0 | Q59: =P59/12 -> 0
A60: =A26 -> 10 | B60: =B26 -> TOTAL PRIMARY | D60: =SUM(D56:D59) -> 10 | E60: =SUM(E56:E59) -> -3 | F60: =SUM(F56:F59) -> -8 | G60: =SUM(G56:G59) -> -4 | H60: =SUM(H56:H59) -> -11 | I60: =SUM(I56:I59) -> -4 | J60: =SUM(J56:J59) -> -2 | K60: =SUM(K56:K59) -> -18 | ... O60: =SUM(O56:O59) -> 0 | P60: =SUM(D60:O60) -> -77 | Q60: =SUM(Q56:Q59) -> -6.4166667
A62: =A28 -> 11 | B62: =B28 -> TRANSMISSION | C62: =C28 -> TRA | D62: {=SUMPRODUCT((H_Rate_Class=$B62)*[5]Customer!D$129:D$238)} -> -1 | E62: {=SUMPRODUCT((H_Rate_Class=$B62)*[5]Customer!E$129:E$238)} -> 2 | F62: {=SUMPRODUCT((H_Rate_Class=$B62)*[5]Customer!F$129:F$238)} -> 4 | G62: {=SUMPRODUCT((H_Rate_Class=$B62)*[5]Customer!G$129:G$238)} -> 1 | H62: {=SUMPRODUCT((H_Rate_Class=$B62)*[5]Customer!H$129:H$238)} -> 1 | I62: {=SUMPRODUCT((H_Rate_Class=$B62)*[5]Customer!I$129:I$238)} -> -1 | J62: {=SUMPRODUCT((H_Rate_Class=$B62)*[5]Customer!J$129:J$238)} -> 1 | K62: {=SUMPRODUCT((H_Rate_Class=$B62)*[5]Customer!K$129:K$238)} -> -4 | ... O62: {=SUMPRODUCT((H_Rate_Class=$B62)*[5]Customer!O$129:O$238)} -> 0 | P62: =SUM(D62:O62) -> -14 | Q62: =P62/12 -> -1.1666667
A64: =A30 -> 12 | B64: =B30 -> LIGHTING | C64: =C30 -> SEC | D64: {=SUMPRODUCT((H_Rate_Class=$B64)*[5]Customer!D$129:D$238)} -> -424 | E64: {=SUMPRODUCT((H_Rate_Class=$B64)*[5]Customer!E$129:E$238)} -> -1305 | F64: {=SUMPRODUCT((H_Rate_Class=$B64)*[5]Customer!F$129:F$238)} -> -421 | G64: {=SUMPRODUCT((H_Rate_Class=$B64)*[5]Customer!G$129:G$238)} -> 430 | H64: {=SUMPRODUCT((H_Rate_Class=$B64)*[5]Customer!H$129:H$238)} -> -1776 | I64: {=SUMPRODUCT((H_Rate_Class=$B64)*[5]Customer!I$129:I$238)} -> 571 | J64: {=SUMPRODUCT((H_Rate_Class=$B64)*[5]Customer!J$129:J$238)} -> -334 | K64: {=SUMPRODUCT((H_Rate_Class=$B64)*[5]Customer!K$129:K$238)} -> -853 | ... O64: {=SUMPRODUCT((H_Rate_Class=$B64)*[5]Customer!O$129:O$238)} -> 0 | P64: =SUM(D64:O64) -> -6271 | Q64: =P64/12 -> -522.58333
A66: =A32 -> 13 | B66: =B32 -> TOTAL RETAIL | D66: =D64+D62+D60+D54+D50+D48 -> 18945 | E66: =E64+E62+E60+E54+E50+E48 -> 16740 | F66: =F64+F62+F60+F54+F50+F48 -> 16733 | G66: =G64+G62+G60+G54+G50+G48 -> 16523 | H66: =H64+H62+H60+H54+H50+H48 -> 12932 | I66: =I64+I62+I60+I54+I50+I48 -> 13927 | J66: =J64+J62+J60+J54+J50+J48 -> 10939 | K66: =K64+K62+K60+K54+K50+K48 -> 5420 | ... M66: =M64+M62+M60+M54+M50+M48 -> -747 | N66: =N64+N62+N60+N54+N50+N153+N48 -> -1331.0007 | O66: =O64+O62+O60+O54+O50+O48 -> 0 | P66: =SUM(D66:O66) -> 113064 | Q66: =P66/12 -> 9421.9999
A68: =A34 -> 14 | B68: =B34 -> WHOLESALE PRI | C68: =C34 -> PRI
A69: =A35 -> 15 | B69: =B35 -> WHOLESALE TRANS | C69: =C35 -> TRA
A70: =A36 -> 16 | B70: =B36 -> TOTAL WHOLESALE | D70: =SUM(D68:D69) -> 0 | E70: =SUM(E68:E69) -> 0 | F70: =SUM(F68:F69) -> 0 | G70: =SUM(G68:G69) -> 0 | H70: =SUM(H68:H69) -> 0 | I70: =SUM(I68:I69) -> 0 | J70: =SUM(J68:J69) -> 0 | K70: =SUM(K68:K69) -> 0 | ... O70: =SUM(O68:O69) -> 0 | P70: =SUM(D70:O70) -> 0 | Q70: =P70/12 -> 0
A72: =A38 -> 17 | B72: =B38 -> TOTAL AEP TEXAS | D72: =+D70+D66 -> 18945 | E72: =+E70+E66 -> 16740 | F72: =+F70+F66 -> 16733 | G72: =+G70+G66 -> 16523 | H72: =+H70+H66 -> 12932 | I72: =+I70+I66 -> 13927 | J72: =+J70+J66 -> 10939 | K72: =+K70+K66 -> 5420 | ... O72: =+O70+O66 -> 0 | P72: =SUM(D72:O72) -> 113064 | Q72: =P72/12 -> 9421.9999
B74: =+B39 -> Note: Secondary < 10 kW includes Unmetered service; Lighting customers are fixture counts.
B76: =+B41 -> AEP TEXAS
B77: OTHER CUSTOMER COUNT ADJUSTMENT
B78: =B9 -> FOR TEST YEAR ENDED SEPTEMBER 30, 2023
D80: =D45 -> 0 | G80: =G45 -> 0
A81: LINE | B81: DESCRIPTION | C81: VOLT | D81: =+D46 -> Oct-22 | E81: =+E46 -> Nov-22 | F81: =+F46 -> Dec-22 | G81: =+G46 -> Jan-23 | H81: =+H46 -> Feb-23 | I81: =+I46 -> Mar-23 | J81: =+J46 -> Apr-23 | K81: =+K46 -> May-23 | ... O81: =+O46 -> Sep-23 | P81: TOTAL | Q81: AVERAGE
A83: 1 | B83: RESIDENTIAL SERVICE | C83: SEC | D83: {=SUMPRODUCT((H_Rate_Class=$B83)*[5]Customer!D$249:D$358)} -> 0 | E83: {=SUMPRODUCT((H_Rate_Class=$B83)*[5]Customer!E$249:E$358)} -> 0 | F83: {=SUMPRODUCT((H_Rate_Class=$B83)*[5]Customer!F$249:F$358)} -> 0 | G83: {=SUMPRODUCT((H_Rate_Class=$B83)*[5]Customer!G$249:G$358)} -> 0 | H83: {=SUMPRODUCT((H_Rate_Class=$B83)*[5]Customer!H$249:H$358)} -> 0 | I83: {=SUMPRODUCT((H_Rate_Class=$B83)*[5]Customer!I$249:I$358)} -> 0 | J83: {=SUMPRODUCT((H_Rate_Class=$B83)*[5]Customer!J$249:J$358)} -> 0 | K83: {=SUMPRODUCT((H_Rate_Class=$B83)*[5]Customer!K$249:K$358)} -> 0 | ... O83: {=SUMPRODUCT((H_Rate_Class=$B83)*[5]Customer!O$249:O$358)} -> 0 | P83: =SUM(D83:O83) -> 0 | Q83: =P83/12 -> 0
A85: 2 | B85: SECONDARY < 10 kW | C85: SEC | D85: {=SUMPRODUCT((H_Rate_Class=$B85)*[5]Customer!D$249:D$358)} -> 0 | E85: {=SUMPRODUCT((H_Rate_Class=$B85)*[5]Customer!E$249:E$358)} -> 0 | F85: {=SUMPRODUCT((H_Rate_Class=$B85)*[5]Customer!F$249:F$358)} -> 0 | G85: {=SUMPRODUCT((H_Rate_Class=$B85)*[5]Customer!G$249:G$358)} -> 0 | H85: {=SUMPRODUCT((H_Rate_Class=$B85)*[5]Customer!H$249:H$358)} -> 0 | I85: {=SUMPRODUCT((H_Rate_Class=$B85)*[5]Customer!I$249:I$358)} -> 0 | J85: {=SUMPRODUCT((H_Rate_Class=$B85)*[5]Customer!J$249:J$358)} -> 0 | K85: {=SUMPRODUCT((H_Rate_Class=$B85)*[5]Customer!K$249:K$358)} -> 0 | ... O85: {=SUMPRODUCT((H_Rate_Class=$B85)*[5]Customer!O$249:O$358)} -> 0 | P85: =SUM(D85:O85) -> 0 | Q85: =P85/12 -> 0
A87: 3 | B87: SECONDARY > 10 kW NCP | C87: SEC | D87: {=SUMPRODUCT((H_Rate_Class=$B87)*[5]Customer!D$249:D$358)} -> 0 | E87: {=SUMPRODUCT((H_Rate_Class=$B87)*[5]Customer!E$249:E$358)} -> 0 | F87: {=SUMPRODUCT((H_Rate_Class=$B87)*[5]Customer!F$249:F$358)} -> 0 | G87: {=SUMPRODUCT((H_Rate_Class=$B87)*[5]Customer!G$249:G$358)} -> 0 | H87: {=SUMPRODUCT((H_Rate_Class=$B87)*[5]Customer!H$249:H$358)} -> 0 | I87: {=SUMPRODUCT((H_Rate_Class=$B87)*[5]Customer!I$249:I$358)} -> 0 | J87: {=SUMPRODUCT((H_Rate_Class=$B87)*[5]Customer!J$249:J$358)} -> 0 | K87: {=SUMPRODUCT((H_Rate_Class=$B87)*[5]Customer!K$249:K$358)} -> 0 | ... O87: {=SUMPRODUCT((H_Rate_Class=$B87)*[5]Customer!O$249:O$358)} -> 0 | P87: =SUM(D87:O87) -> 0 | Q87: =P87/12 -> 0
A88: 4 | B88: SECONDARY > 10 kW 4CP | C88: SEC | D88: {=SUMPRODUCT((H_Rate_Class=$B88)*[5]Customer!D$249:D$358)} -> 0 | E88: {=SUMPRODUCT((H_Rate_Class=$B88)*[5]Customer!E$249:E$358)} -> 0 | F88: {=SUMPRODUCT((H_Rate_Class=$B88)*[5]Customer!F$249:F$358)} -> 0 | G88: {=SUMPRODUCT((H_Rate_Class=$B88)*[5]Customer!G$249:G$358)} -> 0 | H88: {=SUMPRODUCT((H_Rate_Class=$B88)*[5]Customer!H$249:H$358)} -> 0 | I88: {=SUMPRODUCT((H_Rate_Class=$B88)*[5]Customer!I$249:I$358)} -> 0 | J88: {=SUMPRODUCT((H_Rate_Class=$B88)*[5]Customer!J$249:J$358)} -> 0 | K88: {=SUMPRODUCT((H_Rate_Class=$B88)*[5]Customer!K$249:K$358)} -> 0 | ... O88: {=SUMPRODUCT((H_Rate_Class=$B88)*[5]Customer!O$249:O$358)} -> 0 | P88: =SUM(D88:O88) -> 0 | Q88: =P88/12 -> 0
A89: 5 | B89: TOTAL SECONDARY > 10 kW | D89: =SUM(D87:D88) -> 0 | E89: =SUM(E87:E88) -> 0 | F89: =SUM(F87:F88) -> 0 | G89: =SUM(G87:G88) -> 0 | H89: =SUM(H87:H88) -> 0 | I89: =SUM(I87:I88) -> 0 | J89: =SUM(J87:J88) -> 0 | K89: =SUM(K87:K88) -> 0 | ... O89: =SUM(O87:O88) -> 0 | P89: =SUM(D89:O89) -> 0 | Q89: =SUM(Q87:Q88) -> 0
A91: 6 | B91: PRIMARY NCP | C91: PRI | D91: {=SUMPRODUCT((H_Rate_Class=$B91)*[5]Customer!D$249:D$358)} -> 0 | E91: {=SUMPRODUCT((H_Rate_Class=$B91)*[5]Customer!E$249:E$358)} -> 0 | F91: {=SUMPRODUCT((H_Rate_Class=$B91)*[5]Customer!F$249:F$358)} -> 0 | G91: {=SUMPRODUCT((H_Rate_Class=$B91)*[5]Customer!G$249:G$358)} -> 0 | H91: {=SUMPRODUCT((H_Rate_Class=$B91)*[5]Customer!H$249:H$358)} -> 0 | I91: {=SUMPRODUCT((H_Rate_Class=$B91)*[5]Customer!I$249:I$358)} -> 0 | J91: {=SUMPRODUCT((H_Rate_Class=$B91)*[5]Customer!J$249:J$358)} -> 0 | K91: {=SUMPRODUCT((H_Rate_Class=$B91)*[5]Customer!K$249:K$358)} -> 0 | ... O91: {=SUMPRODUCT((H_Rate_Class=$B91)*[5]Customer!O$249:O$358)} -> 0 | P91: =SUM(D91:O91) -> 0 | Q91: =P91/12 -> 0
A92: 7 | B92: PRIMARY 4CP | C92: PRI | D92: {=SUMPRODUCT((H_Rate_Class=$B92)*[5]Customer!D$249:D$358)} -> 0 | E92: {=SUMPRODUCT((H_Rate_Class=$B92)*[5]Customer!E$249:E$358)} -> 0 | F92: {=SUMPRODUCT((H_Rate_Class=$B92)*[5]Customer!F$249:F$358)} -> 0 | G92: {=SUMPRODUCT((H_Rate_Class=$B92)*[5]Customer!G$249:G$358)} -> 0 | H92: {=SUMPRODUCT((H_Rate_Class=$B92)*[5]Customer!H$249:H$358)} -> 0 | I92: {=SUMPRODUCT((H_Rate_Class=$B92)*[5]Customer!I$249:I$358)} -> 0 | J92: {=SUMPRODUCT((H_Rate_Class=$B92)*[5]Customer!J$249:J$358)} -> 0 | K92: {=SUMPRODUCT((H_Rate_Class=$B92)*[5]Customer!K$249:K$358)} -> 0 | ... O92: {=SUMPRODUCT((H_Rate_Class=$B92)*[5]Customer!O$249:O$358)} -> 0 | P92: =SUM(D92:O92) -> 0 | Q92: =P92/12 -> 0
A93: 8 | B93: PRIMARY SUB NCP | C93: PRI | D93: {=SUMPRODUCT((H_Rate_Class=$B93)*[5]Customer!D$249:D$358)} -> 0 | E93: {=SUMPRODUCT((H_Rate_Class=$B93)*[5]Customer!E$249:E$358)} -> 0 | F93: {=SUMPRODUCT((H_Rate_Class=$B93)*[5]Customer!F$249:F$358)} -> 0 | G93: {=SUMPRODUCT((H_Rate_Class=$B93)*[5]Customer!G$249:G$358)} -> 0 | H93: {=SUMPRODUCT((H_Rate_Class=$B93)*[5]Customer!H$249:H$358)} -> 0 | I93: {=SUMPRODUCT((H_Rate_Class=$B93)*[5]Customer!I$249:I$358)} -> 0 | J93: {=SUMPRODUCT((H_Rate_Class=$B93)*[5]Customer!J$249:J$358)} -> 0 | K93: {=SUMPRODUCT((H_Rate_Class=$B93)*[5]Customer!K$249:K$358)} -> 0 | ... O93: {=SUMPRODUCT((H_Rate_Class=$B93)*[5]Customer!O$249:O$358)} -> 0 | P93: =SUM(D93:O93) -> 0 | Q93: =P93/12 -> 0
A94: 9 | B94: PRIMARY SUB 4CP | C94: PRI | P94: =SUM(D94:O94) -> 0 | Q94: =P94/12 -> 0
A95: 10 | B95: TOTAL PRIMARY | D95: =SUM(D91:D92) -> 0 | E95: =SUM(E91:E92) -> 0 | F95: =SUM(F91:F92) -> 0 | G95: =SUM(G91:G92) -> 0 | H95: =SUM(H91:H92) -> 0 | I95: =SUM(I91:I92) -> 0 | J95: =SUM(J91:J92) -> 0 | K95: =SUM(K91:K92) -> 0 | ... N95: =SUM(N91:N92) -> 0 | P95: =SUM(D95:O95) -> 0 | Q95: =SUM(Q91:Q92) -> 0
A97: 11 | B97: TRANSMISSION | C97: TRA | D97: {=SUMPRODUCT((H_Rate_Class=$B97)*[5]Customer!D$249:D$358)} -> 0 | E97: {=SUMPRODUCT((H_Rate_Class=$B97)*[5]Customer!E$249:E$358)} -> 0 | F97: {=SUMPRODUCT((H_Rate_Class=$B97)*[5]Customer!F$249:F$358)} -> 0 | G97: {=SUMPRODUCT((H_Rate_Class=$B97)*[5]Customer!G$249:G$358)} -> 0 | H97: {=SUMPRODUCT((H_Rate_Class=$B97)*[5]Customer!H$249:H$358)} -> 0 | I97: {=SUMPRODUCT((H_Rate_Class=$B97)*[5]Customer!I$249:I$358)} -> 0 | J97: {=SUMPRODUCT((H_Rate_Class=$B97)*[5]Customer!J$249:J$358)} -> 0 | K97: {=SUMPRODUCT((H_Rate_Class=$B97)*[5]Customer!K$249:K$358)} -> 0 | ... O97: {=SUMPRODUCT((H_Rate_Class=$B97)*[5]Customer!O$249:O$358)} -> 0 | P97: =SUM(D97:O97) -> 0 | Q97: =P97/12 -> 0
A99: 12 | B99: LIGHTING | C99: SEC | D99: {=SUMPRODUCT((H_Rate_Class=$B99)*[5]Customer!D$249:D$358)} -> 0 | E99: {=SUMPRODUCT((H_Rate_Class=$B99)*[5]Customer!E$249:E$358)} -> 0 | F99: {=SUMPRODUCT((H_Rate_Class=$B99)*[5]Customer!F$249:F$358)} -> 0 | G99: {=SUMPRODUCT((H_Rate_Class=$B99)*[5]Customer!G$249:G$358)} -> 0 | H99: {=SUMPRODUCT((H_Rate_Class=$B99)*[5]Customer!H$249:H$358)} -> 0 | I99: {=SUMPRODUCT((H_Rate_Class=$B99)*[5]Customer!I$249:I$358)} -> 0 | J99: {=SUMPRODUCT((H_Rate_Class=$B99)*[5]Customer!J$249:J$358)} -> 0 | K99: {=SUMPRODUCT((H_Rate_Class=$B99)*[5]Customer!K$249:K$358)} -> 0 | ... O99: {=SUMPRODUCT((H_Rate_Class=$B99)*[5]Customer!O$249:O$358)} -> 0 | Q99: =P99/12 -> 0
A101: 13 | B101: TOTAL RETAIL | D101: =D99+D97+D95+D89+D85+D83 -> 0 | E101: =E99+E97+E95+E89+E85+E83 -> 0 | F101: =F99+F97+F95+F89+F85+F83 -> 0 | G101: =G99+G97+G95+G89+G85+G83 -> 0 | H101: =H99+H97+H95+H89+H85+H83 -> 0 | I101: =I99+I97+I95+I89+I85+I83 -> 0 | J101: =J99+J97+J95+J89+J85+J83 -> 0 | K101: =K99+K97+K95+K89+K85+K83 -> 0 | ... O101: =O99+O97+O95+O89+O85+O83 -> 0 | P101: =SUM(D101:O101) -> 0 | Q101: =P101/12 -> 0
A103: 14 | B103: WHOLESALE PRI | C103: PRI | P103: =SUM(D103:O103) -> 0 | Q103: =P103/12 -> 0
A104: 15 | B104: WHOLESALE TRANS | C104: TRA | P104: =SUM(D104:O104) -> 0 | Q104: =P104/12 -> 0
A105: 16 | B105: TOTAL WHOLESALE | D105: =SUM(D103:D104) -> 0 | E105: =SUM(E103:E104) -> 0 | F105: =SUM(F103:F104) -> 0 | G105: =SUM(G103:G104) -> 0 | H105: =SUM(H103:H104) -> 0 | I105: =SUM(I103:I104) -> 0 | J105: =SUM(J103:J104) -> 0 | K105: =SUM(K103:K104) -> 0 | ... O105: =SUM(O103:O104) -> 0 | P105: =SUM(D105:O105) -> 0 | Q105: =P105/12 -> 0
A107: 17 | B107: TOTAL AEP TEXAS | D107: =D105+D101 -> 0 | E107: =+E105+E101 -> 0 | F107: =+F105+F101 -> 0 | G107: =+G105+G101 -> 0 | H107: =+H105+H101 -> 0 | I107: =+I105+I101 -> 0 | J107: =+J105+J101 -> 0 | K107: =+K105+K101 -> 0 | L107: =+L105+L101 -> 0 | ... O107: =+O105+O101 -> 0 | P107: =SUM(D107:O107) -> 0 | Q107: =P107/12 -> 0
B109: =+B39 -> Note: Secondary < 10 kW includes Unmetered service; Lighting customers are fixture counts.
B111: =+B41 -> AEP TEXAS
B112: ADJUSTED CUSTOMER COUNT
B113: =B9 -> FOR TEST YEAR ENDED SEPTEMBER 30, 2023
B114: II-H-3.2 | D114: =+D11 -> 0 | G114: =G11 -> 0
A115: Line | B115: DESCRIPTION | C115: VOLT | D115: =+D12 -> Oct-22 | E115: =+E12 -> Nov-22 | F115: =+F12 -> Dec-22 | G115: =+G12 -> Jan-23 | H115: =+H12 -> Feb-23 | I115: =+I12 -> Mar-23 | J115: =+J12 -> Apr-23 | K115: =+K12 -> May-23 | ... P115: =+P12 -> TOTAL | Q115: AVERAGE
A117: 1 | B117: RESIDENTIAL SERVICE | C117: SEC | D117: =D48+D14+D83 -> 935238 | E117: =E48+E14+E83 -> 935238 | F117: =F48+F14+F83 -> 935238 | G117: =G48+G14+G83 -> 935238 | H117: =H48+H14+H83 -> 935238 | I117: =I48+I14+I83 -> 935238 | J117: =J48+J14+J83 -> 935238 | K117: =K48+K14+K83 -> 935238 | ... O117: =O48+O14+O83 -> 935238 | P117: =SUM(D117:O117) -> 11222856 | Q117: =P117/12 -> 935238
A119: 2 | B119: SECONDARY < 10 kW | C119: SEC | D119: =D50+D16+D85 -> 99366 | E119: =E50+E16+E85 -> 99366 | F119: =F50+F16+F85 -> 99366 | G119: =G50+G16+G85 -> 99366 | H119: =H50+H16+H85 -> 99366 | I119: =I50+I16+I85 -> 99366 | J119: =J50+J16+J85 -> 99366 | K119: =K50+K16+K85 -> 99366 | ... O119: =O50+O16+O85 -> 99366 | P119: =SUM(D119:O119) -> 1192392 | Q119: =P119/12 -> 99366
A121: 3 | B121: SECONDARY > 10 kW NCP | C121: SEC | D121: =D52+D18+D87 -> 71833 | E121: =E52+E18+E87 -> 71833 | F121: =F52+F18+F87 -> 71833 | G121: =G52+G18+G87 -> 71833 | H121: =H52+H18+H87 -> 71833 | I121: =I52+I18+I87 -> 71833 | J121: =J52+J18+J87 -> 71833 | K121: =K52+K18+K87 -> 71833 | ... O121: =O52+O18+O87 -> 71833 | P121: =SUM(D121:O121) -> 861996 | Q121: =P121/12 -> 71833
A122: 4 | B122: SECONDARY > 10 kW 4CP | C122: SEC | D122: =D53+D19+D88 -> 576 | E122: =E53+E19+E88 -> 576 | F122: =F53+F19+F88 -> 576 | G122: =G53+G19+G88 -> 576 | H122: =H53+H19+H88 -> 576 | I122: =I53+I19+I88 -> 576 | J122: =J53+J19+J88 -> 576 | K122: =K53+K19+K88 -> 576 | ... O122: =O53+O19+O88 -> 576 | P122: =SUM(D122:O122) -> 6912 | Q122: =P122/12 -> 576
A123: 5 | B123: TOTAL SECONDARY > 10 kW | D123: =SUM(D121:D122) -> 72409 | E123: =SUM(E121:E122) -> 72409 | F123: =SUM(F121:F122) -> 72409 | G123: =SUM(G121:G122) -> 72409 | H123: =SUM(H121:H122) -> 72409 | I123: =SUM(I121:I122) -> 72409 | J123: =SUM(J121:J122) -> 72409 | K123: =SUM(K121:K122) -> 72409 | ... O123: =SUM(O121:O122) -> 72409 | P123: =SUM(D123:O123) -> 868908 | Q123: =P123/12 -> 72409
A125: 6 | B125: PRIMARY NCP | C125: PRI | D125: =D56+D22+D91 -> 550 | E125: =E56+E22+E91 -> 550 | F125: =F56+F22+F91 -> 550 | G125: =G56+G22+G91 -> 550 | H125: =H56+H22+H91 -> 550 | I125: =I56+I22+I91 -> 550 | J125: =J56+J22+J91 -> 550 | K125: =K56+K22+K91 -> 550 | ... O125: =O56+O22+O91 -> 550 | P125: =SUM(D125:O125) -> 6600 | Q125: =P125/12 -> 550
A126: 7 | B126: PRIMARY 4CP | C126: PRI | D126: =D57+D23+D92 -> 469 | E126: =E57+E23+E92 -> 469 | F126: =F57+F23+F92 -> 469 | G126: =G57+G23+G92 -> 469 | H126: =H57+H23+H92 -> 469 | I126: =I57+I23+I92 -> 469 | J126: =J57+J23+J92 -> 469 | K126: =K57+K23+K92 -> 469 | ... O126: =O57+O23+O92 -> 469 | P126: =SUM(D126:O126) -> 5628 | Q126: =P126/12 -> 469
A127: 8 | B127: PRIMARY SUB NCP | C127: PRI | D127: =D58+D24+D93 -> 9 | E127: =E58+E24+E93 -> 9 | F127: =F58+F24+F93 -> 9 | G127: =G58+G24+G93 -> 9 | H127: =H58+H24+H93 -> 9 | I127: =I58+I24+I93 -> 9 | J127: =J58+J24+J93 -> 9 | K127: =K58+K24+K93 -> 9 | ... O127: =O58+O24+O93 -> 9 | P127: =SUM(D127:O127) -> 108 | Q127: =P127/12 -> 9
A128: 9 | B128: PRIMARY SUB 4CP | C128: PRI | D128: =D59+D25+D94 -> 58 | E128: =E59+E25+E94 -> 58 | F128: =F59+F25+F94 -> 58 | G128: =G59+G25+G94 -> 58 | H128: =H59+H25+H94 -> 58 | I128: =I59+I25+I94 -> 58 | J128: =J59+J25+J94 -> 58 | K128: =K59+K25+K94 -> 58 | ... O128: =O59+O25+O94 -> 58 | P128: =SUM(D128:O128) -> 696 | Q128: =P128/12 -> 58
A129: 10 | B129: TOTAL PRIMARY | D129: =SUM(D125:D128) -> 1086 | E129: =SUM(E125:E128) -> 1086 | F129: =SUM(F125:F128) -> 1086 | G129: =SUM(G125:G128) -> 1086 | H129: =SUM(H125:H128) -> 1086 | I129: =SUM(I125:I128) -> 1086 | J129: =SUM(J125:J128) -> 1086 | K129: =SUM(K125:K128) -> 1086 | ... P129: =SUM(P125:P128) -> 13032 | Q129: =P129/12 -> 1086
A131: 11 | B131: TRANSMISSION | C131: TRA | D131: =D62+D28+D97 -> 123 | E131: =E62+E28+E97 -> 123 | F131: =F62+F28+F97 -> 123 | G131: =G62+G28+G97 -> 123 | H131: =H62+H28+H97 -> 123 | I131: =I62+I28+I97 -> 123 | J131: =J62+J28+J97 -> 123 | K131: =K62+K28+K97 -> 123 | ... O131: =O62+O28+O97 -> 123 | P131: =SUM(D131:O131) -> 1476 | Q131: =P131/12 -> 123
A133: 12 | B133: LIGHTING | C133: SEC | D133: =D64+D30+D99 -> 221390 | E133: =E64+E30+E99 -> 221390 | F133: =F64+F30+F99 -> 221390 | G133: =G64+G30+G99 -> 221390 | H133: =H64+H30+H99 -> 221390 | I133: =I64+I30+I99 -> 221390 | J133: =J64+J30+J99 -> 221390 | K133: =K64+K30+K99 -> 221390 | ... O133: =O64+O30+O99 -> 221390 | P133: =SUM(D133:O133) -> 2656680 | Q133: =P133/12 -> 221390
A135: 13 | B135: TOTAL RETAIL | D135: =D133+D131+D129+D123+D119+D117 -> 1329612 | E135: =E133+E131+E129+E123+E119+E117 -> 1329612 | F135: =F133+F131+F129+F123+F119+F117 -> 1329612 | G135: =G133+G131+G129+G123+G119+G117 -> 1329612 | H135: =H133+H131+H129+H123+H119+H117 -> 1329612 | I135: =I133+I131+I129+I123+I119+I117 -> 1329612 | J135: =J133+J131+J129+J123+J119+J117 -> 1329612 | K135: =K133+K131+K129+K123+K119+K117 -> 1329612 | ... O135: =O133+O131+O129+O123+O119+O117 -> 1329612 | P135: =SUM(D135:O135) -> 15955344 | Q135: =P135/12 -> 1329612
A137: 14 | B137: WHOLESALE PRI | C137: PRI | D137: =D68+D34 -> 0 | E137: =E68+E34 -> 0 | F137: =F68+F34 -> 0 | G137: =G68+G34 -> 0 | H137: =H68+H34 -> 0 | I137: =I68+I34 -> 0 | J137: =J68+J34 -> 0 | K137: =K68+K34 -> 0 | ... O137: =O68+O34 -> 0 | P137: =SUM(D137:O137) -> 0 | Q137: =P137/12 -> 0
A138: 15 | B138: WHOLESALE TRANS | C138: TRA | P138: =SUM(D138:O138) -> 0 | Q138: =P138/12 -> 0
A139: 16 | B139: TOTAL WHOLESALE | D139: =SUM(D137:D138) -> 0 | E139: =SUM(E137:E138) -> 0 | F139: =SUM(F137:F138) -> 0 | G139: =SUM(G137:G138) -> 0 | H139: =SUM(H137:H138) -> 0 | I139: =SUM(I137:I138) -> 0 | J139: =SUM(J137:J138) -> 0 | K139: =SUM(K137:K138) -> 0 | ... O139: =SUM(O137:O138) -> 0 | P139: =SUM(D139:O139) -> 0 | Q139: =P139/12 -> 0
A141: 17 | B141: TOTAL AEP TEXAS | D141: =+D139+D135 -> 1329612 | E141: =+E139+E135 -> 1329612 | F141: =+F139+F135 -> 1329612 | G141: =+G139+G135 -> 1329612 | H141: =+H139+H135 -> 1329612 | I141: =+I139+I135 -> 1329612 | J141: =+J139+J135 -> 1329612 | K141: =+K139+K135 -> 1329612 | ... O141: =+O139+O135 -> 1329612 | P141: =SUM(D141:O141) -> 15955344 | Q141: =P141/12 -> 1329612
B143: =+B39 -> Note: Secondary < 10 kW includes Unmetered service; Lighting customers are fixture counts.
B146: =+B7 -> AEP TEXAS
B147: CUSTOMER COUNT ADJUSTMENT FACTOR
B148: =B9 -> FOR TEST YEAR ENDED SEPTEMBER 30, 2023
...

Sheet II-H-4.1 Monthly
B2: PUBLIC UTILITY COMMISSION OF TEXAS
B3: AEP TEXAS INC
B4: II-H-4.1 REVENUE IMPACTS MONTHLY
B5: ='II-H-3.1-3'!B5 -> TEST YEAR ENDING 9/30/2023
B6: =+'II-H-1'!B6 -> DOCKET 56165
B8: AEP TEXAS
B9: UNADJUSTED BILLED REVENUE
B10: FOR TEST YEAR ENDED SEPTEMBER 30, 2023
D11: 5 | E11: 6 | F11: 7 | G11: 8 | H11: 9 | I11: 10 | J11: 11 | K11: 12 | L11: 13 | M11: 14 | N11: 15 | O11: 16
A13: LINE | B13: DESCRIPTION | C13: VOLT | D13: ='II-H-3.1-3'!D12 -> Oct-22 | E13: ='II-H-3.1-3'!E12 -> Nov-22 | F13: ='II-H-3.1-3'!F12 -> Dec-22 | G13: ='II-H-3.1-3'!G12 -> Jan-23 | H13: ='II-H-3.1-3'!H12 -> Feb-23 | I13: ='II-H-3.1-3'!I12 -> Mar-23 | J13: ='II-H-3.1-3'!J12 -> Apr-23 | K13: ='II-H-3.1-3'!K12 -> May-23 | ... O13: ='II-H-3.1-3'!O12 -> Sep-23 | P13: TOTAL
A15: 1 | B15: RESIDENTIAL SERVICE | C15: SEC | D15: 56425580 | E15: 44601434 | F15: 51081571 | G15: 54442758 | H15: 48394601 | I15: 38431846 | J15: 37998133 | K15: 41079166 | L15: 53959354 | M15: 69030332 | N15: 69605383 | O15: 83420626 | P15: =SUM(D15:O15) -> 6.4847078e+08
A17: 2 | B17: SECONDARY < 10 kW | C17: SEC | D17: 3290499.5 | E17: 2982371.1 | F17: 3115337.3 | G17: 3134083.5 | H17: 2908578.4 | I17: 2852572.8 | J17: 2848318.7 | K17: 2967369.7 | L17: 3325482 | M17: 3775007.9 | N17: 3875852.2 | O17: 4332345.5 | P17: =SUM(D17:O17) -> 39407819
A19: 3 | B19: SECONDARY > 10 kW NCP | C19: SEC | D19: 27415277 | E19: 26622320 | F19: 27540490 | G19: 27940911 | H19: 27840854 | I19: 26036947 | J19: 25481203 | K19: 25209442 | L19: 26480058 | M19: 28017106 | N19: 28378038 | O19: 30857212 | P19: =SUM(D19:O19) -> 3.2781986e+08
A20: 4 | B20: SECONDARY > 10 kW 4CP | C20: SEC | D20: 3439438.2 | E20: 3354056.8 | F20: 3326930.7 | G20: 3194064.7 | H20: 3113972.2 | I20: 3034245.7 | J20: 3060922.5 | K20: 3062978.1 | L20: 3211856 | M20: 3329063.6 | N20: 3481281 | O20: 3791890.9 | P20: =SUM(D20:O20) -> 39400700
A21: 5 | B21: TOTAL SECONDARY > 10 kW | D21: =SUM(D19:D20) -> 30854715 | E21: =SUM(E19:E20) -> 29976377 | F21: =SUM(F19:F20) -> 30867420 | G21: =SUM(G19:G20) -> 31134976 | H21: =SUM(H19:H20) -> 30954826 | I21: =SUM(I19:I20) -> 29071192 | J21: =SUM(J19:J20) -> 28542125 | K21: =SUM(K19:K20) -> 28272420 | ... P21: =SUM(P19:P20) -> 3.6722056e+08
A23: 6 | B23: PRIMARY NCP | C23: PRI | D23: =584355.83-D25 -> 569597.3 | E23: =600062.04-E25 -> 586768.88 | F23: =605611.34-F25 -> 592974.94 | G23: =584201.35-G25 -> 571817.45 | H23: =597124.06-H25 -> 584652.52 | I23: =568938.52-I25 -> 557524.27 | J23: =589184.42-J25 -> 577422.65 | K23: =592425.87-K25 -> 579676.47 | L23: =555871.09-L25 -> 543175.2 | M23: =611473.68-M25 -> 598841.47 | N23: =573060.08-N25 -> 560488.82 | O23: =625239.3-O25 -> 611742.9 | P23: =SUM(D23:O23) -> 6934682.9
A24: 7 | B24: PRIMARY 4CP | C24: PRI | D24: =7538118.02-D26 -> 6054429.9 | E24: =7460604.66-E26 -> 5975983.3 | F24: =7465778.22-F26 -> 5991397.9 | G24: =7482120.87-G26 -> 5961338.8 | H24: =7540518.99-H26 -> 6035698 | I24: =7468393.11-I26 -> 6024476.4 | J24: =7190599.96-J26 -> 5753850.8 | K24: =7325868.61-K26 -> 5939152.5 | L24: =7513156.01-L26 -> 6098734.3 | M24: =7549634.37-M26 -> 6174380.7 | N24: =7643794.46-N26 -> 6265912 | O24: =7655581.08-O26 -> 6244177.8 | P24: =SUM(D24:O24) -> 72519532
A25: 8 | B25: PRIMARY SUB NCP | C25: PRI | D25: =+'Primary Sub'!C6 -> 14758.53 | E25: =+'Primary Sub'!D6 -> 13293.16 | F25: =+'Primary Sub'!E6 -> 12636.4 | G25: =+'Primary Sub'!F6 -> 12383.9 | H25: =+'Primary Sub'!G6 -> 12471.54 | I25: =+'Primary Sub'!H6 -> 11414.25 | J25: =+'Primary Sub'!I6 -> 11761.77 | K25: =+'Primary Sub'!J6 -> 12749.4 | ... O25: =+'Primary Sub'!N6 -> 13496.4 | P25: =IF(SUM(D25:O25)='Primary Sub'!O6,SUM(D25:O25),0) -> 152864.71
A26: 9 | B26: PRIMARY SUB 4CP | C26: PRI | D26: =+'Primary Sub'!C7 -> 1483688.1 | E26: =+'Primary Sub'!D7 -> 1484621.4 | F26: =+'Primary Sub'!E7 -> 1474380.3 | G26: =+'Primary Sub'!F7 -> 1520782 | H26: =+'Primary Sub'!G7 -> 1504820.9 | I26: =+'Primary Sub'!H7 -> 1443916.7 | J26: =+'Primary Sub'!I7 -> 1436749.2 | K26: =+'Primary Sub'!J7 -> 1386716.1 | ... O26: =+'Primary Sub'!N7 -> 1411403.3 | P26: =IF(SUM(D26:O26)='Primary Sub'!O7,SUM(D26:O26),0) -> 17314636
A27: 10 | B27: TOTAL PRIMARY | D27: =SUM(D23:D26) -> 8122473.8 | E27: =SUM(E23:E26) -> 8060666.7 | F27: =SUM(F23:F26) -> 8071389.6 | G27: =SUM(G23:G26) -> 8066322.2 | H27: =SUM(H23:H26) -> 8137643.1 | I27: =SUM(I23:I26) -> 8037331.6 | J27: =SUM(J23:J26) -> 7779784.4 | K27: =SUM(K23:K26) -> 7918294.5 | ... P27: =SUM(P23:P26) -> 96921716
A29: 11 | B29: TRANSMISSION | C29: TRA | D29: 5580730.5 | E29: 5814365.7 | F29: 5595855.6 | G29: 6465557.5 | H29: 7059961.4 | I29: 5836392.2 | J29: 5282637.5 | K29: 4284472.4 | L29: 4980371.8 | M29: 5236512.5 | N29: 5177563.3 | O29: 4945189 | P29: =SUM(D29:O29) -> 66259609
A31: 12 | B31: LIGHTING | C31: SEC | D31: 2419720 | E31: 2431884.8 | F31: 2412705.2 | G31: 2414277 | H31: 2421519.7 | I31: 2403129.9 | J31: 2402975.8 | K31: 2402760.9 | L31: 2399047.2 | M31: 2407605.3 | N31: 2391978.4 | O31: 2542454.2 | P31: =SUM(D31:O31) -> 29050058
A33: 13 | B33: TOTAL RETAIL | D33: =D31+D29+D27+D21+D17+D15 -> 1.0669372e+08 | E33: =E31+E29+E27+E21+E17+E15 -> 93867099 | F33: =F31+F29+F27+F21+F17+F15 -> 1.0114428e+08 | G33: =G31+G29+G27+G21+G17+G15 -> 1.0565797e+08 | H33: =H31+H29+H27+H21+H17+H15 -> 99877130 | I33: =I31+I29+I27+I21+I17+I15 -> 86632465 | J33: =J31+J29+J27+J21+J17+J15 -> 84853975 | K33: =K31+K29+K27+K21+K17+K15 -> 86924483 | ... P33: =P31+P29+P27+P21+P17+P15 -> 1.2473305e+09
A35: 14 | B35: WHOLESALE PRI | C35: PRI | P35: =SUM(D35:O35) -> 0
A36: 15 | B36: WHOLESALE TRANS | C36: TRA | P36: =SUM(D36:O36) -> 0
A37: 16 | B37: TOTAL WHOLESALE | D37: =SUM(D35:D36) -> 0 | E37: =SUM(E35:E36) -> 0 | F37: =SUM(F35:F36) -> 0 | G37: =SUM(G35:G36) -> 0 | H37: =SUM(H35:H36) -> 0 | I37: =SUM(I35:I36) -> 0 | J37: =SUM(J35:J36) -> 0 | K37: =SUM(K35:K36) -> 0 | ... P37: =SUM(P35:P36) -> 0
A39: 17 | B39: TOTAL AEP TEXAS | D39: =+D37+D33 -> 1.0669372e+08 | E39: =+E37+E33 -> 93867099 | F39: =+F37+F33 -> 1.0114428e+08 | G39: =+G37+G33 -> 1.0565797e+08 | H39: =+H37+H33 -> 99877130 | I39: =+I37+I33 -> 86632465 | J39: =+J37+J33 -> 84853975 | K39: =+K37+K33 -> 86924483 | ... P39: =+P37+P33 -> 1.2473305e+09
B42: AEP TEXAS
B43: TTRAR RIDER ADJUSTMENT
B44: =B10 -> FOR TEST YEAR ENDED SEPTEMBER 30, 2023
B46: =Riders!C272 -> TTRAR
A47: LINE | B47: DESCRIPTION | C47: VOLT | D47: =+D13 -> Oct-22 | E47: =+E13 -> Nov-22 | F47: =+F13 -> Dec-22 | G47: =+G13 -> Jan-23 | H47: =+H13 -> Feb-23 | I47: =+I13 -> Mar-23 | J47: =+J13 -> Apr-23 | K47: =+K13 -> May-23 | ... O47: =+O13 -> Sep-23 | P47: TOTAL
A49: 1 | B49: RESIDENTIAL SERVICE | C49: SEC | D49: =-VLOOKUP(CONCATENATE($B$46,$B49),Riders!$A$12:$Q$357,'II-H-4.1 Monthly'!D$11,FALSE) -> -240172.01 | E49: =-VLOOKUP(CONCATENATE($B$46,$B49),Riders!$A$12:$Q$357,'II-H-4.1 Monthly'!E$11,FALSE) -> -185417.99 | F49: =-VLOOKUP(CONCATENATE($B$46,$B49),Riders!$A$12:$Q$357,'II-H-4.1 Monthly'!F$11,FALSE) -> -215773.04 | G49: =-VLOOKUP(CONCATENATE($B$46,$B49),Riders!$A$12:$Q$357,'II-H-4.1 Monthly'!G$11,FALSE) -> -231410.9 | H49: =-VLOOKUP(CONCATENATE($B$46,$B49),Riders!$A$12:$Q$357,'II-H-4.1 Monthly'!H$11,FALSE) -> -203666.94 | I49: =-VLOOKUP(CONCATENATE($B$46,$B49),Riders!$A$12:$Q$357,'II-H-4.1 Monthly'!I$11,FALSE) -> -186964.84 | J49: =-VLOOKUP(CONCATENATE($B$46,$B49),Riders!$A$12:$Q$357,'II-H-4.1 Monthly'!J$11,FALSE) -> -184233.9 | K49: =-VLOOKUP(CONCATENATE($B$46,$B49),Riders!$A$12:$Q$357,'II-H-4.1 Monthly'!K$11,FALSE) -> -201160.68 | ... O49: =-VLOOKUP(CONCATENATE($B$46,$B49),Riders!$A$12:$Q$357,'II-H-4.1 Monthly'!O$11,FALSE) -> -347687.62 | P49: =SUM(D49:O49) -> -2981645.4
A51: 2 | B51: SECONDARY < 10 kW | C51: SEC | D51: =-VLOOKUP(CONCATENATE($B$46,$B51),Riders!$A$12:$Q$357,'II-H-4.1 Monthly'!D$11,FALSE) -> -9738.37 | E51: =-VLOOKUP(CONCATENATE($B$46,$B51),Riders!$A$12:$Q$357,'II-H-4.1 Monthly'!E$11,FALSE) -> -8620.42 | F51: =-VLOOKUP(CONCATENATE($B$46,$B51),Riders!$A$12:$Q$357,'II-H-4.1 Monthly'!F$11,FALSE) -> -9141.16 | G51: =-VLOOKUP(CONCATENATE($B$46,$B51),Riders!$A$12:$Q$357,'II-H-4.1 Monthly'!G$11,FALSE) -> -9250.52 | H51: =-VLOOKUP(CONCATENATE($B$46,$B51),Riders!$A$12:$Q$357,'II-H-4.1 Monthly'!H$11,FALSE) -> -8471.09 | I51: =-VLOOKUP(CONCATENATE($B$46,$B51),Riders!$A$12:$Q$357,'II-H-4.1 Monthly'!I$11,FALSE) -> -8342.48 | J51: =-VLOOKUP(CONCATENATE($B$46,$B51),Riders!$A$12:$Q$357,'II-H-4.1 Monthly'!J$11,FALSE) -> -8296.32 | K51: =-VLOOKUP(CONCATENATE($B$46,$B51),Riders!$A$12:$Q$357,'II-H-4.1 Monthly'!K$11,FALSE) -> -8690.12 | ... O51: =-VLOOKUP(CONCATENATE($B$46,$B51),Riders!$A$12:$Q$357,'II-H-4.1 Monthly'!O$11,FALSE) -> -11865.33 | P51: =SUM(D51:O51) -> -115912.84
A53: 3 | B53: SECONDARY > 10 kW NCP | C53: SEC | D53: =-VLOOKUP(CONCATENATE($B$46,$B53),Riders!$A$12:$Q$357,'II-H-4.1 Monthly'!D$11,FALSE) -> -119411.68 | E53: =-VLOOKUP(CONCATENATE($B$46,$B53),Riders!$A$12:$Q$357,'II-H-4.1 Monthly'!E$11,FALSE) -> -116745.57 | F53: =-VLOOKUP(CONCATENATE($B$46,$B53),Riders!$A$12:$Q$357,'II-H-4.1 Monthly'!F$11,FALSE) -> -121510.78 | G53: =-VLOOKUP(CONCATENATE($B$46,$B53),Riders!$A$12:$Q$357,'II-H-4.1 Monthly'!G$11,FALSE) -> -123304.48 | H53: =-VLOOKUP(CONCATENATE($B$46,$B53),Riders!$A$12:$Q$357,'II-H-4.1 Monthly'!H$11,FALSE) -> -123424.46 | I53: =-VLOOKUP(CONCATENATE($B$46,$B53),Riders!$A$12:$Q$357,'II-H-4.1 Monthly'!I$11,FALSE) -> -121481.7 | J53: =-VLOOKUP(CONCATENATE($B$46,$B53),Riders!$A$12:$Q$357,'II-H-4.1 Monthly'!J$11,FALSE) -> -118411.5 | K53: =-VLOOKUP(CONCATENATE($B$46,$B53),Riders!$A$12:$Q$357,'II-H-4.1 Monthly'!K$11,FALSE) -> -116442.54 | ... O53: =-VLOOKUP(CONCATENATE($B$46,$B53),Riders!$A$12:$Q$357,'II-H-4.1 Monthly'!O$11,FALSE) -> -130763.36 | P53: =SUM(D53:O53) -> -1471094.9
A54: 4 | B54: SECONDARY > 10 kW 4CP | C54: SEC | D54: =-VLOOKUP(CONCATENATE($B$46,$B54),Riders!$A$12:$Q$357,'II-H-4.1 Monthly'!D$11,FALSE) -> -16224.01 | E54: =-VLOOKUP(CONCATENATE($B$46,$B54),Riders!$A$12:$Q$357,'II-H-4.1 Monthly'!E$11,FALSE) -> -15867.58 | F54: =-VLOOKUP(CONCATENATE($B$46,$B54),Riders!$A$12:$Q$357,'II-H-4.1 Monthly'!F$11,FALSE) -> -15500.13 | G54: =-VLOOKUP(CONCATENATE($B$46,$B54),Riders!$A$12:$Q$357,'II-H-4.1 Monthly'!G$11,FALSE) -> -14818.11 | H54: =-VLOOKUP(CONCATENATE($B$46,$B54),Riders!$A$12:$Q$357,'II-H-4.1 Monthly'!H$11,FALSE) -> -14239.84 | I54: =-VLOOKUP(CONCATENATE($B$46,$B54),Riders!$A$12:$Q$357,'II-H-4.1 Monthly'!I$11,FALSE) -> -14697.86 | J54: =-VLOOKUP(CONCATENATE($B$46,$B54),Riders!$A$12:$Q$357,'II-H-4.1 Monthly'!J$11,FALSE) -> -14737.91 | K54: =-VLOOKUP(CONCATENATE($B$46,$B54),Riders!$A$12:$Q$357,'II-H-4.1 Monthly'!K$11,FALSE) -> -15082.86 | ... O54: =-VLOOKUP(CONCATENATE($B$46,$B54),Riders!$A$12:$Q$357,'II-H-4.1 Monthly'!O$11,FALSE) -> -18301.78 | P54: =SUM(D54:O54) -> -189910.7
A55: 5 | B55: TOTAL SECONDARY > 10 kW | D55: =SUM(D53:D54) -> -135635.69 | E55: =SUM(E53:E54) -> -132613.15 | F55: =SUM(F53:F54) -> -137010.91 | G55: =SUM(G53:G54) -> -138122.59 | H55: =SUM(H53:H54) -> -137664.3 | I55: =SUM(I53:I54) -> -136179.56 | J55: =SUM(J53:J54) -> -133149.41 | K55: =SUM(K53:K54) -> -131525.4 | ... P55: =SUM(P53:P54) -> -1661005.6
A57: 6 | B57: PRIMARY NCP | C57: PRI | D57: =-VLOOKUP(CONCATENATE($B$46,$B57),Riders!$A$12:$Q$357,'II-H-4.1 Monthly'!D$11,FALSE) -> -2470.67 | E57: =-VLOOKUP(CONCATENATE($B$46,$B57),Riders!$A$12:$Q$357,'II-H-4.1 Monthly'!E$11,FALSE) -> -2576.75 | F57: =-VLOOKUP(CONCATENATE($B$46,$B57),Riders!$A$12:$Q$357,'II-H-4.1 Monthly'!F$11,FALSE) -> -2608.04 | G57: =-VLOOKUP(CONCATENATE($B$46,$B57),Riders!$A$12:$Q$357,'II-H-4.1 Monthly'!G$11,FALSE) -> -2508.79 | H57: =-VLOOKUP(CONCATENATE($B$46,$B57),Riders!$A$12:$Q$357,'II-H-4.1 Monthly'!H$11,FALSE) -> -2573.03 | I57: =-VLOOKUP(CONCATENATE($B$46,$B57),Riders!$A$12:$Q$357,'II-H-4.1 Monthly'!I$11,FALSE) -> -2779.94 | J57: =-VLOOKUP(CONCATENATE($B$46,$B57),Riders!$A$12:$Q$357,'II-H-4.1 Monthly'!J$11,FALSE) -> -2866.86 | K57: =-VLOOKUP(CONCATENATE($B$46,$B57),Riders!$A$12:$Q$357,'II-H-4.1 Monthly'!K$11,FALSE) -> -2922.14 | ... O57: =-VLOOKUP(CONCATENATE($B$46,$B57),Riders!$A$12:$Q$357,'II-H-4.1 Monthly'!O$11,FALSE) -> -2792.79 | P57: =SUM(D57:O57) -> -32510.42
A58: 7 | B58: PRIMARY 4CP | C58: PRI | D58: =-VLOOKUP(CONCATENATE($B$46,$B58),Riders!$A$12:$Q$357,'II-H-4.1 Monthly'!D$11,FALSE) -> -30189.27 | E58: =-VLOOKUP(CONCATENATE($B$46,$B58),Riders!$A$12:$Q$357,'II-H-4.1 Monthly'!E$11,FALSE) -> -29077.19 | F58: =-VLOOKUP(CONCATENATE($B$46,$B58),Riders!$A$12:$Q$357,'II-H-4.1 Monthly'!F$11,FALSE) -> -29381.06 | G58: =-VLOOKUP(CONCATENATE($B$46,$B58),Riders!$A$12:$Q$357,'II-H-4.1 Monthly'!G$11,FALSE) -> -27402.57 | H58: =-VLOOKUP(CONCATENATE($B$46,$B58),Riders!$A$12:$Q$357,'II-H-4.1 Monthly'!H$11,FALSE) -> -28527.79 | I58: =-VLOOKUP(CONCATENATE($B$46,$B58),Riders!$A$12:$Q$357,'II-H-4.1 Monthly'!I$11,FALSE) -> -30374.36 | J58: =-VLOOKUP(CONCATENATE($B$46,$B58),Riders!$A$12:$Q$357,'II-H-4.1 Monthly'!J$11,FALSE) -> -28444.46 | K58: =-VLOOKUP(CONCATENATE($B$46,$B58),Riders!$A$12:$Q$357,'II-H-4.1 Monthly'!K$11,FALSE) -> -31087.72 | ... O58: =-VLOOKUP(CONCATENATE($B$46,$B58),Riders!$A$12:$Q$357,'II-H-4.1 Monthly'!O$11,FALSE) -> -29666.63 | P58: =SUM(D58:O58) -> -359059.31
A59: 8 | B59: PRIMARY SUB NCP | C59: PRI | D59: =-VLOOKUP(CONCATENATE($B$46,$B59),Riders!$A$12:$Q$357,'II-H-4.1 Monthly'!D$11,FALSE) -> -70.66 | E59: =-VLOOKUP(CONCATENATE($B$46,$B59),Riders!$A$12:$Q$357,'II-H-4.1 Monthly'!E$11,FALSE) -> -69.61 | F59: =-VLOOKUP(CONCATENATE($B$46,$B59),Riders!$A$12:$Q$357,'II-H-4.1 Monthly'!F$11,FALSE) -> -66.66 | G59: =-VLOOKUP(CONCATENATE($B$46,$B59),Riders!$A$12:$Q$357,'II-H-4.1 Monthly'!G$11,FALSE) -> -65.37 | H59: =-VLOOKUP(CONCATENATE($B$46,$B59),Riders!$A$12:$Q$357,'II-H-4.1 Monthly'!H$11,FALSE) -> -65.71 | I59: =-VLOOKUP(CONCATENATE($B$46,$B59),Riders!$A$12:$Q$357,'II-H-4.1 Monthly'!I$11,FALSE) -> -64.3 | J59: =-VLOOKUP(CONCATENATE($B$46,$B59),Riders!$A$12:$Q$357,'II-H-4.1 Monthly'!J$11,FALSE) -> -65.41 | K59: =-VLOOKUP(CONCATENATE($B$46,$B59),Riders!$A$12:$Q$357,'II-H-4.1 Monthly'!K$11,FALSE) -> -70.02 | ... O59: =-VLOOKUP(CONCATENATE($B$46,$B59),Riders!$A$12:$Q$357,'II-H-4.1 Monthly'!O$11,FALSE) -> -66.93 | P59: =SUM(D59:O59) -> -814.53
A60: 9 | B60: PRIMARY SUB 4CP | C60: PRI | D60: =-VLOOKUP(CONCATENATE($B$46,$B60),Riders!$A$12:$Q$357,'II-H-4.1 Monthly'!D$11,FALSE) -> -7839.84 | E60: =-VLOOKUP(CONCATENATE($B$46,$B60),Riders!$A$12:$Q$357,'II-H-4.1 Monthly'!E$11,FALSE) -> -7854.05 | F60: =-VLOOKUP(CONCATENATE($B$46,$B60),Riders!$A$12:$Q$357,'II-H-4.1 Monthly'!F$11,FALSE) -> -7769.33 | G60: =-VLOOKUP(CONCATENATE($B$46,$B60),Riders!$A$12:$Q$357,'II-H-4.1 Monthly'!G$11,FALSE) -> -7849.6 | H60: =-VLOOKUP(CONCATENATE($B$46,$B60),Riders!$A$12:$Q$357,'II-H-4.1 Monthly'!H$11,FALSE) -> -7725.86 | I60: =-VLOOKUP(CONCATENATE($B$46,$B60),Riders!$A$12:$Q$357,'II-H-4.1 Monthly'!I$11,FALSE) -> -7802.03 | J60: =-VLOOKUP(CONCATENATE($B$46,$B60),Riders!$A$12:$Q$357,'II-H-4.1 Monthly'!J$11,FALSE) -> -7689.95 | K60: =-VLOOKUP(CONCATENATE($B$46,$B60),Riders!$A$12:$Q$357,'II-H-4.1 Monthly'!K$11,FALSE) -> -7509.65 | ... O60: =-VLOOKUP(CONCATENATE($B$46,$B60),Riders!$A$12:$Q$357,'II-H-4.1 Monthly'!O$11,FALSE) -> -7497.25 | P60: =SUM(D60:O60) -> -92077.74
A61: 10 | B61: TOTAL PRIMARY | D61: =SUM(D57:D60) -> -40570.44 | E61: =SUM(E57:E60) -> -39577.6 | F61: =SUM(F57:F60) -> -39825.09 | G61: =SUM(G57:G60) -> -37826.33 | H61: =SUM(H57:H60) -> -38892.39 | I61: =SUM(I57:I60) -> -41020.63 | J61: =SUM(J57:J60) -> -39066.68 | K61: =SUM(K57:K60) -> -41589.53 | ... P61: =SUM(P57:P60) -> -484462
A63: 11 | B63: TRANSMISSION | C63: TRA | D63: =-VLOOKUP(CONCATENATE($B$46,$B63),Riders!$A$12:$Q$357,'II-H-4.1 Monthly'!D$11,FALSE) -> 0 | E63: =-VLOOKUP(CONCATENATE($B$46,$B63),Riders!$A$12:$Q$357,'II-H-4.1 Monthly'!E$11,FALSE) -> 0 | F63: =-VLOOKUP(CONCATENATE($B$46,$B63),Riders!$A$12:$Q$357,'II-H-4.1 Monthly'!F$11,FALSE) -> 0 | G63: =-VLOOKUP(CONCATENATE($B$46,$B63),Riders!$A$12:$Q$357,'II-H-4.1 Monthly'!G$11,FALSE) -> 0 | H63: =-VLOOKUP(CONCATENATE($B$46,$B63),Riders!$A$12:$Q$357,'II-H-4.1 Monthly'!H$11,FALSE) -> 0 | I63: =-VLOOKUP(CONCATENATE($B$46,$B63),Riders!$A$12:$Q$357,'II-H-4.1 Monthly'!I$11,FALSE) -> 0 | J63: =-VLOOKUP(CONCATENATE($B$46,$B63),Riders!$A$12:$Q$357,'II-H-4.1 Monthly'!J$11,FALSE) -> 0 | K63: =-VLOOKUP(CONCATENATE($B$46,$B63),Riders!$A$12:$Q$357,'II-H-4.1 Monthly'!K$11,FALSE) -> 0 | ... O63: =-VLOOKUP(CONCATENATE($B$46,$B63),Riders!$A$12:$Q$357,'II-H-4.1 Monthly'!O$11,FALSE) -> 0 | P63: =SUM(D63:O63) -> 0
A65: 12 | B65: LIGHTING | C65: SEC | D65: =-VLOOKUP(CONCATENATE($B$46,$B65),Riders!$A$12:$Q$357,'II-H-4.1 Monthly'!D$11,FALSE) -> -5450.92 | E65: =-VLOOKUP(CONCATENATE($B$46,$B65),Riders!$A$12:$Q$357,'II-H-4.1 Monthly'!E$11,FALSE) -> -5472.85 | F65: =-VLOOKUP(CONCATENATE($B$46,$B65),Riders!$A$12:$Q$357,'II-H-4.1 Monthly'!F$11,FALSE) -> -5428.14 | G65: =-VLOOKUP(CONCATENATE($B$46,$B65),Riders!$A$12:$Q$357,'II-H-4.1 Monthly'!G$11,FALSE) -> -5438.82 | H65: =-VLOOKUP(CONCATENATE($B$46,$B65),Riders!$A$12:$Q$357,'II-H-4.1 Monthly'!H$11,FALSE) -> -5408.13 | I65: =-VLOOKUP(CONCATENATE($B$46,$B65),Riders!$A$12:$Q$357,'II-H-4.1 Monthly'!I$11,FALSE) -> -5421.52 | J65: =-VLOOKUP(CONCATENATE($B$46,$B65),Riders!$A$12:$Q$357,'II-H-4.1 Monthly'!J$11,FALSE) -> -5414.41 | K65: =-VLOOKUP(CONCATENATE($B$46,$B65),Riders!$A$12:$Q$357,'II-H-4.1 Monthly'!K$11,FALSE) -> -5411.28 | ... O65: =-VLOOKUP(CONCATENATE($B$46,$B65),Riders!$A$12:$Q$357,'II-H-4.1 Monthly'!O$11,FALSE) -> -5373.17 | P65: =SUM(D65:O65) -> -64983.18
A67: 13 | B67: TOTAL RETAIL | D67: =D65+D63+D61+D55+D51+D49 -> -431567.43 | E67: =E65+E63+E61+E55+E51+E49 -> -371702.01 | F67: =F65+F63+F61+F55+F51+F49 -> -407178.34 | G67: =G65+G63+G61+G55+G51+G49 -> -422049.16 | H67: =H65+H63+H61+H55+H51+H49 -> -394102.85 | I67: =I65+I63+I61+I55+I51+I49 -> -377929.03 | J67: =J65+J63+J61+J55+J51+J49 -> -370160.72 | K67: =K65+K63+K61+K55+K51+K49 -> -388377.01 | ... P67: =P65+P63+P61+P55+P51+P49 -> -5308009.1
A69: 14 | B69: WHOLESALE PRI | C69: PRI | P69: =SUM(D69:O69) -> 0
A70: 15 | B70: WHOLESALE TRANS | C70: TRA | P70: =SUM(D70:O70) -> 0
A71: 16 | B71: TOTAL WHOLESALE | D71: =SUM(D69:D70) -> 0 | E71: =SUM(E69:E70) -> 0 | F71: =SUM(F69:F70) -> 0 | G71: =SUM(G69:G70) -> 0 | H71: =SUM(H69:H70) -> 0 | I71: =SUM(I69:I70) -> 0 | J71: =SUM(J69:J70) -> 0 | K71: =SUM(K69:K70) -> 0 | ... P71: =SUM(P69:P70) -> 0
A73: 17 | B73: TOTAL AEP TEXAS | D73: =+D71+D67 -> -431567.43 | E73: =+E71+E67 -> -371702.01 | F73: =+F71+F67 -> -407178.34 | G73: =+G71+G67 -> -422049.16 | H73: =+H71+H67 -> -394102.85 | I73: =+I71+I67 -> -377929.03 | J73: =+J71+J67 -> -370160.72 | K73: =+K71+K67 -> -388377.01 | ... P73: =+P71+P67 -> -5308009.1
B76: AEP TEXAS
B77: ENERGY EFFICIENCY RIDER ADJUSTMENT
B78: =B10 -> FOR TEST YEAR ENDED SEPTEMBER 30, 2023
B80: =Riders!C69 -> EECR
A81: LINE | B81: DESCRIPTION | C81: VOLT | D81: =$D$13 -> Oct-22 | E81: =$E$13 -> Nov-22 | F81: =$F$13 -> Dec-22 | G81: =$G$13 -> Jan-23 | H81: =$H$13 -> Feb-23 | I81: =$I$13 -> Mar-23 | J81: =$J$13 -> Apr-23 | K81: =$K$13 -> May-23 | L81: =$L$13 -> Jun-23 | M81: =$M$13 -> Jul-23 | N81: =$N$13 -> Aug-23 | O81: =$O$13 -> Sep-23 | P81: TOTAL
A83: 1 | B83: RESIDENTIAL SERVICE | C83: SEC | D83: =-VLOOKUP(CONCATENATE($B$80,$B83),Riders!$A$14:$Q$357,'II-H-4.1 Monthly'!D$11,FALSE) -> -1238036.5 | E83: =-VLOOKUP(CONCATENATE($B$80,$B83),Riders!$A$14:$Q$357,'II-H-4.1 Monthly'!E$11,FALSE) -> -955747.88 | F83: =-VLOOKUP(CONCATENATE($B$80,$B83),Riders!$A$14:$Q$357,'II-H-4.1 Monthly'!F$11,FALSE) -> -1112249.4 | G83: =-VLOOKUP(CONCATENATE($B$80,$B83),Riders!$A$14:$Q$357,'II-H-4.1 Monthly'!G$11,FALSE) -> -1192858.3 | H83: =-VLOOKUP(CONCATENATE($B$80,$B83),Riders!$A$14:$Q$357,'II-H-4.1 Monthly'!H$11,FALSE) -> -1049851.9 | I83: =-VLOOKUP(CONCATENATE($B$80,$B83),Riders!$A$14:$Q$357,'II-H-4.1 Monthly'!I$11,FALSE) -> -852214.81 | J83: =-VLOOKUP(CONCATENATE($B$80,$B83),Riders!$A$14:$Q$357,'II-H-4.1 Monthly'!J$11,FALSE) -> -839735.04 | K83: =-VLOOKUP(CONCATENATE($B$80,$B83),Riders!$A$14:$Q$357,'II-H-4.1 Monthly'!K$11,FALSE) -> -916881.65 | ... O83: =-VLOOKUP(CONCATENATE($B$80,$B83),Riders!$A$14:$Q$357,'II-H-4.1 Monthly'!O$11,FALSE) -> -1584846.7 | P83: =SUM(D83:O83) -> -14232787
A85: 2 | B85: SECONDARY < 10 kW | C85: SEC | D85: =-VLOOKUP(CONCATENATE($B$80,$B85),Riders!$A$14:$Q$357,'II-H-4.1 Monthly'!D$11,FALSE) -> -59343.25 | E85: =-VLOOKUP(CONCATENATE($B$80,$B85),Riders!$A$14:$Q$357,'II-H-4.1 Monthly'!E$11,FALSE) -> -52530.24 | F85: =-VLOOKUP(CONCATENATE($B$80,$B85),Riders!$A$14:$Q$357,'II-H-4.1 Monthly'!F$11,FALSE) -> -55678.84 | G85: =-VLOOKUP(CONCATENATE($B$80,$B85),Riders!$A$14:$Q$357,'II-H-4.1 Monthly'!G$11,FALSE) -> -56356.27 | H85: =-VLOOKUP(CONCATENATE($B$80,$B85),Riders!$A$14:$Q$357,'II-H-4.1 Monthly'!H$11,FALSE) -> -51619.65 | I85: =-VLOOKUP(CONCATENATE($B$80,$B85),Riders!$A$14:$Q$357,'II-H-4.1 Monthly'!I$11,FALSE) -> -41584.56 | J85: =-VLOOKUP(CONCATENATE($B$80,$B85),Riders!$A$14:$Q$357,'II-H-4.1 Monthly'!J$11,FALSE) -> -41330.89 | K85: =-VLOOKUP(CONCATENATE($B$80,$B85),Riders!$A$14:$Q$357,'II-H-4.1 Monthly'!K$11,FALSE) -> -43295.68 | ... O85: =-VLOOKUP(CONCATENATE($B$80,$B85),Riders!$A$14:$Q$357,'II-H-4.1 Monthly'!O$11,FALSE) -> -59114.34 | P85: =SUM(D85:O85) -> -627738
A87: 3 | B87: SECONDARY > 10 kW NCP | C87: SEC | D87: =-VLOOKUP(CONCATENATE($B$80,$B87),Riders!$A$14:$Q$357,'II-H-4.1 Monthly'!D$11,FALSE) -> -772879.08 | E87: =-VLOOKUP(CONCATENATE($B$80,$B87),Riders!$A$14:$Q$357,'II-H-4.1 Monthly'!E$11,FALSE) -> -663295.7 | F87: =-VLOOKUP(CONCATENATE($B$80,$B87),Riders!$A$14:$Q$357,'II-H-4.1 Monthly'!F$11,FALSE) -> -666360.07 | G87: =-VLOOKUP(CONCATENATE($B$80,$B87),Riders!$A$14:$Q$357,'II-H-4.1 Monthly'!G$11,FALSE) -> -668749.17 | H87: =-VLOOKUP(CONCATENATE($B$80,$B87),Riders!$A$14:$Q$357,'II-H-4.1 Monthly'!H$11,FALSE) -> -610872.43 | I87: =-VLOOKUP(CONCATENATE($B$80,$B87),Riders!$A$14:$Q$357,'II-H-4.1 Monthly'!I$11,FALSE) -> -540613.81 | J87: =-VLOOKUP(CONCATENATE($B$80,$B87),Riders!$A$14:$Q$357,'II-H-4.1 Monthly'!J$11,FALSE) -> -555774.12 | K87: =-VLOOKUP(CONCATENATE($B$80,$B87),Riders!$A$14:$Q$357,'II-H-4.1 Monthly'!K$11,FALSE) -> -586696.75 | ... O87: =-VLOOKUP(CONCATENATE($B$80,$B87),Riders!$A$14:$Q$357,'II-H-4.1 Monthly'!O$11,FALSE) -> -811342.1 | P87: =SUM(D87:O87) -> -8162304.2
A88: 4 | B88: SECONDARY > 10 kW 4CP | C88: SEC | D88: =-VLOOKUP(CONCATENATE($B$80,$B88),Riders!$A$14:$Q$357,'II-H-4.1 Monthly'!D$11,FALSE) -> -128164.58 | E88: =-VLOOKUP(CONCATENATE($B$80,$B88),Riders!$A$14:$Q$357,'II-H-4.1 Monthly'!E$11,FALSE) -> -115049.15 | F88: =-VLOOKUP(CONCATENATE($B$80,$B88),Riders!$A$14:$Q$357,'II-H-4.1 Monthly'!F$11,FALSE) -> -118271.6 | G88: =-VLOOKUP(CONCATENATE($B$80,$B88),Riders!$A$14:$Q$357,'II-H-4.1 Monthly'!G$11,FALSE) -> -112842.44 | H88: =-VLOOKUP(CONCATENATE($B$80,$B88),Riders!$A$14:$Q$357,'II-H-4.1 Monthly'!H$11,FALSE) -> -103137.51 | I88: =-VLOOKUP(CONCATENATE($B$80,$B88),Riders!$A$14:$Q$357,'II-H-4.1 Monthly'!I$11,FALSE) -> -91098.98 | J88: =-VLOOKUP(CONCATENATE($B$80,$B88),Riders!$A$14:$Q$357,'II-H-4.1 Monthly'!J$11,FALSE) -> -96399.98 | K88: =-VLOOKUP(CONCATENATE($B$80,$B88),Riders!$A$14:$Q$357,'II-H-4.1 Monthly'!K$11,FALSE) -> -97832.04 | ... O88: =-VLOOKUP(CONCATENATE($B$80,$B88),Riders!$A$14:$Q$357,'II-H-4.1 Monthly'!O$11,FALSE) -> -132703.93 | P88: =SUM(D88:O88) -> -1347101.6
A89: 5 | B89: TOTAL SECONDARY > 10 kW | D89: =SUM(D87:D88) -> -901043.66 | E89: =SUM(E87:E88) -> -778344.85 | F89: =SUM(F87:F88) -> -784631.67 | G89: =SUM(G87:G88) -> -781591.61 | H89: =SUM(H87:H88) -> -714009.94 | I89: =SUM(I87:I88) -> -631712.79 | J89: =SUM(J87:J88) -> -652174.1 | K89: =SUM(K87:K88) -> -684528.79 | ... P89: =SUM(P87:P88) -> -9509405.7
A91: 6 | B91: PRIMARY NCP | C91: PRI | D91: =-VLOOKUP(CONCATENATE($B$80,$B91),Riders!$A$14:$Q$357,'II-H-4.1 Monthly'!D$11,FALSE) -> -4881.74 | E91: =-VLOOKUP(CONCATENATE($B$80,$B91),Riders!$A$14:$Q$357,'II-H-4.1 Monthly'!E$11,FALSE) -> -4807.42 | F91: =-VLOOKUP(CONCATENATE($B$80,$B91),Riders!$A$14:$Q$357,'II-H-4.1 Monthly'!F$11,FALSE) -> -5287.01 | G91: =-VLOOKUP(CONCATENATE($B$80,$B91),Riders!$A$14:$Q$357,'II-H-4.1 Monthly'!G$11,FALSE) -> -4854.06 | H91: =-VLOOKUP(CONCATENATE($B$80,$B91),Riders!$A$14:$Q$357,'II-H-4.1 Monthly'!H$11,FALSE) -> -4832.19 | I91: =-VLOOKUP(CONCATENATE($B$80,$B91),Riders!$A$14:$Q$357,'II-H-4.1 Monthly'!I$11,FALSE) -> -9235.1 | J91: =-VLOOKUP(CONCATENATE($B$80,$B91),Riders!$A$14:$Q$357,'II-H-4.1 Monthly'!J$11,FALSE) -> -9963.25 | K91: =-VLOOKUP(CONCATENATE($B$80,$B91),Riders!$A$14:$Q$357,'II-H-4.1 Monthly'!K$11,FALSE) -> -10943.81 | ... O91: =-VLOOKUP(CONCATENATE($B$80,$B91),Riders!$A$14:$Q$357,'II-H-4.1 Monthly'!O$11,FALSE) -> -11212.87 | P91: =SUM(D91:O91) -> -98002.21
A92: 7 | B92: PRIMARY 4CP | C92: PRI | D92: =-VLOOKUP(CONCATENATE($B$80,$B92),Riders!$A$14:$Q$357,'II-H-4.1 Monthly'!D$11,FALSE) -> -67000.07 | E92: =-VLOOKUP(CONCATENATE($B$80,$B92),Riders!$A$14:$Q$357,'II-H-4.1 Monthly'!E$11,FALSE) -> -65507.19 | F92: =-VLOOKUP(CONCATENATE($B$80,$B92),Riders!$A$14:$Q$357,'II-H-4.1 Monthly'!F$11,FALSE) -> -66426.9 | G92: =-VLOOKUP(CONCATENATE($B$80,$B92),Riders!$A$14:$Q$357,'II-H-4.1 Monthly'!G$11,FALSE) -> -67169.19 | H92: =-VLOOKUP(CONCATENATE($B$80,$B92),Riders!$A$14:$Q$357,'II-H-4.1 Monthly'!H$11,FALSE) -> -61798.26 | I92: =-VLOOKUP(CONCATENATE($B$80,$B92),Riders!$A$14:$Q$357,'II-H-4.1 Monthly'!I$11,FALSE) -> -107305.75 | J92: =-VLOOKUP(CONCATENATE($B$80,$B92),Riders!$A$14:$Q$357,'II-H-4.1 Monthly'!J$11,FALSE) -> -114001.19 | K92: =-VLOOKUP(CONCATENATE($B$80,$B92),Riders!$A$14:$Q$357,'II-H-4.1 Monthly'!K$11,FALSE) -> -122546.26 | ... O92: =-VLOOKUP(CONCATENATE($B$80,$B92),Riders!$A$14:$Q$357,'II-H-4.1 Monthly'!O$11,FALSE) -> -131435.9 | P92: =SUM(D92:O92) -> -1194247.3
A93: 8 | B93: PRIMARY SUB NCP | C93: PRI | D93: =-VLOOKUP(CONCATENATE($B$80,$B93),Riders!$A$14:$Q$357,'II-H-4.1 Monthly'!D$11,FALSE) -> -110.01 | E93: =-VLOOKUP(CONCATENATE($B$80,$B93),Riders!$A$14:$Q$357,'II-H-4.1 Monthly'!E$11,FALSE) -> -104.66 | F93: =-VLOOKUP(CONCATENATE($B$80,$B93),Riders!$A$14:$Q$357,'II-H-4.1 Monthly'!F$11,FALSE) -> -119.08 | G93: =-VLOOKUP(CONCATENATE($B$80,$B93),Riders!$A$14:$Q$357,'II-H-4.1 Monthly'!G$11,FALSE) -> -93.54 | H93: =-VLOOKUP(CONCATENATE($B$80,$B93),Riders!$A$14:$Q$357,'II-H-4.1 Monthly'!H$11,FALSE) -> -94.69 | I93: =-VLOOKUP(CONCATENATE($B$80,$B93),Riders!$A$14:$Q$357,'II-H-4.1 Monthly'!I$11,FALSE) -> -210.6 | J93: =-VLOOKUP(CONCATENATE($B$80,$B93),Riders!$A$14:$Q$357,'II-H-4.1 Monthly'!J$11,FALSE) -> -220.95 | K93: =-VLOOKUP(CONCATENATE($B$80,$B93),Riders!$A$14:$Q$357,'II-H-4.1 Monthly'!K$11,FALSE) -> -245.47 | ... O93: =-VLOOKUP(CONCATENATE($B$80,$B93),Riders!$A$14:$Q$357,'II-H-4.1 Monthly'!O$11,FALSE) -> -257.78 | P93: =SUM(D93:O93) -> -2231.71
A94: 9 | B94: PRIMARY SUB 4CP | C94: PRI | D94: =-VLOOKUP(CONCATENATE($B$80,$B94),Riders!$A$14:$Q$357,'II-H-4.1 Monthly'!D$11,FALSE) -> -17989.01 | E94: =-VLOOKUP(CONCATENATE($B$80,$B94),Riders!$A$14:$Q$357,'II-H-4.1 Monthly'!E$11,FALSE) -> -17191.58 | F94: =-VLOOKUP(CONCATENATE($B$80,$B94),Riders!$A$14:$Q$357,'II-H-4.1 Monthly'!F$11,FALSE) -> -17388.06 | G94: =-VLOOKUP(CONCATENATE($B$80,$B94),Riders!$A$14:$Q$357,'II-H-4.1 Monthly'!G$11,FALSE) -> -20034.71 | H94: =-VLOOKUP(CONCATENATE($B$80,$B94),Riders!$A$14:$Q$357,'II-H-4.1 Monthly'!H$11,FALSE) -> -18352.64 | I94: =-VLOOKUP(CONCATENATE($B$80,$B94),Riders!$A$14:$Q$357,'II-H-4.1 Monthly'!I$11,FALSE) -> -30047.29 | J94: =-VLOOKUP(CONCATENATE($B$80,$B94),Riders!$A$14:$Q$357,'II-H-4.1 Monthly'!J$11,FALSE) -> -32735.33 | K94: =-VLOOKUP(CONCATENATE($B$80,$B94),Riders!$A$14:$Q$357,'II-H-4.1 Monthly'!K$11,FALSE) -> -28974.59 | ... O94: =-VLOOKUP(CONCATENATE($B$80,$B94),Riders!$A$14:$Q$357,'II-H-4.1 Monthly'!O$11,FALSE) -> -26943.76 | P94: =SUM(D94:O94) -> -288623.29
A95: 10 | B95: TOTAL PRIMARY | D95: =SUM(D91:D94) -> -89980.83 | E95: =SUM(E91:E94) -> -87610.85 | F95: =SUM(F91:F94) -> -89221.05 | G95: =SUM(G91:G94) -> -92151.5 | H95: =SUM(H91:H94) -> -85077.78 | I95: =SUM(I91:I94) -> -146798.74 | J95: =SUM(J91:J94) -> -156920.72 | K95: =SUM(K91:K94) -> -162710.13 | ... P95: =SUM(P91:P94) -> -1583104.5
A97: 11 | B97: TRANSMISSION | C97: TRA | D97: =-VLOOKUP(CONCATENATE($B$80,$B97),Riders!$A$14:$Q$357,'II-H-4.1 Monthly'!D$11,FALSE) -> -732.8 | E97: =-VLOOKUP(CONCATENATE($B$80,$B97),Riders!$A$14:$Q$357,'II-H-4.1 Monthly'!E$11,FALSE) -> -822.91 | F97: =-VLOOKUP(CONCATENATE($B$80,$B97),Riders!$A$14:$Q$357,'II-H-4.1 Monthly'!F$11,FALSE) -> -860.63 | G97: =-VLOOKUP(CONCATENATE($B$80,$B97),Riders!$A$14:$Q$357,'II-H-4.1 Monthly'!G$11,FALSE) -> -832.06 | H97: =-VLOOKUP(CONCATENATE($B$80,$B97),Riders!$A$14:$Q$357,'II-H-4.1 Monthly'!H$11,FALSE) -> -818.33 | I97: =-VLOOKUP(CONCATENATE($B$80,$B97),Riders!$A$14:$Q$357,'II-H-4.1 Monthly'!I$11,FALSE) -> -236.54 | J97: =-VLOOKUP(CONCATENATE($B$80,$B97),Riders!$A$14:$Q$357,'II-H-4.1 Monthly'!J$11,FALSE) -> 0 | K97: =-VLOOKUP(CONCATENATE($B$80,$B97),Riders!$A$14:$Q$357,'II-H-4.1 Monthly'!K$11,FALSE) -> 0 | ... O97: =-VLOOKUP(CONCATENATE($B$80,$B97),Riders!$A$14:$Q$357,'II-H-4.1 Monthly'!O$11,FALSE) -> 0 | P97: =SUM(D97:O97) -> -4303.27
A99: 12 | B99: LIGHTING | C99: SEC | D99: =-VLOOKUP(CONCATENATE($B$80,$B99),Riders!$A$14:$Q$357,'II-H-4.1 Monthly'!D$11,FALSE) -> 0 | E99: =-VLOOKUP(CONCATENATE($B$80,$B99),Riders!$A$14:$Q$357,'II-H-4.1 Monthly'!E$11,FALSE) -> 0 | F99: =-VLOOKUP(CONCATENATE($B$80,$B99),Riders!$A$14:$Q$357,'II-H-4.1 Monthly'!F$11,FALSE) -> 0 | G99: =-VLOOKUP(CONCATENATE($B$80,$B99),Riders!$A$14:$Q$357,'II-H-4.1 Monthly'!G$11,FALSE) -> 0 | H99: =-VLOOKUP(CONCATENATE($B$80,$B99),Riders!$A$14:$Q$357,'II-H-4.1 Monthly'!H$11,FALSE) -> 0 | I99: =-VLOOKUP(CONCATENATE($B$80,$B99),Riders!$A$14:$Q$357,'II-H-4.1 Monthly'!I$11,FALSE) -> 0 | J99: =-VLOOKUP(CONCATENATE($B$80,$B99),Riders!$A$14:$Q$357,'II-H-4.1 Monthly'!J$11,FALSE) -> 0 | K99: =-VLOOKUP(CONCATENATE($B$80,$B99),Riders!$A$14:$Q$357,'II-H-4.1 Monthly'!K$11,FALSE) -> 0 | ... O99: =-VLOOKUP(CONCATENATE($B$80,$B99),Riders!$A$14:$Q$357,'II-H-4.1 Monthly'!O$11,FALSE) -> -0.31 | P99: =SUM(D99:O99) -> -0.31
A101: 13 | B101: TOTAL RETAIL | D101: =D99+D97+D95+D89+D85+D83 -> -2289137 | E101: =E99+E97+E95+E89+E85+E83 -> -1875056.7 | F101: =F99+F97+F95+F89+F85+F83 -> -2042641.6 | G101: =G99+G97+G95+G89+G85+G83 -> -2123789.7 | H101: =H99+H97+H95+H89+H85+H83 -> -1901377.6 | I101: =I99+I97+I95+I89+I85+I83 -> -1672547.4 | J101: =J99+J97+J95+J89+J85+J83 -> -1690160.8 | K101: =K99+K97+K95+K89+K85+K83 -> -1807416.2 | ... P101: =P99+P97+P95+P89+P85+P83 -> -25957339
A103: 14 | B103: WHOLESALE PRI | C103: PRI | P103: =SUM(D103:O103) -> 0
A104: 15 | B104: WHOLESALE TRANS | C104: TRA | P104: =SUM(D104:O104) -> 0
A105: 16 | B105: TOTAL WHOLESALE | D105: =SUM(D103:D104) -> 0 | E105: =SUM(E103:E104) -> 0 | F105: =SUM(F103:F104) -> 0 | G105: =SUM(G103:G104) -> 0 | H105: =SUM(H103:H104) -> 0 | I105: =SUM(I103:I104) -> 0 | J105: =SUM(J103:J104) -> 0 | K105: =SUM(K103:K104) -> 0 | ... P105: =SUM(P103:P104) -> 0
A107: 17 | B107: TOTAL AEP TEXAS | D107: =+D105+D101 -> -2289137 | E107: =+E105+E101 -> -1875056.7 | F107: =+F105+F101 -> -2042641.6 | G107: =+G105+G101 -> -2123789.7 | H107: =+H105+H101 -> -1901377.6 | I107: =+I105+I101 -> -1672547.4 | J107: =+J105+J101 -> -1690160.8 | K107: =+K105+K101 -> -1807416.2 | ... P107: =+P105+P101 -> -25957339
B110: AEP TEXAS
B111: TRANSITION CHARGE RIDERS ADJUSTMENT
B112: =B10 -> FOR TEST YEAR ENDED SEPTEMBER 30, 2023
B114: =Riders!C185 -> TC3 | C114: +TC2
A115: LINE | B115: DESCRIPTION | C115: VOLT | D115: =$D$13 -> Oct-22 | E115: =$E$13 -> Nov-22 | F115: =$F$13 -> Dec-22 | G115: =$G$13 -> Jan-23 | H115: =$H$13 -> Feb-23 | I115: =$I$13 -> Mar-23 | J115: =$J$13 -> Apr-23 | K115: =$K$13 -> May-23 | L115: =$L$13 -> Jun-23 | M115: =$M$13 -> Jul-23 | N115: =$N$13 -> Aug-23 | O115: =$O$13 -> Sep-23 | P115: TOTAL
A117: 1 | B117: RESIDENTIAL SERVICE | C117: SEC | D117: =-VLOOKUP(CONCATENATE($B$114,$B117),Riders!$A$14:$Q$357,'II-H-4.1 Monthly'!D$11,FALSE) -> -2460044.1 | E117: =-VLOOKUP(CONCATENATE($B$114,$B117),Riders!$A$14:$Q$357,'II-H-4.1 Monthly'!E$11,FALSE) -> -1920994.6 | F117: =-VLOOKUP(CONCATENATE($B$114,$B117),Riders!$A$14:$Q$357,'II-H-4.1 Monthly'!F$11,FALSE) -> -2162699.9 | G117: =-VLOOKUP(CONCATENATE($B$114,$B117),Riders!$A$14:$Q$357,'II-H-4.1 Monthly'!G$11,FALSE) -> -2298131.3 | H117: =-VLOOKUP(CONCATENATE($B$114,$B117),Riders!$A$14:$Q$357,'II-H-4.1 Monthly'!H$11,FALSE) -> -1983416.2 | I117: =-VLOOKUP(CONCATENATE($B$114,$B117),Riders!$A$14:$Q$357,'II-H-4.1 Monthly'!I$11,FALSE) -> -1674560.3 | J117: =-VLOOKUP(CONCATENATE($B$114,$B117),Riders!$A$14:$Q$357,'II-H-4.1 Monthly'!J$11,FALSE) -> -1683467.9 | K117: =-VLOOKUP(CONCATENATE($B$114,$B117),Riders!$A$14:$Q$357,'II-H-4.1 Monthly'!K$11,FALSE) -> -1838311.2 | ... O117: =-VLOOKUP(CONCATENATE($B$114,$B117),Riders!$A$14:$Q$357,'II-H-4.1 Monthly'!O$11,FALSE) -> -3108468.4 | P117: =SUM(D117:O117) -> -27997172
A119: 2 | B119: SECONDARY < 10 kW | C119: SEC | D119: =-VLOOKUP(CONCATENATE($B$114,$B119),Riders!$A$14:$Q$357,'II-H-4.1 Monthly'!D$11,FALSE) -> -353368.24 | E119: =-VLOOKUP(CONCATENATE($B$114,$B119),Riders!$A$14:$Q$357,'II-H-4.1 Monthly'!E$11,FALSE) -> -314988.55 | F119: =-VLOOKUP(CONCATENATE($B$114,$B119),Riders!$A$14:$Q$357,'II-H-4.1 Monthly'!F$11,FALSE) -> -323699.48 | G119: =-VLOOKUP(CONCATENATE($B$114,$B119),Riders!$A$14:$Q$357,'II-H-4.1 Monthly'!G$11,FALSE) -> -322833.56 | H119: =-VLOOKUP(CONCATENATE($B$114,$B119),Riders!$A$14:$Q$357,'II-H-4.1 Monthly'!H$11,FALSE) -> -290662.69 | I119: =-VLOOKUP(CONCATENATE($B$114,$B119),Riders!$A$14:$Q$357,'II-H-4.1 Monthly'!I$11,FALSE) -> -331301.74 | J119: =-VLOOKUP(CONCATENATE($B$114,$B119),Riders!$A$14:$Q$357,'II-H-4.1 Monthly'!J$11,FALSE) -> -334298.57 | K119: =-VLOOKUP(CONCATENATE($B$114,$B119),Riders!$A$14:$Q$357,'II-H-4.1 Monthly'!K$11,FALSE) -> -357230.77 | ... O119: =-VLOOKUP(CONCATENATE($B$114,$B119),Riders!$A$14:$Q$357,'II-H-4.1 Monthly'!O$11,FALSE) -> -492225.5 | P119: =SUM(D119:O119) -> -4512469.5
A121: 3 | B121: SECONDARY > 10 kW NCP | C121: SEC | D121: =-VLOOKUP(CONCATENATE($B$114,$B121),Riders!$A$14:$Q$357,'II-H-4.1 Monthly'!D$11,FALSE) -> -2200690.8 | E121: =-VLOOKUP(CONCATENATE($B$114,$B121),Riders!$A$14:$Q$357,'II-H-4.1 Monthly'!E$11,FALSE) -> -2034732.6 | F121: =-VLOOKUP(CONCATENATE($B$114,$B121),Riders!$A$14:$Q$357,'II-H-4.1 Monthly'!F$11,FALSE) -> -2028738.9 | G121: =-VLOOKUP(CONCATENATE($B$114,$B121),Riders!$A$14:$Q$357,'II-H-4.1 Monthly'!G$11,FALSE) -> -2054230 | H121: =-VLOOKUP(CONCATENATE($B$114,$B121),Riders!$A$14:$Q$357,'II-H-4.1 Monthly'!H$11,FALSE) -> -1989679.6 | I121: =-VLOOKUP(CONCATENATE($B$114,$B121),Riders!$A$14:$Q$357,'II-H-4.1 Monthly'!I$11,FALSE) -> -2106690.4 | J121: =-VLOOKUP(CONCATENATE($B$114,$B121),Riders!$A$14:$Q$357,'II-H-4.1 Monthly'!J$11,FALSE) -> -2095475.8 | K121: =-VLOOKUP(CONCATENATE($B$114,$B121),Riders!$A$14:$Q$357,'II-H-4.1 Monthly'!K$11,FALSE) -> -2149330.9 | ... O121: =-VLOOKUP(CONCATENATE($B$114,$B121),Riders!$A$14:$Q$357,'II-H-4.1 Monthly'!O$11,FALSE) -> -2672171.5 | P121: =SUM(D121:O121) -> -27005443
A122: 4 | B122: SECONDARY > 10 kW 4CP | C122: SEC | D122: =-VLOOKUP(CONCATENATE($B$114,$B122),Riders!$A$14:$Q$357,'II-H-4.1 Monthly'!D$11,FALSE) -> -212543.74 | E122: =-VLOOKUP(CONCATENATE($B$114,$B122),Riders!$A$14:$Q$357,'II-H-4.1 Monthly'!E$11,FALSE) -> -200879.9 | F122: =-VLOOKUP(CONCATENATE($B$114,$B122),Riders!$A$14:$Q$357,'II-H-4.1 Monthly'!F$11,FALSE) -> -194204.07 | G122: =-VLOOKUP(CONCATENATE($B$114,$B122),Riders!$A$14:$Q$357,'II-H-4.1 Monthly'!G$11,FALSE) -> -191586.61 | H122: =-VLOOKUP(CONCATENATE($B$114,$B122),Riders!$A$14:$Q$357,'II-H-4.1 Monthly'!H$11,FALSE) -> -191509.28 | I122: =-VLOOKUP(CONCATENATE($B$114,$B122),Riders!$A$14:$Q$357,'II-H-4.1 Monthly'!I$11,FALSE) -> -203617.25 | J122: =-VLOOKUP(CONCATENATE($B$114,$B122),Riders!$A$14:$Q$357,'II-H-4.1 Monthly'!J$11,FALSE) -> -201094.71 | K122: =-VLOOKUP(CONCATENATE($B$114,$B122),Riders!$A$14:$Q$357,'II-H-4.1 Monthly'!K$11,FALSE) -> -200120.83 | ... O122: =-VLOOKUP(CONCATENATE($B$114,$B122),Riders!$A$14:$Q$357,'II-H-4.1 Monthly'!O$11,FALSE) -> -268963.7 | P122: =SUM(D122:O122) -> -2541524.5
A123: 5 | B123: TOTAL SECONDARY > 10 kW | D123: =SUM(D121:D122) -> -2413234.6 | E123: =SUM(E121:E122) -> -2235612.5 | F123: =SUM(F121:F122) -> -2222943 | G123: =SUM(G121:G122) -> -2245816.6 | H123: =SUM(H121:H122) -> -2181188.9 | I123: =SUM(I121:I122) -> -2310307.7 | J123: =SUM(J121:J122) -> -2296570.5 | K123: =SUM(K121:K122) -> -2349451.7 | ... P123: =SUM(P121:P122) -> -29546967
A125: 6 | B125: PRIMARY NCP | C125: PRI | D125: =-VLOOKUP(CONCATENATE($B$114,$B125),Riders!$A$14:$Q$357,'II-H-4.1 Monthly'!D$11,FALSE) -> -32664.38 | E125: =-VLOOKUP(CONCATENATE($B$114,$B125),Riders!$A$14:$Q$357,'II-H-4.1 Monthly'!E$11,FALSE) -> -33641.05 | F125: =-VLOOKUP(CONCATENATE($B$114,$B125),Riders!$A$14:$Q$357,'II-H-4.1 Monthly'!F$11,FALSE) -> -34025.65 | G125: =-VLOOKUP(CONCATENATE($B$114,$B125),Riders!$A$14:$Q$357,'II-H-4.1 Monthly'!G$11,FALSE) -> -32384.74 | H125: =-VLOOKUP(CONCATENATE($B$114,$B125),Riders!$A$14:$Q$357,'II-H-4.1 Monthly'!H$11,FALSE) -> -34290.24 | I125: =-VLOOKUP(CONCATENATE($B$114,$B125),Riders!$A$14:$Q$357,'II-H-4.1 Monthly'!I$11,FALSE) -> -40064.57 | J125: =-VLOOKUP(CONCATENATE($B$114,$B125),Riders!$A$14:$Q$357,'II-H-4.1 Monthly'!J$11,FALSE) -> -42285.89 | K125: =-VLOOKUP(CONCATENATE($B$114,$B125),Riders!$A$14:$Q$357,'II-H-4.1 Monthly'!K$11,FALSE) -> -41537.17 | ... O125: =-VLOOKUP(CONCATENATE($B$114,$B125),Riders!$A$14:$Q$357,'II-H-4.1 Monthly'!O$11,FALSE) -> -42212.71 | P125: =SUM(D125:O125) -> -452588.2
A126: 7 | B126: PRIMARY 4CP | C126: PRI | D126: =-VLOOKUP(CONCATENATE($B$114,$B126),Riders!$A$14:$Q$357,'II-H-4.1 Monthly'!D$11,FALSE) -> -417510.87 | E126: =-VLOOKUP(CONCATENATE($B$114,$B126),Riders!$A$14:$Q$357,'II-H-4.1 Monthly'!E$11,FALSE) -> -410744.08 | F126: =-VLOOKUP(CONCATENATE($B$114,$B126),Riders!$A$14:$Q$357,'II-H-4.1 Monthly'!F$11,FALSE) -> -392642.22 | G126: =-VLOOKUP(CONCATENATE($B$114,$B126),Riders!$A$14:$Q$357,'II-H-4.1 Monthly'!G$11,FALSE) -> -400519.53 | H126: =-VLOOKUP(CONCATENATE($B$114,$B126),Riders!$A$14:$Q$357,'II-H-4.1 Monthly'!H$11,FALSE) -> -376225.41 | I126: =-VLOOKUP(CONCATENATE($B$114,$B126),Riders!$A$14:$Q$357,'II-H-4.1 Monthly'!I$11,FALSE) -> -405599.03 | J126: =-VLOOKUP(CONCATENATE($B$114,$B126),Riders!$A$14:$Q$357,'II-H-4.1 Monthly'!J$11,FALSE) -> -368113.47 | K126: =-VLOOKUP(CONCATENATE($B$114,$B126),Riders!$A$14:$Q$357,'II-H-4.1 Monthly'!K$11,FALSE) -> -406213.38 | ... O126: =-VLOOKUP(CONCATENATE($B$114,$B126),Riders!$A$14:$Q$357,'II-H-4.1 Monthly'!O$11,FALSE) -> -426789.07 | P126: =SUM(D126:O126) -> -4901564.6
A127: 8 | B127: PRIMARY SUB NCP | C127: PRI | D127: =-VLOOKUP(CONCATENATE($B$114,$B127),Riders!$A$14:$Q$357,'II-H-4.1 Monthly'!D$11,FALSE) -> -635.43 | E127: =-VLOOKUP(CONCATENATE($B$114,$B127),Riders!$A$14:$Q$357,'II-H-4.1 Monthly'!E$11,FALSE) -> -610.17 | F127: =-VLOOKUP(CONCATENATE($B$114,$B127),Riders!$A$14:$Q$357,'II-H-4.1 Monthly'!F$11,FALSE) -> -562.83 | G127: =-VLOOKUP(CONCATENATE($B$114,$B127),Riders!$A$14:$Q$357,'II-H-4.1 Monthly'!G$11,FALSE) -> -520.08 | H127: =-VLOOKUP(CONCATENATE($B$114,$B127),Riders!$A$14:$Q$357,'II-H-4.1 Monthly'!H$11,FALSE) -> -522.94 | I127: =-VLOOKUP(CONCATENATE($B$114,$B127),Riders!$A$14:$Q$357,'II-H-4.1 Monthly'!I$11,FALSE) -> -515.5 | J127: =-VLOOKUP(CONCATENATE($B$114,$B127),Riders!$A$14:$Q$357,'II-H-4.1 Monthly'!J$11,FALSE) -> -525.12 | K127: =-VLOOKUP(CONCATENATE($B$114,$B127),Riders!$A$14:$Q$357,'II-H-4.1 Monthly'!K$11,FALSE) -> -559.1 | ... O127: =-VLOOKUP(CONCATENATE($B$114,$B127),Riders!$A$14:$Q$357,'II-H-4.1 Monthly'!O$11,FALSE) -> -549.32 | P127: =SUM(D127:O127) -> -6733.65
A128: 9 | B128: PRIMARY SUB 4CP | C128: PRI | D128: =-VLOOKUP(CONCATENATE($B$114,$B128),Riders!$A$14:$Q$357,'II-H-4.1 Monthly'!D$11,FALSE) -> -57858.71 | E128: =-VLOOKUP(CONCATENATE($B$114,$B128),Riders!$A$14:$Q$357,'II-H-4.1 Monthly'!E$11,FALSE) -> -57858.71 | F128: =-VLOOKUP(CONCATENATE($B$114,$B128),Riders!$A$14:$Q$357,'II-H-4.1 Monthly'!F$11,FALSE) -> -57858.71 | G128: =-VLOOKUP(CONCATENATE($B$114,$B128),Riders!$A$14:$Q$357,'II-H-4.1 Monthly'!G$11,FALSE) -> -57858.71 | H128: =-VLOOKUP(CONCATENATE($B$114,$B128),Riders!$A$14:$Q$357,'II-H-4.1 Monthly'!H$11,FALSE) -> -57858.71 | I128: =-VLOOKUP(CONCATENATE($B$114,$B128),Riders!$A$14:$Q$357,'II-H-4.1 Monthly'!I$11,FALSE) -> -57858.71 | J128: =-VLOOKUP(CONCATENATE($B$114,$B128),Riders!$A$14:$Q$357,'II-H-4.1 Monthly'!J$11,FALSE) -> -57858.71 | K128: =-VLOOKUP(CONCATENATE($B$114,$B128),Riders!$A$14:$Q$357,'II-H-4.1 Monthly'!K$11,FALSE) -> -57858.71 | ... O128: =-VLOOKUP(CONCATENATE($B$114,$B128),Riders!$A$14:$Q$357,'II-H-4.1 Monthly'!O$11,FALSE) -> -57858.71 | P128: =SUM(D128:O128) -> -694304.52
A129: 10 | B129: TOTAL PRIMARY | D129: =SUM(D125:D128) -> -508669.39 | E129: =SUM(E125:E128) -> -502854.01 | F129: =SUM(F125:F128) -> -485089.41 | G129: =SUM(G125:G128) -> -491283.06 | H129: =SUM(H125:H128) -> -468897.3 | I129: =SUM(I125:I128) -> -504037.81 | J129: =SUM(J125:J128) -> -468783.19 | K129: =SUM(K125:K128) -> -506168.36 | ... P129: =SUM(P125:P128) -> -6055191
A131: 11 | B131: TRANSMISSION | C131: TRA | D131: =-VLOOKUP(CONCATENATE($B$114,$B131),Riders!$A$14:$Q$357,'II-H-4.1 Monthly'!D$11,FALSE) -> -428092.55 | E131: =-VLOOKUP(CONCATENATE($B$114,$B131),Riders!$A$14:$Q$357,'II-H-4.1 Monthly'!E$11,FALSE) -> -448600.51 | F131: =-VLOOKUP(CONCATENATE($B$114,$B131),Riders!$A$14:$Q$357,'II-H-4.1 Monthly'!F$11,FALSE) -> -484131.9 | G131: =-VLOOKUP(CONCATENATE($B$114,$B131),Riders!$A$14:$Q$357,'II-H-4.1 Monthly'!G$11,FALSE) -> -462922.17 | H131: =-VLOOKUP(CONCATENATE($B$114,$B131),Riders!$A$14:$Q$357,'II-H-4.1 Monthly'!H$11,FALSE) -> -448278.25 | I131: =-VLOOKUP(CONCATENATE($B$114,$B131),Riders!$A$14:$Q$357,'II-H-4.1 Monthly'!I$11,FALSE) -> -361359.06 | J131: =-VLOOKUP(CONCATENATE($B$114,$B131),Riders!$A$14:$Q$357,'II-H-4.1 Monthly'!J$11,FALSE) -> -257349.4 | K131: =-VLOOKUP(CONCATENATE($B$114,$B131),Riders!$A$14:$Q$357,'II-H-4.1 Monthly'!K$11,FALSE) -> -272172.3 | ... O131: =-VLOOKUP(CONCATENATE($B$114,$B131),Riders!$A$14:$Q$357,'II-H-4.1 Monthly'!O$11,FALSE) -> -194591.08 | P131: =SUM(D131:O131) -> -4110819.2
A133: 12 | B133: LIGHTING | C133: SEC | D133: =-VLOOKUP(CONCATENATE($B$114,$B133),Riders!$A$14:$Q$357,'II-H-4.1 Monthly'!D$11,FALSE) -> -100903.39 | E133: =-VLOOKUP(CONCATENATE($B$114,$B133),Riders!$A$14:$Q$357,'II-H-4.1 Monthly'!E$11,FALSE) -> -101295.82 | F133: =-VLOOKUP(CONCATENATE($B$114,$B133),Riders!$A$14:$Q$357,'II-H-4.1 Monthly'!F$11,FALSE) -> -100532.03 | G133: =-VLOOKUP(CONCATENATE($B$114,$B133),Riders!$A$14:$Q$357,'II-H-4.1 Monthly'!G$11,FALSE) -> -100761.35 | H133: =-VLOOKUP(CONCATENATE($B$114,$B133),Riders!$A$14:$Q$357,'II-H-4.1 Monthly'!H$11,FALSE) -> -99387.76 | I133: =-VLOOKUP(CONCATENATE($B$114,$B133),Riders!$A$14:$Q$357,'II-H-4.1 Monthly'!I$11,FALSE) -> -107545.72 | J133: =-VLOOKUP(CONCATENATE($B$114,$B133),Riders!$A$14:$Q$357,'II-H-4.1 Monthly'!J$11,FALSE) -> -107462.1 | K133: =-VLOOKUP(CONCATENATE($B$114,$B133),Riders!$A$14:$Q$357,'II-H-4.1 Monthly'!K$11,FALSE) -> -107502.89 | ... O133: =-VLOOKUP(CONCATENATE($B$114,$B133),Riders!$A$14:$Q$357,'II-H-4.1 Monthly'!O$11,FALSE) -> -106617.17 | P133: =SUM(D133:O133) -> -1252617.1
A135: 13 | B135: TOTAL RETAIL | D135: =D133+D131+D129+D123+D119+D117 -> -6264312.3 | E135: =E133+E131+E129+E123+E119+E117 -> -5524346 | F135: =F133+F131+F129+F123+F119+F117 -> -5779095.8 | G135: =G133+G131+G129+G123+G119+G117 -> -5921748.1 | H135: =H133+H131+H129+H123+H119+H117 -> -5471831.1 | I135: =I133+I131+I129+I123+I119+I117 -> -5289112.3 | J135: =J133+J131+J129+J123+J119+J117 -> -5147931.7 | K135: =K133+K131+K129+K123+K119+K117 -> -5430837.3 | ... P135: =P133+P131+P129+P123+P119+P117 -> -73475236
A137: 14 | B137: WHOLESALE PRI | C137: PRI | P137: =SUM(D137:O137) -> 0
A138: 15 | B138: WHOLESALE TRANS | C138: TRA | P138: =SUM(D138:O138) -> 0
A139: 16 | B139: TOTAL WHOLESALE | D139: =SUM(D137:D138) -> 0 | E139: =SUM(E137:E138) -> 0 | F139: =SUM(F137:F138) -> 0 | G139: =SUM(G137:G138) -> 0 | H139: =SUM(H137:H138) -> 0 | I139: =SUM(I137:I138) -> 0 | J139: =SUM(J137:J138) -> 0 | K139: =SUM(K137:K138) -> 0 | ... P139: =SUM(P137:P138) -> 0
A141: 17 | B141: TOTAL AEP TEXAS | D141: =+D139+D135 -> -6264312.3 | E141: =+E139+E135 -> -5524346 | F141: =+F139+F135 -> -5779095.8 | G141: =+G139+G135 -> -5921748.1 | H141: =+H139+H135 -> -5471831.1 | I141: =+I139+I135 -> -5289112.3 | J141: =+J139+J135 -> -5147931.7 | K141: =+K139+K135 -> -5430837.3 | ... P141: =+P139+P135 -> -73475236
B144: AEP TEXAS
B145: MOBILE GEN RIDER ADJUSTMENT
B146: =B10 -> FOR TEST YEAR ENDED SEPTEMBER 30, 2023
B148: =Riders!C127 -> MTEEE
A149: LINE | B149: DESCRIPTION | C149: VOLT | D149: =$D$13 -> Oct-22 | E149: =$E$13 -> Nov-22 | F149: =$F$13 -> Dec-22 | G149: =$G$13 -> Jan-23 | H149: =$H$13 -> Feb-23 | I149: =$I$13 -> Mar-23 | J149: =$J$13 -> Apr-23 | K149: =$K$13 -> May-23 | L149: =$L$13 -> Jun-23 | M149: =$M$13 -> Jul-23 | N149: =$N$13 -> Aug-23 | O149: =$O$13 -> Sep-23 | P149: TOTAL
A151: 1 | B151: RESIDENTIAL SERVICE | C151: SEC | D151: =-VLOOKUP(CONCATENATE($B$148,$B151),Riders!$A$14:$Q$357,'II-H-4.1 Monthly'!D$11,FALSE) -> 0 | E151: =-VLOOKUP(CONCATENATE($B$148,$B151),Riders!$A$14:$Q$357,'II-H-4.1 Monthly'!E$11,FALSE) -> 0 | F151: =-VLOOKUP(CONCATENATE($B$148,$B151),Riders!$A$14:$Q$357,'II-H-4.1 Monthly'!F$11,FALSE) -> 0 | G151: =-VLOOKUP(CONCATENATE($B$148,$B151),Riders!$A$14:$Q$357,'II-H-4.1 Monthly'!G$11,FALSE) -> 0 | H151: =-VLOOKUP(CONCATENATE($B$148,$B151),Riders!$A$14:$Q$357,'II-H-4.1 Monthly'!H$11,FALSE) -> 0 | I151: =-VLOOKUP(CONCATENATE($B$148,$B151),Riders!$A$14:$Q$357,'II-H-4.1 Monthly'!I$11,FALSE) -> 0 | J151: =-VLOOKUP(CONCATENATE($B$148,$B151),Riders!$A$14:$Q$357,'II-H-4.1 Monthly'!J$11,FALSE) -> 0 | K151: =-VLOOKUP(CONCATENATE($B$148,$B151),Riders!$A$14:$Q$357,'II-H-4.1 Monthly'!K$11,FALSE) -> 0 | ... O151: =-VLOOKUP(CONCATENATE($B$148,$B151),Riders!$A$14:$Q$357,'II-H-4.1 Monthly'!O$11,FALSE) -> -1232462.1 | P151: =SUM(D151:O151) -> -1232462.1
A153: 2 | B153: SECONDARY < 10 kW | C153: SEC | D153: =-VLOOKUP(CONCATENATE($B$148,$B153),Riders!$A$14:$Q$357,'II-H-4.1 Monthly'!D$11,FALSE) -> 0 | E153: =-VLOOKUP(CONCATENATE($B$148,$B153),Riders!$A$14:$Q$357,'II-H-4.1 Monthly'!E$11,FALSE) -> 0 | F153: =-VLOOKUP(CONCATENATE($B$148,$B153),Riders!$A$14:$Q$357,'II-H-4.1 Monthly'!F$11,FALSE) -> 0 | G153: =-VLOOKUP(CONCATENATE($B$148,$B153),Riders!$A$14:$Q$357,'II-H-4.1 Monthly'!G$11,FALSE) -> 0 | H153: =-VLOOKUP(CONCATENATE($B$148,$B153),Riders!$A$14:$Q$357,'II-H-4.1 Monthly'!H$11,FALSE) -> 0 | I153: =-VLOOKUP(CONCATENATE($B$148,$B153),Riders!$A$14:$Q$357,'II-H-4.1 Monthly'!I$11,FALSE) -> 0 | J153: =-VLOOKUP(CONCATENATE($B$148,$B153),Riders!$A$14:$Q$357,'II-H-4.1 Monthly'!J$11,FALSE) -> 0 | K153: =-VLOOKUP(CONCATENATE($B$148,$B153),Riders!$A$14:$Q$357,'II-H-4.1 Monthly'!K$11,FALSE) -> 0 | ... O153: =-VLOOKUP(CONCATENATE($B$148,$B153),Riders!$A$14:$Q$357,'II-H-4.1 Monthly'!O$11,FALSE) -> -107094.36 | P153: =SUM(D153:O153) -> -107094.36
...

Sheet II-H-4.1 Functions
B2: PUBLIC UTILITY COMMISSION OF TEXAS
B3: AEP TEXAS INC
B4: II-H-4.1 REVENUE IMPACTS FUNCTIONS
B5: ='II-H-4.1 Monthly'!B5 -> TEST YEAR ENDING 9/30/2023
B6: =+'II-H-1'!B6 -> DOCKET 56165
A8: AEP TEXAS
A9: UNADJUSTED BILLED REVENUE
A10: FOR TEST YEAR ENDED SEPTEMBER 30, 2023
A13: LINE | B13: DESCRIPTION | C13: VOLT | D13: Customer Revenue - Base Tariff | E13: Meter Revenue - Base Tariff | F13: Distribution Service Revenue - Base Tariff | G13: Facilities Charge | H13: DCRF Revenue | I13: TCRF Revenue | J13: Total Base Tariff Revenue | L13: ='II-H-4.1 Monthly'!B46 -> TTRAR | M13: ='II-H-4.1 Monthly'!B80 -> EECR | N13: ='II-H-4.1 Monthly'!B114 -> TC3 | O13: ='II-H-4.1 Monthly'!B148 -> MTEEE | P13: ='II-H-4.1 Monthly'!B181 -> SRC | Q13: =Riders!A40 -> Miscellaneous Riders | R13: Total Riders | T13: Total Revenue
A15: 1 | B15: RESIDENTIAL SERVICE | C15: SEC | D15: =+'[6]Functional Rev Unadjusted'!C55 -> 15556436 | E15: =+'[6]Functional Rev Unadjusted'!$D$55 -> 37668799 | F15: =+'[6]Functional Rev Unadjusted'!$E$55 -> 2.7879452e+08 | H15: =+'TCRF and DCRF Rider Revenues'!P17 -> 60613642 | I15: =+'TCRF and DCRF Rider Revenues'!P5 -> 1.9521636e+08 | J15: =SUM(D15:I15) -> 5.8784976e+08 | L15: =VLOOKUP(_xlfn.CONCAT(L$13,$B15),Riders!$A$11:$Q$328,17,FALSE) -> 2981645.4 | M15: =VLOOKUP(_xlfn.CONCAT(M$13,$B15),Riders!$A$11:$Q$328,17,FALSE) -> 14232787 | N15: =VLOOKUP(_xlfn.CONCAT(N$13,$B15),Riders!$A$11:$Q$328,17,FALSE) -> 27997172 | O15: =VLOOKUP(_xlfn.CONCAT(O$13,$B15),Riders!$A$11:$Q$328,17,FALSE) -> 1232462.1 | P15: =VLOOKUP(_xlfn.CONCAT(P$13,$B15),Riders!$A$11:$Q$328,17,FALSE) -> 14176856 | Q15: =SUMIF(Riders!$A:$A,_xlfn.CONCAT('II-H-4.1 Functions'!Q$13,'II-H-4.1 Functions'!$B15),Riders!$Q:$Q) -> 96.33 | R15: =L15+M15+N15+O15+P15+Q15 -> 60621019 | T15: =R15+J15 -> 6.4847078e+08
A17: 2 | B17: SECONDARY < 10 kW | C17: SEC | D17: =+'[6]Functional Rev Unadjusted'!$C$56 -> 1657485.9 | E17: =+'[6]Functional Rev Unadjusted'!$D$56 -> 5069882.1 | F17: =+'[6]Functional Rev Unadjusted'!$E$56 -> 14297306 | H17: =+'TCRF and DCRF Rider Revenues'!P18 -> 5782103.6 | I17: =+'TCRF and DCRF Rider Revenues'!P6 -> 6531262.9 | J17: =SUM(D17:I17) -> 33338041 | L17: =VLOOKUP(_xlfn.CONCAT(L$13,$B17),Riders!$A$11:$Q$328,17,FALSE) -> 115912.84 | M17: =VLOOKUP(_xlfn.CONCAT(M$13,$B17),Riders!$A$11:$Q$328,17,FALSE) -> 627738 | N17: =VLOOKUP(_xlfn.CONCAT(N$13,$B17),Riders!$A$11:$Q$328,17,FALSE) -> 4512469.5 | O17: =VLOOKUP(_xlfn.CONCAT(O$13,$B17),Riders!$A$11:$Q$328,17,FALSE) -> 107094.36 | P17: =VLOOKUP(_xlfn.CONCAT(P$13,$B17),Riders!$A$11:$Q$328,17,FALSE) -> 706508.43 | Q17: =SUMIF(Riders!$A:$A,_xlfn.CONCAT('II-H-4.1 Functions'!Q$13,'II-H-4.1 Functions'!$B17),Riders!$Q:$Q) -> 54.79 | R17: =L17+M17+N17+O17+P17+Q17 -> 6069777.9 | T17: =R17+J17 -> 39407819
A19: 3 | B19: SECONDARY > 10 kW NCP | C19: SEC | D19: =+'[6]Functional Rev Unadjusted'!$C$60 -> 1724725.7 | E19: =+'[6]Functional Rev Unadjusted'!$D$60 -> 10817958 | F19: =+'[6]Functional Rev Unadjusted'!$E$60 -> 1.3641227e+08 | G19: =355.01*12 -> 4260.12 | H19: =+'TCRF and DCRF Rider Revenues'!P19 -> 26612208 | I19: =+'TCRF and DCRF Rider Revenues'!P7 -> 1.0750111e+08 | J19: =SUM(D19:I19) -> 2.8307253e+08 | L19: =VLOOKUP(_xlfn.CONCAT(L$13,$B19),Riders!$A$11:$Q$328,17,FALSE) -> 1471094.9 | M19: =VLOOKUP(_xlfn.CONCAT(M$13,$B19),Riders!$A$11:$Q$328,17,FALSE) -> 8162304.2 | N19: =VLOOKUP(_xlfn.CONCAT(N$13,$B19),Riders!$A$11:$Q$328,17,FALSE) -> 27005443 | O19: =VLOOKUP(_xlfn.CONCAT(O$13,$B19),Riders!$A$11:$Q$328,17,FALSE) -> 438124.11 | P19: =VLOOKUP(_xlfn.CONCAT(P$13,$B19),Riders!$A$11:$Q$328,17,FALSE) -> 7674626.1 | Q19: =SUMIF(Riders!$A:$A,_xlfn.CONCAT('II-H-4.1 Functions'!Q$13,'II-H-4.1 Functions'!$B19),Riders!$Q:$Q) -> -10.19 | R19: =L19+M19+N19+O19+P19+Q19 -> 44751582 | T19: =R19+J19 -> 3.2782412e+08
A20: 4 | B20: SECONDARY > 10 kW 4CP | C20: SEC | D20: =+'[6]Functional Rev Unadjusted'!$C$59 -> 13867.348 | E20: =+'[6]Functional Rev Unadjusted'!$D$59 -> 86979.85 | F20: =+'[6]Functional Rev Unadjusted'!$E$59 -> 17581110 | H20: =+'TCRF and DCRF Rider Revenues'!P20 -> 3442679.6 | I20: =+'TCRF and DCRF Rider Revenues'!P8 -> 13326752 | J20: =SUM(D20:I20) -> 34451389 | L20: =VLOOKUP(_xlfn.CONCAT(L$13,$B20),Riders!$A$11:$Q$328,17,FALSE) -> 189910.7 | M20: =VLOOKUP(_xlfn.CONCAT(M$13,$B20),Riders!$A$11:$Q$328,17,FALSE) -> 1347101.6 | N20: =VLOOKUP(_xlfn.CONCAT(N$13,$B20),Riders!$A$11:$Q$328,17,FALSE) -> 2541524.5 | O20: =VLOOKUP(_xlfn.CONCAT(O$13,$B20),Riders!$A$11:$Q$328,17,FALSE) -> 58722.27 | P20: =VLOOKUP(_xlfn.CONCAT(P$13,$B20),Riders!$A$11:$Q$328,17,FALSE) -> 812052.25 | Q20: =SUMIF(Riders!$A:$A,_xlfn.CONCAT('II-H-4.1 Functions'!Q$13,'II-H-4.1 Functions'!$B20),Riders!$Q:$Q) -> 0 | R20: =L20+M20+N20+O20+P20+Q20 -> 4949311.3 | T20: =R20+J20 -> 39400700
A21: 5 | B21: TOTAL SECONDARY > 10 kW | D21: =SUM(D19:D20) -> 1738593 | E21: =SUM(E19:E20) -> 10904938 | F21: =SUM(F19:F20) -> 1.5399338e+08 | G21: =SUM(G19:G20) -> 4260.12 | H21: =SUM(H19:H20) -> 30054888 | I21: =SUM(I19:I20) -> 1.2082786e+08 | J21: =SUM(J19:J20) -> 3.1752392e+08 | L21: =SUM(L19:L20) -> 1661005.6 | M21: =SUM(M19:M20) -> 9509405.7 | N21: =SUM(N19:N20) -> 29546967 | O21: =SUM(O19:O20) -> 496846.38 | P21: =SUM(P19:P20) -> 8486678.4 | Q21: =SUM(Q19:Q20) -> -10.19 | R21: =SUM(R19:R20) -> 49700893 | T21: =R21+J21 -> 3.6722482e+08
A23: 6 | B23: PRIMARY NCP | C23: PRI | D23: =+'[6]Functional Rev Unadjusted'!$C$65 -> 48169.996 | E23: =+'[6]Functional Rev Unadjusted'!$D$65 -> 831473.11 | F23: =+'[6]Functional Rev Unadjusted'!$E$65 -> 2328029.1 | H23: =+'TCRF and DCRF Rider Revenues'!P21-H25 -> 421784.89 | I23: =+'TCRF and DCRF Rider Revenues'!P9-I25 -> 2618516.5 | J23: =SUM(D23:I23) -> 6247973.6 | L23: =VLOOKUP(_xlfn.CONCAT(L$13,$B23),Riders!$A$11:$Q$328,17,FALSE) -> 32510.42 | M23: =VLOOKUP(_xlfn.CONCAT(M$13,$B23),Riders!$A$11:$Q$328,17,FALSE) -> 98002.21 | N23: =VLOOKUP(_xlfn.CONCAT(N$13,$B23),Riders!$A$11:$Q$328,17,FALSE) -> 452588.2 | O23: =VLOOKUP(_xlfn.CONCAT(O$13,$B23),Riders!$A$11:$Q$328,17,FALSE) -> 5785.05 | P23: =VLOOKUP(_xlfn.CONCAT(P$13,$B23),Riders!$A$11:$Q$328,17,FALSE) -> 97823.41 | Q23: =SUMIF(Riders!$A:$A,_xlfn.CONCAT('II-H-4.1 Functions'!Q$13,'II-H-4.1 Functions'!$B23),Riders!$Q:$Q) -> 0 | R23: =L23+M23+N23+O23+P23+Q23 -> 686709.29 | T23: =R23+J23 -> 6934682.9
A24: 7 | B24: PRIMARY 4CP | C24: PRI | D24: =+'[6]Functional Rev Unadjusted'!$C$64 -> 41851.309 | E24: =+'[6]Functional Rev Unadjusted'!$D$64 -> 722404.84 | F24: =+'[6]Functional Rev Unadjusted'!$E$64 -> 25767464 | H24: =+'TCRF and DCRF Rider Revenues'!P22-H26 -> 4675651.1 | I24: =+'TCRF and DCRF Rider Revenues'!P10-I26 -> 33583174 | J24: =SUM(D24:I24) -> 64790545 | L24: =VLOOKUP(_xlfn.CONCAT(L$13,$B24),Riders!$A$11:$Q$328,17,FALSE) -> 359059.31 | M24: =VLOOKUP(_xlfn.CONCAT(M$13,$B24),Riders!$A$11:$Q$328,17,FALSE) -> 1194247.3 | N24: =VLOOKUP(_xlfn.CONCAT(N$13,$B24),Riders!$A$11:$Q$328,17,FALSE) -> 4901564.6 | O24: =VLOOKUP(_xlfn.CONCAT(O$13,$B24),Riders!$A$11:$Q$328,17,FALSE) -> 73420.28 | P24: =VLOOKUP(_xlfn.CONCAT(P$13,$B24),Riders!$A$11:$Q$328,17,FALSE) -> 1200696.1 | Q24: =SUMIF(Riders!$A:$A,_xlfn.CONCAT('II-H-4.1 Functions'!Q$13,'II-H-4.1 Functions'!$B24),Riders!$Q:$Q) -> 0 | R24: =L24+M24+N24+O24+P24+Q24 -> 7728987.6 | T24: =R24+J24 -> 72519532
A25: 8 | B25: PRIMARY SUB NCP | C25: PRI | D25: =+'[6]Functional Rev Unadjusted'!$C$70 -> 792.43188 | E25: =+'[6]Functional Rev Unadjusted'!$D$70 -> 13678.345 | F25: =+'[6]Functional Rev Unadjusted'!$E$70 -> 58063.964 | H25: =+'Prm Sb Rev Rider'!GP75 -> 10636.06 | I25: =+'Primary Sub'!O14 -> 57797.47 | J25: =SUM(D25:I25) -> 140968.27 | L25: =VLOOKUP(_xlfn.CONCAT(L$13,$B25),Riders!$A$11:$Q$328,17,FALSE) -> 814.53 | M25: =VLOOKUP(_xlfn.CONCAT(M$13,$B25),Riders!$A$11:$Q$328,17,FALSE) -> 2231.71 | N25: =VLOOKUP(_xlfn.CONCAT(N$13,$B25),Riders!$A$11:$Q$328,17,FALSE) -> 6733.65 | O25: =VLOOKUP(_xlfn.CONCAT(O$13,$B25),Riders!$A$11:$Q$328,17,FALSE) -> 182.56 | P25: =VLOOKUP(_xlfn.CONCAT(P$13,$B25),Riders!$A$11:$Q$328,17,FALSE) -> 1933.99 | Q25: =SUMIF(Riders!$A:$A,_xlfn.CONCAT('II-H-4.1 Functions'!Q$13,'II-H-4.1 Functions'!$B25),Riders!$Q:$Q) -> 0 | R25: =L25+M25+N25+O25+P25+Q25 -> 11896.44 | T25: =R25+J25 -> 152864.71
A26: 9 | B26: PRIMARY SUB 4CP | C26: PRI | D26: =+'[6]Functional Rev Unadjusted'!$C$69 -> 5088.5362 | E26: =+'[6]Functional Rev Unadjusted'!$D$69 -> 87834.365 | F26: =+'[6]Functional Rev Unadjusted'!$E$69 -> 6556304.3 | H26: =+'Prm Sb Rev Rider'!GP79 -> 1195301.3 | I26: =+'Primary Sub'!O15 -> 8181172.7 | J26: =SUM(D26:I26) -> 16025701 | L26: =VLOOKUP(_xlfn.CONCAT(L$13,$B26),Riders!$A$11:$Q$328,17,FALSE) -> 92077.74 | M26: =VLOOKUP(_xlfn.CONCAT(M$13,$B26),Riders!$A$11:$Q$328,17,FALSE) -> 288623.29 | N26: =VLOOKUP(_xlfn.CONCAT(N$13,$B26),Riders!$A$11:$Q$328,17,FALSE) -> 694304.52 | O26: =VLOOKUP(_xlfn.CONCAT(O$13,$B26),Riders!$A$11:$Q$328,17,FALSE) -> 16763.85 | P26: =VLOOKUP(_xlfn.CONCAT(P$13,$B26),Riders!$A$11:$Q$328,17,FALSE) -> 197165.24 | Q26: =SUMIF(Riders!$A:$A,_xlfn.CONCAT('II-H-4.1 Functions'!Q$13,'II-H-4.1 Functions'!$B26),Riders!$Q:$Q) -> 0 | R26: =L26+M26+N26+O26+P26+Q26 -> 1288934.6 | T26: =R26+J26 -> 17314636
A27: 10 | B27: TOTAL PRIMARY | D27: =SUM(D23:D26) -> 95902.273 | E27: =SUM(E23:E26) -> 1655390.7 | F27: =SUM(F23:F26) -> 34709862 | G27: =SUM(G23:G26) -> 0 | H27: =SUM(H23:H26) -> 6303373.3 | I27: =SUM(I23:I26) -> 44440660 | J27: =SUM(J23:J26) -> 87205188 | L27: =SUM(L23:L26) -> 484462 | M27: =SUM(M23:M26) -> 1583104.5 | N27: =SUM(N23:N26) -> 6055191 | O27: =SUM(O23:O26) -> 96151.74 | P27: =SUM(P23:P26) -> 1497618.7 | Q27: =SUM(Q23:Q26) -> 0 | R27: =SUM(R23:R26) -> 9716527.9 | T27: =SUM(T23:T26) -> 96921716
A29: 11 | B29: TRANSMISSION | C29: TRA | D29: =+'[6]Functional Rev Unadjusted'!$C$73 -> 11562.115 | E29: =+'[6]Functional Rev Unadjusted'!$D$73 -> 1177079 | F29: =+'[6]Functional Rev Unadjusted'!$E$73 -> 8391200.7 | H29: =+'TCRF and DCRF Rider Revenues'!P23 -> 80713.96 | I29: =+'TCRF and DCRF Rider Revenues'!P11 -> 52489197 | J29: =SUM(D29:I29) -> 62149753 | L29: =VLOOKUP(_xlfn.CONCAT(L$13,$B29),Riders!$A$11:$Q$328,17,FALSE) -> 0 | M29: =VLOOKUP(_xlfn.CONCAT(M$13,$B29),Riders!$A$11:$Q$328,17,FALSE) -> 4303.27 | N29: =VLOOKUP(_xlfn.CONCAT(N$13,$B29),Riders!$A$11:$Q$328,17,FALSE) -> 4110819.2 | O29: =VLOOKUP(_xlfn.CONCAT(O$13,$B29),Riders!$A$11:$Q$328,17,FALSE) -> 0 | P29: =VLOOKUP(_xlfn.CONCAT(P$13,$B29),Riders!$A$11:$Q$328,17,FALSE) -> 0 | Q29: =SUMIF(Riders!$A:$A,_xlfn.CONCAT('II-H-4.1 Functions'!Q$13,'II-H-4.1 Functions'!$B29),Riders!$Q:$Q) -> -5266 | R29: =L29+M29+N29+O29+P29+Q29 -> 4109856.4 | T29: =R29+J29 -> 66259609
J30: =SUM(D30:I30) -> 0
A31: 12 | B31: LIGHTING | C31: SEC | D31: =+'[6]Functional Rev Unadjusted'!$C$74 -> 44131.71 | E31: =+'[6]Functional Rev Unadjusted'!$D$74 -> 0 | F31: =+'[6]Functional Rev Unadjusted'!$E$74+'[6]Functional Rev Unadjusted'!$F$74 -> 21637686 | G31: 0 | H31: =+'TCRF and DCRF Rider Revenues'!P24 -> 2033143.5 | I31: =+'TCRF and DCRF Rider Revenues'!P12 -> 2311937 | J31: =SUM(D31:I31) -> 26026898 | L31: =VLOOKUP(_xlfn.CONCAT(L$13,$B31),Riders!$A$11:$Q$328,17,FALSE) -> 64983.18 | M31: =VLOOKUP(_xlfn.CONCAT(M$13,$B31),Riders!$A$11:$Q$328,17,FALSE) -> 0.31 | N31: =VLOOKUP(_xlfn.CONCAT(N$13,$B31),Riders!$A$11:$Q$328,17,FALSE) -> 1252617.1 | O31: =VLOOKUP(_xlfn.CONCAT(O$13,$B31),Riders!$A$11:$Q$328,17,FALSE) -> 27853.23 | P31: =VLOOKUP(_xlfn.CONCAT(P$13,$B31),Riders!$A$11:$Q$328,17,FALSE) -> 1677521.3 | Q31: =SUMIF(Riders!$A:$A,_xlfn.CONCAT('II-H-4.1 Functions'!Q$13,'II-H-4.1 Functions'!$B31),Riders!$Q:$Q) -> 185.46 | R31: =L31+M31+N31+O31+P31+Q31 -> 3023160.6 | T31: =R31+J31 -> 29050058
A33: 13 | B33: TOTAL RETAIL | D33: =D31+D29+D27+D21+D17+D15 -> 19104111 | E33: =E31+E29+E27+E21+E17+E15 -> 56476089 | F33: =F31+F29+F27+F21+F17+F15 -> 5.1182396e+08 | G33: =G31+G29+G27+G21+G17+G15 -> 4260.12 | H33: =H31+H29+H27+H21+H17+H15 -> 1.0486786e+08 | I33: =I31+I29+I27+I21+I17+I15 -> 4.2181728e+08 | J33: =J31+J29+J27+J21+J17+J15 -> 1.1140936e+09 | L33: =L31+L29+L27+L21+L17+L15 -> 5308009.1 | M33: =M31+M29+M27+M21+M17+M15 -> 25957339 | N33: =N31+N29+N27+N21+N17+N15 -> 73475236 | O33: =O31+O29+O27+O21+O17+O15 -> 1960407.8 | P33: =P31+P29+P27+P21+P17+P15 -> 26545183 | Q33: =Q31+Q29+Q27+Q21+Q17+Q15 -> -4939.61 | R33: =R31+R29+R27+R21+R17+R15 -> 1.3324124e+08 | T33: =R33+J33 -> 1.2473348e+09
A35: 14 | B35: WHOLESALE PRI | C35: PRI | J35: =SUM(D35:I35) -> 0 | R35: =SUM(L35:Q35) -> 0 | T35: =R35+J35 -> 0
A36: 15 | B36: WHOLESALE TRANS | C36: TRA | T36: =R36+J36 -> 0
A37: 16 | B37: TOTAL WHOLESALE | D37: =SUM(D35:D36) -> 0 | E37: =SUM(E35:E36) -> 0 | F37: =SUM(F35:F36) -> 0 | G37: =SUM(G35:G36) -> 0 | I37: =SUM(I35:I36) -> 0 | J37: =SUM(J35:J36) -> 0 | L37: =SUM(L35:L36) -> 0 | M37: =SUM(M35:M36) -> 0 | N37: 0 | O37: =SUM(O35:O36) -> 0 | P37: =SUM(P35:P36) -> 0 | Q37: =SUM(Q35:Q36) -> 0 | R37: =SUM(R35:R36) -> 0 | T37: =R37+J37 -> 0
A39: 17 | B39: TOTAL AEP TEXAS | D39: =+D37+D33 -> 19104111 | E39: =+E37+E33 -> 56476089 | F39: =+F37+F33 -> 5.1182396e+08 | G39: =+G37+G33 -> 4260.12 | H39: =+H37+H33 -> 1.0486786e+08 | I39: =+I37+I33 -> 4.2181728e+08 | J39: =+J37+J33 -> 1.1140936e+09 | L39: =+L37+L33 -> 5308009.1 | M39: =+M37+M33 -> 25957339 | N39: =+N37+N33 -> 73475236 | O39: =+O37+O33 -> 1960407.8 | P39: =+P37+P33 -> 26545183 | Q39: =+Q37+Q33 -> -4939.61 | R39: =+R37+R33 -> 1.3324124e+08 | T39: =R39+J39 -> 1.2473348e+09
J41: =+'II-H-4.1 Monthly'!P39 -> 1.2473305e+09 | T41: =+J41-T39 -> -4260.12 | U41: Est Bills
A44: =+A8 -> AEP TEXAS
A45: BASE TARIFF AND RIDER REVENUE ADJUSTMENTS
A46: =+A10 -> FOR TEST YEAR ENDED SEPTEMBER 30, 2023
A49: LINE | B49: DESCRIPTION | C49: VOLT | D49: =$D$13 -> Customer Revenue - Base Tariff | E49: =$E$13 -> Meter Revenue - Base Tariff | F49: Distribution Service Revenue - Base Tariff (Energy Efficiency) | G49: =$G$13 -> Facilities Charge | H49: =+H13 -> DCRF Revenue | I49: =$I$13 -> TCRF Revenue | J49: =$J$13 -> Total Base Tariff Revenue | L49: =+L13 -> TTRAR | M49: =+M13 -> EECR | N49: =+N13 -> TC3 | O49: =+O13 -> MTEEE | P49: =+P13 -> SRC | Q49: =+Q13 -> Miscellaneous Riders | R49: =$R$13 -> Total Riders | T49: =$T$13 -> Total Revenue
A51: 1 | B51: RESIDENTIAL SERVICE | C51: SEC | H51: =+-H15 -> -60613642 | I51: =-I15 -> -1.9521636e+08 | J51: =SUM(D51:I51) -> -2.5583e+08 | L51: =-L15 -> -2981645.4 | M51: =-M15 -> -14232787 | N51: =-N15 -> -27997172 | O51: =-O15 -> -1232462.1 | P51: =-P15 -> -14176856 | Q51: =-Q15 -> -96.33 | R51: =SUM(L51:Q51) -> -60621019 | T51: =R51+J51 -> -3.1645102e+08
A53: 2 | B53: SECONDARY < 10 kW | C53: SEC | H53: =+-H17 -> -5782103.6 | I53: =-I17 -> -6531262.9 | J53: =SUM(D53:I53) -> -12313367 | L53: =-L17 -> -115912.84 | M53: =-M17 -> -627738 | N53: =-N17 -> -4512469.5 | O53: =-O17 -> -107094.36 | P53: =-P17 -> -706508.43 | Q53: =-Q17 -> -54.79 | R53: =SUM(L53:Q53) -> -6069777.9 | T53: =R53+J53 -> -18383144
A55: 3 | B55: SECONDARY > 10 kW NCP | C55: SEC | H55: =+-H19 -> -26612208 | I55: =-I19 -> -1.0750111e+08 | J55: =SUM(D55:I55) -> -1.3411332e+08 | L55: =-L19 -> -1471094.9 | M55: =-M19 -> -8162304.2 | N55: =-N19 -> -27005443 | O55: =-O19 -> -438124.11 | P55: =-P19 -> -7674626.1 | Q55: =-Q19 -> 10.19 | R55: =SUM(L55:Q55) -> -44751582 | T55: =R55+J55 -> -1.788649e+08
A56: 4 | B56: SECONDARY > 10 kW 4CP | C56: SEC | H56: =+-H20 -> -3442679.6 | I56: =-I20 -> -13326752 | J56: =SUM(D56:I56) -> -16769432 | L56: =-L20 -> -189910.7 | M56: =-M20 -> -1347101.6 | N56: =-N20 -> -2541524.5 | O56: =-O20 -> -58722.27 | P56: =-P20 -> -812052.25 | Q56: =-Q20 -> 0 | R56: =SUM(L56:Q56) -> -4949311.3 | T56: =R56+J56 -> -21718743
A57: 5 | B57: TOTAL SECONDARY > 10 kW | D57: =SUM(D55:D56) -> 0 | E57: =SUM(E55:E56) -> 0 | F57: =SUM(F55:F56) -> 0 | G57: =SUM(G55:G56) -> 0 | H57: =SUM(H55:H56) -> -30054888 | I57: =SUM(I55:I56) -> -1.2082786e+08 | J57: =SUM(J55:J56) -> -1.5088275e+08 | L57: =-L21 -> -1661005.6 | M57: =-M21 -> -9509405.7 | N57: =-N21 -> -29546967 | O57: =-O21 -> -496846.38 | P57: =SUM(P55:P56) -> -8486678.4 | Q57: =-Q21 -> 10.19 | R57: =SUM(L57:Q57) -> -49700893 | T57: =R57+J57 -> -2.0058364e+08
A59: 6 | B59: PRIMARY NCP | C59: PRI | H59: =+-H23 -> -421784.89 | I59: =-I23 -> -2618516.5 | J59: =SUM(D59:I59) -> -3040301.3 | L59: =-L23 -> -32510.42 | M59: =-M23 -> -98002.21 | N59: =-N23 -> -452588.2 | O59: =-O23 -> -5785.05 | P59: =-P23 -> -97823.41 | Q59: =-Q23 -> 0 | R59: =SUM(L59:Q59) -> -686709.29 | T59: =R59+J59 -> -3727010.6
A60: 7 | B60: PRIMARY 4CP | C60: PRI | H60: =+-H24 -> -4675651.1 | I60: =-I24 -> -33583174 | J60: =SUM(D60:I60) -> -38258825 | L60: =-L24 -> -359059.31 | M60: =-M24 -> -1194247.3 | N60: =-N24 -> -4901564.6 | O60: =-O24 -> -73420.28 | P60: =-P24 -> -1200696.1 | Q60: =-Q24 -> 0 | R60: =SUM(L60:Q60) -> -7728987.6 | T60: =R60+J60 -> -45987812
A61: 8 | B61: PRIMARY SUB NCP | C61: PRI | H61: =+-H25 -> -10636.06 | I61: =-I25 -> -57797.47 | J61: =SUM(D61:I61) -> -68433.53 | L61: =-L25 -> -814.53 | M61: =-M25 -> -2231.71 | N61: =-N25 -> -6733.65 | O61: =-O25 -> -182.56 | P61: =-P25 -> -1933.99 | Q61: =-Q25 -> 0 | R61: =SUM(L61:Q61) -> -11896.44 | T61: =R61+J61 -> -80329.97
A62: 9 | B62: PRIMARY SUB 4CP | C62: PRI | H62: =+-H26 -> -1195301.3 | I62: =-I26 -> -8181172.7 | J62: =SUM(D62:I62) -> -9376474 | L62: =-L26 -> -92077.74 | M62: =-M26 -> -288623.29 | N62: =-N26 -> -694304.52 | O62: =-O26 -> -16763.85 | P62: =-P26 -> -197165.24 | Q62: =-Q26 -> 0 | R62: =SUM(L62:Q62) -> -1288934.6 | T62: =R62+J62 -> -10665409
A63: 10 | B63: TOTAL PRIMARY | D63: =SUM(D59:D62) -> 0 | E63: =SUM(E59:E62) -> 0 | F63: =SUM(F59:F62) -> 0 | G63: =SUM(G59:G62) -> 0 | H63: =SUM(H59:H62) -> -6303373.3 | I63: =SUM(I59:I62) -> -44440660 | J63: =SUM(J59:J62) -> -50744034 | L63: =SUM(L59:L62) -> -484462 | M63: =SUM(M59:M62) -> -1583104.5 | N63: =SUM(N59:N62) -> -6055191 | O63: =SUM(O59:O62) -> -96151.74 | P63: =SUM(P59:P62) -> -1497618.7 | Q63: =SUM(Q59:Q62) -> 0 | R63: =SUM(R59:R62) -> -9716527.9 | T63: =SUM(T59:T62) -> -60460561
A65: 11 | B65: TRANSMISSION | C65: TRA | H65: =+-H29 -> -80713.96 | I65: =-I29 -> -52489197 | J65: =SUM(D65:I65) -> -52569911 | L65: =-L29 -> 0 | M65: =-M29 -> -4303.27 | N65: =-N29 -> -4110819.2 | O65: =-O29 -> 0 | P65: =-P29 -> 0 | Q65: =-Q29 -> 5266 | R65: =SUM(L65:Q65) -> -4109856.4 | T65: =R65+J65 -> -56679767
A67: 12 | B67: LIGHTING | C67: SEC | H67: =+-H31 -> -2033143.5 | I67: =-I31 -> -2311937 | J67: =SUM(D67:I67) -> -4345080.5 | L67: =-L31 -> -64983.18 | M67: =-M31 -> -0.31 | N67: =-N31 -> -1252617.1 | O67: =-O31 -> -27853.23 | P67: =-P31 -> -1677521.3 | Q67: =-Q31 -> -185.46 | R67: =SUM(L67:Q67) -> -3023160.6 | T67: =R67+J67 -> -7368241.1
A69: 13 | B69: TOTAL RETAIL | D69: =D67+D65+D63+D57+D53+D51 -> 0 | E69: =E67+E65+E63+E57+E53+E52 -> 0 | F69: =F67+F65+F63+F57+F53+F52 -> 0 | G69: =G67+G65+G63+G57+G53+G52 -> 0 | H69: =H67+H65+H63+H57+H53+H51 -> -1.0486786e+08 | I69: =I67+I65+I63+I57+I53+I51 -> -4.2181728e+08 | J69: =SUM(D69:I69) -> -5.2668515e+08 | L69: =+L51+L53+L57+L63+L65+L67 -> -5308009.1 | M69: =+M51+M53+M57+M63+M65+M67 -> -25957339 | N69: =+N51+N53+N57+N63+N65+N67 -> -73475236 | O69: =+O51+O53+O57+O63+O65+O67 -> -1960407.8 | P69: =+P51+P53+P57+P63+P65+P67 -> -26545183 | Q69: =+Q51+Q53+Q57+Q63+Q65+Q67 -> 4939.61 | R69: =+R51+R53+R57+R63+R65+R67 -> -1.3324124e+08 | T69: =R69+J69 -> -6.5992638e+08
A71: 14 | B71: WHOLESALE PRI | C71: PRI | I71: =-I35 -> 0 | J71: =SUM(D71:I71) -> 0 | L71: =-L35 -> 0 | M71: =-M35 -> 0 | N71: =+N35 -> 0 | O71: =-O35 -> 0 | P71: =-P35 -> 0 | Q71: =-Q35 -> 0 | R71: =SUM(L71:Q71) -> 0 | T71: =R71+J71 -> 0
A72: 15 | B72: WHOLESALE TRANS | C72: TRA | L72: =-L36 -> 0 | M72: =-M36 -> 0 | O72: =-O36 -> 0 | P72: =-P36 -> 0 | Q72: =-Q36 -> 0 | T72: =R72+J72 -> 0
A73: 16 | B73: TOTAL WHOLESALE | D73: =SUM(D71:D72) -> 0 | E73: =SUM(E71:E72) -> 0 | F73: =SUM(F71:F72) -> 0 | G73: =SUM(G71:G72) -> 0 | H73: =SUM(H71:H72) -> 0 | I73: =SUM(I71:I72) -> 0 | J73: =SUM(J71:J72) -> 0 | L73: =-L37 -> 0 | M73: =-M37 -> 0 | N73: =-N37 -> 0 | O73: =-O37 -> 0 | P73: =-P37 -> 0 | Q73: =-Q37 -> 0 | R73: =SUM(L73:Q73) -> 0 | T73: =R73+J73 -> 0
A75: 17 | B75: TOTAL AEP TEXAS | D75: =+D73+D69 -> 0 | E75: =+E73+E69 -> 0 | F75: =+F73+F69 -> 0 | G75: =+G73+G69 -> 0 | H75: =+H73+H69 -> -1.0486786e+08 | I75: =+I73+I69 -> -4.2181728e+08 | J75: =+J73+J69 -> -5.2668515e+08 | L75: =-L39 -> -5308009.1 | M75: =-M39 -> -25957339 | N75: =-N39 -> -73475236 | O75: =-O39 -> -1960407.8 | P75: =-P39 -> -26545183 | Q75: =-Q39 -> 4939.61 | R75: =SUM(L75:Q75) -> -1.3324124e+08 | T75: =R75+J75 -> -6.5992638e+08
A79: =+A8 -> AEP TEXAS
A80: CUSTOMER ADJUSTMENT
A81: =A10 -> FOR TEST YEAR ENDED SEPTEMBER 30, 2023
A84: LINE | B84: DESCRIPTION | C84: VOLT | D84: =$D$13 -> Customer Revenue - Base Tariff | E84: =$E$13 -> Meter Revenue - Base Tariff | F84: =$F$13 -> Distribution Service Revenue - Base Tariff | G84: =$G$13 -> Facilities Charge | H84: =+H13 -> DCRF Revenue | I84: =$I$13 -> TCRF Revenue | J84: =$J$13 -> Total Base Tariff Revenue | L84: =+L13 -> TTRAR | M84: =+M13 -> EECR | N84: =+N13 -> TC3 | O84: =+O13 -> MTEEE | P84: =+P13 -> SRC | Q84: =+Q13 -> Miscellaneous Riders | R84: =$R$13 -> Total Riders | T84: =$T$13 -> Total Revenue
A86: 1 | B86: RESIDENTIAL SERVICE | C86: SEC | D86: =+'II-H-3.1-3'!P48*'II-H-3.1-3'!R14 -> 151843.05 | E86: =+'II-H-3.1-3'!P48*'II-H-3.1-3'!S14 -> 367677.1 | F86: =+'II-H-4.1 Monthly'!P286-'II-H-4.1 Functions'!D86-'II-H-4.1 Functions'!E86 -> 2307803.6 | J86: =SUM(D86:I86) -> 2827323.7 | R86: =SUM(L86:Q86) -> 0 | T86: =R86+J86 -> 2827323.7
A88: 2 | B88: SECONDARY < 10 kW | C88: SEC | D88: =+'II-H-3.1-3'!P50*'II-H-3.1-3'!R16 -> 9573.2 | E88: =+'II-H-3.1-3'!P50*'II-H-3.1-3'!S16 -> 30018.82 | F88: =+'II-H-4.1 Monthly'!P288-'II-H-4.1 Functions'!D88-'II-H-4.1 Functions'!E88 -> 44488.277 | J88: =SUM(D88:I88) -> 84080.297 | R88: =SUM(L88:Q88) -> 0 | T88: =R88+J88 -> 84080.297
A90: 3 | B90: SECONDARY > 10 kW NCP | C90: SEC | D90: =+'II-H-3.1-3'!P52*'II-H-3.1-3'!R18 -> 8119.4827 | E90: =+'II-H-3.1-3'!P52*'II-H-3.1-3'!S18 -> 51174.13 | F90: =+'II-H-4.1 Monthly'!P290-'II-H-4.1 Functions'!D90-'II-H-4.1 Functions'!E90 -> 780127.49 | J90: =SUM(D90:I90) -> 839421.11 | R90: =SUM(L90:Q90) -> 0 | T90: =R90+J90 -> 839421.11
A91: 4 | B91: SECONDARY > 10 kW 4CP | C91: SEC | D91: =+'II-H-3.1-3'!P53*'II-H-3.1-3'!R19 -> 129.28 | E91: =+'II-H-3.1-3'!P53*'II-H-3.1-3'!S19 -> 810.88 | F91: =+'II-H-4.1 Monthly'!P291-'II-H-4.1 Functions'!D91-'II-H-4.1 Functions'!E91 -> 164843.58 | J91: =SUM(D91:I91) -> 165783.74 | R91: =SUM(L91:Q91) -> 0 | T91: =R91+J91 -> 165783.74
A92: 5 | B92: TOTAL SECONDARY > 10 kW | D92: =SUM(D90:D91) -> 8248.7627 | E92: =SUM(E90:E91) -> 51985.01 | F92: =SUM(F90:F91) -> 944971.07 | G92: =SUM(G90:G91) -> 0 | I92: =SUM(I90:I91) -> 0 | J92: =SUM(D92:I92) -> 1005204.8 | L92: =SUM(L90:L91) -> 0 | M92: =SUM(M90:M91) -> 0 | O92: =SUM(O90:O91) -> 0 | P92: =SUM(P90:P91) -> 0 | R92: =SUM(L92:Q92) -> 0 | T92: =SUM(T90:T91) -> 1005204.8
A94: 6 | B94: PRIMARY NCP | C94: PRI | D94: =+'II-H-3.1-3'!P56*'II-H-3.1-3'!R22 -> -29.176254 | E94: =+'II-H-3.1-3'!P56*'II-H-3.1-3'!S22 -> -507.48 | F94: =+'II-H-4.1 Monthly'!P294-'II-H-4.1 Functions'!D94-'II-H-4.1 Functions'!E94 -> -4974.2161 | J94: =SUM(D94:I94) -> -5510.8724 | R94: =SUM(L94:Q94) -> 0 | T94: =R94+J94 -> -5510.8724
A95: 7 | B95: PRIMARY 4CP | C95: PRI | D95: =+'II-H-3.1-3'!P57*'II-H-3.1-3'!R23 -> -535.89643 | E95: =+'II-H-3.1-3'!P57*'II-H-3.1-3'!S23 -> -9261.51 | F95: =+'II-H-4.1 Monthly'!P295-'II-H-4.1 Functions'!D95-'II-H-4.1 Functions'!E95 -> -315053.12 | J95: =SUM(D95:I95) -> -324850.52 | R95: =SUM(L95:Q95) -> 0 | T95: =R95+J95 -> -324850.52
A96: 8 | B96: PRIMARY SUB NCP | C96: PRI | D96: =+'II-H-3.1-3'!P58*'II-H-3.1-3'!R24 -> 0 | E96: =+'II-H-3.1-3'!P58*'II-H-3.1-3'!S24 -> 0 | F96: =+'II-H-4.1 Monthly'!P296-'II-H-4.1 Functions'!D96-'II-H-4.1 Functions'!E96 -> 0 | J96: =SUM(D96:I96) -> 0 | R96: =SUM(L96:Q96) -> 0 | T96: =R96+J96 -> 0
A97: 9 | B97: PRIMARY SUB 4CP | C97: PRI | D97: =+'II-H-3.1-3'!P59*'II-H-3.1-3'!R25 -> 0 | E97: =+'II-H-3.1-3'!P59*'II-H-3.1-3'!S25 -> 0 | F97: =+'II-H-4.1 Monthly'!P297-'II-H-4.1 Functions'!D97-'II-H-4.1 Functions'!E97 -> 0 | J97: =SUM(D97:I97) -> 0 | R97: =SUM(L97:Q97) -> 0 | T97: =R97+J97 -> 0
A98: 10 | B98: TOTAL PRIMARY | D98: =SUM(D94:D97) -> -565.07269 | E98: =SUM(E94:E97) -> -9768.99 | F98: =SUM(F94:F97) -> -320027.33 | G98: =SUM(G94:G97) -> 0 | H98: =SUM(H94:H97) -> 0 | I98: =SUM(I94:I97) -> 0 | J98: =SUM(J94:J97) -> -330361.4 | L98: =SUM(L94:L97) -> 0 | M98: =SUM(M94:M97) -> 0 | N98: =SUM(N94:N97) -> 0 | O98: =SUM(O94:O97) -> 0 | P98: =SUM(P94:P97) -> 0 | Q98: =SUM(Q94:Q97) -> 0 | R98: =SUM(R94:R97) -> 0 | T98: =SUM(T94:T97) -> -330361.4
A100: 11 | B100: TRANSMISSION | C100: TRA | D100: =+'II-H-3.1-3'!P62*'II-H-3.1-3'!R28 -> -104.72 | E100: =+'II-H-3.1-3'!P62*'II-H-3.1-3'!S28 -> -10661 | F100: =+'II-H-4.1 Monthly'!P300-'II-H-4.1 Functions'!D100-'II-H-4.1 Functions'!E100 -> -96990.5 | J100: =SUM(D100:I100) -> -107756.22 | R100: =SUM(L100:Q100) -> 0 | T100: =R100+J100 -> -107756.22
A102: 12 | B102: LIGHTING | C102: SEC | D102: =+'II-H-3.1-3'!P64*'II-H-3.1-3'!R30 -> 0 | E102: =+'II-H-3.1-3'!P64*'II-H-3.1-3'!S30 -> 0 | F102: =+'II-H-4.1 Monthly'!P302-'II-H-4.1 Functions'!D102-'II-H-4.1 Functions'!E102 -> -55208.544 | G102: =($G$31/'II-H-3.1-3'!$P$30)*'II-H-3.1-3'!P64 -> 0 | J102: =SUM(D102:I102) -> -55208.544 | R102: =SUM(L102:Q102) -> 0 | T102: =R102+J102 -> -55208.544
A104: 13 | B104: TOTAL RETAIL | D104: =D102+D100+D98+D92+D88+D86 -> 168995.22 | E104: =E102+E100+E98+E92+E88+E86 -> 429250.94 | F104: =F102+F100+F98+F92+F88+F86 -> 2825036.6 | G104: =G102+G100+G98+G92+G88+G86 -> 0 | I104: =I102+I100+I98+I92+I88+I86 -> 0 | J104: =SUM(D104:I104) -> 3423282.7 | L104: =L102+L100+L98+L92+L88+L86 -> 0 | M104: =M102+M100+M98+M92+M88+M86 -> 0 | O104: =O102+O100+O98+O92+O88+O86 -> 0 | P104: =P102+P100+P98+P92+P88+P86 -> 0 | Q104: =Q102+Q100+Q98+Q92+Q88+Q86 -> 0 | R104: =R102+R100+R98+R92+R88+R86 -> 0 | T104: =T102+T100+T98+T92+T88+T86 -> 3423282.7
A106: 14 | B106: WHOLESALE PRI | C106: PRI | J106: =SUM(D106:I106) -> 0 | R106: =SUM(L106:Q106) -> 0 | T106: =R106+J106 -> 0
A107: 15 | B107: WHOLESALE TRANS | C107: TRA | J107: =SUM(D107:I107) -> 0 | R107: =SUM(L107:Q107) -> 0 | T107: =R107+J107 -> 0
A108: 16 | B108: TOTAL WHOLESALE | D108: =SUM(D106:D107) -> 0 | E108: =SUM(E106:E107) -> 0 | F108: =SUM(F106:F107) -> 0 | G108: =SUM(G106:G107) -> 0 | I108: =SUM(I106:I107) -> 0 | J108: =SUM(D108:I108) -> 0 | L108: =SUM(L106:L107) -> 0 | M108: =SUM(M106:M107) -> 0 | O108: =SUM(O106:O107) -> 0 | P108: =SUM(P106:P107) -> 0 | R108: =SUM(L108:Q108) -> 0 | T108: =SUM(T106:T107) -> 0
A110: 17 | B110: TOTAL AEP TEXAS | D110: =+D108+D104 -> 168995.22 | E110: =+E108+E104 -> 429250.94 | F110: =+F108+F104 -> 2825036.6 | G110: =+G108+G104 -> 0 | I110: =+I108+I104 -> 0 | J110: =SUM(D110:I110) -> 3423282.7 | L110: =+L108+L104 -> 0 | M110: =+M108+M104 -> 0 | O110: =+O108+O104 -> 0 | P110: =+P108+P104 -> 0 | Q110: =+Q108+Q104 -> 0 | R110: =+R108+R104 -> 0 | T110: =R110+J110 -> 3423282.7
A113: =+A8 -> AEP TEXAS
A114: WEATHER ADJUSTMENT
A115: =A10 -> FOR TEST YEAR ENDED SEPTEMBER 30, 2023
A118: LINE | B118: DESCRIPTION | C118: VOLT | D118: =$D$13 -> Customer Revenue - Base Tariff | E118: =$E$13 -> Meter Revenue - Base Tariff | F118: =$F$13 -> Distribution Service Revenue - Base Tariff | G118: =$G$13 -> Facilities Charge | H118: =+H13 -> DCRF Revenue | I118: =$I$13 -> TCRF Revenue | J118: =$J$13 -> Total Base Tariff Revenue | L118: =+L13 -> TTRAR | M118: =+M13 -> EECR | N118: =+N13 -> TC3 | O118: =+O13 -> MTEEE | P118: =+P13 -> SRC | Q118: =+Q13 -> Miscellaneous Riders | R118: =$R$13 -> Total Riders | T118: =$T$13 -> Total Revenue
A120: 1 | B120: RESIDENTIAL SERVICE | C120: SEC | F120: ='II-H-4.1 Monthly'!P318 -> -6822080.4 | J120: =SUM(D120:I120) -> -6822080.4 | R120: =SUM(L120:Q120) -> 0 | T120: =R120+J120 -> -6822080.4
A122: 2 | B122: SECONDARY < 10 kW | C122: SEC | F122: ='II-H-4.1 Monthly'!P320 -> -184937.24 | J122: =SUM(D122:I122) -> -184937.24 | R122: =SUM(L122:Q122) -> 0 | T122: =R122+J122 -> -184937.24
A124: 3 | B124: SECONDARY > 10 kW NCP | C124: SEC | F124: ='II-H-4.1 Monthly'!P322 -> -1744192.1 | J124: =SUM(D124:I124) -> -1744192.1 | R124: =SUM(L124:Q124) -> 0 | T124: =R124+J124 -> -1744192.1
A125: 4 | B125: SECONDARY > 10 kW 4CP | C125: SEC | F125: ='II-H-4.1 Monthly'!P323 -> -105136.33 | J125: =SUM(D125:I125) -> -105136.33 | R125: =SUM(L125:Q125) -> 0 | T125: =R125+J125 -> -105136.33
A126: 5 | B126: TOTAL SECONDARY > 10 kW | D126: =SUM(D124:D125) -> 0 | E126: =SUM(E124:E125) -> 0 | F126: =SUM(F124:F125) -> -1849328.5 | G126: =SUM(G124:G125) -> 0 | I126: =SUM(I124:I125) -> 0 | J126: =SUM(J124:J125) -> -1849328.5 | L126: =SUM(L124:L125) -> 0 | M126: =SUM(M124:M125) -> 0 | O126: =SUM(O124:O125) -> 0 | P126: =SUM(P124:P125) -> 0 | Q126: =SUM(Q124:Q125) -> 0 | R126: =SUM(L126:Q126) -> 0 | T126: =R126+J126 -> -1849328.5
A128: 6 | B128: PRIMARY NCP | C128: PRI | F128: ='II-H-4.1 Monthly'!P326 -> -18720.382 | J128: =SUM(D128:I128) -> -18720.382 | R128: =SUM(L128:Q128) -> 0 | T128: =R128+J128 -> -18720.382
A129: 7 | B129: PRIMARY 4CP | C129: PRI | F129: ='II-H-4.1 Monthly'!P327 -> -215756.39 | J129: =SUM(D129:I129) -> -215756.39 | R129: =SUM(L129:Q129) -> 0 | T129: =R129+J129 -> -215756.39
A130: 8 | B130: PRIMARY SUB NCP | C130: PRI | F130: ='II-H-4.1 Monthly'!P328 -> 0
A131: 9 | B131: PRIMARY SUB 4CP | C131: PRI | F131: ='II-H-4.1 Monthly'!P329 -> 0
A132: 10 | B132: TOTAL PRIMARY | D132: =SUM(D128:D131) -> 0 | E132: =SUM(E128:E131) -> 0 | F132: =SUM(F128:F131) -> -234476.77 | G132: =SUM(G128:G131) -> 0 | H132: =SUM(H128:H131) -> 0 | I132: =SUM(I128:I131) -> 0 | J132: =SUM(J128:J131) -> -234476.77 | L132: =SUM(L128:L129) -> 0 | M132: =SUM(M128:M129) -> 0 | O132: =SUM(O128:O129) -> 0 | P132: =SUM(P128:P129) -> 0 | Q132: =SUM(Q128:Q129) -> 0 | R132: =SUM(L132:Q132) -> 0 | T132: =R132+J132 -> -234476.77
A134: 11 | B134: TRANSMISSION | C134: TRA | F134: =+'II-H-4.1 Monthly'!P332 -> -749.674 | J134: =SUM(D134:I134) -> -749.674 | R134: =SUM(L134:Q134) -> 0 | T134: =R134+J134 -> -749.674
A136: 12 | B136: LIGHTING | C136: SEC | J136: =SUM(D136:I136) -> 0 | R136: =SUM(L136:Q136) -> 0 | T136: =R136+J136 -> 0
A138: 13 | B138: TOTAL RETAIL | D138: =D136+D134+D132+D126+D122+D120 -> 0 | E138: =E136+E134+E132+E126+E122+E120 -> 0 | F138: =F136+F134+F132+F126+F122+F120 -> -9091572.5 | G138: =G136+G134+G132+G126+G122+G120 -> 0 | I138: =I136+I134+I132+I126+I122+I120 -> 0 | J138: =J136+J134+J132+J126+J122+J120 -> -9091572.5 | L138: =L136+L134+L132+L126+L122+L120 -> 0 | M138: =M136+M134+M132+M126+M122+M120 -> 0 | O138: =O136+O134+O132+O126+O122+O120 -> 0 | P138: =P136+P134+P132+P126+P122+P120 -> 0 | Q138: =Q136+Q134+Q132+Q126+Q122+Q120 -> 0 | R138: =SUM(L138:Q138) -> 0 | T138: =R138+J138 -> -9091572.5
A140: 14 | B140: WHOLESALE PRI | C140: PRI | J140: =SUM(D140:I140) -> 0 | R140: =SUM(L140:Q140) -> 0 | T140: =R140+J140 -> 0
A141: 15 | B141: WHOLESALE TRANS | C141: TRA | J141: =SUM(D141:I141) -> 0 | R141: =SUM(L141:Q141) -> 0 | T141: =R141+J141 -> 0
A142: 16 | B142: TOTAL WHOLESALE | D142: =SUM(D140:D141) -> 0 | E142: =SUM(E140:E141) -> 0 | F142: =SUM(F140:F141) -> 0 | G142: =SUM(G140:G141) -> 0 | I142: =SUM(I140:I141) -> 0 | J142: =SUM(J140:J141) -> 0 | L142: =SUM(L140:L141) -> 0 | M142: =SUM(M140:M141) -> 0 | O142: =SUM(O140:O141) -> 0 | P142: =SUM(P140:P141) -> 0 | Q142: =SUM(Q140:Q141) -> 0 | R142: =SUM(L142:Q142) -> 0 | T142: =R142+J142 -> 0
A144: 17 | B144: TOTAL AEP TEXAS | D144: =+D142+D138 -> 0 | E144: =+E142+E138 -> 0 | F144: =+F142+F138 -> -9091572.5 | G144: =+G142+G138 -> 0 | I144: =+I142+I138 -> 0 | J144: =+J142+J138 -> -9091572.5 | L144: =+L142+L138 -> 0 | M144: =+M142+M138 -> 0 | O144: =+O142+O138 -> 0 | P144: =+P142+P138 -> 0 | Q144: =+Q142+Q138 -> 0 | R144: =SUM(L144:Q144) -> 0 | T144: =R144+J144 -> -9091572.5
A148: =+A8 -> AEP TEXAS
A149: OTHER REVENUE ADJUSTMENTS
A150: =A10 -> FOR TEST YEAR ENDED SEPTEMBER 30, 2023
A153: LINE | B153: DESCRIPTION | C153: VOLT | D153: =$D$13 -> Customer Revenue - Base Tariff | E153: =$E$13 -> Meter Revenue - Base Tariff | F153: =$F$13 -> Distribution Service Revenue - Base Tariff | G153: =$G$13 -> Facilities Charge | H153: =+H13 -> DCRF Revenue | I153: =$I$13 -> TCRF Revenue | J153: =$J$13 -> Total Base Tariff Revenue | L153: =+L13 -> TTRAR | M153: =+M13 -> EECR | N153: =+N13 -> TC3 | O153: =+O13 -> MTEEE | P153: =+P13 -> SRC | Q153: =+Q13 -> Miscellaneous Riders | R153: =$R$13 -> Total Riders | T153: =$T$13 -> Total Revenue
A155: 1 | B155: RESIDENTIAL SERVICE | C155: SEC | J155: =SUM(D155:I155) -> 0 | R155: =SUM(L155:Q155) -> 0 | T155: =R155+J155 -> 0
A157: 2 | B157: SECONDARY < 10 kW | C157: SEC | J157: =SUM(D157:I157) -> 0 | R157: =SUM(L157:Q157) -> 0 | T157: =R157+J157 -> 0
A159: 3 | B159: SECONDARY > 10 kW NCP | C159: SEC | G159: =-G19 -> -4260.12 | J159: =SUM(D159:I159) -> -4260.12 | R159: =SUM(L159:Q159) -> 0 | T159: =R159+J159 -> -4260.12
A160: 4 | B160: SECONDARY > 10 kW 4CP | C160: SEC | J160: =SUM(D160:I160) -> 0 | R160: =SUM(L160:Q160) -> 0 | T160: =R160+J160 -> 0
A161: 5 | B161: TOTAL SECONDARY > 10 kW | D161: =SUM(D159:D160) -> 0 | E161: =SUM(E159:E160) -> 0 | F161: =SUM(F159:F160) -> 0 | G161: =SUM(G159:G160) -> -4260.12 | I161: =SUM(I159:I160) -> 0 | J161: =SUM(D161:I161) -> -4260.12 | L161: =SUM(L159:L160) -> 0 | M161: =SUM(M159:M160) -> 0 | O161: =SUM(O159:O160) -> 0 | P161: =SUM(P159:P160) -> 0 | Q161: =SUM(Q159:Q160) -> 0 | R161: =SUM(L161:Q161) -> 0 | T161: =R161+J161 -> -4260.12
...

Sheet II-H-4.1 Tran kW
B2: PUBLIC UTILITY COMMISSION OF TEXAS
B3: AEP TEXAS INC
B4: II-H-4.1 TRAN KW ADJUSTMENTS
B5: TEST YEAR ENDING 09/30/2023
B6: =+'II-H-1'!B6 -> DOCKET 56165
B8: ='II-H-1.2'!B7:O7 -> AEP TEXAS
B9: TRANSMISSION KW
B10: FOR TEST YEAR ENDED SEPTEMBER 30, 2023
A13: LINE | B13: DESCRIPTION | C13: VOLT | D13: ='II-H-4.1 Dist kW'!D13 -> Oct-22 | E13: ='II-H-4.1 Dist kW'!E13 -> Nov-22 | F13: ='II-H-4.1 Dist kW'!F13 -> Dec-22 | G13: ='II-H-4.1 Dist kW'!G13 -> Jan-23 | H13: ='II-H-4.1 Dist kW'!H13 -> Feb-23 | I13: ='II-H-4.1 Dist kW'!I13 -> Mar-23 | J13: ='II-H-4.1 Dist kW'!J13 -> Apr-23 | K13: ='II-H-4.1 Dist kW'!K13 -> May-23 | ... O13: ='II-H-4.1 Dist kW'!O13 -> Sep-23 | P13: TOTAL
A15: 1 | B15: RESIDENTIAL SERVICE | C15: SEC | D15: {=SUMPRODUCT((H_Rate_Class=$B15)*'[5]Demand - T'!D$9:D$118)} -> 0 | E15: {=SUMPRODUCT((H_Rate_Class=$B15)*'[5]Demand - T'!E$9:E$118)} -> 0 | F15: {=SUMPRODUCT((H_Rate_Class=$B15)*'[5]Demand - T'!F$9:F$118)} -> 0 | G15: {=SUMPRODUCT((H_Rate_Class=$B15)*'[5]Demand - T'!G$9:G$118)} -> 0 | H15: {=SUMPRODUCT((H_Rate_Class=$B15)*'[5]Demand - T'!H$9:H$118)} -> 0 | I15: {=SUMPRODUCT((H_Rate_Class=$B15)*'[5]Demand - T'!I$9:I$118)} -> 0 | J15: {=SUMPRODUCT((H_Rate_Class=$B15)*'[5]Demand - T'!J$9:J$118)} -> 0 | K15: {=SUMPRODUCT((H_Rate_Class=$B15)*'[5]Demand - T'!K$9:K$118)} -> 0 | ... O15: {=SUMPRODUCT((H_Rate_Class=$B15)*'[5]Demand - T'!O$9:O$118)} -> 0
A17: 2 | B17: SECONDARY < 10 kW | C17: SEC | D17: {=SUMPRODUCT((H_Rate_Class=$B17)*'[5]Demand - T'!D$9:D$118)} -> 0 | E17: {=SUMPRODUCT((H_Rate_Class=$B17)*'[5]Demand - T'!E$9:E$118)} -> 0 | F17: {=SUMPRODUCT((H_Rate_Class=$B17)*'[5]Demand - T'!F$9:F$118)} -> 0 | G17: {=SUMPRODUCT((H_Rate_Class=$B17)*'[5]Demand - T'!G$9:G$118)} -> 0 | H17: {=SUMPRODUCT((H_Rate_Class=$B17)*'[5]Demand - T'!H$9:H$118)} -> 0 | I17: {=SUMPRODUCT((H_Rate_Class=$B17)*'[5]Demand - T'!I$9:I$118)} -> 0 | J17: {=SUMPRODUCT((H_Rate_Class=$B17)*'[5]Demand - T'!J$9:J$118)} -> 0 | K17: {=SUMPRODUCT((H_Rate_Class=$B17)*'[5]Demand - T'!K$9:K$118)} -> 0 | ... O17: {=SUMPRODUCT((H_Rate_Class=$B17)*'[5]Demand - T'!O$9:O$118)} -> 0 | P17: =SUM(D17:O17) -> 0
Q18: tran rate
A19: 3 | B19: SECONDARY > 10 kW NCP | C19: SEC | D19: {=SUMPRODUCT((H_Rate_Class=$B19)*'[5]Demand - T'!D$9:D$118)} -> 2281411.6 | E19: {=SUMPRODUCT((H_Rate_Class=$B19)*'[5]Demand - T'!E$9:E$118)} -> 2232552.4 | F19: {=SUMPRODUCT((H_Rate_Class=$B19)*'[5]Demand - T'!F$9:F$118)} -> 2323174.5 | G19: {=SUMPRODUCT((H_Rate_Class=$B19)*'[5]Demand - T'!G$9:G$118)} -> 2357604.1 | H19: {=SUMPRODUCT((H_Rate_Class=$B19)*'[5]Demand - T'!H$9:H$118)} -> 2359212.8 | I19: {=SUMPRODUCT((H_Rate_Class=$B19)*'[5]Demand - T'!I$9:I$118)} -> 2320876.9 | J19: {=SUMPRODUCT((H_Rate_Class=$B19)*'[5]Demand - T'!J$9:J$118)} -> 2262691.5 | K19: {=SUMPRODUCT((H_Rate_Class=$B19)*'[5]Demand - T'!K$9:K$118)} -> 2226349.1 | ... O19: {=SUMPRODUCT((H_Rate_Class=$B19)*'[5]Demand - T'!O$9:O$118)} -> 2499353.3 | P19: =SUM(D19:O19) -> 28134888 | Q19: ='II-H-4.1 Functions'!I19/'II-H-4.1 Tran kW'!P19 -> 3.8209184
A20: 4 | B20: SECONDARY > 10 kW 4CP | C20: SEC | D20: {=SUMPRODUCT((H_Rate_Class=$B20)*'[5]Demand - T'!D$9:D$118)} -> 193841.8 | E20: {=SUMPRODUCT((H_Rate_Class=$B20)*'[5]Demand - T'!E$9:E$118)} -> 198502.1 | F20: {=SUMPRODUCT((H_Rate_Class=$B20)*'[5]Demand - T'!F$9:F$118)} -> 195840.4 | G20: {=SUMPRODUCT((H_Rate_Class=$B20)*'[5]Demand - T'!G$9:G$118)} -> 188995.4 | H20: {=SUMPRODUCT((H_Rate_Class=$B20)*'[5]Demand - T'!H$9:H$118)} -> 188162.4 | I20: {=SUMPRODUCT((H_Rate_Class=$B20)*'[5]Demand - T'!I$9:I$118)} -> 189840 | J20: {=SUMPRODUCT((H_Rate_Class=$B20)*'[5]Demand - T'!J$9:J$118)} -> 188795.4 | K20: {=SUMPRODUCT((H_Rate_Class=$B20)*'[5]Demand - T'!K$9:K$118)} -> 191873.4 | ... O20: {=SUMPRODUCT((H_Rate_Class=$B20)*'[5]Demand - T'!O$9:O$118)} -> 192436.6 | P20: =SUM(D20:O20) -> 2307282 | Q20: ='II-H-4.1 Functions'!I20/'II-H-4.1 Tran kW'!P20 -> 5.7759529
A21: 5 | B21: TOTAL SECONDARY > 10 kW | D21: =SUM(D19:D20) -> 2475253.4 | E21: =SUM(E19:E20) -> 2431054.5 | F21: =SUM(F19:F20) -> 2519014.9 | G21: =SUM(G19:G20) -> 2546599.5 | H21: =SUM(H19:H20) -> 2547375.2 | I21: =SUM(I19:I20) -> 2510716.9 | J21: =SUM(J19:J20) -> 2451486.9 | K21: =SUM(K19:K20) -> 2418222.5 | ... P21: =SUM(P19:P20) -> 30442170
A23: 6 | B23: PRIMARY NCP | C23: PRI | D23: {=SUMPRODUCT((H_Rate_Class=$B23)*'[5]Demand - T'!D$9:D$118)-D25} -> 51013.5 | E23: {=SUMPRODUCT((H_Rate_Class=$B23)*'[5]Demand - T'!E$9:E$118)-E25} -> 52211.8 | F23: {=SUMPRODUCT((H_Rate_Class=$B23)*'[5]Demand - T'!F$9:F$118)-F25} -> 53969.9 | G23: {=SUMPRODUCT((H_Rate_Class=$B23)*'[5]Demand - T'!G$9:G$118)-G25} -> 52282.7 | H23: {=SUMPRODUCT((H_Rate_Class=$B23)*'[5]Demand - T'!H$9:H$118)-H25} -> 52371.9 | I23: {=SUMPRODUCT((H_Rate_Class=$B23)*'[5]Demand - T'!I$9:I$118)-I25} -> 55565.5 | J23: {=SUMPRODUCT((H_Rate_Class=$B23)*'[5]Demand - T'!J$9:J$118)-J25} -> 58487.3 | K23: {=SUMPRODUCT((H_Rate_Class=$B23)*'[5]Demand - T'!K$9:K$118)-K25} -> 57341.4 | ... O23: {=SUMPRODUCT((H_Rate_Class=$B23)*'[5]Demand - T'!O$9:O$118)-O25} -> 58090.4 | P23: =SUM(D23:O23) -> 666060.7 | Q23: ='II-H-4.1 Functions'!I23/'II-H-4.1 Tran kW'!P23 -> 3.9313481
A24: 7 | B24: PRIMARY 4CP | C24: PRI | D24: {=SUMPRODUCT((H_Rate_Class=$B24)*'[5]Demand - T'!D$9:D$118)-D26} -> 426046.7 | E24: {=SUMPRODUCT((H_Rate_Class=$B24)*'[5]Demand - T'!E$9:E$118)-E26} -> 430454 | F24: {=SUMPRODUCT((H_Rate_Class=$B24)*'[5]Demand - T'!F$9:F$118)-F26} -> 424411.8 | G24: {=SUMPRODUCT((H_Rate_Class=$B24)*'[5]Demand - T'!G$9:G$118)-G26} -> 459454.2 | H24: {=SUMPRODUCT((H_Rate_Class=$B24)*'[5]Demand - T'!H$9:H$118)-H26} -> 449906.1 | I24: {=SUMPRODUCT((H_Rate_Class=$B24)*'[5]Demand - T'!I$9:I$118)-I26} -> 448071.8 | J24: {=SUMPRODUCT((H_Rate_Class=$B24)*'[5]Demand - T'!J$9:J$118)-J26} -> 444946.9 | K24: {=SUMPRODUCT((H_Rate_Class=$B24)*'[5]Demand - T'!K$9:K$118)-K26} -> 469608.2 | ... O24: {=SUMPRODUCT((H_Rate_Class=$B24)*'[5]Demand - T'!O$9:O$118)-O26} -> 436046.8 | P24: =SUM(D24:O24) -> 5344520.5 | Q24: ='II-H-4.1 Functions'!I24/'II-H-4.1 Tran kW'!P24 -> 6.2836645
A25: 8 | B25: PRIMARY SUB NCP | C25: PRI | D25: ='Primary Sub'!C22 -> 1391.9 | E25: ='Primary Sub'!D22 -> 1110.6 | F25: ='Primary Sub'!E22 -> 1034.9 | G25: ='Primary Sub'!F22 -> 1022 | H25: ='Primary Sub'!G22 -> 1033.1 | I25: ='Primary Sub'!H22 -> 1134.4 | J25: ='Primary Sub'!I22 -> 1202 | K25: ='Primary Sub'!J22 -> 1356.4 | ... O25: ='Primary Sub'!N22 -> 1284.3 | P25: =IF(SUM(D25:O25)='Primary Sub'!O22,SUM(D25:O25),0) -> 14509.8
A26: 9 | B26: PRIMARY SUB 4CP | C26: PRI | D26: ='Primary Sub'!C23 -> 106232.1 | E26: ='Primary Sub'!D23 -> 106137.1 | F26: ='Primary Sub'!E23 -> 105862.5 | G26: ='Primary Sub'!F23 -> 111247.5 | H26: ='Primary Sub'!G23 -> 112591.2 | I26: ='Primary Sub'!H23 -> 110842.3 | J26: ='Primary Sub'!I23 -> 110915.8 | K26: ='Primary Sub'!J23 -> 108569.2 | ... O26: ='Primary Sub'!N23 -> 105911 | P26: =IF(SUM(D26:O26)='Primary Sub'!O23,SUM(D26:O26),0) -> 1297038.3
A27: 10 | B27: TOTAL PRIMARY | D27: =SUM(D23:D26) -> 584684.2 | E27: =SUM(E23:E26) -> 589913.5 | F27: =SUM(F23:F26) -> 585279.1 | G27: =SUM(G23:G26) -> 624006.4 | H27: =SUM(H23:H26) -> 615902.3 | I27: =SUM(I23:I26) -> 615614 | J27: =SUM(J23:J26) -> 615552 | K27: =SUM(K23:K26) -> 636875.2 | ... P27: =SUM(P23:P26) -> 7322129.3
A29: 11 | B29: TRANSMISSION | C29: TRA | D29: {=SUMPRODUCT((H_Rate_Class=$B29)*'[5]Demand - T'!D$9:D$118)} -> 686275.3 | E29: {=SUMPRODUCT((H_Rate_Class=$B29)*'[5]Demand - T'!E$9:E$118)} -> 690641.1 | F29: {=SUMPRODUCT((H_Rate_Class=$B29)*'[5]Demand - T'!F$9:F$118)} -> 854607.3 | G29: {=SUMPRODUCT((H_Rate_Class=$B29)*'[5]Demand - T'!G$9:G$118)} -> 841844.8 | H29: {=SUMPRODUCT((H_Rate_Class=$B29)*'[5]Demand - T'!H$9:H$118)} -> 848647.9 | I29: {=SUMPRODUCT((H_Rate_Class=$B29)*'[5]Demand - T'!I$9:I$118)} -> 1034765.2 | J29: {=SUMPRODUCT((H_Rate_Class=$B29)*'[5]Demand - T'!J$9:J$118)} -> 935977.9 | K29: {=SUMPRODUCT((H_Rate_Class=$B29)*'[5]Demand - T'!K$9:K$118)} -> 1014399.4 | ... O29: {=SUMPRODUCT((H_Rate_Class=$B29)*'[5]Demand - T'!O$9:O$118)} -> 758941.4 | P29: =SUM(D29:O29) -> 10435312 | Q29: ='II-H-4.1 Functions'!I29/'II-H-4.1 Tran kW'!P29 -> 5.0299593
A31: 12 | B31: LIGHTING | C31: SEC | D31: {=SUMPRODUCT((H_Rate_Class=$B31)*'[5]Demand - T'!D$9:D$118)} -> 0 | E31: {=SUMPRODUCT((H_Rate_Class=$B31)*'[5]Demand - T'!E$9:E$118)} -> 0 | F31: {=SUMPRODUCT((H_Rate_Class=$B31)*'[5]Demand - T'!F$9:F$118)} -> 0 | G31: {=SUMPRODUCT((H_Rate_Class=$B31)*'[5]Demand - T'!G$9:G$118)} -> 0 | H31: {=SUMPRODUCT((H_Rate_Class=$B31)*'[5]Demand - T'!H$9:H$118)} -> 0 | I31: {=SUMPRODUCT((H_Rate_Class=$B31)*'[5]Demand - T'!I$9:I$118)} -> 0 | J31: {=SUMPRODUCT((H_Rate_Class=$B31)*'[5]Demand - T'!J$9:J$118)} -> 0 | K31: {=SUMPRODUCT((H_Rate_Class=$B31)*'[5]Demand - T'!K$9:K$118)} -> 0 | ... O31: {=SUMPRODUCT((H_Rate_Class=$B31)*'[5]Demand - T'!O$9:O$118)} -> 0 | P31: =SUM(D31:O31) -> 0
A33: 13 | B33: TOTAL RETAIL | D33: =D31+D29+D27+D21+D17+D15 -> 3746212.9 | E33: =E31+E29+E27+E21+E17+E15 -> 3711609.1 | F33: =F31+F29+F27+F21+F17+F15 -> 3958901.3 | G33: =G31+G29+G27+G21+G17+G15 -> 4012450.7 | H33: =H31+H29+H27+H21+H17+H15 -> 4011925.4 | I33: =I31+I29+I27+I21+I17+I15 -> 4161096.1 | J33: =J31+J29+J27+J21+J17+J15 -> 4003016.8 | K33: =K31+K29+K27+K21+K17+K15 -> 4069497.1 | ... P33: =P31+P29+P27+P21+P17+P15 -> 48199612
A35: 14 | B35: WHOLESALE PRI | C35: PRI | P35: =SUM(D35:O35) -> 0
A36: 15 | B36: WHOLESALE TRANS | C36: TRA | P36: =SUM(D36:O36) -> 0
A37: 16 | B37: TOTAL WHOLESALE | D37: =SUM(D35:D36) -> 0 | E37: =SUM(E35:E36) -> 0 | F37: =SUM(F35:F36) -> 0 | G37: =SUM(G35:G36) -> 0 | H37: =SUM(H35:H36) -> 0 | I37: =SUM(I35:I36) -> 0 | J37: =SUM(J35:J36) -> 0 | K37: =SUM(K35:K36) -> 0 | ... P37: =SUM(P35:P36) -> 0
A39: 17 | B39: TOTAL AEP TEXAS | D39: =+D37+D33 -> 3746212.9 | E39: =+E37+E33 -> 3711609.1 | F39: =+F37+F33 -> 3958901.3 | G39: =+G37+G33 -> 4012450.7 | H39: =+H37+H33 -> 4011925.4 | I39: =+I37+I33 -> 4161096.1 | J39: =+J37+J33 -> 4003016.8 | K39: =+K37+K33 -> 4069497.1 | ... P39: =+P37+P33 -> 48199612
B41: =+B8 -> AEP TEXAS
B42: KW WEATHER ADJUSTMENT
B43: =+B10 -> FOR TEST YEAR ENDED SEPTEMBER 30, 2023
A46: LINE | B46: DESCRIPTION | C46: VOLT | D46: =+D13 -> Oct-22 | E46: =+E13 -> Nov-22 | F46: =+F13 -> Dec-22 | G46: =+G13 -> Jan-23 | H46: =+H13 -> Feb-23 | I46: =+I13 -> Mar-23 | J46: =+J13 -> Apr-23 | K46: =+K13 -> May-23 | ... P46: =+P13 -> TOTAL
A48: 1 | B48: RESIDENTIAL SERVICE | C48: SEC | D48: {=SUMPRODUCT((H_Rate_Class=$B48)*'[5]Demand - T'!D$249:D$358)} -> 0 | E48: {=SUMPRODUCT((H_Rate_Class=$B48)*'[5]Demand - T'!E$249:E$358)} -> 0 | F48: {=SUMPRODUCT((H_Rate_Class=$B48)*'[5]Demand - T'!F$249:F$358)} -> 0 | G48: {=SUMPRODUCT((H_Rate_Class=$B48)*'[5]Demand - T'!G$249:G$358)} -> 0 | H48: {=SUMPRODUCT((H_Rate_Class=$B48)*'[5]Demand - T'!H$249:H$358)} -> 0 | I48: {=SUMPRODUCT((H_Rate_Class=$B48)*'[5]Demand - T'!I$249:I$358)} -> 0 | J48: {=SUMPRODUCT((H_Rate_Class=$B48)*'[5]Demand - T'!J$249:J$358)} -> 0 | K48: {=SUMPRODUCT((H_Rate_Class=$B48)*'[5]Demand - T'!K$249:K$358)} -> 0 | ... O48: {=SUMPRODUCT((H_Rate_Class=$B48)*'[5]Demand - T'!O$249:O$358)} -> 0 | P48: =SUM(D48:O48) -> 0
A50: 2 | B50: SECONDARY < 10 kW | C50: SEC | D50: {=SUMPRODUCT((H_Rate_Class=$B50)*'[5]Demand - T'!D$249:D$358)} -> 0 | E50: {=SUMPRODUCT((H_Rate_Class=$B50)*'[5]Demand - T'!E$249:E$358)} -> 0 | F50: {=SUMPRODUCT((H_Rate_Class=$B50)*'[5]Demand - T'!F$249:F$358)} -> 0 | G50: {=SUMPRODUCT((H_Rate_Class=$B50)*'[5]Demand - T'!G$249:G$358)} -> 0 | H50: {=SUMPRODUCT((H_Rate_Class=$B50)*'[5]Demand - T'!H$249:H$358)} -> 0 | I50: {=SUMPRODUCT((H_Rate_Class=$B50)*'[5]Demand - T'!I$249:I$358)} -> 0 | J50: {=SUMPRODUCT((H_Rate_Class=$B50)*'[5]Demand - T'!J$249:J$358)} -> 0 | K50: {=SUMPRODUCT((H_Rate_Class=$B50)*'[5]Demand - T'!K$249:K$358)} -> 0 | ... O50: {=SUMPRODUCT((H_Rate_Class=$B50)*'[5]Demand - T'!O$249:O$358)} -> 0 | P50: =SUM(D50:O50) -> 0
A52: 3 | B52: SECONDARY > 10 kW NCP | C52: SEC | D52: {=SUMPRODUCT((H_Rate_Class=$B52)*'[5]Demand - T'!D$249:D$358)} -> 19015.419 | E52: {=SUMPRODUCT((H_Rate_Class=$B52)*'[5]Demand - T'!E$249:E$358)} -> 28716.312 | F52: {=SUMPRODUCT((H_Rate_Class=$B52)*'[5]Demand - T'!F$249:F$358)} -> -22286.891 | G52: {=SUMPRODUCT((H_Rate_Class=$B52)*'[5]Demand - T'!G$249:G$358)} -> -14948.97 | H52: {=SUMPRODUCT((H_Rate_Class=$B52)*'[5]Demand - T'!H$249:H$358)} -> 334.17099 | I52: {=SUMPRODUCT((H_Rate_Class=$B52)*'[5]Demand - T'!I$249:I$358)} -> -88103.577 | J52: {=SUMPRODUCT((H_Rate_Class=$B52)*'[5]Demand - T'!J$249:J$358)} -> -37763.559 | K52: {=SUMPRODUCT((H_Rate_Class=$B52)*'[5]Demand - T'!K$249:K$358)} -> 43409.456 | ... O52: {=SUMPRODUCT((H_Rate_Class=$B52)*'[5]Demand - T'!O$249:O$358)} -> -104311.23 | P52: =SUM(D52:O52) -> -357891.45
A53: 4 | B53: SECONDARY > 10 kW 4CP | C53: SEC | D53: {=SUMPRODUCT((H_Rate_Class=$B53)*'[5]Demand - T'!D$249:D$358)} -> 1688.2059 | E53: {=SUMPRODUCT((H_Rate_Class=$B53)*'[5]Demand - T'!E$249:E$358)} -> 2085.62 | F53: {=SUMPRODUCT((H_Rate_Class=$B53)*'[5]Demand - T'!F$249:F$358)} -> -853.49097 | G53: {=SUMPRODUCT((H_Rate_Class=$B53)*'[5]Demand - T'!G$249:G$358)} -> -1037.0041 | H53: {=SUMPRODUCT((H_Rate_Class=$B53)*'[5]Demand - T'!H$249:H$358)} -> 217.51944 | I53: {=SUMPRODUCT((H_Rate_Class=$B53)*'[5]Demand - T'!I$249:I$358)} -> -5555.0305 | J53: {=SUMPRODUCT((H_Rate_Class=$B53)*'[5]Demand - T'!J$249:J$358)} -> -2031.0977 | K53: {=SUMPRODUCT((H_Rate_Class=$B53)*'[5]Demand - T'!K$249:K$358)} -> 3345.1153 | ... O53: {=SUMPRODUCT((H_Rate_Class=$B53)*'[5]Demand - T'!O$249:O$358)} -> -3445.0282 | P53: =SUM(D53:O53) -> -12627.604
A54: 5 | B54: TOTAL SECONDARY > 10 kW | D54: =SUM(D52:D53) -> 20703.625 | E54: =SUM(E52:E53) -> 30801.932 | F54: =SUM(F52:F53) -> -23140.382 | G54: =SUM(G52:G53) -> -15985.975 | H54: =SUM(H52:H53) -> 551.69043 | I54: =SUM(I52:I53) -> -93658.608 | J54: =SUM(J52:J53) -> -39794.657 | K54: =SUM(K52:K53) -> 46754.571 | ... P54: =SUM(P52:P53) -> -370519.05
A56: 6 | B56: PRIMARY NCP | C56: PRI | D56: {=SUMPRODUCT((H_Rate_Class=$B56)*'[5]Demand - T'!D$249:D$358)} -> 82.647259 | E56: {=SUMPRODUCT((H_Rate_Class=$B56)*'[5]Demand - T'!E$249:E$358)} -> 127.79527 | F56: {=SUMPRODUCT((H_Rate_Class=$B56)*'[5]Demand - T'!F$249:F$358)} -> -307.93101 | G56: {=SUMPRODUCT((H_Rate_Class=$B56)*'[5]Demand - T'!G$249:G$358)} -> -361.58748 | H56: {=SUMPRODUCT((H_Rate_Class=$B56)*'[5]Demand - T'!H$249:H$358)} -> -148.92916 | I56: {=SUMPRODUCT((H_Rate_Class=$B56)*'[5]Demand - T'!I$249:I$358)} -> -1381.6791 | J56: {=SUMPRODUCT((H_Rate_Class=$B56)*'[5]Demand - T'!J$249:J$358)} -> -723.27762 | K56: {=SUMPRODUCT((H_Rate_Class=$B56)*'[5]Demand - T'!K$249:K$358)} -> 658.34021 | ... O56: {=SUMPRODUCT((H_Rate_Class=$B56)*'[5]Demand - T'!O$249:O$358)} -> -972.71891 | P56: =SUM(D56:O56) -> -5427.9203
A57: 7 | B57: PRIMARY 4CP | C57: PRI | D57: {=SUMPRODUCT((H_Rate_Class=$B57)*'[5]Demand - T'!D$249:D$358)} -> 1053.1712 | E57: {=SUMPRODUCT((H_Rate_Class=$B57)*'[5]Demand - T'!E$249:E$358)} -> 1799.7216 | F57: {=SUMPRODUCT((H_Rate_Class=$B57)*'[5]Demand - T'!F$249:F$358)} -> -2642.4985 | G57: {=SUMPRODUCT((H_Rate_Class=$B57)*'[5]Demand - T'!G$249:G$358)} -> -2779.4912 | H57: {=SUMPRODUCT((H_Rate_Class=$B57)*'[5]Demand - T'!H$249:H$358)} -> -552.32228 | I57: {=SUMPRODUCT((H_Rate_Class=$B57)*'[5]Demand - T'!I$249:I$358)} -> -9775.1396 | J57: {=SUMPRODUCT((H_Rate_Class=$B57)*'[5]Demand - T'!J$249:J$358)} -> -4512.3261 | K57: {=SUMPRODUCT((H_Rate_Class=$B57)*'[5]Demand - T'!K$249:K$358)} -> 3877.2724 | ... O57: {=SUMPRODUCT((H_Rate_Class=$B57)*'[5]Demand - T'!O$249:O$358)} -> -9953.3317 | P57: =SUM(D57:O57) -> -43864.009
A58: 8 | B58: PRIMARY SUB NCP | C58: PRI | D58: {=SUMPRODUCT((H_Rate_Class=$B58)*'[5]Demand - T'!D$249:D$358)} -> 0 | E58: {=SUMPRODUCT((H_Rate_Class=$B58)*'[5]Demand - T'!E$249:E$358)} -> 0 | F58: {=SUMPRODUCT((H_Rate_Class=$B58)*'[5]Demand - T'!F$249:F$358)} -> 0 | G58: {=SUMPRODUCT((H_Rate_Class=$B58)*'[5]Demand - T'!G$249:G$358)} -> 0 | H58: {=SUMPRODUCT((H_Rate_Class=$B58)*'[5]Demand - T'!H$249:H$358)} -> 0 | I58: {=SUMPRODUCT((H_Rate_Class=$B58)*'[5]Demand - T'!I$249:I$358)} -> 0 | J58: {=SUMPRODUCT((H_Rate_Class=$B58)*'[5]Demand - T'!J$249:J$358)} -> 0 | K58: {=SUMPRODUCT((H_Rate_Class=$B58)*'[5]Demand - T'!K$249:K$358)} -> 0 | ... O58: {=SUMPRODUCT((H_Rate_Class=$B58)*'[5]Demand - T'!O$249:O$358)} -> 0 | P58: =SUM(D58:O58) -> 0
A59: 9 | B59: PRIMARY SUB 4CP | C59: PRI | D59: {=SUMPRODUCT((H_Rate_Class=$B59)*'[5]Demand - T'!D$249:D$358)} -> 0 | E59: {=SUMPRODUCT((H_Rate_Class=$B59)*'[5]Demand - T'!E$249:E$358)} -> 0 | F59: {=SUMPRODUCT((H_Rate_Class=$B59)*'[5]Demand - T'!F$249:F$358)} -> 0 | G59: {=SUMPRODUCT((H_Rate_Class=$B59)*'[5]Demand - T'!G$249:G$358)} -> 0 | H59: {=SUMPRODUCT((H_Rate_Class=$B59)*'[5]Demand - T'!H$249:H$358)} -> 0 | I59: {=SUMPRODUCT((H_Rate_Class=$B59)*'[5]Demand - T'!I$249:I$358)} -> 0 | J59: {=SUMPRODUCT((H_Rate_Class=$B59)*'[5]Demand - T'!J$249:J$358)} -> 0 | K59: {=SUMPRODUCT((H_Rate_Class=$B59)*'[5]Demand - T'!K$249:K$358)} -> 0 | ... O59: {=SUMPRODUCT((H_Rate_Class=$B59)*'[5]Demand - T'!O$249:O$358)} -> 0 | P59: =SUM(D59:O59) -> 0
A60: 10 | B60: TOTAL PRIMARY | D60: =SUM(D56:D57) -> 1135.8185 | E60: =SUM(E56:E57) -> 1927.5169 | F60: =SUM(F56:F57) -> -2950.4295 | G60: =SUM(G56:G57) -> -3141.0787 | H60: =SUM(H56:H57) -> -701.25144 | I60: =SUM(I56:I57) -> -11156.819 | J60: =SUM(J56:J57) -> -5235.6037 | K60: =SUM(K56:K57) -> 4535.6126 | ... P60: =SUM(P56:P57) -> -49291.93
A62: 11 | B62: TRANSMISSION | C62: TRA | D62: {=SUMPRODUCT((H_Rate_Class=$B62)*'[5]Demand - T'!D$249:D$358)} -> -27.320155 | E62: {=SUMPRODUCT((H_Rate_Class=$B62)*'[5]Demand - T'!E$249:E$358)} -> -20.368289 | F62: {=SUMPRODUCT((H_Rate_Class=$B62)*'[5]Demand - T'!F$249:F$358)} -> -19.424669 | G62: {=SUMPRODUCT((H_Rate_Class=$B62)*'[5]Demand - T'!G$249:G$358)} -> -88.828832 | H62: {=SUMPRODUCT((H_Rate_Class=$B62)*'[5]Demand - T'!H$249:H$358)} -> -31.93175 | I62: {=SUMPRODUCT((H_Rate_Class=$B62)*'[5]Demand - T'!I$249:I$358)} -> -125.36136 | J62: {=SUMPRODUCT((H_Rate_Class=$B62)*'[5]Demand - T'!J$249:J$358)} -> -98.535264 | K62: {=SUMPRODUCT((H_Rate_Class=$B62)*'[5]Demand - T'!K$249:K$358)} -> -91.790653 | ... O62: {=SUMPRODUCT((H_Rate_Class=$B62)*'[5]Demand - T'!O$249:O$358)} -> -93.300223 | P62: =SUM(D62:O62) -> -902.74177
A64: 12 | B64: LIGHTING | C64: SEC | D64: {=SUMPRODUCT((H_Rate_Class=$B64)*'[5]Demand - T'!D$249:D$358)} -> 0 | E64: {=SUMPRODUCT((H_Rate_Class=$B64)*'[5]Demand - T'!E$249:E$358)} -> 0 | F64: {=SUMPRODUCT((H_Rate_Class=$B64)*'[5]Demand - T'!F$249:F$358)} -> 0 | G64: {=SUMPRODUCT((H_Rate_Class=$B64)*'[5]Demand - T'!G$249:G$358)} -> 0 | H64: {=SUMPRODUCT((H_Rate_Class=$B64)*'[5]Demand - T'!H$249:H$358)} -> 0 | I64: {=SUMPRODUCT((H_Rate_Class=$B64)*'[5]Demand - T'!I$249:I$358)} -> 0 | J64: {=SUMPRODUCT((H_Rate_Class=$B64)*'[5]Demand - T'!J$249:J$358)} -> 0 | K64: {=SUMPRODUCT((H_Rate_Class=$B64)*'[5]Demand - T'!K$249:K$358)} -> 0 | ... O64: {=SUMPRODUCT((H_Rate_Class=$B64)*'[5]Demand - T'!O$249:O$358)} -> 0 | P64: =SUM(D64:O64) -> 0
A66: 13 | B66: TOTAL RETAIL | D66: =D64+D62+D60+D54+D50+D48 -> 21812.123 | E66: =E64+E62+E60+E54+E50+E48 -> 32709.081 | F66: =F64+F62+F60+F54+F50+F48 -> -26110.236 | G66: =G64+G62+G60+G54+G50+G48 -> -19215.882 | H66: =H64+H62+H60+H54+H50+H48 -> -181.49275 | I66: =I64+I62+I60+I54+I50+I48 -> -104940.79 | J66: =J64+J62+J60+J54+J50+J48 -> -45128.796 | K66: =K64+K62+K60+K54+K50+K48 -> 51198.393 | ... P66: =P64+P62+P60+P54+P50+P48 -> -420713.72
A68: 14 | B68: WHOLESALE PRI | C68: PRI | P68: =SUM(D68:O68) -> 0
A69: 15 | B69: WHOLESALE TRANS | C69: TRA | P69: =SUM(D69:O69) -> 0
A70: 16 | B70: TOTAL WHOLESALE | D70: =SUM(D68:D69) -> 0 | E70: =SUM(E68:E69) -> 0 | F70: =SUM(F68:F69) -> 0 | G70: =SUM(G68:G69) -> 0 | H70: =SUM(H68:H69) -> 0 | I70: =SUM(I68:I69) -> 0 | J70: =SUM(J68:J69) -> 0 | K70: =SUM(K68:K69) -> 0 | ... P70: =SUM(P68:P69) -> 0
A72: 17 | B72: TOTAL AEP TEXAS | D72: =+D70+D66 -> 21812.123 | E72: =+E70+E66 -> 32709.081 | F72: =+F70+F66 -> -26110.236 | G72: =+G70+G66 -> -19215.882 | H72: =+H70+H66 -> -181.49275 | I72: =+I70+I66 -> -104940.79 | J72: =+J70+J66 -> -45128.796 | K72: =+K70+K66 -> 51198.393 | ... P72: =+P70+P66 -> -420713.72
B73: =+B8 -> AEP TEXAS
B74: KW CUSTOMER ADJUSTMENT
B75: =+B10 -> FOR TEST YEAR ENDED SEPTEMBER 30, 2023
A78: LINE | B78: DESCRIPTION | C78: VOLT | D78: =+D13 -> Oct-22 | E78: =+E13 -> Nov-22 | F78: =+F13 -> Dec-22 | G78: =+G13 -> Jan-23 | H78: =+H13 -> Feb-23 | I78: =+I13 -> Mar-23 | J78: =+J13 -> Apr-23 | K78: =+K13 -> May-23 | ... O78: =+O13 -> Sep-23 | P78: TOTAL
A80: 1 | B80: RESIDENTIAL SERVICE | C80: SEC | D80: {=SUMPRODUCT((H_Rate_Class=$B80)*'[5]Demand - T'!D$129:D$238)} -> 0 | E80: {=SUMPRODUCT((H_Rate_Class=$B80)*'[5]Demand - T'!E$129:E$238)} -> 0 | F80: {=SUMPRODUCT((H_Rate_Class=$B80)*'[5]Demand - T'!F$129:F$238)} -> 0 | G80: {=SUMPRODUCT((H_Rate_Class=$B80)*'[5]Demand - T'!G$129:G$238)} -> 0 | H80: {=SUMPRODUCT((H_Rate_Class=$B80)*'[5]Demand - T'!H$129:H$238)} -> 0 | I80: {=SUMPRODUCT((H_Rate_Class=$B80)*'[5]Demand - T'!I$129:I$238)} -> 0 | J80: {=SUMPRODUCT((H_Rate_Class=$B80)*'[5]Demand - T'!J$129:J$238)} -> 0 | K80: {=SUMPRODUCT((H_Rate_Class=$B80)*'[5]Demand - T'!K$129:K$238)} -> 0 | ... O80: {=SUMPRODUCT((H_Rate_Class=$B80)*'[5]Demand - T'!O$129:O$238)} -> 0 | P80: =SUM(D80:O80) -> 0
A82: 2 | B82: SECONDARY < 10 kW | C82: SEC | D82: {=SUMPRODUCT((H_Rate_Class=$B82)*'[5]Demand - T'!D$129:D$238)} -> 0 | E82: {=SUMPRODUCT((H_Rate_Class=$B82)*'[5]Demand - T'!E$129:E$238)} -> 0 | F82: {=SUMPRODUCT((H_Rate_Class=$B82)*'[5]Demand - T'!F$129:F$238)} -> 0 | G82: {=SUMPRODUCT((H_Rate_Class=$B82)*'[5]Demand - T'!G$129:G$238)} -> 0 | H82: {=SUMPRODUCT((H_Rate_Class=$B82)*'[5]Demand - T'!H$129:H$238)} -> 0 | I82: {=SUMPRODUCT((H_Rate_Class=$B82)*'[5]Demand - T'!I$129:I$238)} -> 0 | J82: {=SUMPRODUCT((H_Rate_Class=$B82)*'[5]Demand - T'!J$129:J$238)} -> 0 | K82: {=SUMPRODUCT((H_Rate_Class=$B82)*'[5]Demand - T'!K$129:K$238)} -> 0 | ... O82: {=SUMPRODUCT((H_Rate_Class=$B82)*'[5]Demand - T'!O$129:O$238)} -> 0 | P82: =SUM(D82:O82) -> 0
A84: 3 | B84: SECONDARY > 10 kW NCP | C84: SEC | D84: {=SUMPRODUCT((H_Rate_Class=$B84)*'[5]Demand - T'!D$129:D$238)} -> 44471.22 | E84: {=SUMPRODUCT((H_Rate_Class=$B84)*'[5]Demand - T'!E$129:E$238)} -> 49079.089 | F84: {=SUMPRODUCT((H_Rate_Class=$B84)*'[5]Demand - T'!F$129:F$238)} -> 46492.52 | G84: {=SUMPRODUCT((H_Rate_Class=$B84)*'[5]Demand - T'!G$129:G$238)} -> 10272.13 | H84: {=SUMPRODUCT((H_Rate_Class=$B84)*'[5]Demand - T'!H$129:H$238)} -> -6254.9782 | I84: {=SUMPRODUCT((H_Rate_Class=$B84)*'[5]Demand - T'!I$129:I$238)} -> -7251.0514 | J84: {=SUMPRODUCT((H_Rate_Class=$B84)*'[5]Demand - T'!J$129:J$238)} -> 10584.903 | K84: {=SUMPRODUCT((H_Rate_Class=$B84)*'[5]Demand - T'!K$129:K$238)} -> 8456.9739 | ... O84: {=SUMPRODUCT((H_Rate_Class=$B84)*'[5]Demand - T'!O$129:O$238)} -> 0 | P84: =SUM(D84:O84) -> 160181.75
A85: 4 | B85: SECONDARY > 10 kW 4CP | C85: SEC | D85: {=SUMPRODUCT((H_Rate_Class=$B85)*'[5]Demand - T'!D$129:D$238)} -> 5746.4265 | E85: {=SUMPRODUCT((H_Rate_Class=$B85)*'[5]Demand - T'!E$129:E$238)} -> 3890.1485 | F85: {=SUMPRODUCT((H_Rate_Class=$B85)*'[5]Demand - T'!F$129:F$238)} -> 3306.7226 | G85: {=SUMPRODUCT((H_Rate_Class=$B85)*'[5]Demand - T'!G$129:G$238)} -> 3686.616 | H85: {=SUMPRODUCT((H_Rate_Class=$B85)*'[5]Demand - T'!H$129:H$238)} -> 2429.3918 | I85: {=SUMPRODUCT((H_Rate_Class=$B85)*'[5]Demand - T'!I$129:I$238)} -> 1927.0654 | J85: {=SUMPRODUCT((H_Rate_Class=$B85)*'[5]Demand - T'!J$129:J$238)} -> 1418.8247 | K85: {=SUMPRODUCT((H_Rate_Class=$B85)*'[5]Demand - T'!K$129:K$238)} -> 156.47649 | ... O85: {=SUMPRODUCT((H_Rate_Class=$B85)*'[5]Demand - T'!O$129:O$238)} -> 0 | P85: =SUM(D85:O85) -> 19047.225
A86: 5 | B86: TOTAL SECONDARY > 10 kW | D86: =SUM(D84:D85) -> 50217.647 | E86: =SUM(E84:E85) -> 52969.238 | F86: =SUM(F84:F85) -> 49799.243 | G86: =SUM(G84:G85) -> 13958.746 | H86: =SUM(H84:H85) -> -3825.5864 | I86: =SUM(I84:I85) -> -5323.986 | J86: =SUM(J84:J85) -> 12003.728 | K86: =SUM(K84:K85) -> 8613.4504 | ... P86: =SUM(P84:P85) -> 179228.98
A88: 6 | B88: PRIMARY NCP | C88: PRI | D88: {=SUMPRODUCT((H_Rate_Class=$B88)*'[5]Demand - T'!D$129:D$238)} -> -121.35468 | E88: {=SUMPRODUCT((H_Rate_Class=$B88)*'[5]Demand - T'!E$129:E$238)} -> -117.42239 | F88: {=SUMPRODUCT((H_Rate_Class=$B88)*'[5]Demand - T'!F$129:F$238)} -> -111.69649 | G88: {=SUMPRODUCT((H_Rate_Class=$B88)*'[5]Demand - T'!G$129:G$238)} -> -148.50373 | H88: {=SUMPRODUCT((H_Rate_Class=$B88)*'[5]Demand - T'!H$129:H$238)} -> -98.03076 | I88: {=SUMPRODUCT((H_Rate_Class=$B88)*'[5]Demand - T'!I$129:I$238)} -> 196.05956 | J88: {=SUMPRODUCT((H_Rate_Class=$B88)*'[5]Demand - T'!J$129:J$238)} -> 0 | K88: {=SUMPRODUCT((H_Rate_Class=$B88)*'[5]Demand - T'!K$129:K$238)} -> -202.49051 | ... O88: {=SUMPRODUCT((H_Rate_Class=$B88)*'[5]Demand - T'!O$129:O$238)} -> 0 | P88: =SUM(D88:O88) -> -1127.9372
A89: 7 | B89: PRIMARY 4CP | C89: PRI | D89: {=SUMPRODUCT((H_Rate_Class=$B89)*'[5]Demand - T'!D$129:D$238)} -> 9947.65 | E89: {=SUMPRODUCT((H_Rate_Class=$B89)*'[5]Demand - T'!E$129:E$238)} -> -714.18034 | F89: {=SUMPRODUCT((H_Rate_Class=$B89)*'[5]Demand - T'!F$129:F$238)} -> -6692.1744 | G89: {=SUMPRODUCT((H_Rate_Class=$B89)*'[5]Demand - T'!G$129:G$238)} -> -2940.8973 | H89: {=SUMPRODUCT((H_Rate_Class=$B89)*'[5]Demand - T'!H$129:H$238)} -> -11416.711 | I89: {=SUMPRODUCT((H_Rate_Class=$B89)*'[5]Demand - T'!I$129:I$238)} -> -5031.8648 | J89: {=SUMPRODUCT((H_Rate_Class=$B89)*'[5]Demand - T'!J$129:J$238)} -> -736.73333 | K89: {=SUMPRODUCT((H_Rate_Class=$B89)*'[5]Demand - T'!K$129:K$238)} -> -16005.576 | ... O89: {=SUMPRODUCT((H_Rate_Class=$B89)*'[5]Demand - T'!O$129:O$238)} -> 0 | P89: =SUM(D89:O89) -> -66675.404
A90: 8 | B90: PRIMARY SUB NCP | C90: PRI | D90: {=SUMPRODUCT((H_Rate_Class=$B90)*'[5]Demand - T'!D$129:D$238)} -> 0 | E90: {=SUMPRODUCT((H_Rate_Class=$B90)*'[5]Demand - T'!E$129:E$238)} -> 0 | F90: {=SUMPRODUCT((H_Rate_Class=$B90)*'[5]Demand - T'!F$129:F$238)} -> 0 | G90: {=SUMPRODUCT((H_Rate_Class=$B90)*'[5]Demand - T'!G$129:G$238)} -> 0 | H90: {=SUMPRODUCT((H_Rate_Class=$B90)*'[5]Demand - T'!H$129:H$238)} -> 0 | I90: {=SUMPRODUCT((H_Rate_Class=$B90)*'[5]Demand - T'!I$129:I$238)} -> 0 | J90: {=SUMPRODUCT((H_Rate_Class=$B90)*'[5]Demand - T'!J$129:J$238)} -> 0 | K90: {=SUMPRODUCT((H_Rate_Class=$B90)*'[5]Demand - T'!K$129:K$238)} -> 0 | ... O90: {=SUMPRODUCT((H_Rate_Class=$B90)*'[5]Demand - T'!O$129:O$238)} -> 0 | P90: =SUM(D90:O90) -> 0
A91: 9 | B91: PRIMARY SUB 4CP | C91: PRI | D91: {=SUMPRODUCT((H_Rate_Class=$B91)*'[5]Demand - T'!D$129:D$238)} -> 0 | E91: {=SUMPRODUCT((H_Rate_Class=$B91)*'[5]Demand - T'!E$129:E$238)} -> 0 | F91: {=SUMPRODUCT((H_Rate_Class=$B91)*'[5]Demand - T'!F$129:F$238)} -> 0 | G91: {=SUMPRODUCT((H_Rate_Class=$B91)*'[5]Demand - T'!G$129:G$238)} -> 0 | H91: {=SUMPRODUCT((H_Rate_Class=$B91)*'[5]Demand - T'!H$129:H$238)} -> 0 | I91: {=SUMPRODUCT((H_Rate_Class=$B91)*'[5]Demand - T'!I$129:I$238)} -> 0 | J91: {=SUMPRODUCT((H_Rate_Class=$B91)*'[5]Demand - T'!J$129:J$238)} -> 0 | K91: {=SUMPRODUCT((H_Rate_Class=$B91)*'[5]Demand - T'!K$129:K$238)} -> 0 | ... O91: {=SUMPRODUCT((H_Rate_Class=$B91)*'[5]Demand - T'!O$129:O$238)} -> 0 | P91: =SUM(D91:O91) -> 0
A92: 10 | B92: TOTAL PRIMARY | D92: =SUM(D88:D89) -> 9826.2954 | E92: =SUM(E88:E89) -> -831.60272 | F92: =SUM(F88:F89) -> -6803.8709 | G92: =SUM(G88:G89) -> -3089.401 | H92: =SUM(H88:H89) -> -11514.742 | I92: =SUM(I88:I89) -> -4835.8052 | J92: =SUM(J88:J89) -> -736.73333 | K92: =SUM(K88:K89) -> -16208.067 | ... P92: =SUM(P88:P89) -> -67803.342
A94: 11 | B94: TRANSMISSION | C94: TRA | D94: {=SUMPRODUCT((H_Rate_Class=$B94)*'[5]Demand - T'!D$129:D$238)} -> -8694.1391 | E94: {=SUMPRODUCT((H_Rate_Class=$B94)*'[5]Demand - T'!E$129:E$238)} -> -4090.7048 | F94: {=SUMPRODUCT((H_Rate_Class=$B94)*'[5]Demand - T'!F$129:F$238)} -> 45602.047 | G94: {=SUMPRODUCT((H_Rate_Class=$B94)*'[5]Demand - T'!G$129:G$238)} -> -50140.835 | H94: {=SUMPRODUCT((H_Rate_Class=$B94)*'[5]Demand - T'!H$129:H$238)} -> -13945.469 | I94: {=SUMPRODUCT((H_Rate_Class=$B94)*'[5]Demand - T'!I$129:I$238)} -> -18620.139 | J94: {=SUMPRODUCT((H_Rate_Class=$B94)*'[5]Demand - T'!J$129:J$238)} -> -14059.739 | K94: {=SUMPRODUCT((H_Rate_Class=$B94)*'[5]Demand - T'!K$129:K$238)} -> -21032.992 | ... O94: {=SUMPRODUCT((H_Rate_Class=$B94)*'[5]Demand - T'!O$129:O$238)} -> 0 | P94: =SUM(D94:O94) -> -135560.8
A96: 12 | B96: LIGHTING | C96: SEC | D96: {=SUMPRODUCT((H_Rate_Class=$B96)*'[5]Demand - T'!D$129:D$238)} -> 0 | E96: {=SUMPRODUCT((H_Rate_Class=$B96)*'[5]Demand - T'!E$129:E$238)} -> 0 | F96: {=SUMPRODUCT((H_Rate_Class=$B96)*'[5]Demand - T'!F$129:F$238)} -> 0 | G96: {=SUMPRODUCT((H_Rate_Class=$B96)*'[5]Demand - T'!G$129:G$238)} -> 0 | H96: {=SUMPRODUCT((H_Rate_Class=$B96)*'[5]Demand - T'!H$129:H$238)} -> 0 | I96: {=SUMPRODUCT((H_Rate_Class=$B96)*'[5]Demand - T'!I$129:I$238)} -> 0 | J96: {=SUMPRODUCT((H_Rate_Class=$B96)*'[5]Demand - T'!J$129:J$238)} -> 0 | K96: {=SUMPRODUCT((H_Rate_Class=$B96)*'[5]Demand - T'!K$129:K$238)} -> 0 | ... O96: {=SUMPRODUCT((H_Rate_Class=$B96)*'[5]Demand - T'!O$129:O$238)} -> 0 | P96: =SUM(D96:O96) -> 0
A98: 13 | B98: TOTAL RETAIL | D98: =D96+D94+D92+D86+D82+D80 -> 51349.803 | E98: =E96+E94+E92+E86+E82+E80 -> 48046.93 | F98: =F96+F94+F92+F86+F82+F80 -> 88597.419 | G98: =G96+G94+G92+G86+G82+G80 -> -39271.49 | H98: =H96+H94+H92+H86+H82+H80 -> -29285.798 | I98: =I96+I94+I92+I86+I82+I80 -> -28779.93 | J98: =J96+J94+J92+J86+J82+J80 -> -2792.7447 | K98: =K96+K94+K92+K86+K82+K80 -> -28627.608 | ... P98: =P96+P94+P92+P86+P82+P80 -> -24135.161
A100: 14 | B100: WHOLESALE PRI | C100: PRI | D100: 0 | E100: 0 | F100: 0 | G100: 0 | H100: 0 | I100: 0 | J100: 0 | K100: 0 | L100: 0 | M100: 0 | N100: 0 | O100: 0 | P100: =SUM(D100:O100) -> 0
A101: 15 | B101: WHOLESALE TRANS | C101: TRA | P101: =SUM(D101:O101) -> 0
A102: 16 | B102: TOTAL WHOLESALE | D102: =SUM(D100:D101) -> 0 | E102: =SUM(E100:E101) -> 0 | F102: =SUM(F100:F101) -> 0 | G102: =SUM(G100:G101) -> 0 | H102: =SUM(H100:H101) -> 0 | I102: =SUM(I100:I101) -> 0 | J102: =SUM(J100:J101) -> 0 | K102: =SUM(K100:K101) -> 0 | ... P102: =SUM(P100:P101) -> 0
A104: 17 | B104: TOTAL AEP TEXAS | D104: =+D102+D98 -> 51349.803 | E104: =+E102+E98 -> 48046.93 | F104: =+F102+F98 -> 88597.419 | G104: =+G102+G98 -> -39271.49 | H104: =+H102+H98 -> -29285.798 | I104: =+I102+I98 -> -28779.93 | J104: =+J102+J98 -> -2792.7447 | K104: =+K102+K98 -> -28627.608 | ... P104: =+P102+P98 -> -24135.161
B105: =B73 -> AEP TEXAS
B106: OTHER KW ADJUSTMENTS
B107: =B75 -> FOR TEST YEAR ENDED SEPTEMBER 30, 2023
A110: LINE | B110: DESCRIPTION | C110: VOLT | D110: =D13 -> Oct-22 | E110: =E13 -> Nov-22 | F110: =F13 -> Dec-22 | G110: =G13 -> Jan-23 | H110: =H13 -> Feb-23 | I110: =I13 -> Mar-23 | J110: =J13 -> Apr-23 | K110: =K13 -> May-23 | ... O110: =O13 -> Sep-23 | P110: TOTAL
