Workbook
Name IQ_CH: 110000
Name IQ_CQ: 5000
Name IQ_CY: 10000
Name IQ_DAILY: 500000
Name IQ_FH: 100000
Name IQ_FQ: 500
Name IQ_FY: 1000
Name IQ_LTM: 2000
Name IQ_MONTH: 15000
Name IQ_NTM: 6000
Name IQ_WEEK: 50000
Name IQ_YTD: 3000

Sheet AEB-2 Summary
B2: SUMMARY OF COE ANALYSES RESULTS
J4: X | K4: Y
B5: Constant Growth DCF | I5: Constant Growth Mean DCF | J5: =C12 -> 0.087007831 | K5: 7.5
C6: Minimum | D6: Average | E6: Maximum | J6: =D12 -> 0.099570678 | K6: 7.5
C7: Growth Rate | D7: Growth Rate | E7: Growth Rate | J7: =E12 -> 0.11159326 | K7: 7.5
B8: Mean Results: | I8: Constant Growth Median DCF | J8: =C18 -> 0.086894916 | K8: 6.5
B9: 30-Day Average | C9: ='AEB-4 CGDCF'!K21 -> 0.086842598 | D9: ='AEB-4 CGDCF'!L21 -> 0.099403256 | E9: ='AEB-4 CGDCF'!M21 -> 0.11142474 | J9: =D18 -> 0.098058195 | K9: 6.5
B10: 90-Day Average | C10: ='AEB-4 CGDCF'!K57 -> 0.087744025 | D10: ='AEB-4 CGDCF'!L57 -> 0.10031114 | E10: ='AEB-4 CGDCF'!M57 -> 0.11233823 | J10: =E18 -> 0.10709428 | K10: 6.5
B11: 180-Day Average | C11: ='AEB-4 CGDCF'!K93 -> 0.086436869 | D11: ='AEB-4 CGDCF'!L93 -> 0.098997633 | E11: ='AEB-4 CGDCF'!M93 -> 0.11101681 | I11: CAPM | J11: =MIN(C26:E28) -> 0.10385584 | K11: 3
B12: Average | C12: =AVERAGE(C9:C11) -> 0.087007831 | D12: =AVERAGE(D9:D11) -> 0.099570678 | E12: =AVERAGE(E9:E11) -> 0.11159326 | J12: =MAX(C26:E28) -> 0.11630715 | K12: 3
I13: ECAPM | J13: =MIN(C31:E33) -> 0.10844022 | K13: 2
B14: Median Results: | J14: =MAX(C31:E33) -> 0.11777871 | K14: 2
B15: 30-Day Average | C15: ='AEB-4 CGDCF'!K22 -> 0.087327287 | D15: ='AEB-4 CGDCF'!L22 -> 0.09811952 | E15: ='AEB-4 CGDCF'!M22 -> 0.10766884 | I15: Risk Premium | J15: =C35 -> 0.10353074 | K15: 1
B16: 90-Day Average | C16: ='AEB-4 CGDCF'!K58 -> 0.087821922 | D16: ='AEB-4 CGDCF'!L58 -> 0.09919911 | E16: ='AEB-4 CGDCF'!M58 -> 0.10857999 | J16: =E35 -> 0.10298988 | K16: 1
B17: 180-Day Average | C17: ='AEB-4 CGDCF'!K94 -> 0.085535541 | D17: ='AEB-4 CGDCF'!L94 -> 0.096855957 | E17: ='AEB-4 CGDCF'!M94 -> 0.10503401 | I17: Low End ROE Recommendation | J17: 0.1 | K17: 0
B18: Average | C18: =AVERAGE(C15:C17) -> 0.086894916 | D18: =AVERAGE(D15:D17) -> 0.098058195 | E18: =AVERAGE(E15:E17) -> 0.10709428 | J18: =J17 -> 0.1 | K18: 9 | M18: 0
I19: High End ROE Recommendation | J19: 0.11 | K19: =K17 -> 0 | M19: 9
B20: CAPM / ECAPM / Bond Yield Risk Premium | J20: =J19 -> 0.11 | K20: 9 | M20: =M18 -> 0
C21: Current | D21: Near-Term | E21: Longer-Term | I21: Recommended ROE | J21: 0.106 | K21: 4 | M21: 9
C22: 30-Day Avg | D22: Projected | E22: Projected | M22: 2.8
C23: 30-Year | D23: 30-Year | E23: 30-Year
C24: Treasury Yield | D24: Treasury Yield | E24: Treasury Yield
B25: CAPM:
B26: Value Line Beta | C26: ='AEB-5 CAPM'!H24 -> 0.11630715 | D26: ='AEB-5 CAPM'!H58 -> 0.1162392 | E26: ='AEB-5 CAPM'!H92 -> 0.1162392
B27: Bloomberg Beta | C27: ='AEB-5 CAPM'!H126 -> 0.10637532 | D27: ='AEB-5 CAPM'!H160 -> 0.1061927 | E27: ='AEB-5 CAPM'!H194 -> 0.1061927
B28: Long-term Avg. Beta | C28: ='AEB-5 CAPM'!H228 -> 0.10406513 | D28: ='AEB-5 CAPM'!H262 -> 0.10385584 | E28: ='AEB-5 CAPM'!H296 -> 0.10385584
B30: ECAPM:
B31: Value Line Beta | C31: ='AEB-5 CAPM'!I24 -> 0.11777871 | D31: ='AEB-5 CAPM'!I58 -> 0.11772774 | E31: ='AEB-5 CAPM'!I92 -> 0.11772774
B32: Bloomberg Beta | C32: ='AEB-5 CAPM'!I126 -> 0.11032983 | D32: ='AEB-5 CAPM'!I160 -> 0.11019287 | E32: ='AEB-5 CAPM'!I194 -> 0.11019287
B33: Long-term Avg. Beta | C33: ='AEB-5 CAPM'!I228 -> 0.10859719 | D33: ='AEB-5 CAPM'!I262 -> 0.10844022 | E33: ='AEB-5 CAPM'!I296 -> 0.10844022
B35: Bond Yield Risk Premium: | C35: ='AEB-8 Risk Premium'!L47 -> 0.10353074 | D35: ='AEB-8 Risk Premium'!L48 -> 0.10298988 | E35: ='AEB-8 Risk Premium'!L49 -> 0.10298988

Sheet AEB-3 Proxy Selection
B2: PROXY GROUP SCREENING DATA AND RESULTS
D4: [1] | E4: [2] | F4: [3] | G4: [4] | H4: [5] | I4: [6] | J4: [7]
B5: Company | C5: Ticker | D5: Dividends | E5: S&P Credit Rating Between BBB- and AAA | F5: Covered by More Than 1 Analyst | G5: Positive Growth Rates from at least two sources (Value Line, Yahoo! First Call, and Zacks) | H5: % Regulated Operating Income > 60% | I5: % Regulated Electric Operating Income > 80% | J5: Announced Merger
B6: ALLETE, Inc. | C6: ALE | D6: Yes | E6: BBB | F6: Yes | G6: Yes | H6: 1.0283657 | I6: 0.97763701 | J6: No
B7: Alliant Energy Corporation | C7: LNT | D7: Yes | E7: A- | F7: Yes | G7: Yes | H7: 0.96960694 | I7: 0.90661304 | J7: No
B8: Ameren Corporation | C8: AEE | D8: Yes | E8: BBB+ | F8: Yes | G8: Yes | H8: 1 | I8: 0.84572446 | J8: No
B9: Duke Energy Corporation | C9: DUK | D9: Yes | E9: BBB+ | F9: Yes | G9: Yes | H9: 0.9965541 | I9: 0.91341602 | J9: No
B10: Edison International | C10: EIX | D10: Yes | E10: BBB | F10: Yes | G10: Yes | H10: 0.989318 | I10: 1 | J10: No
B11: Entergy Corporation | C11: ETR | D11: Yes | E11: BBB+ | F11: Yes | G11: Yes | H11: 0.9873811 | I11: 0.99461878 | J11: No
B12: Eversource Energy | C12: ES | D12: Yes | E12: A- | F12: Yes | G12: Yes | H12: 0.92382204 | I12: 0.85354453 | J12: No
B13: Evergy, Inc. | C13: EVRG | D13: Yes | E13: BBB+ | F13: Yes | G13: Yes | H13: 1 | I13: 1 | J13: No
B14: IDACORP, Inc. | C14: IDA | D14: Yes | E14: BBB | F14: Yes | G14: Yes | H14: 0.99910992 | I14: 1 | J14: No
B15: NextEra Energy, Inc. | C15: NEE | D15: Yes | E15: A- | F15: Yes | G15: Yes | H15: 0.92156219 | I15: 1 | J15: No
B16: NorthWestern Corporation | C16: NWE | D16: Yes | E16: BBB | F16: Yes | G16: Yes | H16: 0.99748805 | I16: 0.84487532 | J16: No
B17: OGE Energy Corporation | C17: OGE | D17: Yes | E17: BBB+ | F17: Yes | G17: Yes | H17: 1 | I17: 1 | J17: No
... B20: Xcel Energy Inc. | C20: XEL | D20: Yes | E20: A- | F20: Yes | G20: Yes | H20: 1 | I20: 0.86467189 | J20: No
B23: Notes:
B24: [1] Bloomberg Professional
B25: [2] Bloomberg Professional
B26: [3] Yahoo! Finance and Zacks
B27: [4] Yahoo! Finance, Value Line Investment Survey, and Zacks
B28: [5] Form 10-K's for 2022, 2021, and 2020
B29: [6] Form 10-K's for 2022, 2021, and 2020
B30: [7] S&P Capital IQ Pro Financial News Releases

Sheet AEB-4 CGDCF
A2: 30-DAY CONSTANT GROWTH DCF -- AEP TEXAS PROXY GROUP
C4: [1] | D4: [2] | E4: [3] | F4: [4] | G4: [5] | H4: [6] | I4: [7] | J4: [8] | K4: [9] | L4: [10] | M4: [11]
A5: Company | B5: Ticker | C5: Annualized Dividend | D5: Stock Price | E5: Dividend Yield | F5: Expected Dividend Yield | G5: Value Line EPS Growth | H5: Yahoo! Finance EPS Growth | I5: Zacks EPS Growth | J5: Average Growth Rate | K5: Low ROE | L5: Mean ROE | M5: High ROE
A6: ='AEB-3 Proxy Selection'!B6 -> ALLETE, Inc. | B6: ='AEB-3 Proxy Selection'!C6 -> ALE | C6: 2.71 | D6: 60.598 | E6: =C6/D6 -> 0.044720948 | F6: =IFERROR(E6*(1+0.5*J6),"") -> 0.046375623 | G6: 0.06 | H6: 0.081 | I6: 0.081 | J6: =AVERAGE(G6:I6) -> 0.074 | K6: =$E6*(1+0.5*MIN($G6:$I6))+MIN($G6:$I6) -> 0.10606258 | L6: =F6+J6 -> 0.12037562 | M6: =$E6*(1+0.5*MAX($G6:$I6))+MAX($G6:$I6) -> 0.12753215
A7: ='AEB-3 Proxy Selection'!B7 -> Alliant Energy Corporation | B7: ='AEB-3 Proxy Selection'!C7 -> LNT | C7: 1.92 | D7: 49.881497 | E7: =C7/D7 -> 0.038491227 | F7: =IFERROR(E7*(1+0.5*J7),"") -> 0.039732569 | G7: 0.065 | H7: 0.0655 | I7: 0.063 | J7: =AVERAGE(G7:I7) -> 0.0645 | K7: =$E7*(1+0.5*MIN($G7:$I7))+MIN($G7:$I7) -> 0.1027037 | L7: =F7+J7 -> 0.10423257 | M7: =$E7*(1+0.5*MAX($G7:$I7))+MAX($G7:$I7) -> 0.10525181
A8: ='AEB-3 Proxy Selection'!B8 -> Ameren Corporation | B8: ='AEB-3 Proxy Selection'!C8 -> AEE | C8: 2.52 | D8: 71.507333 | E8: =C8/D8 -> 0.035241141 | F8: =IFERROR(E8*(1+0.5*J8),"") -> 0.036269007 | G8: 0.065 | H8: 0.048 | I8: 0.062 | J8: =AVERAGE(G8:I8) -> 0.058333333 | K8: =$E8*(1+0.5*MIN($G8:$I8))+MIN($G8:$I8) -> 0.084086928 | L8: =F8+J8 -> 0.094602341 | M8: =$E8*(1+0.5*MAX($G8:$I8))+MAX($G8:$I8) -> 0.10138648
A9: ='AEB-3 Proxy Selection'!B9 -> Duke Energy Corporation | B9: ='AEB-3 Proxy Selection'!C9 -> DUK | C9: 4.1 | D9: 96.902667 | E9: =C9/D9 -> 0.042310497 | F9: =IFERROR(E9*(1+0.5*J9),"") -> 0.043569234 | G9: 0.05 | H9: 0.0655 | I9: 0.063 | J9: =AVERAGE(G9:I9) -> 0.0595 | K9: =$E9*(1+0.5*MIN($G9:$I9))+MIN($G9:$I9) -> 0.09336826 | L9: =F9+J9 -> 0.10306923 | M9: =$E9*(1+0.5*MAX($G9:$I9))+MAX($G9:$I9) -> 0.10919617
A10: ='AEB-3 Proxy Selection'!B10 -> Edison International | B10: ='AEB-3 Proxy Selection'!C10 -> EIX | C10: 3.12 | D10: 69.70901 | E10: =C10/D10 -> 0.044757485 | F10: =IFERROR(E10*(1+0.5*J10),"") -> 0.045712312 | G10: 0.045 | H10: 0.046 | I10: 0.037 | J10: =AVERAGE(G10:I10) -> 0.042666667 | K10: =$E10*(1+0.5*MIN($G10:$I10))+MIN($G10:$I10) -> 0.082585499 | L10: =F10+J10 -> 0.088378978 | M10: =$E10*(1+0.5*MAX($G10:$I10))+MAX($G10:$I10) -> 0.091786908
A11: ='AEB-3 Proxy Selection'!B11 -> Entergy Corporation | B11: ='AEB-3 Proxy Selection'!C11 -> ETR | C11: 4.52 | D11: 101.03067 | E11: =C11/D11 -> 0.044738891 | F11: =IFERROR(E11*(1+0.5*J11),"") -> 0.04611834 | G11: 0.005 | H11: 0.11 | I11: 0.07 | J11: =AVERAGE(G11:I11) -> 0.061666667 | K11: =$E11*(1+0.5*MIN($G11:$I11))+MIN($G11:$I11) -> 0.049850738 | L11: =F11+J11 -> 0.10778501 | M11: =$E11*(1+0.5*MAX($G11:$I11))+MAX($G11:$I11) -> 0.15719953
A12: ='AEB-3 Proxy Selection'!B12 -> Eversource Energy | B12: ='AEB-3 Proxy Selection'!C12 -> ES | C12: 2.7 | D12: 58.34 | E12: =C12/D12 -> 0.046280425 | F12: =IFERROR(E12*(1+0.5*J12),"") -> 0.047344875 | G12: 0.06 | H12: 0.036 | I12: 0.042 | J12: =AVERAGE(G12:I12) -> 0.046 | K12: =$E12*(1+0.5*MIN($G12:$I12))+MIN($G12:$I12) -> 0.083113473 | L12: =F12+J12 -> 0.093344875 | M12: =$E12*(1+0.5*MAX($G12:$I12))+MAX($G12:$I12) -> 0.10766884
A13: ='AEB-3 Proxy Selection'!B13 -> Evergy, Inc. | B13: ='AEB-3 Proxy Selection'!C13 -> EVRG | C13: 2.57 | D13: 51.868 | E13: =C13/D13 -> 0.049548855 | F13: =IFERROR(E13*(1+0.5*J13),"") -> 0.050729769 | G13: 0.075 | H13: 0.025 | I13: 0.043 | J13: =AVERAGE(G13:I13) -> 0.047666667 | K13: =$E13*(1+0.5*MIN($G13:$I13))+MIN($G13:$I13) -> 0.075168215 | L13: =F13+J13 -> 0.098396436 | M13: =$E13*(1+0.5*MAX($G13:$I13))+MAX($G13:$I13) -> 0.12640694
A14: ='AEB-3 Proxy Selection'!B14 -> IDACORP, Inc. | B14: ='AEB-3 Proxy Selection'!C14 -> IDA | C14: 3.32 | D14: 95.875333 | E14: =C14/D14 -> 0.034628302 | F14: =IFERROR(E14*(1+0.5*J14),"") -> 0.035367039 | G14: 0.04 | H14: 0.044 | I14: 0.044 | J14: =AVERAGE(G14:I14) -> 0.042666667 | K14: =$E14*(1+0.5*MIN($G14:$I14))+MIN($G14:$I14) -> 0.075320868 | L14: =F14+J14 -> 0.078033706 | M14: =$E14*(1+0.5*MAX($G14:$I14))+MAX($G14:$I14) -> 0.079390125
A15: ='AEB-3 Proxy Selection'!B15 -> NextEra Energy, Inc. | B15: ='AEB-3 Proxy Selection'!C15 -> NEE | C15: 1.87 | D15: 59.981 | E15: =C15/D15 -> 0.031176539 | F15: =IFERROR(E15*(1+0.5*J15),"") -> 0.032502062 | G15: 0.095 | H15: 0.0781 | I15: 0.082 | J15: =AVERAGE(G15:I15) -> 0.085033333 | K15: =$E15*(1+0.5*MIN($G15:$I15))+MIN($G15:$I15) -> 0.11049398 | L15: =F15+J15 -> 0.1175354 | M15: =$E15*(1+0.5*MAX($G15:$I15))+MAX($G15:$I15) -> 0.12765742
A16: ='AEB-3 Proxy Selection'!B16 -> NorthWestern Corporation | B16: ='AEB-3 Proxy Selection'!C16 -> NWE | C16: 2.56 | D16: 49.779 | E16: =C16/D16 -> 0.051427309 | F16: =IFERROR(E16*(1+0.5*J16),"") -> 0.05252271 | G16: 0.035 | H16: 0.0408 | I16: 0.052 | J16: =AVERAGE(G16:I16) -> 0.0426 | K16: =$E16*(1+0.5*MIN($G16:$I16))+MIN($G16:$I16) -> 0.087327287 | L16: =F16+J16 -> 0.09512271 | M16: =$E16*(1+0.5*MAX($G16:$I16))+MAX($G16:$I16) -> 0.10476442
A17: ='AEB-3 Proxy Selection'!B17 -> OGE Energy Corporation | B17: ='AEB-3 Proxy Selection'!C17 -> OGE | C17: 1.6728 | D17: 34.14228 | E17: =C17/D17 -> 0.04899497 | F17: =IFERROR(E17*(1+0.5*J17),"") -> 0.050281088 | G17: 0.065 | H17: negative | I17: 0.04 | J17: =AVERAGE(G17:I17) -> 0.0525 | K17: =$E17*(1+0.5*MIN($G17:$I17))+MIN($G17:$I17) -> 0.08997487 | L17: =F17+J17 -> 0.10278109 | M17: =$E17*(1+0.5*MAX($G17:$I17))+MAX($G17:$I17) -> 0.11558731
A18: ='AEB-3 Proxy Selection'!B18 -> Pinnacle West Capital Corporation | B18: ='AEB-3 Proxy Selection'!C18 -> PNW | C18: 3.52 | D18: 70.492387 | E18: =C18/D18 -> 0.04993447 | F18: =IFERROR(E18*(1+0.5*J18),"") -> 0.05096645 | G18: 0.025 | H18: 0.059 | I18: 0.04 | J18: =AVERAGE(G18:I18) -> 0.041333333 | K18: =$E18*(1+0.5*MIN($G18:$I18))+MIN($G18:$I18) -> 0.075558651 | L18: =F18+J18 -> 0.092299783 | M18: =$E18*(1+0.5*MAX($G18:$I18))+MAX($G18:$I18) -> 0.11040754
A19: ='AEB-3 Proxy Selection'!B19 -> Portland General Electric Company | B19: ='AEB-3 Proxy Selection'!C19 -> POR | C19: 1.9 | D19: 42.268437 | E19: =C19/D19 -> 0.044950799 | F19: =IFERROR(E19*(1+0.5*J19),"") -> 0.04611952 | G19: 0.05 | H19: 0.046 | I19: 0.06 | J19: =AVERAGE(G19:I19) -> 0.052 | K19: =$E19*(1+0.5*MIN($G19:$I19))+MIN($G19:$I19) -> 0.091984667 | L19: =F19+J19 -> 0.09811952 | M19: =$E19*(1+0.5*MAX($G19:$I19))+MAX($G19:$I19) -> 0.10629932
A20: ='AEB-3 Proxy Selection'!B20 -> Xcel Energy Inc. | B20: ='AEB-3 Proxy Selection'!C20 -> XEL | C20: 2.08 | D20: 61.14286 | E20: =C20/D20 -> 0.03401869 | F20: =IFERROR(E20*(1+0.5*J20),"") -> 0.035071568 | G20: 0.06 | H20: 0.0657 | I20: 0.06 | J20: =AVERAGE(G20:I20) -> 0.0619 | K20: =$E20*(1+0.5*MIN($G20:$I20))+MIN($G20:$I20) -> 0.095039251 | L20: =F20+J20 -> 0.096971568 | M20: =$E20*(1+0.5*MAX($G20:$I20))+MAX($G20:$I20) -> 0.1008362
A21: Mean | E21: =AVERAGE(E6:E20) -> 0.042748037 | F21: =AVERAGE(F6:F20) -> 0.043912144 | G21: =AVERAGE(G6:G20) -> 0.053 | H21: =AVERAGE(H6:H20) -> 0.0579 | I21: =AVERAGE(I6:I20) -> 0.055933333 | J21: =AVERAGE(J6:J20) -> 0.055491111 | K21: =AVERAGE(K6:K20) -> 0.086842598 | L21: =AVERAGE(L6:L20) -> 0.099403256 | M21: =AVERAGE(M6:M20) -> 0.11142474
A22: Median | E22: =MEDIAN(E6:E20) -> 0.044738891 | F22: =MEDIAN(F6:F20) -> 0.04611834 | G22: =MEDIAN(G6:G20) -> 0.06 | H22: =MEDIAN(H6:H20) -> 0.0535 | I22: =MEDIAN(I6:I20) -> 0.06 | J22: =MEDIAN(J6:J20) -> 0.0525 | K22: =MEDIAN(K6:K20) -> 0.087327287 | L22: =MEDIAN(L6:L20) -> 0.09811952 | M22: =MEDIAN(M6:M20) -> 0.10766884
A24: Notes:
A25: [1] Source: Bloomberg Professional
A26: [2] Source: Bloomberg Professional, equals 30-day average as of January 31, 2024
A27: [3] Equals [1] / [2]
A28: [4] Equals [3] x (1 + 0.50 x [8])
A29: [5] Source: Value Line
A30: [6] Source: Yahoo! Finance
A31: [7] Source: Zacks
A32: [8] Equals Average ([5], [6], [7])
A33: [9] Equals [3] x (1 + 0.50 x Minimum ([5], [6], [7]) + Minimum ([5], [6], [7])
A34: [10] Equals [4] + [8]
A35: [11] Equals [3] x (1 + 0.50 x Maximum ([5], [6], [7]) + Maximum ([5], [6], [7])
A38: 90-DAY CONSTANT GROWTH DCF -- AEP TEXAS PROXY GROUP
C40: [1] | D40: [2] | E40: [3] | F40: [4] | G40: [5] | H40: [6] | I40: [7] | J40: [8] | K40: [9] | L40: [10] | M40: [11]
A41: Company | B41: Ticker | C41: Annualized Dividend | D41: Stock Price | E41: Dividend Yield | F41: Expected Dividend Yield | G41: Value Line EPS Growth | H41: Yahoo! Finance EPS Growth | I41: Zacks EPS Growth | J41: Average Growth Rate | K41: Low ROE | L41: Mean ROE | M41: High ROE
A42: =A6 -> ALLETE, Inc. | B42: =B6 -> ALE | C42: =C6 -> 2.71 | D42: 56.725876 | E42: =C42/D42 -> 0.047773613 | F42: =IFERROR(E42*(1+0.5*J42),"") -> 0.049541236 | G42: =G6 -> 0.06 | H42: =H6 -> 0.081 | I42: =I6 -> 0.081 | J42: =AVERAGE(G42:I42) -> 0.074 | K42: =$E42*(1+0.5*MIN($G42:$I42))+MIN($G42:$I42) -> 0.10920682 | L42: =F42+J42 -> 0.12354124 | M42: =$E42*(1+0.5*MAX($G42:$I42))+MAX($G42:$I42) -> 0.13070844
A43: =A7 -> Alliant Energy Corporation | B43: =B7 -> LNT | C43: =C7 -> 1.92 | D43: 49.294667 | E43: =C43/D43 -> 0.038949447 | F43: =IFERROR(E43*(1+0.5*J43),"") -> 0.040205567 | G43: =G7 -> 0.065 | H43: =H7 -> 0.0655 | I43: =I7 -> 0.063 | J43: =AVERAGE(G43:I43) -> 0.0645 | K43: =$E43*(1+0.5*MIN($G43:$I43))+MIN($G43:$I43) -> 0.10317635 | L43: =F43+J43 -> 0.10470557 | M43: =$E43*(1+0.5*MAX($G43:$I43))+MAX($G43:$I43) -> 0.10572504
A44: =A8 -> Ameren Corporation | B44: =B8 -> AEE | C44: =C8 -> 2.52 | D44: 74.628454 | E44: =C44/D44 -> 0.033767281 | F44: =IFERROR(E44*(1+0.5*J44),"") -> 0.03475216 | G44: =G8 -> 0.065 | H44: =H8 -> 0.048 | I44: =I8 -> 0.062 | J44: =AVERAGE(G44:I44) -> 0.058333333 | K44: =$E44*(1+0.5*MIN($G44:$I44))+MIN($G44:$I44) -> 0.082577696 | L44: =F44+J44 -> 0.093085493 | M44: =$E44*(1+0.5*MAX($G44:$I44))+MAX($G44:$I44) -> 0.099864718
A45: =A9 -> Duke Energy Corporation | B45: =B9 -> DUK | C45: =C9 -> 4.1 | D45: 91.918216 | E45: =C45/D45 -> 0.044604869 | F45: =IFERROR(E45*(1+0.5*J45),"") -> 0.045931864 | G45: =G9 -> 0.05 | H45: =H9 -> 0.0655 | I45: =I9 -> 0.063 | J45: =AVERAGE(G45:I45) -> 0.0595 | K45: =$E45*(1+0.5*MIN($G45:$I45))+MIN($G45:$I45) -> 0.095719991 | L45: =F45+J45 -> 0.10543186 | M45: =$E45*(1+0.5*MAX($G45:$I45))+MAX($G45:$I45) -> 0.11156568
A46: =A10 -> Edison International | B46: =B10 -> EIX | C46: =C10 -> 3.12 | D46: 66.060798 | E46: =C46/D46 -> 0.047229221 | F46: =IFERROR(E46*(1+0.5*J46),"") -> 0.048236777 | G46: =G10 -> 0.045 | H46: =H10 -> 0.046 | I46: =I10 -> 0.037 | J46: =AVERAGE(G46:I46) -> 0.042666667 | K46: =$E46*(1+0.5*MIN($G46:$I46))+MIN($G46:$I46) -> 0.085102961 | L46: =F46+J46 -> 0.090903444 | M46: =$E46*(1+0.5*MAX($G46:$I46))+MAX($G46:$I46) -> 0.094315493
A47: =A11 -> Entergy Corporation | B47: =B11 -> ETR | C47: =C11 -> 4.52 | D47: 97.77523 | E47: =C47/D47 -> 0.046228477 | F47: =IFERROR(E47*(1+0.5*J47),"") -> 0.047653855 | G47: =G11 -> 0.005 | H47: =H11 -> 0.11 | I47: =I11 -> 0.07 | J47: =AVERAGE(G47:I47) -> 0.061666667 | K47: =$E47*(1+0.5*MIN($G47:$I47))+MIN($G47:$I47) -> 0.051344048 | L47: =F47+J47 -> 0.10932052 | M47: =$E47*(1+0.5*MAX($G47:$I47))+MAX($G47:$I47) -> 0.15877104
A48: =A12 -> Eversource Energy | B48: =B12 -> ES | C48: =C12 -> 2.7 | D48: 57.245787 | E48: =C48/D48 -> 0.047165043 | F48: =IFERROR(E48*(1+0.5*J48),"") -> 0.048249839 | G48: =G12 -> 0.06 | H48: =H12 -> 0.036 | I48: =I12 -> 0.042 | J48: =AVERAGE(G48:I48) -> 0.046 | K48: =$E48*(1+0.5*MIN($G48:$I48))+MIN($G48:$I48) -> 0.084014014 | L48: =F48+J48 -> 0.094249839 | M48: =$E48*(1+0.5*MAX($G48:$I48))+MAX($G48:$I48) -> 0.10857999
A49: =A13 -> Evergy, Inc. | B49: =B13 -> EVRG | C49: =C13 -> 2.57 | D49: 50.509026 | E49: =C49/D49 -> 0.050881995 | F49: =IFERROR(E49*(1+0.5*J49),"") -> 0.052094683 | G49: =G13 -> 0.075 | H49: =H13 -> 0.025 | I49: =I13 -> 0.043 | J49: =AVERAGE(G49:I49) -> 0.047666667 | K49: =$E49*(1+0.5*MIN($G49:$I49))+MIN($G49:$I49) -> 0.07651802 | L49: =F49+J49 -> 0.09976135 | M49: =$E49*(1+0.5*MAX($G49:$I49))+MAX($G49:$I49) -> 0.12779007
A50: =A14 -> IDACORP, Inc. | B50: =B14 -> IDA | C50: =C14 -> 3.32 | D50: 96.064384 | E50: =C50/D50 -> 0.034560155 | F50: =IFERROR(E50*(1+0.5*J50),"") -> 0.035297438 | G50: =G14 -> 0.04 | H50: =H14 -> 0.044 | I50: =I14 -> 0.044 | J50: =AVERAGE(G50:I50) -> 0.042666667 | K50: =$E50*(1+0.5*MIN($G50:$I50))+MIN($G50:$I50) -> 0.075251358 | L50: =F50+J50 -> 0.077964105 | M50: =$E50*(1+0.5*MAX($G50:$I50))+MAX($G50:$I50) -> 0.079320478
A51: =A15 -> NextEra Energy, Inc. | B51: =B15 -> NEE | C51: =C15 -> 1.87 | D51: 57.788179 | E51: =C51/D51 -> 0.032359559 | F51: =IFERROR(E51*(1+0.5*J51),"") -> 0.03373538 | G51: =G15 -> 0.095 | H51: =H15 -> 0.0781 | I51: =I15 -> 0.082 | J51: =AVERAGE(G51:I51) -> 0.085033333 | K51: =$E51*(1+0.5*MIN($G51:$I51))+MIN($G51:$I51) -> 0.1117232 | L51: =F51+J51 -> 0.11876871 | M51: =$E51*(1+0.5*MAX($G51:$I51))+MAX($G51:$I51) -> 0.12889664
A52: =A16 -> NorthWestern Corporation | B52: =B16 -> NWE | C52: =C16 -> 2.56 | D52: 49.312859 | E52: =C52/D52 -> 0.051913437 | F52: =IFERROR(E52*(1+0.5*J52),"") -> 0.053019193 | G52: =G16 -> 0.035 | H52: =H16 -> 0.0408 | I52: =I16 -> 0.052 | J52: =AVERAGE(G52:I52) -> 0.0426 | K52: =$E52*(1+0.5*MIN($G52:$I52))+MIN($G52:$I52) -> 0.087821922 | L52: =F52+J52 -> 0.095619193 | M52: =$E52*(1+0.5*MAX($G52:$I52))+MAX($G52:$I52) -> 0.10526319
A53: =A17 -> OGE Energy Corporation | B53: =B17 -> OGE | C53: =C17 -> 1.6728 | D53: 33.977051 | E53: =C53/D53 -> 0.049233231 | F53: =IFERROR(E53*(1+0.5*J53),"") -> 0.050525603 | G53: =G17 -> 0.065 | H53: =H17 -> negative | I53: =I17 -> 0.04 | J53: =AVERAGE(G53:I53) -> 0.0525 | K53: =$E53*(1+0.5*MIN($G53:$I53))+MIN($G53:$I53) -> 0.090217895 | L53: =F53+J53 -> 0.1030256 | M53: =$E53*(1+0.5*MAX($G53:$I53))+MAX($G53:$I53) -> 0.11583331
... A56: =A20 -> Xcel Energy Inc. | B56: =B20 -> XEL | C56: =C20 -> 2.08 | D56: 59.728513 | E56: =C56/D56 -> 0.034824239 | F56: =IFERROR(E56*(1+0.5*J56),"") -> 0.035902049 | G56: =G20 -> 0.06 | H56: =H20 -> 0.0657 | I56: =I20 -> 0.06 | J56: =AVERAGE(G56:I56) -> 0.0619 | K56: =$E56*(1+0.5*MIN($G56:$I56))+MIN($G56:$I56) -> 0.095868966 | L56: =F56+J56 -> 0.097802049 | M56: =$E56*(1+0.5*MAX($G56:$I56))+MAX($G56:$I56) -> 0.10166821
A57: Mean | E57: =AVERAGE(E42:E56) -> 0.043629189 | F57: =AVERAGE(F42:F56) -> 0.044820033 | G57: =AVERAGE(G42:G56) -> 0.053 | H57: =AVERAGE(H42:H56) -> 0.0579 | I57: =AVERAGE(I42:I56) -> 0.055933333 | J57: =AVERAGE(J42:J56) -> 0.055491111 | K57: =AVERAGE(K42:K56) -> 0.087744025 | L57: =AVERAGE(L42:L56) -> 0.10031114 | M57: =AVERAGE(M42:M56) -> 0.11233823
A58: Median | E58: =MEDIAN(E42:E56) -> 0.046228477 | F58: =MEDIAN(F42:F56) -> 0.047653855 | G58: =MEDIAN(G42:G56) -> 0.06 | H58: =MEDIAN(H42:H56) -> 0.0535 | I58: =MEDIAN(I42:I56) -> 0.06 | J58: =MEDIAN(J42:J56) -> 0.0525 | K58: =MEDIAN(K42:K56) -> 0.087821922 | L58: =MEDIAN(L42:L56) -> 0.09919911 | M58: =MEDIAN(M42:M56) -> 0.10857999
A60: Notes:
A61: [1] Source: Bloomberg Professional
A62: [2] Source: Bloomberg Professional, equals 90-day average as of January 31, 2024
A63: [3] Equals [1] / [2]
A64: [4] Equals [3] x (1 + 0.50 x [8])
A65: [5] Source: Value Line
A66: [6] Source: Yahoo! Finance
A67: [7] Source: Zacks
A68: [8] Equals Average ([5], [6], [7])
A69: [9] Equals [3] x (1 + 0.50 x Minimum ([5], [6], [7]) + Minimum ([5], [6], [7])
A70: [10] Equals [4] + [8]
A71: [11] Equals [3] x (1 + 0.50 x Maximum ([5], [6], [7]) + Maximum ([5], [6], [7])
A74: 180-DAY CONSTANT GROWTH DCF -- AEP TEXAS PROXY GROUP
C76: [1] | D76: [2] | E76: [3] | F76: [4] | G76: [5] | H76: [6] | I76: [7] | J76: [8] | K76: [9] | L76: [10] | M76: [11]
A77: Company | B77: Ticker | C77: Annualized Dividend | D77: Stock Price | E77: Dividend Yield | F77: Expected Dividend Yield | G77: Value Line EPS Growth | H77: Yahoo! Finance EPS Growth | I77: Zacks EPS Growth | J77: Average Growth Rate | K77: Low ROE | L77: Mean ROE | M77: High ROE
A78: =A42 -> ALLETE, Inc. | B78: =B42 -> ALE | C78: =C42 -> 2.71 | D78: 56.706133 | E78: =C78/D78 -> 0.047790245 | F78: =IFERROR(E78*(1+0.5*J78),"") -> 0.049558484 | G78: =G42 -> 0.06 | H78: =H42 -> 0.081 | I78: =I42 -> 0.081 | J78: =AVERAGE(G78:I78) -> 0.074 | K78: =$E78*(1+0.5*MIN($G78:$I78))+MIN($G78:$I78) -> 0.10922395 | L78: =F78+J78 -> 0.12355848 | M78: =$E78*(1+0.5*MAX($G78:$I78))+MAX($G78:$I78) -> 0.13072575
A79: =A43 -> Alliant Energy Corporation | B79: =B43 -> LNT | C79: =C43 -> 1.92 | D79: 50.156308 | E79: =C79/D79 -> 0.03828033 | F79: =IFERROR(E79*(1+0.5*J79),"") -> 0.03951487 | G79: =G43 -> 0.065 | H79: =H43 -> 0.0655 | I79: =I43 -> 0.063 | J79: =AVERAGE(G79:I79) -> 0.0645 | K79: =$E79*(1+0.5*MIN($G79:$I79))+MIN($G79:$I79) -> 0.10248616 | L79: =F79+J79 -> 0.10401487 | M79: =$E79*(1+0.5*MAX($G79:$I79))+MAX($G79:$I79) -> 0.10503401
A80: =A44 -> Ameren Corporation | B80: =B44 -> AEE | C80: =C44 -> 2.52 | D80: 77.704048 | E80: =C80/D80 -> 0.032430743 | F80: =IFERROR(E80*(1+0.5*J80),"") -> 0.033376639 | G80: =G44 -> 0.065 | H80: =H44 -> 0.048 | I80: =I44 -> 0.062 | J80: =AVERAGE(G80:I80) -> 0.058333333 | K80: =$E80*(1+0.5*MIN($G80:$I80))+MIN($G80:$I80) -> 0.081209081 | L80: =F80+J80 -> 0.091709973 | M80: =$E80*(1+0.5*MAX($G80:$I80))+MAX($G80:$I80) -> 0.098484742
A81: =A45 -> Duke Energy Corporation | B81: =B45 -> DUK | C81: =C45 -> 4.1 | D81: 90.790562 | E81: =C81/D81 -> 0.045158879 | F81: =IFERROR(E81*(1+0.5*J81),"") -> 0.046502356 | G81: =G45 -> 0.05 | H81: =H45 -> 0.0655 | I81: =I45 -> 0.063 | J81: =AVERAGE(G81:I81) -> 0.0595 | K81: =$E81*(1+0.5*MIN($G81:$I81))+MIN($G81:$I81) -> 0.096287851 | L81: =F81+J81 -> 0.10600236 | M81: =$E81*(1+0.5*MAX($G81:$I81))+MAX($G81:$I81) -> 0.11213783
A82: =A46 -> Edison International | B82: =B46 -> EIX | C82: =C46 -> 3.12 | D82: 66.834096 | E82: =C82/D82 -> 0.046682759 | F82: =IFERROR(E82*(1+0.5*J82),"") -> 0.047678658 | G82: =G46 -> 0.045 | H82: =H46 -> 0.046 | I82: =I46 -> 0.037 | J82: =AVERAGE(G82:I82) -> 0.042666667 | K82: =$E82*(1+0.5*MIN($G82:$I82))+MIN($G82:$I82) -> 0.08454639 | L82: =F82+J82 -> 0.090345325 | M82: =$E82*(1+0.5*MAX($G82:$I82))+MAX($G82:$I82) -> 0.093756463
A83: =A47 -> Entergy Corporation | B83: =B47 -> ETR | C83: =C47 -> 4.52 | D83: 97.247481 | E83: =C83/D83 -> 0.046479353 | F83: =IFERROR(E83*(1+0.5*J83),"") -> 0.047912467 | G83: =G47 -> 0.005 | H83: =H47 -> 0.11 | I83: =I47 -> 0.07 | J83: =AVERAGE(G83:I83) -> 0.061666667 | K83: =$E83*(1+0.5*MIN($G83:$I83))+MIN($G83:$I83) -> 0.051595552 | L83: =F83+J83 -> 0.10957913 | M83: =$E83*(1+0.5*MAX($G83:$I83))+MAX($G83:$I83) -> 0.15903572
A84: =A48 -> Eversource Energy | B84: =B48 -> ES | C84: =C48 -> 2.7 | D84: 62.275433 | E84: =C84/D84 -> 0.04335578 | F84: =IFERROR(E84*(1+0.5*J84),"") -> 0.044352963 | G84: =G48 -> 0.06 | H84: =H48 -> 0.036 | I84: =I48 -> 0.042 | J84: =AVERAGE(G84:I84) -> 0.046 | K84: =$E84*(1+0.5*MIN($G84:$I84))+MIN($G84:$I84) -> 0.080136184 | L84: =F84+J84 -> 0.090352963 | M84: =$E84*(1+0.5*MAX($G84:$I84))+MAX($G84:$I84) -> 0.10465645
A85: =A49 -> Evergy, Inc. | B85: =B49 -> EVRG | C85: =C49 -> 2.57 | D85: 53.558344 | E85: =C85/D85 -> 0.047985054 | F85: =IFERROR(E85*(1+0.5*J85),"") -> 0.049128697 | G85: =G49 -> 0.075 | H85: =H49 -> 0.025 | I85: =I49 -> 0.043 | J85: =AVERAGE(G85:I85) -> 0.047666667 | K85: =$E85*(1+0.5*MIN($G85:$I85))+MIN($G85:$I85) -> 0.073584867 | L85: =F85+J85 -> 0.096795364 | M85: =$E85*(1+0.5*MAX($G85:$I85))+MAX($G85:$I85) -> 0.12478449
A86: =A50 -> IDACORP, Inc. | B86: =B50 -> IDA | C86: =C50 -> 3.32 | D86: 97.924135 | E86: =C86/D86 -> 0.033903797 | F86: =IFERROR(E86*(1+0.5*J86),"") -> 0.034627078 | G86: =G50 -> 0.04 | H86: =H50 -> 0.044 | I86: =I50 -> 0.044 | J86: =AVERAGE(G86:I86) -> 0.042666667 | K86: =$E86*(1+0.5*MIN($G86:$I86))+MIN($G86:$I86) -> 0.074581873 | L86: =F86+J86 -> 0.077293745 | M86: =$E86*(1+0.5*MAX($G86:$I86))+MAX($G86:$I86) -> 0.078649681
A87: =A51 -> NextEra Energy, Inc. | B87: =B51 -> NEE | C87: =C51 -> 1.87 | D87: 64.150123 | E87: =C87/D87 -> 0.029150373 | F87: =IFERROR(E87*(1+0.5*J87),"") -> 0.03038975 | G87: =G51 -> 0.095 | H87: =H51 -> 0.0781 | I87: =I51 -> 0.082 | J87: =AVERAGE(G87:I87) -> 0.085033333 | K87: =$E87*(1+0.5*MIN($G87:$I87))+MIN($G87:$I87) -> 0.10838869 | L87: =F87+J87 -> 0.11542308 | M87: =$E87*(1+0.5*MAX($G87:$I87))+MAX($G87:$I87) -> 0.12553502
A88: =A52 -> NorthWestern Corporation | B88: =B52 -> NWE | C88: =C52 -> 2.56 | D88: 51.543923 | E88: =C88/D88 -> 0.049666379 | F88: =IFERROR(E88*(1+0.5*J88),"") -> 0.050724273 | G88: =G52 -> 0.035 | H88: =H52 -> 0.0408 | I88: =I52 -> 0.052 | J88: =AVERAGE(G88:I88) -> 0.0426 | K88: =$E88*(1+0.5*MIN($G88:$I88))+MIN($G88:$I88) -> 0.085535541 | L88: =F88+J88 -> 0.093324273 | M88: =$E88*(1+0.5*MAX($G88:$I88))+MAX($G88:$I88) -> 0.1029577
A89: =A53 -> OGE Energy Corporation | B89: =B53 -> OGE | C89: =C53 -> 1.6728 | D89: 34.207859 | E89: =C89/D89 -> 0.048901044 | F89: =IFERROR(E89*(1+0.5*J89),"") -> 0.050184696 | G89: =G53 -> 0.065 | H89: =H53 -> negative | I89: =I53 -> 0.04 | J89: =AVERAGE(G89:I89) -> 0.0525 | K89: =$E89*(1+0.5*MIN($G89:$I89))+MIN($G89:$I89) -> 0.089879065 | L89: =F89+J89 -> 0.1026847 | M89: =$E89*(1+0.5*MAX($G89:$I89))+MAX($G89:$I89) -> 0.11549033
... A92: =A56 -> Xcel Energy Inc. | B92: =B56 -> XEL | C92: =C56 -> 2.08 | D92: 60.121227 | E92: =C92/D92 -> 0.034596766 | F92: =IFERROR(E92*(1+0.5*J92),"") -> 0.035667536 | G92: =G56 -> 0.06 | H92: =H56 -> 0.0657 | I92: =I56 -> 0.06 | J92: =AVERAGE(G92:I92) -> 0.0619 | K92: =$E92*(1+0.5*MIN($G92:$I92))+MIN($G92:$I92) -> 0.095634669 | L92: =F92+J92 -> 0.097567536 | M92: =$E92*(1+0.5*MAX($G92:$I92))+MAX($G92:$I92) -> 0.10143327
A93: Mean | E93: =AVERAGE(E78:E92) -> 0.042349983 | F93: =AVERAGE(F78:F92) -> 0.043506522 | G93: =AVERAGE(G78:G92) -> 0.053 | H93: =AVERAGE(H78:H92) -> 0.0579 | I93: =AVERAGE(I78:I92) -> 0.055933333 | J93: =AVERAGE(J78:J92) -> 0.055491111 | K93: =AVERAGE(K78:K92) -> 0.086436869 | L93: =AVERAGE(L78:L92) -> 0.098997633 | M93: =AVERAGE(M78:M92) -> 0.11101681
A94: Median | E94: =MEDIAN(E78:E92) -> 0.045158879 | F94: =MEDIAN(F78:F92) -> 0.046502356 | G94: =MEDIAN(G78:G92) -> 0.06 | H94: =MEDIAN(H78:H92) -> 0.0535 | I94: =MEDIAN(I78:I92) -> 0.06 | J94: =MEDIAN(J78:J92) -> 0.0525 | K94: =MEDIAN(K78:K92) -> 0.085535541 | L94: =MEDIAN(L78:L92) -> 0.096855957 | M94: =MEDIAN(M78:M92) -> 0.10503401
A96: Notes:
A97: [1] Source: Bloomberg Professional
A98: [2] Source: Bloomberg Professional, equals 180-day average as of January 31, 2024
A99: [3] Equals [1] / [2]
A100: [4] Equals [3] x (1 + 0.50 x [8])
A101: [5] Source: Value Line
A102: [6] Source: Yahoo! Finance
A103: [7] Source: Zacks
A104: [8] Equals Average ([5], [6], [7])
A105: [9] Equals [3] x (1 + 0.50 x Minimum ([5], [6], [7]) + Minimum ([5], [6], [7])
A106: [10] Equals [4] + [8]
A107: [11] Equals [3] x (1 + 0.50 x Maximum ([5], [6], [7]) + Maximum ([5], [6], [7])

Sheet AEB-5 CAPM
B2: CAPITAL ASSET PRICING MODEL -- CURRENT RISK-FREE RATE & VL BETA
B4: K = Rf + β (Rm − Rf)
B5: K = Rf + 0.25 x (Rm - Rf) + 0.75 x β x (Rm − Rf)
D7: [1] | E7: [2] | F7: [3] | G7: [4] | H7: [5] | I7: [6]
B8: Company | C8: Ticker | D8: Current 30-day average of 30-year U.S. Treasury bond yield | E8: Beta (β) | F8: Market Return (Rm) | G8: Market Risk Premium (Rm − Rf) | H8: ROE (K) | I8: ECAPM ROE (K)
B9: ='AEB-4 CGDCF'!A6 -> ALLETE, Inc. | C9: ='AEB-4 CGDCF'!B6 -> ALE | D9: ='AEB-8 Risk Premium'!J47 -> 0.041926667 | E9: 0.95 | F9: ='AEB-7 Market Return'!B8 -> 0.12219338 | G9: =F9-D9 -> 0.080266712 | H9: =IFERROR(G9*E9+D9, "") -> 0.11818004 | I9: =IFERROR((0.25*G9)+(0.75*E9*G9)+D9, "") -> 0.11918338
B10: ='AEB-4 CGDCF'!A7 -> Alliant Energy Corporation | C10: ='AEB-4 CGDCF'!B7 -> LNT | D10: =$D$9 -> 0.041926667 | E10: 0.9 | F10: =$F$9 -> 0.12219338 | G10: =F10-D10 -> 0.080266712 | H10: =IFERROR(G10*E10+D10, "") -> 0.11416671 | I10: =IFERROR((0.25*G10)+(0.75*E10*G10)+D10, "") -> 0.11617337
B11: ='AEB-4 CGDCF'!A8 -> Ameren Corporation | C11: ='AEB-4 CGDCF'!B8 -> AEE | D11: =$D$9 -> 0.041926667 | E11: 0.9 | F11: =$F$9 -> 0.12219338 | G11: =F11-D11 -> 0.080266712 | H11: =IFERROR(G11*E11+D11, "") -> 0.11416671 | I11: =IFERROR((0.25*G11)+(0.75*E11*G11)+D11, "") -> 0.11617337
B12: ='AEB-4 CGDCF'!A9 -> Duke Energy Corporation | C12: ='AEB-4 CGDCF'!B9 -> DUK | D12: =$D$9 -> 0.041926667 | E12: 0.85 | F12: =$F$9 -> 0.12219338 | G12: =F12-D12 -> 0.080266712 | H12: =IFERROR(G12*E12+D12, "") -> 0.11015337 | I12: =IFERROR((0.25*G12)+(0.75*E12*G12)+D12, "") -> 0.11316337
B13: ='AEB-4 CGDCF'!A10 -> Edison International | C13: ='AEB-4 CGDCF'!B10 -> EIX | D13: =$D$9 -> 0.041926667 | E13: 1 | F13: =$F$9 -> 0.12219338 | G13: =F13-D13 -> 0.080266712 | H13: =IFERROR(G13*E13+D13, "") -> 0.12219338 | I13: =IFERROR((0.25*G13)+(0.75*E13*G13)+D13, "") -> 0.12219338
B14: ='AEB-4 CGDCF'!A11 -> Entergy Corporation | C14: ='AEB-4 CGDCF'!B11 -> ETR | D14: =$D$9 -> 0.041926667 | E14: 0.95 | F14: =$F$9 -> 0.12219338 | G14: =F14-D14 -> 0.080266712 | H14: =IFERROR(G14*E14+D14, "") -> 0.11818004 | I14: =IFERROR((0.25*G14)+(0.75*E14*G14)+D14, "") -> 0.11918338
B15: ='AEB-4 CGDCF'!A12 -> Eversource Energy | C15: ='AEB-4 CGDCF'!B12 -> ES | D15: =$D$9 -> 0.041926667 | E15: 0.9 | F15: =$F$9 -> 0.12219338 | G15: =F15-D15 -> 0.080266712 | H15: =IFERROR(G15*E15+D15, "") -> 0.11416671 | I15: =IFERROR((0.25*G15)+(0.75*E15*G15)+D15, "") -> 0.11617337
B16: ='AEB-4 CGDCF'!A13 -> Evergy, Inc. | C16: ='AEB-4 CGDCF'!B13 -> EVRG | D16: =$D$9 -> 0.041926667 | E16: 0.95 | F16: =$F$9 -> 0.12219338 | G16: =F16-D16 -> 0.080266712 | H16: =IFERROR(G16*E16+D16, "") -> 0.11818004 | I16: =IFERROR((0.25*G16)+(0.75*E16*G16)+D16, "") -> 0.11918338
B17: ='AEB-4 CGDCF'!A14 -> IDACORP, Inc. | C17: ='AEB-4 CGDCF'!B14 -> IDA | D17: =$D$9 -> 0.041926667 | E17: 0.85 | F17: =$F$9 -> 0.12219338 | G17: =F17-D17 -> 0.080266712 | H17: =IFERROR(G17*E17+D17, "") -> 0.11015337 | I17: =IFERROR((0.25*G17)+(0.75*E17*G17)+D17, "") -> 0.11316337
B18: ='AEB-4 CGDCF'!A15 -> NextEra Energy, Inc. | C18: ='AEB-4 CGDCF'!B15 -> NEE | D18: =$D$9 -> 0.041926667 | E18: 0.95 | F18: =$F$9 -> 0.12219338 | G18: =F18-D18 -> 0.080266712 | H18: =IFERROR(G18*E18+D18, "") -> 0.11818004 | I18: =IFERROR((0.25*G18)+(0.75*E18*G18)+D18, "") -> 0.11918338
B19: ='AEB-4 CGDCF'!A16 -> NorthWestern Corporation | C19: ='AEB-4 CGDCF'!B16 -> NWE | D19: =$D$9 -> 0.041926667 | E19: 0.95 | F19: =$F$9 -> 0.12219338 | G19: =F19-D19 -> 0.080266712 | H19: =IFERROR(G19*E19+D19, "") -> 0.11818004 | I19: =IFERROR((0.25*G19)+(0.75*E19*G19)+D19, "") -> 0.11918338
B20: ='AEB-4 CGDCF'!A17 -> OGE Energy Corporation | C20: ='AEB-4 CGDCF'!B17 -> OGE | D20: =$D$9 -> 0.041926667 | E20: 1.05 | F20: =$F$9 -> 0.12219338 | G20: =F20-D20 -> 0.080266712 | H20: =IFERROR(G20*E20+D20, "") -> 0.12620671 | I20: =IFERROR((0.25*G20)+(0.75*E20*G20)+D20, "") -> 0.12520338
B21: ='AEB-4 CGDCF'!A18 -> Pinnacle West Capital Corporation | C21: ='AEB-4 CGDCF'!B18 -> PNW | D21: =$D$9 -> 0.041926667 | E21: 0.95 | F21: =$F$9 -> 0.12219338 | G21: =F21-D21 -> 0.080266712 | H21: =IFERROR(G21*E21+D21, "") -> 0.11818004 | I21: =IFERROR((0.25*G21)+(0.75*E21*G21)+D21, "") -> 0.11918338
... B23: ='AEB-4 CGDCF'!A20 -> Xcel Energy Inc. | C23: ='AEB-4 CGDCF'!B20 -> XEL | D23: =$D$9 -> 0.041926667 | E23: 0.85 | F23: =$F$9 -> 0.12219338 | G23: =F23-D23 -> 0.080266712 | H23: =IFERROR(G23*E23+D23, "") -> 0.11015337 | I23: =IFERROR((0.25*G23)+(0.75*E23*G23)+D23, "") -> 0.11316337
B24: Mean | H24: =AVERAGE(H9:H23) -> 0.11630715 | I24: =AVERAGE(I9:I23) -> 0.11777871
B25: Median | H25: =MEDIAN(H9:H23) -> 0.11818004 | I25: =MEDIAN(I9:I23) -> 0.11918338
B27: Notes:
B28: [1] Source: Bloomberg Professional, as of January 31, 2024
B29: [2] Source: Value Line
B30: [3] Source: Market Return
B31: [4] Equals [3] - [1]
B32: [5] Equals [1] + [2] x [4]
B33: [6] Equals [1] + 0.25 x ([4]) + 0.75 x ([2] x [4])
B36: CAPITAL ASSET PRICING MODEL -- NEAR-TERM PROJECTED RISK-FREE RATE & VL BETA
B38: K = Rf + β (Rm − Rf)
B39: K = Rf + 0.25 x (Rm - Rf) + 0.75 x β x (Rm − Rf)
D41: [1] | E41: [2] | F41: [3] | G41: [4] | H41: [5] | I41: [6]
B42: Company | C42: Ticker | D42: Near-term projected 30-year U.S. Treasury bond yield (Q2 2024 - Q2 2025) | E42: Beta (β) | F42: Market Return (Rm) | G42: Market Risk Premium (Rm − Rf) | H42: ROE (K) | I42: ECAPM ROE (K)
B43: =B9 -> ALLETE, Inc. | C43: =C9 -> ALE | D43: ='AEB-8 Risk Premium'!J48 -> 0.041 | E43: =E9 -> 0.95 | F43: =F9 -> 0.12219338 | G43: =F43-D43 -> 0.081193378 | H43: =IFERROR(G43*E43+D43,"") -> 0.11813371 | I43: =IFERROR((0.25*G43)+(0.75*E43*G43)+D43,"") -> 0.11914863
B44: =B10 -> Alliant Energy Corporation | C44: =C10 -> LNT | D44: =$D$43 -> 0.041 | E44: =E10 -> 0.9 | F44: =F10 -> 0.12219338 | G44: =F44-D44 -> 0.081193378 | H44: =IFERROR(G44*E44+D44,"") -> 0.11407404 | I44: =IFERROR((0.25*G44)+(0.75*E44*G44)+D44,"") -> 0.11610387
B45: =B11 -> Ameren Corporation | C45: =C11 -> AEE | D45: =$D$43 -> 0.041 | E45: =E11 -> 0.9 | F45: =F11 -> 0.12219338 | G45: =F45-D45 -> 0.081193378 | H45: =IFERROR(G45*E45+D45,"") -> 0.11407404 | I45: =IFERROR((0.25*G45)+(0.75*E45*G45)+D45,"") -> 0.11610387
B46: =B12 -> Duke Energy Corporation | C46: =C12 -> DUK | D46: =$D$43 -> 0.041 | E46: =E12 -> 0.85 | F46: =F12 -> 0.12219338 | G46: =F46-D46 -> 0.081193378 | H46: =IFERROR(G46*E46+D46,"") -> 0.11001437 | I46: =IFERROR((0.25*G46)+(0.75*E46*G46)+D46,"") -> 0.11305912
B47: =B13 -> Edison International | C47: =C13 -> EIX | D47: =$D$43 -> 0.041 | E47: =E13 -> 1 | F47: =F13 -> 0.12219338 | G47: =F47-D47 -> 0.081193378 | H47: =IFERROR(G47*E47+D47,"") -> 0.12219338 | I47: =IFERROR((0.25*G47)+(0.75*E47*G47)+D47,"") -> 0.12219338
B48: =B14 -> Entergy Corporation | C48: =C14 -> ETR | D48: =$D$43 -> 0.041 | E48: =E14 -> 0.95 | F48: =F14 -> 0.12219338 | G48: =F48-D48 -> 0.081193378 | H48: =IFERROR(G48*E48+D48,"") -> 0.11813371 | I48: =IFERROR((0.25*G48)+(0.75*E48*G48)+D48,"") -> 0.11914863
B49: =B15 -> Eversource Energy | C49: =C15 -> ES | D49: =$D$43 -> 0.041 | E49: =E15 -> 0.9 | F49: =F15 -> 0.12219338 | G49: =F49-D49 -> 0.081193378 | H49: =IFERROR(G49*E49+D49,"") -> 0.11407404 | I49: =IFERROR((0.25*G49)+(0.75*E49*G49)+D49,"") -> 0.11610387
B50: =B16 -> Evergy, Inc. | C50: =C16 -> EVRG | D50: =$D$43 -> 0.041 | E50: =E16 -> 0.95 | F50: =F16 -> 0.12219338 | G50: =F50-D50 -> 0.081193378 | H50: =IFERROR(G50*E50+D50,"") -> 0.11813371 | I50: =IFERROR((0.25*G50)+(0.75*E50*G50)+D50,"") -> 0.11914863
B51: =B17 -> IDACORP, Inc. | C51: =C17 -> IDA | D51: =$D$43 -> 0.041 | E51: =E17 -> 0.85 | F51: =F17 -> 0.12219338 | G51: =F51-D51 -> 0.081193378 | H51: =IFERROR(G51*E51+D51,"") -> 0.11001437 | I51: =IFERROR((0.25*G51)+(0.75*E51*G51)+D51,"") -> 0.11305912
B52: =B18 -> NextEra Energy, Inc. | C52: =C18 -> NEE | D52: =$D$43 -> 0.041 | E52: =E18 -> 0.95 | F52: =F18 -> 0.12219338 | G52: =F52-D52 -> 0.081193378 | H52: =IFERROR(G52*E52+D52,"") -> 0.11813371 | I52: =IFERROR((0.25*G52)+(0.75*E52*G52)+D52,"") -> 0.11914863
B53: =B19 -> NorthWestern Corporation | C53: =C19 -> NWE | D53: =$D$43 -> 0.041 | E53: =E19 -> 0.95 | F53: =F19 -> 0.12219338 | G53: =F53-D53 -> 0.081193378 | H53: =IFERROR(G53*E53+D53,"") -> 0.11813371 | I53: =IFERROR((0.25*G53)+(0.75*E53*G53)+D53,"") -> 0.11914863
B54: =B20 -> OGE Energy Corporation | C54: =C20 -> OGE | D54: =$D$43 -> 0.041 | E54: =E20 -> 1.05 | F54: =F20 -> 0.12219338 | G54: =F54-D54 -> 0.081193378 | H54: =IFERROR(G54*E54+D54,"") -> 0.12625305 | I54: =IFERROR((0.25*G54)+(0.75*E54*G54)+D54,"") -> 0.12523813
B55: =B21 -> Pinnacle West Capital Corporation | C55: =C21 -> PNW | D55: =$D$43 -> 0.041 | E55: =E21 -> 0.95 | F55: =F21 -> 0.12219338 | G55: =F55-D55 -> 0.081193378 | H55: =IFERROR(G55*E55+D55,"") -> 0.11813371 | I55: =IFERROR((0.25*G55)+(0.75*E55*G55)+D55,"") -> 0.11914863
... B57: =B23 -> Xcel Energy Inc. | C57: =C23 -> XEL | D57: =$D$43 -> 0.041 | E57: =E23 -> 0.85 | F57: =F23 -> 0.12219338 | G57: =F57-D57 -> 0.081193378 | H57: =IFERROR(G57*E57+D57,"") -> 0.11001437 | I57: =IFERROR((0.25*G57)+(0.75*E57*G57)+D57,"") -> 0.11305912
B58: Mean | H58: =AVERAGE(H43:H57) -> 0.1162392 | I58: =AVERAGE(I43:I57) -> 0.11772774
B59: Median | H59: =MEDIAN(H43:H57) -> 0.11813371 | I59: =MEDIAN(I43:I57) -> 0.11914863
B61: Notes:
B62: [1] Blue Chip Financial Forecasts, Vol. 43, No. 2, February 1, 2024, at 2
B63: [2] Source: Value Line
B64: =$B$30 -> [3] Source: Market Return
B65: [4] Equals [3] - [1]
B66: [5] Equals [1] + [2] x [4]
B67: [6] Equals [1] + 0.25 x ([4]) + 0.75 x ([2] x [4])
B70: CAPITAL ASSET PRICING MODEL -- LONG-TERM PROJECTED RISK-FREE RATE & VL BETA
B72: K = Rf + β (Rm − Rf)
B73: K = Rf + 0.25 x (Rm - Rf) + 0.75 x β x (Rm − Rf)
D75: [1] | E75: [2] | F75: [3] | G75: [4] | H75: [5] | I75: [6]
B76: Company | C76: Ticker | D76: Projected 30-year U.S. Treasury bond yield (2025 - 2029) | E76: Beta (β) | F76: Market Return (Rm) | G76: Market Risk Premium (Rm − Rf) | H76: ROE (K) | I76: ECAPM ROE (K)
B77: =B9 -> ALLETE, Inc. | C77: =C9 -> ALE | D77: ='AEB-8 Risk Premium'!J49 -> 0.041 | E77: =E43 -> 0.95 | F77: =F9 -> 0.12219338 | G77: =F77-D77 -> 0.081193378 | H77: =IFERROR(G77*E77+D77,"") -> 0.11813371 | I77: =IFERROR((0.25*G77)+(0.75*E77*G77)+D77,"") -> 0.11914863
B78: =B10 -> Alliant Energy Corporation | C78: =C10 -> LNT | D78: =$D$77 -> 0.041 | E78: =E44 -> 0.9 | F78: =F10 -> 0.12219338 | G78: =F78-D78 -> 0.081193378 | H78: =IFERROR(G78*E78+D78,"") -> 0.11407404 | I78: =IFERROR((0.25*G78)+(0.75*E78*G78)+D78,"") -> 0.11610387
B79: =B11 -> Ameren Corporation | C79: =C11 -> AEE | D79: =$D$77 -> 0.041 | E79: =E45 -> 0.9 | F79: =F11 -> 0.12219338 | G79: =F79-D79 -> 0.081193378 | H79: =IFERROR(G79*E79+D79,"") -> 0.11407404 | I79: =IFERROR((0.25*G79)+(0.75*E79*G79)+D79,"") -> 0.11610387
B80: =B12 -> Duke Energy Corporation | C80: =C12 -> DUK | D80: =$D$77 -> 0.041 | E80: =E46 -> 0.85 | F80: =F12 -> 0.12219338 | G80: =F80-D80 -> 0.081193378 | H80: =IFERROR(G80*E80+D80,"") -> 0.11001437 | I80: =IFERROR((0.25*G80)+(0.75*E80*G80)+D80,"") -> 0.11305912
B81: =B13 -> Edison International | C81: =C13 -> EIX | D81: =$D$77 -> 0.041 | E81: =E47 -> 1 | F81: =F13 -> 0.12219338 | G81: =F81-D81 -> 0.081193378 | H81: =IFERROR(G81*E81+D81,"") -> 0.12219338 | I81: =IFERROR((0.25*G81)+(0.75*E81*G81)+D81,"") -> 0.12219338
B82: =B14 -> Entergy Corporation | C82: =C14 -> ETR | D82: =$D$77 -> 0.041 | E82: =E48 -> 0.95 | F82: =F14 -> 0.12219338 | G82: =F82-D82 -> 0.081193378 | H82: =IFERROR(G82*E82+D82,"") -> 0.11813371 | I82: =IFERROR((0.25*G82)+(0.75*E82*G82)+D82,"") -> 0.11914863
B83: =B15 -> Eversource Energy | C83: =C15 -> ES | D83: =$D$77 -> 0.041 | E83: =E49 -> 0.9 | F83: =F15 -> 0.12219338 | G83: =F83-D83 -> 0.081193378 | H83: =IFERROR(G83*E83+D83,"") -> 0.11407404 | I83: =IFERROR((0.25*G83)+(0.75*E83*G83)+D83,"") -> 0.11610387
B84: =B16 -> Evergy, Inc. | C84: =C16 -> EVRG | D84: =$D$77 -> 0.041 | E84: =E50 -> 0.95 | F84: =F16 -> 0.12219338 | G84: =F84-D84 -> 0.081193378 | H84: =IFERROR(G84*E84+D84,"") -> 0.11813371 | I84: =IFERROR((0.25*G84)+(0.75*E84*G84)+D84,"") -> 0.11914863
B85: =B17 -> IDACORP, Inc. | C85: =C17 -> IDA | D85: =$D$77 -> 0.041 | E85: =E51 -> 0.85 | F85: =F17 -> 0.12219338 | G85: =F85-D85 -> 0.081193378 | H85: =IFERROR(G85*E85+D85,"") -> 0.11001437 | I85: =IFERROR((0.25*G85)+(0.75*E85*G85)+D85,"") -> 0.11305912
B86: =B18 -> NextEra Energy, Inc. | C86: =C18 -> NEE | D86: =$D$77 -> 0.041 | E86: =E52 -> 0.95 | F86: =F18 -> 0.12219338 | G86: =F86-D86 -> 0.081193378 | H86: =IFERROR(G86*E86+D86,"") -> 0.11813371 | I86: =IFERROR((0.25*G86)+(0.75*E86*G86)+D86,"") -> 0.11914863
B87: =B19 -> NorthWestern Corporation | C87: =C19 -> NWE | D87: =$D$77 -> 0.041 | E87: =E53 -> 0.95 | F87: =F19 -> 0.12219338 | G87: =F87-D87 -> 0.081193378 | H87: =IFERROR(G87*E87+D87,"") -> 0.11813371 | I87: =IFERROR((0.25*G87)+(0.75*E87*G87)+D87,"") -> 0.11914863
B88: =B20 -> OGE Energy Corporation | C88: =C20 -> OGE | D88: =$D$77 -> 0.041 | E88: =E54 -> 1.05 | F88: =F20 -> 0.12219338 | G88: =F88-D88 -> 0.081193378 | H88: =IFERROR(G88*E88+D88,"") -> 0.12625305 | I88: =IFERROR((0.25*G88)+(0.75*E88*G88)+D88,"") -> 0.12523813
B89: =B21 -> Pinnacle West Capital Corporation | C89: =C21 -> PNW | D89: =$D$77 -> 0.041 | E89: =E55 -> 0.95 | F89: =F21 -> 0.12219338 | G89: =F89-D89 -> 0.081193378 | H89: =IFERROR(G89*E89+D89,"") -> 0.11813371 | I89: =IFERROR((0.25*G89)+(0.75*E89*G89)+D89,"") -> 0.11914863
... B91: =B23 -> Xcel Energy Inc. | C91: =C23 -> XEL | D91: =$D$77 -> 0.041 | E91: =E57 -> 0.85 | F91: =F23 -> 0.12219338 | G91: =F91-D91 -> 0.081193378 | H91: =IFERROR(G91*E91+D91,"") -> 0.11001437 | I91: =IFERROR((0.25*G91)+(0.75*E91*G91)+D91,"") -> 0.11305912
B92: Mean | H92: =AVERAGE(H77:H91) -> 0.1162392 | I92: =AVERAGE(I77:I91) -> 0.11772774
B93: Median | H93: =MEDIAN(H77:H91) -> 0.11813371 | I93: =MEDIAN(I77:I91) -> 0.11914863
B95: Notes:
B96: [1] Source: Blue Chip Financial Forecasts, Vol. 42, No. 12, December 1, 2023, at 14
B97: [2] Source: Value Line
B98: =$B$30 -> [3] Source: Market Return
B99: [4] Equals [3] - [1]
B100: [5] Equals [1] + [2] x [4]
B101: [6] Equals [1] + 0.25 x ([4]) + 0.75 x ([2] x [4])
B104: CAPITAL ASSET PRICING MODEL -- CURRENT RISK-FREE RATE & BLOOMBERG BETA
B106: K = Rf + β (Rm − Rf)
B107: K = Rf + 0.25 x (Rm - Rf) + 0.75 x β x (Rm − Rf)
D109: [1] | E109: [2] | F109: [3] | G109: [4] | H109: [5] | I109: [6]
B110: Company | C110: Ticker | D110: =D8 -> Current 30-day average of 30-year U.S. Treasury bond yield | E110: Beta (β) | F110: Market Return (Rm) | G110: Market Risk Premium (Rm − Rf) | H110: ROE (K) | I110: ECAPM ROE (K)
B111: =B77 -> ALLETE, Inc. | C111: =C77 -> ALE | D111: =D9 -> 0.041926667 | E111: 0.81983002 | F111: =F9 -> 0.12219338 | G111: =F111-D111 -> 0.080266712 | H111: =IFERROR(G111*E111+D111,"") -> 0.10773173 | I111: =IFERROR((0.25*G111)+(0.75*E111*G111)+D111,"") -> 0.11134714
B112: =B78 -> Alliant Energy Corporation | C112: =C78 -> LNT | D112: =D10 -> 0.041926667 | E112: 0.78373385 | F112: =F10 -> 0.12219338 | G112: =F112-D112 -> 0.080266712 | H112: =IFERROR(G112*E112+D112,"") -> 0.10483441 | I112: =IFERROR((0.25*G112)+(0.75*E112*G112)+D112,"") -> 0.10917415
B113: =B79 -> Ameren Corporation | C113: =C79 -> AEE | D113: =D11 -> 0.041926667 | E113: 0.74071412 | F113: =F11 -> 0.12219338 | G113: =F113-D113 -> 0.080266712 | H113: =IFERROR(G113*E113+D113,"") -> 0.10138135 | I113: =IFERROR((0.25*G113)+(0.75*E113*G113)+D113,"") -> 0.10658436
B114: =B80 -> Duke Energy Corporation | C114: =C80 -> DUK | D114: =D12 -> 0.041926667 | E114: 0.7147629 | F114: =F12 -> 0.12219338 | G114: =F114-D114 -> 0.080266712 | H114: =IFERROR(G114*E114+D114,"") -> 0.099298334 | I114: =IFERROR((0.25*G114)+(0.75*E114*G114)+D114,"") -> 0.1050221
B115: =B81 -> Edison International | C115: =C81 -> EIX | D115: =D13 -> 0.041926667 | E115: 0.84737519 | F115: =F13 -> 0.12219338 | G115: =F115-D115 -> 0.080266712 | H115: =IFERROR(G115*E115+D115,"") -> 0.10994269 | I115: =IFERROR((0.25*G115)+(0.75*E115*G115)+D115,"") -> 0.11300536
B116: =B82 -> Entergy Corporation | C116: =C82 -> ETR | D116: =D14 -> 0.041926667 | E116: 0.85395941 | F116: =F14 -> 0.12219338 | G116: =F116-D116 -> 0.080266712 | H116: =IFERROR(G116*E116+D116,"") -> 0.11047118 | I116: =IFERROR((0.25*G116)+(0.75*E116*G116)+D116,"") -> 0.11340173
B117: =B83 -> Eversource Energy | C117: =C83 -> ES | D117: =D15 -> 0.041926667 | E117: 0.80328158 | F117: =F15 -> 0.12219338 | G117: =F117-D117 -> 0.080266712 | H117: =IFERROR(G117*E117+D117,"") -> 0.10640344 | I117: =IFERROR((0.25*G117)+(0.75*E117*G117)+D117,"") -> 0.11035092
B118: =B84 -> Evergy, Inc. | C118: =C84 -> EVRG | D118: =D16 -> 0.041926667 | E118: 0.7757774 | F118: =F16 -> 0.12219338 | G118: =F118-D118 -> 0.080266712 | H118: =IFERROR(G118*E118+D118,"") -> 0.10419577 | I118: =IFERROR((0.25*G118)+(0.75*E118*G118)+D118,"") -> 0.10869517
B119: =B85 -> IDACORP, Inc. | C119: =C85 -> IDA | D119: =D17 -> 0.041926667 | E119: 0.79180001 | F119: =F17 -> 0.12219338 | G119: =F119-D119 -> 0.080266712 | H119: =IFERROR(G119*E119+D119,"") -> 0.10548185 | I119: =IFERROR((0.25*G119)+(0.75*E119*G119)+D119,"") -> 0.10965973
B120: =B86 -> NextEra Energy, Inc. | C120: =C86 -> NEE | D120: =D18 -> 0.041926667 | E120: 0.81059787 | F120: =F18 -> 0.12219338 | G120: =F120-D120 -> 0.080266712 | H120: =IFERROR(G120*E120+D120,"") -> 0.10699069 | I120: =IFERROR((0.25*G120)+(0.75*E120*G120)+D120,"") -> 0.11079136
B121: =B87 -> NorthWestern Corporation | C121: =C87 -> NWE | D121: =D19 -> 0.041926667 | E121: 0.86379981 | F121: =F19 -> 0.12219338 | G121: =F121-D121 -> 0.080266712 | H121: =IFERROR(G121*E121+D121,"") -> 0.11126104 | I121: =IFERROR((0.25*G121)+(0.75*E121*G121)+D121,"") -> 0.11399412
...

Sheet AEB-6 LT Beta
A2: HISTORICAL BETA - 2013 - 2022
C4: [1] | D4: [2] | E4: [3] | F4: [4] | G4: [5] | H4: [6] | I4: [7] | J4: [8] | K4: [9] | L4: [10] | M4: [11] | N4: [12]
A5: Company | B5: Ticker | C5: 41639 | D5: 42004 | E5: 42369 | F5: 42735 | G5: 43100 | H5: 43465 | I5: 43830 | J5: 44196 | K5: 44561 | L5: 44926 | M5: 45291 | N5: Average
A6: ='AEB-4 CGDCF'!A6 -> ALLETE, Inc. | B6: ='AEB-4 CGDCF'!B6 -> ALE | C6: 0.75 | D6: 0.8 | E6: 0.8 | F6: 0.75 | G6: 0.8 | H6: 0.65 | I6: 0.65 | J6: 0.85 | K6: 0.9 | L6: 0.9 | M6: 0.9 | N6: =AVERAGE(C6:M6) -> 0.79545455
A7: ='AEB-4 CGDCF'!A7 -> Alliant Energy Corporation | B7: ='AEB-4 CGDCF'!B7 -> LNT | C7: 0.75 | D7: 0.8 | E7: 0.8 | F7: 0.7 | G7: 0.7 | H7: 0.6 | I7: 0.6 | J7: 0.85 | K7: 0.85 | L7: 0.85 | M7: 0.9 | N7: =AVERAGE(C7:M7) -> 0.76363636
A8: ='AEB-4 CGDCF'!A8 -> Ameren Corporation | B8: ='AEB-4 CGDCF'!B8 -> AEE | C8: 0.8 | D8: 0.75 | E8: 0.75 | F8: 0.65 | G8: 0.7 | H8: 0.55 | I8: 0.55 | J8: 0.85 | K8: 0.8 | L8: 0.85 | M8: 0.9 | N8: =AVERAGE(C8:M8) -> 0.74090909
A9: ='AEB-4 CGDCF'!A9 -> Duke Energy Corporation | B9: ='AEB-4 CGDCF'!B9 -> DUK | C9: 0.65 | D9: 0.6 | E9: 0.65 | F9: 0.6 | G9: 0.6 | H9: 0.5 | I9: 0.5 | J9: 0.85 | K9: 0.85 | L9: 0.85 | M9: 0.9 | N9: =AVERAGE(C9:M9) -> 0.68636364
A10: ='AEB-4 CGDCF'!A10 -> Edison International | B10: ='AEB-4 CGDCF'!B10 -> EIX | C10: 0.8 | D10: 0.75 | E10: 0.7 | F10: 0.65 | G10: 0.65 | H10: 0.55 | I10: 0.55 | J10: 0.95 | K10: 0.95 | L10: 0.95 | M10: 1 | N10: =AVERAGE(C10:M10) -> 0.77272727
A11: ='AEB-4 CGDCF'!A11 -> Entergy Corporation | B11: ='AEB-4 CGDCF'!B11 -> ETR | C11: 0.7 | D11: 0.7 | E11: 0.7 | F11: 0.65 | G11: 0.65 | H11: 0.6 | I11: 0.6 | J11: 0.95 | K11: 0.95 | L11: 0.95 | M11: 0.95 | N11: =AVERAGE(C11:M11) -> 0.76363636
A12: ='AEB-4 CGDCF'!A12 -> Eversource Energy | B12: ='AEB-4 CGDCF'!B12 -> ES | E12: 0.75 | F12: 0.7 | G12: 0.65 | H12: 0.6 | I12: 0.55 | J12: 0.9 | K12: 0.9 | L12: 0.9 | M12: 0.9 | N12: =AVERAGE(C12:M12) -> 0.76111111
A13: ='AEB-4 CGDCF'!A13 -> Evergy, Inc. | B13: ='AEB-4 CGDCF'!B13 -> EVRG | H13: NMF | I13: NMF | J13: 1 | K13: 0.95 | L13: 0.9 | M13: 0.9 | N13: =AVERAGE(C13:M13) -> 0.9375
A14: ='AEB-4 CGDCF'!A14 -> IDACORP, Inc. | B14: ='AEB-4 CGDCF'!B14 -> IDA | C14: 0.75 | D14: 0.8 | E14: 0.8 | F14: 0.75 | G14: 0.7 | H14: 0.55 | I14: 0.55 | J14: 0.8 | K14: 0.8 | L14: 0.8 | M14: 0.85 | N14: =AVERAGE(C14:M14) -> 0.74090909
A15: ='AEB-4 CGDCF'!A15 -> NextEra Energy, Inc. | B15: ='AEB-4 CGDCF'!B15 -> NEE | C15: 0.7 | D15: 0.7 | E15: 0.75 | F15: 0.65 | G15: 0.65 | H15: 0.55 | I15: 0.55 | J15: 0.9 | K15: 0.9 | L15: 0.95 | M15: 1 | N15: =AVERAGE(C15:M15) -> 0.75454545
A16: ='AEB-4 CGDCF'!A16 -> NorthWestern Corporation | B16: ='AEB-4 CGDCF'!B16 -> NWE | C16: 0.7 | D16: 0.7 | E16: 0.7 | F16: 0.7 | G16: 0.7 | H16: 0.55 | I16: 0.6 | J16: 0.95 | K16: 0.95 | L16: 0.9 | M16: 0.95 | N16: =AVERAGE(C16:M16) -> 0.76363636
A17: ='AEB-4 CGDCF'!A17 -> OGE Energy Corporation | B17: ='AEB-4 CGDCF'!B17 -> OGE | C17: 0.85 | D17: 0.9 | E17: 0.95 | F17: 0.9 | G17: 0.95 | H17: 0.85 | I17: 0.75 | J17: 1.1 | K17: 1.05 | L17: 1 | M17: 1.05 | N17: =AVERAGE(C17:M17) -> 0.94090909
A18: ='AEB-4 CGDCF'!A18 -> Pinnacle West Capital Corporation | B18: ='AEB-4 CGDCF'!B18 -> PNW | C18: 0.75 | D18: 0.7 | E18: 0.75 | F18: 0.7 | G18: 0.7 | H18: 0.55 | I18: 0.5 | J18: 0.9 | K18: 0.9 | L18: 0.9 | M18: 0.95 | N18: =AVERAGE(C18:M18) -> 0.75454545
A19: ='AEB-4 CGDCF'!A19 -> Portland General Electric Company | B19: ='AEB-4 CGDCF'!B19 -> POR | C19: 0.75 | D19: 0.8 | E19: 0.8 | F19: 0.7 | G19: 0.7 | H19: 0.6 | I19: 0.55 | J19: 0.85 | K19: 0.9 | L19: 0.85 | M19: 0.9 | N19: =AVERAGE(C19:M19) -> 0.76363636
A20: ='AEB-4 CGDCF'!A20 -> Xcel Energy Inc. | B20: ='AEB-4 CGDCF'!B20 -> XEL | C20: 0.65 | D20: 0.65 | E20: 0.65 | F20: 0.6 | G20: 0.6 | H20: 0.5 | I20: 0.5 | J20: 0.8 | K20: 0.8 | L20: 0.8 | M20: 0.85 | N20: =AVERAGE(C20:M20) -> 0.67272727
A21: Mean | C21: =AVERAGE(C6:C20) -> 0.73846154 | D21: =AVERAGE(D6:D20) -> 0.74230769 | E21: =AVERAGE(E6:E20) -> 0.75357143 | F21: =AVERAGE(F6:F20) -> 0.69285714 | G21: =AVERAGE(G6:G20) -> 0.69642857 | H21: =AVERAGE(H6:H20) -> 0.58571429 | I21: =AVERAGE(I6:I20) -> 0.57142857 | J21: =AVERAGE(J6:J20) -> 0.9 | ... N21: =AVERAGE(N6:N20) -> 0.77414983
A23: Notes:
A24: [1] Value Line, dated December 26, 2013.
A25: [2] Value Line, dated December 31, 2014.
A26: [3] Value Line, dated December 30, 2015.
A27: [4] Value Line, dated December 29, 2016.
A28: [5] Value Line, dated December 28, 2017.
A29: [6] Value Line, dated December 27, 2018.
A30: [7] Value Line, dated December 26, 2019.
A31: [8] Value Line, dated December 30, 2020.
A32: [9] Value Line, dated December 29, 2021.
A33: [10] Value Line, dated December 30, 2022.
A34: [11] Value Line, dated December 29, 2023.
A35: [12] Average ([1] - [11])

Sheet AEB-7 Market Return
A1: MARKET RISK PREMIUM DERIVED FROM ANALYSTS' LONG-TERM GROWTH ESTIMATES
A4: [1] Estimated Weighted Average Dividend Yield | B4: =SUM(H19:H521) -> 0.016275252
A6: [2] Estimated Weighted Average Long-Term Growth Rate | B6: =SUM(J19:J521) -> 0.10506316
A8: [3] S&P 500 Estimated Required Market Return | B8: =B4*(1+0.5*B6)+B6 -> 0.12219338
A12: STANDARD AND POOR'S 500 INDEX
C14: [4] | D14: [5] | E14: [6] | F14: [7] | G14: [8] | H14: [9] | I14: [10] | J14: [11]
I15: Bloomberg | J15: Cap-Weighted
C16: Shares | E16: Market | F16: Weight in | G16: Estimated | H16: Cap-Weighted | I16: Long-Term | J16: Long-Term
A17: Name | B17: Ticker | C17: Outst'g | D17: Price | E17: Capitalization | F17: Index | G17: Dividend Yield | H17: Dividend Yield | I17: Growth Est. | J17: Growth Est.
A19: LyondellBasell Industries NV | B19: LYB | C19: 324.362 | D19: 94.12 | E19: =IFERROR(C19*D19,"") -> 30528.951 | F19: =IF(AND(ISNUMBER($I19)), IF(AND($I19<=20%,$I19>0%), $E19/SUMIFS($E$19:$E$521,$I$19:$I$521, ">"&0%,$I$19:$I$521, "<="&20%),""),"") -> 0.00096447138 | G19: 0.053123672 | H19: =IFERROR($G19*$F19,"") -> 5.1236261e-05 | I19: 0.08 | J19: =IFERROR($I19*$F19,"") -> 7.715771e-05
A20: American Express Co | B20: AXP | C20: 723 | D20: 200.74 | E20: =IFERROR(C20*D20,"") -> 145135.02 | F20: =IF(AND(ISNUMBER($I20)), IF(AND($I20<=20%,$I20>0%), $E20/SUMIFS($E$19:$E$521,$I$19:$I$521, ">"&0%,$I$19:$I$521, "<="&20%),""),"") -> 0.0045851091 | G20: 0.011955764 | H20: =IFERROR($G20*$F20,"") -> 5.4818481e-05 | I20: 0.1417 | J20: =IFERROR($I20*$F20,"") -> 0.00064970996
A21: Verizon Communications Inc | B21: VZ | C21: 4204 | D21: 42.35 | E21: =IFERROR(C21*D21,"") -> 178039.4 | F21: =IF(AND(ISNUMBER($I21)), IF(AND($I21<=20%,$I21>0%), $E21/SUMIFS($E$19:$E$521,$I$19:$I$521, ">"&0%,$I$19:$I$521, "<="&20%),""),"") | G21: 0.062809917 | H21: =IFERROR($G21*$F21,"") | I21: -0.041 | J21: =IFERROR($I21*$F21,"")
A22: Broadcom Inc | B22: AVGO | C22: 468.141 | D22: 1180 | E22: =IFERROR(C22*D22,"") -> 552406.38 | F22: =IF(AND(ISNUMBER($I22)), IF(AND($I22<=20%,$I22>0%), $E22/SUMIFS($E$19:$E$521,$I$19:$I$521, ">"&0%,$I$19:$I$521, "<="&20%),""),"") -> 0.017451636 | G22: 0.01779661 | H22: =IFERROR($G22*$F22,"") -> 0.00031057996 | I22: 0.139 | J22: =IFERROR($I22*$F22,"") -> 0.0024257774
A23: Boeing Co/The | B23: BA | C23: 610.135 | D23: 211.04 | E23: =IFERROR(C23*D23,"") -> 128762.89 | F23: =IF(AND(ISNUMBER($I23)), IF(AND($I23<=20%,$I23>0%), $E23/SUMIFS($E$19:$E$521,$I$19:$I$521, ">"&0%,$I$19:$I$521, "<="&20%),""),"") | H23: =IFERROR($G23*$F23,"") | J23: =IFERROR($I23*$F23,"")
A24: Caterpillar Inc | B24: CAT | C24: 509.085 | D24: 300.31 | E24: =IFERROR(C24*D24,"") -> 152883.32 | F24: =IF(AND(ISNUMBER($I24)), IF(AND($I24<=20%,$I24>0%), $E24/SUMIFS($E$19:$E$521,$I$19:$I$521, ">"&0%,$I$19:$I$521, "<="&20%),""),"") -> 0.0048298935 | G24: 0.017315441 | H24: =IFERROR($G24*$F24,"") -> 8.3631734e-05 | I24: 0.2 | J24: =IFERROR($I24*$F24,"") -> 0.00096597869
A25: JPMorgan Chase & Co | B25: JPM | C25: 2891.008 | D25: 174.36 | E25: =IFERROR(C25*D25,"") -> 504076.15 | F25: =IF(AND(ISNUMBER($I25)), IF(AND($I25<=20%,$I25>0%), $E25/SUMIFS($E$19:$E$521,$I$19:$I$521, ">"&0%,$I$19:$I$521, "<="&20%),""),"") -> 0.015924786 | G25: 0.024088094 | H25: =IFERROR($G25*$F25,"") -> 0.00038359774 | I25: 0.02 | J25: =IFERROR($I25*$F25,"") -> 0.00031849572
A26: Chevron Corp | B26: CVX | C26: 1887.749 | D26: 147.43 | E26: =IFERROR(C26*D26,"") -> 278310.84 | F26: =IF(AND(ISNUMBER($I26)), IF(AND($I26<=20%,$I26>0%), $E26/SUMIFS($E$19:$E$521,$I$19:$I$521, ">"&0%,$I$19:$I$521, "<="&20%),""),"") -> 0.0087924027 | G26: 0.040968595 | H26: =IFERROR($G26*$F26,"") -> 0.00036021239 | I26: 0.07265 | J26: =IFERROR($I26*$F26,"") -> 0.00063876806
A27: Coca-Cola Co/The | B27: KO | C27: 4323.414 | D27: 59.49 | E27: =IFERROR(C27*D27,"") -> 257199.9 | F27: =IF(AND(ISNUMBER($I27)), IF(AND($I27<=20%,$I27>0%), $E27/SUMIFS($E$19:$E$521,$I$19:$I$521, ">"&0%,$I$19:$I$521, "<="&20%),""),"") -> 0.0081254655 | G27: 0.030929568 | H27: =IFERROR($G27*$F27,"") -> 0.00025131714 | I27: 0.0658 | J27: =IFERROR($I27*$F27,"") -> 0.00053465563
A28: AbbVie Inc | B28: ABBV | C28: 1765.537 | D28: 164.4 | E28: =IFERROR(C28*D28,"") -> 290254.28 | F28: =IF(AND(ISNUMBER($I28)), IF(AND($I28<=20%,$I28>0%), $E28/SUMIFS($E$19:$E$521,$I$19:$I$521, ">"&0%,$I$19:$I$521, "<="&20%),""),"") -> 0.0091697204 | G28: 0.037712895 | H28: =IFERROR($G28*$F28,"") -> 0.00034581671 | I28: 0.09088 | J28: =IFERROR($I28*$F28,"") -> 0.00083334419
A29: Walt Disney Co/The | B29: DIS | C29: 1830.316 | D29: 96.05 | E29: =IFERROR(C29*D29,"") -> 175801.85 | F29: =IF(AND(ISNUMBER($I29)), IF(AND($I29<=20%,$I29>0%), $E29/SUMIFS($E$19:$E$521,$I$19:$I$521, ">"&0%,$I$19:$I$521, "<="&20%),""),"") -> 0.0055539364 | G29: 0.0062467465 | H29: =IFERROR($G29*$F29,"") -> 3.4694033e-05 | I29: 0.18875 | J29: =IFERROR($I29*$F29,"") -> 0.0010483055
A30: FleetCor Technologies Inc | B30: FLT | C30: 72.204 | D30: 289.93 | E30: =IFERROR(C30*D30,"") -> 20934.106 | F30: =IF(AND(ISNUMBER($I30)), IF(AND($I30<=20%,$I30>0%), $E30/SUMIFS($E$19:$E$521,$I$19:$I$521, ">"&0%,$I$19:$I$521, "<="&20%),""),"") -> 0.00066135078 | H30: =IFERROR($G30*$F30,"") | I30: 0.1279 | J30: =IFERROR($I30*$F30,"") -> 8.4586765e-05
A31: Extra Space Storage Inc | B31: EXR | C31: 211.278 | D31: 144.44 | E31: =IFERROR(C31*D31,"") -> 30516.994 | F31: =IF(AND(ISNUMBER($I31)), IF(AND($I31<=20%,$I31>0%), $E31/SUMIFS($E$19:$E$521,$I$19:$I$521, ">"&0%,$I$19:$I$521, "<="&20%),""),"") -> 0.00096409363 | G31: 0.044862919 | H31: =IFERROR($G31*$F31,"") -> 4.3252054e-05 | I31: 0.012 | J31: =IFERROR($I31*$F31,"") -> 1.1569124e-05
A32: Exxon Mobil Corp | B32: XOM | C32: 4006.133 | D32: 102.81 | E32: =IFERROR(C32*D32,"") -> 411870.53 | F32: =IF(AND(ISNUMBER($I32)), IF(AND($I32<=20%,$I32>0%), $E32/SUMIFS($E$19:$E$521,$I$19:$I$521, ">"&0%,$I$19:$I$521, "<="&20%),""),"") -> 0.013011824 | G32: 0.036961385 | H32: =IFERROR($G32*$F32,"") -> 0.00048093504 | I32: 0.1321 | J32: =IFERROR($I32*$F32,"") -> 0.0017188619
A33: Phillips 66 | B33: PSX | C33: 439.956 | D33: 144.31 | E33: =IFERROR(C33*D33,"") -> 63490.05 | F33: =IF(AND(ISNUMBER($I33)), IF(AND($I33<=20%,$I33>0%), $E33/SUMIFS($E$19:$E$521,$I$19:$I$521, ">"&0%,$I$19:$I$521, "<="&20%),""),"") | G33: 0.029104012 | H33: =IFERROR($G33*$F33,"") | I33: -0.0756 | J33: =IFERROR($I33*$F33,"")
A34: General Electric Co | B34: GE | C34: 1088.386 | D34: 132.42 | E34: =IFERROR(C34*D34,"") -> 144124.07 | F34: =IF(AND(ISNUMBER($I34)), IF(AND($I34<=20%,$I34>0%), $E34/SUMIFS($E$19:$E$521,$I$19:$I$521, ">"&0%,$I$19:$I$521, "<="&20%),""),"") -> 0.0045531713 | G34: 0.0024165534 | H34: =IFERROR($G34*$F34,"") -> 1.1002981e-05 | I34: 0.07 | J34: =IFERROR($I34*$F34,"") -> 0.00031872199
A35: HP Inc | B35: HPQ | C35: 990.902 | D35: 28.71 | E35: =IFERROR(C35*D35,"") -> 28448.796 | F35: =IF(AND(ISNUMBER($I35)), IF(AND($I35<=20%,$I35>0%), $E35/SUMIFS($E$19:$E$521,$I$19:$I$521, ">"&0%,$I$19:$I$521, "<="&20%),""),"") -> 0.00089875507 | G35: 0.038397771 | H35: =IFERROR($G35*$F35,"") -> 3.4510191e-05 | I35: 0.03 | J35: =IFERROR($I35*$F35,"") -> 2.6962652e-05
A36: Home Depot Inc/The | B36: HD | C36: 995.262 | D36: 352.96 | E36: =IFERROR(C36*D36,"") -> 351287.68 | F36: =IF(AND(ISNUMBER($I36)), IF(AND($I36<=20%,$I36>0%), $E36/SUMIFS($E$19:$E$521,$I$19:$I$521, ">"&0%,$I$19:$I$521, "<="&20%),""),"") -> 0.011097889 | G36: 0.023685403 | H36: =IFERROR($G36*$F36,"") -> 0.00026285797 | I36: 0.0182 | J36: =IFERROR($I36*$F36,"") -> 0.00020198158
A37: Monolithic Power Systems Inc | B37: MPWR | C37: 47.912 | D37: 602.72 | E37: =IFERROR(C37*D37,"") -> 28877.521 | F37: =IF(AND(ISNUMBER($I37)), IF(AND($I37<=20%,$I37>0%), $E37/SUMIFS($E$19:$E$521,$I$19:$I$521, ">"&0%,$I$19:$I$521, "<="&20%),""),"") -> 0.00091229934 | G37: 0.0066365808 | H37: =IFERROR($G37*$F37,"") -> 6.0545483e-06 | I37: 0.08 | J37: =IFERROR($I37*$F37,"") -> 7.2983947e-05
A38: International Business Machines Corp | B38: IBM | C38: 913.119 | D38: 183.66 | E38: =IFERROR(C38*D38,"") -> 167703.44 | F38: =IF(AND(ISNUMBER($I38)), IF(AND($I38<=20%,$I38>0%), $E38/SUMIFS($E$19:$E$521,$I$19:$I$521, ">"&0%,$I$19:$I$521, "<="&20%),""),"") -> 0.005298091 | G38: 0.036153762 | H38: =IFERROR($G38*$F38,"") -> 0.00019154592 | I38: 0.0514 | J38: =IFERROR($I38*$F38,"") -> 0.00027232188
A39: Johnson & Johnson | B39: JNJ | C39: 2407.279 | D39: 158.9 | E39: =IFERROR(C39*D39,"") -> 382516.63 | F39: =IF(AND(ISNUMBER($I39)), IF(AND($I39<=20%,$I39>0%), $E39/SUMIFS($E$19:$E$521,$I$19:$I$521, ">"&0%,$I$19:$I$521, "<="&20%),""),"") -> 0.012084475 | G39: 0.029955947 | H39: =IFERROR($G39*$F39,"") -> 0.00036200189 | I39: 0.0376 | J39: =IFERROR($I39*$F39,"") -> 0.00045437625
A40: Lululemon Athletica Inc | B40: LULU | C40: 121.075 | D40: 453.82 | E40: =IFERROR(C40*D40,"") -> 54946.257 | F40: =IF(AND(ISNUMBER($I40)), IF(AND($I40<=20%,$I40>0%), $E40/SUMIFS($E$19:$E$521,$I$19:$I$521, ">"&0%,$I$19:$I$521, "<="&20%),""),"") -> 0.0017358635 | H40: =IFERROR($G40*$F40,"") | I40: 0.17 | J40: =IFERROR($I40*$F40,"") -> 0.00029509679
A41: McDonald's Corp | B41: MCD | C41: 725.342 | D41: 292.72 | E41: =IFERROR(C41*D41,"") -> 212322.11 | F41: =IF(AND(ISNUMBER($I41)), IF(AND($I41<=20%,$I41>0%), $E41/SUMIFS($E$19:$E$521,$I$19:$I$521, ">"&0%,$I$19:$I$521, "<="&20%),""),"") -> 0.0067076853 | G41: 0.022820443 | H41: =IFERROR($G41*$F41,"") -> 0.00015307235 | I41: 0.0953 | J41: =IFERROR($I41*$F41,"") -> 0.00063924241
A42: Merck & Co Inc | B42: MRK | C42: 2534.023 | D42: 120.78 | E42: =IFERROR(C42*D42,"") -> 306059.3 | F42: =IF(AND(ISNUMBER($I42)), IF(AND($I42<=20%,$I42>0%), $E42/SUMIFS($E$19:$E$521,$I$19:$I$521, ">"&0%,$I$19:$I$521, "<="&20%),""),"") -> 0.0096690328 | G42: 0.025500911 | H42: =IFERROR($G42*$F42,"") -> 0.00024656914 | I42: 0.1733 | J42: =IFERROR($I42*$F42,"") -> 0.0016756434
A43: 3M Co | B43: MMM | C43: 552.317 | D43: 94.35 | E43: =IFERROR(C43*D43,"") -> 52111.109 | F43: =IF(AND(ISNUMBER($I43)), IF(AND($I43<=20%,$I43>0%), $E43/SUMIFS($E$19:$E$521,$I$19:$I$521, ">"&0%,$I$19:$I$521, "<="&20%),""),"") -> 0.0016462954 | G43: 0.063593005 | H43: =IFERROR($G43*$F43,"") -> 0.00010469287 | I43: 0.055 | J43: =IFERROR($I43*$F43,"") -> 9.0546248e-05
A44: American Water Works Co Inc | B44: AWK | C44: 194.705 | D44: 124.02 | E44: =IFERROR(C44*D44,"") -> 24147.314 | F44: =IF(AND(ISNUMBER($I44)), IF(AND($I44<=20%,$I44>0%), $E44/SUMIFS($E$19:$E$521,$I$19:$I$521, ">"&0%,$I$19:$I$521, "<="&20%),""),"") -> 0.00076286254 | G44: 0.0228189 | H44: =IFERROR($G44*$F44,"") -> 1.7407684e-05 | I44: 0.07755 | J44: =IFERROR($I44*$F44,"") -> 5.915999e-05
A45: Bank of America Corp | B45: BAC | C45: 7895.5 | D45: 34.01 | E45: =IFERROR(C45*D45,"") -> 268525.95 | F45: =IF(AND(ISNUMBER($I45)), IF(AND($I45<=20%,$I45>0%), $E45/SUMIFS($E$19:$E$521,$I$19:$I$521, ">"&0%,$I$19:$I$521, "<="&20%),""),"") | G45: 0.028226992 | H45: =IFERROR($G45*$F45,"") | I45: -0.07 | J45: =IFERROR($I45*$F45,"")
A46: Pfizer Inc | B46: PFE | C46: 5646.413 | D46: 27.08 | E46: =IFERROR(C46*D46,"") -> 152904.86 | F46: =IF(AND(ISNUMBER($I46)), IF(AND($I46<=20%,$I46>0%), $E46/SUMIFS($E$19:$E$521,$I$19:$I$521, ">"&0%,$I$19:$I$521, "<="&20%),""),"") | G46: 0.062038405 | H46: =IFERROR($G46*$F46,"") | I46: 0.33346 | J46: =IFERROR($I46*$F46,"")
A47: Procter & Gamble Co/The | B47: PG | C47: 2353.021 | D47: 157.14 | E47: =IFERROR(C47*D47,"") -> 369753.72 | F47: =IF(AND(ISNUMBER($I47)), IF(AND($I47<=20%,$I47>0%), $E47/SUMIFS($E$19:$E$521,$I$19:$I$521, ">"&0%,$I$19:$I$521, "<="&20%),""),"") -> 0.011681269 | G47: 0.023945526 | H47: =IFERROR($G47*$F47,"") -> 0.00027971412 | I47: 0.0756 | J47: =IFERROR($I47*$F47,"") -> 0.0008831039
A48: AT&T Inc | B48: T | C48: 7150 | D48: 17.69 | E48: =IFERROR(C48*D48,"") -> 126483.5 | F48: =IF(AND(ISNUMBER($I48)), IF(AND($I48<=20%,$I48>0%), $E48/SUMIFS($E$19:$E$521,$I$19:$I$521, ">"&0%,$I$19:$I$521, "<="&20%),""),"") | G48: 0.062747315 | H48: =IFERROR($G48*$F48,"") | I48: -0.04613 | J48: =IFERROR($I48*$F48,"")
A49: Travelers Cos Inc/The | B49: TRV | C49: 228.2 | D49: 211.36 | E49: =IFERROR(C49*D49,"") -> 48232.352 | F49: =IF(AND(ISNUMBER($I49)), IF(AND($I49<=20%,$I49>0%), $E49/SUMIFS($E$19:$E$521,$I$19:$I$521, ">"&0%,$I$19:$I$521, "<="&20%),""),"") -> 0.0015237576 | G49: 0.018925057 | H49: =IFERROR($G49*$F49,"") -> 2.88372e-05 | I49: 0.19025 | J49: =IFERROR($I49*$F49,"") -> 0.00028989489
A50: RTX Corp | B50: RTX | C50: 1437.901 | D50: 91.12 | E50: =IFERROR(C50*D50,"") -> 131021.54 | F50: =IF(AND(ISNUMBER($I50)), IF(AND($I50<=20%,$I50>0%), $E50/SUMIFS($E$19:$E$521,$I$19:$I$521, ">"&0%,$I$19:$I$521, "<="&20%),""),"") -> 0.0041392357 | G50: 0.025899912 | H50: =IFERROR($G50*$F50,"") -> 0.00010720584 | I50: 0.10135 | J50: =IFERROR($I50*$F50,"") -> 0.00041951153
A51: Analog Devices Inc | B51: ADI | C51: 495.84 | D51: 192.36 | E51: =IFERROR(C51*D51,"") -> 95379.782 | F51: =IF(AND(ISNUMBER($I51)), IF(AND($I51<=20%,$I51>0%), $E51/SUMIFS($E$19:$E$521,$I$19:$I$521, ">"&0%,$I$19:$I$521, "<="&20%),""),"") -> 0.0030132404 | G51: 0.017883136 | H51: =IFERROR($G51*$F51,"") -> 5.3886187e-05 | I51: 0.045 | J51: =IFERROR($I51*$F51,"") -> 0.00013559582
A52: Walmart Inc | B52: WMT | C52: 2692.234 | D52: 165.25 | E52: =IFERROR(C52*D52,"") -> 444891.67 | F52: =IF(AND(ISNUMBER($I52)), IF(AND($I52<=20%,$I52>0%), $E52/SUMIFS($E$19:$E$521,$I$19:$I$521, ">"&0%,$I$19:$I$521, "<="&20%),""),"") -> 0.014055028 | G52: 0.013797277 | H52: =IFERROR($G52*$F52,"") -> 0.00019392112 | I52: 0.03 | J52: =IFERROR($I52*$F52,"") -> 0.00042165085
... A68: Air Products and Chemicals Inc | B68: APD | C68: 222.228 | D68: 255.71 | E68: =IFERROR(C68*D68,"") -> 56825.922 | F68: =IF(AND(ISNUMBER($I68)), IF(AND($I68<=20%,$I68>0%), $E68/SUMIFS($E$19:$E$521,$I$19:$I$521, ">"&0%,$I$19:$I$521, "<="&20%),""),"") -> 0.0017952459 | G68: 0.027687615 | H68: =IFERROR($G68*$F68,"") -> 4.9706077e-05 | I68: 0.1206 | J68: =IFERROR($I68*$F68,"") -> 0.00021650666
A69: Royal Caribbean Cruises Ltd | B69: RCL | C69: 256.235 | D69: 127.5 | E69: =IFERROR(C69*D69,"") -> 32669.963 | F69: =IF(AND(ISNUMBER($I69)), IF(AND($I69<=20%,$I69>0%), $E69/SUMIFS($E$19:$E$521,$I$19:$I$521, ">"&0%,$I$19:$I$521, "<="&20%),""),"") | H69: =IFERROR($G69*$F69,"") | J69: =IFERROR($I69*$F69,"")
A70: Hess Corp | B70: HES | C70: 307.152 | D70: 140.53 | E70: =IFERROR(C70*D70,"") -> 43164.071 | F70: =IF(AND(ISNUMBER($I70)), IF(AND($I70<=20%,$I70>0%), $E70/SUMIFS($E$19:$E$521,$I$19:$I$521, ">"&0%,$I$19:$I$521, "<="&20%),""),"") -> 0.0013636404 | G70: 0.012452857 | H70: =IFERROR($G70*$F70,"") -> 1.6981219e-05 | I70: 0.135 | J70: =IFERROR($I70*$F70,"") -> 0.00018409145
A71: Archer-Daniels-Midland Co | B71: ADM | C71: 533.381 | D71: 55.58 | E71: =IFERROR(C71*D71,"") -> 29645.316 | F71: =IF(AND(ISNUMBER($I71)), IF(AND($I71<=20%,$I71>0%), $E71/SUMIFS($E$19:$E$521,$I$19:$I$521, ">"&0%,$I$19:$I$521, "<="&20%),""),"") | G71: 0.035984167 | H71: =IFERROR($G71*$F71,"") | I71: -0.0781 | J71: =IFERROR($I71*$F71,"")
A72: Automatic Data Processing Inc | B72: ADP | C72: 410.7 | D72: 245.78 | E72: =IFERROR(C72*D72,"") -> 100941.85 | F72: =IF(AND(ISNUMBER($I72)), IF(AND($I72<=20%,$I72>0%), $E72/SUMIFS($E$19:$E$521,$I$19:$I$521, ">"&0%,$I$19:$I$521, "<="&20%),""),"") -> 0.0031889573 | G72: 0.022784604 | H72: =IFERROR($G72*$F72,"") -> 7.2659129e-05 | I72: 0.16 | J72: =IFERROR($I72*$F72,"") -> 0.00051023316
A73: Verisk Analytics Inc | B73: VRSK | C73: 144.987 | D73: 241.53 | E73: =IFERROR(C73*D73,"") -> 35018.71 | F73: =IF(AND(ISNUMBER($I73)), IF(AND($I73<=20%,$I73>0%), $E73/SUMIFS($E$19:$E$521,$I$19:$I$521, ">"&0%,$I$19:$I$521, "<="&20%),""),"") -> 0.0011063119 | G73: 0.0056307705 | H73: =IFERROR($G73*$F73,"") -> 6.2293887e-06 | I73: 0.117 | J73: =IFERROR($I73*$F73,"") -> 0.0001294385
A74: AutoZone Inc | B74: AZO | C74: 17.292 | D74: 2762.13 | E74: =IFERROR(C74*D74,"") -> 47762.752 | F74: =IF(AND(ISNUMBER($I74)), IF(AND($I74<=20%,$I74>0%), $E74/SUMIFS($E$19:$E$521,$I$19:$I$521, ">"&0%,$I$19:$I$521, "<="&20%),""),"") -> 0.001508922 | H74: =IFERROR($G74*$F74,"") | I74: 0.1429 | J74: =IFERROR($I74*$F74,"") -> 0.00021562496
A75: Linde PLC | B75: LIN | C75: 484.89 | D75: 404.83 | E75: =IFERROR(C75*D75,"") -> 196298.02 | F75: =IF(AND(ISNUMBER($I75)), IF(AND($I75<=20%,$I75>0%), $E75/SUMIFS($E$19:$E$521,$I$19:$I$521, ">"&0%,$I$19:$I$521, "<="&20%),""),"") -> 0.0062014518 | G75: 0.012597881 | H75: =IFERROR($G75*$F75,"") -> 7.8125149e-05 | I75: 0.14 | J75: =IFERROR($I75*$F75,"") -> 0.00086820325
A76: Avery Dennison Corp | B76: AVY | C76: 80.531 | D76: 199.45 | E76: =IFERROR(C76*D76,"") -> 16061.908 | F76: =IF(AND(ISNUMBER($I76)), IF(AND($I76<=20%,$I76>0%), $E76/SUMIFS($E$19:$E$521,$I$19:$I$521, ">"&0%,$I$19:$I$521, "<="&20%),""),"") -> 0.00050742819 | G76: 0.016244673 | H76: =IFERROR($G76*$F76,"") -> 8.2430049e-06 | I76: 0.07 | J76: =IFERROR($I76*$F76,"") -> 3.5519973e-05
A77: Enphase Energy Inc | B77: ENPH | C77: 136.551 | D77: 104.13 | E77: =IFERROR(C77*D77,"") -> 14219.056 | F77: =IF(AND(ISNUMBER($I77)), IF(AND($I77<=20%,$I77>0%), $E77/SUMIFS($E$19:$E$521,$I$19:$I$521, ">"&0%,$I$19:$I$521, "<="&20%),""),"") | H77: =IFERROR($G77*$F77,"") | I77: 0.2857 | J77: =IFERROR($I77*$F77,"")
A78: MSCI Inc | B78: MSCI | C78: 79.1 | D78: 598.62 | E78: =IFERROR(C78*D78,"") -> 47350.842 | F78: =IF(AND(ISNUMBER($I78)), IF(AND($I78<=20%,$I78>0%), $E78/SUMIFS($E$19:$E$521,$I$19:$I$521, ">"&0%,$I$19:$I$521, "<="&20%),""),"") -> 0.001495909 | G78: 0.010691257 | H78: =IFERROR($G78*$F78,"") -> 1.5993146e-05 | I78: 0.1212 | J78: =IFERROR($I78*$F78,"") -> 0.00018130417
A79: Ball Corp | B79: BALL | C79: 315.301 | D79: 55.45 | E79: =IFERROR(C79*D79,"") -> 17483.44 | F79: =IF(AND(ISNUMBER($I79)), IF(AND($I79<=20%,$I79>0%), $E79/SUMIFS($E$19:$E$521,$I$19:$I$521, ">"&0%,$I$19:$I$521, "<="&20%),""),"") -> 0.00055233728 | G79: 0.014427412 | H79: =IFERROR($G79*$F79,"") -> 7.9687975e-06 | I79: 0.095 | J79: =IFERROR($I79*$F79,"") -> 5.2472041e-05
A80: Axon Enterprise Inc | B80: AXON | C80: 74.934 | D80: 249.06 | E80: =IFERROR(C80*D80,"") -> 18663.062 | F80: =IF(AND(ISNUMBER($I80)), IF(AND($I80<=20%,$I80>0%), $E80/SUMIFS($E$19:$E$521,$I$19:$I$521, ">"&0%,$I$19:$I$521, "<="&20%),""),"") | H80: =IFERROR($G80*$F80,"") | J80: =IFERROR($I80*$F80,"")
A81: Dayforce Inc | B81: DAY | C81: 156.127 | D81: 69.52 | E81: =IFERROR(C81*D81,"") -> 10853.949 | F81: =IF(AND(ISNUMBER($I81)), IF(AND($I81<=20%,$I81>0%), $E81/SUMIFS($E$19:$E$521,$I$19:$I$521, ">"&0%,$I$19:$I$521, "<="&20%),""),"") | H81: =IFERROR($G81*$F81,"") | J81: =IFERROR($I81*$F81,"")
A82: Carrier Global Corp | B82: CARR | C82: 897.656 | D82: 54.71 | E82: =IFERROR(C82*D82,"") -> 49110.76 | F82: =IF(AND(ISNUMBER($I82)), IF(AND($I82<=20%,$I82>0%), $E82/SUMIFS($E$19:$E$521,$I$19:$I$521, ">"&0%,$I$19:$I$521, "<="&20%),""),"") -> 0.0015515083 | G82: 0.013891428 | H82: =IFERROR($G82*$F82,"") -> 2.1552665e-05 | I82: 0.1094 | J82: =IFERROR($I82*$F82,"") -> 0.00016973501
A83: Bank of New York Mellon Corp/The | B83: BK | C83: 759.344 | D83: 55.46 | E83: =IFERROR(C83*D83,"") -> 42113.218 | F83: =IF(AND(ISNUMBER($I83)), IF(AND($I83<=20%,$I83>0%), $E83/SUMIFS($E$19:$E$521,$I$19:$I$521, ">"&0%,$I$19:$I$521, "<="&20%),""),"") -> 0.0013304418 | G83: 0.030292102 | H83: =IFERROR($G83*$F83,"") -> 4.030188e-05 | I83: 0.1 | J83: =IFERROR($I83*$F83,"") -> 0.00013304418
A84: Otis Worldwide Corp | B84: OTIS | C84: 409.259 | D84: 88.44 | E84: =IFERROR(C84*D84,"") -> 36194.866 | F84: =IF(AND(ISNUMBER($I84)), IF(AND($I84<=20%,$I84>0%), $E84/SUMIFS($E$19:$E$521,$I$19:$I$521, ">"&0%,$I$19:$I$521, "<="&20%),""),"") -> 0.0011434691 | G84: 0.015377657 | H84: =IFERROR($G84*$F84,"") -> 1.7583876e-05 | I84: 0.09 | J84: =IFERROR($I84*$F84,"") -> 0.00010291222
A85: Baxter International Inc | B85: BAX | C85: 507.324 | D85: 38.69 | E85: =IFERROR(C85*D85,"") -> 19628.366 | F85: =IF(AND(ISNUMBER($I85)), IF(AND($I85<=20%,$I85>0%), $E85/SUMIFS($E$19:$E$521,$I$19:$I$521, ">"&0%,$I$19:$I$521, "<="&20%),""),"") | G85: 0.029981907 | H85: =IFERROR($G85*$F85,"") | I85: -0.03 | J85: =IFERROR($I85*$F85,"")
A86: Becton Dickinson & Co | B86: BDX | C86: 289.542 | D86: 238.81 | E86: =IFERROR(C86*D86,"") -> 69145.525 | F86: =IF(AND(ISNUMBER($I86)), IF(AND($I86<=20%,$I86>0%), $E86/SUMIFS($E$19:$E$521,$I$19:$I$521, ">"&0%,$I$19:$I$521, "<="&20%),""),"") | G86: 0.015912231 | H86: =IFERROR($G86*$F86,"") | I86: -0.0202 | J86: =IFERROR($I86*$F86,"")
A87: Berkshire Hathaway Inc | B87: BRK/B | C87: 1308.414 | D87: 383.74 | E87: =IFERROR(C87*D87,"") -> 502090.79 | F87: =IF(AND(ISNUMBER($I87)), IF(AND($I87<=20%,$I87>0%), $E87/SUMIFS($E$19:$E$521,$I$19:$I$521, ">"&0%,$I$19:$I$521, "<="&20%),""),"") | H87: =IFERROR($G87*$F87,"") | J87: =IFERROR($I87*$F87,"")
A88: Best Buy Co Inc | B88: BBY | C88: 215.396 | D88: 72.49 | E88: =IFERROR(C88*D88,"") -> 15614.056 | F88: =IF(AND(ISNUMBER($I88)), IF(AND($I88<=20%,$I88>0%), $E88/SUMIFS($E$19:$E$521,$I$19:$I$521, ">"&0%,$I$19:$I$521, "<="&20%),""),"") -> 0.00049327964 | G88: 0.050765623 | H88: =IFERROR($G88*$F88,"") -> 2.5041648e-05 | I88: 0.03075 | J88: =IFERROR($I88*$F88,"") -> 1.5168349e-05
A89: Boston Scientific Corp | B89: BSX | C89: 1464.983 | D89: 63.26 | E89: =IFERROR(C89*D89,"") -> 92674.825 | F89: =IF(AND(ISNUMBER($I89)), IF(AND($I89<=20%,$I89>0%), $E89/SUMIFS($E$19:$E$521,$I$19:$I$521, ">"&0%,$I$19:$I$521, "<="&20%),""),"") -> 0.0029277853 | H89: =IFERROR($G89*$F89,"") | I89: 0.12095 | J89: =IFERROR($I89*$F89,"") -> 0.00035411563
A90: Bristol-Myers Squibb Co | B90: BMY | C90: 2034.758 | D90: 48.87 | E90: =IFERROR(C90*D90,"") -> 99438.623 | F90: =IF(AND(ISNUMBER($I90)), IF(AND($I90<=20%,$I90>0%), $E90/SUMIFS($E$19:$E$521,$I$19:$I$521, ">"&0%,$I$19:$I$521, "<="&20%),""),"") -> 0.0031414674 | G90: 0.049109883 | H90: =IFERROR($G90*$F90,"") -> 0.0001542771 | I90: 0.02778 | J90: =IFERROR($I90*$F90,"") -> 8.7269965e-05
A91: Brown-Forman Corp | B91: BF/B | C91: 306.475 | D91: 54.9 | E91: =IFERROR(C91*D91,"") -> 16825.478 | F91: =IF(AND(ISNUMBER($I91)), IF(AND($I91<=20%,$I91>0%), $E91/SUMIFS($E$19:$E$521,$I$19:$I$521, ">"&0%,$I$19:$I$521, "<="&20%),""),"") -> 0.0005315509 | G91: 0.015868852 | H91: =IFERROR($G91*$F91,"") -> 8.4351027e-06 | I91: 0.0485 | J91: =IFERROR($I91*$F91,"") -> 2.5780218e-05
A92: Coterra Energy Inc | B92: CTRA | C92: 752.192 | D92: 24.88 | E92: =IFERROR(C92*D92,"") -> 18714.537 | F92: =IF(AND(ISNUMBER($I92)), IF(AND($I92<=20%,$I92>0%), $E92/SUMIFS($E$19:$E$521,$I$19:$I$521, ">"&0%,$I$19:$I$521, "<="&20%),""),"") | G92: 0.032154341 | H92: =IFERROR($G92*$F92,"") | I92: 0.5504 | J92: =IFERROR($I92*$F92,"")
A93: Campbell Soup Co | B93: CPB | C93: 298.1 | D93: 44.63 | E93: =IFERROR(C93*D93,"") -> 13304.203 | F93: =IF(AND(ISNUMBER($I93)), IF(AND($I93<=20%,$I93>0%), $E93/SUMIFS($E$19:$E$521,$I$19:$I$521, ">"&0%,$I$19:$I$521, "<="&20%),""),"") -> 0.00042030671 | G93: 0.033161551 | H93: =IFERROR($G93*$F93,"") -> 1.3938022e-05 | I93: 0.0281 | J93: =IFERROR($I93*$F93,"") -> 1.1810618e-05
A94: Hilton Worldwide Holdings Inc | B94: HLT | C94: 256.44 | D94: 190.96 | E94: =IFERROR(C94*D94,"") -> 48969.782 | F94: =IF(AND(ISNUMBER($I94)), IF(AND($I94<=20%,$I94>0%), $E94/SUMIFS($E$19:$E$521,$I$19:$I$521, ">"&0%,$I$19:$I$521, "<="&20%),""),"") -> 0.0015470546 | G94: 0.0031420193 | H94: =IFERROR($G94*$F94,"") -> 4.8608752e-06 | I94: 0.1714 | J94: =IFERROR($I94*$F94,"") -> 0.00026516515
A95: Carnival Corp | B95: CCL | C95: 1119.445 | D95: 16.58 | E95: =IFERROR(C95*D95,"") -> 18560.398 | F95: =IF(AND(ISNUMBER($I95)), IF(AND($I95<=20%,$I95>0%), $E95/SUMIFS($E$19:$E$521,$I$19:$I$521, ">"&0%,$I$19:$I$521, "<="&20%),""),"") | H95: =IFERROR($G95*$F95,"") | J95: =IFERROR($I95*$F95,"")
A96: Qorvo Inc | B96: QRVO | C96: 97.346 | D96: 99.74 | E96: =IFERROR(C96*D96,"") -> 9709.29 | F96: =IF(AND(ISNUMBER($I96)), IF(AND($I96<=20%,$I96>0%), $E96/SUMIFS($E$19:$E$521,$I$19:$I$521, ">"&0%,$I$19:$I$521, "<="&20%),""),"") -> 0.00030673613 | H96: =IFERROR($G96*$F96,"") | I96: 0.18147 | J96: =IFERROR($I96*$F96,"") -> 5.5663405e-05
A97: Builders FirstSource Inc | B97: BLDR | C97: 123.347 | D97: 173.73 | E97: =IFERROR(C97*D97,"") -> 21429.074 | F97: =IF(AND(ISNUMBER($I97)), IF(AND($I97<=20%,$I97>0%), $E97/SUMIFS($E$19:$E$521,$I$19:$I$521, ">"&0%,$I$19:$I$521, "<="&20%),""),"") | H97: =IFERROR($G97*$F97,"") | I97: -0.0167 | J97: =IFERROR($I97*$F97,"")
A98: UDR Inc | B98: UDR | C98: 328.928 | D98: 36.02 | E98: =IFERROR(C98*D98,"") -> 11847.987 | F98: =IF(AND(ISNUMBER($I98)), IF(AND($I98<=20%,$I98>0%), $E98/SUMIFS($E$19:$E$521,$I$19:$I$521, ">"&0%,$I$19:$I$521, "<="&20%),""),"") -> 0.00037430188 | G98: 0.046640755 | H98: =IFERROR($G98*$F98,"") -> 1.7457722e-05 | I98: 0.0608 | J98: =IFERROR($I98*$F98,"") -> 2.2757554e-05
A99: Clorox Co/The | B99: CLX | C99: 124.059 | D99: 145.25 | E99: =IFERROR(C99*D99,"") -> 18019.57 | F99: =IF(AND(ISNUMBER($I99)), IF(AND($I99<=20%,$I99>0%), $E99/SUMIFS($E$19:$E$521,$I$19:$I$521, ">"&0%,$I$19:$I$521, "<="&20%),""),"") -> 0.00056927469 | G99: 0.033046472 | H99: =IFERROR($G99*$F99,"") -> 1.881252e-05 | I99: 0.119 | J99: =IFERROR($I99*$F99,"") -> 6.7743688e-05
A100: Paycom Software Inc | B100: PAYC | C100: 60.228 | D100: 190.24 | E100: =IFERROR(C100*D100,"") -> 11457.775 | F100: =IF(AND(ISNUMBER($I100)), IF(AND($I100<=20%,$I100>0%), $E100/SUMIFS($E$19:$E$521,$I$19:$I$521, ">"&0%,$I$19:$I$521, "<="&20%),""),"") -> 0.0003619743 | G100: 0.0078847771 | H100: =IFERROR($G100*$F100,"") -> 2.8540867e-06 | I100: 0.1519 | J100: =IFERROR($I100*$F100,"") -> 5.4983896e-05
A101: CMS Energy Corp | B101: CMS | C101: 291.764 | D101: 57.16 | E101: =IFERROR(C101*D101,"") -> 16677.23 | F101: =IF(AND(ISNUMBER($I101)), IF(AND($I101<=20%,$I101>0%), $E101/SUMIFS($E$19:$E$521,$I$19:$I$521, ">"&0%,$I$19:$I$521, "<="&20%),""),"") -> 0.00052686746 | G101: 0.034114766 | H101: =IFERROR($G101*$F101,"") -> 1.797396e-05 | I101: 0.0775 | J101: =IFERROR($I101*$F101,"") -> 4.0832229e-05
A102: Colgate-Palmolive Co | B102: CL | C102: 823.372 | D102: 84.2 | E102: =IFERROR(C102*D102,"") -> 69327.922 | F102: =IF(AND(ISNUMBER($I102)), IF(AND($I102<=20%,$I102>0%), $E102/SUMIFS($E$19:$E$521,$I$19:$I$521, ">"&0%,$I$19:$I$521, "<="&20%),""),"") -> 0.0021902094 | G102: 0.02280285 | H102: =IFERROR($G102*$F102,"") -> 4.9943018e-05 | I102: 0.0818 | J102: =IFERROR($I102*$F102,"") -> 0.00017915913
A103: EPAM Systems Inc | B103: EPAM | C103: 57.7 | D103: 278.11 | E103: =IFERROR(C103*D103,"") -> 16046.947 | F103: =IF(AND(ISNUMBER($I103)), IF(AND($I103<=20%,$I103>0%), $E103/SUMIFS($E$19:$E$521,$I$19:$I$521, ">"&0%,$I$19:$I$521, "<="&20%),""),"") -> 0.00050695554 | H103: =IFERROR($G103*$F103,"") | I103: 0.0487 | J103: =IFERROR($I103*$F103,"") -> 2.4688735e-05
A104: Comerica Inc | B104: CMA | C104: 131.873 | D104: 52.58 | E104: =IFERROR(C104*D104,"") -> 6933.8823 | F104: =IF(AND(ISNUMBER($I104)), IF(AND($I104<=20%,$I104>0%), $E104/SUMIFS($E$19:$E$521,$I$19:$I$521, ">"&0%,$I$19:$I$521, "<="&20%),""),"") | G104: 0.054012933 | H104: =IFERROR($G104*$F104,"") | I104: 0.31 | J104: =IFERROR($I104*$F104,"")
A105: Conagra Brands Inc | B105: CAG | C105: 478.005 | D105: 29.15 | E105: =IFERROR(C105*D105,"") -> 13933.846 | F105: =IF(AND(ISNUMBER($I105)), IF(AND($I105<=20%,$I105>0%), $E105/SUMIFS($E$19:$E$521,$I$19:$I$521, ">"&0%,$I$19:$I$521, "<="&20%),""),"") -> 0.0004401984 | G105: 0.048027444 | H105: =IFERROR($G105*$F105,"") -> 2.1141604e-05 | I105: 0.02075 | J105: =IFERROR($I105*$F105,"") -> 9.1341167e-06
A106: Airbnb Inc | B106: ABNB | C106: 434.745 | D106: 144.14 | E106: =IFERROR(C106*D106,"") -> 62664.144 | F106: =IF(AND(ISNUMBER($I106)), IF(AND($I106<=20%,$I106>0%), $E106/SUMIFS($E$19:$E$521,$I$19:$I$521, ">"&0%,$I$19:$I$521, "<="&20%),""),"") -> 0.0019796872 | H106: =IFERROR($G106*$F106,"") | I106: 0.182 | J106: =IFERROR($I106*$F106,"") -> 0.00036030307
A107: Consolidated Edison Inc | B107: ED | C107: 344.924 | D107: 90.9 | E107: =IFERROR(C107*D107,"") -> 31353.592 | F107: =IF(AND(ISNUMBER($I107)), IF(AND($I107<=20%,$I107>0%), $E107/SUMIFS($E$19:$E$521,$I$19:$I$521, ">"&0%,$I$19:$I$521, "<="&20%),""),"") -> 0.00099052343 | G107: 0.036523652 | H107: =IFERROR($G107*$F107,"") -> 3.6177533e-05 | I107: 0.06 | J107: =IFERROR($I107*$F107,"") -> 5.9431406e-05
A108: Corning Inc | B108: GLW | C108: 853.182 | D108: 32.49 | E108: =IFERROR(C108*D108,"") -> 27719.883 | F108: =IF(AND(ISNUMBER($I108)), IF(AND($I108<=20%,$I108>0%), $E108/SUMIFS($E$19:$E$521,$I$19:$I$521, ">"&0%,$I$19:$I$521, "<="&20%),""),"") -> 0.00087572723 | G108: 0.034472145 | H108: =IFERROR($G108*$F108,"") -> 3.0188196e-05 | I108: 0.0934 | J108: =IFERROR($I108*$F108,"") -> 8.1792923e-05
A109: Cummins Inc | B109: CMI | C109: 141.745 | D109: 239.3 | E109: =IFERROR(C109*D109,"") -> 33919.579 | F109: =IF(AND(ISNUMBER($I109)), IF(AND($I109<=20%,$I109>0%), $E109/SUMIFS($E$19:$E$521,$I$19:$I$521, ">"&0%,$I$19:$I$521, "<="&20%),""),"") -> 0.0010715882 | G109: 0.028081906 | H109: =IFERROR($G109*$F109,"") -> 3.0092237e-05 | I109: 0.0701 | J109: =IFERROR($I109*$F109,"") -> 7.5118329e-05
A110: Caesars Entertainment Inc | B110: CZR | C110: 215.711 | D110: 43.87 | E110: =IFERROR(C110*D110,"") -> 9463.2416 | F110: =IF(AND(ISNUMBER($I110)), IF(AND($I110<=20%,$I110>0%), $E110/SUMIFS($E$19:$E$521,$I$19:$I$521, ">"&0%,$I$19:$I$521, "<="&20%),""),"") | H110: =IFERROR($G110*$F110,"") | I110: 1.2712 | J110: =IFERROR($I110*$F110,"")
A111: Danaher Corp | B111: DHR | C111: 739.2 | D111: 239.91 | E111: =IFERROR(C111*D111,"") -> 177341.47 | F111: =IF(AND(ISNUMBER($I111)), IF(AND($I111<=20%,$I111>0%), $E111/SUMIFS($E$19:$E$521,$I$19:$I$521, ">"&0%,$I$19:$I$521, "<="&20%),""),"") -> 0.0056025761 | G111: 0.0040015006 | H111: =IFERROR($G111*$F111,"") -> 2.2418711e-05 | I111: 0.0583 | J111: =IFERROR($I111*$F111,"") -> 0.00032663019
A112: Target Corp | B112: TGT | C112: 461.662 | D112: 139.08 | E112: =IFERROR(C112*D112,"") -> 64207.951 | F112: =IF(AND(ISNUMBER($I112)), IF(AND($I112<=20%,$I112>0%), $E112/SUMIFS($E$19:$E$521,$I$19:$I$521, ">"&0%,$I$19:$I$521, "<="&20%),""),"") -> 0.0020284592 | G112: 0.031636468 | H112: =IFERROR($G112*$F112,"") -> 6.4173284e-05 | I112: 0.1529 | J112: =IFERROR($I112*$F112,"") -> 0.0003101514
A113: Deere & Co | B113: DE | C113: 279.99 | D113: 393.58 | E113: =IFERROR(C113*D113,"") -> 110198.46 | F113: =IF(AND(ISNUMBER($I113)), IF(AND($I113<=20%,$I113>0%), $E113/SUMIFS($E$19:$E$521,$I$19:$I$521, ">"&0%,$I$19:$I$521, "<="&20%),""),"") -> 0.0034813926 | G113: 0.014939784 | H113: =IFERROR($G113*$F113,"") -> 5.2011251e-05 | I113: 0.03955 | J113: =IFERROR($I113*$F113,"") -> 0.00013768908
A114: Dominion Energy Inc | B114: D | C114: 836.773 | D114: 45.72 | E114: =IFERROR(C114*D114,"") -> 38257.262 | F114: =IF(AND(ISNUMBER($I114)), IF(AND($I114<=20%,$I114>0%), $E114/SUMIFS($E$19:$E$521,$I$19:$I$521, ">"&0%,$I$19:$I$521, "<="&20%),""),"") -> 0.0012086243 | G114: 0.05839895 | H114: =IFERROR($G114*$F114,"") -> 7.0582393e-05 | I114: 0.069 | J114: =IFERROR($I114*$F114,"") -> 8.339508e-05
A115: Dover Corp | B115: DOV | C115: 139.89 | D115: 149.78 | E115: =IFERROR(C115*D115,"") -> 20952.724 | F115: =IF(AND(ISNUMBER($I115)), IF(AND($I115<=20%,$I115>0%), $E115/SUMIFS($E$19:$E$521,$I$19:$I$521, ">"&0%,$I$19:$I$521, "<="&20%),""),"") -> 0.00066193897 | G115: 0.013619976 | H115: =IFERROR($G115*$F115,"") -> 9.0155929e-06 | I115: 0.1 | J115: =IFERROR($I115*$F115,"") -> 6.6193897e-05
A116: Alliant Energy Corp | B116: LNT | C116: 252.719 | D116: 48.66 | E116: =IFERROR(C116*D116,"") -> 12297.307 | F116: =IF(AND(ISNUMBER($I116)), IF(AND($I116<=20%,$I116>0%), $E116/SUMIFS($E$19:$E$521,$I$19:$I$521, ">"&0%,$I$19:$I$521, "<="&20%),""),"") -> 0.00038849681 | G116: 0.03945746 | H116: =IFERROR($G116*$F116,"") -> 1.5329097e-05 | I116: 0.06155 | J116: =IFERROR($I116*$F116,"") -> 2.3911979e-05
A117: Steel Dynamics Inc | B117: STLD | C117: 161.816 | D117: 120.69 | E117: =IFERROR(C117*D117,"") -> 19529.573 | F117: =IF(AND(ISNUMBER($I117)), IF(AND($I117<=20%,$I117>0%), $E117/SUMIFS($E$19:$E$521,$I$19:$I$521, ">"&0%,$I$19:$I$521, "<="&20%),""),"") | G117: 0.014085674 | H117: =IFERROR($G117*$F117,"") | I117: -0.1301 | J117: =IFERROR($I117*$F117,"")
A118: Duke Energy Corp | B118: DUK | C118: 771 | D118: 95.83 | E118: =IFERROR(C118*D118,"") -> 73884.93 | F118: =IF(AND(ISNUMBER($I118)), IF(AND($I118<=20%,$I118>0%), $E118/SUMIFS($E$19:$E$521,$I$19:$I$521, ">"&0%,$I$19:$I$521, "<="&20%),""),"") -> 0.0023341745 | G118: 0.042784097 | H118: =IFERROR($G118*$F118,"") -> 9.9865548e-05 | I118: 0.0634 | J118: =IFERROR($I118*$F118,"") -> 0.00014798666
A119: Regency Centers Corp | B119: REG | C119: 184.576 | D119: 62.67 | E119: =IFERROR(C119*D119,"") -> 11567.378 | F119: =IF(AND(ISNUMBER($I119)), IF(AND($I119<=20%,$I119>0%), $E119/SUMIFS($E$19:$E$521,$I$19:$I$521, ">"&0%,$I$19:$I$521, "<="&20%),""),"") -> 0.00036543689 | G119: 0.042763683 | H119: =IFERROR($G119*$F119,"") -> 1.5627427e-05 | I119: 0.0346 | J119: =IFERROR($I119*$F119,"") -> 1.2644116e-05
A120: Eaton Corp PLC | B120: ETN | C120: 399.3 | D120: 246.08 | E120: =IFERROR(C120*D120,"") -> 98259.744 | F120: =IF(AND(ISNUMBER($I120)), IF(AND($I120<=20%,$I120>0%), $E120/SUMIFS($E$19:$E$521,$I$19:$I$521, ">"&0%,$I$19:$I$521, "<="&20%),""),"") -> 0.0031042242 | G120: 0.013979194 | H120: =IFERROR($G120*$F120,"") -> 4.3394552e-05 | I120: 0.15 | J120: =IFERROR($I120*$F120,"") -> 0.00046563363
A121: Ecolab Inc | B121: ECL | C121: 285.14 | D121: 198.22 | E121: =IFERROR(C121*D121,"") -> 56520.451 | F121: =IF(AND(ISNUMBER($I121)), IF(AND($I121<=20%,$I121>0%), $E121/SUMIFS($E$19:$E$521,$I$19:$I$521, ">"&0%,$I$19:$I$521, "<="&20%),""),"") -> 0.0017855955 | G121: 0.011502371 | H121: =IFERROR($G121*$F121,"") -> 2.0538582e-05 | I121: 0.14333 | J121: =IFERROR($I121*$F121,"") -> 0.0002559294
A122: Revvity Inc | B122: RVTY | C122: 123.407 | D122: 107.18 | E122: =IFERROR(C122*D122,"") -> 13226.762 | F122: =IF(AND(ISNUMBER($I122)), IF(AND($I122<=20%,$I122>0%), $E122/SUMIFS($E$19:$E$521,$I$19:$I$521, ">"&0%,$I$19:$I$521, "<="&20%),""),"") | G122: 0.0026124277 | H122: =IFERROR($G122*$F122,"") | I122: -0.0732 | J122: =IFERROR($I122*$F122,"")
... A128: EQT Corp | B128: EQT | C128: 411.332 | D128: 35.4 | E128: =IFERROR(C128*D128,"") -> 14561.153 | F128: =IF(AND(ISNUMBER($I128)), IF(AND($I128<=20%,$I128>0%), $E128/SUMIFS($E$19:$E$521,$I$19:$I$521, ">"&0%,$I$19:$I$521, "<="&20%),""),"") | G128: 0.01779661 | H128: =IFERROR($G128*$F128,"") | I128: 0.21405 | J128: =IFERROR($I128*$F128,"")
A129: IQVIA Holdings Inc | B129: IQV | C129: 182.5 | D129: 208.23 | E129: =IFERROR(C129*D129,"") -> 38001.975 | F129: =IF(AND(ISNUMBER($I129)), IF(AND($I129<=20%,$I129>0%), $E129/SUMIFS($E$19:$E$521,$I$19:$I$521, ">"&0%,$I$19:$I$521, "<="&20%),""),"") -> 0.0012005593 | H129: =IFERROR($G129*$F129,"") | I129: 0.0967 | J129: =IFERROR($I129*$F129,"") -> 0.00011609409
...

Sheet AEB-8 Risk Premium
B2: BOND YIELD PLUS RISK PREMIUM
C4: [1] | D4: [2] | E4: [3]
B5: Quarter | C5: Average Authorized Electric ROE | D5: U.S. Govt. 30-year Treasury | E5: Risk Premium
B6: 1980.1 | C6: 0.13968571 | D6: 0.11657097 | E6: =C6-D6 -> 0.023114747
B7: 1980.2 | C7: 0.142532 | D7: 0.10524921 | E7: =C7-D7 -> 0.037282794
B8: 1980.3 | C8: 0.142956 | D8: 0.1085 | E8: =C8-D8 -> 0.034456
B9: 1980.4 | C9: 0.14322121 | D9: 0.1209623 | E9: =C9-D9 -> 0.022258917
B10: 1981.1 | C10: 0.14817 | D10: 0.12533279 | E10: =C10-D10 -> 0.022837213
B11: 1981.2 | C11: 0.15049512 | D11: 0.13242857 | E11: =C11-D11 -> 0.018066551
B12: 1981.3 | C12: 0.15305385 | D12: 0.14132344 | E12: =C12-D12 -> 0.011730409
B13: 1981.4 | C13: 0.15588286 | D13: 0.13847869 | E13: =C13-D13 -> 0.017404169
B14: 1982.1 | C14: 0.15713103 | D14: 0.13962131 | E14: =C14-D14 -> 0.017509723
B15: 1982.2 | C15: 0.15602571 | D15: 0.13521905 | E15: =C15-D15 -> 0.020806667
B16: 1982.3 | C16: 0.1585 | D16: 0.12794375 | E16: =C16-D16 -> 0.03055625
B17: 1982.4 | C17: 0.16028387 | D17: 0.1074623 | E17: =C17-D17 -> 0.052821576
... B21: 1983.4 | C21: 0.15368148 | D21: 0.11737 | E21: =C21-D21 -> 0.036311481
B22: 1984.1 | C22: 0.150605 | D22: 0.1203629 | E22: =C22-D22 -> 0.030242097 | G22: SUMMARY OUTPUT
B23: 1984.2 | C23: 0.15182667 | D23: 0.13183968 | E23: =C23-D23 -> 0.019986984
B24: 1984.3 | C24: 0.15382273 | D24: 0.12689048 | E24: =C24-D24 -> 0.026932251 | G24: Regression Statistics
B25: 1984.4 | C25: 0.15690526 | D25: 0.11698852 | E25: =C25-D25 -> 0.039916739 | G25: Multiple R | H25: 0.91431368
B26: 1985.1 | C26: 0.1548 | D26: 0.11584 | E26: =C26-D26 -> 0.03896 | G26: R Square | H26: 0.8359695
B27: 1985.2 | C27: 0.152675 | D27: 0.10995873 | E27: =C27-D27 -> 0.04271627 | G27: Adjusted R Square | H27: 0.83503218
B28: 1985.3 | C28: 0.14910714 | D28: 0.10553016 | E28: =C28-D28 -> 0.043576984 | G28: Standard Error | H28: 0.0056694111
B29: 1985.4 | C29: 0.15107647 | D29: 0.10039839 | E29: =C29-D29 -> 0.050678083 | G29: Observations | H29: 177
B30: 1986.1 | C30: 0.14423333 | D30: 0.087693333 | E30: =C30-D30 -> 0.05654
B31: 1986.2 | C31: 0.14272667 | D31: 0.07490625 | E31: =C31-D31 -> 0.067820417 | G31: ANOVA
B32: 1986.3 | C32: 0.1326 | D32: 0.074042187 | E32: =C32-D32 -> 0.058557812 | H32: df | I32: SS | J32: MS | K32: F | L32: Significance F
B33: 1986.4 | C33: 0.13515556 | D33: 0.075280645 | E33: =C33-D33 -> 0.05987491 | G33: Regression | H33: 1 | I33: 0.028666836 | J33: 0.028666836 | K33: 891.87475 | L33: 1.3308493e-70
B34: 1987.1 | C34: 0.12895556 | D34: 0.074936066 | E34: =C34-D34 -> 0.05401949 | G34: Residual | H34: 175 | I34: 0.0056248889 | J34: 3.2142222e-05
B35: 1987.2 | C35: 0.1317 | D35: 0.085306349 | E35: =C35-D35 -> 0.046393651 | G35: Total | H35: 176 | I35: 0.034291725
B36: 1987.3 | C36: 0.13144 | D36: 0.090592187 | E36: =C36-D36 -> 0.040847813
B37: 1987.4 | C37: 0.1276125 | D37: 0.092301538 | E37: =C37-D37 -> 0.035310962 | H37: Coefficients | I37: Standard Error | J37: t Stat | K37: P-value | L37: Lower 95% | M37: Upper 95% | N37: Lower 95.0% | O37: Upper 95.0%
B38: 1988.1 | C38: 0.1273625 | D38: 0.086266129 | E38: =C38-D38 -> 0.041096371 | G38: Intercept | H38: 0.079059704 | I38: 0.00094791235 | J38: 83.404023 | K38: 7.926274e-143 | L38: 0.077188892 | M38: 0.080930515 | N38: 0.077188892 | O38: 0.080930515
B39: 1988.2 | C39: 0.12695714 | D39: 0.090614286 | E39: =C39-D39 -> 0.036342857 | G39: U.S. Govt. 30-year Treasury | H39: -0.4163371 | I39: 0.013940976 | J39: -29.864272 | K39: 1.3308493e-70 | L39: -0.44385118 | M39: -0.38882301 | N39: -0.44385118 | O39: -0.38882301
B40: 1988.3 | C40: 0.12778571 | D40: 0.091754688 | E40: =C40-D40 -> 0.036031027
B41: 1988.4 | C41: 0.1296875 | D41: 0.089730159 | E41: =C41-D41 -> 0.039957341
B42: 1989.1 | C42: 0.13022857 | D42: 0.09036129 | E42: =C42-D42 -> 0.039867281
B43: 1989.2 | C43: 0.13221429 | D43: 0.086979687 | E43: =C43-D43 -> 0.045234598 | J43: U.S. Govt.
B44: 1989.3 | C44: 0.12375 | D44: 0.081187302 | E44: =C44-D44 -> 0.042562698 | J44: 30-year | K44: Risk
B45: 1989.4 | C45: 0.12828571 | D45: 0.079334375 | E45: =C45-D45 -> 0.048951339 | J45: Treasury | K45: Premium | L45: ROE
B46: 1990.1 | C46: 0.12622857 | D46: 0.08437619 | E46: =C46-D46 -> 0.041852381
B47: 1990.2 | C47: 0.1285 | D47: 0.086479365 | E47: =C47-D47 -> 0.042020635 | G47: Current 30-day average of 30-year U.S. Treasury bond yield [4] | J47: 0.041926667 | K47: =$H$38+($H$39*J47) -> 0.061604077 | L47: =J47+K47 -> 0.10353074
B48: 1990.3 | C48: 0.12537143 | D48: 0.087915873 | E48: =C48-D48 -> 0.037455556 | G48: Blue Chip Near-Term Projected Forecast (Q2 2024 - Q2 2025) [5] | J48: 0.041 | K48: =$H$38+($H$39*J48) -> 0.061989883 | L48: =J48+K48 -> 0.10298988
B49: 1990.4 | C49: 0.12679167 | D49: 0.085578462 | E49: =C49-D49 -> 0.041213205 | G49: Blue Chip Long-Term Projected Forecast (2025-2029) [6] | J49: 0.041 | K49: =$H$38+($H$39*J49) -> 0.061989883 | L49: =J49+K49 -> 0.10298988
B50: 1991.1 | C50: 0.12664167 | D50: 0.082024194 | E50: =C50-D50 -> 0.044617473 | G50: AVERAGE | L50: =AVERAGE(L47:L49) -> 0.10317017
B51: 1991.2 | C51: 0.12671429 | D51: 0.083114063 | E51: =C51-D51 -> 0.043600223
B52: 1991.3 | C52: 0.12492857 | D52: 0.081885938 | E52: =C52-D52 -> 0.043042634 | G52: Notes:
B53: 1991.4 | C53: 0.12421875 | D53: 0.078533846 | E53: =C53-D53 -> 0.045684904 | G53: [1] Source: Regulatory Research Associates, rate cases through January 31, 2024
B54: 1992.1 | C54: 0.12381 | D54: 0.078050794 | E54: =C54-D54 -> 0.045759206 | G54: [2] Source: S&P Capital IQ Pro, quarterly bond yields are the average of each trading day in the quarter
B55: 1992.2 | C55: 0.118275 | D55: 0.07897619 | E55: =C55-D55 -> 0.03929881 | G55: [3] Equals Column [1] − Column [2]
B56: 1992.3 | C56: 0.1203125 | D56: 0.07445625 | E56: =C56-D56 -> 0.04585625 | G56: [4] Source: S&P Capital IQ Pro, 30-day average as of January 31, 2024
B57: 1992.4 | C57: 0.12140667 | D57: 0.075235937 | E57: =C57-D57 -> 0.046170729 | G57: [5] Source: Blue Chip Financial Forecasts, Vol. 43, No. 2, February 1, 2024, at 2
B58: 1993.1 | C58: 0.11835714 | D58: 0.070716129 | E58: =C58-D58 -> 0.047641014 | G58: [6] Source: Blue Chip Financial Forecasts, Vol. 42, No. 12, December 1, 2023, at 14
B59: 1993.2 | C59: 0.11641111 | D59: 0.068584127 | E59: =C59-D59 -> 0.047826984 | G59: [7] See notes [4], [5] & [6]
B60: 1993.3 | C60: 0.11151667 | D60: 0.063154688 | E60: =C60-D60 -> 0.048361979 | G60: ="[8] Equals "&TEXT(H38,"0.0000")&" + ("&TEXT(H39,"0.0000")&" x Column [7])" -> [8] Equals 0.0791 + (-0.4163 x Column [7])
B61: 1993.4 | C61: 0.11041667 | D61: 0.061351563 | E61: =C61-D61 -> 0.049065104 | G61: [9] Equals Column [7] + Column [8]
B62: 1994.1 | C62: 0.11067 | D62: 0.06575873 | E62: =C62-D62 -> 0.04491127
B63: 1994.2 | C63: 0.1113 | D63: 0.073622581 | E63: =C63-D63 -> 0.037677419
B64: 1994.3 | C64: 0.1275 | D64: 0.07589375 | E64: =C64-D64 -> 0.05160625
B65: 1994.4 | C65: 0.11238333 | D65: 0.079633333 | E65: =C65-D65 -> 0.03275
B66: 1995.1 | C66: 0.1196125 | D66: 0.076334375 | E66: =C66-D66 -> 0.043278125
B67: 1995.2 | C67: 0.1131625 | D67: 0.069422222 | E67: =C67-D67 -> 0.043740278
B68: 1995.3 | C68: 0.1137 | D68: 0.067173016 | E68: =C68-D68 -> 0.046526984
B69: 1995.4 | C69: 0.11584286 | D69: 0.062390476 | E69: =C69-D69 -> 0.053452381
B70: 1996.1 | C70: 0.1146 | D70: 0.062916923 | E70: =C70-D70 -> 0.051683077
B71: 1996.2 | C71: 0.11458889 | D71: 0.069215385 | E71: =C71-D71 -> 0.045373504
B72: 1996.3 | C72: 0.107 | D72: 0.069672727 | E72: =C72-D72 -> 0.037327273
B73: 1996.4 | C73: 0.1156 | D73: 0.0662 | E73: =C73-D73 -> 0.0494
B74: 1997.1 | C74: 0.1108 | D74: 0.068153125 | E74: =C74-D74 -> 0.042646875
B75: 1997.2 | C75: 0.11616667 | D75: 0.069369231 | E75: =C75-D75 -> 0.046797436
B76: 1997.3 | C76: 0.12 | D76: 0.065304545 | E76: =C76-D76 -> 0.054695455
B77: 1997.4 | C77: 0.1106 | D77: 0.061478125 | E77: =C77-D77 -> 0.049121875
B78: 1998.1 | C78: 0.113125 | D78: 0.05884375 | E78: =C78-D78 -> 0.05428125
B79: 1998.2 | C79: 0.122 | D79: 0.058490769 | E79: =C79-D79 -> 0.063509231
B80: 1998.3 | C80: 0.1165 | D80: 0.054762121 | E80: =C80-D80 -> 0.061737879
B81: 1998.4 | C81: 0.123 | D81: 0.051071212 | E81: =C81-D81 -> 0.071928788
B82: 1999.1 | C82: 0.104 | D82: 0.053734375 | E82: =C82-D82 -> 0.050265625
B83: 1999.2 | C83: 0.1094 | D83: 0.057987692 | E83: =C83-D83 -> 0.051412308
B84: 1999.3 | C84: 0.1075 | D84: 0.060407576 | E84: =C84-D84 -> 0.047092424
B85: 1999.4 | C85: 0.111 | D85: 0.062559091 | E85: =C85-D85 -> 0.048440909
B86: 2000.1 | C86: 0.112125 | D86: 0.062958462 | E86: =C86-D86 -> 0.049166538
B87: 2000.2 | C87: 0.11 | D87: 0.059787692 | E87: =C87-D87 -> 0.050212308
B88: 2000.3 | C88: 0.1168 | D88: 0.057932308 | E88: =C88-D88 -> 0.058867692
B89: 2000.4 | C89: 0.125 | D89: 0.056907692 | E89: =C89-D89 -> 0.068092308
B90: 2001.1 | C90: 0.11375 | D90: 0.054464615 | E90: =C90-D90 -> 0.059285385
B91: 2001.2 | C91: 0.10875 | D91: 0.057016923 | E91: =C91-D91 -> 0.051733077
B92: 2001.3 | C92: 0.10755714 | D92: 0.055250769 | E92: =C92-D92 -> 0.052306374
B93: 2001.4 | C93: 0.1157 | D93: 0.053019697 | E93: =C93-D93 -> 0.062680303
B94: 2002.1 | C94: 0.1005 | D94: 0.055157813 | E94: =C94-D94 -> 0.045342188
B95: 2002.2 | C95: 0.11405 | D95: 0.056164615 | E95: =C95-D95 -> 0.057885385
B96: 2002.3 | C96: 0.1125 | D96: 0.050868182 | E96: =C96-D96 -> 0.061631818
B97: 2002.4 | C97: 0.11566667 | D97: 0.049322727 | E97: =C97-D97 -> 0.066343939
B98: 2003.1 | C98: 0.11426667 | D98: 0.04851875 | E98: =C98-D98 -> 0.065747917
B99: 2003.2 | C99: 0.111625 | D99: 0.046032308 | E99: =C99-D99 -> 0.065592692
B100: 2003.3 | C100: 0.09875 | D100: 0.051139394 | E100: =C100-D100 -> 0.047610606
B101: 2003.4 | C101: 0.11091667 | D101: 0.05114697 | E101: =C101-D101 -> 0.059769697
B102: 2004.1 | C102: 0.11 | D102: 0.048776923 | E102: =C102-D102 -> 0.061223077
B103: 2004.2 | C103: 0.10638571 | D103: 0.053353846 | E103: =C103-D103 -> 0.053031868
B104: 2004.3 | C104: 0.1075 | D104: 0.051074242 | E104: =C104-D104 -> 0.056425758
... B167: 2020.2 | C167: 0.095166667 | D167: 0.013801538 | E167: =C167-D167 -> 0.081365128
...

Sheet AEB-9 Flotation Cost
A2: FLOTATION COST ADJUSTMENT
C4: [1] | D4: [2] | E4: [3] | F4: [4] | G4: [5] | H4: [6] | I4: [7] | J4: [8] | K4: [9] | L4: [10]
A5: Company | B5: Ticker | C5: Date [i] | D5: Shares Issued (000) | E5: Offering Price | F5: Under-writing Discount [ii] | G5: Offering Expense ($000) | H5: Net Proceeds Per Share | I5: Total Flotation Costs ($000) | J5: Gross Equity Issue Before Costs ($000) | K5: Net Proceeds ($000) | L5: Flotation Cost Percentage
A7: American Electric Power Company, Inc. | B7: AEP | C7: 39904 | D7: 69000 | E7: 24.5 | F7: 0.735 | G7: 400 | H7: =K7/D7 -> 23.759203 | I7: =F7*D7+G7 -> 51115 | J7: =D7*E7 -> 1690500 | K7: =J7-I7 -> 1639385 | L7: =I7/J7 -> 0.030236616
A8: American Electric Power Company, Inc. | B8: AEP | C8: 37679 | D8: 57500 | E8: 20.95 | F8: 0.6285 | G8: 550 | H8: =K8/D8 -> 20.311935 | I8: =F8*D8+G8 -> 36688.75 | J8: =D8*E8 -> 1204625 | K8: =J8-I8 -> 1167936.2 | L8: =I8/J8 -> 0.030456574
A10: Total | I10: =SUM(I7:I8) -> 87803.75 | J10: =SUM(J7:J8) -> 2895125 | K10: =SUM(K7:K8) -> 2807321.2
I11: WEIGHTED AVERAGE FLOTATION COSTS | L11: =I10/J10 -> 0.030328138
A12: Notes:
A13: [i] Offering Completion Date
A14: [ii] Underwriting discount is calculated as the market price minus the offering price when not explicitly given in the prospectus.
A16: ="The flotation cost adjustment is derived by dividing the dividend yield by 1 − F (where F = flotation costs expressed in percentage terms), or by "&TEXT(1-L11,"0.0000")&", and adding that result to the constant growth rate" -> The flotation cost adjustment is derived by dividing the dividend yield by 1 − F (where F = flotation costs expressed in percentage terms), or by 0.9697, and adding that result to the constant growth rate
A17: to determine the cost of equity. Using the formulas shown previously in my testimony, the Constant Growth DCF calculation is modified as follows to accommodate an adjustment for flotation costs:
C23: [11] | D23: [12] | E23: [13] | F23: [14] | G23: [15] | H23: [16] | I23: [17] | J23: [18] | K23: [19] | L23: [20] | M23: [21]
A24: Company | B24: Ticker | C24: Annualized Dividend | D24: Stock Price | E24: Dividend Yield | F24: Expected Dividend Yield | G24: Expected Dividend Yield Adjusted for Flotation Costs | H24: Value Line Earnings Growth | I24: Yahoo! Finance Earnings Growth | J24: Zacks Earnings Growth | K24: Average Earnings Growth | L24: Cost of Equity: Mean Growth Rate | M24: Cost of Equity Adjusted for Flotation Costs
A26: ='AEB-4 CGDCF'!A6 -> ALLETE, Inc. | B26: ='AEB-4 CGDCF'!B6 -> ALE | C26: ='AEB-4 CGDCF'!C6 -> 2.71 | D26: ='AEB-4 CGDCF'!D6 -> 60.598 | E26: =C26/D26 -> 0.044720948 | F26: =IFERROR(E26*(1+0.5*K26),"") -> 0.046375623 | G26: =F26/(1-$L$11) -> 0.047826099 | H26: ='AEB-4 CGDCF'!G6 -> 0.06 | I26: ='AEB-4 CGDCF'!H6 -> 0.081 | J26: ='AEB-4 CGDCF'!I6 -> 0.081 | K26: =AVERAGE(H26:J26) -> 0.074 | L26: =K26+F26 -> 0.12037562 | M26: =K26+G26 -> 0.1218261
A27: ='AEB-4 CGDCF'!A7 -> Alliant Energy Corporation | B27: ='AEB-4 CGDCF'!B7 -> LNT | C27: ='AEB-4 CGDCF'!C7 -> 1.92 | D27: ='AEB-4 CGDCF'!D7 -> 49.881497 | E27: =C27/D27 -> 0.038491227 | F27: =IFERROR(E27*(1+0.5*K27),"") -> 0.039732569 | G27: =F27/(1-$L$11) -> 0.040975273 | H27: ='AEB-4 CGDCF'!G7 -> 0.065 | I27: ='AEB-4 CGDCF'!H7 -> 0.0655 | J27: ='AEB-4 CGDCF'!I7 -> 0.063 | K27: =AVERAGE(H27:J27) -> 0.0645 | L27: =K27+F27 -> 0.10423257 | M27: =K27+G27 -> 0.10547527
A28: ='AEB-4 CGDCF'!A8 -> Ameren Corporation | B28: ='AEB-4 CGDCF'!B8 -> AEE | C28: ='AEB-4 CGDCF'!C8 -> 2.52 | D28: ='AEB-4 CGDCF'!D8 -> 71.507333 | E28: =C28/D28 -> 0.035241141 | F28: =IFERROR(E28*(1+0.5*K28),"") -> 0.036269007 | G28: =F28/(1-$L$11) -> 0.037403382 | H28: ='AEB-4 CGDCF'!G8 -> 0.065 | I28: ='AEB-4 CGDCF'!H8 -> 0.048 | J28: ='AEB-4 CGDCF'!I8 -> 0.062 | K28: =AVERAGE(H28:J28) -> 0.058333333 | L28: =K28+F28 -> 0.094602341 | M28: =K28+G28 -> 0.095736716
A29: ='AEB-4 CGDCF'!A9 -> Duke Energy Corporation | B29: ='AEB-4 CGDCF'!B9 -> DUK | C29: ='AEB-4 CGDCF'!C9 -> 4.1 | D29: ='AEB-4 CGDCF'!D9 -> 96.902667 | E29: =C29/D29 -> 0.042310497 | F29: =IFERROR(E29*(1+0.5*K29),"") -> 0.043569234 | G29: =F29/(1-$L$11) -> 0.044931936 | H29: ='AEB-4 CGDCF'!G9 -> 0.05 | I29: ='AEB-4 CGDCF'!H9 -> 0.0655 | J29: ='AEB-4 CGDCF'!I9 -> 0.063 | K29: =AVERAGE(H29:J29) -> 0.0595 | L29: =K29+F29 -> 0.10306923 | M29: =K29+G29 -> 0.10443194
A30: ='AEB-4 CGDCF'!A10 -> Edison International | B30: ='AEB-4 CGDCF'!B10 -> EIX | C30: ='AEB-4 CGDCF'!C10 -> 3.12 | D30: ='AEB-4 CGDCF'!D10 -> 69.70901 | E30: =C30/D30 -> 0.044757485 | F30: =IFERROR(E30*(1+0.5*K30),"") -> 0.045712312 | G30: =F30/(1-$L$11) -> 0.047142042 | H30: ='AEB-4 CGDCF'!G10 -> 0.045 | I30: ='AEB-4 CGDCF'!H10 -> 0.046 | J30: ='AEB-4 CGDCF'!I10 -> 0.037 | K30: =AVERAGE(H30:J30) -> 0.042666667 | L30: =K30+F30 -> 0.088378978 | M30: =K30+G30 -> 0.089808709
A31: ='AEB-4 CGDCF'!A11 -> Entergy Corporation | B31: ='AEB-4 CGDCF'!B11 -> ETR | C31: ='AEB-4 CGDCF'!C11 -> 4.52 | D31: ='AEB-4 CGDCF'!D11 -> 101.03067 | E31: =C31/D31 -> 0.044738891 | F31: =IFERROR(E31*(1+0.5*K31),"") -> 0.04611834 | G31: =F31/(1-$L$11) -> 0.04756077 | H31: ='AEB-4 CGDCF'!G11 -> 0.005 | I31: ='AEB-4 CGDCF'!H11 -> 0.11 | J31: ='AEB-4 CGDCF'!I11 -> 0.07 | K31: =AVERAGE(H31:J31) -> 0.061666667 | L31: =K31+F31 -> 0.10778501 | M31: =K31+G31 -> 0.10922744
A32: ='AEB-4 CGDCF'!A12 -> Eversource Energy | B32: ='AEB-4 CGDCF'!B12 -> ES | C32: ='AEB-4 CGDCF'!C12 -> 2.7 | D32: ='AEB-4 CGDCF'!D12 -> 58.34 | E32: =C32/D32 -> 0.046280425 | F32: =IFERROR(E32*(1+0.5*K32),"") -> 0.047344875 | G32: =F32/(1-$L$11) -> 0.048825666 | H32: ='AEB-4 CGDCF'!G12 -> 0.06 | I32: ='AEB-4 CGDCF'!H12 -> 0.036 | J32: ='AEB-4 CGDCF'!I12 -> 0.042 | K32: =AVERAGE(H32:J32) -> 0.046 | L32: =K32+F32 -> 0.093344875 | M32: =K32+G32 -> 0.094825666
A33: ='AEB-4 CGDCF'!A13 -> Evergy, Inc. | B33: ='AEB-4 CGDCF'!B13 -> EVRG | C33: ='AEB-4 CGDCF'!C13 -> 2.57 | D33: ='AEB-4 CGDCF'!D13 -> 51.868 | E33: =C33/D33 -> 0.049548855 | F33: =IFERROR(E33*(1+0.5*K33),"") -> 0.050729769 | G33: =F33/(1-$L$11) -> 0.052316429 | H33: ='AEB-4 CGDCF'!G13 -> 0.075 | I33: ='AEB-4 CGDCF'!H13 -> 0.025 | J33: ='AEB-4 CGDCF'!I13 -> 0.043 | K33: =AVERAGE(H33:J33) -> 0.047666667 | L33: =K33+F33 -> 0.098396436 | M33: =K33+G33 -> 0.099983096
A34: ='AEB-4 CGDCF'!A14 -> IDACORP, Inc. | B34: ='AEB-4 CGDCF'!B14 -> IDA | C34: ='AEB-4 CGDCF'!C14 -> 3.32 | D34: ='AEB-4 CGDCF'!D14 -> 95.875333 | E34: =C34/D34 -> 0.034628302 | F34: =IFERROR(E34*(1+0.5*K34),"") -> 0.035367039 | G34: =F34/(1-$L$11) -> 0.036473203 | H34: ='AEB-4 CGDCF'!G14 -> 0.04 | I34: ='AEB-4 CGDCF'!H14 -> 0.044 | J34: ='AEB-4 CGDCF'!I14 -> 0.044 | K34: =AVERAGE(H34:J34) -> 0.042666667 | L34: =K34+F34 -> 0.078033706 | M34: =K34+G34 -> 0.07913987
A35: ='AEB-4 CGDCF'!A15 -> NextEra Energy, Inc. | B35: ='AEB-4 CGDCF'!B15 -> NEE | C35: ='AEB-4 CGDCF'!C15 -> 1.87 | D35: ='AEB-4 CGDCF'!D15 -> 59.981 | E35: =C35/D35 -> 0.031176539 | F35: =IFERROR(E35*(1+0.5*K35),"") -> 0.032502062 | G35: =F35/(1-$L$11) -> 0.033518619 | H35: ='AEB-4 CGDCF'!G15 -> 0.095 | I35: ='AEB-4 CGDCF'!H15 -> 0.0781 | J35: ='AEB-4 CGDCF'!I15 -> 0.082 | K35: =AVERAGE(H35:J35) -> 0.085033333 | L35: =K35+F35 -> 0.1175354 | M35: =K35+G35 -> 0.11855195
A36: ='AEB-4 CGDCF'!A16 -> NorthWestern Corporation | B36: ='AEB-4 CGDCF'!B16 -> NWE | C36: ='AEB-4 CGDCF'!C16 -> 2.56 | D36: ='AEB-4 CGDCF'!D16 -> 49.779 | E36: =C36/D36 -> 0.051427309 | F36: =IFERROR(E36*(1+0.5*K36),"") -> 0.05252271 | G36: =F36/(1-$L$11) -> 0.054165448 | H36: ='AEB-4 CGDCF'!G16 -> 0.035 | I36: ='AEB-4 CGDCF'!H16 -> 0.0408 | J36: ='AEB-4 CGDCF'!I16 -> 0.052 | K36: =AVERAGE(H36:J36) -> 0.0426 | L36: =K36+F36 -> 0.09512271 | M36: =K36+G36 -> 0.096765448
A37: ='AEB-4 CGDCF'!A17 -> OGE Energy Corporation | B37: ='AEB-4 CGDCF'!B17 -> OGE | C37: ='AEB-4 CGDCF'!C17 -> 1.6728 | D37: ='AEB-4 CGDCF'!D17 -> 34.14228 | E37: =C37/D37 -> 0.04899497 | F37: =IFERROR(E37*(1+0.5*K37),"") -> 0.050281088 | G37: =F37/(1-$L$11) -> 0.051853715 | H37: ='AEB-4 CGDCF'!G17 -> 0.065 | I37: ='AEB-4 CGDCF'!H17 -> negative | J37: ='AEB-4 CGDCF'!I17 -> 0.04 | K37: =AVERAGE(H37:J37) -> 0.0525 | L37: =K37+F37 -> 0.10278109 | M37: =K37+G37 -> 0.10435372
... A40: ='AEB-4 CGDCF'!A20 -> Xcel Energy Inc. | B40: ='AEB-4 CGDCF'!B20 -> XEL | C40: ='AEB-4 CGDCF'!C20 -> 2.08 | D40: ='AEB-4 CGDCF'!D20 -> 61.14286 | E40: =C40/D40 -> 0.03401869 | F40: =IFERROR(E40*(1+0.5*K40),"") -> 0.035071568 | G40: =F40/(1-$L$11) -> 0.036168491 | H40: ='AEB-4 CGDCF'!G20 -> 0.06 | I40: ='AEB-4 CGDCF'!H20 -> 0.0657 | J40: ='AEB-4 CGDCF'!I20 -> 0.06 | K40: =AVERAGE(H40:J40) -> 0.0619 | L40: =K40+F40 -> 0.096971568 | M40: =K40+G40 -> 0.098068491
A42: Mean | L42: =AVERAGE(L26:L40) -> 0.099403256 | M42: =AVERAGE(M26:M40) -> 0.10077668
A43: Median | L43: =MEDIAN(L26:L40) -> 0.09811952 | M43: =MEDIAN(M26:M40) -> 0.099561986
A45: Flotation Cost Adjustment (Mean) [22] | M45: =M42-L42 -> 0.0013734271
A46: Flotation Cost Adjustment (Median) [23] | M46: =M43-L43 -> 0.0014424665
A50: Notes:
A51: [1] - [5] Source: American Electric Power Company, Inc. - Prospectus dated February 26, 2003 and Prospectus dated December 22, 2008
A52: [6] Equals [9]/[2]
A53: [7] Equals [5] + ([4] x [2])
A54: [8] Equals [2] x [3]
A55: [9] Equals [8] - [7]
A56: [10] Equals [7] / [8]
A57: [11] Bloomberg Professional
A58: [12] Bloomberg Professional, equals 30-day average as of January 31, 2024
A59: [13] Equals [11] / [12]
A60: [14] Equals [13] x (1 + 0.5 x [19])
A61: [15] Equals [14] / (1 − Flotation Cost)
... A69: [23] Equals [21] (Median) − [20] (Median)

Sheet AEB-10 Reg Risk
B2: COMPARISON OF AEP TEXAS AND PROXY GROUP COMPANIES
B3: RISK ASSESSMENT
G5: [1] | H5: [2] | K5: [3] | M5: [4] | O5: [5] | Q5: [6] | T5: [7] | V5: [8] | X5: [9] | Z5: [10] | AB5: [11]
B6: Proxy Group Company | C6: Operating Subsidiary | D6: Jurisdiction | E6: Service | G6: Electric fuel/gas commodity/purchase power | I6: Test Year | K6: Non-Volumetric Rate Design | T6: Capital Cost Recovery
K7: Revenue Decoupling | M7: Formula-based rates | O7: Straight Fixed-Variable Rate Design | Q7: Non-Volumetric Rate Design | T7: Traditional Generation | V7: Renewables/Non-Traditional Generation | X7: Delivery Infrastructure | Z7: Environmental Compliance | AB7: Capital Cost Recovery
B8: ALLETE, Inc. | C8: ALLETE (Minnesota Power) | D8: Minnesota | E8: Electric | G8: Yes | I8: Fully Forecast | L8: No | N8: No | P8: No | R8: =IF(AND(L8="No",N8="No",P8="No"),"No","Yes") -> No | U8: No | W8: Yes | Y8: No | AA8: No | AC8: =IF(AND(U8="No",W8="No",Y8="No",AA8="No"),"No","Yes") -> Yes
B9: Alliant Energy Corporation | C9: Interstate Power & Light Co. | D9: Iowa | E9: Electric | G9: Yes | I9: Historical | L9: No | N9: No | P9: No | R9: =IF(AND(L9="No",N9="No",P9="No"),"No","Yes") -> No | U9: No | W9: Yes | Y9: No | AA9: Yes | AC9: =IF(AND(U9="No",W9="No",Y9="No",AA9="No"),"No","Yes") -> Yes
C10: Interstate Power & Light Co. | D10: Iowa | E10: Gas | G10: Yes | I10: Historical | L10: No | N10: No | P10: No | R10: =IF(AND(L10="No",N10="No",P10="No"),"No","Yes") -> No | U10: No | W10: No | Y10: No | AA10: No | AC10: =IF(AND(U10="No",W10="No",Y10="No",AA10="No"),"No","Yes") -> No
C11: Wisconsin Power & Light Co. | D11: Wisconsin | E11: Electric | G11: Yes | I11: Fully Forecast | L11: No | N11: No | P11: No | R11: =IF(AND(L11="No",N11="No",P11="No"),"No","Yes") -> No | U11: No | W11: No | Y11: No | AA11: No | AC11: =IF(AND(U11="No",W11="No",Y11="No",AA11="No"),"No","Yes") -> No
C12: Wisconsin Power & Light Co. | D12: Wisconsin | E12: Gas | G12: Yes | I12: Fully Forecast | L12: No | N12: No | P12: No | R12: =IF(AND(L12="No",N12="No",P12="No"),"No","Yes") -> No | U12: No | W12: No | Y12: No | AA12: No | AC12: =IF(AND(U12="No",W12="No",Y12="No",AA12="No"),"No","Yes") -> No
B13: Ameren Corporation | C13: Ameren Illinois Co. | D13: Illinois | E13: Electric | G13: N/A | I13: Historical | L13: Partial | N13: Yes | P13: No | R13: =IF(AND(L13="No",N13="No",P13="No"),"No","Yes") -> Yes | U13: No | W13: Yes | Y13: No | AA13: Yes | AC13: =IF(AND(U13="No",W13="No",Y13="No",AA13="No"),"No","Yes") -> Yes
C14: Ameren Illinois Co. | D14: Illinois | E14: Gas | G14: Yes | I14: Fully Forecast | L14: Partial | N14: No | P14: No | R14: =IF(AND(L14="No",N14="No",P14="No"),"No","Yes") -> Yes | U14: No | W14: No | Y14: Yes | AA14: Yes | AC14: =IF(AND(U14="No",W14="No",Y14="No",AA14="No"),"No","Yes") -> Yes
C15: Union Electric Co. | D15: Missouri | E15: Electric | G15: Yes - Sharing Band | I15: Historical | L15: Partial | N15: No | P15: No | R15: =IF(AND(L15="No",N15="No",P15="No"),"No","Yes") -> Yes | U15: No | W15: Yes | Y15: Yes | AA15: No | AC15: =IF(AND(U15="No",W15="No",Y15="No",AA15="No"),"No","Yes") -> Yes
C16: Union Electric Co. | D16: Missouri | E16: Gas | G16: Yes | I16: Historical | L16: Partial | N16: No | P16: No | R16: =IF(AND(L16="No",N16="No",P16="No"),"No","Yes") -> Yes | U16: No | W16: No | Y16: Yes | AA16: No | AC16: =IF(AND(U16="No",W16="No",Y16="No",AA16="No"),"No","Yes") -> Yes
B17: Duke Energy Corporation | C17: Duke Energy Florida LLC | D17: Florida | E17: Electric | G17: Yes | I17: Fully Forecast | L17: No | N17: No | P17: No | R17: =IF(AND(L17="No",N17="No",P17="No"),"No","Yes") -> No | U17: Yes | W17: Yes | Y17: No | AA17: Yes | AC17: =IF(AND(U17="No",W17="No",Y17="No",AA17="No"),"No","Yes") -> Yes
C18: Duke Energy Indiana LLC | D18: Indiana | E18: Electric | G18: Yes | I18: Historical | L18: Partial | N18: No | P18: No | R18: =IF(AND(L18="No",N18="No",P18="No"),"No","Yes") -> Yes | U18: No | W18: Yes | Y18: Yes | AA18: Yes | AC18: =IF(AND(U18="No",W18="No",Y18="No",AA18="No"),"No","Yes") -> Yes
C19: Duke Energy Kentucky Inc. | D19: Kentucky | E19: Electric | G19: Yes | I19: Fully Forecast | L19: Partial | N19: No | P19: No | R19: =IF(AND(L19="No",N19="No",P19="No"),"No","Yes") -> Yes | U19: No | W19: No | Y19: No | AA19: Yes | AC19: =IF(AND(U19="No",W19="No",Y19="No",AA19="No"),"No","Yes") -> Yes
C20: Duke Energy Kentucky Inc. | D20: Kentucky | E20: Gas | G20: Yes | I20: Fully Forecast | L20: Partial | N20: No | P20: No | R20: =IF(AND(L20="No",N20="No",P20="No"),"No","Yes") -> Yes | U20: No | W20: No | Y20: Yes | AA20: No | AC20: =IF(AND(U20="No",W20="No",Y20="No",AA20="No"),"No","Yes") -> Yes
C21: Duke Energy Carolinas LLC/Duke Energy Progress LLC | D21: North Carolina | E21: Electric | G21: Yes | I21: Historical | L21: No | N21: No | P21: No | R21: =IF(AND(L21="No",N21="No",P21="No"),"No","Yes") -> No | U21: No | W21: Yes | Y21: No | AA21: Yes | AC21: =IF(AND(U21="No",W21="No",Y21="No",AA21="No"),"No","Yes") -> Yes
C22: Piedmont Natural Gas Co. Inc. | D22: North Carolina | E22: Gas | G22: Yes | I22: Historical | L22: Full | N22: No | P22: No | R22: =IF(AND(L22="No",N22="No",P22="No"),"No","Yes") -> Yes | U22: No | W22: No | Y22: Yes | AA22: No | AC22: =IF(AND(U22="No",W22="No",Y22="No",AA22="No"),"No","Yes") -> Yes
C23: Duke Energy Ohio Inc. | D23: Ohio | E23: Electric | G23: N/A | I23: Partially Forecast | L23: Partial | N23: No | P23: No | R23: =IF(AND(L23="No",N23="No",P23="No"),"No","Yes") -> Yes | U23: No | W23: Yes | Y23: Yes | AA23: No | AC23: =IF(AND(U23="No",W23="No",Y23="No",AA23="No"),"No","Yes") -> Yes
C24: Duke Energy Ohio Inc. | D24: Ohio | E24: Gas | G24: Yes | I24: Partially Forecast | L24: No | N24: No | P24: Yes | R24: =IF(AND(L24="No",N24="No",P24="No"),"No","Yes") -> Yes | U24: No | W24: No | Y24: Yes | AA24: Yes | AC24: =IF(AND(U24="No",W24="No",Y24="No",AA24="No"),"No","Yes") -> Yes
C25: Duke Energy Carolinas LLC/Duke Energy Progress LLC | D25: South Carolina | E25: Electric | G25: Yes | I25: Historical | L25: No | N25: No | P25: No | R25: =IF(AND(L25="No",N25="No",P25="No"),"No","Yes") -> No | U25: No | W25: Yes | Y25: No | AA25: Yes | AC25: =IF(AND(U25="No",W25="No",Y25="No",AA25="No"),"No","Yes") -> Yes
C26: Piedmont Natural Gas Co. Inc. | D26: South Carolina | E26: Gas | G26: Yes | I26: Historical | L26: Partial | N26: No | P26: No | R26: =IF(AND(L26="No",N26="No",P26="No"),"No","Yes") -> Yes | U26: No | W26: No | Y26: No | AA26: No | AC26: =IF(AND(U26="No",W26="No",Y26="No",AA26="No"),"No","Yes") -> No
C27: Piedmont Natural Gas Co. Inc. | D27: Tennessee | E27: Gas | G27: Yes | I27: Fully Forecast | L27: Partial | N27: No | P27: No | R27: =IF(AND(L27="No",N27="No",P27="No"),"No","Yes") -> Yes | U27: No | W27: No | Y27: Yes | AA27: No | AC27: =IF(AND(U27="No",W27="No",Y27="No",AA27="No"),"No","Yes") -> Yes
B28: Edison International | C28: Southern California Edison Co. | D28: California | E28: Electric | G28: Yes | I28: Fully Forecast | L28: Full | N28: No | P28: No | R28: =IF(AND(L28="No",N28="No",P28="No"),"No","Yes") -> Yes | U28: No | W28: No | Y28: No | AA28: No | AC28: =IF(AND(U28="No",W28="No",Y28="No",AA28="No"),"No","Yes") -> No
B29: Entergy Corporation | C29: Entergy Arkansas LLC | D29: Arkansas | E29: Electric | G29: Yes | I29: Fully Forecast | L29: Partial | N29: Yes | P29: No | R29: =IF(AND(L29="No",N29="No",P29="No"),"No","Yes") -> Yes | U29: Yes | W29: Yes | Y29: Yes | AA29: No | AC29: =IF(AND(U29="No",W29="No",Y29="No",AA29="No"),"No","Yes") -> Yes
C30: Entergy New Orleans LLC | D30: Louisiana-NOCC | E30: Electric | G30: Yes | I30: Partially Forecast | L30: No | N30: Yes | P30: No | R30: =IF(AND(L30="No",N30="No",P30="No"),"No","Yes") -> Yes | U30: No | W30: Yes | Y30: No | AA30: Yes | AC30: =IF(AND(U30="No",W30="No",Y30="No",AA30="No"),"No","Yes") -> Yes
C31: Entergy New Orleans LLC | D31: Louisiana-NOCC | E31: Gas | G31: Yes | I31: Partially Forecast | L31: No | N31: Yes | P31: No | R31: =IF(AND(L31="No",N31="No",P31="No"),"No","Yes") -> Yes | U31: No | W31: No | Y31: No | AA31: No | AC31: =IF(AND(U31="No",W31="No",Y31="No",AA31="No"),"No","Yes") -> No
C32: Entergy Louisiana LLC | D32: Louisiana | E32: Electric | G32: Yes | I32: Historical | L32: Partial | N32: Yes | P32: No | R32: =IF(AND(L32="No",N32="No",P32="No"),"No","Yes") -> Yes | U32: No | W32: No | Y32: No | AA32: Yes | AC32: =IF(AND(U32="No",W32="No",Y32="No",AA32="No"),"No","Yes") -> Yes
C33: Entergy Louisiana LLC | D33: Louisiana | E33: Gas | G33: Yes | I33: Historical | L33: No | N33: Yes | P33: No | R33: =IF(AND(L33="No",N33="No",P33="No"),"No","Yes") -> Yes | U33: No | W33: No | Y33: Yes | AA33: No | AC33: =IF(AND(U33="No",W33="No",Y33="No",AA33="No"),"No","Yes") -> Yes
C34: Entergy Mississippi LLC | D34: Mississippi | E34: Electric | G34: Yes | I34: Fully Forecast | L34: Partial | N34: Yes | P34: No | R34: =IF(AND(L34="No",N34="No",P34="No"),"No","Yes") -> Yes | U34: No | W34: No | Y34: No | AA34: No | AC34: =IF(AND(U34="No",W34="No",Y34="No",AA34="No"),"No","Yes") -> No
C35: Entergy Texas Inc. | D35: Texas | E35: Electric | G35: Yes | I35: Historical | L35: No | N35: No | P35: No | R35: =IF(AND(L35="No",N35="No",P35="No"),"No","Yes") -> No | U35: Yes | W35: No | Y35: Yes | AA35: No | AC35: =IF(AND(U35="No",W35="No",Y35="No",AA35="No"),"No","Yes") -> Yes
B36: Eversource Energy | C36: Connecticut Light and Power Co. | D36: Connecticut | E36: Electric | G36: N/A | I36: Historical | L36: Full | N36: No | P36: No | R36: =IF(AND(L36="No",N36="No",P36="No"),"No","Yes") -> Yes | U36: No | W36: No | Y36: Yes | AA36: No | AC36: =IF(AND(U36="No",W36="No",Y36="No",AA36="No"),"No","Yes") -> Yes
C37: Yankee Gas Services Co. | D37: Connecticut | E37: Gas | G37: Yes | I37: Historical | L37: Full | N37: No | P37: No | R37: =IF(AND(L37="No",N37="No",P37="No"),"No","Yes") -> Yes | U37: No | W37: No | Y37: Yes | AA37: No | AC37: =IF(AND(U37="No",W37="No",Y37="No",AA37="No"),"No","Yes") -> Yes
C38: Eversource Gas Co. of Massachusetts | D38: Massachusetts | E38: Gas | G38: Yes | I38: Historical | L38: Full | N38: No | P38: No | R38: =IF(AND(L38="No",N38="No",P38="No"),"No","Yes") -> Yes | U38: No | W38: No | Y38: Yes | AA38: Yes | AC38: =IF(AND(U38="No",W38="No",Y38="No",AA38="No"),"No","Yes") -> Yes
C39: NSTAR Electric Co. | D39: Massachusetts | E39: Electric | G39: No | I39: Historical | L39: Full | N39: Yes | P39: No | R39: =IF(AND(L39="No",N39="No",P39="No"),"No","Yes") -> Yes | U39: No | W39: Yes | Y39: Yes | AA39: No | AC39: =IF(AND(U39="No",W39="No",Y39="No",AA39="No"),"No","Yes") -> Yes
C40: NSTAR Gas Co. | D40: Massachusetts | E40: Gas | G40: Yes | I40: Historical | L40: Full | N40: Yes | P40: No | R40: =IF(AND(L40="No",N40="No",P40="No"),"No","Yes") -> Yes | U40: No | W40: No | Y40: Yes | AA40: Yes | AC40: =IF(AND(U40="No",W40="No",Y40="No",AA40="No"),"No","Yes") -> Yes
C41: Public Service Co. of New Hampshire | D41: New Hampshire | E41: Electric | G41: Yes | I41: Historical | L41: Partial | N41: No | P41: No | R41: =IF(AND(L41="No",N41="No",P41="No"),"No","Yes") -> Yes | U41: No | W41: No | Y41: Yes | AA41: No | AC41: =IF(AND(U41="No",W41="No",Y41="No",AA41="No"),"No","Yes") -> Yes
B42: Evergy, Inc. | C42: Evergy Kansas Central Inc | D42: Kansas | E42: Electric | G42: Yes | I42: Historical | L42: Partial | N42: No | P42: No | R42: =IF(AND(L42="No",N42="No",P42="No"),"No","Yes") -> Yes | U42: No | W42: Yes | Y42: No | AA42: Yes | AC42: =IF(AND(U42="No",W42="No",Y42="No",AA42="No"),"No","Yes") -> Yes
C43: Evergy Metro Inc. | D43: Kansas | E43: Electric | G43: Yes | I43: Historical | L43: No | N43: No | P43: No | R43: =IF(AND(L43="No",N43="No",P43="No"),"No","Yes") -> No | U43: No | W43: No | Y43: Yes | AA43: No | AC43: =IF(AND(U43="No",W43="No",Y43="No",AA43="No"),"No","Yes") -> Yes
C44: Evergy Metro Inc | D44: Missouri | E44: Electric | G44: Yes - Sharing Band | I44: Historical | L44: Partial | N44: No | P44: No | R44: =IF(AND(L44="No",N44="No",P44="No"),"No","Yes") -> Yes | U44: No | W44: No | Y44: Yes | AA44: No | AC44: =IF(AND(U44="No",W44="No",Y44="No",AA44="No"),"No","Yes") -> Yes
C45: Evergy Missouri West Inc. | D45: Missouri | E45: Electric | G45: Yes - Sharing Band | I45: Historical | L45: Partial | N45: No | P45: No | R45: =IF(AND(L45="No",N45="No",P45="No"),"No","Yes") -> Yes | U45: No | W45: Yes | Y45: Yes | AA45: No | AC45: =IF(AND(U45="No",W45="No",Y45="No",AA45="No"),"No","Yes") -> Yes
B46: IDACORP, Inc. | C46: Idaho Power Co. | D46: Idaho | E46: Electric | G46: Yes - Sharing Band | I46: Partially Forecast | L46: Full | N46: No | P46: No | R46: =IF(AND(L46="No",N46="No",P46="No"),"No","Yes") -> Yes | U46: No | W46: No | Y46: No | AA46: No | AC46: =IF(AND(U46="No",W46="No",Y46="No",AA46="No"),"No","Yes") -> No
C47: Idaho Power Co. | D47: Oregon | E47: Electric | G47: Yes - Sharing Band | I47: Partially Forecast | L47: No | N47: No | P47: No | R47: =IF(AND(L47="No",N47="No",P47="No"),"No","Yes") -> No | U47: No | W47: No | Y47: No | AA47: No | AC47: =IF(AND(U47="No",W47="No",Y47="No",AA47="No"),"No","Yes") -> No
B48: NextEra Energy, Inc. | C48: Florida Power & Light Co. | D48: Florida | E48: Electric | G48: Yes | I48: Fully Forecast | L48: No | N48: No | P48: No | R48: =IF(AND(L48="No",N48="No",P48="No"),"No","Yes") -> No | U48: Yes | W48: Yes | Y48: No | AA48: Yes | AC48: =IF(AND(U48="No",W48="No",Y48="No",AA48="No"),"No","Yes") -> Yes
C49: Pivotal Utility Holdings Inc. | D49: Florida | E49: Gas | G49: Yes | I49: Fully Forecast | L49: No | N49: No | P49: No | R49: =IF(AND(L49="No",N49="No",P49="No"),"No","Yes") -> No | U49: No | W49: No | Y49: Yes | AA49: Yes | AC49: =IF(AND(U49="No",W49="No",Y49="No",AA49="No"),"No","Yes") -> Yes
C50: Lone Star Transmission LLC | D50: Texas | E50: Electric | G50: N/A | I50: Historical | L50: No | N50: No | P50: No | R50: =IF(AND(L50="No",N50="No",P50="No"),"No","Yes") -> No | U50: No | W50: No | Y50: Yes | AA50: No | AC50: =IF(AND(U50="No",W50="No",Y50="No",AA50="No"),"No","Yes") -> Yes
B51: NorthWestern Corporation | C51: NorthWestern Corporation | D51: Montana | E51: Electric | G51: Yes - Sharing Band | I51: Historical | L51: No | N51: No | P51: No | R51: =IF(AND(L51="No",N51="No",P51="No"),"No","Yes") -> No | U51: No | W51: No | Y51: No | AA51: No | AC51: =IF(AND(U51="No",W51="No",Y51="No",AA51="No"),"No","Yes") -> No
C52: NorthWestern Corporation | D52: Montana | E52: Gas | G52: Yes | I52: Historical | L52: No | N52: No | P52: No | R52: =IF(AND(L52="No",N52="No",P52="No"),"No","Yes") -> No | U52: No | W52: No | Y52: No | AA52: No | AC52: =IF(AND(U52="No",W52="No",Y52="No",AA52="No"),"No","Yes") -> No
C53: NorthWestern Corporation | D53: Nebraska | E53: Gas | G53: Yes | I53: Historical | L53: No | N53: No | P53: No | R53: =IF(AND(L53="No",N53="No",P53="No"),"No","Yes") -> No | U53: No | W53: No | Y53: No | AA53: No | AC53: =IF(AND(U53="No",W53="No",Y53="No",AA53="No"),"No","Yes") -> No
C54: NorthWestern Corporation | D54: South Dakota | E54: Electric | G54: Yes | I54: Historical | L54: No | N54: No | P54: No | R54: =IF(AND(L54="No",N54="No",P54="No"),"No","Yes") -> No | U54: No | W54: No | Y54: No | AA54: No | AC54: =IF(AND(U54="No",W54="No",Y54="No",AA54="No"),"No","Yes") -> No
C55: NorthWestern Corporation | D55: South Dakota | E55: Gas | G55: Yes | I55: Historical | L55: No | N55: No | P55: No | R55: =IF(AND(L55="No",N55="No",P55="No"),"No","Yes") -> No | U55: No | W55: No | Y55: No | AA55: No | AC55: =IF(AND(U55="No",W55="No",Y55="No",AA55="No"),"No","Yes") -> No
B56: OGE Energy Corp. | C56: Oklahoma Gas and Electric Company | D56: Arkansas | E56: Electric | G56: Yes | I56: Historical | L56: Partial | N56: Yes | P56: No | R56: =IF(AND(L56="No",N56="No",P56="No"),"No","Yes") -> Yes | U56: Yes | W56: Yes | Y56: Yes | AA56: Yes | AC56: =IF(AND(U56="No",W56="No",Y56="No",AA56="No"),"No","Yes") -> Yes
C57: Oklahoma Gas and Electric Company | D57: Oklahoma | E57: Electric | G57: Yes | I57: Historical | L57: Partial | N57: No | P57: No | R57: =IF(AND(L57="No",N57="No",P57="No"),"No","Yes") -> Yes | U57: No | W57: No | Y57: Yes | AA57: Yes | AC57: =IF(AND(U57="No",W57="No",Y57="No",AA57="No"),"No","Yes") -> Yes
B58: Pinnacle West Capital Corporation | C58: PNW | D58: Arizona | E58: Electric | G58: Yes | I58: Historical | L58: Partial | N58: Yes | P58: No | R58: =IF(AND(L58="No",N58="No",P58="No"),"No","Yes") -> Yes | U58: No | W58: Yes | Y58: No | AA58: Yes | AC58: =IF(AND(U58="No",W58="No",Y58="No",AA58="No"),"No","Yes") -> Yes
B59: Portland General Electric Company | C59: Portland General Electric Co. | D59: Oregon | E59: Electric | G59: Yes - Sharing Band | I59: Fully Forecast | L59: No | N59: No | P59: No | R59: =IF(AND(L59="No",N59="No",P59="No"),"No","Yes") -> No | U59: Yes | W59: Yes | Y59: No | AA59: Yes | AC59: =IF(AND(U59="No",W59="No",Y59="No",AA59="No"),"No","Yes") -> Yes
B60: Xcel Energy Inc. | C60: Public Service Co. of Colorado | D60: Colorado | E60: Electric | G60: Yes | I60: Historical | L60: Partial | N60: No | P60: No | R60: =IF(AND(L60="No",N60="No",P60="No"),"No","Yes") -> Yes | U60: No | W60: Yes | Y60: No | AA60: No | AC60: =IF(AND(U60="No",W60="No",Y60="No",AA60="No"),"No","Yes") -> Yes
C61: Public Service Co. of Colorado | D61: Colorado | E61: Gas | G61: Yes | I61: Historical | L61: Partial | N61: No | P61: No | R61: =IF(AND(L61="No",N61="No",P61="No"),"No","Yes") -> Yes | U61: No | W61: No | Y61: Yes | AA61: No | AC61: =IF(AND(U61="No",W61="No",Y61="No",AA61="No"),"No","Yes") -> Yes
C62: Northern States Power Co.-Minnesota | D62: Minnesota | E62: Electric | G62: Yes | I62: Fully Forecast | L62: Partial | N62: Yes | P62: No | R62: =IF(AND(L62="No",N62="No",P62="No"),"No","Yes") -> Yes | U62: No | W62: Yes | Y62: No | AA62: Yes | AC62: =IF(AND(U62="No",W62="No",Y62="No",AA62="No"),"No","Yes") -> Yes
C63: Northern States Power Co.-Minnesota | D63: Minnesota | E63: Gas | G63: Yes | I63: Fully Forecast | L63: No | N63: No | P63: No | R63: =IF(AND(L63="No",N63="No",P63="No"),"No","Yes") -> No | U63: No | W63: No | Y63: Yes | AA63: No | AC63: =IF(AND(U63="No",W63="No",Y63="No",AA63="No"),"No","Yes") -> Yes
C64: Southwestern Public Service Co. | D64: New Mexico | E64: Electric | G64: Yes | I64: Historical | L64: No | N64: No | P64: No | R64: =IF(AND(L64="No",N64="No",P64="No"),"No","Yes") -> No | U64: No | W64: Yes | Y64: No | AA64: No | AC64: =IF(AND(U64="No",W64="No",Y64="No",AA64="No"),"No","Yes") -> Yes
C65: Northern States Power Co.-Minnesota | D65: North Dakota | E65: Electric | G65: Yes | I65: Fully Forecast | L65: No | N65: No | P65: No | R65: =IF(AND(L65="No",N65="No",P65="No"),"No","Yes") -> No | U65: No | W65: Yes | Y65: Yes | AA65: No | AC65: =IF(AND(U65="No",W65="No",Y65="No",AA65="No"),"No","Yes") -> Yes
C66: Northern States Power Co.-Minnesota | D66: North Dakota | E66: Gas | G66: Yes | I66: Fully Forecast | L66: No | N66: No | P66: Yes | R66: =IF(AND(L66="No",N66="No",P66="No"),"No","Yes") -> Yes | U66: No | W66: No | Y66: No | AA66: No | AC66: =IF(AND(U66="No",W66="No",Y66="No",AA66="No"),"No","Yes") -> No
C67: Northern States Power Co.-Minnesota | D67: South Dakota | E67: Electric | G67: Yes | I67: Historical | L67: Partial | N67: No | P67: No | R67: =IF(AND(L67="No",N67="No",P67="No"),"No","Yes") -> Yes | U67: Yes | W67: No | Y67: Yes | AA67: Yes | AC67: =IF(AND(U67="No",W67="No",Y67="No",AA67="No"),"No","Yes") -> Yes
C68: Southwestern Public Service Co. | D68: Texas | E68: Electric | G68: Yes | I68: Historical | L68: No | N68: No | P68: No | R68: =IF(AND(L68="No",N68="No",P68="No"),"No","Yes") -> No | U68: No | W68: No | Y68: No | AA68: No | AC68: =IF(AND(U68="No",W68="No",Y68="No",AA68="No"),"No","Yes") -> No
C69: Northern States Power Co.-Wisconsin | D69: Wisconsin | E69: Electric | G69: Yes | I69: Fully Forecast | L69: No | N69: No | P69: No | R69: =IF(AND(L69="No",N69="No",P69="No"),"No","Yes") -> No | U69: No | W69: No | Y69: No | AA69: No | AC69: =IF(AND(U69="No",W69="No",Y69="No",AA69="No"),"No","Yes") -> No
C70: Northern States Power Co.-Wisconsin | D70: Wisconsin | E70: Gas | G70: Yes | I70: Fully Forecast | L70: No | N70: No | P70: No | R70: =IF(AND(L70="No",N70="No",P70="No"),"No","Yes") -> No | U70: No | W70: No | Y70: No | AA70: No | AC70: =IF(AND(U70="No",W70="No",Y70="No",AA70="No"),"No","Yes") -> No
B73: Proxy Group Average | F73: Yes | G73: =COUNTIF($G$8:$G$70,F73) -> 51 | H73: Fully Forecast | I73: =COUNTIF($I$8:$I$70,"Fully Forecast") -> 20 | Q73: Yes | R73: =COUNTIF($R$8:$R$70,"Yes") -> 37 | AB73: Yes | AC73: =COUNTIF($AC$8:$AC$70,"Yes") -> 45
F74: No | G74: =COUNTIF($G$8:$G$70,F74) -> 1 | H74: Partially Forecast | I74: =COUNTIF($I$8:$I$70,"Partially Forecast") -> 6 | Q74: No | R74: =COUNTIF($R$8:$R$70,"No") -> 26 | AB74: No | AC74: =COUNTIF($AC$8:$AC$70,"No") -> 18
E75: Yes - Sharing Band | G75: =COUNTIF($G$8:$G$70,E75) -> 7 | H75: Historical | I75: =COUNTIF($I$8:$I$70,"Historical") -> 37
F76: N/A | G76: =COUNTIF($G$8:$G$70,F76) -> 4
F78: % Yes and N/A | G78: =(G73+G76)/(G73+G74+G75+G76) -> 0.87301587 | H78: Forecast | I78: =(I73+I74)/(I73+I74+I75) -> 0.41269841 | Q78: % Yes | R78: =R73/(R73+R74) -> 0.58730159 | AB78: % Yes | AC78: =AC73/(AC73+AC74) -> 0.71428571
B80: AEP Texas [12] | D80: Texas | G80: N/A | I80: Historical | AC80: =IF(AND(U80="No",W80="No",Y80="No",AA80="No"),"No","Yes") -> Yes
B83: Notes:
B84: [1] S&P Global Market Intelligence, Regulatory Focus: Adjustment Clauses, dated July 18, 2022. Operating subsidiaries not covered in this report were excluded from this exhibit.
B85: [2] Regulatory Research Associates, effective as of May 31, 2023
B86: [3] S&P Global Market Intelligence, Regulatory Focus: Adjustment Clauses, dated July 18, 2022.
B87: [4] Company Form 10-K, Company Tariffs, S&P Capital IQ Pro
B88: [5] S&P Global Market Intelligence, Regulatory Focus: Adjustment Clauses, dated July 18, 2022.
B89: [6] Equals IF( AND( [3]=No, [4]=No, [5]=No), No, Yes)
B90: [7] S&P Global Market Intelligence, Regulatory Focus: Adjustment Clauses, dated July 18, 2022.
B91: [8] S&P Global Market Intelligence, Regulatory Focus: Adjustment Clauses, dated July 18, 2022.
B92: [9] S&P Global Market Intelligence, Regulatory Focus: Adjustment Clauses, dated July 18, 2022.
B93: [10] S&P Global Market Intelligence, Regulatory Focus: Adjustment Clauses, dated July 18, 2022.
B94: [11] Equals IF( AND( [7]=No, [8]=No, [9]=No, [10]=No), No, Yes)
B95: [12] Company Provided Data.

Sheet AEB-11 RegEnv
B2: COMPARISON OF AEP TEXAS AND PROXY GROUP COMPANIES
B3: RRA JURISDICTIONAL RANKINGS
D5: [1] | E5: [2] | H5: Ranking Legend
B6: Ultimate Parent Company | D6: RRA
C7: Jurisdiction | D7: Rank | E7: Numeric Rank | H7: Description | I7: Value
H8: Below Average/3 | I8: 9
B9: ALLETE, Inc. | C9: Minnesota | D9: Average/2 | E9: =IFERROR(INDEX($I$8:$I$16,MATCH(D9,$H$8:$H$16,0)),"") -> 5 | H9: Below Average/2 | I9: 8
B10: Alliant Energy Corporation | C10: Iowa | D10: Above Average/3 | E10: =IFERROR(INDEX($I$8:$I$16,MATCH(D10,$H$8:$H$16,0)),"") -> 3 | H10: Below Average/1 | I10: 7
C11: Wisconsin | D11: Above Average/3 | E11: =IFERROR(INDEX($I$8:$I$16,MATCH(D11,$H$8:$H$16,0)),"") -> 3 | H11: Average/3 | I11: 6
B12: Ameren Corporation | C12: Illinois | D12: Average/2 | E12: =IFERROR(INDEX($I$8:$I$16,MATCH(D12,$H$8:$H$16,0)),"") -> 5 | H12: Average/2 | I12: 5
C13: Missouri | D13: Average/3 | E13: =IFERROR(INDEX($I$8:$I$16,MATCH(D13,$H$8:$H$16,0)),"") -> 6 | H13: Average/1 | I13: 4
B14: Duke Energy Corporation | C14: Florida | D14: Above Average/2 | E14: =IFERROR(INDEX($I$8:$I$16,MATCH(D14,$H$8:$H$16,0)),"") -> 2 | H14: Above Average/3 | I14: 3
C15: Indiana | D15: Average/1 | E15: =IFERROR(INDEX($I$8:$I$16,MATCH(D15,$H$8:$H$16,0)),"") -> 4 | H15: Above Average/2 | I15: 2
C16: Kentucky | D16: Average/2 | E16: =IFERROR(INDEX($I$8:$I$16,MATCH(D16,$H$8:$H$16,0)),"") -> 5 | H16: Above Average/1 | I16: 1
C17: North Carolina | D17: Above Average/3 | E17: =IFERROR(INDEX($I$8:$I$16,MATCH(D17,$H$8:$H$16,0)),"") -> 3
C18: Ohio | D18: Average/2 | E18: =IFERROR(INDEX($I$8:$I$16,MATCH(D18,$H$8:$H$16,0)),"") -> 5
C19: South Carolina | D19: Average/3 | E19: =IFERROR(INDEX($I$8:$I$16,MATCH(D19,$H$8:$H$16,0)),"") -> 6
C20: Tennessee | D20: Above Average/3 | E20: =IFERROR(INDEX($I$8:$I$16,MATCH(D20,$H$8:$H$16,0)),"") -> 3
B21: Edison International | C21: California | D21: Average/1 | E21: =IFERROR(INDEX($I$8:$I$16,MATCH(D21,$H$8:$H$16,0)),"") -> 4
B22: Entergy Corporation | C22: Arkansas | D22: Average/1 | E22: =IFERROR(INDEX($I$8:$I$16,MATCH(D22,$H$8:$H$16,0)),"") -> 4
C23: Louisiana (NOCC) | D23: Average/3 | E23: =IFERROR(INDEX($I$8:$I$16,MATCH(D23,$H$8:$H$16,0)),"") -> 6
C24: Louisiana | D24: Average/2 | E24: =IFERROR(INDEX($I$8:$I$16,MATCH(D24,$H$8:$H$16,0)),"") -> 5
C25: Mississippi | D25: Above Average/3 | E25: =IFERROR(INDEX($I$8:$I$16,MATCH(D25,$H$8:$H$16,0)),"") -> 3
C26: Texas (PUC) | D26: Average/3 | E26: =IFERROR(INDEX($I$8:$I$16,MATCH(D26,$H$8:$H$16,0)),"") -> 6
B27: Eversource Energy | C27: Connecticut | D27: Below Average/2 | E27: =IFERROR(INDEX($I$8:$I$16,MATCH(D27,$H$8:$H$16,0)),"") -> 8
C28: Massachusetts | D28: Average/2 | E28: =IFERROR(INDEX($I$8:$I$16,MATCH(D28,$H$8:$H$16,0)),"") -> 5
C29: New Hampshire | D29: Average/2 | E29: =IFERROR(INDEX($I$8:$I$16,MATCH(D29,$H$8:$H$16,0)),"") -> 5
B30: Evergy, Inc. | C30: Kansas | D30: Below Average/1 | E30: =IFERROR(INDEX($I$8:$I$16,MATCH(D30,$H$8:$H$16,0)),"") -> 7
C31: Missouri | D31: Average/3 | E31: =IFERROR(INDEX($I$8:$I$16,MATCH(D31,$H$8:$H$16,0)),"") -> 6
B32: IDACORP, Inc. | C32: Idaho | D32: Average/2 | E32: =IFERROR(INDEX($I$8:$I$16,MATCH(D32,$H$8:$H$16,0)),"") -> 5
C33: Oregon | D33: Average/2 | E33: =IFERROR(INDEX($I$8:$I$16,MATCH(D33,$H$8:$H$16,0)),"") -> 5
B34: NextEra Energy, Inc. | C34: Florida | D34: Above Average/2 | E34: =IFERROR(INDEX($I$8:$I$16,MATCH(D34,$H$8:$H$16,0)),"") -> 2
C35: Texas (PUC) | D35: Average/3 | E35: =IFERROR(INDEX($I$8:$I$16,MATCH(D35,$H$8:$H$16,0)),"") -> 6
B36: NorthWestern Corporation | C36: Montana | D36: Below Average/1 | E36: =IFERROR(INDEX($I$8:$I$16,MATCH(D36,$H$8:$H$16,0)),"") -> 7
C37: Nebraska | D37: Average/1 | E37: =IFERROR(INDEX($I$8:$I$16,MATCH(D37,$H$8:$H$16,0)),"") -> 4
C38: South Dakota | D38: Average/2 | E38: =IFERROR(INDEX($I$8:$I$16,MATCH(D38,$H$8:$H$16,0)),"") -> 5
B39: OGE Energy Corp. | C39: Arkansas | D39: Average/1 | E39: =IFERROR(INDEX($I$8:$I$16,MATCH(D39,$H$8:$H$16,0)),"") -> 4
C40: Oklahoma | D40: Average/3 | E40: =IFERROR(INDEX($I$8:$I$16,MATCH(D40,$H$8:$H$16,0)),"") -> 6
B41: Pinnacle West Capital Corporation | C41: Arizona | D41: Below Average/3 | E41: =IFERROR(INDEX($I$8:$I$16,MATCH(D41,$H$8:$H$16,0)),"") -> 9
B42: Portland General Electric Company | C42: Oregon | D42: Average/2 | E42: =IFERROR(INDEX($I$8:$I$16,MATCH(D42,$H$8:$H$16,0)),"") -> 5
B43: Xcel Energy Inc. | C43: Colorado | D43: Average/1 | E43: =IFERROR(INDEX($I$8:$I$16,MATCH(D43,$H$8:$H$16,0)),"") -> 4
C44: Minnesota | D44: Average/2 | E44: =IFERROR(INDEX($I$8:$I$16,MATCH(D44,$H$8:$H$16,0)),"") -> 5
C45: New Mexico | D45: Below Average/1 | E45: =IFERROR(INDEX($I$8:$I$16,MATCH(D45,$H$8:$H$16,0)),"") -> 7
C46: North Dakota | D46: Average/1 | E46: =IFERROR(INDEX($I$8:$I$16,MATCH(D46,$H$8:$H$16,0)),"") -> 4
C47: South Dakota | D47: Average/2 | E47: =IFERROR(INDEX($I$8:$I$16,MATCH(D47,$H$8:$H$16,0)),"") -> 5
C48: Texas (PUC) | D48: Average/3 | E48: =IFERROR(INDEX($I$8:$I$16,MATCH(D48,$H$8:$H$16,0)),"") -> 6
C49: Wisconsin | D49: Above Average/3 | E49: =IFERROR(INDEX($I$8:$I$16,MATCH(D49,$H$8:$H$16,0)),"") -> 3
B51: Proxy Group Average | D51: Average/1 to Average/2 | E51: =AVERAGE(E9:E49) -> 4.902439
B53: AEP Texas | C53: Texas (PUC) | D53: =D26 -> Average/3 | E53: =E35 -> 6
B55: Notes
B56: [1] Source: State Regulatory Evaluations, Regulatory Research Associates, as of December 4, 2023.
B57: [2] AA/1= 1, AA/2= 2, AA/3= 3, A/1= 4, A/2= 5, A/3=6, BA/1= 7, BA/2= 8, BA/3= 9

Sheet AEB-12 S&P Cred Sup
B2: COMPARISON OF AEP TEXAS AND PROXY GROUP COMPANIES
B3: S&P JURISDICTIONAL RANKINGS
D5: [1] | E5: [2] | H5: Ranking Legend
B6: Ultimate Parent Company | D6: S&P
C7: Jurisdiction | D7: Rank | E7: Numeric Rank | H7: Description | I7: Value
H8: Most credit supportive | I8: 1
B9: ALLETE, Inc. | C9: Minnesota | D9: Highly credit supportive | E9: =IFERROR(INDEX($I$8:$I$12,MATCH(D9,$H$8:$H$12,0)),"") -> 2 | H9: Highly credit supportive | I9: 2
B10: Alliant Energy Corporation | C10: Iowa | D10: Most credit supportive | E10: =IFERROR(INDEX($I$8:$I$12,MATCH(D10,$H$8:$H$12,0)),"") -> 1 | H10: Very credit supportive | I10: 3
C11: Wisconsin | D11: Most credit supportive | E11: =IFERROR(INDEX($I$8:$I$12,MATCH(D11,$H$8:$H$12,0)),"") -> 1 | H11: More credit supportive | I11: 4
B12: Ameren Corporation | C12: Illinois | D12: Very credit supportive | E12: =IFERROR(INDEX($I$8:$I$12,MATCH(D12,$H$8:$H$12,0)),"") -> 3 | H12: Credit supportive | I12: 5
C13: Missouri | D13: Very credit supportive | E13: =IFERROR(INDEX($I$8:$I$12,MATCH(D13,$H$8:$H$12,0)),"") -> 3
B14: Duke Energy Corporation | C14: Florida | D14: Most credit supportive | E14: =IFERROR(INDEX($I$8:$I$12,MATCH(D14,$H$8:$H$12,0)),"") -> 1
C15: Indiana | D15: Highly credit supportive | E15: =IFERROR(INDEX($I$8:$I$12,MATCH(D15,$H$8:$H$12,0)),"") -> 2
C16: Kentucky | D16: Most credit supportive | E16: =IFERROR(INDEX($I$8:$I$12,MATCH(D16,$H$8:$H$12,0)),"") -> 1
C17: North Carolina | D17: Highly credit supportive | E17: =IFERROR(INDEX($I$8:$I$12,MATCH(D17,$H$8:$H$12,0)),"") -> 2
C18: Ohio | D18: Very credit supportive | E18: =IFERROR(INDEX($I$8:$I$12,MATCH(D18,$H$8:$H$12,0)),"") -> 3
C19: South Carolina | D19: More credit supportive | E19: =IFERROR(INDEX($I$8:$I$12,MATCH(D19,$H$8:$H$12,0)),"") -> 4
C20: Tennessee | D20: Highly credit supportive | E20: =IFERROR(INDEX($I$8:$I$12,MATCH(D20,$H$8:$H$12,0)),"") -> 2
B21: Edison International | C21: California | D21: More credit supportive | E21: =IFERROR(INDEX($I$8:$I$12,MATCH(D21,$H$8:$H$12,0)),"") -> 4
B22: Entergy Corporation | C22: Arkansas | D22: Highly credit supportive | E22: =IFERROR(INDEX($I$8:$I$12,MATCH(D22,$H$8:$H$12,0)),"") -> 2
C23: Louisiana (NOCC) | D23: Highly credit supportive | E23: =IFERROR(INDEX($I$8:$I$12,MATCH(D23,$H$8:$H$12,0)),"") -> 2
C24: Louisiana | D24: Highly credit supportive | E24: =IFERROR(INDEX($I$8:$I$12,MATCH(D24,$H$8:$H$12,0)),"") -> 2
C25: Mississippi | D25: Very credit supportive | E25: =IFERROR(INDEX($I$8:$I$12,MATCH(D25,$H$8:$H$12,0)),"") -> 3
C26: Texas (PUC) | D26: Very credit supportive | E26: =IFERROR(INDEX($I$8:$I$12,MATCH(D26,$H$8:$H$12,0)),"") -> 3
B27: Eversource Energy | C27: Connecticut | D27: More credit supportive | E27: =IFERROR(INDEX($I$8:$I$12,MATCH(D27,$H$8:$H$12,0)),"") -> 4
C28: Massachusetts | D28: Highly credit supportive | E28: =IFERROR(INDEX($I$8:$I$12,MATCH(D28,$H$8:$H$12,0)),"") -> 2
C29: New Hampshire | D29: Highly credit supportive | E29: =IFERROR(INDEX($I$8:$I$12,MATCH(D29,$H$8:$H$12,0)),"") -> 2
B30: Evergy, Inc. | C30: Kansas | D30: Highly credit supportive | E30: =IFERROR(INDEX($I$8:$I$12,MATCH(D30,$H$8:$H$12,0)),"") -> 2
C31: Missouri | D31: Very credit supportive | E31: =IFERROR(INDEX($I$8:$I$12,MATCH(D31,$H$8:$H$12,0)),"") -> 3
B32: IDACORP, Inc. | C32: Idaho | D32: Very credit supportive | E32: =IFERROR(INDEX($I$8:$I$12,MATCH(D32,$H$8:$H$12,0)),"") -> 3
C33: Oregon | D33: More credit supportive | E33: =IFERROR(INDEX($I$8:$I$12,MATCH(D33,$H$8:$H$12,0)),"") -> 4
B34: NextEra Energy, Inc. | C34: Florida | D34: Most credit supportive | E34: =IFERROR(INDEX($I$8:$I$12,MATCH(D34,$H$8:$H$12,0)),"") -> 1
C35: Texas (PUC) | D35: Very credit supportive | E35: =IFERROR(INDEX($I$8:$I$12,MATCH(D35,$H$8:$H$12,0)),"") -> 3
B36: NorthWestern Corporation | C36: Montana | D36: More credit supportive | E36: =IFERROR(INDEX($I$8:$I$12,MATCH(D36,$H$8:$H$12,0)),"") -> 4
C37: Nebraska | D37: Very credit supportive | E37: =IFERROR(INDEX($I$8:$I$12,MATCH(D37,$H$8:$H$12,0)),"") -> 3
C38: South Dakota | D38: Very credit supportive | E38: =IFERROR(INDEX($I$8:$I$12,MATCH(D38,$H$8:$H$12,0)),"") -> 3
B39: OGE Energy Corp. | C39: Arkansas | D39: Highly credit supportive | E39: =IFERROR(INDEX($I$8:$I$12,MATCH(D39,$H$8:$H$12,0)),"") -> 2
C40: Oklahoma | D40: Very credit supportive | E40: =IFERROR(INDEX($I$8:$I$12,MATCH(D40,$H$8:$H$12,0)),"") -> 3
B41: Pinnacle West Capital Corporation | C41: Arizona | D41: More credit supportive | E41: =IFERROR(INDEX($I$8:$I$12,MATCH(D41,$H$8:$H$12,0)),"") -> 4
B42: Portland General Electric Company | C42: Oregon | D42: More credit supportive | E42: =IFERROR(INDEX($I$8:$I$12,MATCH(D42,$H$8:$H$12,0)),"") -> 4
B43: Xcel Energy Inc. | C43: Colorado | D43: Very credit supportive | E43: =IFERROR(INDEX($I$8:$I$12,MATCH(D43,$H$8:$H$12,0)),"") -> 3
C44: Minnesota | D44: Highly credit supportive | E44: =IFERROR(INDEX($I$8:$I$12,MATCH(D44,$H$8:$H$12,0)),"") -> 2
C45: New Mexico | D45: Credit supportive | E45: =IFERROR(INDEX($I$8:$I$12,MATCH(D45,$H$8:$H$12,0)),"") -> 5
C46: North Dakota | D46: Highly credit supportive | E46: =IFERROR(INDEX($I$8:$I$12,MATCH(D46,$H$8:$H$12,0)),"") -> 2
C47: South Dakota | D47: Very credit supportive | E47: =IFERROR(INDEX($I$8:$I$12,MATCH(D47,$H$8:$H$12,0)),"") -> 3
C48: Texas (PUC) | D48: Very credit supportive | E48: =IFERROR(INDEX($I$8:$I$12,MATCH(D48,$H$8:$H$12,0)),"") -> 3
C49: Wisconsin | D49: Most credit supportive | E49: =IFERROR(INDEX($I$8:$I$12,MATCH(D49,$H$8:$H$12,0)),"") -> 1
B51: Proxy Group Average | D51: Very Credit Supportive to Highly Credit Supportive | E51: =AVERAGE(E9:E49) -> 2.6097561
B53: AEP Texas | C53: Texas (PUC) | D53: =D26 -> Very credit supportive | E53: =E26 -> 3
B55: Notes
B56: [1] S&P Global Ratings, "North American Utility Regulatory Jurisdictions Update: No Revised Assessments, But Notable Developments," November 10, 2023.
B57: [2] Most Credit Supp. = 1, Highly Credit Supp. = 2, Very Credit Supp. = 3, More Credit Supp. = 4, Credit Supp. = 5

Sheet AEB-13 Capital Structure
B4: CAPITAL STRUCTURE ANALYSIS
D6: Most Recent 8 Quarters (2021Q4 - 2023Q3)
D7: Common | E7: Long-Term | F7: Preferred
D8: Equity | E8: Debt | F8: Equity | G8: Total
B9: Proxy Group Company | C9: Ticker | D9: Ratio | E9: Ratio | F9: Ratio | G9: Capitalization
B10: ALLETE, Inc. | C10: ALE | D10: 0.59403916 | E10: 0.40596084 | F10: 0 | G10: =SUM(D10:F10) -> 1
B11: Alliant Energy Corporation | C11: LNT | D11: 0.5213728 | E11: 0.4786272 | F11: 0 | G11: =SUM(D11:F11) -> 1
B12: Ameren Corporation | C12: AEE | D12: 0.53225463 | E12: 0.46214914 | F12: 0.005596231 | G12: =SUM(D12:F12) -> 1
B13: Duke Energy Corporation | C13: DUK | D13: 0.52691442 | E13: 0.47308558 | F13: 0 | G13: =SUM(D13:F13) -> 1
B14: Edison International | C14: EIX | D14: 0.41040568 | E14: 0.54618637 | F14: 0.043407948 | G14: =SUM(D14:F14) -> 1
B15: Entergy Corporation | C15: ETR | D15: 0.47749546 | E15: 0.5215211 | F15: 0.00098344054 | G15: =SUM(D15:F15) -> 1
B16: Eversource Energy | C16: ES | D16: 0.54852302 | E16: 0.4447148 | F16: 0.0067621754 | G16: =SUM(D16:F16) -> 1
B17: Evergy, Inc. | C17: EVRG | D17: 0.6114886 | E17: 0.3885114 | F17: 0 | G17: =SUM(D17:F17) -> 1
B18: IDACORP, Inc. | C18: IDA | D18: 0.52953939 | E18: 0.47046061 | F18: 0 | G18: =SUM(D18:F18) -> 1
B19: NextEra Energy, Inc. | C19: NEE | D19: 0.60712009 | E19: 0.39287991 | F19: 0 | G19: =SUM(D19:F19) -> 1
B20: NorthWestern Corporation | C20: NWE | D20: 0.49687063 | E20: 0.50312937 | F20: 0 | G20: =SUM(D20:F20) -> 1
B21: OGE Energy Corp. | C21: OGE | D21: 0.53996582 | E21: 0.46003418 | F21: 0 | G21: =SUM(D21:F21) -> 1
... B24: Xcel Energy Inc. | C24: XEL | D24: 0.54406208 | E24: 0.45593792 | F24: 0 | G24: =SUM(D24:F24) -> 1
B26: Average | D26: =AVERAGE(D10:D24) -> 0.52707401 | E26: =AVERAGE(E10:E24) -> 0.46914267 | F26: =AVERAGE(F10:F24) -> 0.0037833197
B27: Median | D27: =MEDIAN(D10:D24) -> 0.52953939 | E27: =MEDIAN(E10:E24) -> 0.47046061 | F27: =MEDIAN(F10:F24) -> 0
B28: Maximum | D28: =MAX(D10:D24) -> 0.6114886 | E28: =MAX(E10:E24) -> 0.54618637 | F28: =MAX(F10:F24) -> 0.043407948
B29: Minimum | D29: =MIN(D10:D24) -> 0.41040568 | E29: =MIN(E10:E24) -> 0.3885114 | F29: =MIN(F10:F24) -> 0
B31: Notes:
B32: [1] Ratios are weighted by actual common capital, preferred capital, long-term debt of the operating subsidiaries.
B33: [2] Electric and Natural Gas operating subsidiaries with data listed as N/A from S&P Capital IQ have been excluded from the analysis.
