Workbook
Name Print_Area_0: #REF!
Name Print_Area_0: #REF!
Name Print_Area_0: #REF!
Name Print_Area_0: #REF!
Name Print_Area_0: #REF!
Name Print_Area_1: #REF!
Name Print_Area_1: #REF!
Name Print_Area_1: #REF!
Name Print_Area_1: #REF!
Name Print_Area_1: #REF!
Name Print_Area_2: #REF!
Name Print_Area_2: #REF!
Name Print_Area_2: #REF!
Name Print_Area_2: #REF!
Name Print_Area_2: #REF!
Name Print_Area_3: #REF!
Name Print_Area_3: #REF!
Name Print_Area_3: #REF!
Name Print_Area_3: #REF!
Name Print_Area_3: #REF!
Name Print_Area_4: #REF!
Name Print_Area_4: #REF!
Name Print_Area_4: #REF!
Name Print_Area_4: #REF!
Name Print_Area_4: #REF!

Sheet Index
A1: American Electric Power Service Corporation
A2: Monthly Variance Reporting Package
A3: September 2023
A9: Tab 1 | C9: AEPSC Bill Variance Summary
A11: Tab 2 | C11: AEPSC Bill Cost Category Summary - Income Statement
A13: Tab 3 | C13: AEPSC Variance Analysis
A15: Word Document | C15: Discussion of Major Variances
A17: Tab 4 | C17: Employee Fringe Benefit Loading Rates
A19: Tab 5 | C19: Total Bill Variance
A21: Tab 6 | C21: Income Statement Variance

Sheet Tab 1
A2: American Electric Power Service Corporation
A3: Total Bill Variances ( Favorable ) / UnFavorable
A4: Biiled + Manuals
A5: AEPSC Capital
A8: AEPSC Bill Entries
B10: EAST | I10: EAST | J10: WEST | M10: WEST | N10: NON-REG | O10: TRANSCO | P10: JV | Q10: AEPGR | R10: TRANSOURCE | S10: ETT | T10: AEPSC
B11: AEG | C11: APCO | D11: I&M | E11: KENT | F11: KINGS | G11: OPCO | H11: WHEEL | I11: TOTAL | J11: PSO | K11: SWEPCO | L11: AEP TEXAS | M11: TOTAL | N11: TOTAL | O11: TOTAL | P11: TOTAL | Q11: TOTAL | R11: TOTAL | S11: TOTAL | T11: TOTAL
A12: =EOMONTH(TEXT(Index!A3,"mmm-yyyy"),-12) -> 44834 | B12: 0 | C12: 20257693 | D12: 13635994 | E12: 3395405.8 | F12: 779546.29 | G12: 16753924 | H12: 2073638.3 | I12: 56896201 | J12: 8060334 | K12: 10210366 | L12: 16621277 | M12: 34891977 | N12: 1291197.6 | O12: 17722949 | P12: 0 | Q12: 220.33 | R12: 154285.28 | S12: 1734412.3 | T12: 1.1269124e+08
A13: =EOMONTH(A12,12) -> 45199 | B13: 0 | C13: 11749046 | D13: 6132540.4 | E13: 1689956.9 | F13: 527843.42 | G13: 11710481 | H13: 1860869.6 | I13: 33670737 | J13: 4794349.7 | K13: 6625010.1 | L13: 11411481 | M13: 22830841 | N13: 164126.64 | O13: 13595630 | P13: 0 | Q13: -165.13 | R13: 97204.83 | S13: 1709600.7 | T13: 72067975
A14: Variance | B14: =+B13-B12 -> 0 | C14: =+C13-C12 -> -8508647 | D14: =+D13-D12 -> -7503453.2 | E14: =+E13-E12 -> -1705448.9 | F14: =+F13-F12 -> -251702.87 | G14: =+G13-G12 -> -5043443.2 | H14: =+H13-H12 -> -212768.73 | I14: =SUM(B14:H14) -> -23225464 | J14: =+J13-J12 -> -3265984.3 | K14: =+K13-K12 -> -3585355.8 | L14: =+L13-L12 -> -5209795.3 | M14: =SUM(J14:L14) -> -12061135 | N14: =+N13-N12 -> -1127071 | O14: =+O13-O12 -> -4127319.4 | P14: =+P13-P12 -> 0 | Q14: =+Q13-Q12 -> -385.46 | R14: =+R13-R12 -> -57080.45 | S14: =+S13-S12 -> -24811.65 | T14: =SUM(I14,M14,N14:S14) -> -40623267
A16: Manual Entries - Other
B18: EAST | I18: EAST | J18: WEST | M18: WEST | N18: NON-REG | O18: TRANSCO | P18: JV | Q18: AEPGR | R18: TRANSOURCE | S18: ETT | T18: AEPSC
B19: AEG | C19: APCO | D19: I&M | E19: KENT | F19: KINGS | G19: OPCO | H19: WHEEL | I19: TOTAL | J19: PSO | K19: SWEPCO | L19: AEP TEXAS | M19: TOTAL | N19: TOTAL | O19: TOTAL | P19: TOTAL | Q19: TOTAL | R19: TOTAL | S19: TOTAL | T19: TOTAL
A20: =+$A$12 -> 44834 | B20: 0 | C20: -3910585.5 | D20: -4293128.4 | E20: -814957.35 | F20: -132344.21 | G20: -3609985.5 | H20: -214496.7 | I20: -12975498 | J20: -2216245.8 | K20: -2738807.2 | L20: -3758790.2 | M20: -8713843.2 | N20: -512620.66 | O20: -1714437.2 | P20: 0 | Q20: 0 | R20: -32306.81 | S20: -204608.02 | T20: -24153314
A21: =+$A$13 -> 45199 | B21: 0 | C21: 0 | D21: 0 | E21: 0 | F21: 0 | G21: 0 | H21: 0 | I21: 0 | J21: -0.01 | K21: 0 | L21: 0 | M21: -0.01 | N21: 0 | O21: 0 | P21: 0 | Q21: 0 | R21: 0 | S21: 0 | T21: -0.01
A22: Variance | B22: =+B21-B20 -> 0 | C22: =+C21-C20 -> 3910585.5 | D22: =+D21-D20 -> 4293128.4 | E22: =+E21-E20 -> 814957.35 | F22: =+F21-F20 -> 132344.21 | G22: =+G21-G20 -> 3609985.5 | H22: =+H21-H20 -> 214496.7 | I22: =SUM(B22:H22) -> 12975498 | J22: =+J21-J20 -> 2216245.8 | K22: =+K21-K20 -> 2738807.2 | L22: =+L21-L20 -> 3758790.2 | M22: =SUM(J22:L22) -> 8713843.2 | N22: =+N21-N20 -> 512620.66 | O22: =+O21-O20 -> 1714437.2 | P22: =+P21-P20 -> 0 | Q22: =+Q21-Q20 -> 0 | R22: =+R21-R20 -> 32306.81 | S22: =+S21-S20 -> 204608.02 | T22: =SUM(I22,M22,N22:S22) -> 24153314
A24: Total AEPSC Capital
B26: EAST | I26: EAST | J26: WEST | M26: WEST | N26: NON-REG | O26: TRANSCO | P26: JV | Q26: AEPGR | R26: TRANSOURCE | S26: ETT | T26: AEPSC
B27: AEG | C27: APCO | D27: I&M | E27: KENT | F27: KINGS | G27: OPCO | H27: WHEEL | I27: TOTAL | J27: PSO | K27: SWEPCO | L27: AEP TEXAS | M27: TOTAL | N27: TOTAL | O27: TOTAL | P27: TOTAL | Q27: TOTAL | R27: TOTAL | S27: TOTAL | T27: TOTAL
A28: =+$A$12 -> 44834 | B28: =+B12+B20 -> 0 | C28: =+C12+C20 -> 16347107 | D28: =+D12+D20 -> 9342865.1 | E28: =+E12+E20 -> 2580448.4 | F28: =+F12+F20 -> 647202.08 | G28: =+G12+G20 -> 13143938 | H28: =+H12+H20 -> 1859141.6 | I28: =SUM(B28:H28) -> 43920703 | J28: =+J12+J20 -> 5844088.2 | K28: =+K12+K20 -> 7471558.8 | L28: =+L12+L20 -> 12862487 | M28: =SUM(J28:L28) -> 26178133 | N28: =+N12+N20 -> 778576.98 | O28: =+O12+O20 -> 16008512 | P28: =+P12+P20 -> 0 | Q28: =+Q12+Q20 -> 220.33 | R28: =+R12+R20 -> 121978.47 | S28: =+S12+S20 -> 1529804.3 | T28: =SUM(I28,M28,N28:S28) -> 88537929
A29: =+$A$13 -> 45199 | B29: =+B13+B21 -> 0 | C29: =+C13+C21 -> 11749046 | D29: =+D13+D21 -> 6132540.4 | E29: =+E13+E21 -> 1689956.9 | F29: =+F13+F21 -> 527843.42 | G29: =+G13+G21 -> 11710481 | H29: =+H13+H21 -> 1860869.6 | I29: =SUM(B29:H29) -> 33670737 | J29: =+J13+J21 -> 4794349.7 | K29: =+K13+K21 -> 6625010.1 | L29: =+L13+L21 -> 11411481 | M29: =SUM(J29:L29) -> 22830841 | N29: =+N13+N21 -> 164126.64 | O29: =+O13+O21 -> 13595630 | P29: =+P13+P21 -> 0 | Q29: =+Q13+Q21 -> -165.13 | R29: =+R13+R21 -> 97204.83 | S29: =+S13+S21 -> 1709600.7 | T29: =SUM(I29,M29,N29:S29) -> 72067975
A30: Variance | B30: =+B14+B22 -> 0 | C30: =+C14+C22 -> -4598061.5 | D30: =+D14+D22 -> -3210324.8 | E30: =+E14+E22 -> -890491.51 | F30: =+F14+F22 -> -119358.66 | G30: =+G14+G22 -> -1433457.7 | H30: =+H14+H22 -> 1727.97 | I30: =SUM(B30:H30) -> -10249966 | J30: =+J14+J22 -> -1049738.5 | K30: =+K14+K22 -> -846548.65 | L30: =+L14+L22 -> -1451005.1 | M30: =SUM(J30:L30) -> -3347292.2 | N30: =+N14+N22 -> -614450.34 | O30: =+O14+O22 -> -2412882.1 | P30: =+P14+P22 -> 0 | Q30: =+Q14+Q22 -> -385.46 | R30: =+R14+R22 -> -24773.64 | S30: =+S14+S22 -> 179796.37 | T30: =SUM(I30,M30,N30:S30) -> -16469954
A32: AEPSC Other Balance Sheet
A34: AEPSC Bill Entries
B36: EAST | I36: EAST | J36: WEST | M36: WEST | N36: NON-REG | O36: TRANSCO | P36: JV | Q36: AEPGR | R36: TRANSOURCE | S36: ETT | T36: AEPSC
B37: AEG | C37: APCO | D37: I&M | E37: KENT | F37: KINGS | G37: OPCO | H37: WHEEL | I37: TOTAL | J37: PSO | K37: SWEPCO | L37: AEP TEXAS | M37: TOTAL | N37: TOTAL | O37: TOTAL | P37: TOTAL | Q37: TOTAL | R37: TOTAL | S37: TOTAL | T37: TOTAL
A38: =+$A$12 -> 44834 | B38: 65446.85 | C38: 1197796.3 | D38: 1097314.3 | E38: 178363.93 | F38: 13436.16 | G38: 905935.24 | H38: 177370.89 | I38: 3635663.7 | J38: 986072.64 | K38: 1271261.9 | L38: 798916.83 | M38: 3056251.4 | N38: 61104.04 | O38: 651829.46 | P38: 14869.09 | Q38: -728750.92 | R38: 3299.13 | S38: 115784.68 | T38: 6810050.6
A39: =+$A$13 -> 45199 | B39: 11678.82 | C39: 1353182.3 | D39: 838377.32 | E39: 175800.12 | F39: 17422.48 | G39: 696867.79 | H39: 212711.57 | I39: 3306040.4 | J39: 517780.06 | K39: 830396.86 | L39: 617897.14 | M39: 1966074.1 | N39: 42009.01 | O39: 384080.68 | P39: 25780.83 | Q39: -3331124.6 | R39: 1506.23 | S39: 71835.64 | T39: 2466202.3
A40: Variance | B40: =+B39-B38 -> -53768.03 | C40: =+C39-C38 -> 155386.01 | D40: =+D39-D38 -> -258937.01 | E40: =+E39-E38 -> -2563.81 | F40: =+F39-F38 -> 3986.32 | G40: =+G39-G38 -> -209067.45 | H40: =+H39-H38 -> 35340.68 | I40: =SUM(B40:H40) -> -329623.29 | J40: =+J39-J38 -> -468292.58 | K40: =+K39-K38 -> -440865.06 | L40: =+L39-L38 -> -181019.69 | M40: =SUM(J40:L40) -> -1090177.3 | N40: =+N39-N38 -> -19095.03 | O40: =+O39-O38 -> -267748.78 | P40: =+P39-P38 -> 10911.74 | Q40: =+Q39-Q38 -> -2602373.7 | R40: =+R39-R38 -> -1792.9 | S40: =+S39-S38 -> -43949.04 | T40: =SUM(I40,M40,N40:S40) -> -4343848.3
A42: Manual Entries - Other
B44: EAST | I44: EAST | J44: WEST | M44: WEST | N44: NON-REG | O44: TRANSCO | P44: JV | Q44: AEPGR | R44: TRANSOURCE | S44: ETT | T44: AEPSC
B45: AEG | C45: APCO | D45: I&M | E45: KENT | F45: KINGS | G45: OPCO | H45: WHEEL | I45: TOTAL | J45: PSO | K45: SWEPCO | L45: AEP TEXAS | M45: TOTAL | N45: TOTAL | O45: TOTAL | P45: TOTAL | Q45: TOTAL | R45: TOTAL | S45: TOTAL | T45: TOTAL
A46: =+$A$12 -> 44834 | B46: -22496.2 | C46: 0 | D46: -27958.3 | E46: 0 | F46: 0 | G46: 0 | H46: 0 | I46: -50454.5 | J46: 0 | K46: 0 | L46: 0 | M46: 0 | N46: 0 | O46: 0 | P46: 0 | Q46: 0 | R46: 0 | S46: -9.91 | T46: -50464.41
A47: =+$A$13 -> 45199 | B47: 0 | C47: 0 | D47: 0 | E47: 0 | F47: 0 | G47: 0 | H47: 0 | I47: 0 | J47: 0 | K47: 0 | L47: 0 | M47: 0 | N47: 0 | O47: 0 | P47: 0 | Q47: 0 | R47: 0 | S47: 0 | T47: 0
A48: Variance | B48: =+B47-B46 -> 22496.2 | C48: =+C47-C46 -> 0 | D48: =+D47-D46 -> 27958.3 | E48: =+E47-E46 -> 0 | F48: =+F47-F46 -> 0 | G48: =+G47-G46 -> 0 | H48: =+H47-H46 -> 0 | I48: =SUM(B48:H48) -> 50454.5 | J48: =+J47-J46 -> 0 | K48: =+K47-K46 -> 0 | L48: =+L47-L46 -> 0 | M48: =SUM(J48:L48) -> 0 | N48: =+N47-N46 -> 0 | O48: =+O47-O46 -> 0 | P48: =+P47-P46 -> 0 | Q48: =+Q47-Q46 -> 0 | R48: =+R47-R46 -> 0 | S48: =+S47-S46 -> 9.91 | T48: =SUM(I48,M48,N48:S48) -> 50464.41
A50: Total AEPSC Other Balance Sheet
B52: EAST | I52: EAST | J52: WEST | M52: WEST | N52: NON-REG | O52: TRANSCO | P52: JV | Q52: AEPGR | R52: TRANSOURCE | S52: ETT | T52: AEPSC
B53: AEG | C53: APCO | D53: I&M | E53: KENT | F53: KINGS | G53: OPCO | H53: WHEEL | I53: TOTAL | J53: PSO | K53: SWEPCO | L53: AEP TEXAS | M53: TOTAL | N53: TOTAL | O53: TOTAL | P53: TOTAL | Q53: TOTAL | R53: TOTAL | S53: TOTAL | T53: TOTAL
A54: =+$A$12 -> 44834 | B54: =+B38+B46 -> 42950.65 | C54: =+C38+C46 -> 1197796.3 | D54: =+D38+D46 -> 1069356 | E54: =+E38+E46 -> 178363.93 | F54: =+F38+F46 -> 13436.16 | G54: =+G38+G46 -> 905935.24 | H54: =+H38+H46 -> 177370.89 | I54: =SUM(B54:H54) -> 3585209.2 | J54: =+J38+J46 -> 986072.64 | K54: =+K38+K46 -> 1271261.9 | L54: =+L38+L46 -> 798916.83 | M54: =SUM(J54:L54) -> 3056251.4 | N54: =+N38+N46 -> 61104.04 | O54: =+O38+O46 -> 651829.46 | P54: =+P38+P46 -> 14869.09 | Q54: =+Q38+Q46 -> -728750.92 | R54: =+R38+R46 -> 3299.13 | S54: =+S38+S46 -> 115774.77 | T54: =SUM(I54,M54,N54:S54) -> 6759586.2
A55: =+$A$13 -> 45199 | B55: =+B39+B47 -> 11678.82 | C55: =+C39+C47 -> 1353182.3 | D55: =+D39+D47 -> 838377.32 | E55: =+E39+E47 -> 175800.12 | F55: =+F39+F47 -> 17422.48 | G55: =+G39+G47 -> 696867.79 | H55: =+H39+H47 -> 212711.57 | I55: =SUM(B55:H55) -> 3306040.4 | J55: =+J39+J47 -> 517780.06 | K55: =+K39+K47 -> 830396.86 | L55: =+L39+L47 -> 617897.14 | M55: =SUM(J55:L55) -> 1966074.1 | N55: =+N39+N47 -> 42009.01 | O55: =+O39+O47 -> 384080.68 | P55: =+P39+P47 -> 25780.83 | Q55: =+Q39+Q47 -> -3331124.6 | R55: =+R39+R47 -> 1506.23 | S55: =+S39+S47 -> 71835.64 | T55: =SUM(I55,M55,N55:S55) -> 2466202.3
A56: Variance | B56: =+B40+B48 -> -31271.83 | C56: =+C40+C48 -> 155386.01 | D56: =+D40+D48 -> -230978.71 | E56: =+E40+E48 -> -2563.81 | F56: =+F40+F48 -> 3986.32 | G56: =+G40+G48 -> -209067.45 | H56: =+H40+H48 -> 35340.68 | I56: =SUM(B56:H56) -> -279168.79 | J56: =+J40+J48 -> -468292.58 | K56: =+K40+K48 -> -440865.06 | L56: =+L40+L48 -> -181019.69 | M56: =SUM(J56:L56) -> -1090177.3 | N56: =+N40+N48 -> -19095.03 | O56: =+O40+O48 -> -267748.78 | P56: =+P40+P48 -> 10911.74 | Q56: =+Q40+Q48 -> -2602373.7 | R56: =+R40+R48 -> -1792.9 | S56: =+S40+S48 -> -43939.13 | T56: =SUM(I56,M56,N56:S56) -> -4293383.9
A58: AEPSC Income Statement | W58: (Favorable) / | X58: (Favorable) / | Y58: (Favorable) /
W59: Unfavorable | X59: Unfavorable | Y59: Unfavorable
A60: AEPSC Bill Entries | V60: Tab 2: | W60: EAST | X60: WEST | Y60: AEPSC
V61: Cost Category Summary | W61: TOTAL | X61: TOTAL | Y61: TOTAL
B62: EAST | I62: EAST | J62: WEST | M62: WEST | N62: NON-REG | O62: TRANSCO | P62: JV | Q62: AEPGR | R62: TRANSOURCE | S62: ETT | T62: AEPSC | V62: Labor | W62: =+'Tab 2'!J12 -> -503154.7 | X62: =+'Tab 2'!N12 -> -349299.44 | Y62: =+'Tab 2'!U12 -> -1649072.5
B63: AEG | C63: APCO | D63: I&M | E63: KENT | F63: KINGS | G63: OPCO | H63: WHEEL | I63: TOTAL | J63: PSO | K63: SWEPCO | L63: AEP TEXAS | M63: TOTAL | N63: TOTAL | O63: TOTAL | P63: TOTAL | Q63: TOTAL | R63: TOTAL | S63: TOTAL | T63: TOTAL | V63: Fringes | W63: =+'Tab 2'!J20 -> -1247354.3 | X63: =+'Tab 2'!N20 -> -846583.58 | Y63: =+'Tab 2'!U20 -> -2228328.9
A64: =+$A$12 -> 44834 | B64: 36134.49 | C64: 15685924 | D64: 9817586.2 | E64: 2616055.8 | F64: 374466.55 | G64: 11755226 | H64: 1677269.1 | I64: 41962662 | J64: 8188054.7 | K64: 9556816.7 | L64: 9029762.2 | M64: 26774634 | N64: 5049068 | O64: 9188537 | P64: 94961.15 | Q64: 206210.81 | R64: 367954.77 | S64: 1814843.8 | T64: 85458871 | V64: Annual Incentives | W64: =+'Tab 2'!J28 -> -3841753.5 | X64: =+'Tab 2'!N28 -> -2525687.8 | Y64: =+'Tab 2'!U28 -> -8033544.9
A65: =+$A$13 -> 45199 | B65: 67431.62 | C65: 11874285 | D65: 7432132.8 | E65: 1935888.6 | F65: 305240.08 | G65: 9593869.3 | H65: 1264886.2 | I65: 32473733 | J65: 6173015.4 | K65: 7151717.3 | L65: 7397165.5 | M65: 20721898 | N65: 2563410.1 | O65: 6764619.9 | P65: 52004.37 | Q65: 79771.88 | R65: 334636.66 | S65: 1573494.7 | T65: 64563569 | V65: Long Term Incentives | W65: =+'Tab 2'!J36 -> -215755.43 | X65: =+'Tab 2'!N36 -> -153349.05 | Y65: =+'Tab 2'!U36 -> -567984.85
A66: Variance | B66: =+B65-B64 -> 31297.13 | C66: =+C65-C64 -> -3811639.6 | D66: =+D65-D64 -> -2385453.4 | E66: =+E65-E64 -> -680167.15 | F66: =+F65-F64 -> -69226.47 | G66: =+G65-G64 -> -2161356.3 | H66: =+H65-H64 -> -412382.86 | I66: =SUM(B66:H66) -> -9488928.7 | J66: =+J65-J64 -> -2015039.4 | K66: =+K65-K64 -> -2405099.4 | L66: =+L65-L64 -> -1632596.7 | M66: =SUM(J66:L66) -> -6052735.4 | N66: =+N65-N64 -> -2485657.9 | O66: =+O65-O64 -> -2423917 | P66: =+P65-P64 -> -42956.78 | Q66: =+Q65-Q64 -> -126438.93 | R66: =+R65-R64 -> -33318.11 | S66: =+S65-S64 -> -241349.07 | T66: =SUM(I66,M66,N66:S66) -> -20895302 | V66: Reloc / Severance | W66: =+'Tab 2'!J44 -> 856170.13 | X66: =+'Tab 2'!N44 -> 535421.69 | Y66: =+'Tab 2'!U44 -> 1585592.1
V67: Outside Services | W67: =+'Tab 2'!J52 -> -2029718.8 | X67: =+'Tab 2'!N52 -> -1703192.8 | Y67: =+'Tab 2'!U52 -> -4933971.7
A68: Manual Entries - Other | V68: Materials/Supplies | W68: =+'Tab 2'!J60 -> -383706.42 | X68: =+'Tab 2'!N60 -> -159883.21 | Y68: =+'Tab 2'!U60 -> -670036.05
V69: Travel Employee Exp | W69: =+'Tab 2'!J68 -> -238653.16 | X69: =+'Tab 2'!N68 -> -150231.44 | Y69: =+'Tab 2'!U68 -> -508920.97
B70: EAST | I70: EAST | J70: WEST | M70: WEST | N70: NON-REG | O70: TRANSCO | P70: JV | Q70: AEPGR | R70: TRANSOURCE | S70: ETT | T70: AEPSC | V70: Overhead & Shared Services | W70: =+'Tab 2'!J76 -> -649460.22 | X70: =+'Tab 2'!N76 -> 92105.12 | Y70: =+'Tab 2'!U76 -> -569499.53
B71: AEG | C71: APCO | D71: I&M | E71: KENT | F71: KINGS | G71: OPCO | H71: WHEEL | I71: TOTAL | J71: PSO | K71: SWEPCO | L71: AEP TEXAS | M71: TOTAL | N71: TOTAL | O71: TOTAL | P71: TOTAL | Q71: TOTAL | R71: TOTAL | S71: TOTAL | T71: TOTAL | V71: Other | W71: =+'Tab 2'!J84 -> -1235542.4 | X71: =+'Tab 2'!N84 -> -792034.95 | Y71: =+'Tab 2'!U84 -> -3319534.6
A72: =+$A$12 -> 44834 | B72: 0 | C72: 300.09 | D72: 204.49 | E72: 75.61 | F72: 3.12 | G72: 373.98 | H72: 11.01 | I72: 968.3 | J72: 154.44 | K72: 238.61 | L72: 494.36 | M72: 887.41 | N72: 0 | O72: 210.42 | P72: 0 | Q72: 0 | R72: 0 | S72: -2066.12 | T72: 0.01 | V72: =+A58 -> AEPSC Income Statement | W72: =SUM(W62:W71) -> -9488928.7 | X72: =SUM(X62:X71) -> -6052735.4 | Y72: =SUM(Y62:Y71) -> -20895302
A73: =+$A$13 -> 45199 | B73: 0 | C73: 443.84 | D73: 297.62 | E73: 111.75 | F73: 4.67 | G73: 556.2 | H73: 16.46 | I73: 1430.54 | J73: 227.22 | K73: 353.99 | L73: 739.81 | M73: 1321.02 | N73: 0 | O73: 342.11 | P73: 0 | Q73: 0 | R73: 0 | S73: -3093.66 | T73: 0.01 | W73: =+W72-I66 -> -5.2154064e-08 | X73: =+X72-M66 -> 0 | Y73: =+Y72-T66 -> -1.0430813e-07
A74: Variance | B74: =+B73-B72 -> 0 | C74: =+C73-C72 -> 143.75 | D74: =+D73-D72 -> 93.13 | E74: =+E73-E72 -> 36.14 | F74: =+F73-F72 -> 1.55 | G74: =+G73-G72 -> 182.22 | H74: =+H73-H72 -> 5.45 | I74: =SUM(B74:H74) -> 462.24 | J74: =+J73-J72 -> 72.78 | K74: =+K73-K72 -> 115.38 | L74: =+L73-L72 -> 245.45 | M74: =SUM(J74:L74) -> 433.61 | N74: =+N73-N72 -> 0 | O74: =+O73-O72 -> 131.69 | P74: =+P73-P72 -> 0 | Q74: =+Q73-Q72 -> 0 | R74: =+R73-R72 -> 0 | S74: =+S73-S72 -> -1027.54 | T74: =SUM(I74,M74,N74:S74) -> 0
A76: Total AEPSC Income Statement
B78: EAST | I78: EAST | J78: WEST | M78: WEST | N78: NON-REG | O78: TRANSCO | P78: JV | Q78: AEPGR | R78: TRANSOURCE | S78: ETT | T78: AEPSC
B79: AEG | C79: APCO | D79: I&M | E79: KENT | F79: KINGS | G79: OPCO | H79: WHEEL | I79: TOTAL | J79: PSO | K79: SWEPCO | L79: AEP TEXAS | M79: TOTAL | N79: TOTAL | O79: TOTAL | P79: TOTAL | Q79: TOTAL | R79: TOTAL | S79: TOTAL | T79: TOTAL
A80: =+$A$12 -> 44834 | B80: =+B64+B72 -> 36134.49 | C80: =+C64+C72 -> 15686224 | D80: =+D64+D72 -> 9817790.7 | E80: =+E64+E72 -> 2616131.4 | F80: =+F64+F72 -> 374469.67 | G80: =+G64+G72 -> 11755600 | H80: =+H64+H72 -> 1677280.1 | I80: =SUM(B80:H80) -> 41963630 | J80: =+J64+J72 -> 8188209.2 | K80: =+K64+K72 -> 9557055.3 | L80: =+L64+L72 -> 9030256.6 | M80: =SUM(J80:L80) -> 26775521 | N80: =+N64+N72 -> 5049068 | O80: =+O64+O72 -> 9188747.4 | P80: =+P64+P72 -> 94961.15 | Q80: =+Q64+Q72 -> 206210.81 | R80: =+R64+R72 -> 367954.77 | S80: =+S64+S72 -> 1812777.7 | T80: =SUM(I80,M80,N80:S80) -> 85458871
A81: =+$A$13 -> 45199 | B81: =+B65+B73 -> 67431.62 | C81: =+C65+C73 -> 11874728 | D81: =+D65+D73 -> 7432430.4 | E81: =+E65+E73 -> 1936000.4 | F81: =+F65+F73 -> 305244.75 | G81: =+G65+G73 -> 9594425.5 | H81: =+H65+H73 -> 1264902.7 | I81: =SUM(B81:H81) -> 32475164 | J81: =+J65+J73 -> 6173242.6 | K81: =+K65+K73 -> 7152071.3 | L81: =+L65+L73 -> 7397905.3 | M81: =SUM(J81:L81) -> 20723219 | N81: =+N65+N73 -> 2563410.1 | O81: =+O65+O73 -> 6764962 | P81: =+P65+P73 -> 52004.37 | Q81: =+Q65+Q73 -> 79771.88 | R81: =+R65+R73 -> 334636.66 | S81: =+S65+S73 -> 1570401.1 | T81: =SUM(I81,M81,N81:S81) -> 64563569
A82: Variance | B82: =+B66+B74 -> 31297.13 | C82: =+C66+C74 -> -3811495.9 | D82: =+D66+D74 -> -2385360.3 | E82: =+E66+E74 -> -680131.01 | F82: =+F66+F74 -> -69224.92 | G82: =+G66+G74 -> -2161174.1 | H82: =+H66+H74 -> -412377.41 | I82: =SUM(B82:H82) -> -9488466.5 | J82: =+J66+J74 -> -2014966.6 | K82: =+K66+K74 -> -2404984 | L82: =+L66+L74 -> -1632351.2 | M82: =SUM(J82:L82) -> -6052301.8 | N82: =+N66+N74 -> -2485657.9 | O82: =+O66+O74 -> -2423785.4 | P82: =+P66+P74 -> -42956.78 | Q82: =+Q66+Q74 -> -126438.93 | R82: =+R66+R74 -> -33318.11 | S82: =+S66+S74 -> -242376.61 | T82: =SUM(I82,M82,N82:S82) -> -20895302
A85: Total AEPSC Billings
B87: EAST | I87: EAST | J87: WEST | M87: WEST | N87: NON-REG | O87: TRANSCO | P87: JV | Q87: AEPGR | R87: TRANSOURCE | S87: ETT | T87: AEPSC | W87: 457xxx
B88: AEG | C88: APCO | D88: I&M | E88: KENT | F88: KINGS | G88: OPCO | H88: WHEEL | I88: TOTAL | J88: PSO | K88: SWEPCO | L88: AEP TEXAS | M88: TOTAL | N88: TOTAL | O88: TOTAL | P88: TOTAL | Q88: TOTAL | R88: TOTAL | S88: TOTAL | T88: TOTAL | W88: Per GL | X88: Difference
A89: =+$A$12 -> 44834 | B89: =+B28+B54+B80 -> 79085.14 | C89: =+C28+C54+C80 -> 33231128 | D89: =+D28+D54+D80 -> 20230012 | E89: =+E28+E54+E80 -> 5374943.8 | F89: =+F28+F54+F80 -> 1035107.9 | G89: =+G28+G54+G80 -> 25805473 | H89: =+H28+H54+H80 -> 3713792.6 | I89: =SUM(B89:H89) -> 89469543 | J89: =+J28+J54+J80 -> 15018370 | K89: =+K28+K54+K80 -> 18299876 | L89: =+L28+L54+L80 -> 22691660 | M89: =SUM(J89:L89) -> 56009906 | N89: =+N28+N54+N80 -> 5888749 | O89: =+O28+O54+O80 -> 25849089 | P89: =+P28+P54+P80 -> 109830.24 | Q89: =+Q28+Q54+Q80 -> -522319.78 | R89: =+R28+R54+R80 -> 493232.37 | S89: =+S28+S54+S80 -> 3458356.8 | T89: =SUM(I89,M89,N89:S89) -> 1.8075639e+08 | V89: Agrees to 457xxxx | W89: =SUMIF('457-PQ'!C:C,YEAR(Index!A3)-1,'457-PQ'!F:F) -> -1.8075639e+08 | X89: =+W89+T89 -> 0
A90: =+$A$13 -> 45199 | B90: =+B29+B55+B81 -> 79110.44 | C90: =+C29+C55+C81 -> 24976957 | D90: =+D29+D55+D81 -> 14403348 | E90: =+E29+E55+E81 -> 3801757.4 | F90: =+F29+F55+F81 -> 850510.65 | G90: =+G29+G55+G81 -> 22001774 | H90: =+H29+H55+H81 -> 3338483.8 | I90: =SUM(B90:H90) -> 69451941 | J90: =+J29+J55+J81 -> 11485372 | K90: =+K29+K55+K81 -> 14607478 | L90: =+L29+L55+L81 -> 19427284 | M90: =SUM(J90:L90) -> 45520135 | N90: =+N29+N55+N81 -> 2769545.7 | O90: =+O29+O55+O81 -> 20744673 | P90: =+P29+P55+P81 -> 77785.2 | Q90: =+Q29+Q55+Q81 -> -3251517.9 | R90: =+R29+R55+R81 -> 433347.72 | S90: =+S29+S55+S81 -> 3351837.4 | T90: =SUM(I90,M90,N90:S90) -> 1.3909775e+08 | V90: Agrees to 457xxxx | W90: =SUMIF('457-PQ'!C:C,YEAR(Index!A3),'457-PQ'!F:F) -> -1.3909775e+08 | X90: =+W90+T90 -> 0
A91: Variance | B91: =+B90-B89 -> 25.3 | C91: =+C90-C89 -> -8254171.3 | D91: =+D90-D89 -> -5826663.8 | E91: =+E90-E89 -> -1573186.3 | F91: =+F90-F89 -> -184597.26 | G91: =+G90-G89 -> -3803699.2 | H91: =+H90-H89 -> -375308.76 | I91: =SUM(B91:H91) -> -20017601 | J91: =+J90-J89 -> -3532997.6 | K91: =+K90-K89 -> -3692397.7 | L91: =+L90-L89 -> -3264376 | M91: =SUM(J91:L91) -> -10489771 | N91: =+N90-N89 -> -3119203.2 | O91: =+O90-O89 -> -5104416.3 | P91: =+P90-P89 -> -32045.04 | Q91: =+Q90-Q89 -> -2729198.1 | R91: =+R90-R89 -> -59884.65 | S91: =+S90-S89 -> -106519.37 | T91: =SUM(I91,M91,N91:S91) -> -41658639

Sheet Tab 2
B2: AEPSC Bill Variance Summary ( Favorable ) / Unfavorable
B4: No Manual adjustments reflected in these amounts; only items system Billed
B5: Income Statement
B7: Labor Variance (11X, 125, 129, 13X, 190, 1AA, 1AB, U3E)
C8: EAST | J8: EAST | K8: WEST | N8: WEST | O8: NON-REG | P8: TRANSCO | Q8: JV | R8: AEPGR | S8: TRANSOURCE | T8: ETT | U8: AEPSC
C9: AEG | D9: APCO | E9: I&M | F9: KENT | G9: KINGS | H9: OPCO | I9: WHEEL | J9: TOTAL | K9: PSO | L9: SWEPCO | M9: AEP TEXAS | N9: TOTAL | O9: TOTAL | P9: TOTAL | Q9: TOTAL | R9: TOTAL | S9: TOTAL | T9: TOTAL | U9: TOTAL
B10: =TEXT(+'Tab 1'!A12,"mmm-yyyy") -> Sep-2022 | C10: 13327.17 | D10: 4973108.4 | E10: 2971770.1 | F10: 855480.92 | G10: 100162.61 | H10: 3800311.2 | I10: 465351.89 | J10: 13179512 | K10: 2527741.9 | L10: 3056861.1 | M10: 2868542.2 | N10: 8453145.2 | O10: 1351170.2 | P10: 3093107.8 | Q10: 33748.96 | R10: 50061.17 | S10: 111642.23 | T10: 650079.59 | U10: 26922467
B11: =EOMONTH(B10,12) -> 45199 | C11: 26781.37 | D11: 4869395 | E11: 2788468 | F11: 784492.37 | G11: 101219.83 | H11: 3598154.4 | I11: 507846.58 | J11: 12676358 | K11: 2452785.4 | L11: 2848519 | M11: 2802541.4 | N11: 8103845.8 | O11: 848951.69 | P11: 2834608.3 | Q11: 26829.46 | R11: 27253.64 | S11: 143530.3 | T11: 612018.19 | U11: 25273395
B12: Variance | C12: =+C11-C10 -> 13454.2 | D12: =+D11-D10 -> -103713.31 | E12: =+E11-E10 -> -183302.15 | F12: =+F11-F10 -> -70988.55 | G12: =+G11-G10 -> 1057.22 | H12: =+H11-H10 -> -202156.8 | I12: =+I11-I10 -> 42494.69 | J12: =+J11-J10 -> -503154.7 | ... U12: =+U11-U10 -> -1649072.5
B15: Labor Fringe Variance (120, 121, 123, 126, 128, 170)
C16: EAST | J16: EAST | K16: WEST | N16: WEST | O16: NON-REG | P16: TRANSCO | Q16: JV | R16: AEPGR | S16: TRANSOURCE | T16: ETT | U16: AEPSC
C17: AEG | D17: APCO | E17: I&M | F17: KENT | G17: KINGS | H17: OPCO | I17: WHEEL | J17: TOTAL | K17: PSO | L17: SWEPCO | M17: AEP TEXAS | N17: TOTAL | O17: TOTAL | P17: TOTAL | Q17: TOTAL | R17: TOTAL | S17: TOTAL | T17: TOTAL | U17: TOTAL
B18: =+$B$10 -> Sep-2022 | C18: 2941.01 | D18: 961965.66 | E18: 599265.13 | F18: 139145.99 | G18: 13558.16 | H18: 719994.61 | I18: 122496.46 | J18: 2559367 | K18: 536315.7 | L18: 624232.15 | M18: 506440.96 | N18: 1666988.8 | O18: -114170.95 | P18: 493542.1 | Q18: 9702.28 | R18: 11924.14 | S18: 24116.06 | T18: 131667.42 | U18: 4783136.9
B19: =+$B$11 -> 45199 | C19: 4705.07 | D19: 509810.28 | E19: 325118.49 | F19: 93809.24 | G19: 4728.33 | H19: 326956.47 | I19: 46884.83 | J19: 1312012.7 | K19: 314319.02 | L19: 312393.83 | M19: 193692.38 | N19: 820405.23 | O19: 124807.12 | P19: 166337.22 | Q19: 7095.97 | R19: 4453.09 | S19: 30077.39 | T19: 89619.24 | U19: 2554808
B20: Variance | C20: =+C19-C18 -> 1764.06 | D20: =+D19-D18 -> -452155.38 | E20: =+E19-E18 -> -274146.64 | F20: =+F19-F18 -> -45336.75 | G20: =+G19-G18 -> -8829.83 | H20: =+H19-H18 -> -393038.14 | I20: =+I19-I18 -> -75611.63 | J20: =+J19-J18 -> -1247354.3 | ... U20: =+U19-U18 -> -2228328.9
B23: Annual Incentive Variance (122, 140, 141, 146-152, 155, 158, 161)
C24: EAST | J24: EAST | K24: WEST | N24: WEST | O24: NON-REG | P24: TRANSCO | Q24: JV | R24: AEPGR | S24: TRANSOURCE | T24: ETT | U24: AEPSC
C25: AEG | D25: APCO | E25: I&M | F25: KENT | G25: KINGS | H25: OPCO | I25: WHEEL | J25: TOTAL | K25: PSO | L25: SWEPCO | M25: AEP TEXAS | N25: TOTAL | O25: TOTAL | P25: TOTAL | Q25: TOTAL | R25: TOTAL | S25: TOTAL | T25: TOTAL | U25: TOTAL
B26: =+$B$10 -> Sep-2022 | C26: 3702.18 | D26: 1214659.8 | E26: 769190.96 | F26: 195779.92 | G26: 23728.71 | H26: 855703.12 | I26: 133225.69 | J26: 3195990.4 | K26: 642798.41 | L26: 754077.36 | M26: 683542.91 | N26: 2080418.7 | O26: 458298.26 | P26: 722565.37 | Q26: 10687.97 | R26: 14459.78 | S26: 34523.72 | T26: 170662.72 | U26: 6687606.9
B27: =+$B$11 -> 45199 | C27: -1720.87 | D27: -223172.81 | E27: -158631.81 | F27: -47988.56 | G27: -6070.27 | H27: -182468.88 | I27: -25709.91 | J27: -645763.11 | K27: -134805.65 | L27: -146781.45 | M27: -163682 | N27: -445269.1 | O27: -55828.57 | P27: -152996.99 | Q27: -1729.78 | R27: -1305.77 | S27: -10319.7 | T27: -32725.05 | U27: -1345938.1
B28: Variance | C28: =+C27-C26 -> -5423.05 | D28: =+D27-D26 -> -1437832.6 | E28: =+E27-E26 -> -927822.77 | F28: =+F27-F26 -> -243768.48 | G28: =+G27-G26 -> -29798.98 | H28: =+H27-H26 -> -1038172 | I28: =+I27-I26 -> -158935.6 | J28: =+J27-J26 -> -3841753.5 | ... U28: =+U27-U26 -> -8033544.9
B31: Long Term Incentive Variance (145, 153, 154, 157)
C32: EAST | J32: EAST | K32: WEST | N32: WEST | O32: NON-REG | P32: TRANSCO | Q32: JV | R32: AEPGR | S32: TRANSOURCE | T32: ETT | U32: AEPSC
C33: AEG | D33: APCO | E33: I&M | F33: KENT | G33: KINGS | H33: OPCO | I33: WHEEL | J33: TOTAL | K33: PSO | L33: SWEPCO | M33: AEP TEXAS | N33: TOTAL | O33: TOTAL | P33: TOTAL | Q33: TOTAL | R33: TOTAL | S33: TOTAL | T33: TOTAL | U33: TOTAL
B34: =+$B$10 -> Sep-2022 | C34: 2078.31 | D34: 556665.57 | E34: 429349.84 | F34: 91079.18 | G34: 10831.07 | H34: 375010.3 | I34: 69306.13 | J34: 1534320.4 | K34: 321948.63 | L34: 356424.95 | M34: 364284.85 | N34: 1042658.4 | O34: 328282.91 | P34: 345056.5 | Q34: 3437.58 | R34: 10123.01 | S34: 10631.69 | T34: 46274.87 | U34: 3320785.4
B35: =+$B$11 -> 45199 | C35: 2560.99 | D35: 483185.77 | E35: 368142.66 | F35: 86845.78 | G35: 12585.58 | H35: 302456.77 | I35: 62787.42 | J35: 1318565 | K35: 265676.31 | L35: 297286.61 | M35: 326346.46 | N35: 889309.38 | O35: 202601.63 | P35: 295441.42 | Q35: 2099.59 | R35: 6436.02 | S35: 9367.59 | T35: 28979.94 | U35: 2752800.5
B36: Variance | C36: =+C35-C34 -> 482.68 | D36: =+D35-D34 -> -73479.8 | E36: =+E35-E34 -> -61207.18 | F36: =+F35-F34 -> -4233.4 | G36: =+G35-G34 -> 1754.51 | H36: =+H35-H34 -> -72553.53 | I36: =+I35-I34 -> -6518.71 | J36: =+J35-J34 -> -215755.43 | ... U36: =+U35-U34 -> -567984.85
B39: Relocation/Severance Variance (124, 142-144)
C40: EAST | J40: EAST | K40: WEST | N40: WEST | O40: NON-REG | P40: TRANSCO | Q40: JV | R40: AEPGR | S40: TRANSOURCE | T40: ETT | U40: AEPSC
C41: AEG | D41: APCO | E41: I&M | F41: KENT | G41: KINGS | H41: OPCO | I41: WHEEL | J41: TOTAL | K41: PSO | L41: SWEPCO | M41: AEP TEXAS | N41: TOTAL | O41: TOTAL | P41: TOTAL | Q41: TOTAL | R41: TOTAL | S41: TOTAL | T41: TOTAL | U41: TOTAL
B42: =+$B$10 -> Sep-2022 | C42: -1.61 | D42: 151768.78 | E42: 137703.09 | F42: 26894.39 | G42: 3004.56 | H42: 102114.99 | I42: 19343.45 | J42: 440827.65 | K42: 92077.03 | L42: 98887.19 | M42: 119294.55 | N42: 310258.77 | O42: 236.71 | P42: 138815.93 | Q42: 0.03 | R42: -12.99 | S42: 145.77 | T42: 4027.56 | U42: 894299.43
B43: =+$B$11 -> 45199 | C43: 16618.62 | D43: 387481.52 | E43: 266482.16 | F43: 98450.32 | G43: 41288.29 | H43: 418488.1 | I43: 68188.77 | J43: 1296997.8 | K43: 221052.36 | L43: 273257.71 | M43: 351370.39 | N43: 845680.46 | O43: 190079.06 | P43: 91249.56 | Q43: 639.13 | R43: 14116.07 | S43: 18628.95 | T43: 22500.48 | U43: 2479891.5
B44: Variance | C44: =+C43-C42 -> 16620.23 | D44: =+D43-D42 -> 235712.74 | E44: =+E43-E42 -> 128779.07 | F44: =+F43-F42 -> 71555.93 | G44: =+G43-G42 -> 38283.73 | H44: =+H43-H42 -> 316373.11 | I44: =+I43-I42 -> 48845.32 | J44: =+J43-J42 -> 856170.13 | ... U44: =+U43-U42 -> 1585592.1
B47: Outside Services Variance (2xx, 9AA, 9AB)
C48: EAST | J48: EAST | K48: WEST | N48: WEST | O48: NON-REG | P48: TRANSCO | Q48: JV | R48: AEPGR | S48: TRANSOURCE | T48: ETT | U48: AEPSC
C49: AEG | D49: APCO | E49: I&M | F49: KENT | G49: KINGS | H49: OPCO | I49: WHEEL | J49: TOTAL | K49: PSO | L49: SWEPCO | M49: AEP TEXAS | N49: TOTAL | O49: TOTAL | P49: TOTAL | Q49: TOTAL | R49: TOTAL | S49: TOTAL | T49: TOTAL | U49: TOTAL
B50: =+$B$10 -> Sep-2022 | C50: 4430.52 | D50: 2596117 | E50: 1516893 | F50: 294973.72 | G50: 73902.41 | H50: 1695173.5 | I50: 547725.28 | J50: 6729215.4 | K50: 1664544.4 | L50: 1804494.2 | M50: 1261081 | N50: 4730119.5 | O50: 814171.08 | P50: 690559.36 | Q50: 4982.94 | R50: 81776.31 | S50: 105821.19 | T50: 199016.45 | U50: 13355662
B51: =+$B$11 -> 45199 | C51: 5207.99 | D51: 1625020.1 | E51: 1212763.5 | F51: 245387.72 | G51: 39215.02 | H51: 1413365.8 | I51: 158536.57 | J51: 4699496.6 | K51: 874040.57 | L51: 1124036.2 | M51: 1028849.9 | N51: 3026926.7 | O51: -158775.22 | P51: 662255.47 | Q51: 5652.41 | R51: 8666.5 | S51: 51245.26 | T51: 126222.75 | U51: 8421690.5
B52: Variance | C52: =+C51-C50 -> 777.47 | D52: =+D51-D50 -> -971096.96 | E52: =+E51-E50 -> -304129.5 | F52: =+F51-F50 -> -49586 | G52: =+G51-G50 -> -34687.39 | H52: =+H51-H50 -> -281807.69 | I52: =+I51-I50 -> -389188.71 | J52: =+J51-J50 -> -2029718.8 | ... U52: =+U51-U50 -> -4933971.7
B55: Material & Supplies Variance (3xx)
C56: EAST | J56: EAST | K56: WEST | N56: WEST | O56: NON-REG | P56: TRANSCO | Q56: JV | R56: AEPGR | S56: TRANSOURCE | T56: ETT | U56: AEPSC
C57: AEG | D57: APCO | E57: I&M | F57: KENT | G57: KINGS | H57: OPCO | I57: WHEEL | J57: TOTAL | K57: PSO | L57: SWEPCO | M57: AEP TEXAS | N57: TOTAL | O57: TOTAL | P57: TOTAL | Q57: TOTAL | R57: TOTAL | S57: TOTAL | T57: TOTAL | U57: TOTAL
B58: =+$B$10 -> Sep-2022 | C58: 86.97 | D58: 261322.61 | E58: 147322.22 | F58: 60805.37 | G58: 6343.59 | H58: 280381.08 | I58: 25709.12 | J58: 781970.96 | K58: 118908.54 | L58: 127074.12 | M58: 86111.08 | N58: 332093.74 | O58: 22511.65 | P58: 140449.76 | Q58: 2.06 | R58: 2177.06 | S58: 2121.72 | T58: 32571.91 | U58: 1313898.9
B59: =+$B$11 -> 45199 | C59: 78.49 | D59: 134754.51 | E59: 52188.96 | F59: 43811.14 | G59: 1900.16 | H59: 150257.27 | I59: 15274.01 | J59: 398264.54 | K59: 65150.86 | L59: 54191.61 | M59: 52868.06 | N59: 172210.53 | O59: 4373.68 | P59: 58959.59 | Q59: 1.24 | R59: 284.1 | S59: 1563.71 | T59: 8205.42 | U59: 643862.81
B60: Variance | C60: =+C59-C58 -> -8.48 | D60: =+D59-D58 -> -126568.1 | E60: =+E59-E58 -> -95133.26 | F60: =+F59-F58 -> -16994.23 | G60: =+G59-G58 -> -4443.43 | H60: =+H59-H58 -> -130123.81 | I60: =+I59-I58 -> -10435.11 | J60: =+J59-J58 -> -383706.42 | ... U60: =+U59-U58 -> -670036.05
B63: Travel & Emp Exp Variance (4xx, 5xx)
C64: EAST | J64: EAST | K64: WEST | N64: WEST | O64: NON-REG | P64: TRANSCO | Q64: JV | R64: AEPGR | S64: TRANSOURCE | T64: ETT | U64: AEPSC
C65: AEG | D65: APCO | E65: I&M | F65: KENT | G65: KINGS | H65: OPCO | I65: WHEEL | J65: TOTAL | K65: PSO | L65: SWEPCO | M65: AEP TEXAS | N65: TOTAL | O65: TOTAL | P65: TOTAL | Q65: TOTAL | R65: TOTAL | S65: TOTAL | T65: TOTAL | U65: TOTAL
B66: =+$B$10 -> Sep-2022 | C66: 426.87 | D66: 142901.43 | E66: 169581.64 | F66: 41638.54 | G66: 3559.03 | H66: 93622.21 | I66: 14116.77 | J66: 465846.49 | K66: 75420.55 | L66: 84364.17 | M66: 119724.47 | N66: 279509.19 | O66: 13903.13 | P66: 139113.34 | Q66: 7862.98 | R66: 1220.14 | S66: 9578.42 | T66: 42536.11 | U66: 959569.8
B67: =+$B$11 -> 45199 | C67: 223.57 | D67: 68862.7 | E67: 110430.18 | F67: 7257.2 | G67: 467.79 | H67: 28420.93 | I67: 11530.96 | J67: 227193.33 | K67: 34959.7 | L67: 45377.38 | M67: 48940.67 | N67: 129277.75 | O67: 18415.08 | P67: 50028.55 | Q67: 4254.53 | R67: 276.57 | S67: 1449.71 | T67: 19753.31 | U67: 450648.83
B68: Variance | C68: =+C67-C66 -> -203.3 | D68: =+D67-D66 -> -74038.73 | E68: =+E67-E66 -> -59151.46 | F68: =+F67-F66 -> -34381.34 | G68: =+G67-G66 -> -3091.24 | H68: =+H67-H66 -> -65201.28 | I68: =+I67-I66 -> -2585.81 | J68: =+J67-J66 -> -238653.16 | ... U68: =+U67-U66 -> -508920.97
B71: Overhead & Shared Services Variance (6xx, 7xx)
C72: EAST | J72: EAST | K72: WEST | N72: WEST | O72: NON-REG | P72: TRANSCO | Q72: JV | R72: AEPGR | S72: TRANSOURCE | T72: ETT | U72: AEPSC
C73: AEG | D73: APCO | E73: I&M | F73: KENT | G73: KINGS | H73: OPCO | I73: WHEEL | J73: TOTAL | K73: PSO | L73: SWEPCO | M73: AEP TEXAS | N73: TOTAL | O73: TOTAL | P73: TOTAL | Q73: TOTAL | R73: TOTAL | S73: TOTAL | T73: TOTAL | U73: TOTAL
B74: =+$B$10 -> Sep-2022 | C74: 4741.54 | D74: 2591717 | E74: 1800838 | F74: 435048.36 | G74: 70014.9 | H74: 2093367.7 | I74: 212331.06 | J74: 7208058.6 | K74: 1266376.9 | L74: 1396988.4 | M74: 1428716.8 | N74: 4092082 | O74: 1646682.3 | P74: 1562718 | Q74: 7274.24 | R74: 21881 | S74: 35964.56 | T74: 302262.19 | U74: 14876923
B75: =+$B$11 -> 45199 | C75: 9412.92 | D75: 2264776.7 | E75: 1516008.6 | F75: 378996.64 | G75: 59898.48 | H75: 2115130.7 | I75: 214374.42 | J75: 6558598.4 | K75: 1338640 | L75: 1351558.3 | M75: 1493988.9 | N75: 4184187.2 | O75: 1692179.3 | P75: 1314199 | Q75: 7039.53 | R75: 14787.79 | S75: 46575.89 | T75: 489856.32 | U75: 14307423
B76: Variance | C76: =+C75-C74 -> 4671.38 | D76: =+D75-D74 -> -326940.35 | E76: =+E75-E74 -> -284829.41 | F76: =+F75-F74 -> -56051.72 | G76: =+G75-G74 -> -10116.42 | H76: =+H75-H74 -> 21762.94 | I76: =+I75-I74 -> 2043.36 | J76: =+J75-J74 -> -649460.22 | ... U76: =+U75-U74 -> -569499.53
B79: Other Variance (0xx, 9xx, REV)
C80: EAST | J80: EAST | K80: WEST | N80: WEST | O80: NON-REG | P80: TRANSCO | Q80: JV | R80: AEPGR | S80: TRANSOURCE | T80: ETT | U80: AEPSC
C81: AEG | D81: APCO | E81: I&M | F81: KENT | G81: KINGS | H81: OPCO | I81: WHEEL | J81: TOTAL | K81: PSO | L81: SWEPCO | M81: AEP TEXAS | N81: TOTAL | O81: TOTAL | P81: TOTAL | Q81: TOTAL | R81: TOTAL | S81: TOTAL | T81: TOTAL | U81: TOTAL
B82: =+$B$10 -> Sep-2022 | C82: 4401.53 | D82: 2235697.9 | E82: 1275672.3 | F82: 475209.39 | G82: 69361.51 | H82: 1739547 | I82: 67663.22 | J82: 5867552.8 | K82: 941922.74 | L82: 1253413 | M82: 1592023.5 | N82: 3787359.3 | O82: 527982.68 | P82: 1862608.7 | Q82: 17262.11 | R82: 12601.19 | S82: 33409.41 | T82: 235745 | U82: 12344521
B83: =+$B$11 -> 45199 | C83: 3563.47 | D83: 1754170.8 | E83: 951162.14 | F83: 244826.78 | G83: 50006.87 | H83: 1423107.8 | I83: 205172.56 | J83: 4632010.4 | K83: 741196.84 | L83: 991878.13 | M83: 1262249.3 | N83: 2995324.3 | O83: -303393.7 | P83: 1444537.7 | Q83: 122.29 | R83: 4803.87 | S83: 42517.56 | T83: 209064.15 | U83: 9024986.6
B84: Variance | C84: =+C83-C82 -> -838.06 | D84: =+D83-D82 -> -481527.14 | E84: =+E83-E82 -> -324510.12 | F84: =+F83-F82 -> -230382.61 | G84: =+G83-G82 -> -19354.64 | H84: =+H83-H82 -> -316439.13 | I84: =+I83-I82 -> 137509.34 | J84: =+J83-J82 -> -1235542.4 | ... U84: =+U83-U82 -> -3319534.6
B87: Total AEPSC Income Statement
C88: EAST | J88: EAST | K88: WEST | N88: WEST | O88: NON-REG | P88: TRANSCO | Q88: JV | R88: AEPGR | S88: TRANSOURCE | T88: ETT | U88: AEPSC
C89: AEG | D89: APCO | E89: I&M | F89: KENT | G89: KINGS | H89: OPCO | I89: WHEEL | J89: TOTAL | K89: PSO | L89: SWEPCO | M89: AEP TEXAS | N89: TOTAL | O89: TOTAL | P89: TOTAL | Q89: TOTAL | R89: TOTAL | S89: TOTAL | T89: TOTAL | U89: TOTAL | W89: ='Tab 1'!A60& " from:" -> AEPSC Bill Entries from:
B90: =+B82 -> Sep-2022 | C90: =SUMIF($B$1:$B$89,$B$90,C1:C89) -> 36134.49 | D90: =SUMIF($B$1:$B$89,$B$90,D1:D89) -> 15685924 | E90: =SUMIF($B$1:$B$89,$B$90,E1:E89) -> 9817586.2 | F90: =SUMIF($B$1:$B$89,$B$90,F1:F89) -> 2616055.8 | G90: =SUMIF($B$1:$B$89,$B$90,G1:G89) -> 374466.55 | H90: =SUMIF($B$1:$B$89,$B$90,H1:H89) -> 11755226 | I90: =SUMIF($B$1:$B$89,$B$90,I1:I89) -> 1677269.1 | J90: =SUMIF($B$1:$B$89,$B$90,J1:J89) -> 41962662 | ... U90: =SUMIF($B$1:$B$89,$B$90,U1:U89) -> 85458871 | W90: Tab 1
B91: =+B83 -> 45199 | C91: =SUMIF($B$1:$B$89,$B$91,C1:C89) -> 67431.62 | D91: =SUMIF($B$1:$B$89,$B$91,D1:D89) -> 11874285 | E91: =SUMIF($B$1:$B$89,$B$91,E1:E89) -> 7432132.8 | F91: =SUMIF($B$1:$B$89,$B$91,F1:F89) -> 1935888.6 | G91: =SUMIF($B$1:$B$89,$B$91,G1:G89) -> 305240.08 | H91: =SUMIF($B$1:$B$89,$B$91,H1:H89) -> 9593869.3 | I91: =SUMIF($B$1:$B$89,$B$91,I1:I89) -> 1264886.2 | J91: =SUMIF($B$1:$B$89,$B$91,J1:J89) -> 32473733 | ... U91: =SUMIF($B$1:$B$89,$B$91,U1:U89) -> 64563569 | W91: Amount | X91: Diff vs Tab2
B92: Variance | C92: =+C91-C90 -> 31297.13 | D92: =+D91-D90 -> -3811639.6 | E92: =+E91-E90 -> -2385453.4 | F92: =+F91-F90 -> -680167.15 | G92: =+G91-G90 -> -69226.47 | H92: =+H91-H90 -> -2161356.3 | I92: =+I91-I90 -> -412382.86 | J92: =+J91-J90 -> -9488928.7 | ... U92: =+U91-U90 -> -20895302 | W92: =+'Tab 1'!T66 -> -20895302 | X92: =+W92-U92 -> 1.0058284e-07

Sheet Tab 3
B2: American Electric Power Service Corporation Income Statement Variance Analysis Favorable/(Unfavorable)
B3: Billed + Manuals
B4: ( Favorable ) / Unfavorable
D5: EAST | K5: EAST | M5: WEST | P5: WEST | R5: NON-REG | S5: TRANSCO | T5: JV | U5: AEPGR | V5: TRANSOURCE | W5: ETT | Y5: AEPSC
B6: FERC Account Grouping | C6: FERC Account | D6: AEG | E6: APCO | F6: I&M | G6: KENT | H6: KINGS | I6: OPCO | J6: WHEEL | K6: TOTAL | M6: PSO | N6: SWEPCO | O6: AEP TEXAS | P6: TOTAL | R6: TOTAL | S6: TOTAL | T6: TOTAL | U6: TOTAL | V6: TOTAL | W6: TOTAL | Y6: TOTAL
B8: Other Income & Deductions | C8: 4171 Exps of Non-Utility Oper | F8: -16066.38 | K8: =SUM(D8:J8) -> -16066.38 | P8: =SUM(M8:O8) -> 0 | Y8: =+K8+P8+R8+S8+T8+U8+V8+W8 -> -16066.38
C9: 4210 Misc Non-Operating Income | D9: -1146.98 | E9: -10382.87 | F9: -230.43 | G9: -83.37 | H9: -8.12 | I9: -209.2 | J9: -9.75 | K9: =SUM(D9:J9) -> -12070.72 | M9: -102.7 | N9: -191.22 | O9: -133.2 | P9: =SUM(M9:O9) -> -427.12 | R9: -8.87 | S9: -191.75 | U9: -4.11 | V9: 0.83 | Y9: =+K9+P9+R9+S9+T9+U9+V9+W9 -> -12701.74
C10: 4261 Donations | D10: 3.26 | E10: 1428.58 | F10: 787.05 | G10: 283.73 | H10: 45.28 | I10: 1129.11 | J10: 91.63 | K10: =SUM(D10:J10) -> 3768.64 | M10: 589.42 | N10: 796.69 | O10: 979.99 | P10: =SUM(M10:O10) -> 2366.1 | R10: 16.8 | S10: 1173.99 | U10: 6.71 | Y10: =+K10+P10+R10+S10+T10+U10+V10+W10 -> 7332.24
C11: 4263 Penalties | D11: -0.01 | E11: -8.98 | F11: -8.21 | G11: -1.56 | H11: -0.18 | I11: -5.91 | J11: -1.16 | K11: =SUM(D11:J11) -> -26.01 | M11: -5.37 | N11: -5.67 | O11: -7.14 | P11: =SUM(M11:O11) -> -18.18 | R11: -0.62 | S11: -8.01 | U11: -0.26 | V11: -0.31 | W11: -2.09 | Y11: =+K11+P11+R11+S11+T11+U11+V11+W11 -> -55.48
C12: 4264 Civic & Political Activities | D12: -117.91 | E12: -72378.39 | F12: -66494 | G12: -12796.72 | H12: -1407.71 | I12: -54933.65 | J12: -8931.85 | K12: =SUM(D12:J12) -> -217060.23 | M12: 113674.49 | N12: -45568.08 | O12: -54530 | P12: =SUM(M12:O12) -> 13576.41 | R12: -5401.98 | S12: -60760.8 | U12: -1493.08 | V12: -79.65 | W12: 184883.2 | Y12: =+K12+P12+R12+S12+T12+U12+V12+W12 -> -86336.13
C13: 4265 Other Deductions | D13: -32.64 | E13: -21409.35 | F13: -18166.12 | G13: -4057.21 | H13: -423.24 | I13: -14799.04 | J13: -15874.87 | K13: =SUM(D13:J13) -> -74762.47 | M13: -12195.85 | N13: -13486.33 | O13: -17031.32 | P13: =SUM(M13:O13) -> -42713.5 | R13: -1479.73 | S13: -19144.03 | U13: -608.1 | V13: -20.77 | Y13: =+K13+P13+R13+S13+T13+U13+V13+W13 -> -138728.6
B14: Other Income & Deductions Total | D14: -1294.28 | E14: -102751.01 | F14: -100178.09 | G14: -16655.13 | H14: -1793.97 | I14: -68818.69 | J14: -24726 | K14: =SUM(D14:J14) -> -316217.17 | M14: 101959.99 | N14: -58454.61 | O14: -70721.67 | P14: =SUM(M14:O14) -> -27216.29 | R14: -6874.4 | S14: -78930.6 | U14: -2098.84 | V14: -99.9 | W14: 184881.11 | Y14: =+K14+P14+R14+S14+T14+U14+V14+W14 -> -246556.09
B15: Steam Power Generation Expenses | C15: 5000 Oper Supv and Eng | D15: 592.58 | E15: -746558.19 | F15: -404469.39 | G15: -82373.85 | H15: 299.52 | I15: 6910.8 | J15: -164769.42 | K15: =SUM(D15:J15) -> -1390368 | M15: -549100.02 | N15: -648462.83 | O15: 20832.75 | P15: =SUM(M15:O15) -> -1176730.1 | R15: -457.54 | S15: 12677.68 | T15: 0.09 | U15: 2080.97 | V15: 95.05 | W15: 418.73 | Y15: =+K15+P15+R15+S15+T15+U15+V15+W15 -> -2552283.1
C16: 5010 Fuel | D16: 0.94 | E16: 52225.5 | F16: 5184.56 | G16: 7167.2 | H16: -16.73 | I16: -511.69 | J16: 4453.66 | K16: =SUM(D16:J16) -> 68503.44 | M16: 49101.27 | N16: 61157.23 | O16: -450.42 | P16: =SUM(M16:O16) -> 109808.08 | R16: -298.01 | S16: -581.79 | U16: -1837.18 | Y16: =+K16+P16+R16+S16+T16+U16+V16+W16 -> 175594.54
C17: 5020 Steam Exps | E17: -2660.67 | F17: -226.23 | G17: -1.58 | J17: -2769.76 | K17: =SUM(D17:J17) -> -5658.24 | M17: -585.63 | N17: -6453.87 | P17: =SUM(M17:O17) -> -7039.5 | U17: 0.25 | Y17: =+K17+P17+R17+S17+T17+U17+V17+W17 -> -12697.49
C18: 5060 Misc Steam Pwr Exps | D18: -5.2 | E18: -13365.65 | F18: -4126.81 | G18: -1260.53 | H18: -139.79 | I18: -4686.52 | J18: 5529.77 | K18: =SUM(D18:J18) -> -18054.73 | M18: -36630.96 | N18: -20688.72 | O18: -5182.31 | P18: =SUM(M18:O18) -> -62501.99 | R18: -16.35 | S18: -15028.57 | U18: 183.5 | V18: 93.37 | W18: 894.74 | Y18: =+K18+P18+R18+S18+T18+U18+V18+W18 -> -94430.03
C19: 5100 Maint Supv & Eng | E19: 25137.31 | F19: 35485.95 | G19: 1238.15 | H19: -0.03 | I19: -3.24 | J19: -2905.47 | K19: =SUM(D19:J19) -> 58952.67 | M19: -704.45 | N19: 6217.6 | O19: -4.1 | P19: =SUM(M19:O19) -> 5509.05 | S19: -1.53 | Y19: =+K19+P19+R19+S19+T19+U19+V19+W19 -> 64460.19
C20: 5110 Maint of Structures | E20: 33268.21 | F20: -129.29 | G20: -172.73 | J20: -5861.59 | K20: =SUM(D20:J20) -> 27104.6 | M20: 5874.22 | N20: -3695.59 | P20: =SUM(M20:O20) -> 2178.63 | Y20: =+K20+P20+R20+S20+T20+U20+V20+W20 -> 29283.23
C21: 5120 Maint of Boiler Plant | E21: -24800.77 | F21: 2669.79 | G21: 4842 | H21: 0.36 | I21: 34.47 | J21: 16919.01 | K21: =SUM(D21:J21) -> -335.14 | M21: 14561.57 | N21: 880.03 | O21: 59.36 | P21: =SUM(M21:O21) -> 15500.96 | S21: 40.83 | Y21: =+K21+P21+R21+S21+T21+U21+V21+W21 -> 15206.65
C22: 5130 Maint of Electric Plant | E22: 14299.06 | F22: -21875.8 | G22: -112683 | H22: -0.43 | I22: -48.31 | J22: -31168.05 | K22: =SUM(D22:J22) -> -151476.53 | M22: -24019.24 | N22: -7797.39 | O22: -61.46 | P22: =SUM(M22:O22) -> -31878.09 | S22: -23.35 | Y22: =+K22+P22+R22+S22+T22+U22+V22+W22 -> -183377.97
C23: 5140 Maint of Misc Steam Plt | E23: 7981 | F23: -1335.04 | G23: 3195.39 | H23: -0.06 | I23: -6.93 | J23: 2648.91 | K23: =SUM(D23:J23) -> 12483.27 | M23: -3110.65 | N23: -18607.27 | O23: -8.77 | P23: =SUM(M23:O23) -> -21726.69 | S23: -3.31 | U23: -0.43 | Y23: =+K23+P23+R23+S23+T23+U23+V23+W23 -> -9247.16
B24: Steam Power Generation Expenses Total | D24: 588.32 | E24: -654474.2 | F24: -388822.26 | G24: -180048.95 | H24: 142.84 | I24: 1688.58 | J24: -177922.94 | K24: =SUM(D24:J24) -> -1398848.6 | M24: -544613.89 | N24: -637450.81 | O24: 15185.05 | P24: =SUM(M24:O24) -> -1166879.6 | R24: -771.9 | S24: -2920.04 | T24: 0.09 | U24: 427.11 | V24: 188.42 | W24: 1313.47 | Y24: =+K24+P24+R24+S24+T24+U24+V24+W24 -> -2567491.1
B25: Nuclear Power Generation | C25: 5170 Oper Supv & Eng | D25: -0.05 | E25: -20.83 | F25: 1932.27 | G25: -4.28 | H25: -0.63 | I25: -16.38 | J25: -1.18 | K25: =SUM(D25:J25) -> 1888.92 | M25: -7.79 | N25: -11.56 | O25: -14.23 | P25: =SUM(M25:O25) -> -33.58 | R25: -0.26 | S25: -17.22 | U25: -0.13 | Y25: =+K25+P25+R25+S25+T25+U25+V25+W25 -> 1837.73
C26: 5240 Misc Nuclear Power Exps | D26: -4.13 | E26: -958.65 | F26: -370249.87 | G26: -224.98 | H26: -23.96 | I26: -838.94 | J26: -26.58 | K26: =SUM(D26:J26) -> -372327.11 | M26: -435.34 | N26: -591.32 | O26: -830.71 | P26: =SUM(M26:O26) -> -1857.37 | R26: -13.48 | S26: -640.99 | U26: -7.77 | Y26: =+K26+P26+R26+S26+T26+U26+V26+W26 -> -374846.72
C27: 5280 Maint Supv & Eng | D27: 0.7 | E27: -150.02 | F27: -10.83 | G27: 24.54 | H27: 5.07 | I27: 154.84 | J27: -69.94 | K27: =SUM(D27:J27) -> -45.64 | M27: -128.31 | N27: -335.92 | O27: 136.3 | P27: =SUM(M27:O27) -> -327.93 | R27: 3.84 | S27: 176.03 | U27: 2.14 | Y27: =+K27+P27+R27+S27+T27+U27+V27+W27 -> -191.56
C28: 5300 Maint of Reactor Plant Equip | D28: -0.33 | E28: -3785.61 | F28: -120155.75 | G28: -9673.53 | H28: 8.75 | I28: 133.03 | J28: 8683.86 | K28: =SUM(D28:J28) -> -124789.58 | M28: 56.95 | N28: 86.16 | O28: 103.7 | P28: =SUM(M28:O28) -> 246.81 | R28: -2.62 | S28: 92.07 | U28: -2.84 | W28: -3.26 | Y28: =+K28+P28+R28+S28+T28+U28+V28+W28 -> -124459.42
B29: Nuclear Power Generation Total | D29: -3.81 | E29: -4915.11 | F29: -488484.18 | G29: -9878.25 | H29: -10.77 | I29: -567.45 | J29: 8586.16 | K29: =SUM(D29:J29) -> -495273.41 | M29: -514.49 | N29: -852.64 | O29: -604.94 | P29: =SUM(M29:O29) -> -1972.07 | R29: -12.52 | S29: -390.11 | U29: -8.6 | W29: -3.26 | Y29: =+K29+P29+R29+S29+T29+U29+V29+W29 -> -497659.97
B30: Hydraulic Power Generation | C30: 5350 Oper Supv & Eng | E30: 21633.44 | F30: -20855.37 | G30: 123.95 | J30: 107.07 | K30: =SUM(D30:J30) -> 1009.09 | M30: 309.42 | N30: 421.34 | P30: =SUM(M30:O30) -> 730.76 | Y30: =+K30+P30+R30+S30+T30+U30+V30+W30 -> 1739.85
C31: 5370 Hydraulic Expenses | E31: -20395.89 | F31: -7922.9 | G31: -175.87 | J31: -128.71 | K31: =SUM(D31:J31) -> -28623.37 | M31: -637.08 | N31: -857.02 | P31: =SUM(M31:O31) -> -1494.1 | Y31: =+K31+P31+R31+S31+T31+U31+V31+W31 -> -30117.47
C32: 5380 Electric Expenses | E32: 4868.03 | F32: -1380.45 | K32: =SUM(D32:J32) -> 3487.58 | P32: =SUM(M32:O32) -> 0 | Y32: =+K32+P32+R32+S32+T32+U32+V32+W32 -> 3487.58
C33: 5390 Misc Hydr Pwr Gen Exp | E33: -28793.61 | F33: -26314.15 | G33: -11.47 | H33: -0.62 | I33: -80.01 | J33: 19.22 | K33: =SUM(D33:J33) -> -55180.64 | M33: -277.75 | N33: -374.76 | O33: -101.39 | P33: =SUM(M33:O33) -> -753.9 | S33: -38.21 | Y33: =+K33+P33+R33+S33+T33+U33+V33+W33 -> -55972.75
C34: 5400 Rents | E34: -25.68 | F34: -10.23 | I34: -418.98 | K34: =SUM(D34:J34) -> -454.89 | P34: =SUM(M34:O34) -> 0 | Y34: =+K34+P34+R34+S34+T34+U34+V34+W34 -> -454.89
C35: 5410 Maint Supv & Eng | E35: 6370.64 | F35: -326.25 | K35: =SUM(D35:J35) -> 6044.39 | P35: =SUM(M35:O35) -> 0 | Y35: =+K35+P35+R35+S35+T35+U35+V35+W35 -> 6044.39
C36: 5420 Maint of Structures | E36: -2544.84 | F36: -4594.38 | G36: 40.89 | J36: 43.32 | K36: =SUM(D36:J36) -> -7055.01 | M36: 38.23 | N36: 51.46 | P36: =SUM(M36:O36) -> 89.69 | U36: -27 | Y36: =+K36+P36+R36+S36+T36+U36+V36+W36 -> -6992.32
C37: 5430 Maint Rsrvoirs,Dams,&Wtrways | E37: 6469.33 | F37: -558.41 | G37: 900.14 | J37: 33.95 | K37: =SUM(D37:J37) -> 6845.01 | M37: 103.55 | N37: 139.34 | P37: =SUM(M37:O37) -> 242.89 | Y37: =+K37+P37+R37+S37+T37+U37+V37+W37 -> 7087.9
C38: 5440 Maint of Electric Plant | E38: -44401.85 | F38: 12119.32 | G38: 763.25 | H38: -1.06 | I38: -130.34 | J38: 277.42 | K38: =SUM(D38:J38) -> -31373.26 | M38: -66.31 | N38: -95.58 | O38: -169.06 | P38: =SUM(M38:O38) -> -330.95 | S38: -68.29 | Y38: =+K38+P38+R38+S38+T38+U38+V38+W38 -> -31772.5
C39: 5450 Maint of Misc Hydraulic Plant | D39: -0.38 | E39: 142.42 | F39: -17.63 | G39: -27.23 | H39: -2.64 | I39: -82.84 | J39: -1.58 | K39: =SUM(D39:J39) -> 10.12 | M39: -2141.85 | N39: -59.62 | O39: 208.51 | P39: =SUM(M39:O39) -> -1992.96 | R39: -2.14 | S39: -95.17 | U39: -1.23 | Y39: =+K39+P39+R39+S39+T39+U39+V39+W39 -> -2081.38
B40: Hydraulic Power Generation Total | D40: -0.38 | E40: -56678.01 | F40: -49860.45 | G40: 1613.66 | H40: -4.32 | I40: -712.17 | J40: 350.69 | K40: =SUM(D40:J40) -> -105290.98 | M40: -2671.79 | N40: -774.84 | O40: -61.94 | P40: =SUM(M40:O40) -> -3508.57 | R40: -2.14 | S40: -201.67 | U40: -28.23 | Y40: =+K40+P40+R40+S40+T40+U40+V40+W40 -> -109031.59
B41: Other Power Generation | C41: 5460 Oper Supv & Eng | E41: 2412.05 | F41: 870.3 | G41: 350.96 | J41: 328.59 | K41: =SUM(D41:J41) -> 3961.9 | M41: 31082.55 | N41: 2644.43 | P41: =SUM(M41:O41) -> 33726.98 | U41: 15.2 | Y41: =+K41+P41+R41+S41+T41+U41+V41+W41 -> 37704.08
C42: 5470 Fuel Gas Turbine | E42: -1326.8 | K42: =SUM(D42:J42) -> -1326.8 | M42: -17.97 | N42: -24.04 | P42: =SUM(M42:O42) -> -42.01 | Y42: =+K42+P42+R42+S42+T42+U42+V42+W42 -> -1368.81
C43: 5480 Generation Exps | E43: 433.44 | F43: 172 | G43: 120.1 | K43: =SUM(D43:J43) -> 725.54 | M43: 39.83 | N43: 338.72 | P43: =SUM(M43:O43) -> 378.55 | Y43: =+K43+P43+R43+S43+T43+U43+V43+W43 -> 1104.09
C44: 5490 Misc Other Powr Gen Exp | E44: -1971.54 | F44: -14908.34 | G44: -152.87 | J44: -48.2 | K44: =SUM(D44:J44) -> -17080.95 | M44: 644.31 | N44: -582.09 | P44: =SUM(M44:O44) -> 62.22 | U44: 2.19 | Y44: =+K44+P44+R44+S44+T44+U44+V44+W44 -> -17016.54
C45: 5500 Rents | D45: -0.46 | E45: 840.21 | F45: -63.87 | G45: -25.77 | H45: -0.2 | I45: -44.12 | J45: 8.15 | K45: =SUM(D45:J45) -> 713.94 | M45: -1081.7 | N45: -33.8 | O45: -40.95 | P45: =SUM(M45:O45) -> -1156.45 | R45: -2.76 | S45: -66.52 | U45: -1.94 | Y45: =+K45+P45+R45+S45+T45+U45+V45+W45 -> -513.73
C46: 5530 Maint of Generating Plant | E46: 747.21 | F46: 8369.61 | G46: 138.02 | J46: 69.84 | K46: =SUM(D46:J46) -> 9324.68 | M46: -11664.52 | N46: 922.4 | P46: =SUM(M46:O46) -> -10742.12 | U46: 1 | Y46: =+K46+P46+R46+S46+T46+U46+V46+W46 -> -1416.44
B47: Other Power Generation Total | D47: -0.46 | E47: 1134.57 | F47: -5560.3 | G47: 430.44 | H47: -0.2 | I47: -44.12 | J47: 358.38 | K47: =SUM(D47:J47) -> -3681.69 | M47: 19002.5 | N47: 3265.62 | O47: -40.95 | P47: =SUM(M47:O47) -> 22227.17 | R47: -2.76 | S47: -66.52 | U47: 16.45 | Y47: =+K47+P47+R47+S47+T47+U47+V47+W47 -> 18492.65
B48: Other Power Supply Exps | C48: 5560 Sys Control & Load Dispatching | E48: -7215.85 | F48: -23723.57 | G48: -1632.49 | H48: 3.09 | I48: 95.12 | J48: -2588.07 | K48: =SUM(D48:J48) -> -35061.77 | M48: 14025.4 | N48: -8274.98 | P48: =SUM(M48:O48) -> 5750.42 | R48: -1334.88 | S48: -462.43 | V48: -101.23 | Y48: =+K48+P48+R48+S48+T48+U48+V48+W48 -> -31209.89
C49: 5570 Other Expenses | D49: -9.76 | E49: -87780.86 | F49: -32868.58 | G49: -10250.37 | H49: 38.63 | I49: -3445.25 | J49: -14279.55 | K49: =SUM(D49:J49) -> -148595.74 | M49: -33215.58 | N49: -60560.73 | O49: -2253.86 | P49: =SUM(M49:O49) -> -96030.17 | R49: -22145.9 | S49: -5380.8 | T49: -0.08 | U49: 2191.71 | V49: -41.17 | W49: 84.04 | Y49: =+K49+P49+R49+S49+T49+U49+V49+W49 -> -269918.11
B50: Other Power Supply Exps Total | D50: -9.76 | E50: -94996.71 | F50: -56592.15 | G50: -11882.86 | H50: 41.72 | I50: -3350.13 | J50: -16867.62 | K50: =SUM(D50:J50) -> -183657.51 | M50: -19190.18 | N50: -68835.71 | O50: -2253.86 | P50: =SUM(M50:O50) -> -90279.75 | R50: -23480.78 | S50: -5843.23 | T50: -0.08 | U50: 2191.71 | V50: -142.4 | W50: 84.04 | Y50: =+K50+P50+R50+S50+T50+U50+V50+W50 -> -301128
B51: Transmission Exps | C51: 5600 Oper Supv & Eng | D51: -462.71 | E51: -407438.31 | F51: -236265.23 | G51: -54262.07 | H51: -6714.43 | I51: -390763.03 | J51: -17910.4 | K51: =SUM(D51:J51) -> -1113816.2 | M51: -150577.38 | N51: -217080.88 | O51: -515678.26 | P51: =SUM(M51:O51) -> -883336.52 | R51: -1271.86 | S51: -817520.73 | T51: -10.76 | U51: 54.81 | V51: -21361.29 | W51: -178944.95 | Y51: =+K51+P51+R51+S51+T51+U51+V51+W51 -> -3016207.5
C52: 5612 Load Dispatch-Mntr&Op TransSys | E52: 360.68 | F52: -6410.55 | G52: -734.31 | H52: -224.56 | I52: -11373.25 | J52: -556.68 | K52: =SUM(D52:J52) -> -18938.67 | M52: -2619.58 | N52: -2401.08 | O52: 76050.18 | P52: =SUM(M52:O52) -> 71029.52 | S52: -10883.9 | T52: -0.17 | U52: 9.34 | V52: -152.4 | W52: 33112.83 | Y52: =+K52+P52+R52+S52+T52+U52+V52+W52 -> 74176.55
C53: 5613 Load Dispatch-Trans Srvc&Sched | K53: =SUM(D53:J53) -> 0 | M53: 180.61 | N53: 274.87 | O53: 560.38 | P53: =SUM(M53:O53) -> 1015.86 | S53: 57.79 | V53: 11.09 | W53: 81.54 | Y53: =+K53+P53+R53+S53+T53+U53+V53+W53 -> 1166.28
C54: 5614 PJM Adm - SSC & PS-OSS | K54: =SUM(D54:J54) -> 0 | O54: -5022.86 | P54: =SUM(M54:O54) -> -5022.86 | Y54: =+K54+P54+R54+S54+T54+U54+V54+W54 -> -5022.86
C55: 5615 Reliability,Plng&Stds Develop | D55: -0.09 | E55: -2946.48 | F55: -960.13 | G55: -579.42 | H55: -6.05 | I55: -71.94 | J55: -75.14 | K55: =SUM(D55:J55) -> -4639.25 | M55: -165.72 | N55: 763.82 | O55: 2396.08 | P55: =SUM(M55:O55) -> 2994.18 | R55: -0.55 | S55: 3744.96 | T55: 0.24 | U55: -1.03 | V55: 95.32 | W55: -372.89 | Y55: =+K55+P55+R55+S55+T55+U55+V55+W55 -> 1820.98
C56: 5620 Station Expenses | D56: 0.05 | E56: -34877.92 | F56: 269.39 | G56: -7961.69 | H56: -4747.6 | I56: -9674.61 | J56: -953.27 | K56: =SUM(D56:J56) -> -57945.65 | M56: -1090.57 | N56: 233.29 | O56: -4275.59 | P56: =SUM(M56:O56) -> -5132.87 | R56: 0.27 | S56: -24064.59 | T56: -0.01 | U56: 0.14 | W56: -7176.09 | Y56: =+K56+P56+R56+S56+T56+U56+V56+W56 -> -94318.8
C57: 5630 Overhead Line Exps | D57: -0.05 | E57: -3427.72 | F57: -3182.49 | G57: 260.06 | H57: -31.54 | I57: -3281.8 | J57: -99.98 | K57: =SUM(D57:J57) -> -9763.52 | M57: 2843.45 | N57: 893.63 | O57: -4068.72 | P57: =SUM(M57:O57) -> -331.64 | R57: -0.23 | S57: -15163.39 | T57: -0.15 | U57: -0.21 | V57: -271.67 | W57: -1923.87 | Y57: =+K57+P57+R57+S57+T57+U57+V57+W57 -> -27454.68
C58: 5660 Misc Trans Exps | D58: 467.45 | E58: -103570.84 | F58: -46008.63 | G58: -4935.44 | H58: -3874.83 | I58: -104600.16 | J58: -2613.87 | K58: =SUM(D58:J58) -> -265136.32 | M58: -31472.14 | N58: -41241.29 | O58: -66763.83 | P58: =SUM(M58:O58) -> -139477.26 | R58: -9.46 | S58: -78726.11 | T58: 77.43 | U58: 18.05 | V58: -34466.89 | W58: -51864.68 | Y58: =+K58+P58+R58+S58+T58+U58+V58+W58 -> -569585.24
C59: 5670 Rents | E59: 14.02 | K59: =SUM(D59:J59) -> 14.02 | P59: =SUM(M59:O59) -> 0 | S59: 24.1 | Y59: =+K59+P59+R59+S59+T59+U59+V59+W59 -> 38.12
C60: 5680 Maint Supv & Eng | E60: -1314.71 | F60: -2693.41 | G60: -616.28 | H60: -25.15 | I60: -2255.19 | J60: -38.66 | K60: =SUM(D60:J60) -> -6943.4 | M60: 10008.66 | N60: -701.35 | O60: -6065.47 | P60: =SUM(M60:O60) -> 3241.84 | S60: -785.31 | V60: -2.13 | W60: -2515.68 | Y60: =+K60+P60+R60+S60+T60+U60+V60+W60 -> -7004.68
C61: 5690 Maint of Structures | E61: 2673.71 | F61: -754.57 | G61: -549.41 | H61: -11.37 | I61: -2374.57 | J61: -231.16 | K61: =SUM(D61:J61) -> -1247.37 | M61: -464.03 | N61: -675.7 | O61: -1408.27 | P61: =SUM(M61:O61) -> -2548 | S61: -7524.21 | W61: -3670.95 | Y61: =+K61+P61+R61+S61+T61+U61+V61+W61 -> -14990.53
C62: 5691 Maint of Computer Hardware | D62: 0.14 | E62: 3318.61 | F62: 1207.96 | G62: 497.83 | H62: 48.56 | I62: 2353.86 | J62: 116.32 | K62: =SUM(D62:J62) -> 7543.28 | M62: -37.17 | N62: -49.09 | O62: -137.24 | P62: =SUM(M62:O62) -> -223.5 | R62: 0.61 | S62: 9496.27 | T62: 0.02 | U62: 0.03 | V62: -2.93 | Y62: =+K62+P62+R62+S62+T62+U62+V62+W62 -> 16813.78
C63: 5692 Maint of Computer Software | D63: 24.93 | E63: 24281.07 | F63: 9668.58 | G63: 3651.04 | H63: 491.77 | I63: 20141.1 | J63: 958.29 | K63: =SUM(D63:J63) -> 59216.78 | M63: 7882.22 | N63: 11030.33 | O63: 30770.84 | P63: =SUM(M63:O63) -> 49683.39 | R63: -48.82 | S63: 57240.58 | T63: 1.95 | U63: -4.47 | V63: 1894.21 | W63: 13185.91 | Y63: =+K63+P63+R63+S63+T63+U63+V63+W63 -> 181169.53
C64: 5700 Maint of Station Equip | D64: -0.26 | E64: -140074.84 | F64: -22030.56 | G64: 29752.13 | H64: -872.81 | I64: -201387.91 | J64: -5269.53 | K64: =SUM(D64:J64) -> -339883.78 | M64: -29274.35 | N64: -27031.59 | O64: -54464.35 | P64: =SUM(M64:O64) -> -110770.29 | R64: -1.51 | S64: -242495.33 | T64: -0.1 | U64: -1.3 | V64: 517.86 | W64: -38236.99 | Y64: =+K64+P64+R64+S64+T64+U64+V64+W64 -> -730871.44
C65: 5710 Maint of Overhead Lines | D65: -0.25 | E65: -32360.12 | F65: -11823.42 | G65: -86648.94 | H65: -29.67 | I65: 49603.37 | J65: -1298.57 | K65: =SUM(D65:J65) -> -82557.6 | M65: 22065.01 | N65: -1789.2 | O65: 39214 | P65: =SUM(M65:O65) -> 59489.81 | R65: -1.44 | S65: 24624.98 | T65: -0.02 | U65: -0.85 | V65: -11.19 | W65: 4227.62 | Y65: =+K65+P65+R65+S65+T65+U65+V65+W65 -> 5771.31
C66: 5720 Maint of Underground Lines | E66: -148.79 | F66: -103.11 | G66: -37.43 | H66: -1.55 | I66: 2683.61 | J66: -5.65 | K66: =SUM(D66:J66) -> 2387.08 | M66: -87.14 | N66: -391.84 | O66: -243.96 | P66: =SUM(M66:O66) -> -722.94 | S66: 4638.28 | Y66: =+K66+P66+R66+S66+T66+U66+V66+W66 -> 6302.42
C67: 5730 Maint of Misc Trans Plt | D67: -16.61 | E67: -589.74 | F67: -940.77 | G67: -220.33 | H67: -2624.86 | I67: 8440.85 | J67: -98 | K67: =SUM(D67:J67) -> 3950.54 | M67: -1809.91 | N67: -613.49 | O67: -405.82 | P67: =SUM(M67:O67) -> -2829.22 | S67: 15573.62 | T67: 0.01 | V67: 21.89 | W67: 151.6 | Y67: =+K67+P67+R67+S67+T67+U67+V67+W67 -> 16868.44
B68: Transmission Exps Total | D68: 12.6 | E68: -696101.38 | F68: -320026.94 | G68: -122384.26 | H68: -18624.09 | I68: -642559.67 | J68: -28076.3 | K68: =SUM(D68:J68) -> -1827760 | M68: -174618.04 | N68: -278779.57 | O68: -509542.89 | P68: =SUM(M68:O68) -> -962940.5 | R68: -1332.99 | S68: -1081763 | T68: 68.44 | U68: 74.51 | V68: -53728.13 | W68: -233946.6 | Y68: =+K68+P68+R68+S68+T68+U68+V68+W68 -> -4161328.3
B69: Distribution Exps | C69: 5800 Oper Supv & Eng | D69: -7.61 | E69: -31470.08 | F69: -43719.17 | G69: -1982.71 | H69: -1625.14 | I69: -65512.56 | J69: -2209.52 | K69: =SUM(D69:J69) -> -146526.79 | M69: -28878.29 | N69: -29430.47 | O69: -70407.45 | P69: =SUM(M69:O69) -> -128716.21 | R69: -41.49 | S69: -11745.44 | U69: -25.79 | V69: -8.85 | W69: -58.82 | Y69: =+K69+P69+R69+S69+T69+U69+V69+W69 -> -287123.39
C70: 5810 Load Dispatching | D70: -0.15 | E70: -67.25 | F70: -33.52 | G70: -12.01 | H70: -2.49 | I70: -48.46 | J70: -5.41 | K70: =SUM(D70:J70) -> -169.29 | M70: -23.25 | N70: -211.43 | O70: -36.37 | P70: =SUM(M70:O70) -> -271.05 | R70: -0.79 | S70: -56.89 | U70: -0.26 | Y70: =+K70+P70+R70+S70+T70+U70+V70+W70 -> -498.28
C71: 5820 Station Expenses | D71: 0.01 | E71: -22652.85 | F71: -11137.32 | G71: -8099.24 | H71: 1015.54 | I71: -59817.29 | J71: -5179.53 | K71: =SUM(D71:J71) -> -105870.68 | M71: -9568.22 | N71: -11783.56 | O71: -19658.96 | P71: =SUM(M71:O71) -> -41010.74 | R71: 0.06 | S71: -2166.72 | U71: 0.03 | W71: 8.75 | Y71: =+K71+P71+R71+S71+T71+U71+V71+W71 -> -149039.3
C72: 5830 Overhead Lines Expenses | D72: 0.08 | E72: 71.99 | F72: 75.33 | G72: 18.47 | H72: 0.35 | I72: -389.32 | J72: 2.46 | K72: =SUM(D72:J72) -> -220.64 | M72: 38.19 | N72: 57.56 | O72: -1293.04 | P72: =SUM(M72:O72) -> -1197.29 | R72: 0.43 | S72: 4784.76 | U72: 0.24 | Y72: =+K72+P72+R72+S72+T72+U72+V72+W72 -> 3367.5
C73: 5840 Underground Line Expenses | E73: -4106.17 | F73: -2151.96 | G73: -750.54 | H73: -172.99 | I73: -5408.03 | J73: -151.58 | K73: =SUM(D73:J73) -> -12741.27 | M73: -1951.06 | N73: -2110.39 | O73: -4331.14 | P73: =SUM(M73:O73) -> -8392.59 | S73: -2968.17 | Y73: =+K73+P73+R73+S73+T73+U73+V73+W73 -> -24102.03
C74: 5860 Meter Expenses | D74: -0.16 | E74: -693.33 | F74: 196.17 | G74: -667.91 | H74: 9.18 | I74: -1306.16 | J74: -46.46 | K74: =SUM(D74:J74) -> -2508.67 | M74: 907.59 | N74: 620.22 | O74: -8585.65 | P74: =SUM(M74:O74) -> -7057.84 | R74: -0.54 | S74: -533.82 | U74: 0.2 | Y74: =+K74+P74+R74+S74+T74+U74+V74+W74 -> -10100.67
C75: 5870 Customer Installations Expenses | E75: 25280.03 | F75: 7341.94 | G75: -45.26 | H75: 23.86 | I75: 27737.49 | J75: 7.44 | K75: =SUM(D75:J75) -> 60345.5 | M75: 9884.97 | N75: 35202.81 | O75: 40926.94 | P75: =SUM(M75:O75) -> 86014.72 | S75: -206.07 | V75: -0.1 | Y75: =+K75+P75+R75+S75+T75+U75+V75+W75 -> 146154.05
C76: 5880 Misc Distribution Exp | D76: -18.53 | E76: -413275.55 | F76: -225004.32 | G76: -63904.19 | H76: -21678.74 | I76: -575921.22 | J76: -15556.01 | K76: =SUM(D76:J76) -> -1315358.6 | M76: -219261.35 | N76: -189809.79 | O76: -390774.09 | P76: =SUM(M76:O76) -> -799845.23 | R76: -240.42 | S76: 10795.27 | T76: 0.47 | U76: -27.33 | V76: 492.49 | W76: 3467.92 | Y76: =+K76+P76+R76+S76+T76+U76+V76+W76 -> -2100715.4
C77: 5900 Maint Supv & Eng | E77: -891.3 | F77: -513.85 | G77: -190.61 | H77: -29.26 | I77: -5159.7 | J77: -25.84 | K77: =SUM(D77:J77) -> -6810.56 | M77: -387.09 | N77: -491.47 | O77: -825.63 | P77: =SUM(M77:O77) -> -1704.19 | S77: -753.99 | Y77: =+K77+P77+R77+S77+T77+U77+V77+W77 -> -9268.74
C78: 5910 Maint of Structures | E78: -1689.06 | F78: 41 | G78: -892.02 | H78: 0.62 | I78: 73.4 | J78: -2633.65 | K78: =SUM(D78:J78) -> -5099.71 | M78: 28.36 | N78: 48.7 | O78: 100.67 | P78: =SUM(M78:O78) -> 177.73 | S78: 46.97 | Y78: =+K78+P78+R78+S78+T78+U78+V78+W78 -> -4875.01
C79: 5920 Maint of Station Equipment | D79: -0.1 | E79: 28193.86 | F79: 7654.38 | G79: -34025.88 | H79: -1178.6 | I79: -127875.44 | J79: 12672.41 | K79: =SUM(D79:J79) -> -114559.37 | M79: 1199.64 | N79: -7263.34 | O79: -9135.01 | P79: =SUM(M79:O79) -> -15198.71 | R79: -0.58 | S79: -6908.43 | U79: -0.32 | W79: 15.04 | Y79: =+K79+P79+R79+S79+T79+U79+V79+W79 -> -136652.37
C80: 5930 Maint of Overhead Lines | D80: 3.82 | E80: 34285.51 | F80: -6159.32 | G80: -32775.88 | H80: 141.03 | I80: -54241.16 | J80: -93.46 | K80: =SUM(D80:J80) -> -58839.46 | M80: 5472.61 | N80: 1483.13 | O80: 18662.36 | P80: =SUM(M80:O80) -> 25618.1 | R80: 22.22 | S80: 4935.6 | U80: 14.46 | Y80: =+K80+P80+R80+S80+T80+U80+V80+W80 -> -28249.08
C81: 5940 Maint of Underground Lines | D81: -0.11 | E81: -48.27 | F81: -31.66 | G81: -11.8 | H81: -0.95 | I81: -478.59 | J81: -1.24 | K81: =SUM(D81:J81) -> -572.62 | M81: -12997.69 | N81: -23995.07 | O81: -555.67 | P81: =SUM(M81:O81) -> -37548.43 | R81: -0.58 | S81: -37.07 | U81: -0.33 | Y81: =+K81+P81+R81+S81+T81+U81+V81+W81 -> -38159.03
C82: 5960 Maint of Street Lighting | E82: -3.49 | F82: -2.4 | G82: -0.88 | H82: -0.03 | I82: -64.04 | J82: -0.13 | K82: =SUM(D82:J82) -> -70.97 | M82: -2 | N82: -2.75 | O82: -5.72 | P82: =SUM(M82:O82) -> -10.47 | S82: -2.16 | Y82: =+K82+P82+R82+S82+T82+U82+V82+W82 -> -83.6
C83: 5970 Maint of Meters | E83: 9.54 | F83: 6.35 | G83: 1.82 | H83: 0.38 | I83: 14.14 | J83: 0.4 | K83: =SUM(D83:J83) -> 32.63 | M83: 5.72 | N83: 6.39 | O83: 13.56 | P83: =SUM(M83:O83) -> 25.67 | S83: 2.31 | Y83: =+K83+P83+R83+S83+T83+U83+V83+W83 -> 60.61
C84: 5980 Maint of Misc Distr Plt | E84: -253.98 | F84: -1.77 | G84: -0.63 | H84: -0.02 | I84: -3.4 | J84: -0.1 | K84: =SUM(D84:J84) -> -259.9 | M84: -1.61 | N84: -1.96 | O84: -4.1 | P84: =SUM(M84:O84) -> -7.67 | S84: -1.3 | Y84: =+K84+P84+R84+S84+T84+U84+V84+W84 -> -268.87
B85: Distribution Exps Total | D85: -22.75 | E85: -387310.4 | F85: -273440.12 | G85: -143339.27 | H85: -23497.26 | I85: -868400.34 | J85: -13220.22 | K85: =SUM(D85:J85) -> -1709230.4 | M85: -255533.48 | N85: -227681.42 | O85: -445909.3 | P85: =SUM(M85:O85) -> -929124.2 | R85: -261.69 | S85: -4815.15 | T85: 0.47 | U85: -39.1 | V85: 483.54 | W85: 3432.89 | Y85: =+K85+P85+R85+S85+T85+U85+V85+W85 -> -2639553.6
B86: Customer Accounts Exps | C86: 9010 Supv - Customer Accts | D86: -0.73 | E86: -3437.69 | F86: -1812.45 | G86: -591.37 | H86: -166.86 | I86: -8266.55 | J86: -145.74 | K86: =SUM(D86:J86) -> -14421.39 | M86: -2282.78 | N86: -2264.22 | O86: -3682.48 | P86: =SUM(M86:O86) -> -8229.48 | R86: -4.14 | S86: -194.42 | U86: -2.26 | Y86: =+K86+P86+R86+S86+T86+U86+V86+W86 -> -22851.69
C87: 9020 Meter Reading Exps | D87: -0.31 | E87: 825.43 | F87: 9498.65 | G87: 2336.08 | H87: 39.72 | I87: -5066.39 | J87: -1328.79 | K87: =SUM(D87:J87) -> 6304.39 | M87: 332.19 | N87: 5853.91 | O87: 7722.04 | P87: =SUM(M87:O87) -> 13908.14 | R87: -13.97 | S87: -180.75 | U87: -5.78 | V87: -0.18 | Y87: =+K87+P87+R87+S87+T87+U87+V87+W87 -> 20011.85
C88: 9030 Cust Records & Collection Exp | D88: -1.31 | E88: 11808.26 | F88: -62747.24 | G88: -49800.32 | H88: -2234.81 | I88: 77790.39 | J88: -3879.63 | K88: =SUM(D88:J88) -> -29064.66 | M88: -12488.2 | N88: -164267.63 | O88: -20053.58 | P88: =SUM(M88:O88) -> -196809.41 | R88: 2.88 | S88: 142.25 | T88: 1.75 | U88: -4.55 | V88: -8.7 | W88: 277.41 | Y88: =+K88+P88+R88+S88+T88+U88+V88+W88 -> -225463.03
C89: 9050 Misc Cust Accts Exp | E89: 670.86 | F89: 584.96 | G89: 126.3 | H89: 27.95 | I89: 1217.6 | J89: -4.94 | K89: =SUM(D89:J89) -> 2622.73 | M89: 576.5 | N89: 509.5 | O89: 1024.75 | P89: =SUM(M89:O89) -> 2110.75 | Y89: =+K89+P89+R89+S89+T89+U89+V89+W89 -> 4733.48
B90: Customer Accounts Exps Total | D90: -2.35 | E90: 9866.86 | F90: -54476.08 | G90: -47929.31 | H90: -2334 | I90: 65675.05 | J90: -5359.1 | K90: =SUM(D90:J90) -> -34558.93 | M90: -13862.29 | N90: -160168.44 | O90: -14989.27 | P90: =SUM(M90:O90) -> -189020 | R90: -15.23 | S90: -232.92 | T90: 1.75 | U90: -12.59 | V90: -8.88 | W90: 277.41 | Y90: =+K90+P90+R90+S90+T90+U90+V90+W90 -> -223569.39
B91: Customer Service & Informational Exps | C91: 9070 Supv - Customer Service | D91: 0.27 | E91: 1164.03 | F91: -5268.92 | G91: -10.03 | H91: -6.03 | I91: -964.78 | J91: -4.1 | K91: =SUM(D91:J91) -> -5089.56 | M91: -638.21 | N91: 40.76 | O91: 41.92 | P91: =SUM(M91:O91) -> -555.53 | R91: 1.4 | S91: 152.9 | U91: 0.67 | Y91: =+K91+P91+R91+S91+T91+U91+V91+W91 -> -5490.12
C92: 9080 Cust Assistance Exp | E92: -2158.63 | F92: -2101.18 | G92: -468.52 | H92: -91.15 | I92: -2938.66 | J92: -70.63 | K92: =SUM(D92:J92) -> -7828.77 | M92: -6894.65 | N92: -1204.18 | O92: -669.29 | P92: =SUM(M92:O92) -> -8768.12 | S92: -376.69 | Y92: =+K92+P92+R92+S92+T92+U92+V92+W92 -> -16973.58
C93: 9100 Misc Cust Svc&Infor Exp | D93: -8.55 | E93: -2280.65 | F93: -1719.48 | G93: -366.2 | H93: -33.11 | I93: -1134.22 | J93: -279.03 | K93: =SUM(D93:J93) -> -5821.24 | M93: -1307.68 | N93: -1801.49 | O93: -1168.09 | P93: =SUM(M93:O93) -> -4277.26 | R93: -131.48 | S93: -1111.21 | U93: -40.41 | V93: -2.46 | Y93: =+K93+P93+R93+S93+T93+U93+V93+W93 -> -11384.06
B94: Customer Service & Informational Exps Total | D94: -8.28 | E94: -3275.25 | F94: -9089.58 | G94: -844.75 | H94: -130.29 | I94: -5037.66 | J94: -353.76 | K94: =SUM(D94:J94) -> -18739.57 | M94: -8840.54 | N94: -2964.91 | O94: -1795.46 | P94: =SUM(M94:O94) -> -13600.91 | R94: -130.08 | S94: -1335 | U94: -39.74 | V94: -2.46 | Y94: =+K94+P94+R94+S94+T94+U94+V94+W94 -> -33847.76
B95: Sales Expenses | C95: 9120 Demonstrating & Selling Exp | D95: 0.02 | E95: -1272.25 | F95: -714.57 | G95: -268.3 | H95: -56.65 | I95: -1824.55 | J95: -59.22 | K95: =SUM(D95:J95) -> -4195.52 | M95: -651.11 | N95: -676.26 | O95: -1306.19 | P95: =SUM(M95:O95) -> -2633.56 | R95: 0.07 | S95: 4.66 | U95: 0.03 | Y95: =+K95+P95+R95+S95+T95+U95+V95+W95 -> -6824.32
B96: Sales Expenses Total | D96: 0.02 | E96: -1272.25 | F96: -714.57 | G96: -268.3 | H96: -56.65 | I96: -1824.55 | J96: -59.22 | K96: =SUM(D96:J96) -> -4195.52 | M96: -651.11 | N96: -676.26 | O96: -1306.19 | P96: =SUM(M96:O96) -> -2633.56 | R96: 0.07 | S96: 4.66 | U96: 0.03 | Y96: =+K96+P96+R96+S96+T96+U96+V96+W96 -> -6824.32
B97: Administrative & General Exps | C97: 9200 Admin & Gen Salaries | D97: 34571.19 | E97: -627114.6 | F97: -523375.71 | G97: -71981.76 | H97: 30974.9 | I97: -310837.14 | J97: 11968.96 | K97: =SUM(D97:J97) -> -1455794.2 | M97: -313025.96 | N97: -418445.99 | O97: -338021.92 | P97: =SUM(M97:O97) -> -1069493.9 | R97: -13208.1 | S97: -542666.53 | T97: -22510.12 | U97: -34668.16 | V97: -30294.64 | W97: -962.34 | Y97: =+K97+P97+R97+S97+T97+U97+V97+W97 -> -3169597.9
C98: 9210 Office Supplies & Exps | D98: -932.8 | E98: -559669.76 | F98: -192873.24 | G98: -37831.78 | H98: -19861.16 | I98: -180080.18 | J98: -35938.4 | K98: =SUM(D98:J98) -> -1027187.3 | M98: -156240.04 | N98: -167688.85 | O98: -198386.47 | P98: =SUM(M98:O98) -> -522315.36 | R98: -5748.62 | S98: -207300.24 | T98: -7.7 | U98: -1890.8 | V98: -4115.64 | W98: -35947.19 | Y98: =+K98+P98+R98+S98+T98+U98+V98+W98 -> -1804512.9
C99: 9220 Admins Exp Trnsf - Cr | E99: 0.01 | F99: -0.03 | G99: -0.01 | J99: -0.01 | K99: =SUM(D99:J99) -> -0.04 | M99: 0 | P99: =SUM(M99:O99) -> 0 | Y99: =+K99+P99+R99+S99+T99+U99+V99+W99 -> -0.04
C100: 9230 Outside Services Employed | D100: -2386.52 | E100: -711995.23 | F100: -208509.03 | G100: -210793.87 | H100: -17149.71 | I100: -277631.19 | J100: -129868.81 | K100: =SUM(D100:J100) -> -1558334.4 | M100: -490850.95 | N100: -193779.05 | O100: -266674.01 | P100: =SUM(M100:O100) -> -951304.01 | R100: -2435725.7 | S100: -580038.51 | T100: -3004.26 | U100: -75413.84 | V100: 57146.4 | W100: -44161.35 | Y100: =+K100+P100+R100+S100+T100+U100+V100+W100 -> -5590835.7
C101: 9250 Injuries & Damages | D101: 0.39 | E101: -117.99 | F101: -150.89 | G101: 17.98 | H101: 2.71 | I101: -864.13 | J101: -68.16 | K101: =SUM(D101:J101) -> -1180.09 | M101: -328.88 | N101: -1972.46 | O101: -780.5 | P101: =SUM(M101:O101) -> -3081.84 | R101: 2.08 | S101: 94.4 | T101: -17504.24 | U101: -1.14 | Y101: =+K101+P101+R101+S101+T101+U101+V101+W101 -> -21670.83
C102: 9260 Employee Pensions & Benefitis | D102: -82.58 | E102: -2171.09 | F102: -1977.28 | G102: -517.98 | H102: -379.7 | I102: 291.95 | J102: -447.45 | K102: =SUM(D102:J102) -> -5284.13 | M102: -1580.23 | N102: -1641.91 | O102: -4958.57 | P102: =SUM(M102:O102) -> -8180.71 | R102: -308.67 | S102: -796.84 | T102: -2.55 | U102: -73.78 | V102: -86.13 | W102: -122.02 | Y102: =+K102+P102+R102+S102+T102+U102+V102+W102 -> -14854.83
...

Sheet Tab 4
A1: American Electric Power Service Corporation
A2: Employee Fringe Benefit Loading Rate & Carrying Balance
A3: =+Index!A3 -> September 2023
F4: Carrying Balance (103-1860071)
A5: Month | B5: =RIGHT(A3,5) -> 2023 | C5: =+B5-1 -> 2022 | D5: Variance | F5: =+B5 -> 2023 | G5: =+C5 -> 2022 | H5: Variance
D6: INC (DEC)
A7: January | B7: 0.3026 | C7: 0.3284 | D7: =B7-C7 -> -0.0258 | F7: 1169844.7 | G7: 212128.31 | H7: =+F7-G7 -> 957716.4
A8: February | B8: 0.3026 | C8: 0.3284 | D8: =B8-C8 -> -0.0258 | F8: 2926077.9 | G8: 823771.54 | H8: =+F8-G8 -> 2102306.4
A9: March | B9: 0.3026 | C9: 0.3284 | D9: =B9-C9 -> -0.0258 | F9: 1451912.1 | G9: -3612806.6 | H9: =+F9-G9 -> 5064718.7
A10: April | B10: 0.3026 | C10: 0.3284 | D10: =B10-C10 -> -0.0258 | F10: 886927.93 | G10: 2883953.7 | H10: =+F10-G10 -> -1997025.8
A11: May | B11: 0.3026 | C11: 0.325 | D11: =B11-C11 -> -0.0224 | F11: -1349468.3 | G11: -3913449.1 | H11: =+F11-G11 -> 2563980.8
A12: June | B12: 0.28 | C12: 0.297 | D12: =B12-C12 -> -0.017 | F12: 2345064.6 | G12: -3151710.5 | H12: =+F12-G12 -> 5496775.2 | I12: (a)
A13: July | B13: 0.335 | C13: 0.267 | D13: =B13-C13 -> 0.068 | F13: -555121.2 | G13: -2340753.2 | H13: =+F13-G13 -> 1785632
A14: August | B14: 0.32 | C14: 0.272 | D14: =B14-C14 -> 0.048 | F14: -4634707 | G14: -2724875.1 | H14: =+F14-G14 -> -1909831.9
A15: September | B15: 0.265 | C15: 0.288 | D15: =B15-C15 -> -0.023 | F15: -3601591.7 | G15: -5487995.5 | H15: =+F15-G15 -> 1886403.8
A16: October | C16: 0.3 | D16: =B16-C16 -> -0.3 | F16: 0 | G16: -6435297 | H16: =+F16-G16 -> 6435297
A17: November | C17: 0.294 | D17: =B17-C17 -> -0.294 | F17: 0 | G17: -5581342.8 | H17: =+F17-G17 -> 5581342.8
A18: December | C18: 0.282 | D18: =B18-C18 -> -0.282 | F18: 0 | G18: 0 | H18: =+F18-G18 -> 0
A20: December residual Fringe balance cleared to affiliates (post billing Manual): | F20: TBD | G20: 1909741 | H20: =+F20-G20 -> #VALUE!
H21: =+F21-G21 -> 0
A24: (a) - overall overbilling of Fringes at June 2022 was ($10M). In June 2022, ($7M) credit was manually billed to all affiliates 9230003 account to reflect appropriate fringe billings at quarter end. The remaining ($3M) represents the estimated Capital portion not yet billed back to affiliates

Sheet Tab 5
B1: =+'Tab 1'!$A$4 -> Biiled + Manuals | F1: Tab 1: | G1: ='Tab 1'!T30+'Tab 1'!T56+'Tab 1'!T82 -> -41658639 | H1: =ROUND(+G1-SUMIF(B:B,"Grand Total",G:G),2) -> 0
B2: American Electric Power Service Corporation Total Bill Variances - Associated Companies
B3: Region | C3: Affiliate | D3: Affiliate Number and Name | E3: =+'Tab 1'!A12 -> 44834 | F3: =+'Tab 1'!A13 -> 45199 | G3: Variance | H3: Variance %age
B4: a-East | C4: a-AEG | D4: 153 AEG - Rockport | E4: 2379.73 | F4: 730.42 | G4: =+F4-E4 -> -1649.31 | H4: =IF(OR(E4="",F4=""),100%,+G4/E4) -> -0.69306602
D5: 270 AEG Cook Coal Terminal | E5: 76705.41 | F5: 78380.02 | G5: =+F5-E5 -> 1674.61 | H5: =IF(OR(E5="",F5=""),100%,+G5/E5) -> 0.021831707
C6: a-AEG Total | E6: 79085.14 | F6: 79110.44 | G6: =+F6-E6 -> 25.3 | H6: =IF(OR(E6="",F6=""),100%,+G6/E6) -> 0.00031990839
C7: b-APCO | D7: 140 Appalachian Power Co - Dist | E7: 11354697 | F7: 9518491.8 | G7: =+F7-E7 -> -1836205.6 | H7: =IF(OR(E7="",F7=""),100%,+G7/E7) -> -0.1617133
D8: 150 Appalachian Power Co - Trans | E8: 10195117 | F8: 7546613.9 | G8: =+F8-E8 -> -2648503.5 | H8: =IF(OR(E8="",F8=""),100%,+G8/E8) -> -0.25978156
D9: 215 Appalachian Power Co - Gen | E9: 11465350 | F9: 7910707.8 | G9: =+F9-E9 -> -3554642.2 | H9: =IF(OR(E9="",F9=""),100%,+G9/E9) -> -0.31003347
D10: 490 APCO Renewables | E10: 215963.08 | F10: 1143.13 | G10: =+F10-E10 -> -214819.95 | H10: =IF(OR(E10="",F10=""),100%,+G10/E10) -> -0.99470683
C11: b-APCO Total | E11: 33231128 | F11: 24976957 | G11: =+F11-E11 -> -8254171.3 | H11: =IF(OR(E11="",F11=""),100%,+G11/E11) -> -0.24838673
C12: c-I&M | D12: 120 Indiana Michigan Pwr Co - Tran | E12: 3453475.8 | F12: 2229093.6 | G12: =+F12-E12 -> -1224382.2 | H12: =IF(OR(E12="",F12=""),100%,+G12/E12) -> -0.3545362
D13: 132 Indiana Michigan Pwr Co - Gen | E13: 3832806.6 | F13: 2738283.9 | G13: =+F13-E13 -> -1094522.7 | H13: =IF(OR(E13="",F13=""),100%,+G13/E13) -> -0.28556689
D14: 170 Indiana Michigan Pwr Co - Dist | E14: 6734471.6 | F14: 5673590.6 | G14: =+F14-E14 -> -1060881.1 | H14: =IF(OR(E14="",F14=""),100%,+G14/E14) -> -0.15752996
D15: 190 Indiana Michigan Pwr Co - Nuc | E15: 6050665.7 | F15: 3658501.4 | G15: =+F15-E15 -> -2392164.3 | H15: =IF(OR(E15="",F15=""),100%,+G15/E15) -> -0.39535555
D16: 280 Ind Mich River Transp Lakin | E16: 158592.21 | F16: 103878.63 | G16: =+F16-E16 -> -54713.58 | H16: =IF(OR(E16="",F16=""),100%,+G16/E16) -> -0.34499538
C17: c-I&M Total | E17: 20230012 | F17: 14403348 | G17: =+F17-E17 -> -5826663.8 | H17: =IF(OR(E17="",F17=""),100%,+G17/E17) -> -0.28802078
C18: d-KENT | D18: 110 Kentucky Power Co - Dist | E18: 2528841.5 | F18: 1719974.8 | G18: =+F18-E18 -> -808866.75 | H18: =IF(OR(E18="",F18=""),100%,+G18/E18) -> -0.31985664
D19: 117 Kentucky Power Co - Gene | E19: 1112092.9 | F19: 646371.47 | G19: =+F19-E19 -> -465721.4 | H19: =IF(OR(E19="",F19=""),100%,+G19/E19) -> -0.41877923
D20: 180 Kentucky Power Co - Trans | E20: 1734009.4 | F20: 1435411.2 | G20: =+F20-E20 -> -298598.18 | H20: =IF(OR(E20="",F20=""),100%,+G20/E20) -> -0.17220102
C21: d-KENT Total | E21: 5374943.8 | F21: 3801757.4 | G21: =+F21-E21 -> -1573186.3 | H21: =IF(OR(E21="",F21=""),100%,+G21/E21) -> -0.29268889
C22: e-KINGS | D22: 230 Kingsport Power Co - Dist | E22: 709133.86 | F22: 667794.22 | G22: =+F22-E22 -> -41339.64 | H22: =IF(OR(E22="",F22=""),100%,+G22/E22) -> -0.058295961
D23: 260 Kingsport Power Co - Trans | E23: 325974.05 | F23: 182716.43 | G23: =+F23-E23 -> -143257.62 | H23: =IF(OR(E23="",F23=""),100%,+G23/E23) -> -0.43947553
C24: e-KINGS Total | E24: 1035107.9 | F24: 850510.65 | G24: =+F24-E24 -> -184597.26 | H24: =IF(OR(E24="",F24=""),100%,+G24/E24) -> -0.17833625
C25: f-OPCO | D25: 160 Ohio Power Co - Transmission | E25: 8628467.1 | F25: 7552060 | G25: =+F25-E25 -> -1076407.1 | H25: =IF(OR(E25="",F25=""),100%,+G25/E25) -> -0.12475068
D26: 250 Ohio Power Co - Distribution | E26: 17177006 | F26: 14449714 | G26: =+F26-E26 -> -2727292.1 | H26: =IF(OR(E26="",F26=""),100%,+G26/E26) -> -0.15877575
C27: f-OPCO Total | E27: 25805473 | F27: 22001774 | G27: =+F27-E27 -> -3803699.2 | H27: =IF(OR(E27="",F27=""),100%,+G27/E27) -> -0.14739893
C28: g-WHEEL | D28: 200 Wheeling Power Co - Trans | E28: 232126.43 | F28: 304714.48 | G28: =+F28-E28 -> 72588.05 | H28: =IF(OR(E28="",F28=""),100%,+G28/E28) -> 0.31270911
D29: 210 Wheeling Power Co - Dist | E29: 482267.6 | F29: 469996.44 | G29: =+F29-E29 -> -12271.16 | H29: =IF(OR(E29="",F29=""),100%,+G29/E29) -> -0.025444712
D30: 413 Wheeling Power Co - Generation | E30: 2999398.5 | F30: 2563772.9 | G30: =+F30-E30 -> -435625.65 | H30: =IF(OR(E30="",F30=""),100%,+G30/E30) -> -0.14523767
C31: g-WHEEL Total | E31: 3713792.6 | F31: 3338483.8 | G31: =+F31-E31 -> -375308.76 | H31: =IF(OR(E31="",F31=""),100%,+G31/E31) -> -0.10105808
B32: a-East Total | E32: 89469543 | F32: 69451941 | G32: =+F32-E32 -> -20017601 | H32: =IF(OR(E32="",F32=""),100%,+G32/E32) -> -0.22373649
B33: b-West | C33: h-PSO | D33: 114 Public Service Co of OK - Tran | E33: 2690590.7 | F33: 2149731.7 | G33: =+F33-E33 -> -540858.97 | H33: =IF(OR(E33="",F33=""),100%,+G33/E33) -> -0.20101867
D34: 167 Public Service Co of Ok - Dist | E34: 6472940.9 | F34: 5209597.9 | G34: =+F34-E34 -> -1263343.1 | H34: =IF(OR(E34="",F34=""),100%,+G34/E34) -> -0.19517296
D35: 198 Public Service Co of OK - Gen | E35: 4412970.2 | F35: 3009678.9 | G35: =+F35-E35 -> -1403291.3 | H35: =IF(OR(E35="",F35=""),100%,+G35/E35) -> -0.31799248
D36: 474 Public Service Co of OK- Wind | E36: 1441868.1 | F36: 1116363.9 | G36: =+F36-E36 -> -325504.26 | H36: =IF(OR(E36="",F36=""),100%,+G36/E36) -> -0.22575175
C37: h-PSO Total | E37: 15018370 | F37: 11485372 | G37: =+F37-E37 -> -3532997.6 | H37: =IF(OR(E37="",F37=""),100%,+G37/E37) -> -0.23524508
C38: i-SWEPC | D38: 159 SWEPCO-Distribution | E38: 6253771.6 | F38: 4870237 | G38: =+F38-E38 -> -1383534.5 | H38: =IF(OR(E38="",F38=""),100%,+G38/E38) -> -0.22123202
D39: 161 SWEPCO-TX-Distribution | E39: 335783.39 | F39: 404802.81 | G39: =+F39-E39 -> 69019.42 | H39: =IF(OR(E39="",F39=""),100%,+G39/E39) -> 0.20554745
D40: 168 SWEPCO-Generation | E40: 6989707.3 | F40: 4546202.8 | G40: =+F40-E40 -> -2443504.4 | H40: =IF(OR(E40="",F40=""),100%,+G40/E40) -> -0.34958609
D41: 194 SWEPCO-Transmission | E41: 4720613.7 | F41: 4786235.6 | G41: =+F41-E41 -> 65621.85 | H41: =IF(OR(E41="",F41=""),100%,+G41/E41) -> 0.013901127
C42: i-SWEPC Total | E42: 18299876 | F42: 14607478 | G42: =+F42-E42 -> -3692397.7 | H42: =IF(OR(E42="",F42=""),100%,+G42/E42) -> -0.20177173
C43: j-AEP TEXAS | D43: 101 AEP Texas Inc. | E43: 3185.51 | F43: 3511.16 | G43: =+F43-E43 -> 325.65 | H43: =IF(OR(E43="",F43=""),100%,+G43/E43) -> 0.10222853
D44: 119 AEP Texas North Division -Dist | E44: 2240333.1 | F44: 1766114.6 | G44: =+F44-E44 -> -474218.54 | H44: =IF(OR(E44="",F44=""),100%,+G44/E44) -> -0.21167323
D45: 166 AEP Texas North Division - Gen | E45: 185.28 | F45: 193.49 | G45: =+F45-E45 -> 8.21 | H45: =IF(OR(E45="",F45=""),100%,+G45/E45) -> 0.044311313
D46: 169 AEP Texas Central Division-Tra | E46: 7969404.2 | F46: 7166722.8 | G46: =+F46-E46 -> -802681.42 | H46: =IF(OR(E46="",F46=""),100%,+G46/E46) -> -0.10072038
D47: 192 AEP Texas North Division -Tran | E47: 4618194.5 | F47: 3796883.2 | G47: =+F47-E47 -> -821311.32 | H47: =IF(OR(E47="",F47=""),100%,+G47/E47) -> -0.17784251
D48: 211 AEP Texas Central Division-Dis | E48: 7858559.6 | F48: 6693798.1 | G48: =+F48-E48 -> -1164761.5 | H48: =IF(OR(E48="",F48=""),100%,+G48/E48) -> -0.14821564
D49: 371 AEP TX North Generation Co,LLC | E49: 1797.7 | F49: 60.56 | G49: =+F49-E49 -> -1737.14 | H49: =IF(OR(E49="",F49=""),100%,+G49/E49) -> -0.96631251
C50: j-AEP TEXAS Total | E50: 22691660 | F50: 19427284 | G50: =+F50-E50 -> -3264376 | H50: =IF(OR(E50="",F50=""),100%,+G50/E50) -> -0.14385797
B51: b-West Total | E51: 56009906 | F51: 45520135 | G51: =+F51-E51 -> -10489771 | H51: =IF(OR(E51="",F51=""),100%,+G51/E51) -> -0.18728422
B52: c-NR | C52: k-NR | D52: 100 American Electric Power Co. | E52: 3668646 | F52: 1915962.3 | G52: =+F52-E52 -> -1752683.7 | H52: =IF(OR(E52="",F52=""),100%,+G52/E52) -> -0.47774674
D53: 102 AEP Energy Supply LLC | E53: 27000.85 | F53: 114423.53 | G53: =+F53-E53 -> 87422.68 | H53: =IF(OR(E53="",F53=""),100%,+G53/E53) -> 3.2377751
D54: 105 Public Liability | E54: 198.84 | F54: 2793.57 | G54: =+F54-E54 -> 2594.73 | H54: =IF(OR(E54="",F54=""),100%,+G54/E54) -> 13.049336
D55: 143 AEP Pro Serv, Inc. | E55: 43444.32 | F55: 21162.25 | G55: =+F55-E55 -> -22282.07 | H55: =IF(OR(E55="",F55=""),100%,+G55/E55) -> -0.51288799
D56: 154 AEP Credit, Inc | E56: 37345.71 | F56: 74621.75 | G56: =+F56-E56 -> 37276.04 | H56: =IF(OR(E56="",F56=""),100%,+G56/E56) -> 0.99813446
D57: 171 CSW Energy, Inc. | E57: 7617.54 | F57: 3439.97 | G57: =+F57-E57 -> -4177.57 | H57: =IF(OR(E57="",F57=""),100%,+G57/E57) -> -0.54841458
D58: 175 AEP Energy Partners, Inc. | E58: 413983.06 | F58: 254976.3 | G58: =+F58-E58 -> -159006.76 | H58: =IF(OR(E58="",F58=""),100%,+G58/E58) -> -0.38409002
D59: 185 AEP Energy Services, Inc. | E59: 33628.03 | F59: 20997.16 | G59: =+F59-E59 -> -12630.87 | H59: =IF(OR(E59="",F59=""),100%,+G59/E59) -> -0.37560541
D60: 196 AEP Investments, Inc. | E60: -380229.02 | F60: -466454.12 | G60: =+F60-E60 -> -86225.1 | H60: =IF(OR(E60="",F60=""),100%,+G60/E60) -> 0.22677149
D61: 204 AEP T&D Services, LLC | E61: 92732.14 | F61: 98585.17 | G61: =+F61-E61 -> 5853.03 | H61: =IF(OR(E61="",F61=""),100%,+G61/E61) -> 0.063117599
D62: 245 Dolet Hills Lignite Co, LLC | E62: 46069.33 | F62: 28287.21 | G62: =+F62-E62 -> -17782.12 | H62: =IF(OR(E62="",F62=""),100%,+G62/E62) -> -0.38598608
D63: 290 Conesville Coal Prep. Co. | F63: 93.72 | G63: =+F63-E63 -> 93.72 | H63: =IF(OR(E63="",F63=""),100%,+G63/E63) -> 1
D64: 303 Snowcap Coal Company, Inc. | E64: 4498.06 | F64: 2493.63 | G64: =+F64-E64 -> -2004.43 | H64: =IF(OR(E64="",F64=""),100%,+G64/E64) -> -0.445621
D65: 305 AEP Kentucky Coal, LLC | E65: 724.21 | G65: =+F65-E65 -> -724.21 | H65: =IF(OR(E65="",F65=""),100%,+G65/E65) -> 1
D66: 319 United Sciences Testing, Inc | E66: 76.51 | G66: =+F66-E66 -> -76.51 | H66: =IF(OR(E66="",F66=""),100%,+G66/E66) -> 1
D67: 353 AEP Utility Funding LLC | E67: 16823.22 | F67: 7522.68 | G67: =+F67-E67 -> -9300.54 | H67: =IF(OR(E67="",F67=""),100%,+G67/E67) -> -0.55283947
D68: 364 AEP Nonutility Funding LLC | E68: 1799.61 | F68: 1552.6 | G68: =+F68-E68 -> -247.01 | H68: =IF(OR(E68="",F68=""),100%,+G68/E68) -> -0.13725752
D69: 389 Oxbow Lignite Company, LLC | E69: 5310.23 | F69: 9705.49 | G69: =+F69-E69 -> 4395.26 | H69: =IF(OR(E69="",F69=""),100%,+G69/E69) -> 0.82769673
D70: 397 AEP Retail Energy Partners LLC | E70: 453.19 | F70: 420.53 | G70: =+F70-E70 -> -32.66 | H70: =IF(OR(E70="",F70=""),100%,+G70/E70) -> -0.072066904
D71: 400 AEP Energy, Inc | E71: 1000272.6 | F71: 459514.58 | G71: =+F71-E71 -> -540757.97 | H71: =IF(OR(E71="",F71=""),100%,+G71/E71) -> -0.54061063
D72: 412 Ohio Franklin Realty, LLC | E72: 55654.9 | F72: 39197.14 | G72: =+F72-E72 -> -16457.76 | H72: =IF(OR(E72="",F72=""),100%,+G72/E72) -> -0.29571089
D73: 417 Bold Transmission, LLC | E73: 2851.52 | F73: 370.88 | G73: =+F73-E73 -> -2480.64 | H73: =IF(OR(E73="",F73=""),100%,+G73/E73) -> -0.86993603
D74: 419 AEP OnSite Partners, LLC | E74: 337321.1 | F74: 136403.41 | G74: =+F74-E74 -> -200917.69 | H74: =IF(OR(E74="",F74=""),100%,+G74/E74) -> -0.5956274
D75: 422 AEP RENEWABLES, LLC | E75: 142901.26 | F75: 5427.81 | G75: =+F75-E75 -> -137473.45 | H75: =IF(OR(E75="",F75=""),100%,+G75/E75) -> -0.96201706
D76: 425 Solar LLCs | E76: 4637.94 | F76: 877.24 | G76: =+F76-E76 -> -3760.7 | H76: =IF(OR(E76="",F76=""),100%,+G76/E76) -> -0.81085568
D77: 431 Trent Wind Farm LLC | E77: 42550.69 | F77: 677.21 | G77: =+F77-E77 -> -41873.48 | H77: =IF(OR(E77="",F77=""),100%,+G77/E77) -> -0.98408463
D78: 432 Desert Sky Wind Farm LLC | E78: 54956.4 | F78: 700.62 | G78: =+F78-E78 -> -54255.78 | H78: =IF(OR(E78="",F78=""),100%,+G78/E78) -> -0.98725135
... D81: 446 Apple Blossom Wind, LLC | E81: 569.16 | F81: 2247.65 | G81: =+F81-E81 -> 1678.49 | H81: =IF(OR(E81="",F81=""),100%,+G81/E81) -> 2.9490653
D82: 447 Black Oak Wind, LLC | F82: 106.84 | G82: =+F82-E82 -> 106.84 | H82: =IF(OR(E82="",F82=""),100%,+G82/E82) -> 1
D83: 454 Flat Ridge 3 Wind Energy, LLC | E83: 1916.37 | F83: 1382.84 | G83: =+F83-E83 -> -533.53 | H83: =IF(OR(E83="",F83=""),100%,+G83/E83) -> -0.27840657
D84: 466 Apple Blossom Hold Co | F84: 106.84 | G84: =+F84-E84 -> 106.84 | H84: =IF(OR(E84="",F84=""),100%,+G84/E84) -> 1
D85: 471 AEP Ventures, LLC | E85: 34816.15 | F85: 7834.66 | G85: =+F85-E85 -> -26981.49 | H85: =IF(OR(E85="",F85=""),100%,+G85/E85) -> -0.77497052
D86: 472 Great Bend Solar, LLC | E86: 2031.98 | G86: =+F86-E86 -> -2031.98 | H86: =IF(OR(E86="",F86=""),100%,+G86/E86) -> 1
D87: 482 Harry Allen Solar Energy LLC | E87: 100.83 | G87: =+F87-E87 -> -100.83 | H87: =IF(OR(E87="",F87=""),100%,+G87/E87) -> 1
D88: 485 AEP Renewables Development LLC | E88: 533.14 | G88: =+F88-E88 -> -533.14 | H88: =IF(OR(E88="",F88=""),100%,+G88/E88) -> 1
C89: k-NR Total | E89: 5888749 | F89: 2769545.7 | G89: =+F89-E89 -> -3119203.3 | H89: =IF(OR(E89="",F89=""),100%,+G89/E89) -> -0.52968861
B90: c-NR Total | E90: 5888749 | F90: 2769545.7 | G90: =+F90-E90 -> -3119203.3 | H90: =IF(OR(E90="",F90=""),100%,+G90/E90) -> -0.52968861
B91: d-TRANSCO | C91: l-TRANSCO | D91: 369 AEP Transmission Hldg Co, LLC | E91: 132637.22 | F91: 23129.54 | G91: =+F91-E91 -> -109507.68 | H91: =IF(OR(E91="",F91=""),100%,+G91/E91) -> -0.82561803
D92: 370 AEP Transmission Company, LLC | E92: 4263.88 | F92: 7352.46 | G92: =+F92-E92 -> 3088.58 | H92: =IF(OR(E92="",F92=""),100%,+G92/E92) -> 0.72435903
D93: 380 AEP Ohio Trans Co | E93: 11087378 | F93: 8216608.6 | G93: =+F93-E93 -> -2870769.3 | H93: =IF(OR(E93="",F93=""),100%,+G93/E93) -> -0.25892229
D94: 382 AEP Appalachian Trans Co | E94: 261702.71 | F94: 397231.52 | G94: =+F94-E94 -> 135528.81 | H94: =IF(OR(E94="",F94=""),100%,+G94/E94) -> 0.51787316
D95: 383 AEP West Virginia Trans Co | E95: 5948832 | F95: 4516301.6 | G95: =+F95-E95 -> -1432530.4 | H95: =IF(OR(E95="",F95=""),100%,+G95/E95) -> -0.24080869
D96: 384 AEP Kentucky Trans Co | E96: 216935.91 | F96: 140886.92 | G96: =+F96-E96 -> -76048.99 | H96: =IF(OR(E96="",F96=""),100%,+G96/E96) -> -0.35055971
D97: 385 AEP Indiana Michigan Trans Co | E97: 5497137.8 | F97: 4795545.7 | G97: =+F97-E97 -> -701592.03 | H97: =IF(OR(E97="",F97=""),100%,+G97/E97) -> -0.12762861
D98: 386 AEP Oklahoma Trans Co | E98: 2693069.4 | F98: 2641047.6 | G98: =+F98-E98 -> -52021.84 | H98: =IF(OR(E98="",F98=""),100%,+G98/E98) -> -0.019316932
D99: 388 AEP Southwestern Trans Co | E99: 7132.13 | F99: 6568.74 | G99: =+F99-E99 -> -563.39 | H99: =IF(OR(E99="",F99=""),100%,+G99/E99) -> -0.078993232
C100: l-TRANSCO Total | E100: 25849089 | F100: 20744673 | G100: =+F100-E100 -> -5104416.3 | H100: =IF(OR(E100="",F100=""),100%,+G100/E100) -> -0.19746987
B101: d-TRANSCO Total | E101: 25849089 | F101: 20744673 | G101: =+F101-E101 -> -5104416.3 | H101: =IF(OR(E101="",F101=""),100%,+G101/E101) -> -0.19746987
B102: e-JV | C102: m-JV | D102: 376 PATH WV Transmission Co., LLC | E102: 374.14 | F102: 865.71 | G102: =+F102-E102 -> 491.57 | H102: =IF(OR(E102="",F102=""),100%,+G102/E102) -> 1.3138665
...

Sheet Tab 6
B1: =+'Tab 1'!$A$4 -> Biiled + Manuals | F1: Tab 1: | G1: =+'Tab 1'!T82 -> -20895302 | H1: =ROUND(G1-SUMIF(B:B,"Grand Total",G:G),2) -> 0
B2: American Electric Power Service Corporation AEPSC Income Statement
B3: Region | C3: Affiliate | D3: Affiliate Number and Name | E3: =+'Tab 1'!A12 -> 44834 | F3: =+'Tab 1'!A13 -> 45199 | G3: Variance | H3: Variance %age
B4: a-East | C4: a-AEG | D4: 153 AEG - Rockport | E4: 2379.73 | F4: 730.42 | G4: =+F4-E4 -> -1649.31 | H4: =IF(OR(E4="",F4=""),100%,+G4/E4) -> -0.69306602
D5: 270 AEG Cook Coal Terminal | E5: 33754.76 | F5: 66701.2 | G5: =+F5-E5 -> 32946.44 | H5: =IF(OR(E5="",F5=""),100%,+G5/E5) -> 0.97605316
C6: a-AEG Total | E6: 36134.49 | F6: 67431.62 | G6: =+F6-E6 -> 31297.13 | H6: =IF(OR(E6="",F6=""),100%,+G6/E6) -> 0.86612901
C7: b-APCO | D7: 140 Appalachian Power Co - Dist | E7: 5402400.3 | F7: 4554309.4 | G7: =+F7-E7 -> -848090.93 | H7: =IF(OR(E7="",F7=""),100%,+G7/E7) -> -0.1569841
D8: 150 Appalachian Power Co - Trans | E8: 3966262 | F8: 2771542 | G8: =+F8-E8 -> -1194720.1 | H8: =IF(OR(E8="",F8=""),100%,+G8/E8) -> -0.30122067
D9: 215 Appalachian Power Co - Gen | E9: 6317561.9 | F9: 4548877 | G9: =+F9-E9 -> -1768684.8 | H9: =IF(OR(E9="",F9=""),100%,+G9/E9) -> -0.2799632
C10: b-APCO Total | E10: 15686224 | F10: 11874728 | G10: =+F10-E10 -> -3811495.9 | H10: =IF(OR(E10="",F10=""),100%,+G10/E10) -> -0.24298364
C11: c-I&M | D11: 120 Indiana Michigan Pwr Co - Tran | E11: 1396054.9 | F11: 954009.56 | G11: =+F11-E11 -> -442045.31 | H11: =IF(OR(E11="",F11=""),100%,+G11/E11) -> -0.31663892
D12: 132 Indiana Michigan Pwr Co - Gen | E12: 2057360.4 | F12: 1373021.9 | G12: =+F12-E12 -> -684338.52 | H12: =IF(OR(E12="",F12=""),100%,+G12/E12) -> -0.33262939
D13: 170 Indiana Michigan Pwr Co - Dist | E13: 3028202.8 | F13: 2580961.7 | G13: =+F13-E13 -> -447241.08 | H13: =IF(OR(E13="",F13=""),100%,+G13/E13) -> -0.14769192
D14: 190 Indiana Michigan Pwr Co - Nuc | E14: 3229073.4 | F14: 2433197.5 | G14: =+F14-E14 -> -795875.99 | H14: =IF(OR(E14="",F14=""),100%,+G14/E14) -> -0.24647194
D15: 280 Ind Mich River Transp Lakin | E15: 107099.28 | F15: 91239.89 | G15: =+F15-E15 -> -15859.39 | H15: =IF(OR(E15="",F15=""),100%,+G15/E15) -> -0.1480812
C16: c-I&M Total | E16: 9817790.7 | F16: 7432430.4 | G16: =+F16-E16 -> -2385360.3 | H16: =IF(OR(E16="",F16=""),100%,+G16/E16) -> -0.24296304
C17: d-KENT | D17: 110 Kentucky Power Co - Dist | E17: 1228391.3 | F17: 1019154.7 | G17: =+F17-E17 -> -209236.64 | H17: =IF(OR(E17="",F17=""),100%,+G17/E17) -> -0.17033386
D18: 117 Kentucky Power Co - Gene | E18: 701812.12 | F18: 349600.48 | G18: =+F18-E18 -> -352211.64 | H18: =IF(OR(E18="",F18=""),100%,+G18/E18) -> -0.5018603
D19: 180 Kentucky Power Co - Trans | E19: 685927.93 | F19: 567245.2 | G19: =+F19-E19 -> -118682.73 | H19: =IF(OR(E19="",F19=""),100%,+G19/E19) -> -0.17302507
C20: d-KENT Total | E20: 2616131.4 | F20: 1936000.4 | G20: =+F20-E20 -> -680131.01 | H20: =IF(OR(E20="",F20=""),100%,+G20/E20) -> -0.25997586
C21: e-KINGS | D21: 230 Kingsport Power Co - Dist | E21: 300171.39 | F21: 261838.86 | G21: =+F21-E21 -> -38332.53 | H21: =IF(OR(E21="",F21=""),100%,+G21/E21) -> -0.12770214
D22: 260 Kingsport Power Co - Trans | E22: 74298.28 | F22: 43405.89 | G22: =+F22-E22 -> -30892.39 | H22: =IF(OR(E22="",F22=""),100%,+G22/E22) -> -0.41578876
C23: e-KINGS Total | E23: 374469.67 | F23: 305244.75 | G23: =+F23-E23 -> -69224.92 | H23: =IF(OR(E23="",F23=""),100%,+G23/E23) -> -0.18486122
C24: f-OPCO | D24: 160 Ohio Power Co - Transmission | E24: 3195459.1 | F24: 2268086.3 | G24: =+F24-E24 -> -927372.82 | H24: =IF(OR(E24="",F24=""),100%,+G24/E24) -> -0.29021583
D25: 250 Ohio Power Co - Distribution | E25: 8560140.5 | F25: 7326339.3 | G25: =+F25-E25 -> -1233801.3 | H25: =IF(OR(E25="",F25=""),100%,+G25/E25) -> -0.1441333
C26: f-OPCO Total | E26: 11755600 | F26: 9594425.5 | G26: =+F26-E26 -> -2161174.1 | H26: =IF(OR(E26="",F26=""),100%,+G26/E26) -> -0.1838421
C27: g-WHEEL | D27: 200 Wheeling Power Co - Trans | E27: 101592.41 | F27: 83627.48 | G27: =+F27-E27 -> -17964.93 | H27: =IF(OR(E27="",F27=""),100%,+G27/E27) -> -0.17683339
D28: 210 Wheeling Power Co - Dist | E28: 242752.19 | F28: 214163.5 | G28: =+F28-E28 -> -28588.69 | H28: =IF(OR(E28="",F28=""),100%,+G28/E28) -> -0.11776903
D29: 413 Wheeling Power Co - Generation | E29: 1332935.5 | F29: 967111.69 | G29: =+F29-E29 -> -365823.79 | H29: =IF(OR(E29="",F29=""),100%,+G29/E29) -> -0.27444974
C30: g-WHEEL Total | E30: 1677280.1 | F30: 1264902.7 | G30: =+F30-E30 -> -412377.41 | H30: =IF(OR(E30="",F30=""),100%,+G30/E30) -> -0.24586079
B31: a-East Total | E31: 41963630 | F31: 32475164 | G31: =+F31-E31 -> -9488466.5 | H31: =IF(OR(E31="",F31=""),100%,+G31/E31) -> -0.22611167
B32: b-West | C32: h-PSO | D32: 114 Public Service Co of OK - Tran | E32: 1108054.6 | F32: 832792.85 | G32: =+F32-E32 -> -275261.8 | H32: =IF(OR(E32="",F32=""),100%,+G32/E32) -> -0.24841897
D33: 167 Public Service Co of Ok - Dist | E33: 3311712.2 | F33: 2819865.8 | G33: =+F33-E33 -> -491846.36 | H33: =IF(OR(E33="",F33=""),100%,+G33/E33) -> -0.14851724
D34: 198 Public Service Co of OK - Gen | E34: 2849601.7 | F34: 1733895.3 | G34: =+F34-E34 -> -1115706.3 | H34: =IF(OR(E34="",F34=""),100%,+G34/E34) -> -0.39153063
D35: 474 Public Service Co of OK- Wind | E35: 918840.61 | F35: 786688.52 | G35: =+F35-E35 -> -132152.09 | H35: =IF(OR(E35="",F35=""),100%,+G35/E35) -> -0.14382483
C36: h-PSO Total | E36: 8188209.1 | F36: 6173242.6 | G36: =+F36-E36 -> -2014966.6 | H36: =IF(OR(E36="",F36=""),100%,+G36/E36) -> -0.24608147
C37: i-SWEPC | D37: 159 SWEPCO-Distribution | E37: 3207357.4 | F37: 2650493 | G37: =+F37-E37 -> -556864.48 | H37: =IF(OR(E37="",F37=""),100%,+G37/E37) -> -0.17362096
D38: 161 SWEPCO-TX-Distribution | E38: 209535.32 | F38: 203449.43 | G38: =+F38-E38 -> -6085.89 | H38: =IF(OR(E38="",F38=""),100%,+G38/E38) -> -0.029044698
D39: 168 SWEPCO-Generation | E39: 4117775.2 | F39: 2671873.5 | G39: =+F39-E39 -> -1445901.7 | H39: =IF(OR(E39="",F39=""),100%,+G39/E39) -> -0.35113662
D40: 194 SWEPCO-Transmission | E40: 2022387.4 | F40: 1626255.4 | G40: =+F40-E40 -> -396131.96 | H40: =IF(OR(E40="",F40=""),100%,+G40/E40) -> -0.19587343
C41: i-SWEPC Total | E41: 9557055.3 | F41: 7152071.3 | G41: =+F41-E41 -> -2404984 | H41: =IF(OR(E41="",F41=""),100%,+G41/E41) -> -0.25164488
C42: j-AEP TEXAS | D42: 101 AEP Texas Inc. | E42: 3185.51 | F42: 3511.16 | G42: =+F42-E42 -> 325.65 | H42: =IF(OR(E42="",F42=""),100%,+G42/E42) -> 0.10222853
D43: 119 AEP Texas North Division -Dist | E43: 902097.48 | F43: 788302.05 | G43: =+F43-E43 -> -113795.43 | H43: =IF(OR(E43="",F43=""),100%,+G43/E43) -> -0.12614538
D44: 169 AEP Texas Central Division-Tra | E44: 2923751.7 | F44: 2340337.2 | G44: =+F44-E44 -> -583414.44 | H44: =IF(OR(E44="",F44=""),100%,+G44/E44) -> -0.19954309
D45: 192 AEP Texas North Division -Tran | E45: 1778578.6 | F45: 1375220.1 | G45: =+F45-E45 -> -403358.54 | H45: =IF(OR(E45="",F45=""),100%,+G45/E45) -> -0.22678702
D46: 211 AEP Texas Central Division-Dis | E46: 3420845.6 | F46: 2890474.3 | G46: =+F46-E46 -> -530371.34 | H46: =IF(OR(E46="",F46=""),100%,+G46/E46) -> -0.15504101
D47: 371 AEP TX North Generation Co,LLC | E47: 1797.7 | F47: 60.56 | G47: =+F47-E47 -> -1737.14 | H47: =IF(OR(E47="",F47=""),100%,+G47/E47) -> -0.96631251
C48: j-AEP TEXAS Total | E48: 9030256.6 | F48: 7397905.3 | G48: =+F48-E48 -> -1632351.2 | H48: =IF(OR(E48="",F48=""),100%,+G48/E48) -> -0.18076466
B49: b-West Total | E49: 26775521 | F49: 20723219 | G49: =+F49-E49 -> -6052301.8 | H49: =IF(OR(E49="",F49=""),100%,+G49/E49) -> -0.22603862
B50: c-NR | C50: k-NR | D50: 100 American Electric Power Co. | E50: 3549930 | F50: 1867730.2 | G50: =+F50-E50 -> -1682199.9 | H50: =IF(OR(E50="",F50=""),100%,+G50/E50) -> -0.47386846
D51: 102 AEP Energy Supply LLC | E51: 27000.22 | F51: 113982.76 | G51: =+F51-E51 -> 86982.54 | H51: =IF(OR(E51="",F51=""),100%,+G51/E51) -> 3.2215493
D52: 105 Public Liability | E52: 198.84 | F52: 2793.57 | G52: =+F52-E52 -> 2594.73 | H52: =IF(OR(E52="",F52=""),100%,+G52/E52) -> 13.049336
D53: 143 AEP Pro Serv, Inc. | E53: 42431.03 | F53: 20810.26 | G53: =+F53-E53 -> -21620.77 | H53: =IF(OR(E53="",F53=""),100%,+G53/E53) -> -0.50955091
D54: 154 AEP Credit, Inc | E54: 37345.71 | F54: 74621.75 | G54: =+F54-E54 -> 37276.04 | H54: =IF(OR(E54="",F54=""),100%,+G54/E54) -> 0.99813446
D55: 171 CSW Energy, Inc. | E55: 2595.8 | F55: 2988.59 | G55: =+F55-E55 -> 392.79 | H55: =IF(OR(E55="",F55=""),100%,+G55/E55) -> 0.15131751
D56: 175 AEP Energy Partners, Inc. | E56: 291542.38 | F56: 234419.46 | G56: =+F56-E56 -> -57122.92 | H56: =IF(OR(E56="",F56=""),100%,+G56/E56) -> -0.1959335
D57: 185 AEP Energy Services, Inc. | E57: 32862.81 | F57: 20677.23 | G57: =+F57-E57 -> -12185.58 | H57: =IF(OR(E57="",F57=""),100%,+G57/E57) -> -0.37080152
D58: 196 AEP Investments, Inc. | E58: -380230.45 | F58: -466454.34 | G58: =+F58-E58 -> -86223.89 | H58: =IF(OR(E58="",F58=""),100%,+G58/E58) -> 0.22676745
D59: 204 AEP T&D Services, LLC | E59: 89969.87 | F59: 90703.67 | G59: =+F59-E59 -> 733.8 | H59: =IF(OR(E59="",F59=""),100%,+G59/E59) -> 0.0081560638
D60: 245 Dolet Hills Lignite Co, LLC | E60: 31674.87 | F60: 21800.67 | G60: =+F60-E60 -> -9874.2 | H60: =IF(OR(E60="",F60=""),100%,+G60/E60) -> -0.31173609
D61: 290 Conesville Coal Prep. Co. | F61: 93.72 | G61: =+F61-E61 -> 93.72 | H61: =IF(OR(E61="",F61=""),100%,+G61/E61) -> 1
D62: 303 Snowcap Coal Company, Inc. | E62: 125.24 | G62: =+F62-E62 -> -125.24 | H62: =IF(OR(E62="",F62=""),100%,+G62/E62) -> 1
D63: 305 AEP Kentucky Coal, LLC | E63: 724.21 | G63: =+F63-E63 -> -724.21 | H63: =IF(OR(E63="",F63=""),100%,+G63/E63) -> 1
D64: 319 United Sciences Testing, Inc | E64: 76.51 | G64: =+F64-E64 -> -76.51 | H64: =IF(OR(E64="",F64=""),100%,+G64/E64) -> 1
D65: 353 AEP Utility Funding LLC | E65: 16820.26 | F65: 7515.53 | G65: =+F65-E65 -> -9304.73 | H65: =IF(OR(E65="",F65=""),100%,+G65/E65) -> -0.55318586
D66: 364 AEP Nonutility Funding LLC | E66: 1799.53 | F66: 1552.26 | G66: =+F66-E66 -> -247.27 | H66: =IF(OR(E66="",F66=""),100%,+G66/E66) -> -0.1374081
D67: 389 Oxbow Lignite Company, LLC | E67: 5310.23 | F67: 9705.49 | G67: =+F67-E67 -> 4395.26 | H67: =IF(OR(E67="",F67=""),100%,+G67/E67) -> 0.82769673
D68: 397 AEP Retail Energy Partners LLC | E68: 453.19 | F68: 420.52 | G68: =+F68-E68 -> -32.67 | H68: =IF(OR(E68="",F68=""),100%,+G68/E68) -> -0.072088969
D69: 400 AEP Energy, Inc | E69: 542819.78 | F69: 353406.41 | G69: =+F69-E69 -> -189413.37 | H69: =IF(OR(E69="",F69=""),100%,+G69/E69) -> -0.34894338
D70: 412 Ohio Franklin Realty, LLC | E70: 52999.91 | F70: 30224.24 | G70: =+F70-E70 -> -22775.67 | H70: =IF(OR(E70="",F70=""),100%,+G70/E70) -> -0.42973035
D71: 417 Bold Transmission, LLC | E71: 2851.52 | F71: 370.88 | G71: =+F71-E71 -> -2480.64 | H71: =IF(OR(E71="",F71=""),100%,+G71/E71) -> -0.86993603
D72: 419 AEP OnSite Partners, LLC | E72: 334092.67 | F72: 132571.29 | G72: =+F72-E72 -> -201521.38 | H72: =IF(OR(E72="",F72=""),100%,+G72/E72) -> -0.60319007
D73: 422 AEP RENEWABLES, LLC | E73: 141251.94 | F73: 5427.81 | G73: =+F73-E73 -> -135824.13 | H73: =IF(OR(E73="",F73=""),100%,+G73/E73) -> -0.96157355
D74: 425 Solar LLCs | E74: 4637.94 | F74: 877.24 | G74: =+F74-E74 -> -3760.7 | H74: =IF(OR(E74="",F74=""),100%,+G74/E74) -> -0.81085568
D75: 431 Trent Wind Farm LLC | E75: 31808.41 | F75: 677.21 | G75: =+F75-E75 -> -31131.2 | H75: =IF(OR(E75="",F75=""),100%,+G75/E75) -> -0.97870972
D76: 432 Desert Sky Wind Farm LLC | E76: 42084.79 | F76: 700.62 | G76: =+F76-E76 -> -41384.17 | H76: =IF(OR(E76="",F76=""),100%,+G76/E76) -> -0.98335218
... D79: 446 Apple Blossom Wind, LLC | E79: 569.16 | F79: 2247.65 | G79: =+F79-E79 -> 1678.49 | H79: =IF(OR(E79="",F79=""),100%,+G79/E79) -> 2.9490653
D80: 447 Black Oak Wind, LLC | F80: 106.84 | G80: =+F80-E80 -> 106.84 | H80: =IF(OR(E80="",F80=""),100%,+G80/E80) -> 1
D81: 454 Flat Ridge 3 Wind Energy, LLC | E81: 1412.47 | F81: 1382.84 | G81: =+F81-E81 -> -29.63 | H81: =IF(OR(E81="",F81=""),100%,+G81/E81) -> -0.020977437
D82: 466 Apple Blossom Hold Co | F82: 106.84 | G82: =+F82-E82 -> 106.84 | H82: =IF(OR(E82="",F82=""),100%,+G82/E82) -> 1
D83: 471 AEP Ventures, LLC | E83: 8551.63 | F83: 7834.66 | G83: =+F83-E83 -> -716.97 | H83: =IF(OR(E83="",F83=""),100%,+G83/E83) -> -0.083840157
D84: 472 Great Bend Solar, LLC | E84: 2031.98 | G84: =+F84-E84 -> -2031.98 | H84: =IF(OR(E84="",F84=""),100%,+G84/E84) -> 1
D85: 482 Harry Allen Solar Energy LLC | E85: 100.83 | G85: =+F85-E85 -> -100.83 | H85: =IF(OR(E85="",F85=""),100%,+G85/E85) -> 1
D86: 485 AEP Renewables Development LLC | E86: 533.14 | G86: =+F86-E86 -> -533.14 | H86: =IF(OR(E86="",F86=""),100%,+G86/E86) -> 1
C87: k-NR Total | E87: 5049068 | F87: 2563410.1 | G87: =+F87-E87 -> -2485657.9 | H87: =IF(OR(E87="",F87=""),100%,+G87/E87) -> -0.49230034
B88: c-NR Total | E88: 5049068 | F88: 2563410.1 | G88: =+F88-E88 -> -2485657.9 | H88: =IF(OR(E88="",F88=""),100%,+G88/E88) -> -0.49230034
B89: d-TRANSCO | C89: l-TRANSCO | D89: 369 AEP Transmission Hldg Co, LLC | E89: 132630.86 | F89: 23112.05 | G89: =+F89-E89 -> -109518.81 | H89: =IF(OR(E89="",F89=""),100%,+G89/E89) -> -0.82574154
D90: 370 AEP Transmission Company, LLC | E90: 4263.89 | F90: 7346.94 | G90: =+F90-E90 -> 3083.05 | H90: =IF(OR(E90="",F90=""),100%,+G90/E90) -> 0.7230604
D91: 380 AEP Ohio Trans Co | E91: 4040196.1 | F91: 2886060.9 | G91: =+F91-E91 -> -1154135.3 | H91: =IF(OR(E91="",F91=""),100%,+G91/E91) -> -0.28566318
D92: 382 AEP Appalachian Trans Co | E92: 81055.69 | F92: 77504.02 | G92: =+F92-E92 -> -3551.67 | H92: =IF(OR(E92="",F92=""),100%,+G92/E92) -> -0.043817652
D93: 383 AEP West Virginia Trans Co | E93: 1713087.8 | F93: 1325945.7 | G93: =+F93-E93 -> -387142.15 | H93: =IF(OR(E93="",F93=""),100%,+G93/E93) -> -0.22599084
D94: 384 AEP Kentucky Trans Co | E94: 112138.95 | F94: 99960.02 | G94: =+F94-E94 -> -12178.93 | H94: =IF(OR(E94="",F94=""),100%,+G94/E94) -> -0.10860571
D95: 385 AEP Indiana Michigan Trans Co | E95: 2084119.2 | F95: 1549006.1 | G95: =+F95-E95 -> -535113.12 | H95: =IF(OR(E95="",F95=""),100%,+G95/E95) -> -0.25675744
D96: 386 AEP Oklahoma Trans Co | E96: 1014132 | F96: 789459.77 | G96: =+F96-E96 -> -224672.21 | H96: =IF(OR(E96="",F96=""),100%,+G96/E96) -> -0.22154139
D97: 388 AEP Southwestern Trans Co | E97: 7122.84 | F97: 6566.61 | G97: =+F97-E97 -> -556.23 | H97: =IF(OR(E97="",F97=""),100%,+G97/E97) -> -0.078091042
C98: l-TRANSCO Total | E98: 9188747.4 | F98: 6764962 | G98: =+F98-E98 -> -2423785.4 | H98: =IF(OR(E98="",F98=""),100%,+G98/E98) -> -0.26377756
B99: d-TRANSCO Total | E99: 9188747.4 | F99: 6764962 | G99: =+F99-E99 -> -2423785.4 | H99: =IF(OR(E99="",F99=""),100%,+G99/E99) -> -0.26377756
B100: e-JV | C100: m-JV | D100: 376 PATH WV Transmission Co., LLC | E100: 374.14 | F100: 865.71 | G100: =+F100-E100 -> 491.57 | H100: =IF(OR(E100="",F100=""),100%,+G100/E100) -> 1.3138665
D101: 396 RITELine Indiana, LLC | E101: 1167.62 | F101: 1223.32 | G101: =+F101-E101 -> 55.7 | H101: =IF(OR(E101="",F101=""),100%,+G101/E101) -> 0.047703876
D102: 418 Grid Assurance LLC | E102: 93419.39 | F102: 49915.34 | G102: =+F102-E102 -> -43504.05 | H102: =IF(OR(E102="",F102=""),100%,+G102/E102) -> -0.46568544
...

Sheet 457-PQ
A4: BUSINESS_UNIT | B4: DESCR | C4: FISCAL_YEAR | D4: ACCOUNT | E4: DESCR2 | F4: SUM(A.POSTED_TOTAL_AMT)
A5: 103 | B5: AEP Service Corporation | C5: 2022 | D5: 4571001 | E5: Service Rev - Direct Affil | F5: -1.5712888e+08
A6: 103 | B6: AEP Service Corporation | C6: 2022 | D6: 4572001 | E6: Service Rev-Indirect Cost-Affi | F6: -25022085
A7: 103 | B7: AEP Service Corporation | C7: 2022 | D7: 4573001 | E7: Compensation for Capital-Affil | F7: 1394582.6
A8: 103 | B8: AEP Service Corporation | C8: 2023 | D8: 4571001 | E8: Service Rev - Direct Affil | F8: -1.117754e+08
A9: 103 | B9: AEP Service Corporation | C9: 2023 | D9: 4572001 | E9: Service Rev-Indirect Cost-Affi | F9: -24843496
A10: 103 | B10: AEP Service Corporation | C10: 2023 | D10: 4573001 | E10: Compensation for Capital-Affil | F10: -2478846.8
