Workbook
Name IQ_CH: 110000
Name IQ_CQ: 5000
Name IQ_CY: 10000
Name IQ_DAILY: 500000
Name IQ_FH: 100000
Name IQ_FQ: 500
Name IQ_FY: 1000
Name IQ_LTM: 2000
Name IQ_MONTH: 15000
Name IQ_NTM: 6000
Name IQ_WEEK: 50000
Name IQ_YTD: 3000

Sheet II-I-1
C2: PUBLIC UTILITY COMMISSION OF TEXAS
C3: AEP TEXAS INC
C4: II-I-1 CLASS REVENUE REQUIREMENT ANALYSIS
C5: TEST YEAR ENDING 09/30/2023
C6: DOCKET 56165
D8: 1 | E8: 2 | F8: 3 | G8: 4 | H8: 5 | I8: 6 | J8: 7 | K8: 8 | L8: 9
D9: Test Year
C10: Description | D10: Revenue | E10: Residential | F10: Secondary | G10: Secondary | H10: Primary | I10: Transmission | J10: Lighting | K10: Total | L10: BESS
A11: Line | B11: Ref | D11: Requirement | F11: =< 10 kW | G11: > 10 kW | K11: TX Retail
A12: No. | B12: Sch | D12: Total
A14: 1 | B14: IV-J-7 | C14: Transmission (ERCOT Matrix) | D14: 4.2854577e+08 | E14: 2.0657001e+08 | F14: 9203652.3 | G14: 1.2361279e+08 | H14: 39981726 | I14: 49177593 | K14: =SUM(E14:J14) -> 4.2854578e+08
A15: =+A14+1 -> 2 | C15: Distribution | D15: =+'II-I TOTAL COMPANY'!K75 -> 7.9827524e+08 | E15: =+Distribution!K75 -> 4.5485514e+08 | F15: =+Distribution!L75 -> 17570580 | G15: =+Distribution!N75+Distribution!O75 -> 2.3558577e+08 | H15: =+Distribution!Q75+Distribution!R75 -> 48232797 | I15: =+Distribution!T75 -> 4886329 | J15: =+Distribution!U75 -> 28747963 | K15: =SUM(E15:J15) -> 7.8987858e+08 | L15: =+Distribution!V75 -> 1861985.4
A16: =+A15+1 -> 3 | C16: Metering | D16: =+'II-I TOTAL COMPANY'!L75 -> 50185561 | E16: =+Meter!K75 -> 23527397 | F16: =+Meter!L75 -> 4470397.7 | G16: =+Meter!N75+Meter!O75 -> 17747327 | H16: =+Meter!Q75+Meter!R75 -> 2239528.6 | I16: =+Meter!T75 -> 2011888.2 | J16: =+Meter!U75 -> 7.5539466 | K16: =SUM(E16:J16) -> 49996546 | L16: =+Meter!V75 -> 41759.103
A17: =+A16+1 -> 4 | C17: Billling/Customer Service | D17: =+'II-I TOTAL COMPANY'!M75 -> 18851935 | E17: =+TDCustSvc!K75 -> 14986684 | F17: =+TDCustSvc!L75 -> 1592197 | G17: =+TDCustSvc!N75+TDCustSvc!O75 -> 1966806.3 | H17: =+TDCustSvc!Q75+TDCustSvc!R75 -> 27866.936 | I17: =+TDCustSvc!T75 -> 3357.327 | J17: =+TDCustSvc!U75 -> 272365.74 | K17: =SUM(E17:J17) -> 18849278 | L17: =+TDCustSvc!V75 -> 524.32801
A18: =+A17+1 -> 5
A19: =+A18+1 -> 6 | D19: =SUM(D14:D18) -> 1.2958585e+09 | E19: =SUM(E14:E18) -> 6.9993924e+08 | F19: =SUM(F14:F18) -> 32836827 | G19: =SUM(G14:G18) -> 3.7891269e+08 | H19: =SUM(H14:H18) -> 90481919 | I19: =SUM(I14:I18) -> 56079168 | J19: =SUM(J14:J18) -> 29020337 | K19: =SUM(K14:K18) -> 1.2872702e+09 | L19: =SUM(L14:L18) -> 1904268.8
C21: Acctg Schedule I-A | D21: =+D15+D16+D17 -> 8.6731274e+08
D23: =+'[1]I-A-1'!$K$29 -> 8.6731274e+08
D24: =+D21-D23 -> -0.17025912

Sheet II-I-2
B2: PUBLIC UTILITY COMMISSION OF TEXAS
B3: AEP TEXAS INC
B4: II-I-1-2 CLASS ALLOCATION FACTORS
B5: TEST YEAR ENDING 09/30/2023
B6: DOCKET 56165
A9: Line | B9: Description | C9: Allocation | D9: Residential | E9: Secondary | F9: Secondary | G9: Primary | H9: Transmission | I9: Lighting | J9: BESS | K9: Total
A10: No. | C10: Label | E10: =< 10 kW | F10: > 10 kW | K10: TX
A13: 1 | B13: =+Distribution!B669 -> Generation Demand TX 4CP | C13: =+Distribution!E669 -> DEMANDG | D13: =+Distribution!K669 -> 3260753.1 | E13: =+Distribution!L669 -> 128972.63 | F13: =+Distribution!M669 -> 1920489.8 | G13: =+Distribution!P669 -> 544116.53 | H13: =+Distribution!T669 -> 872123.19 | I13: =+Distribution!U669 -> 0 | J13: =+Distribution!V669 -> 0 | K13: =SUM(D13:J13) -> 6726455.3
A14: =+A13+1 -> 2 | B14: =+Distribution!B670 -> Retail Generation Demand | C14: =+Distribution!E670 -> TDEMANDG | D14: =+Distribution!K670 -> 3260753.1 | E14: =+Distribution!L670 -> 128972.63 | F14: =+Distribution!M670 -> 1920489.8 | G14: =+Distribution!P670 -> 544116.53 | H14: =+Distribution!T670 -> 872123.19 | I14: =+Distribution!U670 -> 0 | J14: =+Distribution!V670 -> 0 | K14: =SUM(D14:J14) -> 6726455.3
A15: =+A14+1 -> 3 | B15: =+Distribution!B671 -> Transmission Demands | C15: =+Distribution!E671 -> DEMANDT | D15: =+Distribution!K671 -> 2576796 | E15: =+Distribution!L671 -> 95632 | F15: =+Distribution!M671 -> 1558412 | G15: =+Distribution!P671 -> 578236 | H15: =+Distribution!T671 -> 596099 | I15: =+Distribution!U671 -> 0 | J15: =+Distribution!V671 -> 0 | K15: =SUM(D15:J15) -> 5405175
A16: =+A15+1 -> 4 | B16: =+Distribution!B672 -> Distribution Primary Demands - MDD | C16: =+Distribution!E672 -> DEMANDDP | D16: =+Distribution!K672 -> 4044549.9 | E16: =+Distribution!L672 -> 141089.14 | F16: =+Distribution!M672 -> 2127839.4 | G16: =+Distribution!P672 -> 730743.31 | H16: =+Distribution!T672 -> 0 | I16: =+Distribution!U672 -> 79180.024 | J16: =+Distribution!V672 -> 27135.076 | K16: =SUM(D16:J16) -> 7150536.9
A17: =+A16+1 -> 5 | B17: =+Distribution!B673 -> Distribution Secondary Demand | C17: =+Distribution!E673 -> DEMANDDS | D17: =+Distribution!K673 -> 4044549.9 | E17: =+Distribution!L673 -> 141089.14 | F17: =+Distribution!M673 -> 2127839.4 | G17: =+Distribution!P673 -> 0 | H17: =+Distribution!T673 -> 0 | I17: =+Distribution!U673 -> 79180.024 | J17: =+Distribution!V673 -> 0 | K17: =SUM(D17:J17) -> 6392658.5
A18: =+A17+1 -> 6 | B18: =+Distribution!B674 -> Energy | C18: =+Distribution!E674 -> ENERGY | D18: =+Distribution!K674 -> 1.2589883e+10 | E18: =+Distribution!L674 -> 6.7210011e+08 | F18: =+Distribution!M674 -> 9.2050572e+09 | G18: =+Distribution!P674 -> 4.5250716e+09 | H18: =+Distribution!T674 -> 1.1035697e+10 | I18: =+Distribution!U674 -> 2.383849e+08 | J18: =+Distribution!V674 -> 29603831 | K18: =SUM(D18:J18) -> 3.8295797e+10
A19: =+A18+1 -> 7 | B19: =+Distribution!B675 -> Non-Coincident Peaks | C19: =+Distribution!E675 -> NCP | D19: =+Distribution!K675 -> 79181811 | E19: =+Distribution!L675 -> 2897445.4 | F19: =+Distribution!M675 -> 31023216 | G19: =+Distribution!P675 -> 10189738 | H19: =+Distribution!T675 -> 25972434 | I19: =+Distribution!U675 -> 809370.8 | J19: =+Distribution!V675 -> 550613.44 | K19: =SUM(D19:J19) -> 1.5062463e+08
A20: =+A19+1 -> 8 | B20: =+Distribution!B676 -> Customers | C20: =+Distribution!E676 -> CUSTOMERS | D20: =+Distribution!K676 -> 935238 | E20: =+Distribution!L676 -> 99366 | F20: =+Distribution!M676 -> 72409 | G20: =+Distribution!P676 -> 1086 | H20: =+Distribution!T676 -> 123 | I20: =+Distribution!U676 -> 221390 | J20: =+Distribution!V676 -> 19 | K20: =SUM(D20:J20) -> 1329631
A21: =+A20+1 -> 9 | B21: =+Distribution!B677 -> Distribution Customers | C21: =+Distribution!E677 -> DCUSTOMERS | D21: =+Distribution!K677 -> 935238 | E21: =+Distribution!L677 -> 99366 | F21: =+Distribution!M677 -> 72409 | G21: =+Distribution!P677 -> 1086 | H21: =+Distribution!T677 -> 0 | I21: =+Distribution!U677 -> 220232 | J21: =+Distribution!V677 -> 19 | K21: =SUM(D21:J21) -> 1328350
A22: =+A21+1 -> 10 | B22: =+Distribution!B678 -> Services Account 369 | C22: =+Distribution!E678 -> SERVICES | D22: =+Distribution!K678 -> 935238 | E22: =+Distribution!L678 -> 94498 | F22: =+Distribution!M678 -> 125662 | G22: =+Distribution!P678 -> 0 | H22: =+Distribution!T678 -> 0 | I22: =+Distribution!U678 -> 0 | J22: =+Distribution!V678 -> 0 | K22: =SUM(D22:J22) -> 1155398
A23: =+A22+1 -> 11 | B23: =+Distribution!B679 -> Meters Account 370 | C23: =+Distribution!E679 -> METERS | D23: =+Distribution!K679 -> 935238 | E23: =+Distribution!L679 -> 177705.24 | F23: =+Distribution!M679 -> 705477.84 | G23: =+Distribution!P679 -> 94875.887 | H23: =+Distribution!T679 -> 79975.918 | I23: =+Distribution!U679 -> 0 | J23: =+Distribution!V679 -> 1659.8912 | K23: =SUM(D23:J23) -> 1994932.8
A24: =+A23+1 -> 12 | B24: =+Distribution!B680 -> Non-Roadway Lighting Account 371 | C24: =+Distribution!E680 -> NROADLIGHT | D24: =+Distribution!K680 -> 0 | E24: =+Distribution!L680 -> 0 | F24: =+Distribution!M680 -> 0 | G24: =+Distribution!P680 -> 0 | H24: =+Distribution!T680 -> 0 | I24: =+Distribution!U680 -> 1.1290995e+08 | J24: =+Distribution!V680 -> 0 | K24: =SUM(D24:J24) -> 1.1290995e+08
A25: =+A24+1 -> 13 | B25: =+Distribution!B681 -> Roadway Lighting Account 373 | C25: =+Distribution!E681 -> ROADLIGHT | D25: =+Distribution!K681 -> 0 | E25: =+Distribution!L681 -> 0 | F25: =+Distribution!M681 -> 0 | G25: =+Distribution!P681 -> 0 | H25: =+Distribution!T681 -> 0 | I25: =+Distribution!U681 -> 1.2547495e+08 | J25: =+Distribution!V681 -> 0 | K25: =SUM(D25:J25) -> 1.2547495e+08
... A83: =+A82+1 -> 71 | B83: =+Distribution!B739 -> Excess Mitigation Credit | C83: =+Distribution!E739 -> EMC | D83: =+Distribution!K739 -> 0 | E83: =+Distribution!L739 -> 0 | F83: =+Distribution!M739 -> 0 | G83: =+Distribution!P739 -> 0 | H83: =+Distribution!T739 -> 0 | I83: =+Distribution!U739 -> 0 | J83: =+Distribution!V739 -> 0 | K83: =SUM(D83:J83) -> 0

Sheet II-I-2.c
B2: PUBLIC UTILITY COMMISSION OF TEXAS
B3: AEP TEXAS INC
B4: II-I-1-2 CLASS ALLOCATION FACTORS
B5: TEST YEAR ENDING 09/30/2023
B6: DOCKET 56165
A9: Line | B9: Description | C9: Allocation | D9: Residential | E9: Secondary | F9: Secondary | G9: Primary | H9: Transmission | I9: Lighting | J9: BESS | K9: Total
A10: No. | C10: Label | E10: =< 10 kW | F10: > 10 kW | K10: TX
A13: 1 | B13: =+Distribution!B741 -> Generation Demand TX 4CP | C13: =+Distribution!E741 -> DEMANDG | D13: =+Distribution!K741 -> 0.48476544 | E13: =+Distribution!L741 -> 0.019173937 | F13: =+Distribution!M741 -> 0.28551292 | G13: =+Distribution!P741 -> 0.080892017 | H13: =+Distribution!T741 -> 0.12965569 | I13: =+Distribution!U741 -> 0 | J13: =+Distribution!V741 -> 0 | K13: =SUM(D13:J13) -> 1
A14: =+A13+1 -> 2 | B14: =+Distribution!B742 -> Retail Generation Demand | C14: =+Distribution!E742 -> TDEMANDG | D14: =+Distribution!K742 -> 0.48476544 | E14: =+Distribution!L742 -> 0.019173937 | F14: =+Distribution!M742 -> 0.28551292 | G14: =+Distribution!P742 -> 0.080892017 | H14: =+Distribution!T742 -> 0.12965569 | I14: =+Distribution!U742 -> 0 | J14: =+Distribution!V742 -> 0 | K14: =SUM(D14:J14) -> 1
A15: =+A14+1 -> 3 | B15: =+Distribution!B743 -> Transmission Demands | C15: =+Distribution!E743 -> DEMANDT | D15: =+Distribution!K743 -> 0.47672758 | E15: =+Distribution!L743 -> 0.017692674 | F15: =+Distribution!M743 -> 0.28831851 | G15: =+Distribution!P743 -> 0.10697822 | H15: =+Distribution!T743 -> 0.11028302 | I15: =+Distribution!U743 -> 0 | J15: =+Distribution!V743 -> 0 | K15: =SUM(D15:J15) -> 1
A16: =+A15+1 -> 4 | B16: =+Distribution!B744 -> Distribution Primary Demands - MDD | C16: =+Distribution!E744 -> DEMANDDP | D16: =+Distribution!K744 -> 0.56562885 | E16: =+Distribution!L744 -> 0.019731265 | F16: =+Distribution!M744 -> 0.29757757 | G16: =+Distribution!P744 -> 0.10219419 | H16: =+Distribution!T744 -> 0 | I16: =+Distribution!U744 -> 0.011073298 | J16: =+Distribution!V744 -> 0.0037948306 | K16: =SUM(D16:J16) -> 1
A17: =+A16+1 -> 5 | B17: =+Distribution!B745 -> Distribution Secondary Demand | C17: =+Distribution!E745 -> DEMANDDS | D17: =+Distribution!K745 -> 0.63268669 | E17: =+Distribution!L745 -> 0.022070496 | F17: =+Distribution!M745 -> 0.33285673 | G17: =+Distribution!P745 -> 0 | H17: =+Distribution!T745 -> 0 | I17: =+Distribution!U745 -> 0.012386087 | J17: =+Distribution!V745 -> 0 | K17: =SUM(D17:J17) -> 1
A18: =+A17+1 -> 6 | B18: =+Distribution!B746 -> Energy | C18: =+Distribution!E746 -> ENERGY | D18: =+Distribution!K746 -> 0.32875364 | E18: =+Distribution!L746 -> 0.017550232 | F18: =+Distribution!M746 -> 0.2403673 | G18: =+Distribution!P746 -> 0.11816105 | H18: =+Distribution!T746 -> 0.28816992 | I18: =+Distribution!U746 -> 0.0062248319 | J18: =+Distribution!V746 -> 0.00077303081 | K18: =SUM(D18:J18) -> 1
A19: =+A18+1 -> 7 | B19: =+Distribution!B747 -> Non-Coincident Peaks | C19: =+Distribution!E747 -> NCP | D19: =+Distribution!K747 -> 0.52568967 | E19: =+Distribution!L747 -> 0.019236199 | F19: =+Distribution!M747 -> 0.20596377 | G19: =+Distribution!P747 -> 0.067649878 | H19: =+Distribution!T747 -> 0.17243152 | I19: =+Distribution!U747 -> 0.0053734293 | J19: =+Distribution!V747 -> 0.0036555339 | K19: =SUM(D19:J19) -> 1
A20: =+A19+1 -> 8 | B20: =+Distribution!B748 -> Customers | C20: =+Distribution!E748 -> CUSTOMERS | D20: =+Distribution!K748 -> 0.70338161 | E20: =+Distribution!L748 -> 0.074732012 | F20: =+Distribution!M748 -> 0.054457966 | G20: =+Distribution!P748 -> 0.00081676796 | H20: =+Distribution!T748 -> 9.2506868e-05 | I20: =+Distribution!U748 -> 0.16650484 | J20: =+Distribution!V748 -> 1.4289679e-05 | K20: =SUM(D20:J20) -> 1
A21: =+A20+1 -> 9 | B21: =+Distribution!B749 -> Distribution Customers | C21: =+Distribution!E749 -> DCUSTOMERS | D21: =+Distribution!K749 -> 0.70405992 | E21: =+Distribution!L749 -> 0.07480408 | F21: =+Distribution!M749 -> 0.054510483 | G21: =+Distribution!P749 -> 0.00081755561 | H21: =+Distribution!T749 -> 0 | I21: =+Distribution!U749 -> 0.16579365 | J21: =+Distribution!V749 -> 1.4303459e-05 | K21: =SUM(D21:J21) -> 1
A22: =+A21+1 -> 10 | B22: =+Distribution!B750 -> Services Account 369 | C22: =+Distribution!E750 -> SERVICES | D22: =+Distribution!K750 -> 0.80945094 | E22: =+Distribution!L750 -> 0.081788267 | F22: =+Distribution!M750 -> 0.10876079 | G22: =+Distribution!P750 -> 0 | H22: =+Distribution!T750 -> 0 | I22: =+Distribution!U750 -> 0 | J22: =+Distribution!V750 -> 0 | K22: =SUM(D22:J22) -> 1
A23: =+A22+1 -> 11 | B23: =+Distribution!B751 -> Meters Account 370 | C23: =+Distribution!E751 -> METERS | D23: =+Distribution!K751 -> 0.46880677 | E23: =+Distribution!L751 -> 0.08907831 | F23: =+Distribution!M751 -> 0.35363489 | G23: =+Distribution!P751 -> 0.047558438 | H23: =+Distribution!T751 -> 0.04008953 | I23: =+Distribution!U751 -> 0 | J23: =+Distribution!V751 -> 0.00083205371 | K23: =SUM(D23:J23) -> 1
A24: =+A23+1 -> 12 | B24: =+Distribution!B752 -> Non-Roadway Lighting Account 371 | C24: =+Distribution!E752 -> NROADLIGHT | D24: =+Distribution!K752 -> 0 | E24: =+Distribution!L752 -> 0 | F24: =+Distribution!M752 -> 0 | G24: =+Distribution!P752 -> 0 | H24: =+Distribution!T752 -> 0 | I24: =+Distribution!U752 -> 1 | J24: =+Distribution!V752 -> 0 | K24: =SUM(D24:J24) -> 1
A25: =+A24+1 -> 13 | B25: =+Distribution!B753 -> Roadway Lighting Account 373 | C25: =+Distribution!E753 -> ROADLIGHT | D25: =+Distribution!K753 -> 0 | E25: =+Distribution!L753 -> 0 | F25: =+Distribution!M753 -> 0 | G25: =+Distribution!P753 -> 0 | H25: =+Distribution!T753 -> 0 | I25: =+Distribution!U753 -> 1 | J25: =+Distribution!V753 -> 0 | K25: =SUM(D25:J25) -> 1
... A83: =+A82+1 -> 71 | B83: =+Distribution!B811 -> Excess Mitigation Credit | C83: =+Distribution!E811 -> EMC | D83: =+Distribution!K811 -> 0 | E83: =+Distribution!L811 -> 0 | F83: =+Distribution!M811 -> 0 | G83: =+Distribution!P811 -> 0 | H83: =+Distribution!T811 -> 0 | I83: =+Distribution!U811 -> 0 | J83: =+Distribution!V811 -> 0 | K83: =SUM(D83:J83) -> 0

Sheet II-I-2.f
B2: PUBLIC UTILITY COMMISSION OF TEXAS
B3: AEP TEXAS INC
B4: II-I-1-2 CLASS ALLOCATION RATIONALE
B5: TEST YEAR ENDING 09/30/2023
B6: DOCKET 56165
A9: Acct | B9: Description | C9: Function | D9: Allocation | E9: Description of Allocation | F9: Rationale
A10: No. | D10: Factor
B13: PLANT IN SERVICE
B14: Intangible Plant
A15: 301 | B15: Organization | C15: TDCS | D15: LABOR | E15: Labor for AEP Texas and Service Company | F15: Related to functionalized labor
A16: 303 | B16: Misc Intangible Plant | C16: DIST | D16: LABOR | E16: Labor for AEP Texas and Service Company | F16: Related to functionalized labor
A17: 303 | B17: Misc Intangible Plant | C17: MET | D17: LABOR | E17: Labor for AEP Texas and Service Company | F17: Related to functionalized labor
A18: 303 | B18: Misc Intangible Plant | C18: TDCS | D18: LABOR | E18: Labor for AEP Texas and Service Company | F18: Related to functionalized labor
B20: Transmission Plant
A21: 350-359 | B21: Transmission Plant | C21: TRAN | D21: TRANPLT | E21: N/A | F21: N/A
B23: Distribution Plant
A24: 360-363 | B24: Accounts 360-363 | C24: DIST | D24: DEMANDDP | E24: Distribution Primary Demands (MDD) | F24: Related to customer demand
A25: 364 | B25: Poles,Towers & Fixtures Primary | C25: DIST | D25: DEMANDDP | E25: Distribution Primary Demands (MDD) | F25: Related to customer demand
A26: 364 | B26: Poles,Towers & Fixtures Secondary | C26: DIST | D26: DEMANDDP | E26: Distribution Primary Demands (MDD) | F26: Related to customer demand
A27: 365 | B27: O.H. Conductors & Devices Primary | C27: DIST | D27: DEMANDDP | E27: Distribution Primary Demands (MDD) | F27: Related to customer demand
A28: 365 | B28: O.H. Conductors & Devices Secondary | C28: DIST | D28: DEMANDDS | E28: Distribution Secondary Demands (MDD) | F28: Related to customer demand
A29: 366 | B29: Underground Conduits Primary | C29: DIST | D29: DEMANDDP | E29: Distribution Primary Demands (MDD) | F29: Related to customer demand
A30: 366 | B30: Underground Conduits Secondary | C30: DIST | D30: DEMANDDS | E30: Distribution Secondary Demands (MDD) | F30: Related to customer demand
A31: 367 | B31: U.G. Conductors & Devices Primary | C31: DIST | D31: DEMANDDP | E31: Distribution Primary Demands (MDD) | F31: Related to customer demand
A32: 367 | B32: U.G. Conductors & Devices Secondary | C32: DIST | D32: DEMANDDS | E32: Distribution Secondary Demands (MDD) | F32: Related to customer demand
A33: 368 | B33: Line Transformers Primary | C33: DIST | D33: DEMANDDP | E33: Distribution Primary Demands (MDD) | F33: Related to customer demand
A34: 368 | B34: Line Transformers Secondary | C34: DIST | D34: DEMANDDS | E34: Distribution Secondary Demands (MDD) | F34: Related to customer demand
A35: 369 | B35: Services | C35: DIST | D35: SERVICES | E35: Services Account 369 | F35: Related to customer count
A36: 370 | B36: Meters | C36: DIST | D36: METERS | E36: Meters Account 370 | F36: Related to customer count
... A39: 373 | B39: Street Lights | C39: DIST | D39: ROADLIGHT | E39: Roadway Lighting Account 373 | F39: Related to fixture count
B41: General Plant
A42: 389-399 | B42: General Plant | C42: DIST | D42: LABOR | E42: Labor for AEP Texas and Service Company | F42: Related to functionalized labor
A43: 389-399 | B43: General Plant | C43: MET | D43: LABOR | E43: Labor for AEP Texas and Service Company | F43: Related to functionalized labor
A44: 389-399 | B44: General Plant | C44: TDCS | D44: LABOR | E44: Labor for AEP Texas and Service Company | F44: Related to functionalized labor
A45: 397 | B45: Communicaiton Equipment | C45: DIST | D45: LABOR | E45: Labor for AEP Texas and Service Company | F45: Related to functionalized labor
A46: 398 | B46: Communicaiton Equipment | C46: MET | D46: LABOR | E46: Labor for AEP Texas and Service Company | F46: Related to functionalized labor
A47: 399 | B47: Communicaiton Equipment | C47: TDCS | D47: LABOR | E47: Labor for AEP Texas and Service Company | F47: Related to functionalized labor
B49: Accumulated Depreciation
B50: Intangible Plant Accum. Depr.
A51: 303 | B51: Misc Intangible Plant | C51: DIST | D51: LABOR | E51: Labor for AEP Texas and Service Company | F51: Depreciation allocated based on plant
A52: 303 | B52: Misc Intangible Plant | C52: MET | D52: LABOR | E52: Labor for AEP Texas and Service Company | F52: Depreciation allocated based on plant
A53: 303 | B53: Misc Intangible Plant | C53: TDCS | D53: LABOR | E53: Labor for AEP Texas and Service Company | F53: Depreciation allocated based on plant
B54: Transmission Plant Accum. Depr.
A55: 350-359 | B55: Transmission Plant | C55: TRAN | D55: TRANPLT | E55: N/A | F55: N/A
B57: Distribution Plant Accum. Depr.
A58: 360-363 | B58: Accounts 360-363 | C58: DIST | D58: DEMANDDP | E58: Follows associated plant investment | F58: Follows associated plant investment
A59: 364 | B59: Poles,Towers & Fixtures Primary | C59: DIST | D59: DEMANDDP | E59: Follows associated plant investment | F59: Follows associated plant investment
A60: 364 | B60: Poles,Towers & Fixtures Secondary | C60: DIST | D60: DEMANDDP | E60: Follows associated plant investment | F60: Follows associated plant investment
A61: 365 | B61: O.H. Conductors & Devices Primary | C61: DIST | D61: DEMANDDP | E61: Follows associated plant investment | F61: Follows associated plant investment
A62: 365 | B62: O.H. Conductors & Devices Secondary | C62: DIST | D62: DEMANDDS | E62: Follows associated plant investment | F62: Follows associated plant investment
A63: 366 | B63: Underground Conduits Primary | C63: DIST | D63: DEMANDDP | E63: Follows associated plant investment | F63: Follows associated plant investment
A64: 366 | B64: Underground Conduits Secondary | C64: DIST | D64: DEMANDDS | E64: Follows associated plant investment | F64: Follows associated plant investment
A65: 367 | B65: U.G. Conductors & Devices Primary | C65: DIST | D65: DEMANDDP | E65: Follows associated plant investment | F65: Follows associated plant investment
A66: 367 | B66: U.G. Conductors & Devices Secondary | C66: DIST | D66: DEMANDDS | E66: Follows associated plant investment | F66: Follows associated plant investment
A67: 368 | B67: Line Transformers Primary | C67: DIST | D67: DEMANDDP | E67: Follows associated plant investment | F67: Follows associated plant investment
A68: 368 | B68: Line Transformers Secondary | C68: DIST | D68: DEMANDDS | E68: Follows associated plant investment | F68: Follows associated plant investment
A69: 369 | B69: Services | C69: DIST | D69: SERVICES | E69: Follows associated plant investment | F69: Follows associated plant investment
A70: 370 | B70: Meters | C70: MET | D70: METERS | E70: Follows associated plant investment | F70: Follows associated plant investment
... A73: 373 | B73: Street Lights | C73: DIST | D73: ROADLIGHT | E73: Follows associated plant investment | F73: Follows associated plant investment
B75: General Plant Accum. Depr.
A76: 389-399 | B76: General Plant | C76: MET | D76: LABOR | E76: Follows associated plant investment | F76: Follows associated plant investment
A77: 389-399 | B77: General Plant | C77: TDCS | D77: LABOR | E77: Follows associated plant investment | F77: Follows associated plant investment
A78: 397 | B78: Communicaiton Equipment | C78: DIST | D78: LABOR | E78: Follows associated plant investment | F78: Follows associated plant investment
A79: 398 | B79: Communicaiton Equipment | C79: MET | D79: LABOR | E79: Follows associated plant investment | F79: Follows associated plant investment
A80: 399 | B80: Communicaiton Equipment | C80: TDCS | D80: LABOR | E80: Follows associated plant investment | F80: Follows associated plant investment
B82: Plant Held for Future Use
A83: 105 | B83: Plant Held for Future Use | C83: DIST | D83: DEMANDDP | E83: Distribution Primary Demands (MDD) | F83: Related to customer demand
B85: Other Accumulated Provision
B86: ARO | C86: DIST | D86: DISTPLT | E86: Distribution Plant | F86: Reltated to plant investment
B88: Materials and Supplies
A89: 154 | B89: Materials and Supplies | C89: DIST | D89: PLTSVC | E89: Plant in Service | F89: Related to plant in service
A90: 155 | B90: Materials and Supplies | C90: MET | D90: PLTSVC | E90: Plant in Service | F90: Related to plant in service
A91: 156 | B91: Materials and Supplies | C91: TDCS | D91: PLTSVC | E91: Plant in Service | F91: Related to plant in service
B93: Cash Working Capital
B94: Cash from Operations | C94: DIST | D94: O&M | E94: Total Retail Operations and Maintenance | F94: Related to functionalalized O&M
B95: Cash from Operations | C95: MET | D95: O&M | E95: Total Retail Operations and Maintenance | F95: Related to functionalalized O&M
B96: Customer Deposits | C96: DIST | D96: Customers | E96: Year-end Customers | F96: Related to customer demand
B98: Prepayments
A99: 165 | B99: Prepayments | C99: DIST | D99: PLTSVC | E99: Plant in Service | F99: Related to plant in service
A100: 165 | B100: Prepayments | C100: MET | D100: PLTSVC | E100: Plant in Service | F100: Related to plant in service
A101: 165 | B101: Prepayments | C101: TDCS | D101: PLTSVC | E101: Plant in Service | F101: Related to plant in service
B103: Other Rate Base Items
A104: 253 | B104: Environmental Remediation | C104: DIST | D104: DISTPLT | E104: Distribution Plant | F104: Related to plant in service
A105: 182 | B105: Debt Refinancing - Restructuring | C105: DIST | D105: DISTPLT | E105: Distribution Plant | F105: Related to plant in service
A106: 182 | B106: Debt Refinancing - Restructuring | C106: MET | D106: DISTPLT | E106: Distribution Plant | F106: Related to plant in service
A107: 182 | B107: Debt Refinancing - Restructuring | C107: TDCS | D107: PLTSVC | E107: Plant In Service | F107: Related to plant in service
A108: 182 | B108: Catastrophe Reserve | C108: DIST | D108: DISTPLT | E108: Distribution Plant | F108: Related to plant in service
A109: 182 | B109: Catastrophe Reserve | C109: MET | D109: DISTPLT | E109: Distribution Plant | F109: Related to plant in service
A110: 182 | B110: Non-AMI Meters/Amort | C110: MET | D110: DISTPLT | E110: Distribution Plant | F110: Related to plant in service
A111: 254/253 | B111: Excess Earnings/Other Def Credits | C111: DIST | D111: DISTPLT | E111: Distribution Plant | F111: Related to plant in service
A112: 254/253 | B112: Excess Earnings/Other Def Credits | C112: MET | D112: DISTPLT | E112: Distribution Plant | F112: Related to plant in service
A113: 254/253 | B113: Excess Earnings/Other Def Credits | C113: TDCS | D113: PLTSVC | E113: Plant In Service | F113: Related to plant in service
A114: 182 | B114: SFAS 106 Medicare Subsidy | C114: DIST | D114: DISTPLT | E114: Distribution Plant | F114: Related to plant in service
A115: 182 | B115: SFAS 106 Medicare Subsidy | C115: MET | D115: DISTPLT | E115: Distribution Plant | F115: Related to plant in service
A116: 182 | B116: SFAS 106 Medicare Subsidy | C116: TDCS | D116: LABOR | E116: Labor for AEP Texas and Service Company | F116: Related to plant in service
A117: 182 | B117: SFAS 109 Flow Thru Defd FIT and SIT | C117: DIST | D117: DISTPLT | E117: Distribution Plant | F117: Related to plant in service
A118: 182 | B118: SFAS 109 Flow Thru Defd FIT and SIT | C118: MET | D118: DISTPLT | E118: Distribution Plant | F118: Related to plant in service
A119: 182 | B119: SFAS 109 Flow Thru Defd FIT and SIT | C119: TDCS | D119: PLTSVC | E119: Plant In Service | F119: Related to plant in service
A120: 254/253 | B120: SFAS 109 Liability Grossup & Excess ADIT | C120: DIST | D120: DISTPLT | E120: Distribution Plant | F120: Related to plant in service
A121: 254/253 | B121: SFAS 109 Liability Grossup & Excess ADIT | C121: MET | D121: DISTPLT | E121: Distribution Plant | F121: Related to plant in service
...

Sheet II-I TOTAL COMPANY
D1: 1 | E1: 2 | H1: 7 | J1: 3 | K1: =J1+1 -> 4 | L1: =K1+1 -> 5 | M1: =L1+1 -> 6
B4: PUBLIC UTILITY COMMISION OF TEXAS
B5: AEP TEXAS INC
B6: II-I COST OF SERVICE
B7: TEST YEAR ENDING 09/30/2023
B8: DOCKET 56165
A10: Line | B10: Account | C10: Description | D10: Fuctionalization | E10: Reference | F10: Total AEP TX | G10: Difference | H10: Total AEP Texas | J10: Functionalized | K10: Functionalized | L10: Functionalized | M10: Functionalized | N10: INPUT | P10: Verification
A11: No. | B11: No. | D11: FACTOR | E11: Schedule | F11: As Filed | J11: TRANSMISSION | K11: DISTRIBUTION | L11: T&D METERING | M11: T&D CUST SERV
A12: (1) | B12: (2) | C12: (3) | D12: (4) | E12: (5) | H12: (6) | J12: (7) | K12: (8) | M12: (10)
B13: Schedule I-A Cost of Service by Function | N13: INPUT | P13: Verification
B15: Summary of Results @ Present ROR
A17: 1 | B17: Rate Base by Function
A18: =+A17+1 -> 2 | B18: Plant Investment
A19: =+A18+1 -> 3 | C19: Intangible | F19: =+H19 -> 1.5606761e+08 | G19: =+H19-F19 -> 0 | H19: =SUM(J19:M19) -> 1.5606761e+08 | J19: =+J96 -> 0 | K19: =+K96 -> 1.5236904e+08 | L19: =+L96 -> 3698361.7 | M19: =+M96 -> 212.22859
A20: =+A19+1 -> 4 | C20: Transmission | F20: =+H20 -> 0 | G20: =+H20-F20 -> 0 | H20: =SUM(J20:M20) -> 0 | J20: =+J111 -> 0 | K20: =+K111 -> 0 | L20: =+L111 -> 0 | M20: =+M111 -> 0
A21: =+A20+1 -> 5 | C21: Distribution | F21: =+H21 -> 5.7424589e+09 | G21: =+H21-F21 -> 0 | H21: =SUM(J21:M21) -> 5.7424589e+09 | J21: =+J147 -> 0 | K21: =+K147 -> 5.530937e+09 | L21: =+L147 -> 2.1152186e+08 | M21: =+M147 -> 0
A22: =+A21+1 -> 6 | C22: General | F22: =+H22 -> 6.660567e+08 | G22: =+H22-F22 -> 0 | H22: =SUM(J22:M22) -> 6.660567e+08 | J22: =+J162+J168 -> 0 | K22: =+K162+K168 -> 6.5153933e+08 | L22: =+L162+L168 -> 9067590.5 | M22: =+M162+M168 -> 5449781.4
A23: =+A22+1 -> 7
A24: =+A23+1 -> 8 | B24: Total Plant Investment | F24: =SUM(F19:F23) -> 6.5645832e+09 | G24: =SUM(G19:G23) -> 0 | H24: =SUM(J24:M24) -> 6.5645832e+09 | J24: =SUM(J19:J23) -> 0 | K24: =SUM(K19:K23) -> 6.3348454e+09 | L24: =SUM(L19:L23) -> 2.2428781e+08 | M24: =SUM(M19:M23) -> 5449993.6
A25: =+A24+1 -> 9
A26: =+A25+1 -> 10 | C26: Less Accumulated Depreciation | F26: =+H26 -> -1.6725996e+09 | G26: =+H26-F26 -> 0 | H26: =SUM(J26:M26) -> -1.6725996e+09 | J26: =-J247 -> 0 | K26: =-K247 -> -1.5577575e+09 | L26: =-L247 -> -1.1381186e+08 | M26: =-M247 -> -1030145.8
A27: =+A26+1 -> 11
A28: =+A27+1 -> 12 | B28: Net Plant Investment | F28: =SUM(F24:F26) -> 4.8919836e+09 | G28: =SUM(G24:G26) -> 0 | H28: =SUM(J28:M28) -> 4.8919836e+09 | J28: =+J24+J26 -> 0 | K28: =+K24+K26 -> 4.7770878e+09 | L28: =+L24+L26 -> 1.1047595e+08 | M28: =+M24+M26 -> 4419847.8
A29: =+A28+1 -> 13
A30: =+A29+1 -> 14 | B30: Material and Supplies | F30: =+H30 -> 1.1803546e+08 | G30: =+H30-F30 -> 0 | H30: =SUM(J30:M30) -> 1.1803546e+08 | J30: =+J266 -> 0 | K30: =+K266 -> 1.1523846e+08 | L30: =+L266 -> 2797003.6 | M30: =+M266 -> 0
A31: =+A30+1 -> 15 | B31: Cash Working Capital | F31: =+H31 -> -16937327 | G31: =+H31-F31 -> 0 | H31: =SUM(J31:M31) -> -16937327 | J31: =+J270 -> 0 | K31: =+K270 -> -16416706 | L31: =+L270 -> -467377.98 | M31: =+M270 -> -53243.142
A32: =+A31+1 -> 16 | B32: Prepayments | F32: =+H32 -> 80201587 | G32: =+H32-F32 -> 0 | H32: =SUM(J32:M32) -> 80201587 | J32: =+J276 -> 0 | K32: =+K276 -> 57619309 | L32: =+L276 -> 12780986 | M32: =+M276 -> 9801291.6
A33: =+A32+1 -> 17 | B33: Other Rate Base | F33: =+H33 -> -2.5206533e+08 | G33: =+H33-F33 -> 0 | H33: =SUM(J33:M33) -> -2.5206533e+08 | J33: =+J253+J259+J292 -> 0 | K33: =+K253+K259+K292 -> -2.5972059e+08 | L33: =+L253+L259+L292 -> 7523261.8 | M33: =+M253+M259+M292 -> 131997.36
A34: =+A33+1 -> 18 | B34: Accumulated Deferred Income Taxes | F34: =+H34 -> -5.7272313e+08 | G34: =+H34-F34 -> 0 | H34: =SUM(J34:M34) -> -5.7272313e+08 | J34: =+J306 -> 0 | K34: =+K306 -> -5.5590275e+08 | L34: =+L306 -> -15875665 | M34: =+M306 -> -944718.08
A35: =+A34+1 -> 19 | B35: Customer Deposits | F35: =+H35 -> -42130 | G35: =+H35-F35 -> 0 | H35: =SUM(J35:M35) -> -42130 | K35: =K271 -> -42130 | L35: =L271 -> 0 | M35: =M271 -> 0
A36: =+A35+1 -> 20 | B36: Total Rate Base | F36: =SUM(F28:F35) -> 4.2484528e+09 | G36: =SUM(G28:G34) -> 0 | H36: =SUM(J36:M36) -> 4.2484528e+09 | J36: =SUM(J28:J35) -> 0 | K36: =SUM(K28:K35) -> 4.1178634e+09 | L36: =SUM(L28:L35) -> 1.1723416e+08 | M36: =SUM(M28:M35) -> 13355176
A37: =+A36+1 -> 21
A38: =+A37+1 -> 22
A39: =+A38+1 -> 23 | B39: Current Tariff Revenues | F39: =+H39 -> 5.8173587e+08 | G39: =+H39-F39 -> 0 | H39: =SUM(J39:M39) -> 5.8173587e+08 | K39: =+'[2]II-H-4.1 Functions'!$F$213 -> 5.0555742e+08 | L39: =+'[2]II-H-4.1 Functions'!$E$213 -> 56905339 | M39: =+'[2]II-H-4.1 Functions'!$D$213 -> 19273107 | N39: Sch H
A40: =+A39+1 -> 24 | B40: Current Miscellaneous Revenues | F40: =+H40 -> 26846753 | G40: =+H40-F40 -> 0 | H40: =SUM(J40:M40) -> 26846753 | J40: =+J664 -> 0 | K40: =+K664 -> 25990116 | L40: =+L664 -> 856637.48 | M40: =+M664 -> 0
A41: =+A40+1 -> 25 | B41: Current TCRF Revenues | F41: =+H41 -> 0 | G41: =+H41-F41 -> 0 | H41: =SUM(J41:M41) -> 0 | J41: =+J665 -> 0 | K41: 0 | L41: =+L665 -> 0 | M41: =+M665 -> 0
A42: =+A41+1 -> 26 | B42: Current Rider Revenues | F42: =+H42 -> 0 | G42: =+H42-F42 -> 0 | H42: =SUM(J42:M42) -> 0 | J42: 0 | L42: 0 | M42: 0
A43: =+A42+1 -> 27 | B43: Current Total Revenues | F43: =SUM(F39:F42) -> 6.0858262e+08 | G43: =SUM(G39:G42) -> 0 | H43: =SUM(J43:M43) -> 6.0858262e+08 | J43: =SUM(J39:J42) -> 0 | K43: =SUM(K39:K42) -> 5.3154754e+08 | L43: =SUM(L39:L42) -> 57761977 | M43: =SUM(M39:M42) -> 19273107
A44: =+A43+1 -> 28
A45: =+A44+1 -> 29 | B45: Operation & Maintenance | F45: =+H45 -> 2.0133135e+08 | G45: =+H45-F45 -> 0 | H45: =SUM(J45:M45) -> 2.0133135e+08 | J45: =+J429 -> 0 | K45: =+K429 -> 1.6039674e+08 | L45: =+L429 -> 24275503 | M45: =+M429 -> 16659108
A46: =+A45+1 -> 30 | B46: Depreciation and Amortization | F46: =+H46 -> 2.227321e+08 | G46: =+H46-F46 -> 0 | H46: =SUM(J46:M46) -> 2.227321e+08 | J46: =+J597 -> 0 | K46: =+K597 -> 2.0830453e+08 | L46: =+L597 -> 14340683 | M46: =+M597 -> 86884.013
A47: =+A46+1 -> 31 | B47: Taxes Other Than Income Taxes | F47: =+H47 -> 1.1475319e+08 | G47: =+H47-F47 -> 0 | H47: =SUM(J47:M47) -> 1.1475319e+08 | J47: =+J611 -> 0 | K47: =+K611 -> 1.1119011e+08 | L47: =+L611 -> 2595480.7 | M47: =+M611 -> 967600.54
A48: =+A47+1 -> 32 | B48: Income Tax | F48: =+H48 -> -9476009.7 | G48: =+H48-F48 -> 0 | H48: =SUM(J48:M48) -> -9476009.7 | J48: =+((J52+SUM(J626:J633))*J638)+SUM(J643:J645) -> 0 | K48: =+((K52+SUM(K626:K634))*K638)+SUM(K643:K646) -> -12574045 | L48: =+((L52+SUM(L626:L634))*L638)+SUM(L643:L645) -> 2829548 | M48: =+((M52+SUM(M626:M634))*M638)+SUM(M643:M645) -> 268487.29 | O48: =+((O52+SUM(O626:O633))*O638)+SUM(O643:O645) -> 0 | P48: =+((P52+SUM(P626:P633))*P638)+SUM(P643:P645) -> 0
A49: =+A48+1 -> 33 | B49: Other Expenses | F49: =+H49 -> 0 | G49: =+H49-F49 -> 0 | H49: =SUM(J49:M49) -> 0 | J49: =+J654 -> 0 | K49: =+K654 -> 0 | L49: =+L654 -> 0 | M49: =+M654 -> 0
A50: =+A49+1 -> 34 | B50: Total Operating Expense | F50: =SUM(F45:F49) -> 5.2934062e+08 | G50: =SUM(G45:G49) -> 0 | H50: =SUM(J50:M50) -> 5.2934062e+08 | J50: =SUM(J45:J49) -> 0 | K50: =SUM(K45:K49) -> 4.6731733e+08 | L50: =SUM(L45:L49) -> 44041215 | M50: =SUM(M45:M49) -> 17982080
A51: =+A50+1 -> 35
A52: =+A51+1 -> 36 | B52: Return | F52: =+F43-F50 -> 79242000 | G52: =+G43-G50 -> 0 | H52: =SUM(J52:M52) -> 79242000 | J52: =+J43-J50 -> 0 | K52: =+K43-K50 -> 64230211 | L52: =+L43-L50 -> 13720762 | M52: =+M43-M50 -> 1291026.4
A53: =+A52+1 -> 37 | B53: Rate of Return on Ratebase | F53: 0.05342798 | G53: =+F53-H53 -> 0.034776013 | H53: =+H52/H36 -> 0.018651967 | K53: =+K52/K36 -> 0.015597946 | L53: =+L52/L36 -> 0.11703724 | M53: =+M52/M36 -> 0.09666862
B55: Summary of Results @ Proposed Rate of Return
A57: 1 | B57: Ratebase | F57: =+H57 -> 4.2484528e+09 | G57: =+H57-F57 -> 0 | H57: =SUM(J57:M57) -> 4.2484528e+09 | J57: =+J36 -> 0 | K57: =+K36 -> 4.1178634e+09 | L57: =+L36 -> 1.1723416e+08 | M57: =+M36 -> 13355176
A58: =+A57+1 -> 2 | B58: Proposed Rate of Return | F58: =+H58 -> 0.071755 | H58: =+$N$58 -> 0.071755 | J58: =+$N$58 -> 0.071755 | K58: =+$N$58 -> 0.071755 | L58: =+$N$58 -> 0.071755 | M58: =+$N$58 -> 0.071755 | N58: 0.071755 | O58: II-C-1
A59: =+A58+1 -> 3 | B59: Return @ Proposed | F59: =+H59 -> 3.0484773e+08 | G59: =+H59-F59 -> 0 | H59: =SUM(J59:M59) -> 3.0484773e+08 | J59: =+J57*J58 -> 0 | K59: =+K57*K58 -> 2.9547729e+08 | L59: =+L57*L58 -> 8412137 | M59: =+M57*M58 -> 958300.62
A60: =+A59+1 -> 4
A61: =+A60+1 -> 5 | B61: Operation & Maintenance Expense | F61: =+H61 -> 2.0133135e+08 | G61: =+H61-F61 -> 0 | H61: =SUM(J61:M61) -> 2.0133135e+08 | J61: =+J429-J70 -> 0 | K61: =+K429-K70 -> 1.6039674e+08 | L61: =+L429-L70 -> 24275503 | M61: =+M429-M70 -> 16659108
A62: =+A61+1 -> 6 | B62: Depreciation and Amortization | F62: =+H62 -> 2.227321e+08 | G62: =+H62-F62 -> 0 | H62: =SUM(J62:M62) -> 2.227321e+08 | J62: =+J597-J71 -> 0 | K62: =+K597-K71 -> 2.0830453e+08 | L62: =+L597-L71 -> 14340683 | M62: =+M597-M71 -> 86884.013
A63: =+A62+1 -> 7 | B63: Taxes Other than Income Taxes | F63: =+H63 -> 62990895 | G63: =+H63-F63 -> 0 | H63: =SUM(J63:M63) -> 62990895 | J63: =+J611-J68 -> 0 | K63: =+K611-K68 -> 59427814 | L63: =+L611-L68 -> 2595480.7 | M63: =+M611-M68 -> 967600.54
A64: =+A63+1 -> 8 | B64: Income Taxes | F64: =+H64 -> 50495133 | G64: =+H64-F64 -> 0 | H64: =SUM(J64:M64) -> 50495133 | J64: =J647 -> 0 | K64: =K647 -> 48896698 | L64: =L647 -> 1418394.5 | M64: =M647 -> 180041.19
A65: =+A64+1 -> 9 | B65: Other Expenses | F65: =+H65 -> 0 | G65: =+H65-F65 -> 0 | H65: =SUM(J65:M65) -> 0 | J65: =+J654 -> 0 | K65: =+K654 -> 0 | L65: =+L654 -> 0 | M65: =+M654 -> 0
A66: =+A65+1 -> 10 | B66: Total Operating Expenses | F66: =SUM(F61:F65) -> 5.3754947e+08 | G66: =SUM(G61:G65) -> 0 | H66: =SUM(J66:M66) -> 5.3754947e+08 | J66: =SUM(J61:J65) -> 0 | K66: =SUM(K61:K65) -> 4.7702578e+08 | L66: =SUM(L61:L65) -> 42630062 | M66: =SUM(M61:M65) -> 17893634
A67: =+A66+1 -> 11
A68: =+A67+1 -> 12 | B68: Municipal Franchise Fees | F68: =+H68 -> 51762293 | G68: =+H68-F68 -> 0 | H68: =SUM(J68:M68) -> 51762293 | J68: =+J607 -> 0 | K68: =+K607 -> 51762293 | L68: =+L607 -> 0 | M68: =+M607 -> 0
A69: =+A68+1 -> 13 | B69: Nuclear Decommissioning | F69: =+H69 -> 0 | G69: =+H69-F69 -> 0 | H69: =SUM(J69:M69) -> 0 | J69: =+J652 -> 0 | K69: 0 | L69: =+L652 -> 0 | M69: =+M652 -> 0
A70: =+A69+1 -> 14 | B70: DSM | F70: =+H70 -> 0 | G70: =+H70-F70 -> 0 | H70: =SUM(J70:M70) -> 0 | J70: =J393 -> 0 | K70: 0 | L70: =L393 -> 0 | M70: 0
A71: =+A70+1 -> 15 | B71: Excess Mitigation Credit | F71: =+H71 -> 0 | G71: =+H71-F71 -> 0 | H71: =SUM(J71:M71) -> 0 | J71: 0 | K71: 0 | L71: =L590 -> 0 | M71: =M590 -> 0
A72: =+A71+1 -> 16
A73: =+A72+1 -> 17
A74: =+A73+1 -> 18 | B74: Total Cost of Service | F74: =SUM(F66:F71)+F59 -> 8.9415949e+08 | G74: =+H74-F74 -> 0 | H74: =SUM(J74:M74) -> 8.9415949e+08 | I74: =+I59+I66+I69+I70+I71+I68+I72 -> 0 | J74: =+J59+J66+J70+J71+J68-J72+J69 -> 0 | K74: =+K59+K66+K70+K71+K68-K72+K69 -> 8.2426536e+08 | L74: =+L59+L66+L70+L71+L68-L72+L69 -> 51042199 | M74: =+M59+M66+M70+M71+M68-M72+M69 -> 18851935
A75: =+A74+1 -> 19 | B75: Adjusted Revenue Requirement | F75: =+H75 -> 8.6731274e+08 | G75: =+H75-F75 -> 0 | H75: =SUM(J75:M75) -> 8.6731274e+08 | J75: =+J74-J78 -> 0 | K75: =+K74-K78 -> 7.9827524e+08 | L75: =+L74-L78 -> 50185561 | M75: =+M74-M78 -> 18851935 | N75: =SUM(K75:M75) -> 8.6731274e+08
A76: =+A75+1 -> 20
A77: =+A76+1 -> 21 | B77: Proposed Tariff Revenues | F77: =+H77 -> 8.1555045e+08 | G77: =+H77-F77 -> 0 | H77: =SUM(J77:M77) -> 8.1555045e+08 | J77: =+J74-J78-J80 -> 0 | K77: =+K74-K78-K80 -> 7.4651295e+08 | L77: =+L74-L78-L80 -> 50185561 | M77: =+M74-M78-M80 -> 18851935
A78: =+A77+1 -> 22 | B78: Proposed Miscellaneous Revenues | F78: =+H78 -> 26846753 | G78: =+H78-F78 -> 0 | H78: =SUM(J78:M78) -> 26846753 | J78: =+J664 -> 0 | K78: =+K664 -> 25990116 | L78: =+L664 -> 856637.48 | M78: =+M664 -> 0
A79: =+A78+1 -> 23 | B79: Proposed TCRF Revenues | F79: =+H79 -> 0 | G79: =+H79-F79 -> 0 | H79: =SUM(J79:M79) -> 0 | J79: 0 | K79: 0 | L79: 0 | M79: 0
A80: =+A79+1 -> 24 | B80: Proposed Rider Revenues | F80: =+H80 -> 51762293 | G80: =+H80-F80 -> 0 | H80: =SUM(J80:M80) -> 51762293 | J80: =+J69+J68+J70+J71 -> 0 | K80: =+K69+K68+K70+K71 -> 51762293 | L80: =+L69+L68+L70+L71 -> 0 | M80: =+M69+M68+M70+M71 -> 0
A81: =+A80+1 -> 25 | B81: Proposed Total Revenues | F81: =SUM(F77:F80) -> 8.9415949e+08 | G81: =SUM(G77:G80) -> 0 | H81: =SUM(J81:M81) -> 8.9415949e+08 | I81: =SUM(I77:I80) -> 0 | J81: =SUM(J77:J80) -> 0 | K81: =SUM(K77:K80) -> 8.2426536e+08 | L81: =SUM(L77:L80) -> 51042199 | M81: =SUM(M77:M80) -> 18851935
A82: =+A81+1 -> 26
A83: =+A82+1 -> 27 | B83: Increase / Decrease in Tariff Revenues | F83: =+H83 -> 2.3381458e+08 | G83: =+H83-F83 -> 0 | H83: =SUM(J83:M83) -> 2.3381458e+08 | J83: =+J77-J39 -> 0 | K83: =+K77-K39 -> 2.4095553e+08 | L83: =+L77-L39 -> -6719778.3 | M83: =+M77-M39 -> -421171.87
A84: =+A83+1 -> 28 | B84: Increase / Decrease in Miscellaneous Revenues | F84: =+H84 -> 0 | G84: =+H84-F84 -> 0 | H84: =SUM(J84:M84) -> 0 | J84: =+J78-J40 -> 0 | K84: =+K78-K40 -> 0 | L84: =+L78-L40 -> 0 | M84: =+M78-M40 -> 0
A85: =+A84+1 -> 29 | B85: Increase / Decrease in TCRF Revenues | F85: =+H85 -> 0 | G85: =+H85-F85 -> 0 | H85: =SUM(J85:M85) -> 0 | J85: =+J79-J41 -> 0 | K85: =+K79-K41 -> 0 | L85: =+L79-L41 -> 0 | M85: =+M79-M41 -> 0
A86: =+A85+1 -> 30 | B86: Increase / Decrease in Rider Revenues | F86: =+H86 -> 51762293 | G86: =+H86-F86 -> 0 | H86: =SUM(J86:M86) -> 51762293 | J86: =+J80-J42 -> 0 | K86: =+K80-K42 -> 51762293 | L86: =+L80-L42 -> 0 | M86: =+M80-M42 -> 0
A87: =+A86+1 -> 31 | B87: Increase / Decrease in Total Revenues | F87: =SUM(F83:F86) -> 2.8557687e+08 | G87: =SUM(G83:G86) -> 0 | H87: =SUM(J87:M87) -> 2.8557687e+08 | J87: =SUM(J83:J86) -> 0 | K87: =SUM(K83:K86) -> 2.9271782e+08 | L87: =SUM(L83:L86) -> -6719778.3 | M87: =SUM(M83:M86) -> -421171.87
B90: Schedule II-B-1 Original Cost of Utility Plant
A92: 1 | B92: Intangible Plant
A93: =+A92+1 -> 2 | B93: A301 | C93: Organization | D93: Direct Assign | E93: WP/II-I-1.1/B-1 | F93: =+H93 -> 18123.34 | G93: =+H93-F93 -> 0 | H93: =SUM(J93:M93) -> 18123.34 | K93: =+'[1]II-B-1 Plant'!N15 -> 17344.858 | L93: =+'[1]II-B-1 Plant'!O15 -> 566.25384 | M93: =+'[1]II-B-1 Plant'!P15 -> 212.22859
A94: =+A93+1 -> 3 | B94: A302 | C94: Franchise & Consents | D94: Direct Assign | E94: WP/II-I-1.1/B-1 | F94: =+H94 -> 0 | G94: =+H94-F94 -> 0 | H94: =SUM(J94:M94) -> 0 | K94: =+'[1]II-B-1 Plant'!N16 -> 0 | L94: =+'[1]II-B-1 Plant'!O16 -> 0 | M94: =+'[1]II-B-1 Plant'!P16 -> 0
A95: =+A94+1 -> 4 | B95: A303 | C95: Miscellaneous Intangible Plant | D95: Direct Assign | E95: WP/II-I-1.1/B-1 | F95: =+H95 -> 1.5604949e+08 | G95: =+H95-F95 -> 0 | H95: =SUM(J95:M95) -> 1.5604949e+08 | K95: =+'[1]II-B-1 Plant'!N17 -> 1.5235169e+08 | L95: =+'[1]II-B-1 Plant'!O17 -> 3697795.4 | M95: =+'[1]II-B-1 Plant'!P17 -> 0
A96: =+A95+1 -> 5 | C96: Total Intangible Plant | F96: =SUM(F93:F95) -> 1.5606761e+08 | G96: =SUM(G93:G95) -> 0 | H96: =SUM(H93:H95) -> 1.5606761e+08 | J96: =SUM(J93:J95) -> 0 | K96: =SUM(K93:K95) -> 1.5236904e+08 | L96: =SUM(L93:L95) -> 3698361.7 | M96: =SUM(M93:M95) -> 212.22859
A97: =+A96+1 -> 6
A98: =+A97+1 -> 7 | B98: Schedule II-B-1 Original Cost of Utility Plant (Continued)
A99: =+A98+1 -> 8
A100: =+A99+1 -> 9 | B100: Transmission Plant
A101: =+A100+1 -> 10 | B101: A350 | C101: Land and Land Rights | D101: Direct Assign | E101: WP/II-I-1.1/B-1 | F101: =+H101 -> 0 | G101: =+H101-F101 -> 0 | H101: =SUM(J101:M101) -> 0 | K101: 0 | L101: 0 | M101: 0
A102: =+A101+1 -> 11 | B102: A352 | C102: Structures and Improvements | D102: Direct Assign | E102: WP/II-I-1.1/B-1 | F102: =+H102 -> 0 | G102: =+H102-F102 -> 0 | H102: =SUM(J102:M102) -> 0 | K102: 0 | L102: 0 | M102: 0
A103: =+A102+1 -> 12 | B103: A353 | C103: Station Equipment | D103: Direct Assign | E103: WP/II-I-1.1/B-1 | F103: =+H103 -> 0 | G103: =+H103-F103 -> 0 | H103: =SUM(J103:M103) -> 0 | K103: 0 | L103: 0 | M103: 0
A104: =+A103+1 -> 13 | B104: A354 | C104: Towers and Fixtures | D104: Direct Assign | E104: WP/II-I-1.1/B-1 | F104: =+H104 -> 0 | G104: =+H104-F104 -> 0 | H104: =SUM(J104:M104) -> 0 | K104: 0 | L104: 0 | M104: 0
A105: =+A104+1 -> 14 | B105: A355 | C105: Poles and Fixtures | D105: Direct Assign | E105: WP/II-I-1.1/B-1 | F105: =+H105 -> 0 | G105: =+H105-F105 -> 0 | H105: =SUM(J105:M105) -> 0 | K105: 0 | L105: 0 | M105: 0
A106: =+A105+1 -> 15 | B106: A356 | C106: O.H. Conductors & Devices | D106: Direct Assign | E106: WP/II-I-1.1/B-1 | F106: =+H106 -> 0 | G106: =+H106-F106 -> 0 | H106: =SUM(J106:M106) -> 0 | K106: 0 | L106: 0 | M106: 0
A107: =+A106+1 -> 16 | B107: A357 | C107: Undergound Conduit | D107: Direct Assign | E107: WP/II-I-1.1/B-1 | F107: =+H107 -> 0 | G107: =+H107-F107 -> 0 | H107: =SUM(J107:M107) -> 0 | K107: 0 | L107: 0 | M107: 0
A108: =+A107+1 -> 17 | B108: A358 | C108: Underground Conductors | D108: Direct Assign | E108: WP/II-I-1.1/B-1 | F108: =+H108 -> 0 | G108: =+H108-F108 -> 0 | H108: =SUM(J108:M108) -> 0 | K108: 0 | L108: 0 | M108: 0
A109: =+A108+1 -> 18 | B109: A359 | C109: Roads and Trails | D109: Direct Assign | E109: WP/II-I-1.1/B-1 | F109: =+H109 -> 0 | G109: =+H109-F109 -> 0 | H109: =SUM(J109:M109) -> 0 | K109: 0 | L109: 0 | M109: 0
A110: =+A109+1 -> 19
...

Sheet Juris Alloc Split
D1: 1 | E1: 2 | F1: 7 | G1: 13 | H1: 4
B3: ='II-I TOTAL COMPANY'!B4 -> PUBLIC UTILITY COMMISION OF TEXAS
B4: ='II-I TOTAL COMPANY'!B5 -> AEP TEXAS INC
B5: ='II-I TOTAL COMPANY'!B6 -> II-I COST OF SERVICE
B6: ='II-I TOTAL COMPANY'!B7 -> TEST YEAR ENDING 09/30/2023
B7: DOCKET 56165 | E7: Jurisdictional Split
A10: Line | B10: Account | C10: Description | E10: Reference | F10: Total | G10: Oth Jurisdiction | H10: Texas Retail | I10: Retail | J10: Distribution | K10: Dist Other | L10: Distr Retail | M10: Dist Retail | N10: Check
A11: No. | B11: No. | D11: ALLOC | E11: Schedule | F11: AEP TX | I11: Jurisdiction | J11: Total | K11: Jurisdiction | L11: Jurisdiction | M11: Allocation | N11: Column
A12: -1 | B12: =+A12-1 -> -2 | C12: =+B12-1 -> -3 | D12: =+C12-1 -> -4 | E12: =+D12-1 -> -5 | F12: =+E12-1 -> -6 | G12: =+F12-1 -> -7 | H12: =+G12-1 -> -8
B13: Schedule I-A Cost of Service by Function
B15: Schedule II-B-1 Original Cost of Utility Plant
A17: 1 | B17: Intangible Plant
A18: =+A17+1 -> 2 | B18: A301 | C18: Organization | F18: =+'II-I TOTAL COMPANY'!H93 -> 18123.34 | G18: =+Distribution!I93+Meter!I93+TDCustSvc!I93 -> 0 | H18: =+Distribution!J93+Meter!J93+TDCustSvc!J93 -> 18123.34 | I18: =IFERROR(+H18/F18,0) -> 1 | J18: =+Distribution!H93+Meter!H93+TDCustSvc!H93 -> 18123.34 | K18: =+Distribution!I93+Meter!I93+TDCustSvc!I93 -> 0 | L18: =+Distribution!J93+Meter!J93+TDCustSvc!J93 -> 18123.34 | M18: =IFERROR(+L18/J18,0) -> 1
A19: =+A18+1 -> 3 | B19: A303 | C19: Miscellaneous Intangible Plant | F19: =+'II-I TOTAL COMPANY'!H94 -> 0 | G19: =+Distribution!I94+Meter!I94+TDCustSvc!I94 -> 0 | H19: =Distribution!J94+Meter!J94+TDCustSvc!J94 -> 0 | I19: =IFERROR(+H19/F19,0) -> 0 | J19: =+Distribution!H94+Meter!H94+TDCustSvc!H94 -> 0 | K19: =+Distribution!I94+Meter!I94+TDCustSvc!I94 -> 0 | L19: =+Distribution!J94+Meter!J94+TDCustSvc!J94 -> 0 | M19: =IFERROR(+L19/J19,0) -> 0 | N19: =IF(SUM(G19+H19)=F19,"OK",0) -> OK
A20: =+A19+1 -> 4 | B20: A303 | C20: Miscellaneous Intangible Plant | F20: =+'II-I TOTAL COMPANY'!H95 -> 1.5604949e+08 | G20: =+Distribution!I95+Meter!I95+TDCustSvc!I95 -> 0 | H20: =+Distribution!J95+Meter!J95+TDCustSvc!J95 -> 1.5604949e+08 | I20: =IFERROR(+H20/F20,0) -> 1 | J20: =+Distribution!H95+Meter!H95+TDCustSvc!H95 -> 1.5604949e+08 | K20: =+Distribution!I95+Meter!I95+TDCustSvc!I95 -> 0 | L20: =+Distribution!J95+Meter!J95+TDCustSvc!J95 -> 1.5604949e+08 | M20: =IFERROR(+L20/J20,0) -> 1 | N20: =IF(SUM(G20+H20)=F20,"OK",0) -> OK
A21: =+A20+1 -> 5 | C21: Total Intangible Plant | F21: =+'II-I TOTAL COMPANY'!H96 -> 1.5606761e+08 | G21: =+Distribution!I96+Meter!I96+TDCustSvc!I96 -> 0 | H21: =+Distribution!J96+Meter!J96+TDCustSvc!J96 -> 1.5606761e+08 | I21: =+H21/F21 -> 1 | J21: =+Distribution!H96+Meter!H96+TDCustSvc!H96 -> 1.5606761e+08 | K21: =+Distribution!I96+Meter!I96+TDCustSvc!I96 -> 0 | L21: =+Distribution!J96+Meter!J96+TDCustSvc!J96 -> 1.5606761e+08 | M21: =+L21/J21 -> 1 | N21: =IF(SUM(G21+H21)=F21,"OK",0) -> OK
A22: =+A21+1 -> 6 | N22: =IF(SUM(G22+H22)=F22,"OK",0) -> OK
A23: =+A22+1 -> 7 | B23: Schedule II-B-1 Original Cost of Utility Plant (Continued) | N23: =IF(SUM(G23+H23)=F23,"OK",0) -> OK
A24: =+A23+1 -> 8 | N24: =IF(SUM(G24+H24)=F24,"OK",0) -> OK
A25: =+A24+1 -> 9 | B25: Transmission Plant | N25: =IF(SUM(G25+H25)=F25,"OK",0) -> OK
A26: =+A25+1 -> 10 | B26: A350 | C26: Land and Land Rights | F26: =+'II-I TOTAL COMPANY'!H101 -> 0 | G26: =+Distribution!I101+Meter!I101+TDCustSvc!I101 -> 0 | H26: =+Distribution!J101+Meter!J101+TDCustSvc!J101 -> 0 | I26: =IFERROR(+H26/F26,) -> 0 | J26: =+Distribution!H101+Meter!H101+TDCustSvc!H101 -> 0 | K26: =+Distribution!I101+Meter!I101+TDCustSvc!I101 -> 0 | L26: =+Distribution!J101+Meter!J101+TDCustSvc!J101 -> 0 | M26: =IFERROR(+L26/J26,0) -> 0 | N26: =IF(SUM(G26+H26)=F26,"OK",0) -> OK
A27: =+A26+1 -> 11 | B27: A352 | C27: Structures and Improvements | F27: =+'II-I TOTAL COMPANY'!H102 -> 0 | G27: =+Distribution!I102+Meter!I102+TDCustSvc!I102 -> 0 | H27: =+Distribution!J102+Meter!J102+TDCustSvc!J102 -> 0 | I27: =IFERROR(+H27/F27,) -> 0 | J27: =+Distribution!H102+Meter!H102+TDCustSvc!H102 -> 0 | K27: =+Distribution!I102+Meter!I102+TDCustSvc!I102 -> 0 | L27: =+Distribution!J102+Meter!J102+TDCustSvc!J102 -> 0 | M27: =IFERROR(+L27/J27,0) -> 0 | N27: =IF(SUM(G27+H27)=F27,"OK",0) -> OK
A28: =+A27+1 -> 12 | B28: A353 | C28: Station Equipment | F28: =+'II-I TOTAL COMPANY'!H103 -> 0 | G28: =+Distribution!I103+Meter!I103+TDCustSvc!I103 -> 0 | H28: =+Distribution!J103+Meter!J103+TDCustSvc!J103 -> 0 | I28: =IFERROR(+H28/F28,) -> 0 | J28: =+Distribution!H103+Meter!H103+TDCustSvc!H103 -> 0 | K28: =+Distribution!I103+Meter!I103+TDCustSvc!I103 -> 0 | L28: =+Distribution!J103+Meter!J103+TDCustSvc!J103 -> 0 | M28: =IFERROR(+L28/J28,0) -> 0 | N28: =IF(SUM(G28+H28)=F28,"OK",0) -> OK
A29: =+A28+1 -> 13 | B29: A354 | C29: Towers and Fixtures | F29: =+'II-I TOTAL COMPANY'!H104 -> 0 | G29: =+Distribution!I104+Meter!I104+TDCustSvc!I104 -> 0 | H29: =+Distribution!J104+Meter!J104+TDCustSvc!J104 -> 0 | I29: =IFERROR(+H29/F29,) -> 0 | J29: =+Distribution!H104+Meter!H104+TDCustSvc!H104 -> 0 | K29: =+Distribution!I104+Meter!I104+TDCustSvc!I104 -> 0 | L29: =+Distribution!J104+Meter!J104+TDCustSvc!J104 -> 0 | M29: =IFERROR(+L29/J29,0) -> 0 | N29: =IF(SUM(G29+H29)=F29,"OK",0) -> OK
A30: =+A29+1 -> 14 | B30: A355 | C30: Poles and Fixtures | F30: =+'II-I TOTAL COMPANY'!H105 -> 0 | G30: =+Distribution!I105+Meter!I105+TDCustSvc!I105 -> 0 | H30: =+Distribution!J105+Meter!J105+TDCustSvc!J105 -> 0 | I30: =IFERROR(+H30/F30,) -> 0 | J30: =+Distribution!H105+Meter!H105+TDCustSvc!H105 -> 0 | K30: =+Distribution!I105+Meter!I105+TDCustSvc!I105 -> 0 | L30: =+Distribution!J105+Meter!J105+TDCustSvc!J105 -> 0 | M30: =IFERROR(+L30/J30,0) -> 0 | N30: =IF(SUM(G30+H30)=F30,"OK",0) -> OK
A31: =+A30+1 -> 15 | B31: A356 | C31: O.H. Conductors & Devices | F31: =+'II-I TOTAL COMPANY'!H106 -> 0 | G31: =+Distribution!I106+Meter!I106+TDCustSvc!I106 -> 0 | H31: =+Distribution!J106+Meter!J106+TDCustSvc!J106 -> 0 | I31: =IFERROR(+H31/F31,) -> 0 | J31: =+Distribution!H106+Meter!H106+TDCustSvc!H106 -> 0 | K31: =+Distribution!I106+Meter!I106+TDCustSvc!I106 -> 0 | L31: =+Distribution!J106+Meter!J106+TDCustSvc!J106 -> 0 | M31: =IFERROR(+L31/J31,0) -> 0 | N31: =IF(SUM(G31+H31)=F31,"OK",0) -> OK
A32: =+A31+1 -> 16 | B32: A357 | C32: Undergound Conduit | F32: =+'II-I TOTAL COMPANY'!H107 -> 0 | G32: =+Distribution!I107+Meter!I107+TDCustSvc!I107 -> 0 | H32: =+Distribution!J107+Meter!J107+TDCustSvc!J107 -> 0 | I32: =IFERROR(+H32/F32,) -> 0 | J32: =+Distribution!H107+Meter!H107+TDCustSvc!H107 -> 0 | K32: =+Distribution!I107+Meter!I107+TDCustSvc!I107 -> 0 | L32: =+Distribution!J107+Meter!J107+TDCustSvc!J107 -> 0 | M32: =IFERROR(+L32/J32,0) -> 0 | N32: =IF(SUM(G32+H32)=F32,"OK",0) -> OK
A33: =+A32+1 -> 17 | B33: A358 | C33: Underground Conductors | F33: =+'II-I TOTAL COMPANY'!H108 -> 0 | G33: =+Distribution!I108+Meter!I108+TDCustSvc!I108 -> 0 | H33: =+Distribution!J108+Meter!J108+TDCustSvc!J108 -> 0 | I33: =IFERROR(+H33/F33,) -> 0 | J33: =+Distribution!H108+Meter!H108+TDCustSvc!H108 -> 0 | K33: =+Distribution!I108+Meter!I108+TDCustSvc!I108 -> 0 | L33: =+Distribution!J108+Meter!J108+TDCustSvc!J108 -> 0 | M33: =IFERROR(+L33/J33,0) -> 0 | N33: =IF(SUM(G33+H33)=F33,"OK",0) -> OK
A34: =+A33+1 -> 18 | B34: A359 | C34: Roads and Trails | F34: =+'II-I TOTAL COMPANY'!H109 -> 0 | G34: =+Distribution!I109+Meter!I109+TDCustSvc!I109 -> 0 | H34: =+Distribution!J109+Meter!J109+TDCustSvc!J109 -> 0 | I34: =IFERROR(+H34/F34,) -> 0 | J34: =+Distribution!H109+Meter!H109+TDCustSvc!H109 -> 0 | K34: =+Distribution!I109+Meter!I109+TDCustSvc!I109 -> 0 | L34: =+Distribution!J109+Meter!J109+TDCustSvc!J109 -> 0 | M34: =IFERROR(+L34/J34,0) -> 0 | N34: =IF(SUM(G34+H34)=F34,"OK",0) -> OK
A35: =+A34+1 -> 19 | N35: =IF(SUM(G35+H35)=F35,"OK",0) -> OK
A36: =+A35+1 -> 20 | C36: Total Transmission Plant | F36: =+'II-I TOTAL COMPANY'!H111 -> 0 | G36: =+Distribution!I111+Meter!I111+TDCustSvc!I111 -> 0 | H36: =+Distribution!J111+Meter!J111+TDCustSvc!J111 -> 0 | I36: =IFERROR(+H36/F36,) -> 0 | J36: =+Distribution!H111+Meter!H111+TDCustSvc!H111 -> 0 | K36: =+Distribution!I111+Meter!I111+TDCustSvc!I111 -> 0 | L36: =+Distribution!J111+Meter!J111+TDCustSvc!J111 -> 0 | M36: =IFERROR(+L36/J36,0) -> 0 | N36: =IF(SUM(G36+H36)=F36,"OK",0) -> OK
A37: =+A36+1 -> 21 | N37: =IF(SUM(G37+H37)=F37,"OK",0) -> OK
A38: =+A37+1 -> 22 | B38: Distribution Plant | N38: =IF(SUM(G38+H38)=F38,"OK",0) -> OK
A39: =+A38+1 -> 23 | B39: A360 | C39: Land and Land Rights | F39: =+'II-I TOTAL COMPANY'!H114 -> 42018495 | G39: =+Distribution!I114+Meter!I114+TDCustSvc!I114 -> 0 | H39: =+Distribution!J114+Meter!J114+TDCustSvc!J114 -> 42018495 | I39: =+H39/F39 -> 1 | J39: =+Distribution!H114+Meter!H114+TDCustSvc!H114 -> 42018495 | K39: =+Distribution!I114+Meter!I114+TDCustSvc!I114 -> 0 | L39: =+Distribution!J114+Meter!J114+TDCustSvc!J114 -> 42018495 | M39: =+L39/J39 -> 1 | N39: =IF(SUM(G39+H39)=F39,"OK",0) -> OK
A40: =+A39+1 -> 24 | B40: A361 | C40: Structures and Improvements | F40: =+'II-I TOTAL COMPANY'!H115 -> 88124441 | G40: =+Distribution!I115+Meter!I115+TDCustSvc!I115 -> 0 | H40: =+Distribution!J115+Meter!J115+TDCustSvc!J115 -> 88124441 | I40: =+H40/F40 -> 1 | J40: =+Distribution!H115+Meter!H115+TDCustSvc!H115 -> 88124441 | K40: =+Distribution!I115+Meter!I115+TDCustSvc!I115 -> 0 | L40: =+Distribution!J115+Meter!J115+TDCustSvc!J115 -> 88124441 | M40: =+L40/J40 -> 1 | N40: =IF(SUM(G40+H40)=F40,"OK",0) -> OK
A41: =+A40+1 -> 25 | B41: A362 | C41: Station Equipment | F41: =+'II-I TOTAL COMPANY'!H116 -> 9.3770968e+08 | G41: =+Distribution!I116+Meter!I116+TDCustSvc!I116 -> 0 | H41: =+Distribution!J116+Meter!J116+TDCustSvc!J116 -> 9.3770968e+08 | I41: =+H41/F41 -> 1 | J41: =+Distribution!H116+Meter!H116+TDCustSvc!H116 -> 9.3770968e+08 | K41: =+Distribution!I116+Meter!I116+TDCustSvc!I116 -> 0 | L41: =+Distribution!J116+Meter!J116+TDCustSvc!J116 -> 9.3770968e+08 | M41: =+L41/J41 -> 1 | N41: =IF(SUM(G41+H41)=F41,"OK",0) -> OK
A42: =+A41+1 -> 26 | B42: A363 | C42: Storage Battery Equipment | F42: =+'II-I TOTAL COMPANY'!H117 -> 0 | G42: =+Distribution!I117+Meter!I117+TDCustSvc!I117 -> 0 | H42: =+Distribution!J117+Meter!J117+TDCustSvc!J117 -> 0 | J42: =+Distribution!H117+Meter!H117+TDCustSvc!H117 -> 0 | K42: =+Distribution!I117+Meter!I117+TDCustSvc!I117 -> 0 | L42: =+Distribution!J117+Meter!J117+TDCustSvc!J117 -> 0 | N42: =IF(SUM(G42+H42)=F42,"OK",0) -> OK
A43: =+A42+1 -> 27 | B43: A364 | C43: Poles,Towers & Fixtures | N43: =IF(SUM(G43+H43)=F43,"OK",0) -> OK
A44: =+A43+1 -> 28 | C44: Primary | F44: =+'II-I TOTAL COMPANY'!H119 -> 8.5392307e+08 | G44: =+Distribution!I119+Meter!I119+TDCustSvc!I119 -> 0 | H44: =+Distribution!J119+Meter!J119+TDCustSvc!J119 -> 8.5392307e+08 | I44: =+H44/F44 -> 1 | J44: =+Distribution!H119+Meter!H119+TDCustSvc!H119 -> 8.5392307e+08 | K44: =+Distribution!I119+Meter!I119+TDCustSvc!I119 -> 0 | L44: =+Distribution!J119+Meter!J119+TDCustSvc!J119 -> 8.5392307e+08 | M44: =+L44/J44 -> 1 | N44: =IF(SUM(G44+H44)=F44,"OK",0) -> OK
A45: =+A44+1 -> 29 | C45: Secondary | F45: =+'II-I TOTAL COMPANY'!H120 -> 3.6231831e+08 | G45: =+Distribution!I120+Meter!I120+TDCustSvc!I120 -> 0 | H45: =+Distribution!J120+Meter!J120+TDCustSvc!J120 -> 3.6231831e+08 | I45: =+H45/F45 -> 1 | J45: =+Distribution!H120+Meter!H120+TDCustSvc!H120 -> 3.6231831e+08 | K45: =+Distribution!I120+Meter!I120+TDCustSvc!I120 -> 0 | L45: =+Distribution!J120+Meter!J120+TDCustSvc!J120 -> 3.6231831e+08 | M45: =+L45/J45 -> 1 | N45: =IF(SUM(G45+H45)=F45,"OK",0) -> OK
A46: =+A45+1 -> 30 | C46: Total Account 364 | F46: =+'II-I TOTAL COMPANY'!H121 -> 1.2162414e+09 | G46: =+Distribution!I121+Meter!I121+TDCustSvc!I121 -> 0 | H46: =+Distribution!J121+Meter!J121+TDCustSvc!J121 -> 1.2162414e+09 | I46: =+H46/F46 -> 1 | J46: =+Distribution!H121+Meter!H121+TDCustSvc!H121 -> 1.2162414e+09 | K46: =+Distribution!I121+Meter!I121+TDCustSvc!I121 -> 0 | L46: =+Distribution!J121+Meter!J121+TDCustSvc!J121 -> 1.2162414e+09 | M46: =+L46/J46 -> 1 | N46: =IF(SUM(G46+H46)=F46,"OK",0) -> OK
A47: =+A46+1 -> 31 | B47: A365 | C47: O.H. Conductors & Devices | J47: =+Distribution!H122+Meter!H122+TDCustSvc!H122 -> 0 | K47: =+Distribution!I122+Meter!I122+TDCustSvc!I122 -> 0 | L47: =+Distribution!J122+Meter!J122+TDCustSvc!J122 -> 0 | N47: =IF(SUM(G47+H47)=F47,"OK",0) -> OK
A48: =+A47+1 -> 32 | C48: Primary | F48: =+'II-I TOTAL COMPANY'!H123 -> 9.0563004e+08 | G48: =+Distribution!I123+Meter!I123+TDCustSvc!I123 -> 0 | H48: =+Distribution!J123+Meter!J123+TDCustSvc!J123 -> 9.0563004e+08 | I48: =+H48/F48 -> 1 | J48: =+Distribution!H123+Meter!H123+TDCustSvc!H123 -> 9.0563004e+08 | K48: =+Distribution!I123+Meter!I123+TDCustSvc!I123 -> 0 | L48: =+Distribution!J123+Meter!J123+TDCustSvc!J123 -> 9.0563004e+08 | M48: =+L48/J48 -> 1 | N48: =IF(SUM(G48+H48)=F48,"OK",0) -> OK
A49: =+A48+1 -> 33 | C49: Secondary | F49: =+'II-I TOTAL COMPANY'!H124 -> 1.7999696e+08 | G49: =+Distribution!I124+Meter!I124+TDCustSvc!I124 -> 0 | H49: =+Distribution!J124+Meter!J124+TDCustSvc!J124 -> 1.7999696e+08 | I49: =+H49/F49 -> 1 | J49: =+Distribution!H124+Meter!H124+TDCustSvc!H124 -> 1.7999696e+08 | K49: =+Distribution!I124+Meter!I124+TDCustSvc!I124 -> 0 | L49: =+Distribution!J124+Meter!J124+TDCustSvc!J124 -> 1.7999696e+08 | M49: =+L49/J49 -> 1 | N49: =IF(SUM(G49+H49)=F49,"OK",0) -> OK
A50: =+A49+1 -> 34 | C50: Total Account 365 | F50: =+'II-I TOTAL COMPANY'!H125 -> 1.085627e+09 | G50: =+Distribution!I125+Meter!I125+TDCustSvc!I125 -> 0 | H50: =+Distribution!J125+Meter!J125+TDCustSvc!J125 -> 1.085627e+09 | I50: =+H50/F50 -> 1 | J50: =+Distribution!H125+Meter!H125+TDCustSvc!H125 -> 1.085627e+09 | K50: =+Distribution!I125+Meter!I125+TDCustSvc!I125 -> 0 | L50: =+Distribution!J125+Meter!J125+TDCustSvc!J125 -> 1.085627e+09 | M50: =+L50/J50 -> 1 | N50: =IF(SUM(G50+H50)=F50,"OK",0) -> OK
A51: =+A50+1 -> 35 | N51: =IF(SUM(G51+H51)=F51,"OK",0) -> OK
A52: =+A51+1 -> 36 | B52: A366 | C52: Underground Conduits | N52: =IF(SUM(G52+H52)=F52,"OK",0) -> OK
A53: =+A52+1 -> 37 | C53: Primary | F53: =+'II-I TOTAL COMPANY'!H128 -> 74685544 | G53: =+Distribution!I128+Meter!I128+TDCustSvc!I128 -> 0 | H53: =+Distribution!J128+Meter!J128+TDCustSvc!J128 -> 74685544 | I53: =+H53/F53 -> 1 | J53: =+Distribution!H128+Meter!H128+TDCustSvc!H128 -> 74685544 | K53: =+Distribution!I128+Meter!I128+TDCustSvc!I128 -> 0 | L53: =+Distribution!J128+Meter!J128+TDCustSvc!J128 -> 74685544 | M53: =+L53/J53 -> 1 | N53: =IF(SUM(G53+H53)=F53,"OK",0) -> OK
A54: =+A53+1 -> 38 | C54: Secondary | F54: =+'II-I TOTAL COMPANY'!H129 -> 49977357 | G54: =+Distribution!I129+Meter!I129+TDCustSvc!I129 -> 0 | H54: =+Distribution!J129+Meter!J129+TDCustSvc!J129 -> 49977357 | I54: =+H54/F54 -> 1 | J54: =+Distribution!H129+Meter!H129+TDCustSvc!H129 -> 49977357 | K54: =+Distribution!I129+Meter!I129+TDCustSvc!I129 -> 0 | L54: =+Distribution!J129+Meter!J129+TDCustSvc!J129 -> 49977357 | M54: =+L54/J54 -> 1 | N54: =IF(SUM(G54+H54)=F54,"OK",0) -> OK
A55: =+A54+1 -> 39 | C55: Total Account 366 | F55: =+'II-I TOTAL COMPANY'!H130 -> 1.246629e+08 | G55: =+Distribution!I130+Meter!I130+TDCustSvc!I130 -> 0 | H55: =+Distribution!J130+Meter!J130+TDCustSvc!J130 -> 1.246629e+08 | I55: =+H55/F55 -> 1 | J55: =+Distribution!H130+Meter!H130+TDCustSvc!H130 -> 1.246629e+08 | K55: =+Distribution!I130+Meter!I130+TDCustSvc!I130 -> 0 | L55: =+Distribution!J130+Meter!J130+TDCustSvc!J130 -> 1.246629e+08 | M55: =+L55/J55 -> 1 | N55: =IF(SUM(G55+H55)=F55,"OK",0) -> OK
A56: =+A55+1 -> 40 | N56: =IF(SUM(G56+H56)=F56,"OK",0) -> OK
A57: =+A56+1 -> 41 | B57: A367 | C57: U.G. Conductors & Devices | N57: =IF(SUM(G57+H57)=F57,"OK",0) -> OK
A58: =+A57+1 -> 42 | C58: Primary | F58: =+'II-I TOTAL COMPANY'!H133 -> 2.9973321e+08 | G58: =+Distribution!I133+Meter!I133+TDCustSvc!I133 -> 0 | H58: =+Distribution!J133+Meter!J133+TDCustSvc!J133 -> 2.9973321e+08 | I58: =+H58/F58 -> 1 | J58: =+Distribution!H133+Meter!H133+TDCustSvc!H133 -> 2.9973321e+08 | K58: =+Distribution!I133+Meter!I133+TDCustSvc!I133 -> 0 | L58: =+Distribution!J133+Meter!J133+TDCustSvc!J133 -> 2.9973321e+08 | M58: =+L58/J58 -> 1 | N58: =IF(SUM(G58+H58)=F58,"OK",0) -> OK
A59: =+A58+1 -> 43 | C59: Secondary | F59: =+'II-I TOTAL COMPANY'!H134 -> 2.005726e+08 | G59: =+Distribution!I134+Meter!I134+TDCustSvc!I134 -> 0 | H59: =+Distribution!J134+Meter!J134+TDCustSvc!J134 -> 2.005726e+08 | I59: =+H59/F59 -> 1 | J59: =+Distribution!H134+Meter!H134+TDCustSvc!H134 -> 2.005726e+08 | K59: =+Distribution!I134+Meter!I134+TDCustSvc!I134 -> 0 | L59: =+Distribution!J134+Meter!J134+TDCustSvc!J134 -> 2.005726e+08 | M59: =+L59/J59 -> 1 | N59: =IF(SUM(G59+H59)=F59,"OK",0) -> OK
A60: =+A59+1 -> 44 | C60: Total Account 367 | F60: =+'II-I TOTAL COMPANY'!H135 -> 5.0030581e+08 | G60: =+Distribution!I135+Meter!I135+TDCustSvc!I135 -> 0 | H60: =+Distribution!J135+Meter!J135+TDCustSvc!J135 -> 5.0030581e+08 | I60: =+H60/F60 -> 1 | J60: =+Distribution!H135+Meter!H135+TDCustSvc!H135 -> 5.0030581e+08 | K60: =+Distribution!I135+Meter!I135+TDCustSvc!I135 -> 0 | L60: =+Distribution!J135+Meter!J135+TDCustSvc!J135 -> 5.0030581e+08 | M60: =+L60/J60 -> 1 | N60: =IF(SUM(G60+H60)=F60,"OK",0) -> OK
A61: =+A60+1 -> 45 | B61: A368 | C61: Line Transformers | N61: =IF(SUM(G61+H61)=F61,"OK",0) -> OK
A62: =+A61+1 -> 46 | C62: Primary | F62: =+'II-I TOTAL COMPANY'!H137 -> 95170292 | G62: =+Distribution!I137+Meter!I137+TDCustSvc!I137 -> 0 | H62: =+Distribution!J137+Meter!J137+TDCustSvc!J137 -> 95170292 | I62: =+H62/F62 -> 1 | J62: =+Distribution!H137+Meter!H137+TDCustSvc!H137 -> 95170292 | K62: =+Distribution!I137+Meter!I137+TDCustSvc!I137 -> 0 | L62: =+Distribution!J137+Meter!J137+TDCustSvc!J137 -> 95170292 | M62: =+L62/J62 -> 1 | N62: =IF(SUM(G62+H62)=F62,"OK",0) -> OK
A63: =+A62+1 -> 47 | C63: Secondary | F63: =+'II-I TOTAL COMPANY'!H138 -> 8.1642254e+08 | G63: =+Distribution!I138+Meter!I138+TDCustSvc!I138 -> 0 | H63: =+Distribution!J138+Meter!J138+TDCustSvc!J138 -> 8.1642254e+08 | I63: =+H63/F63 -> 1 | J63: =+Distribution!H138+Meter!H138+TDCustSvc!H138 -> 8.1642254e+08 | K63: =+Distribution!I138+Meter!I138+TDCustSvc!I138 -> 0 | L63: =+Distribution!J138+Meter!J138+TDCustSvc!J138 -> 8.1642254e+08 | M63: =+L63/J63 -> 1 | N63: =IF(SUM(G63+H63)=F63,"OK",0) -> OK
A64: =+A63+1 -> 48 | C64: Total Account 368 | F64: =+'II-I TOTAL COMPANY'!H139 -> 9.1159283e+08 | G64: =+Distribution!I139+Meter!I139+TDCustSvc!I139 -> 0 | H64: =+Distribution!J139+Meter!J139+TDCustSvc!J139 -> 9.1159283e+08 | I64: =+H64/F64 -> 1 | J64: =+Distribution!H139+Meter!H139+TDCustSvc!H139 -> 9.1159283e+08 | K64: =+Distribution!I139+Meter!I139+TDCustSvc!I139 -> 0 | L64: =+Distribution!J139+Meter!J139+TDCustSvc!J139 -> 9.1159283e+08 | M64: =+L64/J64 -> 1 | N64: =IF(SUM(G64+H64)=F64,"OK",0) -> OK
A65: =+A64+1 -> 49 | N65: =IF(SUM(G65+H65)=F65,"OK",0) -> OK
A66: =+A65+1 -> 50 | B66: A369 | C66: Services | F66: =+'II-I TOTAL COMPANY'!H141 -> 4.1058031e+08 | G66: =+Distribution!I141+Meter!I141+TDCustSvc!I141 -> 0 | H66: =+Distribution!J141+Meter!J141+TDCustSvc!J141 -> 4.1058031e+08 | I66: =+H66/F66 -> 1 | J66: =+Distribution!H141+Meter!H141+TDCustSvc!H141 -> 4.1058031e+08 | K66: =+Distribution!I141+Meter!I141+TDCustSvc!I141 -> 0 | L66: =+Distribution!J141+Meter!J141+TDCustSvc!J141 -> 4.1058031e+08 | M66: =+L66/J66 -> 1 | N66: =IF(SUM(G66+H66)=F66,"OK",0) -> OK
A67: =+A66+1 -> 51 | B67: A370 | C67: Meters | F67: =+'II-I TOTAL COMPANY'!H142 -> 48515731 | G67: =+Distribution!I142+Meter!I142+TDCustSvc!I142 -> 0 | H67: =+Distribution!J142+Meter!J142+TDCustSvc!J142 -> 48515731 | I67: =+H67/F67 -> 1 | J67: =+Distribution!H142+Meter!H142+TDCustSvc!H142 -> 48515731 | K67: =+Distribution!I142+Meter!I142+TDCustSvc!I142 -> 0 | L67: =+Distribution!J142+Meter!J142+TDCustSvc!J142 -> 48515731 | M67: =+L67/J67 -> 1 | N67: =IF(SUM(G67+H67)=F67,"OK",0) -> OK
A68: =+A67+1 -> 52 | B68: A371 | C68: Install. on Customer Prem. | F68: =+'II-I TOTAL COMPANY'!H143 -> 74059353 | G68: =+Distribution!I143+Meter!I143+TDCustSvc!I143 -> 0 | H68: =+Distribution!J143+Meter!J143+TDCustSvc!J143 -> 74059353 | I68: =+H68/F68 -> 1 | J68: =+Distribution!H143+Meter!H143+TDCustSvc!H143 -> 74059353 | K68: =+Distribution!I143+Meter!I143+TDCustSvc!I143 -> 0 | L68: =+Distribution!J143+Meter!J143+TDCustSvc!J143 -> 74059353 | M68: =+L68/J68 -> 1 | N68: =IF(SUM(G68+H68)=F68,"OK",0) -> OK
A69: =+A68+1 -> 53 | B69: A372 | C69: Leased Prop. on Cust. Premises | F69: =+'II-I TOTAL COMPANY'!H144 -> 87033.378 | G69: =+Distribution!I144+Meter!I144+TDCustSvc!I144 -> 0 | H69: =+Distribution!J144+Meter!J144+TDCustSvc!J144 -> 87033.378 | N69: =IF(SUM(G69+H69)=F69,"OK",0) -> OK
A70: =+A69+1 -> 54 | B70: A373 | C70: Street Lights | F70: =+'II-I TOTAL COMPANY'!H145 -> 1.3992778e+08 | G70: =+Distribution!I145+Meter!I145+TDCustSvc!I145 -> 0 | H70: =+Distribution!J145+Meter!J145+TDCustSvc!J145 -> 1.3992778e+08 | I70: =+H70/F70 -> 1 | J70: =+Distribution!H145+Meter!H145+TDCustSvc!H145 -> 1.3992778e+08 | K70: =+Distribution!I145+Meter!I145+TDCustSvc!I145 -> 0 | L70: =+Distribution!J145+Meter!J145+TDCustSvc!J145 -> 1.3992778e+08 | M70: =+L70/J70 -> 1 | N70: =IF(SUM(G70+H70)=F70,"OK",0) -> OK
A71: =+A70+1 -> 55 | B71: A374 | C71: Land Owned in Fee | F71: =+'II-I TOTAL COMPANY'!H146 -> 1.6300613e+08 | G71: =+Distribution!I146+Meter!I146+TDCustSvc!I146 -> 0 | H71: =+Distribution!J146+Meter!J146+TDCustSvc!J146 -> 1.6300613e+08 | I71: =+H71/F71 -> 1 | J71: =+Distribution!H146+Meter!H146+TDCustSvc!H146 -> 1.6300613e+08 | K71: =+Distribution!I146+Meter!I146+TDCustSvc!I146 -> 0 | L71: =+Distribution!J146+Meter!J146+TDCustSvc!J146 -> 1.6300613e+08 | M71: =+L71/J71 -> 1 | N71: =IF(SUM(G71+H71)=F71,"OK",0) -> OK
A72: =+A71+1 -> 56 | C72: Total Distribution Plant | F72: =+'II-I TOTAL COMPANY'!H147 -> 5.7424589e+09 | G72: =+Distribution!I147+Meter!I147+TDCustSvc!I147 -> 0 | H72: =+Distribution!J147+Meter!J147+TDCustSvc!J147 -> 5.7424589e+09 | I72: =+H72/F72 -> 1 | J72: =+Distribution!H147+Meter!H147+TDCustSvc!H147 -> 5.7424589e+09 | K72: =+Distribution!I147+Meter!I147+TDCustSvc!I147 -> 0 | L72: =+Distribution!J147+Meter!J147+TDCustSvc!J147 -> 5.7424589e+09 | M72: =+L72/J72 -> 1 | N72: =IF(SUM(G72+H72)=F72,"OK",0) -> OK
B73: Schedule II-B-2 General Plant Functionalization | N73: =IF(SUM(G73+H73)=F73,"OK",0) -> OK
N74: =IF(SUM(G74+H74)=F74,"OK",0) -> OK
A75: 1 | B75: General Plant | N75: =IF(SUM(G75+H75)=F75,"OK",0) -> OK
A76: =+A75+1 -> 2 | B76: A389 | C76: Land and Land Rights | F76: =+'II-I TOTAL COMPANY'!H151 -> 32445048 | G76: =+Distribution!I151+Meter!I151+TDCustSvc!I151 -> 0 | H76: =+Distribution!J151+Meter!J151+TDCustSvc!J151 -> 32445048 | I76: =+H76/F76 -> 1 | J76: =+Distribution!H151+Meter!H151+TDCustSvc!H151 -> 32445048 | K76: =+Distribution!I151+Meter!I151+TDCustSvc!I151 -> 0 | L76: =+Distribution!J151+Meter!J151+TDCustSvc!J151 -> 32445048 | M76: =+L76/J76 -> 1 | N76: =IF(SUM(G76+H76)=F76,"OK",0) -> OK
A77: =+A76+1 -> 3 | B77: A390 | C77: Structures and Improvements | F77: =+'II-I TOTAL COMPANY'!H152 -> 3.238841e+08 | G77: =+Distribution!I152+Meter!I152+TDCustSvc!I152 -> 0 | H77: =+Distribution!J152+Meter!J152+TDCustSvc!J152 -> 3.238841e+08 | I77: =+H77/F77 -> 1 | J77: =+Distribution!H152+Meter!H152+TDCustSvc!H152 -> 3.238841e+08 | K77: =+Distribution!I152+Meter!I152+TDCustSvc!I152 -> 0 | L77: =+Distribution!J152+Meter!J152+TDCustSvc!J152 -> 3.238841e+08 | M77: =+L77/J77 -> 1 | N77: =IF(SUM(G77+H77)=F77,"OK",0) -> OK
A78: =+A77+1 -> 4 | B78: A391 | C78: Office Furniture & Equip. | F78: =+'II-I TOTAL COMPANY'!H153 -> 7711246.2 | G78: =+Distribution!I153+Meter!I153+TDCustSvc!I153 -> 0 | H78: =+Distribution!J153+Meter!J153+TDCustSvc!J153 -> 7711246.2 | I78: =+H78/F78 -> 1 | J78: =+Distribution!H153+Meter!H153+TDCustSvc!H153 -> 7711246.2 | K78: =+Distribution!I153+Meter!I153+TDCustSvc!I153 -> 0 | L78: =+Distribution!J153+Meter!J153+TDCustSvc!J153 -> 7711246.2 | M78: =+L78/J78 -> 1 | N78: =IF(SUM(G78+H78)=F78,"OK",0) -> OK
A79: =+A78+1 -> 5 | B79: A392 | C79: Transportation Equipment | F79: =+'II-I TOTAL COMPANY'!H154 -> 185899.15 | G79: =+Distribution!I154+Meter!I154+TDCustSvc!I154 -> 0 | H79: =+Distribution!J154+Meter!J154+TDCustSvc!J154 -> 185899.15 | I79: =+H79/F79 -> 1 | J79: =+Distribution!H154+Meter!H154+TDCustSvc!H154 -> 185899.15 | K79: =+Distribution!I154+Meter!I154+TDCustSvc!I154 -> 0 | L79: =+Distribution!J154+Meter!J154+TDCustSvc!J154 -> 185899.15 | M79: =+L79/J79 -> 1 | N79: =IF(SUM(G79+H79)=F79,"OK",0) -> OK
A80: =+A79+1 -> 6 | B80: A393 | C80: Stores Equipment | F80: =+'II-I TOTAL COMPANY'!H155 -> 2440138 | G80: =+Distribution!I155+Meter!I155+TDCustSvc!I155 -> 0 | H80: =+Distribution!J155+Meter!J155+TDCustSvc!J155 -> 2440138 | I80: =+H80/F80 -> 1 | J80: =+Distribution!H155+Meter!H155+TDCustSvc!H155 -> 2440138 | K80: =+Distribution!I155+Meter!I155+TDCustSvc!I155 -> 0 | L80: =+Distribution!J155+Meter!J155+TDCustSvc!J155 -> 2440138 | M80: =+L80/J80 -> 1 | N80: =IF(SUM(G80+H80)=F80,"OK",0) -> OK
A81: =+A80+1 -> 7 | B81: A394 | C81: Tools, Shop & Garage Equip. | F81: =+'II-I TOTAL COMPANY'!H156 -> 39443279 | G81: =+Distribution!I156+Meter!I156+TDCustSvc!I156 -> 0 | H81: =+Distribution!J156+Meter!J156+TDCustSvc!J156 -> 39443279 | I81: =+H81/F81 -> 1 | J81: =+Distribution!H156+Meter!H156+TDCustSvc!H156 -> 39443279 | K81: =+Distribution!I156+Meter!I156+TDCustSvc!I156 -> 0 | L81: =+Distribution!J156+Meter!J156+TDCustSvc!J156 -> 39443279 | M81: =+L81/J81 -> 1 | N81: =IF(SUM(G81+H81)=F81,"OK",0) -> OK
A82: =+A81+1 -> 8 | B82: A395 | C82: Laboratory Equipment | F82: =+'II-I TOTAL COMPANY'!H157 -> 365677.13 | G82: =+Distribution!I157+Meter!I157+TDCustSvc!I157 -> 0 | H82: =+Distribution!J157+Meter!J157+TDCustSvc!J157 -> 365677.13 | I82: =+H82/F82 -> 1 | J82: =+Distribution!H157+Meter!H157+TDCustSvc!H157 -> 365677.13 | K82: =+Distribution!I157+Meter!I157+TDCustSvc!I157 -> 0 | L82: =+Distribution!J157+Meter!J157+TDCustSvc!J157 -> 365677.13 | M82: =+L82/J82 -> 1 | N82: =IF(SUM(G82+H82)=F82,"OK",0) -> 0
A83: =+A82+1 -> 9 | B83: A396 | C83: Power Operated Equipment | F83: =+'II-I TOTAL COMPANY'!H158 -> 21837.099 | G83: =+Distribution!I158+Meter!I158+TDCustSvc!I158 -> 0 | H83: =+Distribution!J158+Meter!J158+TDCustSvc!J158 -> 21837.099 | I83: =+H83/F83 -> 1 | J83: =+Distribution!H158+Meter!H158+TDCustSvc!H158 -> 21837.099 | K83: =+Distribution!I158+Meter!I158+TDCustSvc!I158 -> 0 | L83: =+Distribution!J158+Meter!J158+TDCustSvc!J158 -> 21837.099 | M83: =+L83/J83 -> 1 | N83: =IF(SUM(G83+H83)=F83,"OK",0) -> OK
A84: =+A83+1 -> 10 | B84: A398 | C84: Misc. Equipment | F84: =+'II-I TOTAL COMPANY'!H159 -> 7411308.8 | G84: =+Distribution!I159+Meter!I159+TDCustSvc!I159 -> 0 | H84: =+Distribution!J159+Meter!J159+TDCustSvc!J159 -> 7411308.8 | I84: =+H84/F84 -> 1 | J84: =+Distribution!H159+Meter!H159+TDCustSvc!H159 -> 7411308.8 | K84: =+Distribution!I159+Meter!I159+TDCustSvc!I159 -> 0 | L84: =+Distribution!J159+Meter!J159+TDCustSvc!J159 -> 7411308.8 | M84: =+L84/J84 -> 1 | N84: =IF(SUM(G84+H84)=F84,"OK",0) -> OK
A85: =+A84+1 -> 11 | B85: A399 | C85: Other Tang. Property | F85: =+'II-I TOTAL COMPANY'!H160 -> 1287227.5 | G85: =+Distribution!I160+Meter!I160+TDCustSvc!I160 -> 0 | H85: =+Distribution!J160+Meter!J160+TDCustSvc!J160 -> 1287227.6 | N85: =IF(SUM(G85+H85)=F85,"OK",0) -> OK
A86: =+A85+1 -> 12 | N86: =IF(SUM(G86+H86)=F86,"OK",0) -> OK
A87: =+A86+1 -> 13 | C87: Total General Plant | F87: =+'II-I TOTAL COMPANY'!H162 -> 4.1519576e+08 | G87: =+Distribution!I162+Meter!I162+TDCustSvc!I162 -> 0 | H87: =+Distribution!J162+Meter!J162+TDCustSvc!J162 -> 4.1401785e+08 | I87: =+H87/F87 -> 0.997163 | J87: =+Distribution!H162+Meter!H162+TDCustSvc!H162 -> 4.1519576e+08 | K87: =+Distribution!I162+Meter!I162+TDCustSvc!I162 -> 0 | L87: =+Distribution!J162+Meter!J162+TDCustSvc!J162 -> 4.1401785e+08 | M87: =+L87/J87 -> 0.997163 | N87: =IF(SUM(G87+H87)=F87,"OK",0) -> 0
A88: =+A87+1 -> 14 | N88: =IF(SUM(G88+H88)=F88,"OK",0) -> OK
A89: =+A88+1 -> 15 | N89: =IF(SUM(G89+H89)=F89,"OK",0) -> OK
A90: =+A89+1 -> 16 | N90: =IF(SUM(G90+H90)=F90,"OK",0) -> OK
A91: =+A90+1 -> 17 | B91: Schedule II-B-3 Communication Equipment Functionalization | N91: =IF(SUM(G91+H91)=F91,"OK",0) -> OK
A92: =+A91+1 -> 18 | N92: =IF(SUM(G92+H92)=F92,"OK",0) -> OK
A93: =+A92+1 -> 19 | B93: A397 | C93: Communication Equipment | F93: =+'II-I TOTAL COMPANY'!H168 -> 2.5086094e+08 | G93: =+Distribution!I168+Meter!I168+TDCustSvc!I168 -> 0 | H93: =+Distribution!J168+Meter!J168+TDCustSvc!J168 -> 2.5086094e+08 | I93: =+H93/F93 -> 1 | J93: =+Distribution!H168+Meter!H168+TDCustSvc!H168 -> 2.5086094e+08 | K93: =+Distribution!I168+Meter!I168+TDCustSvc!I168 -> 0 | L93: =+Distribution!J168+Meter!J168+TDCustSvc!J168 -> 2.5086094e+08 | M93: =+L93/J93 -> 1 | N93: =IF(SUM(G93+H93)=F93,"OK",0) -> OK
A94: =+A93+1 -> 20 | N94: =IF(SUM(G94+H94)=F94,"OK",0) -> OK
A95: =+A94+1 -> 21 | N95: =IF(SUM(G95+H95)=F95,"OK",0) -> OK
A96: =+A95+1 -> 22 | B96: Total Plant In Service | F96: =+'II-I TOTAL COMPANY'!H171 -> 6.5645832e+09 | G96: =+Distribution!I171+Meter!I171+TDCustSvc!I171 -> 0 | H96: =+Distribution!J171+Meter!J171+TDCustSvc!J171 -> 6.5645832e+09 | I96: =+H96/F96 -> 1 | J96: =+Distribution!H171+Meter!H171+TDCustSvc!H171 -> 6.5645832e+09 | K96: =+Distribution!I171+Meter!I171+TDCustSvc!I171 -> 0 | L96: =+Distribution!J171+Meter!J171+TDCustSvc!J171 -> 6.5645832e+09 | M96: =+L96/J96 -> 1 | N96: =IF(SUM(G96+H96)=F96,"OK",0) -> OK
A97: =+A96+1 -> 23 | N97: =IF(SUM(G97+H97)=F97,"OK",0) -> OK
A98: =+A97+1 -> 24 | N98: =IF(SUM(G98+H98)=F98,"OK",0) -> OK
A99: =+A98+1 -> 25 | B99: Schedule II-B-4 Unbundled Construction Work In Progress | N99: =IF(SUM(G99+H99)=F99,"OK",0) -> OK
A100: =+A99+1 -> 26 | N100: =IF(SUM(G100+H100)=F100,"OK",0) -> OK
A101: =+A100+1 -> 27 | B101: Construction Work In Progress | N101: =IF(SUM(G101+H101)=F101,"OK",0) -> OK
A102: =+A101+1 -> 28 | B102: Total Construction Work In Progress | F102: =+'II-I TOTAL COMPANY'!H177 -> 0 | G102: =+Distribution!I177+Meter!I177+TDCustSvc!I177 -> 0 | H102: =+Distribution!J177+Meter!J177+TDCustSvc!J177 -> 0 | J102: =+Distribution!H177+Meter!H177+TDCustSvc!H177 -> 0 | K102: =+Distribution!I177+Meter!I177+TDCustSvc!I177 -> 0 | L102: =+Distribution!J177+Meter!J177+TDCustSvc!J177 -> 0 | N102: =IF(SUM(G102+H102)=F102,"OK",0) -> OK
A103: =+A102+1 -> 29 | N103: =IF(SUM(G103+H103)=F103,"OK",0) -> OK
A104: =+A103+1 -> 30 | N104: =IF(SUM(G104+H104)=F104,"OK",0) -> OK
A105: =+A104+1 -> 31 | N105: =IF(SUM(G105+H105)=F105,"OK",0) -> OK
...

Sheet Retail Summary Proposed
W2: =+V2+1 -> 1
B3: ='II-I TOTAL COMPANY'!B4 -> PUBLIC UTILITY COMMISION OF TEXAS
B4: ='II-I TOTAL COMPANY'!B5 -> AEP TEXAS INC
B5: ='II-I TOTAL COMPANY'!B6 -> II-I COST OF SERVICE
B6: ='II-I TOTAL COMPANY'!B7 -> TEST YEAR ENDING 09/30/2023
B7: DOCKET 56165
I8: Total | L8: Total
H9: Secondary | I9: Secondary | J9: Secondary | K9: Secondary | L9: Primary | M9: Primary | N9: Primary | O9: Primary | P9: Transmission | Q9: Lighting | R9: BESS
A10: Line | D10: Total | E10: Oth Jurisdiction | F10: Texas Retail | G10: Residential | H10: GS < = 10kw | I10: GS > 10kw | J10: GS > 10kw | K10: GS > 10kw | M10: 4CP | N10: NCP | O10: Sub | S10: Check
A11: No. | D11: AEP Texas | J11: 4CP | K11: NCP | S11: Column
A12: -1 | B12: =+A12-1 -> -2 | C12: =+B12-1 -> -3 | D12: =+C12-1 -> -4 | E12: =+D12-1 -> -5 | F12: =+E12-1 -> -6 | G12: =+F12-1 -> -7 | H12: =+G12-1 -> -8 | I12: =+H12-1 -> -9 | ... R12: =+Q12-1 -> -18
B13: Unit Cost
B15: Unit Cost @ Present Rates
A16: 1 | B16: Transmission | D16: =E16+F16 -> 0 | E16: 0 | F16: =SUM(G16:R16)-(L16+I16) -> 0 | G16: =+Distribution!K332 -> 0 | H16: =+Distribution!L332 -> 0 | I16: =+Distribution!M332 -> 0 | J16: =+Distribution!N332 -> 0 | K16: =+Distribution!O332 -> 0 | L16: =+Distribution!P332 -> 0 | M16: =+Distribution!Q332 -> 0 | N16: =+Distribution!R332 -> 0 | ... R16: =+Distribution!V332 -> 0
B17: $ / kw - NCP | D17: =D16/D$100 -> 0 | E17: =IFERROR(E16/E$100,0) -> 0 | F17: =F16/F$100 -> 0 | G17: =G16/G$100 -> 0 | H17: =H16/H$100 -> 0 | I17: =I16/I$100 -> 0 | J17: =J16/J$100 -> 0 | K17: =K16/K$100 -> 0 | L17: =L16/L$100 -> 0 | M17: =M16/M$100 -> 0 | ... Q17: =Q16/Q$100 -> 0 | R17: =IFERROR(R16/R$100,0) -> 0
B18: $ / kWh | D18: =D16/D$101 -> 0 | E18: =IFERROR(E16/E$101,0) -> 0 | F18: =F16/F$101 -> 0 | G18: =G16/G$101 -> 0 | H18: =H16/H$101 -> 0 | I18: =I16/I$101 -> 0 | J18: =J16/J$101 -> 0 | K18: =K16/K$101 -> 0 | L18: =L16/L$101 -> 0 | M18: =M16/M$101 -> 0 | ... Q18: =Q16/Q$101 -> 0 | R18: =IFERROR(R16/R$101,0) -> 0
B19: $ / Cust / Month | D19: =+(D16/D$102)/12 -> 0 | E19: =IFERROR(+(E16/E$102)/12,0) -> 0 | F19: =+(F16/F$102)/12 -> 0 | G19: =+(G16/G$102)/12 -> 0 | H19: =+(H16/H$102)/12 -> 0 | I19: =+(I16/I$102)/12 -> 0 | J19: =+(J16/J$102)/12 -> 0 | K19: =+(K16/K$102)/12 -> 0 | L19: =+(L16/L$102)/12 -> 0 | M19: =+(M16/M$102)/12 -> 0 | ... Q19: =+(Q16/Q$102)/12 -> 0 | R19: =IFERROR(+(R16/R$102)/12,0) -> 0
A21: 2 | B21: Distribution | D21: =E21+F21 -> 5.0555742e+08 | E21: =Distribution!I39 -> 0 | F21: =Distribution!J39 -> 5.0555742e+08 | G21: =Distribution!K39 -> 2.7428025e+08 | H21: =Distribution!L39 -> 14156857 | I21: =Distribution!M39 -> 1.5308902e+08 | J21: =Distribution!N39 -> 17640817 | K21: =Distribution!O39 -> 1.3544821e+08 | L21: =Distribution!P39 -> 34155357 | ... R21: =Distribution!V39 -> 1
B22: $ / kw - NCP | D22: =D21/D$100 -> 3.3564061 | E22: =IFERROR(E21/E$100,0) -> 0 | F22: =F21/F$100 -> 3.3564061 | G22: =G21/G$100 -> 3.46393 | H22: =H21/H$100 -> 4.885979 | I22: =I21/I$100 -> 4.8443026 | J22: =J21/J$100 -> 4.8360199 | K22: =K21/K$100 -> 4.8453835 | L22: =L21/L$100 -> 3.1043426 | M22: =M21/M$100 -> 3.1081296 | ... Q22: =Q21/Q$100 -> 26.665747 | R22: =IFERROR(R21/R$100,0) -> 1.8161562e-06
B23: $ / kWh | D23: =D21/D$101 -> 0.013201381 | E23: =IFERROR(E21/E$101,0) -> 0 | F23: =F21/F$101 -> 0.013201381 | G23: =G21/G$101 -> 0.021785767 | H23: =H21/H$101 -> 0.021063614 | I23: =I21/I$101 -> 0.016630969 | J23: =J21/J$101 -> 0.013470728 | K23: =K21/K$101 -> 0.017155135 | L23: =L21/L$101 -> 0.0075480258 | M23: =M21/M$101 -> 0.0067152445 | ... Q23: =Q21/Q$101 -> 0.09053626 | R23: =IFERROR(R21/R$101,0) -> 3.3779412e-08
B24: $ / Cust / Month | D24: =+(D21/D$102)/12 -> 31.685321 | E24: =IFERROR(+(E21/E$102)/12,0) -> 0 | F24: =+(F21/F$102)/12 -> 31.685321 | G24: =+(G21/G$102)/12 -> 24.439434 | H24: =+(H21/H$102)/12 -> 11.872654 | I24: =+(I21/I$102)/12 -> 176.18554 | J24: =+(J21/J$102)/12 -> 2552.2016 | K24: =+(K21/K$102)/12 -> 157.13322 | L24: =+(L21/L$102)/12 -> 2620.8838 | M24: =+(M21/M$102)/12 -> 4484.1248 | ... Q24: =+(Q21/Q$102)/12 -> 8.1238528 | R24: =IFERROR(+(R21/R$102)/12,0) -> 0.0043859649
A26: 3 | B26: Meters | D26: =E26+F26 -> 56905340 | E26: =Meter!I39 -> 0 | F26: =Meter!J39 -> 56905340 | G26: =Meter!K39 -> 38036476 | H26: =Meter!L39 -> 5099901 | I26: =Meter!M39 -> 10956923 | J26: =Meter!N39 -> 87790.73 | K26: =Meter!O39 -> 10869132 | L26: =Meter!P39 -> 1645621.7 | ... R26: =Meter!V39 -> 1
B27: $ / kw - NCP | D27: =D26/D$100 -> 0.37779572 | E27: =IFERROR(E26/E$100,0) -> 0 | F27: =F26/F$100 -> 0.37779572 | G27: =G26/G$100 -> 0.48036886 | H27: =H26/H$100 -> 1.7601371 | I27: =I26/I$100 -> 0.34671753 | J27: =J26/J$100 -> 0.024066782 | K27: =K26/K$100 -> 0.38882103 | L27: =L26/L$100 -> 0.14956873 | M27: =M26/M$100 -> 0.087830258 | ... Q27: =Q26/Q$100 -> 0 | R27: =IFERROR(R26/R$100,0) -> 1.8161562e-06
B28: $ / kWh | D28: =D26/D$101 -> 0.0014859422 | E28: =IFERROR(E26/E$101,0) -> 0 | F28: =F26/F$101 -> 0.0014859422 | G28: =G26/G$101 -> 0.0030211939 | H28: =H26/H$101 -> 0.007588008 | I28: =I26/I$101 -> 0.0011903155 | J28: =J26/J$101 -> 6.7037994e-05 | K28: =K26/K$101 -> 0.0013766253 | L28: =L26/L$101 -> 0.00036366754 | M28: =M26/M$101 -> 0.00018976096 | ... Q28: =Q26/Q$101 -> 0 | R28: =IFERROR(R26/R$101,0) -> 3.3779412e-08
B29: $ / Cust / Month | D29: =+(D26/D$102)/12 -> 3.566487 | E29: =IFERROR(+(E26/E$102)/12,0) -> 0 | F29: =+(F26/F$102)/12 -> 3.566487 | G29: =+(G26/G$102)/12 -> 3.3891976 | H29: =+(H26/H$102)/12 -> 4.2770339 | I29: =+(I26/I$102)/12 -> 12.609992 | J29: =+(J26/J$102)/12 -> 12.701205 | K29: =+(K26/K$102)/12 -> 12.60926 | L29: =+(L26/L$102)/12 -> 126.27545 | M29: =+(M26/M$102)/12 -> 126.71346 | ... Q29: =+(Q26/Q$102)/12 -> 0 | R29: =IFERROR(+(R26/R$102)/12,0) -> 0.0043859649
A31: 4 | B31: T&D Customer Service | D31: =E31+F31 -> 19273108 | E31: =TDCustSvc!I39 -> 0 | F31: =TDCustSvc!J39 -> 19273108 | G31: =TDCustSvc!K39 -> 15708279 | H31: =TDCustSvc!L39 -> 1667059.1 | I31: =TDCustSvc!M39 -> 1746841.8 | J31: =TDCustSvc!N39 -> 13996.628 | K31: =TDCustSvc!O39 -> 1732845.2 | L31: =TDCustSvc!P39 -> 95337.2 | ... R31: =TDCustSvc!V39 -> 1
B32: $ / kw - NCP | D32: =D31/D$100 -> 0.12795456 | E32: =IFERROR(E31/E$100,0) -> 0 | F32: =F31/F$100 -> 0.12795456 | G32: =G31/G$100 -> 0.19838242 | H32: =H31/H$100 -> 0.57535481 | I32: =I31/I$100 -> 0.055276532 | J32: =J31/J$100 -> 0.0038370087 | K32: =K31/K$100 -> 0.061989003 | L32: =L31/L$100 -> 0.0086650926 | M32: =M31/M$100 -> 0.0050883787 | ... Q32: =Q31/Q$100 -> 0.054525948 | R32: =IFERROR(R31/R$100,0) -> 1.8161562e-06
B33: $ / kWh | D33: =D31/D$101 -> 0.00050326952 | E33: =IFERROR(E31/E$101,0) -> 0 | F33: =F31/F$101 -> 0.00050326952 | G33: =G31/G$101 -> 0.0012476907 | H33: =H31/H$101 -> 0.0024803733 | I33: =I31/I$101 -> 0.00018976979 | J33: =J31/J$101 -> 1.0687983e-05 | K33: =K31/K$101 -> 0.00021947277 | L33: =L31/L$101 -> 2.1068661e-05 | M33: =M31/M$101 -> 1.0993656e-05 | ... Q33: =Q31/Q$101 -> 0.00018512796 | R33: =IFERROR(R31/R$101,0) -> 3.3779412e-08
B34: $ / Cust / Month | D34: =+(D31/D$102)/12 -> 1.2079233 | E34: =IFERROR(+(E31/E$102)/12,0) -> 0 | F34: =+(F31/F$102)/12 -> 1.2079233 | G34: =+(G31/G$102)/12 -> 1.3996686 | H34: =+(H31/H$102)/12 -> 1.3980798 | I34: =+(I31/I$102)/12 -> 2.0103875 | J34: =+(J31/J$102)/12 -> 2.0249751 | K34: =+(K31/K$102)/12 -> 2.0102705 | L34: =+(L31/L$102)/12 -> 7.3156231 | M34: =+(M31/M$102)/12 -> 7.341047 | ... Q34: =+(Q31/Q$102)/12 -> 0.016611602 | R34: =IFERROR(+(R31/R$102)/12,0) -> 0.0043859649
A36: 5 | B36: Municipal Gross Receipt Fee | D36: =E36+F36 -> 0 | E36: 0 | F36: 0 | G36: 0 | H36: 0 | I36: =SUM(G36:H36) -> 0 | J36: 0 | K36: 0 | L36: =SUM(M36:O36) -> 0 | M36: 0 | N36: 0 | O36: 0 | P36: 0 | Q36: 0 | R36: 0
B37: $ / kw - NCP | D37: =D36/D$100 -> 0 | E37: =IFERROR(E36/E$100,0) -> 0 | F37: =F36/F$100 -> 0 | G37: =G36/G$100 -> 0 | H37: =H36/H$100 -> 0 | I37: =I36/I$100 -> 0 | J37: =J36/J$100 -> 0 | K37: =K36/K$100 -> 0 | L37: =L36/L$100 -> 0 | M37: =M36/M$100 -> 0 | ... Q37: =Q36/Q$100 -> 0 | R37: =IFERROR(R36/R$100,0) -> 0
B38: $ / kWh | D38: =D36/D$101 -> 0 | E38: =IFERROR(E36/E$101,0) -> 0 | F38: =F36/F$101 -> 0 | G38: =G36/G$101 -> 0 | H38: =H36/H$101 -> 0 | I38: =I36/I$101 -> 0 | J38: =J36/J$101 -> 0 | K38: =K36/K$101 -> 0 | L38: =L36/L$101 -> 0 | M38: =M36/M$101 -> 0 | ... Q38: =Q36/Q$101 -> 0 | R38: =IFERROR(R36/R$101,0) -> 0
B39: $ / Cust / Month | D39: =+(D36/D$102)/12 -> 0 | E39: =IFERROR(+(E36/E$102)/12,0) -> 0 | F39: =+(F36/F$102)/12 -> 0 | G39: =+(G36/G$102)/12 -> 0 | H39: =+(H36/H$102)/12 -> 0 | I39: =+(I36/I$102)/12 -> 0 | J39: =+(J36/J$102)/12 -> 0 | K39: =+(K36/K$102)/12 -> 0 | L39: =+(L36/L$102)/12 -> 0 | M39: =+(M36/M$102)/12 -> 0 | ... Q39: =+(Q36/Q$102)/12 -> 0 | R39: =IFERROR(+(R36/R$102)/12,0) -> 0
A41: 6 | B41: Nuclear Decommissioning | D41: =E41+F41 -> 0 | E41: 0 | F41: 0 | G41: 0 | H41: 0 | I41: 0 | J41: 0 | K41: 0 | L41: 0 | M41: 0 | N41: 0 | O41: 0 | P41: 0 | Q41: 0 | R41: 0
B42: $ / kw - NCP | D42: =D41/D$100 -> 0 | E42: =IFERROR(E41/E$100,0) -> 0 | F42: =F41/F$100 -> 0 | G42: =G41/G$100 -> 0 | H42: =H41/H$100 -> 0 | I42: =I41/I$100 -> 0 | J42: =J41/J$100 -> 0 | K42: =K41/K$100 -> 0 | L42: =L41/L$100 -> 0 | M42: =M41/M$100 -> 0 | ... Q42: =Q41/Q$100 -> 0 | R42: =IFERROR(R41/R$100,0) -> 0
B43: $ / kWh | D43: =D41/D$101 -> 0 | E43: =IFERROR(E41/E$101,0) -> 0 | F43: =F41/F$101 -> 0 | G43: =G41/G$101 -> 0 | H43: =H41/H$101 -> 0 | I43: =I41/I$101 -> 0 | J43: =J41/J$101 -> 0 | K43: =K41/K$101 -> 0 | L43: =L41/L$101 -> 0 | M43: =M41/M$101 -> 0 | ... Q43: =Q41/Q$101 -> 0 | R43: =IFERROR(R41/R$101,0) -> 0
B44: $ / Cust / Month | D44: =+(D41/D$102)/12 -> 0 | E44: =IFERROR(+(E41/E$102)/12,0) -> 0 | F44: =+(F41/F$102)/12 -> 0 | G44: =+(G41/G$102)/12 -> 0 | H44: =+(H41/H$102)/12 -> 0 | I44: =+(I41/I$102)/12 -> 0 | J44: =+(J41/J$102)/12 -> 0 | K44: =+(K41/K$102)/12 -> 0 | L44: =+(L41/L$102)/12 -> 0 | M44: =+(M41/M$102)/12 -> 0 | ... Q44: =+(Q41/Q$102)/12 -> 0 | R44: =IFERROR(+(R41/R$102)/12,0) -> 0
A46: 7 | B46: Total Revenue Requirement | D46: =E46+F46 -> 5.8173587e+08 | E46: 0 | F46: =+F41+F36+F31+F26+F21+F16 -> 5.8173587e+08 | G46: =+G41+G36+G31+G26+G21+G16 -> 3.28025e+08 | H46: =+H41+H36+H31+H26+H21+H16 -> 20923817 | I46: =+I41+I36+I31+I26+I21+I16 -> 1.6579279e+08 | J46: =+J41+J36+J31+J26+J21+J16 -> 17742605 | K46: =+K41+K36+K31+K26+K21+K16 -> 1.4805018e+08 | L46: =+L41+L36+L31+L26+L21+L16 -> 35896316 | M46: =+M41+M36+M31+M26+M21+M16 -> 25991113 | ... R46: =+R41+R36+R31+R26+R21+R16 -> 3
B47: $ / kw - NCP | D47: =D46/D$100 -> 3.8621564 | E47: =IFERROR(E46/E$100,0) -> 0 | F47: =F46/F$100 -> 3.8621564 | G47: =G46/G$100 -> 4.1426813 | H47: =H46/H$100 -> 7.2214708 | I47: =I46/I$100 -> 5.2462967 | J47: =J46/J$100 -> 4.8639236 | K47: =K46/K$100 -> 5.2961935 | L47: =L46/L$100 -> 3.2625764 | M47: =M46/M$100 -> 3.2010482 | ... Q47: =Q46/Q$100 -> 26.720273 | R47: =IFERROR(R46/R$100,0) -> 5.4484685e-06
B48: $ / kWh | D48: =D46/D$101 -> 0.015190593 | E48: =IFERROR(E46/E$101,0) -> 0 | F48: =F46/F$101 -> 0.015190593 | G48: =G46/G$101 -> 0.026054652 | H48: =H46/H$101 -> 0.031131995 | I48: =I46/I$101 -> 0.018011055 | J48: =J46/J$101 -> 0.013548454 | K48: =K46/K$101 -> 0.018751233 | L48: =L46/L$101 -> 0.007932762 | M48: =M46/M$101 -> 0.0069159992 | ... Q48: =Q46/Q$101 -> 0.090721388 | R48: =IFERROR(R46/R$101,0) -> 1.0133824e-07
B49: $ / Cust / Month | D49: =+(D46/D$102)/12 -> 36.459732 | E49: =IFERROR(+(E46/E$102)/12,0) -> 0 | F49: =+(F46/F$102)/12 -> 36.459732 | G49: =+(G46/G$102)/12 -> 29.2283 | H49: =+(H46/H$102)/12 -> 17.547767 | I49: =+(I46/I$102)/12 -> 190.80592 | J49: =+(J46/J$102)/12 -> 2566.9278 | K49: =+(K46/K$102)/12 -> 171.75275 | L49: =+(L46/L$102)/12 -> 2754.4749 | M49: =+(M46/M$102)/12 -> 4618.1793 | ... Q49: =+(Q46/Q$102)/12 -> 8.1404644 | R49: =IFERROR(+(R46/R$102)/12,0) -> 0.013157895
B51: Unit Cost @ Proposed Rates
A52: 1 | B52: Transmission - TCOS | D52: =SUM(E52:F52) -> 0 | E52: 0 | F52: =SUM(G52:R52)-L52-I52 -> 0 | G52: =+Distribution!K332 -> 0 | H52: =+Distribution!L332 -> 0 | I52: =SUM(J52:K52) -> 0 | J52: =+Distribution!N332 -> 0 | K52: =+Distribution!O332 -> 0 | L52: =SUM(M52:O52) -> 0 | M52: =+Distribution!Q332 -> 0 | N52: =+Distribution!R332 -> 0 | O52: =+Distribution!S332 -> 0 | P52: =+Distribution!T332 -> 0 | Q52: =+Distribution!U332 -> 0 | R52: =+Distribution!V332 -> 0
B53: $ / kw - NCP | D53: =D52/D$100 -> 0 | E53: =IFERROR(E52/E$100,0) -> 0 | F53: =F52/F$100 -> 0 | G53: =G52/G$100 -> 0 | H53: =H52/H$100 -> 0 | I53: =I52/I$100 -> 0 | J53: =J52/J$100 -> 0 | K53: =K52/K$100 -> 0 | L53: =L52/L$100 -> 0 | M53: =M52/M$100 -> 0 | ... Q53: =Q52/Q$100 -> 0 | R53: =IFERROR(R52/R$100,0) -> 0
B54: $ / kWh | D54: =D52/D$101 -> 0 | E54: =IFERROR(E52/E$101,0) -> 0 | F54: =F52/F$101 -> 0 | G54: =G52/G$101 -> 0 | H54: =H52/H$101 -> 0 | I54: =I52/I$101 -> 0 | J54: =J52/J$101 -> 0 | K54: =K52/K$101 -> 0 | L54: =L52/L$101 -> 0 | M54: =M52/M$101 -> 0 | ... Q54: =Q52/Q$101 -> 0 | R54: =IFERROR(R52/R$101,0) -> 0
B55: $ / Cust / Month | D55: =+(D52/D$102)/12 -> 0 | E55: =IFERROR(+(E52/E$102)/12,0) -> 0 | F55: =+(F52/F$102)/12 -> 0 | G55: =+(G52/G$102)/12 -> 0 | H55: =+(H52/H$102)/12 -> 0 | I55: =+(I52/I$102)/12 -> 0 | J55: =+(J52/J$102)/12 -> 0 | K55: =+(K52/K$102)/12 -> 0 | L55: =+(L52/L$102)/12 -> 0 | M55: =+(M52/M$102)/12 -> 0 | ... Q55: =+(Q52/Q$102)/12 -> 0 | R55: =IFERROR(+(R52/R$102)/12,0) -> 0
A57: 2 | B57: Distribution | D57: =E57+F57 -> 7.4651298e+08 | E57: =Distribution!I77-E52 -> 0 | F57: =Distribution!J77-F52 -> 7.4651298e+08 | G57: =Distribution!K77-G52 -> 4.3153351e+08 | H57: =Distribution!L77-H52 -> 16585327 | I57: =SUM(J57:K57) -> 2.1803201e+08 | J57: =Distribution!N77-J52 -> 28867976 | K57: =Distribution!O77-K52 -> 1.8916404e+08 | L57: =SUM(M57:O57) -> 50209142 | M57: =Distribution!Q77-M52 -> 40840093 | N57: =Distribution!R77-N52 -> 2956297.7 | O57: =Distribution!S77-O52 -> 6412750.5 | P57: =Distribution!T77-P52 -> 16068.329 | Q57: =Distribution!U77-Q52 -> 28274936 | R57: =Distribution!V77-R52 -> 1861985.4
B58: $ / kw - NCP | D58: =D57/D$100 -> 4.956115 | E58: =IFERROR(E57/E$100,0) -> 0 | F58: =F57/F$100 -> 4.956115 | G58: =G57/G$100 -> 5.449907 | H58: =H57/H$100 -> 5.7241207 | I58: =I57/I$100 -> 6.8993388 | J58: =J57/J$100 -> 7.9138116 | K58: =K57/K$100 -> 6.7669578 | L58: =L57/L$100 -> 4.5634533 | M58: =M57/M$100 -> 5.0298387 | ... Q58: =Q57/Q$100 -> 34.934466 | R58: =IFERROR(R57/R$100,0) -> 3.3816563
B59: $ / kWh | D59: =D57/D$101 -> 0.01949334 | E59: =IFERROR(E57/E$101,0) -> 0 | F59: =F57/F$101 -> 0.01949334 | G59: =G57/G$101 -> 0.034276214 | H59: =H57/H$101 -> 0.02467687 | I59: =I57/I$101 -> 0.023686112 | J59: =J57/J$101 -> 0.022043913 | K59: =K57/K$101 -> 0.023958491 | L59: =L57/L$101 -> 0.011095767 | M59: =M57/M$101 -> 0.010867178 | ... Q59: =Q57/Q$101 -> 0.11861043 | R59: =IFERROR(R57/R$101,0) -> 0.062896772
B60: $ / Cust / Month | D60: =+(D57/D$102)/12 -> 46.786977 | E60: =IFERROR(+(E57/E$102)/12,0) -> 0 | F60: =+(F57/F$102)/12 -> 46.786977 | G60: =+(G57/G$102)/12 -> 38.451309 | H60: =+(H57/H$102)/12 -> 13.909291 | I60: =+(I57/I$102)/12 -> 250.92646 | J60: =+(J57/J$102)/12 -> 4176.5012 | K60: =+(K57/K$102)/12 -> 219.44886 | L60: =+(L57/L$102)/12 -> 3852.7579 | M60: =+(M57/M$102)/12 -> 7256.5908 | ... Q60: =+(Q57/Q$102)/12 -> 10.642959 | R60: =IFERROR(+(R57/R$102)/12,0) -> 8166.6026
A62: 3 | B62: Meters | D62: =E62+F62 -> 50185561 | E62: =Meter!I77 -> 0 | F62: =Meter!J77 -> 50185561 | G62: =Meter!K77 -> 23527397 | H62: =Meter!L77 -> 4470397.7 | I62: =Meter!M77 -> 17747327 | J62: =Meter!N77 -> 346260.55 | K62: =Meter!O77 -> 17401067 | L62: =Meter!P77 -> 2386784.2 | ... R62: =Meter!V77 -> 41759.103
B63: $ / kw - NCP | D63: =D62/D$100 -> 0.33318297 | E63: =IFERROR(E62/E$100,0) -> 0 | F63: =F62/F$100 -> 0.33318297 | G63: =G62/G$100 -> 0.29713133 | H63: =H62/H$100 -> 1.5428756 | I63: =I62/I$100 -> 0.56159104 | J63: =J62/J$100 -> 0.094923202 | K63: =K62/K$100 -> 0.62248769 | L63: =L62/L$100 -> 0.21693217 | M63: =M62/M$100 -> 0.12695059 | ... Q63: =Q62/Q$100 -> 9.3331099e-06 | R63: =IFERROR(R62/R$100,0) -> 0.075841053
B64: $ / kWh | D64: =D62/D$101 -> 0.0013104718 | E64: =IFERROR(E62/E$101,0) -> 0 | F64: =F62/F$101 -> 0.0013104718 | G64: =G62/G$101 -> 0.0018687543 | H64: =H62/H$101 -> 0.0066513866 | I64: =I62/I$101 -> 0.0019279975 | J64: =J62/J$101 -> 0.00026440847 | K64: =K62/K$101 -> 0.0022039248 | L64: =L62/L$101 -> 0.00052745776 | M64: =M62/M$101 -> 0.00027428207 | ... Q64: =Q62/Q$101 -> 3.1688025e-08 | R64: =IFERROR(R62/R$101,0) -> 0.001410598
B65: $ / Cust / Month | D65: =+(D62/D$102)/12 -> 3.1453314 | E65: =IFERROR(+(E62/E$102)/12,0) -> 0 | F65: =+(F62/F$102)/12 -> 3.1453314 | G65: =+(G62/G$102)/12 -> 2.0963823 | H65: =+(H62/H$102)/12 -> 3.7491007 | I65: =+(I62/I$102)/12 -> 20.424864 | J65: =+(J62/J$102)/12 -> 50.095565 | K65: =+(K62/K$102)/12 -> 20.186946 | L65: =+(L62/L$102)/12 -> 183.14796 | M65: =+(M62/M$102)/12 -> 183.15268 | ... Q65: =+(Q62/Q$102)/12 -> 2.8433784e-06 | R65: =IFERROR(+(R62/R$102)/12,0) -> 183.15396
A67: 4 | B67: T&D Customer Service | D67: =E67+F67 -> 18851935 | E67: =TDCustSvc!I77 -> 0 | F67: =TDCustSvc!J77 -> 18851935 | G67: =TDCustSvc!K77 -> 14986684 | H67: =TDCustSvc!L77 -> 1592197 | I67: =TDCustSvc!M77 -> 1966806.3 | J67: =TDCustSvc!N77 -> 15728.928 | K67: =TDCustSvc!O77 -> 1951077.3 | L67: =TDCustSvc!P77 -> 29999.575 | ... R67: =TDCustSvc!V77 -> 524.32801
B68: $ / kw - NCP | D68: =D67/D$100 -> 0.12515838 | E68: =IFERROR(E67/E$100,0) -> 0 | F68: =F67/F$100 -> 0.12515838 | G68: =G67/G$100 -> 0.18926928 | H68: =H67/H$100 -> 0.54951753 | I68: =I67/I$100 -> 0.062237021 | J68: =J67/J$100 -> 0.004311898 | K68: =K67/K$100 -> 0.069795814 | L68: =L67/L$100 -> 0.0027266281 | M68: =M67/M$100 -> 0.0015911271 | ... Q68: =Q67/Q$100 -> 0.33651541 | R68: =IFERROR(R67/R$100,0) -> 0.00095226155
B69: $ / kWh | D69: =D67/D$101 -> 0.00049227163 | E69: =IFERROR(E67/E$101,0) -> 0 | F69: =F67/F$101 -> 0.00049227163 | G69: =G67/G$101 -> 0.0011903752 | H69: =H67/H$101 -> 0.0023689879 | I69: =I67/I$101 -> 0.00021366584 | J69: =J67/J$101 -> 1.2010787e-05 | K69: =K67/K$101 -> 0.00024711287 | L69: =L67/L$101 -> 6.6296353e-06 | M69: =M67/M$101 -> 3.4376969e-06 | ... Q69: =Q67/Q$101 -> 0.0011425461 | R69: =IFERROR(R67/R$101,0) -> 1.7711492e-05
B70: $ / Cust / Month | D70: =+(D67/D$102)/12 -> 1.1815267 | E70: =IFERROR(+(E67/E$102)/12,0) -> 0 | F70: =+(F67/F$102)/12 -> 1.1815267 | G70: =+(G67/G$102)/12 -> 1.3353717 | H70: =+(H67/H$102)/12 -> 1.3352966 | I70: =+(I67/I$102)/12 -> 2.263538 | J70: =+(J67/J$102)/12 -> 2.2755972 | K70: =+(K67/K$102)/12 -> 2.2634413 | L70: =+(L67/L$102)/12 -> 2.3019931 | M70: =+(M67/M$102)/12 -> 2.2955325 | ... Q70: =+(Q67/Q$102)/12 -> 0.10252109 | R70: =IFERROR(+(R67/R$102)/12,0) -> 2.2996842
A72: 5 | B72: Municipal Gross Receipt Fee | D72: =E72+F72 -> 51762293 | E72: =Distribution!I68 -> 0 | F72: =Distribution!J68 -> 51762293 | G72: =Distribution!K68 -> 23321633 | H72: =Distribution!L68 -> 985252.86 | I72: =Distribution!M68 -> 17553759 | J72: =Distribution!N68 -> 2398321.4 | K72: =Distribution!O68 -> 15155437 | L72: =Distribution!P68 -> 4558360.3 | ... R72: =Distribution!V68 -> 0
B73: $ / kw - NCP | D73: =D72/D$100 -> 0.34365093 | E73: =IFERROR(E72/E$100,0) -> 0 | F73: =F72/F$100 -> 0.34365093 | G73: =G72/G$100 -> 0.29453271 | H73: =H72/H$100 -> 0.34004191 | I73: =I72/I$100 -> 0.55546581 | J73: =J72/J$100 -> 0.65747123 | K73: =K72/K$100 -> 0.54215487 | L73: =L72/L$100 -> 0.41430432 | M73: =M72/M$100 -> 0.51970182 | ... Q73: =Q72/Q$100 -> 0.5844382 | R73: =IFERROR(R72/R$100,0) -> 0
B74: $ / kWh | D74: =D72/D$101 -> 0.0013516442 | E74: =IFERROR(E72/E$101,0) -> 0 | F74: =F72/F$101 -> 0.0013516442 | G74: =G72/G$101 -> 0.0018524107 | H74: =H72/H$101 -> 0.0014659317 | I74: =I72/I$101 -> 0.001906969 | J74: =J72/J$101 -> 0.0018313853 | K74: =K72/K$101 -> 0.0019195055 | L74: =L72/L$101 -> 0.0010073565 | M74: =M72/M$101 -> 0.0011228376 | ... Q74: =Q72/Q$101 -> 0.0019843003 | R74: =IFERROR(R72/R$101,0) -> 0
B75: $ / Cust / Month | D75: =+(D72/D$102)/12 -> 3.2441515 | E75: =IFERROR(+(E72/E$102)/12,0) -> 0 | F75: =+(F72/F$102)/12 -> 3.2441515 | G75: =+(G72/G$102)/12 -> 2.078048 | H75: =+(H72/H$102)/12 -> 0.82628268 | I75: =+(I72/I$102)/12 -> 20.202091 | J75: =+(J72/J$102)/12 -> 346.97937 | K75: =+(K72/K$102)/12 -> 17.581795 | L75: =+(L72/L$102)/12 -> 349.7821 | M75: =+(M72/M$102)/12 -> 749.77821 | ... Q75: =+(Q72/Q$102)/12 -> 0.17805201 | R75: =IFERROR(+(R72/R$102)/12,0) -> 0
A77: 6 | B77: Nuclear Decommissioning | D77: =E77+F77 -> 0 | E77: =Distribution!I69 -> 0 | F77: =Distribution!J69 -> 0 | G77: =Distribution!K69 -> 0 | H77: =Distribution!L69 -> 0 | I77: =Distribution!M69 -> 0 | J77: =Distribution!N69 -> 0 | K77: =Distribution!O69 -> 0 | L77: =Distribution!P69 -> 0 | ... R77: =Distribution!V69 -> 0
B78: $ / kw - NCP | D78: =D77/D$100 -> 0 | E78: =IFERROR(E77/E$100,0) -> 0 | F78: =F77/F$100 -> 0 | G78: =G77/G$100 -> 0 | H78: =H77/H$100 -> 0 | I78: =I77/I$100 -> 0 | J78: =J77/J$100 -> 0 | K78: =K77/K$100 -> 0 | L78: =L77/L$100 -> 0 | M78: =M77/M$100 -> 0 | ... Q78: =Q77/Q$100 -> 0 | R78: =IFERROR(R77/R$100,0) -> 0
B79: $ / kWh | D79: =D77/D$101 -> 0 | E79: =IFERROR(E77/E$101,0) -> 0 | F79: =F77/F$101 -> 0 | G79: =G77/G$101 -> 0 | H79: =H77/H$101 -> 0 | I79: =I77/I$101 -> 0 | J79: =J77/J$101 -> 0 | K79: =K77/K$101 -> 0 | L79: =L77/L$101 -> 0 | M79: =M77/M$101 -> 0 | ... Q79: =Q77/Q$101 -> 0 | R79: =IFERROR(R77/R$101,0) -> 0
B80: $ / Cust / Month | D80: =+(D77/D$102)/12 -> 0 | E80: =IFERROR(+(E77/E$102)/12,0) -> 0 | F80: =+(F77/F$102)/12 -> 0 | G80: =+(G77/G$102)/12 -> 0 | H80: =+(H77/H$102)/12 -> 0 | I80: =+(I77/I$102)/12 -> 0 | J80: =+(J77/J$102)/12 -> 0 | K80: =+(K77/K$102)/12 -> 0 | L80: =+(L77/L$102)/12 -> 0 | M80: =+(M77/M$102)/12 -> 0 | ... Q80: =+(Q77/Q$102)/12 -> 0 | R80: =IFERROR(+(R77/R$102)/12,0) -> 0
A82: 7 | B82: DSM | D82: =E82+F82 -> 0 | E82: =+Distribution!I70 -> 0 | F82: =+Distribution!J70 -> 0 | G82: =+Distribution!K70 -> 0 | H82: =+Distribution!L70 -> 0 | I82: =SUM(J82:K82) -> 0 | J82: =+Distribution!N70 -> 0 | K82: =+Distribution!O70 -> 0 | L82: =SUM(M82:N82) -> 0 | M82: =+Distribution!Q70 -> 0 | N82: =+Distribution!R70 -> 0 | O82: =+Distribution!S70 -> 0 | P82: =+Distribution!T70 -> 0 | Q82: =+Distribution!U70 -> 0 | R82: =+Distribution!V70 -> 0
B83: $ / kw - NCP | D83: =D82/D$100 -> 0 | E83: =IFERROR(E82/E$100,0) -> 0 | F83: =F82/F$100 -> 0 | G83: =G82/G$100 -> 0 | H83: =H82/H$100 -> 0 | I83: =I82/I$100 -> 0 | J83: =J82/J$100 -> 0 | K83: =K82/K$100 -> 0 | L83: =L82/L$100 -> 0 | M83: =M82/M$100 -> 0 | ... Q83: =Q82/Q$100 -> 0 | R83: =IFERROR(R82/R$100,0) -> 0
B84: $ / kWh | D84: =D82/D$101 -> 0 | E84: =IFERROR(E82/E$101,0) -> 0 | F84: =F82/F$101 -> 0 | G84: =G82/G$101 -> 0 | H84: =H82/H$101 -> 0 | I84: =I82/I$101 -> 0 | J84: =J82/J$101 -> 0 | K84: =K82/K$101 -> 0 | L84: =L82/L$101 -> 0 | M84: =M82/M$101 -> 0 | ... Q84: =Q82/Q$101 -> 0 | R84: =IFERROR(R82/R$101,0) -> 0
B85: $ / Cust / Month | D85: =+(D82/D$102)/12 -> 0 | E85: =IFERROR(+(E82/E$102)/12,0) -> 0 | F85: =+(F82/F$102)/12 -> 0 | G85: =+(G82/G$102)/12 -> 0 | H85: =+(H82/H$102)/12 -> 0 | I85: =+(I82/I$102)/12 -> 0 | J85: =+(J82/J$102)/12 -> 0 | K85: =+(K82/K$102)/12 -> 0 | L85: =+(L82/L$102)/12 -> 0 | M85: =+(M82/M$102)/12 -> 0 | ... Q85: =+(Q82/Q$102)/12 -> 0 | R85: =IFERROR(+(R82/R$102)/12,0) -> 0
A87: 8 | B87: EMC | D87: =E87+F87 -> 0 | E87: =+Distribution!I71 -> 0 | F87: =+Distribution!J71 -> 0 | G87: =+Distribution!K71 -> 0 | H87: =+Distribution!L71 -> 0 | I87: =+Distribution!M71 -> 0 | J87: =+Distribution!N71 -> 0 | K87: =+Distribution!O71 -> 0 | L87: =+Distribution!P71 -> 0 | ... R87: =+Distribution!V71 -> 0
B88: $ / kw - NCP | D88: =D87/D$100 -> 0 | E88: =IFERROR(E87/E$100,0) -> 0 | F88: =F87/F$100 -> 0 | G88: =G87/G$100 -> 0 | H88: =H87/H$100 -> 0 | I88: =I87/I$100 -> 0 | J88: =J87/J$100 -> 0 | K88: =K87/K$100 -> 0 | L88: =L87/L$100 -> 0 | M88: =M87/M$100 -> 0 | ... Q88: =Q87/Q$100 -> 0 | R88: =IFERROR(R87/R$100,0) -> 0
B89: $ / kWh | D89: =D87/D$101 -> 0 | E89: =IFERROR(E87/E$101,0) -> 0 | F89: =F87/F$101 -> 0 | G89: =G87/G$101 -> 0 | H89: =H87/H$101 -> 0 | I89: =I87/I$101 -> 0 | J89: =J87/J$101 -> 0 | K89: =K87/K$101 -> 0 | L89: =L87/L$101 -> 0 | M89: =M87/M$101 -> 0 | ... Q89: =Q87/Q$101 -> 0 | R89: =IFERROR(R87/R$101,0) -> 0
B90: $ / Cust / Month | D90: =+(D87/D$102)/12 -> 0 | E90: =IFERROR(+(E87/E$102)/12,0) -> 0 | F90: =+(F87/F$102)/12 -> 0 | G90: =+(G87/G$102)/12 -> 0 | H90: =+(H87/H$102)/12 -> 0 | I90: =+(I87/I$102)/12 -> 0 | J90: =+(J87/J$102)/12 -> 0 | K90: =+(K87/K$102)/12 -> 0 | L90: =+(L87/L$102)/12 -> 0 | M90: =+(M87/M$102)/12 -> 0 | ... Q90: =+(Q87/Q$102)/12 -> 0 | R90: =IFERROR(+(R87/R$102)/12,0) -> 0
A92: 9 | B92: Total Revenue Requirement | D92: =E92+F92 -> 8.6731277e+08 | E92: =+E77+E72+E67+E62+E57+E52 -> 0 | F92: =SUM(G92:R92)-I92-L92 -> 8.6731277e+08 | G92: =+G87+G82+G77+G72+G67+G62+G57+G52 -> 4.9336922e+08 | H92: =+H87+H82+H77+H72+H67+H62+H57+H52 -> 23633174 | I92: =+I87+I82+I77+I72+I67+I62+I57+I52 -> 2.5529991e+08 | J92: =+J87+J82+J77+J72+J67+J62+J57+J52 -> 31628287 | K92: =+K87+K82+K77+K72+K67+K62+K57+K52 -> 2.2367162e+08 | L92: =+L87+L82+L77+L72+L67+L62+L57+L52 -> 57184286 | M92: =+M87+M82+M77+M72+M67+M62+M57+M52 -> 46103548 | N92: =+N87+N82+N77+N72+N67+N62+N57+N52 -> 4396645.2 | ... R92: =+R87+R82+R77+R72+R67+R62+R57+R52 -> 1904268.8
B93: $ / kw - NCP | D93: =D92/D$100 -> 5.7581073 | E93: =IFERROR(E92/E$100,0) -> 0 | F93: =F92/F$100 -> 5.7581073 | G93: =G92/G$100 -> 6.2308404 | H93: =H92/H$100 -> 8.1565557 | I93: =I92/I$100 -> 8.0786327 | J93: =J92/J$100 -> 8.6705179 | K93: =K92/K$100 -> 8.0013961 | L93: =L92/L$100 -> 5.1974164 | M93: =M92/M$100 -> 5.6780822 | ... Q93: =Q92/Q$100 -> 35.855429 | R93: =IFERROR(R92/R$100,0) -> 3.4584496
B94: $ / kWh | D94: =D92/D$101 -> 0.022647727 | E94: =IFERROR(E92/E$101,0) -> 0 | F94: =F92/F$101 -> 0.022647727 | G94: =G92/G$101 -> 0.039187754 | H94: =H92/H$101 -> 0.035163176 | I94: =I92/I$101 -> 0.027734744 | J94: =J92/J$101 -> 0.024151717 | K94: =K92/K$101 -> 0.028329034 | L94: =L92/L$101 -> 0.012637211 | M94: =M92/M$101 -> 0.012267735 | ... Q94: =Q92/Q$101 -> 0.12173731 | R94: =IFERROR(R92/R$101,0) -> 0.064325082
B95: $ / Cust / Month | D95: =+(D92/D$102)/12 -> 54.357986 | E95: =IFERROR(+(E92/E$102)/12,0) -> 0 | F95: =+(F92/F$102)/12 -> 54.357986 | G95: =+(G92/G$102)/12 -> 43.961111 | H95: =+(H92/H$102)/12 -> 19.819971 | I95: =+(I92/I$102)/12 -> 293.81696 | J95: =+(J92/J$102)/12 -> 4575.8517 | K95: =+(K92/K$102)/12 -> 259.48104 | L95: =+(L92/L$102)/12 -> 4387.99 | M95: =+(M92/M$102)/12 -> 8191.8173 | ... Q95: =+(Q92/Q$102)/12 -> 10.923535 | R95: =IFERROR(+(R92/R$102)/12,0) -> 8352.0563
B97: Change in Revenues | D97: =+(D92-(D46-D16))/(D46-D16) -> 0.49090473 | F97: =+(F92-(F46-F16))/(F46-F16) -> 0.49090473 | G97: =+(G92-(G46-G16))/(G46-G16) -> 0.5040598 | H97: =+(H92-(H46-H16))/(H46-H16) -> 0.12948676 | I97: =+(I92-(I46-I16))/(I46-I16) -> 0.5398734 | J97: =+(J92-(J46-J16))/(J46-J16) -> 0.78261801 | K97: =+(K92-(K46-K16))/(K46-K16) -> 0.51078244 | L97: =+(L92-(L46-L16))/(L46-L16) -> 0.5930405 | M97: =+(M92-(M46-M16))/(M46-M16) -> 0.77381965 | ... R97: =+(R92-(R46-R16))/(R46-R16) -> 634755.28
B100: kW - NCP/Billed kW Demand | D100: =+Distribution!H675 -> 1.5062463e+08 | E100: =+Distribution!I675 -> 0 | F100: =+Distribution!J675 -> 1.5062463e+08 | G100: =+Distribution!K675 -> 79181811 | H100: =+Distribution!L675 -> 2897445.4 | I100: =SUM(J100:K100) -> 31601871 | J100: =+'[2]II-H-4.1 Dist kW'!$P$151 -> 3647796.7 | K100: =+'[2]II-H-4.1 Dist kW'!$P$150 -> 27954074 | L100: =SUM(M100:O100) -> 11002445 | M100: =+'[2]II-H-4.1 Dist kW'!$P$155 -> 8119563.2 | N100: =+'[2]II-H-4.1 Dist kW'!$P$154 -> 746204.33 | O100: =+'[2]II-H-4.1 Dist kW'!$P$156+'[2]II-H-4.1 Dist kW'!$P$157 -> 2136677 | P100: =+'[2]II-H-4.1 Dist kW'!$P$160 -> 32091906 | Q100: =+Distribution!U675 -> 809370.8 | R100: =+Distribution!V675 -> 550613.44
B101: Metered kWh | D101: =+Distribution!H688 -> 3.8295797e+10 | E101: =+Distribution!I688 -> 0 | F101: =+Distribution!J688 -> 3.8295797e+10 | G101: =+Distribution!K688 -> 1.2589883e+10 | H101: =+Distribution!L688 -> 6.7210011e+08 | I101: =+Distribution!M688 -> 9.2050572e+09 | J101: =+Distribution!N688 -> 1.3095668e+09 | K101: =+Distribution!O688 -> 7.8954904e+09 | ... R101: =+Distribution!V688 -> 29603831
B102: # of Customers | D102: =+Distribution!H676 -> 1329631 | E102: =+Distribution!I676 -> 0 | F102: =+Distribution!J676 -> 1329631 | G102: =+Distribution!K676 -> 935238 | H102: =+Distribution!L676 -> 99366 | I102: =+Distribution!M676 -> 72409 | J102: =+Distribution!N676 -> 576 | K102: =+Distribution!O676 -> 71833 | ... R102: =+Distribution!V676 -> 19

Sheet Distribution
D1: 1 | E1: 2 | H1: 7 | I1: 13 | J1: 6 | K1: =J1+1 -> 7 | L1: =K1+1 -> 8 | M1: =L1+1 -> 9 | N1: =M1+1 -> 10 | O1: =N1+1 -> 11 | P1: =O1+1 -> 12 | Q1: =P1+1 -> 13 | R1: =Q1+1 -> 14 | ... V1: =U1+1 -> 18
B3: ='II-I TOTAL COMPANY'!B4 -> PUBLIC UTILITY COMMISION OF TEXAS
B4: ='II-I TOTAL COMPANY'!B5 -> AEP TEXAS INC
B5: ='II-I TOTAL COMPANY'!B6 -> II-I COST OF SERVICE
B6: ='II-I TOTAL COMPANY'!B7 -> TEST YEAR ENDING 09/30/2023
B7: DOCKET 56165 | D7: Distribution
M8: Total | P8: Total
L9: Secondary | M9: Secondary | N9: Secondary | O9: Secondary | P9: Primary | Q9: Primary | R9: Primary | S9: Primary | T9: Transmission | U9: Lighting | V9: BESS
A10: Line | B10: Account | C10: Description | E10: Reference | F10: Total AEP Texas | G10: Difference | H10: Total | I10: Oth Jurisdiction | J10: Texas Retail | K10: Residential | L10: GS < = 10kw | M10: GS > 10kw | N10: GS > 10kw | O10: GS > 10kw | Q10: 4CP | R10: NCP | S10: Sub | W10: Check
A11: No. | B11: No. | D11: ALLOC | E11: Schedule | F11: As Filed | N11: 4CP | O11: NCP | W11: Column
A12: -1 | B12: =+A12-1 -> -2 | C12: =+B12-1 -> -3 | D12: =+C12-1 -> -4 | E12: =+D12-1 -> -5 | H12: =+E12-1 -> -6 | I12: =+H12-1 -> -7 | J12: =+I12-1 -> -8 | K12: =+J12-1 -> -9 | L12: =+K12-1 -> -10 | M12: =+L12-1 -> -11 | N12: =+M12-1 -> -12 | O12: =+N12-1 -> -13 | P12: =+O12-1 -> -14 | ... V12: =+U12-1 -> -20
B13: Schedule I-A Cost of Service by Function
B15: Summary of Results @ Present ROR
A17: =+A16+1 -> 1 | B17: Rate Base by Function
A18: =+A17+1 -> 2 | B18: Plant Investment
A19: =+A18+1 -> 3 | C19: Intangible | H19: =+I19+J19 -> 1.5236904e+08 | I19: 0 | J19: =+K19+L19+M19+P19+T19+U19+V19 -> 1.5236904e+08 | K19: =+K96 -> 87564019 | L19: =+L96 -> 3238501.3 | M19: =SUM(N19:O19) -> 44981883 | N19: =+N96 -> 5991324.3 | O19: =+O96 -> 38990559 | P19: =SUM(Q19:S19) -> 11862740 | Q19: =+Q96 -> 9650052.6 | R19: =+R96 -> 698380.78 | S19: =+S96 -> 1514306.7 | T19: =+T96 -> 820.99542 | U19: =+U96 -> 4280695.4 | V19: =+V96 -> 440379.82 | W19: =IF((+K19+L19+M19+P19+T19+U19+V19)-H19=0,"OK",(+K19+L19+M19+P19+T19+U19+V19)-H19) -> OK | X19: =+'II-I TOTAL COMPANY'!K19-Distribution!H19 -> 0
A20: =+A19+1 -> 4 | C20: Transmission | H20: =+I20+J20 -> 0 | I20: 0 | J20: =+K20+L20+M20+P20+T20+U20+V20 -> 0 | K20: =+K111 -> 0 | L20: =+L111 -> 0 | M20: =SUM(N20:O20) -> 0 | N20: =+N111 -> 0 | O20: =+O111 -> 0 | P20: =SUM(Q20:S20) -> 0 | Q20: =+Q111 -> 0 | R20: =+R111 -> 0 | S20: =+S111 -> 0 | T20: =+T111 -> 0 | U20: =+U111 -> 0 | V20: =+V111 -> 0 | W20: =IF((+K20+L20+M20+P20+T20+U20+V20)-H20=0,"OK",(+K20+L20+M20+P20+T20+U20+V20)-H20) -> OK | X20: =+'II-I TOTAL COMPANY'!K20-Distribution!H20 -> 0
A21: =+A20+1 -> 5 | C21: Distribution | H21: =+I21+J21 -> 5.530937e+09 | I21: 0 | J21: =+K21+L21+M21+P21+T21+U21+V21 -> 5.530937e+09 | K21: =+K147 -> 3.2154441e+09 | L21: =+L147 -> 1.3415403e+08 | M21: =SUM(N21:O21) -> 1.5614549e+09 | N21: =+N147 -> 2.0385822e+08 | O21: =+O147 -> 1.3575967e+09 | P21: =SUM(Q21:S21) -> 3.369426e+08 | Q21: =+Q147 -> 2.7410183e+08 | R21: =+R147 -> 19835589 | S21: =+S147 -> 43005177 | T21: =+T147 -> 0 | U21: =+U147 -> 2.7042948e+08 | V21: =+V147 -> 12511867 | W21: =IF((+K21+L21+M21+P21+T21+U21+V21)-H21=0,"OK",(+K21+L21+M21+P21+T21+U21+V21)-H21) -> OK | X21: =+'II-I TOTAL COMPANY'!K21-Distribution!H21 -> 0
A22: =+A21+1 -> 6 | C22: General | H22: =+I22+J22 -> 6.5153933e+08 | I22: 0 | J22: =+K22+L22+M22+P22+T22+U22+V22 -> 6.5153933e+08 | K22: =+K162+K168 -> 3.744291e+08 | L22: =+L162+L168 -> 13848030 | M22: =SUM(N22:O22) -> 1.9234528e+08 | N22: =+N162+N168 -> 25619269 | O22: =+O162+O168 -> 1.6672601e+08 | P22: =SUM(Q22:S22) -> 50725802 | Q22: =+Q162+Q168 -> 41264215 | R22: =+R162+R168 -> 2986318.9 | S22: =+S162+S168 -> 6475268.2 | T22: =+T162+T168 -> 3510.6266 | U22: =+U162+U168 -> 18304515 | V22: =+V162+V168 -> 1883091 | W22: =IF((+K22+L22+M22+P22+T22+U22+V22)-H22=0,"OK",(+K22+L22+M22+P22+T22+U22+V22)-H22) -> OK | X22: =+'II-I TOTAL COMPANY'!K22-Distribution!H22 -> 0
A23: =+A22+1 -> 7 | W23: =IF((+K23+L23+M23+P23+T23+U23+V23)-H23=0,"OK",(+K23+L23+M23+P23+T23+U23+V23)-H23) -> OK | X23: =+'II-I TOTAL COMPANY'!K23-Distribution!H23 -> 0
A24: =+A23+1 -> 8 | B24: Total Plant Investment | H24: =+I24+J24 -> 6.3348454e+09 | I24: 0 | J24: =+K24+L24+M24+P24+T24+U24+V24 -> 6.3348454e+09 | K24: =SUM(K19:K23) -> 3.6774373e+09 | L24: =SUM(L19:L23) -> 1.5124056e+08 | M24: =SUM(N24:O24) -> 1.7987821e+09 | N24: =SUM(N19:N23) -> 2.3546881e+08 | O24: =SUM(O19:O23) -> 1.5633133e+09 | P24: =SUM(Q24:S24) -> 3.9953114e+08 | Q24: =SUM(Q19:Q23) -> 3.250161e+08 | R24: =SUM(R19:R23) -> 23520289 | S24: =SUM(S19:S23) -> 50994752 | T24: =SUM(T19:T23) -> 4331.622 | U24: =SUM(U19:U23) -> 2.9301469e+08 | V24: =SUM(V19:V23) -> 14835338 | W24: =IF((+K24+L24+M24+P24+T24+U24+V24)-H24=0,"OK",(+K24+L24+M24+P24+T24+U24+V24)-H24) -> OK | X24: =+'II-I TOTAL COMPANY'!K24-Distribution!H24 -> 0
A25: =+A24+1 -> 9 | W25: =IF((+K25+L25+M25+P25+T25+U25+V25)-H25=0,"OK",(+K25+L25+M25+P25+T25+U25+V25)-H25) -> OK | X25: =+'II-I TOTAL COMPANY'!K25-Distribution!H25 -> 0
A26: =+A25+1 -> 10 | C26: Less Accumulated Depreciation | H26: =+I26+J26 -> -1.5577575e+09 | I26: 0 | J26: =+K26+L26+M26+P26+T26+U26+V26 -> -1.5577575e+09 | K26: =-K247 -> -9.1116697e+08 | L26: =-L247 -> -42978044 | M26: =SUM(N26:O26) -> -4.130936e+08 | N26: =-N247 -> -52510669 | O26: =-O247 -> -3.6058293e+08 | P26: =SUM(Q26:S26) -> -89509328 | Q26: =-Q247 -> -72815200 | R26: =-R247 -> -5269399 | S26: =-S247 -> -11424728 | T26: =-T247 -> -1235.542 | U26: =-U247 -> -97684756 | V26: =-V247 -> -3323608 | W26: =IF((+K26+L26+M26+P26+T26+U26+V26)-H26=0,"OK",(+K26+L26+M26+P26+T26+U26+V26)-H26) -> OK | X26: =+'II-I TOTAL COMPANY'!K26-Distribution!H26 -> 0
A27: =+A26+1 -> 11 | W27: =IF((+K27+L27+M27+P27+T27+U27+V27)-H27=0,"OK",(+K27+L27+M27+P27+T27+U27+V27)-H27) -> OK | X27: =+'II-I TOTAL COMPANY'!K27-Distribution!H27 -> 0
A28: =+A27+1 -> 12 | B28: Net Plant Investment | H28: =+I28+J28 -> 4.7770878e+09 | I28: 0 | J28: =+K28+L28+M28+P28+T28+U28+V28 -> 4.7770878e+09 | K28: =+K24+K26 -> 2.7662703e+09 | L28: =+L24+L26 -> 1.0826251e+08 | M28: =SUM(N28:O28) -> 1.3856885e+09 | N28: =+N24+N26 -> 1.8295814e+08 | O28: =+O24+O26 -> 1.2027303e+09 | P28: =SUM(Q28:S28) -> 3.1002181e+08 | Q28: =+Q24+Q26 -> 2.522009e+08 | R28: =+R24+R26 -> 18250890 | S28: =+S24+S26 -> 39570023 | T28: =+T24+T26 -> 3096.08 | U28: =+U24+U26 -> 1.9532993e+08 | V28: =+V24+V26 -> 11511730 | W28: =IF((+K28+L28+M28+P28+T28+U28+V28)-H28=0,"OK",(+K28+L28+M28+P28+T28+U28+V28)-H28) -> OK | X28: =+'II-I TOTAL COMPANY'!K28-Distribution!H28 -> 0
A29: =+A28+1 -> 13 | W29: =IF((+K29+L29+M29+P29+T29+U29+V29)-H29=0,"OK",(+K29+L29+M29+P29+T29+U29+V29)-H29) -> OK | X29: =+'II-I TOTAL COMPANY'!K29-Distribution!H29 -> 0
A30: =+A29+1 -> 14 | B30: Material and Supplies | H30: =+I30+J30 -> 1.1523846e+08 | I30: 0 | J30: =+K30+L30+M30+P30+T30+U30+V30 -> 1.1523846e+08 | K30: =+K266 -> 66897006 | L30: =+L266 -> 2751247.6 | M30: =SUM(N30:O30) -> 32722009 | N30: =+N266 -> 4283460.8 | O30: =+O266 -> 28438548 | P30: =SUM(Q30:S30) -> 7267951.9 | Q30: =+Q266 -> 5912433.7 | R30: =+R266 -> 427862.34 | S30: =+S266 -> 927655.86 | T30: =+T266 -> 78.797413 | U30: =+U266 -> 5330289.6 | V30: =+V266 -> 269872.63 | W30: =IF((+K30+L30+M30+P30+T30+U30+V30)-H30=0,"OK",(+K30+L30+M30+P30+T30+U30+V30)-H30) -> OK | X30: =+'II-I TOTAL COMPANY'!K30-Distribution!H30 -> 0
A31: =+A30+1 -> 15 | B31: Cash Working Capital | H31: =+I31+J31 -> -16416706 | I31: 0 | J31: =+K31+L31+M31+P31+T31+U31+V31 -> -16416706 | K31: =+K270 -> -9449452.8 | L31: =+L270 -> -352463.19 | M31: =SUM(N31:O31) -> -4843118.5 | N31: =+N270 -> -643964.5 | O31: =+O270 -> -4199154 | P31: =SUM(Q31:S31) -> -1240918 | Q31: =+Q270 -> -1008991.2 | R31: =+R270 -> -73108.72 | S31: =+S270 -> -158818.14 | T31: =+T270 -> -1601.2039 | U31: =+U270 -> -483317.19 | V31: =+V270 -> -45834.79 | W31: =IF((+K31+L31+M31+P31+T31+U31+V31)-H31=0,"OK",(+K31+L31+M31+P31+T31+U31+V31)-H31) -> OK | X31: =+'II-I TOTAL COMPANY'!K31-Distribution!H31 -> 0
A32: =+A31+1 -> 16 | B32: Prepayments | H32: =+I32+J32 -> 57619309 | I32: 0 | J32: =+K32+L32+M32+P32+T32+U32+V32 -> 57619309 | K32: =+K276 -> 33448550 | L32: =+L276 -> 1375625.7 | M32: =SUM(N32:O32) -> 16361028 | N32: =+N276 -> 2141733.4 | O32: =+O276 -> 14219294 | P32: =SUM(Q32:S32) -> 3633981.1 | Q32: =+Q276 -> 2956221 | R32: =+R276 -> 213931.47 | S32: =+S276 -> 463828.58 | T32: =+T276 -> 39.398762 | U32: =+U276 -> 2665148.5 | V32: =+V276 -> 134936.51 | W32: =IF((+K32+L32+M32+P32+T32+U32+V32)-H32=0,"OK",(+K32+L32+M32+P32+T32+U32+V32)-H32) -> OK | X32: =+'II-I TOTAL COMPANY'!K32-Distribution!H32 -> 0
A33: =+A32+1 -> 17 | B33: Other Rate Base | H33: =+I33+J33 -> -2.5972059e+08 | I33: 0 | J33: =+K33+L33+M33+P33+T33+U33+V33 -> -2.5972059e+08 | K33: =+K253+K259+K292 -> -1.5115887e+08 | L33: =+L253+L259+L292 -> -6348106.3 | M33: =SUM(N33:O33) -> -73158728 | N33: =+N253+N259+N292 -> -9539471.3 | O33: =+O253+O259+O292 -> -63619257 | P33: =SUM(Q33:S33) -> -15379319 | Q33: =+Q253+Q259+Q292 -> -12511032 | R33: =+R253+R259+R292 -> -905370.4 | S33: =+S253+S259+S292 -> -1962916.9 | T33: =+T253+T259+T292 -> 0 | U33: =+U253+U259+U292 -> -13104482 | V33: =+V253+V259+V292 -> -571088.35 | W33: =IF((+K33+L33+M33+P33+T33+U33+V33)-H33=0,"OK",(+K33+L33+M33+P33+T33+U33+V33)-H33) -> OK | X33: =+'II-I TOTAL COMPANY'!K33-Distribution!H33 -> 0
A34: =+A33+1 -> 18 | B34: Accumulated Deferred Income Taxes | H34: =+I34+J34 -> -5.5590275e+08 | I34: 0 | J34: =+K34+L34+M34+P34+T34+U34+V34 -> -5.5590275e+08 | K34: =+K306 -> -3.2317747e+08 | L34: =+L306 -> -13483537 | M34: =+M306 -> -1.5693852e+08 | N34: =+N306 -> -20489357 | O34: =+O306 -> -1.3644916e+08 | P34: =+P306 -> -33865386 | Q34: =+Q306 -> -27549394 | R34: =+R306 -> -1993633 | ... V34: =+V306 -> -1257541.2 | W34: =IF((+K34+L34+M34+P34+T34+U34+V34)-H34=0,"OK",(+K34+L34+M34+P34+T34+U34+V34)-H34) -> OK | X34: =+'II-I TOTAL COMPANY'!K34-Distribution!H34 -> 0
A35: =+A34+1 -> 19 | B35: Customer Deposits | H35: =+I35+J35 -> -42130 | J35: =+K35+L35+M35+P35+T35+U35+V35 -> -42130 | K35: =K271 -> -29633.467 | L35: =L271 -> -3148.4597 | M35: =M271 -> -2294.3141 | N35: =N271 -> -18.250838 | O35: =O271 -> -2276.0633 | P35: =P271 -> -34.410434 | Q35: =Q271 -> -14.860491 | R35: =R271 -> -17.427015 | ... V35: =V271 -> -0.60202417 | W35: =IF((+K35+L35+M35+P35+T35+U35+V35)-H35=0,"OK",(+K35+L35+M35+P35+T35+U35+V35)-H35) -> OK | X35: =+'II-I TOTAL COMPANY'!K35-Distribution!H35 -> 0
A36: =+A35+1 -> 20 | B36: Total Rate Base | H36: =+I36+J36 -> 4.1178634e+09 | I36: 0 | J36: =+K36+L36+M36+P36+T36+U36+V36 -> 4.1178634e+09 | K36: =SUM(K28:K35) -> 2.3828004e+09 | L36: =SUM(L28:L35) -> 92202132 | M36: =SUM(N36:O36) -> 1.1998288e+09 | N36: =SUM(N28:N35) -> 1.5871052e+08 | O36: =SUM(O28:O35) -> 1.0411183e+09 | P36: =SUM(Q36:S36) -> 2.7043809e+08 | Q36: =SUM(Q28:Q35) -> 2.2000012e+08 | R36: =SUM(R28:R35) -> 15920554 | S36: =SUM(S28:S35) -> 34517412 | T36: =SUM(T28:T35) -> 1609.175 | U36: =SUM(U28:U35) -> 1.6255026e+08 | V36: =SUM(V28:V35) -> 10042074 | W36: =IF((+K36+L36+M36+P36+T36+U36+V36)-H36=0,"OK",(+K36+L36+M36+P36+T36+U36+V36)-H36) -> OK | X36: =+'II-I TOTAL COMPANY'!K36-Distribution!H36 -> 0
A37: =+A36+1 -> 21 | W37: =IF((+K37+L37+M37+P37+T37+U37+V37)-H37=0,"OK",(+K37+L37+M37+P37+T37+U37+V37)-H37) -> OK
A38: =+A37+1 -> 22 | W38: =IF((+K38+L38+M38+P38+T38+U38+V38)-H38=0,"OK",(+K38+L38+M38+P38+T38+U38+V38)-H38) -> OK
A39: =+A38+1 -> 23 | B39: Current Tariff Revenues | H39: =+I39+J39 -> 5.0555742e+08 | I39: 0 | J39: =+K39+L39+M39+P39+T39+U39+V39 -> 5.0555742e+08 | K39: =+'[2]II-H-4.1 Functions'!$F$189 -> 2.7428025e+08 | L39: =+'[2]II-H-4.1 Functions'!$F$191 -> 14156857 | M39: =SUM(N39:O39) -> 1.5308902e+08 | N39: =+'[2]II-H-4.1 Functions'!$F$194 -> 17640817 | O39: =+'[2]II-H-4.1 Functions'!$F$193 -> 1.3544821e+08 | P39: =SUM(Q39:S39) -> 34155357 | Q39: =+'[2]II-H-4.1 Functions'!$F$198 -> 25236655 | R39: =+'[2]II-H-4.1 Functions'!$F$197 -> 2304334.5 | S39: =+'[2]II-H-4.1 Functions'!$F$199+'[2]II-H-4.1 Functions'!$F$200 -> 6614368.3 | T39: =+'[2]II-H-4.1 Functions'!$F$203 -> 8293460.5 | U39: =+'[2]II-H-4.1 Functions'!$F$205 -> 21582477 | V39: 1 | W39: =IF((+K39+L39+M39+P39+T39+U39+V39)-H39=0,"OK",(+K39+L39+M39+P39+T39+U39+V39)-H39) -> OK | X39: =+'II-I TOTAL COMPANY'!K39-Distribution!H39 -> -0.99999994
A40: =+A39+1 -> 24 | B40: Current Miscellaneous Revenues | H40: =+I40+J40 -> 25990116 | I40: 0 | J40: =+K40+L40+M40+P40+T40+U40+V40 -> 25990116 | K40: =+K664 -> 15127423 | L40: =+L664 -> 558594.37 | M40: =SUM(N40:O40) -> 7773135.9 | N40: =+N664 -> 1036465.3 | O40: =+O664 -> 6736670.7 | P40: =SUM(Q40:S40) -> 1915541.8 | Q40: =+Q664 -> 1558245.6 | R40: =+R664 -> 112816.11 | S40: =+S664 -> 244480.1 | T40: =+T664 -> 12.506463 | U40: =+U664 -> 544278.97 | V40: =+V664 -> 71128.654 | W40: =IF((+K40+L40+M40+P40+T40+U40+V40)-H40=0,"OK",(+K40+L40+M40+P40+T40+U40+V40)-H40) -> OK | X40: =+'II-I TOTAL COMPANY'!K40-Distribution!H40 -> 0
A41: =+A40+1 -> 25 | B41: Current TCRF Revenues | H41: =+I41+J41 -> 0 | I41: 0 | J41: =+K41+L41+M41+P41+T41+U41+V41 -> 0 | K41: =K666 -> 0 | L41: =L666 -> 0 | M41: =SUM(N41:O41) -> 0 | N41: =N666 -> 0 | O41: =O666 -> 0 | P41: =SUM(Q41:S41) -> 0 | Q41: =Q666 -> 0 | R41: =R666 -> 0 | S41: =S666 -> 0 | T41: =T666 -> 0 | U41: =U666 -> 0 | V41: =V666 -> 0 | W41: =IF((+K41+L41+M41+P41+T41+U41+V41)-H41=0,"OK",(+K41+L41+M41+P41+T41+U41+V41)-H41) -> OK | X41: =+'II-I TOTAL COMPANY'!K41-Distribution!H41 -> 0
A42: =+A41+1 -> 26 | B42: Current Rider Revenues | H42: =+I42+J42 -> 0 | I42: 0 | J42: =+K42+L42+M42+P42+T42+U42+V42 -> 0 | K42: 0 | L42: 0 | M42: =SUM(N42:O42) -> 0 | N42: 0 | O42: 0 | P42: =SUM(Q42:S42) -> 0 | Q42: 0 | R42: 0 | S42: 0 | T42: 0 | U42: 0 | V42: 0 | W42: =IF((+K42+L42+M42+P42+T42+U42+V42)-H42=0,"OK",(+K42+L42+M42+P42+T42+U42+V42)-H42) -> OK | X42: =+'II-I TOTAL COMPANY'!K42-Distribution!H42 -> 0
A43: =+A42+1 -> 27 | B43: Current Total Revenues | H43: =+I43+J43 -> 5.3154754e+08 | I43: 0 | J43: =+K43+L43+M43+P43+T43+U43+V43 -> 5.3154754e+08 | K43: =SUM(K39:K42) -> 2.8940767e+08 | L43: =SUM(L39:L42) -> 14715451 | M43: =SUM(N43:O43) -> 1.6086216e+08 | N43: =SUM(N39:N42) -> 18677283 | O43: =SUM(O39:O42) -> 1.4218488e+08 | P43: =SUM(Q43:S43) -> 36070899 | Q43: =SUM(Q39:Q42) -> 26794900 | R43: =SUM(R39:R42) -> 2417150.6 | S43: =SUM(S39:S42) -> 6858848.4 | T43: =SUM(T39:T42) -> 8293473 | U43: =SUM(U39:U42) -> 22126756 | V43: =SUM(V39:V42) -> 71129.654 | W43: =IF((+K43+L43+M43+P43+T43+U43+V43)-H43=0,"OK",(+K43+L43+M43+P43+T43+U43+V43)-H43) -> OK | X43: =+'II-I TOTAL COMPANY'!K43-Distribution!H43 -> -1
A44: =+A43+1 -> 28 | W44: =IF((+K44+L44+M44+P44+T44+U44+V44)-H44=0,"OK",(+K44+L44+M44+P44+T44+U44+V44)-H44) -> OK | X44: =+'II-I TOTAL COMPANY'!K44-Distribution!H44 -> 0
A45: =+A44+1 -> 29 | B45: Operation & Maintenance | H45: =+I45+J45 -> 1.6039676e+08 | I45: 0 | J45: =+K45+L45+M45+P45+T45+U45+V45 -> 1.6039676e+08 | K45: =+K429 -> 92324348 | L45: =+L429 -> 3443684.5 | M45: =SUM(N45:O45) -> 47318904 | N45: =+N429 -> 6291750.9 | O45: =+O429 -> 41027154 | P45: =SUM(Q45:S45) -> 12124189 | Q45: =+Q429 -> 9858184.9 | R45: =+R429 -> 714296.91 | S45: =+S429 -> 1551706.9 | T45: =+T429 -> 15644.303 | U45: =+U429 -> 4722172.3 | V45: =+V429 -> 447821.39 | W45: =IF((+K45+L45+M45+P45+T45+U45+V45)-H45=0,"OK",(+K45+L45+M45+P45+T45+U45+V45)-H45) -> OK | X45: =+'II-I TOTAL COMPANY'!K45-Distribution!H45 -> -26.2
A46: =+A45+1 -> 30 | B46: Depreciation and Amortization | H46: =+I46+J46 -> 2.0830453e+08 | I46: 0 | J46: =+K46+L46+M46+P46+T46+U46+V46 -> 2.0830453e+08 | K46: =+K597 -> 1.2068229e+08 | L46: =+L597 -> 4657071.7 | M46: =SUM(N46:O46) -> 60843978 | N46: =+N597 -> 8051790.1 | O46: =+O597 -> 52792188 | P46: =SUM(Q46:S46) -> 13452438 | Q46: =+Q597 -> 10943444 | R46: =+R597 -> 791944.91 | S46: =+S597 -> 1717049.2 | T46: =+T597 -> 245.76563 | U46: =+U597 -> 8169006 | V46: =+V597 -> 499498.89 | W46: =IF((+K46+L46+M46+P46+T46+U46+V46)-H46=0,"OK",(+K46+L46+M46+P46+T46+U46+V46)-H46) -> OK | X46: =+'II-I TOTAL COMPANY'!K46-Distribution!H46 -> 0
A47: =+A46+1 -> 31 | B47: Taxes Other Than Income Taxes | H47: =+I47+J47 -> 1.1119011e+08 | I47: 0 | J47: =+K47+L47+M47+P47+T47+U47+V47 -> 1.1119011e+08 | K47: =+K611 -> 57713870 | L47: =+L611 -> 2324144.5 | M47: =SUM(N47:O47) -> 34823760 | N47: =+N611 -> 4680519.5 | O47: =+O611 -> 30143241 | P47: =SUM(Q47:S47) -> 8471736.5 | Q47: =+Q611 -> 7403255.4 | R47: =+R611 -> 447034.21 | S47: =+S611 -> 621446.87 | T47: =+T611 -> 4870314.9 | U47: =+U611 -> 2840972 | V47: =+V611 -> 145309.17 | W47: =IF((+K47+L47+M47+P47+T47+U47+V47)-H47=0,"OK",(+K47+L47+M47+P47+T47+U47+V47)-H47) -> OK | X47: =+'II-I TOTAL COMPANY'!K47-Distribution!H47 -> 0
A48: =+A47+1 -> 32 | B48: Income Tax | H48: =+I48+J48 -> -12574050 | I48: 0 | J48: =+K48+L48+M48+P48+T48+U48+V48 -> -12574050 | K48: =(((+K52+SUM(K626:K634))*K638)+SUM(K643:K646)) -> -9636515.3 | L48: =(((+L52+SUM(L626:L634))*L638)+SUM(L643:L646)) -> 371427.64 | M48: =SUM(N48:O48) -> -3045770.8 | N48: =(((+N52+SUM(N626:N634))*N638)+SUM(N643:N646)) -> -970922.09 | O48: =(((+O52+SUM(O626:O634))*O638)+SUM(O643:O646)) -> -2074848.7 | P48: =SUM(Q48:S48) -> -1099155.3 | Q48: =(((+Q52+SUM(Q626:Q634))*Q638)+SUM(Q643:Q646)) -> -1535772.8 | R48: =(((+R52+SUM(R626:R634))*R638)+SUM(R643:R646)) -> 7703.2059 | S48: =(((+S52+SUM(S626:S634))*S638)+SUM(S643:S646)) -> 428914.28 | T48: =(((+T52+SUM(T626:T634))*T638)+SUM(T643:T646)) -> 715518.72 | U48: =(((+U52+SUM(U626:U634))*U638)+SUM(U643:U646)) -> 391545.92 | V48: =(((+V52+SUM(V626:V634))*V638)+SUM(V643:V646)) -> -271101.13 | W48: =IF((+K48+L48+M48+P48+T48+U48+V48)-H48=0,"OK",(+K48+L48+M48+P48+T48+U48+V48)-H48) -> OK | X48: =+'II-I TOTAL COMPANY'!K48-Distribution!H48 -> 5.292
A49: =+A48+1 -> 33 | B49: Other Expenses | H49: =+I49+J49 -> 0 | I49: 0 | J49: =+K49+L49+M49+P49+T49+U49+V49 -> 0 | K49: =+K654 -> 0 | L49: =+L654 -> 0 | M49: =SUM(N49:O49) -> 0 | N49: =+N654 -> 0 | O49: =+O654 -> 0 | P49: =SUM(Q49:S49) -> 0 | Q49: =+Q654 -> 0 | R49: =+R654 -> 0 | S49: =+S654 -> 0 | T49: =+T654 -> 0 | U49: =+U654 -> 0 | V49: =+V654 -> 0 | W49: =IF((+K49+L49+M49+P49+T49+U49+V49)-H49=0,"OK",(+K49+L49+M49+P49+T49+U49+V49)-H49) -> OK | X49: =+'II-I TOTAL COMPANY'!K49-Distribution!H49 -> 0
A50: =+A49+1 -> 34 | B50: Total Operating Expense | H50: =+I50+J50 -> 4.6731735e+08 | I50: 0 | J50: =+K50+L50+M50+P50+T50+U50+V50 -> 4.6731735e+08 | K50: =SUM(K45:K49) -> 2.6108399e+08 | L50: =SUM(L45:L49) -> 10796328 | M50: =SUM(N50:O50) -> 1.3994087e+08 | N50: =SUM(N45:N49) -> 18053138 | O50: =SUM(O45:O49) -> 1.2188773e+08 | P50: =SUM(Q50:S50) -> 32949208 | Q50: =SUM(Q45:Q49) -> 26669112 | R50: =SUM(R45:R49) -> 1960979.2 | S50: =SUM(S45:S49) -> 4319117.2 | T50: =SUM(T45:T49) -> 5601723.7 | U50: =SUM(U45:U49) -> 16123696 | V50: =SUM(V45:V49) -> 821528.32 | W50: =IF((+K50+L50+M50+P50+T50+U50+V50)-H50=0,"OK",(+K50+L50+M50+P50+T50+U50+V50)-H50) -> OK | X50: =+'II-I TOTAL COMPANY'!K50-Distribution!H50 -> -20.908
A51: =+A50+1 -> 35 | K51: =+K650 -> 0 | L51: =+L650 -> 0 | M51: =SUM(N51:O51) -> 0 | N51: =+N650 -> 0 | O51: =+O650 -> 0 | P51: =SUM(Q51:S51) -> 0 | Q51: =+Q650 -> 0 | R51: =+R650 -> 0 | S51: =+S650 -> 0 | T51: =+T650 -> 0 | U51: =+U650 -> 0 | V51: =+V650 -> 0 | W51: =IF((+K51+L51+M51+P51+T51+U51+V51)-H51=0,"OK",(+K51+L51+M51+P51+T51+U51+V51)-H51) -> OK | X51: =+'II-I TOTAL COMPANY'!K51-Distribution!H51 -> 0
A52: =+A51+1 -> 36 | B52: Return | H52: =+I52+J52 -> 64230191 | I52: 0 | J52: =+K52+L52+M52+P52+T52+U52+V52 -> 64230191 | K52: =+K43-K50 -> 28323679 | L52: =+L43-L50 -> 3919123 | M52: =SUM(N52:O52) -> 20921288 | N52: =+N43-N50 -> 624144.37 | O52: =+O43-O50 -> 20297143 | P52: =SUM(Q52:S52) -> 3121691 | Q52: =+Q43-Q50 -> 125788.35 | R52: =+R43-R50 -> 456171.42 | S52: =+S43-S50 -> 2539731.2 | T52: =+T43-T50 -> 2691749.4 | U52: =+U43-U50 -> 6003059.9 | V52: =+V43-V50 -> -750398.67 | W52: =IF((+K52+L52+M52+P52+T52+U52+V52)-H52=0,"OK",(+K52+L52+M52+P52+T52+U52+V52)-H52) -> OK | X52: =+'II-I TOTAL COMPANY'!K52-Distribution!H52 -> 19.908
A53: =+A52+1 -> 37 | B53: Rate of Return on Ratebase | H53: =+H52/H36 -> 0.015597941 | J53: =+J52/J36 -> 0.015597941 | K53: =+K52/K36 -> 0.011886719 | L53: =+L52/L36 -> 0.042505775 | M53: =+M52/M36 -> 0.017436894 | N53: =+N52/N36 -> 0.003932596 | O53: =+O52/O36 -> 0.01949552 | P53: =+P52/P36 -> 0.011543089 | Q53: =+Q52/Q36 -> 0.0005717649 | ... U53: =+U52/U36 -> 0.036930484 | X53: =+'II-I TOTAL COMPANY'!K53-Distribution!H53 -> 4.834546e-09
W54: =IF((+K54+L54+M54+P54+T54+U54+V54)-H54=0,"OK",(+K54+L54+M54+P54+T54+U54+V54)-H54) -> OK | X54: =+'II-I TOTAL COMPANY'!K54-Distribution!H54 -> 0
B55: Summary of Results @ Proposed Rate of Return | W55: =IF((+K55+L55+M55+P55+T55+U55+V55)-H55=0,"OK",(+K55+L55+M55+P55+T55+U55+V55)-H55) -> OK | X55: =+'II-I TOTAL COMPANY'!K55-Distribution!H55 -> 0
W56: =IF((+K56+L56+M56+P56+T56+U56+V56)-H56=0,"OK",(+K56+L56+M56+P56+T56+U56+V56)-H56) -> OK | X56: =+'II-I TOTAL COMPANY'!K56-Distribution!H56 -> 0
A57: 1 | B57: Ratebase | H57: =+I57+J57 -> 4.1178634e+09 | I57: 0 | J57: =+K57+L57+M57+P57+T57+U57+V57 -> 4.1178634e+09 | K57: =+K36 -> 2.3828004e+09 | L57: =+L36 -> 92202132 | M57: =SUM(N57:O57) -> 1.1998288e+09 | N57: =+N36 -> 1.5871052e+08 | O57: =+O36 -> 1.0411183e+09 | P57: =SUM(Q57:S57) -> 2.7043809e+08 | Q57: =+Q36 -> 2.2000012e+08 | R57: =+R36 -> 15920554 | S57: =+S36 -> 34517412 | T57: =+T36 -> 1609.175 | U57: =+U36 -> 1.6255026e+08 | V57: =+V36 -> 10042074 | W57: =IF((+K57+L57+M57+P57+T57+U57+V57)-H57=0,"OK",(+K57+L57+M57+P57+T57+U57+V57)-H57) -> OK | X57: =+'II-I TOTAL COMPANY'!K57-Distribution!H57 -> 0
A58: =+A57+1 -> 2 | B58: Proposed Rate of Return | H58: =+'II-I TOTAL COMPANY'!K58 -> 0.071755 | I58: =$H$58 -> 0.071755 | J58: =$H$58 -> 0.071755 | K58: =$H$58 -> 0.071755 | L58: =$H$58 -> 0.071755 | M58: =$H$58 -> 0.071755 | N58: =$H$58 -> 0.071755 | O58: =$H$58 -> 0.071755 | P58: =$H$58 -> 0.071755 | ... V58: =$H$58 -> 0.071755 | W58: =IF((+K58+L58+M58+P58+T58+U58+V58)-H58=0,"OK",(+K58+L58+M58+P58+T58+U58+V58)-H58) -> 0.43053 | X58: =+'II-I TOTAL COMPANY'!K58-Distribution!H58 -> 0
A59: =+A58+1 -> 3 | B59: Return @ Proposed | H59: =+I59+J59 -> 2.9547729e+08 | I59: 0 | J59: =+K59+L59+M59+P59+T59+U59+V59 -> 2.9547729e+08 | K59: =+K57*K58 -> 1.7097784e+08 | L59: =+L57*L58 -> 6615964 | M59: =SUM(N59:O59) -> 86093718 | N59: =+N57*N58 -> 11388274 | O59: =+O57*O58 -> 74705445 | P59: =SUM(Q59:S59) -> 19405285 | Q59: =+Q57*Q58 -> 15786109 | R59: =+R57*R58 -> 1142379.4 | S59: =+S57*S58 -> 2476796.9 | T59: =+T57*T58 -> 115.46635 | U59: =+U57*U58 -> 11663794 | V59: =+V57*V58 -> 720569.01 | W59: =IF((+K59+L59+M59+P59+T59+U59+V59)-H59=0,"OK",(+K59+L59+M59+P59+T59+U59+V59)-H59) -> OK | X59: =+'II-I TOTAL COMPANY'!K59-Distribution!H59 -> 0
A60: =+A59+1 -> 4 | W60: =IF((+K60+L60+M60+P60+T60+U60+V60)-H60=0,"OK",(+K60+L60+M60+P60+T60+U60+V60)-H60) -> OK | X60: =+'II-I TOTAL COMPANY'!K60-Distribution!H60 -> 0
A61: =+A60+1 -> 5 | B61: Operation & Maintenance Expense | H61: =+I61+J61 -> 1.6039676e+08 | I61: 0 | J61: =+K61+L61+M61+P61+T61+U61+V61 -> 1.6039676e+08 | K61: =+K429-K70 -> 92324348 | L61: =+L429-L70 -> 3443684.5 | M61: =SUM(N61:O61) -> 47318904 | N61: =+N429-N70 -> 6291750.9 | O61: =+O429-O70 -> 41027154 | P61: =SUM(Q61:S61) -> 12124189 | Q61: =+Q429-Q70 -> 9858184.9 | R61: =+R429-R70 -> 714296.91 | S61: =+S429-S70 -> 1551706.9 | T61: =+T429-T70 -> 15644.303 | U61: =+U429-U70 -> 4722172.3 | V61: =+V429-V70 -> 447821.39 | W61: =IF((+K61+L61+M61+P61+T61+U61+V61)-H61=0,"OK",(+K61+L61+M61+P61+T61+U61+V61)-H61) -> OK | X61: =+'II-I TOTAL COMPANY'!K61-Distribution!H61 -> -26.2
A62: =+A61+1 -> 6 | B62: Depreciation and Amortization | H62: =+I62+J62 -> 2.0830453e+08 | I62: 0 | J62: =+K62+L62+M62+P62+T62+U62+V62 -> 2.0830453e+08 | K62: =+K597-K71 -> 1.2068229e+08 | L62: =+L597-L71 -> 4657071.7 | M62: =SUM(N62:O62) -> 60843978 | N62: =+N597-N71 -> 8051790.1 | O62: =+O597-O71 -> 52792188 | P62: =SUM(Q62:S62) -> 13452438 | Q62: =+Q597-Q71 -> 10943444 | R62: =+R597-R71 -> 791944.91 | S62: =+S597-S71 -> 1717049.2 | T62: =+T597-T71 -> 245.76563 | U62: =+U597-U71 -> 8169006 | V62: =+V597-V71 -> 499498.89 | W62: =IF((+K62+L62+M62+P62+T62+U62+V62)-H62=0,"OK",(+K62+L62+M62+P62+T62+U62+V62)-H62) -> OK | X62: =+'II-I TOTAL COMPANY'!K62-Distribution!H62 -> 0
A63: =+A62+1 -> 7 | B63: Taxes Other than Income Taxes | H63: =+I63+J63 -> 59427814 | I63: 0 | J63: =+K63+L63+M63+P63+T63+U63+V63 -> 59427814 | K63: =+K611-K68 -> 34392236 | L63: =+L611-L68 -> 1338891.7 | M63: =SUM(N63:O63) -> 17270002 | N63: =+N611-N68 -> 2282198.1 | O63: =+O611-O68 -> 14987804 | P63: =SUM(Q63:S63) -> 3913376.2 | Q63: =+Q611-Q68 -> 3183503.6 | R63: =+R611-R68 -> 230379.77 | S63: =+S611-S68 -> 499492.81 | T63: =+T611-T68 -> 54.200749 | U63: =+U611-U68 -> 2367944.8 | V63: =+V611-V68 -> 145309.17 | W63: =IF((+K63+L63+M63+P63+T63+U63+V63)-H63=0,"OK",(+K63+L63+M63+P63+T63+U63+V63)-H63) -> OK | X63: =+'II-I TOTAL COMPANY'!K63-Distribution!H63 -> 0
A64: =+A63+1 -> 8 | B64: Income Taxes | H64: =+I64+J64 -> 48896698 | I64: 0 | J64: =+K64+L64+M64+P64+T64+U64+V64 -> 48896698 | K64: =(((+K59+SUM(K626:K634))*K638)+SUM(K642:K646)) -> 28284212 | L64: =(((+L59+SUM(L626:L634))*L638)+SUM(L642:L646)) -> 1088309.4 | M64: =SUM(N64:O64) -> 14278546 | N64: =(((+N59+SUM(N626:N634))*N638)+SUM(N642:N646)) -> 1890428.7 | O64: =(((+O59+SUM(O626:O634))*O638)+SUM(O642:O646)) -> 12388117 | P64: =SUM(Q64:S64) -> 3229395 | Q64: =(((+Q59+SUM(Q626:Q634))*Q638)+SUM(Q642:Q646)) -> 2627097.2 | R64: =(((+R59+SUM(R626:R634))*R638)+SUM(R642:R646)) -> 190112.91 | S64: =(((+S59+SUM(S626:S634))*S638)+SUM(S642:S646)) -> 412184.9 | T64: =(((+T59+SUM(T626:T634))*T638)+SUM(T642:T646)) -> 21.099844 | U64: =(((+U59+SUM(U626:U634))*U638)+SUM(U642:U646)) -> 1896298 | V64: =(((+V59+SUM(V626:V634))*V638)+SUM(V642:V646)) -> 119915.59 | W64: =IF((+K64+L64+M64+P64+T64+U64+V64)-H64=0,"OK",(+K64+L64+M64+P64+T64+U64+V64)-H64) -> OK | X64: =+'II-I TOTAL COMPANY'!K64-Distribution!H64 -> 0
A65: =+A64+1 -> 9 | B65: Other Expenses | H65: =+I65+J65 -> 0 | I65: 0 | J65: =+K65+L65+M65+P65+T65+U65+V65 -> 0 | K65: 0 | L65: 0 | M65: =SUM(N65:O65) -> 0 | N65: 0 | O65: 0 | P65: =SUM(Q65:S65) -> 0 | Q65: 0 | R65: 0 | S65: 0 | T65: 0 | U65: 0 | V65: 0 | W65: =IF((+K65+L65+M65+P65+T65+U65+V65)-H65=0,"OK",(+K65+L65+M65+P65+T65+U65+V65)-H65) -> OK | X65: =+'II-I TOTAL COMPANY'!K65-Distribution!H65 -> 0
A66: =+A65+1 -> 10 | B66: Total Operating Expenses | H66: =+I66+J66 -> 4.770258e+08 | I66: 0 | J66: =+K66+L66+M66+P66+T66+U66+V66 -> 4.770258e+08 | K66: =SUM(K61:K65) -> 2.7568309e+08 | L66: =SUM(L61:L65) -> 10527957 | M66: =SUM(N66:O66) -> 1.3971143e+08 | N66: =SUM(N61:N65) -> 18516168 | O66: =SUM(O61:O65) -> 1.2119526e+08 | P66: =SUM(Q66:S66) -> 32719398 | Q66: =SUM(Q61:Q65) -> 26612230 | R66: =SUM(R61:R65) -> 1926734.5 | S66: =SUM(S61:S65) -> 4180433.8 | T66: =SUM(T61:T65) -> 15965.369 | U66: =SUM(U61:U65) -> 17155421 | V66: =SUM(V61:V65) -> 1212545 | W66: =IF((+K66+L66+M66+P66+T66+U66+V66)-H66=0,"OK",(+K66+L66+M66+P66+T66+U66+V66)-H66) -> OK | X66: =+'II-I TOTAL COMPANY'!K66-Distribution!H66 -> -26.2
A67: =+A66+1 -> 11 | W67: =IF((+K67+L67+M67+P67+T67+U67+V67)-H67=0,"OK",(+K67+L67+M67+P67+T67+U67+V67)-H67) -> OK | X67: =+'II-I TOTAL COMPANY'!K67-Distribution!H67 -> 0
A68: =+A67+1 -> 12 | B68: Municipal Franchise Fees | H68: =+I68+J68 -> 51762293 | I68: 0 | J68: =+K68+L68+M68+P68+T68+U68+V68 -> 51762293 | K68: =K607 -> 23321633 | L68: =L607 -> 985252.86 | M68: =M607 -> 17553759 | N68: =N607 -> 2398321.4 | O68: =O607 -> 15155437 | P68: =SUM(Q68:S68) -> 4558360.3 | Q68: =Q607 -> 4219751.8 | R68: =R607 -> 216654.44 | S68: =S607 -> 121954.06 | T68: =T607 -> 4870260.7 | U68: =U607 -> 473027.21 | V68: =V607 -> 0 | W68: =IF((+K68+L68+M68+P68+T68+U68+V68)-H68=0,"OK",(+K68+L68+M68+P68+T68+U68+V68)-H68) -> OK | X68: =+'II-I TOTAL COMPANY'!K68-Distribution!H68 -> 0
A69: =+A68+1 -> 13 | B69: Nuclear Decommissioning | H69: =+I69+J69 -> 0 | I69: 0 | J69: =+K69+L69+M69+P69+T69+U69+V69 -> 0 | K69: =K652 -> 0 | L69: =L652 -> 0 | M69: =SUM(N69:O69) -> 0 | N69: =N652 -> 0 | O69: =O652 -> 0 | P69: =SUM(Q69:S69) -> 0 | Q69: =Q652 -> 0 | R69: =R652 -> 0 | S69: =S652 -> 0 | T69: =T652 -> 0 | U69: =U652 -> 0 | V69: =V652 -> 0 | W69: =IF((+K69+L69+M69+P69+T69+U69+V69)-H69=0,"OK",(+K69+L69+M69+P69+T69+U69+V69)-H69) -> OK | X69: =+'II-I TOTAL COMPANY'!K69-Distribution!H69 -> 0
A70: =+A69+1 -> 14 | B70: DSM | H70: =+I70+J70 -> 0 | I70: 0 | J70: =+K70+L70+M70+P70+T70+U70+V70 -> 0 | K70: =K393 -> 0 | L70: =L393 -> 0 | M70: =M393 -> 0 | N70: =N393 -> 0 | O70: =O393 -> 0 | P70: =SUM(Q70:S70) -> 0 | Q70: =Q393 -> 0 | R70: =R393 -> 0 | S70: =S393 -> 0 | T70: =T393 -> 0 | U70: =U393 -> 0 | V70: =V393 -> 0 | W70: =IF((+K70+L70+M70+P70+T70+U70+V70)-H70=0,"OK",(+K70+L70+M70+P70+T70+U70+V70)-H70) -> OK | X70: =+'II-I TOTAL COMPANY'!K70-Distribution!H70 -> 0
A71: =+A70+1 -> 15 | B71: Excess Mitigation Credit | H71: =+I71+J71 -> 0 | I71: 0 | J71: =+K71+L71+M71+P71+T71+U71+V71 -> 0 | K71: =K590 -> 0 | L71: =L590 -> 0 | M71: =M590 -> 0 | N71: =N590 -> 0 | O71: =O590 -> 0 | P71: =SUM(Q71:S71) -> 0 | Q71: =Q590 -> 0 | R71: =R590 -> 0 | S71: =S590 -> 0 | T71: =T590 -> 0 | U71: =U590 -> 0 | V71: =V590 -> 0 | W71: =IF((+K71+L71+M71+P71+T71+U71+V71)-H71=0,"OK",(+K71+L71+M71+P71+T71+U71+V71)-H71) -> OK | X71: =+'II-I TOTAL COMPANY'!K71-Distribution!H71 -> 0
A72: =+A71+1 -> 16 | W72: =IF((+K72+L72+M72+P72+T72+U72+V72)-H72=0,"OK",(+K72+L72+M72+P72+T72+U72+V72)-H72) -> OK | X72: =+'II-I TOTAL COMPANY'!K72-Distribution!H72 -> 0
A73: =+A72+1 -> 17 | W73: =IF((+K73+L73+M73+P73+T73+U73+V73)-H73=0,"OK",(+K73+L73+M73+P73+T73+U73+V73)-H73) -> OK | X73: =+'II-I TOTAL COMPANY'!K73-Distribution!H73 -> 0
A74: =+A73+1 -> 18 | B74: Total Cost of Service | H74: =+I74+J74 -> 8.2426539e+08 | I74: 0 | J74: =+K74+L74+M74+P74+T74+U74+V74 -> 8.2426539e+08 | K74: =+K59+K66+K68+K69+K70+K71+K72 -> 4.6998256e+08 | L74: =+L59+L66+L68+L69+L70+L71+L72 -> 18129174 | M74: =SUM(N74:O74) -> 2.4335891e+08 | N74: =+N59+N66+N68+N69+N70+N71+N72 -> 32302763 | O74: =+O59+O66+O68+O69+O70+O71+O72 -> 2.1105614e+08 | P74: =SUM(Q74:S74) -> 56683044 | Q74: =+Q59+Q66+Q68+Q69+Q70+Q71+Q72 -> 46618091 | R74: =+R59+R66+R68+R69+R70+R71+R72 -> 3285768.3 | S74: =+S59+S66+S68+S69+S70+S71+S72 -> 6779184.7 | T74: =+T59+T66+T68+T69+T70+T71+T72 -> 4886341.5 | U74: =+U59+U66+U68+U69+U70+U71+U72 -> 29292242 | V74: =+V59+V66+V68+V69+V70+V71+V72 -> 1933114.1 | W74: =IF((+K74+L74+M74+P74+T74+U74+V74)-H74=0,"OK",(+K74+L74+M74+P74+T74+U74+V74)-H74) -> OK | X74: =+'II-I TOTAL COMPANY'!K74-Distribution!H74 -> -26.2
A75: =+A74+1 -> 19 | B75: Adjusted Revenue Requirement | H75: =+I75+J75 -> 7.9827527e+08 | I75: 0 | J75: =+K75+L75+M75+P75+T75+U75+V75 -> 7.9827527e+08 | K75: =+K74-K78 -> 4.5485514e+08 | L75: =+L74-L78 -> 17570580 | M75: =SUM(N75:O75) -> 2.3558577e+08 | N75: =+N74-N78 -> 31266297 | O75: =+O74-O78 -> 2.0431947e+08 | P75: =SUM(Q75:S75) -> 54767502 | Q75: =+Q74-Q78 -> 45059845 | R75: =+R74-R78 -> 3172952.2 | S75: =+S74-S78 -> 6534704.6 | T75: =+T74-T78 -> 4886329 | U75: =+U74-U78 -> 28747963 | V75: =+V74-V78 -> 1861985.4 | W75: =IF((+K75+L75+M75+P75+T75+U75+V75)-H75=0,"OK",(+K75+L75+M75+P75+T75+U75+V75)-H75) -> OK | X75: =+'II-I TOTAL COMPANY'!K75-Distribution!H75 -> -26.2
A76: =+A75+1 -> 20 | W76: =IF((+K76+L76+M76+P76+T76+U76+V76)-H76=0,"OK",(+K76+L76+M76+P76+T76+U76+V76)-H76) -> OK | X76: =+'II-I TOTAL COMPANY'!K76-Distribution!H76 -> 0
A77: =+A76+1 -> 21 | B77: Proposed Tariff Revenues | H77: =+I77+J77 -> 7.4651298e+08 | I77: 0 | J77: =+K77+L77+M77+P77+T77+U77+V77 -> 7.4651298e+08 | K77: =+K74-K80-K78 -> 4.3153351e+08 | L77: =+L74-L80-L78 -> 16585327 | M77: =SUM(N77:O77) -> 2.1803201e+08 | N77: =+N74-N80-N78 -> 28867976 | O77: =+O74-O80-O78 -> 1.8916404e+08 | P77: =SUM(Q77:S77) -> 50209142 | Q77: =+Q74-Q80-Q78 -> 40840093 | R77: =+R74-R80-R78 -> 2956297.7 | S77: =+S74-S80-S78 -> 6412750.5 | T77: =+T74-T80-T78 -> 16068.329 | U77: =+U74-U80-U78 -> 28274936 | V77: =+V74-V80-V78 -> 1861985.4 | W77: =IF((+K77+L77+M77+P77+T77+U77+V77)-H77=0,"OK",(+K77+L77+M77+P77+T77+U77+V77)-H77) -> OK | X77: =+'II-I TOTAL COMPANY'!K77-Distribution!H77 -> -26.2
A78: =+A77+1 -> 22 | B78: Proposed Miscellaneous Revenues | H78: =+I78+J78 -> 25990116 | I78: 0 | J78: =+K78+L78+M78+P78+T78+U78+V78 -> 25990116 | K78: =K40 -> 15127423 | L78: =L40 -> 558594.37 | M78: =SUM(N78:O78) -> 7773135.9 | N78: =N40 -> 1036465.3 | O78: =O40 -> 6736670.7 | P78: =SUM(Q78:S78) -> 1915541.8 | Q78: =Q40 -> 1558245.6 | R78: =R40 -> 112816.11 | S78: =S40 -> 244480.1 | T78: =T40 -> 12.506463 | U78: =U40 -> 544278.97 | V78: =V40 -> 71128.654 | W78: =IF((+K78+L78+M78+P78+T78+U78+V78)-H78=0,"OK",(+K78+L78+M78+P78+T78+U78+V78)-H78) -> OK | X78: =+'II-I TOTAL COMPANY'!K78-Distribution!H78 -> 0
A79: =+A78+1 -> 23 | B79: Proposed TCRF Revenues | H79: =+I79+J79 -> 0 | I79: 0 | J79: =+K79+L79+M79+P79+T79+U79+V79 -> 0 | K79: 0 | L79: 0 | M79: =SUM(N79:O79) -> 0 | N79: 0 | O79: 0 | P79: =SUM(Q79:S79) -> 0 | Q79: 0 | R79: 0 | S79: 0 | T79: 0 | U79: 0 | V79: 0 | W79: =IF((+K79+L79+M79+P79+T79+U79+V79)-H79=0,"OK",(+K79+L79+M79+P79+T79+U79+V79)-H79) -> OK | X79: =+'II-I TOTAL COMPANY'!K79-Distribution!H79 -> 0
A80: =+A79+1 -> 24 | B80: Proposed Rider Revenues | H80: =+I80+J80 -> 51762293 | I80: 0 | J80: =+K80+L80+M80+P80+T80+U80+V80 -> 51762293 | K80: =+K69+K68+K70+K71 -> 23321633 | L80: =+L69+L68+L70+L71 -> 985252.86 | M80: =SUM(N80:O80) -> 17553759 | N80: =+N69+N68+N70+N71 -> 2398321.4 | O80: =+O69+O68+O70+O71 -> 15155437 | P80: =SUM(Q80:S80) -> 4558360.3 | Q80: =+Q69+Q68+Q70+Q71 -> 4219751.8 | R80: =+R69+R68+R70+R71 -> 216654.44 | S80: =+S69+S68+S70+S71 -> 121954.06 | T80: =+T69+T68+T70+T71 -> 4870260.7 | U80: =+U69+U68+U70+U71 -> 473027.21 | V80: =+V69+V68+V70+V71 -> 0 | W80: =IF((+K80+L80+M80+P80+T80+U80+V80)-H80=0,"OK",(+K80+L80+M80+P80+T80+U80+V80)-H80) -> OK | X80: =+'II-I TOTAL COMPANY'!K80-Distribution!H80 -> 0
A81: =+A80+1 -> 25 | B81: Proposed Total Revenues | H81: =+I81+J81 -> 8.2426539e+08 | I81: 0 | J81: =+K81+L81+M81+P81+T81+U81+V81 -> 8.2426539e+08 | K81: =SUM(K77:K80) -> 4.6998256e+08 | L81: =SUM(L77:L80) -> 18129174 | M81: =SUM(N81:O81) -> 2.4335891e+08 | N81: =SUM(N77:N80) -> 32302763 | O81: =SUM(O77:O80) -> 2.1105614e+08 | P81: =SUM(Q81:S81) -> 56683044 | Q81: =SUM(Q77:Q80) -> 46618091 | R81: =SUM(R77:R80) -> 3285768.3 | S81: =SUM(S77:S80) -> 6779184.7 | T81: =SUM(T77:T80) -> 4886341.5 | U81: =SUM(U77:U80) -> 29292242 | V81: =SUM(V77:V80) -> 1933114.1 | W81: =IF((+K81+L81+M81+P81+T81+U81+V81)-H81=0,"OK",(+K81+L81+M81+P81+T81+U81+V81)-H81) -> OK | X81: =+'II-I TOTAL COMPANY'!K81-Distribution!H81 -> -26.2
A82: =+A81+1 -> 26 | W82: =IF((+K82+L82+M82+P82+T82+U82+V82)-H82=0,"OK",(+K82+L82+M82+P82+T82+U82+V82)-H82) -> OK | X82: =+'II-I TOTAL COMPANY'!K82-Distribution!H82 -> 0
A83: =+A82+1 -> 27 | B83: Increase / Decrease in Tariff Revenues | H83: =+I83+J83 -> 2.4095555e+08 | I83: 0 | J83: =+K83+L83+M83+P83+T83+U83+V83 -> 2.4095555e+08 | K83: =+K77-K39 -> 1.5725326e+08 | L83: =+L77-L39 -> 2428469.9 | M83: =SUM(N83:O83) -> 64942989 | N83: =+N77-N39 -> 11227159 | O83: =+O77-O39 -> 53715830 | P83: =SUM(Q83:S83) -> 16053784 | Q83: =+Q77-Q39 -> 15603439 | R83: =+R77-R39 -> 651963.21 | S83: =+S77-S39 -> -201617.8 | T83: =+T77-T39 -> -8277392.2 | U83: =+U77-U39 -> 6692459.1 | V83: =+V77-V39 -> 1861984.4 | W83: =IF((+K83+L83+M83+P83+T83+U83+V83)-H83=0,"OK",(+K83+L83+M83+P83+T83+U83+V83)-H83) -> OK | X83: =+'II-I TOTAL COMPANY'!K83-Distribution!H83 -> -25.2
A84: =+A83+1 -> 28 | B84: Increase / Decrease in Miscellaneous Revenues | H84: =+I84+J84 -> 0 | I84: 0 | J84: =+K84+L84+M84+P84+T84+U84+V84 -> 0 | K84: =+K78-K40 -> 0 | L84: =+L78-L40 -> 0 | M84: =SUM(N84:O84) -> 0 | N84: =+N78-N40 -> 0 | O84: =+O78-O40 -> 0 | P84: =SUM(Q84:S84) -> 0 | Q84: =+Q78-Q40 -> 0 | R84: =+R78-R40 -> 0 | S84: =+S78-S40 -> 0 | T84: =+T78-T40 -> 0 | U84: =+U78-U40 -> 0 | V84: =+V78-V40 -> 0 | W84: =IF((+K84+L84+M84+P84+T84+U84+V84)-H84=0,"OK",(+K84+L84+M84+P84+T84+U84+V84)-H84) -> OK | X84: =+'II-I TOTAL COMPANY'!K84-Distribution!H84 -> 0
A85: =+A84+1 -> 29 | B85: Increase / Decrease in TCRF Revenues | H85: =+I85+J85 -> 0 | I85: 0 | J85: =+K85+L85+M85+P85+T85+U85+V85 -> 0 | K85: =+K79-K41 -> 0 | L85: =+L79-L41 -> 0 | M85: =SUM(N85:O85) -> 0 | N85: =+N79-N41 -> 0 | O85: =+O79-O41 -> 0 | P85: =SUM(Q85:S85) -> 0 | Q85: =+Q79-Q41 -> 0 | R85: =+R79-R41 -> 0 | S85: =+S79-S41 -> 0 | T85: =+T79-T41 -> 0 | U85: =+U79-U41 -> 0 | V85: =+V79-V41 -> 0 | W85: =IF((+K85+L85+M85+P85+T85+U85+V85)-H85=0,"OK",(+K85+L85+M85+P85+T85+U85+V85)-H85) -> OK | X85: =+'II-I TOTAL COMPANY'!K85-Distribution!H85 -> 0
A86: =+A85+1 -> 30 | B86: Increase / Decrease in Rider Revenues | H86: =+I86+J86 -> 51762293 | I86: 0 | J86: =+K86+L86+M86+P86+T86+U86+V86 -> 51762293 | K86: =+K80-K42 -> 23321633 | L86: =+L80-L42 -> 985252.86 | M86: =SUM(N86:O86) -> 17553759 | N86: =+N80-N42 -> 2398321.4 | O86: =+O80-O42 -> 15155437 | P86: =SUM(Q86:S86) -> 4558360.3 | Q86: =+Q80-Q42 -> 4219751.8 | R86: =+R80-R42 -> 216654.44 | S86: =+S80-S42 -> 121954.06 | T86: =+T80-T42 -> 4870260.7 | U86: =+U80-U42 -> 473027.21 | V86: =+V80-V42 -> 0 | W86: =IF((+K86+L86+M86+P86+T86+U86+V86)-H86=0,"OK",(+K86+L86+M86+P86+T86+U86+V86)-H86) -> OK | X86: =+'II-I TOTAL COMPANY'!K86-Distribution!H86 -> 0
A87: =+A86+1 -> 31 | B87: Increase / Decrease in Total Revenues | H87: =+I87+J87 -> 2.9271785e+08 | I87: 0 | J87: =+K87+L87+M87+P87+T87+U87+V87 -> 2.9271785e+08 | K87: =SUM(K83:K86) -> 1.8057489e+08 | L87: =SUM(L83:L86) -> 3413722.7 | M87: =SUM(N87:O87) -> 82496747 | N87: =SUM(N83:N86) -> 13625480 | O87: =SUM(O83:O86) -> 68871267 | P87: =SUM(Q87:S87) -> 20612144 | Q87: =SUM(Q83:Q86) -> 19823190 | R87: =SUM(R83:R86) -> 868617.65 | S87: =SUM(S83:S86) -> -79663.737 | T87: =SUM(T83:T86) -> -3407131.5 | U87: =SUM(U83:U86) -> 7165486.3 | V87: =SUM(V83:V86) -> 1861984.4 | W87: =IF((+K87+L87+M87+P87+T87+U87+V87)-H87=0,"OK",(+K87+L87+M87+P87+T87+U87+V87)-H87) -> OK | X87: =+'II-I TOTAL COMPANY'!K87-Distribution!H87 -> -25.2
B90: Schedule II-B-1 Original Cost of Utility Plant
A92: 1 | B92: Intangible Plant | W92: =SUM(Q94:V94,N94:O94,K94:L94) -> 0
A93: =+A92+1 -> 2 | B93: A301 | C93: Organization | D93: LABOR | E93: II-I-1 Column (8) | H93: ='II-I TOTAL COMPANY'!K93 -> 17344.858 | I93: 0 | J93: =SUM(K93:V93)-M93-P93 -> 17344.858 | K93: =VLOOKUP($D93,$E$741:$V$815,K$1,FALSE)*$H93 -> 9967.8087 | L93: =VLOOKUP($D93,$E$741:$V$815,L$1,FALSE)*$H93 -> 368.65327 | M93: =SUM(N93:O93) -> 5120.4914 | N93: =VLOOKUP($D93,$E$741:$V$815,N$1,FALSE)*$H93 -> 682.01956 | O93: =VLOOKUP($D93,$E$741:$V$815,O$1,FALSE)*$H93 -> 4438.4718 | P93: =SUM(Q93:S93) -> 1350.3894 | Q93: =VLOOKUP($D93,$E$741:$V$815,Q$1,FALSE)*$H93 -> 1098.5092 | R93: =VLOOKUP($D93,$E$741:$V$815,R$1,FALSE)*$H93 -> 79.499845 | S93: =VLOOKUP($D93,$E$741:$V$815,S$1,FALSE)*$H93 -> 172.38039 | T93: =VLOOKUP($D93,$E$741:$V$815,T$1,FALSE)*$H93 -> 0.093457625 | U93: =VLOOKUP($D93,$E$741:$V$815,U$1,FALSE)*$H93 -> 487.29093 | V93: =VLOOKUP($D93,$E$741:$V$815,V$1,FALSE)*$H93 -> 50.130428 | W93: =IF((+K93+L93+M93+P93+T93+U93+V93)-H93=0,"OK",(+K93+L93+M93+P93+T93+U93+V93)-H93) -> 3.6379788e-12
A94: =+A93+1 -> 3 | B94: A302 | C94: Franchise and Consents | D94: LABOR | E94: II-I-1 Column (8) | H94: ='II-I TOTAL COMPANY'!K94 -> 0 | I94: 0 | J94: =SUM(K94:V94)-M94-P94 -> 0 | K94: =VLOOKUP($D94,$E$741:$V$815,K$1,FALSE)*$H94 -> 0 | L94: =VLOOKUP($D94,$E$741:$V$815,L$1,FALSE)*$H94 -> 0 | M94: =SUM(N94:O94) -> 0 | N94: =VLOOKUP($D94,$E$741:$V$815,N$1,FALSE)*$H94 -> 0 | O94: =VLOOKUP($D94,$E$741:$V$815,O$1,FALSE)*$H94 -> 0 | P94: =SUM(Q94:S94) -> 0 | Q94: =VLOOKUP($D94,$E$741:$V$815,Q$1,FALSE)*$H94 -> 0 | R94: =VLOOKUP($D94,$E$741:$V$815,R$1,FALSE)*$H94 -> 0 | S94: =VLOOKUP($D94,$E$741:$V$815,S$1,FALSE)*$H94 -> 0 | T94: =VLOOKUP($D94,$E$741:$V$815,T$1,FALSE)*$H94 -> 0 | U94: =VLOOKUP($D94,$E$741:$V$815,U$1,FALSE)*$H94 -> 0 | V94: =VLOOKUP($D94,$E$741:$V$815,V$1,FALSE)*$H94 -> 0 | W94: =IF((+K94+L94+M94+P94+T94+U94+V94)-H94=0,"OK",(+K94+L94+M94+P94+T94+U94+V94)-H94) -> OK
A95: =+A94+1 -> 4 | B95: A303 | C95: Miscellaneous Intangible Plant | D95: LABOR | E95: II-I-1 Column (8) | H95: ='II-I TOTAL COMPANY'!K95 -> 1.5235169e+08 | I95: 0 | J95: =SUM(K95:V95)-M95-P95 -> 1.5235169e+08 | K95: =VLOOKUP($D95,$E$741:$V$815,K$1,FALSE)*$H95 -> 87554051 | L95: =VLOOKUP($D95,$E$741:$V$815,L$1,FALSE)*$H95 -> 3238132.7 | M95: =SUM(N95:O95) -> 44976763 | N95: =VLOOKUP($D95,$E$741:$V$815,N$1,FALSE)*$H95 -> 5990642.2 | O95: =VLOOKUP($D95,$E$741:$V$815,O$1,FALSE)*$H95 -> 38986121 | P95: =SUM(Q95:S95) -> 11861390 | Q95: =VLOOKUP($D95,$E$741:$V$815,Q$1,FALSE)*$H95 -> 9648954.1 | R95: =VLOOKUP($D95,$E$741:$V$815,R$1,FALSE)*$H95 -> 698301.28 | S95: =VLOOKUP($D95,$E$741:$V$815,S$1,FALSE)*$H95 -> 1514134.4 | T95: =VLOOKUP($D95,$E$741:$V$815,T$1,FALSE)*$H95 -> 820.90196 | U95: =VLOOKUP($D95,$E$741:$V$815,U$1,FALSE)*$H95 -> 4280208.1 | V95: =VLOOKUP($D95,$E$741:$V$815,V$1,FALSE)*$H95 -> 440329.69 | W95: =IF((+K95+L95+M95+P95+T95+U95+V95)-H95=0,"OK",(+K95+L95+M95+P95+T95+U95+V95)-H95) -> OK
A96: =+A95+1 -> 5 | C96: Total Intangible Plant | H96: =SUM(H93:H95) -> 1.5236904e+08 | I96: =SUM(I93:I95) -> 0 | J96: =SUM(K96:V96)-M96-P96 -> 1.5236904e+08 | K96: =SUM(K93:K95) -> 87564019 | L96: =SUM(L93:L95) -> 3238501.3 | M96: =SUM(N96:O96) -> 44981883 | N96: =SUM(N93:N95) -> 5991324.3 | O96: =SUM(O93:O95) -> 38990559 | P96: =SUM(Q96:S96) -> 11862740 | Q96: =SUM(Q93:Q95) -> 9650052.6 | R96: =SUM(R93:R95) -> 698380.78 | S96: =SUM(S93:S95) -> 1514306.7 | T96: =SUM(T93:T95) -> 820.99542 | U96: =SUM(U93:U95) -> 4280695.4 | V96: =SUM(V93:V95) -> 440379.82 | W96: =IF((+K96+L96+M96+P96+T96+U96+V96)-H96=0,"OK",(+K96+L96+M96+P96+T96+U96+V96)-H96) -> OK
A97: =+A96+1 -> 6 | W97: =IF((+K97+L97+M97+P97+T97+U97+V97)-H97=0,"OK",(+K97+L97+M97+P97+T97+U97+V97)-H97) -> OK
A98: =1+A97 -> 7 | B98: Schedule II-B-1 Original Cost of Utility Plant (Continued) | W98: =IF((+K98+L98+M98+P98+T98+U98+V98)-H98=0,"OK",(+K98+L98+M98+P98+T98+U98+V98)-H98) -> OK
A99: =1+A98 -> 8 | W99: =IF((+K99+L99+M99+P99+T99+U99+V99)-H99=0,"OK",(+K99+L99+M99+P99+T99+U99+V99)-H99) -> OK
A100: =1+A99 -> 9 | B100: Transmission Plant | W100: =IF((+K100+L100+M100+P100+T100+U100+V100)-H100=0,"OK",(+K100+L100+M100+P100+T100+U100+V100)-H100) -> OK
A101: =+A100+1 -> 10 | B101: A350 | C101: Land and Land Rights | D101: DEMANDDP | E101: II-I-1 Column (8) | H101: ='II-I TOTAL COMPANY'!K101 -> 0 | I101: 0 | J101: =SUM(K101:V101)-M101-P101 -> 0 | K101: =VLOOKUP($D101,$E$741:$V$815,K$1,FALSE)*$H101 -> 0 | L101: =VLOOKUP($D101,$E$741:$V$815,L$1,FALSE)*$H101 -> 0 | M101: =SUM(N101:O101) -> 0 | N101: =VLOOKUP($D101,$E$741:$V$815,N$1,FALSE)*$H101 -> 0 | O101: =VLOOKUP($D101,$E$741:$V$815,O$1,FALSE)*$H101 -> 0 | P101: =SUM(Q101:S101) -> 0 | Q101: =VLOOKUP($D101,$E$741:$V$815,Q$1,FALSE)*$H101 -> 0 | R101: =VLOOKUP($D101,$E$741:$V$815,R$1,FALSE)*$H101 -> 0 | S101: =VLOOKUP($D101,$E$741:$V$815,S$1,FALSE)*$H101 -> 0 | T101: =VLOOKUP($D101,$E$741:$V$815,T$1,FALSE)*$H101 -> 0 | U101: =VLOOKUP($D101,$E$741:$V$815,U$1,FALSE)*$H101 -> 0 | V101: =VLOOKUP($D101,$E$741:$V$815,V$1,FALSE)*$H101 -> 0 | W101: =IF((+K101+L101+M101+P101+T101+U101+V101)-H101=0,"OK",(+K101+L101+M101+P101+T101+U101+V101)-H101) -> OK
A102: =+A101+1 -> 11 | B102: A352 | C102: Structures and Improvements | D102: DEMANDDP | E102: II-I-1 Column (8) | H102: ='II-I TOTAL COMPANY'!K102 -> 0 | I102: 0 | J102: =SUM(K102:V102)-M102-P102 -> 0 | K102: =VLOOKUP($D102,$E$741:$V$815,K$1,FALSE)*$H102 -> 0 | L102: =VLOOKUP($D102,$E$741:$V$815,L$1,FALSE)*$H102 -> 0 | M102: =SUM(N102:O102) -> 0 | N102: =VLOOKUP($D102,$E$741:$V$815,N$1,FALSE)*$H102 -> 0 | O102: =VLOOKUP($D102,$E$741:$V$815,O$1,FALSE)*$H102 -> 0 | P102: =SUM(Q102:S102) -> 0 | Q102: =VLOOKUP($D102,$E$741:$V$815,Q$1,FALSE)*$H102 -> 0 | R102: =VLOOKUP($D102,$E$741:$V$815,R$1,FALSE)*$H102 -> 0 | S102: =VLOOKUP($D102,$E$741:$V$815,S$1,FALSE)*$H102 -> 0 | T102: =VLOOKUP($D102,$E$741:$V$815,T$1,FALSE)*$H102 -> 0 | U102: =VLOOKUP($D102,$E$741:$V$815,U$1,FALSE)*$H102 -> 0 | V102: =VLOOKUP($D102,$E$741:$V$815,V$1,FALSE)*$H102 -> 0 | W102: =IF((+K102+L102+M102+P102+T102+U102+V102)-H102=0,"OK",(+K102+L102+M102+P102+T102+U102+V102)-H102) -> OK
A103: =+A102+1 -> 12 | B103: A353 | C103: Station Equipment | D103: DEMANDDP | E103: II-I-1 Column (8) | H103: ='II-I TOTAL COMPANY'!K103 -> 0 | I103: 0 | J103: =SUM(K103:V103)-M103-P103 -> 0 | K103: =VLOOKUP($D103,$E$741:$V$815,K$1,FALSE)*$H103 -> 0 | L103: =VLOOKUP($D103,$E$741:$V$815,L$1,FALSE)*$H103 -> 0 | M103: =SUM(N103:O103) -> 0 | N103: =VLOOKUP($D103,$E$741:$V$815,N$1,FALSE)*$H103 -> 0 | O103: =VLOOKUP($D103,$E$741:$V$815,O$1,FALSE)*$H103 -> 0 | P103: =SUM(Q103:S103) -> 0 | Q103: =VLOOKUP($D103,$E$741:$V$815,Q$1,FALSE)*$H103 -> 0 | R103: =VLOOKUP($D103,$E$741:$V$815,R$1,FALSE)*$H103 -> 0 | S103: =VLOOKUP($D103,$E$741:$V$815,S$1,FALSE)*$H103 -> 0 | T103: =VLOOKUP($D103,$E$741:$V$815,T$1,FALSE)*$H103 -> 0 | U103: =VLOOKUP($D103,$E$741:$V$815,U$1,FALSE)*$H103 -> 0 | V103: =VLOOKUP($D103,$E$741:$V$815,V$1,FALSE)*$H103 -> 0 | W103: =IF((+K103+L103+M103+P103+T103+U103+V103)-H103=0,"OK",(+K103+L103+M103+P103+T103+U103+V103)-H103) -> OK
A104: =+A103+1 -> 13 | B104: A354 | C104: Towers and Fixtures | D104: DEMANDDP | E104: II-I-1 Column (8) | H104: ='II-I TOTAL COMPANY'!K104 -> 0 | I104: 0 | J104: =SUM(K104:V104)-M104-P104 -> 0 | K104: =VLOOKUP($D104,$E$741:$V$815,K$1,FALSE)*$H104 -> 0 | L104: =VLOOKUP($D104,$E$741:$V$815,L$1,FALSE)*$H104 -> 0 | M104: =SUM(N104:O104) -> 0 | N104: =VLOOKUP($D104,$E$741:$V$815,N$1,FALSE)*$H104 -> 0 | O104: =VLOOKUP($D104,$E$741:$V$815,O$1,FALSE)*$H104 -> 0 | P104: =SUM(Q104:S104) -> 0 | Q104: =VLOOKUP($D104,$E$741:$V$815,Q$1,FALSE)*$H104 -> 0 | R104: =VLOOKUP($D104,$E$741:$V$815,R$1,FALSE)*$H104 -> 0 | S104: =VLOOKUP($D104,$E$741:$V$815,S$1,FALSE)*$H104 -> 0 | T104: =VLOOKUP($D104,$E$741:$V$815,T$1,FALSE)*$H104 -> 0 | U104: =VLOOKUP($D104,$E$741:$V$815,U$1,FALSE)*$H104 -> 0 | V104: =VLOOKUP($D104,$E$741:$V$815,V$1,FALSE)*$H104 -> 0 | W104: =IF((+K104+L104+M104+P104+T104+U104+V104)-H104=0,"OK",(+K104+L104+M104+P104+T104+U104+V104)-H104) -> OK
A105: =+A104+1 -> 14 | B105: A355 | C105: Poles and Fixtures | D105: DEMANDDP | E105: II-I-1 Column (8) | H105: ='II-I TOTAL COMPANY'!K105 -> 0 | I105: 0 | J105: =SUM(K105:V105)-M105-P105 -> 0 | K105: =VLOOKUP($D105,$E$741:$V$815,K$1,FALSE)*$H105 -> 0 | L105: =VLOOKUP($D105,$E$741:$V$815,L$1,FALSE)*$H105 -> 0 | M105: =SUM(N105:O105) -> 0 | N105: =VLOOKUP($D105,$E$741:$V$815,N$1,FALSE)*$H105 -> 0 | O105: =VLOOKUP($D105,$E$741:$V$815,O$1,FALSE)*$H105 -> 0 | P105: =SUM(Q105:S105) -> 0 | Q105: =VLOOKUP($D105,$E$741:$V$815,Q$1,FALSE)*$H105 -> 0 | R105: =VLOOKUP($D105,$E$741:$V$815,R$1,FALSE)*$H105 -> 0 | S105: =VLOOKUP($D105,$E$741:$V$815,S$1,FALSE)*$H105 -> 0 | T105: =VLOOKUP($D105,$E$741:$V$815,T$1,FALSE)*$H105 -> 0 | U105: =VLOOKUP($D105,$E$741:$V$815,U$1,FALSE)*$H105 -> 0 | V105: =VLOOKUP($D105,$E$741:$V$815,V$1,FALSE)*$H105 -> 0 | W105: =IF((+K105+L105+M105+P105+T105+U105+V105)-H105=0,"OK",(+K105+L105+M105+P105+T105+U105+V105)-H105) -> OK
A106: =+A105+1 -> 15 | B106: A356 | C106: O.H. Conductors & Devices | D106: DEMANDDP | E106: II-I-1 Column (8) | H106: ='II-I TOTAL COMPANY'!K106 -> 0 | I106: 0 | J106: =SUM(K106:V106)-M106-P106 -> 0 | K106: =VLOOKUP($D106,$E$741:$V$815,K$1,FALSE)*$H106 -> 0 | L106: =VLOOKUP($D106,$E$741:$V$815,L$1,FALSE)*$H106 -> 0 | M106: =SUM(N106:O106) -> 0 | N106: =VLOOKUP($D106,$E$741:$V$815,N$1,FALSE)*$H106 -> 0 | O106: =VLOOKUP($D106,$E$741:$V$815,O$1,FALSE)*$H106 -> 0 | P106: =SUM(Q106:S106) -> 0 | Q106: =VLOOKUP($D106,$E$741:$V$815,Q$1,FALSE)*$H106 -> 0 | R106: =VLOOKUP($D106,$E$741:$V$815,R$1,FALSE)*$H106 -> 0 | S106: =VLOOKUP($D106,$E$741:$V$815,S$1,FALSE)*$H106 -> 0 | T106: =VLOOKUP($D106,$E$741:$V$815,T$1,FALSE)*$H106 -> 0 | U106: =VLOOKUP($D106,$E$741:$V$815,U$1,FALSE)*$H106 -> 0 | V106: =VLOOKUP($D106,$E$741:$V$815,V$1,FALSE)*$H106 -> 0 | W106: =IF((+K106+L106+M106+P106+T106+U106+V106)-H106=0,"OK",(+K106+L106+M106+P106+T106+U106+V106)-H106) -> OK
...

Sheet Meter
D1: 1 | E1: 2 | H1: 7 | I1: 13 | J1: 6 | K1: =J1+1 -> 7 | L1: =K1+1 -> 8 | M1: =L1+1 -> 9 | N1: =M1+1 -> 10 | O1: =N1+1 -> 11 | P1: =O1+1 -> 12 | Q1: =P1+1 -> 13 | R1: =Q1+1 -> 14 | ... V1: =U1+1 -> 18
B3: ='II-I TOTAL COMPANY'!B4 -> PUBLIC UTILITY COMMISION OF TEXAS
B4: ='II-I TOTAL COMPANY'!B5 -> AEP TEXAS INC
B5: ='II-I TOTAL COMPANY'!B6 -> II-I COST OF SERVICE
B6: ='II-I TOTAL COMPANY'!B7 -> TEST YEAR ENDING 09/30/2023
B7: DOCKET 56165 | E7: Metering
M8: Total | P8: Total
L9: Secondary | M9: Secondary | N9: Secondary | O9: Secondary | P9: Primary | Q9: Primary | R9: Primary | S9: Primary | T9: Transmission | U9: Lighting | V9: BESS
A10: Line | B10: Account | C10: Description | E10: Reference | F10: Total AEP Texas | G10: Difference | H10: Total | I10: Oth Jurisdiction | J10: Texas Retail | K10: Residential | L10: GS < = 10kw | M10: GS > 10kw | N10: GS > 10kw | O10: GS > 10kw | Q10: 4CP | R10: NCP | S10: Sub | W10: Check
A11: No. | B11: No. | D11: ALLOC | E11: Schedule | F11: As Filed | N11: 4CP | O11: NCP | W11: Column
A12: -1 | B12: =+A12-1 -> -2 | C12: =+B12-1 -> -3 | D12: =+C12-1 -> -4 | E12: =+D12-1 -> -5 | H12: =+E12-1 -> -6 | I12: =+H12-1 -> -7 | J12: =+I12-1 -> -8 | K12: =+J12-1 -> -9 | L12: =+K12-1 -> -10 | M12: =+L12-1 -> -11 | N12: =+M12-1 -> -12 | O12: =+N12-1 -> -13 | P12: =+O12-1 -> -14 | ... V12: =+U12-1 -> -20
B13: Schedule I-A Cost of Service by Function
B15: Summary of Results @ Present ROR
A17: =+A16+1 -> 1 | B17: Rate Base by Function
A18: =+A17+1 -> 2 | B18: Plant Investment
A19: =+A18+1 -> 3 | C19: Intangible | H19: =+I19+J19 -> 3698361.7 | I19: 0 | J19: =+K19+L19+M19+P19+T19+U19+V19 -> 3698361.7 | K19: =+K96 -> 1733817 | L19: =+L96 -> 329443.81 | M19: =SUM(N19:O19) -> 1307869.7 | N19: =+N96 -> 25515.573 | O19: =+O96 -> 1282354.2 | P19: =SUM(Q19:S19) -> 175888.3 | Q19: =+Q96 -> 75959.13 | R19: =+R96 -> 89077.87 | S19: =+S96 -> 10851.304 | T19: =+T96 -> 148265.58 | U19: =+U96 -> 0 | V19: =+V96 -> 3077.2355 | W19: =IF((+K19+L19+M19+P19+T19+U19+V19)-H19=0,"OK",(+K19+L19+M19+P19+T19+U19+V19)-H19) -> OK | Y19: =+'II-I TOTAL COMPANY'!L19-Meter!H19 -> 0
A20: =+A19+1 -> 4 | C20: Transmission | H20: =+I20+J20 -> 0 | I20: 0 | J20: =+K20+L20+M20+P20+T20+U20+V20 -> 0 | K20: =+K111 -> 0 | L20: =+L111 -> 0 | M20: =SUM(N20:O20) -> 0 | N20: =+N111 -> 0 | O20: =+O111 -> 0 | P20: =SUM(Q20:S20) -> 0 | Q20: =+Q111 -> 0 | R20: =+R111 -> 0 | S20: =+S111 -> 0 | T20: =+T111 -> 0 | U20: =+U111 -> 0 | V20: =+V111 -> 0 | W20: =IF((+K20+L20+M20+P20+T20+U20+V20)-H20=0,"OK",(+K20+L20+M20+P20+T20+U20+V20)-H20) -> OK | Y20: =+'II-I TOTAL COMPANY'!L20-Meter!H20 -> 0
A21: =+A20+1 -> 5 | C21: Distribution | H21: =+I21+J21 -> 2.1152186e+08 | I21: 0 | J21: =+K21+L21+M21+P21+T21+U21+V21 -> 2.1152186e+08 | K21: =+K147 -> 99162882 | L21: =+L147 -> 18842010 | M21: =SUM(N21:O21) -> 74801511 | N21: =+N147 -> 1459322.2 | O21: =+O147 -> 73342189 | P21: =SUM(Q21:S21) -> 10059649 | Q21: =+Q147 -> 4344360.6 | R21: =+R147 -> 5094665.9 | S21: =+S147 -> 620622.94 | T21: =+T147 -> 8479812.1 | U21: =+U147 -> 0 | V21: =+V147 -> 175997.55 | W21: =IF((+K21+L21+M21+P21+T21+U21+V21)-H21=0,"OK",(+K21+L21+M21+P21+T21+U21+V21)-H21) -> OK | Y21: =+'II-I TOTAL COMPANY'!L21-Meter!H21 -> 0
A22: =+A21+1 -> 6 | C22: General | H22: =+I22+J22 -> 9067590.5 | I22: 0 | J22: =+K22+L22+M22+P22+T22+U22+V22 -> 9067590.5 | K22: =+K162+K168 -> 4250947.9 | L22: =+L162+L168 -> 807725.64 | M22: =SUM(N22:O22) -> 3206616.4 | N22: =+N162+N168 -> 62558.718 | O22: =+O162+O168 -> 3144057.7 | P22: =SUM(Q22:S22) -> 431240.44 | Q22: =+Q162+Q168 -> 186235.51 | R22: =+R162+R168 -> 218399.86 | S22: =+S162+S168 -> 26605.073 | T22: =+T162+T168 -> 363515.44 | U22: =+U162+U168 -> 0 | V22: =+V162+V168 -> 7544.7223 | W22: =IF((+K22+L22+M22+P22+T22+U22+V22)-H22=0,"OK",(+K22+L22+M22+P22+T22+U22+V22)-H22) -> OK | Y22: =+'II-I TOTAL COMPANY'!L22-Meter!H22 -> 0
A23: =+A22+1 -> 7 | P23: =SUM(Q23:S23) -> 0 | W23: =IF((+K23+L23+M23+P23+T23+U23+V23)-H23=0,"OK",(+K23+L23+M23+P23+T23+U23+V23)-H23) -> OK | Y23: =+'II-I TOTAL COMPANY'!L23-Meter!H23 -> 0
A24: =+A23+1 -> 8 | B24: Total Plant Investment | H24: =+I24+J24 -> 2.2428781e+08 | I24: 0 | J24: =+K24+L24+M24+P24+T24+U24+V24 -> 2.2428781e+08 | K24: =SUM(K19:K23) -> 1.0514765e+08 | L24: =SUM(L19:L23) -> 19979179 | M24: =SUM(N24:O24) -> 79315998 | N24: =SUM(N19:N23) -> 1547396.5 | O24: =SUM(O19:O23) -> 77768601 | P24: =SUM(Q24:S24) -> 10666778 | Q24: =SUM(Q19:Q23) -> 4606555.2 | R24: =SUM(R19:R23) -> 5402143.6 | S24: =SUM(S19:S23) -> 658079.31 | T24: =SUM(T19:T23) -> 8991593.1 | U24: =SUM(U19:U23) -> 0 | V24: =SUM(V19:V23) -> 186619.51 | W24: =IF((+K24+L24+M24+P24+T24+U24+V24)-H24=0,"OK",(+K24+L24+M24+P24+T24+U24+V24)-H24) -> OK | Y24: =+'II-I TOTAL COMPANY'!L24-Meter!H24 -> 0
A25: =+A24+1 -> 9 | P25: =SUM(Q25:S25) -> 0 | W25: =IF((+K25+L25+M25+P25+T25+U25+V25)-H25=0,"OK",(+K25+L25+M25+P25+T25+U25+V25)-H25) -> OK | Y25: =+'II-I TOTAL COMPANY'!L25-Meter!H25 -> 0
A26: =+A25+1 -> 10 | C26: Less Accumulated Depreciation | H26: =+I26+J26 -> -1.1381186e+08 | I26: 0 | J26: =+K26+L26+M26+P26+T26+U26+V26 -> -1.1381186e+08 | K26: =-K247 -> -53355773 | L26: =-L247 -> -10138169 | M26: =SUM(N26:O26) -> -40247847 | N26: =-N247 -> -785205.76 | O26: =-O247 -> -39462641 | P26: =SUM(Q26:S26) -> -5412714.5 | Q26: =-Q247 -> -2337535.1 | R26: =-R247 -> -2741245.8 | S26: =-S247 -> -333933.58 | T26: =-T247 -> -4562664.2 | U26: =-U247 -> 0 | V26: =-V247 -> -94697.584 | W26: =IF((+K26+L26+M26+P26+T26+U26+V26)-H26=0,"OK",(+K26+L26+M26+P26+T26+U26+V26)-H26) -> OK | Y26: =+'II-I TOTAL COMPANY'!L26-Meter!H26 -> 0
A27: =+A26+1 -> 11 | P27: =SUM(Q27:S27) -> 0 | W27: =IF((+K27+L27+M27+P27+T27+U27+V27)-H27=0,"OK",(+K27+L27+M27+P27+T27+U27+V27)-H27) -> OK | Y27: =+'II-I TOTAL COMPANY'!L27-Meter!H27 -> 0
A28: =+A27+1 -> 12 | B28: Net Plant Investment | H28: =+I28+J28 -> 1.1047595e+08 | I28: 0 | J28: =+K28+L28+M28+P28+T28+U28+V28 -> 1.1047595e+08 | K28: =+K24+K26 -> 51791873 | L28: =+L24+L26 -> 9841010.9 | M28: =SUM(N28:O28) -> 39068151 | N28: =+N24+N26 -> 762190.77 | O28: =+O24+O26 -> 38305960 | P28: =SUM(Q28:S28) -> 5254063.6 | Q28: =+Q24+Q26 -> 2269020.1 | R28: =+R24+R26 -> 2660897.8 | S28: =+S24+S26 -> 324145.73 | T28: =+T24+T26 -> 4428928.9 | U28: =+U24+U26 -> 0 | V28: =+V24+V26 -> 91921.923 | W28: =IF((+K28+L28+M28+P28+T28+U28+V28)-H28=0,"OK",(+K28+L28+M28+P28+T28+U28+V28)-H28) -> OK | Y28: =+'II-I TOTAL COMPANY'!L28-Meter!H28 -> 0
A29: =+A28+1 -> 13 | P29: =SUM(Q29:S29) -> 0 | W29: =IF((+K29+L29+M29+P29+T29+U29+V29)-H29=0,"OK",(+K29+L29+M29+P29+T29+U29+V29)-H29) -> OK | Y29: =+'II-I TOTAL COMPANY'!L29-Meter!H29 -> 0
A30: =+A29+1 -> 14 | B30: Material and Supplies | H30: =+I30+J30 -> 2797003.6 | I30: 0 | J30: =+K30+L30+M30+P30+T30+U30+V30 -> 2797003.6 | K30: =+K266 -> 1311254.2 | L30: =+L266 -> 249152.35 | M30: =SUM(N30:O30) -> 989118.06 | N30: =+N266 -> 19296.963 | O30: =+O266 -> 969821.1 | P30: =SUM(Q30:S30) -> 133021.12 | Q30: =+Q266 -> 57446.506 | R30: =+R266 -> 67367.971 | S30: =+S266 -> 8206.6437 | T30: =+T266 -> 112130.56 | U30: =+U266 -> 0 | V30: =+V266 -> 2327.2572 | W30: =IF((+K30+L30+M30+P30+T30+U30+V30)-H30=0,"OK",(+K30+L30+M30+P30+T30+U30+V30)-H30) -> OK | Y30: =+'II-I TOTAL COMPANY'!L30-Meter!H30 -> 0
A31: =+A30+1 -> 15 | B31: Cash Working Capital | H31: =+I31+J31 -> -467377.98 | I31: 0 | J31: =+K31+L31+M31+P31+T31+U31+V31 -> -467377.98 | K31: =+K270 -> -219109.96 | L31: =+L270 -> -41633.24 | M31: =SUM(N31:O31) -> -165281.16 | N31: =+N270 -> -3224.5134 | O31: =+O270 -> -162056.65 | P31: =SUM(Q31:S31) -> -22227.767 | Q31: =+Q270 -> -9599.2841 | R31: =+R270 -> -11257.156 | S31: =+S270 -> -1371.3263 | T31: =+T270 -> -18736.963 | U31: =+U270 -> 0 | V31: =+V270 -> -388.88358 | W31: =IF((+K31+L31+M31+P31+T31+U31+V31)-H31=0,"OK",(+K31+L31+M31+P31+T31+U31+V31)-H31) -> OK | Y31: =+'II-I TOTAL COMPANY'!L31-Meter!H31 -> 0
A32: =+A31+1 -> 16 | B32: Prepayments | H32: =+I32+J32 -> 12780986 | I32: 0 | J32: =+K32+L32+M32+P32+T32+U32+V32 -> 12780986 | K32: =+K276 -> 5991812.9 | L32: =+L276 -> 1138508.6 | M32: =SUM(N32:O32) -> 4519802.7 | N32: =+N276 -> 88178.012 | O32: =+O276 -> 4431624.7 | P32: =SUM(Q32:S32) -> 607843.74 | Q32: =+Q276 -> 262503.42 | R32: =+R276 -> 307839.83 | S32: =+S276 -> 37500.488 | T32: =+T276 -> 512383.73 | U32: =+U276 -> 0 | V32: =+V276 -> 10634.467 | W32: =IF((+K32+L32+M32+P32+T32+U32+V32)-H32=0,"OK",(+K32+L32+M32+P32+T32+U32+V32)-H32) -> OK | Y32: =+'II-I TOTAL COMPANY'!L32-Meter!H32 -> 0
A33: =+A32+1 -> 17 | B33: Other Rate Base | H33: =+I33+J33 -> 7523261.8 | I33: 0 | J33: =+K33+L33+M33+P33+T33+U33+V33 -> 7523261.8 | K33: =+K253+K259+K292 -> 3527689.8 | L33: =+L253+L259+L292 -> 669633.93 | M33: =SUM(N33:O33) -> 2660063.1 | N33: =+N253+N259+N292 -> 52154.676 | O33: =+O253+O259+O292 -> 2607908.4 | P33: =SUM(Q33:S33) -> 358208.61 | Q33: =+Q253+Q259+Q292 -> 154991.53 | R33: =+R253+R259+R292 -> 181066.58 | S33: =+S253+S259+S292 -> 22150.491 | T33: =+T253+T259+T292 -> 301300.23 | U33: =+U253+U259+U292 -> 83.913244 | V33: =+V253+V259+V292 -> 6282.2097 | W33: =IF((+K33+L33+M33+P33+T33+U33+V33)-H33=0,"OK",(+K33+L33+M33+P33+T33+U33+V33)-H33) -> OK | Y33: =+'II-I TOTAL COMPANY'!L33-Meter!H33 -> 0
A34: =+A33+1 -> 18 | B34: Accumulated Deferred Income Taxes | H34: =+I34+J34 -> -15875665 | I34: 0 | J34: =+K34+L34+M34+P34+T34+U34+V34 -> -15875665 | K34: =+K306 -> -7442619.2 | L34: =+L306 -> -1414177.4 | M34: =+M306 -> -5614189.1 | N34: =+N306+N271 -> -109528.68 | O34: =+O306+O271 -> -5504660.4 | P34: =SUM(Q34:S34) -> -755021.82 | Q34: =+Q306+Q271 -> -326063.75 | R34: =+R306+R271 -> -382377.54 | S34: =+S306+S271 -> -46580.536 | T34: =+T306+T271 -> -636447.94 | U34: =+U306+U271 -> 0 | V34: =+V306+V271 -> -13209.406 | W34: =IF((+K34+L34+M34+P34+T34+U34+V34)-H34=0,"OK",(+K34+L34+M34+P34+T34+U34+V34)-H34) -> OK | Y34: =+'II-I TOTAL COMPANY'!L34-Meter!H34 -> 0
A35: =+A34+1 -> 19 | B35: Customer Deposits | H35: =+I35+J35 -> 0 | K35: =K271 -> 0 | L35: =L271 -> 0 | M35: =M271 -> 0 | P35: =SUM(Q35:S35) -> 0 | W35: =IF((+K35+L35+M35+P35+T35+U35+V35)-H35=0,"OK",(+K35+L35+M35+P35+T35+U35+V35)-H35) -> OK | Y35: =+'II-I TOTAL COMPANY'!L35-Meter!H35 -> 0
A36: =+A35+1 -> 20 | B36: Total Rate Base | H36: =+I36+J36 -> 1.1723416e+08 | I36: 0 | J36: =+K36+L36+M36+P36+T36+U36+V36 -> 1.1723416e+08 | K36: =SUM(K28:K35) -> 54960901 | L36: =SUM(L28:L35) -> 10442495 | M36: =SUM(N36:O36) -> 41457664 | N36: =SUM(N28:N35) -> 809067.22 | O36: =SUM(O28:O35) -> 40648597 | P36: =SUM(Q36:S36) -> 5575887.5 | Q36: =SUM(Q28:Q35) -> 2408298.5 | R36: =SUM(R28:R35) -> 2823537.5 | S36: =SUM(S28:S35) -> 344051.49 | T36: =SUM(T28:T35) -> 4699558.5 | U36: =SUM(U28:U35) -> 83.913244 | V36: =SUM(V28:V35) -> 97567.568 | W36: =IF((+K36+L36+M36+P36+T36+U36+V36)-H36=0,"OK",(+K36+L36+M36+P36+T36+U36+V36)-H36) -> OK | Y36: =+'II-I TOTAL COMPANY'!L36-Meter!H36 -> 0
A37: =+A36+1 -> 21 | P37: =SUM(Q37:S37) -> 0 | W37: =IF((+K37+L37+M37+P37+T37+U37+V37)-H37=0,"OK",(+K37+L37+M37+P37+T37+U37+V37)-H37) -> OK | Y37: =+'II-I TOTAL COMPANY'!L37-Meter!H37 -> 0
A38: =+A37+1 -> 22 | P38: =SUM(Q38:S38) -> 0 | W38: =IF((+K38+L38+M38+P38+T38+U38+V38)-H38=0,"OK",(+K38+L38+M38+P38+T38+U38+V38)-H38) -> OK | Y38: =+'II-I TOTAL COMPANY'!L38-Meter!H38 -> 0 | AC38: =SUM(Y38:AB38) -> 0
A39: =+A38+1 -> 23 | B39: Current Tariff Revenues | H39: =+I39+J39 -> 56905340 | I39: 0 | J39: =+K39+L39+M39+P39+T39+U39+V39 -> 56905340 | K39: =+'[2]II-H-4.1 Functions'!$E$189 -> 38036476 | L39: =+'[2]II-H-4.1 Functions'!$E$191 -> 5099901 | M39: =SUM(N39:O39) -> 10956923 | N39: =+'[2]II-H-4.1 Functions'!$E$194 -> 87790.73 | O39: =+'[2]II-H-4.1 Functions'!$E$193 -> 10869132 | P39: =SUM(Q39:S39) -> 1645621.7 | Q39: =+'[2]II-H-4.1 Functions'!$E$198 -> 713143.33 | R39: =+'[2]II-H-4.1 Functions'!$E$197 -> 830965.63 | S39: =+'[2]II-H-4.1 Functions'!$E$199+'[2]II-H-4.1 Functions'!$E$200 -> 101512.71 | T39: =+'[2]II-H-4.1 Functions'!$E$203 -> 1166418 | U39: =+'[2]II-H-4.1 Functions'!$E$205 -> 0 | V39: 1 | W39: =IF((+K39+L39+M39+P39+T39+U39+V39)-H39=0,"OK",(+K39+L39+M39+P39+T39+U39+V39)-H39) -> OK | Y39: =+'II-I TOTAL COMPANY'!L39-Meter!H39 -> -1
A40: =+A39+1 -> 24 | B40: Current Miscellaneous Revenues | H40: =+I40+J40 -> 856637.48 | I40: 0 | J40: =+K40+L40+M40+P40+T40+U40+V40 -> 856637.48 | K40: =+K664 -> 401597.45 | L40: =+L664 -> 76307.819 | M40: =SUM(N40:O40) -> 302936.91 | N40: =+N664 -> 5910.0753 | O40: =+O664 -> 297026.83 | P40: =SUM(Q40:S40) -> 40740.341 | Q40: =+Q664 -> 17594.125 | R40: =+R664 -> 20632.769 | S40: =+S664 -> 2513.4464 | T40: =+T664 -> 34342.194 | U40: =+U664 -> 0 | V40: =+V664 -> 712.76839 | W40: =IF((+K40+L40+M40+P40+T40+U40+V40)-H40=0,"OK",(+K40+L40+M40+P40+T40+U40+V40)-H40) -> OK | Y40: =+'II-I TOTAL COMPANY'!L40-Meter!H40 -> 0
A41: =+A40+1 -> 25 | B41: Current TCRF Revenues | H41: =+I41+J41 -> 0 | I41: 0 | J41: =+K41+L41+M41+P41+T41+U41+V41 -> 0 | K41: =K666 -> 0 | L41: =L666 -> 0 | M41: =SUM(N41:O41) -> 0 | N41: =N666 -> 0 | O41: =O666 -> 0 | P41: =SUM(Q41:S41) -> 0 | Q41: =Q666 -> 0 | R41: =R666 -> 0 | S41: =S666 -> 0 | T41: =T666 -> 0 | U41: =U666 -> 0 | V41: =V666 -> 0 | W41: =IF((+K41+L41+M41+P41+T41+U41+V41)-H41=0,"OK",(+K41+L41+M41+P41+T41+U41+V41)-H41) -> OK | Y41: =+'II-I TOTAL COMPANY'!L41-Meter!H41 -> 0
A42: =+A41+1 -> 26 | B42: Current Rider Revenues | H42: =+I42+J42 -> 0 | I42: 0 | J42: =+K42+L42+M42+P42+T42+U42+V42 -> 0 | K42: 0 | L42: 0 | M42: =SUM(N42:O42) -> 0 | N42: 0 | O42: 0 | P42: =SUM(Q42:S42) -> 0 | Q42: 0 | R42: 0 | S42: 0 | T42: 0 | U42: 0 | V42: 0 | W42: =IF((+K42+L42+M42+P42+T42+U42+V42)-H42=0,"OK",(+K42+L42+M42+P42+T42+U42+V42)-H42) -> OK | Y42: =+'II-I TOTAL COMPANY'!L42-Meter!H42 -> 0
A43: =+A42+1 -> 27 | B43: Current Total Revenues | H43: =+I43+J43 -> 57761978 | I43: 0 | J43: =+K43+L43+M43+P43+T43+U43+V43 -> 57761978 | K43: =SUM(K39:K42) -> 38438074 | L43: =SUM(L39:L42) -> 5176208.8 | M43: =SUM(N43:O43) -> 11259859 | N43: =SUM(N39:N42) -> 93700.805 | O43: =SUM(O39:O42) -> 11166159 | P43: =SUM(Q43:S43) -> 1686362 | Q43: =SUM(Q39:Q42) -> 730737.46 | R43: =SUM(R39:R42) -> 851598.4 | S43: =SUM(S39:S42) -> 104026.16 | T43: =SUM(T39:T42) -> 1200760.2 | U43: =SUM(U39:U42) -> 0 | V43: =SUM(V39:V42) -> 713.76839 | W43: =IF((+K43+L43+M43+P43+T43+U43+V43)-H43=0,"OK",(+K43+L43+M43+P43+T43+U43+V43)-H43) -> OK | Y43: =+'II-I TOTAL COMPANY'!L43-Meter!H43 -> -1
A44: =+A43+1 -> 28 | P44: =SUM(Q44:S44) -> 0 | W44: =IF((+K44+L44+M44+P44+T44+U44+V44)-H44=0,"OK",(+K44+L44+M44+P44+T44+U44+V44)-H44) -> OK | Y44: =+'II-I TOTAL COMPANY'!L44-Meter!H44 -> 0
A45: =+A44+1 -> 29 | B45: Operation & Maintenance | H45: =+I45+J45 -> 24275503 | I45: 0 | J45: =+K45+L45+M45+P45+T45+U45+V45 -> 24275503 | K45: =+K429 -> 11380520 | L45: =+L429 -> 2162420.8 | M45: =SUM(N45:O45) -> 8584664.9 | N45: =+N429 -> 167480.47 | O45: =+O429 -> 8417184.5 | P45: =SUM(Q45:S45) -> 1154505 | Q45: =+Q429 -> 498584.58 | R45: =+R429 -> 584694.06 | S45: =+S429 -> 71226.368 | T45: =+T429 -> 973193.51 | U45: =+U429 -> 0 | V45: =+V429 -> 20198.522 | W45: =IF((+K45+L45+M45+P45+T45+U45+V45)-H45=0,"OK",(+K45+L45+M45+P45+T45+U45+V45)-H45) -> OK | Y45: =+'II-I TOTAL COMPANY'!L45-Meter!H45 -> 0
A46: =+A45+1 -> 30 | B46: Depreciation and Amortization | H46: =+I46+J46 -> 14340683 | I46: 0 | J46: =+K46+L46+M46+P46+T46+U46+V46 -> 14340683 | K46: =+K597 -> 6723009.5 | L46: =+L597 -> 1277443.8 | M46: =SUM(N46:O46) -> 5071366.1 | N46: =+N597 -> 98938.606 | O46: =+O597 -> 4972427.5 | P46: =SUM(Q46:S46) -> 682020.51 | Q46: =+Q597 -> 294537.4 | R46: =+R597 -> 345406.33 | S46: =+S597 -> 42076.772 | T46: =+T597 -> 574911.26 | U46: =+U597 -> 0 | V46: =+V597 -> 11932.219 | W46: =IF((+K46+L46+M46+P46+T46+U46+V46)-H46=0,"OK",(+K46+L46+M46+P46+T46+U46+V46)-H46) -> OK | Y46: =+'II-I TOTAL COMPANY'!L46-Meter!H46 -> 0
A47: =+A46+1 -> 31 | B47: Taxes Other Than Income Taxes | H47: =+I47+J47 -> 2595480.7 | I47: 0 | J47: =+K47+L47+M47+P47+T47+U47+V47 -> 2595480.7 | K47: =+K611 -> 1216783 | L47: =+L611 -> 231198.1 | M47: =SUM(N47:O47) -> 917850.16 | N47: =+N611 -> 17908.025 | O47: =+O611 -> 899942.14 | P47: =SUM(Q47:S47) -> 123439.32 | Q47: =+Q611 -> 53310.16 | R47: =+R611 -> 62513.373 | S47: =+S611 -> 7615.7866 | T47: =+T611 -> 104049.9 | U47: =+U611 -> 0.46875315 | V47: =+V611 -> 2159.7047 | W47: =IF((+K47+L47+M47+P47+T47+U47+V47)-H47=0,"OK",(+K47+L47+M47+P47+T47+U47+V47)-H47) -> OK | Y47: =+'II-I TOTAL COMPANY'!L47-Meter!H47 -> 0
A48: =+A47+1 -> 32 | B48: Income Tax | H48: =+I48+J48 -> 2829548.2 | I48: 0 | J48: =+K48+L48+M48+P48+T48+U48+V48 -> 2829548.2 | K48: =(((+K52+SUM(K626:K634))*K638)+SUM(K643:K646)) -> 3711868.9 | L48: =(((+L52+SUM(L626:L634))*L638)+SUM(L643:L646)) -> 258537.22 | M48: =SUM(N48:O48) -> -924396.62 | N48: =(((+N52+SUM(N626:N634))*N638)+SUM(N643:N646)) -> -44489.761 | O48: =(((+O52+SUM(O626:O634))*O638)+SUM(O643:O646)) -> -879906.86 | P48: =SUM(Q48:S48) -> -88182.249 | Q48: =(((+Q52+SUM(Q626:Q634))*Q638)+SUM(Q643:Q646)) -> -37566.559 | R48: =(((+R52+SUM(R626:R634))*R638)+SUM(R643:R646)) -> -45172.353 | S48: =(((+S52+SUM(S626:S634))*S638)+SUM(S643:S646)) -> -5443.3371 | T48: =(((+T52+SUM(T626:T634))*T638)+SUM(T643:T646)) -> -120689.84 | U48: =(((+U52+SUM(U626:U634))*U638)+SUM(U643:U646)) -> -0.52233011 | V48: =(((+V52+SUM(V626:V634))*V638)+SUM(V643:V646)) -> -7588.7366 | W48: =IF((+K48+L48+M48+P48+T48+U48+V48)-H48=0,"OK",(+K48+L48+M48+P48+T48+U48+V48)-H48) -> OK | Y48: =+'II-I TOTAL COMPANY'!L48-Meter!H48 -> -0.21
A49: =+A48+1 -> 33 | B49: Other Expenses | H49: =+I49+J49 -> 0 | I49: 0 | J49: =+K49+L49+M49+P49+T49+U49+V49 -> 0 | K49: =+K654 -> 0 | L49: =+L654 -> 0 | M49: =SUM(N49:O49) -> 0 | N49: =+N654 -> 0 | O49: =+O654 -> 0 | P49: =SUM(Q49:S49) -> 0 | Q49: =+Q654 -> 0 | R49: =+R654 -> 0 | S49: =+S654 -> 0 | T49: =+T654 -> 0 | U49: =+U654 -> 0 | V49: =+V654 -> 0 | W49: =IF((+K49+L49+M49+P49+T49+U49+V49)-H49=0,"OK",(+K49+L49+M49+P49+T49+U49+V49)-H49) -> OK | Y49: =+'II-I TOTAL COMPANY'!L49-Meter!H49 -> 0
A50: =+A49+1 -> 34 | B50: Total Operating Expense | H50: =+I50+J50 -> 44041215 | I50: 0 | J50: =+K50+L50+M50+P50+T50+U50+V50 -> 44041215 | K50: =SUM(K45:K49) -> 23032182 | L50: =SUM(L45:L49) -> 3929599.9 | M50: =SUM(N50:O50) -> 13649485 | N50: =SUM(N45:N49) -> 239837.34 | O50: =SUM(O45:O49) -> 13409647 | P50: =SUM(Q50:S50) -> 1871782.6 | Q50: =SUM(Q45:Q49) -> 808865.58 | R50: =SUM(R45:R49) -> 947441.42 | S50: =SUM(S45:S49) -> 115475.59 | T50: =SUM(T45:T49) -> 1531464.8 | U50: =SUM(U45:U49) -> -0.053576961 | V50: =SUM(V45:V49) -> 26701.709 | W50: =IF((+K50+L50+M50+P50+T50+U50+V50)-H50=0,"OK",(+K50+L50+M50+P50+T50+U50+V50)-H50) -> OK | Y50: =+'II-I TOTAL COMPANY'!L50-Meter!H50 -> -0.20999999
A51: =+A50+1 -> 35 | P51: =SUM(Q51:S51) -> 0 | W51: =IF((+K51+L51+M51+P51+T51+U51+V51)-H51=0,"OK",(+K51+L51+M51+P51+T51+U51+V51)-H51) -> OK | Y51: =+'II-I TOTAL COMPANY'!L51-Meter!H51 -> 0
A52: =+A51+1 -> 36 | B52: Return | H52: =+I52+J52 -> 13720763 | I52: 0 | J52: =+K52+L52+M52+P52+T52+U52+V52 -> 13720763 | K52: =+K43-K50 -> 15405892 | L52: =+L43-L50 -> 1246608.9 | M52: =SUM(N52:O52) -> -2389625.1 | N52: =+N43-N50 -> -146136.54 | O52: =+O43-O50 -> -2243488.6 | P52: =SUM(Q52:S52) -> -185420.57 | Q52: =+Q43-Q50 -> -78128.121 | R52: =+R43-R50 -> -95843.02 | S52: =+S43-S50 -> -11449.432 | T52: =+T43-T50 -> -330704.68 | U52: =+U43-U50 -> 0.053576961 | V52: =+V43-V50 -> -25987.941 | W52: =IF((+K52+L52+M52+P52+T52+U52+V52)-H52=0,"OK",(+K52+L52+M52+P52+T52+U52+V52)-H52) -> OK | Y52: =+'II-I TOTAL COMPANY'!L52-Meter!H52 -> -0.79000001
A53: =+A52+1 -> 37 | B53: Rate of Return on Ratebase | H53: =+H52/H36 -> 0.11703724 | J53: =+J52/J36 -> 0.11703724 | K53: =+K52/K36 -> 0.2803064 | L53: =+L52/L36 -> 0.11937845 | M53: =+M52/M36 -> -0.057640129 | N53: =+N52/N36 -> -0.18062348 | O53: =+O52/O36 -> -0.055192276 | P53: =SUM(Q53:S53) -> -0.09966377 | Q53: =+Q52/Q36 -> -0.032441211 | R53: =+R52/R36 -> -0.033944306 | S53: =+S52/S36 -> -0.033278253 | T53: =+T52/T36 -> -0.070369308 | W53: =IF((+K53+L53+M53+P53+T53+U53+V53)-H53=0,"OK",(+K53+L53+M53+P53+T53+U53+V53)-H53) -> 0.054974392 | Y53: =+'II-I TOTAL COMPANY'!L53-Meter!H53 -> -6.7386504e-09
W54: =IF((+K54+L54+M54+P54+T54+U54+V54)-H54=0,"OK",(+K54+L54+M54+P54+T54+U54+V54)-H54) -> OK | Y54: =+'II-I TOTAL COMPANY'!L54-Meter!H54 -> 0
B55: Summary of Results @ Proposed Rate of Return | P55: =SUM(Q55:S55) -> 0 | W55: =IF((+K55+L55+M55+P55+T55+U55+V55)-H55=0,"OK",(+K55+L55+M55+P55+T55+U55+V55)-H55) -> OK | Y55: =+'II-I TOTAL COMPANY'!L55-Meter!H55 -> 0
P56: =SUM(Q56:S56) -> 0 | W56: =IF((+K56+L56+M56+P56+T56+U56+V56)-H56=0,"OK",(+K56+L56+M56+P56+T56+U56+V56)-H56) -> OK | Y56: =+'II-I TOTAL COMPANY'!L56-Meter!H56 -> 0
A57: 1 | B57: Ratebase | H57: =+I57+J57 -> 1.1723416e+08 | I57: 0 | J57: =+K57+L57+M57+P57+T57+U57+V57 -> 1.1723416e+08 | K57: =+K36 -> 54960901 | L57: =+L36 -> 10442495 | M57: =SUM(N57:O57) -> 41457664 | N57: =+N36 -> 809067.22 | O57: =+O36 -> 40648597 | P57: =SUM(Q57:S57) -> 5575887.5 | Q57: =+Q36 -> 2408298.5 | R57: =+R36 -> 2823537.5 | S57: =+S36 -> 344051.49 | T57: =+T36 -> 4699558.5 | U57: =+U36 -> 83.913244 | V57: =+V36 -> 97567.568 | W57: =IF((+K57+L57+M57+P57+T57+U57+V57)-H57=0,"OK",(+K57+L57+M57+P57+T57+U57+V57)-H57) -> OK | Y57: =+'II-I TOTAL COMPANY'!L57-Meter!H57 -> 0
A58: =1+A57 -> 2 | B58: Proposed Rate of Return | H58: ='II-I TOTAL COMPANY'!$L$58 -> 0.071755 | I58: ='II-I TOTAL COMPANY'!$L$58 -> 0.071755 | J58: ='II-I TOTAL COMPANY'!$L$58 -> 0.071755 | K58: ='II-I TOTAL COMPANY'!$L$58 -> 0.071755 | L58: ='II-I TOTAL COMPANY'!$L$58 -> 0.071755 | M58: ='II-I TOTAL COMPANY'!$L$58 -> 0.071755 | N58: ='II-I TOTAL COMPANY'!$L$58 -> 0.071755 | O58: ='II-I TOTAL COMPANY'!$L$58 -> 0.071755 | ... V58: ='II-I TOTAL COMPANY'!$L$58 -> 0.071755 | W58: =IF((+K58+L58+M58+P58+T58+U58+V58)-H58=0,"OK",(+K58+L58+M58+P58+T58+U58+V58)-H58) -> 0.43053 | Y58: =+'II-I TOTAL COMPANY'!L58-Meter!H58 -> 0
A59: =1+A58 -> 3 | B59: Return @ Proposed | H59: =+I59+J59 -> 8412137 | I59: 0 | J59: =+K59+L59+M59+P59+T59+U59+V59 -> 8412137 | K59: =+K57*K58 -> 3943719.5 | L59: =+L57*L58 -> 749301.24 | M59: =SUM(N59:O59) -> 2974794.7 | N59: =+N57*N58 -> 58054.618 | O59: =+O57*O58 -> 2916740.1 | P59: =SUM(Q59:S59) -> 400097.81 | Q59: =+Q57*Q58 -> 172807.46 | R59: =+R57*R58 -> 202602.93 | S59: =+S57*S58 -> 24687.415 | T59: =+T57*T58 -> 337216.82 | U59: =+U57*U58 -> 6.0211948 | V59: =+V57*V58 -> 7000.9608 | W59: =IF((+K59+L59+M59+P59+T59+U59+V59)-H59=0,"OK",(+K59+L59+M59+P59+T59+U59+V59)-H59) -> OK | Y59: =+'II-I TOTAL COMPANY'!L59-Meter!H59 -> 0
A60: =1+A59 -> 4 | P60: =SUM(Q60:S60) -> 0 | W60: =IF((+K60+L60+M60+P60+T60+U60+V60)-H60=0,"OK",(+K60+L60+M60+P60+T60+U60+V60)-H60) -> OK | Y60: =+'II-I TOTAL COMPANY'!L60-Meter!H60 -> 0
A61: =1+A60 -> 5 | B61: Operation & Maintenance Expense | H61: =+I61+J61 -> 24275503 | I61: 0 | J61: =+K61+L61+M61+P61+T61+U61+V61 -> 24275503 | K61: =+K429-K70 -> 11380520 | L61: =+L429 -> 2162420.8 | M61: =SUM(N61:O61) -> 8584664.9 | N61: =+N429 -> 167480.47 | O61: =+O429 -> 8417184.5 | P61: =SUM(Q61:S61) -> 1154505 | Q61: =+Q429 -> 498584.58 | R61: =+R429 -> 584694.06 | S61: =+S429 -> 71226.368 | T61: =+T429 -> 973193.51 | U61: =+U429 -> 0 | V61: =+V429 -> 20198.522 | W61: =IF((+K61+L61+M61+P61+T61+U61+V61)-H61=0,"OK",(+K61+L61+M61+P61+T61+U61+V61)-H61) -> OK | Y61: =+'II-I TOTAL COMPANY'!L61-Meter!H61 -> 0
A62: =1+A61 -> 6 | B62: Depreciation and Amortization | H62: =+I62+J62 -> 14340683 | I62: 0 | J62: =+K62+L62+M62+P62+T62+U62+V62 -> 14340683 | K62: =+K597-K71 -> 6723009.5 | L62: =+L597-L71 -> 1277443.8 | M62: =SUM(N62:O62) -> 5071366.1 | N62: =+N597-N71 -> 98938.606 | O62: =+O597-O71 -> 4972427.5 | P62: =SUM(Q62:S62) -> 682020.51 | Q62: =+Q597-Q71 -> 294537.4 | R62: =+R597-R71 -> 345406.33 | S62: =+S597-S71 -> 42076.772 | T62: =+T597-T71 -> 574911.26 | U62: =+U597-U71 -> 0 | V62: =+V597-V71 -> 11932.219 | W62: =IF((+K62+L62+M62+P62+T62+U62+V62)-H62=0,"OK",(+K62+L62+M62+P62+T62+U62+V62)-H62) -> OK | Y62: =+'II-I TOTAL COMPANY'!L62-Meter!H62 -> 0
A63: =1+A62 -> 7 | B63: Taxes Other than Income Taxes | H63: =+I63+J63 -> 2595480.7 | I63: 0 | J63: =+K63+L63+M63+P63+T63+U63+V63 -> 2595480.7 | K63: =+K611-K68 -> 1216783 | L63: =+L611-L68 -> 231198.1 | M63: =SUM(N63:O63) -> 917850.16 | N63: =+N611-N68 -> 17908.025 | O63: =+O611-O68 -> 899942.14 | P63: =SUM(Q63:S63) -> 123439.32 | Q63: =+Q611-Q68 -> 53310.16 | R63: =+R611-R68 -> 62513.373 | S63: =+S611-S68 -> 7615.7866 | T63: =+T611-T68 -> 104049.9 | U63: =+U611-U68 -> 0.46875315 | V63: =+V611-V68 -> 2159.7047 | W63: =IF((+K63+L63+M63+P63+T63+U63+V63)-H63=0,"OK",(+K63+L63+M63+P63+T63+U63+V63)-H63) -> OK | Y63: =+'II-I TOTAL COMPANY'!L63-Meter!H63 -> 0
A64: =1+A63 -> 8 | B64: Income Taxes | H64: =+I64+J64 -> 1418394.5 | I64: 0 | J64: =+K64+L64+M64+P64+T64+U64+V64 -> 1418394.5 | K64: =(((+K59+SUM(K626:K634))*K638)+SUM(K642:K645)) -> 664962.26 | L64: =(((+L59+SUM(L626:L634))*L638)+SUM(L642:L645)) -> 126341.52 | M64: =SUM(N64:O64) -> 501588.41 | N64: =(((+N59+SUM(N626:N634))*N638)+SUM(N642:N645)) -> 9788.901 | O64: =(((+O59+SUM(O626:O634))*O638)+SUM(O642:O645)) -> 491799.51 | P64: =SUM(Q64:S64) -> 67461.877 | Q64: =(((+Q59+SUM(Q626:Q634))*Q638)+SUM(Q642:Q645)) -> 29137.836 | R64: =(((+R59+SUM(R626:R634))*R638)+SUM(R642:R645)) -> 34161.381 | S64: =(((+S59+SUM(S626:S634))*S638)+SUM(S642:S645)) -> 4162.6602 | T64: =(((+T59+SUM(T626:T634))*T638)+SUM(T642:T645)) -> 56858.917 | U64: =(((+U59+SUM(U626:U634))*U638)+SUM(U642:U645)) -> 1.0639987 | V64: =(((+V59+SUM(V626:V634))*V638)+SUM(V642:V645)) -> 1180.4651 | W64: =IF((+K64+L64+M64+P64+T64+U64+V64)-H64=0,"OK",(+K64+L64+M64+P64+T64+U64+V64)-H64) -> OK | Y64: =+'II-I TOTAL COMPANY'!L64-Meter!H64 -> 0
A65: =1+A64 -> 9 | B65: Other Expenses | H65: =+I65+J65 -> 0 | I65: 0 | J65: =+K65+L65+M65+P65+T65+U65+V65 -> 0 | K65: =+K654-K68-K69 -> 0 | L65: =+L654-L68-L69 -> 0 | M65: =SUM(N65:O65) -> 0 | N65: =+N654-N68-N69 -> 0 | O65: =+O654-O68-O69 -> 0 | P65: =SUM(Q65:S65) -> 0 | Q65: =+Q654-Q68-Q69 -> 0 | R65: =+R654-R68-R69 -> 0 | S65: =+S654-S68-S69 -> 0 | T65: =+T654-T68-T69 -> 0 | U65: =+U654-U68-U69 -> 0 | V65: =+V654-V68-V69 -> 0 | W65: =IF((+K65+L65+M65+P65+T65+U65+V65)-H65=0,"OK",(+K65+L65+M65+P65+T65+U65+V65)-H65) -> OK | Y65: =+'II-I TOTAL COMPANY'!L65-Meter!H65 -> 0
A66: =1+A65 -> 10 | B66: Total Operating Expenses | H66: =+I66+J66 -> 42630062 | I66: 0 | J66: =+K66+L66+M66+P66+T66+U66+V66 -> 42630062 | K66: =SUM(K61:K65) -> 19985275 | L66: =SUM(L61:L65) -> 3797404.2 | M66: =SUM(N66:O66) -> 15075470 | N66: =SUM(N61:N65) -> 294116 | O66: =SUM(O61:O65) -> 14781354 | P66: =SUM(Q66:S66) -> 2027426.7 | Q66: =SUM(Q61:Q65) -> 875569.97 | R66: =SUM(R61:R65) -> 1026775.2 | S66: =SUM(S61:S65) -> 125081.59 | T66: =SUM(T61:T65) -> 1709013.6 | U66: =SUM(U61:U65) -> 1.5327518 | V66: =SUM(V61:V65) -> 35470.911 | W66: =IF((+K66+L66+M66+P66+T66+U66+V66)-H66=0,"OK",(+K66+L66+M66+P66+T66+U66+V66)-H66) -> OK | Y66: =+'II-I TOTAL COMPANY'!L66-Meter!H66 -> 0
A67: =1+A66 -> 11 | P67: =SUM(Q67:S67) -> 0 | W67: =IF((+K67+L67+M67+P67+T67+U67+V67)-H67=0,"OK",(+K67+L67+M67+P67+T67+U67+V67)-H67) -> OK | Y67: =+'II-I TOTAL COMPANY'!L67-Meter!H67 -> 0
A68: =1+A67 -> 12 | B68: Municipal Franchise Fees | H68: =+I68+J68 -> 0 | I68: 0 | J68: =+K68+L68+M68+P68+T68+U68+V68 -> 0 | K68: =K607 -> 0 | L68: =L607 -> 0 | M68: =M607 -> 0 | N68: =N607 -> 0 | O68: =O607 -> 0 | P68: =SUM(Q68:S68) -> 0 | Q68: =Q607 -> 0 | R68: =R607 -> 0 | S68: =S607 -> 0 | T68: =T607 -> 0 | U68: =U607 -> 0 | V68: =V607 -> 0 | W68: =IF((+K68+L68+M68+P68+T68+U68+V68)-H68=0,"OK",(+K68+L68+M68+P68+T68+U68+V68)-H68) -> OK | Y68: =+'II-I TOTAL COMPANY'!L68-Meter!H68 -> 0
A69: =1+A68 -> 13 | B69: Nuclear Decommissioning | H69: =+I69+J69 -> 0 | I69: 0 | J69: =+K69+L69+M69+P69+T69+U69+V69 -> 0 | K69: =K652 -> 0 | L69: =L652 -> 0 | M69: =SUM(N69:O69) -> 0 | N69: =N652 -> 0 | O69: =O652 -> 0 | P69: =SUM(Q69:S69) -> 0 | Q69: =Q652 -> 0 | R69: =R652 -> 0 | S69: =S652 -> 0 | T69: =T652 -> 0 | U69: =U652 -> 0 | V69: =V652 -> 0 | W69: =IF((+K69+L69+M69+P69+T69+U69+V69)-H69=0,"OK",(+K69+L69+M69+P69+T69+U69+V69)-H69) -> OK | Y69: =+'II-I TOTAL COMPANY'!L69-Meter!H69 -> 0
A70: =1+A69 -> 14 | B70: DSM | H70: =+I70+J70 -> 0 | I70: 0 | J70: =+K70+L70+M70+P70+T70+U70+V70 -> 0 | K70: =K393 -> 0 | L70: =L393 -> 0 | M70: =M393 -> 0 | N70: =N393 -> 0 | O70: =O393 -> 0 | P70: =SUM(Q70:S70) -> 0 | Q70: =Q393 -> 0 | R70: =R393 -> 0 | S70: =S393 -> 0 | T70: =T393 -> 0 | U70: =U393 -> 0 | V70: =V393 -> 0 | W70: =IF((+K70+L70+M70+P70+T70+U70+V70)-H70=0,"OK",(+K70+L70+M70+P70+T70+U70+V70)-H70) -> OK | Y70: =+'II-I TOTAL COMPANY'!L70-Meter!H70 -> 0
A71: =1+A70 -> 15 | B71: Excess Mitigation Credit | H71: =+I71+J71 -> 0 | I71: 0 | J71: =+K71+L71+M71+P71+T71+U71+V71 -> 0 | K71: =K590 -> 0 | L71: =L590 -> 0 | M71: =M590 -> 0 | N71: =N590 -> 0 | O71: =O590 -> 0 | P71: =SUM(Q71:S71) -> 0 | Q71: =Q590 -> 0 | R71: =R590 -> 0 | S71: =S590 -> 0 | T71: =T590 -> 0 | U71: =U590 -> 0 | V71: =V590 -> 0 | W71: =IF((+K71+L71+M71+P71+T71+U71+V71)-H71=0,"OK",(+K71+L71+M71+P71+T71+U71+V71)-H71) -> OK | Y71: =+'II-I TOTAL COMPANY'!L71-Meter!H71 -> 0
A72: =1+A71 -> 16 | P72: =SUM(Q72:S72) -> 0 | W72: =IF((+K72+L72+M72+P72+T72+U72+V72)-H72=0,"OK",(+K72+L72+M72+P72+T72+U72+V72)-H72) -> OK | Y72: =+'II-I TOTAL COMPANY'!L72-Meter!H72 -> 0
A73: =1+A72 -> 17 | P73: =SUM(Q73:S73) -> 0 | W73: =IF((+K73+L73+M73+P73+T73+U73+V73)-H73=0,"OK",(+K73+L73+M73+P73+T73+U73+V73)-H73) -> OK | Y73: =+'II-I TOTAL COMPANY'!L73-Meter!H73 -> 0
A74: =1+A73 -> 18 | B74: Total Cost of Service | H74: =+I74+J74 -> 51042199 | I74: 0 | J74: =+K74+L74+M74+P74+T74+U74+V74 -> 51042199 | K74: =+K59+K66+K68+K69+K70+K71+K72 -> 23928995 | L74: =+L59+L66+L68+L69+L70+L71+L72 -> 4546705.5 | M74: =SUM(N74:O74) -> 18050264 | N74: =+N59+N66+N68+N69+N70+N71+N72 -> 352170.62 | O74: =+O59+O66+O68+O69+O70+O71+O72 -> 17698094 | P74: =SUM(Q74:S74) -> 2427524.5 | Q74: =+Q59+Q66+Q68+Q69+Q70+Q71+Q72 -> 1048377.4 | R74: =+R59+R66+R68+R69+R70+R71+R72 -> 1229378.1 | S74: =+S59+S66+S68+S69+S70+S71+S72 -> 149769 | T74: =+T59+T66+T68+T69+T70+T71+T72 -> 2046230.4 | U74: =+U59+U66+U68+U69+U70+U71+U72 -> 7.5539466 | V74: =+V59+V66+V68+V69+V70+V71+V72 -> 42471.872 | W74: =IF((+K74+L74+M74+P74+T74+U74+V74)-H74=0,"OK",(+K74+L74+M74+P74+T74+U74+V74)-H74) -> OK | Y74: =+'II-I TOTAL COMPANY'!L74-Meter!H74 -> 0
A75: =1+A74 -> 19 | B75: Adjusted Revenue Requirement | H75: =+I75+J75 -> 50185561 | I75: 0 | J75: =+K75+L75+M75+P75+T75+U75+V75 -> 50185561 | K75: =+K74-K78 -> 23527397 | L75: =+L74-L78 -> 4470397.7 | M75: =SUM(N75:O75) -> 17747327 | N75: =+N74-N78 -> 346260.55 | O75: =+O74-O78 -> 17401067 | P75: =SUM(Q75:S75) -> 2386784.2 | Q75: =+Q74-Q78 -> 1030783.3 | R75: =+R74-R78 -> 1208745.3 | S75: =+S74-S78 -> 147255.55 | T75: =+T74-T78 -> 2011888.2 | U75: =+U74-U78 -> 7.5539466 | V75: =+V74-V78 -> 41759.103 | W75: =IF((+K75+L75+M75+P75+T75+U75+V75)-H75=0,"OK",(+K75+L75+M75+P75+T75+U75+V75)-H75) -> OK | Y75: =+'II-I TOTAL COMPANY'!L75-Meter!H75 -> 0
A76: =1+A75 -> 20 | P76: =SUM(Q76:S76) -> 0 | W76: =IF((+K76+L76+M76+P76+T76+U76+V76)-H76=0,"OK",(+K76+L76+M76+P76+T76+U76+V76)-H76) -> OK | Y76: =+'II-I TOTAL COMPANY'!L76-Meter!H76 -> 0
A77: =1+A76 -> 21 | B77: Proposed Tariff Revenues | H77: =+I77+J77 -> 50185561 | I77: 0 | J77: =+K77+L77+M77+P77+T77+U77+V77 -> 50185561 | K77: =+K74-K80-K78 -> 23527397 | L77: =+L74-L80-L78 -> 4470397.7 | M77: =SUM(N77:O77) -> 17747327 | N77: =+N74-N80-N78 -> 346260.55 | O77: =+O74-O80-O78 -> 17401067 | P77: =SUM(Q77:S77) -> 2386784.2 | Q77: =+Q74-Q80-Q78 -> 1030783.3 | R77: =+R74-R80-R78 -> 1208745.3 | S77: =+S74-S80-S78 -> 147255.55 | T77: =+T74-T80-T78 -> 2011888.2 | U77: =+U74-U80-U78 -> 7.5539466 | V77: =+V74-V80-V78 -> 41759.103 | W77: =IF((+K77+L77+M77+P77+T77+U77+V77)-H77=0,"OK",(+K77+L77+M77+P77+T77+U77+V77)-H77) -> OK | Y77: =+'II-I TOTAL COMPANY'!L77-Meter!H77 -> 0
A78: =1+A77 -> 22 | B78: Proposed Miscellaneous Revenues | H78: =+I78+J78 -> 856637.48 | I78: 0 | J78: =+K78+L78+M78+P78+T78+U78+V78 -> 856637.48 | K78: =K40 -> 401597.45 | L78: =L40 -> 76307.819 | M78: =SUM(N78:O78) -> 302936.91 | N78: =N40 -> 5910.0753 | O78: =O40 -> 297026.83 | P78: =SUM(Q78:S78) -> 40740.341 | Q78: =Q40 -> 17594.125 | R78: =R40 -> 20632.769 | S78: =S40 -> 2513.4464 | T78: =T40 -> 34342.194 | U78: =U40 -> 0 | V78: =V40 -> 712.76839 | W78: =IF((+K78+L78+M78+P78+T78+U78+V78)-H78=0,"OK",(+K78+L78+M78+P78+T78+U78+V78)-H78) -> OK | Y78: =+'II-I TOTAL COMPANY'!L78-Meter!H78 -> 0
A79: =1+A78 -> 23 | B79: Proposed TCRF Revenues | H79: =+I79+J79 -> 0 | I79: 0 | J79: =+K79+L79+M79+P79+T79+U79+V79 -> 0 | K79: 0 | L79: 0 | M79: =SUM(N79:O79) -> 0 | N79: 0 | O79: 0 | P79: =SUM(Q79:S79) -> 0 | Q79: 0 | R79: 0 | S79: 0 | T79: 0 | U79: 0 | V79: 0 | W79: =IF((+K79+L79+M79+P79+T79+U79+V79)-H79=0,"OK",(+K79+L79+M79+P79+T79+U79+V79)-H79) -> OK | Y79: =+'II-I TOTAL COMPANY'!L79-Meter!H79 -> 0
A80: =1+A79 -> 24 | B80: Proposed Rider Revenues | H80: =+I80+J80 -> 0 | I80: 0 | J80: =+K80+L80+M80+P80+T80+U80+V80 -> 0 | K80: =+K69+K68+K70+K71 -> 0 | L80: =+L69+L68+L70+L71 -> 0 | M80: =SUM(N80:O80) -> 0 | N80: =+N69+N68+N70+N71 -> 0 | O80: =+O69+O68+O70+O71 -> 0 | P80: =SUM(Q80:S80) -> 0 | Q80: =+Q69+Q68+Q70+Q71 -> 0 | R80: =+R69+R68+R70+R71 -> 0 | S80: =+S69+S68+S70+S71 -> 0 | T80: =+T69+T68+T70+T71 -> 0 | U80: =+U69+U68+U70+U71 -> 0 | V80: =+V69+V68+V70+V71 -> 0 | W80: =IF((+K80+L80+M80+P80+T80+U80+V80)-H80=0,"OK",(+K80+L80+M80+P80+T80+U80+V80)-H80) -> OK | Y80: =+'II-I TOTAL COMPANY'!L80-Meter!H80 -> 0
A81: =1+A80 -> 25 | B81: Proposed Total Revenues | H81: =+I81+J81 -> 51042199 | I81: 0 | J81: =+K81+L81+M81+P81+T81+U81+V81 -> 51042199 | K81: =SUM(K77:K80) -> 23928995 | L81: =SUM(L77:L80) -> 4546705.5 | M81: =SUM(N81:O81) -> 18050264 | N81: =SUM(N77:N80) -> 352170.62 | O81: =SUM(O77:O80) -> 17698094 | P81: =SUM(Q81:S81) -> 2427524.5 | Q81: =SUM(Q77:Q80) -> 1048377.4 | R81: =SUM(R77:R80) -> 1229378.1 | S81: =SUM(S77:S80) -> 149769 | T81: =SUM(T77:T80) -> 2046230.4 | U81: =SUM(U77:U80) -> 7.5539466 | V81: =SUM(V77:V80) -> 42471.872 | W81: =IF((+K81+L81+M81+P81+T81+U81+V81)-H81=0,"OK",(+K81+L81+M81+P81+T81+U81+V81)-H81) -> OK | Y81: =+'II-I TOTAL COMPANY'!L81-Meter!H81 -> 0
A82: =1+A81 -> 26 | P82: =SUM(Q82:S82) -> 0 | W82: =IF((+K82+L82+M82+P82+T82+U82+V82)-H82=0,"OK",(+K82+L82+M82+P82+T82+U82+V82)-H82) -> OK | Y82: =+'II-I TOTAL COMPANY'!L82-Meter!H82 -> 0
A83: =1+A82 -> 27 | B83: Increase / Decrease in Tariff Revenues | H83: =+I83+J83 -> -6719779.3 | I83: 0 | J83: =+K83+L83+M83+P83+T83+U83+V83 -> -6719779.3 | K83: =+K77-K39 -> -14509079 | L83: =+L77-L39 -> -629503.3 | M83: =SUM(N83:O83) -> 6790404.9 | N83: =+N77-N39 -> 258469.82 | O83: =+O77-O39 -> 6531935.1 | P83: =SUM(Q83:S83) -> 741162.51 | Q83: =+Q77-Q39 -> 317639.98 | R83: =+R77-R39 -> 377779.69 | S83: =+S77-S39 -> 45742.844 | T83: =+T77-T39 -> 845470.26 | U83: =+U77-U39 -> 7.5539466 | V83: =+V77-V39 -> 41758.103 | W83: =IF((+K83+L83+M83+P83+T83+U83+V83)-H83=0,"OK",(+K83+L83+M83+P83+T83+U83+V83)-H83) -> OK | Y83: =+'II-I TOTAL COMPANY'!L83-Meter!H83 -> 1
A84: =1+A83 -> 28 | B84: Increase / Decrease in Miscellaneous Revenues | H84: =+I84+J84 -> 0 | I84: 0 | J84: =+K84+L84+M84+P84+T84+U84+V84 -> 0 | K84: =+K78-K40 -> 0 | L84: =+L78-L40 -> 0 | M84: =SUM(N84:O84) -> 0 | N84: =+N78-N40 -> 0 | O84: =+O78-O40 -> 0 | P84: =SUM(Q84:S84) -> 0 | Q84: =+Q78-Q40 -> 0 | R84: =+R78-R40 -> 0 | S84: =+S78-S40 -> 0 | T84: =+T78-T40 -> 0 | U84: =+U78-U40 -> 0 | V84: =+V78-V40 -> 0 | W84: =IF((+K84+L84+M84+P84+T84+U84+V84)-H84=0,"OK",(+K84+L84+M84+P84+T84+U84+V84)-H84) -> OK | Y84: =+'II-I TOTAL COMPANY'!L84-Meter!H84 -> 0
A85: =1+A84 -> 29 | B85: Increase / Decrease in TCRF Revenues | H85: =+I85+J85 -> 0 | I85: 0 | J85: =+K85+L85+M85+P85+T85+U85+V85 -> 0 | K85: =+K79-K41 -> 0 | L85: =+L79-L41 -> 0 | M85: =SUM(N85:O85) -> 0 | N85: =+N79-N41 -> 0 | O85: =+O79-O41 -> 0 | P85: =SUM(Q85:S85) -> 0 | Q85: =+Q79-Q41 -> 0 | R85: =+R79-R41 -> 0 | S85: =+S79-S41 -> 0 | T85: =+T79-T41 -> 0 | U85: =+U79-U41 -> 0 | V85: =+V79-V41 -> 0 | W85: =IF((+K85+L85+M85+P85+T85+U85+V85)-H85=0,"OK",(+K85+L85+M85+P85+T85+U85+V85)-H85) -> OK | Y85: =+'II-I TOTAL COMPANY'!L85-Meter!H85 -> 0
A86: =1+A85 -> 30 | B86: Increase / Decrease in Rider Revenues | H86: =+I86+J86 -> 0 | I86: 0 | J86: =+K86+L86+M86+P86+T86+U86+V86 -> 0 | K86: =+K80-K42 -> 0 | L86: =+L80-L42 -> 0 | M86: =SUM(N86:O86) -> 0 | N86: =+N80-N42 -> 0 | O86: =+O80-O42 -> 0 | P86: =SUM(Q86:S86) -> 0 | Q86: =+Q80-Q42 -> 0 | R86: =+R80-R42 -> 0 | S86: =+S80-S42 -> 0 | T86: =+T80-T42 -> 0 | U86: =+U80-U42 -> 0 | V86: =+V80-V42 -> 0 | W86: =IF((+K86+L86+M86+P86+T86+U86+V86)-H86=0,"OK",(+K86+L86+M86+P86+T86+U86+V86)-H86) -> OK | Y86: =+'II-I TOTAL COMPANY'!L86-Meter!H86 -> 0
A87: =1+A86 -> 31 | B87: Increase / Decrease in Total Revenues | H87: =+I87+J87 -> -6719779.3 | I87: 0 | J87: =+K87+L87+M87+P87+T87+U87+V87 -> -6719779.3 | K87: =SUM(K83:K86) -> -14509079 | L87: =SUM(L83:L86) -> -629503.3 | M87: =SUM(N87:O87) -> 6790404.9 | N87: =SUM(N83:N86) -> 258469.82 | O87: =SUM(O83:O86) -> 6531935.1 | P87: =SUM(Q87:S87) -> 741162.51 | Q87: =SUM(Q83:Q86) -> 317639.98 | R87: =SUM(R83:R86) -> 377779.69 | S87: =SUM(S83:S86) -> 45742.844 | T87: =SUM(T83:T86) -> 845470.26 | U87: =SUM(U83:U86) -> 7.5539466 | V87: =SUM(V83:V86) -> 41758.103 | W87: =IF((+K87+L87+M87+P87+T87+U87+V87)-H87=0,"OK",(+K87+L87+M87+P87+T87+U87+V87)-H87) -> OK | Y87: =+'II-I TOTAL COMPANY'!L87-Meter!H87 -> 1
P88: =SUM(Q88:S88) -> 0
P89: =SUM(Q89:S89) -> 0
B90: Schedule II-B-1 Original Cost of Utility Plant | P90: =SUM(Q90:S90) -> 0
P91: =SUM(Q91:S91) -> 0
A92: 1 | B92: Intangible Plant | P92: =SUM(Q92:S92) -> 0
A93: =+A92+1 -> 2 | B93: A301 | C93: Organization | D93: LABOR | E93: II-I-1 Column (9) | H93: ='II-I TOTAL COMPANY'!L93 -> 566.25384 | I93: 0 | J93: =SUM(K93:V93)-M93-P93 -> 566.25384 | K93: =VLOOKUP($D93,$E$741:$V$815,K$1,FALSE)*$H93 -> 265.46363 | L93: =VLOOKUP($D93,$E$741:$V$815,L$1,FALSE)*$H93 -> 50.440935 | M93: =SUM(N93:O93) -> 200.24712 | N93: =VLOOKUP($D93,$E$741:$V$815,N$1,FALSE)*$H93 -> 3.9066733 | O93: =VLOOKUP($D93,$E$741:$V$815,O$1,FALSE)*$H93 -> 196.34044 | P93: =SUM(Q93:S93) -> 26.930148 | Q93: =VLOOKUP($D93,$E$741:$V$815,Q$1,FALSE)*$H93 -> 11.630055 | R93: =VLOOKUP($D93,$E$741:$V$815,R$1,FALSE)*$H93 -> 13.638657 | S93: =VLOOKUP($D93,$E$741:$V$815,S$1,FALSE)*$H93 -> 1.6614364 | T93: =VLOOKUP($D93,$E$741:$V$815,T$1,FALSE)*$H93 -> 22.70085 | U93: =VLOOKUP($D93,$E$741:$V$815,U$1,FALSE)*$H93 -> 0 | V93: =VLOOKUP($D93,$E$741:$V$815,V$1,FALSE)*$H93 -> 0.4711536 | W93: =IF((+K93+L93+M93+P93+T93+U93+V93)-H93=0,"OK",(+K93+L93+M93+P93+T93+U93+V93)-H93) -> OK
A94: =+A93+1 -> 3 | B94: A303 | C94: Miscellaneous Intangible Plant | D94: LABOR | E94: II-I-1 Column (9) | H94: ='II-I TOTAL COMPANY'!L94 -> 0 | I94: 0 | J94: =SUM(K94:V94)-M94-P94 -> 0 | K94: =VLOOKUP($D94,$E$741:$V$815,K$1,FALSE)*$H94 -> 0 | L94: =VLOOKUP($D94,$E$741:$V$815,L$1,FALSE)*$H94 -> 0 | M94: =SUM(N94:O94) -> 0 | N94: =VLOOKUP($D94,$E$741:$V$815,N$1,FALSE)*$H94 -> 0 | O94: =VLOOKUP($D94,$E$741:$V$815,O$1,FALSE)*$H94 -> 0 | P94: =SUM(Q94:S94) -> 0 | Q94: =VLOOKUP($D94,$E$741:$V$815,Q$1,FALSE)*$H94 -> 0 | R94: =VLOOKUP($D94,$E$741:$V$815,R$1,FALSE)*$H94 -> 0 | S94: =VLOOKUP($D94,$E$741:$V$815,S$1,FALSE)*$H94 -> 0 | T94: =VLOOKUP($D94,$E$741:$V$815,T$1,FALSE)*$H94 -> 0 | U94: =VLOOKUP($D94,$E$741:$V$815,U$1,FALSE)*$H94 -> 0 | V94: =VLOOKUP($D94,$E$741:$V$815,V$1,FALSE)*$H94 -> 0 | W94: =IF((+K94+L94+M94+P94+T94+U94+V94)-H94=0,"OK",(+K94+L94+M94+P94+T94+U94+V94)-H94) -> OK
A95: =+A94+1 -> 4 | B95: A303 | C95: Miscellaneous Intangible Plant | D95: LABOR | E95: II-I-1 Column (9) | H95: ='II-I TOTAL COMPANY'!L95 -> 3697795.4 | I95: 0 | J95: =SUM(K95:V95)-M95-P95 -> 3697795.4 | K95: =VLOOKUP($D95,$E$741:$V$815,K$1,FALSE)*$H95 -> 1733551.5 | L95: =VLOOKUP($D95,$E$741:$V$815,L$1,FALSE)*$H95 -> 329393.37 | M95: =SUM(N95:O95) -> 1307669.5 | N95: =VLOOKUP($D95,$E$741:$V$815,N$1,FALSE)*$H95 -> 25511.666 | O95: =VLOOKUP($D95,$E$741:$V$815,O$1,FALSE)*$H95 -> 1282157.8 | P95: =SUM(Q95:S95) -> 175861.37 | Q95: =VLOOKUP($D95,$E$741:$V$815,Q$1,FALSE)*$H95 -> 75947.5 | R95: =VLOOKUP($D95,$E$741:$V$815,R$1,FALSE)*$H95 -> 89064.232 | S95: =VLOOKUP($D95,$E$741:$V$815,S$1,FALSE)*$H95 -> 10849.643 | T95: =VLOOKUP($D95,$E$741:$V$815,T$1,FALSE)*$H95 -> 148242.88 | U95: =VLOOKUP($D95,$E$741:$V$815,U$1,FALSE)*$H95 -> 0 | V95: =VLOOKUP($D95,$E$741:$V$815,V$1,FALSE)*$H95 -> 3076.7644 | W95: =IF((+K95+L95+M95+P95+T95+U95+V95)-H95=0,"OK",(+K95+L95+M95+P95+T95+U95+V95)-H95) -> 4.6566129e-10
A96: =+A95+1 -> 5 | C96: Total Intangible Plant | H96: =SUM(H93:H95) -> 3698361.7 | I96: =SUM(I93:I95) -> 0 | J96: =SUM(K96:V96)-M96-P96 -> 3698361.7 | K96: =SUM(K93:K95) -> 1733817 | L96: =SUM(L93:L95) -> 329443.81 | M96: =SUM(N96:O96) -> 1307869.7 | N96: =SUM(N93:N95) -> 25515.573 | O96: =SUM(O93:O95) -> 1282354.2 | P96: =SUM(Q96:S96) -> 175888.3 | Q96: =SUM(Q93:Q95) -> 75959.13 | R96: =SUM(R93:R95) -> 89077.87 | S96: =SUM(S93:S95) -> 10851.304 | T96: =SUM(T93:T95) -> 148265.58 | U96: =SUM(U93:U95) -> 0 | V96: =SUM(V93:V95) -> 3077.2355 | W96: =IF((+K96+L96+M96+P96+T96+U96+V96)-H96=0,"OK",(+K96+L96+M96+P96+T96+U96+V96)-H96) -> OK
A97: =+A96+1 -> 6 | P97: =SUM(Q97:S97) -> 0 | W97: =IF((+K97+L97+M97+P97+T97+U97+V97)-H97=0,"OK",(+K97+L97+M97+P97+T97+U97+V97)-H97) -> OK
A98: =1+A97 -> 7 | B98: Schedule II-B-1 Original Cost of Utility Plant (Continued) | P98: =SUM(Q98:S98) -> 0 | W98: =IF((+K98+L98+M98+P98+T98+U98+V98)-H98=0,"OK",(+K98+L98+M98+P98+T98+U98+V98)-H98) -> OK
A99: =1+A98 -> 8 | P99: =SUM(Q99:S99) -> 0 | W99: =IF((+K99+L99+M99+P99+T99+U99+V99)-H99=0,"OK",(+K99+L99+M99+P99+T99+U99+V99)-H99) -> OK
A100: =1+A99 -> 9 | B100: Transmission Plant | P100: =SUM(Q100:S100) -> 0 | W100: =IF((+K100+L100+M100+P100+T100+U100+V100)-H100=0,"OK",(+K100+L100+M100+P100+T100+U100+V100)-H100) -> OK
A101: =+A100+1 -> 10 | B101: A350 | C101: Land and Land Rights | D101: DEMANDDP | E101: II-I-1 Column (9) | H101: ='II-I TOTAL COMPANY'!L101 -> 0 | I101: 0 | J101: =SUM(K101:V101)-M101-P101 -> 0 | K101: =VLOOKUP($D101,$E$741:$V$815,K$1,FALSE)*$H101 -> 0 | L101: =VLOOKUP($D101,$E$741:$V$815,L$1,FALSE)*$H101 -> 0 | M101: =SUM(N101:O101) -> 0 | N101: =VLOOKUP($D101,$E$741:$V$815,N$1,FALSE)*$H101 -> 0 | O101: =VLOOKUP($D101,$E$741:$V$815,O$1,FALSE)*$H101 -> 0 | P101: =SUM(Q101:S101) -> 0 | Q101: =VLOOKUP($D101,$E$741:$V$815,Q$1,FALSE)*$H101 -> 0 | R101: =VLOOKUP($D101,$E$741:$V$815,R$1,FALSE)*$H101 -> 0 | S101: =VLOOKUP($D101,$E$741:$V$815,S$1,FALSE)*$H101 -> 0 | T101: =VLOOKUP($D101,$E$741:$V$815,T$1,FALSE)*$H101 -> 0 | U101: =VLOOKUP($D101,$E$741:$V$815,U$1,FALSE)*$H101 -> 0 | V101: =VLOOKUP($D101,$E$741:$V$815,V$1,FALSE)*$H101 -> 0 | W101: =IF((+K101+L101+M101+P101+T101+U101+V101)-H101=0,"OK",(+K101+L101+M101+P101+T101+U101+V101)-H101) -> OK
A102: =+A101+1 -> 11 | B102: A352 | C102: Structures and Improvements | D102: DEMANDDP | E102: II-I-1 Column (9) | H102: ='II-I TOTAL COMPANY'!L102 -> 0 | I102: 0 | J102: =SUM(K102:V102)-M102-P102 -> 0 | K102: =VLOOKUP($D102,$E$741:$V$815,K$1,FALSE)*$H102 -> 0 | L102: =VLOOKUP($D102,$E$741:$V$815,L$1,FALSE)*$H102 -> 0 | M102: =SUM(N102:O102) -> 0 | N102: =VLOOKUP($D102,$E$741:$V$815,N$1,FALSE)*$H102 -> 0 | O102: =VLOOKUP($D102,$E$741:$V$815,O$1,FALSE)*$H102 -> 0 | P102: =SUM(Q102:S102) -> 0 | Q102: =VLOOKUP($D102,$E$741:$V$815,Q$1,FALSE)*$H102 -> 0 | R102: =VLOOKUP($D102,$E$741:$V$815,R$1,FALSE)*$H102 -> 0 | S102: =VLOOKUP($D102,$E$741:$V$815,S$1,FALSE)*$H102 -> 0 | T102: =VLOOKUP($D102,$E$741:$V$815,T$1,FALSE)*$H102 -> 0 | U102: =VLOOKUP($D102,$E$741:$V$815,U$1,FALSE)*$H102 -> 0 | V102: =VLOOKUP($D102,$E$741:$V$815,V$1,FALSE)*$H102 -> 0 | W102: =IF((+K102+L102+M102+P102+T102+U102+V102)-H102=0,"OK",(+K102+L102+M102+P102+T102+U102+V102)-H102) -> OK
A103: =+A102+1 -> 12 | B103: A353 | C103: Station Equipment | D103: DEMANDDP | E103: II-I-1 Column (9) | H103: ='II-I TOTAL COMPANY'!L103 -> 0 | I103: 0 | J103: =SUM(K103:V103)-M103-P103 -> 0 | K103: =VLOOKUP($D103,$E$741:$V$815,K$1,FALSE)*$H103 -> 0 | L103: =VLOOKUP($D103,$E$741:$V$815,L$1,FALSE)*$H103 -> 0 | M103: =SUM(N103:O103) -> 0 | N103: =VLOOKUP($D103,$E$741:$V$815,N$1,FALSE)*$H103 -> 0 | O103: =VLOOKUP($D103,$E$741:$V$815,O$1,FALSE)*$H103 -> 0 | P103: =SUM(Q103:S103) -> 0 | Q103: =VLOOKUP($D103,$E$741:$V$815,Q$1,FALSE)*$H103 -> 0 | R103: =VLOOKUP($D103,$E$741:$V$815,R$1,FALSE)*$H103 -> 0 | S103: =VLOOKUP($D103,$E$741:$V$815,S$1,FALSE)*$H103 -> 0 | T103: =VLOOKUP($D103,$E$741:$V$815,T$1,FALSE)*$H103 -> 0 | U103: =VLOOKUP($D103,$E$741:$V$815,U$1,FALSE)*$H103 -> 0 | V103: =VLOOKUP($D103,$E$741:$V$815,V$1,FALSE)*$H103 -> 0 | W103: =IF((+K103+L103+M103+P103+T103+U103+V103)-H103=0,"OK",(+K103+L103+M103+P103+T103+U103+V103)-H103) -> OK
...

Sheet TDCustSvc
D1: 1 | E1: 2 | H1: 7 | I1: 13 | J1: 6 | K1: =J1+1 -> 7 | L1: =K1+1 -> 8 | M1: =L1+1 -> 9 | N1: =M1+1 -> 10 | O1: =N1+1 -> 11 | P1: =O1+1 -> 12 | Q1: =P1+1 -> 13 | R1: =Q1+1 -> 14 | ... V1: =U1+1 -> 18
B3: ='II-I TOTAL COMPANY'!B4 -> PUBLIC UTILITY COMMISION OF TEXAS
B4: ='II-I TOTAL COMPANY'!B5 -> AEP TEXAS INC
B5: ='II-I TOTAL COMPANY'!B6 -> II-I COST OF SERVICE
B6: ='II-I TOTAL COMPANY'!B7 -> TEST YEAR ENDING 09/30/2023
B7: DOCKET 56165 | E7: Customer Service
M8: Total | P8: Total
L9: Secondary | M9: Secondary | N9: Secondary | O9: Secondary | P9: Primary | Q9: Primary | R9: Primary | S9: Primary | T9: Transmission | U9: Lighting | V9: BESS
A10: Line | B10: Account | C10: Description | E10: Reference | F10: Total AEP Texas | G10: Difference | H10: Total | I10: Oth Jurisdiction | J10: Texas Retail | K10: Residential | L10: GS < = 10kw | M10: GS > 10kw | N10: GS > 10kw | O10: GS > 10kw | Q10: 4CP | R10: NCP | S10: Sub | W10: Check
A11: No. | B11: No. | D11: ALLOC | E11: Schedule | F11: As Filed | N11: 4CP | O11: NCP | W11: Column
A12: -1 | B12: =+A12-1 -> -2 | C12: =+B12-1 -> -3 | D12: =+C12-1 -> -4 | E12: =+D12-1 -> -5 | H12: =+E12-1 -> -6 | I12: =+H12-1 -> -7 | J12: =+I12-1 -> -8 | K12: =+J12-1 -> -9 | L12: =+K12-1 -> -10 | M12: =+L12-1 -> -11 | N12: =+M12-1 -> -12 | O12: =+N12-1 -> -13 | P12: =+O12-1 -> -14 | ... V12: =+U12-1 -> -20
B13: Schedule I-A Cost of Service by Function
B15: Summary of Results @ Present ROR
A17: =+A16+1 -> 1 | B17: Rate Base by Function
A18: =+A17+1 -> 2 | B18: Plant Investment
A19: =+A18+1 -> 3 | C19: Intangible | H19: =+I19+J19 -> 212.22859 | I19: 0 | J19: =+K19+L19+M19+P19+T19+U19+V19 -> 212.22859 | K19: =+K96 -> 173.97813 | L19: =+L96 -> 18.484611 | M19: =SUM(N19:O19) -> 12.231253 | N19: =+N96 -> 0.097297319 | O19: =+O96 -> 12.133955 | P19: =SUM(Q19:S19) -> 0.18638682 | Q19: =+Q96 -> 0.07922299 | R19: =+R96 -> 0.092905426 | S19: =+S96 -> 0.014258404 | T19: =+T96 -> 0.020957609 | U19: =+U96 -> 7.3240477 | V19: =+V96 -> 0.0032094602 | W19: =IF((+K19+L19+M19+P19+T19+U19+V19)-H19=0,"OK",(+K19+L19+M19+P19+T19+U19+V19)-H19) -> OK | Y19: =+'II-I TOTAL COMPANY'!M19-TDCustSvc!H19 -> 0
A20: =+A19+1 -> 4 | C20: Transmission | H20: =+I20+J20 -> 0 | I20: 0 | J20: =+K20+L20+M20+P20+T20+U20+V20 -> 0 | K20: =+K111 -> 0 | L20: =+L111 -> 0 | M20: =SUM(N20:O20) -> 0 | N20: =+N111 -> 0 | O20: =+O111 -> 0 | P20: =SUM(Q20:S20) -> 0 | Q20: =+Q111 -> 0 | R20: =+R111 -> 0 | S20: =+S111 -> 0 | T20: =+T111 -> 0 | U20: =+U111 -> 0 | V20: =+V111 -> 0 | W20: =IF((+K20+L20+M20+P20+T20+U20+V20)-H20=0,"OK",(+K20+L20+M20+P20+T20+U20+V20)-H20) -> OK | Y20: =+'II-I TOTAL COMPANY'!M20-TDCustSvc!H20 -> 0
A21: =+A20+1 -> 5 | C21: Distribution | H21: =+I21+J21 -> 0 | I21: 0 | J21: =+K21+L21+M21+P21+T21+U21+V21 -> 0 | K21: =+K147 -> 0 | L21: =+L147 -> 0 | M21: =SUM(N21:O21) -> 0 | N21: =+N147 -> 0 | O21: =+O147 -> 0 | P21: =SUM(Q21:S21) -> 0 | Q21: =+Q147 -> 0 | R21: =+R147 -> 0 | S21: =+S147 -> 0 | T21: =+T147 -> 0 | U21: =+U147 -> 0 | V21: =+V147 -> 0 | W21: =IF((+K21+L21+M21+P21+T21+U21+V21)-H21=0,"OK",(+K21+L21+M21+P21+T21+U21+V21)-H21) -> OK | Y21: =+'II-I TOTAL COMPANY'!M21-TDCustSvc!H21 -> 0
A22: =+A21+1 -> 6 | C22: General | H22: =+I22+J22 -> 5449781.4 | I22: 0 | J22: =+K22+L22+M22+P22+T22+U22+V22 -> 5449781.4 | K22: =+K162+K168 -> 4467554.3 | L22: =+L162+L168 -> 474663.14 | M22: =SUM(N22:O22) -> 314084.23 | N22: =+N162+N168 -> 2498.4811 | O22: =+O162+O168 -> 311585.75 | P22: =SUM(Q22:S22) -> 4786.195 | Q22: =+Q162+Q168 -> 2034.3535 | R22: =+R162+R168 -> 2385.7024 | S22: =+S162+S168 -> 366.13909 | T22: =+T162+T168 -> 538.16683 | U22: =+U162+U168 -> 188072.96 | V22: =+V162+V168 -> 82.415174 | W22: =IF((+K22+L22+M22+P22+T22+U22+V22)-H22=0,"OK",(+K22+L22+M22+P22+T22+U22+V22)-H22) -> OK | Y22: =+'II-I TOTAL COMPANY'!M22-TDCustSvc!H22 -> 0
A23: =+A22+1 -> 7 | W23: =IF((+K23+L23+M23+P23+T23+U23+V23)-H23=0,"OK",(+K23+L23+M23+P23+T23+U23+V23)-H23) -> OK | Y23: =+'II-I TOTAL COMPANY'!M23-TDCustSvc!H23 -> 0
A24: =+A23+1 -> 8 | B24: Total Plant Investment | H24: =+I24+J24 -> 5449993.6 | I24: 0 | J24: =+K24+L24+M24+P24+T24+U24+V24 -> 5449993.6 | K24: =SUM(K19:K23) -> 4467728.3 | L24: =SUM(L19:L23) -> 474681.62 | M24: =SUM(N24:O24) -> 314096.46 | N24: =SUM(N19:N23) -> 2498.5784 | O24: =SUM(O19:O23) -> 311597.88 | P24: =SUM(Q24:S24) -> 4786.3814 | Q24: =SUM(Q19:Q23) -> 2034.4327 | R24: =SUM(R19:R23) -> 2385.7953 | S24: =SUM(S19:S23) -> 366.15335 | T24: =SUM(T19:T23) -> 538.18779 | U24: =SUM(U19:U23) -> 188080.28 | V24: =SUM(V19:V23) -> 82.418383 | W24: =IF((+K24+L24+M24+P24+T24+U24+V24)-H24=0,"OK",(+K24+L24+M24+P24+T24+U24+V24)-H24) -> OK | Y24: =+'II-I TOTAL COMPANY'!M24-TDCustSvc!H24 -> 0
A25: =+A24+1 -> 9 | W25: =IF((+K25+L25+M25+P25+T25+U25+V25)-H25=0,"OK",(+K25+L25+M25+P25+T25+U25+V25)-H25) -> OK | Y25: =+'II-I TOTAL COMPANY'!M25-TDCustSvc!H25 -> 0
